Workbook

Sheet 0. Supuestos
A1: SUPUESTOS — aquí se teclean las TASAS y los DRIVERS del modelo
A2: Cambia las celdas VERDES: el resto del libro se recalcula solo. Las partidas de gasto se teclean en su hoja (también en verde) y no se repiten aquí.
A3: ACTIVIDAD
A4: Clientes/día (media del año 1) | B4: 45 | C4: Clientes servidos al día de media del año. Es el mismo «Clientes/día objetivo (Año 1)» que ya declaraba el fichero v1.1
A5: Ticket medio SIN IVA (€) | B5: 12 | C5: SIN IVA. Es el mismo 12 € que ya usaban Punto Equilibrio y la columna realista de Escenarios (declarar que es SIN IVA no cambia ningún número, sólo aclara qué era). Dentro del rango 10-15 € de la fila «Ticket medio food truck» de la tabla DATOS DE REFERENCIA DEL SECTOR, en la hoja de Instrucciones
A6: Días de apertura al año | B6: 250 | C6: El MISMO dato lo usan la cuenta de resultados, el punto de equilibrio y los escenarios. La versión anterior traía TRES calendarios que no coincidían: 25 días de servicio al mes en el punto de equilibrio (300 al año), 5 servicios por semana durante 48 semanas en los escenarios (240 al año) y ninguno declarado en la cuenta de resultados. Se fijan 250 días —5 días de servicio a la semana por 50 semanas activas, dentro de los «4-6 días operativos por semana» que declara este mismo libro— porque son los únicos que reproducen al céntimo la facturación que el propio libro ya publicaba: 45 × 12 × 250 = 135.000 €
A7: Crecimiento de volumen del año 2 | B7: 0.15 | C7: El fichero v1.1 proyectaba 175.000 € en el año 2 sobre 135.000 € (+29,6 %): se redondea a la baja porque un food truck de un año no tiene todavía rutas ni clientela corporativa consolidadas (mismo criterio conservador que tapas-bar y cafetería)
A8: Crecimiento de volumen del año 3 | B8: 0.1 | C8: El fichero v1.1 proyectaba 215.000 € sobre 175.000 € (+22,9 %): igual, redondeado a la baja
A9: PVP equivalente con IVA (calculado) | B9: =IFERROR(IF($B$5="","",$B$5*(1+SUMPRODUCT('PyG 3 Años'!$E$10:$E$11,'PyG 3 Años'!$G$10:$G$11))),"") -> 13.2 | C9: =IFERROR("Ticket sin IVA más el IVA medio ponderado de tus líneas de venta: "&TEXT(SUMPRODUCT('PyG 3 Años'!$E$10:$E$11,'PyG 3 Años'!$G$10:$G$11)*100,"0")&" %. En sala todo va al 10 % (art. 91.Uno.2.2.º de la Ley 37/1992, alcohol incluido); el alcohol que sale por delivery y el pan común, si los tienes, mueven la media. Aquí va redondeado. Compáralo con el rango del sector, que va con IVA.","") -> Ticket sin IVA más el IVA medio ponderado de tus líneas de venta: 10 %. En sala todo va al 10 % (art. 91.Uno.2.2.º de la Ley 37/1992, alcohol incluido); el alcohol que sale por delivery y el pan común, si los tienes, mueven la media. Aquí va redondeado. Compáralo con el rango del sector, que va con IVA.
A10: MIX Y COSTE DE MERCANCÍA
A11: Ventas de COMIDA sobre el total | B11: 0.8519 | C11: Peso de la COMIDA sobre el total de ventas. Es un INPUT: cámbialo aquí y el P&L, la tesorería y el IVA repercutido se recalculan solos
A12: Ventas de BEBIDA sobre el total | B12: =IFERROR(IF(COUNT(B11)=0,"",1-B11),"") -> 0.1481 | C12: Se calcula como el resto: comida + bebida = 100 %
A13: Coste de mercancía sobre las ventas de COMIDA | B13: 0.28 | C13: Coste de mercancía de la comida: dentro del 28-33 % de la fila «Food cost comida» de la tabla DATOS DE REFERENCIA DEL SECTOR de la hoja de Instrucciones («depende del concepto: burger 30 %, tacos 25 %, poke 35 %»). Se toma el extremo bajo del rango porque la compra diaria que exige un food truck, sin cámara grande, reduce la merma frente a una cocina fija. Es la palanca más sensible del plan: con el 33 % el resultado del primer año se queda muy justo
A14: Coste de mercancía sobre las ventas de BEBIDA | B14: 0.22 | C14: Bebidas embotelladas y refrescos: extremo bajo del 22-28 % de la fila «Food cost bebidas» de la tabla DATOS DE REFERENCIA DEL SECTOR de la hoja de Instrucciones («refrescos y agua embotellada, margen alto»)
A15: Consumibles sobre ventas | B15: 0.03 | C15: Packaging biodegradable: extremo bajo del 3-5 % de la fila «Coste packaging / ventas» de la tabla DATOS DE REFERENCIA DEL SECTOR de la hoja de Instrucciones. Es una partida realmente cara en un food truck (obligatoria por normativa municipal en muchos casos, como recuerda la fase de equipamiento de tu checklist) y por eso se cita al lado del food cost, no dentro de «varios»
A16: Ventas por delivery sobre el total | B16: 0 | C16: A CERO por defecto: este negocio vende en el punto de venta móvil, no reparte a domicilio. Súbelo si activas un canal de delivery desde una ubicación fija
A17: Comisión de la plataforma de delivery | B17: 0.28 | C17: Sin uso mientras pct_delivery esté a 0: rango habitual de comisión de plataforma si algún día operas desde una ubicación fija con reparto
A18: Comisión de los medios de pago | B18: 0.008 | C18: Tarjeta y bizum sobre el total facturado: un food truck urbano cobra en tarjeta/contactless la mayoría de los tickets
A19: PERSONAL
A20: Seguridad Social a cargo de la empresa | B20: 0.33 | C20: Contingencias comunes + AT/EP + desempleo + FOGASA + FP; ajusta a tu convenio y bonificaciones
A21: Número de pagas anuales | B21: 14 | C21: Salario bruto anual = bruto mensual × pagas
A22: SMI anual de referencia (€) | B22: 17094 | C22: SMI 2026: 17.094 € al año (1.221 €/mes en 14 pagas), suelo legal por jornada completa. Comprueba el importe vigente si presentas el plan en otro ejercicio
A23: LOCAL Y FIJOS
A24: Alquiler mensual del local (€) | B24: 400 | C24: ESTE NEGOCIO NO PAGA RENTA DE LOCAL: esta celda es el coste mensual del aparcamiento o la nave en la que el vehículo pernocta y se prepara cada jornada, y de ella salen también la fianza y los meses previos a la apertura. Es un concepto distinto del generador, que va en la celda de suministros. 400 €/mes es lo que cuesta una plaza cubierta con toma de agua y desagüe para un vehículo comercial grande en una ciudad media española: pide presupuesto en tu zona antes de firmar
A25: Fianza del aparcamiento (meses) | B25: 2 | C25: Dos meses de fianza por la plaza o la nave, menos que los tres habituales de un local comercial
A26: Suministros mensuales de luz, agua y gas (€) | B26: 200 | C26: Combustible del generador eléctrico y mantenimiento de las tomas de agua y de vertido. Es el mismo concepto que la versión anterior llamaba «Generador (combustible/alquiler)» dentro de los costes fijos: ahora vive en una celda, para poder cambiarlo en un solo sitio y que el resto del libro se entere
A27: Seguros (€/año) | B27: 2500 | C27: Responsabilidad civil profesional alimentaria —la fase 1 de tu checklist pide un mínimo de 300.000 € de cobertura— más el seguro del vehículo a todo riesgo. Es la MISMA prima que la versión anterior contaba dos veces, una en la inversión y otra como gasto del año: aquí se cuenta una sola vez, que es como se paga
A28: Varios e imprevistos sobre ventas | B28: 0.05 | C28: Combustible del vehículo para desplazarse entre ubicaciones más el colchón de gasto corriente no presupuestado. Es un coste VARIABLE: sube y baja con los servicios que se hacen, así que no puede vivir entre los fijos, porque movería el punto de equilibrio sin que se notara. Agrupa dos partidas que la versión anterior tenía sueltas: el combustible, que ya era variable, y los varios e imprevistos, que estaban mal clasificados como fijos
A29: FINANCIACIÓN
A30: Recursos propios aportados (€) | B30: 25000 | C30: Aportación del titular. Con menos, el banco no entra: pide un 25-30 % de fondos propios sobre la necesidad de caja de este plan
A31: Préstamo bancario solicitado (€) | B31: 72000 | C31: Principal solicitado. La hoja de Financiación comprueba que el origen de fondos cuadra con la necesidad de caja de la hoja 1 (25.000 € de recursos propios + 72.000 € de préstamo = 97.000 €). Está por encima de los 73.400 € que sumaba la versión anterior porque el fondo de maniobra pasa a ser de verdad de tres meses, y porque ahora se suman a la necesidad de caja el IVA de la inversión —que hay que adelantar aunque se recupere— y los imprevistos de la puesta en marcha
A32: Tipo de interés nominal anual | B32: 0.065 | C32: Tipo nominal anual; un préstamo de menor importe y sin garantía inmobiliaria (el vehículo es la garantía) suele salir algo por encima del de un local: pide oferta a dos entidades y a una línea ICO/ENISA de emprendedores antes de fijarlo
A33: Plazo del préstamo (años) | B33: 6 | C33: Años totales, carencia incluida. Un vehículo se amortiza más rápido que unas obras de local, así que el plazo también es más corto
A34: Carencia de principal (años) | B34: 1 | C34: Primer año sólo intereses, que es cuando la caja está más tensa (adaptación del vehículo + primeras semanas de rodaje probando ubicaciones)
A35: Fondo de maniobra (meses de costes fijos) | B35: 3 | C35: Mínimo que exige este mismo libro (Instrucciones): un colchón por debajo de 3 meses no cubre un bache de mal tiempo o de temporada baja de eventos
A36: FISCAL
A37: Impuesto de Sociedades, nueva creación | B37: 0.15 | C37: Art. 29.1 LIS: el PRIMER ejercicio con base imponible positiva y el SIGUIENTE. El libro lo aproxima contando los dos primeros ejercicios con base positiva: coincide con la ley salvo que entre ellos haya un ejercicio en pérdidas
A38: Impuesto de Sociedades, tipo general | B38: 0.25 | C38: A partir del tercer ejercicio con base positiva. Es el tipo general del art. 29.1 LIS: si tu cifra de negocios queda por debajo de 1 M € (microempresa) o de 10 M € (reducida dimensión), desde 2025 hay tipos más bajos que se implantan de forma gradual; confirma el de tu ejercicio con tu asesor y cámbialo aquí
A39: IVA repercutido de restauración | B39: 0.1 | C39: Tipo reducido de hostelería
A40: IVA repercutido/soportado general | B40: 0.21 | C40: Tipo general. En este libro lo usan dos cosas: el IVA que soportas al comprar el alcohol (el proveedor lo factura al 21 %) y el que repercutes por el alcohol que sale por delivery (es una entrega de bienes). El alcohol servido en sala va al reducido: su tipo está en el bloque de desglose del IVA. Suministros, equipamiento y servicios tienen su tipo en la celda de abajo. El libro manda al general sólo el alcohol: si compras refrescos o zumos con azúcares añadidos, su factura también va al 21 % (art. 91.Uno.1.1.º de la Ley 37/1992)
A41: IVA soportado en compras e inversión | B41: 0.21 | C41: Recuperable vía modelo 303, pero hay que adelantarlo
A42: Bases negativas de ejercicios anteriores (€) | B42: 0 | C42: Pérdidas pendientes de compensar al empezar (art. 26 LIS)
A43: AMORTIZACIÓN
A44: Vida útil de obra e instalaciones (años) | B44: 8 | C44: Vehículo, adaptación y rotulación, instalación de gas, depósito de aguas y proyecto técnico: todo lo que va montado en el vehículo se amortiza con él. Ocho años son el 12,5 % anual, por debajo del coeficiente lineal máximo del 16 % que la tabla del art. 12.1 de la Ley del Impuesto sobre Sociedades fija para los elementos de transporte. Confírmalo con tu asesor
A45: Vida útil de maquinaria y mobiliario (años) | B45: 10 | C45: Equipamiento de cocina, generador, TPV, menaje y toldo. El uso es más intenso que en una cocina fija por el montaje y el desmontaje diarios, pero el coeficiente lineal máximo de la tabla del art. 12.1 de la Ley del Impuesto sobre Sociedades es del 12 % para maquinaria y del 10 % para mobiliario: por debajo de 9-10 años el exceso no sería deducible. Confírmalo con tu asesor
A47: CRECIMIENTO Y ACTUALIZACIÓN DE COSTES
A48: Subida anual de los costes fijos | B48: 0 | C48: A CERO: las tres columnas están en euros del año 1 (términos reales). Súbela si quieres proyectar en euros corrientes
A49: ARRANQUE Y AFORO
A51: Plazas de pie y mesas altas junto al vehículo | B51: 16 | C51: DATO INFORMATIVO: no entra en ningún cálculo de este libro. Son las cuatro mesas altas plegables de cuatro posiciones que presupuesta la partida «Toldo, mobiliario exterior plegable» de la hoja de inversión. Un food truck no tiene aforo legal ni plazas sentadas, así que aquí no se calcula ninguna rotación por plaza: el techo real de este negocio son los clientes por servicio, que la tabla de referencias de este mismo libro sitúa en 40-80, y quien manda sobre el volumen es la celda «Clientes/día» de arriba
A52: Actividad del mes 1 sobre la de crucero | B52: 0.55 | C52: Un food truck que arranca no factura desde el primer día lo mismo que a los seis meses: hay que probar ubicaciones, entrar en los mercados y que la gente te conozca. Con 100 % se elimina la rampa y el año 1 se proyecta a velocidad de crucero
A53: Meses hasta alcanzar el régimen de crucero | B53: 6 | C53: La rampa sube en línea recta desde el porcentaje de arriba hasta el 100 % en este número de meses
A54: Meses de alquiler del aparcamiento ANTES de abrir | B54: 2 | C54: La adaptación del vehículo dura 4-8 semanas según la fase 2 de tu propio checklist: son dos meses de aparcamiento y base que se pagan antes de facturar el primer euro, así que forman parte de la inversión y no de la cuenta de resultados
A55: Imprevistos sobre las partidas de compra y adaptación del vehículo (%) | B55: 0.08 | C55: Se conserva el mismo 8 % que la versión anterior tenía escrito a mano en su fila de imprevistos, ahora calculado por fórmula sobre las partidas de compra y adaptación del vehículo: si cambias el precio del vehículo, los imprevistos se recalculan solos. La nota de esa fila, en la hoja de Inversión, enumera exactamente qué partidas entran
A57: COBROS, PAGOS Y DESGLOSE DEL IVA
A58: Días medios de cobro | B58: 0 | C58: En la ventanilla se cobra al contado (0 días). Súbelo si trabajas con organizadores de eventos o con clientes de catering que pagan a 15 o 30 días, o con plataformas que liquidan más tarde
A59: Días medios de pago a proveedor | B59: 30 | C59: Lo que te financian tus proveedores. Es lo primero que se pierde si te retrasas en un pago
A60: Mes de la paga extra de verano | B60: 7 | C60: Mes del año (1-12) en el que sale de caja la primera paga extra
A61: Mes de la paga extra de Navidad | B61: 12 | C61: Mes del año (1-12) en el que sale de caja la segunda paga extra
A62: Bebida ALCOHÓLICA sobre el total de bebida | B62: 0.05 | C62: Bebida ALCOHÓLICA sobre el total de bebida: casi nula — la línea de bebida de este plan es refrescos, agua y zumos, como describe la fila «Food cost bebidas» de la tabla de referencias («refrescos y agua embotellada»); sólo alguna cerveza envasada ocasional en festivales de música. El resto va al IVA reducido de hostelería. Este mismo peso reparte el IVA que SOPORTAS al comprar la bebida (la parte alcohólica al tipo general y el resto al reducido): si tu proveedor te factura al 21 % los refrescos y zumos con azúcares o edulcorantes añadidos —que es lo que manda el art. 91.Uno.1.1.º de la Ley 37/1992—, soportarás algo más de IVA del que estima el libro; lo recuperas igual con el modelo 303
A63: IVA de la bebida ALCOHÓLICA para consumir en el acto | B63: 0.1 | C63: 10 %, igual que el resto de lo que se sirve para consumir en el acto: el art. 91.Uno.2.2.º de la Ley 37/1992 del IVA grava al tipo reducido los servicios de hostelería y «el suministro de comidas y bebidas para consumir en el acto», sin excluir el alcohol, y eso es lo que hace un food truck. Si vendes alcohol envasado PARA LLEVAR no hay consumo en el acto y esa parte va al tipo general: el libro lo aplica sólo a la parte alcohólica que sale por el canal de la celda «Ventas por delivery sobre el total», que en este plan está a cero; súbela si abres ese canal
A64: UMBRALES Y SUELOS DE CONTROL
A65: DSCR mínimo aceptable | B65: 1 | C65: Por debajo de 1 el negocio no genera para pagar el préstamo. Ponlo en el covenant que te exija tu banco
A66: DSCR objetivo (verde) | B66: 1.25 | C66: Lo que suele pedir una entidad para dar el préstamo sin garantías adicionales
A67: Holgura mínima sobre el punto de equilibrio | B67: 0.15 | C67: Cuánto deben superar las ventas previstas a las del equilibrio de caja (costes fijos y cuota del préstamo). La caída que aguantas es algo menor: con un 15 % de holgura, un 13 % de lo previsto
A68: Suelo salarial anual del convenio provincial (€) | B68: 0 | C68: El convenio PROVINCIAL de hostelería (o el de comercio, según cómo se clasifique la actividad de venta ambulante en tu provincia) es el suelo real del sector: cópialo de la tabla salarial que corresponda. Con 0 el semáforo compara sólo contra el SMI

Sheet Inversión Inicial
A1: PLAN DE NEGOCIO: FOOD TRUCK
A2: Inversión Inicial Estimada — España 2026
A3: Ajusta las cifras a tu proyecto.
A5: Concepto | B5: Importe | C5: % s/inversión | D5: Notas | E5: ¿Lleva IVA?
A6: INVERSIÓN | B6: =IFERROR(IF(COUNT(B7:B23)=0,"",SUM(B7:B23)),"") -> 63944 | C6: =IFERROR(B6/$B$26,"") -> 0.77983531
A7: Vehículo food truck (nuevo o segunda mano) | B7: 25000 | C7: =IFERROR(B7/$B$26,"") -> 0.30488995 | D7: Furgoneta adaptada o remolque. Segunda mano desde 15K | E7: Sí
A8: Adaptación y rotulación vehículo | B8: 8000 | C8: =IFERROR(B8/$B$26,"") -> 0.097564783 | D8: Ventanilla servicio, mostrador, rotulación integral | E8: Sí
A9: Equipamiento cocina móvil | B9: 10000 | C9: =IFERROR(B9/$B$26,"") -> 0.12195598 | D9: Plancha, freidora, campaña, nevera, fregadero | E9: Sí
A10: Generador eléctrico o conexión | B10: 3000 | C10: =IFERROR(B10/$B$26,"") -> 0.036586794 | D10: Generador insonorizado o kit conexión a red | E10: Sí
A11: Instalación gas (si aplica) | B11: 1500 | C11: =IFERROR(B11/$B$26,"") -> 0.018293397 | D11: Certificación gas obligatoria, revisión anual | E11: Sí
A12: Depósito de agua + aguas residuales | B12: 800 | C12: =IFERROR(B12/$B$26,"") -> 0.0097564783 | D12: Depósito de agua limpia y de aguas residuales del vehículo: es el equipo que exige el proyecto técnico sanitario para servir comida fuera de un local con acometida | E12: Sí
A13: Constitución SL + notaría + registro | B13: 800 | C13: =IFERROR(B13/$B$26,"") -> 0.0097564783 | D13: SL unipersonal exprés. Las tasas y el arancel del Registro Mercantil no llevan IVA, pero los honorarios del notario y de tu gestoría sí (21 %, deducible): el libro deja la fila entera fuera del IVA que hay que adelantar para no inflarlo. Si tu presupuesto es sobre todo de honorarios, cambia el desplegable de la columna «¿Lleva IVA?» a «Sí» | E13: No
A14: Licencias y permisos (promedio) | B14: 2000 | C14: =IFERROR(B14/$B$26,"") -> 0.024391196 | D14: Varía mucho por municipio y comunidad autónoma: pide el importe en el tuyo antes de cerrar el presupuesto | E14: No
A15: Proyecto técnico sanitario | B15: 1500 | C15: =IFERROR(B15/$B$26,"") -> 0.018293397 | D15: Obligatorio para la actividad alimentaria móvil: planos de instalación, flujos y depósitos de agua | E15: Sí
A16: TPV móvil + datáfono | B16: 800 | C16: =IFERROR(B16/$B$26,"") -> 0.0097564783 | D16: TPV tablet + datáfono 4G para cobros | E16: Sí
A17: Menaje, utensilios, packaging eco | B17: 1500 | C17: =IFERROR(B17/$B$26,"") -> 0.018293397 | D17: Menaje, utensilios y cubertería desechable: es el equipamiento que se amortiza. La primera compra de envases entra aquí sólo como arranque; el packaging de cada día NO se amortiza, va como coste variable en la línea «Consumibles y envases» de la cuenta de resultados, al porcentaje sobre ventas de la hoja de Supuestos | E17: Sí
A18: Stock inicial de producto | B18: 1000 | C18: =IFERROR(B18/$B$26,"") -> 0.012195598 | D18: Género para las primeras dos semanas de servicio. El libro calcula el IVA que adelantas por esta fila al tipo general, aunque los alimentos se compren al 10 % (o al 4 %): son unos euros de más en la caja del arranque, que se recuperan igual con el modelo 303 | E18: Sí
... A20: Toldo, mobiliario exterior plegable | B20: 1500 | C20: =IFERROR(B20/$B$26,"") -> 0.018293397 | D20: Mesas altas plegables, sombrilla, banderolas | E20: Sí
A21: Fianza del alquiler | B21: =IFERROR(IF('0. Supuestos'!$B$24="","",'0. Supuestos'!$B$24*'0. Supuestos'!$B$25),"") -> 800 | C21: =IFERROR(B21/$B$26,"") -> 0.0097564783 | D21: =IFERROR(""&TEXT('0. Supuestos'!$B$25,"0")&" meses de renta, al tipo de la hoja de Supuestos. Es un activo recuperable al cerrar: ni se amortiza ni lleva IVA","") -> 2 meses de renta, al tipo de la hoja de Supuestos. Es un activo recuperable al cerrar: ni se amortiza ni lleva IVA | E21: No
A22: Alquiler de los meses previos a la apertura | B22: =IFERROR(IF('0. Supuestos'!$B$24="","",'0. Supuestos'!$B$24*'0. Supuestos'!$B$54),"") -> 800 | C22: =IFERROR(B22/$B$26,"") -> 0.0097564783 | D22: =IFERROR("Renta "&IF('0. Supuestos'!$B$54=1,"del mes","de los "&TEXT('0. Supuestos'!$B$54,"0")&" meses")&" de obra y licencias. NO se solapa con el P&L, que arranca el día de la apertura: los doce meses del P&L son los doce de explotación","") -> Renta de los 2 meses de obra y licencias. NO se solapa con el P&L, que arranca el día de la apertura: los doce meses del P&L son los doce de explotación | E22: Sí
A23: Imprevistos de obra y acondicionamiento | B23: =IFERROR(IF(COUNT(B7,B8,B11,B12,B15)=0,"",ROUND((B7+B8+B11+B12+B15)*'0. Supuestos'!$B$55,0)),"") -> 2944 | C23: =IFERROR(B23/$B$26,"") -> 0.03590384 | D23: =IFERROR("Al "&TEXT('0. Supuestos'!$B$55,"0%")&" de las partidas de OBRA Y ACONDICIONAMIENTO de este bloque (Vehículo food truck (nuevo o segunda mano), Adaptación y rotulación vehículo, Instalación gas (si aplica), Depósito de agua + aguas residuales y Proyecto técnico sanitario), no "&"del bloque entero: el resto de partidas del bloque quedan fuera. Un banco no financia una reforma sin colchón: el porcentaje está en la hoja de Supuestos","") -> Al 8% de las partidas de OBRA Y ACONDICIONAMIENTO de este bloque (Vehículo food truck (nuevo o segunda mano), Adaptación y rotulación vehículo, Instalación gas (si aplica), Depósito de agua + aguas residuales y Proyecto técnico sanitario), no del bloque entero: el resto de partidas del bloque quedan fuera. Un banco no financia una reforma sin colchón: el porcentaje está en la hoja de Supuestos | E23: Sí
A24: FONDO DE MANIOBRA | B24: =IFERROR(IF(B25="","",B25),"") -> 18052.8 | C24: =IFERROR(B24/$B$26,"") -> 0.22016469
A25: Colchón operativo hasta alcanzar el equilibrio | B25: =IFERROR(IF('0. Supuestos'!$B$35*('PyG 3 Años'!$B$38-'PyG 3 Años'!$B$36)=0,"",'0. Supuestos'!$B$35*('PyG 3 Años'!$B$38-'PyG 3 Años'!$B$36)/12),"") -> 18052.8 | C25: =IFERROR(B25/$B$26,"") -> 0.22016469 | D25: =IFERROR("Cubre "&TEXT('0. Supuestos'!$B$35,"0")&IF('0. Supuestos'!$B$35=1," mes"," meses")&" de costes fijos DE CAJA del año 1 (los del P&L menos la amortización, que no se paga), que es el mínimo que exigen las Instrucciones de este libro","") -> Cubre 3 meses de costes fijos DE CAJA del año 1 (los del P&L menos la amortización, que no se paga), que es el mínimo que exigen las Instrucciones de este libro | E25: No
A26: INVERSIÓN TOTAL (suma de los bloques) | B26: =IFERROR(B6+B24,"") -> 81996.8 | D26: =IFERROR("Los porcentajes de la columna C se leen sobre esta cifra, que incluye el fondo de maniobra ("&TEXT(C24,"0%")&" del total). Para comparar el desglose con otro plan, usa la fila de CAPEX de abajo.","") -> Los porcentajes de la columna C se leen sobre esta cifra, que incluye el fondo de maniobra (22% del total). Para comparar el desglose con otro plan, usa la fila de CAPEX de abajo.
A27: CAPEX (inversión sin el fondo de maniobra) | B27: =IFERROR(B26-B24,"") -> 63944 | D27: Es lo que se compra: obra, equipamiento, lanzamiento y gastos de constitución. El colchón de caja no es inversión, es circulante
A28: IVA soportado sobre la inversión (recuperable) | B28: =IFERROR(IF(B26="","",SUMIF($E$7:$E$23,"Sí",$B$7:$B$23)*'0. Supuestos'!$B$41),"") -> 12672.24 | D28: =IFERROR("Al "&TEXT('0. Supuestos'!$B$41,"0%")&" sobre las partidas marcadas con «Sí» en la columna de IVA. Las tasas y licencias no están sujetas y los seguros están exentos (art. 20.Uno.16 LIVA). Las tasas y aranceles registrales no llevan IVA; los honorarios de notaría y gestoría sí "&"(21 %, deducible). Se recupera con el modelo 303, pero hay que adelantarlo","") -> Al 21% sobre las partidas marcadas con «Sí» en la columna de IVA. Las tasas y licencias no están sujetas y los seguros están exentos (art. 20.Uno.16 LIVA). Las tasas y aranceles registrales no llevan IVA; los honorarios de notaría y gestoría sí (21 %, deducible). Se recupera con el modelo 303, pero hay que adelantarlo
A29: NECESIDAD TOTAL DE CAJA AL ARRANQUE | B29: =IFERROR(B26+B28,"") -> 94669.04 | D29: Es la cifra que tiene que cubrir la hoja de Financiación
A30: BASES DE AMORTIZACIÓN (no suman a la inversión)
A31: Obra, instalaciones y acondicionamiento | B31: =IFERROR(IF(B7="","",B7+B8+B11+B12+B15+B23),"") -> 39744 | D31: =IFERROR("Se amortiza en "&TEXT('0. Supuestos'!$B$44,"0")&" años","") -> Se amortiza en 8 años
A32: Maquinaria, mobiliario y equipos | B32: =IFERROR(IF(B9="","",B9+B10+B16+B17+B20),"") -> 16800 | D32: =IFERROR("Se amortiza en "&TEXT('0. Supuestos'!$B$45,"0")&" años","") -> Se amortiza en 10 años
A33: Amortización anual del inmovilizado | B33: =IFERROR(B31/MAX(1,'0. Supuestos'!$B$44)+B32/MAX(1,'0. Supuestos'!$B$45),"") -> 6648 | D33: =IFERROR("No se amortizan, por no ser inmovilizado, Constitución SL + notaría + registro, Licencias y permisos (promedio), Stock inicial de producto, Marketing lanzamiento, Fianza del alquiler, Alquiler de los meses previos a la apertura ni Colchón "&"operativo hasta alcanzar el equilibrio. Suman "&TEXT(B26-B31-B32,"0")&" € de los "&TEXT(B26,"0")&" € de inversión.","") -> No se amortizan, por no ser inmovilizado, Constitución SL + notaría + registro, Licencias y permisos (promedio), Stock inicial de producto, Marketing lanzamiento, Fianza del alquiler, Alquiler de los meses previos a la apertura ni Colchón operativo hasta alcanzar el equilibrio. Suman 25453 € de los 81997 € de inversión.

Sheet PyG 3 Años
A1: CUENTA DE RESULTADOS PREVISIONAL — 3 AÑOS
A2: Escenario realista — Food Truck urbano
A4: Concepto | B4: Año 1 | C4: Año 2 | D4: Año 3 | E4: % s/ventas (año 1) | F4: Notas | G4: Tipo de IVA de la línea (%)
A5: INGRESOS
A6: Clientes/día (media) | B6: =IFERROR(IF('0. Supuestos'!$B$4="","",'0. Supuestos'!$B$4),"") -> 45 | C6: =IFERROR(B6*(1+'0. Supuestos'!$B$7),"") -> 51.75 | D6: =IFERROR(C6*(1+'0. Supuestos'!$B$8),"") -> 56.925 | F6: El crecimiento de los años 2 y 3 está en la hoja de Supuestos
A7: Ticket medio sin IVA | B7: =IFERROR(IF('0. Supuestos'!$B$5="","",'0. Supuestos'!$B$5),"") -> 12 | C7: =IFERROR(IF(B7="","",B7),"") -> 12 | D7: =IFERROR(IF(C7="","",C7),"") -> 12 | F7: Constante en euros del año 1: una subida de precios es una decisión aparte
A8: Días de apertura al año | B8: =IFERROR(IF('0. Supuestos'!$B$6="","",'0. Supuestos'!$B$6),"") -> 250 | C8: =IFERROR(IF(B8="","",B8),"") -> 250 | D8: =IFERROR(IF(C8="","",C8),"") -> 250
A9: INGRESOS TOTALES (sin IVA) | B9: =IFERROR(IF(B6*B7*B8=0,"",B6*B7*B8),"") -> 135000 | C9: =IFERROR(IF(C6*C7*C8=0,"",C6*C7*C8),"") -> 155250 | D9: =IFERROR(IF(D6*D7*D8=0,"",D6*D7*D8),"") -> 170775 | E9: =IFERROR(IF(B9="","",1),"") -> 1
A10: Ventas de comida (calle, mercados y catering privado) | B10: =IFERROR(IF(B9="","",B9*$E$10),"") -> 115006.5 | C10: =IFERROR(IF(C9="","",C9*$E$10),"") -> 132257.47 | D10: =IFERROR(IF(D9="","",D9*$E$10),"") -> 145483.22 | E10: =IFERROR(IF('0. Supuestos'!$B$11="","",'0. Supuestos'!$B$11),"") -> 0.8519 | F10: Producto principal servido en ubicaciones fijas y mercados, más el catering y las celebraciones privadas (la línea «Catering/eventos privados» de la v1.1, que en el fichero original NO llevaba coste de mercancía propio: aquí SÍ lo lleva, con el mismo tipo que la comida de calle) | G10: =IFERROR(IF(B9="","",'0. Supuestos'!$B$39),"") -> 0.1
A11: Ventas de bebida (refrescos, agua y zumos embotellados) | B11: =IFERROR(IF(B9="","",B9*$E$11),"") -> 19993.5 | C11: =IFERROR(IF(C9="","",C9*$E$11),"") -> 22992.525 | D11: =IFERROR(IF(D9="","",D9*$E$11),"") -> 25291.777 | E11: =IFERROR(IF('0. Supuestos'!$B$12="","",'0. Supuestos'!$B$12),"") -> 0.1481 | F11: Bebidas embotelladas de acompañamiento del menú: el food truck no sirve bebida de barra | G11: =IFERROR(IF(B9="","",('0. Supuestos'!$B$62*((1-'0. Supuestos'!$B$16)*'0. Supuestos'!$B$63+'0. Supuestos'!$B$16*'0. Supuestos'!$B$40)+(1-'0. Supuestos'!$B$62)*'0. Supuestos'!$B$39)),"") -> 0.1
A12: COSTES VARIABLES
A13: Coste de mercancía — comida | B13: =IFERROR(IF(B9="","",B9*'0. Supuestos'!$B$11*'0. Supuestos'!$B$13),"") -> 32201.82 | C13: =IFERROR(IF(C9="","",C9*'0. Supuestos'!$B$11*'0. Supuestos'!$B$13),"") -> 37032.093 | D13: =IFERROR(IF(D9="","",D9*'0. Supuestos'!$B$11*'0. Supuestos'!$B$13),"") -> 40735.302 | E13: =IFERROR(B13/$B$9,"") -> 0.238532 | F13: =IFERROR("Al "&TEXT('0. Supuestos'!$B$13,"0%")&" de las ventas de COMIDA, no del total: la bebida tiene su propia línea","") -> Al 28% de las ventas de COMIDA, no del total: la bebida tiene su propia línea | G13: =IFERROR(IF(B9="","",'0. Supuestos'!$B$39),"") -> 0.1
A14: Coste de mercancía — bebida | B14: =IFERROR(IF(B9="","",B9*'0. Supuestos'!$B$12*'0. Supuestos'!$B$14),"") -> 4398.57 | C14: =IFERROR(IF(C9="","",C9*'0. Supuestos'!$B$12*'0. Supuestos'!$B$14),"") -> 5058.3555 | D14: =IFERROR(IF(D9="","",D9*'0. Supuestos'!$B$12*'0. Supuestos'!$B$14),"") -> 5564.191 | E14: =IFERROR(B14/$B$9,"") -> 0.032582 | F14: =IFERROR("Al "&TEXT('0. Supuestos'!$B$14,"0%")&" de las ventas de BEBIDA","") -> Al 22% de las ventas de BEBIDA | G14: =IFERROR(IF(B9="","",('0. Supuestos'!$B$62*'0. Supuestos'!$B$40+(1-'0. Supuestos'!$B$62)*'0. Supuestos'!$B$39)),"") -> 0.1055
A15: Consumibles y envases | B15: =IFERROR(IF(B9="","",B9*'0. Supuestos'!$B$15),"") -> 4050 | C15: =IFERROR(IF(C9="","",C9*'0. Supuestos'!$B$15),"") -> 4657.5 | D15: =IFERROR(IF(D9="","",D9*'0. Supuestos'!$B$15),"") -> 5123.25 | E15: =IFERROR(B15/$B$9,"") -> 0.03 | G15: =IFERROR(IF(B9="","",'0. Supuestos'!$B$41),"") -> 0.21
A16: Comisiones de delivery | B16: =IFERROR(IF(B9="","",B9*'0. Supuestos'!$B$16*'0. Supuestos'!$B$17),"") -> 0 | C16: =IFERROR(IF(C9="","",C9*'0. Supuestos'!$B$16*'0. Supuestos'!$B$17),"") -> 0 | D16: =IFERROR(IF(D9="","",D9*'0. Supuestos'!$B$16*'0. Supuestos'!$B$17),"") -> 0 | E16: =IFERROR(B16/$B$9,"") -> 0 | F16: Sobre las ventas DEL CANAL. Con 0 % de delivery en Supuestos, esta línea vale cero | G16: =IFERROR(IF(B9="","",'0. Supuestos'!$B$41),"") -> 0.21
A17: Comisiones de los medios de pago | B17: =IFERROR(IF(B9="","",B9*'0. Supuestos'!$B$18),"") -> 1080 | C17: =IFERROR(IF(C9="","",C9*'0. Supuestos'!$B$18),"") -> 1242 | D17: =IFERROR(IF(D9="","",D9*'0. Supuestos'!$B$18),"") -> 1366.2 | E17: =IFERROR(B17/$B$9,"") -> 0.008 | F17: Las comisiones de los medios de pago están EXENTAS de IVA (art. 20.Uno.18 LIVA): no se deduce nada por ellas | G17: 0
A18: Varios e imprevistos | B18: =IFERROR(IF(B9="","",B9*'0. Supuestos'!$B$28),"") -> 6750 | C18: =IFERROR(IF(C9="","",C9*'0. Supuestos'!$B$28),"") -> 7762.5 | D18: =IFERROR(IF(D9="","",D9*'0. Supuestos'!$B$28),"") -> 8538.75 | E18: =IFERROR(B18/$B$9,"") -> 0.05 | F18: =IFERROR("Al "&TEXT('0. Supuestos'!$B$28,"0%")&" de las ventas. Es un coste VARIABLE: sube y baja con la facturación, así que no puede vivir en los costes fijos","") -> Al 5% de las ventas. Es un coste VARIABLE: sube y baja con la facturación, así que no puede vivir en los costes fijos | G18: =IFERROR(IF(B9="","",'0. Supuestos'!$B$41),"") -> 0.21
A19: TOTAL COSTES VARIABLES | B19: =IFERROR(IF(B9="","",SUM(B13:B18)),"") -> 48480.39 | C19: =IFERROR(IF(C9="","",SUM(C13:C18)),"") -> 55752.448 | D19: =IFERROR(IF(D9="","",SUM(D13:D18)),"") -> 61327.693 | E19: =IFERROR(B19/$B$9,"") -> 0.359114
A20: MARGEN BRUTO | B20: =IFERROR(IF(B9="","",B9-B19),"") -> 86519.61 | C20: =IFERROR(IF(C9="","",C9-C19),"") -> 99497.551 | D20: =IFERROR(IF(D9="","",D9-D19),"") -> 109447.31 | E20: =IFERROR(B20/$B$9,"") -> 0.640886
A21: COSTES FIJOS
A22: Aparcamiento y base del vehículo | B22: =IFERROR(IF(B9="","",'0. Supuestos'!$B$24*12),"") -> 4800 | C22: =IFERROR(IF(C9="","",B22*(1+'0. Supuestos'!$B$48)),"") -> 4800 | D22: =IFERROR(IF(D9="","",C22*(1+'0. Supuestos'!$B$48)),"") -> 4800 | E22: =IFERROR(B22/$B$9,"") -> 0.035555556 | F22: El importe mensual está en la hoja de Supuestos; aquí se multiplica por doce. Es la plaza de aparcamiento y la base del vehículo (agua, limpieza y vaciado de residuales), no la renta de un local. Los meses previos a la apertura están en la hoja de Inversión y NO se cuentan dos veces | G22: =IFERROR(IF(B9="","",'0. Supuestos'!$B$41),"") -> 0.21
A23: Personal (nóminas + Seguridad Social) | B23: =IFERROR(IF(B9="","",'Personal'!$G$9),"") -> 42081.2 | C23: =IFERROR(IF(C9="","",'Personal'!$B$13),"") -> 48081.2 | D23: =IFERROR(IF(D9="","",'Personal'!$B$14),"") -> 54081.2 | E23: =IFERROR(B23/$B$9,"") -> 0.31171259 | F23: Sale de la hoja de Personal: es el MISMO número, no una estimación aparte. Los años 2 y 3 suman las INCORPORACIONES declaradas en esa hoja, no un porcentaje de volumen | G23: 0
A24: Suministros (luz, agua, gas) | B24: =IFERROR(IF(B9="","",'0. Supuestos'!$B$26*12),"") -> 2400 | C24: =IFERROR(IF(C9="","",B24*(1+'0. Supuestos'!$B$48)),"") -> 2400 | D24: =IFERROR(IF(D9="","",C24*(1+'0. Supuestos'!$B$48)),"") -> 2400 | E24: =IFERROR(B24/$B$9,"") -> 0.017777778 | F24: Combustible del generador eléctrico, agua limpia y vaciado de residuales en la base del vehículo. Luz y gas van al 21 % y la factura del agua al 10 %: el libro aplica a toda la partida el tipo de la columna de al lado (21 %), así que si el agua pesa mucho en tu caso, sepárala en su propia línea | G24: =IFERROR(IF(B9="","",'0. Supuestos'!$B$41),"") -> 0.21
A25: Seguros (RC + multirriesgo) | B25: =IFERROR(IF(B9="","",'0. Supuestos'!$B$27),"") -> 2500 | C25: =IFERROR(IF(C9="","",B25*(1+'0. Supuestos'!$B$48)),"") -> 2500 | D25: =IFERROR(IF(D9="","",C25*(1+'0. Supuestos'!$B$48)),"") -> 2500 | E25: =IFERROR(B25/$B$9,"") -> 0.018518519 | F25: Las operaciones de seguro están EXENTAS de IVA (art. 20.Uno.16 LIVA): la prima no lleva IVA deducible | G25: 0
A26: Permisos y licencias (anuales) | B26: 3600 | C26: =IFERROR(IF(C9="","",B26*(1+'0. Supuestos'!$B$48)),"") -> 3600 | D26: =IFERROR(IF(D9="","",C26*(1+'0. Supuestos'!$B$48)),"") -> 3600 | E26: =IFERROR(B26/$B$9,"") -> 0.026666667 | G26: =IFERROR(IF(B9="","",'0. Supuestos'!$B$41),"") -> 0.21
A27: Mantenimiento vehículo + ITV | B27: 2400 | C27: =IFERROR(IF(C9="","",B27*(1+'0. Supuestos'!$B$48)),"") -> 2400 | D27: =IFERROR(IF(D9="","",C27*(1+'0. Supuestos'!$B$48)),"") -> 2400 | E27: =IFERROR(B27/$B$9,"") -> 0.017777778 | G27: =IFERROR(IF(B9="","",'0. Supuestos'!$B$41),"") -> 0.21
A28: Marketing y publicidad | B28: 4800 | C28: =IFERROR(IF(C9="","",B28*(1+'0. Supuestos'!$B$48)),"") -> 4800 | D28: =IFERROR(IF(D9="","",C28*(1+'0. Supuestos'!$B$48)),"") -> 4800 | E28: =IFERROR(B28/$B$9,"") -> 0.035555556 | G28: =IFERROR(IF(B9="","",'0. Supuestos'!$B$41),"") -> 0.21
A29: Gestoría + contabilidad | B29: 1800 | C29: =IFERROR(IF(C9="","",B29*(1+'0. Supuestos'!$B$48)),"") -> 1800 | D29: =IFERROR(IF(D9="","",C29*(1+'0. Supuestos'!$B$48)),"") -> 1800 | E29: =IFERROR(B29/$B$9,"") -> 0.013333333 | G29: =IFERROR(IF(B9="","",'0. Supuestos'!$B$41),"") -> 0.21
A30: Software (TPV, web, RRSS) | B30: 600 | C30: =IFERROR(IF(C9="","",B30*(1+'0. Supuestos'!$B$48)),"") -> 600 | D30: =IFERROR(IF(D9="","",C30*(1+'0. Supuestos'!$B$48)),"") -> 600 | E30: =IFERROR(B30/$B$9,"") -> 0.0044444444 | G30: =IFERROR(IF(B9="","",'0. Supuestos'!$B$41),"") -> 0.21
A31: Limpieza y productos | B31: 1200 | C31: =IFERROR(IF(C9="","",B31*(1+'0. Supuestos'!$B$48)),"") -> 1200 | D31: =IFERROR(IF(D9="","",C31*(1+'0. Supuestos'!$B$48)),"") -> 1200 | E31: =IFERROR(B31/$B$9,"") -> 0.0088888889 | G31: =IFERROR(IF(B9="","",'0. Supuestos'!$B$41),"") -> 0.21
A32: Gestión de residuos (orgánico, cartón y aceite usado) | B32: 400 | C32: =IFERROR(IF(C9="","",B32*(1+'0. Supuestos'!$B$48)),"") -> 400 | D32: =IFERROR(IF(D9="","",C32*(1+'0. Supuestos'!$B$48)),"") -> 400 | E32: =IFERROR(B32/$B$9,"") -> 0.002962963 | F32: Gestor autorizado. El propio checklist ya avisa de que la freidora genera aceite usado que hay que gestionar, pero nunca contrataba el servicio. Pide presupuesto en tu zona | G32: =IFERROR(IF(B9="","",'0. Supuestos'!$B$41),"") -> 0.21
A33: Desinsectación, desratización y desinfección (DDD) | B33: 400 | C33: =IFERROR(IF(C9="","",B33*(1+'0. Supuestos'!$B$48)),"") -> 400 | D33: =IFERROR(IF(D9="","",C33*(1+'0. Supuestos'!$B$48)),"") -> 400 | E33: =IFERROR(B33/$B$9,"") -> 0.002962963 | F33: Empresa inscrita en el ROESB; forma parte del plan APPCC móvil que el checklist ya exige en su fase de personal | G33: =IFERROR(IF(B9="","",'0. Supuestos'!$B$41),"") -> 0.21
A34: Prevención de riesgos laborales y vigilancia de la salud | B34: 350 | C34: =IFERROR(IF(C9="","",B34*(1+'0. Supuestos'!$B$48)),"") -> 350 | D34: =IFERROR(IF(D9="","",C34*(1+'0. Supuestos'!$B$48)),"") -> 350 | E34: =IFERROR(B34/$B$9,"") -> 0.0025925926 | F34: El plan de prevención es obligatorio; el proveedor externo, no (art. 30.5 de la Ley 31/1995). A quién se marca como responsable se corrige en el propio checklist | G34: =IFERROR(IF(B9="","",'0. Supuestos'!$B$41),"") -> 0.21
A35: Derechos de autor por música ambiental (SGAE/AGEDI-AIE) | B35: 200 | C35: =IFERROR(IF(C9="","",B35*(1+'0. Supuestos'!$B$48)),"") -> 200 | D35: =IFERROR(IF(D9="","",C35*(1+'0. Supuestos'!$B$48)),"") -> 200 | E35: =IFERROR(B35/$B$9,"") -> 0.0014814815 | F35: Sólo se paga si el food truck pone música propia en ferias y festivales (distinto de la licencia del organizador, que cubre el recinto y no cada puesto). Presupuesto mínimo por si se usa | G35: =IFERROR(IF(B9="","",'0. Supuestos'!$B$41),"") -> 0.21
A36: Amortización del inmovilizado | B36: =IFERROR(IF(B9="","",'Inversión Inicial'!$B$33),"") -> 6648 | C36: =IFERROR(IF(C9="","",B36),"") -> 6648 | D36: =IFERROR(IF(D9="","",B36),"") -> 6648 | E36: =IFERROR(B36/$B$9,"") -> 0.049244444 | F36: Sale de las bases de amortización de la hoja de Inversión: sólo inmovilizado real. NO sube con el IPC: es una cuota sobre el coste HISTÓRICO del inmovilizado | G36: 0
A37: Gastos financieros (intereses del préstamo) | B37: =IFERROR(IF(B9="","",'Financiación'!$B$44),"") -> 4680 | C37: =IFERROR(IF(C9="","",'Financiación'!$B$46),"") -> 4680 | D37: =IFERROR(IF(D9="","",'Financiación'!$B$48),"") -> 3858.0304 | E37: =IFERROR(B37/$B$9,"") -> 0.034666667 | F37: Sólo los INTERESES son gasto. La devolución del principal va en la hoja de Tesorería | G37: 0
A38: TOTAL COSTES FIJOS | B38: =IFERROR(IF(B9="","",SUM(B22:B37)),"") -> 78859.2 | C38: =IFERROR(IF(C9="","",SUM(C22:C37)),"") -> 84859.2 | D38: =IFERROR(IF(D9="","",SUM(D22:D37)),"") -> 90037.23 | E38: =IFERROR(B38/$B$9,"") -> 0.58414222
A39: IVA soportado de los costes variables | B39: =IFERROR(IF(B9="","",SUMPRODUCT(B13:B18,G13:G18)),"") -> 5952.2311 | C39: =IFERROR(IF(C9="","",SUMPRODUCT(C13:C18,G13:G18)),"") -> 6845.0658 | D39: =IFERROR(IF(D9="","",SUMPRODUCT(D13:D18,G13:G18)),"") -> 7529.5724 | F39: Cada línea a SU tipo, leído de la columna de al lado. Es lo que la hoja de Tesorería paga de más a los proveedores y luego se deduce
A40: IVA soportado de los costes fijos | B40: =IFERROR(IF(B9="","",SUMPRODUCT(B22:B37,G22:G37)),"") -> 4819.5 | C40: =IFERROR(IF(C9="","",SUMPRODUCT(C22:C37,G22:G37)),"") -> 4819.5 | D40: =IFERROR(IF(D9="","",SUMPRODUCT(D22:D37,G22:G37)),"") -> 4819.5
A41: RESULTADO ANTES DE IMPUESTOS | B41: =IFERROR(IF(B9="","",B20-B38),"") -> 7660.41 | C41: =IFERROR(IF(C9="","",C20-C38),"") -> 14638.351 | D41: =IFERROR(IF(D9="","",D20-D38),"") -> 19410.076 | E41: =IFERROR(B41/$B$9,"") -> 0.056743778
A42: Bases negativas pendientes al inicio | B42: =IFERROR(IF(B9="","",'0. Supuestos'!$B$42),"") -> 0 | C42: =IFERROR(IF(C9="","",B47),"") -> 0 | D42: =IFERROR(IF(D9="","",C47),"") -> 0 | F42: Art. 26 LIS: las pérdidas de un ejercicio se compensan con los beneficios de los siguientes
A43: Base imponible (después de compensar) | B43: =IFERROR(IF(B9="","",MAX(0,B41-B42)),"") -> 7660.41 | C43: =IFERROR(IF(C9="","",MAX(0,C41-C42)),"") -> 14638.351 | D43: =IFERROR(IF(D9="","",MAX(0,D41-D42)),"") -> 19410.076
A44: Ejercicios con base positiva (acumulado) | B44: =IFERROR(IF(B9="","",IF(B43>0,1,0)),"") -> 1 | C44: =IFERROR(IF(C9="","",B44+IF(C43>0,1,0)),"") -> 2 | D44: =IFERROR(IF(D9="","",C44+IF(D43>0,1,0)),"") -> 3
A45: Tipo de Impuesto de Sociedades aplicado | B45: =IFERROR(IF(B9="","",IF(B43<=0,"",IF(B44<=2,'0. Supuestos'!$B$37,'0. Supuestos'!$B$38))),"") -> 0.15 | C45: =IFERROR(IF(C9="","",IF(C43<=0,"",IF(C44<=2,'0. Supuestos'!$B$37,'0. Supuestos'!$B$38))),"") -> 0.15 | D45: =IFERROR(IF(D9="","",IF(D43<=0,"",IF(D44<=2,'0. Supuestos'!$B$37,'0. Supuestos'!$B$38))),"") -> 0.25 | F45: Art. 29.1 LIS: el 15 % de entidad de nueva creación se aplica al PRIMER ejercicio con base positiva y al SIGUIENTE, no al primer año de vida. El libro lo aproxima contando los dos primeros ejercicios con base positiva
A46: Impuesto de Sociedades | B46: =IFERROR(IF(B9="","",IF(B45="",0,B43*B45)),"") -> 1149.0615 | C46: =IFERROR(IF(C9="","",IF(C45="",0,C43*C45)),"") -> 2195.7527 | D46: =IFERROR(IF(D9="","",IF(D45="",0,D43*D45)),"") -> 4852.5191
A47: Bases negativas pendientes al cierre | B47: =IFERROR(IF(B9="","",MAX(0,B42-B41)),"") -> 0 | C47: =IFERROR(IF(C9="","",MAX(0,C42-C41)),"") -> 0 | D47: =IFERROR(IF(D9="","",MAX(0,D42-D41)),"") -> 0
A48: RESULTADO NETO | B48: =IFERROR(IF(B9="","",B41-B46),"") -> 6511.3485 | C48: =IFERROR(IF(C9="","",C41-C46),"") -> 12442.599 | D48: =IFERROR(IF(D9="","",D41-D46),"") -> 14557.557 | E48: =IFERROR(B48/$B$9,"") -> 0.048232211
A49: RATIOS CLAVE
A50: Ratio | B50: Año 1 | C50: Año 2 | D50: Año 3 | E50: Umbral | F50: Comentario
A51: Margen bruto / Ventas | B51: =IFERROR(IF(B9="","",B20/B9),"") -> 0.640886 | C51: =IFERROR(IF(C9="","",C20/C9),"") -> 0.640886 | D51: =IFERROR(IF(D9="","",D20/D9),"") -> 0.640886 | E51: 0.62 | F51: Suelo del propio libro: la fila «Margen bruto objetivo» (> 62 %) de la tabla DATOS DE REFERENCIA DEL SECTOR, en la hoja de Instrucciones. Más bajo que el de un restaurante por el peso del packaging y del combustible
A52: Coste de mercancía (comida + bebida) | B52: =IFERROR(IF(B9="","",B13+B14),"") -> 36600.39 | C52: =IFERROR(IF(C9="","",C13+C14),"") -> 42090.448 | D52: =IFERROR(IF(D9="","",D13+D14),"") -> 46299.493
A53: Coste de mercancía / Ventas | B53: =IFERROR(IF(B9="","",B52/B9),"") -> 0.271114 | C53: =IFERROR(IF(C9="","",C52/C9),"") -> 0.271114 | D53: =IFERROR(IF(D9="","",D52/D9),"") -> 0.271114 | E53: 0.33 | F53: Techo mezclado de los food cost que publica la tabla de referencias de este libro (comida 28-33 %, bebida 22-28 %). La ratio de al lado mide sólo la MERCANCÍA: los consumibles y los envases tienen su propia línea en la cuenta de resultados y no entran aquí, así que el caso base se queda holgadamente por debajo del techo
A54: Coste de personal / Ventas | B54: =IFERROR(IF(B9="","",B23/B9),"") -> 0.31171259 | C54: =IFERROR(IF(C9="","",C23/C9),"") -> 0.30970177 | D54: =IFERROR(IF(D9="","",D23/D9),"") -> 0.31668101 | E54: 0.32 | F54: Techo del propio libro: la fila «Coste personal sobre ventas» (25-32 %) de la tabla DATOS DE REFERENCIA DEL SECTOR, en la hoja de Instrucciones («menos personal que un restaurante: 2-3 personas»)
A55: Aparcamiento / Ventas | B55: =IFERROR(IF(B9="","",B22/B9),"") -> 0.035555556 | C55: =IFERROR(IF(C9="","",C22/C9),"") -> 0.030917874 | D55: =IFERROR(IF(D9="","",D22/D9),"") -> 0.028107159 | E55: 0.05 | F55: No hay referencia de local en este libro (el food truck no paga renta de local): 5 % es un techo prudente para el aparcamiento/base del vehículo, muy por debajo del 8-12 % de un negocio con local fijo (mismo orden que el resto de la familia, adaptado a este molde)
A56: Resultado neto / Ventas | B56: =IFERROR(IF(B9="","",B48/B9),"") -> 0.048232211 | C56: =IFERROR(IF(C9="","",C48/C9),"") -> 0.080145564 | D56: =IFERROR(IF(D9="","",D48/D9),"") -> 0.085244077 | E56: 0.04 | F56: Derivado del suelo de EBITDA que declara este producto para el año 2 —la fila «EBITDA objetivo (año 2)», 20-30 %, de la tabla de referencias—: descontando amortización, intereses e Impuesto de Sociedades, un EBITDA en la franja baja del rango deja un resultado neto positivo ya en el año 1, aunque ajustado por ser el primer ejercicio
A57: Punto de equilibrio alcanzado | B57: =IFERROR(IF(B9="","",IF(B9>='Punto Equilibrio'!$B$16,"Sí","No")),"") -> Sí | C57: =IFERROR(IF(C9="","",IF(C9>='Punto Equilibrio'!$C$16,"Sí","No")),"") -> Sí | D57: =IFERROR(IF(D9="","",IF(D9>='Punto Equilibrio'!$D$16,"Sí","No")),"") -> Sí | F57: Compara las ventas de CADA año con el umbral de ese mismo año, que calcula la hoja de Punto de Equilibrio con los costes fijos del año
A59: Todas las cifras van SIN IVA. Las columnas de los años 2 y 3 están en euros del año 1 salvo que subas la actualización de costes en la hoja de Supuestos. La columna «Tipo de IVA de la línea» dice, en las líneas de VENTA, a qué tipo se repercute cada una, y en las de COSTE a qué tipo se compra la partida. La lee la hoja de Tesorería: los seguros y las comisiones de los medios de pago están exentos, y las nóminas, la amortización y los intereses no llevan IVA.

Sheet Punto Equilibrio
A1: ANÁLISIS DE PUNTO DE EQUILIBRIO
A2: Break-even — Food Truck
A4: Variable | B4: Año 1 | C4: Año 2 | D4: Año 3 | E4: Notas
A5: DATOS BASE POR AÑO
A6: Costes fijos anuales | B6: =IFERROR(IF('PyG 3 Años'!$B$9="","",'PyG 3 Años'!$B$38),"") -> 78859.2 | C6: =IFERROR(IF('PyG 3 Años'!$C$9="","",'PyG 3 Años'!$C$38),"") -> 84859.2 | D6: =IFERROR(IF('PyG 3 Años'!$D$9="","",'PyG 3 Años'!$D$38),"") -> 90037.23 | E6: Los MISMOS costes fijos del P&L. Cada año tiene los suyos: por eso el umbral no puede ser uno solo para los tres
A7: Costes fijos mensuales | B7: =IFERROR(IF('PyG 3 Años'!$B$9="","",B6/12),"") -> 6571.6 | C7: =IFERROR(IF('PyG 3 Años'!$C$9="","",C6/12),"") -> 7071.6 | D7: =IFERROR(IF('PyG 3 Años'!$D$9="","",D6/12),"") -> 7503.1025
A8: Ticket medio sin IVA | B8: =IFERROR(IF('PyG 3 Años'!$B$9="","",'PyG 3 Años'!$B$7),"") -> 12 | C8: =IFERROR(IF('PyG 3 Años'!$C$9="","",'PyG 3 Años'!$C$7),"") -> 12 | D8: =IFERROR(IF('PyG 3 Años'!$D$9="","",'PyG 3 Años'!$D$7),"") -> 12
A9: Coste variable por cliente | B9: =IFERROR(IF('PyG 3 Años'!$B$9="","",'PyG 3 Años'!$B$19/('PyG 3 Años'!$B$6*'PyG 3 Años'!$B$8)),"") -> 4.309368 | C9: =IFERROR(IF('PyG 3 Años'!$C$9="","",'PyG 3 Años'!$C$19/('PyG 3 Años'!$C$6*'PyG 3 Años'!$C$8)),"") -> 4.309368 | D9: =IFERROR(IF('PyG 3 Años'!$D$9="","",'PyG 3 Años'!$D$19/('PyG 3 Años'!$D$6*'PyG 3 Años'!$D$8)),"") -> 4.309368 | E9: Sale del total de costes variables del P&L, no de una estimación aparte. Incluye los varios e imprevistos, que son un porcentaje de las ventas
A10: Margen de contribución por cliente | B10: =IFERROR(IF('PyG 3 Años'!$B$9="","",B8-B9),"") -> 7.690632 | C10: =IFERROR(IF('PyG 3 Años'!$C$9="","",C8-C9),"") -> 7.690632 | D10: =IFERROR(IF('PyG 3 Años'!$D$9="","",D8-D9),"") -> 7.690632 | E10: Ticket menos coste variable unitario
A11: Días de apertura al año | B11: =IFERROR(IF('PyG 3 Años'!$B$9="","",'PyG 3 Años'!$B$8),"") -> 250 | C11: =IFERROR(IF('PyG 3 Años'!$C$9="","",'PyG 3 Años'!$C$8),"") -> 250 | D11: =IFERROR(IF('PyG 3 Años'!$D$9="","",'PyG 3 Años'!$D$8),"") -> 250 | E11: El mismo calendario que el P&L y que los escenarios
A12: Devolución de principal del año (cuota) | B12: =IFERROR(IF('PyG 3 Años'!$B$9="","",'Financiación'!$B$45),"") -> 0 | C12: =IFERROR(IF('PyG 3 Años'!$C$9="","",'Financiación'!$B$47),"") -> 12645.687 | D12: =IFERROR(IF('PyG 3 Años'!$D$9="","",'Financiación'!$B$49),"") -> 13467.656 | E12: El principal NO es gasto del P&L, pero sale de la caja. Sin él, el umbral de equilibrio se publica por debajo del real
A13: PUNTO DE EQUILIBRIO CONTABLE (incluye amortización)
A14: Clientes necesarios al año | B14: =IFERROR(IF('PyG 3 Años'!$B$9="","",IF(B10<=0,"",B6/B10)),"") -> 10253.93 | C14: =IFERROR(IF('PyG 3 Años'!$C$9="","",IF(C10<=0,"",C6/C10)),"") -> 11034.1 | D14: =IFERROR(IF('PyG 3 Años'!$D$9="","",IF(D10<=0,"",D6/D10)),"") -> 11707.39
A15: Clientes necesarios al día | B15: =IFERROR(IF('PyG 3 Años'!$B$9="","",B14/B11),"") -> 41.015719 | C15: =IFERROR(IF('PyG 3 Años'!$C$9="","",C14/C11),"") -> 44.136399 | D15: =IFERROR(IF('PyG 3 Años'!$D$9="","",D14/D11),"") -> 46.829561
A16: Ingresos necesarios al año | B16: =IFERROR(IF('PyG 3 Años'!$B$9="","",B14*B8),"") -> 123047.16 | C16: =IFERROR(IF('PyG 3 Años'!$C$9="","",C14*C8),"") -> 132409.2 | D16: =IFERROR(IF('PyG 3 Años'!$D$9="","",D14*D8),"") -> 140488.68
A17: PUNTO DE EQUILIBRIO DE CAJA (incluye la cuota del préstamo)
A18: Costes fijos de caja + principal del año | B18: =IFERROR(IF('PyG 3 Años'!$B$9="","",B6-'PyG 3 Años'!$B$36+B12),"") -> 72211.2 | C18: =IFERROR(IF('PyG 3 Años'!$C$9="","",C6-'PyG 3 Años'!$C$36+C12),"") -> 90856.887 | D18: =IFERROR(IF('PyG 3 Años'!$D$9="","",D6-'PyG 3 Años'!$D$36+D12),"") -> 96856.887 | E18: Los fijos del P&L sin la amortización (que no se paga) y CON la devolución de principal (que sí). Es el umbral que decide si la caja aguanta
A19: Clientes necesarios al año (caja) | B19: =IFERROR(IF('PyG 3 Años'!$B$9="","",IF(B10<=0,"",B18/B10)),"") -> 9389.5014 | C19: =IFERROR(IF('PyG 3 Años'!$C$9="","",IF(C10<=0,"",C18/C10)),"") -> 11813.969 | D19: =IFERROR(IF('PyG 3 Años'!$D$9="","",IF(D10<=0,"",D18/D10)),"") -> 12594.139
A20: Clientes necesarios al día (caja) | B20: =IFERROR(IF('PyG 3 Años'!$B$9="","",B19/B11),"") -> 37.558006 | C20: =IFERROR(IF('PyG 3 Años'!$C$9="","",C19/C11),"") -> 47.255875 | D20: =IFERROR(IF('PyG 3 Años'!$D$9="","",D19/D11),"") -> 50.376555
A21: Ingresos necesarios al año (caja) | B21: =IFERROR(IF('PyG 3 Años'!$B$9="","",B19*B8),"") -> 112674.02 | C21: =IFERROR(IF('PyG 3 Años'!$C$9="","",C19*C8),"") -> 141767.63 | D21: =IFERROR(IF('PyG 3 Años'!$D$9="","",D19*D8),"") -> 151129.67
A22: CONTRASTE CON EL PLAN
A23: Clientes/día previstos en el plan | B23: =IFERROR(IF('PyG 3 Años'!$B$9="","",'PyG 3 Años'!$B$6),"") -> 45 | C23: =IFERROR(IF('PyG 3 Años'!$C$9="","",'PyG 3 Años'!$C$6),"") -> 51.75 | D23: =IFERROR(IF('PyG 3 Años'!$D$9="","",'PyG 3 Años'!$D$6),"") -> 56.925
A24: Holgura sobre el equilibrio de CAJA (%) | B24: =IFERROR(IF('PyG 3 Años'!$B$9="","",B23/B20-1),"") -> 0.19814669 | C24: =IFERROR(IF('PyG 3 Años'!$C$9="","",C23/C20-1),"") -> 0.095101925 | D24: =IFERROR(IF('PyG 3 Años'!$D$9="","",D23/D20-1),"") -> 0.12998993 | E24: Cuánto superan tus ventas previstas a las del equilibrio de caja. La caída que aguantas antes de no poder pagar los costes fijos y la cuota es algo menor: con un 25 % de holgura, un 20 %. El mínimo exigible está en la hoja de Supuestos
A25: INTERPRETACIÓN
A26: =IFERROR("Con el ticket medio sin IVA de la fila de arriba necesitas "&TEXT(ROUNDUP(B15,0),"0")&" clientes al día durante los "&TEXT(B11,"0")&" días que abres para no perder dinero (equilibrio contable, con la amortización dentro), y "&TEXT(ROUNDUP(B20,0),"0")&" para que la caja aguante (equilibrio de caja: sin la amortización, que no se paga, y con la cuota del préstamo del año"&IF(B12=0,"; este año sólo intereses, porque el préstamo está en carencia","")&"). En las filas «Ingresos necesarios al año» tienes esas mismas cifras en euros.","") -> Con el ticket medio sin IVA de la fila de arriba necesitas 42 clientes al día durante los 250 días que abres para no perder dinero (equilibrio contable, con la amortización dentro), y 38 para que la caja aguante (equilibrio de caja: sin la amortización, que no se paga, y con la cuota del préstamo del año; este año sólo intereses, porque el préstamo está en carencia). En las filas «Ingresos necesarios al año» tienes esas mismas cifras en euros.
A28: SENSIBILIDAD DEL PUNTO DE EQUILIBRIO
A29: Clientes/día necesarios para cubrir costes según el ticket medio (columnas) y el coste variable por cliente (filas). En verde, los que están por debajo de los clientes que prevé el plan.
A31: Clientes/día necesarios: ticket medio sin IVA (columnas) × coste variable por cliente (filas) | B31: =IFERROR($B$8-2,"") -> 10 | C31: =IFERROR(IF($B$8="","",$B$8),"") -> 12 | D31: =IFERROR($B$8+2,"") -> 14 | E31: =IFERROR($B$8+4,"") -> 16
A32: =IFERROR($B$9*0.85,"") -> 3.6629628 | B32: =IFERROR(IF($B$31-$A32<=0,"",$B$6/($B$31-$A32)/$B$11),"") -> 49.7767 | C32: =IFERROR(IF($C$31-$A32<=0,"",$B$6/($C$31-$A32)/$B$11),"") -> 37.835599 | D32: =IFERROR(IF($D$31-$A32<=0,"",$B$6/($D$31-$A32)/$B$11),"") -> 30.515204 | E32: =IFERROR(IF($E$31-$A32<=0,"",$B$6/($E$31-$A32)/$B$11),"") -> 25.568278
A33: =IFERROR($B$9*0.925,"") -> 3.9861654 | B33: =IFERROR(IF($B$31-$A33<=0,"",$B$6/($B$31-$A33)/$B$11),"") -> 52.451858 | C33: =IFERROR(IF($C$31-$A33<=0,"",$B$6/($C$31-$A33)/$B$11),"") -> 39.361531 | D33: =IFERROR(IF($D$31-$A33<=0,"",$B$6/($D$31-$A33)/$B$11),"") -> 31.500101 | E33: =IFERROR(IF($E$31-$A33<=0,"",$B$6/($E$31-$A33)/$B$11),"") -> 26.25613
A34: =IFERROR($B$9*1.0,"") -> 4.309368 | B34: =IFERROR(IF($B$31-$A34<=0,"",$B$6/($B$31-$A34)/$B$11),"") -> 55.430891 | C34: =IFERROR(IF($C$31-$A34<=0,"",$B$6/($C$31-$A34)/$B$11),"") -> 41.015719 | D34: =IFERROR(IF($D$31-$A34<=0,"",$B$6/($D$31-$A34)/$B$11),"") -> 32.550694 | E34: =IFERROR(IF($E$31-$A34<=0,"",$B$6/($E$31-$A34)/$B$11),"") -> 26.982014
A35: =IFERROR($B$9*1.075,"") -> 4.6325706 | B35: =IFERROR(IF($B$31-$A35<=0,"",$B$6/($B$31-$A35)/$B$11),"") -> 58.768691 | C35: =IFERROR(IF($C$31-$A35<=0,"",$B$6/($C$31-$A35)/$B$11),"") -> 42.815042 | D35: =IFERROR(IF($D$31-$A35<=0,"",$B$6/($D$31-$A35)/$B$11),"") -> 33.673785 | E35: =IFERROR(IF($E$31-$A35<=0,"",$B$6/($E$31-$A35)/$B$11),"") -> 27.749176
A36: =IFERROR($B$9*1.15,"") -> 4.9557732 | B36: =IFERROR(IF($B$31-$A36<=0,"",$B$6/($B$31-$A36)/$B$11),"") -> 62.534222 | C36: =IFERROR(IF($C$31-$A36<=0,"",$B$6/($C$31-$A36)/$B$11),"") -> 44.779478 | D36: =IFERROR(IF($D$31-$A36<=0,"",$B$6/($D$31-$A36)/$B$11),"") -> 34.877144 | E36: =IFERROR(IF($E$31-$A36<=0,"",$B$6/($E$31-$A36)/$B$11),"") -> 28.561239

Sheet Escenarios
A1: ANÁLISIS DE ESCENARIOS
A4: Métrica | B4: Pesimista | C4: Realista | D4: Optimista | E4: Notas
A5: Clientes/día | B5: 30 | C5: =IFERROR(IF('PyG 3 Años'!$B$6="","",'PyG 3 Años'!$B$6),"") -> 45 | D5: 65
A6: Ticket medio sin IVA | B6: 10 | C6: =IFERROR(IF('PyG 3 Años'!$B$7="","",'PyG 3 Años'!$B$7),"") -> 12 | D6: 14
A7: Días de apertura al año | B7: 250 | C7: =IFERROR(IF('PyG 3 Años'!$B$8="","",'PyG 3 Años'!$B$8),"") -> 250 | D7: 250
A8: INGRESOS ANUALES (sin IVA) | B8: =IFERROR(IF(B5*B6*B7=0,"",B5*B6*B7),"") -> 75000 | C8: =IFERROR(IF(C5*C6*C7=0,"",C5*C6*C7),"") -> 135000 | D8: =IFERROR(IF(D5*D6*D7=0,"",D5*D6*D7),"") -> 227500
A9: Coste de mercancía — comida | B9: =IFERROR(IF(B8="","",B8*'0. Supuestos'!$B$11*'0. Supuestos'!$B$13),"") -> 17889.9 | C9: =IFERROR(IF(C8="","",C8*'0. Supuestos'!$B$11*'0. Supuestos'!$B$13),"") -> 32201.82 | D9: =IFERROR(IF(D8="","",D8*'0. Supuestos'!$B$11*'0. Supuestos'!$B$13),"") -> 54266.03
A10: Coste de mercancía — bebida | B10: =IFERROR(IF(B8="","",B8*'0. Supuestos'!$B$12*'0. Supuestos'!$B$14),"") -> 2443.65 | C10: =IFERROR(IF(C8="","",C8*'0. Supuestos'!$B$12*'0. Supuestos'!$B$14),"") -> 4398.57 | D10: =IFERROR(IF(D8="","",D8*'0. Supuestos'!$B$12*'0. Supuestos'!$B$14),"") -> 7412.405
A11: Consumibles y envases | B11: =IFERROR(IF(B8="","",B8*'0. Supuestos'!$B$15),"") -> 2250 | C11: =IFERROR(IF(C8="","",C8*'0. Supuestos'!$B$15),"") -> 4050 | D11: =IFERROR(IF(D8="","",D8*'0. Supuestos'!$B$15),"") -> 6825
A12: Comisiones de delivery | B12: =IFERROR(IF(B8="","",B8*'0. Supuestos'!$B$16*'0. Supuestos'!$B$17),"") -> 0 | C12: =IFERROR(IF(C8="","",C8*'0. Supuestos'!$B$16*'0. Supuestos'!$B$17),"") -> 0 | D12: =IFERROR(IF(D8="","",D8*'0. Supuestos'!$B$16*'0. Supuestos'!$B$17),"") -> 0
A13: Comisiones de los medios de pago | B13: =IFERROR(IF(B8="","",B8*'0. Supuestos'!$B$18),"") -> 600 | C13: =IFERROR(IF(C8="","",C8*'0. Supuestos'!$B$18),"") -> 1080 | D13: =IFERROR(IF(D8="","",D8*'0. Supuestos'!$B$18),"") -> 1820
A14: Varios e imprevistos | B14: =IFERROR(IF(B8="","",B8*'0. Supuestos'!$B$28),"") -> 3750 | C14: =IFERROR(IF(C8="","",C8*'0. Supuestos'!$B$28),"") -> 6750 | D14: =IFERROR(IF(D8="","",D8*'0. Supuestos'!$B$28),"") -> 11375
A15: TOTAL COSTES VARIABLES | B15: =IFERROR(IF(B8="","",SUM(B9:B14)),"") -> 26933.55 | C15: =IFERROR(IF(C8="","",SUM(C9:C14)),"") -> 48480.39 | D15: =IFERROR(IF(D8="","",SUM(D9:D14)),"") -> 81698.435
A16: MARGEN BRUTO | B16: =IFERROR(IF(B8="","",B8-B15),"") -> 48066.45 | C16: =IFERROR(IF(C8="","",C8-C15),"") -> 86519.61 | D16: =IFERROR(IF(D8="","",D8-D15),"") -> 145801.57
A17: COSTES FIJOS (los del P&L) | B17: =IFERROR(IF(B8="","",'PyG 3 Años'!$B$38),"") -> 78859.2 | C17: =IFERROR(IF(C8="","",'PyG 3 Años'!$B$38),"") -> 78859.2 | D17: =IFERROR(IF(D8="","",'PyG 3 Años'!$B$38),"") -> 78859.2 | E17: Los costes fijos no cambian con el escenario: por eso son fijos
A18: RESULTADO ANTES DE IMPUESTOS | B18: =IFERROR(IF(B8="","",B16-B17),"") -> -30792.75 | C18: =IFERROR(IF(C8="","",C16-C17),"") -> 7660.41 | D18: =IFERROR(IF(D8="","",D16-D17),"") -> 66942.365
A19: Impuesto de Sociedades | B19: =IFERROR(IF(B8="","",MAX(0,B18-'0. Supuestos'!$B$42)*'0. Supuestos'!$B$37),"") -> 0 | C19: =IFERROR(IF(C8="","",MAX(0,C18-'0. Supuestos'!$B$42)*'0. Supuestos'!$B$37),"") -> 1149.0615 | D19: =IFERROR(IF(D8="","",MAX(0,D18-'0. Supuestos'!$B$42)*'0. Supuestos'!$B$37),"") -> 10041.355 | E19: Al tipo de entidad de nueva creación, compensando las bases negativas anteriores
A20: RESULTADO NETO | B20: =IFERROR(IF(B8="","",B18-B19),"") -> -30792.75 | C20: =IFERROR(IF(C8="","",C18-C19),"") -> 6511.3485 | D20: =IFERROR(IF(D8="","",D18-D19),"") -> 56901.01
A21: Clientes/día para el equilibrio | B21: =IFERROR(IF(B8="","",IF(B6-B15/(B5*B7)<=0,"",B17/(B6-B15/(B5*B7))/B7)),"") -> 49.218863 | C21: =IFERROR(IF(C8="","",IF(C6-C15/(C5*C7)<=0,"",C17/(C6-C15/(C5*C7))/C7)),"") -> 41.015719 | D21: =IFERROR(IF(D8="","",IF(D6-D15/(D5*D7)<=0,"",D17/(D6-D15/(D5*D7))/D7)),"") -> 35.15633
A22: LO QUE CADA ESCENARIO EXIGE
A23: Coste de personal / Ventas | B23: =IFERROR(IF(B8="","",'PyG 3 Años'!$B$23/B8),"") -> 0.56108267 | C23: =IFERROR(IF(C8="","",'PyG 3 Años'!$B$23/C8),"") -> 0.31171259 | D23: =IFERROR(IF(D8="","",'PyG 3 Años'!$B$23/D8),"") -> 0.18497231 | E23: La MISMA plantilla en los tres escenarios. Si en el pesimista se dispara, el ajuste hay que hacerlo en la hoja de Personal, no aquí
A24: Clientes al año por jornada equivalente | B24: =IFERROR(IF(B8="","",B5*B7/'Personal'!$C$9),"") -> 4658.3851 | C24: =IFERROR(IF(C8="","",C5*C7/'Personal'!$C$9),"") -> 6987.5776 | D24: =IFERROR(IF(D8="","",D5*D7/'Personal'!$C$9),"") -> 10093.168 | E24: Clientes que tendría que sacar cada jornada completa del cuadro de Personal. En el optimista dice si hace falta contratar
A25: Saldo de caja al cierre del año 1 (estimado, el mismo método en los tres escenarios) | B25: =IFERROR(IF(B8="","",'Inversión Inicial'!$B$25+B20+'PyG 3 Años'!$B$36-'Financiación'!$B$45),"") -> -6091.95 | C25: =IFERROR(IF(C8="","",'Inversión Inicial'!$B$25+C20+'PyG 3 Años'!$B$36-'Financiación'!$B$45),"") -> 31212.149 | D25: =IFERROR(IF(D8="","",'Inversión Inicial'!$B$25+D20+'PyG 3 Años'!$B$36-'Financiación'!$B$45),"") -> 81601.81 | E25: Saldo ESTIMADO: fondo de maniobra más el resultado del año, devolviendo la amortización (que no se paga) y restando el principal del préstamo. No incluye el desfase de cobros y pagos ni la liquidación del IVA, así que las tres columnas se pueden comparar entre sí. En rojo, el escenario se queda sin caja
A26: Saldo real del mes 12 de la hoja de Tesorería (sólo realista) | C26: =IFERROR(IF(C8="","",'Tesorería 12 meses'!$M$22),"") -> 40484.129 | E26: El saldo REAL del caso base, con su desfase de cobros y pagos y su liquidación de IVA. Sólo existe para el escenario realista, que es el único con tesorería mensual propia: por eso no está en la fila de arriba, donde se compararía contra dos estimaciones
A28: La columna «Realista» lee sus tres datos de la hoja de Supuestos, así que reproduce EXACTAMENTE el año 1 del P&L. Los otros dos escenarios usan las mismas tasas de coste: lo único que cambia son los clientes, el ticket y los días. Los COSTES FIJOS sí son los mismos en los tres: los varios e imprevistos, que son un porcentaje de las ventas, van arriba con los variables y cada escenario carga los suyos.

Sheet Personal
A1: ESTRUCTURA DE PERSONAL Y COSTES
A2: =IFERROR("Convenio Hostelería — "&TEXT('0. Supuestos'!$B$21,"0")&" pagas + SS "&TEXT('0. Supuestos'!$B$20*100,"0")&" %","") -> Convenio Hostelería — 14 pagas + SS 33 %
A4: Puesto | B4: Personas | C4: Jornada | D4: Bruto mes (€, total del puesto) | E4: Seg. Social a cargo de la empresa (€) | F4: Coste mes (€, total del puesto) | G4: Coste año (€) | H4: Horas/semana por persona | I4: Horas/año del puesto | J4: Notas
A5: Propietario/a — chef, gestión y conducción | B5: 1 | C5: 1 | D5: 1500 | E5: =IFERROR(IF(D5="","",D5*'0. Supuestos'!$B$20),"") -> 495 | F5: =IFERROR(IF(D5="","",D5+E5),"") -> 1995 | G5: =IFERROR(IF(D5="","",F5*MAX(12,'0. Supuestos'!$B$21)),"") -> 27930 | H5: =IFERROR(IF(D5="","",C5*$B$16),"") -> 40 | I5: =IFERROR(IF(D5="","",H5*B5*$B$17),"") -> 1840 | J5: Elabora el producto, conduce el vehículo entre ubicaciones y lleva la gestión, compras y RRSS. Cubre el turno fuerte de los 250 días de servicio al año
A6: Ayudante de cocina y servicio | B6: 1 | C6: 0.45 | D6: 560 | E6: =IFERROR(IF(D6="","",D6*'0. Supuestos'!$B$20),"") -> 184.8 | F6: =IFERROR(IF(D6="","",D6+E6),"") -> 744.8 | G6: =IFERROR(IF(D6="","",F6*MAX(12,'0. Supuestos'!$B$21)),"") -> 10427.2 | H6: =IFERROR(IF(D6="","",C6*$B$16),"") -> 18 | I6: =IFERROR(IF(D6="","",H6*B6*$B$17),"") -> 828 | J6: Prep, montaje, atención al cliente y desmontaje. A tiempo parcial: un food truck de dos servicios diarios como máximo no necesita una segunda persona a jornada completa. Por encima del SMI en proporción a su jornada
A7: Refuerzo de festivales y eventos grandes | B7: 1 | C7: 0.1 | D7: 125 | E7: =IFERROR(IF(D7="","",D7*'0. Supuestos'!$B$20),"") -> 41.25 | F7: =IFERROR(IF(D7="","",D7+E7),"") -> 166.25 | G7: =IFERROR(IF(D7="","",F7*MAX(12,'0. Supuestos'!$B$21)),"") -> 2327.5 | H7: =IFERROR(IF(D7="","",C7*$B$16),"") -> 4 | I7: =IFERROR(IF(D7="","",H7*B7*$B$17),"") -> 184 | J7: Sólo para los picos de afluencia que el propio fichero describe («Festivales = facturación x3-5 en un día»): unas pocas jornadas al mes, no un puesto estable. Por encima del SMI en proporción a su jornada
A8: Suplencias de vacaciones y descansos | B8: 1 | C8: 0.06 | D8: 75 | E8: =IFERROR(IF(D8="","",D8*'0. Supuestos'!$B$20),"") -> 24.75 | F8: =IFERROR(IF(D8="","",D8+E8),"") -> 99.75 | G8: =IFERROR(IF(D8="","",F8*MAX(12,'0. Supuestos'!$B$21)),"") -> 1396.5 | H8: =IFERROR(IF(D8="","",C8*$B$16),"") -> 2.4 | I8: =IFERROR(IF(D8="","",H8*B8*$B$17),"") -> 110.4 | J8: Cobertura de los 30 días de vacaciones (art. 38 ET) del propietario y del ayudante, y del descanso semanal. Por encima del SMI en proporción a su jornada
A9: TOTAL PLANTILLA | B9: =IFERROR(IF(COUNT(D5:D8)=0,"",SUM(B5:B8)),"") -> 4 | C9: =IFERROR(IF(COUNT(D5:D8)=0,"",SUM(C5:C8)),"") -> 1.61 | D9: =IFERROR(IF(COUNT(D5:D8)=0,"",SUM(D5:D8)),"") -> 2260 | E9: =IFERROR(IF(COUNT(D5:D8)=0,"",SUM(E5:E8)),"") -> 745.8 | F9: =IFERROR(IF(COUNT(D5:D8)=0,"",SUM(F5:F8)),"") -> 3005.8 | G9: =IFERROR(IF(COUNT(D5:D8)=0,"",SUM(G5:G8)),"") -> 42081.2 | I9: =IFERROR(IF(COUNT(D5:D8)=0,"",SUM(I5:I8)),"") -> 2962.4
A10: CRECIMIENTO DE LA PLANTILLA (coste escalonado)
A11: Coste anual de las incorporaciones del año 2 (€) | B11: 6000 | J11: Coste ANUAL completo (bruto + Seguridad Social × pagas) de lo que se contrate ese año. El P&L lo suma al coste del año anterior: la plantilla no crece con un porcentaje, crece con personas
A12: Coste anual de las incorporaciones del año 3 (€) | B12: 6000 | J12: Coste ANUAL completo (bruto + Seguridad Social × pagas) de lo que se contrate ese año. El P&L lo suma al coste del año anterior: la plantilla no crece con un porcentaje, crece con personas
A13: Coste de personal del año 2 | B13: =IFERROR(IF(G9="","",G9*(1+'0. Supuestos'!$B$48)+B11),"") -> 48081.2
A14: Coste de personal del año 3 | B14: =IFERROR(IF(B13="","",B13*(1+'0. Supuestos'!$B$48)+B12),"") -> 54081.2
A15: COBERTURA POR HORAS DE SERVICIO
A16: Jornada completa del convenio (horas/semana) | B16: 40 | J16: Art. 34.1 del Estatuto de los Trabajadores; tu convenio provincial puede fijar menos
A17: Semanas trabajadas al año por persona | B17: 46 | J17: 46 semanas: 52 menos las vacaciones (30 días naturales, art. 38 ET), los festivos y las ausencias medias
A18: Horas de servicio al día que hay que cubrir | B18: 12 | J18: Jornada efectiva completa del día de servicio: carga, desplazamiento, montaje, servicio, recogida y limpieza. El servicio al público es sólo una parte
A19: Personas necesarias a la vez en cada franja | B19: 1 | J19: Presencia media a bordo. En los picos de un festival hará falta un segundo par de manos: súbelo aquí y la plantilla se dimensiona sola
A20: Horas de servicio a cubrir al año | B20: =IFERROR(IF(OR(B18="",B19="",'0. Supuestos'!$B$6=""),"",B18*B19*'0. Supuestos'!$B$6),"") -> 3000
A21: Horas contratadas al año | B21: =IFERROR(IF(I9="","",I9),"") -> 2962.4
A22: Cobertura (contratadas / necesarias) | B22: =IFERROR(B21/B20,"") -> 0.98746667 | J22: Por debajo del 100 % la plantilla no llega a cubrir el horario que declara el plan: o se contrata más o se recorta el horario
A24: Las columnas «Bruto mes», «Seg. Social», «Coste mes» y «Coste año» son TOTALES de la fila: en un puesto con dos personas incluyen a las dos. «Jornada» es el porcentaje sobre la jornada completa del convenio y sirve para comparar el salario con el suelo legal en proporción. El tipo de Seguridad Social y el número de pagas están en la hoja «0. Supuestos».
A25: El suelo salarial es el MAYOR entre el SMI y el salario de convenio, los dos en la hoja «0. Supuestos»; las jornadas parciales lo llevan en proporción. El convenio aplicable es el PROVINCIAL de hostelería: no existe una tabla salarial estatal única, así que la celda del convenio se entrega vacía para que copies la de tu provincia.

Sheet Instrucciones
A1: INSTRUCCIONES DE USO — Plan financiero Food Truck
A3: CÓMO SE USA ESTE LIBRO
A4: Este plan financiero es un MODELO: sólo se teclea en las celdas VERDES y el resto se recalcula solo.
A5: 1. «0. Supuestos» es la hoja de mando: clientes, ticket sin IVA, días de apertura, mezcla de comida y bebida, coste de mercancía, alquiler, financiación e impuestos.
A6: 2. Las partidas de la inversión, los costes fijos y la plantilla se teclean en su propia hoja, también en verde. Ningún número se escribe dos veces.
A7: 3. Sólo «Punto Equilibrio» se deriva entera de lo anterior. En las otras tres hojas también hay celdas verdes que puedes tocar: el escenario pesimista y el optimista en «Escenarios», la estacionalidad y la rampa de arranque en «Tesorería 12 meses», y las cuatro fuentes alternativas de financiación en «Financiación». Todo lo demás se calcula.
A8: 4. Todas las cifras van SIN IVA. Para pasar un PVP a precio sin IVA, divide por el tipo que le corresponda: entre 1,10 en sala (comida y bebida, alcohol incluido: art. 91.Uno.2.2.º de la Ley 37/1992 del IVA) y, cuando se venden para llevar, los alimentos —bollería y pastelería incluidas—, que son productos alimenticios al tipo reducido por el art. 91.Uno.1.1.º; y entre 1,21 el tipo general, que en hostelería sólo alcanza a lo que sale del local como entrega de bienes excluida del reducido: el alcohol y los refrescos o zumos con azúcares añadidos para llevar o a domicilio (la comida para llevar sigue al 10 %); el libro lo aplica al alcohol del canal de delivery. El tipo de cada línea de venta está en la columna «Tipo de IVA de la línea» del P&L y de ahí salen los cobros, el IVA repercutido y el PVP equivalente. El IVA de la inversión se adelanta y se recupera con el modelo 303.
A9: 5. Si cambias la plantilla, el P&L la lee sola: el coste de personal sale de la hoja «Personal», no de una estimación aparte.
A10: 6. La hoja «Tesorería 12 meses» responde la pregunta que decide una operación bancaria: en qué mes se agota la caja. El saldo mínimo del año nunca puede salir en rojo.
A11: 7. La hoja «Financiación» cuadra lo que hace falta con lo que se aporta y monta el cuadro de amortización del préstamo. Si la diferencia sale en rojo, el plan no está financiado.
A12: 8. El documento Word de este pack es el de la versión 1.1: las cifras válidas son las de este Excel, que es el que se recalcula solo cuando cambias una celda verde.
A14: RATIOS QUE AUDITA EL LIBRO
A15: Los umbrales viven en la columna «Umbral» del bloque RATIOS CLAVE del P&L: cámbialos ahí y el semáforo cambia con ellos.
A17: Ratio | B17: Valor del año 1 | C17: Umbral | D17: Estado
A18: Coste de mercancía / Ventas | B18: =IFERROR(IF('PyG 3 Años'!$B$53="","",'PyG 3 Años'!$B$53),"") -> 0.271114 | C18: =IFERROR(IF('PyG 3 Años'!$E$53="","",'PyG 3 Años'!$E$53),"") -> 0.33 | D18: =IFERROR(IF(OR(B18="",C18=""),"",IF(B18<=C18,"CUMPLE","REVISAR")),"") -> CUMPLE
A19: Coste de personal / Ventas | B19: =IFERROR(IF('PyG 3 Años'!$B$54="","",'PyG 3 Años'!$B$54),"") -> 0.31171259 | C19: =IFERROR(IF('PyG 3 Años'!$E$54="","",'PyG 3 Años'!$E$54),"") -> 0.32 | D19: =IFERROR(IF(OR(B19="",C19=""),"",IF(B19<=C19,"CUMPLE","REVISAR")),"") -> CUMPLE
A20: Aparcamiento / Ventas | B20: =IFERROR(IF('PyG 3 Años'!$B$55="","",'PyG 3 Años'!$B$55),"") -> 0.035555556 | C20: =IFERROR(IF('PyG 3 Años'!$E$55="","",'PyG 3 Años'!$E$55),"") -> 0.05 | D20: =IFERROR(IF(OR(B20="",C20=""),"",IF(B20<=C20,"CUMPLE","REVISAR")),"") -> CUMPLE
A21: Resultado neto / Ventas | B21: =IFERROR(IF('PyG 3 Años'!$B$56="","",'PyG 3 Años'!$B$56),"") -> 0.048232211 | C21: =IFERROR(IF('PyG 3 Años'!$E$56="","",'PyG 3 Años'!$E$56),"") -> 0.04 | D21: =IFERROR(IF(OR(B21="",C21=""),"",IF(B21>=C21,"CUMPLE","REVISAR")),"") -> CUMPLE
A22: Margen bruto / Ventas | B22: =IFERROR(IF('PyG 3 Años'!$B$51="","",'PyG 3 Años'!$B$51),"") -> 0.640886 | C22: =IFERROR(IF('PyG 3 Años'!$E$51="","",'PyG 3 Años'!$E$51),"") -> 0.62 | D22: =IFERROR(IF(OR(B22="",C22=""),"",IF(B22>=C22,"CUMPLE","REVISAR")),"") -> CUMPLE
A24: CIFRAS DE ESTE PLAN
A25: Inversión total (suma de los bloques) | B25: =IFERROR(IF('Inversión Inicial'!$B$26="","",'Inversión Inicial'!$B$26),"") -> 81996.8
A26: Necesidad total de caja al arranque | B26: =IFERROR(IF('Inversión Inicial'!$B$29="","",'Inversión Inicial'!$B$29),"") -> 94669.04
A27: Fondo de maniobra dotado | B27: =IFERROR(IF('Inversión Inicial'!$B$25="","",'Inversión Inicial'!$B$25),"") -> 18052.8
A28: Facturación prevista del año 1 | B28: =IFERROR(IF('PyG 3 Años'!$B$9="","",'PyG 3 Años'!$B$9),"") -> 135000
A29: Resultado neto del año 1 | B29: =IFERROR(IF('PyG 3 Años'!$B$48="","",'PyG 3 Años'!$B$48),"") -> 6511.3485
A30: Clientes/día para el punto de equilibrio CONTABLE (con la amortización dentro) | B30: =IFERROR(IF('Punto Equilibrio'!$B$15="","",'Punto Equilibrio'!$B$15),"") -> 41.015719
A31: Payback del proyecto (años), antes de la deuda | B31: =IFERROR(IF('Tesorería 12 meses'!$B$31="","",'Tesorería 12 meses'!$B$31),"") -> Más de 3 años
A33: QUÉ HA CAMBIADO RESPECTO DE LA VERSIÓN 1.1
A34: Concepto | B34: v1.1 | C34: v2.2 | D34: Por qué
A35: Coste de personal en la cuenta de resultados | B35: 42.000 € | C35: 42.081 €, leídos de la hoja Personal | D35: La cuenta de resultados usaba una cifra tecleada a mano que no era la de su propia hoja de Personal, que sumaba 76.566 €. Ahora la lee de ahí: si cambias un sueldo, el plan entero se recalcula
A36: Plantilla | B36: 3 puestos / 76.566 € al año | C36: 4 puestos (1 a jornada completa y 3 parciales) / 42.081 € al año | D36: Dimensionada para los 250 días de servicio que hace este plan, con una línea nueva para cubrir vacaciones y descansos. Con la plantilla anterior el personal se comía el 56,7 % de las ventas y el negocio no era viable con sus propios números
A37: Días de servicio al año | B37: tres calendarios distintos en el mismo paquete: 300 días en el punto de equilibrio, 240 en los escenarios y ninguno declarado en la cuenta de resultados | C37: 250 días, un solo dato para todo el libro | D37: Son los días que hacen exacta la facturación que el propio plan ya publicaba: 45 clientes × 12 € × 250 días = 135.000 €. Equivalen a 5 días de servicio por semana durante 50 semanas
A38: Ticket medio | B38: 12 € sin decir si llevaba IVA | C38: 12 € SIN IVA | D38: El número no cambia; lo que cambia es que ahora se declara qué es. Con el IVA de hostelería son 13,20 € de precio de venta al público, dentro del rango 10-15 € que recoge este mismo libro
A39: Aparcamiento y base del vehículo | B39: no estaba | C39: 400 €/mes (4.800 € al año), más dos meses de fianza y dos meses antes de abrir | D39: Un food truck necesita un sitio en el que pernoctar, cargar agua y vaciar residuos. El plan anterior no lo pagaba en ninguna línea, así que el negocio parecía no tener ningún coste de suelo
A40: Fondo de maniobra | B40: 6.000 €, etiquetados «3 meses» | C40: 18.053 €: tres meses de costes fijos de caja, calculados por fórmula | D40: Los 6.000 € daban para 1,1 meses, no para 3. Es el colchón que evita cerrar por una racha de mal tiempo o un mes flojo de eventos
A41: Amortización | B41: 10.343 € al año, a 7 años planos sobre todo, incluido lo que no es inmovilizado | C41: dos vidas útiles: el vehículo, su adaptación y los imprevistos de la puesta en marcha a 8 años, y el equipamiento y el mobiliario a 10. La cuota del año la calcula la hoja de Inversión | D41: El vehículo se amortiza más rápido que el equipamiento porque son cosas distintas para Hacienda. Y el fondo de maniobra, el stock y el marketing no se amortizan: no son inmovilizado
A42: Seguro del vehículo y RC | B42: 2.500 € en la inversión Y 2.500 € al año en los gastos: la misma prima contada dos veces | C42: 2.500 € al año, una sola vez | D42: Contarla en los dos sitios inflaba la inversión, el IVA a adelantar y el dinero que hay que pedir al banco
A43: Generador | B43: 2.400 € al año como línea suelta, además de los suministros | C43: 2.400 € al año dentro de la celda de suministros | D43: Era el mismo gasto escrito en dos sitios. Ahora se cambia en uno solo y el resto del libro se entera
A44: Imprevistos de la puesta en marcha | B44: 5.500 € escritos a mano (un 8 % del total) | C44: el mismo 8 %, pero calculado sobre la compra y la adaptación del vehículo | D44: Si cambias el precio del vehículo, los imprevistos se recalculan solos en vez de quedarse en la cifra vieja
A45: Impuesto de Sociedades | B45: 25 % los tres años, sin compensar pérdidas | C45: 15 % los dos primeros ejercicios con beneficio, compensando las pérdidas anteriores | D45: Es el tipo que la ley reserva a las empresas de nueva creación, y las pérdidas de un año se restan del beneficio de los siguientes
... A51: Sueldos y SMI | B51: sueldos sin comparar con ningún suelo legal | C51: ninguna fila por debajo del SMI en proporción a su jornada, y una celda para el convenio de tu provincia | D51: El convenio provincial de hostelería manda sobre el SMI: cópialo en la hoja de Supuestos y el semáforo te avisa si algún sueldo se queda corto
A53: DATOS DE REFERENCIA DEL SECTOR
A54: Referencia | B54: Valor | C54: Fuente | D54: Nota
A55: Food cost comida | B55: 28-33 % | C55: Fichero v1.1 | D55: Depende del concepto: burger 30 %, tacos 25 %, poke 35 %. Este plan trabaja con el 28 %, el extremo bajo: si tu carta va al 33 %, el resultado del primer año se queda muy justo
A56: Food cost bebidas | B56: 22-28 % | C56: Fichero v1.1 | D56: Refrescos y agua embotellada, margen alto
A57: Coste packaging / ventas | B57: 3-5 % | C57: Fichero v1.1 | D57: Packaging eco más caro pero obligatorio en muchos municipios
A58: Coste personal sobre ventas | B58: 25-32 % | C58: Fichero v1.1 | D58: Menos personal que un restaurante: 2-3 personas
A59: Ticket medio food truck | B59: 10-15 € | C59: Fichero v1.1 | D59: Menú completo: plato + bebida + extra. El de este plan son 12 € SIN IVA, que con el tipo de hostelería salen 13,20 € de PVP
A60: Clientes por servicio | B60: 40-80 | C60: Fichero v1.1 | D60: Depende de ubicación, evento y día de la semana. Este plan proyecta 45, el extremo bajo del rango, a propósito
A61: Margen bruto objetivo | B61: > 62 % | C61: Fichero v1.1 | D61: Inferior a un restaurante por el peso del packaging y el combustible
A62: EBITDA objetivo (año 2) | B62: 20-30 % | C62: Fichero v1.1 | D62: Muy rentable si aciertas las ubicaciones. Con los supuestos de partida este plan se queda por debajo del rango: es lo que hay que mejorar subiendo clientes por servicio o ticket
A63: Retorno de la inversión | B63: 12-24 meses | C63: Fichero v1.1 | D63: Es la referencia del sector. El de ESTE plan lo calcula la hoja de Tesorería y sale más largo: se mide sobre la inversión completa, con el fondo de maniobra dentro —el IVA no cuenta, porque se recupera con el modelo 303— y con el flujo que genera el negocio ANTES de pagar al banco. Esa misma hoja publica debajo el plazo medido sólo sobre lo que se compra, sin el fondo de maniobra, que sale más corto
A64: Días operativos/semana | B64: 4-6 | C64: Fichero v1.1 | D64: Mercados, eventos, zona de oficinas, festivales
A65: Servicios por día | B65: 1-2 | C65: Fichero v1.1 | D65: Comida (12-15 h) y/o cena (19-23 h) según ubicación
... A68: Convenio colectivo aplicable | B68: PROVINCIAL de hostelería o de comercio (según clasificación de la venta ambulante) | C68: Fichero v1.1 (fase 4 del checklist) | D68: No existe una tabla salarial estatal única: copia la tabla que te corresponda en la celda de Supuestos
A70: Para editar una celda que no esté en verde: Revisar → Desproteger hoja (no tiene contraseña).
A71: Más plantillas y kits del catálogo en aichef.pro/productos-digitales
A72: Diseñado por John Guerrero — chef y consultor gastronómico desde 2010, en cocina desde los 17 años · johnguerrero.es
A73: Versión 2.2 · septiembre 2026 · aichef.pro/plan-negocio-food-truck · info@aichef.pro

Sheet Tesorería 12 meses
A1: PREVISIÓN DE TESORERÍA — AÑO 1
A2: El P&L dice si el negocio gana dinero; esta hoja dice si le queda caja para llegar a fin de mes. Es la primera que mira un banco.
A4: Concepto | B4: Mes 1 (€) | C4: Mes 2 (€) | D4: Mes 3 (€) | E4: Mes 4 (€) | F4: Mes 5 (€) | G4: Mes 6 (€) | H4: Mes 7 (€) | I4: Mes 8 (€) | J4: Mes 9 (€) | K4: Mes 10 (€) | L4: Mes 11 (€) | M4: Mes 12 (€) | N4: Año (€)
A5: Estacionalidad del mes (suma 100 %) | B5: 0.06 | C5: 0.062 | D5: 0.075 | E5: 0.08 | F5: 0.088 | G5: 0.098 | H5: 0.105 | I5: 0.1 | J5: 0.088 | K5: 0.08 | L5: 0.074 | M5: 0.09 | N5: =IFERROR(IF('PyG 3 Años'!$B$9="","",SUM(B5:M5)),"") -> 1 | O5: Perfil de tu zona: agosto flojo en ciudad y fuerte en costa. Tiene que sumar 100 %
A6: Rampa de arranque (% de la actividad de crucero) | B6: =IFERROR(IF('PyG 3 Años'!$B$9="","",MIN(1,'0. Supuestos'!$B$52+(1-'0. Supuestos'!$B$52)*0/MAX(1,'0. Supuestos'!$B$53-1))),"") -> 0.55 | C6: =IFERROR(IF('PyG 3 Años'!$B$9="","",MIN(1,'0. Supuestos'!$B$52+(1-'0. Supuestos'!$B$52)*1/MAX(1,'0. Supuestos'!$B$53-1))),"") -> 0.64 | D6: =IFERROR(IF('PyG 3 Años'!$B$9="","",MIN(1,'0. Supuestos'!$B$52+(1-'0. Supuestos'!$B$52)*2/MAX(1,'0. Supuestos'!$B$53-1))),"") -> 0.73 | E6: =IFERROR(IF('PyG 3 Años'!$B$9="","",MIN(1,'0. Supuestos'!$B$52+(1-'0. Supuestos'!$B$52)*3/MAX(1,'0. Supuestos'!$B$53-1))),"") -> 0.82 | F6: =IFERROR(IF('PyG 3 Años'!$B$9="","",MIN(1,'0. Supuestos'!$B$52+(1-'0. Supuestos'!$B$52)*4/MAX(1,'0. Supuestos'!$B$53-1))),"") -> 0.91 | G6: =IFERROR(IF('PyG 3 Años'!$B$9="","",MIN(1,'0. Supuestos'!$B$52+(1-'0. Supuestos'!$B$52)*5/MAX(1,'0. Supuestos'!$B$53-1))),"") -> 1 | H6: =IFERROR(IF('PyG 3 Años'!$B$9="","",MIN(1,'0. Supuestos'!$B$52+(1-'0. Supuestos'!$B$52)*6/MAX(1,'0. Supuestos'!$B$53-1))),"") -> 1 | I6: =IFERROR(IF('PyG 3 Años'!$B$9="","",MIN(1,'0. Supuestos'!$B$52+(1-'0. Supuestos'!$B$52)*7/MAX(1,'0. Supuestos'!$B$53-1))),"") -> 1 | J6: =IFERROR(IF('PyG 3 Años'!$B$9="","",MIN(1,'0. Supuestos'!$B$52+(1-'0. Supuestos'!$B$52)*8/MAX(1,'0. Supuestos'!$B$53-1))),"") -> 1 | K6: =IFERROR(IF('PyG 3 Años'!$B$9="","",MIN(1,'0. Supuestos'!$B$52+(1-'0. Supuestos'!$B$52)*9/MAX(1,'0. Supuestos'!$B$53-1))),"") -> 1 | L6: =IFERROR(IF('PyG 3 Años'!$B$9="","",MIN(1,'0. Supuestos'!$B$52+(1-'0. Supuestos'!$B$52)*10/MAX(1,'0. Supuestos'!$B$53-1))),"") -> 1 | M6: =IFERROR(IF('PyG 3 Años'!$B$9="","",MIN(1,'0. Supuestos'!$B$52+(1-'0. Supuestos'!$B$52)*11/MAX(1,'0. Supuestos'!$B$53-1))),"") -> 1 | O6: Sube en línea recta desde el porcentaje del mes 1 hasta el 100 % en los meses que digas en Supuestos. Con el mes 1 al 100 % la rampa desaparece
A7: Reparto de la actividad por mes (calculado) | B7: =IFERROR(IF('PyG 3 Años'!$B$9="","",B5*B6/SUMPRODUCT($B$5:$M$5,$B$6:$M$6)),"") -> 0.03633921 | C7: =IFERROR(IF('PyG 3 Años'!$B$9="","",C5*C6/SUMPRODUCT($B$5:$M$5,$B$6:$M$6)),"") -> 0.043695147 | D7: =IFERROR(IF('PyG 3 Años'!$B$9="","",D5*D6/SUMPRODUCT($B$5:$M$5,$B$6:$M$6)),"") -> 0.060290053 | E7: =IFERROR(IF('PyG 3 Años'!$B$9="","",E5*E6/SUMPRODUCT($B$5:$M$5,$B$6:$M$6)),"") -> 0.072237945 | F7: =IFERROR(IF('PyG 3 Años'!$B$9="","",F5*F6/SUMPRODUCT($B$5:$M$5,$B$6:$M$6)),"") -> 0.08818315 | G7: =IFERROR(IF('PyG 3 Años'!$B$9="","",G5*G6/SUMPRODUCT($B$5:$M$5,$B$6:$M$6)),"") -> 0.10791644 | H7: =IFERROR(IF('PyG 3 Años'!$B$9="","",H5*H6/SUMPRODUCT($B$5:$M$5,$B$6:$M$6)),"") -> 0.11562476 | I7: =IFERROR(IF('PyG 3 Años'!$B$9="","",I5*I6/SUMPRODUCT($B$5:$M$5,$B$6:$M$6)),"") -> 0.11011882 | ... M7: =IFERROR(IF('PyG 3 Años'!$B$9="","",M5*M6/SUMPRODUCT($B$5:$M$5,$B$6:$M$6)),"") -> 0.099106936 | N7: =IFERROR(IF('PyG 3 Años'!$B$9="","",SUM(B7:M7)),"") -> 1 | O7: Estacionalidad × rampa, normalizado a 100 %: el AÑO factura lo que dice el P&L, pero repartido como lo reparte un local que acaba de abrir
A8: COBROS
A9: Ventas cobradas (con IVA repercutido) | B9: =IFERROR(IF('PyG 3 Años'!$B$9="","",('PyG 3 Años'!$B$9+'PyG 3 Años'!$B$9*SUMPRODUCT('PyG 3 Años'!$E$10:$E$11,'PyG 3 Años'!$G$10:$G$11))*B7*(1-MIN(30,'0. Supuestos'!$B$58)/30)),"") -> 5396.3727 | C9: =IFERROR(IF('PyG 3 Años'!$B$9="","",('PyG 3 Años'!$B$9+'PyG 3 Años'!$B$9*SUMPRODUCT('PyG 3 Años'!$E$10:$E$11,'PyG 3 Años'!$G$10:$G$11))*(C7*(1-MIN(30,'0. Supuestos'!$B$58)/30)+B7*MIN(30,'0. Supuestos'!$B$58)/30)),"") -> 6488.7293 | D9: =IFERROR(IF('PyG 3 Años'!$B$9="","",('PyG 3 Años'!$B$9+'PyG 3 Años'!$B$9*SUMPRODUCT('PyG 3 Años'!$E$10:$E$11,'PyG 3 Años'!$G$10:$G$11))*(D7*(1-MIN(30,'0. Supuestos'!$B$58)/30)+C7*MIN(30,'0. Supuestos'!$B$58)/30)),"") -> 8953.0729 | E9: =IFERROR(IF('PyG 3 Años'!$B$9="","",('PyG 3 Años'!$B$9+'PyG 3 Años'!$B$9*SUMPRODUCT('PyG 3 Años'!$E$10:$E$11,'PyG 3 Años'!$G$10:$G$11))*(E7*(1-MIN(30,'0. Supuestos'!$B$58)/30)+D7*MIN(30,'0. Supuestos'!$B$58)/30)),"") -> 10727.335 | F9: =IFERROR(IF('PyG 3 Años'!$B$9="","",('PyG 3 Años'!$B$9+'PyG 3 Años'!$B$9*SUMPRODUCT('PyG 3 Años'!$E$10:$E$11,'PyG 3 Años'!$G$10:$G$11))*(F7*(1-MIN(30,'0. Supuestos'!$B$58)/30)+E7*MIN(30,'0. Supuestos'!$B$58)/30)),"") -> 13095.198 | G9: =IFERROR(IF('PyG 3 Años'!$B$9="","",('PyG 3 Años'!$B$9+'PyG 3 Años'!$B$9*SUMPRODUCT('PyG 3 Años'!$E$10:$E$11,'PyG 3 Años'!$G$10:$G$11))*(G7*(1-MIN(30,'0. Supuestos'!$B$58)/30)+F7*MIN(30,'0. Supuestos'!$B$58)/30)),"") -> 16025.592 | H9: =IFERROR(IF('PyG 3 Años'!$B$9="","",('PyG 3 Años'!$B$9+'PyG 3 Años'!$B$9*SUMPRODUCT('PyG 3 Años'!$E$10:$E$11,'PyG 3 Años'!$G$10:$G$11))*(H7*(1-MIN(30,'0. Supuestos'!$B$58)/30)+G7*MIN(30,'0. Supuestos'!$B$58)/30)),"") -> 17170.277 | I9: =IFERROR(IF('PyG 3 Años'!$B$9="","",('PyG 3 Años'!$B$9+'PyG 3 Años'!$B$9*SUMPRODUCT('PyG 3 Años'!$E$10:$E$11,'PyG 3 Años'!$G$10:$G$11))*(I7*(1-MIN(30,'0. Supuestos'!$B$58)/30)+H7*MIN(30,'0. Supuestos'!$B$58)/30)),"") -> 16352.645 | J9: =IFERROR(IF('PyG 3 Años'!$B$9="","",('PyG 3 Años'!$B$9+'PyG 3 Años'!$B$9*SUMPRODUCT('PyG 3 Años'!$E$10:$E$11,'PyG 3 Años'!$G$10:$G$11))*(J7*(1-MIN(30,'0. Supuestos'!$B$58)/30)+I7*MIN(30,'0. Supuestos'!$B$58)/30)),"") -> 14390.327 | ... M9: =IFERROR(IF('PyG 3 Años'!$B$9="","",('PyG 3 Años'!$B$9+'PyG 3 Años'!$B$9*SUMPRODUCT('PyG 3 Años'!$E$10:$E$11,'PyG 3 Años'!$G$10:$G$11))*(M7*(1-MIN(30,'0. Supuestos'!$B$58)/30)+L7*MIN(30,'0. Supuestos'!$B$58)/30)),"") -> 14717.38 | N9: =IFERROR(IF('PyG 3 Años'!$B$9="","",SUM(B9:M9)),"") -> 148500 | O9: Ventas del mes con el IVA repercutido, corregidas por los días medios de cobro de la hoja de Supuestos
A10: PAGOS
A11: Compras y costes variables (IVA incluido) | B11: =IFERROR(IF('PyG 3 Años'!$B$9="","",-('PyG 3 Años'!$B$13*(1+'PyG 3 Años'!$G$13)+'PyG 3 Años'!$B$14*(1+'PyG 3 Años'!$G$14)+'PyG 3 Años'!$B$15*(1+'PyG 3 Años'!$G$15)+'PyG 3 Años'!$B$16*(1+'PyG 3 Años'!$G$16)+'PyG 3 Años'!$B$17*(1+'PyG 3 Años'!$G$17)+'PyG 3 Años'!$B$18*(1+'PyG 3 Años'!$G$18))*B7*(1-MIN(30,'0. Supuestos'!$B$59)/30)),"") -> 0 | C11: =IFERROR(IF('PyG 3 Años'!$B$9="","",-('PyG 3 Años'!$B$13*(1+'PyG 3 Años'!$G$13)+'PyG 3 Años'!$B$14*(1+'PyG 3 Años'!$G$14)+'PyG 3 Años'!$B$15*(1+'PyG 3 Años'!$G$15)+'PyG 3 Años'!$B$16*(1+'PyG 3 Años'!$G$16)+'PyG 3 Años'!$B$17*(1+'PyG 3 Años'!$G$17)+'PyG 3 Años'!$B$18*(1+'PyG 3 Años'!$G$18))*(C7*(1-MIN(30,'0. Supuestos'!$B$59)/30)+B7*MIN(30,'0. Supuestos'!$B$59)/30)),"") -> -1978.0385 | D11: =IFERROR(IF('PyG 3 Años'!$B$9="","",-('PyG 3 Años'!$B$13*(1+'PyG 3 Años'!$G$13)+'PyG 3 Años'!$B$14*(1+'PyG 3 Años'!$G$14)+'PyG 3 Años'!$B$15*(1+'PyG 3 Años'!$G$15)+'PyG 3 Años'!$B$16*(1+'PyG 3 Años'!$G$16)+'PyG 3 Años'!$B$17*(1+'PyG 3 Años'!$G$17)+'PyG 3 Años'!$B$18*(1+'PyG 3 Años'!$G$18))*(D7*(1-MIN(30,'0. Supuestos'!$B$59)/30)+C7*MIN(30,'0. Supuestos'!$B$59)/30)),"") -> -2378.4414 | E11: =IFERROR(IF('PyG 3 Años'!$B$9="","",-('PyG 3 Años'!$B$13*(1+'PyG 3 Años'!$G$13)+'PyG 3 Años'!$B$14*(1+'PyG 3 Años'!$G$14)+'PyG 3 Años'!$B$15*(1+'PyG 3 Años'!$G$15)+'PyG 3 Años'!$B$16*(1+'PyG 3 Años'!$G$16)+'PyG 3 Años'!$B$17*(1+'PyG 3 Años'!$G$17)+'PyG 3 Años'!$B$18*(1+'PyG 3 Años'!$G$18))*(E7*(1-MIN(30,'0. Supuestos'!$B$59)/30)+D7*MIN(30,'0. Supuestos'!$B$59)/30)),"") -> -3281.7456 | F11: =IFERROR(IF('PyG 3 Años'!$B$9="","",-('PyG 3 Años'!$B$13*(1+'PyG 3 Años'!$G$13)+'PyG 3 Años'!$B$14*(1+'PyG 3 Años'!$G$14)+'PyG 3 Años'!$B$15*(1+'PyG 3 Años'!$G$15)+'PyG 3 Años'!$B$16*(1+'PyG 3 Años'!$G$16)+'PyG 3 Años'!$B$17*(1+'PyG 3 Años'!$G$17)+'PyG 3 Años'!$B$18*(1+'PyG 3 Años'!$G$18))*(F7*(1-MIN(30,'0. Supuestos'!$B$59)/30)+E7*MIN(30,'0. Supuestos'!$B$59)/30)),"") -> -3932.1007 | G11: =IFERROR(IF('PyG 3 Años'!$B$9="","",-('PyG 3 Años'!$B$13*(1+'PyG 3 Años'!$G$13)+'PyG 3 Años'!$B$14*(1+'PyG 3 Años'!$G$14)+'PyG 3 Años'!$B$15*(1+'PyG 3 Años'!$G$15)+'PyG 3 Años'!$B$16*(1+'PyG 3 Años'!$G$16)+'PyG 3 Años'!$B$17*(1+'PyG 3 Años'!$G$17)+'PyG 3 Años'!$B$18*(1+'PyG 3 Años'!$G$18))*(G7*(1-MIN(30,'0. Supuestos'!$B$59)/30)+F7*MIN(30,'0. Supuestos'!$B$59)/30)),"") -> -4800.04 | H11: =IFERROR(IF('PyG 3 Años'!$B$9="","",-('PyG 3 Años'!$B$13*(1+'PyG 3 Años'!$G$13)+'PyG 3 Años'!$B$14*(1+'PyG 3 Años'!$G$14)+'PyG 3 Años'!$B$15*(1+'PyG 3 Años'!$G$15)+'PyG 3 Años'!$B$16*(1+'PyG 3 Años'!$G$16)+'PyG 3 Años'!$B$17*(1+'PyG 3 Años'!$G$17)+'PyG 3 Años'!$B$18*(1+'PyG 3 Años'!$G$18))*(H7*(1-MIN(30,'0. Supuestos'!$B$59)/30)+G7*MIN(30,'0. Supuestos'!$B$59)/30)),"") -> -5874.1748 | I11: =IFERROR(IF('PyG 3 Años'!$B$9="","",-('PyG 3 Años'!$B$13*(1+'PyG 3 Años'!$G$13)+'PyG 3 Años'!$B$14*(1+'PyG 3 Años'!$G$14)+'PyG 3 Años'!$B$15*(1+'PyG 3 Años'!$G$15)+'PyG 3 Años'!$B$16*(1+'PyG 3 Años'!$G$16)+'PyG 3 Años'!$B$17*(1+'PyG 3 Años'!$G$17)+'PyG 3 Años'!$B$18*(1+'PyG 3 Años'!$G$18))*(I7*(1-MIN(30,'0. Supuestos'!$B$59)/30)+H7*MIN(30,'0. Supuestos'!$B$59)/30)),"") -> -6293.7587 | J11: =IFERROR(IF('PyG 3 Años'!$B$9="","",-('PyG 3 Años'!$B$13*(1+'PyG 3 Años'!$G$13)+'PyG 3 Años'!$B$14*(1+'PyG 3 Años'!$G$14)+'PyG 3 Años'!$B$15*(1+'PyG 3 Años'!$G$15)+'PyG 3 Años'!$B$16*(1+'PyG 3 Años'!$G$16)+'PyG 3 Años'!$B$17*(1+'PyG 3 Años'!$G$17)+'PyG 3 Años'!$B$18*(1+'PyG 3 Años'!$G$18))*(J7*(1-MIN(30,'0. Supuestos'!$B$59)/30)+I7*MIN(30,'0. Supuestos'!$B$59)/30)),"") -> -5994.0559 | ... M11: =IFERROR(IF('PyG 3 Años'!$B$9="","",-('PyG 3 Años'!$B$13*(1+'PyG 3 Años'!$G$13)+'PyG 3 Años'!$B$14*(1+'PyG 3 Años'!$G$14)+'PyG 3 Años'!$B$15*(1+'PyG 3 Años'!$G$15)+'PyG 3 Años'!$B$16*(1+'PyG 3 Años'!$G$16)+'PyG 3 Años'!$B$17*(1+'PyG 3 Años'!$G$17)+'PyG 3 Años'!$B$18*(1+'PyG 3 Años'!$G$18))*(M7*(1-MIN(30,'0. Supuestos'!$B$59)/30)+L7*MIN(30,'0. Supuestos'!$B$59)/30)),"") -> -4435.6014 | N11: =IFERROR(IF('PyG 3 Años'!$B$9="","",SUM(B11:M11)),"") -> -49037.971 | O11: =IFERROR("Materia prima, consumibles, comisiones e imprevistos, cada uno con SU tipo de IVA (la columna del P&L) y con los días de pago a proveedor de Supuestos."&IF('0. Supuestos'!$B$59=0,""," Con "&TEXT('0. Supuestos'!$B$59,"0")&" días de pago, las primeras compras se pagan ya en el año siguiente: la columna «Año» de esta fila recoge "&TEXT(MAX(0,12-ROUNDUP('0. Supuestos'!$B$59/30,0)),"0")&" mensualidades de compra, no el coste del ejercicio."),"") -> Materia prima, consumibles, comisiones e imprevistos, cada uno con SU tipo de IVA (la columna del P&L) y con los días de pago a proveedor de Supuestos. Con 30 días de pago, las primeras compras se pagan ya en el año siguiente: la columna «Año» de esta fila recoge 11 mensualidades de compra, no el coste del ejercicio.
A12: Costes fijos de explotación (IVA incluido) | B12: =IFERROR(IF('PyG 3 Años'!$B$9="","",-('PyG 3 Años'!$B$38-'PyG 3 Años'!$B$23-'PyG 3 Años'!$B$36-'PyG 3 Años'!$B$37+'PyG 3 Años'!$B$40)/12),"") -> -2522.4583 | C12: =IFERROR(IF('PyG 3 Años'!$B$9="","",-('PyG 3 Años'!$B$38-'PyG 3 Años'!$B$23-'PyG 3 Años'!$B$36-'PyG 3 Años'!$B$37+'PyG 3 Años'!$B$40)/12),"") -> -2522.4583 | D12: =IFERROR(IF('PyG 3 Años'!$B$9="","",-('PyG 3 Años'!$B$38-'PyG 3 Años'!$B$23-'PyG 3 Años'!$B$36-'PyG 3 Años'!$B$37+'PyG 3 Años'!$B$40)/12),"") -> -2522.4583 | E12: =IFERROR(IF('PyG 3 Años'!$B$9="","",-('PyG 3 Años'!$B$38-'PyG 3 Años'!$B$23-'PyG 3 Años'!$B$36-'PyG 3 Años'!$B$37+'PyG 3 Años'!$B$40)/12),"") -> -2522.4583 | F12: =IFERROR(IF('PyG 3 Años'!$B$9="","",-('PyG 3 Años'!$B$38-'PyG 3 Años'!$B$23-'PyG 3 Años'!$B$36-'PyG 3 Años'!$B$37+'PyG 3 Años'!$B$40)/12),"") -> -2522.4583 | G12: =IFERROR(IF('PyG 3 Años'!$B$9="","",-('PyG 3 Años'!$B$38-'PyG 3 Años'!$B$23-'PyG 3 Años'!$B$36-'PyG 3 Años'!$B$37+'PyG 3 Años'!$B$40)/12),"") -> -2522.4583 | H12: =IFERROR(IF('PyG 3 Años'!$B$9="","",-('PyG 3 Años'!$B$38-'PyG 3 Años'!$B$23-'PyG 3 Años'!$B$36-'PyG 3 Años'!$B$37+'PyG 3 Años'!$B$40)/12),"") -> -2522.4583 | I12: =IFERROR(IF('PyG 3 Años'!$B$9="","",-('PyG 3 Años'!$B$38-'PyG 3 Años'!$B$23-'PyG 3 Años'!$B$36-'PyG 3 Años'!$B$37+'PyG 3 Años'!$B$40)/12),"") -> -2522.4583 | ... M12: =IFERROR(IF('PyG 3 Años'!$B$9="","",-('PyG 3 Años'!$B$38-'PyG 3 Años'!$B$23-'PyG 3 Años'!$B$36-'PyG 3 Años'!$B$37+'PyG 3 Años'!$B$40)/12),"") -> -2522.4583 | N12: =IFERROR(IF('PyG 3 Años'!$B$9="","",SUM(B12:M12)),"") -> -30269.5 | O12: Los fijos que salen de caja, cada uno con su tipo de IVA: los seguros están exentos y no llevan
A13: Nóminas y Seguridad Social | B13: =IFERROR(IF('PyG 3 Años'!$B$9="","",-'PyG 3 Años'!$B$23/MAX(12,'0. Supuestos'!$B$21)*(1+IF(1='0. Supuestos'!$B$60,(MAX(12,'0. Supuestos'!$B$21)-12)/2,0)+IF(1='0. Supuestos'!$B$61,(MAX(12,'0. Supuestos'!$B$21)-12)/2,0))),"") -> -3005.8 | C13: =IFERROR(IF('PyG 3 Años'!$B$9="","",-'PyG 3 Años'!$B$23/MAX(12,'0. Supuestos'!$B$21)*(1+IF(2='0. Supuestos'!$B$60,(MAX(12,'0. Supuestos'!$B$21)-12)/2,0)+IF(2='0. Supuestos'!$B$61,(MAX(12,'0. Supuestos'!$B$21)-12)/2,0))),"") -> -3005.8 | D13: =IFERROR(IF('PyG 3 Años'!$B$9="","",-'PyG 3 Años'!$B$23/MAX(12,'0. Supuestos'!$B$21)*(1+IF(3='0. Supuestos'!$B$60,(MAX(12,'0. Supuestos'!$B$21)-12)/2,0)+IF(3='0. Supuestos'!$B$61,(MAX(12,'0. Supuestos'!$B$21)-12)/2,0))),"") -> -3005.8 | E13: =IFERROR(IF('PyG 3 Años'!$B$9="","",-'PyG 3 Años'!$B$23/MAX(12,'0. Supuestos'!$B$21)*(1+IF(4='0. Supuestos'!$B$60,(MAX(12,'0. Supuestos'!$B$21)-12)/2,0)+IF(4='0. Supuestos'!$B$61,(MAX(12,'0. Supuestos'!$B$21)-12)/2,0))),"") -> -3005.8 | F13: =IFERROR(IF('PyG 3 Años'!$B$9="","",-'PyG 3 Años'!$B$23/MAX(12,'0. Supuestos'!$B$21)*(1+IF(5='0. Supuestos'!$B$60,(MAX(12,'0. Supuestos'!$B$21)-12)/2,0)+IF(5='0. Supuestos'!$B$61,(MAX(12,'0. Supuestos'!$B$21)-12)/2,0))),"") -> -3005.8 | G13: =IFERROR(IF('PyG 3 Años'!$B$9="","",-'PyG 3 Años'!$B$23/MAX(12,'0. Supuestos'!$B$21)*(1+IF(6='0. Supuestos'!$B$60,(MAX(12,'0. Supuestos'!$B$21)-12)/2,0)+IF(6='0. Supuestos'!$B$61,(MAX(12,'0. Supuestos'!$B$21)-12)/2,0))),"") -> -3005.8 | H13: =IFERROR(IF('PyG 3 Años'!$B$9="","",-'PyG 3 Años'!$B$23/MAX(12,'0. Supuestos'!$B$21)*(1+IF(7='0. Supuestos'!$B$60,(MAX(12,'0. Supuestos'!$B$21)-12)/2,0)+IF(7='0. Supuestos'!$B$61,(MAX(12,'0. Supuestos'!$B$21)-12)/2,0))),"") -> -6011.6 | I13: =IFERROR(IF('PyG 3 Años'!$B$9="","",-'PyG 3 Años'!$B$23/MAX(12,'0. Supuestos'!$B$21)*(1+IF(8='0. Supuestos'!$B$60,(MAX(12,'0. Supuestos'!$B$21)-12)/2,0)+IF(8='0. Supuestos'!$B$61,(MAX(12,'0. Supuestos'!$B$21)-12)/2,0))),"") -> -3005.8 | J13: =IFERROR(IF('PyG 3 Años'!$B$9="","",-'PyG 3 Años'!$B$23/MAX(12,'0. Supuestos'!$B$21)*(1+IF(9='0. Supuestos'!$B$60,(MAX(12,'0. Supuestos'!$B$21)-12)/2,0)+IF(9='0. Supuestos'!$B$61,(MAX(12,'0. Supuestos'!$B$21)-12)/2,0))),"") -> -3005.8 | K13: =IFERROR(IF('PyG 3 Años'!$B$9="","",-'PyG 3 Años'!$B$23/MAX(12,'0. Supuestos'!$B$21)*(1+IF(10='0. Supuestos'!$B$60,(MAX(12,'0. Supuestos'!$B$21)-12)/2,0)+IF(10='0. Supuestos'!$B$61,(MAX(12,'0. Supuestos'!$B$21)-12)/2,0))),"") -> -3005.8 | L13: =IFERROR(IF('PyG 3 Años'!$B$9="","",-'PyG 3 Años'!$B$23/MAX(12,'0. Supuestos'!$B$21)*(1+IF(11='0. Supuestos'!$B$60,(MAX(12,'0. Supuestos'!$B$21)-12)/2,0)+IF(11='0. Supuestos'!$B$61,(MAX(12,'0. Supuestos'!$B$21)-12)/2,0))),"") -> -3005.8 | M13: =IFERROR(IF('PyG 3 Años'!$B$9="","",-'PyG 3 Años'!$B$23/MAX(12,'0. Supuestos'!$B$21)*(1+IF(12='0. Supuestos'!$B$60,(MAX(12,'0. Supuestos'!$B$21)-12)/2,0)+IF(12='0. Supuestos'!$B$61,(MAX(12,'0. Supuestos'!$B$21)-12)/2,0))),"") -> -6011.6 | N13: =IFERROR(IF('PyG 3 Años'!$B$9="","",SUM(B13:M13)),"") -> -42081.2 | O13: Doce mensualidades más las pagas extra en los meses que digas en Supuestos. La suma del año es la misma que la del P&L
A14: Intereses del préstamo | B14: =IFERROR(IF('PyG 3 Años'!$B$9="","",-'Financiación'!$B$44/12),"") -> -390 | C14: =IFERROR(IF('PyG 3 Años'!$B$9="","",-'Financiación'!$B$44/12),"") -> -390 | D14: =IFERROR(IF('PyG 3 Años'!$B$9="","",-'Financiación'!$B$44/12),"") -> -390 | E14: =IFERROR(IF('PyG 3 Años'!$B$9="","",-'Financiación'!$B$44/12),"") -> -390 | F14: =IFERROR(IF('PyG 3 Años'!$B$9="","",-'Financiación'!$B$44/12),"") -> -390 | G14: =IFERROR(IF('PyG 3 Años'!$B$9="","",-'Financiación'!$B$44/12),"") -> -390 | H14: =IFERROR(IF('PyG 3 Años'!$B$9="","",-'Financiación'!$B$44/12),"") -> -390 | I14: =IFERROR(IF('PyG 3 Años'!$B$9="","",-'Financiación'!$B$44/12),"") -> -390 | ... M14: =IFERROR(IF('PyG 3 Años'!$B$9="","",-'Financiación'!$B$44/12),"") -> -390 | N14: =IFERROR(IF('PyG 3 Años'!$B$9="","",SUM(B14:M14)),"") -> -4680
A15: Devolución de principal del préstamo | B15: =IFERROR(IF('PyG 3 Años'!$B$9="","",-'Financiación'!$B$45/12),"") -> 0 | C15: =IFERROR(IF('PyG 3 Años'!$B$9="","",-'Financiación'!$B$45/12),"") -> 0 | D15: =IFERROR(IF('PyG 3 Años'!$B$9="","",-'Financiación'!$B$45/12),"") -> 0 | E15: =IFERROR(IF('PyG 3 Años'!$B$9="","",-'Financiación'!$B$45/12),"") -> 0 | F15: =IFERROR(IF('PyG 3 Años'!$B$9="","",-'Financiación'!$B$45/12),"") -> 0 | G15: =IFERROR(IF('PyG 3 Años'!$B$9="","",-'Financiación'!$B$45/12),"") -> 0 | H15: =IFERROR(IF('PyG 3 Años'!$B$9="","",-'Financiación'!$B$45/12),"") -> 0 | I15: =IFERROR(IF('PyG 3 Años'!$B$9="","",-'Financiación'!$B$45/12),"") -> 0 | ... M15: =IFERROR(IF('PyG 3 Años'!$B$9="","",-'Financiación'!$B$45/12),"") -> 0 | N15: =IFERROR(IF('PyG 3 Años'!$B$9="","",SUM(B15:M15)),"") -> 0
A16: IVA repercutido del mes (memoria) | B16: =IFERROR(IF('PyG 3 Años'!$B$9="","",'PyG 3 Años'!$B$9*B7*SUMPRODUCT('PyG 3 Años'!$E$10:$E$11,'PyG 3 Años'!$G$10:$G$11)),"") -> 490.57934 | C16: =IFERROR(IF('PyG 3 Años'!$B$9="","",'PyG 3 Años'!$B$9*C7*SUMPRODUCT('PyG 3 Años'!$E$10:$E$11,'PyG 3 Años'!$G$10:$G$11)),"") -> 589.88449 | D16: =IFERROR(IF('PyG 3 Años'!$B$9="","",'PyG 3 Años'!$B$9*D7*SUMPRODUCT('PyG 3 Años'!$E$10:$E$11,'PyG 3 Años'!$G$10:$G$11)),"") -> 813.91572 | E16: =IFERROR(IF('PyG 3 Años'!$B$9="","",'PyG 3 Años'!$B$9*E7*SUMPRODUCT('PyG 3 Años'!$E$10:$E$11,'PyG 3 Años'!$G$10:$G$11)),"") -> 975.21225 | F16: =IFERROR(IF('PyG 3 Años'!$B$9="","",'PyG 3 Años'!$B$9*F7*SUMPRODUCT('PyG 3 Años'!$E$10:$E$11,'PyG 3 Años'!$G$10:$G$11)),"") -> 1190.4725 | G16: =IFERROR(IF('PyG 3 Años'!$B$9="","",'PyG 3 Años'!$B$9*G7*SUMPRODUCT('PyG 3 Años'!$E$10:$E$11,'PyG 3 Años'!$G$10:$G$11)),"") -> 1456.872 | H16: =IFERROR(IF('PyG 3 Años'!$B$9="","",'PyG 3 Años'!$B$9*H7*SUMPRODUCT('PyG 3 Años'!$E$10:$E$11,'PyG 3 Años'!$G$10:$G$11)),"") -> 1560.9342 | I16: =IFERROR(IF('PyG 3 Años'!$B$9="","",'PyG 3 Años'!$B$9*I7*SUMPRODUCT('PyG 3 Años'!$E$10:$E$11,'PyG 3 Años'!$G$10:$G$11)),"") -> 1486.604 | ... M16: =IFERROR(IF('PyG 3 Años'!$B$9="","",'PyG 3 Años'!$B$9*M7*SUMPRODUCT('PyG 3 Años'!$E$10:$E$11,'PyG 3 Años'!$G$10:$G$11)),"") -> 1337.9436 | N16: =IFERROR(IF('PyG 3 Años'!$B$9="","",SUM(B16:M16)),"") -> 13500 | O16: Cada línea de venta a SU tipo, leído de la columna de IVA del P&L: en sala, alcohol incluido, el reducido (art. 91.Uno.2.2.º de la Ley 37/1992 del IVA); el alcohol que sale por delivery, al general; el pan común y las harinas panificables, al superreducido (art. 91.Dos.1.1.º)
A17: IVA soportado del mes (memoria) | B17: =IFERROR(IF('PyG 3 Años'!$B$9="","",'PyG 3 Años'!$B$39*B7+'PyG 3 Años'!$B$40/12),"") -> 617.92438 | C17: =IFERROR(IF('PyG 3 Años'!$B$9="","",'PyG 3 Años'!$B$39*C7+'PyG 3 Años'!$B$40/12),"") -> 661.70861 | D17: =IFERROR(IF('PyG 3 Años'!$B$9="","",'PyG 3 Años'!$B$39*D7+'PyG 3 Años'!$B$40/12),"") -> 760.48533 | E17: =IFERROR(IF('PyG 3 Años'!$B$9="","",'PyG 3 Años'!$B$39*E7+'PyG 3 Años'!$B$40/12),"") -> 831.60194 | F17: =IFERROR(IF('PyG 3 Años'!$B$9="","",'PyG 3 Años'!$B$39*F7+'PyG 3 Años'!$B$40/12),"") -> 926.51149 | G17: =IFERROR(IF('PyG 3 Años'!$B$9="","",'PyG 3 Años'!$B$39*G7+'PyG 3 Años'!$B$40/12),"") -> 1043.9686 | H17: =IFERROR(IF('PyG 3 Años'!$B$9="","",'PyG 3 Años'!$B$39*H7+'PyG 3 Años'!$B$40/12),"") -> 1089.8503 | I17: =IFERROR(IF('PyG 3 Años'!$B$9="","",'PyG 3 Años'!$B$39*I7+'PyG 3 Años'!$B$40/12),"") -> 1057.0777 | ... M17: =IFERROR(IF('PyG 3 Años'!$B$9="","",'PyG 3 Años'!$B$39*M7+'PyG 3 Años'!$B$40/12),"") -> 991.53239 | N17: =IFERROR(IF('PyG 3 Años'!$B$9="","",SUM(B17:M17)),"") -> 10771.731 | O17: Cada partida a su tipo, leído de la columna de IVA del P&L: los seguros y las comisiones de los medios de pago están exentos
A18: IVA a compensar arrastrado (inversión incluida) | E18: =IFERROR(IF('PyG 3 Años'!$B$9="","",'Inversión Inicial'!$B$28),"") -> 12672.24 | H18: =IFERROR(IF('PyG 3 Años'!$B$9="","",MAX(0,-E19)),"") -> 12817.979 | K18: =IFERROR(IF('PyG 3 Años'!$B$9="","",MAX(0,-H19)),"") -> 11997.504 | O18: El IVA soportado de la INVERSIÓN entra aquí: se compensa contra el repercutido de los trimestres siguientes hasta agotarlo (modelo 303)
A19: Resultado de la liquidación trimestral | E19: =IFERROR(IF('PyG 3 Años'!$B$9="","",SUM(B16:D16)-SUM(B17:D17)-E18),"") -> -12817.979 | H19: =IFERROR(IF('PyG 3 Años'!$B$9="","",SUM(E16:G16)-SUM(E17:G17)-H18),"") -> -11997.504 | K19: =IFERROR(IF('PyG 3 Años'!$B$9="","",SUM(H16:J16)-SUM(H17:J17)-K18),"") -> -10767.106 | O19: Repercutido menos soportado del trimestre menos lo que venía arrastrado. En negativo NO se paga: se compensa en el trimestre siguiente
A20: Pago del IVA (modelo 303) | E20: =IFERROR(IF('PyG 3 Años'!$B$9="","",IF(E19<=0,"",-E19)),"") | H20: =IFERROR(IF('PyG 3 Años'!$B$9="","",IF(H19<=0,"",-H19)),"") | K20: =IFERROR(IF('PyG 3 Años'!$B$9="","",IF(K19<=0,"",-K19)),"") | N20: =IFERROR(IF('PyG 3 Años'!$B$9="","",SUM(B20:M20)),"") -> 0 | O20: Sólo sale caja cuando el resultado del trimestre es positivo. Los meses sin liquidación van en blanco, no a cero. La celda se pinta en ROJO cuando el pago del 303 se lleva más caja de la que queda ese mes
A21: FLUJO DEL MES | B21: =IFERROR(IF('PyG 3 Años'!$B$9="","",SUM(B9:B15)+IF(B20="",0,B20)),"") -> -521.88565 | C21: =IFERROR(IF('PyG 3 Años'!$B$9="","",SUM(C9:C15)+IF(C20="",0,C20)),"") -> -1407.5674 | D21: =IFERROR(IF('PyG 3 Años'!$B$9="","",SUM(D9:D15)+IF(D20="",0,D20)),"") -> 656.37315 | E21: =IFERROR(IF('PyG 3 Años'!$B$9="","",SUM(E9:E15)+IF(E20="",0,E20)),"") -> 1527.3308 | F21: =IFERROR(IF('PyG 3 Años'!$B$9="","",SUM(F9:F15)+IF(F20="",0,F20)),"") -> 3244.8387 | G21: =IFERROR(IF('PyG 3 Años'!$B$9="","",SUM(G9:G15)+IF(G20="",0,G20)),"") -> 5307.2933 | H21: =IFERROR(IF('PyG 3 Años'!$B$9="","",SUM(H9:H15)+IF(H20="",0,H20)),"") -> 2372.0436 | I21: =IFERROR(IF('PyG 3 Años'!$B$9="","",SUM(I9:I15)+IF(I20="",0,I20)),"") -> 4140.6275 | ... M21: =IFERROR(IF('PyG 3 Años'!$B$9="","",SUM(M9:M15)+IF(M20="",0,M20)),"") -> 1357.7203 | N21: =IFERROR(IF('PyG 3 Años'!$B$9="","",SUM(B21:M21)),"") -> 22431.329
A22: SALDO ACUMULADO DE CAJA | B22: =IFERROR(IF('PyG 3 Años'!$B$9="","",'Inversión Inicial'!$B$25+B21),"") -> 17530.914 | C22: =IFERROR(IF('PyG 3 Años'!$B$9="","",B22+C21),"") -> 16123.347 | D22: =IFERROR(IF('PyG 3 Años'!$B$9="","",C22+D21),"") -> 16779.72 | E22: =IFERROR(IF('PyG 3 Años'!$B$9="","",D22+E21),"") -> 18307.051 | F22: =IFERROR(IF('PyG 3 Años'!$B$9="","",E22+F21),"") -> 21551.89 | G22: =IFERROR(IF('PyG 3 Años'!$B$9="","",F22+G21),"") -> 26859.183 | H22: =IFERROR(IF('PyG 3 Años'!$B$9="","",G22+H21),"") -> 29231.227 | I22: =IFERROR(IF('PyG 3 Años'!$B$9="","",H22+I21),"") -> 33371.854 | J22: =IFERROR(IF('PyG 3 Años'!$B$9="","",I22+J21),"") -> 35849.867 | ... M22: =IFERROR(IF('PyG 3 Años'!$B$9="","",L22+M21),"") -> 40484.129
A23: Saldo mínimo del año | B23: =IFERROR(IF('PyG 3 Años'!$B$9="","",IF(COUNT(B22:M22)=0,"",MIN(B22:M22))),"") -> 16123.347 | D23: Si es negativo, sube el fondo de maniobra o el préstamo: te quedas sin caja
A24: Mes en el que la caja toca fondo | B24: =IFERROR(IF('PyG 3 Años'!$B$9="","",IF(COUNT(B22:M22)=0,"",MATCH(MIN(B22:M22),B22:M22,0))),"") -> 2 | D24: Es la respuesta a la pregunta que decide una operación bancaria: en qué mes se agota la caja
A25: RETORNO DE LA INVERSIÓN
A26: Flujo de caja libre antes de la deuda, año 1 | B26: =IFERROR(IF('PyG 3 Años'!$B$9="","",'PyG 3 Años'!$B$48+'PyG 3 Años'!$B$36+'Financiación'!$B$44),"") -> 17839.349 | D26: Resultado neto más amortización (que no se paga) más los intereses de ese año: el principal no se resta porque este flujo es ANTES de la deuda. La MISMA base que los años 2 y 3, para que el payback compare peras con peras
A27: Flujo de caja libre antes de la deuda, año 2 | B27: =IFERROR(IF('PyG 3 Años'!$B$9="","",'PyG 3 Años'!$C$48+'PyG 3 Años'!$C$36+'Financiación'!$B$46),"") -> 23770.599 | D27: Resultado neto más amortización (que no se paga) más los intereses de ese año: el principal no se resta porque este flujo es ANTES de la deuda. Sin tabla mensual, es una estimación
A28: Flujo de caja libre antes de la deuda, año 3 | B28: =IFERROR(IF('PyG 3 Años'!$B$9="","",'PyG 3 Años'!$D$48+'PyG 3 Años'!$D$36+'Financiación'!$B$48),"") -> 25063.588 | D28: Resultado neto más amortización (que no se paga) más los intereses de ese año: el principal no se resta porque este flujo es ANTES de la deuda. Sin tabla mensual, es una estimación
A29: Informativo: flujo REAL de caja del año 1 (tabla mensual, antes de la deuda) | B29: =IFERROR(IF('PyG 3 Años'!$B$9="","",N21+'Financiación'!$B$44+'Financiación'!$B$45),"") -> 27111.329 | D29: La suma de los doce FLUJO DEL MES de arriba, devolviéndole los intereses y el principal que se pagaron ese año. NO es la que usa el payback: lleva dentro el IVA que todavía no se ha liquidado y el crédito del proveedor, dos cosas que hay que devolver y que los años 2 y 3 no tienen
A30: Inversión a recuperar (sin el IVA, que se recupera por el 303) | B30: =IFERROR(IF('PyG 3 Años'!$B$9="","",'Inversión Inicial'!$B$29-'Inversión Inicial'!$B$28),"") -> 81996.8 | D30: CAPEX más fondo de maniobra: la necesidad total de caja MENOS el IVA soportado de la inversión, que no se pierde (se recupera con el modelo 303 y esta misma hoja lo compensa trimestre a trimestre). El fondo de maniobra sí se recupera al cerrar, pero hasta entonces está inmovilizado
A31: Payback del proyecto (años), antes de la deuda | B31: =IFERROR(IF('PyG 3 Años'!$B$9="","",IF(B26>=B30,ROUND(B30/B26,1),IF(B26+B27>=B30,ROUND(1+(B30-B26)/B27,1),IF(B26+B27+B28>=B30,ROUND(2+(B30-B26-B27)/B28,1),"Más de 3 años")))),"") -> Más de 3 años | D31: Mide cuánto tarda el negocio en devolver la inversión con lo que genera ANTES de pagar al banco, con la MISMA base de flujo en los tres años; si puedes pagar la cuota lo dice el DSCR de la hoja de Financiación. El documento Word del pack sigue en la versión 1.1 y no lee esta celda: las cifras válidas son las de este libro
A32: Payback sobre el CAPEX, sin fondo de maniobra (años) | B32: =IFERROR(IF('PyG 3 Años'!$B$9="","",IF(B26>='Inversión Inicial'!$B$27,ROUND('Inversión Inicial'!$B$27/B26,1),IF(B26+B27>='Inversión Inicial'!$B$27,ROUND(1+('Inversión Inicial'!$B$27-B26)/B27,1),IF(B26+B27+B28>='Inversión Inicial'!$B$27,ROUND(2+('Inversión Inicial'!$B$27-B26-B27)/B28,1),"Más de 3 años")))),"") -> 2.9 | D32: El mismo cálculo sobre lo que se COMPRA (obra, equipamiento, lanzamiento y constitución), sin el fondo de maniobra: ese dinero no se gasta, se inmoviliza y vuelve al cerrar el negocio. Informativo: el payback que se publica es el de arriba
A34: El IVA del cuarto trimestre se liquida en enero del año siguiente, así que no aparece en este cuadro. El Impuesto de Sociedades del año 1 se paga en julio del año 2. La cuota del préstamo se reparte en doce partes iguales siguiendo el cuadro ANUAL de la hoja de Financiación, y las nóminas en doce mensualidades más las dos pagas extra en su mes.

Sheet Financiación
A1: PLAN DE FINANCIACIÓN
A2: Qué hace falta, de dónde sale y cuánto cuesta devolverlo. Es la hoja que el banco pide junto con el P&L.
A4: Concepto | B4: Importe | C4: Notas
A5: ORIGEN DE FONDOS
A6: Recursos propios de los socios | B6: =IFERROR(IF('0. Supuestos'!$B$30="","",'0. Supuestos'!$B$30),"") -> 25000
A7: Préstamo bancario | B7: =IFERROR(IF('0. Supuestos'!$B$31="","",'0. Supuestos'!$B$31),"") -> 72000
A8: Línea ICO (avalada por el ICO, la concede tu banco) | B8: 0 | C8: Consulta las líneas del ejercicio en curso en ico.es
A9: Préstamo participativo ENISA | B9: 0 | C9: Para sociedades; sin garantías personales
A10: Business angels o socios inversores | B10: 0 | C10: Entra en el capital: diluye, no se devuelve
A11: Subvenciones autonómicas o locales | B11: 0 | C11: Suelen cobrarse DESPUÉS de justificar el gasto
A12: TOTAL ORIGEN DE FONDOS | B12: =IFERROR(IF(COUNT(B6:B11)=0,"",SUM(B6:B11)),"") -> 97000
A13: USOS
A14: Necesidad total de caja al arranque | B14: =IFERROR(IF('Inversión Inicial'!$B$29="","",'Inversión Inicial'!$B$29),"") -> 94669.04 | C14: Inversión más el IVA que hay que adelantar
A15: Diferencia (origen - usos) | B15: =IFERROR(B12-B14,"") -> 2330.96 | C15: En rojo (negativa) el plan NO está financiado. Muy por encima de cero tampoco es gratis: se pagan intereses por un dinero que no se usa
A16: Diferencia sobre los usos (%) | B16: =IFERROR(B15/B14,"") -> 0.0246222 | C16: Ámbar por encima del margen que fijes: es deuda que pagas sin necesitarla
A17: Exceso de financiación admisible (%) | B17: 0.05 | C17: Un pequeño colchón sobre la necesidad es sano; un 20 % de más son intereses tirados
A18: Préstamo que ajustaría el origen a la necesidad | B18: =IFERROR(MAX(0,B14-B12+B7),"") -> 69669.04 | C18: Cópialo en «Préstamo bancario solicitado» de la hoja de Supuestos y la diferencia se pone a cero
A19: CONDICIONES DEL PRÉSTAMO
A20: Importe del principal | B20: =IFERROR(IF('0. Supuestos'!$B$31=0,"",'0. Supuestos'!$B$31),"") -> 72000
A21: Tipo de interés nominal anual | B21: =IFERROR(IF('0. Supuestos'!$B$32="","",'0. Supuestos'!$B$32),"") -> 0.065
A22: Plazo total (años) | B22: =IFERROR(IF('0. Supuestos'!$B$33="","",'0. Supuestos'!$B$33),"") -> 6
A23: Carencia de principal aplicada (años) | B23: =IFERROR(IF(OR('0. Supuestos'!$B$34="",'0. Supuestos'!$B$33=""),"",IF('0. Supuestos'!$B$34>='0. Supuestos'!$B$33,0,'0. Supuestos'!$B$34)),"") -> 1 | C23: Una carencia igual o mayor que el plazo no existe: la hoja la anula en origen
A24: Cuota anual durante la amortización | B24: =IFERROR(IF(B22-B23<=0,"",IF(B21=0,B20/(B22-B23),B20*B21/(1-(1+B21)^-(B22-B23)))),"") -> 17325.687 | C24: Sistema francés, anualidad algebraica. Con el tipo al 0 % es el principal entre los años de amortización: sin esa rama el cuadro se apagaba entero
A25: CUADRO DE AMORTIZACIÓN
A26: Año | B26: Capital pendiente | C26: Intereses | D26: Amortización de principal | E26: Cuota total | F26: Capital al cierre | G26: Flujo disponible para la deuda (después de impuestos; del año 4 en adelante, el del año 3 mantenido) | H26: DSCR del año
A27: 1 | B27: =IFERROR(IF(B20="","",B20),"") -> 72000 | C27: =IFERROR(IF(OR(1>B22,B27=""),"",B27*B21),"") -> 4680 | D27: =IFERROR(IF(OR(1>B22,B27=""),"",IF(1<=B23,0,MIN(B27,B24-C27))),"") -> 0 | E27: =IFERROR(IF(C27="","",C27+D27),"") -> 4680 | F27: =IFERROR(IF(D27="","",B27-D27),"") -> 72000 | G27: =IFERROR(IF(E27="","",'PyG 3 Años'!$B$41-'PyG 3 Años'!$B$46+'PyG 3 Años'!$B$36+'PyG 3 Años'!$B$37),"") -> 17839.349 | H27: =IFERROR(IF(OR(E27="",E27=0),"",G27/E27),"") -> 3.8118266
A28: 2 | B28: =IFERROR(IF(OR(2>B22,F27=""),"",F27),"") -> 72000 | C28: =IFERROR(IF(OR(2>B22,B28=""),"",B28*B21),"") -> 4680 | D28: =IFERROR(IF(OR(2>B22,B28=""),"",IF(2<=B23,0,MIN(B28,B24-C28))),"") -> 12645.687 | E28: =IFERROR(IF(C28="","",C28+D28),"") -> 17325.687 | F28: =IFERROR(IF(D28="","",B28-D28),"") -> 59354.313 | G28: =IFERROR(IF(E28="","",'PyG 3 Años'!$C$41-'PyG 3 Años'!$C$46+'PyG 3 Años'!$C$36+'PyG 3 Años'!$C$37),"") -> 23770.599 | H28: =IFERROR(IF(OR(E28="",E28=0),"",G28/E28),"") -> 1.371986
A29: 3 | B29: =IFERROR(IF(OR(3>B22,F28=""),"",F28),"") -> 59354.313 | C29: =IFERROR(IF(OR(3>B22,B29=""),"",B29*B21),"") -> 3858.0304 | D29: =IFERROR(IF(OR(3>B22,B29=""),"",IF(3<=B23,0,MIN(B29,B24-C29))),"") -> 13467.656 | E29: =IFERROR(IF(C29="","",C29+D29),"") -> 17325.687 | F29: =IFERROR(IF(D29="","",B29-D29),"") -> 45886.657 | G29: =IFERROR(IF(E29="","",'PyG 3 Años'!$D$41-'PyG 3 Años'!$D$46+'PyG 3 Años'!$D$36+'PyG 3 Años'!$D$37),"") -> 25063.588 | H29: =IFERROR(IF(OR(E29="",E29=0),"",G29/E29),"") -> 1.4466144
A30: 4 | B30: =IFERROR(IF(OR(4>B22,F29=""),"",F29),"") -> 45886.657 | C30: =IFERROR(IF(OR(4>B22,B30=""),"",B30*B21),"") -> 2982.6327 | D30: =IFERROR(IF(OR(4>B22,B30=""),"",IF(4<=B23,0,MIN(B30,B24-C30))),"") -> 14343.054 | E30: =IFERROR(IF(C30="","",C30+D30),"") -> 17325.687 | F30: =IFERROR(IF(D30="","",B30-D30),"") -> 31543.603 | G30: =IFERROR(IF(E30="","",'PyG 3 Años'!$D$41-'PyG 3 Años'!$D$46+'PyG 3 Años'!$D$36+'PyG 3 Años'!$D$37),"") -> 25063.588 | H30: =IFERROR(IF(OR(E30="",E30=0),"",G30/E30),"") -> 1.4466144
A31: 5 | B31: =IFERROR(IF(OR(5>B22,F30=""),"",F30),"") -> 31543.603 | C31: =IFERROR(IF(OR(5>B22,B31=""),"",B31*B21),"") -> 2050.3342 | D31: =IFERROR(IF(OR(5>B22,B31=""),"",IF(5<=B23,0,MIN(B31,B24-C31))),"") -> 15275.353 | E31: =IFERROR(IF(C31="","",C31+D31),"") -> 17325.687 | F31: =IFERROR(IF(D31="","",B31-D31),"") -> 16268.25 | G31: =IFERROR(IF(E31="","",'PyG 3 Años'!$D$41-'PyG 3 Años'!$D$46+'PyG 3 Años'!$D$36+'PyG 3 Años'!$D$37),"") -> 25063.588 | H31: =IFERROR(IF(OR(E31="",E31=0),"",G31/E31),"") -> 1.4466144
A32: 6 | B32: =IFERROR(IF(OR(6>B22,F31=""),"",F31),"") -> 16268.25 | C32: =IFERROR(IF(OR(6>B22,B32=""),"",B32*B21),"") -> 1057.4363 | D32: =IFERROR(IF(OR(6>B22,B32=""),"",IF(6<=B23,0,MIN(B32,B24-C32))),"") -> 16268.25 | E32: =IFERROR(IF(C32="","",C32+D32),"") -> 17325.687 | F32: =IFERROR(IF(D32="","",B32-D32),"") -> 0 | G32: =IFERROR(IF(E32="","",'PyG 3 Años'!$D$41-'PyG 3 Años'!$D$46+'PyG 3 Años'!$D$36+'PyG 3 Años'!$D$37),"") -> 25063.588 | H32: =IFERROR(IF(OR(E32="",E32=0),"",G32/E32),"") -> 1.4466144
A33: 7 | B33: =IFERROR(IF(OR(7>B22,F32=""),"",F32),"") | C33: =IFERROR(IF(OR(7>B22,B33=""),"",B33*B21),"") | D33: =IFERROR(IF(OR(7>B22,B33=""),"",IF(7<=B23,0,MIN(B33,B24-C33))),"") | E33: =IFERROR(IF(C33="","",C33+D33),"") | F33: =IFERROR(IF(D33="","",B33-D33),"") | G33: =IFERROR(IF(E33="","",'PyG 3 Años'!$D$41-'PyG 3 Años'!$D$46+'PyG 3 Años'!$D$36+'PyG 3 Años'!$D$37),"") | H33: =IFERROR(IF(OR(E33="",E33=0),"",G33/E33),"")
A34: 8 | B34: =IFERROR(IF(OR(8>B22,F33=""),"",F33),"") | C34: =IFERROR(IF(OR(8>B22,B34=""),"",B34*B21),"") | D34: =IFERROR(IF(OR(8>B22,B34=""),"",IF(8<=B23,0,MIN(B34,B24-C34))),"") | E34: =IFERROR(IF(C34="","",C34+D34),"") | F34: =IFERROR(IF(D34="","",B34-D34),"") | G34: =IFERROR(IF(E34="","",'PyG 3 Años'!$D$41-'PyG 3 Años'!$D$46+'PyG 3 Años'!$D$36+'PyG 3 Años'!$D$37),"") | H34: =IFERROR(IF(OR(E34="",E34=0),"",G34/E34),"")
A35: 9 | B35: =IFERROR(IF(OR(9>B22,F34=""),"",F34),"") | C35: =IFERROR(IF(OR(9>B22,B35=""),"",B35*B21),"") | D35: =IFERROR(IF(OR(9>B22,B35=""),"",IF(9<=B23,0,MIN(B35,B24-C35))),"") | E35: =IFERROR(IF(C35="","",C35+D35),"") | F35: =IFERROR(IF(D35="","",B35-D35),"") | G35: =IFERROR(IF(E35="","",'PyG 3 Años'!$D$41-'PyG 3 Años'!$D$46+'PyG 3 Años'!$D$36+'PyG 3 Años'!$D$37),"") | H35: =IFERROR(IF(OR(E35="",E35=0),"",G35/E35),"")
A36: 10 | B36: =IFERROR(IF(OR(10>B22,F35=""),"",F35),"") | C36: =IFERROR(IF(OR(10>B22,B36=""),"",B36*B21),"") | D36: =IFERROR(IF(OR(10>B22,B36=""),"",IF(10<=B23,0,MIN(B36,B24-C36))),"") | E36: =IFERROR(IF(C36="","",C36+D36),"") | F36: =IFERROR(IF(D36="","",B36-D36),"") | G36: =IFERROR(IF(E36="","",'PyG 3 Años'!$D$41-'PyG 3 Años'!$D$46+'PyG 3 Años'!$D$36+'PyG 3 Años'!$D$37),"") | H36: =IFERROR(IF(OR(E36="",E36=0),"",G36/E36),"")
A37: 11 | B37: =IFERROR(IF(OR(11>B22,F36=""),"",F36),"") | C37: =IFERROR(IF(OR(11>B22,B37=""),"",B37*B21),"") | D37: =IFERROR(IF(OR(11>B22,B37=""),"",IF(11<=B23,0,MIN(B37,B24-C37))),"") | E37: =IFERROR(IF(C37="","",C37+D37),"") | F37: =IFERROR(IF(D37="","",B37-D37),"") | G37: =IFERROR(IF(E37="","",'PyG 3 Años'!$D$41-'PyG 3 Años'!$D$46+'PyG 3 Años'!$D$36+'PyG 3 Años'!$D$37),"") | H37: =IFERROR(IF(OR(E37="",E37=0),"",G37/E37),"")
A38: 12 | B38: =IFERROR(IF(OR(12>B22,F37=""),"",F37),"") | C38: =IFERROR(IF(OR(12>B22,B38=""),"",B38*B21),"") | D38: =IFERROR(IF(OR(12>B22,B38=""),"",IF(12<=B23,0,MIN(B38,B24-C38))),"") | E38: =IFERROR(IF(C38="","",C38+D38),"") | F38: =IFERROR(IF(D38="","",B38-D38),"") | G38: =IFERROR(IF(E38="","",'PyG 3 Años'!$D$41-'PyG 3 Años'!$D$46+'PyG 3 Años'!$D$36+'PyG 3 Años'!$D$37),"") | H38: =IFERROR(IF(OR(E38="",E38=0),"",G38/E38),"")
A39: 13 | B39: =IFERROR(IF(OR(13>B22,F38=""),"",F38),"") | C39: =IFERROR(IF(OR(13>B22,B39=""),"",B39*B21),"") | D39: =IFERROR(IF(OR(13>B22,B39=""),"",IF(13<=B23,0,MIN(B39,B24-C39))),"") | E39: =IFERROR(IF(C39="","",C39+D39),"") | F39: =IFERROR(IF(D39="","",B39-D39),"") | G39: =IFERROR(IF(E39="","",'PyG 3 Años'!$D$41-'PyG 3 Años'!$D$46+'PyG 3 Años'!$D$36+'PyG 3 Años'!$D$37),"") | H39: =IFERROR(IF(OR(E39="",E39=0),"",G39/E39),"")
A40: 14 | B40: =IFERROR(IF(OR(14>B22,F39=""),"",F39),"") | C40: =IFERROR(IF(OR(14>B22,B40=""),"",B40*B21),"") | D40: =IFERROR(IF(OR(14>B22,B40=""),"",IF(14<=B23,0,MIN(B40,B24-C40))),"") | E40: =IFERROR(IF(C40="","",C40+D40),"") | F40: =IFERROR(IF(D40="","",B40-D40),"") | G40: =IFERROR(IF(E40="","",'PyG 3 Años'!$D$41-'PyG 3 Años'!$D$46+'PyG 3 Años'!$D$36+'PyG 3 Años'!$D$37),"") | H40: =IFERROR(IF(OR(E40="",E40=0),"",G40/E40),"")
A41: 15 | B41: =IFERROR(IF(OR(15>B22,F40=""),"",F40),"") | C41: =IFERROR(IF(OR(15>B22,B41=""),"",B41*B21),"") | D41: =IFERROR(IF(OR(15>B22,B41=""),"",IF(15<=B23,0,MIN(B41,B24-C41))),"") | E41: =IFERROR(IF(C41="","",C41+D41),"") | F41: =IFERROR(IF(D41="","",B41-D41),"") | G41: =IFERROR(IF(E41="","",'PyG 3 Años'!$D$41-'PyG 3 Años'!$D$46+'PyG 3 Años'!$D$36+'PyG 3 Años'!$D$37),"") | H41: =IFERROR(IF(OR(E41="",E41=0),"",G41/E41),"")
A42: Tolerancia de cierre del cuadro (€) | B42: 0.01 | C42: Margen por redondeo. Por encima, el cuadro no cierra y hay capital sin devolver
A43: Capital pendiente al vencimiento | B43: =IFERROR(IF(B20="","",ROUND(B20-SUM(D27:D41),2)),"") -> 0 | C43: Tiene que ser cero: el principal devuelto en el cuadro tiene que ser el prestado. Si sale positivo, el plazo no llega
A44: Intereses del año 1 | B44: =IFERROR(IF(B20="","",IF(C27="",0,C27)),"") -> 4680
A45: Devolución de principal del año 1 | B45: =IFERROR(IF(B20="","",IF(D27="",0,D27)),"") -> 0
A46: Intereses del año 2 | B46: =IFERROR(IF(B20="","",IF(C28="",0,C28)),"") -> 4680
A47: Devolución de principal del año 2 | B47: =IFERROR(IF(B20="","",IF(D28="",0,D28)),"") -> 12645.687
A48: Intereses del año 3 | B48: =IFERROR(IF(B20="","",IF(C29="",0,C29)),"") -> 3858.0304
A49: Devolución de principal del año 3 | B49: =IFERROR(IF(B20="","",IF(D29="",0,D29)),"") -> 13467.656
A50: COBERTURA DEL SERVICIO DE LA DEUDA (DSCR)
A51: DSCR del año 1 | B51: =IFERROR(('PyG 3 Años'!$B$41-'PyG 3 Años'!$B$46+'PyG 3 Años'!$B$36+B44)/(B44+B45),"") -> 3.8118266 | C51: Año de CARENCIA si la hay: con sólo intereses en el denominador el ratio se dispara y no mide el negocio
A52: DSCR del año 2 | B52: =IFERROR(('PyG 3 Años'!$C$41-'PyG 3 Años'!$C$46+'PyG 3 Años'!$C$36+B46)/(B46+B47),"") -> 1.371986
A53: DSCR del año 3 | B53: =IFERROR(('PyG 3 Años'!$D$41-'PyG 3 Años'!$D$46+'PyG 3 Años'!$D$36+B48)/(B48+B49),"") -> 1.4466144
A54: DSCR mínimo de todo el cuadro | B54: =IFERROR(IF(COUNT(H27:H41)=0,"",MIN(H27:H41)),"") -> 1.371986 | C54: El peor año de los que dura el préstamo, no el mejor de los tres que proyecta el P&L. Es el número que decide una operación. Ojo al alcance: los años 1 a 3 salen del P&L y del año 4 en adelante el cuadro MANTIENE el flujo del año 3, así que el mínimo de esos años es una proyección sostenida, no un año calculado. El flujo va después de impuestos
A56: El DSCR se calcula ANTES de la deuda y DESPUÉS de impuestos: al resultado antes de impuestos se le resta el Impuesto de Sociedades y se le devuelven la amortización contable y los intereses; el resultado se divide entre lo que hay que pagar ese año. Por debajo del mínimo de la hoja de Supuestos, el negocio no genera para pagar el préstamo. En el cuadro, el flujo de caja disponible de los años 4 en adelante se mantiene en el del año 3: el P&L sólo proyecta tres, y aquí no se inventa un crecimiento que no está calculado.
