Workbook

Sheet Instrucciones
A1: Carta de Apertura y Escandallo del Churro
A2: AI Chef Pro · aichef.pro — Cómo Montar una Churrería-Chocolatería
A3: Para qué sirve: decidir a cuánto vendes la ración, la docena, el kilo y la taza, con el coste real de la masa frita y del aceite que se lleva, y saber qué margen te queda de verdad.
A5: Instrucciones de Uso
A6: Celdas verdes = campos editables
A7: Las celdas en crema son resultados que el libro calcula; las blancas con fórmula, también. No escribas encima.
A9: 1. Hoja «Parámetros». Arriba, el IVA de cada canal: la sala al 10 % y, para llevar, una celda por categoría. Chocolate y bebidas para llevar van al 10 % en celda verde con un aviso (consulta a tu asesor: con agua y un preparado azucarado podría ser el 21 %); granizado y horchata para llevar llevan el 21 % por prudencia, también en celda verde y con el mismo aviso (es zona gris: lo decide tu asesor). Abajo, los supuestos de la masa y del aceite, y la tabla de insumos: es la ÚNICA tabla donde se tocan los precios. El del aceite es la celda única de todo el paquete.
A10: 2. Hoja «Escandallo por kg de Masa». Cuánto cuesta un kilo de masa con el preparado comercial y con un mix propio, cuánto cuesta un churro y una porra, y de la masa a cada una de las 24 referencias de la carta. Al pie, la receta y el envase de cada referencia: el envase sólo cuenta cuando se vende para llevar.
A11: 3. Hoja «Absorción de Aceite y Merma». Los euros de aceite que se lleva cada kilo de masa frita y lo que cuesta la masa que se fríe y no se vende. Aquí sólo está el aceite ABSORBIDO; la renovación del aceite de la cuba la calcula el libro 4.
A12: 4. Hoja «Chocolate a la Taza». Lo que cuesta una taza y qué dice la etiqueta de tu preparado. La carta usa la denominación que figura en esa etiqueta; si el cacao seco total baja del 35 % o lleva grasa vegetal, la hoja te pide consultar a tu servicio de consumo antes de imprimir la carta.
A13: 5. Hoja «Coste Hora». El coste de empresa de una hora de tu plantilla y los minutos de mano de obra que lleva cada ración. Nace con el de El Molinete; cuando rellenes el libro 8, su fila de CUADRE te dirá si este número se ha quedado viejo.
A14: 6. Hoja «Ración, Docena o Kilo». Los siete formatos de churro y porra, comparados por los euros que deja cada kilo de masa que fríes.
... A63: Versión 1.0 · octubre 2026 · aichef.pro/guia-churreria-chocolateria · info@aichef.pro

Sheet Parámetros
A1: Parámetros
A2: AI Chef Pro · aichef.pro — Cómo Montar una Churrería-Chocolatería
A3: Todo lo que el resto de hojas da por sabido vive aquí. Ninguna fórmula de este libro lleva un número de IVA, de margen o de umbral dentro.
A4: IVA por Canal (El Capítulo 03 de la Guía lo Explica) | K4: Lo que Copian Otros Libros (No Muevas Estas Celdas)
A5: IVA en sala, barra y terraza (servicio de hostelería) | B5: 0.1 | C5: tipo | D5: CHN-71c + FC-IVA-01 | E5: Servicio de hostelería: lo que se consume en barra, sala o terraza, bebidas incluidas, va al tipo reducido. | K5: Precio del aceite (base imponible), EUR/L | L5: =G34 -> 1.996 | M5: Lo copia: libro 2 (calculadora-capex-churreria.xlsx, hoja Parámetros, X17); libro 4 (aceite-de-fritura-coste-y-cambio.xlsx, hoja Parámetros, X2)
A6: IVA de churros y porras para llevar | B6: 0.1 | C6: tipo | D6: FC-IVA-02 | E6: Churros y porras para llevar: entrega de un alimento. | K6: Absorción de aceite, en % del peso frito | L6: =B18 -> 0.1 | M6: Lo copia: libro 4 (aceite-de-fritura-coste-y-cambio.xlsx, hoja Parámetros, X2)
A7: IVA del chocolate a la taza para llevar | B7: 0.1 | C7: tipo | D7: CUN-18 | E7: Consulta a tu asesor: con agua y un preparado azucarado podría ser el 21 %. El Molinete aplica el 10 % y lo deja en celda verde: es una zona gris y el tipo lo decide tu asesor, no este libro. | K7: Densidad del aceite, kg/L | L7: =B19 -> 0.92 | M7: Lo copia: libro 4 (aceite-de-fritura-coste-y-cambio.xlsx, hoja Parámetros, X2)
A8: IVA de las demás bebidas para llevar (café, leche con cacao, zumo, agua, batido) | B8: 0.1 | C8: tipo | D8: CUN-18 + CHN-71c | E8: Consulta a tu asesor: con agua y un preparado azucarado podría ser el 21 %. El mismo aviso vale para todas las bebidas para llevar, leche con cacao incluida. El refresco con azúcar añadido para llevar va al tipo general: tiene su propia fila. | K8: Precio del preparado para masa (base imponible), EUR/kg | L8: =G33 -> 1.45 | M8: Lo copia: libro 2 (calculadora-capex-churreria.xlsx, hoja Parámetros, X17)
A9: IVA del granizado y la horchata para llevar | B9: 0.21 | C9: tipo | D9: FC-IVA-04 + CUN-17 | E9: Aviso, no regla: El Molinete pone el 21 % por prudencia. Desde el 1-1-2021 las bebidas refrescantes con azúcares añadidos para llevar quedan fuera del tipo reducido y no hay una consulta que diga si tu granizado o tu horchata lo son. Es zona gris: consúltalo con tu asesor y, si te confirma el 10 %, cámbialo aquí. En sala siguen al 10 % (servicio de hostelería). | K9: Kilos fritos que salen de un kilo de masa, kg/kg | L9: =B17 -> 0.9 | M9: Lo copia: libro 1 (produccion-hora-punta-y-local.xlsx, hoja Parámetros, X1 bis)
A10: IVA general (envases, equipamiento, servicios) | B10: 0.21 | C10: tipo | D10: CHN-71c | E10: Tipo general: equipamiento, obra, envases y servicios. | K10: Precio del insumo «Chocolate a la taza en polvo (bolsa de 800 g, rinde 4,3 L)» (base imponible), EUR/unidad | L10: =G35 -> 7.1875 | M10: Lo copia: libro 2 (calculadora-capex-churreria.xlsx, hoja Parámetros, X17)
A11: IVA soportado de los alimentos que compras | B11: 0.1 | C11: tipo | D11: supuesto declarado | E11: IVA soportado del mix, el aceite y el preparado: compruébalo en cada factura, el aceite ha tenido tipos rebajados temporales. | K11: Precio del insumo «Cobertura de chocolate negro (1 kg)» (base imponible), EUR/unidad | L11: =G36 -> 6.5 | M11: Lo copia: libro 2 (calculadora-capex-churreria.xlsx, hoja Parámetros, X17)
K12: Precio del insumo «Cucurucho de cartón para churros (caja de 100)» (base imponible), EUR/unidad | L12: =G37 -> 0.15 | M12: Lo copia: libro 2 (calculadora-capex-churreria.xlsx, hoja Parámetros, X17)
A13: Masa, Fritura y Aceite (Supuestos Declarados de El Molinete) | K13: Precio del insumo «Vaso de papel plastificado con tapa» (base imponible), EUR/unidad | L13: =G51 -> 0.08 | M13: Lo copia: libro 2 (calculadora-capex-churreria.xlsx, hoja Parámetros, X17)
A14: Gramos de masa por churro (lo que se vende) | B14: 20 | C14: g/pieza | D14: supuesto declarado | E14: Supuesto de El Molinete: pesa diez churros de tu masa y divide. | K14: Precio del insumo «Papel antigrasa para sueltos» (base imponible), EUR/unidad | L14: =G52 -> 0.02 | M14: Lo copia: libro 2 (calculadora-capex-churreria.xlsx, hoja Parámetros, X17)
A15: Gramos de masa por porra (lo que se vende) | B15: 60 | C15: g/pieza | D15: supuesto declarado | E15: Supuesto de El Molinete: pesa diez porras de tu masa y divide. | K15: Precio del insumo «Caja de cartón para el kilo» (base imponible), EUR/unidad | L15: =G53 -> 0.25 | M15: Lo copia: libro 2 (calculadora-capex-churreria.xlsx, hoja Parámetros, X17)
A16: Merma: masa que se fríe y no se vende | B16: 0.05 | C16: sobre lo frito | D16: supuesto declarado | E16: Masa que se fríe y no se vende: restos, piezas rotas y el sobrante del cierre. Se produce y se fríe igual. | K16: Precio del insumo «Café en grano» (base imponible), EUR/unidad | L16: =G42 -> 18 | M16: Lo copia: libro 2 (calculadora-capex-churreria.xlsx, hoja Parámetros, X17)
A17: Kilos fritos que salen de un kilo de masa | B17: 0.9 | C17: kg/kg | D17: supuesto declarado | E17: La masa pierde agua al freírse y gana aceite: lo que pesa la pieza frita frente a la masa cruda. Sin fuente pública. | K17: Precio del insumo «Leche» (base imponible), EUR/unidad | L17: =G41 -> 0.85 | M17: Lo copia: libro 2 (calculadora-capex-churreria.xlsx, hoja Parámetros, X17)
A18: Absorción de aceite, en % del peso frito | B18: 0.1 | C18: del peso frito | D18: supuesto declarado | E18: Supuesto, sin fuente pública; pon el tuyo. Aceite que se queda en la pieza, en % de lo que pesa ya frita: pesa una tanda de masa antes y después de freír. | K18: Precio del insumo «Azúcar para espolvorear y sobres» (base imponible), EUR/unidad | L18: =G40 -> 1 | M18: Lo copia: libro 2 (calculadora-capex-churreria.xlsx, hoja Parámetros, X17)
A19: Densidad del aceite | B19: 0.92 | C19: kg/L | D19: supuesto declarado | E19: Supuesto, sin fuente pública; pon el tuyo (lo trae la ficha técnica del aceite). Hace falta porque la absorción va en peso y el aceite se compra por litros. | K19: Precio del insumo «Cacao soluble» (base imponible), EUR/unidad | L19: =G44 -> 6 | M19: Lo copia: libro 2 (calculadora-capex-churreria.xlsx, hoja Parámetros, X17)
A20: Azúcar para espolvorear por cada 100 g de masa vendida | B20: 5 | C20: g/100 g | D20: supuesto declarado | E20: Azúcar para espolvorear, por cada 100 g de masa vendida. | K20: Precio del insumo «Infusión (sobre)» (base imponible), EUR/unidad | L20: =G43 -> 0.06 | M20: Lo copia: libro 2 (calculadora-capex-churreria.xlsx, hoja Parámetros, X17)
A21: Kilos de preparado comercial por kilo de masa | B21: 0.34782609 | C21: kg/kg | D21: CUS-21 | E21: El vendedor declara que cada saco de 4 kg prepara unos 11,5 kg de masa; el resto hasta el kilo es agua, sin coste. | K21: Precio del insumo «Agua (botella de 50 cl)» (base imponible), EUR/unidad | L21: =G46 -> 0.22 | M21: Lo copia: libro 2 (calculadora-capex-churreria.xlsx, hoja Parámetros, X17)
A22: Masa con la que costeas la carta | B22: Preparado comercial | C22: lista | D22: decisión 5 | E22: El Molinete compra el preparado comercial. Cambia a «Mix propio» para ver el escandallo con tu mezcla (hoja «Escandallo por kg de Masa»).
A24: El Vaso para Llevar, Cobrado Aparte
A25: Vaso para llevar (plástico o papel plastificado), cobrado aparte: importe con IVA | B25: 0.1 | C25: EUR/vaso | D25: supuesto declarado | E25: El importe es un supuesto: la ley obliga a cobrarlo aparte, no fija cuánto. Su IVA, el de la bebida, en celda verde. Su IVA es el de «las demás bebidas para llevar» (fila 8).
A27: Umbrales de la Decisión de Surtido (Criterio de la Casa)
A28: Margen mínimo por unidad para no revisar el precio | B28: 0.5 | C28: EUR/unidad | D28: supuesto declarado | E28: Criterio de la casa, no del sector: es el margen en EUROS de la unidad de venta. Un margen alto en porcentaje sobre un churro de 0,30 EUR no paga la renta.
A29: Rotación mínima para no vigilar una referencia | B29: 2 | C29: % del mix | D29: supuesto declarado | E29: Por debajo de este peso en el mix de invierno Y en el de verano, la referencia ocupa carta, stock y cabeza sin vender.
A31: Insumos: La Única Tabla Donde se Tocan los Precios
A32: Insumo | B32: Precio del formato (EUR) | C32: ¿El precio lleva IVA? | D32: Tipo de IVA | E32: Cantidad del formato | F32: Unidad | G32: Precio SIN IVA por unidad (EUR) | H32: Fuente | I32: Base de IVA declarada y nota
A33: Preparado para masa de churro (caja de 6 sacos de 4 kg) | B33: 34.8 | C33: No | D33: ='Parámetros'!$B$11 -> 0.1 | E33: 24 | F33: kg | G33: =IFERROR(IF(C33="Sí",B33/(1+D33),B33)/E33,"") -> 1.45 | H33: CUS-21 | I33: Base de la fuente: sin IVA, declarada en la ficha («Impuestos excluidos»). Precio de una caja de 6 sacos de 4 kg, impuestos excluidos (tienda del proveedor, leída el 03-10-2026). Cada saco prepara unos 11,5 kg de masa.
A34: Aceite especial de fritura (garrafa de 25 L) | B34: 49.9 | C34: No | D34: ='Parámetros'!$B$11 -> 0.1 | E34: 25 | F34: L | G34: =IFERROR(IF(C34="Sí",B34/(1+D34),B34)/E34,"") -> 1.996 | H34: CUS-23 | I34: Base de la fuente: sin IVA, declarada en la ficha («Impuestos excluidos»). El techo de las dos garrafas de la ficha. Es la CELDA ÚNICA del precio del aceite de todo el paquete: vive en el libro 3 y la copian el 4 y el 2.
A35: Chocolate a la taza en polvo (bolsa de 800 g, rinde 4,3 L) | B35: 5.75 | C35: No | D35: ='Parámetros'!$B$11 -> 0.1 | E35: 0.8 | F35: kg | G35: =IFERROR(IF(C35="Sí",B35/(1+D35),B35)/E35,"") -> 7.1875 | H35: CUS-24 | I35: Base de la fuente: sin IVA, declarada en la ficha («Impuestos excluidos»). El techo por kilo de la ficha. La ficha no dice a qué denominación del RD 1055/2003 corresponde: la carta usa la de la etiqueta.
A36: Cobertura de chocolate negro (1 kg) | B36: 6.5 | C36: No | D36: ='Parámetros'!$B$11 -> 0.1 | E36: 1 | F36: kg | G36: =IFERROR(IF(C36="Sí",B36/(1+D36),B36)/E36,"") -> 6.5 | H36: CUS-24 | I36: Base de la fuente: sin IVA, declarada en la ficha («Impuestos excluidos»). Para rellenar y bañar churros.
A37: Cucurucho de cartón para churros (caja de 100) | B37: 15 | C37: No | D37: ='Parámetros'!$B$10 -> 0.21 | E37: 100 | F37: ud | G37: =IFERROR(IF(C37="Sí",B37/(1+D37),B37)/E37,"") -> 0.15 | H37: CUS-25 | I37: Base de la fuente: sin IVA, inferida (celda «¿lleva IVA?» en verde, «no» por defecto). Su composición está por confirmar: no se presenta como conforme a la ley de plásticos.
A38: Harina especial para churros (mix propio) | B38: 0.8 | C38: No | D38: ='Parámetros'!$B$11 -> 0.1 | E38: 1 | F38: kg | G38: =IFERROR(IF(C38="Sí",B38/(1+D38),B38)/E38,"") -> 0.8 | H38: supuesto declarado | I38: Base de la fuente: supuesto, sin IVA. Sólo para la decisión 5: el proveedor verificado no publica precio.
A39: Sal | B39: 0.4 | C39: No | D39: ='Parámetros'!$B$11 -> 0.1 | E39: 1 | F39: kg | G39: =IFERROR(IF(C39="Sí",B39/(1+D39),B39)/E39,"") -> 0.4 | H39: supuesto declarado | I39: Base de la fuente: supuesto, sin IVA. Mix propio.
A40: Azúcar para espolvorear y sobres | B40: 1 | C40: No | D40: ='Parámetros'!$B$11 -> 0.1 | E40: 1 | F40: kg | G40: =IFERROR(IF(C40="Sí",B40/(1+D40),B40)/E40,"") -> 1 | H40: supuesto declarado | I40: Base de la fuente: supuesto, sin IVA. El azúcar glas que publica CUS-25 es otro producto.
A41: Leche | B41: 0.85 | C41: No | D41: ='Parámetros'!$B$11 -> 0.1 | E41: 1 | F41: L | G41: =IFERROR(IF(C41="Sí",B41/(1+D41),B41)/E41,"") -> 0.85 | H41: supuesto declarado | I41: Base de la fuente: supuesto, sin IVA.
A42: Café en grano | B42: 18 | C42: No | D42: ='Parámetros'!$B$11 -> 0.1 | E42: 1 | F42: kg | G42: =IFERROR(IF(C42="Sí",B42/(1+D42),B42)/E42,"") -> 18 | H42: supuesto declarado | I42: Base de la fuente: supuesto, sin IVA. Sin fuente de precio de café en el research.
A43: Infusión (sobre) | B43: 0.06 | C43: No | D43: ='Parámetros'!$B$11 -> 0.1 | E43: 1 | F43: ud | G43: =IFERROR(IF(C43="Sí",B43/(1+D43),B43)/E43,"") -> 0.06 | H43: supuesto declarado | I43: Base de la fuente: supuesto, sin IVA.
A44: Cacao soluble | B44: 6 | C44: No | D44: ='Parámetros'!$B$11 -> 0.1 | E44: 1 | F44: kg | G44: =IFERROR(IF(C44="Sí",B44/(1+D44),B44)/E44,"") -> 6 | H44: supuesto declarado | I44: Base de la fuente: supuesto, sin IVA.
A45: Naranja para zumo | B45: 1.1 | C45: No | D45: ='Parámetros'!$B$11 -> 0.1 | E45: 1 | F45: kg | G45: =IFERROR(IF(C45="Sí",B45/(1+D45),B45)/E45,"") -> 1.1 | H45: supuesto declarado | I45: Base de la fuente: supuesto, sin IVA.
A46: Agua (botella de 50 cl) | B46: 0.22 | C46: No | D46: ='Parámetros'!$B$11 -> 0.1 | E46: 1 | F46: ud | G46: =IFERROR(IF(C46="Sí",B46/(1+D46),B46)/E46,"") -> 0.22 | H46: supuesto declarado | I46: Base de la fuente: supuesto, sin IVA.
A47: Base de granizado (por vaso) | B47: 0.45 | C47: No | D47: ='Parámetros'!$B$11 -> 0.1 | E47: 1 | F47: ud | G47: =IFERROR(IF(C47="Sí",B47/(1+D47),B47)/E47,"") -> 0.45 | H47: supuesto declarado | I47: Base de la fuente: supuesto, sin IVA. Comprada ya preparada.
A48: Horchata a granel | B48: 2.2 | C48: No | D48: ='Parámetros'!$B$11 -> 0.1 | E48: 1 | F48: L | G48: =IFERROR(IF(C48="Sí",B48/(1+D48),B48)/E48,"") -> 2.2 | H48: supuesto declarado | I48: Base de la fuente: supuesto, sin IVA.
A49: Helado (por bola) | B49: 0.45 | C49: No | D49: ='Parámetros'!$B$11 -> 0.1 | E49: 1 | F49: ud | G49: =IFERROR(IF(C49="Sí",B49/(1+D49),B49)/E49,"") -> 0.45 | H49: supuesto declarado | I49: Base de la fuente: supuesto, sin IVA. Comprado a un obrador: El Molinete no fabrica helado.
A50: Sirope (por batido) | B50: 0.05 | C50: No | D50: ='Parámetros'!$B$11 -> 0.1 | E50: 1 | F50: ud | G50: =IFERROR(IF(C50="Sí",B50/(1+D50),B50)/E50,"") -> 0.05 | H50: supuesto declarado | I50: Base de la fuente: supuesto, sin IVA.
A51: Vaso de papel plastificado con tapa | B51: 0.08 | C51: No | D51: ='Parámetros'!$B$10 -> 0.21 | E51: 1 | F51: ud | G51: =IFERROR(IF(C51="Sí",B51/(1+D51),B51)/E51,"") -> 0.08 | H51: supuesto declarado | I51: Base de la fuente: supuesto, sin IVA. Lleva plástico: se cobra aparte (CUN-41).
A52: Papel antigrasa para sueltos | B52: 0.02 | C52: No | D52: ='Parámetros'!$B$10 -> 0.21 | E52: 1 | F52: ud | G52: =IFERROR(IF(C52="Sí",B52/(1+D52),B52)/E52,"") -> 0.02 | H52: supuesto declarado | I52: Base de la fuente: supuesto, sin IVA.
A53: Caja de cartón para el kilo | B53: 0.25 | C53: No | D53: ='Parámetros'!$B$10 -> 0.21 | E53: 1 | F53: ud | G53: =IFERROR(IF(C53="Sí",B53/(1+D53),B53)/E53,"") -> 0.25 | H53: supuesto declarado | I53: Base de la fuente: supuesto, sin IVA.
A56: Listas de validación (no las borres: las usan los desplegables)
A57: Sí o no | B57: Masa
A58: Sí | B58: Preparado comercial
A59: No | B59: Mix propio
A62: Versión 1.0 · octubre 2026 · aichef.pro/guia-churreria-chocolateria · info@aichef.pro

Sheet Escandallo por kg de Masa
A1: Escandallo por kg de Masa
A2: AI Chef Pro · aichef.pro — Cómo Montar una Churrería-Chocolatería
A3: Datos de ejemplo para que las fórmulas calculen: las cantidades no son una receta. Todos los precios, SIN IVA, de la tabla de insumos de «Parámetros».
A5: 1. Un Kilo de Masa con el Preparado Comercial
A6: Concepto | B6: Cantidad por kg de masa | C6: Unidad | D6: Precio SIN IVA por unidad (EUR) | E6: Importe (EUR) | F6: Fuente
A7: Preparado para masa de churro (caja de 6 sacos de 4 kg) | B7: ='Parámetros'!$B$21 -> 0.34782609 | C7: kg | D7: ='Parámetros'!$G$33 -> 1.45 | E7: =IFERROR(B7*D7,"") -> 0.50434783 | F7: CUS-21
A8: Agua (sin coste) | B8: =1-B7 -> 0.65217391 | C8: L | D8: sin coste | F8: calculado
A9: COSTE DE 1 KG DE MASA CON EL PREPARADO (EUR) | E9: =SUM(E7:E8) -> 0.50434783
A11: 2. Un Kilo de Masa con Mix Propio (Decisión 5)
A12: Concepto | B12: Cantidad por kg de masa | C12: Unidad | D12: Precio SIN IVA por unidad (EUR) | E12: Importe (EUR) | F12: Fuente
A13: Harina especial para churros (mix propio) | B13: 0.45 | C13: kg | D13: ='Parámetros'!$G$38 -> 0.8 | E13: =IFERROR(B13*D13,"") -> 0.36 | F13: supuesto declarado | G13: Proporciones de EJEMPLO para que la comparación calcule, no una receta. El ahorro del mix propio se paga con pesar, tamizar y con la regularidad de la masa.
A14: Sal | B14: 0.008 | C14: kg | D14: ='Parámetros'!$G$39 -> 0.4 | E14: =IFERROR(B14*D14,"") -> 0.0032 | F14: supuesto declarado
A15: Agua (sin coste) | B15: =1-SUM(B13:B14) -> 0.542 | C15: L | D15: sin coste | F15: calculado
A16: COSTE DE 1 KG DE MASA CON MIX PROPIO (EUR) | E16: =SUM(E13:E15) -> 0.3632
A18: Ahorro del mix propio por kg de masa (EUR) | B18: =E9-E16 -> 0.14114783
A19: COSTE DEL KG DE MASA CON EL QUE COSTEAS (EUR) | B19: =IF('Parámetros'!$B$22="Mix propio",E16,E9) -> 0.50434783
A20: Masa elegida en «Parámetros» | B20: ='Parámetros'!$B$22 -> Preparado comercial
A22: 3. La Pieza: Churro y Porra
A23: Concepto | B23: Churro | C23: Porra
A24: Gramos de masa por pieza (lo que se vende) | B24: ='Parámetros'!$B$14 -> 20 | C24: ='Parámetros'!$B$15 -> 60
A25: Gramos de masa que hay que freír por pieza (con la merma) | B25: =IFERROR(B24/(1-'Parámetros'!$B$16),"") -> 21.052632 | C25: =IFERROR(C24/(1-'Parámetros'!$B$16),"") -> 63.157895
A26: Piezas por kilo de masa vendida | B26: =IFERROR(1000/B24,"") -> 50 | C26: =IFERROR(1000/C24,"") -> 16.666667
A27: Coste de la masa por pieza (EUR) | B27: =IFERROR(B25/1000*$B$19,"") -> 0.010617849 | C27: =IFERROR(C25/1000*$B$19,"") -> 0.031853547
A28: Aceite absorbido por pieza (EUR) | B28: =IFERROR(B25/1000*'Absorción de Aceite y Merma'!$B$11,"") -> 0.0041107551 | C28: =IFERROR(C25/1000*'Absorción de Aceite y Merma'!$B$11,"") -> 0.012332265
A29: Azúcar de espolvorear por pieza (EUR) | B29: =IFERROR(B24/1000*'Parámetros'!$B$20/100*'Parámetros'!$G$40,"") -> 0.001 | C29: =IFERROR(C24/1000*'Parámetros'!$B$20/100*'Parámetros'!$G$40,"") -> 0.003
A30: COSTE DE MATERIA DE LA PIEZA (EUR) | B30: =SUM(B27:B29) -> 0.015728604 | C30: =SUM(C27:C29) -> 0.047185812
A31: Coste de materia de una docena (EUR) | B31: =IFERROR(B30*12,"") -> 0.18874325 | C31: =IFERROR(C30*12,"") -> 0.56622975
A33: 4. De la Masa a Cada Referencia de la Carta
A34: Id y referencia | B34: Familia | C34: Piezas de la unidad | D34: Tipo de pieza | E34: Kilos fritos (sólo si se vende al peso) | F34: Masa vendida (kg) | G34: Masa que se fríe, con merma (kg) | H34: Coste de la masa (EUR) | I34: Azúcar (EUR) | J34: Receta, sin envase (EUR) | K34: Envase para llevar (EUR) | L34: Aceite absorbido (EUR) | M34: MATERIA EN SALA, aceite incluido (EUR) | N34: MATERIA PARA LLEVAR, aceite y envase incluidos (EUR)
A35: CH1 · Ración de churros (6 uds) | B35: Churros y porras | C35: 6 | D35: churro | E35: 0 | F35: =IF(E35>0,IFERROR(E35/'Parámetros'!$B$17,""),IFERROR(C35*IF(D35="porra",'Parámetros'!$B$15,IF(D35="churro",'Parámetros'!$B$14,0))/1000,"")) -> 0.12 | G35: =IFERROR(F35/(1-'Parámetros'!$B$16),"") -> 0.12631579 | H35: =IFERROR(G35*$B$19,"") -> 0.063707094 | I35: =IFERROR(F35*'Parámetros'!$B$20/100*'Parámetros'!$G$40,"") -> 0.006 | J35: =SUMIF($A$63:$A$100,"CH1",$I$63:$I$100) -> 0 | K35: =SUMIF($A$63:$A$100,"CH1",$J$63:$J$100) -> 0.15 | L35: =IFERROR(G35*'Absorción de Aceite y Merma'!$B$11,"") -> 0.024664531 | M35: =IFERROR(H35+I35+J35+L35,"") -> 0.094371625 | N35: =IFERROR(M35+K35,"") -> 0.24437162
A36: CH2 · Media ración de churros (3 uds) | B36: Churros y porras | C36: 3 | D36: churro | E36: 0 | F36: =IF(E36>0,IFERROR(E36/'Parámetros'!$B$17,""),IFERROR(C36*IF(D36="porra",'Parámetros'!$B$15,IF(D36="churro",'Parámetros'!$B$14,0))/1000,"")) -> 0.06 | G36: =IFERROR(F36/(1-'Parámetros'!$B$16),"") -> 0.063157895 | H36: =IFERROR(G36*$B$19,"") -> 0.031853547 | I36: =IFERROR(F36*'Parámetros'!$B$20/100*'Parámetros'!$G$40,"") -> 0.003 | J36: =SUMIF($A$63:$A$100,"CH2",$I$63:$I$100) -> 0 | K36: =SUMIF($A$63:$A$100,"CH2",$J$63:$J$100) -> 0 | L36: =IFERROR(G36*'Absorción de Aceite y Merma'!$B$11,"") -> 0.012332265 | M36: =IFERROR(H36+I36+J36+L36,"") -> 0.047185812 | N36: =IFERROR(M36+K36,"") -> 0.047185812
A37: CH3 · Ración de porras (3 uds) | B37: Churros y porras | C37: 3 | D37: porra | E37: 0 | F37: =IF(E37>0,IFERROR(E37/'Parámetros'!$B$17,""),IFERROR(C37*IF(D37="porra",'Parámetros'!$B$15,IF(D37="churro",'Parámetros'!$B$14,0))/1000,"")) -> 0.18 | G37: =IFERROR(F37/(1-'Parámetros'!$B$16),"") -> 0.18947368 | H37: =IFERROR(G37*$B$19,"") -> 0.095560641 | I37: =IFERROR(F37*'Parámetros'!$B$20/100*'Parámetros'!$G$40,"") -> 0.009 | J37: =SUMIF($A$63:$A$100,"CH3",$I$63:$I$100) -> 0 | K37: =SUMIF($A$63:$A$100,"CH3",$J$63:$J$100) -> 0.15 | L37: =IFERROR(G37*'Absorción de Aceite y Merma'!$B$11,"") -> 0.036996796 | M37: =IFERROR(H37+I37+J37+L37,"") -> 0.14155744 | N37: =IFERROR(M37+K37,"") -> 0.29155744
A38: CH4 · Churro suelto | B38: Churros y porras | C38: 1 | D38: churro | E38: 0 | F38: =IF(E38>0,IFERROR(E38/'Parámetros'!$B$17,""),IFERROR(C38*IF(D38="porra",'Parámetros'!$B$15,IF(D38="churro",'Parámetros'!$B$14,0))/1000,"")) -> 0.02 | G38: =IFERROR(F38/(1-'Parámetros'!$B$16),"") -> 0.021052632 | H38: =IFERROR(G38*$B$19,"") -> 0.010617849 | I38: =IFERROR(F38*'Parámetros'!$B$20/100*'Parámetros'!$G$40,"") -> 0.001 | J38: =SUMIF($A$63:$A$100,"CH4",$I$63:$I$100) -> 0 | K38: =SUMIF($A$63:$A$100,"CH4",$J$63:$J$100) -> 0.02 | L38: =IFERROR(G38*'Absorción de Aceite y Merma'!$B$11,"") -> 0.0041107551 | M38: =IFERROR(H38+I38+J38+L38,"") -> 0.015728604 | N38: =IFERROR(M38+K38,"") -> 0.035728604
A39: CH5 · Porra suelta | B39: Churros y porras | C39: 1 | D39: porra | E39: 0 | F39: =IF(E39>0,IFERROR(E39/'Parámetros'!$B$17,""),IFERROR(C39*IF(D39="porra",'Parámetros'!$B$15,IF(D39="churro",'Parámetros'!$B$14,0))/1000,"")) -> 0.06 | G39: =IFERROR(F39/(1-'Parámetros'!$B$16),"") -> 0.063157895 | H39: =IFERROR(G39*$B$19,"") -> 0.031853547 | I39: =IFERROR(F39*'Parámetros'!$B$20/100*'Parámetros'!$G$40,"") -> 0.003 | J39: =SUMIF($A$63:$A$100,"CH5",$I$63:$I$100) -> 0 | K39: =SUMIF($A$63:$A$100,"CH5",$J$63:$J$100) -> 0.02 | L39: =IFERROR(G39*'Absorción de Aceite y Merma'!$B$11,"") -> 0.012332265 | M39: =IFERROR(H39+I39+J39+L39,"") -> 0.047185812 | N39: =IFERROR(M39+K39,"") -> 0.067185812
A40: CH6 · Docena de churros para llevar | B40: Churros y porras | C40: 12 | D40: churro | E40: 0 | F40: =IF(E40>0,IFERROR(E40/'Parámetros'!$B$17,""),IFERROR(C40*IF(D40="porra",'Parámetros'!$B$15,IF(D40="churro",'Parámetros'!$B$14,0))/1000,"")) -> 0.24 | G40: =IFERROR(F40/(1-'Parámetros'!$B$16),"") -> 0.25263158 | H40: =IFERROR(G40*$B$19,"") -> 0.12741419 | I40: =IFERROR(F40*'Parámetros'!$B$20/100*'Parámetros'!$G$40,"") -> 0.012 | J40: =SUMIF($A$63:$A$100,"CH6",$I$63:$I$100) -> 0 | K40: =SUMIF($A$63:$A$100,"CH6",$J$63:$J$100) -> 0.15 | L40: =IFERROR(G40*'Absorción de Aceite y Merma'!$B$11,"") -> 0.049329062 | M40: =IFERROR(H40+I40+J40+L40,"") -> 0.18874325 | N40: =IFERROR(M40+K40,"") -> 0.33874325
A41: CH7 · Kilo de churros para llevar | B41: Churros y porras | C41: 0 | D41: churro | E41: 1 | F41: =IF(E41>0,IFERROR(E41/'Parámetros'!$B$17,""),IFERROR(C41*IF(D41="porra",'Parámetros'!$B$15,IF(D41="churro",'Parámetros'!$B$14,0))/1000,"")) -> 1.1111111 | G41: =IFERROR(F41/(1-'Parámetros'!$B$16),"") -> 1.1695906 | H41: =IFERROR(G41*$B$19,"") -> 0.5898805 | I41: =IFERROR(F41*'Parámetros'!$B$20/100*'Parámetros'!$G$40,"") -> 0.055555556 | J41: =SUMIF($A$63:$A$100,"CH7",$I$63:$I$100) -> 0 | K41: =SUMIF($A$63:$A$100,"CH7",$J$63:$J$100) -> 0.25 | L41: =IFERROR(G41*'Absorción de Aceite y Merma'!$B$11,"") -> 0.22837529 | M41: =IFERROR(H41+I41+J41+L41,"") -> 0.87381134 | N41: =IFERROR(M41+K41,"") -> 1.1238113
A42: RE1 · Churro relleno de chocolate (ud) | B42: Rellenos y especiales | C42: 1 | D42: porra | E42: 0 | F42: =IF(E42>0,IFERROR(E42/'Parámetros'!$B$17,""),IFERROR(C42*IF(D42="porra",'Parámetros'!$B$15,IF(D42="churro",'Parámetros'!$B$14,0))/1000,"")) -> 0.06 | G42: =IFERROR(F42/(1-'Parámetros'!$B$16),"") -> 0.063157895 | H42: =IFERROR(G42*$B$19,"") -> 0.031853547 | I42: =IFERROR(F42*'Parámetros'!$B$20/100*'Parámetros'!$G$40,"") -> 0.003 | J42: =SUMIF($A$63:$A$100,"RE1",$I$63:$I$100) -> 0.13 | K42: =SUMIF($A$63:$A$100,"RE1",$J$63:$J$100) -> 0 | L42: =IFERROR(G42*'Absorción de Aceite y Merma'!$B$11,"") -> 0.012332265 | M42: =IFERROR(H42+I42+J42+L42,"") -> 0.17718581 | N42: =IFERROR(M42+K42,"") -> 0.17718581
A43: RE2 · Ración de churros con cobertura de chocolate (6 uds) | B43: Rellenos y especiales | C43: 6 | D43: churro | E43: 0 | F43: =IF(E43>0,IFERROR(E43/'Parámetros'!$B$17,""),IFERROR(C43*IF(D43="porra",'Parámetros'!$B$15,IF(D43="churro",'Parámetros'!$B$14,0))/1000,"")) -> 0.12 | G43: =IFERROR(F43/(1-'Parámetros'!$B$16),"") -> 0.12631579 | H43: =IFERROR(G43*$B$19,"") -> 0.063707094 | I43: =IFERROR(F43*'Parámetros'!$B$20/100*'Parámetros'!$G$40,"") -> 0.006 | J43: =SUMIF($A$63:$A$100,"RE2",$I$63:$I$100) -> 0.195 | K43: =SUMIF($A$63:$A$100,"RE2",$J$63:$J$100) -> 0 | L43: =IFERROR(G43*'Absorción de Aceite y Merma'!$B$11,"") -> 0.024664531 | M43: =IFERROR(H43+I43+J43+L43,"") -> 0.28937162 | N43: =IFERROR(M43+K43,"") -> 0.28937162
A44: CT1 · Chocolate a la taza en barra | B44: Chocolate a la taza | C44: 0 | D44: sin masa | E44: 0 | F44: =IF(E44>0,IFERROR(E44/'Parámetros'!$B$17,""),IFERROR(C44*IF(D44="porra",'Parámetros'!$B$15,IF(D44="churro",'Parámetros'!$B$14,0))/1000,"")) -> 0 | G44: =IFERROR(F44/(1-'Parámetros'!$B$16),"") -> 0 | H44: =IFERROR(G44*$B$19,"") -> 0 | I44: =IFERROR(F44*'Parámetros'!$B$20/100*'Parámetros'!$G$40,"") -> 0 | J44: =SUMIF($A$63:$A$100,"CT1",$I$63:$I$100) -> 0.43744186 | K44: =SUMIF($A$63:$A$100,"CT1",$J$63:$J$100) -> 0 | L44: =IFERROR(G44*'Absorción de Aceite y Merma'!$B$11,"") -> 0 | M44: =IFERROR(H44+I44+J44+L44,"") -> 0.43744186 | N44: =IFERROR(M44+K44,"") -> 0.43744186
A45: CT2 · Chocolate a la taza en terraza | B45: Chocolate a la taza | C45: 0 | D45: sin masa | E45: 0 | F45: =IF(E45>0,IFERROR(E45/'Parámetros'!$B$17,""),IFERROR(C45*IF(D45="porra",'Parámetros'!$B$15,IF(D45="churro",'Parámetros'!$B$14,0))/1000,"")) -> 0 | G45: =IFERROR(F45/(1-'Parámetros'!$B$16),"") -> 0 | H45: =IFERROR(G45*$B$19,"") -> 0 | I45: =IFERROR(F45*'Parámetros'!$B$20/100*'Parámetros'!$G$40,"") -> 0 | J45: =SUMIF($A$63:$A$100,"CT2",$I$63:$I$100) -> 0.43744186 | K45: =SUMIF($A$63:$A$100,"CT2",$J$63:$J$100) -> 0 | L45: =IFERROR(G45*'Absorción de Aceite y Merma'!$B$11,"") -> 0 | M45: =IFERROR(H45+I45+J45+L45,"") -> 0.43744186 | N45: =IFERROR(M45+K45,"") -> 0.43744186
A46: CT3 · Chocolate con churros (taza y ración de 6) | B46: Chocolate a la taza | C46: 6 | D46: churro | E46: 0 | F46: =IF(E46>0,IFERROR(E46/'Parámetros'!$B$17,""),IFERROR(C46*IF(D46="porra",'Parámetros'!$B$15,IF(D46="churro",'Parámetros'!$B$14,0))/1000,"")) -> 0.12 | G46: =IFERROR(F46/(1-'Parámetros'!$B$16),"") -> 0.12631579 | H46: =IFERROR(G46*$B$19,"") -> 0.063707094 | I46: =IFERROR(F46*'Parámetros'!$B$20/100*'Parámetros'!$G$40,"") -> 0.006 | J46: =SUMIF($A$63:$A$100,"CT3",$I$63:$I$100) -> 0.43744186 | K46: =SUMIF($A$63:$A$100,"CT3",$J$63:$J$100) -> 0 | L46: =IFERROR(G46*'Absorción de Aceite y Merma'!$B$11,"") -> 0.024664531 | M46: =IFERROR(H46+I46+J46+L46,"") -> 0.53181349 | N46: =IFERROR(M46+K46,"") -> 0.53181349
A47: CT4 · Chocolate a la taza para llevar | B47: Chocolate a la taza | C47: 0 | D47: sin masa | E47: 0 | F47: =IF(E47>0,IFERROR(E47/'Parámetros'!$B$17,""),IFERROR(C47*IF(D47="porra",'Parámetros'!$B$15,IF(D47="churro",'Parámetros'!$B$14,0))/1000,"")) -> 0 | G47: =IFERROR(F47/(1-'Parámetros'!$B$16),"") -> 0 | H47: =IFERROR(G47*$B$19,"") -> 0 | I47: =IFERROR(F47*'Parámetros'!$B$20/100*'Parámetros'!$G$40,"") -> 0 | J47: =SUMIF($A$63:$A$100,"CT4",$I$63:$I$100) -> 0.43744186 | K47: =SUMIF($A$63:$A$100,"CT4",$J$63:$J$100) -> 0.08 | L47: =IFERROR(G47*'Absorción de Aceite y Merma'!$B$11,"") -> 0 | M47: =IFERROR(H47+I47+J47+L47,"") -> 0.43744186 | N47: =IFERROR(M47+K47,"") -> 0.51744186
A48: CT5 · Media taza de chocolate | B48: Chocolate a la taza | C48: 0 | D48: sin masa | E48: 0 | F48: =IF(E48>0,IFERROR(E48/'Parámetros'!$B$17,""),IFERROR(C48*IF(D48="porra",'Parámetros'!$B$15,IF(D48="churro",'Parámetros'!$B$14,0))/1000,"")) -> 0 | G48: =IFERROR(F48/(1-'Parámetros'!$B$16),"") -> 0 | H48: =IFERROR(G48*$B$19,"") -> 0 | I48: =IFERROR(F48*'Parámetros'!$B$20/100*'Parámetros'!$G$40,"") -> 0 | J48: =SUMIF($A$63:$A$100,"CT5",$I$63:$I$100) -> 0.26246512 | K48: =SUMIF($A$63:$A$100,"CT5",$J$63:$J$100) -> 0 | L48: =IFERROR(G48*'Absorción de Aceite y Merma'!$B$11,"") -> 0 | M48: =IFERROR(H48+I48+J48+L48,"") -> 0.26246512 | N48: =IFERROR(M48+K48,"") -> 0.26246512
A49: CB1 · Café solo | B49: Cafés y bebidas | C49: 0 | D49: sin masa | E49: 0 | F49: =IF(E49>0,IFERROR(E49/'Parámetros'!$B$17,""),IFERROR(C49*IF(D49="porra",'Parámetros'!$B$15,IF(D49="churro",'Parámetros'!$B$14,0))/1000,"")) -> 0 | G49: =IFERROR(F49/(1-'Parámetros'!$B$16),"") -> 0 | H49: =IFERROR(G49*$B$19,"") -> 0 | I49: =IFERROR(F49*'Parámetros'!$B$20/100*'Parámetros'!$G$40,"") -> 0 | J49: =SUMIF($A$63:$A$100,"CB1",$I$63:$I$100) -> 0.134 | K49: =SUMIF($A$63:$A$100,"CB1",$J$63:$J$100) -> 0.08 | L49: =IFERROR(G49*'Absorción de Aceite y Merma'!$B$11,"") -> 0 | M49: =IFERROR(H49+I49+J49+L49,"") -> 0.134 | N49: =IFERROR(M49+K49,"") -> 0.214
A50: CB2 · Café con leche | B50: Cafés y bebidas | C50: 0 | D50: sin masa | E50: 0 | F50: =IF(E50>0,IFERROR(E50/'Parámetros'!$B$17,""),IFERROR(C50*IF(D50="porra",'Parámetros'!$B$15,IF(D50="churro",'Parámetros'!$B$14,0))/1000,"")) -> 0 | G50: =IFERROR(F50/(1-'Parámetros'!$B$16),"") -> 0 | H50: =IFERROR(G50*$B$19,"") -> 0 | I50: =IFERROR(F50*'Parámetros'!$B$20/100*'Parámetros'!$G$40,"") -> 0 | J50: =SUMIF($A$63:$A$100,"CB2",$I$63:$I$100) -> 0.2615 | K50: =SUMIF($A$63:$A$100,"CB2",$J$63:$J$100) -> 0.08 | L50: =IFERROR(G50*'Absorción de Aceite y Merma'!$B$11,"") -> 0 | M50: =IFERROR(H50+I50+J50+L50,"") -> 0.2615 | N50: =IFERROR(M50+K50,"") -> 0.3415
A51: CB3 · Infusión | B51: Cafés y bebidas | C51: 0 | D51: sin masa | E51: 0 | F51: =IF(E51>0,IFERROR(E51/'Parámetros'!$B$17,""),IFERROR(C51*IF(D51="porra",'Parámetros'!$B$15,IF(D51="churro",'Parámetros'!$B$14,0))/1000,"")) -> 0 | G51: =IFERROR(F51/(1-'Parámetros'!$B$16),"") -> 0 | H51: =IFERROR(G51*$B$19,"") -> 0 | I51: =IFERROR(F51*'Parámetros'!$B$20/100*'Parámetros'!$G$40,"") -> 0 | J51: =SUMIF($A$63:$A$100,"CB3",$I$63:$I$100) -> 0.068 | K51: =SUMIF($A$63:$A$100,"CB3",$J$63:$J$100) -> 0 | L51: =IFERROR(G51*'Absorción de Aceite y Merma'!$B$11,"") -> 0 | M51: =IFERROR(H51+I51+J51+L51,"") -> 0.068 | N51: =IFERROR(M51+K51,"") -> 0.068
A52: CB4 · Leche con cacao | B52: Cafés y bebidas | C52: 0 | D52: sin masa | E52: 0 | F52: =IF(E52>0,IFERROR(E52/'Parámetros'!$B$17,""),IFERROR(C52*IF(D52="porra",'Parámetros'!$B$15,IF(D52="churro",'Parámetros'!$B$14,0))/1000,"")) -> 0 | G52: =IFERROR(F52/(1-'Parámetros'!$B$16),"") -> 0 | H52: =IFERROR(G52*$B$19,"") -> 0 | I52: =IFERROR(F52*'Parámetros'!$B$20/100*'Parámetros'!$G$40,"") -> 0 | J52: =SUMIF($A$63:$A$100,"CB4",$I$63:$I$100) -> 0.26 | K52: =SUMIF($A$63:$A$100,"CB4",$J$63:$J$100) -> 0.08 | L52: =IFERROR(G52*'Absorción de Aceite y Merma'!$B$11,"") -> 0 | M52: =IFERROR(H52+I52+J52+L52,"") -> 0.26 | N52: =IFERROR(M52+K52,"") -> 0.34
A53: CB5 · Zumo de naranja natural | B53: Cafés y bebidas | C53: 0 | D53: sin masa | E53: 0 | F53: =IF(E53>0,IFERROR(E53/'Parámetros'!$B$17,""),IFERROR(C53*IF(D53="porra",'Parámetros'!$B$15,IF(D53="churro",'Parámetros'!$B$14,0))/1000,"")) -> 0 | G53: =IFERROR(F53/(1-'Parámetros'!$B$16),"") -> 0 | H53: =IFERROR(G53*$B$19,"") -> 0 | I53: =IFERROR(F53*'Parámetros'!$B$20/100*'Parámetros'!$G$40,"") -> 0 | J53: =SUMIF($A$63:$A$100,"CB5",$I$63:$I$100) -> 0.495 | K53: =SUMIF($A$63:$A$100,"CB5",$J$63:$J$100) -> 0.08 | L53: =IFERROR(G53*'Absorción de Aceite y Merma'!$B$11,"") -> 0 | M53: =IFERROR(H53+I53+J53+L53,"") -> 0.495 | N53: =IFERROR(M53+K53,"") -> 0.575
A54: CB6 · Agua (botella de 50 cl) | B54: Cafés y bebidas | C54: 0 | D54: sin masa | E54: 0 | F54: =IF(E54>0,IFERROR(E54/'Parámetros'!$B$17,""),IFERROR(C54*IF(D54="porra",'Parámetros'!$B$15,IF(D54="churro",'Parámetros'!$B$14,0))/1000,"")) -> 0 | G54: =IFERROR(F54/(1-'Parámetros'!$B$16),"") -> 0 | H54: =IFERROR(G54*$B$19,"") -> 0 | I54: =IFERROR(F54*'Parámetros'!$B$20/100*'Parámetros'!$G$40,"") -> 0 | J54: =SUMIF($A$63:$A$100,"CB6",$I$63:$I$100) -> 0.22 | K54: =SUMIF($A$63:$A$100,"CB6",$J$63:$J$100) -> 0 | L54: =IFERROR(G54*'Absorción de Aceite y Merma'!$B$11,"") -> 0 | M54: =IFERROR(H54+I54+J54+L54,"") -> 0.22 | N54: =IFERROR(M54+K54,"") -> 0.22
A55: CV1 · Granizado | B55: Carta de verano | C55: 0 | D55: sin masa | E55: 0 | F55: =IF(E55>0,IFERROR(E55/'Parámetros'!$B$17,""),IFERROR(C55*IF(D55="porra",'Parámetros'!$B$15,IF(D55="churro",'Parámetros'!$B$14,0))/1000,"")) -> 0 | G55: =IFERROR(F55/(1-'Parámetros'!$B$16),"") -> 0 | H55: =IFERROR(G55*$B$19,"") -> 0 | I55: =IFERROR(F55*'Parámetros'!$B$20/100*'Parámetros'!$G$40,"") -> 0 | J55: =SUMIF($A$63:$A$100,"CV1",$I$63:$I$100) -> 0.45 | K55: =SUMIF($A$63:$A$100,"CV1",$J$63:$J$100) -> 0.08 | L55: =IFERROR(G55*'Absorción de Aceite y Merma'!$B$11,"") -> 0 | M55: =IFERROR(H55+I55+J55+L55,"") -> 0.45 | N55: =IFERROR(M55+K55,"") -> 0.53
A56: CV2 · Horchata | B56: Carta de verano | C56: 0 | D56: sin masa | E56: 0 | F56: =IF(E56>0,IFERROR(E56/'Parámetros'!$B$17,""),IFERROR(C56*IF(D56="porra",'Parámetros'!$B$15,IF(D56="churro",'Parámetros'!$B$14,0))/1000,"")) -> 0 | G56: =IFERROR(F56/(1-'Parámetros'!$B$16),"") -> 0 | H56: =IFERROR(G56*$B$19,"") -> 0 | I56: =IFERROR(F56*'Parámetros'!$B$20/100*'Parámetros'!$G$40,"") -> 0 | J56: =SUMIF($A$63:$A$100,"CV2",$I$63:$I$100) -> 0.55 | K56: =SUMIF($A$63:$A$100,"CV2",$J$63:$J$100) -> 0.08 | L56: =IFERROR(G56*'Absorción de Aceite y Merma'!$B$11,"") -> 0 | M56: =IFERROR(H56+I56+J56+L56,"") -> 0.55 | N56: =IFERROR(M56+K56,"") -> 0.63
A57: CV3 · Helado (bola) | B57: Carta de verano | C57: 0 | D57: sin masa | E57: 0 | F57: =IF(E57>0,IFERROR(E57/'Parámetros'!$B$17,""),IFERROR(C57*IF(D57="porra",'Parámetros'!$B$15,IF(D57="churro",'Parámetros'!$B$14,0))/1000,"")) -> 0 | G57: =IFERROR(F57/(1-'Parámetros'!$B$16),"") -> 0 | H57: =IFERROR(G57*$B$19,"") -> 0 | I57: =IFERROR(F57*'Parámetros'!$B$20/100*'Parámetros'!$G$40,"") -> 0 | J57: =SUMIF($A$63:$A$100,"CV3",$I$63:$I$100) -> 0.45 | K57: =SUMIF($A$63:$A$100,"CV3",$J$63:$J$100) -> 0 | L57: =IFERROR(G57*'Absorción de Aceite y Merma'!$B$11,"") -> 0 | M57: =IFERROR(H57+I57+J57+L57,"") -> 0.45 | N57: =IFERROR(M57+K57,"") -> 0.45
A58: CV4 · Batido | B58: Carta de verano | C58: 0 | D58: sin masa | E58: 0 | F58: =IF(E58>0,IFERROR(E58/'Parámetros'!$B$17,""),IFERROR(C58*IF(D58="porra",'Parámetros'!$B$15,IF(D58="churro",'Parámetros'!$B$14,0))/1000,"")) -> 0 | G58: =IFERROR(F58/(1-'Parámetros'!$B$16),"") -> 0 | H58: =IFERROR(G58*$B$19,"") -> 0 | I58: =IFERROR(F58*'Parámetros'!$B$20/100*'Parámetros'!$G$40,"") -> 0 | J58: =SUMIF($A$63:$A$100,"CV4",$I$63:$I$100) -> 0.7125 | K58: =SUMIF($A$63:$A$100,"CV4",$J$63:$J$100) -> 0.08 | L58: =IFERROR(G58*'Absorción de Aceite y Merma'!$B$11,"") -> 0 | M58: =IFERROR(H58+I58+J58+L58,"") -> 0.7125 | N58: =IFERROR(M58+K58,"") -> 0.7925
A61: 5. Receta y Envase de Cada Referencia | F61: Una línea por insumo. El envase sólo cuenta cuando la referencia se vende para llevar. El chocolate entra por taza o media taza, con el coste de la hoja «Chocolate a la Taza».
A62: Id | B62: Referencia | C62: Insumo | D62: Cantidad por unidad vendida | E62: Unidad | F62: Cuándo cuenta | G62: Precio SIN IVA por unidad (EUR) | H62: Importe (EUR) | I62: Cuenta siempre (EUR) | J62: Cuenta sólo para llevar (EUR)
A63: CH1 | B63: Ración de churros (6 uds) | C63: Cucurucho de cartón para churros (caja de 100) | D63: 1 | E63: =IF(OR(C63="Taza de chocolate",C63="Media taza de chocolate"),"ud",IFERROR(INDEX('Parámetros'!$F$33:$F$53,MATCH(C63,'Parámetros'!$A$33:$A$53,0)),"")) -> ud | F63: Sólo para llevar | G63: =IF(C63="Taza de chocolate",'Chocolate a la Taza'!$B$15,IF(C63="Media taza de chocolate",'Chocolate a la Taza'!$B$16,IFERROR(INDEX('Parámetros'!$G$33:$G$53,MATCH(C63,'Parámetros'!$A$33:$A$53,0)),""))) -> 0.15 | H63: =IFERROR(D63*G63,"") -> 0.15 | I63: =IF(F63="Siempre",H63,0) -> 0 | J63: =IF(F63="Sólo para llevar",H63,0) -> 0.15
A64: CH3 | B64: Ración de porras (3 uds) | C64: Cucurucho de cartón para churros (caja de 100) | D64: 1 | E64: =IF(OR(C64="Taza de chocolate",C64="Media taza de chocolate"),"ud",IFERROR(INDEX('Parámetros'!$F$33:$F$53,MATCH(C64,'Parámetros'!$A$33:$A$53,0)),"")) -> ud | F64: Sólo para llevar | G64: =IF(C64="Taza de chocolate",'Chocolate a la Taza'!$B$15,IF(C64="Media taza de chocolate",'Chocolate a la Taza'!$B$16,IFERROR(INDEX('Parámetros'!$G$33:$G$53,MATCH(C64,'Parámetros'!$A$33:$A$53,0)),""))) -> 0.15 | H64: =IFERROR(D64*G64,"") -> 0.15 | I64: =IF(F64="Siempre",H64,0) -> 0 | J64: =IF(F64="Sólo para llevar",H64,0) -> 0.15
A65: CH4 | B65: Churro suelto | C65: Papel antigrasa para sueltos | D65: 1 | E65: =IF(OR(C65="Taza de chocolate",C65="Media taza de chocolate"),"ud",IFERROR(INDEX('Parámetros'!$F$33:$F$53,MATCH(C65,'Parámetros'!$A$33:$A$53,0)),"")) -> ud | F65: Sólo para llevar | G65: =IF(C65="Taza de chocolate",'Chocolate a la Taza'!$B$15,IF(C65="Media taza de chocolate",'Chocolate a la Taza'!$B$16,IFERROR(INDEX('Parámetros'!$G$33:$G$53,MATCH(C65,'Parámetros'!$A$33:$A$53,0)),""))) -> 0.02 | H65: =IFERROR(D65*G65,"") -> 0.02 | I65: =IF(F65="Siempre",H65,0) -> 0 | J65: =IF(F65="Sólo para llevar",H65,0) -> 0.02
A66: CH5 | B66: Porra suelta | C66: Papel antigrasa para sueltos | D66: 1 | E66: =IF(OR(C66="Taza de chocolate",C66="Media taza de chocolate"),"ud",IFERROR(INDEX('Parámetros'!$F$33:$F$53,MATCH(C66,'Parámetros'!$A$33:$A$53,0)),"")) -> ud | F66: Sólo para llevar | G66: =IF(C66="Taza de chocolate",'Chocolate a la Taza'!$B$15,IF(C66="Media taza de chocolate",'Chocolate a la Taza'!$B$16,IFERROR(INDEX('Parámetros'!$G$33:$G$53,MATCH(C66,'Parámetros'!$A$33:$A$53,0)),""))) -> 0.02 | H66: =IFERROR(D66*G66,"") -> 0.02 | I66: =IF(F66="Siempre",H66,0) -> 0 | J66: =IF(F66="Sólo para llevar",H66,0) -> 0.02
A67: CH6 | B67: Docena de churros para llevar | C67: Cucurucho de cartón para churros (caja de 100) | D67: 1 | E67: =IF(OR(C67="Taza de chocolate",C67="Media taza de chocolate"),"ud",IFERROR(INDEX('Parámetros'!$F$33:$F$53,MATCH(C67,'Parámetros'!$A$33:$A$53,0)),"")) -> ud | F67: Sólo para llevar | G67: =IF(C67="Taza de chocolate",'Chocolate a la Taza'!$B$15,IF(C67="Media taza de chocolate",'Chocolate a la Taza'!$B$16,IFERROR(INDEX('Parámetros'!$G$33:$G$53,MATCH(C67,'Parámetros'!$A$33:$A$53,0)),""))) -> 0.15 | H67: =IFERROR(D67*G67,"") -> 0.15 | I67: =IF(F67="Siempre",H67,0) -> 0 | J67: =IF(F67="Sólo para llevar",H67,0) -> 0.15
A68: CH7 | B68: Kilo de churros para llevar | C68: Caja de cartón para el kilo | D68: 1 | E68: =IF(OR(C68="Taza de chocolate",C68="Media taza de chocolate"),"ud",IFERROR(INDEX('Parámetros'!$F$33:$F$53,MATCH(C68,'Parámetros'!$A$33:$A$53,0)),"")) -> ud | F68: Sólo para llevar | G68: =IF(C68="Taza de chocolate",'Chocolate a la Taza'!$B$15,IF(C68="Media taza de chocolate",'Chocolate a la Taza'!$B$16,IFERROR(INDEX('Parámetros'!$G$33:$G$53,MATCH(C68,'Parámetros'!$A$33:$A$53,0)),""))) -> 0.25 | H68: =IFERROR(D68*G68,"") -> 0.25 | I68: =IF(F68="Siempre",H68,0) -> 0 | J68: =IF(F68="Sólo para llevar",H68,0) -> 0.25
A69: RE1 | B69: Churro relleno de chocolate (ud) | C69: Cobertura de chocolate negro (1 kg) | D69: 0.02 | E69: =IF(OR(C69="Taza de chocolate",C69="Media taza de chocolate"),"ud",IFERROR(INDEX('Parámetros'!$F$33:$F$53,MATCH(C69,'Parámetros'!$A$33:$A$53,0)),"")) -> kg | F69: Siempre | G69: =IF(C69="Taza de chocolate",'Chocolate a la Taza'!$B$15,IF(C69="Media taza de chocolate",'Chocolate a la Taza'!$B$16,IFERROR(INDEX('Parámetros'!$G$33:$G$53,MATCH(C69,'Parámetros'!$A$33:$A$53,0)),""))) -> 6.5 | H69: =IFERROR(D69*G69,"") -> 0.13 | I69: =IF(F69="Siempre",H69,0) -> 0.13 | J69: =IF(F69="Sólo para llevar",H69,0) -> 0
A70: RE2 | B70: Ración de churros con cobertura de chocolate (6 uds) | C70: Cobertura de chocolate negro (1 kg) | D70: 0.03 | E70: =IF(OR(C70="Taza de chocolate",C70="Media taza de chocolate"),"ud",IFERROR(INDEX('Parámetros'!$F$33:$F$53,MATCH(C70,'Parámetros'!$A$33:$A$53,0)),"")) -> kg | F70: Siempre | G70: =IF(C70="Taza de chocolate",'Chocolate a la Taza'!$B$15,IF(C70="Media taza de chocolate",'Chocolate a la Taza'!$B$16,IFERROR(INDEX('Parámetros'!$G$33:$G$53,MATCH(C70,'Parámetros'!$A$33:$A$53,0)),""))) -> 6.5 | H70: =IFERROR(D70*G70,"") -> 0.195 | I70: =IF(F70="Siempre",H70,0) -> 0.195 | J70: =IF(F70="Sólo para llevar",H70,0) -> 0
A71: CT1 | B71: Chocolate a la taza en barra | C71: Taza de chocolate | D71: 1 | E71: =IF(OR(C71="Taza de chocolate",C71="Media taza de chocolate"),"ud",IFERROR(INDEX('Parámetros'!$F$33:$F$53,MATCH(C71,'Parámetros'!$A$33:$A$53,0)),"")) -> ud | F71: Siempre | G71: =IF(C71="Taza de chocolate",'Chocolate a la Taza'!$B$15,IF(C71="Media taza de chocolate",'Chocolate a la Taza'!$B$16,IFERROR(INDEX('Parámetros'!$G$33:$G$53,MATCH(C71,'Parámetros'!$A$33:$A$53,0)),""))) -> 0.43744186 | H71: =IFERROR(D71*G71,"") -> 0.43744186 | I71: =IF(F71="Siempre",H71,0) -> 0.43744186 | J71: =IF(F71="Sólo para llevar",H71,0) -> 0
A72: CT2 | B72: Chocolate a la taza en terraza | C72: Taza de chocolate | D72: 1 | E72: =IF(OR(C72="Taza de chocolate",C72="Media taza de chocolate"),"ud",IFERROR(INDEX('Parámetros'!$F$33:$F$53,MATCH(C72,'Parámetros'!$A$33:$A$53,0)),"")) -> ud | F72: Siempre | G72: =IF(C72="Taza de chocolate",'Chocolate a la Taza'!$B$15,IF(C72="Media taza de chocolate",'Chocolate a la Taza'!$B$16,IFERROR(INDEX('Parámetros'!$G$33:$G$53,MATCH(C72,'Parámetros'!$A$33:$A$53,0)),""))) -> 0.43744186 | H72: =IFERROR(D72*G72,"") -> 0.43744186 | I72: =IF(F72="Siempre",H72,0) -> 0.43744186 | J72: =IF(F72="Sólo para llevar",H72,0) -> 0
A73: CT3 | B73: Chocolate con churros (taza y ración de 6) | C73: Taza de chocolate | D73: 1 | E73: =IF(OR(C73="Taza de chocolate",C73="Media taza de chocolate"),"ud",IFERROR(INDEX('Parámetros'!$F$33:$F$53,MATCH(C73,'Parámetros'!$A$33:$A$53,0)),"")) -> ud | F73: Siempre | G73: =IF(C73="Taza de chocolate",'Chocolate a la Taza'!$B$15,IF(C73="Media taza de chocolate",'Chocolate a la Taza'!$B$16,IFERROR(INDEX('Parámetros'!$G$33:$G$53,MATCH(C73,'Parámetros'!$A$33:$A$53,0)),""))) -> 0.43744186 | H73: =IFERROR(D73*G73,"") -> 0.43744186 | I73: =IF(F73="Siempre",H73,0) -> 0.43744186 | J73: =IF(F73="Sólo para llevar",H73,0) -> 0
A74: CT4 | B74: Chocolate a la taza para llevar | C74: Taza de chocolate | D74: 1 | E74: =IF(OR(C74="Taza de chocolate",C74="Media taza de chocolate"),"ud",IFERROR(INDEX('Parámetros'!$F$33:$F$53,MATCH(C74,'Parámetros'!$A$33:$A$53,0)),"")) -> ud | F74: Siempre | G74: =IF(C74="Taza de chocolate",'Chocolate a la Taza'!$B$15,IF(C74="Media taza de chocolate",'Chocolate a la Taza'!$B$16,IFERROR(INDEX('Parámetros'!$G$33:$G$53,MATCH(C74,'Parámetros'!$A$33:$A$53,0)),""))) -> 0.43744186 | H74: =IFERROR(D74*G74,"") -> 0.43744186 | I74: =IF(F74="Siempre",H74,0) -> 0.43744186 | J74: =IF(F74="Sólo para llevar",H74,0) -> 0
... A100: CV4 | B100: Batido | C100: Vaso de papel plastificado con tapa | D100: 1 | E100: =IF(OR(C100="Taza de chocolate",C100="Media taza de chocolate"),"ud",IFERROR(INDEX('Parámetros'!$F$33:$F$53,MATCH(C100,'Parámetros'!$A$33:$A$53,0)),"")) -> ud | F100: Sólo para llevar | G100: =IF(C100="Taza de chocolate",'Chocolate a la Taza'!$B$15,IF(C100="Media taza de chocolate",'Chocolate a la Taza'!$B$16,IFERROR(INDEX('Parámetros'!$G$33:$G$53,MATCH(C100,'Parámetros'!$A$33:$A$53,0)),""))) -> 0.08 | H100: =IFERROR(D100*G100,"") -> 0.08 | I100: =IF(F100="Siempre",H100,0) -> 0 | J100: =IF(F100="Sólo para llevar",H100,0) -> 0.08
A103: Listas de validación (no las borres: las usan los desplegables)
A104: Tipo de pieza | B104: Cuándo cuenta | C104: Insumo
A105: churro | B105: Siempre | C105: Preparado para masa de churro (caja de 6 sacos de 4 kg)
A106: porra | B106: Sólo para llevar | C106: Aceite especial de fritura (garrafa de 25 L)
A107: sin masa | C107: Chocolate a la taza en polvo (bolsa de 800 g, rinde 4,3 L)
C108: Cobertura de chocolate negro (1 kg)
C109: Cucurucho de cartón para churros (caja de 100)
C110: Harina especial para churros (mix propio)
C111: Sal
C112: Azúcar para espolvorear y sobres
C113: Leche
C114: Café en grano
C115: Infusión (sobre)
C116: Cacao soluble
C117: Naranja para zumo
C118: Agua (botella de 50 cl)
C119: Base de granizado (por vaso)
... C127: Media taza de chocolate
A130: Versión 1.0 · octubre 2026 · aichef.pro/guia-churreria-chocolateria · info@aichef.pro

Sheet Absorción de Aceite y Merma
A1: Absorción de Aceite y Merma
A2: AI Chef Pro · aichef.pro — Cómo Montar una Churrería-Chocolatería
A3: El aceite que se lleva la masa frita, en euros. La renovación del aceite de la cuba (el descarte) la calcula el libro 4.
A4: Del Aceite al Euro por Kilo de Masa | K4: Lo que Copian Otros Libros (No Muevas Estas Celdas)
A5: Kilos fritos que salen de un kilo de masa | B5: ='Parámetros'!$B$17 -> 0.9 | C5: kg/kg | K5: Aceite absorbido por ración media (mix de invierno), EUR | L5: =B20 -> 0.019119579 | M5: Lo copia: libro 4 (aceite-de-fritura-coste-y-cambio.xlsx, hoja Parámetros, X2 bis)
A6: Absorción de aceite, en % del peso frito | B6: ='Parámetros'!$B$18 -> 0.1
A7: Kilos de aceite que se lleva un kilo de masa | B7: =IFERROR(B5*B6,"") -> 0.09 | C7: kg
A8: Densidad del aceite | B8: ='Parámetros'!$B$19 -> 0.92 | C8: kg/L
A9: Litros de aceite que se lleva un kilo de masa | B9: =IFERROR(B7/B8,"") -> 0.097826087 | C9: L
A10: Precio del aceite (base imponible) | B10: ='Parámetros'!$L$5 -> 1.996 | C10: EUR/L
A11: EUROS DE ACEITE ABSORBIDO POR KILO DE MASA | B11: =IFERROR(B9*B10,"") -> 0.19526087 | C11: EUR/kg
A13: La Merma
A14: Merma: masa que se fríe y no se vende | B14: ='Parámetros'!$B$16 -> 0.05
A15: Kilos de masa que hay que freír por kilo vendido | B15: =IFERROR(1/(1-B14),"") -> 1.0526316 | C15: kg/kg
A16: Coste de la merma por kilo vendido (masa y aceite) | B16: =IFERROR((B15-1)*('Escandallo por kg de Masa'!$B$19+B11),"") -> 0.03682151 | C16: EUR/kg
A18: Por Ración Media
A19: Kilos de masa que se fríen por ración media (mix de invierno) | B19: ='Mix y Ticket Canal y Temporada'!$L$5 -> 0.097918129 | C19: kg/ración | D19: La ración media es la unidad de venta media de la carta, ponderada por el mix de invierno (hoja «Mix y Ticket Canal y Temporada»).
A20: ACEITE ABSORBIDO POR RACIÓN MEDIA | B20: =IFERROR(B19*B11,"") -> 0.019119579 | C20: EUR/ración | D20: El libro 4 recibe esta cifra para la fila de contraste «aceite absorbido (3) más renovación (4) = aceite total por ración». El 6 suma las dos, cada una con su fuente.
A21: Litros de aceite absorbido cada 100 raciones | B21: =IFERROR(B19*B9*100,"") -> 0.95789474 | C21: L
A22: Peso del aceite absorbido en la materia de la ración media | B22: =IFERROR(B20/'Mix y Ticket Canal y Temporada'!$D$7,"") -> 0.067597868
A25: Si la Absorción Fuera Otra (Pon las Tuyas)
A26: Absorción de aceite, en % del peso frito | B26: EUR de aceite por kilo de masa | C26: EUR de aceite por ración media | D26: Diferencia por ración frente a tu absorción (EUR) | E26: Diferencia cada 1.000 raciones (EUR)
A27: 0.06 | B27: =IFERROR($B$5*A27/$B$8*$B$10,"") -> 0.11715652 | C27: =IFERROR(B27*$B$19,"") -> 0.011471747 | D27: =IFERROR(C27-$B$20,"") -> -0.0076478316 | E27: =IFERROR(D27*1000,"") -> -7.6478316
A28: 0.08 | B28: =IFERROR($B$5*A28/$B$8*$B$10,"") -> 0.1562087 | C28: =IFERROR(B28*$B$19,"") -> 0.015295663 | D28: =IFERROR(C28-$B$20,"") -> -0.0038239158 | E28: =IFERROR(D28*1000,"") -> -3.8239158
A29: 0.1 | B29: =IFERROR($B$5*A29/$B$8*$B$10,"") -> 0.19526087 | C29: =IFERROR(B29*$B$19,"") -> 0.019119579 | D29: =IFERROR(C29-$B$20,"") -> 0 | E29: =IFERROR(D29*1000,"") -> 0
A30: 0.12 | B30: =IFERROR($B$5*A30/$B$8*$B$10,"") -> 0.23431304 | C30: =IFERROR(B30*$B$19,"") -> 0.022943495 | D30: =IFERROR(C30-$B$20,"") -> 0.0038239158 | E30: =IFERROR(D30*1000,"") -> 3.8239158
A31: 0.14 | B31: =IFERROR($B$5*A31/$B$8*$B$10,"") -> 0.27336522 | C31: =IFERROR(B31*$B$19,"") -> 0.026767411 | D31: =IFERROR(C31-$B$20,"") -> 0.0076478316 | E31: =IFERROR(D31*1000,"") -> 7.6478316
A33: La absorción es un supuesto declarado, sin fuente pública: mídela pesando una tanda de masa antes y después de freír. Cambiar de aceite o de freidora la mueve.
A35: Versión 1.0 · octubre 2026 · aichef.pro/guia-churreria-chocolateria · info@aichef.pro

Sheet Chocolate a la Taza
A1: Chocolate a la Taza
A2: AI Chef Pro · aichef.pro — Cómo Montar una Churrería-Chocolatería
A3: Lo que cuesta una taza y qué dice la etiqueta de tu preparado. La carta usa la denominación que figura en esa etiqueta.
A5: 1. Lo que Cuesta el Chocolate
A6: Precio del preparado SIN IVA (EUR/kg) | B6: ='Parámetros'!$G$35 -> 7.1875
A7: Kilos de preparado del formato que compras | B7: ='Parámetros'!$E$35 -> 0.8
A8: Litros de chocolate que rinde ese formato (lo dice el envase) | B8: 4.3
A9: Kilos de preparado por litro de chocolate | B9: =IFERROR(B7/B8,"") -> 0.18604651
A10: Coste del preparado por litro de chocolate (EUR) | B10: =IFERROR(B9*B6,"") -> 1.3372093
A11: Leche, litro por litro de chocolate (EUR/L) | B11: ='Parámetros'!$G$41 -> 0.85
A12: COSTE DEL CHOCOLATE POR LITRO (EUR) | B12: =B10+B11 -> 2.1872093
A13: Mililitros de una taza | B13: 200 | C13: supuesto declarado
A14: Mililitros de media taza | B14: 120 | C14: supuesto declarado
A15: COSTE DE UNA TAZA (EUR) | B15: =IFERROR(B13/1000*B12,"") -> 0.43744186
A16: Coste de media taza (EUR) | B16: =IFERROR(B14/1000*B12,"") -> 0.26246512
A19: 2. Qué Dice la Etiqueta de Tu Preparado
A20: Denominación que figura en la etiqueta del preparado (cópiala tal cual) | B20: Chocolate a la taza | C20: Supuesto del ejemplo: un preparado comercial cuya etiqueta dice «chocolate a la taza». Pon la de TU preparado.
A21: Cacao seco total que declara la etiqueta | B21: 0.35 | C21: Lo que dice la etiqueta del preparado del ejemplo. Copia el de la etiqueta de TU preparado.
A22: ¿La etiqueta declara grasa vegetal distinta de la manteca de cacao? | B22: No
A23: Cacao seco total mínimo del producto «chocolate a la taza» | B23: 0.35
A24: AVISO ANTES DE IMPRIMIR LA CARTA | B24: =IF(NOT(ISNUMBER(B21)),"",IF(OR(B21<B23,B22="Sí"),"Consulta a tu servicio de consumo antes de imprimir la carta","Sin aviso: la carta usa la denominación de la etiqueta")) -> Sin aviso: la carta usa la denominación de la etiqueta
A25: Nombre con el que la taza va en tu carta | B25: =B20 -> Chocolate a la taza | C25: Es una interpretación, no una regla del Real Decreto: la carta repite la denominación de la etiqueta y, si hay aviso, lo consultas antes de imprimir. La decisión 6 es qué preparado compras y qué dice su etiqueta.
A27: 3. El IVA de la Taza para Llevar
A28: IVA que aplicas a la taza para llevar (de «Parámetros») | B28: ='Parámetros'!$B$7 -> 0.1
A29: Zona gris: El Molinete aplica el 10 % en celda verde. Consulta a tu asesor: con agua y un preparado azucarado podría ser el 21 %. Se cambia en «Parámetros», en una sola celda.
A31: 4. Las Tazas de la Carta
A32: Referencia | B32: PVP con IVA (EUR) | C32: Ingreso medio SIN IVA (EUR) | D32: Materia media (EUR) | E32: Margen por unidad (EUR) | F32: Margen sobre materia | G32: Nota
A33: CT1 · Chocolate a la taza en barra | B33: ='Mix y Ticket Canal y Temporada'!$D$26 -> 2 | C33: ='Mix y Ticket Canal y Temporada'!$O$26 -> 1.8181818 | D33: ='Mix y Ticket Canal y Temporada'!$R$26 -> 0.43744186 | E33: =IFERROR(C33-D33,"") -> 1.38074 | F33: =IFERROR(1-D33/C33,"") -> 0.75940698 | G33: Precio de La Churrería de Granada (2026). La denominación de la carta es la de la etiqueta del preparado.
A34: CT2 · Chocolate a la taza en terraza | B34: ='Mix y Ticket Canal y Temporada'!$D$27 -> 2.5 | C34: ='Mix y Ticket Canal y Temporada'!$O$27 -> 2.2727273 | D34: ='Mix y Ticket Canal y Temporada'!$R$27 -> 0.43744186 | E34: =IFERROR(C34-D34,"") -> 1.8352854 | F34: =IFERROR(1-D34/C34,"") -> 0.80752558 | G34: Precio de La Churrería de Granada (2026).
A35: CT3 · Chocolate con churros (taza y ración de 6) | B35: ='Mix y Ticket Canal y Temporada'!$D$28 -> 3.8 | C35: ='Mix y Ticket Canal y Temporada'!$O$28 -> 3.4545455 | D35: ='Mix y Ticket Canal y Temporada'!$R$28 -> 0.53181349 | E35: =IFERROR(C35-D35,"") -> 2.922732 | F35: =IFERROR(1-D35/C35,"") -> 0.84605399 | G35: Supuesto dentro del rango de 3,50-4 € con chocolate que publica CHS-32 (genérico de un proveedor de TPV).
A36: CT4 · Chocolate a la taza para llevar | B36: ='Mix y Ticket Canal y Temporada'!$D$29 -> 2.2 | C36: ='Mix y Ticket Canal y Temporada'!$O$29 -> 2.0909091 | D36: ='Mix y Ticket Canal y Temporada'!$R$29 -> 0.51744186 | E36: =IFERROR(C36-D36,"") -> 1.5734672 | F36: =IFERROR(1-D36/C36,"") -> 0.75252781 | G36: Su IVA es la celda verde del 10 % con aviso; el vaso se cobra aparte.
A37: CT5 · Media taza de chocolate | B37: ='Mix y Ticket Canal y Temporada'!$D$30 -> 1.3 | C37: ='Mix y Ticket Canal y Temporada'!$O$30 -> 1.1818182 | D37: ='Mix y Ticket Canal y Temporada'!$R$30 -> 0.26246512 | E37: =IFERROR(C37-D37,"") -> 0.91935307 | F37: =IFERROR(1-D37/C37,"") -> 0.77791413
A41: Listas de validación (no las borres: las usan los desplegables)
A42: Sí o no
A43: Sí
A44: No
A46: Versión 1.0 · octubre 2026 · aichef.pro/guia-churreria-chocolateria · info@aichef.pro

Sheet Coste Hora
A1: Coste Hora
A2: AI Chef Pro · aichef.pro — Cómo Montar una Churrería-Chocolatería
A3: El coste de empresa de una hora de tu plantilla y la mano de obra que lleva cada ración. La plantilla y el convenio viven en el libro 8.
A4: La Hora y la Ración | K4: Lo que Copian Otros Libros (No Muevas Estas Celdas)
A5: COSTE HORA DE MANO DE OBRA (coste de empresa por hora contratada) | B5: 13.243843 | C5: EUR/h | D5: Supuesto calculado con la plantilla de El Molinete (titular, dos churreros, un camarero y el medio refuerzo; convenio de ejemplo con tablas de 2025, suelo del SMI 2026 y Seguridad Social de empresa). Este libro va antes que el 8 y lo SUPONE: cuando rellenes el 8, su fila de CUADRE compara este número con el de tu plantilla. | K5: Coste hora de mano de obra, EUR/h | L5: =B5 -> 13.243843 | M5: Lo copia: libro 5 (temporada-franjas-y-ferias.xlsx, hoja Parámetros, X5); libro 8 (turnos-plantilla-y-madrugada.xlsx, hoja Parámetros, X8)
A6: Minutos de mano de obra por ración | B6: 4.4748603 | C6: min/ración | D6: Supuesto calculado: las horas contratadas de la plantilla al año, por 60, entre las raciones del año de El Molinete. Con tus números: horas de tu plantilla (libro 8) por 60 entre tus raciones del año (libro 5).
A7: Raciones por hora de mano de obra | B7: =IFERROR(60/B6,"") -> 13.40824 | C7: raciones/h
A8: COSTE DE MANO DE OBRA POR RACIÓN | B8: =IFERROR(B5*B6/60,"") -> 0.98773912 | C8: EUR/ración
A9: Ticket SIN IVA por ración (mix de invierno) | B9: ='Mix y Ticket Canal y Temporada'!$D$6 -> 2.1613636 | C9: EUR/ración
A10: Peso de la mano de obra sobre el ticket | B10: =IFERROR(B8/B9,"") -> 0.45699812
A11: Lo que Vale un Minuto
A12: Coste de un minuto de mano de obra (EUR) | B12: =IFERROR(B5/60,"") -> 0.22073071
A13: Mano de obra cada 100 raciones (EUR) | B13: =IFERROR(B8*100,"") -> 98.773912
A15: Por qué está aquí: el margen de la carta no paga sólo la materia. «Los Dos Márgenes» resta este coste para que veas el margen que te queda tras aceite y mano de obra. El libro 5 lo usa para valorar las horas de refuerzo, y el 8 lo cuadra con tu plantilla.
A17: Versión 1.0 · octubre 2026 · aichef.pro/guia-churreria-chocolateria · info@aichef.pro

Sheet Ración, Docena o Kilo
A1: Ración, Docena o Kilo
A2: AI Chef Pro · aichef.pro — Cómo Montar una Churrería-Chocolatería
A3: Los formatos de churro y porra, comparados por los euros SIN IVA que deja cada kilo de masa que fríes (decisión 7).
A6: Formato | B6: Piezas | C6: PVP con IVA (EUR) | D6: Precio por pieza con IVA (EUR) | E6: Canal que manda | F6: Ingreso SIN IVA (EUR) | G6: Materia, aceite incluido (EUR) | H6: Margen por unidad (EUR) | I6: Masa que se fríe (kg) | J6: EUR QUE DEJA CADA KG DE MASA | K6: Año y fuente del precio
A7: CH1 · Ración de churros (6 uds) | B7: ='Escandallo por kg de Masa'!$C$35 -> 6 | C7: ='Mix y Ticket Canal y Temporada'!$D$17 -> 2.6 | D7: =IF(B7>0,IFERROR(C7/B7,""),"") -> 0.43333333 | E7: =IF('Mix y Ticket Canal y Temporada'!$F$17>=1-'Mix y Ticket Canal y Temporada'!$F$17,"Para llevar","Sala") -> Sala | F7: =IF(E7="Para llevar",'Mix y Ticket Canal y Temporada'!$N$17,'Mix y Ticket Canal y Temporada'!$K$17) -> 2.3636364 | G7: =IF(E7="Para llevar",'Escandallo por kg de Masa'!$N$35,'Escandallo por kg de Masa'!$M$35) -> 0.094371625 | H7: =IFERROR(F7-G7,"") -> 2.2692647 | I7: ='Escandallo por kg de Masa'!$G$35 -> 0.12631579 | J7: =IFERROR(H7/I7,"") -> 17.965013 | K7: ='Mix y Ticket Canal y Temporada'!$C$17&" · "&'Mix y Ticket Canal y Temporada'!$E$17 -> 2025 · CUS-17
A8: CH2 · Media ración de churros (3 uds) | B8: ='Escandallo por kg de Masa'!$C$36 -> 3 | C8: ='Mix y Ticket Canal y Temporada'!$D$18 -> 1.4 | D8: =IF(B8>0,IFERROR(C8/B8,""),"") -> 0.46666667 | E8: =IF('Mix y Ticket Canal y Temporada'!$F$18>=1-'Mix y Ticket Canal y Temporada'!$F$18,"Para llevar","Sala") -> Sala | F8: =IF(E8="Para llevar",'Mix y Ticket Canal y Temporada'!$N$18,'Mix y Ticket Canal y Temporada'!$K$18) -> 1.2727273 | G8: =IF(E8="Para llevar",'Escandallo por kg de Masa'!$N$36,'Escandallo por kg de Masa'!$M$36) -> 0.047185812 | H8: =IFERROR(F8-G8,"") -> 1.2255415 | I8: ='Escandallo por kg de Masa'!$G$36 -> 0.063157895 | J8: =IFERROR(H8/I8,"") -> 19.404406 | K8: ='Mix y Ticket Canal y Temporada'!$C$18&" · "&'Mix y Ticket Canal y Temporada'!$E$18 -> 2025 · CUS-17
A9: CH3 · Ración de porras (3 uds) | B9: ='Escandallo por kg de Masa'!$C$37 -> 3 | C9: ='Mix y Ticket Canal y Temporada'!$D$19 -> 2.7 | D9: =IF(B9>0,IFERROR(C9/B9,""),"") -> 0.9 | E9: =IF('Mix y Ticket Canal y Temporada'!$F$19>=1-'Mix y Ticket Canal y Temporada'!$F$19,"Para llevar","Sala") -> Sala | F9: =IF(E9="Para llevar",'Mix y Ticket Canal y Temporada'!$N$19,'Mix y Ticket Canal y Temporada'!$K$19) -> 2.4545455 | G9: =IF(E9="Para llevar",'Escandallo por kg de Masa'!$N$37,'Escandallo por kg de Masa'!$M$37) -> 0.14155744 | H9: =IFERROR(F9-G9,"") -> 2.312988 | I9: ='Escandallo por kg de Masa'!$G$37 -> 0.18947368 | J9: =IFERROR(H9/I9,"") -> 12.207437 | K9: ='Mix y Ticket Canal y Temporada'!$C$19&" · "&'Mix y Ticket Canal y Temporada'!$E$19 -> 2026 · supuesto declarado
A10: CH4 · Churro suelto | B10: ='Escandallo por kg de Masa'!$C$38 -> 1 | C10: ='Mix y Ticket Canal y Temporada'!$D$20 -> 0.3 | D10: =IF(B10>0,IFERROR(C10/B10,""),"") -> 0.3 | E10: =IF('Mix y Ticket Canal y Temporada'!$F$20>=1-'Mix y Ticket Canal y Temporada'!$F$20,"Para llevar","Sala") -> Para llevar | F10: =IF(E10="Para llevar",'Mix y Ticket Canal y Temporada'!$N$20,'Mix y Ticket Canal y Temporada'!$K$20) -> 0.27272727 | G10: =IF(E10="Para llevar",'Escandallo por kg de Masa'!$N$38,'Escandallo por kg de Masa'!$M$38) -> 0.035728604 | H10: =IFERROR(F10-G10,"") -> 0.23699867 | I10: ='Escandallo por kg de Masa'!$G$38 -> 0.021052632 | J10: =IFERROR(H10/I10,"") -> 11.257437 | K10: ='Mix y Ticket Canal y Temporada'!$C$20&" · "&'Mix y Ticket Canal y Temporada'!$E$20 -> 2026 · CUS-16
A11: CH5 · Porra suelta | B11: ='Escandallo por kg de Masa'!$C$39 -> 1 | C11: ='Mix y Ticket Canal y Temporada'!$D$21 -> 0.6 | D11: =IF(B11>0,IFERROR(C11/B11,""),"") -> 0.6 | E11: =IF('Mix y Ticket Canal y Temporada'!$F$21>=1-'Mix y Ticket Canal y Temporada'!$F$21,"Para llevar","Sala") -> Para llevar | F11: =IF(E11="Para llevar",'Mix y Ticket Canal y Temporada'!$N$21,'Mix y Ticket Canal y Temporada'!$K$21) -> 0.54545455 | G11: =IF(E11="Para llevar",'Escandallo por kg de Masa'!$N$39,'Escandallo por kg de Masa'!$M$39) -> 0.067185812 | H11: =IFERROR(F11-G11,"") -> 0.47826873 | I11: ='Escandallo por kg de Masa'!$G$39 -> 0.063157895 | J11: =IFERROR(H11/I11,"") -> 7.5725883 | K11: ='Mix y Ticket Canal y Temporada'!$C$21&" · "&'Mix y Ticket Canal y Temporada'!$E$21 -> 2026 · CUS-16
A12: CH6 · Docena de churros para llevar | B12: ='Escandallo por kg de Masa'!$C$40 -> 12 | C12: ='Mix y Ticket Canal y Temporada'!$D$22 -> 3.5 | D12: =IF(B12>0,IFERROR(C12/B12,""),"") -> 0.29166667 | E12: =IF('Mix y Ticket Canal y Temporada'!$F$22>=1-'Mix y Ticket Canal y Temporada'!$F$22,"Para llevar","Sala") -> Para llevar | F12: =IF(E12="Para llevar",'Mix y Ticket Canal y Temporada'!$N$22,'Mix y Ticket Canal y Temporada'!$K$22) -> 3.1818182 | G12: =IF(E12="Para llevar",'Escandallo por kg de Masa'!$N$40,'Escandallo por kg de Masa'!$M$40) -> 0.33874325 | H12: =IFERROR(F12-G12,"") -> 2.8430749 | I12: ='Escandallo por kg de Masa'!$G$40 -> 0.25263158 | J12: =IFERROR(H12/I12,"") -> 11.253838 | K12: ='Mix y Ticket Canal y Temporada'!$C$22&" · "&'Mix y Ticket Canal y Temporada'!$E$22 -> 2026 · supuesto declarado
A13: CH7 · Kilo de churros para llevar | B13: ='Escandallo por kg de Masa'!$C$41 -> 0 | C13: ='Mix y Ticket Canal y Temporada'!$D$23 -> 10 | D13: =IF(B13>0,IFERROR(C13/B13,""),"") | E13: =IF('Mix y Ticket Canal y Temporada'!$F$23>=1-'Mix y Ticket Canal y Temporada'!$F$23,"Para llevar","Sala") -> Para llevar | F13: =IF(E13="Para llevar",'Mix y Ticket Canal y Temporada'!$N$23,'Mix y Ticket Canal y Temporada'!$K$23) -> 9.0909091 | G13: =IF(E13="Para llevar",'Escandallo por kg de Masa'!$N$41,'Escandallo por kg de Masa'!$M$41) -> 1.1238113 | H13: =IFERROR(F13-G13,"") -> 7.9670978 | I13: ='Escandallo por kg de Masa'!$G$41 -> 1.1695906 | J13: =IFERROR(H13/I13,"") -> 6.8118686 | K13: ='Mix y Ticket Canal y Temporada'!$C$23&" · "&'Mix y Ticket Canal y Temporada'!$E$23 -> 2026 · supuesto declarado
A15: Lo que Dice la Comparación
A16: El formato que más deja por kilo de masa | B16: =IFERROR(INDEX(A7:A13,MATCH(MAX(J7:J13),J7:J13,0)),"") -> CH2 · Media ración de churros (3 uds)
A17: Lo que deja ese formato por kilo de masa (EUR) | B17: =MAX(J7:J13) -> 19.404406
A18: El formato que menos deja por kilo de masa | B18: =IFERROR(INDEX(A7:A13,MATCH(MIN(J7:J13),J7:J13,0)),"") -> CH7 · Kilo de churros para llevar
A19: Lo que deja ese formato por kilo de masa (EUR) | B19: =MIN(J7:J13) -> 6.8118686
A20: Ración de churros frente al kilo: EUR más por kilo de masa | B20: =IFERROR(J7-J13,"") -> 11.153144
A22: El kilo es el formato con menos euros por kilo de masa porque se vende por peso frito, al precio más bajo por pieza. No es un error que lo tengas: es el que trae el pedido grande del domingo. Lo que esta hoja te dice es cuánto cuesta cada formato en masa, en aceite y en freidora, para que el precio de cada uno sea una decisión. El canal que manda es el de la mayor parte de sus ventas (hoja «Mix y Ticket Canal y Temporada»).
A24: Versión 1.0 · octubre 2026 · aichef.pro/guia-churreria-chocolateria · info@aichef.pro

Sheet Mix y Ticket Canal y Temporada
A1: Mix y Ticket Canal y Temporada
A2: AI Chef Pro · aichef.pro — Cómo Montar una Churrería-Chocolatería
A3: El PVP con IVA de cada referencia, la parte que se vende para llevar y dos mixes: invierno (septiembre a junio) y verano (julio y agosto). Cada mix suma 100.
A4: Ticket y Materia por Canal y Temporada | K4: Lo que Copian Otros Libros (No Muevas Estas Celdas)
A5: Por ración | B5: Invierno · sala | C5: Invierno · para llevar | D5: Invierno · total | E5: Verano · sala | F5: Verano · para llevar | G5: Verano · total | K5: Kilos de masa por ración media (mix de invierno, merma incluida) | L5: =D11 -> 0.097918129 | M5: Lo copia: libro 1 (produccion-hora-punta-y-local.xlsx, hoja Parámetros, X1); libro 4 (aceite-de-fritura-coste-y-cambio.xlsx, hoja Parámetros, X2 bis)
A6: Ticket SIN IVA por ración (EUR) | B6: =IFERROR(SUMPRODUCT(U17:U40,K17:K40)/U$41,"") -> 2.1480519 | C6: =IFERROR(SUMPRODUCT(V17:V40,N17:N40)/V$41,"") -> 2.1924242 | D6: =IFERROR(SUMPRODUCT(S17:S40,O17:O40)/S$41,"") -> 2.1613636 | E6: =IFERROR(SUMPRODUCT(W17:W40,K17:K40)/W$41,"") -> 2.2277629 | F6: =IFERROR(SUMPRODUCT(X17:X40,N17:N40)/X$41,"") -> 2.1586804 | G6: =IFERROR(SUMPRODUCT(T17:T40,O17:O40)/T$41,"") -> 2.2067273 | K6: Ticket SIN IVA por ración en verano (carta de verano), EUR | L6: =G6 -> 2.2067273 | M6: Lo copia: libro 5 (temporada-franjas-y-ferias.xlsx, hoja Parámetros, X5)
A7: Coste de materia por ración, aceite absorbido incluido (EUR) | B7: =IFERROR(SUMPRODUCT(U17:U40,P17:P40)/U$41,"") -> 0.27314864 | C7: =IFERROR(SUMPRODUCT(V17:V40,Q17:Q40)/V$41,"") -> 0.30546293 | D7: =IFERROR(SUMPRODUCT(S17:S40,R17:R40)/S$41,"") -> 0.28284293 | E7: =IFERROR(SUMPRODUCT(W17:W40,P17:P40)/W$41,"") -> 0.3475811 | F7: =IFERROR(SUMPRODUCT(X17:X40,Q17:Q40)/X$41,"") -> 0.3834419 | G7: =IFERROR(SUMPRODUCT(T17:T40,R17:R40)/T$41,"") -> 0.35850072 | K7: Coste de materia por ración en verano, aceite absorbido incluido, EUR | L7: =G7 -> 0.35850072 | M7: Lo copia: libro 5 (temporada-franjas-y-ferias.xlsx, hoja Parámetros, X5)
A8: Margen sobre materia por ración (EUR) | B8: =IFERROR(B6-B7,"") -> 1.8749033 | C8: =IFERROR(C6-C7,"") -> 1.8869613 | D8: =IFERROR(D6-D7,"") -> 1.8785207 | E8: =IFERROR(E6-E7,"") -> 1.8801818 | F8: =IFERROR(F6-F7,"") -> 1.7752385 | G8: =IFERROR(G6-G7,"") -> 1.8482266 | K8: Coste de materia por ración para llevar (invierno), aceite absorbido incluido, EUR | L8: =C7 -> 0.30546293 | M8: Lo copia: libro 5 (temporada-franjas-y-ferias.xlsx, hoja Parámetros, X5); libro 6 (plan-financiero-3-anos-churreria.xlsx, hoja 0. Supuestos, X11)
A9: Margen sobre materia (%) | B9: =IFERROR(1-B7/B6,"") -> 0.8728389 | C9: =IFERROR(1-C7/C6,"") -> 0.86067344 | D9: =IFERROR(1-D7/D6,"") -> 0.86913682 | E9: =IFERROR(1-E7/E6,"") -> 0.84397751 | F9: =IFERROR(1-F7/F6,"") -> 0.82237208 | G9: =IFERROR(1-G7/G6,"") -> 0.8375419 | K9: Coste de materia por ración en sala (invierno), aceite absorbido incluido, EUR | L9: =B7 -> 0.27314864 | M9: Lo copia: libro 6 (plan-financiero-3-anos-churreria.xlsx, hoja 0. Supuestos, X11)
A10: Parte de las raciones del canal | B10: =IFERROR(U$41/S$41,"") -> 0.7 | C10: =IFERROR(V$41/S$41,"") -> 0.3 | D10: =IFERROR(S$41/S$41,"") -> 1 | E10: =IFERROR(W$41/T$41,"") -> 0.6955 | F10: =IFERROR(X$41/T$41,"") -> 0.3045 | G10: =IFERROR(T$41/T$41,"") -> 1 | K10: Ticket SIN IVA por ración en sala (invierno), EUR | L10: =B6 -> 2.1480519 | M10: Lo copia: libro 6 (plan-financiero-3-anos-churreria.xlsx, hoja 0. Supuestos, X11)
A11: Kilos de masa que se fríen por ración media | B11: =IFERROR(SUMPRODUCT(U17:U40,Y17:Y40)/U$41,"") -> 0.070827068 | C11: =IFERROR(SUMPRODUCT(V17:V40,Y17:Y40)/V$41,"") -> 0.1611306 | D11: =IFERROR(SUMPRODUCT(S17:S40,Y17:Y40)/S$41,"") -> 0.097918129 | E11: =IFERROR(SUMPRODUCT(W17:W40,Y17:Y40)/W$41,"") -> 0.038276136 | F11: =IFERROR(SUMPRODUCT(X17:X40,Y17:Y40)/X$41,"") -> 0.082347632 | G11: =IFERROR(SUMPRODUCT(T17:T40,Y17:Y40)/T$41,"") -> 0.051695906 | K11: Ticket SIN IVA por ración para llevar (invierno), EUR | L11: =C6 -> 2.1924242 | M11: Lo copia: libro 6 (plan-financiero-3-anos-churreria.xlsx, hoja 0. Supuestos, X11)
A12: Comprobación: cada mix suma 100 | B12: =IF(OR(NOT(ISNUMBER(S41)),NOT(ISNUMBER(T41))),"",IF(AND(ROUND(S41,6)=100,ROUND(T41,6)=100),"CUADRAN los dos mixes","REVISA: algún mix no suma 100")) -> CUADRAN los dos mixes | K12: Raciones en sala, en fracción (0,70 = 70 %; el resto, para llevar) | L12: =B10 -> 0.7 | M12: Lo copia: libro 6 (plan-financiero-3-anos-churreria.xlsx, hoja 0. Supuestos, X11)
A13: El ticket incluye, al llevar, el vaso cobrado aparte. La materia incluye el aceite absorbido y, al llevar, el envase. Las franjas del día no están aquí: viven en el libro 5.
A16: Id y referencia | B16: Familia | C16: Año del precio | D16: PVP con IVA (EUR) | E16: Fuente del precio | F16: Parte que se vende para llevar | G16: ¿Vaso cobrado aparte al llevar? | H16: IVA para llevar: categoría | I16: IVA en sala | J16: IVA para llevar | K16: PVP SIN IVA en sala (EUR) | L16: PVP SIN IVA para llevar (EUR) | M16: Vaso SIN IVA (EUR) | N16: Ingreso SIN IVA para llevar (EUR) | O16: Ingreso medio SIN IVA (EUR) | P16: Materia en sala (EUR) | Q16: Materia para llevar (EUR) | R16: Materia media (EUR) | S16: Mix de invierno (%) | T16: Mix de julio y agosto (%) | U16: Peso sala invierno | V16: Peso llevar invierno | W16: Peso sala verano | X16: Peso llevar verano | Y16: Masa que se fríe (kg) | Z16: Alérgenos de la receta del ejemplo
A17: CH1 · Ración de churros (6 uds) | B17: Churros y porras | C17: 2025 | D17: 2.6 | E17: CUS-17 | F17: 0.15 | G17: No | H17: Comida para llevar | I17: ='Parámetros'!$B$5 -> 0.1 | J17: ='Parámetros'!$B$6 -> 0.1 | K17: =IFERROR(D17/(1+I17),"") -> 2.3636364 | L17: =IFERROR(D17/(1+J17),"") -> 2.3636364 | M17: =IF(G17="Sí",IFERROR('Parámetros'!$B$25/(1+'Parámetros'!$B$8),""),0) -> 0 | N17: =IFERROR(L17+M17,"") -> 2.3636364 | O17: =IFERROR((1-F17)*K17+F17*N17,"") -> 2.3636364 | P17: ='Escandallo por kg de Masa'!$M$35 -> 0.094371625 | Q17: ='Escandallo por kg de Masa'!$N$35 -> 0.24437162 | R17: =IFERROR((1-F17)*P17+F17*Q17,"") -> 0.11687162 | S17: 20 | T17: 12 | U17: =IFERROR(S17*(1-F17),"") -> 17 | V17: =IFERROR(S17*F17,"") -> 3 | W17: =IFERROR(T17*(1-F17),"") -> 10.2 | X17: =IFERROR(T17*F17,"") -> 1.8 | Y17: ='Escandallo por kg de Masa'!$G$35 -> 0.12631579 | Z17: gluten
A18: CH2 · Media ración de churros (3 uds) | B18: Churros y porras | C18: 2025 | D18: 1.4 | E18: CUS-17 | F18: 0 | G18: No | H18: Comida para llevar | I18: ='Parámetros'!$B$5 -> 0.1 | J18: ='Parámetros'!$B$6 -> 0.1 | K18: =IFERROR(D18/(1+I18),"") -> 1.2727273 | L18: =IFERROR(D18/(1+J18),"") -> 1.2727273 | M18: =IF(G18="Sí",IFERROR('Parámetros'!$B$25/(1+'Parámetros'!$B$8),""),0) -> 0 | N18: =IFERROR(L18+M18,"") -> 1.2727273 | O18: =IFERROR((1-F18)*K18+F18*N18,"") -> 1.2727273 | P18: ='Escandallo por kg de Masa'!$M$36 -> 0.047185812 | Q18: ='Escandallo por kg de Masa'!$N$36 -> 0.047185812 | R18: =IFERROR((1-F18)*P18+F18*Q18,"") -> 0.047185812 | S18: 4 | T18: 3 | U18: =IFERROR(S18*(1-F18),"") -> 4 | V18: =IFERROR(S18*F18,"") -> 0 | W18: =IFERROR(T18*(1-F18),"") -> 3 | X18: =IFERROR(T18*F18,"") -> 0 | Y18: ='Escandallo por kg de Masa'!$G$36 -> 0.063157895 | Z18: gluten
A19: CH3 · Ración de porras (3 uds) | B19: Churros y porras | C19: 2026 | D19: 2.7 | E19: supuesto declarado | F19: 0.25 | G19: No | H19: Comida para llevar | I19: ='Parámetros'!$B$5 -> 0.1 | J19: ='Parámetros'!$B$6 -> 0.1 | K19: =IFERROR(D19/(1+I19),"") -> 2.4545455 | L19: =IFERROR(D19/(1+J19),"") -> 2.4545455 | M19: =IF(G19="Sí",IFERROR('Parámetros'!$B$25/(1+'Parámetros'!$B$8),""),0) -> 0 | N19: =IFERROR(L19+M19,"") -> 2.4545455 | O19: =IFERROR((1-F19)*K19+F19*N19,"") -> 2.4545455 | P19: ='Escandallo por kg de Masa'!$M$37 -> 0.14155744 | Q19: ='Escandallo por kg de Masa'!$N$37 -> 0.29155744 | R19: =IFERROR((1-F19)*P19+F19*Q19,"") -> 0.17905744 | S19: 6 | T19: 3 | U19: =IFERROR(S19*(1-F19),"") -> 4.5 | V19: =IFERROR(S19*F19,"") -> 1.5 | W19: =IFERROR(T19*(1-F19),"") -> 2.25 | X19: =IFERROR(T19*F19,"") -> 0.75 | Y19: ='Escandallo por kg de Masa'!$G$37 -> 0.18947368 | Z19: gluten
A20: CH4 · Churro suelto | B20: Churros y porras | C20: 2026 | D20: 0.3 | E20: CUS-16 | F20: 1 | G20: No | H20: Comida para llevar | I20: ='Parámetros'!$B$5 -> 0.1 | J20: ='Parámetros'!$B$6 -> 0.1 | K20: =IFERROR(D20/(1+I20),"") -> 0.27272727 | L20: =IFERROR(D20/(1+J20),"") -> 0.27272727 | M20: =IF(G20="Sí",IFERROR('Parámetros'!$B$25/(1+'Parámetros'!$B$8),""),0) -> 0 | N20: =IFERROR(L20+M20,"") -> 0.27272727 | O20: =IFERROR((1-F20)*K20+F20*N20,"") -> 0.27272727 | P20: ='Escandallo por kg de Masa'!$M$38 -> 0.015728604 | Q20: ='Escandallo por kg de Masa'!$N$38 -> 0.035728604 | R20: =IFERROR((1-F20)*P20+F20*Q20,"") -> 0.035728604 | S20: 6 | T20: 4 | U20: =IFERROR(S20*(1-F20),"") -> 0 | V20: =IFERROR(S20*F20,"") -> 6 | W20: =IFERROR(T20*(1-F20),"") -> 0 | X20: =IFERROR(T20*F20,"") -> 4 | Y20: ='Escandallo por kg de Masa'!$G$38 -> 0.021052632 | Z20: gluten
A21: CH5 · Porra suelta | B21: Churros y porras | C21: 2026 | D21: 0.6 | E21: CUS-16 | F21: 1 | G21: No | H21: Comida para llevar | I21: ='Parámetros'!$B$5 -> 0.1 | J21: ='Parámetros'!$B$6 -> 0.1 | K21: =IFERROR(D21/(1+I21),"") -> 0.54545455 | L21: =IFERROR(D21/(1+J21),"") -> 0.54545455 | M21: =IF(G21="Sí",IFERROR('Parámetros'!$B$25/(1+'Parámetros'!$B$8),""),0) -> 0 | N21: =IFERROR(L21+M21,"") -> 0.54545455 | O21: =IFERROR((1-F21)*K21+F21*N21,"") -> 0.54545455 | P21: ='Escandallo por kg de Masa'!$M$39 -> 0.047185812 | Q21: ='Escandallo por kg de Masa'!$N$39 -> 0.067185812 | R21: =IFERROR((1-F21)*P21+F21*Q21,"") -> 0.067185812 | S21: 3 | T21: 2 | U21: =IFERROR(S21*(1-F21),"") -> 0 | V21: =IFERROR(S21*F21,"") -> 3 | W21: =IFERROR(T21*(1-F21),"") -> 0 | X21: =IFERROR(T21*F21,"") -> 2 | Y21: ='Escandallo por kg de Masa'!$G$39 -> 0.063157895 | Z21: gluten
A22: CH6 · Docena de churros para llevar | B22: Churros y porras | C22: 2026 | D22: 3.5 | E22: supuesto declarado | F22: 1 | G22: No | H22: Comida para llevar | I22: ='Parámetros'!$B$5 -> 0.1 | J22: ='Parámetros'!$B$6 -> 0.1 | K22: =IFERROR(D22/(1+I22),"") -> 3.1818182 | L22: =IFERROR(D22/(1+J22),"") -> 3.1818182 | M22: =IF(G22="Sí",IFERROR('Parámetros'!$B$25/(1+'Parámetros'!$B$8),""),0) -> 0 | N22: =IFERROR(L22+M22,"") -> 3.1818182 | O22: =IFERROR((1-F22)*K22+F22*N22,"") -> 3.1818182 | P22: ='Escandallo por kg de Masa'!$M$40 -> 0.18874325 | Q22: ='Escandallo por kg de Masa'!$N$40 -> 0.33874325 | R22: =IFERROR((1-F22)*P22+F22*Q22,"") -> 0.33874325 | S22: 6 | T22: 3 | U22: =IFERROR(S22*(1-F22),"") -> 0 | V22: =IFERROR(S22*F22,"") -> 6 | W22: =IFERROR(T22*(1-F22),"") -> 0 | X22: =IFERROR(T22*F22,"") -> 3 | Y22: ='Escandallo por kg de Masa'!$G$40 -> 0.25263158 | Z22: gluten
A23: CH7 · Kilo de churros para llevar | B23: Churros y porras | C23: 2026 | D23: 10 | E23: supuesto declarado | F23: 1 | G23: No | H23: Comida para llevar | I23: ='Parámetros'!$B$5 -> 0.1 | J23: ='Parámetros'!$B$6 -> 0.1 | K23: =IFERROR(D23/(1+I23),"") -> 9.0909091 | L23: =IFERROR(D23/(1+J23),"") -> 9.0909091 | M23: =IF(G23="Sí",IFERROR('Parámetros'!$B$25/(1+'Parámetros'!$B$8),""),0) -> 0 | N23: =IFERROR(L23+M23,"") -> 9.0909091 | O23: =IFERROR((1-F23)*K23+F23*N23,"") -> 9.0909091 | P23: ='Escandallo por kg de Masa'!$M$41 -> 0.87381134 | Q23: ='Escandallo por kg de Masa'!$N$41 -> 1.1238113 | R23: =IFERROR((1-F23)*P23+F23*Q23,"") -> 1.1238113 | S23: 2 | T23: 1 | U23: =IFERROR(S23*(1-F23),"") -> 0 | V23: =IFERROR(S23*F23,"") -> 2 | W23: =IFERROR(T23*(1-F23),"") -> 0 | X23: =IFERROR(T23*F23,"") -> 1 | Y23: ='Escandallo por kg de Masa'!$G$41 -> 1.1695906 | Z23: gluten
A24: RE1 · Churro relleno de chocolate (ud) | B24: Rellenos y especiales | C24: 2026 | D24: 1.2 | E24: supuesto declarado | F24: 0 | G24: No | H24: Comida para llevar | I24: ='Parámetros'!$B$5 -> 0.1 | J24: ='Parámetros'!$B$6 -> 0.1 | K24: =IFERROR(D24/(1+I24),"") -> 1.0909091 | L24: =IFERROR(D24/(1+J24),"") -> 1.0909091 | M24: =IF(G24="Sí",IFERROR('Parámetros'!$B$25/(1+'Parámetros'!$B$8),""),0) -> 0 | N24: =IFERROR(L24+M24,"") -> 1.0909091 | O24: =IFERROR((1-F24)*K24+F24*N24,"") -> 1.0909091 | P24: ='Escandallo por kg de Masa'!$M$42 -> 0.17718581 | Q24: ='Escandallo por kg de Masa'!$N$42 -> 0.17718581 | R24: =IFERROR((1-F24)*P24+F24*Q24,"") -> 0.17718581 | S24: 3 | T24: 2 | U24: =IFERROR(S24*(1-F24),"") -> 3 | V24: =IFERROR(S24*F24,"") -> 0 | W24: =IFERROR(T24*(1-F24),"") -> 2 | X24: =IFERROR(T24*F24,"") -> 0 | Y24: ='Escandallo por kg de Masa'!$G$42 -> 0.063157895 | Z24: gluten, leche, soja
A25: RE2 · Ración de churros con cobertura de chocolate (6 uds) | B25: Rellenos y especiales | C25: 2026 | D25: 3.5 | E25: supuesto declarado | F25: 0 | G25: No | H25: Comida para llevar | I25: ='Parámetros'!$B$5 -> 0.1 | J25: ='Parámetros'!$B$6 -> 0.1 | K25: =IFERROR(D25/(1+I25),"") -> 3.1818182 | L25: =IFERROR(D25/(1+J25),"") -> 3.1818182 | M25: =IF(G25="Sí",IFERROR('Parámetros'!$B$25/(1+'Parámetros'!$B$8),""),0) -> 0 | N25: =IFERROR(L25+M25,"") -> 3.1818182 | O25: =IFERROR((1-F25)*K25+F25*N25,"") -> 3.1818182 | P25: ='Escandallo por kg de Masa'!$M$43 -> 0.28937162 | Q25: ='Escandallo por kg de Masa'!$N$43 -> 0.28937162 | R25: =IFERROR((1-F25)*P25+F25*Q25,"") -> 0.28937162 | S25: 2 | T25: 1 | U25: =IFERROR(S25*(1-F25),"") -> 2 | V25: =IFERROR(S25*F25,"") -> 0 | W25: =IFERROR(T25*(1-F25),"") -> 1 | X25: =IFERROR(T25*F25,"") -> 0 | Y25: ='Escandallo por kg de Masa'!$G$43 -> 0.12631579 | Z25: gluten, leche, soja
A26: CT1 · Chocolate a la taza en barra | B26: Chocolate a la taza | C26: 2026 | D26: 2 | E26: CUS-15 | F26: 0 | G26: No | H26: Chocolate para llevar (zona gris) | I26: ='Parámetros'!$B$5 -> 0.1 | J26: ='Parámetros'!$B$7 -> 0.1 | K26: =IFERROR(D26/(1+I26),"") -> 1.8181818 | L26: =IFERROR(D26/(1+J26),"") -> 1.8181818 | M26: =IF(G26="Sí",IFERROR('Parámetros'!$B$25/(1+'Parámetros'!$B$8),""),0) -> 0 | N26: =IFERROR(L26+M26,"") -> 1.8181818 | O26: =IFERROR((1-F26)*K26+F26*N26,"") -> 1.8181818 | P26: ='Escandallo por kg de Masa'!$M$44 -> 0.43744186 | Q26: ='Escandallo por kg de Masa'!$N$44 -> 0.43744186 | R26: =IFERROR((1-F26)*P26+F26*Q26,"") -> 0.43744186 | S26: 12 | T26: 4 | U26: =IFERROR(S26*(1-F26),"") -> 12 | V26: =IFERROR(S26*F26,"") -> 0 | W26: =IFERROR(T26*(1-F26),"") -> 4 | X26: =IFERROR(T26*F26,"") -> 0 | Y26: ='Escandallo por kg de Masa'!$G$44 -> 0 | Z26: leche
A27: CT2 · Chocolate a la taza en terraza | B27: Chocolate a la taza | C27: 2026 | D27: 2.5 | E27: CUS-15 | F27: 0 | G27: No | H27: Chocolate para llevar (zona gris) | I27: ='Parámetros'!$B$5 -> 0.1 | J27: ='Parámetros'!$B$7 -> 0.1 | K27: =IFERROR(D27/(1+I27),"") -> 2.2727273 | L27: =IFERROR(D27/(1+J27),"") -> 2.2727273 | M27: =IF(G27="Sí",IFERROR('Parámetros'!$B$25/(1+'Parámetros'!$B$8),""),0) -> 0 | N27: =IFERROR(L27+M27,"") -> 2.2727273 | O27: =IFERROR((1-F27)*K27+F27*N27,"") -> 2.2727273 | P27: ='Escandallo por kg de Masa'!$M$45 -> 0.43744186 | Q27: ='Escandallo por kg de Masa'!$N$45 -> 0.43744186 | R27: =IFERROR((1-F27)*P27+F27*Q27,"") -> 0.43744186 | S27: 4 | T27: 2 | U27: =IFERROR(S27*(1-F27),"") -> 4 | V27: =IFERROR(S27*F27,"") -> 0 | W27: =IFERROR(T27*(1-F27),"") -> 2 | X27: =IFERROR(T27*F27,"") -> 0 | Y27: ='Escandallo por kg de Masa'!$G$45 -> 0 | Z27: leche
A28: CT3 · Chocolate con churros (taza y ración de 6) | B28: Chocolate a la taza | C28: 2026 | D28: 3.8 | E28: supuesto declarado | F28: 0 | G28: No | H28: Chocolate para llevar (zona gris) | I28: ='Parámetros'!$B$5 -> 0.1 | J28: ='Parámetros'!$B$7 -> 0.1 | K28: =IFERROR(D28/(1+I28),"") -> 3.4545455 | L28: =IFERROR(D28/(1+J28),"") -> 3.4545455 | M28: =IF(G28="Sí",IFERROR('Parámetros'!$B$25/(1+'Parámetros'!$B$8),""),0) -> 0 | N28: =IFERROR(L28+M28,"") -> 3.4545455 | O28: =IFERROR((1-F28)*K28+F28*N28,"") -> 3.4545455 | P28: ='Escandallo por kg de Masa'!$M$46 -> 0.53181349 | Q28: ='Escandallo por kg de Masa'!$N$46 -> 0.53181349 | R28: =IFERROR((1-F28)*P28+F28*Q28,"") -> 0.53181349 | S28: 10 | T28: 4 | U28: =IFERROR(S28*(1-F28),"") -> 10 | V28: =IFERROR(S28*F28,"") -> 0 | W28: =IFERROR(T28*(1-F28),"") -> 4 | X28: =IFERROR(T28*F28,"") -> 0 | Y28: ='Escandallo por kg de Masa'!$G$46 -> 0.12631579 | Z28: gluten, leche
A29: CT4 · Chocolate a la taza para llevar | B29: Chocolate a la taza | C29: 2026 | D29: 2.2 | E29: supuesto declarado | F29: 1 | G29: Sí | H29: Chocolate para llevar (zona gris) | I29: ='Parámetros'!$B$5 -> 0.1 | J29: ='Parámetros'!$B$7 -> 0.1 | K29: =IFERROR(D29/(1+I29),"") -> 2 | L29: =IFERROR(D29/(1+J29),"") -> 2 | M29: =IF(G29="Sí",IFERROR('Parámetros'!$B$25/(1+'Parámetros'!$B$8),""),0) -> 0.090909091 | N29: =IFERROR(L29+M29,"") -> 2.0909091 | O29: =IFERROR((1-F29)*K29+F29*N29,"") -> 2.0909091 | P29: ='Escandallo por kg de Masa'!$M$47 -> 0.43744186 | Q29: ='Escandallo por kg de Masa'!$N$47 -> 0.51744186 | R29: =IFERROR((1-F29)*P29+F29*Q29,"") -> 0.51744186 | S29: 3 | T29: 1 | U29: =IFERROR(S29*(1-F29),"") -> 0 | V29: =IFERROR(S29*F29,"") -> 3 | W29: =IFERROR(T29*(1-F29),"") -> 0 | X29: =IFERROR(T29*F29,"") -> 1 | Y29: ='Escandallo por kg de Masa'!$G$47 -> 0 | Z29: leche
A30: CT5 · Media taza de chocolate | B30: Chocolate a la taza | C30: 2026 | D30: 1.3 | E30: supuesto declarado | F30: 0 | G30: No | H30: Chocolate para llevar (zona gris) | I30: ='Parámetros'!$B$5 -> 0.1 | J30: ='Parámetros'!$B$7 -> 0.1 | K30: =IFERROR(D30/(1+I30),"") -> 1.1818182 | L30: =IFERROR(D30/(1+J30),"") -> 1.1818182 | M30: =IF(G30="Sí",IFERROR('Parámetros'!$B$25/(1+'Parámetros'!$B$8),""),0) -> 0 | N30: =IFERROR(L30+M30,"") -> 1.1818182 | O30: =IFERROR((1-F30)*K30+F30*N30,"") -> 1.1818182 | P30: ='Escandallo por kg de Masa'!$M$48 -> 0.26246512 | Q30: ='Escandallo por kg de Masa'!$N$48 -> 0.26246512 | R30: =IFERROR((1-F30)*P30+F30*Q30,"") -> 0.26246512 | S30: 2 | T30: 1 | U30: =IFERROR(S30*(1-F30),"") -> 2 | V30: =IFERROR(S30*F30,"") -> 0 | W30: =IFERROR(T30*(1-F30),"") -> 1 | X30: =IFERROR(T30*F30,"") -> 0 | Y30: ='Escandallo por kg de Masa'!$G$48 -> 0 | Z30: leche
A31: CB1 · Café solo | B31: Cafés y bebidas | C31: 2026 | D31: 1.3 | E31: supuesto declarado | F31: 0.25 | G31: Sí | H31: Bebida para llevar (zona gris) | I31: ='Parámetros'!$B$5 -> 0.1 | J31: ='Parámetros'!$B$8 -> 0.1 | K31: =IFERROR(D31/(1+I31),"") -> 1.1818182 | L31: =IFERROR(D31/(1+J31),"") -> 1.1818182 | M31: =IF(G31="Sí",IFERROR('Parámetros'!$B$25/(1+'Parámetros'!$B$8),""),0) -> 0.090909091 | N31: =IFERROR(L31+M31,"") -> 1.2727273 | O31: =IFERROR((1-F31)*K31+F31*N31,"") -> 1.2045455 | P31: ='Escandallo por kg de Masa'!$M$49 -> 0.134 | Q31: ='Escandallo por kg de Masa'!$N$49 -> 0.214 | R31: =IFERROR((1-F31)*P31+F31*Q31,"") -> 0.154 | S31: 4 | T31: 4 | U31: =IFERROR(S31*(1-F31),"") -> 3 | V31: =IFERROR(S31*F31,"") -> 1 | W31: =IFERROR(T31*(1-F31),"") -> 3 | X31: =IFERROR(T31*F31,"") -> 1 | Y31: ='Escandallo por kg de Masa'!$G$49 -> 0 | Z31: ninguno en la receta del ejemplo
A32: CB2 · Café con leche | B32: Cafés y bebidas | C32: 2026 | D32: 1.6 | E32: supuesto declarado | F32: 0.4 | G32: Sí | H32: Bebida para llevar (zona gris) | I32: ='Parámetros'!$B$5 -> 0.1 | J32: ='Parámetros'!$B$8 -> 0.1 | K32: =IFERROR(D32/(1+I32),"") -> 1.4545455 | L32: =IFERROR(D32/(1+J32),"") -> 1.4545455 | M32: =IF(G32="Sí",IFERROR('Parámetros'!$B$25/(1+'Parámetros'!$B$8),""),0) -> 0.090909091 | N32: =IFERROR(L32+M32,"") -> 1.5454545 | O32: =IFERROR((1-F32)*K32+F32*N32,"") -> 1.4909091 | P32: ='Escandallo por kg de Masa'!$M$50 -> 0.2615 | Q32: ='Escandallo por kg de Masa'!$N$50 -> 0.3415 | R32: =IFERROR((1-F32)*P32+F32*Q32,"") -> 0.2935 | S32: 6 | T32: 5 | U32: =IFERROR(S32*(1-F32),"") -> 3.6 | V32: =IFERROR(S32*F32,"") -> 2.4 | W32: =IFERROR(T32*(1-F32),"") -> 3 | X32: =IFERROR(T32*F32,"") -> 2 | Y32: ='Escandallo por kg de Masa'!$G$50 -> 0 | Z32: leche
A33: CB3 · Infusión | B33: Cafés y bebidas | C33: 2026 | D33: 1.4 | E33: supuesto declarado | F33: 0 | G33: No | H33: Bebida para llevar (zona gris) | I33: ='Parámetros'!$B$5 -> 0.1 | J33: ='Parámetros'!$B$8 -> 0.1 | K33: =IFERROR(D33/(1+I33),"") -> 1.2727273 | L33: =IFERROR(D33/(1+J33),"") -> 1.2727273 | M33: =IF(G33="Sí",IFERROR('Parámetros'!$B$25/(1+'Parámetros'!$B$8),""),0) -> 0 | N33: =IFERROR(L33+M33,"") -> 1.2727273 | O33: =IFERROR((1-F33)*K33+F33*N33,"") -> 1.2727273 | P33: ='Escandallo por kg de Masa'!$M$51 -> 0.068 | Q33: ='Escandallo por kg de Masa'!$N$51 -> 0.068 | R33: =IFERROR((1-F33)*P33+F33*Q33,"") -> 0.068 | S33: 1 | T33: 1 | U33: =IFERROR(S33*(1-F33),"") -> 1 | V33: =IFERROR(S33*F33,"") -> 0 | W33: =IFERROR(T33*(1-F33),"") -> 1 | X33: =IFERROR(T33*F33,"") -> 0 | Y33: ='Escandallo por kg de Masa'!$G$51 -> 0 | Z33: ninguno en la receta del ejemplo
A34: CB4 · Leche con cacao | B34: Cafés y bebidas | C34: 2026 | D34: 1.6 | E34: supuesto declarado | F34: 0.3 | G34: Sí | H34: Bebida para llevar (zona gris) | I34: ='Parámetros'!$B$5 -> 0.1 | J34: ='Parámetros'!$B$8 -> 0.1 | K34: =IFERROR(D34/(1+I34),"") -> 1.4545455 | L34: =IFERROR(D34/(1+J34),"") -> 1.4545455 | M34: =IF(G34="Sí",IFERROR('Parámetros'!$B$25/(1+'Parámetros'!$B$8),""),0) -> 0.090909091 | N34: =IFERROR(L34+M34,"") -> 1.5454545 | O34: =IFERROR((1-F34)*K34+F34*N34,"") -> 1.4818182 | P34: ='Escandallo por kg de Masa'!$M$52 -> 0.26 | Q34: ='Escandallo por kg de Masa'!$N$52 -> 0.34 | R34: =IFERROR((1-F34)*P34+F34*Q34,"") -> 0.284 | S34: 2 | T34: 2 | U34: =IFERROR(S34*(1-F34),"") -> 1.4 | V34: =IFERROR(S34*F34,"") -> 0.6 | W34: =IFERROR(T34*(1-F34),"") -> 1.4 | X34: =IFERROR(T34*F34,"") -> 0.6 | Y34: ='Escandallo por kg de Masa'!$G$52 -> 0 | Z34: leche
A35: CB5 · Zumo de naranja natural | B35: Cafés y bebidas | C35: 2026 | D35: 2.5 | E35: supuesto declarado | F35: 0.25 | G35: Sí | H35: Bebida para llevar (zona gris) | I35: ='Parámetros'!$B$5 -> 0.1 | J35: ='Parámetros'!$B$8 -> 0.1 | K35: =IFERROR(D35/(1+I35),"") -> 2.2727273 | L35: =IFERROR(D35/(1+J35),"") -> 2.2727273 | M35: =IF(G35="Sí",IFERROR('Parámetros'!$B$25/(1+'Parámetros'!$B$8),""),0) -> 0.090909091 | N35: =IFERROR(L35+M35,"") -> 2.3636364 | O35: =IFERROR((1-F35)*K35+F35*N35,"") -> 2.2954545 | P35: ='Escandallo por kg de Masa'!$M$53 -> 0.495 | Q35: ='Escandallo por kg de Masa'!$N$53 -> 0.575 | R35: =IFERROR((1-F35)*P35+F35*Q35,"") -> 0.515 | S35: 2 | T35: 4 | U35: =IFERROR(S35*(1-F35),"") -> 1.5 | V35: =IFERROR(S35*F35,"") -> 0.5 | W35: =IFERROR(T35*(1-F35),"") -> 3 | X35: =IFERROR(T35*F35,"") -> 1 | Y35: ='Escandallo por kg de Masa'!$G$53 -> 0 | Z35: ninguno en la receta del ejemplo
A36: CB6 · Agua (botella de 50 cl) | B36: Cafés y bebidas | C36: 2026 | D36: 1.2 | E36: supuesto declarado | F36: 0.5 | G36: No | H36: Bebida para llevar (zona gris) | I36: ='Parámetros'!$B$5 -> 0.1 | J36: ='Parámetros'!$B$8 -> 0.1 | K36: =IFERROR(D36/(1+I36),"") -> 1.0909091 | L36: =IFERROR(D36/(1+J36),"") -> 1.0909091 | M36: =IF(G36="Sí",IFERROR('Parámetros'!$B$25/(1+'Parámetros'!$B$8),""),0) -> 0 | N36: =IFERROR(L36+M36,"") -> 1.0909091 | O36: =IFERROR((1-F36)*K36+F36*N36,"") -> 1.0909091 | P36: ='Escandallo por kg de Masa'!$M$54 -> 0.22 | Q36: ='Escandallo por kg de Masa'!$N$54 -> 0.22 | R36: =IFERROR((1-F36)*P36+F36*Q36,"") -> 0.22 | S36: 2 | T36: 5 | U36: =IFERROR(S36*(1-F36),"") -> 1 | V36: =IFERROR(S36*F36,"") -> 1 | W36: =IFERROR(T36*(1-F36),"") -> 2.5 | X36: =IFERROR(T36*F36,"") -> 2.5 | Y36: ='Escandallo por kg de Masa'!$G$54 -> 0 | Z36: ninguno en la receta del ejemplo
A37: CV1 · Granizado | B37: Carta de verano | C37: 2026 | D37: 3 | E37: CUS-11 | F37: 0.4 | G37: Sí | H37: Refresco azucarado para llevar | I37: ='Parámetros'!$B$5 -> 0.1 | J37: ='Parámetros'!$B$9 -> 0.21 | K37: =IFERROR(D37/(1+I37),"") -> 2.7272727 | L37: =IFERROR(D37/(1+J37),"") -> 2.4793388 | M37: =IF(G37="Sí",IFERROR('Parámetros'!$B$25/(1+'Parámetros'!$B$8),""),0) -> 0.090909091 | N37: =IFERROR(L37+M37,"") -> 2.5702479 | O37: =IFERROR((1-F37)*K37+F37*N37,"") -> 2.6644628 | P37: ='Escandallo por kg de Masa'!$M$55 -> 0.45 | Q37: ='Escandallo por kg de Masa'!$N$55 -> 0.53 | R37: =IFERROR((1-F37)*P37+F37*Q37,"") -> 0.482 | S37: 0 | T37: 12 | U37: =IFERROR(S37*(1-F37),"") -> 0 | V37: =IFERROR(S37*F37,"") -> 0 | W37: =IFERROR(T37*(1-F37),"") -> 7.2 | X37: =IFERROR(T37*F37,"") -> 4.8 | Y37: ='Escandallo por kg de Masa'!$G$55 -> 0 | Z37: ninguno en la receta del ejemplo
A38: CV2 · Horchata | B38: Carta de verano | C38: 2026 | D38: 3 | E38: CUS-11 | F38: 0.4 | G38: Sí | H38: Refresco azucarado para llevar | I38: ='Parámetros'!$B$5 -> 0.1 | J38: ='Parámetros'!$B$9 -> 0.21 | K38: =IFERROR(D38/(1+I38),"") -> 2.7272727 | L38: =IFERROR(D38/(1+J38),"") -> 2.4793388 | M38: =IF(G38="Sí",IFERROR('Parámetros'!$B$25/(1+'Parámetros'!$B$8),""),0) -> 0.090909091 | N38: =IFERROR(L38+M38,"") -> 2.5702479 | O38: =IFERROR((1-F38)*K38+F38*N38,"") -> 2.6644628 | P38: ='Escandallo por kg de Masa'!$M$56 -> 0.55 | Q38: ='Escandallo por kg de Masa'!$N$56 -> 0.63 | R38: =IFERROR((1-F38)*P38+F38*Q38,"") -> 0.582 | S38: 0 | T38: 10 | U38: =IFERROR(S38*(1-F38),"") -> 0 | V38: =IFERROR(S38*F38,"") -> 0 | W38: =IFERROR(T38*(1-F38),"") -> 6 | X38: =IFERROR(T38*F38,"") -> 4 | Y38: ='Escandallo por kg de Masa'!$G$56 -> 0 | Z38: ninguno en la receta del ejemplo
A39: CV3 · Helado (bola) | B39: Carta de verano | C39: 2026 | D39: 2.2 | E39: supuesto declarado | F39: 0 | G39: No | H39: Comida para llevar | I39: ='Parámetros'!$B$5 -> 0.1 | J39: ='Parámetros'!$B$6 -> 0.1 | K39: =IFERROR(D39/(1+I39),"") -> 2 | L39: =IFERROR(D39/(1+J39),"") -> 2 | M39: =IF(G39="Sí",IFERROR('Parámetros'!$B$25/(1+'Parámetros'!$B$8),""),0) -> 0 | N39: =IFERROR(L39+M39,"") -> 2 | O39: =IFERROR((1-F39)*K39+F39*N39,"") -> 2 | P39: ='Escandallo por kg de Masa'!$M$57 -> 0.45 | Q39: ='Escandallo por kg de Masa'!$N$57 -> 0.45 | R39: =IFERROR((1-F39)*P39+F39*Q39,"") -> 0.45 | S39: 0 | T39: 9 | U39: =IFERROR(S39*(1-F39),"") -> 0 | V39: =IFERROR(S39*F39,"") -> 0 | W39: =IFERROR(T39*(1-F39),"") -> 9 | X39: =IFERROR(T39*F39,"") -> 0 | Y39: ='Escandallo por kg de Masa'!$G$57 -> 0 | Z39: leche
A40: CV4 · Batido | B40: Carta de verano | C40: 2026 | D40: 4 | E40: CUS-11 | F40: 0.2 | G40: Sí | H40: Bebida para llevar (zona gris) | I40: ='Parámetros'!$B$5 -> 0.1 | J40: ='Parámetros'!$B$8 -> 0.1 | K40: =IFERROR(D40/(1+I40),"") -> 3.6363636 | L40: =IFERROR(D40/(1+J40),"") -> 3.6363636 | M40: =IF(G40="Sí",IFERROR('Parámetros'!$B$25/(1+'Parámetros'!$B$8),""),0) -> 0.090909091 | N40: =IFERROR(L40+M40,"") -> 3.7272727 | O40: =IFERROR((1-F40)*K40+F40*N40,"") -> 3.6545455 | P40: ='Escandallo por kg de Masa'!$M$58 -> 0.7125 | Q40: ='Escandallo por kg de Masa'!$N$58 -> 0.7925 | R40: =IFERROR((1-F40)*P40+F40*Q40,"") -> 0.7285 | S40: 0 | T40: 5 | U40: =IFERROR(S40*(1-F40),"") -> 0 | V40: =IFERROR(S40*F40,"") -> 0 | W40: =IFERROR(T40*(1-F40),"") -> 4 | X40: =IFERROR(T40*F40,"") -> 1 | Y40: ='Escandallo por kg de Masa'!$G$58 -> 0 | Z40: leche
A41: TOTAL | S41: =SUM(S17:S40) -> 100 | T41: =SUM(T17:T40) -> 100 | U41: =SUM(U17:U40) -> 70 | V41: =SUM(V17:V40) -> 30 | W41: =SUM(W17:W40) -> 69.55 | X41: =SUM(X17:X40) -> 30.45
A42: Vaso para llevar cobrado aparte (fila propia del ticket): el importe está en «Parámetros» y se suma al ingreso de cada bebida que lo lleva.
A45: Listas de validación (no las borres: las usan los desplegables)
A46: Sí o no
A47: Sí
A48: No
A50: Versión 1.0 · octubre 2026 · aichef.pro/guia-churreria-chocolateria · info@aichef.pro

Sheet Los Dos Márgenes
A1: Los Dos Márgenes
A2: AI Chef Pro · aichef.pro — Cómo Montar una Churrería-Chocolatería
A3: Dos márgenes que no son la misma cosa, al lado de las dos cifras publicadas con las que se suelen comparar. Cada cifra, con su definición pegada.
A4: Tus Dos Márgenes (Salen de Tu Escandallo)
A5: Margen | B5: Invierno | C5: Julio y agosto | D5: Definición
A6: 1. Margen sobre materia prima | B6: ='Mix y Ticket Canal y Temporada'!$D$9 -> 0.86913682 | C6: ='Mix y Ticket Canal y Temporada'!$G$9 -> 0.8375419 | D6: 1 menos (materia prima más aceite absorbido) entre el ticket SIN IVA, con el mix de la temporada. Es el comparable al «más del 60 % en producto». Es el que usa el plan financiero (libro 6).
A7: 2. Margen tras aceite y mano de obra | B7: =IFERROR(1-('Mix y Ticket Canal y Temporada'!$D$7+'Coste Hora'!$B$8)/'Mix y Ticket Canal y Temporada'!$D$6,"") -> 0.4121387 | C7: =IFERROR(1-('Mix y Ticket Canal y Temporada'!$G$7+'Coste Hora'!$B$8)/'Mix y Ticket Canal y Temporada'!$G$6,"") -> 0.38993828 | D7: 1 menos (materia, aceite absorbido y mano de obra por ración, de la hoja «Coste Hora») entre el ticket SIN IVA. Sin renta, suministros ni amortización: no es la rentabilidad del negocio, que sale del libro 6.
A8: Margen 1 en euros por ración | B8: ='Mix y Ticket Canal y Temporada'!$D$8 -> 1.8785207 | C8: ='Mix y Ticket Canal y Temporada'!$G$8 -> 1.8482266
A9: Margen 2 en euros por ración | B9: =IFERROR('Mix y Ticket Canal y Temporada'!$D$6-'Mix y Ticket Canal y Temporada'!$D$7-'Coste Hora'!$B$8,"") -> 0.89078159 | C9: =IFERROR('Mix y Ticket Canal y Temporada'!$G$6-'Mix y Ticket Canal y Temporada'!$G$7-'Coste Hora'!$B$8,"") -> 0.86048744
A11: Con Qué se Suelen Comparar (Cada Una con Su Definición)
A12: Quién lo publica | B12: Cifra (como número) | C12: Fuente | D12: Qué mide de verdad
A13: Loomis Pay (proveedor de TPV) | B13: 0.6 | C13: CUS-01 | D13: Dice: márgenes superiores al 60 % en producto. Qué mide: margen sobre materia prima, sin método publicado.
A14: Javier, gestor de La Artesana (Palma) | B14: 0.5 | C14: CUS-30 | D14: Dice: «un poquito más del 50 %». Qué mide: rentabilidad declarada de palabra, no un margen sobre materia prima.
A15: Fiabilidad baja la del «un poquito más del 50 %»: lo dice de palabra el gestor de La Artesana en una entrevista, sin método. Ninguna de las dos cifras entra en el plan financiero.
A16: La Comparación, en Invierno
A18: Tu margen 1 frente a «más del 60 % en producto» | B18: =IF(NOT(ISNUMBER(B6)),"",IF(B6>B13,"Por encima: tu carta deja más sobre materia que esa referencia","Por debajo: revisa precios o mermas antes de abrir")) -> Por encima: tu carta deja más sobre materia que esa referencia
A19: Tu margen 2 frente al «un poquito más del 50 %» | B19: =IF(NOT(ISNUMBER(B7)),"",IF(B7>B14,"Por encima, con cautela: aquella cifra es rentabilidad declarada, no este margen","Por debajo, con cautela: aquella cifra es rentabilidad declarada, no este margen")) -> Por debajo, con cautela: aquella cifra es rentabilidad declarada, no este margen
A20: Puntos de diferencia del margen 1 | B20: =IFERROR(B6-B13,"") -> 0.26913682
A21: Puntos de diferencia del margen 2 | B21: =IFERROR(B7-B14,"") -> -0.087861305
A23: Por qué dos márgenes: el primero dice si el PRECIO cubre la materia; el segundo, si además cubre las manos que la fríen. Un margen sobre materia muy alto es normal en una churrería, porque la masa es barata: lo caro es la madrugada. Por eso el plan financiero toma el margen 1 de tu escandallo y resta la nómina aparte.
A25: Versión 1.0 · octubre 2026 · aichef.pro/guia-churreria-chocolateria · info@aichef.pro

Sheet Decisión de Surtido
A1: Decisión de Surtido
A2: AI Chef Pro · aichef.pro — Cómo Montar una Churrería-Chocolatería
A3: Margen en EUROS por unidad contra rotación. Los dos umbrales están en «Parámetros» y son criterio de la casa.
A6: Id y referencia | B6: Familia | C6: Ingreso medio SIN IVA (EUR) | D6: Materia media (EUR) | E6: Margen por unidad (EUR) | F6: Margen sobre ingreso | G6: Mix de invierno (%) | H6: Mix de julio y agosto (%) | I6: Margen cada 100 raciones de invierno (EUR) | J6: ¿Margen por encima del umbral? | K6: ¿Rotación por encima del umbral? | L6: Veredicto | M6: Qué hacer
A7: CH1 · Ración de churros (6 uds) | B7: Churros y porras | C7: ='Mix y Ticket Canal y Temporada'!$O$17 -> 2.3636364 | D7: ='Mix y Ticket Canal y Temporada'!$R$17 -> 0.11687162 | E7: =IFERROR(C7-D7,"") -> 2.2467647 | F7: =IFERROR(E7/C7,"") -> 0.95055431 | G7: ='Mix y Ticket Canal y Temporada'!$S$17 -> 20 | H7: ='Mix y Ticket Canal y Temporada'!$T$17 -> 12 | I7: =IFERROR(E7*G7,"") -> 44.935295 | J7: =IF(NOT(ISNUMBER(E7)),"",IF(E7>='Parámetros'!$B$28,"Sí","No")) -> Sí | K7: =IF(MAX(G7,H7)>='Parámetros'!$B$29,"Sí","No") -> Sí | L7: =IF(OR(J7="",K7=""),"",IF(AND(J7="Sí",K7="Sí"),"Mantener",IF(AND(J7="No",K7="Sí"),"Revisar precio",IF(J7="Sí","Vigilar rotación","Retirar")))) -> Mantener | M7: Si sale «Revisar precio», mira primero el PVP y el canal en «Mix y Ticket Canal y Temporada»; si sale «Vigilar rotación», cuánto stock y cuánta carta ocupa.
A8: CH2 · Media ración de churros (3 uds) | B8: Churros y porras | C8: ='Mix y Ticket Canal y Temporada'!$O$18 -> 1.2727273 | D8: ='Mix y Ticket Canal y Temporada'!$R$18 -> 0.047185812 | E8: =IFERROR(C8-D8,"") -> 1.2255415 | F8: =IFERROR(E8/C8,"") -> 0.96292543 | G8: ='Mix y Ticket Canal y Temporada'!$S$18 -> 4 | H8: ='Mix y Ticket Canal y Temporada'!$T$18 -> 3 | I8: =IFERROR(E8*G8,"") -> 4.9021658 | J8: =IF(NOT(ISNUMBER(E8)),"",IF(E8>='Parámetros'!$B$28,"Sí","No")) -> Sí | K8: =IF(MAX(G8,H8)>='Parámetros'!$B$29,"Sí","No") -> Sí | L8: =IF(OR(J8="",K8=""),"",IF(AND(J8="Sí",K8="Sí"),"Mantener",IF(AND(J8="No",K8="Sí"),"Revisar precio",IF(J8="Sí","Vigilar rotación","Retirar")))) -> Mantener | M8: Si sale «Revisar precio», mira primero el PVP y el canal en «Mix y Ticket Canal y Temporada»; si sale «Vigilar rotación», cuánto stock y cuánta carta ocupa.
A9: CH3 · Ración de porras (3 uds) | B9: Churros y porras | C9: ='Mix y Ticket Canal y Temporada'!$O$19 -> 2.4545455 | D9: ='Mix y Ticket Canal y Temporada'!$R$19 -> 0.17905744 | E9: =IFERROR(C9-D9,"") -> 2.275488 | F9: =IFERROR(E9/C9,"") -> 0.92705067 | G9: ='Mix y Ticket Canal y Temporada'!$S$19 -> 6 | H9: ='Mix y Ticket Canal y Temporada'!$T$19 -> 3 | I9: =IFERROR(E9*G9,"") -> 13.652928 | J9: =IF(NOT(ISNUMBER(E9)),"",IF(E9>='Parámetros'!$B$28,"Sí","No")) -> Sí | K9: =IF(MAX(G9,H9)>='Parámetros'!$B$29,"Sí","No") -> Sí | L9: =IF(OR(J9="",K9=""),"",IF(AND(J9="Sí",K9="Sí"),"Mantener",IF(AND(J9="No",K9="Sí"),"Revisar precio",IF(J9="Sí","Vigilar rotación","Retirar")))) -> Mantener | M9: Si sale «Revisar precio», mira primero el PVP y el canal en «Mix y Ticket Canal y Temporada»; si sale «Vigilar rotación», cuánto stock y cuánta carta ocupa.
A10: CH4 · Churro suelto | B10: Churros y porras | C10: ='Mix y Ticket Canal y Temporada'!$O$20 -> 0.27272727 | D10: ='Mix y Ticket Canal y Temporada'!$R$20 -> 0.035728604 | E10: =IFERROR(C10-D10,"") -> 0.23699867 | F10: =IFERROR(E10/C10,"") -> 0.86899512 | G10: ='Mix y Ticket Canal y Temporada'!$S$20 -> 6 | H10: ='Mix y Ticket Canal y Temporada'!$T$20 -> 4 | I10: =IFERROR(E10*G10,"") -> 1.421992 | J10: =IF(NOT(ISNUMBER(E10)),"",IF(E10>='Parámetros'!$B$28,"Sí","No")) -> No | K10: =IF(MAX(G10,H10)>='Parámetros'!$B$29,"Sí","No") -> Sí | L10: =IF(OR(J10="",K10=""),"",IF(AND(J10="Sí",K10="Sí"),"Mantener",IF(AND(J10="No",K10="Sí"),"Revisar precio",IF(J10="Sí","Vigilar rotación","Retirar")))) -> Revisar precio | M10: La pieza suelta deja poco por unidad y mucho por kilo de masa: mira la hoja «Ración, Docena o Kilo» antes de tocarle el precio.
A11: CH5 · Porra suelta | B11: Churros y porras | C11: ='Mix y Ticket Canal y Temporada'!$O$21 -> 0.54545455 | D11: ='Mix y Ticket Canal y Temporada'!$R$21 -> 0.067185812 | E11: =IFERROR(C11-D11,"") -> 0.47826873 | F11: =IFERROR(E11/C11,"") -> 0.87682601 | G11: ='Mix y Ticket Canal y Temporada'!$S$21 -> 3 | H11: ='Mix y Ticket Canal y Temporada'!$T$21 -> 2 | I11: =IFERROR(E11*G11,"") -> 1.4348062 | J11: =IF(NOT(ISNUMBER(E11)),"",IF(E11>='Parámetros'!$B$28,"Sí","No")) -> No | K11: =IF(MAX(G11,H11)>='Parámetros'!$B$29,"Sí","No") -> Sí | L11: =IF(OR(J11="",K11=""),"",IF(AND(J11="Sí",K11="Sí"),"Mantener",IF(AND(J11="No",K11="Sí"),"Revisar precio",IF(J11="Sí","Vigilar rotación","Retirar")))) -> Revisar precio | M11: La pieza suelta deja poco por unidad y mucho por kilo de masa: mira la hoja «Ración, Docena o Kilo» antes de tocarle el precio.
A12: CH6 · Docena de churros para llevar | B12: Churros y porras | C12: ='Mix y Ticket Canal y Temporada'!$O$22 -> 3.1818182 | D12: ='Mix y Ticket Canal y Temporada'!$R$22 -> 0.33874325 | E12: =IFERROR(C12-D12,"") -> 2.8430749 | F12: =IFERROR(E12/C12,"") -> 0.89353784 | G12: ='Mix y Ticket Canal y Temporada'!$S$22 -> 6 | H12: ='Mix y Ticket Canal y Temporada'!$T$22 -> 3 | I12: =IFERROR(E12*G12,"") -> 17.05845 | J12: =IF(NOT(ISNUMBER(E12)),"",IF(E12>='Parámetros'!$B$28,"Sí","No")) -> Sí | K12: =IF(MAX(G12,H12)>='Parámetros'!$B$29,"Sí","No") -> Sí | L12: =IF(OR(J12="",K12=""),"",IF(AND(J12="Sí",K12="Sí"),"Mantener",IF(AND(J12="No",K12="Sí"),"Revisar precio",IF(J12="Sí","Vigilar rotación","Retirar")))) -> Mantener | M12: Si sale «Revisar precio», mira primero el PVP y el canal en «Mix y Ticket Canal y Temporada»; si sale «Vigilar rotación», cuánto stock y cuánta carta ocupa.
A13: CH7 · Kilo de churros para llevar | B13: Churros y porras | C13: ='Mix y Ticket Canal y Temporada'!$O$23 -> 9.0909091 | D13: ='Mix y Ticket Canal y Temporada'!$R$23 -> 1.1238113 | E13: =IFERROR(C13-D13,"") -> 7.9670978 | F13: =IFERROR(E13/C13,"") -> 0.87638075 | G13: ='Mix y Ticket Canal y Temporada'!$S$23 -> 2 | H13: ='Mix y Ticket Canal y Temporada'!$T$23 -> 1 | I13: =IFERROR(E13*G13,"") -> 15.934196 | J13: =IF(NOT(ISNUMBER(E13)),"",IF(E13>='Parámetros'!$B$28,"Sí","No")) -> Sí | K13: =IF(MAX(G13,H13)>='Parámetros'!$B$29,"Sí","No") -> Sí | L13: =IF(OR(J13="",K13=""),"",IF(AND(J13="Sí",K13="Sí"),"Mantener",IF(AND(J13="No",K13="Sí"),"Revisar precio",IF(J13="Sí","Vigilar rotación","Retirar")))) -> Mantener | M13: Si sale «Revisar precio», mira primero el PVP y el canal en «Mix y Ticket Canal y Temporada»; si sale «Vigilar rotación», cuánto stock y cuánta carta ocupa.
A14: RE1 · Churro relleno de chocolate (ud) | B14: Rellenos y especiales | C14: ='Mix y Ticket Canal y Temporada'!$O$24 -> 1.0909091 | D14: ='Mix y Ticket Canal y Temporada'!$R$24 -> 0.17718581 | E14: =IFERROR(C14-D14,"") -> 0.91372328 | F14: =IFERROR(E14/C14,"") -> 0.83757967 | G14: ='Mix y Ticket Canal y Temporada'!$S$24 -> 3 | H14: ='Mix y Ticket Canal y Temporada'!$T$24 -> 2 | I14: =IFERROR(E14*G14,"") -> 2.7411698 | J14: =IF(NOT(ISNUMBER(E14)),"",IF(E14>='Parámetros'!$B$28,"Sí","No")) -> Sí | K14: =IF(MAX(G14,H14)>='Parámetros'!$B$29,"Sí","No") -> Sí | L14: =IF(OR(J14="",K14=""),"",IF(AND(J14="Sí",K14="Sí"),"Mantener",IF(AND(J14="No",K14="Sí"),"Revisar precio",IF(J14="Sí","Vigilar rotación","Retirar")))) -> Mantener | M14: Si sale «Revisar precio», mira primero el PVP y el canal en «Mix y Ticket Canal y Temporada»; si sale «Vigilar rotación», cuánto stock y cuánta carta ocupa.
A15: RE2 · Ración de churros con cobertura de chocolate (6 uds) | B15: Rellenos y especiales | C15: ='Mix y Ticket Canal y Temporada'!$O$25 -> 3.1818182 | D15: ='Mix y Ticket Canal y Temporada'!$R$25 -> 0.28937162 | E15: =IFERROR(C15-D15,"") -> 2.8924466 | F15: =IFERROR(E15/C15,"") -> 0.90905463 | G15: ='Mix y Ticket Canal y Temporada'!$S$25 -> 2 | H15: ='Mix y Ticket Canal y Temporada'!$T$25 -> 1 | I15: =IFERROR(E15*G15,"") -> 5.7848931 | J15: =IF(NOT(ISNUMBER(E15)),"",IF(E15>='Parámetros'!$B$28,"Sí","No")) -> Sí | K15: =IF(MAX(G15,H15)>='Parámetros'!$B$29,"Sí","No") -> Sí | L15: =IF(OR(J15="",K15=""),"",IF(AND(J15="Sí",K15="Sí"),"Mantener",IF(AND(J15="No",K15="Sí"),"Revisar precio",IF(J15="Sí","Vigilar rotación","Retirar")))) -> Mantener | M15: Si sale «Revisar precio», mira primero el PVP y el canal en «Mix y Ticket Canal y Temporada»; si sale «Vigilar rotación», cuánto stock y cuánta carta ocupa.
A16: CT1 · Chocolate a la taza en barra | B16: Chocolate a la taza | C16: ='Mix y Ticket Canal y Temporada'!$O$26 -> 1.8181818 | D16: ='Mix y Ticket Canal y Temporada'!$R$26 -> 0.43744186 | E16: =IFERROR(C16-D16,"") -> 1.38074 | F16: =IFERROR(E16/C16,"") -> 0.75940698 | G16: ='Mix y Ticket Canal y Temporada'!$S$26 -> 12 | H16: ='Mix y Ticket Canal y Temporada'!$T$26 -> 4 | I16: =IFERROR(E16*G16,"") -> 16.568879 | J16: =IF(NOT(ISNUMBER(E16)),"",IF(E16>='Parámetros'!$B$28,"Sí","No")) -> Sí | K16: =IF(MAX(G16,H16)>='Parámetros'!$B$29,"Sí","No") -> Sí | L16: =IF(OR(J16="",K16=""),"",IF(AND(J16="Sí",K16="Sí"),"Mantener",IF(AND(J16="No",K16="Sí"),"Revisar precio",IF(J16="Sí","Vigilar rotación","Retirar")))) -> Mantener | M16: Si sale «Revisar precio», mira primero el PVP y el canal en «Mix y Ticket Canal y Temporada»; si sale «Vigilar rotación», cuánto stock y cuánta carta ocupa.
A17: CT2 · Chocolate a la taza en terraza | B17: Chocolate a la taza | C17: ='Mix y Ticket Canal y Temporada'!$O$27 -> 2.2727273 | D17: ='Mix y Ticket Canal y Temporada'!$R$27 -> 0.43744186 | E17: =IFERROR(C17-D17,"") -> 1.8352854 | F17: =IFERROR(E17/C17,"") -> 0.80752558 | G17: ='Mix y Ticket Canal y Temporada'!$S$27 -> 4 | H17: ='Mix y Ticket Canal y Temporada'!$T$27 -> 2 | I17: =IFERROR(E17*G17,"") -> 7.3411416 | J17: =IF(NOT(ISNUMBER(E17)),"",IF(E17>='Parámetros'!$B$28,"Sí","No")) -> Sí | K17: =IF(MAX(G17,H17)>='Parámetros'!$B$29,"Sí","No") -> Sí | L17: =IF(OR(J17="",K17=""),"",IF(AND(J17="Sí",K17="Sí"),"Mantener",IF(AND(J17="No",K17="Sí"),"Revisar precio",IF(J17="Sí","Vigilar rotación","Retirar")))) -> Mantener | M17: Si sale «Revisar precio», mira primero el PVP y el canal en «Mix y Ticket Canal y Temporada»; si sale «Vigilar rotación», cuánto stock y cuánta carta ocupa.
A18: CT3 · Chocolate con churros (taza y ración de 6) | B18: Chocolate a la taza | C18: ='Mix y Ticket Canal y Temporada'!$O$28 -> 3.4545455 | D18: ='Mix y Ticket Canal y Temporada'!$R$28 -> 0.53181349 | E18: =IFERROR(C18-D18,"") -> 2.922732 | F18: =IFERROR(E18/C18,"") -> 0.84605399 | G18: ='Mix y Ticket Canal y Temporada'!$S$28 -> 10 | H18: ='Mix y Ticket Canal y Temporada'!$T$28 -> 4 | I18: =IFERROR(E18*G18,"") -> 29.22732 | J18: =IF(NOT(ISNUMBER(E18)),"",IF(E18>='Parámetros'!$B$28,"Sí","No")) -> Sí | K18: =IF(MAX(G18,H18)>='Parámetros'!$B$29,"Sí","No") -> Sí | L18: =IF(OR(J18="",K18=""),"",IF(AND(J18="Sí",K18="Sí"),"Mantener",IF(AND(J18="No",K18="Sí"),"Revisar precio",IF(J18="Sí","Vigilar rotación","Retirar")))) -> Mantener | M18: Si sale «Revisar precio», mira primero el PVP y el canal en «Mix y Ticket Canal y Temporada»; si sale «Vigilar rotación», cuánto stock y cuánta carta ocupa.
A19: CT4 · Chocolate a la taza para llevar | B19: Chocolate a la taza | C19: ='Mix y Ticket Canal y Temporada'!$O$29 -> 2.0909091 | D19: ='Mix y Ticket Canal y Temporada'!$R$29 -> 0.51744186 | E19: =IFERROR(C19-D19,"") -> 1.5734672 | F19: =IFERROR(E19/C19,"") -> 0.75252781 | G19: ='Mix y Ticket Canal y Temporada'!$S$29 -> 3 | H19: ='Mix y Ticket Canal y Temporada'!$T$29 -> 1 | I19: =IFERROR(E19*G19,"") -> 4.7204017 | J19: =IF(NOT(ISNUMBER(E19)),"",IF(E19>='Parámetros'!$B$28,"Sí","No")) -> Sí | K19: =IF(MAX(G19,H19)>='Parámetros'!$B$29,"Sí","No") -> Sí | L19: =IF(OR(J19="",K19=""),"",IF(AND(J19="Sí",K19="Sí"),"Mantener",IF(AND(J19="No",K19="Sí"),"Revisar precio",IF(J19="Sí","Vigilar rotación","Retirar")))) -> Mantener | M19: Si sale «Revisar precio», mira primero el PVP y el canal en «Mix y Ticket Canal y Temporada»; si sale «Vigilar rotación», cuánto stock y cuánta carta ocupa.
A20: CT5 · Media taza de chocolate | B20: Chocolate a la taza | C20: ='Mix y Ticket Canal y Temporada'!$O$30 -> 1.1818182 | D20: ='Mix y Ticket Canal y Temporada'!$R$30 -> 0.26246512 | E20: =IFERROR(C20-D20,"") -> 0.91935307 | F20: =IFERROR(E20/C20,"") -> 0.77791413 | G20: ='Mix y Ticket Canal y Temporada'!$S$30 -> 2 | H20: ='Mix y Ticket Canal y Temporada'!$T$30 -> 1 | I20: =IFERROR(E20*G20,"") -> 1.8387061 | J20: =IF(NOT(ISNUMBER(E20)),"",IF(E20>='Parámetros'!$B$28,"Sí","No")) -> Sí | K20: =IF(MAX(G20,H20)>='Parámetros'!$B$29,"Sí","No") -> Sí | L20: =IF(OR(J20="",K20=""),"",IF(AND(J20="Sí",K20="Sí"),"Mantener",IF(AND(J20="No",K20="Sí"),"Revisar precio",IF(J20="Sí","Vigilar rotación","Retirar")))) -> Mantener | M20: Si sale «Revisar precio», mira primero el PVP y el canal en «Mix y Ticket Canal y Temporada»; si sale «Vigilar rotación», cuánto stock y cuánta carta ocupa.
A21: CB1 · Café solo | B21: Cafés y bebidas | C21: ='Mix y Ticket Canal y Temporada'!$O$31 -> 1.2045455 | D21: ='Mix y Ticket Canal y Temporada'!$R$31 -> 0.154 | E21: =IFERROR(C21-D21,"") -> 1.0505455 | F21: =IFERROR(E21/C21,"") -> 0.87215094 | G21: ='Mix y Ticket Canal y Temporada'!$S$31 -> 4 | H21: ='Mix y Ticket Canal y Temporada'!$T$31 -> 4 | I21: =IFERROR(E21*G21,"") -> 4.2021818 | J21: =IF(NOT(ISNUMBER(E21)),"",IF(E21>='Parámetros'!$B$28,"Sí","No")) -> Sí | K21: =IF(MAX(G21,H21)>='Parámetros'!$B$29,"Sí","No") -> Sí | L21: =IF(OR(J21="",K21=""),"",IF(AND(J21="Sí",K21="Sí"),"Mantener",IF(AND(J21="No",K21="Sí"),"Revisar precio",IF(J21="Sí","Vigilar rotación","Retirar")))) -> Mantener | M21: Si sale «Revisar precio», mira primero el PVP y el canal en «Mix y Ticket Canal y Temporada»; si sale «Vigilar rotación», cuánto stock y cuánta carta ocupa.
A22: CB2 · Café con leche | B22: Cafés y bebidas | C22: ='Mix y Ticket Canal y Temporada'!$O$32 -> 1.4909091 | D22: ='Mix y Ticket Canal y Temporada'!$R$32 -> 0.2935 | E22: =IFERROR(C22-D22,"") -> 1.1974091 | F22: =IFERROR(E22/C22,"") -> 0.80314024 | G22: ='Mix y Ticket Canal y Temporada'!$S$32 -> 6 | H22: ='Mix y Ticket Canal y Temporada'!$T$32 -> 5 | I22: =IFERROR(E22*G22,"") -> 7.1844545 | J22: =IF(NOT(ISNUMBER(E22)),"",IF(E22>='Parámetros'!$B$28,"Sí","No")) -> Sí | K22: =IF(MAX(G22,H22)>='Parámetros'!$B$29,"Sí","No") -> Sí | L22: =IF(OR(J22="",K22=""),"",IF(AND(J22="Sí",K22="Sí"),"Mantener",IF(AND(J22="No",K22="Sí"),"Revisar precio",IF(J22="Sí","Vigilar rotación","Retirar")))) -> Mantener | M22: Si sale «Revisar precio», mira primero el PVP y el canal en «Mix y Ticket Canal y Temporada»; si sale «Vigilar rotación», cuánto stock y cuánta carta ocupa.
A23: CB3 · Infusión | B23: Cafés y bebidas | C23: ='Mix y Ticket Canal y Temporada'!$O$33 -> 1.2727273 | D23: ='Mix y Ticket Canal y Temporada'!$R$33 -> 0.068 | E23: =IFERROR(C23-D23,"") -> 1.2047273 | F23: =IFERROR(E23/C23,"") -> 0.94657143 | G23: ='Mix y Ticket Canal y Temporada'!$S$33 -> 1 | H23: ='Mix y Ticket Canal y Temporada'!$T$33 -> 1 | I23: =IFERROR(E23*G23,"") -> 1.2047273 | J23: =IF(NOT(ISNUMBER(E23)),"",IF(E23>='Parámetros'!$B$28,"Sí","No")) -> Sí | K23: =IF(MAX(G23,H23)>='Parámetros'!$B$29,"Sí","No") -> No | L23: =IF(OR(J23="",K23=""),"",IF(AND(J23="Sí",K23="Sí"),"Mantener",IF(AND(J23="No",K23="Sí"),"Revisar precio",IF(J23="Sí","Vigilar rotación","Retirar")))) -> Vigilar rotación | M23: Si sale «Revisar precio», mira primero el PVP y el canal en «Mix y Ticket Canal y Temporada»; si sale «Vigilar rotación», cuánto stock y cuánta carta ocupa.
A24: CB4 · Leche con cacao | B24: Cafés y bebidas | C24: ='Mix y Ticket Canal y Temporada'!$O$34 -> 1.4818182 | D24: ='Mix y Ticket Canal y Temporada'!$R$34 -> 0.284 | E24: =IFERROR(C24-D24,"") -> 1.1978182 | F24: =IFERROR(E24/C24,"") -> 0.80834356 | G24: ='Mix y Ticket Canal y Temporada'!$S$34 -> 2 | H24: ='Mix y Ticket Canal y Temporada'!$T$34 -> 2 | I24: =IFERROR(E24*G24,"") -> 2.3956364 | J24: =IF(NOT(ISNUMBER(E24)),"",IF(E24>='Parámetros'!$B$28,"Sí","No")) -> Sí | K24: =IF(MAX(G24,H24)>='Parámetros'!$B$29,"Sí","No") -> Sí | L24: =IF(OR(J24="",K24=""),"",IF(AND(J24="Sí",K24="Sí"),"Mantener",IF(AND(J24="No",K24="Sí"),"Revisar precio",IF(J24="Sí","Vigilar rotación","Retirar")))) -> Mantener | M24: Si sale «Revisar precio», mira primero el PVP y el canal en «Mix y Ticket Canal y Temporada»; si sale «Vigilar rotación», cuánto stock y cuánta carta ocupa.
A25: CB5 · Zumo de naranja natural | B25: Cafés y bebidas | C25: ='Mix y Ticket Canal y Temporada'!$O$35 -> 2.2954545 | D25: ='Mix y Ticket Canal y Temporada'!$R$35 -> 0.515 | E25: =IFERROR(C25-D25,"") -> 1.7804545 | F25: =IFERROR(E25/C25,"") -> 0.77564356 | G25: ='Mix y Ticket Canal y Temporada'!$S$35 -> 2 | H25: ='Mix y Ticket Canal y Temporada'!$T$35 -> 4 | I25: =IFERROR(E25*G25,"") -> 3.5609091 | J25: =IF(NOT(ISNUMBER(E25)),"",IF(E25>='Parámetros'!$B$28,"Sí","No")) -> Sí | K25: =IF(MAX(G25,H25)>='Parámetros'!$B$29,"Sí","No") -> Sí | L25: =IF(OR(J25="",K25=""),"",IF(AND(J25="Sí",K25="Sí"),"Mantener",IF(AND(J25="No",K25="Sí"),"Revisar precio",IF(J25="Sí","Vigilar rotación","Retirar")))) -> Mantener | M25: Si sale «Revisar precio», mira primero el PVP y el canal en «Mix y Ticket Canal y Temporada»; si sale «Vigilar rotación», cuánto stock y cuánta carta ocupa.
A26: CB6 · Agua (botella de 50 cl) | B26: Cafés y bebidas | C26: ='Mix y Ticket Canal y Temporada'!$O$36 -> 1.0909091 | D26: ='Mix y Ticket Canal y Temporada'!$R$36 -> 0.22 | E26: =IFERROR(C26-D26,"") -> 0.87090909 | F26: =IFERROR(E26/C26,"") -> 0.79833333 | G26: ='Mix y Ticket Canal y Temporada'!$S$36 -> 2 | H26: ='Mix y Ticket Canal y Temporada'!$T$36 -> 5 | I26: =IFERROR(E26*G26,"") -> 1.7418182 | J26: =IF(NOT(ISNUMBER(E26)),"",IF(E26>='Parámetros'!$B$28,"Sí","No")) -> Sí | K26: =IF(MAX(G26,H26)>='Parámetros'!$B$29,"Sí","No") -> Sí | L26: =IF(OR(J26="",K26=""),"",IF(AND(J26="Sí",K26="Sí"),"Mantener",IF(AND(J26="No",K26="Sí"),"Revisar precio",IF(J26="Sí","Vigilar rotación","Retirar")))) -> Mantener | M26: Si sale «Revisar precio», mira primero el PVP y el canal en «Mix y Ticket Canal y Temporada»; si sale «Vigilar rotación», cuánto stock y cuánta carta ocupa.
A27: CV1 · Granizado | B27: Carta de verano | C27: ='Mix y Ticket Canal y Temporada'!$O$37 -> 2.6644628 | D27: ='Mix y Ticket Canal y Temporada'!$R$37 -> 0.482 | E27: =IFERROR(C27-D27,"") -> 2.1824628 | F27: =IFERROR(E27/C27,"") -> 0.8191005 | G27: ='Mix y Ticket Canal y Temporada'!$S$37 -> 0 | H27: ='Mix y Ticket Canal y Temporada'!$T$37 -> 12 | I27: =IFERROR(E27*G27,"") -> 0 | J27: =IF(NOT(ISNUMBER(E27)),"",IF(E27>='Parámetros'!$B$28,"Sí","No")) -> Sí | K27: =IF(MAX(G27,H27)>='Parámetros'!$B$29,"Sí","No") -> Sí | L27: =IF(OR(J27="",K27=""),"",IF(AND(J27="Sí",K27="Sí"),"Mantener",IF(AND(J27="No",K27="Sí"),"Revisar precio",IF(J27="Sí","Vigilar rotación","Retirar")))) -> Mantener | M27: Sólo se vende en julio y agosto: léela con el mix de verano, no con el de invierno. Es la decisión 9 (libro 5).
A28: CV2 · Horchata | B28: Carta de verano | C28: ='Mix y Ticket Canal y Temporada'!$O$38 -> 2.6644628 | D28: ='Mix y Ticket Canal y Temporada'!$R$38 -> 0.582 | E28: =IFERROR(C28-D28,"") -> 2.0824628 | F28: =IFERROR(E28/C28,"") -> 0.78156948 | G28: ='Mix y Ticket Canal y Temporada'!$S$38 -> 0 | H28: ='Mix y Ticket Canal y Temporada'!$T$38 -> 10 | I28: =IFERROR(E28*G28,"") -> 0 | J28: =IF(NOT(ISNUMBER(E28)),"",IF(E28>='Parámetros'!$B$28,"Sí","No")) -> Sí | K28: =IF(MAX(G28,H28)>='Parámetros'!$B$29,"Sí","No") -> Sí | L28: =IF(OR(J28="",K28=""),"",IF(AND(J28="Sí",K28="Sí"),"Mantener",IF(AND(J28="No",K28="Sí"),"Revisar precio",IF(J28="Sí","Vigilar rotación","Retirar")))) -> Mantener | M28: Sólo se vende en julio y agosto: léela con el mix de verano, no con el de invierno. Es la decisión 9 (libro 5).
A29: CV3 · Helado (bola) | B29: Carta de verano | C29: ='Mix y Ticket Canal y Temporada'!$O$39 -> 2 | D29: ='Mix y Ticket Canal y Temporada'!$R$39 -> 0.45 | E29: =IFERROR(C29-D29,"") -> 1.55 | F29: =IFERROR(E29/C29,"") -> 0.775 | G29: ='Mix y Ticket Canal y Temporada'!$S$39 -> 0 | H29: ='Mix y Ticket Canal y Temporada'!$T$39 -> 9 | I29: =IFERROR(E29*G29,"") -> 0 | J29: =IF(NOT(ISNUMBER(E29)),"",IF(E29>='Parámetros'!$B$28,"Sí","No")) -> Sí | K29: =IF(MAX(G29,H29)>='Parámetros'!$B$29,"Sí","No") -> Sí | L29: =IF(OR(J29="",K29=""),"",IF(AND(J29="Sí",K29="Sí"),"Mantener",IF(AND(J29="No",K29="Sí"),"Revisar precio",IF(J29="Sí","Vigilar rotación","Retirar")))) -> Mantener | M29: Sólo se vende en julio y agosto: léela con el mix de verano, no con el de invierno. Es la decisión 9 (libro 5).
A30: CV4 · Batido | B30: Carta de verano | C30: ='Mix y Ticket Canal y Temporada'!$O$40 -> 3.6545455 | D30: ='Mix y Ticket Canal y Temporada'!$R$40 -> 0.7285 | E30: =IFERROR(C30-D30,"") -> 2.9260455 | F30: =IFERROR(E30/C30,"") -> 0.8006592 | G30: ='Mix y Ticket Canal y Temporada'!$S$40 -> 0 | H30: ='Mix y Ticket Canal y Temporada'!$T$40 -> 5 | I30: =IFERROR(E30*G30,"") -> 0 | J30: =IF(NOT(ISNUMBER(E30)),"",IF(E30>='Parámetros'!$B$28,"Sí","No")) -> Sí | K30: =IF(MAX(G30,H30)>='Parámetros'!$B$29,"Sí","No") -> Sí | L30: =IF(OR(J30="",K30=""),"",IF(AND(J30="Sí",K30="Sí"),"Mantener",IF(AND(J30="No",K30="Sí"),"Revisar precio",IF(J30="Sí","Vigilar rotación","Retirar")))) -> Mantener | M30: Sólo se vende en julio y agosto: léela con el mix de verano, no con el de invierno. Es la decisión 9 (libro 5).
A31: TOTAL | I31: =SUM(I7:I30) -> 187.85207
A33: Recuento
A34: Referencias con veredicto «Mantener» | B34: =COUNTIF(L7:L30,"Mantener") -> 21
A35: Referencias con veredicto «Revisar precio» | B35: =COUNTIF(L7:L30,"Revisar precio") -> 2
A36: Referencias con veredicto «Vigilar rotación» | B36: =COUNTIF(L7:L30,"Vigilar rotación") -> 1
A37: Referencias con veredicto «Retirar» | B37: =COUNTIF(L7:L30,"Retirar") -> 0
A39: El total de la columna I es el margen sobre materia de 100 raciones con el mix de invierno. No decidas el surtido con el margen en porcentaje: es lo que hace parecer rentable lo que sólo es barato.
A41: Versión 1.0 · octubre 2026 · aichef.pro/guia-churreria-chocolateria · info@aichef.pro
