Workbook

Sheet Instrucciones
A1: Producción, Hora Punta y Local
A2: AI Chef Pro · aichef.pro — Cómo Montar una Churrería-Chocolatería
A3: Para qué sirve: decidir si ese local admite una freidora y cuánto produce tu línea, con la demanda base de un día de diario y de un día punta. Responde a dos preguntas: ¿una churrera o dos? y ¿ese local sirve?
A5: Instrucciones de Uso
A6: Celdas verdes = campos editables
A7: Las celdas en crema son resultados que el libro calcula; las blancas con fórmula, también. No escribas encima.
A9: 1. Hoja «Parámetros». La superficie del local, los umbrales del Código Técnico para las cocinas (1 kW por litro de freidora, riesgo bajo, medio y alto, distancia de los filtros) y las dos celdas verdes donde copias del libro 3 los kilos de masa por ración media y los kilos fritos por kilo de masa, cada una con su fila de CUADRE.
A10: 2. Hoja «Zonas y m²». Reparte los metros del local en sus seis zonas. La terraza va aparte y con su propia autorización.
A11: 3. Hoja «Equipos y Capacidad». Los kilos de masa por hora que saca de verdad cada eslabón: la línea con su churrero/a, la freidora por tandas y la amasadora. Y cuántas personas hay en la línea en el pico del fin de semana.
A12: 4. Hoja «Freidoras, Potencia y Riesgo». Los litros y el tipo de cada freidora, los kW de los demás aparatos de cocción y si proteges los aparatos con extinción automática. Sale el riesgo de la cocina, si la extinción automática es obligatoria y a qué distancia van los filtros.
A13: 5. Hoja «Cuello de Botella». El eslabón que manda y las raciones por hora que aguanta el conjunto, y cuántas horas de línea te pide el día tipo y el día punta.
A14: 6. Hoja «Día Tipo y Día Punta». Las raciones de un día de diario y de un sábado, domingo o festivo. Es la ÚNICA fuente de la demanda base de todo el paquete: de aquí salen los kilos de masa, los kilos fritos, las tandas y los amasados.
... A42: Versión 1.0 · octubre 2026 · aichef.pro/guia-churreria-chocolateria · info@aichef.pro

Sheet Parámetros
A1: Parámetros
A2: AI Chef Pro · aichef.pro — Cómo Montar una Churrería-Chocolatería
A3: Lo que vale para todo el libro. Ninguna fórmula lleva un número dentro: los umbrales, las distancias y las conversiones viven aquí.
A4: Parámetro | B4: Valor | C4: Unidad | D4: Procedencia | E4: Nota
A5: El Local
A6: Superficie útil del local | B6: 75 | C6: m² | D6: CHS-37a + CUS-02 | E6: El caso de El Molinete: 75 m² en seis zonas, la cifra en la que convergen dos traspasos reales del mismo formato. Pon la útil de tu local, no la del anuncio.
A7: Terraza (aparte de la superficie útil) | B7: 20 | C7: m² | D7: supuesto declarado | E7: Supuesto de El Molinete. Va aparte de los metros del local y con su propia autorización de ocupación de la vía pública.
A8: Cocina y Riesgo de Incendio (Código Técnico, DB-SI)
A9: kW que computa cada litro de freidora | B9: 1 | C9: kW por litro | D9: CUN-26 | E9: Las freidoras se computan a 1 kW por litro de capacidad, tengan la potencia que tengan. Es la nota (2) de la tabla 2.1 del DB-SI.
A10: Riesgo especial BAJO con más de | B10: 20 | C10: kW | D10: CUN-26 | E10: Umbral de la tabla 2.1 del DB-SI para las cocinas según su potencia instalada. Hasta aquí la cocina no es local de riesgo especial.
A11: Riesgo especial MEDIO con más de | B11: 30 | C11: kW | D11: CUN-26 | E11: Umbral de la tabla 2.1 del DB-SI para las cocinas según su potencia instalada.
A12: Riesgo especial ALTO (y extinción automática obligatoria) con más de | B12: 50 | C12: kW | D12: CUN-26 | E12: Umbral de la tabla 2.1 del DB-SI para las cocinas según su potencia instalada. Por encima, el sistema automático de extinción es obligatorio (SI 4).
A13: Distancia mínima del filtro al foco: aparato de gas | B13: 1.2 | C13: m | D13: CUN-26 | E13: Nota (3) de la tabla 2.1: más de 1,20 m si el aparato es de gas o de parrilla.
A14: Distancia mínima del filtro al foco: aparato de parrilla | B14: 1.2 | C14: m | D14: CUN-26 | E14: Nota (3) de la tabla 2.1: lo mismo que el gas, más de 1,20 m.
A15: Distancia mínima del filtro al foco: otros aparatos | B15: 0.5 | C15: m | D15: CUN-26 | E15: Nota (3) de la tabla 2.1: más de 0,50 m con los demás tipos (la freidora eléctrica, por ejemplo); con gas o parrilla son 1,20 m.
A16: Producción y Calendario
A17: Días tipo por semana (de lunes a viernes) | B17: 5 | C17: días | D17: calendario | E17: El festivo entre semana se trabaja como un domingo: cuéntalo como día punta.
A18: Días punta por semana (sábado y domingo) | B18: 2 | C18: días | D18: calendario | E18: Sábados, domingos y festivos: la demanda del día punta.
A19: Minutos que tiene una hora | B19: 60 | C19: min/h | D19: conversión | E19: Conversión de unidades. Vive aquí para que ninguna fórmula lleve un número dentro.
A20: Tolerancia de la fila de CUADRE | B20: 0.02 | C20: desviación | D20: heredado de la hermana | E20: Por encima de esta desviación, la fila de CUADRE avisa de que lo que has copiado del libro 3 ya no es lo que aquel publica.
A21: Lo que Copias de Otros Libros
A22: cópialo del libro 3: carta-de-apertura-y-escandallo-churro.xlsx!Mix y Ticket Canal y Temporada!L5 | B22: 0.097918129 | C22: kg/ración | D22: cruce X1 (libro 3) | E22: Kilos de masa (merma incluida) por ración media de tu carta, mix de invierno. Con este número las raciones por hora salen de los kilos por hora de la línea. Nace con el de El Molinete.
A23: Lo que publica hoy esa celda del libro 3 (anótalo cada vez que lo abras) | B23: 0.097918129 | C23: kg/ración | E23: Si arriba usas otra cifra -porque has cambiado la carta o la masa-, la fila de CUADRE te avisa en vez de dejar las dos separadas en silencio.
A24: Desviación entre las dos | B24: =IFERROR(ABS(B22-B23)/B23,"") -> 0
A25: CUADRE: los kilos por ración que usas frente a los que publica el libro 3 | B25: =IF(NOT(ISNUMBER(B24)),"",IF(B24<=B20,"CUADRA","REVISA: no es lo que publica el libro 3")) -> CUADRA
A26: cópialo del libro 3: carta-de-apertura-y-escandallo-churro.xlsx!Parámetros!L9 | B26: 0.9 | C26: kg/kg | D26: cruce X1 bis (libro 3) | E26: Supuesto de El Molinete, que nace en el libro 3 (hoja «Parámetros»): pesa una tanda de masa antes y después de freír. Se copia de allí para que la masa tenga una sola cifra en todo el paquete; con él se pasan los kilos de masa a kilos fritos.
A27: Lo que publica hoy esa celda del libro 3 (anótalo cada vez que lo abras) | B27: 0.9 | C27: kg/kg | E27: Si arriba usas otra cifra -porque has cambiado la carta o la masa-, la fila de CUADRE te avisa en vez de dejar las dos separadas en silencio.
A28: Desviación entre las dos | B28: =IFERROR(ABS(B26-B27)/B27,"") -> 0
A29: CUADRE: los kilos fritos por kilo de masa que usas frente a los que publica el libro 3 | B29: =IF(NOT(ISNUMBER(B28)),"",IF(B28<=B20,"CUADRA","REVISA: no es lo que publica el libro 3")) -> CUADRA

Sheet Zonas y m²
A1: Zonas y M²
A2: AI Chef Pro · aichef.pro — Cómo Montar una Churrería-Chocolatería
A3: Las seis zonas de una churrería-chocolatería con obrador de masa a la vista, freidora bajo campana, barra y sala. La terraza, aparte.
K4: Lo que Copian Otros Libros (No Muevas Estas Celdas)
A5: Nº | B5: Zona | C5: Bloque | D5: m² | E5: % del local | F5: Qué tiene que cumplir | K5: Superficie útil del local (m²) | L5: ='Parámetros'!$B$6 -> 75 | M5: Lo copia: libro 2 (calculadora-capex-churreria.xlsx, hoja Parámetros, X9 bis)
A6: 1 | B6: Obrador de masa a la vista | C6: Producción | D6: 10 | E6: =IFERROR(D6/$D$13,"") -> 0.13333333 | F6: Amasadora, dosificadora y mesa de trabajo. A la vista del cliente: es parte del reclamo, y obliga a que esté siempre presentable.
A7: 2 | B7: Fritura bajo campana | C7: Producción | D7: 6 | E7: =IFERROR(D7/$D$13,"") -> 0.08 | F7: La freidora de gas de 25 L y el escurridor, bajo la campana de 1.200 mm. Es la zona que decide si el local sirve: conducto, potencia y gas.
A8: 3 | B8: Barra y despacho a calle | C8: Atención al cliente | D8: 12 | E8: =IFERROR(D8/$D$13,"") -> 0.16 | F8: Cafetera, chocolateras, caja y la ventanilla del despacho para llevar.
A9: 4 | B9: Sala | C9: Atención al cliente | D9: 32 | E9: =IFERROR(D9/$D$13,"") -> 0.42666667 | F9: Mesas y sillas del consumo en el local.
A10: 5 | B10: Aseos y vestuario | C10: Servicios | D10: 8 | E10: =IFERROR(D10/$D$13,"") -> 0.10666667 | F10: Aseo de público y vestuario de personal. Si no caben, el local no sirve.
A11: 6 | B11: Almacén de harina, aceite, envase y bidón de aceite usado | C11: Servicios | D11: 7 | E11: =IFERROR(D11/$D$13,"") -> 0.093333333 | F11: El bidón del aceite usado espera aquí al gestor autorizado.
B13: TOTAL repartido | D13: =SUM(D6:D11) -> 75 | E13: =SUM(E6:E11) -> 1
B14: Superficie útil declarada en «Parámetros» | D14: ='Parámetros'!$B$6 -> 75
B15: Descuadre (m²) | D15: =IFERROR(D13-D14,"") -> 0 | F15: Si no es cero, o te sobran metros sin asignar o has repartido más de los que tiene el local.
B17: Metros de producción (obrador de masa y fritura) | D17: =SUMIF(C6:C11,"Producción",D6:D11) -> 16
B18: Parte del local dedicada a producción | D18: =IFERROR(D17/D13,"") -> 0.21333333
B19: Metros de atención al cliente (barra, despacho y sala) | D19: =SUMIF(C6:C11,"Atención al cliente",D6:D11) -> 44
B20: Parte del local dedicada al cliente | D20: =IFERROR(D19/D13,"") -> 0.58666667
B21: Metros de servicios (aseos, vestuario y almacén) | D21: =SUMIF(C6:C11,"Servicios",D6:D11) -> 15
B22: Terraza, aparte (de «Parámetros») | D22: ='Parámetros'!$B$7 -> 20 | F22: No suma a la superficie útil y va con autorización propia de ocupación de la vía pública.
B24: LA ZONA QUE DECIDE SI EL LOCAL SIRVE ES LA MÁS PEQUEÑA. Los seis metros de fritura bajo campana son los que piden conducto a cubierta, gas o potencia y el riesgo de incendio del Código Técnico. Antes de repartir el resto, comprueba en la «Ficha de Visita a Local» que esa zona tiene salida.

Sheet Equipos y Capacidad
A1: Equipos y Capacidad
A2: AI Chef Pro · aichef.pro — Cómo Montar una Churrería-Chocolatería
A3: Todo en kilos de masa por hora: la línea con su churrero/a, la freidora por tandas y la amasadora. Mide el tuyo; el del folleto no vale.
A4: Personas | K4: Lo que Copian Otros Libros (No Muevas Estas Celdas)
A5: Personas en la línea en el pico del fin de semana | D5: 2 | F5: Supuesto de El Molinete: dos personas en la línea el sábado y el domingo por la mañana. Viaja al libro 8, que comprueba el cuadrante. | K5: Personas en la línea en el pico | L5: =D5 -> 2 | M5: Lo copia: libro 8 (turnos-plantilla-y-madrugada.xlsx, hoja Parámetros, X6)
A8: Nº | B8: Eslabón | C8: ¿Cuenta para el cuello? | D8: kg de masa por ciclo | E8: Minutos por ciclo | F8: kg de masa por hora | G8: Cuenta (kg/h) | H8: Procedencia | I8: Nota
A9: 1 | B9: Línea de dosificado y fritura (con su churrero/a) | C9: Sí | D9: No aplica | E9: No aplica | F9: 12 | G9: =IF(C9="Sí",F9,"") -> 12 | H9: supuesto declarado | I9: Los kilos de masa por hora que la línea saca DE VERDAD con la persona que la trabaja. Nunca el máximo del folleto del fabricante: mídelo un domingo, pesando la masa que entra en una hora.
A10: 2 | B10: Freidora (por tandas) | C10: Sí | D10: 1 | E10: 4 | F10: =IFERROR(D10*'Parámetros'!$B$19/E10,"") -> 15 | G10: =IF(C10="Sí",F10,"") -> 15 | H10: supuesto declarado | I10: Kilos de masa que caben en una tanda y minutos de la carga al escurrido. Con dos cubas, la freidora deja de mandar; mira antes qué le pasa al riesgo de incendio en la hoja «Freidoras, Potencia y Riesgo».
A11: 3 | B11: Amasadora | C11: Sí | D11: 30 | E11: 20 | F11: =IFERROR(D11*'Parámetros'!$B$19/E11,"") -> 90 | G11: =IF(C11="Sí",F11,"") -> 90 | H11: CUS-35a | I11: Capacidad declarada de la amasadora automática del ejemplo y minutos de un amasado completo (supuesto). Casi nunca manda: amasa mucho más deprisa de lo que se fríe.
B14: kg de masa por hora y persona en la línea | F14: =IFERROR(F9/D5,"") -> 6 | I14: Lo que rinde cada persona de la línea. Si la segunda persona no sube los kilos por hora, no está en la línea: está despachando.
B17: Listas de validación (no las borres: las usan los desplegables)
B18: Sí o No
B19: Sí
B20: No

Sheet Freidoras, Potencia y Riesgo
A1: Freidoras, Potencia y Riesgo
A2: AI Chef Pro · aichef.pro — Cómo Montar una Churrería-Chocolatería
A3: Los kW que computa tu cocina según el Código Técnico, el riesgo de incendio que te toca y a qué distancia van los filtros.
K4: Lo que Copian Otros Libros (No Muevas Estas Celdas)
A5: Nº | B5: Freidora | C5: ¿La tienes? | D5: Litros de cuba | E5: Tipo de aparato | F5: kW computables | G5: Distancia mínima del filtro | H5: Procedencia | I5: Nota | K5: Litros totales de cuba | L5: =D9 -> 25 | M5: Lo copia: libro 4 (aceite-de-fritura-coste-y-cambio.xlsx, hoja Parámetros, X3)
A6: 1 | B6: Freidora de churros de una cuba | C6: Sí | D6: 25 | E6: Gas | F6: =IF(C6="Sí",D6*'Parámetros'!$B$9,"") -> 25 | G6: =IF(C6="Sí",IF(E6="Gas",'Parámetros'!$B$13,IF(E6="Parrilla",'Parámetros'!$B$14,'Parámetros'!$B$15)),"") -> 1.2 | H6: CUS-33a | I6: La freidora de gas de 25 L del ejemplo, bajo la campana. Si es eléctrica, cambia el tipo a «Otro»: la distancia del filtro baja y la potencia a contratar sube. | K6: ¿Necesitas extinción automática? (1 sí, 0 no) | L6: =D14 -> 0 | M6: Lo copia: libro 2 (calculadora-capex-churreria.xlsx, hoja Parámetros, X9)
A7: 2 | B7: Segunda freidora (la decisión «¿una churrera o dos?») | C7: No | D7: 25 | E7: Gas | F7: =IF(C7="Sí",D7*'Parámetros'!$B$9,"") | G7: =IF(C7="Sí",IF(E7="Gas",'Parámetros'!$B$13,IF(E7="Parrilla",'Parámetros'!$B$14,'Parámetros'!$B$15)),"") | H7: supuesto declarado | I7: Marcada «No» a propósito. Cámbiala a «Sí» y mira cómo se mueven los kW computables, el riesgo de la cocina y la extinción automática ANTES de comprarla.
B9: Litros totales de cuba (freidoras que tienes) | D9: =SUMIF(C6:C7,"Sí",D6:D7) -> 25
B10: kW computables de las freidoras | D10: =SUM(F6:F7) -> 25
B11: kW de los demás aparatos de cocción (míralo en su placa) | D11: 3 | I11: Sólo computan los aparatos directamente destinados a preparar alimentos y susceptibles de provocar ignición (nota 2 de la tabla 2.1 del DB-SI, leída el 03-10-2026). El Molinete cuenta sus dos chocolateras al baño maría: confirma con tu técnico si las tuyas computan; si no, pon 0.
B12: kW COMPUTABLES DE TU COCINA | D12: =SUM(D10:D11) -> 28
B13: Riesgo de la cocina | D13: =IF(NOT(ISNUMBER(D12)),"",IF(D12>'Parámetros'!$B$12,"Riesgo alto",IF(D12>'Parámetros'!$B$11,"Riesgo medio",IF(D12>'Parámetros'!$B$10,"Riesgo bajo","No es local de riesgo especial")))) -> Riesgo bajo | I13: De 20 a 30 kW, bajo; de 30 a 50, medio; por encima de 50, alto. Un local de riesgo especial pide conductos EI 30 y sectorización: es obra con proyecto y entra en el libro 2.
B14: ¿Extinción automática obligatoria? (1 sí, 0 no) | D14: =IF(ISNUMBER(D12),IF(D12>'Parámetros'!$B$12,1,0),"") -> 0
B15: ¿Extinción automática obligatoria? | D15: =IF(NOT(ISNUMBER(D14)),"",IF(D14=1,"Sí, obligatoria","No obligatoria")) -> No obligatoria | I15: Por encima de 50 kW, el sistema automático de extinción es obligatorio (DB-SI, SI 4). Esta cifra viaja al libro 2, que presupuesta el sistema sólo si sale 1.
B17: Si Proteges los Aparatos con Extinción Automática
B18: ¿Proteges los aparatos con un sistema automático de extinción? | D18: No | I18: El Molinete no la instala: con su potencia no la necesita. Ponerla aunque no sea obligatoria es la otra salida de la decisión 4, con su coste en el libro 2.
B19: ¿El edificio es de uso hospitalario o residencial público? | D19: No | I19: Una churrería no lo es. Dentro de un hotel o un hospital, la nota (2) no te libra y los umbrales son otros.
B20: VEREDICTO DEL CÓDIGO TÉCNICO PARA TU COCINA | D20: =IF(NOT(ISNUMBER(D12)),"",IF(D12<='Parámetros'!$B$10,"No es local de riesgo especial (no pasa del umbral bajo)",IF(AND(D18="Sí",D19="No"),"No es local de riesgo especial (nota 2 del CTE), aunque te sigue aplicando la nota (3)",IF(D12>'Parámetros'!$B$12,"Riesgo alto sin extinción automática: es obligatoria","Local de riesgo especial: "&LOWER(D13))))) -> Local de riesgo especial: riesgo bajo
B21: ¿Te aplica la nota (3) (campana, conductos EI 30 y filtros)? | D21: =IF(NOT(ISNUMBER(D12)),"",IF(D12>'Parámetros'!$B$10,"Sí","No")) -> Sí | I21: La nota (3) alcanza a la cocina que es local de riesgo especial, y la sigue alcanzando aunque la extinción automática la saque de esa categoría.
B22: Distancia mínima del filtro al foco de calor | D22: =IFERROR(IF(COUNTIF(C6:C7,"Sí")=0,"",MAX(G6:G7)),"") -> 1.2 | I22: Más de 1,20 m si el aparato es de gas o de parrilla; más de 0,50 m con los demás. Con varias freidoras manda la más exigente.
B23: Qué te obliga a pedir en la visita | D23: =IF(D21="","",IF(D21="Sí","Campana separada de materiales no A1, conductos EI 30 y filtros a la distancia de arriba","Campana y conducto según la ordenanza de tu municipio")) -> Campana separada de materiales no A1, conductos EI 30 y filtros a la distancia de arriba
B26: Listas de validación (no las borres: las usan los desplegables)
B27: Sí o No | C27: Tipo de aparato
B28: Sí | C28: Gas
B29: No | C29: Parrilla
C30: Otro

Sheet Cuello de Botella
A1: Cuello de Botella
A2: AI Chef Pro · aichef.pro — Cómo Montar una Churrería-Chocolatería
A3: El eslabón que manda y las raciones por hora que aguanta el conjunto. Cómo se reparte la demanda por franjas y si aguantas el pico del domingo lo calcula el libro 5 con esta capacidad.
K4: Lo que Copian Otros Libros (No Muevas Estas Celdas)
A5: Capacidad del Conjunto | K5: Capacidad del conjunto (raciones por hora) | L5: =B11 -> 122.55136 | M5: Lo copia: libro 5 (temporada-franjas-y-ferias.xlsx, hoja Parámetros, X4)
A6: Kilos de masa por hora que aguanta el conjunto | B6: =IFERROR(MIN('Equipos y Capacidad'!$G$9:$G$11),"") -> 12 | D6: El eslabón más lento marca el ritmo de toda la línea.
A7: El eslabón que manda | B7: =IFERROR(INDEX('Equipos y Capacidad'!$B$9:$B$11,MATCH(B6,'Equipos y Capacidad'!$G$9:$G$11,0)),"") -> Línea de dosificado y fritura (con su churrero/a) | D7: Es el que hay que mejorar primero. Comprar otro equipo antes es dinero parado.
A8: Kilos por hora del segundo eslabón más justo | B8: =IFERROR(SMALL('Equipos y Capacidad'!$G$9:$G$11,2),"") -> 15 | D8: Si está muy cerca del primero, resolver sólo el cuello te sube poco la capacidad.
A9: Y es | B9: =IFERROR(INDEX('Equipos y Capacidad'!$B$9:$B$11,MATCH(B8,'Equipos y Capacidad'!$G$9:$G$11,0)),"") -> Freidora (por tandas)
A10: Kilos de masa por ración media (copiados del libro 3) | B10: ='Parámetros'!$B$22 -> 0.097918129 | D10: Viene de la celda verde de «Parámetros», con su fila de CUADRE.
A11: RACIONES POR HORA QUE AGUANTA EL CONJUNTO | B11: =IFERROR(B6/B10,"") -> 122.55136 | D11: Es la cifra que viaja al libro 5, que la cruza con tus franjas y con la cola del domingo.
A12: Raciones por hora y persona en la línea | B12: =IFERROR(B11/'Equipos y Capacidad'!$D$5,"") -> 61.275681
A14: Horas de Línea que Te Pide el Día
A15: Horas de línea a pleno ritmo en el día tipo | B15: =IFERROR('Día Tipo y Día Punta'!$B$8/B6,"") -> 2.039961 | D15: Son horas de fritura si la línea no parase nunca. La demanda no llega repartida: la mitad del día se concentra en el desayuno.
A16: Horas de línea a pleno ritmo en el día punta | B16: =IFERROR('Día Tipo y Día Punta'!$C$8/B6,"") -> 3.2639376
A17: ¿Una churrera o dos? | B17: =IF(B11="","","El veredicto está en el libro 5, hoja «Capacidad contra el Pico», celda E23: allí esta capacidad se cruza con tus franjas") -> El veredicto está en el libro 5, hoja «Capacidad contra el Pico», celda E23: allí esta capacidad se cruza con tus franjas | D17: La respuesta no está en el total del día sino en la hora punta del domingo, y esa hora sólo existe en el libro 5. Aquí ves el eslabón que manda y cuánto sube la capacidad si lo mejoras; allí, con esa capacidad copiada, sale el veredicto «una, con refuerzo, o dos». Si dice que hace falta más línea, activa la segunda freidora aquí y vuelve a copiar la capacidad.

Sheet Día Tipo y Día Punta
A1: Día Tipo y Día Punta
A2: AI Chef Pro · aichef.pro — Cómo Montar una Churrería-Chocolatería
A3: La ÚNICA fuente de la demanda base del paquete: las raciones de un día de diario y de un sábado, domingo o festivo. El reparto por mes y por franja lo hace el libro 5.
K4: Lo que Copian Otros Libros (No Muevas Estas Celdas)
A5: Concepto | B5: Día tipo (lunes a viernes) | C5: Día punta (sábado, domingo y festivo) | D5: Nota | K5: kg fritos en un día tipo | L5: =B10 -> 22.031579 | M5: Lo copia: libro 4 (aceite-de-fritura-coste-y-cambio.xlsx, hoja Parámetros, X3)
A6: Raciones al día | B6: 250 | C6: 400 | D6: Supuesto de El Molinete, no un dato del sector. Pon las tuyas: al principio, una estimación; a los tres meses, las del TPV. | K6: kg fritos en un día punta | L6: =C10 -> 35.250526 | M6: Lo copia: libro 4 (aceite-de-fritura-coste-y-cambio.xlsx, hoja Parámetros, X3)
A7: Kilos de masa por ración media (de «Parámetros») | B7: ='Parámetros'!$B$22 -> 0.097918129 | C7: ='Parámetros'!$B$22 -> 0.097918129 | D7: Copiados del libro 3, merma incluida. | K7: Raciones del día tipo | L7: =B6 -> 250 | M7: Lo copia: libro 4 (aceite-de-fritura-coste-y-cambio.xlsx, hoja Parámetros, X3 bis); libro 5 (temporada-franjas-y-ferias.xlsx, hoja Parámetros, X4)
A8: Kilos de masa al día | B8: =IFERROR(B6*B7,"") -> 24.479532 | C8: =IFERROR(C6*C7,"") -> 39.167251 | D8: Lo que hay que amasar, dosificar y freír. | K8: Raciones del día punta | L8: =C6 -> 400 | M8: Lo copia: libro 4 (aceite-de-fritura-coste-y-cambio.xlsx, hoja Parámetros, X3 bis); libro 5 (temporada-franjas-y-ferias.xlsx, hoja Parámetros, X4)
A9: Kilos fritos por kilo de masa (de «Parámetros») | B9: ='Parámetros'!$B$26 -> 0.9 | C9: ='Parámetros'!$B$26 -> 0.9
A10: KILOS FRITOS AL DÍA | B10: =IFERROR(B8*B9,"") -> 22.031579 | C10: =IFERROR(C8*C9,"") -> 35.250526 | D10: Es lo que viaja al libro 4 para calcular el aceite que se lleva el producto.
A11: Tandas de freidora al día | B11: =IFERROR(ROUNDUP(B8/'Equipos y Capacidad'!$D$10,0),"") -> 25 | C11: =IFERROR(ROUNDUP(C8/'Equipos y Capacidad'!$D$10,0),"") -> 40
A12: Amasados al día | B12: =IFERROR(ROUNDUP(B8/'Equipos y Capacidad'!$D$11,0),"") -> 1 | C12: =IFERROR(ROUNDUP(C8/'Equipos y Capacidad'!$D$11,0),"") -> 2 | D12: Con una amasadora grande, uno o dos al día; el resto del tiempo está parada.
A13: Horas de línea a pleno ritmo | B13: =IFERROR(B8/'Cuello de Botella'!$B$6,"") -> 2.039961 | C13: =IFERROR(C8/'Cuello de Botella'!$B$6,"") -> 3.2639376 | D13: Con el eslabón que manda en la hoja «Cuello de Botella».
A15: La Semana Tipo
A16: Raciones de la semana tipo | B16: =IFERROR(B6*'Parámetros'!$B$17+C6*'Parámetros'!$B$18,"") -> 2050 | D16: Sin estacionalidad: las raciones del año, mes a mes, las reparte el libro 5 con sus doce coeficientes.
A17: Kilos de masa de la semana tipo | B17: =IFERROR(B8*'Parámetros'!$B$17+C8*'Parámetros'!$B$18,"") -> 200.73216
A18: Raciones de un día medio de la semana | B18: =IFERROR(B16/('Parámetros'!$B$17+'Parámetros'!$B$18),"") -> 292.85714

Sheet Ficha de Visita a Local
A1: Ficha de Visita a Local
A2: AI Chef Pro · aichef.pro — Cómo Montar una Churrería-Chocolatería
A3: Imprímela y llévala a cada visita. Los cuatro eliminatorios van primero y en este orden. Una respuesta que descarta en un eliminatorio y el veredicto es DESCARTAR.
A5: Nº | B5: Qué se comprueba | C5: ¿Eliminatorio? | D5: Cómo se comprueba | E5: Respuesta | F5: Respuesta que descarta | G5: Respuesta que obliga a obra con licencia | H5: Dato de tu proyecto | I5: Veredicto | J5: Nota y norma
A6: 1 | B6: ¿La extracción necesita proyecto? | C6: Sí | D6: Pregunta al técnico, con el plano delante, por dónde subiría el conducto. Si cruza fachada, patio o cubierta comunitaria, la obra lleva proyecto. | E6: Sí | F6: Ninguna | G6: Sí | I6: =IF(E6="","",IF(E6="Por comprobar",IF(C6="Sí","Pendiente","Por comprobar"),IF(E6=F6,IF(C6="Sí","DESCARTAR","Punto débil"),IF(E6=G6,"Con obra y licencia","OK")))) -> Con obra y licencia | J6: Si el conducto tiene que subir a cubierta o cruzar fachada o patio, casi siempre: licencia de obra y técnico, aunque la actividad vaya por declaración responsable.
A7: 2 | B7: ¿Se puede llevar un conducto a cubierta? | C7: Sí | D7: Sube a la cubierta con el propietario y pide por escrito el permiso de la comunidad ANTES de firmar. | E7: Sí | F7: No | G7: Ninguna | I7: =IF(E7="","",IF(E7="Por comprobar",IF(C7="Sí","Pendiente","Por comprobar"),IF(E7=F7,IF(C7="Sí","DESCARTAR","Punto débil"),IF(E7=G7,"Con obra y licencia","OK")))) -> OK | J7: En el ejemplo de Madrid, quien cocina evacua por conducto a cubierta; la excepción de los 4 kW eléctricos no ampara una freidora de baño abierto.
A8: 3 | B8: ¿Hay gas, o hay que llevarlo? | C8: Sí | D8: Pide el certificado de la última inspección de la instalación de gas del local o pregunta a la distribuidora si llega la acometida. | E8: Sí | F8: No | G8: Ninguna | I8: =IF(E8="","",IF(E8="Por comprobar",IF(C8="Sí","Pendiente","Por comprobar"),IF(E8=F8,IF(C8="Sí","DESCARTAR","Punto débil"),IF(E8=G8,"Con obra y licencia","OK")))) -> OK | J8: Gas con instalación receptora (inspección cada cinco años) o freidora eléctrica con su potencia contratada. La bombona pequeña no vale para un local (CUN-28).
A9: 4 | B9: ¿Aguanta la potencia y el riesgo de incendio? | C9: Sí | D9: Lleva los kW de la hoja «Freidoras, Potencia y Riesgo» a la visita y pregunta al técnico si la cocina puede quedar sectorizada como local de riesgo especial. | E9: Sí | F9: No | G9: Ninguna | H9: =ROUND('Freidoras, Potencia y Riesgo'!$D$12,0)&" kW · "&'Freidoras, Potencia y Riesgo'!$D$13 -> 28 kW · Riesgo bajo | I9: =IF(E9="","",IF(E9="Por comprobar",IF(C9="Sí","Pendiente","Por comprobar"),IF(E9=F9,IF(C9="Sí","DESCARTAR","Punto débil"),IF(E9=G9,"Con obra y licencia","OK")))) -> OK | J9: Freidoras a 1 kW por litro: por encima de 20 kW la cocina es local de riesgo especial.
A10: 5 | B10: ¿La superficie útil llega a los m² que has repartido por zonas? | C10: No | D10: Superficie útil real, sin muros ni patinillos. El anuncio suele dar la construida. | E10: Sí | F10: No | G10: Ninguna | H10: ='Zonas y m²'!$D$13 -> 75 | I10: =IF(E10="","",IF(E10="Por comprobar",IF(C10="Sí","Pendiente","Por comprobar"),IF(E10=F10,IF(C10="Sí","DESCARTAR","Punto débil"),IF(E10=G10,"Con obra y licencia","OK")))) -> OK | J10: Entre la superficie construida y la útil se van con facilidad diez metros. El dato de la derecha es lo que has repartido en «Zonas y m²».
A11: 6 | B11: ¿Caben el aseo de público y el vestuario del personal? | C11: No | D11: Dibújalos sobre el plano con sus puertas antes de firmar. | E11: Sí | F11: No | G11: Ninguna | I11: =IF(E11="","",IF(E11="Por comprobar",IF(C11="Sí","Pendiente","Por comprobar"),IF(E11=F11,IF(C11="Sí","DESCARTAR","Punto débil"),IF(E11=G11,"Con obra y licencia","OK")))) -> OK | J11: Si no caben, el local no sirve aunque el resto encaje: es obra o es otro local.
A12: 7 | B12: ¿Hay sitio para el almacén y el bidón del aceite usado? | C12: No | D12: Mide el hueco del almacén: harina, aceite nuevo, envases y el bidón que espera al gestor. | E12: Sí | F12: No | G12: Ninguna | I12: =IF(E12="","",IF(E12="Por comprobar",IF(C12="Sí","Pendiente","Por comprobar"),IF(E12=F12,IF(C12="Sí","DESCARTAR","Punto débil"),IF(E12=G12,"Con obra y licencia","OK")))) -> OK | J12: El bidón del aceite usado no puede quedarse en la zona de fritura ni en la sala.
A13: 8 | B13: ¿La acera admite terraza y el ayuntamiento la autoriza? | C13: No | D13: Pregunta en el ayuntamiento por la ocupación de la vía pública en esa calle. | E13: Por comprobar | F13: No | G13: Ninguna | I13: =IF(E13="","",IF(E13="Por comprobar",IF(C13="Sí","Pendiente","Por comprobar"),IF(E13=F13,IF(C13="Sí","DESCARTAR","Punto débil"),IF(E13=G13,"Con obra y licencia","OK")))) -> Por comprobar | J13: La terraza va con autorización propia, aparte de la actividad: la ocupación de la vía pública queda fuera del régimen de declaración responsable.
B15: Motivos de descarte | E15: =COUNTIF(I6:I13,"DESCARTAR") -> 0
B16: Eliminatorios sin comprobar | E16: =COUNTIF(I6:I13,"Pendiente") -> 0
B17: Obligan a obra con proyecto y licencia | E17: =COUNTIF(I6:I13,"Con obra y licencia") -> 1
B18: Puntos débiles y cosas por comprobar | E18: =COUNTIF(I6:I13,"Punto débil")+COUNTIF(I6:I13,"Por comprobar") -> 1
B19: Resueltos sin problema | E19: =COUNTIF(I6:I13,"OK") -> 6
B20: El primer eliminatorio que tumba el local | E20: =IFERROR(INDEX(B6:B13,MATCH("DESCARTAR",I6:I13,0)),"Ninguno") -> Ninguno
B21: VEREDICTO DEL LOCAL | E21: =IF(E15>0,"DESCARTAR ESTE LOCAL",IF(E16>0,"NO DECIDAS TODAVÍA",IF(E17+E18>0,"SIGUE ADELANTE CON RESERVAS","SIGUE ADELANTE"))) -> SIGUE ADELANTE CON RESERVAS
B23: Listas de validación (no las borres: las usan los desplegables)
B24: Respuesta
B25: Sí
B26: No
B27: Por comprobar
B29: POR QUÉ ESTE ORDEN. Primero, si la extracción necesita proyecto: la actividad puede ir por declaración responsable, pero la obra del conducto no, y eso cambia plazos y dinero. Después, si el conducto puede llegar a cubierta: si no puede, no hay freidora. Luego el gas o la potencia para una freidora eléctrica (la bombona pequeña no vale para un local fijo). Y al final, si la cocina puede ser local de riesgo especial con los kW que vas a instalar. Lo que no es eliminatorio encarece la obra: llévalo al libro 2 como partida.
