Workbook

Sheet Instrucciones
B2: 03 · Previsión de Tesorería (Cash Flow) — 12 Meses
B4: AI Chef Pro · aichef.pro — Kit Plan Financiero para Restaurantes
B6: Cómo usar esta plantilla:
B7: ▸ Introduce los cobros y pagos previstos mes a mes.
B8: ▸ El IVA trimestral se calcula automáticamente (línea 'Liquidación IVA').
B9: ▸ La pestaña 'Alertas' marca en rojo los meses donde el saldo < umbral de seguridad.
B11: Conceptos:
B12: ▸ Cobros = ingresos reales de caja (con IVA incluido).
B13: ▸ Pagos = salidas reales de caja (con IVA incluido).
B14: ▸ Saldo Final = Saldo Inicial + Cobros - Pagos.

Sheet Flujo Mensual
A1: Cash Flow Forecast — 12 Meses
A2: AI Chef Pro · aichef.pro — Kit Plan Financiero para Restaurantes
A4: Concepto | B4: Ene | C4: Feb | D4: Mar | E4: Abr | F4: May | G4: Jun | H4: Jul | I4: Ago | J4: Sep | K4: Oct | L4: Nov | M4: Dic
A5: SALDO INICIAL | B5: 15000 | C5: =B22 | D5: =C22 | E5: =D22 | F5: =E22 | G5: =F22 | H5: =G22 | I5: =H22 | J5: =I22 | ... M5: =L22
A6: COBROS (Entradas)
A7: Ventas comedor (IVA incl.) | B7: 0 | C7: 0 | D7: 0 | E7: 0 | F7: 0 | G7: 0 | H7: 0 | I7: 0 | J7: 0 | K7: 0 | L7: 0 | M7: 0
A8: Ventas barra (IVA incl.) | B8: 0 | C8: 0 | D8: 0 | E8: 0 | F8: 0 | G8: 0 | H8: 0 | I8: 0 | J8: 0 | K8: 0 | L8: 0 | M8: 0
A9: Ventas delivery (IVA incl.) | B9: 0 | C9: 0 | D9: 0 | E9: 0 | F9: 0 | G9: 0 | H9: 0 | I9: 0 | J9: 0 | K9: 0 | L9: 0 | M9: 0
A10: Eventos / Catering | B10: 0 | C10: 0 | D10: 0 | E10: 0 | F10: 0 | G10: 0 | H10: 0 | I10: 0 | J10: 0 | K10: 0 | L10: 0 | M10: 0
A11: Otros cobros | B11: 0 | C11: 0 | D11: 0 | E11: 0 | F11: 0 | G11: 0 | H11: 0 | I11: 0 | J11: 0 | K11: 0 | L11: 0 | M11: 0
A12: TOTAL COBROS | B12: =SUM(B7:B11) | C12: =SUM(C7:C11) | D12: =SUM(D7:D11) | E12: =SUM(E7:E11) | F12: =SUM(F7:F11) | G12: =SUM(G7:G11) | H12: =SUM(H7:H11) | I12: =SUM(I7:I11) | ... M12: =SUM(M7:M11)
A13: PAGOS (Salidas)
A14: Compras materia prima | B14: 0 | C14: 0 | D14: 0 | E14: 0 | F14: 0 | G14: 0 | H14: 0 | I14: 0 | J14: 0 | K14: 0 | L14: 0 | M14: 0
A15: Nóminas + SS | B15: 0 | C15: 0 | D15: 0 | E15: 0 | F15: 0 | G15: 0 | H15: 0 | I15: 0 | J15: 0 | K15: 0 | L15: 0 | M15: 0
A16: Alquiler | B16: 0 | C16: 0 | D16: 0 | E16: 0 | F16: 0 | G16: 0 | H16: 0 | I16: 0 | J16: 0 | K16: 0 | L16: 0 | M16: 0
A17: Suministros | B17: 0 | C17: 0 | D17: 0 | E17: 0 | F17: 0 | G17: 0 | H17: 0 | I17: 0 | J17: 0 | K17: 0 | L17: 0 | M17: 0
A18: Marketing | B18: 0 | C18: 0 | D18: 0 | E18: 0 | F18: 0 | G18: 0 | H18: 0 | I18: 0 | J18: 0 | K18: 0 | L18: 0 | M18: 0
A19: Gestoría / Admin | B19: 0 | C19: 0 | D19: 0 | E19: 0 | F19: 0 | G19: 0 | H19: 0 | I19: 0 | J19: 0 | K19: 0 | L19: 0 | M19: 0
A20: Cuota préstamo | B20: 0 | C20: 0 | D20: 0 | E20: 0 | F20: 0 | G20: 0 | H20: 0 | I20: 0 | J20: 0 | K20: 0 | L20: 0 | M20: 0
A21: Liquidación IVA trimestral | B21: 0 | C21: 0 | D21: 0 | E21: 0 | F21: 0 | G21: 0 | H21: 0 | I21: 0 | J21: 0 | K21: 0 | L21: 0 | M21: 0
A22: Otros pagos | B22: 0 | C22: 0 | D22: 0 | E22: 0 | F22: 0 | G22: 0 | H22: 0 | I22: 0 | J22: 0 | K22: 0 | L22: 0 | M22: 0
A23: TOTAL PAGOS | B23: =SUM(B14:B22) | C23: =SUM(C14:C22) | D23: =SUM(D14:D22) | E23: =SUM(E14:E22) | F23: =SUM(F14:F22) | G23: =SUM(G14:G22) | H23: =SUM(H14:H22) | I23: =SUM(I14:I22) | ... M23: =SUM(M14:M22)
A24: FLUJO NETO MES | B24: =B12-B23 | C24: =C12-C23 | D24: =D12-D23 | E24: =E12-E23 | F24: =F12-F23 | G24: =G12-G23 | H24: =H12-H23 | I24: =I12-I23 | ... M24: =M12-M23
A25: SALDO FINAL | B25: =B5+B24 | C25: =C5+C24 | D25: =D5+D24 | E25: =E5+E24 | F25: =F5+F24 | G25: =G5+G24 | H25: =H5+H24 | I25: =I5+I24 | ... M25: =M5+M24
A27: © 2026 AI Chef Pro · aichef.pro

Sheet Alertas
B1: Alertas de Tesorería
B3: Umbral de seguridad (€): | C3: 5000
B5: Mes | C5: Saldo Final | D5: Alerta
B6: Ene | C6: ='Flujo Mensual'!B25 | D6: =IF(C6<$C$3,"⚠️ BAJO MÍNIMO","OK")
B7: Feb | C7: ='Flujo Mensual'!C25 | D7: =IF(C7<$C$3,"⚠️ BAJO MÍNIMO","OK")
B8: Mar | C8: ='Flujo Mensual'!D25 | D8: =IF(C8<$C$3,"⚠️ BAJO MÍNIMO","OK")
B9: Abr | C9: ='Flujo Mensual'!E25 | D9: =IF(C9<$C$3,"⚠️ BAJO MÍNIMO","OK")
B10: May | C10: ='Flujo Mensual'!F25 | D10: =IF(C10<$C$3,"⚠️ BAJO MÍNIMO","OK")
B11: Jun | C11: ='Flujo Mensual'!G25 | D11: =IF(C11<$C$3,"⚠️ BAJO MÍNIMO","OK")
B12: Jul | C12: ='Flujo Mensual'!H25 | D12: =IF(C12<$C$3,"⚠️ BAJO MÍNIMO","OK")
B13: Ago | C13: ='Flujo Mensual'!I25 | D13: =IF(C13<$C$3,"⚠️ BAJO MÍNIMO","OK")
B14: Sep | C14: ='Flujo Mensual'!J25 | D14: =IF(C14<$C$3,"⚠️ BAJO MÍNIMO","OK")
B15: Oct | C15: ='Flujo Mensual'!K25 | D15: =IF(C15<$C$3,"⚠️ BAJO MÍNIMO","OK")
B16: Nov | C16: ='Flujo Mensual'!L25 | D16: =IF(C16<$C$3,"⚠️ BAJO MÍNIMO","OK")
B17: Dic | C17: ='Flujo Mensual'!M25 | D17: =IF(C17<$C$3,"⚠️ BAJO MÍNIMO","OK")
A20: © 2026 AI Chef Pro · aichef.pro
