Workbook

Sheet Instrucciones
B2: 04 · Presupuesto de Inversión (CAPEX)
B4: AI Chef Pro · aichef.pro — Kit Plan Financiero para Restaurantes
B6: Cómo usar esta plantilla:
B7: ▸ Cada pestaña cubre una categoría de inversión inicial.
B8: ▸ Introduce el presupuesto estimado y luego el coste real.
B9: ▸ La desviación se calcula automáticamente (% sobre presupuesto).
B10: ▸ La pestaña Resumen consolida todas las categorías.
B12: Categorías:
B13: ▸ Obra civil, Equipamiento Cocina, Mobiliario Sala, Tecnología, Licencias y Permisos.

Sheet Obra
A1: Inversión — Obra
A2: AI Chef Pro · aichef.pro — Kit Plan Financiero para Restaurantes
A4: Partida | B4: Presupuesto (€) | C4: Real (€) | D4: Desviación % | E4: Notas
A5: Demolición y vaciado | B5: 0 | C5: 0 | D5: =IF(B5=0,0,(C5-B5)/B5)
A6: Albañilería | B6: 0 | C6: 0 | D6: =IF(B6=0,0,(C6-B6)/B6)
A7: Fontanería | B7: 0 | C7: 0 | D7: =IF(B7=0,0,(C7-B7)/B7)
A8: Electricidad | B8: 0 | C8: 0 | D8: =IF(B8=0,0,(C8-B8)/B8)
A9: Climatización / Extracción | B9: 0 | C9: 0 | D9: =IF(B9=0,0,(C9-B9)/B9)
A10: Pintura y acabados | B10: 0 | C10: 0 | D10: =IF(B10=0,0,(C10-B10)/B10)
A11: Suelo | B11: 0 | C11: 0 | D11: =IF(B11=0,0,(C11-B11)/B11)
A12: Fachada / Rótulo | B12: 0 | C12: 0 | D12: =IF(B12=0,0,(C12-B12)/B12)
A13: Baños clientes | B13: 0 | C13: 0 | D13: =IF(B13=0,0,(C13-B13)/B13)
A14: Vestuarios personal | B14: 0 | C14: 0 | D14: =IF(B14=0,0,(C14-B14)/B14)
A15: TOTAL OBRA | B15: =SUM(B5:B14) | C15: =SUM(C5:C14) | D15: =IF(B15=0,0,(C15-B15)/B15)
A17: © 2026 AI Chef Pro · aichef.pro

Sheet Equipamiento Cocina
A1: Inversión — Equipamiento Cocina
A2: AI Chef Pro · aichef.pro — Kit Plan Financiero para Restaurantes
A4: Partida | B4: Presupuesto (€) | C4: Real (€) | D4: Desviación % | E4: Notas
A5: Cocina industrial (fogones) | B5: 0 | C5: 0 | D5: =IF(B5=0,0,(C5-B5)/B5)
A6: Horno combinado | B6: 0 | C6: 0 | D6: =IF(B6=0,0,(C6-B6)/B6)
A7: Plancha / Grill | B7: 0 | C7: 0 | D7: =IF(B7=0,0,(C7-B7)/B7)
A8: Freidora | B8: 0 | C8: 0 | D8: =IF(B8=0,0,(C8-B8)/B8)
A9: Cámara frigorífica | B9: 0 | C9: 0 | D9: =IF(B9=0,0,(C9-B9)/B9)
A10: Congelador | B10: 0 | C10: 0 | D10: =IF(B10=0,0,(C10-B10)/B10)
A11: Mesa de trabajo inox | B11: 0 | C11: 0 | D11: =IF(B11=0,0,(C11-B11)/B11)
A12: Lavavajillas industrial | B12: 0 | C12: 0 | D12: =IF(B12=0,0,(C12-B12)/B12)
A13: Campana extractora | B13: 0 | C13: 0 | D13: =IF(B13=0,0,(C13-B13)/B13)
A14: Pequeño material cocina | B14: 0 | C14: 0 | D14: =IF(B14=0,0,(C14-B14)/B14)
A15: TOTAL EQUIPAMIENTO COCINA | B15: =SUM(B5:B14) | C15: =SUM(C5:C14) | D15: =IF(B15=0,0,(C15-B15)/B15)
A17: © 2026 AI Chef Pro · aichef.pro

Sheet Mobiliario Sala
A1: Inversión — Mobiliario Sala
A2: AI Chef Pro · aichef.pro — Kit Plan Financiero para Restaurantes
A4: Partida | B4: Presupuesto (€) | C4: Real (€) | D4: Desviación % | E4: Notas
A5: Mesas | B5: 0 | C5: 0 | D5: =IF(B5=0,0,(C5-B5)/B5)
A6: Sillas | B6: 0 | C6: 0 | D6: =IF(B6=0,0,(C6-B6)/B6)
A7: Barra | B7: 0 | C7: 0 | D7: =IF(B7=0,0,(C7-B7)/B7)
A8: Taburetes barra | B8: 0 | C8: 0 | D8: =IF(B8=0,0,(C8-B8)/B8)
A9: Estanterías / decoración | B9: 0 | C9: 0 | D9: =IF(B9=0,0,(C9-B9)/B9)
A10: Iluminación | B10: 0 | C10: 0 | D10: =IF(B10=0,0,(C10-B10)/B10)
A11: Terraza (mesas + sillas) | B11: 0 | C11: 0 | D11: =IF(B11=0,0,(C11-B11)/B11)
A12: Textil (manteles, servilletas) | B12: 0 | C12: 0 | D12: =IF(B12=0,0,(C12-B12)/B12)
A13: TOTAL MOBILIARIO SALA | B13: =SUM(B5:B12) | C13: =SUM(C5:C12) | D13: =IF(B13=0,0,(C13-B13)/B13)
A15: © 2026 AI Chef Pro · aichef.pro

Sheet Tecnología
A1: Inversión — Tecnología
A2: AI Chef Pro · aichef.pro — Kit Plan Financiero para Restaurantes
A4: Partida | B4: Presupuesto (€) | C4: Real (€) | D4: Desviación % | E4: Notas
A5: TPV (hardware + software) | B5: 0 | C5: 0 | D5: =IF(B5=0,0,(C5-B5)/B5)
A6: Impresoras comandas | B6: 0 | C6: 0 | D6: =IF(B6=0,0,(C6-B6)/B6)
A7: Datáfono | B7: 0 | C7: 0 | D7: =IF(B7=0,0,(C7-B7)/B7)
A8: Sistema de reservas | B8: 0 | C8: 0 | D8: =IF(B8=0,0,(C8-B8)/B8)
A9: Wifi / Red | B9: 0 | C9: 0 | D9: =IF(B9=0,0,(C9-B9)/B9)
A10: Pantallas / Digital signage | B10: 0 | C10: 0 | D10: =IF(B10=0,0,(C10-B10)/B10)
A11: Web / App delivery | B11: 0 | C11: 0 | D11: =IF(B11=0,0,(C11-B11)/B11)
A12: Sistema de seguridad (cámaras) | B12: 0 | C12: 0 | D12: =IF(B12=0,0,(C12-B12)/B12)
A13: TOTAL TECNOLOGÍA | B13: =SUM(B5:B12) | C13: =SUM(C5:C12) | D13: =IF(B13=0,0,(C13-B13)/B13)
A15: © 2026 AI Chef Pro · aichef.pro

Sheet Licencias
A1: Inversión — Licencias
A2: AI Chef Pro · aichef.pro — Kit Plan Financiero para Restaurantes
A4: Partida | B4: Presupuesto (€) | C4: Real (€) | D4: Desviación % | E4: Notas
A5: Licencia de apertura | B5: 0 | C5: 0 | D5: =IF(B5=0,0,(C5-B5)/B5)
A6: Licencia de obras | B6: 0 | C6: 0 | D6: =IF(B6=0,0,(C6-B6)/B6)
A7: Proyecto técnico (arquitecto) | B7: 0 | C7: 0 | D7: =IF(B7=0,0,(C7-B7)/B7)
A8: Certificado energético | B8: 0 | C8: 0 | D8: =IF(B8=0,0,(C8-B8)/B8)
A9: Plan de autoprotección | B9: 0 | C9: 0 | D9: =IF(B9=0,0,(C9-B9)/B9)
A10: Alta Hacienda / SS | B10: 0 | C10: 0 | D10: =IF(B10=0,0,(C10-B10)/B10)
A11: Registro sanitario | B11: 0 | C11: 0 | D11: =IF(B11=0,0,(C11-B11)/B11)
A12: SGAE / Derechos música | B12: 0 | C12: 0 | D12: =IF(B12=0,0,(C12-B12)/B12)
A13: Seguros (año 1) | B13: 0 | C13: 0 | D13: =IF(B13=0,0,(C13-B13)/B13)
A14: TOTAL LICENCIAS | B14: =SUM(B5:B13) | C14: =SUM(C5:C13) | D14: =IF(B14=0,0,(C14-B14)/B14)
A16: © 2026 AI Chef Pro · aichef.pro

Sheet Resumen
A1: Resumen de Inversión Total
A2: AI Chef Pro · aichef.pro — Kit Plan Financiero para Restaurantes
A4: Categoría | B4: Presupuesto (€) | C4: Real (€) | D4: Desviación %
A5: Obra | B5: ='Obra'!B15 | C5: ='Obra'!C15 | D5: =IF(B5=0,0,(C5-B5)/B5)
A6: Equipamiento Cocina | B6: ='Equipamiento Cocina'!B15 | C6: ='Equipamiento Cocina'!C15 | D6: =IF(B6=0,0,(C6-B6)/B6)
A7: Mobiliario Sala | B7: ='Mobiliario Sala'!B13 | C7: ='Mobiliario Sala'!C13 | D7: =IF(B7=0,0,(C7-B7)/B7)
A8: Tecnología | B8: ='Tecnología'!B13 | C8: ='Tecnología'!C13 | D8: =IF(B8=0,0,(C8-B8)/B8)
A9: Licencias | B9: ='Licencias'!B14 | C9: ='Licencias'!C14 | D9: =IF(B9=0,0,(C9-B9)/B9)
A10: INVERSIÓN TOTAL | B10: =SUM(B5:B9) | C10: =SUM(C5:C9) | D10: =IF(B10=0,0,(C10-B10)/B10)
A13: © 2026 AI Chef Pro · aichef.pro
