Workbook

Sheet Instructions
A1: Vendor List, Price Comparison & Scorecard
A2: AI Chef Pro — aichef.pro
A4: Set up your vendors, approve them, and compare their prices — all in one file.
A6: TABS:
A7: 1. Vendor Directory — tax info (Tax ID (EIN / VAT no.)), food safety info (Food license / FDA reg. no.), contact, order and delivery days, and approval status
A8: 2. Price Comparison — up to 5 vendors per product, compared by price normalized per unit
A9: 3. Vendor Scorecard — quality, price, timeliness, service and flexibility (1-5), with an A/B/C/D grade
A10: 4. Vendor Terms — payment terms, order minimum, volume rebate, delivery fee and hours
A12: HOW TO USE:
A13: 1. Set up each vendor in the directory. Ask them in writing for their Tax ID (EIN / VAT no.) and their Food license / FDA reg. no.: without that you can't approve them or set them up in accounting.
A14: 2. Mark Approved and note the date. Review the paperwork at least once a year: it's the vendor-approval prerequisite your HACCP / food safety plan requires.
A15: 3. In the comparison, fill in the pack size and the content of each line BEFORE entering prices. That's what keeps you from comparing a 5-quart jug to a quart and picking the priciest vendor while thinking it's the cheapest.
... A23: Version 2.0 · September 2026 · aichef.pro/en/digital-products/restaurant-inventory-templates · info@aichef.pro

Sheet Vendor Directory
A1: VENDOR DIRECTORY
A2: Sample profiles (one per purchasing category). The Food license / FDA reg. no. comes from the vendor: ask for it in writing and keep it with their spec sheet.
A3: # | B3: Vendor | C3: Category | D3: Tax ID (EIN / VAT no.) | E3: Food license / FDA reg. no. | F3: Contact | G3: Phone | H3: Email | I3: Issue contact | J3: Address | K3: Order day | L3: Delivery day | M3: Lead time (days) | N3: Order Minimum | O3: Payment terms | P3: Approved (Y/N) | Q3: Approval date | R3: Last review date | S3: Notes
A4: 1 | B4: Prime Cut Meats (sample) | C4: Meat & Poultry | D4: 00-0000001 | E4: USDA Est. 00001 | F4: Mike Reynolds | G4: (555) 555-0101 | H4: orders@primecutmeats.example | I4: credits@primecutmeats.example · (555) 555-0102 | J4: 1200 Industrial Pkwy, Unit 12 · Anytown, USA 00001 | K4: Mon & Thu by 12 p.m. | L4: Tue & Fri | M4: 1 | N4: 300 | O4: Net 30 | P4: Y | Q4: 46063 | R4: 46218 | S4: Require an invoice with lot numbers and arrival temperature.
A5: 2 | B5: Harbor Fresh Seafood (sample) | C5: Seafood | D5: 00-0000002 | E5: FDA Reg. 00000000002 | F5: Dana Whitfield | G5: (555) 555-0103 | H5: orders@harborfreshseafood.example | I5: credits@harborfreshseafood.example · (555) 555-0104 | J5: Pier 8, Harbor Market · Anytown, USA 00002 | K5: Daily by 5 p.m. | L5: Tue to Sat | M5: 1 | N5: 200 | O5: Net 15 | P5: Y | Q5: 46086 | R5: 46223 | S5: Arrives on ice; reject anything above 41 °F.
A6: 3 | B6: Green Valley Produce (sample) | C6: Produce | D6: 00-0000003 | E6: PACA Lic. 00000003 | F6: Carlos Mendez | G6: (555) 555-0105 | H6: orders@greenvalleyproduce.example | I6: credits@greenvalleyproduce.example | J6: Produce Terminal, Bldg 4 · Anytown, USA 00003 | K6: Mon, Wed & Fri by 6 p.m. | L6: Tue, Thu & Sat | M6: 1 | N6: 150 | O6: COD | P6: Y | Q6: 46034 | R6: 46215 | S6: Seasonal produce: confirm prices every week.
A7: 4 | B7: Pantry Foodservice Supply (sample) | C7: Dry Goods | D7: 00-0000004 | E7: FDA Reg. 00000000004 | F7: Tom Becker | G7: (555) 555-0106 | H7: orders@pantryfoodservice.example | I7: credits@pantryfoodservice.example | J7: 450 Commerce Dr, Suite 27 · Anytown, USA 00004 | K7: Tue by 2 p.m. | L7: Thu | M7: 2 | N7: 500 | O7: Net 45 | P7: Y | Q7: 46073 | R7: 46221 | S7: 2% volume rebate on purchases over $2,000 a month.
A8: 5 | B8: Metro Beverage Distributors (sample) | C8: Alcoholic Beverages | D8: 00-0000005 | E8: State dist. lic. 000005 | F8: Jen Park | G8: (555) 555-0107 | H8: orders@metrobeverage.example | I8: credits@metrobeverage.example | J8: 82 Route 40 · Anytown, USA 00005 | K8: Mon by 12 p.m. | L8: Wed | M8: 2 | N8: 250 | O8: Net 30 | P8: Y | Q8: 46050 | R8: 46213 | S8: Kegs and CO2 cylinders on loan: check the deposit on every invoice.
A9: 6 | B9: ProClean Janitorial Supply (sample) | C9: Paper & Cleaning | D9: 00-0000006 | E9: N/A (non-food supplier) | F9: Lisa Grant | G9: (555) 555-0108 | H9: orders@procleansupply.example | I9: credits@procleansupply.example | J9: 15 Industry Ave · Anytown, USA 00006 | K9: Wed by 4 p.m. | L9: Fri | M9: 2 | N9: 150 | O9: Net 30 | P9: Pending | Q9: 46056 | R9: 46237 | S9: Grade D (2.2/5) at the last review: approval ON HOLD until it improves. Find an alternative before the next review.
A10: 7
A11: 8
A12: 9
A13: 10
A14: 11
A15: 12
A16: 13
A17: 14
A18: 15
A19: 16
A20: 17
A21: 18
... A23: 20

Sheet Price Comparison
A1: PRICE COMPARISON BY VENDOR
A2: The five price columns are the first five vendors in the directory: ask them for a quote on the SAME pack size. Fill in Pack Size and Content BEFORE the prices: without Content there's no per-unit price to compare, and the row will tell you so. Columns P to T (hidden) are that per-unit price. And check the Status column: an expired comparison is worse than not having one, because you'd be negotiating with a number the vendor no longer honors.
A3: # | B3: Product | C3: Unit | D3: Pack size | E3: Content (lb/gal/each) | F3: =IF('Vendor Directory'!$B$4="","Vendor 1",'Vendor Directory'!$B$4) -> Prime Cut Meats (sample) | G3: =IF('Vendor Directory'!$B$5="","Vendor 2",'Vendor Directory'!$B$5) -> Harbor Fresh Seafood (sample) | H3: =IF('Vendor Directory'!$B$6="","Vendor 3",'Vendor Directory'!$B$6) -> Green Valley Produce (sample) | I3: =IF('Vendor Directory'!$B$7="","Vendor 4",'Vendor Directory'!$B$7) -> Pantry Foodservice Supply (sample) | J3: =IF('Vendor Directory'!$B$8="","Vendor 5",'Vendor Directory'!$B$8) -> Metro Beverage Distributors (sample) | K3: Best price/unit | L3: Best vendor | M3: % Difference | N3: Quote date | O3: Valid until | P3: Norm. 1 | Q3: Norm. 2 | R3: Norm. 3 | S3: Norm. 4 | T3: Norm. 5 | U3: Quote status
A4: 1 | B4: Boneless chicken breast | C4: lb | D4: Case, 40 lb | E4: 40 | F4: 124 | G4: 128 | H4: 131.2 | J4: 126.4 | K4: =IF(COUNT($F4:$J4)=0,"",IF($E4="","⚠ missing pack size",IF(COUNT($P4:$T4)=0,"",MIN($P4:$T4)))) -> 3.1 | L4: =IF(OR($K4="",$K4="⚠ missing pack size"),"",IFERROR(INDEX($F$3:$J$3,MATCH($K4,$P4:$T4,0)),"")) -> Prime Cut Meats (sample) | M4: =IF(OR($K4="",$K4="⚠ missing pack size"),"",IFERROR((MAX($P4:$T4)-$K4)/$K4,"")) -> 0.058064516 | N4: =TODAY()-21 -> 46269 | O4: =TODAY()+9 -> 46299 | P4: =IF(OR($F4="",$F4<=0,$E4="",$E4<=0),"",IFERROR($F4/$E4,"")) -> 3.1 | Q4: =IF(OR($G4="",$G4<=0,$E4="",$E4<=0),"",IFERROR($G4/$E4,"")) -> 3.2 | R4: =IF(OR($H4="",$H4<=0,$E4="",$E4<=0),"",IFERROR($H4/$E4,"")) -> 3.28 | S4: =IF(OR($I4="",$I4<=0,$E4="",$E4<=0),"",IFERROR($I4/$E4,"")) | T4: =IF(OR($J4="",$J4<=0,$E4="",$E4<=0),"",IFERROR($J4/$E4,"")) -> 3.16 | U4: =IF($O4="","",IF($O4<TODAY(),"⛔ QUOTE EXPIRED",IF($O4-TODAY()<=7,"🟡 expires this week","🟢 current"))) -> 🟢 current
A5: 2 | B5: Beef tenderloin (PSMO) | C5: lb | D5: Whole PSMO, about 6 lb | E5: 6 | K5: =IF(COUNT($F5:$J5)=0,"",IF($E5="","⚠ missing pack size",IF(COUNT($P5:$T5)=0,"",MIN($P5:$T5)))) | L5: =IF(OR($K5="",$K5="⚠ missing pack size"),"",IFERROR(INDEX($F$3:$J$3,MATCH($K5,$P5:$T5,0)),"")) | M5: =IF(OR($K5="",$K5="⚠ missing pack size"),"",IFERROR((MAX($P5:$T5)-$K5)/$K5,"")) | P5: =IF(OR($F5="",$F5<=0,$E5="",$E5<=0),"",IFERROR($F5/$E5,"")) | Q5: =IF(OR($G5="",$G5<=0,$E5="",$E5<=0),"",IFERROR($G5/$E5,"")) | R5: =IF(OR($H5="",$H5<=0,$E5="",$E5<=0),"",IFERROR($H5/$E5,"")) | S5: =IF(OR($I5="",$I5<=0,$E5="",$E5<=0),"",IFERROR($I5/$E5,"")) | T5: =IF(OR($J5="",$J5<=0,$E5="",$E5<=0),"",IFERROR($J5/$E5,"")) | U5: =IF($O5="","",IF($O5<TODAY(),"⛔ QUOTE EXPIRED",IF($O5-TODAY()<=7,"🟡 expires this week","🟢 current")))
A6: 3 | B6: Fresh salmon fillet | C6: lb | D6: Whole side, about 3 lb | E6: 3 | K6: =IF(COUNT($F6:$J6)=0,"",IF($E6="","⚠ missing pack size",IF(COUNT($P6:$T6)=0,"",MIN($P6:$T6)))) | L6: =IF(OR($K6="",$K6="⚠ missing pack size"),"",IFERROR(INDEX($F$3:$J$3,MATCH($K6,$P6:$T6,0)),"")) | M6: =IF(OR($K6="",$K6="⚠ missing pack size"),"",IFERROR((MAX($P6:$T6)-$K6)/$K6,"")) | P6: =IF(OR($F6="",$F6<=0,$E6="",$E6<=0),"",IFERROR($F6/$E6,"")) | Q6: =IF(OR($G6="",$G6<=0,$E6="",$E6<=0),"",IFERROR($G6/$E6,"")) | R6: =IF(OR($H6="",$H6<=0,$E6="",$E6<=0),"",IFERROR($H6/$E6,"")) | S6: =IF(OR($I6="",$I6<=0,$E6="",$E6<=0),"",IFERROR($I6/$E6,"")) | T6: =IF(OR($J6="",$J6<=0,$E6="",$E6<=0),"",IFERROR($J6/$E6,"")) | U6: =IF($O6="","",IF($O6<TODAY(),"⛔ QUOTE EXPIRED",IF($O6-TODAY()<=7,"🟡 expires this week","🟢 current")))
A7: 4 | B7: Extra virgin olive oil | C7: gal | D7: Case, 4 x 1 gal | E7: 4 | F7: 136 | G7: 134 | H7: 132.8 | I7: 129.92 | J7: 138 | K7: =IF(COUNT($F7:$J7)=0,"",IF($E7="","⚠ missing pack size",IF(COUNT($P7:$T7)=0,"",MIN($P7:$T7)))) -> 32.48 | L7: =IF(OR($K7="",$K7="⚠ missing pack size"),"",IFERROR(INDEX($F$3:$J$3,MATCH($K7,$P7:$T7,0)),"")) -> Pantry Foodservice Supply (sample) | M7: =IF(OR($K7="",$K7="⚠ missing pack size"),"",IFERROR((MAX($P7:$T7)-$K7)/$K7,"")) -> 0.062192118 | N7: =TODAY()-21 -> 46269 | O7: =TODAY()+9 -> 46299 | P7: =IF(OR($F7="",$F7<=0,$E7="",$E7<=0),"",IFERROR($F7/$E7,"")) -> 34 | Q7: =IF(OR($G7="",$G7<=0,$E7="",$E7<=0),"",IFERROR($G7/$E7,"")) -> 33.5 | R7: =IF(OR($H7="",$H7<=0,$E7="",$E7<=0),"",IFERROR($H7/$E7,"")) -> 33.2 | S7: =IF(OR($I7="",$I7<=0,$E7="",$E7<=0),"",IFERROR($I7/$E7,"")) -> 32.48 | T7: =IF(OR($J7="",$J7<=0,$E7="",$E7<=0),"",IFERROR($J7/$E7,"")) -> 34.5 | U7: =IF($O7="","",IF($O7<TODAY(),"⛔ QUOTE EXPIRED",IF($O7-TODAY()<=7,"🟡 expires this week","🟢 current"))) -> 🟢 current
A8: 5 | B8: Tomatoes | C8: lb | D8: 25 lb case | E8: 25 | F8: 51.25 | G8: 52.5 | H8: 49.5 | I8: 50.5 | J8: 49.75 | K8: =IF(COUNT($F8:$J8)=0,"",IF($E8="","⚠ missing pack size",IF(COUNT($P8:$T8)=0,"",MIN($P8:$T8)))) -> 1.98 | L8: =IF(OR($K8="",$K8="⚠ missing pack size"),"",IFERROR(INDEX($F$3:$J$3,MATCH($K8,$P8:$T8,0)),"")) -> Green Valley Produce (sample) | M8: =IF(OR($K8="",$K8="⚠ missing pack size"),"",IFERROR((MAX($P8:$T8)-$K8)/$K8,"")) -> 0.060606061 | N8: =TODAY()-14 -> 46276 | O8: =TODAY()+16 -> 46306 | P8: =IF(OR($F8="",$F8<=0,$E8="",$E8<=0),"",IFERROR($F8/$E8,"")) -> 2.05 | Q8: =IF(OR($G8="",$G8<=0,$E8="",$E8<=0),"",IFERROR($G8/$E8,"")) -> 2.1 | R8: =IF(OR($H8="",$H8<=0,$E8="",$E8<=0),"",IFERROR($H8/$E8,"")) -> 1.98 | S8: =IF(OR($I8="",$I8<=0,$E8="",$E8<=0),"",IFERROR($I8/$E8,"")) -> 2.02 | T8: =IF(OR($J8="",$J8<=0,$E8="",$E8<=0),"",IFERROR($J8/$E8,"")) -> 1.99 | U8: =IF($O8="","",IF($O8<TODAY(),"⛔ QUOTE EXPIRED",IF($O8-TODAY()<=7,"🟡 expires this week","🟢 current"))) -> 🟢 current
A9: 6 | B9: Romaine lettuce | C9: each | D9: Case, 24 heads | E9: 24 | K9: =IF(COUNT($F9:$J9)=0,"",IF($E9="","⚠ missing pack size",IF(COUNT($P9:$T9)=0,"",MIN($P9:$T9)))) | L9: =IF(OR($K9="",$K9="⚠ missing pack size"),"",IFERROR(INDEX($F$3:$J$3,MATCH($K9,$P9:$T9,0)),"")) | M9: =IF(OR($K9="",$K9="⚠ missing pack size"),"",IFERROR((MAX($P9:$T9)-$K9)/$K9,"")) | P9: =IF(OR($F9="",$F9<=0,$E9="",$E9<=0),"",IFERROR($F9/$E9,"")) | Q9: =IF(OR($G9="",$G9<=0,$E9="",$E9<=0),"",IFERROR($G9/$E9,"")) | R9: =IF(OR($H9="",$H9<=0,$E9="",$E9<=0),"",IFERROR($H9/$E9,"")) | S9: =IF(OR($I9="",$I9<=0,$E9="",$E9<=0),"",IFERROR($I9/$E9,"")) | T9: =IF(OR($J9="",$J9<=0,$E9="",$E9<=0),"",IFERROR($J9/$E9,"")) | U9: =IF($O9="","",IF($O9<TODAY(),"⛔ QUOTE EXPIRED",IF($O9-TODAY()<=7,"🟡 expires this week","🟢 current")))
A10: 7 | B10: Arborio rice | C10: lb | D10: 25 lb bag | E10: 25 | K10: =IF(COUNT($F10:$J10)=0,"",IF($E10="","⚠ missing pack size",IF(COUNT($P10:$T10)=0,"",MIN($P10:$T10)))) | L10: =IF(OR($K10="",$K10="⚠ missing pack size"),"",IFERROR(INDEX($F$3:$J$3,MATCH($K10,$P10:$T10,0)),"")) | M10: =IF(OR($K10="",$K10="⚠ missing pack size"),"",IFERROR((MAX($P10:$T10)-$K10)/$K10,"")) | P10: =IF(OR($F10="",$F10<=0,$E10="",$E10<=0),"",IFERROR($F10/$E10,"")) | Q10: =IF(OR($G10="",$G10<=0,$E10="",$E10<=0),"",IFERROR($G10/$E10,"")) | R10: =IF(OR($H10="",$H10<=0,$E10="",$E10<=0),"",IFERROR($H10/$E10,"")) | S10: =IF(OR($I10="",$I10<=0,$E10="",$E10<=0),"",IFERROR($I10/$E10,"")) | T10: =IF(OR($J10="",$J10<=0,$E10="",$E10<=0),"",IFERROR($J10/$E10,"")) | U10: =IF($O10="","",IF($O10<TODAY(),"⛔ QUOTE EXPIRED",IF($O10-TODAY()<=7,"🟡 expires this week","🟢 current")))
A11: 8 | B11: Large eggs | C11: dozen | D11: 15 dozen case | E11: 15 | K11: =IF(COUNT($F11:$J11)=0,"",IF($E11="","⚠ missing pack size",IF(COUNT($P11:$T11)=0,"",MIN($P11:$T11)))) | L11: =IF(OR($K11="",$K11="⚠ missing pack size"),"",IFERROR(INDEX($F$3:$J$3,MATCH($K11,$P11:$T11,0)),"")) | M11: =IF(OR($K11="",$K11="⚠ missing pack size"),"",IFERROR((MAX($P11:$T11)-$K11)/$K11,"")) | P11: =IF(OR($F11="",$F11<=0,$E11="",$E11<=0),"",IFERROR($F11/$E11,"")) | Q11: =IF(OR($G11="",$G11<=0,$E11="",$E11<=0),"",IFERROR($G11/$E11,"")) | R11: =IF(OR($H11="",$H11<=0,$E11="",$E11<=0),"",IFERROR($H11/$E11,"")) | S11: =IF(OR($I11="",$I11<=0,$E11="",$E11<=0),"",IFERROR($I11/$E11,"")) | T11: =IF(OR($J11="",$J11<=0,$E11="",$E11<=0),"",IFERROR($J11/$E11,"")) | U11: =IF($O11="","",IF($O11<TODAY(),"⛔ QUOTE EXPIRED",IF($O11-TODAY()<=7,"🟡 expires this week","🟢 current")))
A12: 9 | B12: Whole milk | C12: gal | D12: Case, 4 x 1 gal | E12: 4 | K12: =IF(COUNT($F12:$J12)=0,"",IF($E12="","⚠ missing pack size",IF(COUNT($P12:$T12)=0,"",MIN($P12:$T12)))) | L12: =IF(OR($K12="",$K12="⚠ missing pack size"),"",IFERROR(INDEX($F$3:$J$3,MATCH($K12,$P12:$T12,0)),"")) | M12: =IF(OR($K12="",$K12="⚠ missing pack size"),"",IFERROR((MAX($P12:$T12)-$K12)/$K12,"")) | P12: =IF(OR($F12="",$F12<=0,$E12="",$E12<=0),"",IFERROR($F12/$E12,"")) | Q12: =IF(OR($G12="",$G12<=0,$E12="",$E12<=0),"",IFERROR($G12/$E12,"")) | R12: =IF(OR($H12="",$H12<=0,$E12="",$E12<=0),"",IFERROR($H12/$E12,"")) | S12: =IF(OR($I12="",$I12<=0,$E12="",$E12<=0),"",IFERROR($I12/$E12,"")) | T12: =IF(OR($J12="",$J12<=0,$E12="",$E12<=0),"",IFERROR($J12/$E12,"")) | U12: =IF($O12="","",IF($O12<TODAY(),"⛔ QUOTE EXPIRED",IF($O12-TODAY()<=7,"🟡 expires this week","🟢 current")))
A13: 10 | B13: Parmesan | C13: lb | D13: Case, 2 x 5 lb wedges | E13: 10 | K13: =IF(COUNT($F13:$J13)=0,"",IF($E13="","⚠ missing pack size",IF(COUNT($P13:$T13)=0,"",MIN($P13:$T13)))) | L13: =IF(OR($K13="",$K13="⚠ missing pack size"),"",IFERROR(INDEX($F$3:$J$3,MATCH($K13,$P13:$T13,0)),"")) | M13: =IF(OR($K13="",$K13="⚠ missing pack size"),"",IFERROR((MAX($P13:$T13)-$K13)/$K13,"")) | P13: =IF(OR($F13="",$F13<=0,$E13="",$E13<=0),"",IFERROR($F13/$E13,"")) | Q13: =IF(OR($G13="",$G13<=0,$E13="",$E13<=0),"",IFERROR($G13/$E13,"")) | R13: =IF(OR($H13="",$H13<=0,$E13="",$E13<=0),"",IFERROR($H13/$E13,"")) | S13: =IF(OR($I13="",$I13<=0,$E13="",$E13<=0),"",IFERROR($I13/$E13,"")) | T13: =IF(OR($J13="",$J13<=0,$E13="",$E13<=0),"",IFERROR($J13/$E13,"")) | U13: =IF($O13="","",IF($O13<TODAY(),"⛔ QUOTE EXPIRED",IF($O13-TODAY()<=7,"🟡 expires this week","🟢 current")))

Sheet Vendor Scorecard
A1: VENDOR SCORECARD
A2: The grade needs at least 3 scored criteria: with just one, the average doesn't mean anything. The last column cross-checks the grade against the "Approved" box in the directory: a "D — Replace" that's still marked Approved is a contradiction, and vendor approval is a prerequisite of your HACCP / food safety plan.
A3: # | B3: Vendor | C3: Quality (1-5) | D3: Price (1-5) | E3: Timeliness (1-5) | F3: Service (1-5) | G3: Flexibility (1-5) | H3: AVERAGE SCORE (1-5) | I3: Grade | J3: Consistency with directory
A4: 1 | B4: Prime Cut Meats (sample) | C4: 5 | D4: 4 | E4: 5 | F4: 5 | G4: 5 | H4: =IF(COUNT($C4:$G4)<3,"",AVERAGE($C4:$G4)) -> 4.8 | I4: =IF($H4="","",IF($H4>=4.5,"A — Preferred",IF($H4>=3.5,"B — Approved",IF($H4>=2.5,"C — Monitor","D — Replace")))) -> A — Preferred | J4: =IF($I4="","",IF(IFERROR(VLOOKUP($B4,'Vendor Directory'!$B$4:$P$23,15,FALSE),"")<>"Y","—",IF(LEFT($I4,1)="D","⚠ D grade but still approved: review it",IF(LEFT($I4,1)="C","🟡 C grade: monitor it, still approved","✓ consistent")))) -> ✓ consistent
A5: 2 | B5: Harbor Fresh Seafood (sample) | C5: 5 | D5: 3 | E5: 4 | F5: 4 | G5: 3 | H5: =IF(COUNT($C5:$G5)<3,"",AVERAGE($C5:$G5)) -> 3.8 | I5: =IF($H5="","",IF($H5>=4.5,"A — Preferred",IF($H5>=3.5,"B — Approved",IF($H5>=2.5,"C — Monitor","D — Replace")))) -> B — Approved | J5: =IF($I5="","",IF(IFERROR(VLOOKUP($B5,'Vendor Directory'!$B$4:$P$23,15,FALSE),"")<>"Y","—",IF(LEFT($I5,1)="D","⚠ D grade but still approved: review it",IF(LEFT($I5,1)="C","🟡 C grade: monitor it, still approved","✓ consistent")))) -> ✓ consistent
A6: 3 | B6: Green Valley Produce (sample) | C6: 4 | D6: 4 | E6: 3 | F6: 4 | G6: 4 | H6: =IF(COUNT($C6:$G6)<3,"",AVERAGE($C6:$G6)) -> 3.8 | I6: =IF($H6="","",IF($H6>=4.5,"A — Preferred",IF($H6>=3.5,"B — Approved",IF($H6>=2.5,"C — Monitor","D — Replace")))) -> B — Approved | J6: =IF($I6="","",IF(IFERROR(VLOOKUP($B6,'Vendor Directory'!$B$4:$P$23,15,FALSE),"")<>"Y","—",IF(LEFT($I6,1)="D","⚠ D grade but still approved: review it",IF(LEFT($I6,1)="C","🟡 C grade: monitor it, still approved","✓ consistent")))) -> ✓ consistent
A7: 4 | B7: Pantry Foodservice Supply (sample) | C7: 3 | D7: 5 | E7: 4 | F7: 3 | G7: 2 | H7: =IF(COUNT($C7:$G7)<3,"",AVERAGE($C7:$G7)) -> 3.4 | I7: =IF($H7="","",IF($H7>=4.5,"A — Preferred",IF($H7>=3.5,"B — Approved",IF($H7>=2.5,"C — Monitor","D — Replace")))) -> C — Monitor | J7: =IF($I7="","",IF(IFERROR(VLOOKUP($B7,'Vendor Directory'!$B$4:$P$23,15,FALSE),"")<>"Y","—",IF(LEFT($I7,1)="D","⚠ D grade but still approved: review it",IF(LEFT($I7,1)="C","🟡 C grade: monitor it, still approved","✓ consistent")))) -> 🟡 C grade: monitor it, still approved
A8: 5 | B8: Metro Beverage Distributors (sample) | C8: 4 | D8: 4 | E8: 5 | F8: 4 | G8: 4 | H8: =IF(COUNT($C8:$G8)<3,"",AVERAGE($C8:$G8)) -> 4.2 | I8: =IF($H8="","",IF($H8>=4.5,"A — Preferred",IF($H8>=3.5,"B — Approved",IF($H8>=2.5,"C — Monitor","D — Replace")))) -> B — Approved | J8: =IF($I8="","",IF(IFERROR(VLOOKUP($B8,'Vendor Directory'!$B$4:$P$23,15,FALSE),"")<>"Y","—",IF(LEFT($I8,1)="D","⚠ D grade but still approved: review it",IF(LEFT($I8,1)="C","🟡 C grade: monitor it, still approved","✓ consistent")))) -> ✓ consistent
A9: 6 | B9: ProClean Janitorial Supply (sample) | C9: 2 | D9: 3 | E9: 2 | F9: 2 | G9: 2 | H9: =IF(COUNT($C9:$G9)<3,"",AVERAGE($C9:$G9)) -> 2.2 | I9: =IF($H9="","",IF($H9>=4.5,"A — Preferred",IF($H9>=3.5,"B — Approved",IF($H9>=2.5,"C — Monitor","D — Replace")))) -> D — Replace | J9: =IF($I9="","",IF(IFERROR(VLOOKUP($B9,'Vendor Directory'!$B$4:$P$23,15,FALSE),"")<>"Y","—",IF(LEFT($I9,1)="D","⚠ D grade but still approved: review it",IF(LEFT($I9,1)="C","🟡 C grade: monitor it, still approved","✓ consistent")))) -> —
A10: 7 | H10: =IF(COUNT($C10:$G10)<3,"",AVERAGE($C10:$G10)) | I10: =IF($H10="","",IF($H10>=4.5,"A — Preferred",IF($H10>=3.5,"B — Approved",IF($H10>=2.5,"C — Monitor","D — Replace")))) | J10: =IF($I10="","",IF(IFERROR(VLOOKUP($B10,'Vendor Directory'!$B$4:$P$23,15,FALSE),"")<>"Y","—",IF(LEFT($I10,1)="D","⚠ D grade but still approved: review it",IF(LEFT($I10,1)="C","🟡 C grade: monitor it, still approved","✓ consistent"))))
A11: 8 | H11: =IF(COUNT($C11:$G11)<3,"",AVERAGE($C11:$G11)) | I11: =IF($H11="","",IF($H11>=4.5,"A — Preferred",IF($H11>=3.5,"B — Approved",IF($H11>=2.5,"C — Monitor","D — Replace")))) | J11: =IF($I11="","",IF(IFERROR(VLOOKUP($B11,'Vendor Directory'!$B$4:$P$23,15,FALSE),"")<>"Y","—",IF(LEFT($I11,1)="D","⚠ D grade but still approved: review it",IF(LEFT($I11,1)="C","🟡 C grade: monitor it, still approved","✓ consistent"))))
A12: 9 | H12: =IF(COUNT($C12:$G12)<3,"",AVERAGE($C12:$G12)) | I12: =IF($H12="","",IF($H12>=4.5,"A — Preferred",IF($H12>=3.5,"B — Approved",IF($H12>=2.5,"C — Monitor","D — Replace")))) | J12: =IF($I12="","",IF(IFERROR(VLOOKUP($B12,'Vendor Directory'!$B$4:$P$23,15,FALSE),"")<>"Y","—",IF(LEFT($I12,1)="D","⚠ D grade but still approved: review it",IF(LEFT($I12,1)="C","🟡 C grade: monitor it, still approved","✓ consistent"))))
A13: 10 | H13: =IF(COUNT($C13:$G13)<3,"",AVERAGE($C13:$G13)) | I13: =IF($H13="","",IF($H13>=4.5,"A — Preferred",IF($H13>=3.5,"B — Approved",IF($H13>=2.5,"C — Monitor","D — Replace")))) | J13: =IF($I13="","",IF(IFERROR(VLOOKUP($B13,'Vendor Directory'!$B$4:$P$23,15,FALSE),"")<>"Y","—",IF(LEFT($I13,1)="D","⚠ D grade but still approved: review it",IF(LEFT($I13,1)="C","🟡 C grade: monitor it, still approved","✓ consistent"))))

Sheet Vendor Terms
A1: VENDOR TERMS
A2: Vendor, payment terms, order minimum, and order and delivery days ARE PULLED AUTOMATICALLY from the Vendor Directory: they're entered once, in one place. What you fill in here is the negotiation-specific part: volume rebate, delivery fee, delivery window and notes.
A3: # | B3: Vendor | C3: Payment terms | D3: Order Minimum | E3: Volume rebate (%) | F3: Delivery fee | G3: Delivery window | H3: Order days | I3: Delivery days | J3: Notes
A4: 1 | B4: =IF('Vendor Directory'!$B4="","",'Vendor Directory'!$B4) -> Prime Cut Meats (sample) | C4: =IF('Vendor Directory'!$O4="","",'Vendor Directory'!$O4) -> Net 30 | D4: =IF('Vendor Directory'!$N4="","",'Vendor Directory'!$N4) -> 300 | E4: 0.02 | F4: Free over $300 | G4: 7:00-9:00 a.m. | H4: =IF('Vendor Directory'!$K4="","",'Vendor Directory'!$K4) -> Mon & Thu by 12 p.m. | I4: =IF('Vendor Directory'!$L4="","",'Vendor Directory'!$L4) -> Tue & Fri | J4: $25 delivery fee below the minimum.
A5: 2 | B5: =IF('Vendor Directory'!$B5="","",'Vendor Directory'!$B5) -> Harbor Fresh Seafood (sample) | C5: =IF('Vendor Directory'!$O5="","",'Vendor Directory'!$O5) -> Net 15 | D5: =IF('Vendor Directory'!$N5="","",'Vendor Directory'!$N5) -> 200 | E5: 0 | F5: Free | G5: 6:30-8:00 a.m. | H5: =IF('Vendor Directory'!$K5="","",'Vendor Directory'!$K5) -> Daily by 5 p.m. | I5: =IF('Vendor Directory'!$L5="","",'Vendor Directory'!$L5) -> Tue to Sat | J5: Market price, set the day before delivery.
A6: 3 | B6: =IF('Vendor Directory'!$B6="","",'Vendor Directory'!$B6) -> Green Valley Produce (sample) | C6: =IF('Vendor Directory'!$O6="","",'Vendor Directory'!$O6) -> COD | D6: =IF('Vendor Directory'!$N6="","",'Vendor Directory'!$N6) -> 150 | E6: 0 | F6: Free over $150 | G6: 6:00-8:00 a.m. | H6: =IF('Vendor Directory'!$K6="","",'Vendor Directory'!$K6) -> Mon, Wed & Fri by 6 p.m. | I6: =IF('Vendor Directory'!$L6="","",'Vendor Directory'!$L6) -> Tue, Thu & Sat | J6: No order minimum on Saturdays.
A7: 4 | B7: =IF('Vendor Directory'!$B7="","",'Vendor Directory'!$B7) -> Pantry Foodservice Supply (sample) | C7: =IF('Vendor Directory'!$O7="","",'Vendor Directory'!$O7) -> Net 45 | D7: =IF('Vendor Directory'!$N7="","",'Vendor Directory'!$N7) -> 500 | E7: 0.02 | F7: $35 below the minimum | G7: 9:00 a.m.-1:00 p.m. | H7: =IF('Vendor Directory'!$K7="","",'Vendor Directory'!$K7) -> Tue by 2 p.m. | I7: =IF('Vendor Directory'!$L7="","",'Vendor Directory'!$L7) -> Thu | J7: Rebate paid quarterly.
A8: 5 | B8: =IF('Vendor Directory'!$B8="","",'Vendor Directory'!$B8) -> Metro Beverage Distributors (sample) | C8: =IF('Vendor Directory'!$O8="","",'Vendor Directory'!$O8) -> Net 30 | D8: =IF('Vendor Directory'!$N8="","",'Vendor Directory'!$N8) -> 250 | E8: 0.03 | F8: Free over $250 | G8: 10:00 a.m.-1:00 p.m. | H8: =IF('Vendor Directory'!$K8="","",'Vendor Directory'!$K8) -> Mon by 12 p.m. | I8: =IF('Vendor Directory'!$L8="","",'Vendor Directory'!$L8) -> Wed | J8: Deposit on kegs and returnable crates.
A9: 6 | B9: =IF('Vendor Directory'!$B9="","",'Vendor Directory'!$B9) -> ProClean Janitorial Supply (sample) | C9: =IF('Vendor Directory'!$O9="","",'Vendor Directory'!$O9) -> Net 30 | D9: =IF('Vendor Directory'!$N9="","",'Vendor Directory'!$N9) -> 150 | E9: 0 | F9: Free over $150 | G9: 11:00 a.m.-2:00 p.m. | H9: =IF('Vendor Directory'!$K9="","",'Vendor Directory'!$K9) -> Wed by 4 p.m. | I9: =IF('Vendor Directory'!$L9="","",'Vendor Directory'!$L9) -> Fri | J9: Safety Data Sheets (SDS) with every delivery.
A10: 7 | B10: =IF('Vendor Directory'!$B10="","",'Vendor Directory'!$B10) | C10: =IF('Vendor Directory'!$O10="","",'Vendor Directory'!$O10) | D10: =IF('Vendor Directory'!$N10="","",'Vendor Directory'!$N10) | H10: =IF('Vendor Directory'!$K10="","",'Vendor Directory'!$K10) | I10: =IF('Vendor Directory'!$L10="","",'Vendor Directory'!$L10)
A11: 8 | B11: =IF('Vendor Directory'!$B11="","",'Vendor Directory'!$B11) | C11: =IF('Vendor Directory'!$O11="","",'Vendor Directory'!$O11) | D11: =IF('Vendor Directory'!$N11="","",'Vendor Directory'!$N11) | H11: =IF('Vendor Directory'!$K11="","",'Vendor Directory'!$K11) | I11: =IF('Vendor Directory'!$L11="","",'Vendor Directory'!$L11)
A12: 9 | B12: =IF('Vendor Directory'!$B12="","",'Vendor Directory'!$B12) | C12: =IF('Vendor Directory'!$O12="","",'Vendor Directory'!$O12) | D12: =IF('Vendor Directory'!$N12="","",'Vendor Directory'!$N12) | H12: =IF('Vendor Directory'!$K12="","",'Vendor Directory'!$K12) | I12: =IF('Vendor Directory'!$L12="","",'Vendor Directory'!$L12)
A13: 10 | B13: =IF('Vendor Directory'!$B13="","",'Vendor Directory'!$B13) | C13: =IF('Vendor Directory'!$O13="","",'Vendor Directory'!$O13) | D13: =IF('Vendor Directory'!$N13="","",'Vendor Directory'!$N13) | H13: =IF('Vendor Directory'!$K13="","",'Vendor Directory'!$K13) | I13: =IF('Vendor Directory'!$L13="","",'Vendor Directory'!$L13)
