Workbook

Sheet Instructions
A1: Purchase Order Template & Order Log
A2: AI Chef Pro — aichef.pro
A4: Generate purchase orders with the correct tax on every line and the breakdown a packing slip requires.
A5: 1. Fill in your business info once, in the green block on the right: business name, Tax ID (EIN / VAT no.), delivery address and contact. Without it, whoever receives the order doesn't know who's ordering or where to deliver.
A6: 2. Set up your vendors on the "Vendors" tab. The order's drop-down, the phone number and the order minimum in the header all come from that table.
A7: 3. On "Current Order", enter the product, category, unit, quantity and price. Tax fills in automatically: it first looks up the PRODUCT in the exceptions table on the "Tax Rates" tab and, if it's not there, applies its category's rate. You can override it line by line by typing your own rate. If you skip the category, the tax cell stays BLANK instead of silently defaulting to a rate — type the rates you actually pay so nothing is assumed for you.
A8: 3a. The first THREE lines are an example with quantity and price so you can see the order working — net amount, tax and total, broken down by rate. DELETE THEM before sending your first order.
A9: 4. If you enter a quantity and skip the price, the subtotal cell warns "missing cost" instead of valuing the line at 0.00 and adding it to the total as if it were free.
A10: 5. The order totals are in rows 40 to 42: net amount (pre-tax), tax amount and order total. Right below, in row 43, the file tells you whether the order MEETS THE VENDOR'S MINIMUM and, if not, how much you are short: that is what saves you the delivery fee. Rows 45 to 48 break the order down by tax rate (0%, 5% and 20% by default: type the rates you actually pay).
A11: 6. When you close the order, copy row 4 of "Order Log" and paste it as values: it's already linked to the current order. That row 4 does NOT add into the period total, precisely so the order isn't counted twice while you're copying it.
A12: 7. The "Tax Rates" tab holds TWO tables: the tax rate for each category and, next to it, the product-level exceptions. Both ship at 0% and empty — type the rates you actually pay and add your own exceptions: they're tables, not numbers buried inside a formula. In the U.S., food and drinks bought for resale are usually tax-exempt with a resale certificate (0%), while supplies carry your local sales tax; in the UK, VAT is 0%, 5% or 20%. Check with your accountant.
A13: To send it: File → Print → Save as PDF. The sheet is already set to Letter landscape and repeats the table header on every page.
... A17: Version 2.0 · September 2026 · aichef.pro/en/digital-products/restaurant-inventory-templates · info@aichef.pro

Sheet Current Order
A1: PURCHASE ORDER
A2: SAMPLE: the header and the first three lines are filled in so you can see the order working (tax per line, net amount, tax amount, total, breakdown by rate, and the order-minimum alert). DELETE THEM before sending your first order.
A3: Vendor: | C3: Prime Cut Meats (sample) | D3: Phone | E3: =IF($C$3="","",IFERROR(VLOOKUP($C$3,Vendors!$A$4:$H$23,3,FALSE),"")) -> (555) 555-0101 | F3: Business name
A4: Order date: | C4: 46252 | D4: Order min. | E4: =IF($C$3="","",IFERROR(VLOOKUP($C$3,Vendors!$A$4:$H$23,5,FALSE),"")) -> 300 | F4: Tax ID (EIN / VAT no.)
A5: Delivery date: | C5: 46253 | F5: Deliver to
A6: Order #: | C6: PO-2026-004 | F6: Contact
A8: # | B8: Product | C8: Category | D8: Unit | E8: Quantity | F8: Price/unit | G8: Subtotal | H8: Tax % | I8: Total
A9: 1 | B9: Beef tenderloin (PSMO) | C9: Meat & Poultry | D9: lb | E9: 12 | F9: 17.21 | G9: =IF($E9="","",IF($F9="","⚠ missing cost",$E9*$F9)) -> 206.52 | H9: =IF($B9="","",IFERROR(VLOOKUP($B9,'Tax Rates'!$E$2:$F$20,2,FALSE),IF($C9="","",IFERROR(VLOOKUP($C9,'Tax Rates'!$A$2:$B$11,2,FALSE),"")))) -> 0 | I9: =IF(OR($E9="",$F9=""),"",$E9*$F9*(1+$H9/100)) -> 206.52
A10: 2 | B10: House red wine (750 ml) | C10: Alcoholic Beverages | D10: bottle | E10: 12 | F10: 10.31 | G10: =IF($E10="","",IF($F10="","⚠ missing cost",$E10*$F10)) -> 123.72 | H10: =IF($B10="","",IFERROR(VLOOKUP($B10,'Tax Rates'!$E$2:$F$20,2,FALSE),IF($C10="","",IFERROR(VLOOKUP($C10,'Tax Rates'!$A$2:$B$11,2,FALSE),"")))) -> 0 | I10: =IF(OR($E10="",$F10=""),"",$E10*$F10*(1+$H10/100)) -> 123.72
A11: 3 | B11: Romaine lettuce | C11: Produce | D11: each | E11: 10 | F11: 1.6 | G11: =IF($E11="","",IF($F11="","⚠ missing cost",$E11*$F11)) -> 16 | H11: =IF($B11="","",IFERROR(VLOOKUP($B11,'Tax Rates'!$E$2:$F$20,2,FALSE),IF($C11="","",IFERROR(VLOOKUP($C11,'Tax Rates'!$A$2:$B$11,2,FALSE),"")))) -> 0 | I11: =IF(OR($E11="",$F11=""),"",$E11*$F11*(1+$H11/100)) -> 16
A12: 4 | G12: =IF($E12="","",IF($F12="","⚠ missing cost",$E12*$F12)) | H12: =IF($B12="","",IFERROR(VLOOKUP($B12,'Tax Rates'!$E$2:$F$20,2,FALSE),IF($C12="","",IFERROR(VLOOKUP($C12,'Tax Rates'!$A$2:$B$11,2,FALSE),"")))) | I12: =IF(OR($E12="",$F12=""),"",$E12*$F12*(1+$H12/100))
A13: 5 | G13: =IF($E13="","",IF($F13="","⚠ missing cost",$E13*$F13)) | H13: =IF($B13="","",IFERROR(VLOOKUP($B13,'Tax Rates'!$E$2:$F$20,2,FALSE),IF($C13="","",IFERROR(VLOOKUP($C13,'Tax Rates'!$A$2:$B$11,2,FALSE),"")))) | I13: =IF(OR($E13="",$F13=""),"",$E13*$F13*(1+$H13/100))
A14: 6 | G14: =IF($E14="","",IF($F14="","⚠ missing cost",$E14*$F14)) | H14: =IF($B14="","",IFERROR(VLOOKUP($B14,'Tax Rates'!$E$2:$F$20,2,FALSE),IF($C14="","",IFERROR(VLOOKUP($C14,'Tax Rates'!$A$2:$B$11,2,FALSE),"")))) | I14: =IF(OR($E14="",$F14=""),"",$E14*$F14*(1+$H14/100))
A15: 7 | G15: =IF($E15="","",IF($F15="","⚠ missing cost",$E15*$F15)) | H15: =IF($B15="","",IFERROR(VLOOKUP($B15,'Tax Rates'!$E$2:$F$20,2,FALSE),IF($C15="","",IFERROR(VLOOKUP($C15,'Tax Rates'!$A$2:$B$11,2,FALSE),"")))) | I15: =IF(OR($E15="",$F15=""),"",$E15*$F15*(1+$H15/100))
A16: 8 | G16: =IF($E16="","",IF($F16="","⚠ missing cost",$E16*$F16)) | H16: =IF($B16="","",IFERROR(VLOOKUP($B16,'Tax Rates'!$E$2:$F$20,2,FALSE),IF($C16="","",IFERROR(VLOOKUP($C16,'Tax Rates'!$A$2:$B$11,2,FALSE),"")))) | I16: =IF(OR($E16="",$F16=""),"",$E16*$F16*(1+$H16/100))
A17: 9 | G17: =IF($E17="","",IF($F17="","⚠ missing cost",$E17*$F17)) | H17: =IF($B17="","",IFERROR(VLOOKUP($B17,'Tax Rates'!$E$2:$F$20,2,FALSE),IF($C17="","",IFERROR(VLOOKUP($C17,'Tax Rates'!$A$2:$B$11,2,FALSE),"")))) | I17: =IF(OR($E17="",$F17=""),"",$E17*$F17*(1+$H17/100))
A18: 10 | G18: =IF($E18="","",IF($F18="","⚠ missing cost",$E18*$F18)) | H18: =IF($B18="","",IFERROR(VLOOKUP($B18,'Tax Rates'!$E$2:$F$20,2,FALSE),IF($C18="","",IFERROR(VLOOKUP($C18,'Tax Rates'!$A$2:$B$11,2,FALSE),"")))) | I18: =IF(OR($E18="",$F18=""),"",$E18*$F18*(1+$H18/100))
A19: 11 | G19: =IF($E19="","",IF($F19="","⚠ missing cost",$E19*$F19)) | H19: =IF($B19="","",IFERROR(VLOOKUP($B19,'Tax Rates'!$E$2:$F$20,2,FALSE),IF($C19="","",IFERROR(VLOOKUP($C19,'Tax Rates'!$A$2:$B$11,2,FALSE),"")))) | I19: =IF(OR($E19="",$F19=""),"",$E19*$F19*(1+$H19/100))
A20: 12 | G20: =IF($E20="","",IF($F20="","⚠ missing cost",$E20*$F20)) | H20: =IF($B20="","",IFERROR(VLOOKUP($B20,'Tax Rates'!$E$2:$F$20,2,FALSE),IF($C20="","",IFERROR(VLOOKUP($C20,'Tax Rates'!$A$2:$B$11,2,FALSE),"")))) | I20: =IF(OR($E20="",$F20=""),"",$E20*$F20*(1+$H20/100))
A21: 13 | G21: =IF($E21="","",IF($F21="","⚠ missing cost",$E21*$F21)) | H21: =IF($B21="","",IFERROR(VLOOKUP($B21,'Tax Rates'!$E$2:$F$20,2,FALSE),IF($C21="","",IFERROR(VLOOKUP($C21,'Tax Rates'!$A$2:$B$11,2,FALSE),"")))) | I21: =IF(OR($E21="",$F21=""),"",$E21*$F21*(1+$H21/100))
A22: 14 | G22: =IF($E22="","",IF($F22="","⚠ missing cost",$E22*$F22)) | H22: =IF($B22="","",IFERROR(VLOOKUP($B22,'Tax Rates'!$E$2:$F$20,2,FALSE),IF($C22="","",IFERROR(VLOOKUP($C22,'Tax Rates'!$A$2:$B$11,2,FALSE),"")))) | I22: =IF(OR($E22="",$F22=""),"",$E22*$F22*(1+$H22/100))
A23: 15 | G23: =IF($E23="","",IF($F23="","⚠ missing cost",$E23*$F23)) | H23: =IF($B23="","",IFERROR(VLOOKUP($B23,'Tax Rates'!$E$2:$F$20,2,FALSE),IF($C23="","",IFERROR(VLOOKUP($C23,'Tax Rates'!$A$2:$B$11,2,FALSE),"")))) | I23: =IF(OR($E23="",$F23=""),"",$E23*$F23*(1+$H23/100))
... A38: 30 | G38: =IF($E38="","",IF($F38="","⚠ missing cost",$E38*$F38)) | H38: =IF($B38="","",IFERROR(VLOOKUP($B38,'Tax Rates'!$E$2:$F$20,2,FALSE),IF($C38="","",IFERROR(VLOOKUP($C38,'Tax Rates'!$A$2:$B$11,2,FALSE),"")))) | I38: =IF(OR($E38="",$F38=""),"",$E38*$F38*(1+$H38/100))
F40: NET AMOUNT (PRE-TAX) | H40: =SUM($G$9:$G$38) -> 346.24
F41: TAX AMOUNT | H41: =SUM($I$9:$I$38)-$H$40 -> 0
F42: ORDER TOTAL | H42: =$H$40+$H$41 -> 346.24
A43: =IF(OR($E$4="",$H$40=""),"",IF($H$40>=$E$4,"✓ This order meets the vendor's minimum","⚠ BELOW THE ORDER MINIMUM: you may be charged a delivery fee")) -> ✓ This order meets the vendor's minimum | F43: SHORT OF MINIMUM | H43: =IF(OR($E$4="",$H$40=""),"",MAX(0,$E$4-$H$40)) -> 0
A45: Tax % | B45: Net amount | C45: Tax amount | D45: Total
A46: 0 | B46: =SUMIF($H$9:$H$38,$A46,$G$9:$G$38) -> 346.24 | C46: =IFERROR($B46*$A46/100,"") -> 0 | D46: =$B46+$C46 -> 346.24
A47: 5 | B47: =SUMIF($H$9:$H$38,$A47,$G$9:$G$38) -> 0 | C47: =IFERROR($B47*$A47/100,"") -> 0 | D47: =$B47+$C47 -> 0
A48: 20 | B48: =SUMIF($H$9:$H$38,$A48,$G$9:$G$38) -> 0 | C48: =IFERROR($B48*$A48/100,"") -> 0 | D48: =$B48+$C48 -> 0
A49: Breakdown by tax rate: type the rates you actually pay in the green cells of column A (0, 5 and 20 are only a starting point; UK VAT uses 0, 5 and 20%). The sum of the Net amount column has to match the NET AMOUNT (PRE-TAX) above.

Sheet Vendors
A1: VENDORS
A2: Set up your vendors here: the drop-down on the "Current Order" tab, and the phone number and order minimum in its header, all come from this table. The first six rows are an example: overwrite them with your own. THIS TABLE IS THE OPERATIONAL COPY of the Vendor Directory in file 02 (Vendor List, Price Comparison & Scorecard): the kit's nine files are independent and deliberately not linked to each other (moving an .xlsx to another folder would break the link and you'd see #REF!), so if you change an order minimum or an order day there, change it here too: this is the one that actually feeds the order.
A3: Vendor | B3: Main category | C3: Phone | D3: Email | E3: Order minimum | F3: Order day | G3: Lead time (days) | H3: Notes
A4: Prime Cut Meats (sample) | B4: Meat & Poultry | C4: (555) 555-0101 | D4: orders@primecutmeats.example | E4: 300 | F4: Mon & Thu by 12 p.m. | G4: 1 | H4: Require an invoice with lot numbers and arrival temperature
A5: Harbor Fresh Seafood (sample) | B5: Seafood | C5: (555) 555-0103 | D5: orders@harborfreshseafood.example | E5: 200 | F5: Daily by 5 p.m. | G5: 1 | H5: Arrives on ice; reject anything above 41 °F
A6: Green Valley Produce (sample) | B6: Produce | C6: (555) 555-0105 | D6: orders@greenvalleyproduce.example | E6: 150 | F6: Mon, Wed & Fri by 6 p.m. | G6: 1 | H6: Seasonal produce: confirm prices every week
A7: Pantry Foodservice Supply (sample) | B7: Dry Goods | C7: (555) 555-0106 | D7: orders@pantryfoodservice.example | E7: 500 | F7: Tue by 2 p.m. | G7: 2 | H7: 2% volume rebate on purchases over $2,000 a month
A8: Metro Beverage Distributors (sample) | B8: Alcoholic Beverages | C8: (555) 555-0107 | D8: orders@metrobeverage.example | E8: 250 | F8: Mon by 12 p.m. | G8: 2 | H8: Kegs and CO2 cylinders on loan: check the deposit on every invoice
A9: ProClean Janitorial Supply (sample) | B9: Paper & Cleaning | C9: (555) 555-0108 | D9: orders@procleansupply.example | E9: 150 | F9: Wed by 4 p.m. | G9: 2 | H9: Ask for the Safety Data Sheet (SDS) of every product
A25: The COMPLETE profile for each vendor (Tax ID, Food license / FDA reg. no., payment terms, approval status and price comparison) lives in file 02 of the kit (Vendor List, Price Comparison & Scorecard). Here you only need what the order requires.

Sheet Order Log
A1: ORDER LOG
A2: Row 4 is LINKED to the current order. When you close it, copy that row and paste it as values into the first free row; then you can clear the order.
A3: Date | B3: Order # | C3: Vendor | D3: Products | E3: Subtotal | F3: Tax | G3: Total | H3: Status | I3: Notes
A4: =IF('Current Order'!$C$4="","",'Current Order'!$C$4) -> 46252 | B4: =IF('Current Order'!$C$6="","",'Current Order'!$C$6) -> PO-2026-004 | C4: =IF('Current Order'!$C$3="","",'Current Order'!$C$3) -> Prime Cut Meats (sample) | D4: =IF(COUNTIF('Current Order'!$B$9:$B$38,"<>")=0,"",COUNTIF('Current Order'!$B$9:$B$38,"<>")&" lines") -> 3 lines | E4: ='Current Order'!$H$40 -> 346.24 | F4: ='Current Order'!$H$41 -> 0 | G4: ='Current Order'!$H$42 -> 346.24 | I4: CURRENT ORDER — this row updates itself and does NOT add into the period total. Copy it as values into the first free row when you close the order.
A5: 46223 | B5: PO-2026-001 | C5: Prime Cut Meats (sample) | D5: 6 lines | E5: 570.82 | F5: 0 | G5: 570.82 | H5: Invoiced | I5: No issues (sample)
A6: 46237 | B6: PO-2026-002 | C6: Metro Beverage Distributors (sample) | D6: 4 lines | E6: 453.48 | F6: 0 | G6: 453.48 | H6: Received | I6: 1/2 bbl keg on deposit (sample)
A7: 46248 | B7: PO-2026-003 | C7: Green Valley Produce (sample) | D7: 9 lines | E7: 352.94 | F7: 0 | G7: 352.94 | H7: Received with issues | I7: Two cases of tomatoes pulled (sample)
D45: PERIOD TOTAL (rows 5 to 43) | E45: =SUM($E$5:$E$43) -> 1377.24 | F45: =SUM($F$5:$F$43) -> 0 | G45: =SUM($G$5:$G$43) -> 1377.24

Sheet Tax Rates
A1: Category | B1: Tax % | C1: Note | E1: Product | F1: Tax % | G1: Why it's not its category's rate
A2: Meat & Poultry | B2: 0 | C2: Default rate by category: type the rate you actually pay for each one. On every order line, you can override the rate for that line by typing your own. | G2: EXCEPTIONS by product. The order looks up the PRODUCT NAME in this table FIRST, and only falls back to its category's rate if it's not found. This table ships empty: add your own exceptions here whenever a specific product — say, a "Dairy & Eggs" or "Dry Goods" item — is taxed differently than the rest of its category. Type the EXACT name you use on the order.
A3: Seafood | B3: 0
A4: Dairy & Eggs | B4: 0
A5: Produce | B5: 0
A6: Dry Goods | B6: 0
A7: Frozen | B7: 0
A8: Alcoholic Beverages | B8: 0
A9: Non-Alcoholic Beverages | B9: 0
A10: Paper & Cleaning | B10: 0
A11: Other | B11: 0
