Workbook

Sheet Instructions
A1: Food Waste Log & Action Plan
A2: AI Chef Pro — aichef.pro
A4: Log every instance of waste, see where you're losing money, and put a plan on it with an owner and a date.
A5: 1. Log every instance of waste on "Daily Waste Log": date, product, category, quantity, unit, price and reason.
A6: 2. The line's cost calculates itself. If you're missing the price, the cell warns you instead of valuing the waste at 0.00 and making you think you lost nothing.
A7: 3. "Waste by Category" aggregates by the kit's 10 categories and counts the reasons. Don't type anything there except last month's cost, which is what gives you the trend.
A8: 4. In "Waste Dashboard", type the month's purchases in the green cell, net of any tax you can reclaim (in the U.S., usually the invoice subtotal). Without it the 3% target cannot be calculated; the target percentage is editable too.
A9: 5. "Action Plan" turns the analysis into tasks. It comes with five typical causes already written in for you to adapt to your place.
A10: TARGET: keep waste below 3% of the month's purchases. It is a percentage of YOUR purchases, not a fixed dollar amount: $500 of waste is a lot for a bar and very little for a hotel.
A12: To edit a locked cell: Review → Unprotect Sheet (no password). Green cells are already editable without unprotecting anything.
A13: Designed by John Guerrero — chef and restaurant consultant since 2010, in professional kitchens since age 17 · johnguerrero.es
A14: Version 2.0 · September 2026 · aichef.pro/en/digital-products/restaurant-inventory-templates · info@aichef.pro

Sheet Daily Waste Log
A1: DAILY WASTE LOG
A2: The first three lines are a SAMPLE so the analysis and dashboard start with numbers: delete them before starting your month.
A3: Date | B3: Product | C3: Category | D3: Quantity | E3: Unit | F3: Price/unit | G3: Total Cost | H3: Reason | I3: Handled by | J3: Corrective Action
B4: Beef tenderloin (sample) | C4: Meat & Poultry | D4: 2.5 | E4: lb | F4: 17.21 | G4: =IF($D4="","",IF($F4="","⚠ missing cost",$D4*$F4)) -> 43.025 | H4: Prep error | I4: Head chef | J4: Butcher yield test with a target yield and weighed trim
B5: Fresh cod fillet (sample) | C5: Seafood | D5: 5 | E5: lb | F5: 11.5 | G5: =IF($D5="","",IF($F5="","⚠ missing cost",$D5*$F5)) -> 57.5 | H5: Cold chain failure | I5: Sous chef | J5: Check the walk-in twice a day and make sure the door closes
B6: Romaine lettuce (sample) | C6: Produce | D6: 6 | E6: each | F6: 1.6 | G6: =IF($D6="","",IF($F6="","⚠ missing cost",$D6*$F6)) -> 9.6 | H6: Past use-by date | I6: Purchasing manager | J6: Label the opening date and use in expiration order (FEFO)
G7: =IF($D7="","",IF($F7="","⚠ missing cost",$D7*$F7))
G8: =IF($D8="","",IF($F8="","⚠ missing cost",$D8*$F8))
G9: =IF($D9="","",IF($F9="","⚠ missing cost",$D9*$F9))
G10: =IF($D10="","",IF($F10="","⚠ missing cost",$D10*$F10))
G11: =IF($D11="","",IF($F11="","⚠ missing cost",$D11*$F11))
G12: =IF($D12="","",IF($F12="","⚠ missing cost",$D12*$F12))
G13: =IF($D13="","",IF($F13="","⚠ missing cost",$D13*$F13))
G14: =IF($D14="","",IF($F14="","⚠ missing cost",$D14*$F14))
G15: =IF($D15="","",IF($F15="","⚠ missing cost",$D15*$F15))
G16: =IF($D16="","",IF($F16="","⚠ missing cost",$D16*$F16))
G17: =IF($D17="","",IF($F17="","⚠ missing cost",$D17*$F17))
G18: =IF($D18="","",IF($F18="","⚠ missing cost",$D18*$F18))
... G103: =IF($D103="","",IF($F103="","⚠ missing cost",$D103*$F103))
F105: MONTH TOTAL: | G105: =SUM(G4:G103) -> 110.125

Sheet Waste by Category
A1: WASTE ANALYSIS BY CATEGORY
A3: Category | B3: # Incidents | C3: Total Cost | D3: % of Total | E3: Prior month cost | F3: Trend vs prior month (%) | H3: Reason | I3: # of times
A4: Meat & Poultry | B4: =COUNTIF('Daily Waste Log'!$C$4:$C$103,$A4) -> 1 | C4: =SUMIF('Daily Waste Log'!$C$4:$C$103,$A4,'Daily Waste Log'!$G$4:$G$103) -> 43.025 | D4: =IFERROR($C4/$C$14,"") -> 0.3906924 | F4: =IFERROR(IF($E4="","",$C4/$E4-1),"") | H4: Past use-by date | I4: =COUNTIF('Daily Waste Log'!$H$4:$H$103,$H4) -> 1
A5: Seafood | B5: =COUNTIF('Daily Waste Log'!$C$4:$C$103,$A5) -> 1 | C5: =SUMIF('Daily Waste Log'!$C$4:$C$103,$A5,'Daily Waste Log'!$G$4:$G$103) -> 57.5 | D5: =IFERROR($C5/$C$14,"") -> 0.52213394 | F5: =IFERROR(IF($E5="","",$C5/$E5-1),"") | H5: Poor condition on arrival | I5: =COUNTIF('Daily Waste Log'!$H$4:$H$103,$H5) -> 0
A6: Dairy & Eggs | B6: =COUNTIF('Daily Waste Log'!$C$4:$C$103,$A6) -> 0 | C6: =SUMIF('Daily Waste Log'!$C$4:$C$103,$A6,'Daily Waste Log'!$G$4:$G$103) -> 0 | D6: =IFERROR($C6/$C$14,"") -> 0 | F6: =IFERROR(IF($E6="","",$C6/$E6-1),"") | H6: Breakage or spill | I6: =COUNTIF('Daily Waste Log'!$H$4:$H$103,$H6) -> 0
A7: Produce | B7: =COUNTIF('Daily Waste Log'!$C$4:$C$103,$A7) -> 1 | C7: =SUMIF('Daily Waste Log'!$C$4:$C$103,$A7,'Daily Waste Log'!$G$4:$G$103) -> 9.6 | D7: =IFERROR($C7/$C$14,"") -> 0.087173666 | F7: =IFERROR(IF($E7="","",$C7/$E7-1),"") | H7: Prep error | I7: =COUNTIF('Daily Waste Log'!$H$4:$H$103,$H7) -> 1
A8: Dry Goods | B8: =COUNTIF('Daily Waste Log'!$C$4:$C$103,$A8) -> 0 | C8: =SUMIF('Daily Waste Log'!$C$4:$C$103,$A8,'Daily Waste Log'!$G$4:$G$103) -> 0 | D8: =IFERROR($C8/$C$14,"") -> 0 | F8: =IFERROR(IF($E8="","",$C8/$E8-1),"") | H8: Overproduction | I8: =COUNTIF('Daily Waste Log'!$H$4:$H$103,$H8) -> 0
A9: Frozen | B9: =COUNTIF('Daily Waste Log'!$C$4:$C$103,$A9) -> 0 | C9: =SUMIF('Daily Waste Log'!$C$4:$C$103,$A9,'Daily Waste Log'!$G$4:$G$103) -> 0 | D9: =IFERROR($C9/$C$14,"") -> 0 | F9: =IFERROR(IF($E9="","",$C9/$E9-1),"") | H9: Customer return | I9: =COUNTIF('Daily Waste Log'!$H$4:$H$103,$H9) -> 0
A10: Alcoholic Beverages | B10: =COUNTIF('Daily Waste Log'!$C$4:$C$103,$A10) -> 0 | C10: =SUMIF('Daily Waste Log'!$C$4:$C$103,$A10,'Daily Waste Log'!$G$4:$G$103) -> 0 | D10: =IFERROR($C10/$C$14,"") -> 0 | F10: =IFERROR(IF($E10="","",$C10/$E10-1),"") | H10: Cold chain failure | I10: =COUNTIF('Daily Waste Log'!$H$4:$H$103,$H10) -> 1
A11: Non-Alcoholic Beverages | B11: =COUNTIF('Daily Waste Log'!$C$4:$C$103,$A11) -> 0 | C11: =SUMIF('Daily Waste Log'!$C$4:$C$103,$A11,'Daily Waste Log'!$G$4:$G$103) -> 0 | D11: =IFERROR($C11/$C$14,"") -> 0 | F11: =IFERROR(IF($E11="","",$C11/$E11-1),"") | H11: Butchery trim loss | I11: =COUNTIF('Daily Waste Log'!$H$4:$H$103,$H11) -> 0
A12: Paper & Cleaning | B12: =COUNTIF('Daily Waste Log'!$C$4:$C$103,$A12) -> 0 | C12: =SUMIF('Daily Waste Log'!$C$4:$C$103,$A12,'Daily Waste Log'!$G$4:$G$103) -> 0 | D12: =IFERROR($C12/$C$14,"") -> 0 | F12: =IFERROR(IF($E12="","",$C12/$E12-1),"") | H12: Dish sent back | I12: =COUNTIF('Daily Waste Log'!$H$4:$H$103,$H12) -> 0
A13: Other | B13: =COUNTIF('Daily Waste Log'!$C$4:$C$103,$A13) -> 0 | C13: =SUMIF('Daily Waste Log'!$C$4:$C$103,$A13,'Daily Waste Log'!$G$4:$G$103) -> 0 | D13: =IFERROR($C13/$C$14,"") -> 0 | F13: =IFERROR(IF($E13="","",$C13/$E13-1),"") | H13: Unexplained variance | I13: =COUNTIF('Daily Waste Log'!$H$4:$H$103,$H13) -> 0
A14: MONTH TOTAL | B14: =SUM($B$4:$B$13) -> 3 | C14: =SUM($C$4:$C$13) -> 110.125 | D14: =IFERROR(SUM($D$4:$D$13),"") -> 1 | E14: =SUM($E$4:$E$13) -> 0 | F14: =IFERROR(IF($E$14=0,"",$C$14/$E$14-1),"")

Sheet Waste Dashboard
A1: WASTE DASHBOARD — MONTH
A3: KPI | B3: Result | C3: Target | D3: Status
A4: Total waste cost | B4: ='Daily Waste Log'!$G$105 -> 110.125 | C4: =IFERROR(IF($B$10="","",$B$10*$B$11),"") -> 447 | D4: =IF(OR($B$4="",$C$4=""),"",IF($B$4<=$C$4,"🟢 OK","🔴 ALERT")) -> 🟢 OK
A5: % waste over purchases | B5: =IFERROR($B$4/$B$10,"") -> 0.0073909396 | C5: =IF($B$11="","",$B$11) -> 0.03 | D5: =IF(OR($B$5="",$C$5=""),"",IF($B$5<=$C$5,"🟢 OK",IF($B$5<=$C$5*1.5,"🟡 REVIEW","🔴 ALERT"))) -> 🟢 OK
A6: # of incidents | B6: =COUNTIF('Daily Waste Log'!$B$4:$B$103,"<>") -> 3 | C6: 20 | D6: =IF($B$6="","",IF($B$6<=$C$6,"🟢 OK","🟡 REVIEW")) -> 🟢 OK
A7: Category with the most waste | B7: =IF(MAX('Waste by Category'!$C$4:$C$13)<=0,"— no waste logged —",IFERROR(INDEX('Waste by Category'!$A$4:$A$13,MATCH(MAX('Waste by Category'!$C$4:$C$13),'Waste by Category'!$C$4:$C$13,0)),"")) -> Seafood | C7: Tackle it in the plan
A8: Most frequent reason | B8: =IF(MAX('Waste by Category'!$I$4:$I$13)<=0,"— no waste logged —",IFERROR(INDEX('Waste by Category'!$H$4:$H$13,MATCH(MAX('Waste by Category'!$I$4:$I$13),'Waste by Category'!$I$4:$I$13,0))&" · "&MAX('Waste by Category'!$I$4:$I$13)&" times","")) -> Past use-by date · 1 times | C8: Tackle it in the plan | D8: If several reasons tie, it shows the first one on the list: check the reasons table in the analysis to see them all.
A10: Month's purchases (pre-tax) | B10: 14900
A11: Waste target over purchases | B11: 0.03
A13: Type the month's purchases in the green cell, net of recoverable tax (the subtotal of your vendor invoices). Without it, the kit's own 3% target cannot be calculated: that is why the dollar target is no longer a fixed "under $500" but that percentage of YOUR purchases.

Sheet Action Plan
A1: ACTION PLAN — WASTE REDUCTION
A2: The first five rows are the most common causes of kitchen waste, already written in. Adapt them, add a date and an owner, and estimate the monthly cost you avoid.
A3: Priority | B3: Category | C3: Problem detected | D3: Root cause | E3: Corrective action | F3: Handled by | G3: Due date | H3: Monthly cost avoided | I3: Status and follow-up
A4: High | B4: Meat & Poultry | C4: Prepped food is thrown out at the end of service | D4: Overproduction: prep is done by habit, not against the cover forecast | E4: Prep against the day's forecast and log the leftovers in the waste log before closing | F4: Head chef | H4: 250 | I4: Pending
A5: High | B5: Produce | C5: Expired product turns up with newer stock in front of it | D5: Date labeling is incomplete: opening dates are not written down | E5: Date-label everything you open and put what expires first in front | F5: Sous chef | H5: 175 | I5: In progress
A6: Medium | B6: Seafood | C6: Product lost to a cold chain failure | D6: The walk-in isn't checked daily and the door is left open during service | E6: Temperature log twice a day and a door check at the end of every service | F6: HACCP / food safety plan lead | H6: 135 | I6: Pending
A7: Medium | B7: Meat & Poultry | C7: Butchery trim loss runs above plan | D7: Every cook trims differently: there is no yield test | E7: Butcher yield test with a target yield and weighed trim once a week | F7: Station chef | H7: 110 | I7: Pending
A8: Low | B8: Dry Goods | C8: Dead stock in dry storage | D8: Orders exceed real usage: nobody checks on-hand before ordering | E8: Order from the "Order Qty" column of the inventory sheet and respect the reorder point | F8: Purchasing manager | H8: 55 | I8: Pending
G25: TOTAL ESTIMATED SAVINGS | H25: =SUM($H$4:$H$23) -> 725
