Workbook

Sheet Instructions
A1: Purchasing Cost Analysis & Food Cost KPIs
A2: AI Chef Pro — aichef.pro
A4: See where your purchasing money is going and calculate your cost KPIs.
A6: ALL AMOUNTS ARE PRE-TAX (NET AMOUNT).
A7: Tax you can reclaim is not part of food cost. If you copy the invoice total instead of the net amount, your food cost comes out inflated by the tax on the invoice (up to 20% with UK VAT) and every decision you base on it will be wrong. In the U.S., food bought for resale is usually tax exempt, so subtotal and total often match; sales tax you cannot reclaim is a real cost and stays in.
A9: TABS:
A10: 1. Spend by Category — the kit's 10 categories, month by month; it's the table that feeds all the others
A11: 2. Monthly Trend — each month's total, its variance, and the year-to-date accumulated
A12: 3. Top 20 Items — the products taking the biggest bite of your spend, with the price-increase alert and the Top 5 ranking, which sorts itself (you don't need to sort the table)
A13: 4. KPI Dashboard — food cost, cost per cover and variance, calculated for real
A15: HOW IT'S USED:
A16: Every month, load your spend by category on "Spend by Category". The rest of the file calculates itself.
... A26: Version 2.0 · September 2026 · aichef.pro/en/digital-products/restaurant-inventory-templates · info@aichef.pro

Sheet Spend by Category
A1: PURCHASING COST BY CATEGORY (PRE-TAX)
A2: All amounts are pre-tax (net amount). The January column carries sample data: delete it and load your own.
A3: Category | B3: Jan | C3: Feb | D3: Mar | E3: Apr | F3: May | G3: Jun | H3: Jul | I3: Aug | J3: Sep | K3: Oct | L3: Nov | M3: Dec | N3: Year total (pre-tax) | O3: % of Total
A4: Meat & Poultry | B4: 3650 | N4: =SUM(B4:M4) -> 3650 | O4: =IFERROR($N4/$N$14,"") -> 0.24496644
A5: Seafood | B5: 2900 | N5: =SUM(B5:M5) -> 2900 | O5: =IFERROR($N5/$N$14,"") -> 0.19463087
A6: Dairy & Eggs | B6: 1150 | N6: =SUM(B6:M6) -> 1150 | O6: =IFERROR($N6/$N$14,"") -> 0.077181208
A7: Produce | B7: 1700 | N7: =SUM(B7:M7) -> 1700 | O7: =IFERROR($N7/$N$14,"") -> 0.11409396
A8: Dry Goods | B8: 1450 | N8: =SUM(B8:M8) -> 1450 | O8: =IFERROR($N8/$N$14,"") -> 0.097315436
A9: Frozen | B9: 650 | N9: =SUM(B9:M9) -> 650 | O9: =IFERROR($N9/$N$14,"") -> 0.043624161
A10: Alcoholic Beverages | B10: 1900 | N10: =SUM(B10:M10) -> 1900 | O10: =IFERROR($N10/$N$14,"") -> 0.12751678
A11: Non-Alcoholic Beverages | B11: 700 | N11: =SUM(B11:M11) -> 700 | O11: =IFERROR($N11/$N$14,"") -> 0.046979866
A12: Paper & Cleaning | B12: 550 | N12: =SUM(B12:M12) -> 550 | O12: =IFERROR($N12/$N$14,"") -> 0.036912752
A13: Other | B13: 250 | N13: =SUM(B13:M13) -> 250 | O13: =IFERROR($N13/$N$14,"") -> 0.016778523
A14: TOTAL | B14: =SUM(B4:B13) -> 14900 | C14: =SUM(C4:C13) -> 0 | D14: =SUM(D4:D13) -> 0 | E14: =SUM(E4:E13) -> 0 | F14: =SUM(F4:F13) -> 0 | G14: =SUM(G4:G13) -> 0 | H14: =SUM(H4:H13) -> 0 | I14: =SUM(I4:I13) -> 0 | ... N14: =SUM(N4:N13) -> 14900 | O14: =IFERROR($N14/$N$14,"") -> 1
A16: Row 14 (TOTAL) is what the "KPI Dashboard" reads. There, in a green cell, you choose WHICH period you're measuring: a specific month or the full year. The sales, covers and inventory figures you enter on the dashboard have to match that same period.

Sheet Monthly Trend
A1: MONTHLY TREND OF PURCHASING SPEND (PRE-TAX)
A2: Nothing gets typed here: it all pulls automatically from the TOTAL row on "Spend by Category".
A3: Month | B3: Month's purchases | C3: Variance vs prior month (%) | D3: Year-to-date accumulated
A4: January | B4: ='Spend by Category'!B$14 -> 14900 | D4: =SUM($B$4:$B4) -> 14900
A5: February | B5: ='Spend by Category'!C$14 -> 0 | C5: =IF(OR($B4=0,$B5=0),"",IFERROR($B5/$B4-1,"")) | D5: =SUM($B$4:$B5) -> 14900
A6: March | B6: ='Spend by Category'!D$14 -> 0 | C6: =IF(OR($B5=0,$B6=0),"",IFERROR($B6/$B5-1,"")) | D6: =SUM($B$4:$B6) -> 14900
A7: April | B7: ='Spend by Category'!E$14 -> 0 | C7: =IF(OR($B6=0,$B7=0),"",IFERROR($B7/$B6-1,"")) | D7: =SUM($B$4:$B7) -> 14900
A8: May | B8: ='Spend by Category'!F$14 -> 0 | C8: =IF(OR($B7=0,$B8=0),"",IFERROR($B8/$B7-1,"")) | D8: =SUM($B$4:$B8) -> 14900
A9: June | B9: ='Spend by Category'!G$14 -> 0 | C9: =IF(OR($B8=0,$B9=0),"",IFERROR($B9/$B8-1,"")) | D9: =SUM($B$4:$B9) -> 14900
A10: July | B10: ='Spend by Category'!H$14 -> 0 | C10: =IF(OR($B9=0,$B10=0),"",IFERROR($B10/$B9-1,"")) | D10: =SUM($B$4:$B10) -> 14900
A11: August | B11: ='Spend by Category'!I$14 -> 0 | C11: =IF(OR($B10=0,$B11=0),"",IFERROR($B11/$B10-1,"")) | D11: =SUM($B$4:$B11) -> 14900
A12: September | B12: ='Spend by Category'!J$14 -> 0 | C12: =IF(OR($B11=0,$B12=0),"",IFERROR($B12/$B11-1,"")) | D12: =SUM($B$4:$B12) -> 14900
A13: October | B13: ='Spend by Category'!K$14 -> 0 | C13: =IF(OR($B12=0,$B13=0),"",IFERROR($B13/$B12-1,"")) | D13: =SUM($B$4:$B13) -> 14900
A14: November | B14: ='Spend by Category'!L$14 -> 0 | C14: =IF(OR($B13=0,$B14=0),"",IFERROR($B14/$B13-1,"")) | D14: =SUM($B$4:$B14) -> 14900
A15: December | B15: ='Spend by Category'!M$14 -> 0 | C15: =IF(OR($B14=0,$B15=0),"",IFERROR($B15/$B14-1,"")) | D15: =SUM($B$4:$B15) -> 14900
A17: The variance stays blank as long as either month is at zero: a month you haven't loaded yet isn't a 100% drop.

Sheet Top 20 Items
A1: TOP 20 ITEMS — BIGGEST SPEND
A2: Sample data; illustrative pre-tax prices — replace them with your own. You do NOT need to sort the table: the Top 5 ranking below sorts itself with LARGE, no matter what order you type things in.
A3: # | B3: Product | C3: Category | D3: Unit | E3: Monthly spend | F3: Estimated annual spend — month x 12 | G3: % of Top 20 | H3: Prior price | I3: Current price | J3: Price variance (%) | K3: Vendor
A4: 1 | B4: Beef tenderloin (PSMO) | C4: Meat & Poultry | D4: lb | E4: 1032.6 | F4: =IF($E4="","",$E4*12) -> 12391.2 | G4: =IFERROR($E4/$E$24,"") -> 0.16638495 | H4: 16.4 | I4: 17.21 | J4: =IF(OR($H4="",$I4=""),"",$I4/$H4-1) -> 0.049390244 | K4: Prime Cut Meats (sample)
A5: 2 | B5: Fresh salmon fillet | C5: Seafood | D5: lb | E5: 1194 | F5: =IF($E5="","",$E5*12) -> 14328 | G5: =IFERROR($E5/$E$24,"") -> 0.19239167 | H5: 9.15 | I5: 9.95 | J5: =IF(OR($H5="",$I5=""),"",$I5/$H5-1) -> 0.087431694 | K5: Harbor Fresh Seafood (sample)
A6: 3 | B6: Shrimp 16/20 | C6: Seafood | D6: lb | E6: 809.1 | F6: =IF($E6="","",$E6*12) -> 9709.2 | G6: =IFERROR($E6/$E$24,"") -> 0.13037194 | H6: 8.75 | I6: 8.99 | J6: =IF(OR($H6="",$I6=""),"",$I6/$H6-1) -> 0.027428571 | K6: Harbor Fresh Seafood (sample)
A7: 4 | B7: Boneless chicken breast | C7: Meat & Poultry | D7: lb | E7: 837 | F7: =IF($E7="","",$E7*12) -> 10044 | G7: =IFERROR($E7/$E$24,"") -> 0.13486753 | H7: 2.96 | I7: 3.1 | J7: =IF(OR($H7="",$I7=""),"",$I7/$H7-1) -> 0.047297297 | K7: Prime Cut Meats (sample)
A8: 5 | B8: Draft beer (1/2 bbl) | C8: Alcoholic Beverages | D8: keg | E8: 1237.5 | F8: =IF($E8="","",$E8*12) -> 14850 | G8: =IFERROR($E8/$E$24,"") -> 0.19940091 | H8: 159 | I8: 165 | J8: =IF(OR($H8="",$I8=""),"",$I8/$H8-1) -> 0.037735849 | K8: Metro Beverage Distributors (sample)
A9: 6 | B9: Extra virgin olive oil | C9: Dry Goods | D9: gal | E9: 584.64 | F9: =IF($E9="","",$E9*12) -> 7015.68 | G9: =IFERROR($E9/$E$24,"") -> 0.094204241 | H9: 28.6 | I9: 32.48 | J9: =IF(OR($H9="",$I9=""),"",$I9/$H9-1) -> 0.13566434 | K9: Pantry Foodservice Supply (sample)
A10: 7 | B10: Parmesan | C10: Dairy & Eggs | D10: lb | E10: 237.5 | F10: =IF($E10="","",$E10*12) -> 2850 | G10: =IFERROR($E10/$E$24,"") -> 0.038268862 | H10: 9.3 | I10: 9.5 | J10: =IF(OR($H10="",$I10=""),"",$I10/$H10-1) -> 0.021505376 | K10: Pantry Foodservice Supply (sample)
A11: 8 | B11: Russet potatoes | C11: Produce | D11: lb | E11: 273.75 | F11: =IF($E11="","",$E11*12) -> 3285 | G11: =IFERROR($E11/$E$24,"") -> 0.044109899 | H11: 0.82 | I11: 0.73 | J11: =IF(OR($H11="",$I11=""),"",$I11/$H11-1) -> -0.1097561 | K11: Green Valley Produce (sample)
A12: 9 | F12: =IF($E12="","",$E12*12) | G12: =IFERROR($E12/$E$24,"") -> 0 | J12: =IF(OR($H12="",$I12=""),"",$I12/$H12-1)
A13: 10 | F13: =IF($E13="","",$E13*12) | G13: =IFERROR($E13/$E$24,"") -> 0 | J13: =IF(OR($H13="",$I13=""),"",$I13/$H13-1)
A14: 11 | F14: =IF($E14="","",$E14*12) | G14: =IFERROR($E14/$E$24,"") -> 0 | J14: =IF(OR($H14="",$I14=""),"",$I14/$H14-1)
A15: 12 | F15: =IF($E15="","",$E15*12) | G15: =IFERROR($E15/$E$24,"") -> 0 | J15: =IF(OR($H15="",$I15=""),"",$I15/$H15-1)
A16: 13 | F16: =IF($E16="","",$E16*12) | G16: =IFERROR($E16/$E$24,"") -> 0 | J16: =IF(OR($H16="",$I16=""),"",$I16/$H16-1)
A17: 14 | F17: =IF($E17="","",$E17*12) | G17: =IFERROR($E17/$E$24,"") -> 0 | J17: =IF(OR($H17="",$I17=""),"",$I17/$H17-1)
A18: 15 | F18: =IF($E18="","",$E18*12) | G18: =IFERROR($E18/$E$24,"") -> 0 | J18: =IF(OR($H18="",$I18=""),"",$I18/$H18-1)
A19: 16 | F19: =IF($E19="","",$E19*12) | G19: =IFERROR($E19/$E$24,"") -> 0 | J19: =IF(OR($H19="",$I19=""),"",$I19/$H19-1)
A20: 17 | F20: =IF($E20="","",$E20*12) | G20: =IFERROR($E20/$E$24,"") -> 0 | J20: =IF(OR($H20="",$I20=""),"",$I20/$H20-1)
A21: 18 | F21: =IF($E21="","",$E21*12) | G21: =IFERROR($E21/$E$24,"") -> 0 | J21: =IF(OR($H21="",$I21=""),"",$I21/$H21-1)
A22: 19 | F22: =IF($E22="","",$E22*12) | G22: =IFERROR($E22/$E$24,"") -> 0 | J22: =IF(OR($H22="",$I22=""),"",$I22/$H22-1)
A23: 20 | F23: =IF($E23="","",$E23*12) | G23: =IFERROR($E23/$E$24,"") -> 0 | J23: =IF(OR($H23="",$I23=""),"",$I23/$H23-1)
A24: TOTAL | E24: =SUM($E$4:$E$23) -> 6206.09 | F24: =SUM($F$4:$F$23) -> 74473.08 | G24: =IFERROR($E$24/$E$24,"") -> 1
L26: Top 5 items | M26: Monthly spend
L27: =IFERROR(INDEX($B$4:$B$23,MATCH(LARGE($E$4:$E$23,1),$E$4:$E$23,0)),"") -> Draft beer (1/2 bbl) | M27: =IFERROR(LARGE($E$4:$E$23,1),"") -> 1237.5
L28: =IFERROR(INDEX($B$4:$B$23,MATCH(LARGE($E$4:$E$23,2),$E$4:$E$23,0)),"") -> Fresh salmon fillet | M28: =IFERROR(LARGE($E$4:$E$23,2),"") -> 1194
L29: =IFERROR(INDEX($B$4:$B$23,MATCH(LARGE($E$4:$E$23,3),$E$4:$E$23,0)),"") -> Beef tenderloin (PSMO) | M29: =IFERROR(LARGE($E$4:$E$23,3),"") -> 1032.6
L30: =IFERROR(INDEX($B$4:$B$23,MATCH(LARGE($E$4:$E$23,4),$E$4:$E$23,0)),"") -> Boneless chicken breast | M30: =IFERROR(LARGE($E$4:$E$23,4),"") -> 837
L31: =IFERROR(INDEX($B$4:$B$23,MATCH(LARGE($E$4:$E$23,5),$E$4:$E$23,0)),"") -> Shrimp 16/20 | M31: =IFERROR(LARGE($E$4:$E$23,5),"") -> 809.1
A33: The Top 5 ranking on the right calculates itself with LARGE: you don't need to sort the table, and in fact the sheet is protected so you don't accidentally reorder it. If two products spend exactly the same, it shows the first one twice; change it by a cent and they separate.

Sheet KPI Dashboard
A1: DASHBOARD — PURCHASING KPIS
A2: Choose the period and fill in the green cells. Everything else calculates itself, using pre-tax amounts. The Status column tells you at a glance whether each KPI is where it should be.
A3: KPI | B3: Result | C3: Target | D3: How it's calculated | E3: Status
A4: Food cost (%) | B4: =IFERROR(($B$14+$B$6-$B$15)/$B$12,"") -> 0.3100616 | C4: 0.32 | D4: (Beginning inventory + Purchases for the period - Ending inventory) / Sales. It's USAGE, not purchases. A healthy range for a restaurant is 28% to 32%: this sets the CEILING, change it to your own. | E4: =IF(OR($B$4="",$C$4=""),"",IF($B$4<=$C$4,"🟢 OK",IF($B$4<=$C$4*1.1,"🟡 REVIEW","🔴 ALERT"))) -> 🟢 OK
A5: Cost per cover | B5: =IFERROR(($B$14+$B$6-$B$15-'Spend by Category'!$N$12-'Spend by Category'!$N$13)/$B$13,"") -> 9.862069 | C5: =IFERROR($B$17*0.3,"") -> 10.077 | D5: Raw ingredient usage (excluding "Paper & Cleaning" and "Other") / covers served. The target is 30% of your average check, not a fixed dollar figure. | E5: =IF(OR($B$5="",$C$5=""),"",IF($B$5<=$C$5,"🟢 OK",IF($B$5<=$C$5*1.1,"🟡 REVIEW","🔴 ALERT"))) -> 🟢 OK
A6: Period purchases | B6: =IF($B$10="","",IF($B$10="Full year",'Spend by Category'!$N$14,IFERROR(INDEX('Spend by Category'!$B$14:$M$14,MATCH($B$10,'Spend by Category'!$B$3:$M$3,0)),""))) -> 14900 | C6: — | D6: Total for the month you choose above, from the "Spend by Category" tab.
A7: Variance vs prior period | B7: =IFERROR($B$6/$B$16-1,"") -> 0.041958042 | C7: 0.05 | D7: Period purchases / prior period purchases - 1. Compared in absolute value: a 20% drop needs an explanation too. | E7: =IF(OR($B$7="",$C$7=""),"",IF(ABS($B$7)<=$C$7,"🟢 OK",IF(ABS($B$7)<=$C$7*2,"🟡 REVIEW","🔴 ALERT"))) -> 🟢 OK
A8: Items up more than 5% | B8: =COUNTIF('Top 20 Items'!$J$4:$J$23,">0.05") -> 2 | C8: 0 | D8: Top 20 lines whose price variance is over 5%. | E8: =IF(OR($B$8="",$C$8=""),"",IF($B$8<=$C$8,"🟢 OK",IF($B$8<=2,"🟡 REVIEW","🔴 ALERT"))) -> 🟡 REVIEW
A9: Biggest price increase | B9: =IFERROR(INDEX('Top 20 Items'!$B$4:$B$23,MATCH(MAX('Top 20 Items'!$J$4:$J$23),'Top 20 Items'!$J$4:$J$23,0)),"") -> Extra virgin olive oil | C9: — | D9: Top 20 item with the highest variance.
A10: PERIOD BEING MEASURED | B10: Jan | D10: Choose the month you loaded on "Spend by Category", or "Full year". The sales, covers and inventory figures you enter below have to match THAT period.
A11: PERIOD DATA — fill in these cells
A12: Period sales (pre-tax) | B12: 48700 | D12: Net amount, pre-tax. Same period as the purchases you loaded.
A13: Covers served | B13: 1450 | D13: Actual guests for the period, not reservations.
A14: Beginning inventory | B14: 6100 | D14: Inventory value at the start of the period (template 01, Kitchen & Bar Inventory Sheet with Par Levels, or BONUS-08, Month-End Inventory Count).
A15: Ending inventory | B15: 5900 | D15: Inventory value at the close of the period.
A16: Prior period purchases | B16: 14300 | D16: For the variance. Pre-tax, same as everything else.
A17: Average check | B17: 33.59 | D17: Sales / covers. Sets the cost-per-cover target.
A19: Sample figures consistent with January in "Spend by Category": $14,900 of purchases, $6,100 of beginning and $5,900 of ending inventory, $48,700 of sales and 1,450 covers give a food cost of 31.0%, within target. Replace them with yours.
