Workbook

Sheet Instructions
A1: BONUS: Reorder Point & Order Quantity Calculator
A2: AI Chef Pro — aichef.pro
A4: Calculate when to order each product and how much you should order.
A6: THE TWO FORMULAS:
A7: Reorder point = daily usage x lead time + safety stock
A8: Safety stock = daily usage x coverage days (that's why coverage is typed in DAYS and the column next to it converts it to units)
A10: TABS:
A11: 1. Reorder Calculator — one line per product; columns WITHOUT a green fill calculate themselves (in this kit, green is always what you type)
A12: 2. Parameters — order cost, carrying cost and shelf-life factor, all editable; the EOQ and the suggested-quantity cap come from these
A14: HOW IT'S USED:
A15: Fill in the green cells: daily usage, lead time, coverage, price, shelf life and vendor.
A16: When stock drops to the reorder point, place the order. Not before, not after.
... A26: Version 2.0 · September 2026 · aichef.pro/en/digital-products/restaurant-inventory-templates · info@aichef.pro

Sheet Reorder Calculator
A1: CALCULATOR — OPTIMAL REORDER POINT
A2: Sample data; illustrative pre-tax prices — replace them with your own. Daily usage and shelf life are for YOUR place: the sample figures are for a 60-cover restaurant and come from the SAME table as the par levels on template 01 (Kitchen & Bar Inventory Sheet with Par Levels), so the reorder point here and the par level there are the same number.
A3: # | B3: Product | C3: Category | D3: Daily usage (units/day) | E3: Lead time (days) | F3: Safety coverage (days) | G3: Safety stock (units) | H3: Reorder point (units) | I3: Price/unit | J3: Shelf life (days) | K3: Max stock (units) — par max from 01 | L3: Theoretical EOQ (units) | M3: Suggested order quantity (units) | N3: Order frequency (days) | O3: Vendor
A4: 1 | B4: Boneless chicken breast | C4: Meat & Poultry | D4: 9 | E4: 1 | F4: 1 | G4: =IF(OR($D4="",$F4=""),"",$D4*$F4) -> 9 | H4: =IF(OR($D4="",$E4="",$F4=""),"",$D4*$E4+$G4) -> 18 | I4: 3.1 | J4: 4 | K4: 40 | L4: =IFERROR(IF(OR($D4="",$D4<=0,$I4="",$I4<=0,Parameters!$D$4<=0,Parameters!$D$5<=0),"",ROUND(SQRT(2*$D4*365*Parameters!$D$4/($I4*Parameters!$D$5)),0)),"") -> 159 | M4: =IFERROR(IF(OR($L4="",$J4=""),"",MIN($L4,ROUND($D4*$J4*Parameters!$D$12,0),IF($K4="",$L4,$K4))),"") -> 25 | N4: =IF(OR($D4="",$D4<=0,$M4=""),"",ROUND($M4/$D4,0)) -> 3 | O4: Prime Cut Meats (sample)
A5: 2 | B5: Beef tenderloin (PSMO) | C5: Meat & Poultry | D5: 2 | E5: 2 | F5: 1 | G5: =IF(OR($D5="",$F5=""),"",$D5*$F5) -> 2 | H5: =IF(OR($D5="",$E5="",$F5=""),"",$D5*$E5+$G5) -> 6 | I5: 17.21 | J5: 8 | K5: 18 | L5: =IFERROR(IF(OR($D5="",$D5<=0,$I5="",$I5<=0,Parameters!$D$4<=0,Parameters!$D$5<=0),"",ROUND(SQRT(2*$D5*365*Parameters!$D$4/($I5*Parameters!$D$5)),0)),"") -> 32 | M5: =IFERROR(IF(OR($L5="",$J5=""),"",MIN($L5,ROUND($D5*$J5*Parameters!$D$12,0),IF($K5="",$L5,$K5))),"") -> 11 | N5: =IF(OR($D5="",$D5<=0,$M5=""),"",ROUND($M5/$D5,0)) -> 6 | O5: Prime Cut Meats (sample)
A6: 3 | B6: Fresh salmon fillet | C6: Seafood | D6: 4 | E6: 1 | F6: 1 | G6: =IF(OR($D6="",$F6=""),"",$D6*$F6) -> 4 | H6: =IF(OR($D6="",$E6="",$F6=""),"",$D6*$E6+$G6) -> 8 | I6: 9.95 | J6: 3 | K6: 20 | L6: =IFERROR(IF(OR($D6="",$D6<=0,$I6="",$I6<=0,Parameters!$D$4<=0,Parameters!$D$5<=0),"",ROUND(SQRT(2*$D6*365*Parameters!$D$4/($I6*Parameters!$D$5)),0)),"") -> 59 | M6: =IFERROR(IF(OR($L6="",$J6=""),"",MIN($L6,ROUND($D6*$J6*Parameters!$D$12,0),IF($K6="",$L6,$K6))),"") -> 8 | N6: =IF(OR($D6="",$D6<=0,$M6=""),"",ROUND($M6/$D6,0)) -> 2 | O6: Harbor Fresh Seafood (sample)
A7: 4 | B7: Whole milk | C7: Dairy & Eggs | D7: 2 | E7: 2 | F7: 1 | G7: =IF(OR($D7="",$F7=""),"",$D7*$F7) -> 2 | H7: =IF(OR($D7="",$E7="",$F7=""),"",$D7*$E7+$G7) -> 6 | I7: 4.23 | J7: 12 | K7: 16 | L7: =IFERROR(IF(OR($D7="",$D7<=0,$I7="",$I7<=0,Parameters!$D$4<=0,Parameters!$D$5<=0),"",ROUND(SQRT(2*$D7*365*Parameters!$D$4/($I7*Parameters!$D$5)),0)),"") -> 64 | M7: =IFERROR(IF(OR($L7="",$J7=""),"",MIN($L7,ROUND($D7*$J7*Parameters!$D$12,0),IF($K7="",$L7,$K7))),"") -> 16 | N7: =IF(OR($D7="",$D7<=0,$M7=""),"",ROUND($M7/$D7,0)) -> 8 | O7: Pantry Foodservice Supply (sample)
A8: 5 | B8: Russet potatoes | C8: Produce | D8: 12.5 | E8: 2 | F8: 2 | G8: =IF(OR($D8="",$F8=""),"",$D8*$F8) -> 25 | H8: =IF(OR($D8="",$E8="",$F8=""),"",$D8*$E8+$G8) -> 50 | I8: 0.73 | J8: 30 | K8: 150 | L8: =IFERROR(IF(OR($D8="",$D8<=0,$I8="",$I8<=0,Parameters!$D$4<=0,Parameters!$D$5<=0),"",ROUND(SQRT(2*$D8*365*Parameters!$D$4/($I8*Parameters!$D$5)),0)),"") -> 387 | M8: =IFERROR(IF(OR($L8="",$J8=""),"",MIN($L8,ROUND($D8*$J8*Parameters!$D$12,0),IF($K8="",$L8,$K8))),"") -> 150 | N8: =IF(OR($D8="",$D8<=0,$M8=""),"",ROUND($M8/$D8,0)) -> 12 | O8: Green Valley Produce (sample)
A9: 6 | B9: Extra virgin olive oil | C9: Dry Goods | D9: 0.6 | E9: 4 | F9: 1 | G9: =IF(OR($D9="",$F9=""),"",$D9*$F9) -> 0.6 | H9: =IF(OR($D9="",$E9="",$F9=""),"",$D9*$E9+$G9) -> 3 | I9: 32.48 | J9: 540 | K9: 8 | L9: =IFERROR(IF(OR($D9="",$D9<=0,$I9="",$I9<=0,Parameters!$D$4<=0,Parameters!$D$5<=0),"",ROUND(SQRT(2*$D9*365*Parameters!$D$4/($I9*Parameters!$D$5)),0)),"") -> 13 | M9: =IFERROR(IF(OR($L9="",$J9=""),"",MIN($L9,ROUND($D9*$J9*Parameters!$D$12,0),IF($K9="",$L9,$K9))),"") -> 8 | N9: =IF(OR($D9="",$D9<=0,$M9=""),"",ROUND($M9/$D9,0)) -> 13 | O9: Pantry Foodservice Supply (sample)
A10: 7 | B10: Arborio rice | C10: Dry Goods | D10: 4 | E10: 4 | F10: 1 | G10: =IF(OR($D10="",$F10=""),"",$D10*$F10) -> 4 | H10: =IF(OR($D10="",$E10="",$F10=""),"",$D10*$E10+$G10) -> 20 | I10: 2.1 | J10: 720 | K10: 50 | L10: =IFERROR(IF(OR($D10="",$D10<=0,$I10="",$I10<=0,Parameters!$D$4<=0,Parameters!$D$5<=0),"",ROUND(SQRT(2*$D10*365*Parameters!$D$4/($I10*Parameters!$D$5)),0)),"") -> 129 | M10: =IFERROR(IF(OR($L10="",$J10=""),"",MIN($L10,ROUND($D10*$J10*Parameters!$D$12,0),IF($K10="",$L10,$K10))),"") -> 50 | N10: =IF(OR($D10="",$D10<=0,$M10=""),"",ROUND($M10/$D10,0)) -> 13 | O10: Pantry Foodservice Supply (sample)
A11: 8 | B11: Draft beer (1/2 bbl) | C11: Alcoholic Beverages | D11: 0.25 | E11: 3 | F11: 5 | G11: =IF(OR($D11="",$F11=""),"",$D11*$F11) -> 1.25 | H11: =IF(OR($D11="",$E11="",$F11=""),"",$D11*$E11+$G11) -> 2 | I11: 165 | J11: 120 | K11: 6 | L11: =IFERROR(IF(OR($D11="",$D11<=0,$I11="",$I11<=0,Parameters!$D$4<=0,Parameters!$D$5<=0),"",ROUND(SQRT(2*$D11*365*Parameters!$D$4/($I11*Parameters!$D$5)),0)),"") -> 4 | M11: =IFERROR(IF(OR($L11="",$J11=""),"",MIN($L11,ROUND($D11*$J11*Parameters!$D$12,0),IF($K11="",$L11,$K11))),"") -> 4 | N11: =IF(OR($D11="",$D11<=0,$M11=""),"",ROUND($M11/$D11,0)) -> 16 | O11: Metro Beverage Distributors (sample)
A12: 9 | G12: =IF(OR($D12="",$F12=""),"",$D12*$F12) | H12: =IF(OR($D12="",$E12="",$F12=""),"",$D12*$E12+$G12) | L12: =IFERROR(IF(OR($D12="",$D12<=0,$I12="",$I12<=0,Parameters!$D$4<=0,Parameters!$D$5<=0),"",ROUND(SQRT(2*$D12*365*Parameters!$D$4/($I12*Parameters!$D$5)),0)),"") | M12: =IFERROR(IF(OR($L12="",$J12=""),"",MIN($L12,ROUND($D12*$J12*Parameters!$D$12,0),IF($K12="",$L12,$K12))),"") | N12: =IF(OR($D12="",$D12<=0,$M12=""),"",ROUND($M12/$D12,0))
A13: 10 | G13: =IF(OR($D13="",$F13=""),"",$D13*$F13) | H13: =IF(OR($D13="",$E13="",$F13=""),"",$D13*$E13+$G13) | L13: =IFERROR(IF(OR($D13="",$D13<=0,$I13="",$I13<=0,Parameters!$D$4<=0,Parameters!$D$5<=0),"",ROUND(SQRT(2*$D13*365*Parameters!$D$4/($I13*Parameters!$D$5)),0)),"") | M13: =IFERROR(IF(OR($L13="",$J13=""),"",MIN($L13,ROUND($D13*$J13*Parameters!$D$12,0),IF($K13="",$L13,$K13))),"") | N13: =IF(OR($D13="",$D13<=0,$M13=""),"",ROUND($M13/$D13,0))
A14: 11 | G14: =IF(OR($D14="",$F14=""),"",$D14*$F14) | H14: =IF(OR($D14="",$E14="",$F14=""),"",$D14*$E14+$G14) | L14: =IFERROR(IF(OR($D14="",$D14<=0,$I14="",$I14<=0,Parameters!$D$4<=0,Parameters!$D$5<=0),"",ROUND(SQRT(2*$D14*365*Parameters!$D$4/($I14*Parameters!$D$5)),0)),"") | M14: =IFERROR(IF(OR($L14="",$J14=""),"",MIN($L14,ROUND($D14*$J14*Parameters!$D$12,0),IF($K14="",$L14,$K14))),"") | N14: =IF(OR($D14="",$D14<=0,$M14=""),"",ROUND($M14/$D14,0))
A15: 12 | G15: =IF(OR($D15="",$F15=""),"",$D15*$F15) | H15: =IF(OR($D15="",$E15="",$F15=""),"",$D15*$E15+$G15) | L15: =IFERROR(IF(OR($D15="",$D15<=0,$I15="",$I15<=0,Parameters!$D$4<=0,Parameters!$D$5<=0),"",ROUND(SQRT(2*$D15*365*Parameters!$D$4/($I15*Parameters!$D$5)),0)),"") | M15: =IFERROR(IF(OR($L15="",$J15=""),"",MIN($L15,ROUND($D15*$J15*Parameters!$D$12,0),IF($K15="",$L15,$K15))),"") | N15: =IF(OR($D15="",$D15<=0,$M15=""),"",ROUND($M15/$D15,0))
A16: 13 | G16: =IF(OR($D16="",$F16=""),"",$D16*$F16) | H16: =IF(OR($D16="",$E16="",$F16=""),"",$D16*$E16+$G16) | L16: =IFERROR(IF(OR($D16="",$D16<=0,$I16="",$I16<=0,Parameters!$D$4<=0,Parameters!$D$5<=0),"",ROUND(SQRT(2*$D16*365*Parameters!$D$4/($I16*Parameters!$D$5)),0)),"") | M16: =IFERROR(IF(OR($L16="",$J16=""),"",MIN($L16,ROUND($D16*$J16*Parameters!$D$12,0),IF($K16="",$L16,$K16))),"") | N16: =IF(OR($D16="",$D16<=0,$M16=""),"",ROUND($M16/$D16,0))
A17: 14 | G17: =IF(OR($D17="",$F17=""),"",$D17*$F17) | H17: =IF(OR($D17="",$E17="",$F17=""),"",$D17*$E17+$G17) | L17: =IFERROR(IF(OR($D17="",$D17<=0,$I17="",$I17<=0,Parameters!$D$4<=0,Parameters!$D$5<=0),"",ROUND(SQRT(2*$D17*365*Parameters!$D$4/($I17*Parameters!$D$5)),0)),"") | M17: =IFERROR(IF(OR($L17="",$J17=""),"",MIN($L17,ROUND($D17*$J17*Parameters!$D$12,0),IF($K17="",$L17,$K17))),"") | N17: =IF(OR($D17="",$D17<=0,$M17=""),"",ROUND($M17/$D17,0))
A18: 15 | G18: =IF(OR($D18="",$F18=""),"",$D18*$F18) | H18: =IF(OR($D18="",$E18="",$F18=""),"",$D18*$E18+$G18) | L18: =IFERROR(IF(OR($D18="",$D18<=0,$I18="",$I18<=0,Parameters!$D$4<=0,Parameters!$D$5<=0),"",ROUND(SQRT(2*$D18*365*Parameters!$D$4/($I18*Parameters!$D$5)),0)),"") | M18: =IFERROR(IF(OR($L18="",$J18=""),"",MIN($L18,ROUND($D18*$J18*Parameters!$D$12,0),IF($K18="",$L18,$K18))),"") | N18: =IF(OR($D18="",$D18<=0,$M18=""),"",ROUND($M18/$D18,0))
A19: 16 | G19: =IF(OR($D19="",$F19=""),"",$D19*$F19) | H19: =IF(OR($D19="",$E19="",$F19=""),"",$D19*$E19+$G19) | L19: =IFERROR(IF(OR($D19="",$D19<=0,$I19="",$I19<=0,Parameters!$D$4<=0,Parameters!$D$5<=0),"",ROUND(SQRT(2*$D19*365*Parameters!$D$4/($I19*Parameters!$D$5)),0)),"") | M19: =IFERROR(IF(OR($L19="",$J19=""),"",MIN($L19,ROUND($D19*$J19*Parameters!$D$12,0),IF($K19="",$L19,$K19))),"") | N19: =IF(OR($D19="",$D19<=0,$M19=""),"",ROUND($M19/$D19,0))
A20: 17 | G20: =IF(OR($D20="",$F20=""),"",$D20*$F20) | H20: =IF(OR($D20="",$E20="",$F20=""),"",$D20*$E20+$G20) | L20: =IFERROR(IF(OR($D20="",$D20<=0,$I20="",$I20<=0,Parameters!$D$4<=0,Parameters!$D$5<=0),"",ROUND(SQRT(2*$D20*365*Parameters!$D$4/($I20*Parameters!$D$5)),0)),"") | M20: =IFERROR(IF(OR($L20="",$J20=""),"",MIN($L20,ROUND($D20*$J20*Parameters!$D$12,0),IF($K20="",$L20,$K20))),"") | N20: =IF(OR($D20="",$D20<=0,$M20=""),"",ROUND($M20/$D20,0))
A21: 18 | G21: =IF(OR($D21="",$F21=""),"",$D21*$F21) | H21: =IF(OR($D21="",$E21="",$F21=""),"",$D21*$E21+$G21) | L21: =IFERROR(IF(OR($D21="",$D21<=0,$I21="",$I21<=0,Parameters!$D$4<=0,Parameters!$D$5<=0),"",ROUND(SQRT(2*$D21*365*Parameters!$D$4/($I21*Parameters!$D$5)),0)),"") | M21: =IFERROR(IF(OR($L21="",$J21=""),"",MIN($L21,ROUND($D21*$J21*Parameters!$D$12,0),IF($K21="",$L21,$K21))),"") | N21: =IF(OR($D21="",$D21<=0,$M21=""),"",ROUND($M21/$D21,0))
A22: 19 | G22: =IF(OR($D22="",$F22=""),"",$D22*$F22) | H22: =IF(OR($D22="",$E22="",$F22=""),"",$D22*$E22+$G22) | L22: =IFERROR(IF(OR($D22="",$D22<=0,$I22="",$I22<=0,Parameters!$D$4<=0,Parameters!$D$5<=0),"",ROUND(SQRT(2*$D22*365*Parameters!$D$4/($I22*Parameters!$D$5)),0)),"") | M22: =IFERROR(IF(OR($L22="",$J22=""),"",MIN($L22,ROUND($D22*$J22*Parameters!$D$12,0),IF($K22="",$L22,$K22))),"") | N22: =IF(OR($D22="",$D22<=0,$M22=""),"",ROUND($M22/$D22,0))
A23: 20 | G23: =IF(OR($D23="",$F23=""),"",$D23*$F23) | H23: =IF(OR($D23="",$E23="",$F23=""),"",$D23*$E23+$G23) | L23: =IFERROR(IF(OR($D23="",$D23<=0,$I23="",$I23<=0,Parameters!$D$4<=0,Parameters!$D$5<=0),"",ROUND(SQRT(2*$D23*365*Parameters!$D$4/($I23*Parameters!$D$5)),0)),"") | M23: =IFERROR(IF(OR($L23="",$J23=""),"",MIN($L23,ROUND($D23*$J23*Parameters!$D$12,0),IF($K23="",$L23,$K23))),"") | N23: =IF(OR($D23="",$D23<=0,$M23=""),"",ROUND($M23/$D23,0))
... A33: 30 | G33: =IF(OR($D33="",$F33=""),"",$D33*$F33) | H33: =IF(OR($D33="",$E33="",$F33=""),"",$D33*$E33+$G33) | L33: =IFERROR(IF(OR($D33="",$D33<=0,$I33="",$I33<=0,Parameters!$D$4<=0,Parameters!$D$5<=0),"",ROUND(SQRT(2*$D33*365*Parameters!$D$4/($I33*Parameters!$D$5)),0)),"") | M33: =IFERROR(IF(OR($L33="",$J33=""),"",MIN($L33,ROUND($D33*$J33*Parameters!$D$12,0),IF($K33="",$L33,$K33))),"") | N33: =IF(OR($D33="",$D33<=0,$M33=""),"",ROUND($M33/$D33,0))
A35: Columns WITHOUT a green fill (don't touch): safety stock, reorder point, theoretical EOQ, suggested quantity and frequency. If frequency comes out blank, it's because daily usage is empty or zero, not because the formula is broken. The suggested quantity carries THREE caps: the EOQ, 70% of what you use within the shelf life, and your max stock — whichever of the three is smallest wins.

Sheet Parameters
A1: REFERENCE PARAMETERS
A3: Parameter | B3: Typical range | C3: Notes | D3: Used in the formula
A4: Order cost | B4: 2-5 (in your currency) | C4: What it costs you to PLACE an order: time to make it, receiving, matching the packing slip, and logging the invoice. | D4: 3
A5: Carrying cost (% annual) | B5: 20-30% annual | C5: On the product's VALUE: tied-up capital, refrigeration, insurance, and the waste from what spoils while it waits. | D5: 0.25
A6: Meat lead time | B6: 1-2 days | C6: Typically daily deliveries.
A7: Seafood lead time | B7: 1 day | C7: Daily delivery required.
A8: Dry goods lead time | B8: 3-5 days | C8: Weekly orders.
A9: Frozen lead time | B9: 2-3 days | C9: Orders twice a week.
A10: Safety coverage (days) — column F | B10: 1-3 days | C10: Typed in DAYS. Column G converts it to units: daily usage x coverage days. It used to be entered in days here and added as units there, and the reorder point came out half of what it should be.
A11: Shelf life (days) — column J | B11: Fresh 2-5 · refrigerated 7-15 · dry 180-720 | C11: Days the product holds up in your walk-in cooler from the moment you receive it.
A12: Shelf-life factor | B12: 0.7 (70%) | C12: The suggested quantity never exceeds this percentage of what you use within the shelf life: the rest is the cushion for a slow day. It's a genuine green cell, not a number buried inside the 30 formulas. | D12: 0.7
A13: Max stock (units) — column K | B13: The Par Max from template 01 (Kitchen & Bar Inventory Sheet with Par Levels) | C13: The third cap on the suggested quantity: no matter what the EOQ and shelf life say, you don't order more than fits in your walk-in cooler. Leave it blank if you don't want that cap.
A15: The THREE green cells feed the formulas: order cost, annual carrying cost, and the shelf-life factor. The rest of the table is reference material so you know what to type in each column of the Reorder Calculator.
