Workbook

Sheet Instrucciones
B2: 04 · Presupuesto de Inversión (CAPEX)
B4: AI Chef Pro · aichef.pro — Kit Plan Financiero para Restaurantes
B6: Cómo usar esta plantilla:
B7: ▸ Cada pestaña cubre una categoría de inversión inicial.
B8: ▸ Cada partida lleva Base, IVA % e IVA (€): el desembolso real es la columna «Total con IVA», que con un 21 % es un quinto más de lo que enseña el presupuesto.
B9: ▸ La desviación se calcula automáticamente (% sobre presupuesto).
B10: ▸ La pestaña Resumen consolida todas las categorías.
B12: Categorías:
B13: ▸ Obra, Equipamiento Cocina, Mobiliario Sala, Tecnología, Licencias.
B17: ▸ El coeficiente de amortización por pestaña (obra 3 %, cocina 12 %, mobiliario 10 %, tecnología 25 %) da la dotación anual que pide el 07.
B19: ▸ Lo que no es CAPEX —traspaso, fianza, stock inicial, nóminas pre-apertura, imprevistos y fondo de maniobra— va en la pestaña 'Otros conceptos de apertura'.
B21: Para editar una celda que no esté en verde: Revisar → Desproteger hoja (no tiene contraseña).
... B23: Versión 2.0 · agosto 2026 · aichef.pro/kit-plan-financiero · info@aichef.pro

Sheet Obra
A1: Inversión — Obra
A2: AI Chef Pro · aichef.pro — Kit Plan Financiero para Restaurantes
A4: Partida | B4: Base (€) | C4: IVA % | D4: IVA (€) | E4: Total con IVA (€) | F4: Real (€) | G4: Desviación % | H4: Coef. amortización | I4: Dotación anual (€) | J4: Notas
A5: Demolición y vaciado | B5: 0 | C5: 0.21 | D5: =$B5*$C5 -> 0 | E5: =$B5+$D5 -> 0 | F5: 0 | G5: =IFERROR(($F5-$B5)/$B5,"") | H5: 0.03 | I5: =$B5*$H5 -> 0
A6: Albañilería | B6: 0 | C6: 0.21 | D6: =$B6*$C6 -> 0 | E6: =$B6+$D6 -> 0 | F6: 0 | G6: =IFERROR(($F6-$B6)/$B6,"") | H6: 0.03 | I6: =$B6*$H6 -> 0
A7: Fontanería | B7: 0 | C7: 0.21 | D7: =$B7*$C7 -> 0 | E7: =$B7+$D7 -> 0 | F7: 0 | G7: =IFERROR(($F7-$B7)/$B7,"") | H7: 0.03 | I7: =$B7*$H7 -> 0
A8: Electricidad | B8: 0 | C8: 0.21 | D8: =$B8*$C8 -> 0 | E8: =$B8+$D8 -> 0 | F8: 0 | G8: =IFERROR(($F8-$B8)/$B8,"") | H8: 0.03 | I8: =$B8*$H8 -> 0
A9: Climatización / Extracción | B9: 0 | C9: 0.21 | D9: =$B9*$C9 -> 0 | E9: =$B9+$D9 -> 0 | F9: 0 | G9: =IFERROR(($F9-$B9)/$B9,"") | H9: 0.03 | I9: =$B9*$H9 -> 0
A10: Pintura y acabados | B10: 0 | C10: 0.21 | D10: =$B10*$C10 -> 0 | E10: =$B10+$D10 -> 0 | F10: 0 | G10: =IFERROR(($F10-$B10)/$B10,"") | H10: 0.03 | I10: =$B10*$H10 -> 0
A11: Suelo | B11: 0 | C11: 0.21 | D11: =$B11*$C11 -> 0 | E11: =$B11+$D11 -> 0 | F11: 0 | G11: =IFERROR(($F11-$B11)/$B11,"") | H11: 0.03 | I11: =$B11*$H11 -> 0
A12: Fachada / Rótulo | B12: 0 | C12: 0.21 | D12: =$B12*$C12 -> 0 | E12: =$B12+$D12 -> 0 | F12: 0 | G12: =IFERROR(($F12-$B12)/$B12,"") | H12: 0.03 | I12: =$B12*$H12 -> 0
A13: Baños clientes | B13: 0 | C13: 0.21 | D13: =$B13*$C13 -> 0 | E13: =$B13+$D13 -> 0 | F13: 0 | G13: =IFERROR(($F13-$B13)/$B13,"") | H13: 0.03 | I13: =$B13*$H13 -> 0
A14: Vestuarios personal | B14: 0 | C14: 0.21 | D14: =$B14*$C14 -> 0 | E14: =$B14+$D14 -> 0 | F14: 0 | G14: =IFERROR(($F14-$B14)/$B14,"") | H14: 0.03 | I14: =$B14*$H14 -> 0
A15: TOTAL OBRA | B15: =SUM(B5:B14) -> 0 | D15: =SUM(D5:D14) -> 0 | E15: =SUM(E5:E14) -> 0 | F15: =SUM(F5:F14) -> 0 | G15: =IFERROR(($F15-$B15)/$B15,"") | I15: =SUM(I5:I14) -> 0
A17: © 2026 AI Chef Pro · aichef.pro

Sheet Equipamiento Cocina
A1: Inversión — Equipamiento Cocina
A2: AI Chef Pro · aichef.pro — Kit Plan Financiero para Restaurantes
A4: Partida | B4: Base (€) | C4: IVA % | D4: IVA (€) | E4: Total con IVA (€) | F4: Real (€) | G4: Desviación % | H4: Coef. amortización | I4: Dotación anual (€) | J4: Notas
A5: Cocina industrial (fogones) | B5: 0 | C5: 0.21 | D5: =$B5*$C5 -> 0 | E5: =$B5+$D5 -> 0 | F5: 0 | G5: =IFERROR(($F5-$B5)/$B5,"") | H5: 0.12 | I5: =$B5*$H5 -> 0
A6: Horno combinado | B6: 0 | C6: 0.21 | D6: =$B6*$C6 -> 0 | E6: =$B6+$D6 -> 0 | F6: 0 | G6: =IFERROR(($F6-$B6)/$B6,"") | H6: 0.12 | I6: =$B6*$H6 -> 0
A7: Plancha / Grill | B7: 0 | C7: 0.21 | D7: =$B7*$C7 -> 0 | E7: =$B7+$D7 -> 0 | F7: 0 | G7: =IFERROR(($F7-$B7)/$B7,"") | H7: 0.12 | I7: =$B7*$H7 -> 0
A8: Freidora | B8: 0 | C8: 0.21 | D8: =$B8*$C8 -> 0 | E8: =$B8+$D8 -> 0 | F8: 0 | G8: =IFERROR(($F8-$B8)/$B8,"") | H8: 0.12 | I8: =$B8*$H8 -> 0
A9: Cámara frigorífica | B9: 0 | C9: 0.21 | D9: =$B9*$C9 -> 0 | E9: =$B9+$D9 -> 0 | F9: 0 | G9: =IFERROR(($F9-$B9)/$B9,"") | H9: 0.12 | I9: =$B9*$H9 -> 0
A10: Congelador | B10: 0 | C10: 0.21 | D10: =$B10*$C10 -> 0 | E10: =$B10+$D10 -> 0 | F10: 0 | G10: =IFERROR(($F10-$B10)/$B10,"") | H10: 0.12 | I10: =$B10*$H10 -> 0
A11: Mesa de trabajo inox | B11: 0 | C11: 0.21 | D11: =$B11*$C11 -> 0 | E11: =$B11+$D11 -> 0 | F11: 0 | G11: =IFERROR(($F11-$B11)/$B11,"") | H11: 0.12 | I11: =$B11*$H11 -> 0
A12: Lavavajillas industrial | B12: 0 | C12: 0.21 | D12: =$B12*$C12 -> 0 | E12: =$B12+$D12 -> 0 | F12: 0 | G12: =IFERROR(($F12-$B12)/$B12,"") | H12: 0.12 | I12: =$B12*$H12 -> 0
A13: Campana extractora | B13: 0 | C13: 0.21 | D13: =$B13*$C13 -> 0 | E13: =$B13+$D13 -> 0 | F13: 0 | G13: =IFERROR(($F13-$B13)/$B13,"") | H13: 0.12 | I13: =$B13*$H13 -> 0
A14: Pequeño material cocina | B14: 0 | C14: 0.21 | D14: =$B14*$C14 -> 0 | E14: =$B14+$D14 -> 0 | F14: 0 | G14: =IFERROR(($F14-$B14)/$B14,"") | H14: 0.12 | I14: =$B14*$H14 -> 0
A15: Menaje y utillaje de cocina (gastronorms, cuchillería) | B15: 0 | C15: 0.21 | D15: =$B15*$C15 -> 0 | E15: =$B15+$D15 -> 0 | F15: 0 | G15: =IFERROR(($F15-$B15)/$B15,"") | H15: 0.12 | I15: =$B15*$H15 -> 0
A16: Estantería de almacén y cámara de bebidas | B16: 0 | C16: 0.21 | D16: =$B16*$C16 -> 0 | E16: =$B16+$D16 -> 0 | F16: 0 | G16: =IFERROR(($F16-$B16)/$B16,"") | H16: 0.12 | I16: =$B16*$H16 -> 0
A17: TOTAL EQUIPAMIENTO COCINA | B17: =SUM(B5:B16) -> 0 | D17: =SUM(D5:D16) -> 0 | E17: =SUM(E5:E16) -> 0 | F17: =SUM(F5:F16) -> 0 | G17: =IFERROR(($F17-$B17)/$B17,"") | I17: =SUM(I5:I16) -> 0
A19: © 2026 AI Chef Pro · aichef.pro

Sheet Mobiliario Sala
A1: Inversión — Mobiliario Sala
A2: AI Chef Pro · aichef.pro — Kit Plan Financiero para Restaurantes
A4: Partida | B4: Base (€) | C4: IVA % | D4: IVA (€) | E4: Total con IVA (€) | F4: Real (€) | G4: Desviación % | H4: Coef. amortización | I4: Dotación anual (€) | J4: Notas
A5: Mesas | B5: 0 | C5: 0.21 | D5: =$B5*$C5 -> 0 | E5: =$B5+$D5 -> 0 | F5: 0 | G5: =IFERROR(($F5-$B5)/$B5,"") | H5: 0.1 | I5: =$B5*$H5 -> 0
A6: Sillas | B6: 0 | C6: 0.21 | D6: =$B6*$C6 -> 0 | E6: =$B6+$D6 -> 0 | F6: 0 | G6: =IFERROR(($F6-$B6)/$B6,"") | H6: 0.1 | I6: =$B6*$H6 -> 0
A7: Barra | B7: 0 | C7: 0.21 | D7: =$B7*$C7 -> 0 | E7: =$B7+$D7 -> 0 | F7: 0 | G7: =IFERROR(($F7-$B7)/$B7,"") | H7: 0.1 | I7: =$B7*$H7 -> 0
A8: Taburetes barra | B8: 0 | C8: 0.21 | D8: =$B8*$C8 -> 0 | E8: =$B8+$D8 -> 0 | F8: 0 | G8: =IFERROR(($F8-$B8)/$B8,"") | H8: 0.1 | I8: =$B8*$H8 -> 0
A9: Estanterías / decoración | B9: 0 | C9: 0.21 | D9: =$B9*$C9 -> 0 | E9: =$B9+$D9 -> 0 | F9: 0 | G9: =IFERROR(($F9-$B9)/$B9,"") | H9: 0.1 | I9: =$B9*$H9 -> 0
A10: Iluminación | B10: 0 | C10: 0.21 | D10: =$B10*$C10 -> 0 | E10: =$B10+$D10 -> 0 | F10: 0 | G10: =IFERROR(($F10-$B10)/$B10,"") | H10: 0.1 | I10: =$B10*$H10 -> 0
A11: Terraza (mesas + sillas) | B11: 0 | C11: 0.21 | D11: =$B11*$C11 -> 0 | E11: =$B11+$D11 -> 0 | F11: 0 | G11: =IFERROR(($F11-$B11)/$B11,"") | H11: 0.1 | I11: =$B11*$H11 -> 0
A12: Textil (manteles, servilletas) | B12: 0 | C12: 0.21 | D12: =$B12*$C12 -> 0 | E12: =$B12+$D12 -> 0 | F12: 0 | G12: =IFERROR(($F12-$B12)/$B12,"") | H12: 0.1 | I12: =$B12*$H12 -> 0
A13: Vajilla, cristalería y cubertería (con reposición) | B13: 0 | C13: 0.21 | D13: =$B13*$C13 -> 0 | E13: =$B13+$D13 -> 0 | F13: 0 | G13: =IFERROR(($F13-$B13)/$B13,"") | H13: 0.1 | I13: =$B13*$H13 -> 0
A14: Uniformes y EPI | B14: 0 | C14: 0.21 | D14: =$B14*$C14 -> 0 | E14: =$B14+$D14 -> 0 | F14: 0 | G14: =IFERROR(($F14-$B14)/$B14,"") | H14: 0.1 | I14: =$B14*$H14 -> 0
A15: TOTAL MOBILIARIO SALA | B15: =SUM(B5:B14) -> 0 | D15: =SUM(D5:D14) -> 0 | E15: =SUM(E5:E14) -> 0 | F15: =SUM(F5:F14) -> 0 | G15: =IFERROR(($F15-$B15)/$B15,"") | I15: =SUM(I5:I14) -> 0
A17: © 2026 AI Chef Pro · aichef.pro

Sheet Tecnología
A1: Inversión — Tecnología
A2: AI Chef Pro · aichef.pro — Kit Plan Financiero para Restaurantes
A4: Partida | B4: Base (€) | C4: IVA % | D4: IVA (€) | E4: Total con IVA (€) | F4: Real (€) | G4: Desviación % | H4: Coef. amortización | I4: Dotación anual (€) | J4: Notas
A5: TPV (hardware + software) | B5: 0 | C5: 0.21 | D5: =$B5*$C5 -> 0 | E5: =$B5+$D5 -> 0 | F5: 0 | G5: =IFERROR(($F5-$B5)/$B5,"") | H5: 0.25 | I5: =$B5*$H5 -> 0
A6: Impresoras comandas | B6: 0 | C6: 0.21 | D6: =$B6*$C6 -> 0 | E6: =$B6+$D6 -> 0 | F6: 0 | G6: =IFERROR(($F6-$B6)/$B6,"") | H6: 0.25 | I6: =$B6*$H6 -> 0
A7: Datáfono | B7: 0 | C7: 0.21 | D7: =$B7*$C7 -> 0 | E7: =$B7+$D7 -> 0 | F7: 0 | G7: =IFERROR(($F7-$B7)/$B7,"") | H7: 0.25 | I7: =$B7*$H7 -> 0
A8: Sistema de reservas | B8: 0 | C8: 0.21 | D8: =$B8*$C8 -> 0 | E8: =$B8+$D8 -> 0 | F8: 0 | G8: =IFERROR(($F8-$B8)/$B8,"") | H8: 0.25 | I8: =$B8*$H8 -> 0
A9: Wifi / Red | B9: 0 | C9: 0.21 | D9: =$B9*$C9 -> 0 | E9: =$B9+$D9 -> 0 | F9: 0 | G9: =IFERROR(($F9-$B9)/$B9,"") | H9: 0.25 | I9: =$B9*$H9 -> 0
A10: Pantallas / Digital signage | B10: 0 | C10: 0.21 | D10: =$B10*$C10 -> 0 | E10: =$B10+$D10 -> 0 | F10: 0 | G10: =IFERROR(($F10-$B10)/$B10,"") | H10: 0.25 | I10: =$B10*$H10 -> 0
A11: Web / App delivery | B11: 0 | C11: 0.21 | D11: =$B11*$C11 -> 0 | E11: =$B11+$D11 -> 0 | F11: 0 | G11: =IFERROR(($F11-$B11)/$B11,"") | H11: 0.25 | I11: =$B11*$H11 -> 0
A12: Sistema de seguridad (cámaras) | B12: 0 | C12: 0.21 | D12: =$B12*$C12 -> 0 | E12: =$B12+$D12 -> 0 | F12: 0 | G12: =IFERROR(($F12-$B12)/$B12,"") | H12: 0.25 | I12: =$B12*$H12 -> 0
A13: TOTAL TECNOLOGÍA | B13: =SUM(B5:B12) -> 0 | D13: =SUM(D5:D12) -> 0 | E13: =SUM(E5:E12) -> 0 | F13: =SUM(F5:F12) -> 0 | G13: =IFERROR(($F13-$B13)/$B13,"") | I13: =SUM(I5:I12) -> 0
A15: © 2026 AI Chef Pro · aichef.pro

Sheet Licencias
A1: Inversión — Licencias
A2: AI Chef Pro · aichef.pro — Kit Plan Financiero para Restaurantes
A4: Partida | B4: Base (€) | C4: IVA % | D4: IVA (€) | E4: Total con IVA (€) | F4: Real (€) | G4: Desviación % | H4: Coef. amortización | I4: Dotación anual (€) | J4: Notas
A5: Licencia de apertura | B5: 0 | C5: 0 | D5: =$B5*$C5 -> 0 | E5: =$B5+$D5 -> 0 | F5: 0 | G5: =IFERROR(($F5-$B5)/$B5,"") | H5: 0 | I5: =$B5*$H5 -> 0
A6: Licencia de obras | B6: 0 | C6: 0 | D6: =$B6*$C6 -> 0 | E6: =$B6+$D6 -> 0 | F6: 0 | G6: =IFERROR(($F6-$B6)/$B6,"") | H6: 0 | I6: =$B6*$H6 -> 0
A7: Proyecto técnico (arquitecto) | B7: 0 | C7: 0 | D7: =$B7*$C7 -> 0 | E7: =$B7+$D7 -> 0 | F7: 0 | G7: =IFERROR(($F7-$B7)/$B7,"") | H7: 0 | I7: =$B7*$H7 -> 0
A8: Certificado energético | B8: 0 | C8: 0 | D8: =$B8*$C8 -> 0 | E8: =$B8+$D8 -> 0 | F8: 0 | G8: =IFERROR(($F8-$B8)/$B8,"") | H8: 0 | I8: =$B8*$H8 -> 0
A9: Plan de autoprotección | B9: 0 | C9: 0 | D9: =$B9*$C9 -> 0 | E9: =$B9+$D9 -> 0 | F9: 0 | G9: =IFERROR(($F9-$B9)/$B9,"") | H9: 0 | I9: =$B9*$H9 -> 0
A10: Alta Hacienda / SS | B10: 0 | C10: 0 | D10: =$B10*$C10 -> 0 | E10: =$B10+$D10 -> 0 | F10: 0 | G10: =IFERROR(($F10-$B10)/$B10,"") | H10: 0 | I10: =$B10*$H10 -> 0
A11: Registro sanitario | B11: 0 | C11: 0 | D11: =$B11*$C11 -> 0 | E11: =$B11+$D11 -> 0 | F11: 0 | G11: =IFERROR(($F11-$B11)/$B11,"") | H11: 0 | I11: =$B11*$H11 -> 0
A12: SGAE / Derechos música | B12: 0 | C12: 0 | D12: =$B12*$C12 -> 0 | E12: =$B12+$D12 -> 0 | F12: 0 | G12: =IFERROR(($F12-$B12)/$B12,"") | H12: 0 | I12: =$B12*$H12 -> 0
A13: TOTAL LICENCIAS | B13: =SUM(B5:B12) -> 0 | D13: =SUM(D5:D12) -> 0 | E13: =SUM(E5:E12) -> 0 | F13: =SUM(F5:F12) -> 0 | G13: =IFERROR(($F13-$B13)/$B13,"") | I13: =SUM(I5:I12) -> 0
A15: © 2026 AI Chef Pro · aichef.pro

Sheet Otros conceptos de apertura
A1: Otros conceptos de apertura — lo que no es CAPEX y hay que pagar igual
A2: AI Chef Pro · aichef.pro — Kit Plan Financiero para Restaurantes
A4: Concepto | B4: Base (€) | C4: IVA % | D4: IVA (€) | E4: Total con IVA (€) | F4: Real (€) | G4: Desviación % | H4: Notas
A5: Traspaso del local | B5: 0 | C5: 0.21 | D5: =$B5*$C5 -> 0 | E5: =$B5+$D5 -> 0 | F5: 0 | G5: =IFERROR(($F5-$B5)/$B5,"")
A6: Fianza y primeras rentas | B6: 0 | C6: 0 | D6: =$B6*$C6 -> 0 | E6: =$B6+$D6 -> 0 | F6: 0 | G6: =IFERROR(($F6-$B6)/$B6,"") | H6: La fianza se recupera al salir; las rentas anticipadas, no.
A7: Constitución, notaría y registro | B7: 0 | C7: 0.21 | D7: =$B7*$C7 -> 0 | E7: =$B7+$D7 -> 0 | F7: 0 | G7: =IFERROR(($F7-$B7)/$B7,"")
A8: STOCK INICIAL de despensa y bodega | B8: 0 | C8: 0.1 | D8: =$B8*$C8 -> 0 | E8: =$B8+$D8 -> 0 | F8: 0 | G8: =IFERROR(($F8-$B8)/$B8,"") | H8: Semanas de consumo × coste diario de materia prima. En un casual de 60 plazas, 2-4 semanas suelen ser 8.000-15.000 €.
A9: Nóminas y formación pre-apertura | B9: 0 | C9: 0 | D9: =$B9*$C9 -> 0 | E9: =$B9+$D9 -> 0 | F9: 0 | G9: =IFERROR(($F9-$B9)/$B9,"") | H9: Las dos o tres semanas de plantilla antes de facturar el primer euro.
A10: Marketing de lanzamiento | B10: 0 | C10: 0.21 | D10: =$B10*$C10 -> 0 | E10: =$B10+$D10 -> 0 | F10: 0 | G10: =IFERROR(($F10-$B10)/$B10,"")
A11: Seguros (año 1) | B11: 0 | C11: 0 | D11: =$B11*$C11 -> 0 | E11: =$B11+$D11 -> 0 | F11: 0 | G11: =IFERROR(($F11-$B11)/$B11,"") | H11: Gasto anticipado NO amortizable. Venía de la pestaña Licencias: no es CAPEX y duplicaba 02!Datos!C8.
A12: Imprevistos (5-10 % de la inversión) | B12: 0 | C12: 0.21 | D12: =$B12*$C12 -> 0 | E12: =$B12+$D12 -> 0 | F12: 0 | G12: =IFERROR(($F12-$B12)/$B12,"") | H12: Sobre «INVERSIÓN TOTAL (CAPEX)» de la pestaña Resumen.
A13: FONDO DE MANIOBRA (3-6 meses de costes fijos) | B13: 0 | C13: 0 | D13: =$B13*$C13 -> 0 | E13: =$B13+$D13 -> 0 | F13: 0 | G13: =IFERROR(($F13-$B13)/$B13,"") | H13: Es lo que pide BONUS-09!C15 y hasta hoy no tenía dónde ponerse. Referencia: 02!Datos!C14 × 3 a 6.
A14: TOTAL OTROS CONCEPTOS DE APERTURA | B14: =SUM(B5:B13) -> 0 | D14: =SUM(D5:D13) -> 0 | E14: =SUM(E5:E13) -> 0 | F14: =SUM(F5:F13) -> 0 | G14: =IFERROR(($F14-$B14)/$B14,"")
A16: Ninguno de estos conceptos se amortiza: son gasto del ejercicio o circulante. Por eso no llevan coeficiente.
A18: © 2026 AI Chef Pro · aichef.pro

Sheet Resumen
A1: Resumen de Inversión Total
A2: AI Chef Pro · aichef.pro — Kit Plan Financiero para Restaurantes
A4: Categoría | B4: Base (€) | C4: IVA (€) | D4: Total con IVA (€) | E4: Real (€) | F4: Desviación % | G4: Dotación anual (€)
A5: Obra | B5: ='Obra'!B15 -> 0 | C5: ='Obra'!D15 -> 0 | D5: ='Obra'!E15 -> 0 | E5: ='Obra'!F15 -> 0 | F5: =IFERROR(($E5-$B5)/$B5,"") | G5: ='Obra'!I15 -> 0
A6: Equipamiento Cocina | B6: ='Equipamiento Cocina'!B17 -> 0 | C6: ='Equipamiento Cocina'!D17 -> 0 | D6: ='Equipamiento Cocina'!E17 -> 0 | E6: ='Equipamiento Cocina'!F17 -> 0 | F6: =IFERROR(($E6-$B6)/$B6,"") | G6: ='Equipamiento Cocina'!I17 -> 0
A7: Mobiliario Sala | B7: ='Mobiliario Sala'!B15 -> 0 | C7: ='Mobiliario Sala'!D15 -> 0 | D7: ='Mobiliario Sala'!E15 -> 0 | E7: ='Mobiliario Sala'!F15 -> 0 | F7: =IFERROR(($E7-$B7)/$B7,"") | G7: ='Mobiliario Sala'!I15 -> 0
A8: Tecnología | B8: ='Tecnología'!B13 -> 0 | C8: ='Tecnología'!D13 -> 0 | D8: ='Tecnología'!E13 -> 0 | E8: ='Tecnología'!F13 -> 0 | F8: =IFERROR(($E8-$B8)/$B8,"") | G8: ='Tecnología'!I13 -> 0
A9: Licencias | B9: ='Licencias'!B13 -> 0 | C9: ='Licencias'!D13 -> 0 | D9: ='Licencias'!E13 -> 0 | E9: ='Licencias'!F13 -> 0 | F9: =IFERROR(($E9-$B9)/$B9,"") | G9: ='Licencias'!I13 -> 0
A10: INVERSIÓN TOTAL (CAPEX) | B10: =SUM(B5:B9) -> 0 | C10: =SUM(C5:C9) -> 0 | D10: =SUM(D5:D9) -> 0 | E10: =SUM(E5:E9) -> 0 | F10: =IFERROR(($E10-$B10)/$B10,"") | G10: =SUM(G5:G9) -> 0
A11: Otros conceptos de apertura | B11: ='Otros conceptos de apertura'!B14 -> 0 | C11: ='Otros conceptos de apertura'!D14 -> 0 | D11: ='Otros conceptos de apertura'!E14 -> 0 | E11: ='Otros conceptos de apertura'!F14 -> 0 | F11: =IFERROR(($E11-$B11)/$B11,"")
A12: DESEMBOLSO TOTAL DE APERTURA (base + IVA) | B12: =B10+B11 -> 0 | C12: =C10+C11 -> 0 | D12: =D10+D11 -> 0 | E12: =E10+E11 -> 0 | F12: =IFERROR(($E12-$B12)/$B12,"")
A14: De dónde sale cada dato (el encadenado realista entre libros):
A15: ▸ La «Dotación anual (€)» de la fila 10 es la que se copia a 07!Proyecciones, fila «Amortización».
A16: ▸ El «IVA (€)» de la fila 12 es IVA soportado: se recupera vía modelo 303, pero hay que ADELANTARLO. El préstamo tiene que cubrirlo.
A30: © 2026 AI Chef Pro · aichef.pro
