Workbook

Sheet Instrucciones
B2: 05 · P&L Mensual — Real vs Presupuesto
B4: AI Chef Pro · aichef.pro — Kit Plan Financiero para Restaurantes
B6: Cómo usar esta plantilla:
B7: ▸ Cada mes tiene su pestaña con columnas: Presupuesto, Real, Desviación €, Desviación %.
B8: ▸ El semáforo va CON SIGNO: en ingresos y EBITDA avisa cuando te quedas corto; en gastos, cuando te pasas. Los umbrales son editables en «Resumen Anual» (B22:B25).
B9: ▸ Food Cost % se mide sobre las ventas de comida (total menos barra) y Beverage Cost % sobre las de barra.
B10: ▸ La pestaña Resumen consolida los 12 meses.
B11: ▸ El estado «—» significa que ese mes todavía no tiene presupuesto: el semáforo no opina hasta que lo pongas.
B13: Todas las cifras van SIN IVA; en el 03 (tesorería) van CON IVA porque es caja.
B14: Para editar una celda que no esté en verde: Revisar → Desproteger hoja (no tiene contraseña).
B15: Diseñado por John Guerrero — chef y consultor gastronómico desde 2010, en cocina desde los 17 años · johnguerrero.es
B16: Versión 2.0 · agosto 2026 · aichef.pro/kit-plan-financiero · info@aichef.pro

Sheet Ene
A1: P&L Ene — Real vs Presupuesto
A2: AI Chef Pro · aichef.pro — Kit Plan Financiero para Restaurantes
A4: Concepto | B4: Presupuesto (€) | C4: Real (€) | D4: Desviación (€) | E4: Desviación % | F4: Semáforo
A5: INGRESOS
A6: Ventas Comedor (sin IVA) | B6: 0 | C6: 0 | D6: =C6-B6 -> 0 | E6: =IF($B6=0,"",IFERROR(($C6-$B6)/$B6,"")) | F6: =IFERROR(IF(ISNUMBER($E6),IF($E6>=-'Resumen Anual'!$B$22,"✅ OK",IF($E6>=-'Resumen Anual'!$B$23,"⚠️ Atención","🔴 Alerta")),"—"),"—") -> —
A7: Ventas Barra (sin IVA) | B7: 0 | C7: 0 | D7: =C7-B7 -> 0 | E7: =IF($B7=0,"",IFERROR(($C7-$B7)/$B7,"")) | F7: =IFERROR(IF(ISNUMBER($E7),IF($E7>=-'Resumen Anual'!$B$22,"✅ OK",IF($E7>=-'Resumen Anual'!$B$23,"⚠️ Atención","🔴 Alerta")),"—"),"—") -> —
A8: Ventas Delivery (sin IVA) | B8: 0 | C8: 0 | D8: =C8-B8 -> 0 | E8: =IF($B8=0,"",IFERROR(($C8-$B8)/$B8,"")) | F8: =IFERROR(IF(ISNUMBER($E8),IF($E8>=-'Resumen Anual'!$B$22,"✅ OK",IF($E8>=-'Resumen Anual'!$B$23,"⚠️ Atención","🔴 Alerta")),"—"),"—") -> —
A9: Eventos / Catering (sin IVA) | B9: 0 | C9: 0 | D9: =C9-B9 -> 0 | E9: =IF($B9=0,"",IFERROR(($C9-$B9)/$B9,"")) | F9: =IFERROR(IF(ISNUMBER($E9),IF($E9>=-'Resumen Anual'!$B$22,"✅ OK",IF($E9>=-'Resumen Anual'!$B$23,"⚠️ Atención","🔴 Alerta")),"—"),"—") -> —
A10: TOTAL INGRESOS (sin IVA) | B10: =B6+B7+B8+B9 -> 0 | C10: =C6+C7+C8+C9 -> 0 | D10: =C10-B10 -> 0 | E10: =IF($B10=0,"",IFERROR(($C10-$B10)/$B10,"")) | F10: =IFERROR(IF(ISNUMBER($E10),IF($E10>=-'Resumen Anual'!$B$22,"✅ OK",IF($E10>=-'Resumen Anual'!$B$23,"⚠️ Atención","🔴 Alerta")),"—"),"—") -> —
A12: GASTOS
A13: Coste de comida (materia prima) | B13: 0 | C13: 0 | D13: =C13-B13 -> 0 | E13: =IF($B13=0,"",IFERROR(($C13-$B13)/$B13,"")) | F13: =IFERROR(IF(ISNUMBER($E13),IF($E13<='Resumen Anual'!$B$22,"✅ OK",IF($E13<='Resumen Anual'!$B$23,"⚠️ Atención","🔴 Alerta")),"—"),"—") -> —
A14: Coste de bebida (barra) | B14: 0 | C14: 0 | D14: =C14-B14 -> 0 | E14: =IF($B14=0,"",IFERROR(($C14-$B14)/$B14,"")) | F14: =IFERROR(IF(ISNUMBER($E14),IF($E14<='Resumen Anual'!$B$22,"✅ OK",IF($E14<='Resumen Anual'!$B$23,"⚠️ Atención","🔴 Alerta")),"—"),"—") -> —
A15: Personal (Labor) | B15: 0 | C15: 0 | D15: =C15-B15 -> 0 | E15: =IF($B15=0,"",IFERROR(($C15-$B15)/$B15,"")) | F15: =IFERROR(IF(ISNUMBER($E15),IF($E15<='Resumen Anual'!$B$22,"✅ OK",IF($E15<='Resumen Anual'!$B$23,"⚠️ Atención","🔴 Alerta")),"—"),"—") -> —
A16: Comisiones de plataformas (delivery) | B16: 0 | C16: 0 | D16: =C16-B16 -> 0 | E16: =IF($B16=0,"",IFERROR(($C16-$B16)/$B16,"")) | F16: =IFERROR(IF(ISNUMBER($E16),IF($E16<='Resumen Anual'!$B$22,"✅ OK",IF($E16<='Resumen Anual'!$B$23,"⚠️ Atención","🔴 Alerta")),"—"),"—") -> —
A17: Alquiler | B17: 0 | C17: 0 | D17: =C17-B17 -> 0 | E17: =IF($B17=0,"",IFERROR(($C17-$B17)/$B17,"")) | F17: =IFERROR(IF(ISNUMBER($E17),IF($E17<='Resumen Anual'!$B$22,"✅ OK",IF($E17<='Resumen Anual'!$B$23,"⚠️ Atención","🔴 Alerta")),"—"),"—") -> —
A18: Suministros | B18: 0 | C18: 0 | D18: =C18-B18 -> 0 | E18: =IF($B18=0,"",IFERROR(($C18-$B18)/$B18,"")) | F18: =IFERROR(IF(ISNUMBER($E18),IF($E18<='Resumen Anual'!$B$22,"✅ OK",IF($E18<='Resumen Anual'!$B$23,"⚠️ Atención","🔴 Alerta")),"—"),"—") -> —
A19: Marketing | B19: 0 | C19: 0 | D19: =C19-B19 -> 0 | E19: =IF($B19=0,"",IFERROR(($C19-$B19)/$B19,"")) | F19: =IFERROR(IF(ISNUMBER($E19),IF($E19<='Resumen Anual'!$B$22,"✅ OK",IF($E19<='Resumen Anual'!$B$23,"⚠️ Atención","🔴 Alerta")),"—"),"—") -> —
A20: Administración / Otros | B20: 0 | C20: 0 | D20: =C20-B20 -> 0 | E20: =IF($B20=0,"",IFERROR(($C20-$B20)/$B20,"")) | F20: =IFERROR(IF(ISNUMBER($E20),IF($E20<='Resumen Anual'!$B$22,"✅ OK",IF($E20<='Resumen Anual'!$B$23,"⚠️ Atención","🔴 Alerta")),"—"),"—") -> —
A21: TOTAL GASTOS | B21: =SUM(B13:B20) -> 0 | C21: =SUM(C13:C20) -> 0 | D21: =C21-B21 -> 0 | E21: =IF($B21=0,"",IFERROR(($C21-$B21)/$B21,"")) | F21: =IFERROR(IF(ISNUMBER($E21),IF($E21<='Resumen Anual'!$B$22,"✅ OK",IF($E21<='Resumen Anual'!$B$23,"⚠️ Atención","🔴 Alerta")),"—"),"—") -> —
A23: EBITDA | B23: =B10-B21 -> 0 | C23: =C10-C21 -> 0 | D23: =C23-B23 -> 0 | E23: =IF($B23=0,"",IFERROR(($C23-$B23)/ABS($B23),"")) | F23: =IFERROR(IF(ISNUMBER($E23),IF($E23>=-'Resumen Anual'!$B$22,"✅ OK",IF($E23>=-'Resumen Anual'!$B$23,"⚠️ Atención","🔴 Alerta")),"—"),"—") -> —
A24: Margen EBITDA % | B24: =IF(B10=0,"",B23/B10) | C24: =IF(C10=0,"",C23/C10) | D24: =IFERROR($C24-$B24,"") | E24: p.p. | F24: =IFERROR(IF(ISNUMBER($D24),IF($D24>=-'Resumen Anual'!$B$24,"✅ OK",IF($D24>=-'Resumen Anual'!$B$25,"⚠️ Atención","🔴 Alerta")),"—"),"—") -> —
A26: RATIOS AUTOMÁTICOS
A27: Food Cost % (sobre ventas de comida) | B27: =IF((B10-B7)<=0,"",B13/(B10-B7)) | C27: =IF((C10-C7)<=0,"",C13/(C10-C7)) | D27: =IFERROR($C27-$B27,"") | E27: p.p. | F27: =IFERROR(IF(ISNUMBER($D27),IF($D27<='Resumen Anual'!$B$24,"✅ OK",IF($D27<='Resumen Anual'!$B$25,"⚠️ Atención","🔴 Alerta")),"—"),"—") -> —
A28: Beverage Cost % (sobre ventas de barra) | B28: =IF(B7=0,"",B14/B7) | C28: =IF(C7=0,"",C14/C7) | D28: =IFERROR($C28-$B28,"") | E28: p.p. | F28: =IFERROR(IF(ISNUMBER($D28),IF($D28<='Resumen Anual'!$B$24,"✅ OK",IF($D28<='Resumen Anual'!$B$25,"⚠️ Atención","🔴 Alerta")),"—"),"—") -> —
A29: Labor Cost % | B29: =IF(B10=0,"",B15/B10) | C29: =IF(C10=0,"",C15/C10) | D29: =IFERROR($C29-$B29,"") | E29: p.p. | F29: =IFERROR(IF(ISNUMBER($D29),IF($D29<='Resumen Anual'!$B$24,"✅ OK",IF($D29<='Resumen Anual'!$B$25,"⚠️ Atención","🔴 Alerta")),"—"),"—") -> —
A30: Prime Cost % (comida + bebida + personal) | B30: =IF(B10=0,"",(B13+B14+B15)/B10) | C30: =IF(C10=0,"",(C13+C14+C15)/C10) | D30: =IFERROR($C30-$B30,"") | E30: p.p. | F30: =IFERROR(IF(ISNUMBER($D30),IF($D30<='Resumen Anual'!$B$24,"✅ OK",IF($D30<='Resumen Anual'!$B$25,"⚠️ Atención","🔴 Alerta")),"—"),"—") -> —
A32: © 2026 AI Chef Pro · aichef.pro

Sheet Feb
A1: P&L Feb — Real vs Presupuesto
A2: AI Chef Pro · aichef.pro — Kit Plan Financiero para Restaurantes
A4: Concepto | B4: Presupuesto (€) | C4: Real (€) | D4: Desviación (€) | E4: Desviación % | F4: Semáforo
A5: INGRESOS
A6: Ventas Comedor (sin IVA) | B6: 0 | C6: 0 | D6: =C6-B6 -> 0 | E6: =IF($B6=0,"",IFERROR(($C6-$B6)/$B6,"")) | F6: =IFERROR(IF(ISNUMBER($E6),IF($E6>=-'Resumen Anual'!$B$22,"✅ OK",IF($E6>=-'Resumen Anual'!$B$23,"⚠️ Atención","🔴 Alerta")),"—"),"—") -> —
A7: Ventas Barra (sin IVA) | B7: 0 | C7: 0 | D7: =C7-B7 -> 0 | E7: =IF($B7=0,"",IFERROR(($C7-$B7)/$B7,"")) | F7: =IFERROR(IF(ISNUMBER($E7),IF($E7>=-'Resumen Anual'!$B$22,"✅ OK",IF($E7>=-'Resumen Anual'!$B$23,"⚠️ Atención","🔴 Alerta")),"—"),"—") -> —
A8: Ventas Delivery (sin IVA) | B8: 0 | C8: 0 | D8: =C8-B8 -> 0 | E8: =IF($B8=0,"",IFERROR(($C8-$B8)/$B8,"")) | F8: =IFERROR(IF(ISNUMBER($E8),IF($E8>=-'Resumen Anual'!$B$22,"✅ OK",IF($E8>=-'Resumen Anual'!$B$23,"⚠️ Atención","🔴 Alerta")),"—"),"—") -> —
A9: Eventos / Catering (sin IVA) | B9: 0 | C9: 0 | D9: =C9-B9 -> 0 | E9: =IF($B9=0,"",IFERROR(($C9-$B9)/$B9,"")) | F9: =IFERROR(IF(ISNUMBER($E9),IF($E9>=-'Resumen Anual'!$B$22,"✅ OK",IF($E9>=-'Resumen Anual'!$B$23,"⚠️ Atención","🔴 Alerta")),"—"),"—") -> —
A10: TOTAL INGRESOS (sin IVA) | B10: =B6+B7+B8+B9 -> 0 | C10: =C6+C7+C8+C9 -> 0 | D10: =C10-B10 -> 0 | E10: =IF($B10=0,"",IFERROR(($C10-$B10)/$B10,"")) | F10: =IFERROR(IF(ISNUMBER($E10),IF($E10>=-'Resumen Anual'!$B$22,"✅ OK",IF($E10>=-'Resumen Anual'!$B$23,"⚠️ Atención","🔴 Alerta")),"—"),"—") -> —
A12: GASTOS
A13: Coste de comida (materia prima) | B13: 0 | C13: 0 | D13: =C13-B13 -> 0 | E13: =IF($B13=0,"",IFERROR(($C13-$B13)/$B13,"")) | F13: =IFERROR(IF(ISNUMBER($E13),IF($E13<='Resumen Anual'!$B$22,"✅ OK",IF($E13<='Resumen Anual'!$B$23,"⚠️ Atención","🔴 Alerta")),"—"),"—") -> —
A14: Coste de bebida (barra) | B14: 0 | C14: 0 | D14: =C14-B14 -> 0 | E14: =IF($B14=0,"",IFERROR(($C14-$B14)/$B14,"")) | F14: =IFERROR(IF(ISNUMBER($E14),IF($E14<='Resumen Anual'!$B$22,"✅ OK",IF($E14<='Resumen Anual'!$B$23,"⚠️ Atención","🔴 Alerta")),"—"),"—") -> —
A15: Personal (Labor) | B15: 0 | C15: 0 | D15: =C15-B15 -> 0 | E15: =IF($B15=0,"",IFERROR(($C15-$B15)/$B15,"")) | F15: =IFERROR(IF(ISNUMBER($E15),IF($E15<='Resumen Anual'!$B$22,"✅ OK",IF($E15<='Resumen Anual'!$B$23,"⚠️ Atención","🔴 Alerta")),"—"),"—") -> —
A16: Comisiones de plataformas (delivery) | B16: 0 | C16: 0 | D16: =C16-B16 -> 0 | E16: =IF($B16=0,"",IFERROR(($C16-$B16)/$B16,"")) | F16: =IFERROR(IF(ISNUMBER($E16),IF($E16<='Resumen Anual'!$B$22,"✅ OK",IF($E16<='Resumen Anual'!$B$23,"⚠️ Atención","🔴 Alerta")),"—"),"—") -> —
A17: Alquiler | B17: 0 | C17: 0 | D17: =C17-B17 -> 0 | E17: =IF($B17=0,"",IFERROR(($C17-$B17)/$B17,"")) | F17: =IFERROR(IF(ISNUMBER($E17),IF($E17<='Resumen Anual'!$B$22,"✅ OK",IF($E17<='Resumen Anual'!$B$23,"⚠️ Atención","🔴 Alerta")),"—"),"—") -> —
A18: Suministros | B18: 0 | C18: 0 | D18: =C18-B18 -> 0 | E18: =IF($B18=0,"",IFERROR(($C18-$B18)/$B18,"")) | F18: =IFERROR(IF(ISNUMBER($E18),IF($E18<='Resumen Anual'!$B$22,"✅ OK",IF($E18<='Resumen Anual'!$B$23,"⚠️ Atención","🔴 Alerta")),"—"),"—") -> —
A19: Marketing | B19: 0 | C19: 0 | D19: =C19-B19 -> 0 | E19: =IF($B19=0,"",IFERROR(($C19-$B19)/$B19,"")) | F19: =IFERROR(IF(ISNUMBER($E19),IF($E19<='Resumen Anual'!$B$22,"✅ OK",IF($E19<='Resumen Anual'!$B$23,"⚠️ Atención","🔴 Alerta")),"—"),"—") -> —
A20: Administración / Otros | B20: 0 | C20: 0 | D20: =C20-B20 -> 0 | E20: =IF($B20=0,"",IFERROR(($C20-$B20)/$B20,"")) | F20: =IFERROR(IF(ISNUMBER($E20),IF($E20<='Resumen Anual'!$B$22,"✅ OK",IF($E20<='Resumen Anual'!$B$23,"⚠️ Atención","🔴 Alerta")),"—"),"—") -> —
A21: TOTAL GASTOS | B21: =SUM(B13:B20) -> 0 | C21: =SUM(C13:C20) -> 0 | D21: =C21-B21 -> 0 | E21: =IF($B21=0,"",IFERROR(($C21-$B21)/$B21,"")) | F21: =IFERROR(IF(ISNUMBER($E21),IF($E21<='Resumen Anual'!$B$22,"✅ OK",IF($E21<='Resumen Anual'!$B$23,"⚠️ Atención","🔴 Alerta")),"—"),"—") -> —
A23: EBITDA | B23: =B10-B21 -> 0 | C23: =C10-C21 -> 0 | D23: =C23-B23 -> 0 | E23: =IF($B23=0,"",IFERROR(($C23-$B23)/ABS($B23),"")) | F23: =IFERROR(IF(ISNUMBER($E23),IF($E23>=-'Resumen Anual'!$B$22,"✅ OK",IF($E23>=-'Resumen Anual'!$B$23,"⚠️ Atención","🔴 Alerta")),"—"),"—") -> —
A24: Margen EBITDA % | B24: =IF(B10=0,"",B23/B10) | C24: =IF(C10=0,"",C23/C10) | D24: =IFERROR($C24-$B24,"") | E24: p.p. | F24: =IFERROR(IF(ISNUMBER($D24),IF($D24>=-'Resumen Anual'!$B$24,"✅ OK",IF($D24>=-'Resumen Anual'!$B$25,"⚠️ Atención","🔴 Alerta")),"—"),"—") -> —
A26: RATIOS AUTOMÁTICOS
A27: Food Cost % (sobre ventas de comida) | B27: =IF((B10-B7)<=0,"",B13/(B10-B7)) | C27: =IF((C10-C7)<=0,"",C13/(C10-C7)) | D27: =IFERROR($C27-$B27,"") | E27: p.p. | F27: =IFERROR(IF(ISNUMBER($D27),IF($D27<='Resumen Anual'!$B$24,"✅ OK",IF($D27<='Resumen Anual'!$B$25,"⚠️ Atención","🔴 Alerta")),"—"),"—") -> —
A28: Beverage Cost % (sobre ventas de barra) | B28: =IF(B7=0,"",B14/B7) | C28: =IF(C7=0,"",C14/C7) | D28: =IFERROR($C28-$B28,"") | E28: p.p. | F28: =IFERROR(IF(ISNUMBER($D28),IF($D28<='Resumen Anual'!$B$24,"✅ OK",IF($D28<='Resumen Anual'!$B$25,"⚠️ Atención","🔴 Alerta")),"—"),"—") -> —
A29: Labor Cost % | B29: =IF(B10=0,"",B15/B10) | C29: =IF(C10=0,"",C15/C10) | D29: =IFERROR($C29-$B29,"") | E29: p.p. | F29: =IFERROR(IF(ISNUMBER($D29),IF($D29<='Resumen Anual'!$B$24,"✅ OK",IF($D29<='Resumen Anual'!$B$25,"⚠️ Atención","🔴 Alerta")),"—"),"—") -> —
A30: Prime Cost % (comida + bebida + personal) | B30: =IF(B10=0,"",(B13+B14+B15)/B10) | C30: =IF(C10=0,"",(C13+C14+C15)/C10) | D30: =IFERROR($C30-$B30,"") | E30: p.p. | F30: =IFERROR(IF(ISNUMBER($D30),IF($D30<='Resumen Anual'!$B$24,"✅ OK",IF($D30<='Resumen Anual'!$B$25,"⚠️ Atención","🔴 Alerta")),"—"),"—") -> —
A32: © 2026 AI Chef Pro · aichef.pro

Sheet Mar
A1: P&L Mar — Real vs Presupuesto
A2: AI Chef Pro · aichef.pro — Kit Plan Financiero para Restaurantes
A4: Concepto | B4: Presupuesto (€) | C4: Real (€) | D4: Desviación (€) | E4: Desviación % | F4: Semáforo
A5: INGRESOS
A6: Ventas Comedor (sin IVA) | B6: 0 | C6: 0 | D6: =C6-B6 -> 0 | E6: =IF($B6=0,"",IFERROR(($C6-$B6)/$B6,"")) | F6: =IFERROR(IF(ISNUMBER($E6),IF($E6>=-'Resumen Anual'!$B$22,"✅ OK",IF($E6>=-'Resumen Anual'!$B$23,"⚠️ Atención","🔴 Alerta")),"—"),"—") -> —
A7: Ventas Barra (sin IVA) | B7: 0 | C7: 0 | D7: =C7-B7 -> 0 | E7: =IF($B7=0,"",IFERROR(($C7-$B7)/$B7,"")) | F7: =IFERROR(IF(ISNUMBER($E7),IF($E7>=-'Resumen Anual'!$B$22,"✅ OK",IF($E7>=-'Resumen Anual'!$B$23,"⚠️ Atención","🔴 Alerta")),"—"),"—") -> —
A8: Ventas Delivery (sin IVA) | B8: 0 | C8: 0 | D8: =C8-B8 -> 0 | E8: =IF($B8=0,"",IFERROR(($C8-$B8)/$B8,"")) | F8: =IFERROR(IF(ISNUMBER($E8),IF($E8>=-'Resumen Anual'!$B$22,"✅ OK",IF($E8>=-'Resumen Anual'!$B$23,"⚠️ Atención","🔴 Alerta")),"—"),"—") -> —
A9: Eventos / Catering (sin IVA) | B9: 0 | C9: 0 | D9: =C9-B9 -> 0 | E9: =IF($B9=0,"",IFERROR(($C9-$B9)/$B9,"")) | F9: =IFERROR(IF(ISNUMBER($E9),IF($E9>=-'Resumen Anual'!$B$22,"✅ OK",IF($E9>=-'Resumen Anual'!$B$23,"⚠️ Atención","🔴 Alerta")),"—"),"—") -> —
A10: TOTAL INGRESOS (sin IVA) | B10: =B6+B7+B8+B9 -> 0 | C10: =C6+C7+C8+C9 -> 0 | D10: =C10-B10 -> 0 | E10: =IF($B10=0,"",IFERROR(($C10-$B10)/$B10,"")) | F10: =IFERROR(IF(ISNUMBER($E10),IF($E10>=-'Resumen Anual'!$B$22,"✅ OK",IF($E10>=-'Resumen Anual'!$B$23,"⚠️ Atención","🔴 Alerta")),"—"),"—") -> —
A12: GASTOS
A13: Coste de comida (materia prima) | B13: 0 | C13: 0 | D13: =C13-B13 -> 0 | E13: =IF($B13=0,"",IFERROR(($C13-$B13)/$B13,"")) | F13: =IFERROR(IF(ISNUMBER($E13),IF($E13<='Resumen Anual'!$B$22,"✅ OK",IF($E13<='Resumen Anual'!$B$23,"⚠️ Atención","🔴 Alerta")),"—"),"—") -> —
A14: Coste de bebida (barra) | B14: 0 | C14: 0 | D14: =C14-B14 -> 0 | E14: =IF($B14=0,"",IFERROR(($C14-$B14)/$B14,"")) | F14: =IFERROR(IF(ISNUMBER($E14),IF($E14<='Resumen Anual'!$B$22,"✅ OK",IF($E14<='Resumen Anual'!$B$23,"⚠️ Atención","🔴 Alerta")),"—"),"—") -> —
A15: Personal (Labor) | B15: 0 | C15: 0 | D15: =C15-B15 -> 0 | E15: =IF($B15=0,"",IFERROR(($C15-$B15)/$B15,"")) | F15: =IFERROR(IF(ISNUMBER($E15),IF($E15<='Resumen Anual'!$B$22,"✅ OK",IF($E15<='Resumen Anual'!$B$23,"⚠️ Atención","🔴 Alerta")),"—"),"—") -> —
A16: Comisiones de plataformas (delivery) | B16: 0 | C16: 0 | D16: =C16-B16 -> 0 | E16: =IF($B16=0,"",IFERROR(($C16-$B16)/$B16,"")) | F16: =IFERROR(IF(ISNUMBER($E16),IF($E16<='Resumen Anual'!$B$22,"✅ OK",IF($E16<='Resumen Anual'!$B$23,"⚠️ Atención","🔴 Alerta")),"—"),"—") -> —
A17: Alquiler | B17: 0 | C17: 0 | D17: =C17-B17 -> 0 | E17: =IF($B17=0,"",IFERROR(($C17-$B17)/$B17,"")) | F17: =IFERROR(IF(ISNUMBER($E17),IF($E17<='Resumen Anual'!$B$22,"✅ OK",IF($E17<='Resumen Anual'!$B$23,"⚠️ Atención","🔴 Alerta")),"—"),"—") -> —
A18: Suministros | B18: 0 | C18: 0 | D18: =C18-B18 -> 0 | E18: =IF($B18=0,"",IFERROR(($C18-$B18)/$B18,"")) | F18: =IFERROR(IF(ISNUMBER($E18),IF($E18<='Resumen Anual'!$B$22,"✅ OK",IF($E18<='Resumen Anual'!$B$23,"⚠️ Atención","🔴 Alerta")),"—"),"—") -> —
A19: Marketing | B19: 0 | C19: 0 | D19: =C19-B19 -> 0 | E19: =IF($B19=0,"",IFERROR(($C19-$B19)/$B19,"")) | F19: =IFERROR(IF(ISNUMBER($E19),IF($E19<='Resumen Anual'!$B$22,"✅ OK",IF($E19<='Resumen Anual'!$B$23,"⚠️ Atención","🔴 Alerta")),"—"),"—") -> —
A20: Administración / Otros | B20: 0 | C20: 0 | D20: =C20-B20 -> 0 | E20: =IF($B20=0,"",IFERROR(($C20-$B20)/$B20,"")) | F20: =IFERROR(IF(ISNUMBER($E20),IF($E20<='Resumen Anual'!$B$22,"✅ OK",IF($E20<='Resumen Anual'!$B$23,"⚠️ Atención","🔴 Alerta")),"—"),"—") -> —
A21: TOTAL GASTOS | B21: =SUM(B13:B20) -> 0 | C21: =SUM(C13:C20) -> 0 | D21: =C21-B21 -> 0 | E21: =IF($B21=0,"",IFERROR(($C21-$B21)/$B21,"")) | F21: =IFERROR(IF(ISNUMBER($E21),IF($E21<='Resumen Anual'!$B$22,"✅ OK",IF($E21<='Resumen Anual'!$B$23,"⚠️ Atención","🔴 Alerta")),"—"),"—") -> —
A23: EBITDA | B23: =B10-B21 -> 0 | C23: =C10-C21 -> 0 | D23: =C23-B23 -> 0 | E23: =IF($B23=0,"",IFERROR(($C23-$B23)/ABS($B23),"")) | F23: =IFERROR(IF(ISNUMBER($E23),IF($E23>=-'Resumen Anual'!$B$22,"✅ OK",IF($E23>=-'Resumen Anual'!$B$23,"⚠️ Atención","🔴 Alerta")),"—"),"—") -> —
A24: Margen EBITDA % | B24: =IF(B10=0,"",B23/B10) | C24: =IF(C10=0,"",C23/C10) | D24: =IFERROR($C24-$B24,"") | E24: p.p. | F24: =IFERROR(IF(ISNUMBER($D24),IF($D24>=-'Resumen Anual'!$B$24,"✅ OK",IF($D24>=-'Resumen Anual'!$B$25,"⚠️ Atención","🔴 Alerta")),"—"),"—") -> —
A26: RATIOS AUTOMÁTICOS
A27: Food Cost % (sobre ventas de comida) | B27: =IF((B10-B7)<=0,"",B13/(B10-B7)) | C27: =IF((C10-C7)<=0,"",C13/(C10-C7)) | D27: =IFERROR($C27-$B27,"") | E27: p.p. | F27: =IFERROR(IF(ISNUMBER($D27),IF($D27<='Resumen Anual'!$B$24,"✅ OK",IF($D27<='Resumen Anual'!$B$25,"⚠️ Atención","🔴 Alerta")),"—"),"—") -> —
A28: Beverage Cost % (sobre ventas de barra) | B28: =IF(B7=0,"",B14/B7) | C28: =IF(C7=0,"",C14/C7) | D28: =IFERROR($C28-$B28,"") | E28: p.p. | F28: =IFERROR(IF(ISNUMBER($D28),IF($D28<='Resumen Anual'!$B$24,"✅ OK",IF($D28<='Resumen Anual'!$B$25,"⚠️ Atención","🔴 Alerta")),"—"),"—") -> —
A29: Labor Cost % | B29: =IF(B10=0,"",B15/B10) | C29: =IF(C10=0,"",C15/C10) | D29: =IFERROR($C29-$B29,"") | E29: p.p. | F29: =IFERROR(IF(ISNUMBER($D29),IF($D29<='Resumen Anual'!$B$24,"✅ OK",IF($D29<='Resumen Anual'!$B$25,"⚠️ Atención","🔴 Alerta")),"—"),"—") -> —
A30: Prime Cost % (comida + bebida + personal) | B30: =IF(B10=0,"",(B13+B14+B15)/B10) | C30: =IF(C10=0,"",(C13+C14+C15)/C10) | D30: =IFERROR($C30-$B30,"") | E30: p.p. | F30: =IFERROR(IF(ISNUMBER($D30),IF($D30<='Resumen Anual'!$B$24,"✅ OK",IF($D30<='Resumen Anual'!$B$25,"⚠️ Atención","🔴 Alerta")),"—"),"—") -> —
A32: © 2026 AI Chef Pro · aichef.pro

Sheet Abr
A1: P&L Abr — Real vs Presupuesto
A2: AI Chef Pro · aichef.pro — Kit Plan Financiero para Restaurantes
A4: Concepto | B4: Presupuesto (€) | C4: Real (€) | D4: Desviación (€) | E4: Desviación % | F4: Semáforo
A5: INGRESOS
A6: Ventas Comedor (sin IVA) | B6: 0 | C6: 0 | D6: =C6-B6 -> 0 | E6: =IF($B6=0,"",IFERROR(($C6-$B6)/$B6,"")) | F6: =IFERROR(IF(ISNUMBER($E6),IF($E6>=-'Resumen Anual'!$B$22,"✅ OK",IF($E6>=-'Resumen Anual'!$B$23,"⚠️ Atención","🔴 Alerta")),"—"),"—") -> —
A7: Ventas Barra (sin IVA) | B7: 0 | C7: 0 | D7: =C7-B7 -> 0 | E7: =IF($B7=0,"",IFERROR(($C7-$B7)/$B7,"")) | F7: =IFERROR(IF(ISNUMBER($E7),IF($E7>=-'Resumen Anual'!$B$22,"✅ OK",IF($E7>=-'Resumen Anual'!$B$23,"⚠️ Atención","🔴 Alerta")),"—"),"—") -> —
A8: Ventas Delivery (sin IVA) | B8: 0 | C8: 0 | D8: =C8-B8 -> 0 | E8: =IF($B8=0,"",IFERROR(($C8-$B8)/$B8,"")) | F8: =IFERROR(IF(ISNUMBER($E8),IF($E8>=-'Resumen Anual'!$B$22,"✅ OK",IF($E8>=-'Resumen Anual'!$B$23,"⚠️ Atención","🔴 Alerta")),"—"),"—") -> —
A9: Eventos / Catering (sin IVA) | B9: 0 | C9: 0 | D9: =C9-B9 -> 0 | E9: =IF($B9=0,"",IFERROR(($C9-$B9)/$B9,"")) | F9: =IFERROR(IF(ISNUMBER($E9),IF($E9>=-'Resumen Anual'!$B$22,"✅ OK",IF($E9>=-'Resumen Anual'!$B$23,"⚠️ Atención","🔴 Alerta")),"—"),"—") -> —
A10: TOTAL INGRESOS (sin IVA) | B10: =B6+B7+B8+B9 -> 0 | C10: =C6+C7+C8+C9 -> 0 | D10: =C10-B10 -> 0 | E10: =IF($B10=0,"",IFERROR(($C10-$B10)/$B10,"")) | F10: =IFERROR(IF(ISNUMBER($E10),IF($E10>=-'Resumen Anual'!$B$22,"✅ OK",IF($E10>=-'Resumen Anual'!$B$23,"⚠️ Atención","🔴 Alerta")),"—"),"—") -> —
A12: GASTOS
A13: Coste de comida (materia prima) | B13: 0 | C13: 0 | D13: =C13-B13 -> 0 | E13: =IF($B13=0,"",IFERROR(($C13-$B13)/$B13,"")) | F13: =IFERROR(IF(ISNUMBER($E13),IF($E13<='Resumen Anual'!$B$22,"✅ OK",IF($E13<='Resumen Anual'!$B$23,"⚠️ Atención","🔴 Alerta")),"—"),"—") -> —
A14: Coste de bebida (barra) | B14: 0 | C14: 0 | D14: =C14-B14 -> 0 | E14: =IF($B14=0,"",IFERROR(($C14-$B14)/$B14,"")) | F14: =IFERROR(IF(ISNUMBER($E14),IF($E14<='Resumen Anual'!$B$22,"✅ OK",IF($E14<='Resumen Anual'!$B$23,"⚠️ Atención","🔴 Alerta")),"—"),"—") -> —
A15: Personal (Labor) | B15: 0 | C15: 0 | D15: =C15-B15 -> 0 | E15: =IF($B15=0,"",IFERROR(($C15-$B15)/$B15,"")) | F15: =IFERROR(IF(ISNUMBER($E15),IF($E15<='Resumen Anual'!$B$22,"✅ OK",IF($E15<='Resumen Anual'!$B$23,"⚠️ Atención","🔴 Alerta")),"—"),"—") -> —
A16: Comisiones de plataformas (delivery) | B16: 0 | C16: 0 | D16: =C16-B16 -> 0 | E16: =IF($B16=0,"",IFERROR(($C16-$B16)/$B16,"")) | F16: =IFERROR(IF(ISNUMBER($E16),IF($E16<='Resumen Anual'!$B$22,"✅ OK",IF($E16<='Resumen Anual'!$B$23,"⚠️ Atención","🔴 Alerta")),"—"),"—") -> —
A17: Alquiler | B17: 0 | C17: 0 | D17: =C17-B17 -> 0 | E17: =IF($B17=0,"",IFERROR(($C17-$B17)/$B17,"")) | F17: =IFERROR(IF(ISNUMBER($E17),IF($E17<='Resumen Anual'!$B$22,"✅ OK",IF($E17<='Resumen Anual'!$B$23,"⚠️ Atención","🔴 Alerta")),"—"),"—") -> —
A18: Suministros | B18: 0 | C18: 0 | D18: =C18-B18 -> 0 | E18: =IF($B18=0,"",IFERROR(($C18-$B18)/$B18,"")) | F18: =IFERROR(IF(ISNUMBER($E18),IF($E18<='Resumen Anual'!$B$22,"✅ OK",IF($E18<='Resumen Anual'!$B$23,"⚠️ Atención","🔴 Alerta")),"—"),"—") -> —
A19: Marketing | B19: 0 | C19: 0 | D19: =C19-B19 -> 0 | E19: =IF($B19=0,"",IFERROR(($C19-$B19)/$B19,"")) | F19: =IFERROR(IF(ISNUMBER($E19),IF($E19<='Resumen Anual'!$B$22,"✅ OK",IF($E19<='Resumen Anual'!$B$23,"⚠️ Atención","🔴 Alerta")),"—"),"—") -> —
A20: Administración / Otros | B20: 0 | C20: 0 | D20: =C20-B20 -> 0 | E20: =IF($B20=0,"",IFERROR(($C20-$B20)/$B20,"")) | F20: =IFERROR(IF(ISNUMBER($E20),IF($E20<='Resumen Anual'!$B$22,"✅ OK",IF($E20<='Resumen Anual'!$B$23,"⚠️ Atención","🔴 Alerta")),"—"),"—") -> —
A21: TOTAL GASTOS | B21: =SUM(B13:B20) -> 0 | C21: =SUM(C13:C20) -> 0 | D21: =C21-B21 -> 0 | E21: =IF($B21=0,"",IFERROR(($C21-$B21)/$B21,"")) | F21: =IFERROR(IF(ISNUMBER($E21),IF($E21<='Resumen Anual'!$B$22,"✅ OK",IF($E21<='Resumen Anual'!$B$23,"⚠️ Atención","🔴 Alerta")),"—"),"—") -> —
A23: EBITDA | B23: =B10-B21 -> 0 | C23: =C10-C21 -> 0 | D23: =C23-B23 -> 0 | E23: =IF($B23=0,"",IFERROR(($C23-$B23)/ABS($B23),"")) | F23: =IFERROR(IF(ISNUMBER($E23),IF($E23>=-'Resumen Anual'!$B$22,"✅ OK",IF($E23>=-'Resumen Anual'!$B$23,"⚠️ Atención","🔴 Alerta")),"—"),"—") -> —
A24: Margen EBITDA % | B24: =IF(B10=0,"",B23/B10) | C24: =IF(C10=0,"",C23/C10) | D24: =IFERROR($C24-$B24,"") | E24: p.p. | F24: =IFERROR(IF(ISNUMBER($D24),IF($D24>=-'Resumen Anual'!$B$24,"✅ OK",IF($D24>=-'Resumen Anual'!$B$25,"⚠️ Atención","🔴 Alerta")),"—"),"—") -> —
A26: RATIOS AUTOMÁTICOS
A27: Food Cost % (sobre ventas de comida) | B27: =IF((B10-B7)<=0,"",B13/(B10-B7)) | C27: =IF((C10-C7)<=0,"",C13/(C10-C7)) | D27: =IFERROR($C27-$B27,"") | E27: p.p. | F27: =IFERROR(IF(ISNUMBER($D27),IF($D27<='Resumen Anual'!$B$24,"✅ OK",IF($D27<='Resumen Anual'!$B$25,"⚠️ Atención","🔴 Alerta")),"—"),"—") -> —
A28: Beverage Cost % (sobre ventas de barra) | B28: =IF(B7=0,"",B14/B7) | C28: =IF(C7=0,"",C14/C7) | D28: =IFERROR($C28-$B28,"") | E28: p.p. | F28: =IFERROR(IF(ISNUMBER($D28),IF($D28<='Resumen Anual'!$B$24,"✅ OK",IF($D28<='Resumen Anual'!$B$25,"⚠️ Atención","🔴 Alerta")),"—"),"—") -> —
A29: Labor Cost % | B29: =IF(B10=0,"",B15/B10) | C29: =IF(C10=0,"",C15/C10) | D29: =IFERROR($C29-$B29,"") | E29: p.p. | F29: =IFERROR(IF(ISNUMBER($D29),IF($D29<='Resumen Anual'!$B$24,"✅ OK",IF($D29<='Resumen Anual'!$B$25,"⚠️ Atención","🔴 Alerta")),"—"),"—") -> —
A30: Prime Cost % (comida + bebida + personal) | B30: =IF(B10=0,"",(B13+B14+B15)/B10) | C30: =IF(C10=0,"",(C13+C14+C15)/C10) | D30: =IFERROR($C30-$B30,"") | E30: p.p. | F30: =IFERROR(IF(ISNUMBER($D30),IF($D30<='Resumen Anual'!$B$24,"✅ OK",IF($D30<='Resumen Anual'!$B$25,"⚠️ Atención","🔴 Alerta")),"—"),"—") -> —
A32: © 2026 AI Chef Pro · aichef.pro

Sheet May
A1: P&L May — Real vs Presupuesto
A2: AI Chef Pro · aichef.pro — Kit Plan Financiero para Restaurantes
A4: Concepto | B4: Presupuesto (€) | C4: Real (€) | D4: Desviación (€) | E4: Desviación % | F4: Semáforo
A5: INGRESOS
A6: Ventas Comedor (sin IVA) | B6: 0 | C6: 0 | D6: =C6-B6 -> 0 | E6: =IF($B6=0,"",IFERROR(($C6-$B6)/$B6,"")) | F6: =IFERROR(IF(ISNUMBER($E6),IF($E6>=-'Resumen Anual'!$B$22,"✅ OK",IF($E6>=-'Resumen Anual'!$B$23,"⚠️ Atención","🔴 Alerta")),"—"),"—") -> —
A7: Ventas Barra (sin IVA) | B7: 0 | C7: 0 | D7: =C7-B7 -> 0 | E7: =IF($B7=0,"",IFERROR(($C7-$B7)/$B7,"")) | F7: =IFERROR(IF(ISNUMBER($E7),IF($E7>=-'Resumen Anual'!$B$22,"✅ OK",IF($E7>=-'Resumen Anual'!$B$23,"⚠️ Atención","🔴 Alerta")),"—"),"—") -> —
A8: Ventas Delivery (sin IVA) | B8: 0 | C8: 0 | D8: =C8-B8 -> 0 | E8: =IF($B8=0,"",IFERROR(($C8-$B8)/$B8,"")) | F8: =IFERROR(IF(ISNUMBER($E8),IF($E8>=-'Resumen Anual'!$B$22,"✅ OK",IF($E8>=-'Resumen Anual'!$B$23,"⚠️ Atención","🔴 Alerta")),"—"),"—") -> —
A9: Eventos / Catering (sin IVA) | B9: 0 | C9: 0 | D9: =C9-B9 -> 0 | E9: =IF($B9=0,"",IFERROR(($C9-$B9)/$B9,"")) | F9: =IFERROR(IF(ISNUMBER($E9),IF($E9>=-'Resumen Anual'!$B$22,"✅ OK",IF($E9>=-'Resumen Anual'!$B$23,"⚠️ Atención","🔴 Alerta")),"—"),"—") -> —
A10: TOTAL INGRESOS (sin IVA) | B10: =B6+B7+B8+B9 -> 0 | C10: =C6+C7+C8+C9 -> 0 | D10: =C10-B10 -> 0 | E10: =IF($B10=0,"",IFERROR(($C10-$B10)/$B10,"")) | F10: =IFERROR(IF(ISNUMBER($E10),IF($E10>=-'Resumen Anual'!$B$22,"✅ OK",IF($E10>=-'Resumen Anual'!$B$23,"⚠️ Atención","🔴 Alerta")),"—"),"—") -> —
A12: GASTOS
A13: Coste de comida (materia prima) | B13: 0 | C13: 0 | D13: =C13-B13 -> 0 | E13: =IF($B13=0,"",IFERROR(($C13-$B13)/$B13,"")) | F13: =IFERROR(IF(ISNUMBER($E13),IF($E13<='Resumen Anual'!$B$22,"✅ OK",IF($E13<='Resumen Anual'!$B$23,"⚠️ Atención","🔴 Alerta")),"—"),"—") -> —
A14: Coste de bebida (barra) | B14: 0 | C14: 0 | D14: =C14-B14 -> 0 | E14: =IF($B14=0,"",IFERROR(($C14-$B14)/$B14,"")) | F14: =IFERROR(IF(ISNUMBER($E14),IF($E14<='Resumen Anual'!$B$22,"✅ OK",IF($E14<='Resumen Anual'!$B$23,"⚠️ Atención","🔴 Alerta")),"—"),"—") -> —
A15: Personal (Labor) | B15: 0 | C15: 0 | D15: =C15-B15 -> 0 | E15: =IF($B15=0,"",IFERROR(($C15-$B15)/$B15,"")) | F15: =IFERROR(IF(ISNUMBER($E15),IF($E15<='Resumen Anual'!$B$22,"✅ OK",IF($E15<='Resumen Anual'!$B$23,"⚠️ Atención","🔴 Alerta")),"—"),"—") -> —
A16: Comisiones de plataformas (delivery) | B16: 0 | C16: 0 | D16: =C16-B16 -> 0 | E16: =IF($B16=0,"",IFERROR(($C16-$B16)/$B16,"")) | F16: =IFERROR(IF(ISNUMBER($E16),IF($E16<='Resumen Anual'!$B$22,"✅ OK",IF($E16<='Resumen Anual'!$B$23,"⚠️ Atención","🔴 Alerta")),"—"),"—") -> —
A17: Alquiler | B17: 0 | C17: 0 | D17: =C17-B17 -> 0 | E17: =IF($B17=0,"",IFERROR(($C17-$B17)/$B17,"")) | F17: =IFERROR(IF(ISNUMBER($E17),IF($E17<='Resumen Anual'!$B$22,"✅ OK",IF($E17<='Resumen Anual'!$B$23,"⚠️ Atención","🔴 Alerta")),"—"),"—") -> —
A18: Suministros | B18: 0 | C18: 0 | D18: =C18-B18 -> 0 | E18: =IF($B18=0,"",IFERROR(($C18-$B18)/$B18,"")) | F18: =IFERROR(IF(ISNUMBER($E18),IF($E18<='Resumen Anual'!$B$22,"✅ OK",IF($E18<='Resumen Anual'!$B$23,"⚠️ Atención","🔴 Alerta")),"—"),"—") -> —
A19: Marketing | B19: 0 | C19: 0 | D19: =C19-B19 -> 0 | E19: =IF($B19=0,"",IFERROR(($C19-$B19)/$B19,"")) | F19: =IFERROR(IF(ISNUMBER($E19),IF($E19<='Resumen Anual'!$B$22,"✅ OK",IF($E19<='Resumen Anual'!$B$23,"⚠️ Atención","🔴 Alerta")),"—"),"—") -> —
A20: Administración / Otros | B20: 0 | C20: 0 | D20: =C20-B20 -> 0 | E20: =IF($B20=0,"",IFERROR(($C20-$B20)/$B20,"")) | F20: =IFERROR(IF(ISNUMBER($E20),IF($E20<='Resumen Anual'!$B$22,"✅ OK",IF($E20<='Resumen Anual'!$B$23,"⚠️ Atención","🔴 Alerta")),"—"),"—") -> —
A21: TOTAL GASTOS | B21: =SUM(B13:B20) -> 0 | C21: =SUM(C13:C20) -> 0 | D21: =C21-B21 -> 0 | E21: =IF($B21=0,"",IFERROR(($C21-$B21)/$B21,"")) | F21: =IFERROR(IF(ISNUMBER($E21),IF($E21<='Resumen Anual'!$B$22,"✅ OK",IF($E21<='Resumen Anual'!$B$23,"⚠️ Atención","🔴 Alerta")),"—"),"—") -> —
A23: EBITDA | B23: =B10-B21 -> 0 | C23: =C10-C21 -> 0 | D23: =C23-B23 -> 0 | E23: =IF($B23=0,"",IFERROR(($C23-$B23)/ABS($B23),"")) | F23: =IFERROR(IF(ISNUMBER($E23),IF($E23>=-'Resumen Anual'!$B$22,"✅ OK",IF($E23>=-'Resumen Anual'!$B$23,"⚠️ Atención","🔴 Alerta")),"—"),"—") -> —
A24: Margen EBITDA % | B24: =IF(B10=0,"",B23/B10) | C24: =IF(C10=0,"",C23/C10) | D24: =IFERROR($C24-$B24,"") | E24: p.p. | F24: =IFERROR(IF(ISNUMBER($D24),IF($D24>=-'Resumen Anual'!$B$24,"✅ OK",IF($D24>=-'Resumen Anual'!$B$25,"⚠️ Atención","🔴 Alerta")),"—"),"—") -> —
A26: RATIOS AUTOMÁTICOS
A27: Food Cost % (sobre ventas de comida) | B27: =IF((B10-B7)<=0,"",B13/(B10-B7)) | C27: =IF((C10-C7)<=0,"",C13/(C10-C7)) | D27: =IFERROR($C27-$B27,"") | E27: p.p. | F27: =IFERROR(IF(ISNUMBER($D27),IF($D27<='Resumen Anual'!$B$24,"✅ OK",IF($D27<='Resumen Anual'!$B$25,"⚠️ Atención","🔴 Alerta")),"—"),"—") -> —
A28: Beverage Cost % (sobre ventas de barra) | B28: =IF(B7=0,"",B14/B7) | C28: =IF(C7=0,"",C14/C7) | D28: =IFERROR($C28-$B28,"") | E28: p.p. | F28: =IFERROR(IF(ISNUMBER($D28),IF($D28<='Resumen Anual'!$B$24,"✅ OK",IF($D28<='Resumen Anual'!$B$25,"⚠️ Atención","🔴 Alerta")),"—"),"—") -> —
A29: Labor Cost % | B29: =IF(B10=0,"",B15/B10) | C29: =IF(C10=0,"",C15/C10) | D29: =IFERROR($C29-$B29,"") | E29: p.p. | F29: =IFERROR(IF(ISNUMBER($D29),IF($D29<='Resumen Anual'!$B$24,"✅ OK",IF($D29<='Resumen Anual'!$B$25,"⚠️ Atención","🔴 Alerta")),"—"),"—") -> —
A30: Prime Cost % (comida + bebida + personal) | B30: =IF(B10=0,"",(B13+B14+B15)/B10) | C30: =IF(C10=0,"",(C13+C14+C15)/C10) | D30: =IFERROR($C30-$B30,"") | E30: p.p. | F30: =IFERROR(IF(ISNUMBER($D30),IF($D30<='Resumen Anual'!$B$24,"✅ OK",IF($D30<='Resumen Anual'!$B$25,"⚠️ Atención","🔴 Alerta")),"—"),"—") -> —
A32: © 2026 AI Chef Pro · aichef.pro

Sheet Jun
A1: P&L Jun — Real vs Presupuesto
A2: AI Chef Pro · aichef.pro — Kit Plan Financiero para Restaurantes
A4: Concepto | B4: Presupuesto (€) | C4: Real (€) | D4: Desviación (€) | E4: Desviación % | F4: Semáforo
A5: INGRESOS
A6: Ventas Comedor (sin IVA) | B6: 0 | C6: 0 | D6: =C6-B6 -> 0 | E6: =IF($B6=0,"",IFERROR(($C6-$B6)/$B6,"")) | F6: =IFERROR(IF(ISNUMBER($E6),IF($E6>=-'Resumen Anual'!$B$22,"✅ OK",IF($E6>=-'Resumen Anual'!$B$23,"⚠️ Atención","🔴 Alerta")),"—"),"—") -> —
A7: Ventas Barra (sin IVA) | B7: 0 | C7: 0 | D7: =C7-B7 -> 0 | E7: =IF($B7=0,"",IFERROR(($C7-$B7)/$B7,"")) | F7: =IFERROR(IF(ISNUMBER($E7),IF($E7>=-'Resumen Anual'!$B$22,"✅ OK",IF($E7>=-'Resumen Anual'!$B$23,"⚠️ Atención","🔴 Alerta")),"—"),"—") -> —
A8: Ventas Delivery (sin IVA) | B8: 0 | C8: 0 | D8: =C8-B8 -> 0 | E8: =IF($B8=0,"",IFERROR(($C8-$B8)/$B8,"")) | F8: =IFERROR(IF(ISNUMBER($E8),IF($E8>=-'Resumen Anual'!$B$22,"✅ OK",IF($E8>=-'Resumen Anual'!$B$23,"⚠️ Atención","🔴 Alerta")),"—"),"—") -> —
A9: Eventos / Catering (sin IVA) | B9: 0 | C9: 0 | D9: =C9-B9 -> 0 | E9: =IF($B9=0,"",IFERROR(($C9-$B9)/$B9,"")) | F9: =IFERROR(IF(ISNUMBER($E9),IF($E9>=-'Resumen Anual'!$B$22,"✅ OK",IF($E9>=-'Resumen Anual'!$B$23,"⚠️ Atención","🔴 Alerta")),"—"),"—") -> —
A10: TOTAL INGRESOS (sin IVA) | B10: =B6+B7+B8+B9 -> 0 | C10: =C6+C7+C8+C9 -> 0 | D10: =C10-B10 -> 0 | E10: =IF($B10=0,"",IFERROR(($C10-$B10)/$B10,"")) | F10: =IFERROR(IF(ISNUMBER($E10),IF($E10>=-'Resumen Anual'!$B$22,"✅ OK",IF($E10>=-'Resumen Anual'!$B$23,"⚠️ Atención","🔴 Alerta")),"—"),"—") -> —
A12: GASTOS
A13: Coste de comida (materia prima) | B13: 0 | C13: 0 | D13: =C13-B13 -> 0 | E13: =IF($B13=0,"",IFERROR(($C13-$B13)/$B13,"")) | F13: =IFERROR(IF(ISNUMBER($E13),IF($E13<='Resumen Anual'!$B$22,"✅ OK",IF($E13<='Resumen Anual'!$B$23,"⚠️ Atención","🔴 Alerta")),"—"),"—") -> —
A14: Coste de bebida (barra) | B14: 0 | C14: 0 | D14: =C14-B14 -> 0 | E14: =IF($B14=0,"",IFERROR(($C14-$B14)/$B14,"")) | F14: =IFERROR(IF(ISNUMBER($E14),IF($E14<='Resumen Anual'!$B$22,"✅ OK",IF($E14<='Resumen Anual'!$B$23,"⚠️ Atención","🔴 Alerta")),"—"),"—") -> —
A15: Personal (Labor) | B15: 0 | C15: 0 | D15: =C15-B15 -> 0 | E15: =IF($B15=0,"",IFERROR(($C15-$B15)/$B15,"")) | F15: =IFERROR(IF(ISNUMBER($E15),IF($E15<='Resumen Anual'!$B$22,"✅ OK",IF($E15<='Resumen Anual'!$B$23,"⚠️ Atención","🔴 Alerta")),"—"),"—") -> —
A16: Comisiones de plataformas (delivery) | B16: 0 | C16: 0 | D16: =C16-B16 -> 0 | E16: =IF($B16=0,"",IFERROR(($C16-$B16)/$B16,"")) | F16: =IFERROR(IF(ISNUMBER($E16),IF($E16<='Resumen Anual'!$B$22,"✅ OK",IF($E16<='Resumen Anual'!$B$23,"⚠️ Atención","🔴 Alerta")),"—"),"—") -> —
A17: Alquiler | B17: 0 | C17: 0 | D17: =C17-B17 -> 0 | E17: =IF($B17=0,"",IFERROR(($C17-$B17)/$B17,"")) | F17: =IFERROR(IF(ISNUMBER($E17),IF($E17<='Resumen Anual'!$B$22,"✅ OK",IF($E17<='Resumen Anual'!$B$23,"⚠️ Atención","🔴 Alerta")),"—"),"—") -> —
A18: Suministros | B18: 0 | C18: 0 | D18: =C18-B18 -> 0 | E18: =IF($B18=0,"",IFERROR(($C18-$B18)/$B18,"")) | F18: =IFERROR(IF(ISNUMBER($E18),IF($E18<='Resumen Anual'!$B$22,"✅ OK",IF($E18<='Resumen Anual'!$B$23,"⚠️ Atención","🔴 Alerta")),"—"),"—") -> —
A19: Marketing | B19: 0 | C19: 0 | D19: =C19-B19 -> 0 | E19: =IF($B19=0,"",IFERROR(($C19-$B19)/$B19,"")) | F19: =IFERROR(IF(ISNUMBER($E19),IF($E19<='Resumen Anual'!$B$22,"✅ OK",IF($E19<='Resumen Anual'!$B$23,"⚠️ Atención","🔴 Alerta")),"—"),"—") -> —
A20: Administración / Otros | B20: 0 | C20: 0 | D20: =C20-B20 -> 0 | E20: =IF($B20=0,"",IFERROR(($C20-$B20)/$B20,"")) | F20: =IFERROR(IF(ISNUMBER($E20),IF($E20<='Resumen Anual'!$B$22,"✅ OK",IF($E20<='Resumen Anual'!$B$23,"⚠️ Atención","🔴 Alerta")),"—"),"—") -> —
A21: TOTAL GASTOS | B21: =SUM(B13:B20) -> 0 | C21: =SUM(C13:C20) -> 0 | D21: =C21-B21 -> 0 | E21: =IF($B21=0,"",IFERROR(($C21-$B21)/$B21,"")) | F21: =IFERROR(IF(ISNUMBER($E21),IF($E21<='Resumen Anual'!$B$22,"✅ OK",IF($E21<='Resumen Anual'!$B$23,"⚠️ Atención","🔴 Alerta")),"—"),"—") -> —
A23: EBITDA | B23: =B10-B21 -> 0 | C23: =C10-C21 -> 0 | D23: =C23-B23 -> 0 | E23: =IF($B23=0,"",IFERROR(($C23-$B23)/ABS($B23),"")) | F23: =IFERROR(IF(ISNUMBER($E23),IF($E23>=-'Resumen Anual'!$B$22,"✅ OK",IF($E23>=-'Resumen Anual'!$B$23,"⚠️ Atención","🔴 Alerta")),"—"),"—") -> —
A24: Margen EBITDA % | B24: =IF(B10=0,"",B23/B10) | C24: =IF(C10=0,"",C23/C10) | D24: =IFERROR($C24-$B24,"") | E24: p.p. | F24: =IFERROR(IF(ISNUMBER($D24),IF($D24>=-'Resumen Anual'!$B$24,"✅ OK",IF($D24>=-'Resumen Anual'!$B$25,"⚠️ Atención","🔴 Alerta")),"—"),"—") -> —
A26: RATIOS AUTOMÁTICOS
A27: Food Cost % (sobre ventas de comida) | B27: =IF((B10-B7)<=0,"",B13/(B10-B7)) | C27: =IF((C10-C7)<=0,"",C13/(C10-C7)) | D27: =IFERROR($C27-$B27,"") | E27: p.p. | F27: =IFERROR(IF(ISNUMBER($D27),IF($D27<='Resumen Anual'!$B$24,"✅ OK",IF($D27<='Resumen Anual'!$B$25,"⚠️ Atención","🔴 Alerta")),"—"),"—") -> —
A28: Beverage Cost % (sobre ventas de barra) | B28: =IF(B7=0,"",B14/B7) | C28: =IF(C7=0,"",C14/C7) | D28: =IFERROR($C28-$B28,"") | E28: p.p. | F28: =IFERROR(IF(ISNUMBER($D28),IF($D28<='Resumen Anual'!$B$24,"✅ OK",IF($D28<='Resumen Anual'!$B$25,"⚠️ Atención","🔴 Alerta")),"—"),"—") -> —
A29: Labor Cost % | B29: =IF(B10=0,"",B15/B10) | C29: =IF(C10=0,"",C15/C10) | D29: =IFERROR($C29-$B29,"") | E29: p.p. | F29: =IFERROR(IF(ISNUMBER($D29),IF($D29<='Resumen Anual'!$B$24,"✅ OK",IF($D29<='Resumen Anual'!$B$25,"⚠️ Atención","🔴 Alerta")),"—"),"—") -> —
A30: Prime Cost % (comida + bebida + personal) | B30: =IF(B10=0,"",(B13+B14+B15)/B10) | C30: =IF(C10=0,"",(C13+C14+C15)/C10) | D30: =IFERROR($C30-$B30,"") | E30: p.p. | F30: =IFERROR(IF(ISNUMBER($D30),IF($D30<='Resumen Anual'!$B$24,"✅ OK",IF($D30<='Resumen Anual'!$B$25,"⚠️ Atención","🔴 Alerta")),"—"),"—") -> —
A32: © 2026 AI Chef Pro · aichef.pro

Sheet Jul
A1: P&L Jul — Real vs Presupuesto
A2: AI Chef Pro · aichef.pro — Kit Plan Financiero para Restaurantes
A4: Concepto | B4: Presupuesto (€) | C4: Real (€) | D4: Desviación (€) | E4: Desviación % | F4: Semáforo
A5: INGRESOS
A6: Ventas Comedor (sin IVA) | B6: 0 | C6: 0 | D6: =C6-B6 -> 0 | E6: =IF($B6=0,"",IFERROR(($C6-$B6)/$B6,"")) | F6: =IFERROR(IF(ISNUMBER($E6),IF($E6>=-'Resumen Anual'!$B$22,"✅ OK",IF($E6>=-'Resumen Anual'!$B$23,"⚠️ Atención","🔴 Alerta")),"—"),"—") -> —
A7: Ventas Barra (sin IVA) | B7: 0 | C7: 0 | D7: =C7-B7 -> 0 | E7: =IF($B7=0,"",IFERROR(($C7-$B7)/$B7,"")) | F7: =IFERROR(IF(ISNUMBER($E7),IF($E7>=-'Resumen Anual'!$B$22,"✅ OK",IF($E7>=-'Resumen Anual'!$B$23,"⚠️ Atención","🔴 Alerta")),"—"),"—") -> —
A8: Ventas Delivery (sin IVA) | B8: 0 | C8: 0 | D8: =C8-B8 -> 0 | E8: =IF($B8=0,"",IFERROR(($C8-$B8)/$B8,"")) | F8: =IFERROR(IF(ISNUMBER($E8),IF($E8>=-'Resumen Anual'!$B$22,"✅ OK",IF($E8>=-'Resumen Anual'!$B$23,"⚠️ Atención","🔴 Alerta")),"—"),"—") -> —
A9: Eventos / Catering (sin IVA) | B9: 0 | C9: 0 | D9: =C9-B9 -> 0 | E9: =IF($B9=0,"",IFERROR(($C9-$B9)/$B9,"")) | F9: =IFERROR(IF(ISNUMBER($E9),IF($E9>=-'Resumen Anual'!$B$22,"✅ OK",IF($E9>=-'Resumen Anual'!$B$23,"⚠️ Atención","🔴 Alerta")),"—"),"—") -> —
A10: TOTAL INGRESOS (sin IVA) | B10: =B6+B7+B8+B9 -> 0 | C10: =C6+C7+C8+C9 -> 0 | D10: =C10-B10 -> 0 | E10: =IF($B10=0,"",IFERROR(($C10-$B10)/$B10,"")) | F10: =IFERROR(IF(ISNUMBER($E10),IF($E10>=-'Resumen Anual'!$B$22,"✅ OK",IF($E10>=-'Resumen Anual'!$B$23,"⚠️ Atención","🔴 Alerta")),"—"),"—") -> —
A12: GASTOS
A13: Coste de comida (materia prima) | B13: 0 | C13: 0 | D13: =C13-B13 -> 0 | E13: =IF($B13=0,"",IFERROR(($C13-$B13)/$B13,"")) | F13: =IFERROR(IF(ISNUMBER($E13),IF($E13<='Resumen Anual'!$B$22,"✅ OK",IF($E13<='Resumen Anual'!$B$23,"⚠️ Atención","🔴 Alerta")),"—"),"—") -> —
A14: Coste de bebida (barra) | B14: 0 | C14: 0 | D14: =C14-B14 -> 0 | E14: =IF($B14=0,"",IFERROR(($C14-$B14)/$B14,"")) | F14: =IFERROR(IF(ISNUMBER($E14),IF($E14<='Resumen Anual'!$B$22,"✅ OK",IF($E14<='Resumen Anual'!$B$23,"⚠️ Atención","🔴 Alerta")),"—"),"—") -> —
A15: Personal (Labor) | B15: 0 | C15: 0 | D15: =C15-B15 -> 0 | E15: =IF($B15=0,"",IFERROR(($C15-$B15)/$B15,"")) | F15: =IFERROR(IF(ISNUMBER($E15),IF($E15<='Resumen Anual'!$B$22,"✅ OK",IF($E15<='Resumen Anual'!$B$23,"⚠️ Atención","🔴 Alerta")),"—"),"—") -> —
A16: Comisiones de plataformas (delivery) | B16: 0 | C16: 0 | D16: =C16-B16 -> 0 | E16: =IF($B16=0,"",IFERROR(($C16-$B16)/$B16,"")) | F16: =IFERROR(IF(ISNUMBER($E16),IF($E16<='Resumen Anual'!$B$22,"✅ OK",IF($E16<='Resumen Anual'!$B$23,"⚠️ Atención","🔴 Alerta")),"—"),"—") -> —
A17: Alquiler | B17: 0 | C17: 0 | D17: =C17-B17 -> 0 | E17: =IF($B17=0,"",IFERROR(($C17-$B17)/$B17,"")) | F17: =IFERROR(IF(ISNUMBER($E17),IF($E17<='Resumen Anual'!$B$22,"✅ OK",IF($E17<='Resumen Anual'!$B$23,"⚠️ Atención","🔴 Alerta")),"—"),"—") -> —
A18: Suministros | B18: 0 | C18: 0 | D18: =C18-B18 -> 0 | E18: =IF($B18=0,"",IFERROR(($C18-$B18)/$B18,"")) | F18: =IFERROR(IF(ISNUMBER($E18),IF($E18<='Resumen Anual'!$B$22,"✅ OK",IF($E18<='Resumen Anual'!$B$23,"⚠️ Atención","🔴 Alerta")),"—"),"—") -> —
A19: Marketing | B19: 0 | C19: 0 | D19: =C19-B19 -> 0 | E19: =IF($B19=0,"",IFERROR(($C19-$B19)/$B19,"")) | F19: =IFERROR(IF(ISNUMBER($E19),IF($E19<='Resumen Anual'!$B$22,"✅ OK",IF($E19<='Resumen Anual'!$B$23,"⚠️ Atención","🔴 Alerta")),"—"),"—") -> —
A20: Administración / Otros | B20: 0 | C20: 0 | D20: =C20-B20 -> 0 | E20: =IF($B20=0,"",IFERROR(($C20-$B20)/$B20,"")) | F20: =IFERROR(IF(ISNUMBER($E20),IF($E20<='Resumen Anual'!$B$22,"✅ OK",IF($E20<='Resumen Anual'!$B$23,"⚠️ Atención","🔴 Alerta")),"—"),"—") -> —
A21: TOTAL GASTOS | B21: =SUM(B13:B20) -> 0 | C21: =SUM(C13:C20) -> 0 | D21: =C21-B21 -> 0 | E21: =IF($B21=0,"",IFERROR(($C21-$B21)/$B21,"")) | F21: =IFERROR(IF(ISNUMBER($E21),IF($E21<='Resumen Anual'!$B$22,"✅ OK",IF($E21<='Resumen Anual'!$B$23,"⚠️ Atención","🔴 Alerta")),"—"),"—") -> —
A23: EBITDA | B23: =B10-B21 -> 0 | C23: =C10-C21 -> 0 | D23: =C23-B23 -> 0 | E23: =IF($B23=0,"",IFERROR(($C23-$B23)/ABS($B23),"")) | F23: =IFERROR(IF(ISNUMBER($E23),IF($E23>=-'Resumen Anual'!$B$22,"✅ OK",IF($E23>=-'Resumen Anual'!$B$23,"⚠️ Atención","🔴 Alerta")),"—"),"—") -> —
A24: Margen EBITDA % | B24: =IF(B10=0,"",B23/B10) | C24: =IF(C10=0,"",C23/C10) | D24: =IFERROR($C24-$B24,"") | E24: p.p. | F24: =IFERROR(IF(ISNUMBER($D24),IF($D24>=-'Resumen Anual'!$B$24,"✅ OK",IF($D24>=-'Resumen Anual'!$B$25,"⚠️ Atención","🔴 Alerta")),"—"),"—") -> —
A26: RATIOS AUTOMÁTICOS
A27: Food Cost % (sobre ventas de comida) | B27: =IF((B10-B7)<=0,"",B13/(B10-B7)) | C27: =IF((C10-C7)<=0,"",C13/(C10-C7)) | D27: =IFERROR($C27-$B27,"") | E27: p.p. | F27: =IFERROR(IF(ISNUMBER($D27),IF($D27<='Resumen Anual'!$B$24,"✅ OK",IF($D27<='Resumen Anual'!$B$25,"⚠️ Atención","🔴 Alerta")),"—"),"—") -> —
A28: Beverage Cost % (sobre ventas de barra) | B28: =IF(B7=0,"",B14/B7) | C28: =IF(C7=0,"",C14/C7) | D28: =IFERROR($C28-$B28,"") | E28: p.p. | F28: =IFERROR(IF(ISNUMBER($D28),IF($D28<='Resumen Anual'!$B$24,"✅ OK",IF($D28<='Resumen Anual'!$B$25,"⚠️ Atención","🔴 Alerta")),"—"),"—") -> —
A29: Labor Cost % | B29: =IF(B10=0,"",B15/B10) | C29: =IF(C10=0,"",C15/C10) | D29: =IFERROR($C29-$B29,"") | E29: p.p. | F29: =IFERROR(IF(ISNUMBER($D29),IF($D29<='Resumen Anual'!$B$24,"✅ OK",IF($D29<='Resumen Anual'!$B$25,"⚠️ Atención","🔴 Alerta")),"—"),"—") -> —
A30: Prime Cost % (comida + bebida + personal) | B30: =IF(B10=0,"",(B13+B14+B15)/B10) | C30: =IF(C10=0,"",(C13+C14+C15)/C10) | D30: =IFERROR($C30-$B30,"") | E30: p.p. | F30: =IFERROR(IF(ISNUMBER($D30),IF($D30<='Resumen Anual'!$B$24,"✅ OK",IF($D30<='Resumen Anual'!$B$25,"⚠️ Atención","🔴 Alerta")),"—"),"—") -> —
A32: © 2026 AI Chef Pro · aichef.pro

Sheet Ago
A1: P&L Ago — Real vs Presupuesto
A2: AI Chef Pro · aichef.pro — Kit Plan Financiero para Restaurantes
A4: Concepto | B4: Presupuesto (€) | C4: Real (€) | D4: Desviación (€) | E4: Desviación % | F4: Semáforo
A5: INGRESOS
A6: Ventas Comedor (sin IVA) | B6: 0 | C6: 0 | D6: =C6-B6 -> 0 | E6: =IF($B6=0,"",IFERROR(($C6-$B6)/$B6,"")) | F6: =IFERROR(IF(ISNUMBER($E6),IF($E6>=-'Resumen Anual'!$B$22,"✅ OK",IF($E6>=-'Resumen Anual'!$B$23,"⚠️ Atención","🔴 Alerta")),"—"),"—") -> —
A7: Ventas Barra (sin IVA) | B7: 0 | C7: 0 | D7: =C7-B7 -> 0 | E7: =IF($B7=0,"",IFERROR(($C7-$B7)/$B7,"")) | F7: =IFERROR(IF(ISNUMBER($E7),IF($E7>=-'Resumen Anual'!$B$22,"✅ OK",IF($E7>=-'Resumen Anual'!$B$23,"⚠️ Atención","🔴 Alerta")),"—"),"—") -> —
A8: Ventas Delivery (sin IVA) | B8: 0 | C8: 0 | D8: =C8-B8 -> 0 | E8: =IF($B8=0,"",IFERROR(($C8-$B8)/$B8,"")) | F8: =IFERROR(IF(ISNUMBER($E8),IF($E8>=-'Resumen Anual'!$B$22,"✅ OK",IF($E8>=-'Resumen Anual'!$B$23,"⚠️ Atención","🔴 Alerta")),"—"),"—") -> —
A9: Eventos / Catering (sin IVA) | B9: 0 | C9: 0 | D9: =C9-B9 -> 0 | E9: =IF($B9=0,"",IFERROR(($C9-$B9)/$B9,"")) | F9: =IFERROR(IF(ISNUMBER($E9),IF($E9>=-'Resumen Anual'!$B$22,"✅ OK",IF($E9>=-'Resumen Anual'!$B$23,"⚠️ Atención","🔴 Alerta")),"—"),"—") -> —
A10: TOTAL INGRESOS (sin IVA) | B10: =B6+B7+B8+B9 -> 0 | C10: =C6+C7+C8+C9 -> 0 | D10: =C10-B10 -> 0 | E10: =IF($B10=0,"",IFERROR(($C10-$B10)/$B10,"")) | F10: =IFERROR(IF(ISNUMBER($E10),IF($E10>=-'Resumen Anual'!$B$22,"✅ OK",IF($E10>=-'Resumen Anual'!$B$23,"⚠️ Atención","🔴 Alerta")),"—"),"—") -> —
A12: GASTOS
A13: Coste de comida (materia prima) | B13: 0 | C13: 0 | D13: =C13-B13 -> 0 | E13: =IF($B13=0,"",IFERROR(($C13-$B13)/$B13,"")) | F13: =IFERROR(IF(ISNUMBER($E13),IF($E13<='Resumen Anual'!$B$22,"✅ OK",IF($E13<='Resumen Anual'!$B$23,"⚠️ Atención","🔴 Alerta")),"—"),"—") -> —
A14: Coste de bebida (barra) | B14: 0 | C14: 0 | D14: =C14-B14 -> 0 | E14: =IF($B14=0,"",IFERROR(($C14-$B14)/$B14,"")) | F14: =IFERROR(IF(ISNUMBER($E14),IF($E14<='Resumen Anual'!$B$22,"✅ OK",IF($E14<='Resumen Anual'!$B$23,"⚠️ Atención","🔴 Alerta")),"—"),"—") -> —
A15: Personal (Labor) | B15: 0 | C15: 0 | D15: =C15-B15 -> 0 | E15: =IF($B15=0,"",IFERROR(($C15-$B15)/$B15,"")) | F15: =IFERROR(IF(ISNUMBER($E15),IF($E15<='Resumen Anual'!$B$22,"✅ OK",IF($E15<='Resumen Anual'!$B$23,"⚠️ Atención","🔴 Alerta")),"—"),"—") -> —
A16: Comisiones de plataformas (delivery) | B16: 0 | C16: 0 | D16: =C16-B16 -> 0 | E16: =IF($B16=0,"",IFERROR(($C16-$B16)/$B16,"")) | F16: =IFERROR(IF(ISNUMBER($E16),IF($E16<='Resumen Anual'!$B$22,"✅ OK",IF($E16<='Resumen Anual'!$B$23,"⚠️ Atención","🔴 Alerta")),"—"),"—") -> —
A17: Alquiler | B17: 0 | C17: 0 | D17: =C17-B17 -> 0 | E17: =IF($B17=0,"",IFERROR(($C17-$B17)/$B17,"")) | F17: =IFERROR(IF(ISNUMBER($E17),IF($E17<='Resumen Anual'!$B$22,"✅ OK",IF($E17<='Resumen Anual'!$B$23,"⚠️ Atención","🔴 Alerta")),"—"),"—") -> —
A18: Suministros | B18: 0 | C18: 0 | D18: =C18-B18 -> 0 | E18: =IF($B18=0,"",IFERROR(($C18-$B18)/$B18,"")) | F18: =IFERROR(IF(ISNUMBER($E18),IF($E18<='Resumen Anual'!$B$22,"✅ OK",IF($E18<='Resumen Anual'!$B$23,"⚠️ Atención","🔴 Alerta")),"—"),"—") -> —
A19: Marketing | B19: 0 | C19: 0 | D19: =C19-B19 -> 0 | E19: =IF($B19=0,"",IFERROR(($C19-$B19)/$B19,"")) | F19: =IFERROR(IF(ISNUMBER($E19),IF($E19<='Resumen Anual'!$B$22,"✅ OK",IF($E19<='Resumen Anual'!$B$23,"⚠️ Atención","🔴 Alerta")),"—"),"—") -> —
A20: Administración / Otros | B20: 0 | C20: 0 | D20: =C20-B20 -> 0 | E20: =IF($B20=0,"",IFERROR(($C20-$B20)/$B20,"")) | F20: =IFERROR(IF(ISNUMBER($E20),IF($E20<='Resumen Anual'!$B$22,"✅ OK",IF($E20<='Resumen Anual'!$B$23,"⚠️ Atención","🔴 Alerta")),"—"),"—") -> —
A21: TOTAL GASTOS | B21: =SUM(B13:B20) -> 0 | C21: =SUM(C13:C20) -> 0 | D21: =C21-B21 -> 0 | E21: =IF($B21=0,"",IFERROR(($C21-$B21)/$B21,"")) | F21: =IFERROR(IF(ISNUMBER($E21),IF($E21<='Resumen Anual'!$B$22,"✅ OK",IF($E21<='Resumen Anual'!$B$23,"⚠️ Atención","🔴 Alerta")),"—"),"—") -> —
A23: EBITDA | B23: =B10-B21 -> 0 | C23: =C10-C21 -> 0 | D23: =C23-B23 -> 0 | E23: =IF($B23=0,"",IFERROR(($C23-$B23)/ABS($B23),"")) | F23: =IFERROR(IF(ISNUMBER($E23),IF($E23>=-'Resumen Anual'!$B$22,"✅ OK",IF($E23>=-'Resumen Anual'!$B$23,"⚠️ Atención","🔴 Alerta")),"—"),"—") -> —
A24: Margen EBITDA % | B24: =IF(B10=0,"",B23/B10) | C24: =IF(C10=0,"",C23/C10) | D24: =IFERROR($C24-$B24,"") | E24: p.p. | F24: =IFERROR(IF(ISNUMBER($D24),IF($D24>=-'Resumen Anual'!$B$24,"✅ OK",IF($D24>=-'Resumen Anual'!$B$25,"⚠️ Atención","🔴 Alerta")),"—"),"—") -> —
A26: RATIOS AUTOMÁTICOS
A27: Food Cost % (sobre ventas de comida) | B27: =IF((B10-B7)<=0,"",B13/(B10-B7)) | C27: =IF((C10-C7)<=0,"",C13/(C10-C7)) | D27: =IFERROR($C27-$B27,"") | E27: p.p. | F27: =IFERROR(IF(ISNUMBER($D27),IF($D27<='Resumen Anual'!$B$24,"✅ OK",IF($D27<='Resumen Anual'!$B$25,"⚠️ Atención","🔴 Alerta")),"—"),"—") -> —
A28: Beverage Cost % (sobre ventas de barra) | B28: =IF(B7=0,"",B14/B7) | C28: =IF(C7=0,"",C14/C7) | D28: =IFERROR($C28-$B28,"") | E28: p.p. | F28: =IFERROR(IF(ISNUMBER($D28),IF($D28<='Resumen Anual'!$B$24,"✅ OK",IF($D28<='Resumen Anual'!$B$25,"⚠️ Atención","🔴 Alerta")),"—"),"—") -> —
A29: Labor Cost % | B29: =IF(B10=0,"",B15/B10) | C29: =IF(C10=0,"",C15/C10) | D29: =IFERROR($C29-$B29,"") | E29: p.p. | F29: =IFERROR(IF(ISNUMBER($D29),IF($D29<='Resumen Anual'!$B$24,"✅ OK",IF($D29<='Resumen Anual'!$B$25,"⚠️ Atención","🔴 Alerta")),"—"),"—") -> —
A30: Prime Cost % (comida + bebida + personal) | B30: =IF(B10=0,"",(B13+B14+B15)/B10) | C30: =IF(C10=0,"",(C13+C14+C15)/C10) | D30: =IFERROR($C30-$B30,"") | E30: p.p. | F30: =IFERROR(IF(ISNUMBER($D30),IF($D30<='Resumen Anual'!$B$24,"✅ OK",IF($D30<='Resumen Anual'!$B$25,"⚠️ Atención","🔴 Alerta")),"—"),"—") -> —
A32: © 2026 AI Chef Pro · aichef.pro

Sheet Sep
A1: P&L Sep — Real vs Presupuesto
A2: AI Chef Pro · aichef.pro — Kit Plan Financiero para Restaurantes
A4: Concepto | B4: Presupuesto (€) | C4: Real (€) | D4: Desviación (€) | E4: Desviación % | F4: Semáforo
A5: INGRESOS
A6: Ventas Comedor (sin IVA) | B6: 0 | C6: 0 | D6: =C6-B6 -> 0 | E6: =IF($B6=0,"",IFERROR(($C6-$B6)/$B6,"")) | F6: =IFERROR(IF(ISNUMBER($E6),IF($E6>=-'Resumen Anual'!$B$22,"✅ OK",IF($E6>=-'Resumen Anual'!$B$23,"⚠️ Atención","🔴 Alerta")),"—"),"—") -> —
A7: Ventas Barra (sin IVA) | B7: 0 | C7: 0 | D7: =C7-B7 -> 0 | E7: =IF($B7=0,"",IFERROR(($C7-$B7)/$B7,"")) | F7: =IFERROR(IF(ISNUMBER($E7),IF($E7>=-'Resumen Anual'!$B$22,"✅ OK",IF($E7>=-'Resumen Anual'!$B$23,"⚠️ Atención","🔴 Alerta")),"—"),"—") -> —
A8: Ventas Delivery (sin IVA) | B8: 0 | C8: 0 | D8: =C8-B8 -> 0 | E8: =IF($B8=0,"",IFERROR(($C8-$B8)/$B8,"")) | F8: =IFERROR(IF(ISNUMBER($E8),IF($E8>=-'Resumen Anual'!$B$22,"✅ OK",IF($E8>=-'Resumen Anual'!$B$23,"⚠️ Atención","🔴 Alerta")),"—"),"—") -> —
A9: Eventos / Catering (sin IVA) | B9: 0 | C9: 0 | D9: =C9-B9 -> 0 | E9: =IF($B9=0,"",IFERROR(($C9-$B9)/$B9,"")) | F9: =IFERROR(IF(ISNUMBER($E9),IF($E9>=-'Resumen Anual'!$B$22,"✅ OK",IF($E9>=-'Resumen Anual'!$B$23,"⚠️ Atención","🔴 Alerta")),"—"),"—") -> —
A10: TOTAL INGRESOS (sin IVA) | B10: =B6+B7+B8+B9 -> 0 | C10: =C6+C7+C8+C9 -> 0 | D10: =C10-B10 -> 0 | E10: =IF($B10=0,"",IFERROR(($C10-$B10)/$B10,"")) | F10: =IFERROR(IF(ISNUMBER($E10),IF($E10>=-'Resumen Anual'!$B$22,"✅ OK",IF($E10>=-'Resumen Anual'!$B$23,"⚠️ Atención","🔴 Alerta")),"—"),"—") -> —
A12: GASTOS
A13: Coste de comida (materia prima) | B13: 0 | C13: 0 | D13: =C13-B13 -> 0 | E13: =IF($B13=0,"",IFERROR(($C13-$B13)/$B13,"")) | F13: =IFERROR(IF(ISNUMBER($E13),IF($E13<='Resumen Anual'!$B$22,"✅ OK",IF($E13<='Resumen Anual'!$B$23,"⚠️ Atención","🔴 Alerta")),"—"),"—") -> —
A14: Coste de bebida (barra) | B14: 0 | C14: 0 | D14: =C14-B14 -> 0 | E14: =IF($B14=0,"",IFERROR(($C14-$B14)/$B14,"")) | F14: =IFERROR(IF(ISNUMBER($E14),IF($E14<='Resumen Anual'!$B$22,"✅ OK",IF($E14<='Resumen Anual'!$B$23,"⚠️ Atención","🔴 Alerta")),"—"),"—") -> —
A15: Personal (Labor) | B15: 0 | C15: 0 | D15: =C15-B15 -> 0 | E15: =IF($B15=0,"",IFERROR(($C15-$B15)/$B15,"")) | F15: =IFERROR(IF(ISNUMBER($E15),IF($E15<='Resumen Anual'!$B$22,"✅ OK",IF($E15<='Resumen Anual'!$B$23,"⚠️ Atención","🔴 Alerta")),"—"),"—") -> —
A16: Comisiones de plataformas (delivery) | B16: 0 | C16: 0 | D16: =C16-B16 -> 0 | E16: =IF($B16=0,"",IFERROR(($C16-$B16)/$B16,"")) | F16: =IFERROR(IF(ISNUMBER($E16),IF($E16<='Resumen Anual'!$B$22,"✅ OK",IF($E16<='Resumen Anual'!$B$23,"⚠️ Atención","🔴 Alerta")),"—"),"—") -> —
A17: Alquiler | B17: 0 | C17: 0 | D17: =C17-B17 -> 0 | E17: =IF($B17=0,"",IFERROR(($C17-$B17)/$B17,"")) | F17: =IFERROR(IF(ISNUMBER($E17),IF($E17<='Resumen Anual'!$B$22,"✅ OK",IF($E17<='Resumen Anual'!$B$23,"⚠️ Atención","🔴 Alerta")),"—"),"—") -> —
A18: Suministros | B18: 0 | C18: 0 | D18: =C18-B18 -> 0 | E18: =IF($B18=0,"",IFERROR(($C18-$B18)/$B18,"")) | F18: =IFERROR(IF(ISNUMBER($E18),IF($E18<='Resumen Anual'!$B$22,"✅ OK",IF($E18<='Resumen Anual'!$B$23,"⚠️ Atención","🔴 Alerta")),"—"),"—") -> —
A19: Marketing | B19: 0 | C19: 0 | D19: =C19-B19 -> 0 | E19: =IF($B19=0,"",IFERROR(($C19-$B19)/$B19,"")) | F19: =IFERROR(IF(ISNUMBER($E19),IF($E19<='Resumen Anual'!$B$22,"✅ OK",IF($E19<='Resumen Anual'!$B$23,"⚠️ Atención","🔴 Alerta")),"—"),"—") -> —
A20: Administración / Otros | B20: 0 | C20: 0 | D20: =C20-B20 -> 0 | E20: =IF($B20=0,"",IFERROR(($C20-$B20)/$B20,"")) | F20: =IFERROR(IF(ISNUMBER($E20),IF($E20<='Resumen Anual'!$B$22,"✅ OK",IF($E20<='Resumen Anual'!$B$23,"⚠️ Atención","🔴 Alerta")),"—"),"—") -> —
A21: TOTAL GASTOS | B21: =SUM(B13:B20) -> 0 | C21: =SUM(C13:C20) -> 0 | D21: =C21-B21 -> 0 | E21: =IF($B21=0,"",IFERROR(($C21-$B21)/$B21,"")) | F21: =IFERROR(IF(ISNUMBER($E21),IF($E21<='Resumen Anual'!$B$22,"✅ OK",IF($E21<='Resumen Anual'!$B$23,"⚠️ Atención","🔴 Alerta")),"—"),"—") -> —
A23: EBITDA | B23: =B10-B21 -> 0 | C23: =C10-C21 -> 0 | D23: =C23-B23 -> 0 | E23: =IF($B23=0,"",IFERROR(($C23-$B23)/ABS($B23),"")) | F23: =IFERROR(IF(ISNUMBER($E23),IF($E23>=-'Resumen Anual'!$B$22,"✅ OK",IF($E23>=-'Resumen Anual'!$B$23,"⚠️ Atención","🔴 Alerta")),"—"),"—") -> —
A24: Margen EBITDA % | B24: =IF(B10=0,"",B23/B10) | C24: =IF(C10=0,"",C23/C10) | D24: =IFERROR($C24-$B24,"") | E24: p.p. | F24: =IFERROR(IF(ISNUMBER($D24),IF($D24>=-'Resumen Anual'!$B$24,"✅ OK",IF($D24>=-'Resumen Anual'!$B$25,"⚠️ Atención","🔴 Alerta")),"—"),"—") -> —
A26: RATIOS AUTOMÁTICOS
A27: Food Cost % (sobre ventas de comida) | B27: =IF((B10-B7)<=0,"",B13/(B10-B7)) | C27: =IF((C10-C7)<=0,"",C13/(C10-C7)) | D27: =IFERROR($C27-$B27,"") | E27: p.p. | F27: =IFERROR(IF(ISNUMBER($D27),IF($D27<='Resumen Anual'!$B$24,"✅ OK",IF($D27<='Resumen Anual'!$B$25,"⚠️ Atención","🔴 Alerta")),"—"),"—") -> —
A28: Beverage Cost % (sobre ventas de barra) | B28: =IF(B7=0,"",B14/B7) | C28: =IF(C7=0,"",C14/C7) | D28: =IFERROR($C28-$B28,"") | E28: p.p. | F28: =IFERROR(IF(ISNUMBER($D28),IF($D28<='Resumen Anual'!$B$24,"✅ OK",IF($D28<='Resumen Anual'!$B$25,"⚠️ Atención","🔴 Alerta")),"—"),"—") -> —
A29: Labor Cost % | B29: =IF(B10=0,"",B15/B10) | C29: =IF(C10=0,"",C15/C10) | D29: =IFERROR($C29-$B29,"") | E29: p.p. | F29: =IFERROR(IF(ISNUMBER($D29),IF($D29<='Resumen Anual'!$B$24,"✅ OK",IF($D29<='Resumen Anual'!$B$25,"⚠️ Atención","🔴 Alerta")),"—"),"—") -> —
A30: Prime Cost % (comida + bebida + personal) | B30: =IF(B10=0,"",(B13+B14+B15)/B10) | C30: =IF(C10=0,"",(C13+C14+C15)/C10) | D30: =IFERROR($C30-$B30,"") | E30: p.p. | F30: =IFERROR(IF(ISNUMBER($D30),IF($D30<='Resumen Anual'!$B$24,"✅ OK",IF($D30<='Resumen Anual'!$B$25,"⚠️ Atención","🔴 Alerta")),"—"),"—") -> —
A32: © 2026 AI Chef Pro · aichef.pro

Sheet Oct
A1: P&L Oct — Real vs Presupuesto
A2: AI Chef Pro · aichef.pro — Kit Plan Financiero para Restaurantes
A4: Concepto | B4: Presupuesto (€) | C4: Real (€) | D4: Desviación (€) | E4: Desviación % | F4: Semáforo
A5: INGRESOS
A6: Ventas Comedor (sin IVA) | B6: 0 | C6: 0 | D6: =C6-B6 -> 0 | E6: =IF($B6=0,"",IFERROR(($C6-$B6)/$B6,"")) | F6: =IFERROR(IF(ISNUMBER($E6),IF($E6>=-'Resumen Anual'!$B$22,"✅ OK",IF($E6>=-'Resumen Anual'!$B$23,"⚠️ Atención","🔴 Alerta")),"—"),"—") -> —
A7: Ventas Barra (sin IVA) | B7: 0 | C7: 0 | D7: =C7-B7 -> 0 | E7: =IF($B7=0,"",IFERROR(($C7-$B7)/$B7,"")) | F7: =IFERROR(IF(ISNUMBER($E7),IF($E7>=-'Resumen Anual'!$B$22,"✅ OK",IF($E7>=-'Resumen Anual'!$B$23,"⚠️ Atención","🔴 Alerta")),"—"),"—") -> —
A8: Ventas Delivery (sin IVA) | B8: 0 | C8: 0 | D8: =C8-B8 -> 0 | E8: =IF($B8=0,"",IFERROR(($C8-$B8)/$B8,"")) | F8: =IFERROR(IF(ISNUMBER($E8),IF($E8>=-'Resumen Anual'!$B$22,"✅ OK",IF($E8>=-'Resumen Anual'!$B$23,"⚠️ Atención","🔴 Alerta")),"—"),"—") -> —
A9: Eventos / Catering (sin IVA) | B9: 0 | C9: 0 | D9: =C9-B9 -> 0 | E9: =IF($B9=0,"",IFERROR(($C9-$B9)/$B9,"")) | F9: =IFERROR(IF(ISNUMBER($E9),IF($E9>=-'Resumen Anual'!$B$22,"✅ OK",IF($E9>=-'Resumen Anual'!$B$23,"⚠️ Atención","🔴 Alerta")),"—"),"—") -> —
A10: TOTAL INGRESOS (sin IVA) | B10: =B6+B7+B8+B9 -> 0 | C10: =C6+C7+C8+C9 -> 0 | D10: =C10-B10 -> 0 | E10: =IF($B10=0,"",IFERROR(($C10-$B10)/$B10,"")) | F10: =IFERROR(IF(ISNUMBER($E10),IF($E10>=-'Resumen Anual'!$B$22,"✅ OK",IF($E10>=-'Resumen Anual'!$B$23,"⚠️ Atención","🔴 Alerta")),"—"),"—") -> —
A12: GASTOS
A13: Coste de comida (materia prima) | B13: 0 | C13: 0 | D13: =C13-B13 -> 0 | E13: =IF($B13=0,"",IFERROR(($C13-$B13)/$B13,"")) | F13: =IFERROR(IF(ISNUMBER($E13),IF($E13<='Resumen Anual'!$B$22,"✅ OK",IF($E13<='Resumen Anual'!$B$23,"⚠️ Atención","🔴 Alerta")),"—"),"—") -> —
A14: Coste de bebida (barra) | B14: 0 | C14: 0 | D14: =C14-B14 -> 0 | E14: =IF($B14=0,"",IFERROR(($C14-$B14)/$B14,"")) | F14: =IFERROR(IF(ISNUMBER($E14),IF($E14<='Resumen Anual'!$B$22,"✅ OK",IF($E14<='Resumen Anual'!$B$23,"⚠️ Atención","🔴 Alerta")),"—"),"—") -> —
A15: Personal (Labor) | B15: 0 | C15: 0 | D15: =C15-B15 -> 0 | E15: =IF($B15=0,"",IFERROR(($C15-$B15)/$B15,"")) | F15: =IFERROR(IF(ISNUMBER($E15),IF($E15<='Resumen Anual'!$B$22,"✅ OK",IF($E15<='Resumen Anual'!$B$23,"⚠️ Atención","🔴 Alerta")),"—"),"—") -> —
A16: Comisiones de plataformas (delivery) | B16: 0 | C16: 0 | D16: =C16-B16 -> 0 | E16: =IF($B16=0,"",IFERROR(($C16-$B16)/$B16,"")) | F16: =IFERROR(IF(ISNUMBER($E16),IF($E16<='Resumen Anual'!$B$22,"✅ OK",IF($E16<='Resumen Anual'!$B$23,"⚠️ Atención","🔴 Alerta")),"—"),"—") -> —
A17: Alquiler | B17: 0 | C17: 0 | D17: =C17-B17 -> 0 | E17: =IF($B17=0,"",IFERROR(($C17-$B17)/$B17,"")) | F17: =IFERROR(IF(ISNUMBER($E17),IF($E17<='Resumen Anual'!$B$22,"✅ OK",IF($E17<='Resumen Anual'!$B$23,"⚠️ Atención","🔴 Alerta")),"—"),"—") -> —
A18: Suministros | B18: 0 | C18: 0 | D18: =C18-B18 -> 0 | E18: =IF($B18=0,"",IFERROR(($C18-$B18)/$B18,"")) | F18: =IFERROR(IF(ISNUMBER($E18),IF($E18<='Resumen Anual'!$B$22,"✅ OK",IF($E18<='Resumen Anual'!$B$23,"⚠️ Atención","🔴 Alerta")),"—"),"—") -> —
A19: Marketing | B19: 0 | C19: 0 | D19: =C19-B19 -> 0 | E19: =IF($B19=0,"",IFERROR(($C19-$B19)/$B19,"")) | F19: =IFERROR(IF(ISNUMBER($E19),IF($E19<='Resumen Anual'!$B$22,"✅ OK",IF($E19<='Resumen Anual'!$B$23,"⚠️ Atención","🔴 Alerta")),"—"),"—") -> —
A20: Administración / Otros | B20: 0 | C20: 0 | D20: =C20-B20 -> 0 | E20: =IF($B20=0,"",IFERROR(($C20-$B20)/$B20,"")) | F20: =IFERROR(IF(ISNUMBER($E20),IF($E20<='Resumen Anual'!$B$22,"✅ OK",IF($E20<='Resumen Anual'!$B$23,"⚠️ Atención","🔴 Alerta")),"—"),"—") -> —
A21: TOTAL GASTOS | B21: =SUM(B13:B20) -> 0 | C21: =SUM(C13:C20) -> 0 | D21: =C21-B21 -> 0 | E21: =IF($B21=0,"",IFERROR(($C21-$B21)/$B21,"")) | F21: =IFERROR(IF(ISNUMBER($E21),IF($E21<='Resumen Anual'!$B$22,"✅ OK",IF($E21<='Resumen Anual'!$B$23,"⚠️ Atención","🔴 Alerta")),"—"),"—") -> —
A23: EBITDA | B23: =B10-B21 -> 0 | C23: =C10-C21 -> 0 | D23: =C23-B23 -> 0 | E23: =IF($B23=0,"",IFERROR(($C23-$B23)/ABS($B23),"")) | F23: =IFERROR(IF(ISNUMBER($E23),IF($E23>=-'Resumen Anual'!$B$22,"✅ OK",IF($E23>=-'Resumen Anual'!$B$23,"⚠️ Atención","🔴 Alerta")),"—"),"—") -> —
A24: Margen EBITDA % | B24: =IF(B10=0,"",B23/B10) | C24: =IF(C10=0,"",C23/C10) | D24: =IFERROR($C24-$B24,"") | E24: p.p. | F24: =IFERROR(IF(ISNUMBER($D24),IF($D24>=-'Resumen Anual'!$B$24,"✅ OK",IF($D24>=-'Resumen Anual'!$B$25,"⚠️ Atención","🔴 Alerta")),"—"),"—") -> —
A26: RATIOS AUTOMÁTICOS
A27: Food Cost % (sobre ventas de comida) | B27: =IF((B10-B7)<=0,"",B13/(B10-B7)) | C27: =IF((C10-C7)<=0,"",C13/(C10-C7)) | D27: =IFERROR($C27-$B27,"") | E27: p.p. | F27: =IFERROR(IF(ISNUMBER($D27),IF($D27<='Resumen Anual'!$B$24,"✅ OK",IF($D27<='Resumen Anual'!$B$25,"⚠️ Atención","🔴 Alerta")),"—"),"—") -> —
A28: Beverage Cost % (sobre ventas de barra) | B28: =IF(B7=0,"",B14/B7) | C28: =IF(C7=0,"",C14/C7) | D28: =IFERROR($C28-$B28,"") | E28: p.p. | F28: =IFERROR(IF(ISNUMBER($D28),IF($D28<='Resumen Anual'!$B$24,"✅ OK",IF($D28<='Resumen Anual'!$B$25,"⚠️ Atención","🔴 Alerta")),"—"),"—") -> —
A29: Labor Cost % | B29: =IF(B10=0,"",B15/B10) | C29: =IF(C10=0,"",C15/C10) | D29: =IFERROR($C29-$B29,"") | E29: p.p. | F29: =IFERROR(IF(ISNUMBER($D29),IF($D29<='Resumen Anual'!$B$24,"✅ OK",IF($D29<='Resumen Anual'!$B$25,"⚠️ Atención","🔴 Alerta")),"—"),"—") -> —
A30: Prime Cost % (comida + bebida + personal) | B30: =IF(B10=0,"",(B13+B14+B15)/B10) | C30: =IF(C10=0,"",(C13+C14+C15)/C10) | D30: =IFERROR($C30-$B30,"") | E30: p.p. | F30: =IFERROR(IF(ISNUMBER($D30),IF($D30<='Resumen Anual'!$B$24,"✅ OK",IF($D30<='Resumen Anual'!$B$25,"⚠️ Atención","🔴 Alerta")),"—"),"—") -> —
A32: © 2026 AI Chef Pro · aichef.pro

Sheet Nov
A1: P&L Nov — Real vs Presupuesto
A2: AI Chef Pro · aichef.pro — Kit Plan Financiero para Restaurantes
A4: Concepto | B4: Presupuesto (€) | C4: Real (€) | D4: Desviación (€) | E4: Desviación % | F4: Semáforo
A5: INGRESOS
A6: Ventas Comedor (sin IVA) | B6: 0 | C6: 0 | D6: =C6-B6 -> 0 | E6: =IF($B6=0,"",IFERROR(($C6-$B6)/$B6,"")) | F6: =IFERROR(IF(ISNUMBER($E6),IF($E6>=-'Resumen Anual'!$B$22,"✅ OK",IF($E6>=-'Resumen Anual'!$B$23,"⚠️ Atención","🔴 Alerta")),"—"),"—") -> —
A7: Ventas Barra (sin IVA) | B7: 0 | C7: 0 | D7: =C7-B7 -> 0 | E7: =IF($B7=0,"",IFERROR(($C7-$B7)/$B7,"")) | F7: =IFERROR(IF(ISNUMBER($E7),IF($E7>=-'Resumen Anual'!$B$22,"✅ OK",IF($E7>=-'Resumen Anual'!$B$23,"⚠️ Atención","🔴 Alerta")),"—"),"—") -> —
A8: Ventas Delivery (sin IVA) | B8: 0 | C8: 0 | D8: =C8-B8 -> 0 | E8: =IF($B8=0,"",IFERROR(($C8-$B8)/$B8,"")) | F8: =IFERROR(IF(ISNUMBER($E8),IF($E8>=-'Resumen Anual'!$B$22,"✅ OK",IF($E8>=-'Resumen Anual'!$B$23,"⚠️ Atención","🔴 Alerta")),"—"),"—") -> —
A9: Eventos / Catering (sin IVA) | B9: 0 | C9: 0 | D9: =C9-B9 -> 0 | E9: =IF($B9=0,"",IFERROR(($C9-$B9)/$B9,"")) | F9: =IFERROR(IF(ISNUMBER($E9),IF($E9>=-'Resumen Anual'!$B$22,"✅ OK",IF($E9>=-'Resumen Anual'!$B$23,"⚠️ Atención","🔴 Alerta")),"—"),"—") -> —
A10: TOTAL INGRESOS (sin IVA) | B10: =B6+B7+B8+B9 -> 0 | C10: =C6+C7+C8+C9 -> 0 | D10: =C10-B10 -> 0 | E10: =IF($B10=0,"",IFERROR(($C10-$B10)/$B10,"")) | F10: =IFERROR(IF(ISNUMBER($E10),IF($E10>=-'Resumen Anual'!$B$22,"✅ OK",IF($E10>=-'Resumen Anual'!$B$23,"⚠️ Atención","🔴 Alerta")),"—"),"—") -> —
A12: GASTOS
A13: Coste de comida (materia prima) | B13: 0 | C13: 0 | D13: =C13-B13 -> 0 | E13: =IF($B13=0,"",IFERROR(($C13-$B13)/$B13,"")) | F13: =IFERROR(IF(ISNUMBER($E13),IF($E13<='Resumen Anual'!$B$22,"✅ OK",IF($E13<='Resumen Anual'!$B$23,"⚠️ Atención","🔴 Alerta")),"—"),"—") -> —
A14: Coste de bebida (barra) | B14: 0 | C14: 0 | D14: =C14-B14 -> 0 | E14: =IF($B14=0,"",IFERROR(($C14-$B14)/$B14,"")) | F14: =IFERROR(IF(ISNUMBER($E14),IF($E14<='Resumen Anual'!$B$22,"✅ OK",IF($E14<='Resumen Anual'!$B$23,"⚠️ Atención","🔴 Alerta")),"—"),"—") -> —
A15: Personal (Labor) | B15: 0 | C15: 0 | D15: =C15-B15 -> 0 | E15: =IF($B15=0,"",IFERROR(($C15-$B15)/$B15,"")) | F15: =IFERROR(IF(ISNUMBER($E15),IF($E15<='Resumen Anual'!$B$22,"✅ OK",IF($E15<='Resumen Anual'!$B$23,"⚠️ Atención","🔴 Alerta")),"—"),"—") -> —
A16: Comisiones de plataformas (delivery) | B16: 0 | C16: 0 | D16: =C16-B16 -> 0 | E16: =IF($B16=0,"",IFERROR(($C16-$B16)/$B16,"")) | F16: =IFERROR(IF(ISNUMBER($E16),IF($E16<='Resumen Anual'!$B$22,"✅ OK",IF($E16<='Resumen Anual'!$B$23,"⚠️ Atención","🔴 Alerta")),"—"),"—") -> —
A17: Alquiler | B17: 0 | C17: 0 | D17: =C17-B17 -> 0 | E17: =IF($B17=0,"",IFERROR(($C17-$B17)/$B17,"")) | F17: =IFERROR(IF(ISNUMBER($E17),IF($E17<='Resumen Anual'!$B$22,"✅ OK",IF($E17<='Resumen Anual'!$B$23,"⚠️ Atención","🔴 Alerta")),"—"),"—") -> —
A18: Suministros | B18: 0 | C18: 0 | D18: =C18-B18 -> 0 | E18: =IF($B18=0,"",IFERROR(($C18-$B18)/$B18,"")) | F18: =IFERROR(IF(ISNUMBER($E18),IF($E18<='Resumen Anual'!$B$22,"✅ OK",IF($E18<='Resumen Anual'!$B$23,"⚠️ Atención","🔴 Alerta")),"—"),"—") -> —
A19: Marketing | B19: 0 | C19: 0 | D19: =C19-B19 -> 0 | E19: =IF($B19=0,"",IFERROR(($C19-$B19)/$B19,"")) | F19: =IFERROR(IF(ISNUMBER($E19),IF($E19<='Resumen Anual'!$B$22,"✅ OK",IF($E19<='Resumen Anual'!$B$23,"⚠️ Atención","🔴 Alerta")),"—"),"—") -> —
A20: Administración / Otros | B20: 0 | C20: 0 | D20: =C20-B20 -> 0 | E20: =IF($B20=0,"",IFERROR(($C20-$B20)/$B20,"")) | F20: =IFERROR(IF(ISNUMBER($E20),IF($E20<='Resumen Anual'!$B$22,"✅ OK",IF($E20<='Resumen Anual'!$B$23,"⚠️ Atención","🔴 Alerta")),"—"),"—") -> —
A21: TOTAL GASTOS | B21: =SUM(B13:B20) -> 0 | C21: =SUM(C13:C20) -> 0 | D21: =C21-B21 -> 0 | E21: =IF($B21=0,"",IFERROR(($C21-$B21)/$B21,"")) | F21: =IFERROR(IF(ISNUMBER($E21),IF($E21<='Resumen Anual'!$B$22,"✅ OK",IF($E21<='Resumen Anual'!$B$23,"⚠️ Atención","🔴 Alerta")),"—"),"—") -> —
A23: EBITDA | B23: =B10-B21 -> 0 | C23: =C10-C21 -> 0 | D23: =C23-B23 -> 0 | E23: =IF($B23=0,"",IFERROR(($C23-$B23)/ABS($B23),"")) | F23: =IFERROR(IF(ISNUMBER($E23),IF($E23>=-'Resumen Anual'!$B$22,"✅ OK",IF($E23>=-'Resumen Anual'!$B$23,"⚠️ Atención","🔴 Alerta")),"—"),"—") -> —
A24: Margen EBITDA % | B24: =IF(B10=0,"",B23/B10) | C24: =IF(C10=0,"",C23/C10) | D24: =IFERROR($C24-$B24,"") | E24: p.p. | F24: =IFERROR(IF(ISNUMBER($D24),IF($D24>=-'Resumen Anual'!$B$24,"✅ OK",IF($D24>=-'Resumen Anual'!$B$25,"⚠️ Atención","🔴 Alerta")),"—"),"—") -> —
A26: RATIOS AUTOMÁTICOS
A27: Food Cost % (sobre ventas de comida) | B27: =IF((B10-B7)<=0,"",B13/(B10-B7)) | C27: =IF((C10-C7)<=0,"",C13/(C10-C7)) | D27: =IFERROR($C27-$B27,"") | E27: p.p. | F27: =IFERROR(IF(ISNUMBER($D27),IF($D27<='Resumen Anual'!$B$24,"✅ OK",IF($D27<='Resumen Anual'!$B$25,"⚠️ Atención","🔴 Alerta")),"—"),"—") -> —
A28: Beverage Cost % (sobre ventas de barra) | B28: =IF(B7=0,"",B14/B7) | C28: =IF(C7=0,"",C14/C7) | D28: =IFERROR($C28-$B28,"") | E28: p.p. | F28: =IFERROR(IF(ISNUMBER($D28),IF($D28<='Resumen Anual'!$B$24,"✅ OK",IF($D28<='Resumen Anual'!$B$25,"⚠️ Atención","🔴 Alerta")),"—"),"—") -> —
A29: Labor Cost % | B29: =IF(B10=0,"",B15/B10) | C29: =IF(C10=0,"",C15/C10) | D29: =IFERROR($C29-$B29,"") | E29: p.p. | F29: =IFERROR(IF(ISNUMBER($D29),IF($D29<='Resumen Anual'!$B$24,"✅ OK",IF($D29<='Resumen Anual'!$B$25,"⚠️ Atención","🔴 Alerta")),"—"),"—") -> —
A30: Prime Cost % (comida + bebida + personal) | B30: =IF(B10=0,"",(B13+B14+B15)/B10) | C30: =IF(C10=0,"",(C13+C14+C15)/C10) | D30: =IFERROR($C30-$B30,"") | E30: p.p. | F30: =IFERROR(IF(ISNUMBER($D30),IF($D30<='Resumen Anual'!$B$24,"✅ OK",IF($D30<='Resumen Anual'!$B$25,"⚠️ Atención","🔴 Alerta")),"—"),"—") -> —
A32: © 2026 AI Chef Pro · aichef.pro

Sheet Dic
A1: P&L Dic — Real vs Presupuesto
A2: AI Chef Pro · aichef.pro — Kit Plan Financiero para Restaurantes
A4: Concepto | B4: Presupuesto (€) | C4: Real (€) | D4: Desviación (€) | E4: Desviación % | F4: Semáforo
A5: INGRESOS
A6: Ventas Comedor (sin IVA) | B6: 0 | C6: 0 | D6: =C6-B6 -> 0 | E6: =IF($B6=0,"",IFERROR(($C6-$B6)/$B6,"")) | F6: =IFERROR(IF(ISNUMBER($E6),IF($E6>=-'Resumen Anual'!$B$22,"✅ OK",IF($E6>=-'Resumen Anual'!$B$23,"⚠️ Atención","🔴 Alerta")),"—"),"—") -> —
A7: Ventas Barra (sin IVA) | B7: 0 | C7: 0 | D7: =C7-B7 -> 0 | E7: =IF($B7=0,"",IFERROR(($C7-$B7)/$B7,"")) | F7: =IFERROR(IF(ISNUMBER($E7),IF($E7>=-'Resumen Anual'!$B$22,"✅ OK",IF($E7>=-'Resumen Anual'!$B$23,"⚠️ Atención","🔴 Alerta")),"—"),"—") -> —
A8: Ventas Delivery (sin IVA) | B8: 0 | C8: 0 | D8: =C8-B8 -> 0 | E8: =IF($B8=0,"",IFERROR(($C8-$B8)/$B8,"")) | F8: =IFERROR(IF(ISNUMBER($E8),IF($E8>=-'Resumen Anual'!$B$22,"✅ OK",IF($E8>=-'Resumen Anual'!$B$23,"⚠️ Atención","🔴 Alerta")),"—"),"—") -> —
A9: Eventos / Catering (sin IVA) | B9: 0 | C9: 0 | D9: =C9-B9 -> 0 | E9: =IF($B9=0,"",IFERROR(($C9-$B9)/$B9,"")) | F9: =IFERROR(IF(ISNUMBER($E9),IF($E9>=-'Resumen Anual'!$B$22,"✅ OK",IF($E9>=-'Resumen Anual'!$B$23,"⚠️ Atención","🔴 Alerta")),"—"),"—") -> —
A10: TOTAL INGRESOS (sin IVA) | B10: =B6+B7+B8+B9 -> 0 | C10: =C6+C7+C8+C9 -> 0 | D10: =C10-B10 -> 0 | E10: =IF($B10=0,"",IFERROR(($C10-$B10)/$B10,"")) | F10: =IFERROR(IF(ISNUMBER($E10),IF($E10>=-'Resumen Anual'!$B$22,"✅ OK",IF($E10>=-'Resumen Anual'!$B$23,"⚠️ Atención","🔴 Alerta")),"—"),"—") -> —
A12: GASTOS
A13: Coste de comida (materia prima) | B13: 0 | C13: 0 | D13: =C13-B13 -> 0 | E13: =IF($B13=0,"",IFERROR(($C13-$B13)/$B13,"")) | F13: =IFERROR(IF(ISNUMBER($E13),IF($E13<='Resumen Anual'!$B$22,"✅ OK",IF($E13<='Resumen Anual'!$B$23,"⚠️ Atención","🔴 Alerta")),"—"),"—") -> —
A14: Coste de bebida (barra) | B14: 0 | C14: 0 | D14: =C14-B14 -> 0 | E14: =IF($B14=0,"",IFERROR(($C14-$B14)/$B14,"")) | F14: =IFERROR(IF(ISNUMBER($E14),IF($E14<='Resumen Anual'!$B$22,"✅ OK",IF($E14<='Resumen Anual'!$B$23,"⚠️ Atención","🔴 Alerta")),"—"),"—") -> —
A15: Personal (Labor) | B15: 0 | C15: 0 | D15: =C15-B15 -> 0 | E15: =IF($B15=0,"",IFERROR(($C15-$B15)/$B15,"")) | F15: =IFERROR(IF(ISNUMBER($E15),IF($E15<='Resumen Anual'!$B$22,"✅ OK",IF($E15<='Resumen Anual'!$B$23,"⚠️ Atención","🔴 Alerta")),"—"),"—") -> —
A16: Comisiones de plataformas (delivery) | B16: 0 | C16: 0 | D16: =C16-B16 -> 0 | E16: =IF($B16=0,"",IFERROR(($C16-$B16)/$B16,"")) | F16: =IFERROR(IF(ISNUMBER($E16),IF($E16<='Resumen Anual'!$B$22,"✅ OK",IF($E16<='Resumen Anual'!$B$23,"⚠️ Atención","🔴 Alerta")),"—"),"—") -> —
A17: Alquiler | B17: 0 | C17: 0 | D17: =C17-B17 -> 0 | E17: =IF($B17=0,"",IFERROR(($C17-$B17)/$B17,"")) | F17: =IFERROR(IF(ISNUMBER($E17),IF($E17<='Resumen Anual'!$B$22,"✅ OK",IF($E17<='Resumen Anual'!$B$23,"⚠️ Atención","🔴 Alerta")),"—"),"—") -> —
A18: Suministros | B18: 0 | C18: 0 | D18: =C18-B18 -> 0 | E18: =IF($B18=0,"",IFERROR(($C18-$B18)/$B18,"")) | F18: =IFERROR(IF(ISNUMBER($E18),IF($E18<='Resumen Anual'!$B$22,"✅ OK",IF($E18<='Resumen Anual'!$B$23,"⚠️ Atención","🔴 Alerta")),"—"),"—") -> —
A19: Marketing | B19: 0 | C19: 0 | D19: =C19-B19 -> 0 | E19: =IF($B19=0,"",IFERROR(($C19-$B19)/$B19,"")) | F19: =IFERROR(IF(ISNUMBER($E19),IF($E19<='Resumen Anual'!$B$22,"✅ OK",IF($E19<='Resumen Anual'!$B$23,"⚠️ Atención","🔴 Alerta")),"—"),"—") -> —
A20: Administración / Otros | B20: 0 | C20: 0 | D20: =C20-B20 -> 0 | E20: =IF($B20=0,"",IFERROR(($C20-$B20)/$B20,"")) | F20: =IFERROR(IF(ISNUMBER($E20),IF($E20<='Resumen Anual'!$B$22,"✅ OK",IF($E20<='Resumen Anual'!$B$23,"⚠️ Atención","🔴 Alerta")),"—"),"—") -> —
A21: TOTAL GASTOS | B21: =SUM(B13:B20) -> 0 | C21: =SUM(C13:C20) -> 0 | D21: =C21-B21 -> 0 | E21: =IF($B21=0,"",IFERROR(($C21-$B21)/$B21,"")) | F21: =IFERROR(IF(ISNUMBER($E21),IF($E21<='Resumen Anual'!$B$22,"✅ OK",IF($E21<='Resumen Anual'!$B$23,"⚠️ Atención","🔴 Alerta")),"—"),"—") -> —
A23: EBITDA | B23: =B10-B21 -> 0 | C23: =C10-C21 -> 0 | D23: =C23-B23 -> 0 | E23: =IF($B23=0,"",IFERROR(($C23-$B23)/ABS($B23),"")) | F23: =IFERROR(IF(ISNUMBER($E23),IF($E23>=-'Resumen Anual'!$B$22,"✅ OK",IF($E23>=-'Resumen Anual'!$B$23,"⚠️ Atención","🔴 Alerta")),"—"),"—") -> —
A24: Margen EBITDA % | B24: =IF(B10=0,"",B23/B10) | C24: =IF(C10=0,"",C23/C10) | D24: =IFERROR($C24-$B24,"") | E24: p.p. | F24: =IFERROR(IF(ISNUMBER($D24),IF($D24>=-'Resumen Anual'!$B$24,"✅ OK",IF($D24>=-'Resumen Anual'!$B$25,"⚠️ Atención","🔴 Alerta")),"—"),"—") -> —
A26: RATIOS AUTOMÁTICOS
A27: Food Cost % (sobre ventas de comida) | B27: =IF((B10-B7)<=0,"",B13/(B10-B7)) | C27: =IF((C10-C7)<=0,"",C13/(C10-C7)) | D27: =IFERROR($C27-$B27,"") | E27: p.p. | F27: =IFERROR(IF(ISNUMBER($D27),IF($D27<='Resumen Anual'!$B$24,"✅ OK",IF($D27<='Resumen Anual'!$B$25,"⚠️ Atención","🔴 Alerta")),"—"),"—") -> —
A28: Beverage Cost % (sobre ventas de barra) | B28: =IF(B7=0,"",B14/B7) | C28: =IF(C7=0,"",C14/C7) | D28: =IFERROR($C28-$B28,"") | E28: p.p. | F28: =IFERROR(IF(ISNUMBER($D28),IF($D28<='Resumen Anual'!$B$24,"✅ OK",IF($D28<='Resumen Anual'!$B$25,"⚠️ Atención","🔴 Alerta")),"—"),"—") -> —
A29: Labor Cost % | B29: =IF(B10=0,"",B15/B10) | C29: =IF(C10=0,"",C15/C10) | D29: =IFERROR($C29-$B29,"") | E29: p.p. | F29: =IFERROR(IF(ISNUMBER($D29),IF($D29<='Resumen Anual'!$B$24,"✅ OK",IF($D29<='Resumen Anual'!$B$25,"⚠️ Atención","🔴 Alerta")),"—"),"—") -> —
A30: Prime Cost % (comida + bebida + personal) | B30: =IF(B10=0,"",(B13+B14+B15)/B10) | C30: =IF(C10=0,"",(C13+C14+C15)/C10) | D30: =IFERROR($C30-$B30,"") | E30: p.p. | F30: =IFERROR(IF(ISNUMBER($D30),IF($D30<='Resumen Anual'!$B$24,"✅ OK",IF($D30<='Resumen Anual'!$B$25,"⚠️ Atención","🔴 Alerta")),"—"),"—") -> —
A32: © 2026 AI Chef Pro · aichef.pro

Sheet Resumen Anual
A1: Resumen Anual — Real vs Presupuesto
A2: AI Chef Pro · aichef.pro — Kit Plan Financiero para Restaurantes
A4: Concepto | B4: Ene | C4: Feb | D4: Mar | E4: Abr | F4: May | G4: Jun | H4: Jul | I4: Ago | J4: Sep | K4: Oct | L4: Nov | M4: Dic | N4: TOTAL
A5: Total Ingresos (Ppto, sin IVA) | B5: ='Ene'!B10 -> 0 | C5: ='Feb'!B10 -> 0 | D5: ='Mar'!B10 -> 0 | E5: ='Abr'!B10 -> 0 | F5: ='May'!B10 -> 0 | G5: ='Jun'!B10 -> 0 | H5: ='Jul'!B10 -> 0 | I5: ='Ago'!B10 -> 0 | J5: ='Sep'!B10 -> 0 | K5: ='Oct'!B10 -> 0 | L5: ='Nov'!B10 -> 0 | M5: ='Dic'!B10 -> 0 | N5: =SUM(B5:M5) -> 0
A6: Total Ingresos (Real, sin IVA) | B6: ='Ene'!C10 -> 0 | C6: ='Feb'!C10 -> 0 | D6: ='Mar'!C10 -> 0 | E6: ='Abr'!C10 -> 0 | F6: ='May'!C10 -> 0 | G6: ='Jun'!C10 -> 0 | H6: ='Jul'!C10 -> 0 | I6: ='Ago'!C10 -> 0 | J6: ='Sep'!C10 -> 0 | K6: ='Oct'!C10 -> 0 | L6: ='Nov'!C10 -> 0 | M6: ='Dic'!C10 -> 0 | N6: =SUM(B6:M6) -> 0
A7: Total Gastos (Ppto) | B7: ='Ene'!B21 -> 0 | C7: ='Feb'!B21 -> 0 | D7: ='Mar'!B21 -> 0 | E7: ='Abr'!B21 -> 0 | F7: ='May'!B21 -> 0 | G7: ='Jun'!B21 -> 0 | H7: ='Jul'!B21 -> 0 | I7: ='Ago'!B21 -> 0 | J7: ='Sep'!B21 -> 0 | K7: ='Oct'!B21 -> 0 | L7: ='Nov'!B21 -> 0 | M7: ='Dic'!B21 -> 0 | N7: =SUM(B7:M7) -> 0
A8: Total Gastos (Real) | B8: ='Ene'!C21 -> 0 | C8: ='Feb'!C21 -> 0 | D8: ='Mar'!C21 -> 0 | E8: ='Abr'!C21 -> 0 | F8: ='May'!C21 -> 0 | G8: ='Jun'!C21 -> 0 | H8: ='Jul'!C21 -> 0 | I8: ='Ago'!C21 -> 0 | J8: ='Sep'!C21 -> 0 | K8: ='Oct'!C21 -> 0 | L8: ='Nov'!C21 -> 0 | M8: ='Dic'!C21 -> 0 | N8: =SUM(B8:M8) -> 0
A9: EBITDA (Ppto) | B9: ='Ene'!B23 -> 0 | C9: ='Feb'!B23 -> 0 | D9: ='Mar'!B23 -> 0 | E9: ='Abr'!B23 -> 0 | F9: ='May'!B23 -> 0 | G9: ='Jun'!B23 -> 0 | H9: ='Jul'!B23 -> 0 | I9: ='Ago'!B23 -> 0 | J9: ='Sep'!B23 -> 0 | K9: ='Oct'!B23 -> 0 | L9: ='Nov'!B23 -> 0 | M9: ='Dic'!B23 -> 0 | N9: =SUM(B9:M9) -> 0
A10: EBITDA (Real) | B10: ='Ene'!C23 -> 0 | C10: ='Feb'!C23 -> 0 | D10: ='Mar'!C23 -> 0 | E10: ='Abr'!C23 -> 0 | F10: ='May'!C23 -> 0 | G10: ='Jun'!C23 -> 0 | H10: ='Jul'!C23 -> 0 | I10: ='Ago'!C23 -> 0 | J10: ='Sep'!C23 -> 0 | K10: ='Oct'!C23 -> 0 | L10: ='Nov'!C23 -> 0 | M10: ='Dic'!C23 -> 0 | N10: =SUM(B10:M10) -> 0
A11: Desviación de ingresos (€) | B11: =B6-B5 -> 0 | C11: =C6-C5 -> 0 | D11: =D6-D5 -> 0 | E11: =E6-E5 -> 0 | F11: =F6-F5 -> 0 | G11: =G6-G5 -> 0 | H11: =H6-H5 -> 0 | I11: =I6-I5 -> 0 | ... M11: =M6-M5 -> 0 | N11: =SUM(B11:M11) -> 0
A12: Desviación de ingresos (%) | B12: =IFERROR((B6-B5)/ABS(B5),"") | C12: =IFERROR((C6-C5)/ABS(C5),"") | D12: =IFERROR((D6-D5)/ABS(D5),"") | E12: =IFERROR((E6-E5)/ABS(E5),"") | F12: =IFERROR((F6-F5)/ABS(F5),"") | G12: =IFERROR((G6-G5)/ABS(G5),"") | H12: =IFERROR((H6-H5)/ABS(H5),"") | I12: =IFERROR((I6-I5)/ABS(I5),"") | ... N12: =IFERROR((N6-N5)/ABS(N5),"")
A13: Desviación de EBITDA (€) | B13: =B10-B9 -> 0 | C13: =C10-C9 -> 0 | D13: =D10-D9 -> 0 | E13: =E10-E9 -> 0 | F13: =F10-F9 -> 0 | G13: =G10-G9 -> 0 | H13: =H10-H9 -> 0 | I13: =I10-I9 -> 0 | ... M13: =M10-M9 -> 0 | N13: =SUM(B13:M13) -> 0
A14: Coste de comida (real, €) | B14: ='Ene'!C13 -> 0 | C14: ='Feb'!C13 -> 0 | D14: ='Mar'!C13 -> 0 | E14: ='Abr'!C13 -> 0 | F14: ='May'!C13 -> 0 | G14: ='Jun'!C13 -> 0 | H14: ='Jul'!C13 -> 0 | I14: ='Ago'!C13 -> 0 | J14: ='Sep'!C13 -> 0 | K14: ='Oct'!C13 -> 0 | L14: ='Nov'!C13 -> 0 | M14: ='Dic'!C13 -> 0 | N14: =SUM(B14:M14) -> 0
A15: Coste de bebida (real, €) | B15: ='Ene'!C14 -> 0 | C15: ='Feb'!C14 -> 0 | D15: ='Mar'!C14 -> 0 | E15: ='Abr'!C14 -> 0 | F15: ='May'!C14 -> 0 | G15: ='Jun'!C14 -> 0 | H15: ='Jul'!C14 -> 0 | I15: ='Ago'!C14 -> 0 | J15: ='Sep'!C14 -> 0 | K15: ='Oct'!C14 -> 0 | L15: ='Nov'!C14 -> 0 | M15: ='Dic'!C14 -> 0 | N15: =SUM(B15:M15) -> 0
A16: Personal — Labor (real, €) | B16: ='Ene'!C15 -> 0 | C16: ='Feb'!C15 -> 0 | D16: ='Mar'!C15 -> 0 | E16: ='Abr'!C15 -> 0 | F16: ='May'!C15 -> 0 | G16: ='Jun'!C15 -> 0 | H16: ='Jul'!C15 -> 0 | I16: ='Ago'!C15 -> 0 | J16: ='Sep'!C15 -> 0 | K16: ='Oct'!C15 -> 0 | L16: ='Nov'!C15 -> 0 | M16: ='Dic'!C15 -> 0 | N16: =SUM(B16:M16) -> 0
A17: Prime Cost (real, €) | B17: =B14+B15+B16 -> 0 | C17: =C14+C15+C16 -> 0 | D17: =D14+D15+D16 -> 0 | E17: =E14+E15+E16 -> 0 | F17: =F14+F15+F16 -> 0 | G17: =G14+G15+G16 -> 0 | H17: =H14+H15+H16 -> 0 | I17: =I14+I15+I16 -> 0 | ... M17: =M14+M15+M16 -> 0 | N17: =SUM(B17:M17) -> 0
A18: Prime Cost % (real) | B18: =IF(B6=0,"",B17/B6) | C18: =IF(C6=0,"",C17/C6) | D18: =IF(D6=0,"",D17/D6) | E18: =IF(E6=0,"",E17/E6) | F18: =IF(F6=0,"",F17/F6) | G18: =IF(G6=0,"",G17/G6) | H18: =IF(H6=0,"",H17/H6) | I18: =IF(I6=0,"",I17/I6) | ... N18: =IF(N6=0,"",N17/N6)
A21: TOLERANCIAS DEL SEMÁFORO (edítalas si tu negocio manda)
A22: Desviación tolerada — verde (± % sobre presupuesto) | B22: 0.05
A23: Desviación de atención — ámbar (± %) | B23: 0.1
A24: Desviación tolerada en ratios — verde (p.p.) | B24: 0.02
A25: Desviación de atención en ratios — ámbar (p.p.) | B25: 0.05
A45: © 2026 AI Chef Pro · aichef.pro
