Workbook

Sheet Instrucciones
B2: 07 · Informe de Viabilidad — Presentación Bancaria
B4: AI Chef Pro · aichef.pro — Kit Plan Financiero para Restaurantes
B6: Cómo usar esta plantilla:
B7: ▸ Completa cada pestaña con los datos de tu proyecto.
B8: ▸ El formato profesional está listo para presentar directamente al banco.
B9: ▸ TIR, VAN y Payback se calculan solos en Proyecciones sobre el FLUJO LIBRE DEL PROYECTO (sin deuda ni intereses) y la inversión del Resumen Ejecutivo; la capacidad de pagar el préstamo la mide el DSCR de Ratios. La tasa de descuento es tuya (celda C27).
B10: ▸ Incluye sección de garantías y avales.
B12: Pestañas:
B13: ▸ Resumen Ejecutivo: datos clave del proyecto.
B14: ▸ Proyecciones: P&L + Cash Flow resumido 5 años.
B15: ▸ Financiación: cuadro de amortización del préstamo. De ahí salen los intereses del P&L, la cuota del DSCR y la línea de cuota de la tesorería del 03.
B16: ▸ Ratios: indicadores de solvencia y rentabilidad. El DSCR compara el flujo libre del proyecto del año 1 (Proyecciones, fila 17) con el servicio de deuda de ese año (Financiación): mide si el negocio paga la cuota.
... B25: Versión 2.0 · agosto 2026 · aichef.pro/kit-plan-financiero · info@aichef.pro

Sheet Resumen Ejecutivo
B1: Resumen Ejecutivo del Proyecto
B2: AI Chef Pro · aichef.pro — Kit Plan Financiero para Restaurantes
B3: VALORES DE EJEMPLO — sustitúyelos por los tuyos
B4: DATOS DEL PROYECTO
B5: Nombre del restaurante
B6: Concepto / Tipo de cocina
B7: Ubicación
B8: Superficie total (m²)
B9: Aforo (cubiertos)
B10: Fecha prevista de apertura
B12: DATOS FINANCIEROS CLAVE
B13: Inversión total necesaria
B14: Fondos propios aportados
B15: Financiación solicitada | C15: ='Financiación'!$C$4 -> 0
B16: Plazo de amortización solicitado | C16: =IF('Financiación'!$C$4=0,"—",'Financiación'!$C$6) -> —
B17: Facturación prevista Año 1 (sin IVA) | C17: =Proyecciones!$B$4 -> 0
B18: EBITDA previsto Año 1 | C18: =Proyecciones!$B$11 -> 0
B19: Payback estimado | C19: =Proyecciones!$B$26 -> —
B21: EQUIPO PROMOTOR
B22: Nombre del promotor/a
B23: Experiencia en hostelería
B24: Formación
B25: Otros socios
A27: © 2026 AI Chef Pro · aichef.pro
B29: Financiación, plazo, facturación, EBITDA y payback se calculan solos desde Financiación y Proyecciones: no se teclean dos veces.

Sheet Proyecciones
A1: Proyecciones Financieras — 5 Años
A3: Concepto | B3: Año 1 | C3: Año 2 | D3: Año 3 | E3: Año 4 | F3: Año 5
A4: Facturación (sin IVA) | B4: 0 | C4: 0 | D4: 0 | E4: 0 | F4: 0
A5: Coste de comida | B5: 0 | C5: 0 | D5: 0 | E5: 0 | F5: 0
A6: Coste de bebida | B6: 0 | C6: 0 | D6: 0 | E6: 0 | F6: 0
A7: Personal | B7: 0 | C7: 0 | D7: 0 | E7: 0 | F7: 0
A8: Comisiones de plataformas (delivery) | B8: 0 | C8: 0 | D8: 0 | E8: 0 | F8: 0
A9: Otros gastos operativos | B9: 0 | C9: 0 | D9: 0 | E9: 0 | F9: 0
A10: TOTAL GASTOS | B10: =SUM(B5:B9) -> 0 | C10: =SUM(C5:C9) -> 0 | D10: =SUM(D5:D9) -> 0 | E10: =SUM(E5:E9) -> 0 | F10: =SUM(F5:F9) -> 0
A11: EBITDA | B11: =B4-B10 -> 0 | C11: =C4-C10 -> 0 | D11: =D4-D10 -> 0 | E11: =E4-E10 -> 0 | F11: =F4-F10 -> 0
A12: Amortización | B12: 0 | C12: 0 | D12: 0 | E12: 0 | F12: 0 | G12: Cópiala de 04!Resumen, columna «Dotación anual (€)» de la fila INVERSIÓN TOTAL.
A13: Intereses de la deuda | B13: ='Financiación'!$D$12 -> 0 | C13: ='Financiación'!$D$13 -> 0 | D13: ='Financiación'!$D$14 -> 0 | E13: ='Financiación'!$D$15 -> 0 | F13: ='Financiación'!$D$16 -> 0
A14: BAI (Beneficio Antes de Impuestos) | B14: =B11-B12-B13 -> 0 | C14: =C11-C12-C13 -> 0 | D14: =D11-D12-D13 -> 0 | E14: =E11-E12-E13 -> 0 | F14: =F11-F12-F13 -> 0
A15: Impuesto sobre Sociedades | B15: =IF(B14>0,B14*$C$29,0) -> 0 | C15: =IF(C14>0,C14*$C$29,0) -> 0 | D15: =IF(D14>0,D14*$C$29,0) -> 0 | E15: =IF(E14>0,E14*$C$29,0) -> 0 | F15: =IF(F14>0,F14*$C$29,0) -> 0
A16: BENEFICIO NETO | B16: =B14-B15 -> 0 | C16: =C14-C15 -> 0 | D16: =D14-D15 -> 0 | E16: =E14-E15 -> 0 | F16: =F14-F15 -> 0
A17: Flujo libre del proyecto (sin deuda) | B17: =B11-MAX(0,(B11-B12)*$C$29) -> 0 | C17: =C11-MAX(0,(C11-C12)*$C$29) -> 0 | D17: =D11-MAX(0,(D11-D12)*$C$29) -> 0 | E17: =E11-MAX(0,(E11-E12)*$C$29) -> 0 | F17: =F11-MAX(0,(F11-F12)*$C$29) -> 0 | G17: EBITDA menos el Impuesto de Sociedades calculado SIN intereses. Es la fila que alimenta la TIR, el VAN y el payback de abajo.
A18: CASH FLOW OPERATIVO | B18: =B16+B12 -> 0 | C18: =C16+C12 -> 0 | D18: =D16+D12 -> 0 | E18: =E16+E12 -> 0 | F18: =F16+F12 -> 0
A20: FLUJOS DEL PROYECTO E INDICADORES DE RENTABILIDAD
A21: Concepto | B21: Año 0 | C21: Año 1 | D21: Año 2 | E21: Año 3 | F21: Año 4 | G21: Año 5
A22: Flujo de caja del proyecto | B22: =-'Resumen Ejecutivo'!$C$13 -> 0 | C22: =B17 -> 0 | D22: =C17 -> 0 | E22: =D17 -> 0 | F22: =E17 -> 0 | G22: =F17 -> 0
A23: Flujo acumulado | B23: =B22 -> 0 | C23: =$B23+C22 -> 0 | D23: =$C23+D22 -> 0 | E23: =$D23+E22 -> 0 | F23: =$E23+F22 -> 0 | G23: =$F23+G22 -> 0
A24: TIR del proyecto (sin apalancamiento) | B24: =IFERROR(IRR($B$22:$G$22),"—") -> —
A25: VAN del proyecto | B25: =IFERROR(NPV($C$27,$C$22:$G$22)+$B$22,"—") -> 0
A26: Payback del proyecto (años) | B26: =IFERROR(IF($G$23<0,"No se recupera en 5 años",COUNTIF($B$23:$G$23,"<0")-1+(-INDEX($B$23:$G$23,COUNTIF($B$23:$G$23,"<0")))/INDEX($B$22:$G$22,COUNTIF($B$23:$G$23,"<0")+1)),"—") -> —
A27: Tasa de descuento anual (%) — la usa el VAN | C27: 0.08
A28: Es el coste de capital que exige quien pone el dinero. Un 8 % es la referencia habitual en hostelería; súbela si tu riesgo es mayor.
A29: Tipo del Impuesto sobre Sociedades (%) | C29: 0.25
A30: Tipo general 25 %. Entidad de NUEVA CREACIÓN: 15 % los dos primeros ejercicios con base positiva (art. 29.1 LIS). Si tributas por IRPF (autónomo), pon 0 aquí y calcula el IRPF fuera.
A32: La inversión del año 0 sale del Resumen Ejecutivo: este informe se entrega a un tercero y ningún dato de ejemplo queda precargado con aspecto de dato real.
A33: TIR/VAN/payback se calculan sobre el flujo libre del proyecto, sin deuda ni intereses: miden si el negocio se sostiene por sí mismo. La capacidad de pagar el préstamo se mide con el DSCR de la hoja Ratios.
A45: © 2026 AI Chef Pro · aichef.pro

Sheet Financiación
B1: Financiación — Cuadro de Amortización
B2: AI Chef Pro · aichef.pro — Kit Plan Financiero para Restaurantes
B3: DATOS DEL PRÉSTAMO
B4: Importe solicitado (€) | C4: 0 | D4: El que pides al banco.
B5: Tipo de interés nominal anual (%) | C5: 0.06 | D5: TIN, no TAE. (valor orientativo — cámbialo)
B6: Plazo (años) | C6: 8 | D6: Plazo TOTAL, carencia incluida. (valor orientativo — cámbialo)
B7: Carencia de capital (años) | C7: 0 | D7: Años iniciales en los que sólo pagas intereses; después la cuota se calcula sobre el plazo restante.
B8: CUOTA ANUAL (€) | C8: =IF(($C$6-$C$7)<=0,"La carencia no puede igualar ni superar el plazo",IFERROR($C$4*$C$5/(1-(1+$C$5)^(-($C$6-$C$7))),0)) -> 0 | D8: Anualidad constante (sistema francés), calculada sobre el plazo posterior a la carencia. La carencia tiene que ser MENOR que el plazo: si no, no queda ningún año sobre el que repartir el capital y aquí sale un aviso en vez de una cifra.
B10: CUADRO DE AMORTIZACIÓN (años 1-5)
A11: Año | B11: Capital pendiente inicio (€) | C11: Cuota anual (€) | D11: Intereses (€) | E11: Amortización de capital (€) | F11: Capital pendiente fin (€)
A12: 1 | B12: =$C$4 -> 0 | C12: =IF($C$6<=$C$7,"—",IF($A12>$C$6,0,IF($A12<=$C$7,$B12*$C$5,$C$8))) -> 0 | D12: =IF($A12>$C$6,0,$B12*$C$5) -> 0 | E12: =IF($C$6<=$C$7,0,IF($A12>$C$6,0,$C12-$D12)) -> 0 | F12: =$B12-$E12 -> 0
A13: 2 | B13: =$F$12 -> 0 | C13: =IF($C$6<=$C$7,"—",IF($A13>$C$6,0,IF($A13<=$C$7,$B13*$C$5,$C$8))) -> 0 | D13: =IF($A13>$C$6,0,$B13*$C$5) -> 0 | E13: =IF($C$6<=$C$7,0,IF($A13>$C$6,0,$C13-$D13)) -> 0 | F13: =$B13-$E13 -> 0
A14: 3 | B14: =$F$13 -> 0 | C14: =IF($C$6<=$C$7,"—",IF($A14>$C$6,0,IF($A14<=$C$7,$B14*$C$5,$C$8))) -> 0 | D14: =IF($A14>$C$6,0,$B14*$C$5) -> 0 | E14: =IF($C$6<=$C$7,0,IF($A14>$C$6,0,$C14-$D14)) -> 0 | F14: =$B14-$E14 -> 0
A15: 4 | B15: =$F$14 -> 0 | C15: =IF($C$6<=$C$7,"—",IF($A15>$C$6,0,IF($A15<=$C$7,$B15*$C$5,$C$8))) -> 0 | D15: =IF($A15>$C$6,0,$B15*$C$5) -> 0 | E15: =IF($C$6<=$C$7,0,IF($A15>$C$6,0,$C15-$D15)) -> 0 | F15: =$B15-$E15 -> 0
A16: 5 | B16: =$F$15 -> 0 | C16: =IF($C$6<=$C$7,"—",IF($A16>$C$6,0,IF($A16<=$C$7,$B16*$C$5,$C$8))) -> 0 | D16: =IF($A16>$C$6,0,$B16*$C$5) -> 0 | E16: =IF($C$6<=$C$7,0,IF($A16>$C$6,0,$C16-$D16)) -> 0 | F16: =$B16-$E16 -> 0
B18: La cuota de la columna C es la que se copia a 03!«Flujo Mensual», fila 23 (dividida entre 12), y la que divide el DSCR de la pestaña Ratios.
B19: Los intereses de la columna D alimentan la fila «Intereses de la deuda» de Proyecciones: no los teclees dos veces.
B20: Con carencia, los primeros años la columna «Amortización de capital» sale a 0 y el capital pendiente no baja: es lo que de verdad pasa en un ICO de apertura.
A22: © 2026 AI Chef Pro · aichef.pro

Sheet Ratios
B1: Ratios de Solvencia y Rentabilidad
B3: Ratio | C3: Valor | D3: Referencia Bancaria | E3: Estado | F3: Óptimo (nº) | G3: Límite (nº) | H3: Sentido
B4: Ratio de endeudamiento | C4: =IFERROR($C$16/($C$16+$C$15),"Indica deuda y fondos propios") -> Indica deuda y fondos propios | D4: < 60% | E4: =IFERROR(IF(ISNUMBER($C4),IF($C4<=$F$4,"✅",IF($C4<=$G$4,"⚠️","🔴")),"—"),"—") -> — | F4: 0.6 | G4: 0.7 | H4: menor es mejor
B5: Cobertura de deuda (DSCR) | C5: =IFERROR(Proyecciones!$B$17/'Financiación'!$C$12,"Indica el préstamo") -> Indica el préstamo | D5: > 1.25x | E5: =IFERROR(IF(ISNUMBER($C5),IF($C5>=$F$5,"✅",IF($C5>=$G$5,"⚠️","🔴")),"—"),"—") -> — | F5: 1.25 | G5: 1.15 | H5: mayor es mejor
B6: Ratio de liquidez corriente | C6: =IFERROR($C$13/$C$14,"Indica el balance") -> Indica el balance | D6: > 1.0x | E6: =IFERROR(IF(ISNUMBER($C6),IF($C6>=$F$6,"✅",IF($C6>=$G$6,"⚠️","🔴")),"—"),"—") -> — | F6: 1 | G6: 0.9 | H6: mayor es mejor
B7: Margen EBITDA / Ventas | C7: =IFERROR(Proyecciones!$B$11/Proyecciones!$B$4,"Indica la facturación") -> Indica la facturación | D7: > 15% | E7: =IFERROR(IF(ISNUMBER($C7),IF($C7>=$F$7,"✅",IF($C7>=$G$7,"⚠️","🔴")),"—"),"—") -> — | F7: 0.15 | G7: 0.1 | H7: mayor es mejor
B8: ROI (Return on Investment) | C8: =IFERROR(Proyecciones!$B$16/$C$17,"Indica la inversión") -> Indica la inversión | D8: > 10% | E8: =IFERROR(IF(ISNUMBER($C8),IF($C8>=$F$8,"✅",IF($C8>=$G$8,"⚠️","🔴")),"—"),"—") -> — | F8: 0.1 | G8: 0.05 | H8: mayor es mejor
B9: Fondos propios / Inversión | C9: =IFERROR($C$15/$C$17,"Indica la inversión") -> Indica la inversión | D9: > 30% | E9: =IFERROR(IF(ISNUMBER($C9),IF($C9>=$F$9,"✅",IF($C9>=$G$9,"⚠️","🔴")),"—"),"—") -> — | F9: 0.3 | G9: 0.2 | H9: mayor es mejor
B10: Deuda / EBITDA | C10: =IFERROR($C$16/Proyecciones!$B$11,"Indica el EBITDA") -> Indica el EBITDA | D10: < 3.5x | E10: =IFERROR(IF(ISNUMBER($C10),IF($C10<=$F$10,"✅",IF($C10<=$G$10,"⚠️","🔴")),"—"),"—") -> — | F10: 3.5 | G10: 4.5 | H10: menor es mejor
B12: DATOS DE BALANCE Y DEUDA
B13: Activo corriente (€) | C13: 0
B14: Pasivo corriente (€) | C14: 0
B15: Fondos propios (€) | C15: 0
B16: Deuda financiera viva (€) | C16: 0
B17: Inversión total del proyecto (€) | C17: ='Resumen Ejecutivo'!$C$13 -> 0
B20: El margen EBITDA usa los MISMOS umbrales que el dashboard 06 (óptimo > 15 %, ajustado 10-15 %): antes este informe pedía «> 12 %» y el mismo restaurante aprobaba en un libro y quedaba en ámbar en el otro.
B21: El DSCR divide el FLUJO LIBRE DEL PROYECTO del año 1 (Proyecciones, fila 17: EBITDA menos el Impuesto sobre Sociedades, antes de intereses) entre el servicio de deuda de ese mismo año (Financiación, columna «Cuota anual», año 1). El numerador va ANTES de la deuda a propósito: si le restaras los intereses, estarías descontándolos dos veces.
A24: © 2026 AI Chef Pro · aichef.pro

Sheet Garantías
B1: Garantías y Avales Ofrecidos
B3: Tipo de Garantía | C3: Valor (€) | D3: Descripción
B4: Aval personal del promotor | C4: 0
B5: Hipoteca sobre local (si propiedad) | C5: 0
B6: Pignoración de depósitos | C6: 0
B7: Aval SGR (Sociedad de Garantía Recíproca) | C7: 0
B8: Seguro de caución | C8: 0
B9: Fianza / depósito adicional | C9: 0
B10: TOTAL GARANTÍAS | C10: =SUM(C4:C9) -> 0
A13: © 2026 AI Chef Pro · aichef.pro
