Workbook

Sheet Instrucciones
B2: BONUS 08 · Simulador What-If de Escenarios
B4: AI Chef Pro · aichef.pro — Kit Plan Financiero para Restaurantes
B6: Cómo usar esta plantilla:
B7: ▸ Cambia los valores de Ticket medio, Cubiertos / día y Food Cost en la zona de inputs.
B8: ▸ El P&L se recalcula instantáneamente para cada escenario.
B9: ▸ Compara 3 escenarios lado a lado: Pesimista, Base, Optimista.
B11: Ideal para:
B12: ▸ Preparar planes de contingencia.
B13: ▸ Negociar con inversores o socios.
B14: ▸ Evaluar el impacto de subidas de precios o cambios de carta.
B16: Todas las cifras van SIN IVA; en el 03 (tesorería) van CON IVA porque es caja.
B17: Para editar una celda que no esté en verde: Revisar → Desproteger hoja (no tiene contraseña).
... B19: Versión 2.0 · agosto 2026 · aichef.pro/kit-plan-financiero · info@aichef.pro

Sheet Simulador
A1: Simulador de Escenarios — What If
A2: AI Chef Pro · aichef.pro — Kit Plan Financiero para Restaurantes
A3: VALORES DE EJEMPLO — sustitúyelos por los tuyos
A4: Variable / Resultado | B4: Pesimista | C4: Base | D4: Optimista
A5: VARIABLES DE ENTRADA
A6: Ticket medio (€, sin IVA) | B6: 18 | C6: 22 | D6: 28
A7: Cubiertos / día | B7: 40 | C7: 55 | D7: 75
A8: Días apertura / mes | B8: 25 | C8: 26 | D8: 27
A9: % Coste variable (food + comisiones de delivery) | B9: 0.4 | C9: 0.35 | D9: 0.3
A10: Labor Cost % | B10: 0.32 | C10: 0.28 | D10: 0.25
A11: Costes fijos mensuales SIN personal y SIN cuota de préstamo (alquiler, suministros, seguros, marketing, gestoría, otros) | B11: 6500 | C11: 6200 | D11: 5900
A12: Si copias los costes fijos del 02, RESTA antes las nóminas y la cuota: el personal ya entra arriba como % sobre ventas y el EBITDA se mide antes del servicio de deuda.
A13: P&L MENSUAL SIMULADO
A14: Facturación mensual (sin IVA) | B14: =B6*B7*B8 -> 18000 | C14: =C6*C7*C8 -> 31460 | D14: =D6*D7*D8 -> 56700
A15: Food Cost (€) | B15: =B14*B9 -> 7200 | C15: =C14*C9 -> 11011 | D15: =D14*D9 -> 17010
A16: Labor Cost (€) | B16: =B14*B10 -> 5760 | C16: =C14*C10 -> 8808.8 | D16: =D14*D10 -> 14175
A17: Costes fijos (€) | B17: =B11 -> 6500 | C17: =C11 -> 6200 | D17: =D11 -> 5900
A18: TOTAL GASTOS | B18: =B15+B16+B17 -> 19460 | C18: =C15+C16+C17 -> 26019.8 | D18: =D15+D16+D17 -> 37085
A19: EBITDA MENSUAL | B19: =B14-B18 -> -1460 | C19: =C14-C18 -> 5440.2 | D19: =D14-D18 -> 19615
A20: Margen EBITDA % | B20: =IF(B14=0,"",B19/B14) -> -0.081111111 | C20: =IF(C14=0,"",C19/C14) -> 0.17292435 | D20: =IF(D14=0,"",D19/D14) -> 0.34594356
A21: EBITDA ANUAL | B21: =B19*12 -> -17520 | C21: =C19*12 -> 65282.4 | D21: =D19*12 -> 235380
A22: Base común con el 02: mismo ticket (22 €), mismos cubiertos/día (55), mismos días (26), mismo % de coste variable (35 %) y los mismos costes fijos sin personal (6.200 €). El EBITDA base coincide: ~17 % sobre ventas en los dos libros.
A24: © 2026 AI Chef Pro · aichef.pro

Sheet Comparativa
B1: Comparativa de Escenarios — Resumen Anual
B3: Indicador | C3: Pesimista | D3: Base | E3: Optimista
B4: Facturación anual (sin IVA) | C4: =Simulador!B14*12 -> 216000 | D4: =Simulador!C14*12 -> 377520 | E4: =Simulador!D14*12 -> 680400
B5: Food Cost anual | C5: =Simulador!B15*12 -> 86400 | D5: =Simulador!C15*12 -> 132132 | E5: =Simulador!D15*12 -> 204120
B6: Labor Cost anual | C6: =Simulador!B16*12 -> 69120 | D6: =Simulador!C16*12 -> 105705.6 | E6: =Simulador!D16*12 -> 170100
B7: EBITDA anual | C7: =Simulador!B21 -> -17520 | D7: =Simulador!C21 -> 65282.4 | E7: =Simulador!D21 -> 235380
B8: Margen EBITDA % | C8: =Simulador!B20 -> -0.081111111 | D8: =Simulador!C20 -> 0.17292435 | E8: =Simulador!D20 -> 0.34594356
A11: © 2026 AI Chef Pro · aichef.pro
