Workbook

Sheet Instructions
A1: Kitchen Capacity and Site Visit Checklist
A2: AI Chef Pro · aichef.pro — How to Open a Pastry Shop
A3: Purpose: decide whether THAT space works and how many pieces a day the equipment you're buying can handle.
A5: How to use it
A6: 1. "Settings" sheet: start here. Shift hours, shifts per day, pieces you want to turn out, square footage, power and fuel type of the ovens. Everything else in the workbook recalculates from here; there isn't a single number hidden inside a formula.
A7: 2. "Zones and Square Feet" sheet: split the square feet among the seven zones and number the one-way flow route from 1 to 7. The sheet tells you whether the split matches the declared square footage, what share of the space is production kitchen and whether the route has a crossing.
A8: 3. "Capacity by Equipment" sheet: one row per machine. Say whether you have it, how much fits in a cycle, how many pieces come out of that amount, how many minutes the cycle lasts and what share of your assortment goes through it. The sheet returns the pieces per day THAT machine allows the whole production kitchen.
A9: 4. "Bottleneck" sheet: the result. Which machine is in charge, how many pieces a day the whole kitchen can handle, how much cushion you have over a normal day and what happens in each of the six peaks of the year. This is where you see whether Three Kings Day fits in the production kitchen you're buying.
A10: 5. "Site Visit Checklist" sheet: print it and take it to every visit. Eighteen checks, eight of them deal-breakers. A single "No" on a deal-breaker item and the verdict is RULE OUT: it's not pessimism, it's that the defect can't be fixed with reasonable money.
A12: Green cells = fields you can edit
A14: What to know before you start
A15: THIS WORKBOOK DECIDES A PURCHASE, NOT A WORK WEEK. Day-to-day production -what gets made on Tuesday and how much- belongs with your daily task checklists. Here we only answer how many pieces a day the equipment you're about to pay for allows, the question you can't answer after you've bought.
... A21: Where this workbook ends and your task calendar and checklists begin
A22: What you need | B22: Where it is | C22: Why it isn't here
A23: What gets produced each day of the week and in what order | B23: Your production schedule (daily task checklists) | C23: That's the operation of the production kitchen you ALREADY have. This workbook decides the purchase: how many pieces a day the machine allows.
A24: The dates of each campaign and what you do in each one | B24: Your annual task calendar | C24: Your task calendar sets the dates and the what. Here the peak enters only as a multiplier of pieces per day; each campaign's dollars are in seasonal-peaks-planner.xlsx.
A25: How many people you need and what they cost with payroll taxes | B25: staff-schedule-and-labor-cost.xlsx | C25: Here the shift hours are a capacity parameter, not a staffing plan.
A26: What each machine costs and how long it takes to arrive | B26: startup-cost-calculator.xlsx and equipment-and-suppliers-checklist.xlsx | C26: Price and lead time don't change capacity. They're kept apart on purpose so you can decide first what you need and then what it costs.
A27: It's a declared COPY, not a link: nowhere in this guide's workbooks is there a formula pointing to another file. A link between workbooks breaks as soon as someone moves a folder, and then the workbook lies without telling you. Where a green cell would bring in data from another workbook or from your own records, it comes with its own default value, declared as an assumption, and its note tells you what replaces it.
A29: How often to use this workbook
A30: Cadence: the "Site Visit Checklist" sheet, ONCE PER SPACE you visit, and you keep it even if you rule the space out -comparing three spaces is what shows you what you're accepting-. The capacity sheets, every time you change a piece of equipment in the budget and, after you open, ONCE A YEAR before the Three Kings Day campaign.
A32: To edit the structure or a cell that isn't green: Review > Unprotect Sheet (no password).
A34: Designed by John Guerrero — chef and restaurant consultant since 2010, in the kitchen since age 17.
A35: Version 1.0 · October 2026 · aichef.pro/en/digital-products/how-to-open-a-pastry-shop · info@aichef.pro

Sheet Settings
A1: Settings
A2: AI Chef Pro · aichef.pro — How to Open a Pastry Shop
A3: Everything the workbook calculates comes from here. Not one number lives inside a formula.
A5: Parameter | B5: Value | C5: Unit | D5: Source | E5: What it is and where it comes from
A6: Production kitchen shift length | B6: 8 | C6: h per shift | D6: assumption | E6: Length of the production kitchen shift. It's the number that multiplies everything else: with two shifts, capacity doubles without buying a single machine.
A7: Production kitchen shifts per day | B7: 1 | C7: shifts | D7: assumption | E7: La Clara works one early-morning shift. A second shift is the cheapest lever there is for raising capacity, and the most expensive one in labor.
A8: Productive hours as a share of the workday | B8: 0.85 | C8: % | D8: assumption | E8: The share of the workday the machine is really working. The rest is receiving, cleaning, swapping trays and waiting.
A9: Minutes available per day | B9: =IFERROR(B6*B7*B8*60,"") -> 408 | C9: minutes | D9: Calculated | E9: Shift hours × shifts × productive hours × 60. This is where each piece of equipment's cycles per day come from.
A10: Days open per week | B10: 6 | C10: days | D10: assumption | E10: 6 days a week × 52 weeks = 312, minus 12 closing days for a vacation in August = 300. Holidays are NOT subtracted: you choose your own days and hours (check your lease and local rules).
A11: Days open per year | B11: 300 | C11: days | D11: assumption | E11: 312 days open minus 12 closing days for vacation.
A12: Pieces per day at cruising speed | B12: 476 | C12: pieces per day | D12: assumption | E12: What you have to turn out every day once the business is running smoothly. It comes from customers per day times pieces per ticket, both assumptions: there's no public foot-traffic data for pastry shops. If you have your own production data, replace it.
A13: Safety margin required over capacity | B13: 0.1 | C13: % | D13: assumption | E13: The minimum cushion you want over a normal day. Below it, the workbook warns you: a breakdown, a sick call or a big order leaves you short of product even if on paper you make it.
A14: Total square footage of the space | B14: 968.75194 | C14: sq ft | D14: Assumption | E14: The 969 sq ft of the reference case. It's the area the build-out scenarios of $55.74, $83.61 and $111.48 per sq ft in startup-cost-calculator.xlsx are based on.
A15: Minimum share of the space given to the production kitchen | B15: 0.45 | C15: % | D15: assumption | E15: House rule, not a code: below this, the front of the shop eats the kitchen and you end up buying semi-finished goods. If you sell mostly by custom order, lower it; if the sales floor is your showcase, raise it.
A16: Electrical power of the ovens | B16: 34 | C16: kW | D16: Assumption | E16: The ovens ONLY. 34 kW is the working point of the case's two convection ovens.
A17: Total connected load planned | B17: 62 | C17: kW | D17: assumption | E17: The ovens are only part of it. The 62 kW of connected load also covers refrigeration, mixing, HVAC and lighting, and it's an assumption: your electrician and the utility decide the service you need, not a table. Ask for it in amps and volts, and whether it's three-phase.
A18: Oven fuel | B18: Electric | C18: Electric or Gas | D18: assumption | E18: Changes the hood airflow you need and, if you choose gas, adds a question for the gas utility and the building department: can the service and piping carry your ovens?
A19: Exhaust airflow per kW, electric equipment | B19: 23.543111 | C19: CFM per kW | D19: Assumption | E19: Hood sizing rule of thumb for electric equipment. A design assumption: the hood manufacturer and your mechanical code set the real number.
A20: Exhaust airflow per kW, gas equipment | B20: 29.428889 | C20: CFM per kW | D20: Assumption | E20: Hood sizing rule of thumb for gas equipment. A design assumption, like the one above.
A21: Hood airflow needed | B21: =IFERROR(B16*IF(B18="Gas",B20,B19),"") -> 800.46578 | C21: CFM | D21: Calculated | E21: Oven power × the airflow per kW that matches your fuel. It's the number to take to the visit: if the space can't deliver it, there's no pastry shop.
A22: Minimum clear ceiling height you require | B22: 9.8425197 | C22: ft | D22: assumption | E22: With hood, duct and dropped ceiling, under 9.8 ft the production kitchen runs out of air and out of room for the duct.
A23: Number of zones in the space | B23: 7 | C23: zones | D23: Assumption | E23: The zones in the case's plan for a pastry shop production kitchen. If your space doesn't allow all seven, it isn't tight: one is missing.
A25: Validation lists (don't delete them: the dropdowns use them)
A26: Oven fuel
A27: Electric
A28: Gas
A30: The values marked "assumption" are from the example pastry shop "La Clara" (969 sq ft, a 484 sq ft production kitchen, one early-morning shift). They're not industry data: they're a consistent starting point so you can see the workbook working before you enter your own.

Sheet Zones and Square Feet
A1: Zones and Square Feet
A2: AI Chef Pro · aichef.pro — How to Open a Pastry Shop
A3: The seven zones in the case's plan for a pastry shop, and the one-way flow route.
A5: No. | B5: Zone | C5: Block | D5: sq ft | E5: Share of the space (%) | F5: Workflow step | G5: What it has to meet
A6: 1 | B6: Production kitchen | C6: Production kitchen | D6: 484.37597 | E6: =IFERROR(D6/$D$14,"") -> 0.5 | F6: 3 | G6: Prep area, off-limits to customers. One-way flow: ingredients come in at one end and finished product leaves at the other without crossing them. Hand sinks where people work (Food Code 5-203.11).
A7: 2 | B7: Sales floor (front counter) | C7: Front counter | D7: 236.80603 | E7: =IFERROR(D7/$D$14,"") -> 0.24444444 | F7: 5 | G7: Counter, refrigerated display case, ambient display and room for a line, with a stretch of counter at least 36 inches long and no more than 36 inches high (ADA Standards 904.4.1).
A8: 3 | B8: Dry storage | C8: Cold and dry storage | D8: 53.819552 | E8: =IFERROR(D8/$D$14,"") -> 0.055555556 | F8: 1 | G8: Flour, sugar and dry goods on shelving, never on the floor.
A9: 4 | B9: Walk-in cooler | C9: Cold and dry storage | D9: 43.055642 | E9: =IFERROR(D9/$D$14,"") -> 0.044444444 | F9: 2 | G9: Filled pastries held at 41 °F or below (Food Code 3-501.16).
A10: 5 | B10: Finished goods storage | C10: Cold and dry storage | D10: 32.291731 | E10: =IFERROR(D10/$D$14,"") -> 0.033333333 | F10: 4 | G10: Shelf-stable product and assembled packaging.
A11: 6 | B11: Staff restroom and lockers | C11: Restrooms and lockers | D11: 86.111283 | E11: =IFERROR(D11/$D$14,"") -> 0.088888889 | F11: 7 | G11: Staff restroom and a place to change, with lockers; your local plumbing code sets how many restrooms you need.
A12: 7 | B12: Trash and recycling | C12: Restrooms and lockers | D12: 32.291731 | E12: =IFERROR(D12/$D$14,"") -> 0.033333333 | F12: 6 | G12: Enclosed, with labeled bins and its own way out: trash never crosses the production kitchen.
B14: TOTAL allocated | D14: =SUM(D6:D12) -> 968.75194 | E14: =SUM(E6:E12) -> 1
B15: Square footage declared on "Settings" | D15: ='Settings'!B14 -> 968.75194
B16: Mismatch (sq ft) | D16: =IFERROR(D14-D15,"") -> 0 | G16: If it isn't zero, you either have square feet left unassigned or you've allocated more than the space has.
B18: Square feet of production kitchen | D18: =SUMIF(C6:C12,"Production kitchen",D6:D12) -> 484.37597
B19: Share of the space given to the production kitchen | D19: =IFERROR(D18/D14,"") -> 0.5
B20: Square feet of sales floor (front counter) | D20: =SUMIF(C6:C12,"Front counter",D6:D12) -> 236.80603
B21: Share of the space given to sales | D21: =IFERROR(D20/D14,"") -> 0.24444444
B22: Minimum production kitchen you set | D22: ='Settings'!B15 -> 0.45
B23: Verdict on the allocation | D23: =IF(D19="","",IF(D19<D22,"The production kitchen falls short","Allocation is enough")) -> Allocation is enough
B25: One-way flow: ingredients come in at one end and the product leaves at the other
B26: Sum of the steps you numbered | D26: =SUM(F6:F12) -> 28
B27: Sum it should come to (1 + 2 + ... + n) | D27: =IFERROR('Settings'!B23*('Settings'!B23+1)/2,"") -> 28
B28: Are they numbered 1 to n with no repeats? | D28: =IF(AND(D26=D27,MIN(F6:F12)=1,MAX(F6:F12)='Settings'!B23),"Yes","Check the numbering") -> Yes | G28: Numbering check: the sum has to match and the steps have to run from 1 to the number of zones. It won't catch a permutation that adds up the same; what it does catch -and it's what always happens- is a repeated number or a skipped one.
B29: Ingredients come in before the production kitchen | D29: =IF(F8<F6,"Yes","No") -> Yes
B30: The walk-in cooler comes before the production kitchen | D30: =IF(F9<F6,"Yes","No") -> Yes
B31: Finished product leaves after the production kitchen | D31: =IF(F10>F6,"Yes","No") -> Yes
B32: Finished product reaches the counter without going back | D32: =IF(F10<=F7,"Yes","No") -> Yes
B33: Trash leaves after the production kitchen | D33: =IF(F12>F6,"Yes","No") -> Yes
B35: ONE-WAY FLOW VERDICT | D35: =IF(COUNTIF(D29:D33,"No")>0,"There is a crossing in the flow","One-way flow is correct") -> One-way flow is correct
B37: The one-way flow isn't a design preference: it's making sure raw ingredients and finished product never cross. When the space doesn't allow it, a sign or a schedule doesn't fix it; construction does, or it doesn't get fixed. That's why you draw this route on the plan BEFORE you sign.

Sheet Capacity by Equipment
A1: Capacity by Equipment
A2: AI Chef Pro · aichef.pro — How to Open a Pastry Shop
A3: One model for every machine: what fits in a cycle, how many pieces come out of that, how long the cycle lasts and what share of your assortment goes through it.
A5: No. | B5: Equipment | C5: Category | D5: Have it? | E5: Capacity per cycle | F5: Unit of capacity | G5: Pieces per unit | H5: Pieces per cycle | I5: Minutes per cycle | J5: Cycles per day | K5: Pieces per day of the equipment | L5: Share of the assortment that goes through it (%) | M5: Kitchen pieces per day it allows | N5: Counts toward the bottleneck | O5: Source | P5: Note
A6: 1 | B6: Spiral mixer, 25 kg (55 lb) of dough | C6: Mixing | D6: Yes | E6: 25 | F6: kg of dough per batch | G6: 19.6 | H6: =IFERROR(E6*G6,"") -> 490 | I6: 30 | J6: =IFERROR(INT('Settings'!$B$9/I6),"") -> 13 | K6: =IFERROR(H6*J6,"") -> 6370 | L6: 0.55 | M6: =IFERROR(K6/L6,"") -> 11581.818 | N6: =IF(D6="Yes",M6,"") -> 11581.818 | O6: assumption | P6: The pieces per kg come from the croissant batch in the opening menu: 1.02 kg of dough for 20 pieces, or 19.6 pieces per kg. Change the number if your assortment weighs more per piece.
A7: 2 | B7: Planetary mixer, 20 L (about 21 qt) | C7: Mixing | D7: Yes | E7: 20 | F7: L of dough or cream per batch | G7: 8 | H7: =IFERROR(E7*G7,"") -> 160 | I7: 25 | J7: =IFERROR(INT('Settings'!$B$9/I7),"") -> 16 | K7: =IFERROR(H7*J7,"") -> 2560 | L7: 0.3 | M7: =IFERROR(K7/L7,"") -> 8533.3333 | N7: =IF(D7="Yes",M7,"") -> 8533.3333 | O7: Assumption | P7: Planetary mixer, about 900 W. It's the one that sets the pace for creams, mousses and meringues, not for doughs.
A8: 3 | B8: Dough sheeter, up to 16 in wide | C8: Sheeting | D8: Yes | E8: 3 | F8: dough blocks per cycle | G8: 20 | H8: =IFERROR(E8*G8,"") -> 60 | I8: 20 | J8: =IFERROR(INT('Settings'!$B$9/I8),"") -> 20 | K8: =IFERROR(H8*J8,"") -> 1200 | L8: 0.25 | M8: =IFERROR(K8/L8,"") -> 4800 | N8: =IF(D8="Yes",M8,"") -> 4800 | O8: Assumption | P8: Dough sheeter, 16 in. One block of dough makes a batch of 20 viennoiserie pieces, so three blocks are 60 pieces per cycle.
A9: 4 | B9: Convection oven, 6 trays | C9: Heat | D9: Yes | E9: 6 | F9: trays per bake | G9: 12 | H9: =IFERROR(E9*G9,"") -> 72 | I9: 25 | J9: =IFERROR(INT('Settings'!$B$9/I9),"") -> 16 | K9: =IFERROR(H9*J9,"") -> 1152 | L9: 0.6 | M9: =IFERROR(K9/L9,"") -> 1920 | N9: =IF(D9="Yes",M9,"") -> 1920 | O9: Assumption | P9: Convection oven, 6 trays. The pieces per tray are for medium-size viennoiserie: lower them for cakes and raise them for petit fours.
A10: 5 | B10: Convection oven, 4 trays | C10: Heat | D10: Yes | E10: 4 | F10: trays per bake | G10: 12 | H10: =IFERROR(E10*G10,"") -> 48 | I10: 25 | J10: =IFERROR(INT('Settings'!$B$9/I10),"") -> 16 | K10: =IFERROR(H10*J10,"") -> 768 | L10: 0.25 | M10: =IFERROR(K10/L10,"") -> 3072 | N10: =IF(D10="Yes",M10,"") -> 3072 | O10: Assumption | P10: The second oven isn't there to produce more: it's there so you can bake at two temperatures at once.
A11: 6 | B11: Retarder-proofer (roll-in) | C11: Refrigeration | D11: Yes | E11: 2 | F11: carts per cycle | G11: 90 | H11: =IFERROR(E11*G11,"") -> 180 | I11: 120 | J11: =IFERROR(INT('Settings'!$B$9/I11),"") -> 3 | K11: =IFERROR(H11*J11,"") -> 540 | L11: 0.35 | M11: =IFERROR(K11/L11,"") -> 1542.8571 | N11: =IF(D11="Yes",M11,"") -> 1542.8571 | O11: Assumption | P11: It's what lets viennoiserie be baked at 7:00 without anyone coming in at 3:00. Its cycle is long, so it limits more than it seems.
A12: 7 | B12: Blast chiller, 4 trays | C12: Freezing | D12: Yes | E12: 4 | F12: trays per cycle | G12: 12 | H12: =IFERROR(E12*G12,"") -> 48 | I12: 90 | J12: =IFERROR(INT('Settings'!$B$9/I12),"") -> 4 | K12: =IFERROR(H12*J12,"") -> 192 | L12: 0.4 | M12: =IFERROR(K12/L12,"") -> 480 | N12: =IF(D12="Yes",M12,"") -> 480 | O12: Assumption | P12: Irinox MultiFresh line. Long, mandatory cycle for filled items: the number-one bottleneck candidate in a pastry shop. A household chest freezer is NOT a blast chiller: it can't meet the Food Code cooling rule (135 °F to 70 °F in 2 hours, to 41 °F within 6 hours total).
A13: 8 | B13: Walk-in cooler, about 283 cu ft (8 m³) | C13: Refrigeration | D13: Yes | E13: 282.51733 | F13: usable cu ft per rotation | G13: 1.9821793 | H13: =IFERROR(E13*G13,"") -> 560 | I13: 400 | J13: =IFERROR(INT('Settings'!$B$9/I13),"") -> 1 | K13: =IFERROR(H13*J13,"") -> 560 | L13: 0.45 | M13: =IFERROR(K13/L13,"") -> 1244.4444 | N13: =IF(D13="Yes",M13,"") -> 1244.4444 | O13: assumption | P13: Here the "cycle" is one rotation of the cooler: with 400 minutes, one rotation fits in a day. It's the one that holds filled pastries at 41 °F or below.
A14: 9 | B14: Refrigerated bakery display case | C14: Storefront and display | D14: Yes | E14: 10.010437 | F14: sq ft of display per restock | G14: 12.077395 | H14: =IFERROR(E14*G14,"") -> 120.9 | I14: 120 | J14: =IFERROR(INT('Settings'!$B$9/I14),"") -> 3 | K14: =IFERROR(H14*J14,"") -> 362.7 | L14: 0.35 | M14: =IFERROR(K14/L14,"") -> 1036.2857 | N14: =IF(D14="Yes",M14,"") -> 1036.2857 | O14: Assumption | P14: Refrigerated display case, curved glass, about 5 ft, with 10.0 sq ft of display. At 120 minutes per restock you get three restocks of the case a day.
A15: 10 | B15: Modular deck oven | C15: Heat | D15: No | E15: 4 | F15: trays per bake | G15: 14 | H15: =IFERROR(E15*G15,"") -> 56 | I15: 35 | J15: =IFERROR(INT('Settings'!$B$9/I15),"") -> 11 | K15: =IFERROR(H15*J15,"") -> 616 | L15: 0.2 | M15: =IFERROR(K15/L15,"") -> 3080 | N15: =IF(D15="Yes",M15,"") | O15: Assumption | P15: OPTIONAL. Marked "No" on purpose: change it to "Yes" and watch how the bottleneck moves before you spend the money.
B17: Minutes available per day (from "Settings") | E17: ='Settings'!B9 -> 408
B18: Equipment you say you have | E18: =COUNTIF(D6:D15,"Yes") -> 9
B19: Equipment that doesn't count (cycle longer than the workday) | E19: =COUNTIF(J6:J15,0) -> 0 | P19: A zero in "cycles per day" means that machine's cycle doesn't fit in the workday you declared. It's not a workbook error: with that shift, that machine produces nothing.
B21: Validation lists (don't delete them: the dropdowns use them)
B22: Have it?
B23: Yes
B24: No
B26: The green columns on this sheet are the ones to push back on with the salesperson: how much really fits in a cycle, how long the full cycle lasts (with loading and unloading, not the one in the brochure) and what share of your assortment goes through it. If you have your own production data, use it for each machine's real percentage; until then, the defaults are assumptions consistent with La Clara's 30-item menu.

Sheet Bottleneck
A1: Bottleneck
A2: AI Chef Pro · aichef.pro — How to Open a Pastry Shop
A3: The equipment in charge, the pieces per day the whole kitchen can handle and what happens in each of the six peaks of the year.
A5: The normal day
A6: Pieces per day you want to turn out | B6: ='Settings'!B12 -> 476
A7: Pieces per day the whole kitchen allows | B7: =IFERROR(MIN('Capacity by Equipment'!$N$6:$N$15),"") -> 480
A8: The equipment that limits you | B8: =IFERROR(INDEX('Capacity by Equipment'!$B$6:$B$15,MATCH(B7,'Capacity by Equipment'!$N$6:$N$15,0)),"") -> Blast chiller, 4 trays
A9: Cushion over a normal day (pieces) | B9: =IFERROR(B7-B6,"") -> 4
A10: Cushion over a normal day (%) | B10: =IFERROR(B9/B6,"") -> 0.0084033613
A11: Safety margin you set | B11: ='Settings'!B13 -> 0.1
A12: NORMAL-DAY VERDICT | B12: =IF(B7="","",IF(B7<B6,"YOU DON'T MAKE IT",IF(B10<B11,"TIGHT","ENOUGH"))) -> TIGHT | J12: "TIGHT" means you get through the normal day, but with less than the safety margin you set yourself: a breakdown, a sick call or a big order leaves you short of product.
A13: The second-tightest equipment allows | B13: =IFERROR(SMALL('Capacity by Equipment'!$N$6:$N$15,2),"") -> 1036.2857
A14: And it is | B14: =IFERROR(INDEX('Capacity by Equipment'!$B$6:$B$15,MATCH(B13,'Capacity by Equipment'!$N$6:$N$15,0)),"") -> Refrigerated bakery display case | J14: Look at both together before buying: if the second is very close to the first, fixing only the bottleneck raises your capacity by four pieces and leaves your money out.
A16: The six peaks of the year
A17: Peak | B17: Dates | C17: Factor over a normal day | D17: Pieces per day needed | E17: Pieces per day the whole kitchen allows | F17: Shortfall (pieces per day) | G17: Can you handle it? | H17: Star product | I17: Star product units per day during the campaign | J17: Note
A18: Día de Reyes (Three Kings Day) | B18: January 2–6 | C18: 6 | D18: =IFERROR($B$6*C18,"") -> 2856 | E18: =IFERROR($B$7,"") -> 480 | F18: =IFERROR(E18-D18,"") -> -2376 | G18: =IF(F18="","",IF(F18<0,"NO","YES")) -> NO | H18: Rosca de Reyes | I18: 160 | J18: The peak that decides the year. The campaign units are those of the FIVE best-selling days: 160 a day, 800 in total, 47% of the roscas the menu mix assigns to the year (1.2% of the pieces). The rest sell in the week before, outside the campaign window, which is why they aren't in this row. In the US the rosca shares its season with the king cake (Epiphany to Mardi Gras), and searches average about 90,500 a month for "rosca de reyes" and 110,000 for "king cake" (DataForSEO, October 2026): scale references, never price or market share. A cream-filled rosca carries the 41 °F cold-holding limit (Food Code 3-501.16) and date marking (3-501.17) on the biggest production day: that limits production as much as the oven does.
A19: Valentine's Day | B19: February 13–14 | C19: 1.8 | D19: =IFERROR($B$6*C19,"") -> 856.8 | E19: =IFERROR($B$7,"") -> 480 | F19: =IFERROR(E19-D19,"") -> -376.8 | G19: =IF(F19="","",IF(F19<0,"NO","YES")) -> NO | H19: Raspberry macarons | I19: 260 | J19: Two-day, high-ticket campaign, not volume: you win with boxes and presentation, not with more oven. The special production for this date is heart-shaped cakes, bonbons and macarons.
A20: Mother's Day | B20: Día de las Madres (May 10) and US Mother's Day (2nd Sunday of May) | C20: 1.9 | D20: =IFERROR($B$6*C20,"") -> 904.4 | E20: =IFERROR($B$7,"") -> 480 | F20: =IFERROR(E20-D20,"") -> -424.4 | G20: =IF(F20="","",IF(F20<0,"NO","YES")) -> NO | H20: 70% chocolate cake | I20: 96 | J20: One operating date for Día de las Madres (May 10) and US Mother's Day (2nd Sunday of May): a personalized cake, made to order. What matters to this guide is the load on the production kitchen, not the calendar.
A21: Easter (Holy Week) | B21: Palm Sunday to Easter Sunday | C21: 2.4 | D21: =IFERROR($B$6*C21,"") -> 1142.4 | E21: =IFERROR($B$7,"") -> 480 | F21: =IFERROR(E21-D21,"") -> -662.4 | G21: =IF(F21="","",IF(F21<0,"NO","YES")) -> NO | H21: Torrijas | I21: 230 | J21: Eight days in a row of extra production, more exhausting than the five of Three Kings Day even though the peak is smaller. Torrijas and Easter cakes (monas) at once: one needs a fryer and cold, the other an oven and chocolate. That's 230 torrijas a day and 1,840 over the campaign: 99% of the torrijas the menu mix assigns to the year, because they aren't made outside Holy Week.
A22: First Communions and graduations | B22: mid-April to mid-June | C22: 1.6 | D22: =IFERROR($B$6*C22,"") -> 761.6 | E22: =IFERROR($B$7,"") -> 480 | F22: =IFERROR(E22-D22,"") -> -281.6 | G22: =IF(F22="","",IF(F22<0,"NO","YES")) -> NO | H22: Strawberries-and-cream cake | I22: 34 | J22: It's not a peak, it's a two-month PLATEAU, which is why you carry it with staff and not with overtime. Everything is by custom order: deposit, delivery calendar and cancellation risk (chapter 16).
A23: All Saints' Day and Día de los Muertos | B23: October 30 – November 1 | C23: 2.6 | D23: =IFERROR($B$6*C23,"") -> 1237.6 | E23: =IFERROR($B$7,"") -> 480 | F23: =IFERROR(E23-D23,"") -> -757.6 | G23: =IF(F23="","",IF(F23<0,"NO","YES")) -> NO | H23: Buñuelos (cream-filled fritters) | I23: 470 | J23: Three days with three items that are only made now: buñuelos, huesos de santo and panellets. The buñuelos are cream-filled (41 °F or below, and date-marked if held) and the other two are shelf-stable at room temperature: that's why buñuelos are made the same day and huesos de santo can be made ahead. That food-safety detail IS the campaign planning. It's 470 buñuelos a day and 1,410 over the three days: 99% of the buñuelos the menu mix assigns to the year, because they aren't made outside this date.
A25: Peaks you can't handle | B25: =COUNTIF(G18:G23,"NO") -> 6
A26: The worst shortfall (pieces per day) | B26: =IFERROR(MIN(F18:F23),"") -> -2376
A27: And it's the peak of | B27: =IFERROR(INDEX($A$18:$A$23,MATCH(B26,$F$18:$F$23,0)),"") -> Día de Reyes (Three Kings Day)
A28: CAMPAIGN VERDICT | B28: =IF(B25=0,"You handle all six peaks",IF(B25=1,"One peak is more than the kitchen can take","Several peaks are more than the kitchen can take")) -> Several peaks are more than the kitchen can take
A30: A peak that doesn't fit in the production kitchen is NOT a reason to buy more machine: buying for Three Kings Day means having money sitting idle the other 299 days. What you do is get ahead on production (scheduled freezing with a blast chiller, not a chest freezer), load the campaign onto shelf-stable items that can be made days ahead, and close orders with a date. Each campaign's dollars are in seasonal-peaks-planner.xlsx; its dates and task list belong in your annual task calendar.
A32: The column "star product units per day during the campaign" is here as a contrast, not a calculation: it's the units of the product that defines the peak. The 420 roscas a day on Three Kings Day versus zero on a normal day are the reason this sheet exists.

Sheet Site Visit Checklist
A1: Site Visit Checklist
A2: AI Chef Pro · aichef.pro — How to Open a Pastry Shop
A3: Print it and take it to every visit. A single "No" on a deal-breaker item and the verdict is RULE OUT.
A5: No. | B5: What you check | C5: Deal-breaker? | D5: How to check it | E5: Answer | F5: Measured value | G5: Threshold | H5: Does the value pass? | I5: Verdict | J5: Note and rule
A6: 1 | B6: There's a route for the hood's own duct up to the roof | C6: Yes | D6: Go up on the roof with the landlord and look at where the duct would run; it can't tie into the restroom or front-of-house exhaust. Get it in writing before you sign. | E6: Yes | G6: Not applicable | I6: =IF(H6="No",IF(C6="Yes","RULE OUT","Weak point"),IF(E6="","",IF(E6="No",IF(C6="Yes","RULE OUT","Weak point"),IF(E6="To check","Pending","OK")))) -> OK | J6: Industry rule of thumb, NOT a verified code: the duct usually has to reach the roof, and how far above it and how far from air intakes and property lines is set by your adopted mechanical code and NFPA 96: ask the building department. It's the item that rules out the most spaces and the one to settle BEFORE you sign, not after.
A7: 2 | B7: The hood type the space has (or can take) matches your ovens | C7: Yes | D7: Type I with fire suppression for deck ovens, Type II for enclosed electric convection: get the answer in writing from the building or mechanical department. Ask for the mechanical plans or open the dropped ceiling to see what's there. | E7: Yes | G7: Not applicable | I7: =IF(H7="No",IF(C7="Yes","RULE OUT","Weak point"),IF(E7="","",IF(E7="No",IF(C7="Yes","RULE OUT","Weak point"),IF(E7="To check","Pending","OK")))) -> OK | J7: Hood type follows the appliance, its listing and your jurisdiction's adopted mechanical code (IMC 507): Type I with grease duct and fire suppression where appliances give off grease or smoke, Type II for heat and steam, and none for a single light-duty electric oven or an appliance listed to UL 710B. Don't read those exceptions as yours: a Type II where your ovens need a Type I means a new hood, duct and fire suppression system to budget.
A8: 3 | B8: The available exhaust airflow covers what your ovens need | C8: No | D8: Measure it, or ask for the spec sheet of the existing exhaust fan. The threshold is calculated on the "Settings" sheet from your oven power and your fuel type. | E8: Yes | F8: 824.00889 | G8: ='Settings'!B21 -> 800.46578 | H8: =IF(AND(ISNUMBER(F8),ISNUMBER(G8)),IF(F8>=G8,"Yes","No"),"") -> Yes | I8: =IF(H8="No",IF(C8="Yes","RULE OUT","Weak point"),IF(E8="","",IF(E8="No",IF(C8="Yes","RULE OUT","Weak point"),IF(E8="To check","Pending","OK")))) -> OK | J8: Sizing rule of thumb: 23.5 CFM per kW for electric equipment and 29.4 for gas. If the space falls short, the cost of replacing the exhaust fan goes into startup-cost-calculator.xlsx.
A9: 4 | B9: The electrical service available covers what you're going to install | C9: Yes | D9: Ask for the service size (amps, voltage, single- or three-phase) and ask the utility what capacity the building's service can deliver. | E9: Yes | F9: 70 | G9: ='Settings'!B17 -> 62 | H9: =IF(AND(ISNUMBER(F9),ISNUMBER(G9)),IF(F9>=G9,"Yes","No"),"") -> Yes | I9: =IF(H9="No",IF(C9="Yes","RULE OUT","Weak point"),IF(E9="","",IF(E9="No",IF(C9="Yes","RULE OUT","Weak point"),IF(E9="To check","Pending","OK")))) -> OK | J9: Raising the available power of a service can cost more than the whole build-out and depends on the utility, not on your budget.
A10: 5 | B10: Zoning allows a bakery with on-site production at that address | C10: Yes | D10: Ask the planning or zoning department, in writing and for that specific address, not over the phone. Ask whether they issue a zoning verification letter. | E10: Yes | G10: Not applicable | I10: =IF(H10="No",IF(C10="Yes","RULE OUT","Weak point"),IF(E10="","",IF(E10="No",IF(C10="Yes","RULE OUT","Weak point"),IF(E10="To check","Pending","OK")))) -> OK | J10: A space that's a store today doesn't automatically allow a production kitchen: it's food production, with exhaust and early-morning hours.
A11: 6 | B11: The landlord and the center's CC&Rs or rules allow the use, the hood and the roof penetration | C11: Yes | D11: Get the landlord's written approval and read the CC&Rs or the center or association rules. A restaurant next door isn't proof enough. | E11: Yes | G11: Not applicable | I11: =IF(H11="No",IF(C11="Yes","RULE OUT","Weak point"),IF(E11="","",IF(E11="No",IF(C11="Yes","RULE OUT","Weak point"),IF(E11="To check","Pending","OK")))) -> OK | J11: A recorded restriction or a center rule binds you even if the city gives you the permit, and the duct usually crosses a common area or the roof.
A12: 7 | B12: The clear ceiling height reaches the height you've set | C12: No | D12: Laser measure from the finished floor to the underside of the structure, at the lowest point, not the highest. | E12: Yes | F12: 10.498688 | G12: ='Settings'!B22 -> 9.8425197 | H12: =IF(AND(ISNUMBER(F12),ISNUMBER(G12)),IF(F12>=G12,"Yes","No"),"") -> Yes | I12: =IF(H12="No",IF(C12="Yes","RULE OUT","Weak point"),IF(E12="","",IF(E12="No",IF(C12="Yes","RULE OUT","Weak point"),IF(E12="To check","Pending","OK")))) -> OK | J12: With hood, duct and dropped ceiling, every inch counts. Measure where the oven goes.
A13: 8 | B13: The usable floor area covers the square feet you've allotted by zone | C13: No | D13: Real usable area, not counting walls or shafts. Compare it with the total on the "Zones and Square Feet" sheet. | E13: Yes | F13: 990.27976 | G13: ='Settings'!B14 -> 968.75194 | H13: =IF(AND(ISNUMBER(F13),ISNUMBER(G13)),IF(F13>=G13,"Yes","No"),"") -> Yes | I13: =IF(H13="No",IF(C13="Yes","RULE OUT","Weak point"),IF(E13="","",IF(E13="No",IF(C13="Yes","RULE OUT","Weak point"),IF(E13="To check","Pending","OK")))) -> OK | J13: A listing's square footage is usually gross. The one that matters is usable, and about 108 sq ft can easily vanish between the two.
A14: 9 | B14: The production kitchen can be closed off so customers can't get in | C14: Yes | D14: Draw the seven zones on the floor plan before you sign. If they don't fit with the door where it is, they don't fit. | E14: Yes | G14: Not applicable | I14: =IF(H14="No",IF(C14="Yes","RULE OUT","Weak point"),IF(E14="","",IF(E14="No",IF(C14="Yes","RULE OUT","Weak point"),IF(E14="To check","Pending","OK")))) -> OK | J14: The production kitchen is a prep area off-limits to customers. It's not a design recommendation: it's what separates a production kitchen from a kitchen on display.
A15: 10 | B15: The seven zones fit with a one-way flow and no crossings | C15: No | D15: Check the route on the "Zones and Square Feet" sheet: ingredients, production kitchen, finished goods, counter. | E15: Yes | G15: Not applicable | I15: =IF(H15="No",IF(C15="Yes","RULE OUT","Weak point"),IF(E15="","",IF(E15="No",IF(C15="Yes","RULE OUT","Weak point"),IF(E15="To check","Pending","OK")))) -> OK | J15: Fitting the square feet doesn't mean fitting the route. A production kitchen where the trash goes out the way the flour comes in won't pass plan review.
A16: 11 | B16: There's hot and cold water and a drain where the equipment goes | C16: No | D16: Find the existing drains. Moving a drain means cutting up the slab across the whole space. | E16: Yes | G16: Not applicable | I16: =IF(H16="No",IF(C16="Yes","RULE OUT","Weak point"),IF(E16="","",IF(E16="No",IF(C16="Yes","RULE OUT","Weak point"),IF(E16="To check","Pending","OK")))) -> OK | J16: A steam oven, the blast chiller and the sinks need a drain at their spot, not at the far end of the space.
A17: 12 | B17: Floors and walls can take a smooth, durable, easily cleanable finish, with coved floor-wall junctions | C17: No | D17: Look at the real condition: cracked tile, bare drywall, raw concrete. A kitchen finish is construction, not paint. | E17: Yes | G17: Not applicable | I17: =IF(H17="No",IF(C17="Yes","RULE OUT","Weak point"),IF(E17="","",IF(E17="No",IF(C17="Yes","RULE OUT","Weak point"),IF(E17="To check","Pending","OK")))) -> OK | J17: Smooth, durable, easily cleanable surfaces (Food Code 6-201.11), coved floor-wall junctions (6-201.13) and a hand sink where people work (5-203.11). In Texas, walls and ceilings in prep areas have to be light in color (25 TAC §228.171). It isn't an extra: it's a requirement.
A18: 13 | B18: There's room for a staff restroom and changing area | C18: No | D18: Count the square feet and find where the drain stacks are; your local plumbing code sets how many restrooms you need. A new restroom with no stack nearby is a big job. | E18: Yes | G18: Not applicable | I18: =IF(H18="No",IF(C18="Yes","RULE OUT","Weak point"),IF(E18="","",IF(E18="No",IF(C18="Yes","RULE OUT","Weak point"),IF(E18="To check","Pending","OK")))) -> OK | J18: Staff need their own restroom and locker space; customers have theirs. The 118 sq ft on the zones sheet (restrooms and lockers) already account for it.
A19: 14 | B19: Deliveries can come in without crossing the customer area | C19: No | D19: Go at the hour you'd take deliveries, not at noon. Check for a loading zone or a back door, and whether the building allows it. | E19: Yes | G19: Not applicable | I19: =IF(H19="No",IF(C19="Yes","RULE OUT","Weak point"),IF(E19="","",IF(E19="No",IF(C19="Yes","RULE OUT","Weak point"),IF(E19="To check","Pending","OK")))) -> OK | J19: Flour comes in sacks, every day. If it comes in through the front door, it comes past the customer every morning.
A20: 15 | B20: Trash goes out without opening into the production kitchen | C20: No | D20: Find the trash room or enclosure and its door. It has to be closed, with labeled bins. | E20: Yes | G20: Not applicable | I20: =IF(H20="No",IF(C20="Yes","RULE OUT","Weak point"),IF(E20="","",IF(E20="No",IF(C20="Yes","RULE OUT","Weak point"),IF(E20="To check","Pending","OK")))) -> OK | J20: The trash area can't open into the production kitchen. It's one of the few floor-plan defects with no cheap fix.
A21: 16 | B21: The space is accessible or can be made accessible | C21: No | D21: Measure the entry step and the door width. A step at the entrance may be the landlord's or the city's call, not yours. | E21: Yes | G21: Not applicable | I21: =IF(H21="No",IF(C21="Yes","RULE OUT","Weak point"),IF(E21="","",IF(E21="No",IF(C21="Yes","RULE OUT","Weak point"),IF(E21="To check","Pending","OK")))) -> OK | J21: Customers have to be able to get in and be served. The standard for a sales counter is a stretch no higher than 36 inches (ADA Standards 904.4.1). Who pays for entrance changes (you, the landlord or the city) depends on the lease and local rules: ask before you sign.
A22: 17 | B22: If you'll bake on gas, the gas service and piping can carry your ovens | C22: Yes | D22: Ask the gas utility for the meter size and pressure at the space, and ask the building department what permit and inspection new gas piping needs. | E22: To check | G22: Not applicable | I22: =IF(H22="No",IF(C22="Yes","RULE OUT","Weak point"),IF(E22="","",IF(E22="No",IF(C22="Yes","RULE OUT","Weak point"),IF(E22="To check","Pending","OK")))) -> Pending | J22: Gas ovens need the service, meter and piping sized for their load, and new piping needs its own permit and inspection. Get it in writing before you commit to gas; if you go electric, this item doesn't apply.
A23: 18 | B23: The lease and what comes with the space are clear before you sign | C23: Yes | D23: Read the whole lease: use clause, permit contingency, CAM and NNN charges, personal guarantee, and who pays for the build-out (TI allowance). | E23: To check | G23: Not applicable | I23: =IF(H23="No",IF(C23="Yes","RULE OUT","Weak point"),IF(E23="","",IF(E23="No",IF(C23="Yes","RULE OUT","Weak point"),IF(E23="To check","Pending","OK")))) -> Pending | J23: Who pays for the build-out, how many years the lease runs and what happens to the improvements at the end are three numbers in startup-cost-calculator.xlsx, not three details.
B25: Items on the checklist | E25: =COUNTIF(C6:C23,"Yes")+COUNTIF(C6:C23,"No") -> 18
B26: Of which, deal-breakers | E26: =COUNTIF(C6:C23,"Yes") -> 8
B27: Reasons to rule out | E27: =COUNTIF(I6:I23,"RULE OUT") -> 0
B28: Weak points | E28: =COUNTIF(I6:I23,"Weak point") -> 0
B29: Items pending | E29: =COUNTIF(I6:I23,"Pending") -> 2
B30: Resolved with no problem | E30: =COUNTIF(I6:I23,"OK") -> 16
B31: Checklist completed | E31: =IFERROR((E25-E29)/E25,"") -> 0.88888889
B32: VERDICT ON THE SPACE | E32: =IF(E27>0,"RULE OUT THIS SPACE",IF(E29>0,"DON'T DECIDE YET",IF(E28>0,"GO AHEAD WITH CAUTION","GO AHEAD"))) -> DON'T DECIDE YET
B34: Validation lists (don't delete them: the dropdowns use them)
B35: Answer
B36: Yes
B37: No
B38: To check
B40: The eight deal-breaker items aren't deal-breakers out of taste: they're the defects that can't be fixed with reasonable money, or that don't depend on you (the landlord, zoning, the electrical service, the roof). The rest make the build-out more expensive and have to go into startup-cost-calculator.xlsx as a line item, not rule out the space. And keep the checklist for the spaces you rule out: comparing three checklists is what shows you what you're accepting without realizing it.
