Workbook

Sheet Instructions
A1: Opening Menu and Batch Recipe Costing
A2: AI Chef Pro · aichef.pro — How to Open a Pastry Shop
A3: What it's for: deciding what you sell, at what price, and which egg route each item takes, with its holding temperature and its date mark.
A5: How to use it
A6: 1. "Settings" sheet: start with the production kitchen staff block. The production kitchen's cost per hour is NOT an industry figure and you don't type it: it's calculated from the base pay in your wage table, the pay periods, each person's FTE and the payroll taxes, workers' comp and benefits the employer pays. Below that are the purchase prices, one per ingredient: it's the only table where prices are entered, and all 226 lines of the recipe costing draw from it.
A7: 2. "Batch Costing" sheet: one row per ingredient and per item. The costing unit is THE BATCH, not the piece: that's how a production kitchen works, and it's the only way labor adds up. Enter the net quantity you use, the factor that converts the purchase unit into the unit of use (12 to go from a dozen to each, 1 if they match) and the trim loss. The line cost calculates itself.
A8: 3. "Labor Cost per Hour" sheet: the minutes each batch takes and the selling price. From there come labor cost per piece, total cost, food cost and margin in dollars. It's the sheet that teaches you to stop giving your work away.
A9: 4. "Egg & TCS Decision" sheet: for each item, choose the egg route and say whether it's filled and whether the finished item is shelf-stable at room temperature. The workbook returns the holding temperature, which test applies and whether the item needs a date mark when held more than 24 hours. The shelf life is yours to declare.
A10: 5. "Mix and Average Ticket" sheet: split 100% of your units across the 30 items. That gives you your average ticket, which you can't copy from a study because we found no reliable published average ticket for bakeries.
A11: 6. "Menu Decision" sheet: it crosses margin with turnover and tells you what to keep, what to review the price of and what to drop. Go over it three months after opening, with real sales, and again each time the season changes.
A13: Green cells = fields you can edit
A15: What to know before you start
... A30: Version 1.0 · October 2026 · aichef.pro/en/digital-products/how-to-open-a-pastry-shop · info@aichef.pro

Sheet Settings
A1: Settings
A2: AI Chef Pro · aichef.pro — How to Open a Pastry Shop
A3: The production kitchen's cost per hour is CALCULATED here from your team and your wage table. It isn't an industry figure.
A5: Production kitchen staff | B5: FTE | C5: Pay grade | D5: Monthly base pay ($) | E5: Annual base pay ($) | F5: Annual employer cost ($) | G5: Note
A6: Head Pastry Chef (P1) | B6: 1 | C6: 2 · Management and supervisors | D6: 1784.8625 | E6: =IFERROR(D6*'Settings'!$B$11,"") -> 21418.35 | F6: =IFERROR(E6*B6*(1+'Settings'!$B$12),"") -> 28486.406 | G6: Shift: Early bake (04:30-12:30). Only the PRODUCTION KITCHEN area goes into the hourly cost: the front counter doesn't bake.
A7: Pastry Cook (P2) | B7: 1 | C7: 3 · Skilled specialists | D7: 1721.1375 | E7: =IFERROR(D7*'Settings'!$B$11,"") -> 20653.65 | F7: =IFERROR(E7*B7*(1+'Settings'!$B$12),"") -> 27469.355 | G7: Shift: Early bake (05:00-13:00). Only the PRODUCTION KITCHEN area goes into the hourly cost: the front counter doesn't bake.
A8: Bakery Assistant (P3) | B8: 0.5 | C8: 5 · Support staff | D8: 1490.525 | E8: =IFERROR(D8*'Settings'!$B$11,"") -> 17886.3 | F8: =IFERROR(E8*B8*(1+'Settings'!$B$12),"") -> 11894.39 | G8: Shift: Morning (07:00-11:00). Only the PRODUCTION KITCHEN area goes into the hourly cost: the front counter doesn't bake.
A9: TOTAL PRODUCTION KITCHEN | B9: =SUM(B6:B8) -> 2.5 | C9: FTEs | D9: sum of the three roles | F9: =SUM(F6:F8) -> 67850.15
A11: Pay periods per year | B11: 12 | C11: pay periods | D11: case assumption | G11: 12 monthly payments with no extra-pay months: the annual total is the same as in the case's wage table. Enter the monthly equivalent of what you actually pay.
A12: Payroll taxes, workers' comp and benefits | B12: 0.33 | C12: on base pay | D12: case assumption | G12: What the employer pays on top of base pay: FICA (7.65%), federal and state unemployment tax and workers' comp come to about 10%; the rest of the 33% depends on whether you offer health insurance and paid time off. It's the line that turns base pay into a cost, and the one that surprises people most.
A13: Annual hours actually worked | B13: 1780 | C13: hours/year | D13: assumption | G13: 40 hours times 52 weeks is 2,080, minus paid time off and holidays.
A14: Productive hours as a share of the workday | B14: 0.85 | C14: of the workday | D14: assumption | G14: The part of the workday spent at the bench. The rest is receiving, cleaning, training and meetings: hours you pay for that don't produce.
A15: Productive hours of the production kitchen per year | B15: =IFERROR($B$9*'Settings'!$B$13*'Settings'!$B$14,"") -> 3782.5 | C15: hours/year | D15: calculated | G15: Production kitchen FTEs times annual hours actually worked times the productive share.
A16: PRODUCTIVE HOURLY COST OF THE PRODUCTION KITCHEN | B16: =IFERROR($F$9/'Settings'!$B$15,"") -> 17.937911 | C16: $/hour | D16: calculated | G16: Annual employer cost of the production kitchen divided by its PRODUCTIVE hours (with the 85% factor above). This is the number that goes into every batch, and the one almost nobody charges. Don't confuse it with the "average cost per PAID hour of the team" in staff-schedule-and-labor-cost.xlsx ($14.89) or the "cost per PAID hour of seasonal help" in seasonal-peaks-planner.xlsx ($13.36): all three are right, and each one divides by something different.
A18: Sales tax on what you sell (prices are pre-tax)
A19: Sales tax on pastries sold to go | B19: 0 | C19: on the pre-tax price | D19: your state's rule | G19: 0 by default: in the four example states (CA, TX, NY, FL), bakery items sold to go are generally exempt. Prices in this workbook are before sales tax, so this rate doesn't change any margin.
A20: Sales tax on bread sold to go | B20: 0 | C20: on the pre-tax price | D20: your state's rule | G20: Bread doesn't change your tax: sold to go it follows the same rule as pastries. What it does bring is a full label on any bread you bag yourself (Food Code 3-602.11).
A21: Sales tax on food eaten at your tables | B21: 0 | C21: on the pre-tax price | D21: your state's rule | G21: If you add tables, what's eaten on site is generally taxable. Your POS has to ring up to-go and for-here sales separately (chapter 19 of the guide).
A23: The margin rule: ONE number, and the other is derived
A24: Target food cost | B24: 0.32 | C24: of the price before tax | D24: industry rule (30-35%) | G24: This is the ONLY margin number you type. The industry rule is a 30-35% food cost ON THE SELLING PRICE, which equals a 65-70% gross margin on that same selling price (Toast, a POS vendor, publishes 28-35% for bakeries: third-party estimates, not official figures). Watch out for sources that give the margin ON COST: 65-70% on cost is a food cost of 59-61%, a much weaker number. Before you compare your margin with anyone's, ask what base it's calculated on.
A25: Target gross margin (derived) | B25: =IFERROR(1-'Settings'!$B$24,"") -> 0.68 | C25: of the price before tax | D25: calculated | G25: One minus the target food cost. You don't type it on purpose: asking for both numbers lets them disagree, and that's the most common method mistake in the trade.
A27: Food Code limits (FDA Food Code 2022, checked October 2026)
A28: Cold-holding limit: filled, not shelf-stable | B28: 41 | C28: °F | D28: Food Code 3-501.16 | G28: Filled items that aren't shelf-stable at room temperature are TCS food: hold them at 41 °F or below. Whether an item is TCS depends on its pH and water activity (1-201.10).
A29: Cold-holding limit: egg route needs cold | B29: 41 | C29: °F | D29: Food Code 3-501.16 and 3-501.17 | G29: Items made with egg cooked through or with pasteurized egg product that aren't shelf-stable. The Food Code sets the same 41 °F, so there's no conflict between this row and the one above.
A30: Date-mark trigger (hours held) | B30: 24 | C30: hours | D30: Food Code 3-501.16 and 3-501.17 | G30: Ready-to-eat TCS food held more than 24 hours has to be date marked: 7 days at most at 41 °F or below, with the day you make it as day 1 (3-501.17). It isn't a shelf life: it's a legal ceiling.
A31: Gluten-free threshold | B31: 20 | C31: ppm (mg/kg) | D31: 21 CFR 101.91 | G31: It isn't a free claim: under 20 ppm of gluten in the food as sold. Rice flour isn't enough if your kitchen shares tools with wheat flour.
A33: Waste, packaging and sales
A34: Target trim loss | B34: 0.05 | C34: of production | D34: case assumption | G34: The case's target. If your real waste runs above 10%, review the production plan, not the recipe costing.
A35: Packaging as a share of product cost | B35: 0.1 | C35: of cost | D35: case assumption | G35: 10% of product cost in the case: in pastry the box isn't an extra, it's part of the product. Check it against your own supplier quotes.
A36: Pieces per customer | B36: 2.6 | C36: pieces/ticket | D36: assumption | G36: The average ticket comes from here and you DON'T type it. We found no reliable published average ticket for US bakeries: yours is calculated from your menu and your mix, so you can show it for what it is.
A37: Turnover threshold for the menu traffic light | B37: 1 | C37: % of mix | D37: assumption | G37: Below this share of the mix, an item counts as low turnover on the "Menu Decision" sheet. A house rule, not an industry one: raise it if your menu is shorter.
A39: Purchase prices (the only price table)
A40: Ingredient | B40: Purchase price ($) | C40: Purchase unit | D40: Where it comes from | G40: Note
A41: Sunflower oil | B41: 1.8 | C41: L | D41: assumption
A42: Extra virgin olive oil | B42: 7.2 | C42: L | D42: assumption
A43: Orange blossom water | B43: 14 | C43: L | D43: assumption
A44: Raw Marcona almonds | B44: 15.5 | C44: kg | D44: assumption
A45: Almond meal | B45: 13.5 | C45: kg | D45: assumption
A46: Cornstarch | B46: 2.1 | C46: kg | D46: assumption
A47: Granulated sugar | B47: 1.2 | C47: kg | D47: copied from the kit
A48: Powdered sugar | B48: 2.5 | C48: kg | D48: copied from the kit
A49: Cocoa powder | B49: 12 | C49: kg | D49: copied from the kit
A50: Ground cinnamon | B50: 18 | C50: kg | D50: assumption
A51: White chocolate | B51: 15 | C51: kg | D51: copied from the kit
A52: Dark chocolate 70% | B52: 18 | C52: kg | D52: copied from the kit
... A89: Carrots | B89: 1.1 | C89: kg | D89: assumption
A91: The nineteen prices marked "copied from the kit" are the same ones the Food Cost Kit Pro uses (05-bakery-cake-pricing): they're what make the same croissant cost the same in both products. Watch the butter: the CME price for bulk Grade AA butter that USDA reports every week is NOT the price of the 82% European-style laminating butter a pastry kitchen buys. Use it to track volatility, never to set a price.
A93: Version 1.0 · October 2026 · aichef.pro/en/digital-products/how-to-open-a-pastry-shop · info@aichef.pro

Sheet Batch Costing
A1: Batch Costing
A2: AI Chef Pro · aichef.pro — How to Open a Pastry Shop
A3: The costing unit is THE BATCH, not the piece. Prices come from the single table on "Settings".
A5: Ref | B5: Item | C5: Family | D5: Ingredient | E5: Net quantity | F5: Unit of use | G5: Conversion factor | H5: Trim loss | I5: Gross quantity | J5: Purchase price ($) | K5: Purchase unit | L5: Line cost ($) | M5: Source
A6: B1 | B6: Butter croissant | C6: Viennoiserie | D6: High-gluten flour | E6: 0.5 | F6: kg | G6: 1 | H6: 0.08 | I6: =IFERROR(E6/(1-H6),"") -> 0.54347826 | J6: =IFERROR(VLOOKUP($D6,'Settings'!$A$41:$C$89,2,FALSE),"") -> 1.1 | K6: kg | L6: =IFERROR(I6/G6*J6,"") -> 0.59782609 | M6: EXACT COPY of the Food Cost Kit Pro (05-bakery-cake-pricing, "Croissants" sheet). Same costing in both products: a customer who owns both can't see two different costs for the same piece.
A7: B1 | D7: Laminating butter (82% butterfat) | E7: 0.28 | F7: kg | G7: 1 | H7: 0.03 | I7: =IFERROR(E7/(1-H7),"") -> 0.28865979 | J7: =IFERROR(VLOOKUP($D7,'Settings'!$A$41:$C$89,2,FALSE),"") -> 12 | K7: kg | L7: =IFERROR(I7/G7*J7,"") -> 3.4639175
A8: B1 | D8: Whole milk | E8: 0.15 | F8: L | G8: 1 | H8: 0.03 | I8: =IFERROR(E8/(1-H8),"") -> 0.15463918 | J8: =IFERROR(VLOOKUP($D8,'Settings'!$A$41:$C$89,2,FALSE),"") -> 1.1 | K8: L | L8: =IFERROR(I8/G8*J8,"") -> 0.17010309
A9: B1 | D9: Granulated sugar | E9: 0.06 | F9: kg | G9: 1 | H9: 0.02 | I9: =IFERROR(E9/(1-H9),"") -> 0.06122449 | J9: =IFERROR(VLOOKUP($D9,'Settings'!$A$41:$C$89,2,FALSE),"") -> 1.2 | K9: kg | L9: =IFERROR(I9/G9*J9,"") -> 0.073469388
A10: B1 | D10: Fresh yeast | E10: 0.02 | F10: kg | G10: 1 | H10: 0.05 | I10: =IFERROR(E10/(1-H10),"") -> 0.021052632 | J10: =IFERROR(VLOOKUP($D10,'Settings'!$A$41:$C$89,2,FALSE),"") -> 5 | K10: kg | L10: =IFERROR(I10/G10*J10,"") -> 0.10526316
A11: B1 | D11: Salt | E11: 0.01 | F11: kg | G11: 1 | H11: 0.02 | I11: =IFERROR(E11/(1-H11),"") -> 0.010204082 | J11: =IFERROR(VLOOKUP($D11,'Settings'!$A$41:$C$89,2,FALSE),"") -> 0.6 | K11: kg | L11: =IFERROR(I11/G11*J11,"") -> 0.006122449
A12: B1 | D12: Eggs (for egg wash) | E12: 1 | F12: each | G12: 12 | H12: 0 | I12: =IFERROR(E12/(1-H12),"") -> 1 | J12: =IFERROR(VLOOKUP($D12,'Settings'!$A$41:$C$89,2,FALSE),"") -> 3.6 | K12: dozen | L12: =IFERROR(I12/G12*J12,"") -> 0.3
A13: B2 | B13: Pain au chocolat (chocolate croissant) | C13: Viennoiserie | D13: High-gluten flour | E13: 0.5 | F13: kg | G13: 1 | H13: 0.08 | I13: =IFERROR(E13/(1-H13),"") -> 0.54347826 | J13: =IFERROR(VLOOKUP($D13,'Settings'!$A$41:$C$89,2,FALSE),"") -> 1.1 | K13: kg | L13: =IFERROR(I13/G13*J13,"") -> 0.59782609 | M13: assumption (same dough as B1, from the kit, plus two chocolate batons per piece)
A14: B2 | D14: Laminating butter (82% butterfat) | E14: 0.28 | F14: kg | G14: 1 | H14: 0.03 | I14: =IFERROR(E14/(1-H14),"") -> 0.28865979 | J14: =IFERROR(VLOOKUP($D14,'Settings'!$A$41:$C$89,2,FALSE),"") -> 12 | K14: kg | L14: =IFERROR(I14/G14*J14,"") -> 3.4639175
A15: B2 | D15: Whole milk | E15: 0.15 | F15: L | G15: 1 | H15: 0.03 | I15: =IFERROR(E15/(1-H15),"") -> 0.15463918 | J15: =IFERROR(VLOOKUP($D15,'Settings'!$A$41:$C$89,2,FALSE),"") -> 1.1 | K15: L | L15: =IFERROR(I15/G15*J15,"") -> 0.17010309
A16: B2 | D16: Granulated sugar | E16: 0.06 | F16: kg | G16: 1 | H16: 0.02 | I16: =IFERROR(E16/(1-H16),"") -> 0.06122449 | J16: =IFERROR(VLOOKUP($D16,'Settings'!$A$41:$C$89,2,FALSE),"") -> 1.2 | K16: kg | L16: =IFERROR(I16/G16*J16,"") -> 0.073469388
A17: B2 | D17: Fresh yeast | E17: 0.02 | F17: kg | G17: 1 | H17: 0.05 | I17: =IFERROR(E17/(1-H17),"") -> 0.021052632 | J17: =IFERROR(VLOOKUP($D17,'Settings'!$A$41:$C$89,2,FALSE),"") -> 5 | K17: kg | L17: =IFERROR(I17/G17*J17,"") -> 0.10526316
A18: B2 | D18: Salt | E18: 0.01 | F18: kg | G18: 1 | H18: 0.02 | I18: =IFERROR(E18/(1-H18),"") -> 0.010204082 | J18: =IFERROR(VLOOKUP($D18,'Settings'!$A$41:$C$89,2,FALSE),"") -> 0.6 | K18: kg | L18: =IFERROR(I18/G18*J18,"") -> 0.006122449
A19: B2 | D19: Dark chocolate 70% | E19: 0.2 | F19: kg | G19: 1 | H19: 0.02 | I19: =IFERROR(E19/(1-H19),"") -> 0.20408163 | J19: =IFERROR(VLOOKUP($D19,'Settings'!$A$41:$C$89,2,FALSE),"") -> 18 | K19: kg | L19: =IFERROR(I19/G19*J19,"") -> 3.6734694
A20: B2 | D20: Eggs (for egg wash) | E20: 1 | F20: each | G20: 12 | H20: 0 | I20: =IFERROR(E20/(1-H20),"") -> 1 | J20: =IFERROR(VLOOKUP($D20,'Settings'!$A$41:$C$89,2,FALSE),"") -> 3.6 | K20: dozen | L20: =IFERROR(I20/G20*J20,"") -> 0.3
A21: B3 | B21: Custard napolitana (cream-filled laminated pastry) | C21: Viennoiserie | D21: High-gluten flour | E21: 0.5 | F21: kg | G21: 1 | H21: 0.08 | I21: =IFERROR(E21/(1-H21),"") -> 0.54347826 | J21: =IFERROR(VLOOKUP($D21,'Settings'!$A$41:$C$89,2,FALSE),"") -> 1.1 | K21: kg | L21: =IFERROR(I21/G21*J21,"") -> 0.59782609 | M21: assumption (the kit's dough plus an example pastry cream)
A22: B3 | D22: Laminating butter (82% butterfat) | E22: 0.28 | F22: kg | G22: 1 | H22: 0.03 | I22: =IFERROR(E22/(1-H22),"") -> 0.28865979 | J22: =IFERROR(VLOOKUP($D22,'Settings'!$A$41:$C$89,2,FALSE),"") -> 12 | K22: kg | L22: =IFERROR(I22/G22*J22,"") -> 3.4639175
A23: B3 | D23: Whole milk | E23: 0.15 | F23: L | G23: 1 | H23: 0.03 | I23: =IFERROR(E23/(1-H23),"") -> 0.15463918 | J23: =IFERROR(VLOOKUP($D23,'Settings'!$A$41:$C$89,2,FALSE),"") -> 1.1 | K23: L | L23: =IFERROR(I23/G23*J23,"") -> 0.17010309
A24: B3 | D24: Granulated sugar | E24: 0.06 | F24: kg | G24: 1 | H24: 0.02 | I24: =IFERROR(E24/(1-H24),"") -> 0.06122449 | J24: =IFERROR(VLOOKUP($D24,'Settings'!$A$41:$C$89,2,FALSE),"") -> 1.2 | K24: kg | L24: =IFERROR(I24/G24*J24,"") -> 0.073469388
A25: B3 | D25: Fresh yeast | E25: 0.02 | F25: kg | G25: 1 | H25: 0.05 | I25: =IFERROR(E25/(1-H25),"") -> 0.021052632 | J25: =IFERROR(VLOOKUP($D25,'Settings'!$A$41:$C$89,2,FALSE),"") -> 5 | K25: kg | L25: =IFERROR(I25/G25*J25,"") -> 0.10526316
A26: B3 | D26: Salt | E26: 0.01 | F26: kg | G26: 1 | H26: 0.02 | I26: =IFERROR(E26/(1-H26),"") -> 0.010204082 | J26: =IFERROR(VLOOKUP($D26,'Settings'!$A$41:$C$89,2,FALSE),"") -> 0.6 | K26: kg | L26: =IFERROR(I26/G26*J26,"") -> 0.006122449
A27: B3 | D27: Whole milk | E27: 0.6 | F27: L | G27: 1 | H27: 0.02 | I27: =IFERROR(E27/(1-H27),"") -> 0.6122449 | J27: =IFERROR(VLOOKUP($D27,'Settings'!$A$41:$C$89,2,FALSE),"") -> 1.1 | K27: L | L27: =IFERROR(I27/G27*J27,"") -> 0.67346939
A28: B3 | D28: Granulated sugar | E28: 0.14 | F28: kg | G28: 1 | H28: 0.02 | I28: =IFERROR(E28/(1-H28),"") -> 0.14285714 | J28: =IFERROR(VLOOKUP($D28,'Settings'!$A$41:$C$89,2,FALSE),"") -> 1.2 | K28: kg | L28: =IFERROR(I28/G28*J28,"") -> 0.17142857
A29: B3 | D29: Eggs (each) | E29: 4 | F29: each | G29: 12 | H29: 0 | I29: =IFERROR(E29/(1-H29),"") -> 4 | J29: =IFERROR(VLOOKUP($D29,'Settings'!$A$41:$C$89,2,FALSE),"") -> 3.6 | K29: dozen | L29: =IFERROR(I29/G29*J29,"") -> 1.2
A30: B3 | D30: Cornstarch | E30: 0.05 | F30: kg | G30: 1 | H30: 0.02 | I30: =IFERROR(E30/(1-H30),"") -> 0.051020408 | J30: =IFERROR(VLOOKUP($D30,'Settings'!$A$41:$C$89,2,FALSE),"") -> 2.1 | K30: kg | L30: =IFERROR(I30/G30*J30,"") -> 0.10714286
A31: B3 | D31: Vanilla bean paste | E31: 0.002 | F31: kg | G31: 1 | H31: 0 | I31: =IFERROR(E31/(1-H31),"") -> 0.002 | J31: =IFERROR(VLOOKUP($D31,'Settings'!$A$41:$C$89,2,FALSE),"") -> 92 | K31: kg | L31: =IFERROR(I31/G31*J31,"") -> 0.184
A32: B3 | D32: Eggs (for egg wash) | E32: 1 | F32: each | G32: 12 | H32: 0 | I32: =IFERROR(E32/(1-H32),"") -> 1 | J32: =IFERROR(VLOOKUP($D32,'Settings'!$A$41:$C$89,2,FALSE),"") -> 3.6 | K32: dozen | L32: =IFERROR(I32/G32*J32,"") -> 0.3
A33: B4 | B33: Palmier | C33: Viennoiserie | D33: Pastry flour | E33: 0.45 | F33: kg | G33: 1 | H33: 0.08 | I33: =IFERROR(E33/(1-H33),"") -> 0.48913043 | J33: =IFERROR(VLOOKUP($D33,'Settings'!$A$41:$C$89,2,FALSE),"") -> 0.9 | K33: kg | L33: =IFERROR(I33/G33*J33,"") -> 0.44021739 | M33: assumption
A34: B4 | D34: Laminating butter (82% butterfat) | E34: 0.36 | F34: kg | G34: 1 | H34: 0.03 | I34: =IFERROR(E34/(1-H34),"") -> 0.37113402 | J34: =IFERROR(VLOOKUP($D34,'Settings'!$A$41:$C$89,2,FALSE),"") -> 12 | K34: kg | L34: =IFERROR(I34/G34*J34,"") -> 4.4536082
A35: B4 | D35: Granulated sugar | E35: 0.3 | F35: kg | G35: 1 | H35: 0.02 | I35: =IFERROR(E35/(1-H35),"") -> 0.30612245 | J35: =IFERROR(VLOOKUP($D35,'Settings'!$A$41:$C$89,2,FALSE),"") -> 1.2 | K35: kg | L35: =IFERROR(I35/G35*J35,"") -> 0.36734694
A36: B4 | D36: Salt | E36: 0.01 | F36: kg | G36: 1 | H36: 0.02 | I36: =IFERROR(E36/(1-H36),"") -> 0.010204082 | J36: =IFERROR(VLOOKUP($D36,'Settings'!$A$41:$C$89,2,FALSE),"") -> 0.6 | K36: kg | L36: =IFERROR(I36/G36*J36,"") -> 0.006122449
A37: B5 | B37: Raisin snail (pain aux raisins) | C37: Viennoiserie | D37: High-gluten flour | E37: 0.45 | F37: kg | G37: 1 | H37: 0.08 | I37: =IFERROR(E37/(1-H37),"") -> 0.48913043 | J37: =IFERROR(VLOOKUP($D37,'Settings'!$A$41:$C$89,2,FALSE),"") -> 1.1 | K37: kg | L37: =IFERROR(I37/G37*J37,"") -> 0.53804348 | M37: assumption
A38: B5 | D38: Laminating butter (82% butterfat) | E38: 0.22 | F38: kg | G38: 1 | H38: 0.03 | I38: =IFERROR(E38/(1-H38),"") -> 0.22680412 | J38: =IFERROR(VLOOKUP($D38,'Settings'!$A$41:$C$89,2,FALSE),"") -> 12 | K38: kg | L38: =IFERROR(I38/G38*J38,"") -> 2.7216495
A39: B5 | D39: Whole milk | E39: 0.14 | F39: L | G39: 1 | H39: 0.03 | I39: =IFERROR(E39/(1-H39),"") -> 0.1443299 | J39: =IFERROR(VLOOKUP($D39,'Settings'!$A$41:$C$89,2,FALSE),"") -> 1.1 | K39: L | L39: =IFERROR(I39/G39*J39,"") -> 0.15876289
A40: B5 | D40: Granulated sugar | E40: 0.05 | F40: kg | G40: 1 | H40: 0.02 | I40: =IFERROR(E40/(1-H40),"") -> 0.051020408 | J40: =IFERROR(VLOOKUP($D40,'Settings'!$A$41:$C$89,2,FALSE),"") -> 1.2 | K40: kg | L40: =IFERROR(I40/G40*J40,"") -> 0.06122449
A41: B5 | D41: Fresh yeast | E41: 0.018 | F41: kg | G41: 1 | H41: 0.05 | I41: =IFERROR(E41/(1-H41),"") -> 0.018947368 | J41: =IFERROR(VLOOKUP($D41,'Settings'!$A$41:$C$89,2,FALSE),"") -> 5 | K41: kg | L41: =IFERROR(I41/G41*J41,"") -> 0.094736842
A42: B5 | D42: Salt | E42: 0.009 | F42: kg | G42: 1 | H42: 0.02 | I42: =IFERROR(E42/(1-H42),"") -> 0.0091836735 | J42: =IFERROR(VLOOKUP($D42,'Settings'!$A$41:$C$89,2,FALSE),"") -> 0.6 | K42: kg | L42: =IFERROR(I42/G42*J42,"") -> 0.0055102041
A43: B5 | D43: Raisins | E43: 0.15 | F43: kg | G43: 1 | H43: 0.02 | I43: =IFERROR(E43/(1-H43),"") -> 0.15306122 | J43: =IFERROR(VLOOKUP($D43,'Settings'!$A$41:$C$89,2,FALSE),"") -> 5.2 | K43: kg | L43: =IFERROR(I43/G43*J43,"") -> 0.79591837
A44: B5 | D44: Rum | E44: 0.03 | F44: L | G44: 1 | H44: 0 | I44: =IFERROR(E44/(1-H44),"") -> 0.03 | J44: =IFERROR(VLOOKUP($D44,'Settings'!$A$41:$C$89,2,FALSE),"") -> 9.8 | K44: L | L44: =IFERROR(I44/G44*J44,"") -> 0.294
A45: B5 | D45: Whole milk | E45: 0.35 | F45: L | G45: 1 | H45: 0.02 | I45: =IFERROR(E45/(1-H45),"") -> 0.35714286 | J45: =IFERROR(VLOOKUP($D45,'Settings'!$A$41:$C$89,2,FALSE),"") -> 1.1 | K45: L | L45: =IFERROR(I45/G45*J45,"") -> 0.39285714
A46: B5 | D46: Granulated sugar | E46: 0.08 | F46: kg | G46: 1 | H46: 0.02 | I46: =IFERROR(E46/(1-H46),"") -> 0.081632653 | J46: =IFERROR(VLOOKUP($D46,'Settings'!$A$41:$C$89,2,FALSE),"") -> 1.2 | K46: kg | L46: =IFERROR(I46/G46*J46,"") -> 0.097959184
A47: B5 | D47: Eggs (each) | E47: 2 | F47: each | G47: 12 | H47: 0 | I47: =IFERROR(E47/(1-H47),"") -> 2 | J47: =IFERROR(VLOOKUP($D47,'Settings'!$A$41:$C$89,2,FALSE),"") -> 3.6 | K47: dozen | L47: =IFERROR(I47/G47*J47,"") -> 0.6
A48: B5 | D48: Cornstarch | E48: 0.03 | F48: kg | G48: 1 | H48: 0.02 | I48: =IFERROR(E48/(1-H48),"") -> 0.030612245 | J48: =IFERROR(VLOOKUP($D48,'Settings'!$A$41:$C$89,2,FALSE),"") -> 2.1 | K48: kg | L48: =IFERROR(I48/G48*J48,"") -> 0.064285714
A49: B5 | D49: Eggs (for egg wash) | E49: 1 | F49: each | G49: 12 | H49: 0 | I49: =IFERROR(E49/(1-H49),"") -> 1 | J49: =IFERROR(VLOOKUP($D49,'Settings'!$A$41:$C$89,2,FALSE),"") -> 3.6 | K49: dozen | L49: =IFERROR(I49/G49*J49,"") -> 0.3
A50: B6 | B50: Ensaïmada (Mallorcan spiral pastry) | C50: Viennoiserie | D50: High-gluten flour | E50: 0.6 | F50: kg | G50: 1 | H50: 0.08 | I50: =IFERROR(E50/(1-H50),"") -> 0.65217391 | J50: =IFERROR(VLOOKUP($D50,'Settings'!$A$41:$C$89,2,FALSE),"") -> 1.1 | K50: kg | L50: =IFERROR(I50/G50*J50,"") -> 0.7173913 | M50: assumption
A51: B6 | D51: Lard | E51: 0.2 | F51: kg | G51: 1 | H51: 0.03 | I51: =IFERROR(E51/(1-H51),"") -> 0.20618557 | J51: =IFERROR(VLOOKUP($D51,'Settings'!$A$41:$C$89,2,FALSE),"") -> 4.4 | K51: kg | L51: =IFERROR(I51/G51*J51,"") -> 0.90721649
A52: B6 | D52: Granulated sugar | E52: 0.12 | F52: kg | G52: 1 | H52: 0.02 | I52: =IFERROR(E52/(1-H52),"") -> 0.12244898 | J52: =IFERROR(VLOOKUP($D52,'Settings'!$A$41:$C$89,2,FALSE),"") -> 1.2 | K52: kg | L52: =IFERROR(I52/G52*J52,"") -> 0.14693878
A53: B6 | D53: Eggs (each) | E53: 3 | F53: each | G53: 12 | H53: 0 | I53: =IFERROR(E53/(1-H53),"") -> 3 | J53: =IFERROR(VLOOKUP($D53,'Settings'!$A$41:$C$89,2,FALSE),"") -> 3.6 | K53: dozen | L53: =IFERROR(I53/G53*J53,"") -> 0.9
A54: B6 | D54: Fresh yeast | E54: 0.02 | F54: kg | G54: 1 | H54: 0.05 | I54: =IFERROR(E54/(1-H54),"") -> 0.021052632 | J54: =IFERROR(VLOOKUP($D54,'Settings'!$A$41:$C$89,2,FALSE),"") -> 5 | K54: kg | L54: =IFERROR(I54/G54*J54,"") -> 0.10526316
A55: B6 | D55: Salt | E55: 0.008 | F55: kg | G55: 1 | H55: 0.02 | I55: =IFERROR(E55/(1-H55),"") -> 0.0081632653 | J55: =IFERROR(VLOOKUP($D55,'Settings'!$A$41:$C$89,2,FALSE),"") -> 0.6 | K55: kg | L55: =IFERROR(I55/G55*J55,"") -> 0.0048979592
A56: B6 | D56: Powdered sugar | E56: 0.04 | F56: kg | G56: 1 | H56: 0.02 | I56: =IFERROR(E56/(1-H56),"") -> 0.040816327 | J56: =IFERROR(VLOOKUP($D56,'Settings'!$A$41:$C$89,2,FALSE),"") -> 2.5 | K56: kg | L56: =IFERROR(I56/G56*J56,"") -> 0.10204082
A57: PI1 | B57: Napoleon (mille-feuille) | C57: Individual pastries | D57: Pastry flour | E57: 0.35 | F57: kg | G57: 1 | H57: 0.08 | I57: =IFERROR(E57/(1-H57),"") -> 0.38043478 | J57: =IFERROR(VLOOKUP($D57,'Settings'!$A$41:$C$89,2,FALSE),"") -> 0.9 | K57: kg | L57: =IFERROR(I57/G57*J57,"") -> 0.3423913 | M57: assumption
A58: PI1 | D58: Laminating butter (82% butterfat) | E58: 0.28 | F58: kg | G58: 1 | H58: 0.03 | I58: =IFERROR(E58/(1-H58),"") -> 0.28865979 | J58: =IFERROR(VLOOKUP($D58,'Settings'!$A$41:$C$89,2,FALSE),"") -> 12 | K58: kg | L58: =IFERROR(I58/G58*J58,"") -> 3.4639175
A59: PI1 | D59: Salt | E59: 0.008 | F59: kg | G59: 1 | H59: 0.02 | I59: =IFERROR(E59/(1-H59),"") -> 0.0081632653 | J59: =IFERROR(VLOOKUP($D59,'Settings'!$A$41:$C$89,2,FALSE),"") -> 0.6 | K59: kg | L59: =IFERROR(I59/G59*J59,"") -> 0.0048979592
A60: PI1 | D60: Whole milk | E60: 0.8 | F60: L | G60: 1 | H60: 0.02 | I60: =IFERROR(E60/(1-H60),"") -> 0.81632653 | J60: =IFERROR(VLOOKUP($D60,'Settings'!$A$41:$C$89,2,FALSE),"") -> 1.1 | K60: L | L60: =IFERROR(I60/G60*J60,"") -> 0.89795918
A61: PI1 | D61: Granulated sugar | E61: 0.18 | F61: kg | G61: 1 | H61: 0.02 | I61: =IFERROR(E61/(1-H61),"") -> 0.18367347 | J61: =IFERROR(VLOOKUP($D61,'Settings'!$A$41:$C$89,2,FALSE),"") -> 1.2 | K61: kg | L61: =IFERROR(I61/G61*J61,"") -> 0.22040816
A62: PI1 | D62: Eggs (each) | E62: 5 | F62: each | G62: 12 | H62: 0 | I62: =IFERROR(E62/(1-H62),"") -> 5 | J62: =IFERROR(VLOOKUP($D62,'Settings'!$A$41:$C$89,2,FALSE),"") -> 3.6 | K62: dozen | L62: =IFERROR(I62/G62*J62,"") -> 1.5
A63: PI1 | D63: Cornstarch | E63: 0.06 | F63: kg | G63: 1 | H63: 0.02 | I63: =IFERROR(E63/(1-H63),"") -> 0.06122449 | J63: =IFERROR(VLOOKUP($D63,'Settings'!$A$41:$C$89,2,FALSE),"") -> 2.1 | K63: kg | L63: =IFERROR(I63/G63*J63,"") -> 0.12857143
A64: PI1 | D64: Vanilla bean paste | E64: 0.002 | F64: kg | G64: 1 | H64: 0 | I64: =IFERROR(E64/(1-H64),"") -> 0.002 | J64: =IFERROR(VLOOKUP($D64,'Settings'!$A$41:$C$89,2,FALSE),"") -> 92 | K64: kg | L64: =IFERROR(I64/G64*J64,"") -> 0.184
A65: PI1 | D65: Heavy cream (35% fat) | E65: 0.3 | F65: L | G65: 1 | H65: 0.03 | I65: =IFERROR(E65/(1-H65),"") -> 0.30927835 | J65: =IFERROR(VLOOKUP($D65,'Settings'!$A$41:$C$89,2,FALSE),"") -> 3.8 | K65: L | L65: =IFERROR(I65/G65*J65,"") -> 1.1752577
A66: PI1 | D66: Powdered sugar | E66: 0.05 | F66: kg | G66: 1 | H66: 0.02 | I66: =IFERROR(E66/(1-H66),"") -> 0.051020408 | J66: =IFERROR(VLOOKUP($D66,'Settings'!$A$41:$C$89,2,FALSE),"") -> 2.5 | K66: kg | L66: =IFERROR(I66/G66*J66,"") -> 0.12755102
A67: PI2 | B67: Éclair | C67: Individual pastries | D67: Pastry flour | E67: 0.18 | F67: kg | G67: 1 | H67: 0.08 | I67: =IFERROR(E67/(1-H67),"") -> 0.19565217 | J67: =IFERROR(VLOOKUP($D67,'Settings'!$A$41:$C$89,2,FALSE),"") -> 0.9 | K67: kg | L67: =IFERROR(I67/G67*J67,"") -> 0.17608696 | M67: assumption
A68: PI2 | D68: Butter | E68: 0.14 | F68: kg | G68: 1 | H68: 0.03 | I68: =IFERROR(E68/(1-H68),"") -> 0.1443299 | J68: =IFERROR(VLOOKUP($D68,'Settings'!$A$41:$C$89,2,FALSE),"") -> 9 | K68: kg | L68: =IFERROR(I68/G68*J68,"") -> 1.2989691
A69: PI2 | D69: Eggs (each) | E69: 6 | F69: each | G69: 12 | H69: 0 | I69: =IFERROR(E69/(1-H69),"") -> 6 | J69: =IFERROR(VLOOKUP($D69,'Settings'!$A$41:$C$89,2,FALSE),"") -> 3.6 | K69: dozen | L69: =IFERROR(I69/G69*J69,"") -> 1.8
A70: PI2 | D70: Salt | E70: 0.004 | F70: kg | G70: 1 | H70: 0.02 | I70: =IFERROR(E70/(1-H70),"") -> 0.0040816327 | J70: =IFERROR(VLOOKUP($D70,'Settings'!$A$41:$C$89,2,FALSE),"") -> 0.6 | K70: kg | L70: =IFERROR(I70/G70*J70,"") -> 0.0024489796
A71: PI2 | D71: Whole milk | E71: 0.7 | F71: L | G71: 1 | H71: 0.02 | I71: =IFERROR(E71/(1-H71),"") -> 0.71428571 | J71: =IFERROR(VLOOKUP($D71,'Settings'!$A$41:$C$89,2,FALSE),"") -> 1.1 | K71: L | L71: =IFERROR(I71/G71*J71,"") -> 0.78571429
A72: PI2 | D72: Granulated sugar | E72: 0.16 | F72: kg | G72: 1 | H72: 0.02 | I72: =IFERROR(E72/(1-H72),"") -> 0.16326531 | J72: =IFERROR(VLOOKUP($D72,'Settings'!$A$41:$C$89,2,FALSE),"") -> 1.2 | K72: kg | L72: =IFERROR(I72/G72*J72,"") -> 0.19591837
A73: PI2 | D73: Eggs (each) | E73: 4 | F73: each | G73: 12 | H73: 0 | I73: =IFERROR(E73/(1-H73),"") -> 4 | J73: =IFERROR(VLOOKUP($D73,'Settings'!$A$41:$C$89,2,FALSE),"") -> 3.6 | K73: dozen | L73: =IFERROR(I73/G73*J73,"") -> 1.2
A74: PI2 | D74: Cornstarch | E74: 0.055 | F74: kg | G74: 1 | H74: 0.02 | I74: =IFERROR(E74/(1-H74),"") -> 0.056122449 | J74: =IFERROR(VLOOKUP($D74,'Settings'!$A$41:$C$89,2,FALSE),"") -> 2.1 | K74: kg | L74: =IFERROR(I74/G74*J74,"") -> 0.11785714
A75: PI2 | D75: Vanilla bean paste | E75: 0.002 | F75: kg | G75: 1 | H75: 0 | I75: =IFERROR(E75/(1-H75),"") -> 0.002 | J75: =IFERROR(VLOOKUP($D75,'Settings'!$A$41:$C$89,2,FALSE),"") -> 92 | K75: kg | L75: =IFERROR(I75/G75*J75,"") -> 0.184
A76: PI2 | D76: Dark chocolate 70% | E76: 0.12 | F76: kg | G76: 1 | H76: 0.02 | I76: =IFERROR(E76/(1-H76),"") -> 0.12244898 | J76: =IFERROR(VLOOKUP($D76,'Settings'!$A$41:$C$89,2,FALSE),"") -> 18 | K76: kg | L76: =IFERROR(I76/G76*J76,"") -> 2.2040816
A77: PI2 | D77: Powdered sugar | E77: 0.06 | F77: kg | G77: 1 | H77: 0.02 | I77: =IFERROR(E77/(1-H77),"") -> 0.06122449 | J77: =IFERROR(VLOOKUP($D77,'Settings'!$A$41:$C$89,2,FALSE),"") -> 2.5 | K77: kg | L77: =IFERROR(I77/G77*J77,"") -> 0.15306122
A78: PI3 | B78: Raspberry macarons | C78: Individual pastries | D78: Almond flour | E78: 0.15 | F78: kg | G78: 1 | H78: 0.02 | I78: =IFERROR(E78/(1-H78),"") -> 0.15306122 | J78: =IFERROR(VLOOKUP($D78,'Settings'!$A$41:$C$89,2,FALSE),"") -> 14 | K78: kg | L78: =IFERROR(I78/G78*J78,"") -> 2.1428571 | M78: EXACT COPY of the Food Cost Kit Pro (05-bakery-cake-pricing, "Macarons" sheet). Same costing in both products: a customer who owns both can't see two different costs for the same piece.
A79: PI3 | D79: Powdered sugar | E79: 0.15 | F79: kg | G79: 1 | H79: 0.02 | I79: =IFERROR(E79/(1-H79),"") -> 0.15306122 | J79: =IFERROR(VLOOKUP($D79,'Settings'!$A$41:$C$89,2,FALSE),"") -> 2.5 | K79: kg | L79: =IFERROR(I79/G79*J79,"") -> 0.38265306
A80: PI3 | D80: Egg whites | E80: 0.11 | F80: kg | G80: 1 | H80: 0.05 | I80: =IFERROR(E80/(1-H80),"") -> 0.11578947 | J80: =IFERROR(VLOOKUP($D80,'Settings'!$A$41:$C$89,2,FALSE),"") -> 6 | K80: kg | L80: =IFERROR(I80/G80*J80,"") -> 0.69473684
A81: PI3 | D81: Granulated sugar | E81: 0.15 | F81: kg | G81: 1 | H81: 0.02 | I81: =IFERROR(E81/(1-H81),"") -> 0.15306122 | J81: =IFERROR(VLOOKUP($D81,'Settings'!$A$41:$C$89,2,FALSE),"") -> 1.2 | K81: kg | L81: =IFERROR(I81/G81*J81,"") -> 0.18367347
A82: PI3 | D82: Frozen raspberries | E82: 0.1 | F82: kg | G82: 1 | H82: 0.07 | I82: =IFERROR(E82/(1-H82),"") -> 0.10752688 | J82: =IFERROR(VLOOKUP($D82,'Settings'!$A$41:$C$89,2,FALSE),"") -> 9 | K82: kg | L82: =IFERROR(I82/G82*J82,"") -> 0.96774194
A83: PI3 | D83: White chocolate | E83: 0.08 | F83: kg | G83: 1 | H83: 0.12 | I83: =IFERROR(E83/(1-H83),"") -> 0.090909091 | J83: =IFERROR(VLOOKUP($D83,'Settings'!$A$41:$C$89,2,FALSE),"") -> 15 | K83: kg | L83: =IFERROR(I83/G83*J83,"") -> 1.3636364
A84: PI3 | D84: Red food coloring (50 g jar · 2 g per batch) | E84: 0.04 | F84: each | G84: 1 | H84: 0 | I84: =IFERROR(E84/(1-H84),"") -> 0.04 | J84: =IFERROR(VLOOKUP($D84,'Settings'!$A$41:$C$89,2,FALSE),"") -> 4 | K84: each | L84: =IFERROR(I84/G84*J84,"") -> 0.16
A85: PI4 | B85: Fruit tart | C85: Individual pastries | D85: Pastry flour | E85: 0.4 | F85: kg | G85: 1 | H85: 0.08 | I85: =IFERROR(E85/(1-H85),"") -> 0.43478261 | J85: =IFERROR(VLOOKUP($D85,'Settings'!$A$41:$C$89,2,FALSE),"") -> 0.9 | K85: kg | L85: =IFERROR(I85/G85*J85,"") -> 0.39130435 | M85: assumption
A86: PI4 | D86: Butter | E86: 0.2 | F86: kg | G86: 1 | H86: 0.03 | I86: =IFERROR(E86/(1-H86),"") -> 0.20618557 | J86: =IFERROR(VLOOKUP($D86,'Settings'!$A$41:$C$89,2,FALSE),"") -> 9 | K86: kg | L86: =IFERROR(I86/G86*J86,"") -> 1.8556701
A87: PI4 | D87: Powdered sugar | E87: 0.12 | F87: kg | G87: 1 | H87: 0.02 | I87: =IFERROR(E87/(1-H87),"") -> 0.12244898 | J87: =IFERROR(VLOOKUP($D87,'Settings'!$A$41:$C$89,2,FALSE),"") -> 2.5 | K87: kg | L87: =IFERROR(I87/G87*J87,"") -> 0.30612245
A88: PI4 | D88: Eggs (each) | E88: 2 | F88: each | G88: 12 | H88: 0 | I88: =IFERROR(E88/(1-H88),"") -> 2 | J88: =IFERROR(VLOOKUP($D88,'Settings'!$A$41:$C$89,2,FALSE),"") -> 3.6 | K88: dozen | L88: =IFERROR(I88/G88*J88,"") -> 0.6
A89: PI4 | D89: Salt | E89: 0.004 | F89: kg | G89: 1 | H89: 0.02 | I89: =IFERROR(E89/(1-H89),"") -> 0.0040816327 | J89: =IFERROR(VLOOKUP($D89,'Settings'!$A$41:$C$89,2,FALSE),"") -> 0.6 | K89: kg | L89: =IFERROR(I89/G89*J89,"") -> 0.0024489796
A90: PI4 | D90: Whole milk | E90: 0.5 | F90: L | G90: 1 | H90: 0.02 | I90: =IFERROR(E90/(1-H90),"") -> 0.51020408 | J90: =IFERROR(VLOOKUP($D90,'Settings'!$A$41:$C$89,2,FALSE),"") -> 1.1 | K90: L | L90: =IFERROR(I90/G90*J90,"") -> 0.56122449
A91: PI4 | D91: Granulated sugar | E91: 0.11 | F91: kg | G91: 1 | H91: 0.02 | I91: =IFERROR(E91/(1-H91),"") -> 0.1122449 | J91: =IFERROR(VLOOKUP($D91,'Settings'!$A$41:$C$89,2,FALSE),"") -> 1.2 | K91: kg | L91: =IFERROR(I91/G91*J91,"") -> 0.13469388
A92: PI4 | D92: Eggs (each) | E92: 3 | F92: each | G92: 12 | H92: 0 | I92: =IFERROR(E92/(1-H92),"") -> 3 | J92: =IFERROR(VLOOKUP($D92,'Settings'!$A$41:$C$89,2,FALSE),"") -> 3.6 | K92: dozen | L92: =IFERROR(I92/G92*J92,"") -> 0.9
A93: PI4 | D93: Cornstarch | E93: 0.04 | F93: kg | G93: 1 | H93: 0.02 | I93: =IFERROR(E93/(1-H93),"") -> 0.040816327 | J93: =IFERROR(VLOOKUP($D93,'Settings'!$A$41:$C$89,2,FALSE),"") -> 2.1 | K93: kg | L93: =IFERROR(I93/G93*J93,"") -> 0.085714286
A94: PI4 | D94: Fresh strawberries | E94: 0.35 | F94: kg | G94: 1 | H94: 0.12 | I94: =IFERROR(E94/(1-H94),"") -> 0.39772727 | J94: =IFERROR(VLOOKUP($D94,'Settings'!$A$41:$C$89,2,FALSE),"") -> 6.2 | K94: kg | L94: =IFERROR(I94/G94*J94,"") -> 2.4659091
A95: PI4 | D95: Kiwi | E95: 0.2 | F95: kg | G95: 1 | H95: 0.18 | I95: =IFERROR(E95/(1-H95),"") -> 0.24390244 | J95: =IFERROR(VLOOKUP($D95,'Settings'!$A$41:$C$89,2,FALSE),"") -> 2.6 | K95: kg | L95: =IFERROR(I95/G95*J95,"") -> 0.63414634
A96: PI4 | D96: Frozen mixed berries | E96: 0.15 | F96: kg | G96: 1 | H96: 0.03 | I96: =IFERROR(E96/(1-H96),"") -> 0.15463918 | J96: =IFERROR(VLOOKUP($D96,'Settings'!$A$41:$C$89,2,FALSE),"") -> 10.5 | K96: kg | L96: =IFERROR(I96/G96*J96,"") -> 1.6237113
A97: PI4 | D97: Neutral mirror glaze | E97: 0.08 | F97: kg | G97: 1 | H97: 0.02 | I97: =IFERROR(E97/(1-H97),"") -> 0.081632653 | J97: =IFERROR(VLOOKUP($D97,'Settings'!$A$41:$C$89,2,FALSE),"") -> 11.5 | K97: kg | L97: =IFERROR(I97/G97*J97,"") -> 0.93877551
A98: PI5 | B98: Cream puff (profiterole) | C98: Individual pastries | D98: Pastry flour | E98: 0.2 | F98: kg | G98: 1 | H98: 0.08 | I98: =IFERROR(E98/(1-H98),"") -> 0.2173913 | J98: =IFERROR(VLOOKUP($D98,'Settings'!$A$41:$C$89,2,FALSE),"") -> 0.9 | K98: kg | L98: =IFERROR(I98/G98*J98,"") -> 0.19565217 | M98: assumption
A99: PI5 | D99: Butter | E99: 0.16 | F99: kg | G99: 1 | H99: 0.03 | I99: =IFERROR(E99/(1-H99),"") -> 0.16494845 | J99: =IFERROR(VLOOKUP($D99,'Settings'!$A$41:$C$89,2,FALSE),"") -> 9 | K99: kg | L99: =IFERROR(I99/G99*J99,"") -> 1.4845361
A100: PI5 | D100: Eggs (each) | E100: 7 | F100: each | G100: 12 | H100: 0 | I100: =IFERROR(E100/(1-H100),"") -> 7 | J100: =IFERROR(VLOOKUP($D100,'Settings'!$A$41:$C$89,2,FALSE),"") -> 3.6 | K100: dozen | L100: =IFERROR(I100/G100*J100,"") -> 2.1
A101: PI5 | D101: Salt | E101: 0.004 | F101: kg | G101: 1 | H101: 0.02 | I101: =IFERROR(E101/(1-H101),"") -> 0.0040816327 | J101: =IFERROR(VLOOKUP($D101,'Settings'!$A$41:$C$89,2,FALSE),"") -> 0.6 | K101: kg | L101: =IFERROR(I101/G101*J101,"") -> 0.0024489796
...

Sheet Labor Cost per Hour
A1: Labor Cost per Hour
A2: AI Chef Pro · aichef.pro — How to Open a Pastry Shop
A3: Labor charged per piece. It's the sheet that teaches you to stop giving your work away.
A5: Ref | B5: Item | C5: Family | D5: Units per batch | E5: Labor minutes per batch | F5: Labor hours per batch | G5: Production kitchen cost per hour ($) | H5: Labor cost of the batch ($) | I5: Labor per unit ($) | J5: Materials per unit ($) | K5: Total cost per unit ($) | L5: Menu price ($) | M5: VAT/GST included (0 in the US) | N5: Price before tax ($) | O5: Food cost | P5: Gross margin | Q5: Margin per unit ($) | R5: Labor share of total cost | S5: Minutes per piece
A6: B1 | B6: Butter croissant | C6: Viennoiserie | D6: ='Batch Costing'!D236 -> 20 | E6: 55 | F6: =IFERROR(E6/60,"") -> 0.91666667 | G6: ='Settings'!$B$16 -> 17.937911 | H6: =IFERROR(F6*G6,"") -> 16.443085 | I6: =IFERROR(H6/D6,"") -> 0.82215427 | J6: ='Batch Costing'!G236 -> 0.23583509 | K6: =IFERROR(I6+J6,"") -> 1.0579894 | L6: 1.4545455 | M6: 0 | N6: =IFERROR(L6/(1+M6),"") -> 1.4545455 | O6: =IFERROR(J6/N6,"") -> 0.16213662 | P6: =IFERROR(1-O6,"") -> 0.83786338 | Q6: =IFERROR(N6-K6,"") -> 0.3965561 | R6: =IFERROR(I6/K6,"") -> 0.77709125 | S6: =IFERROR(E6/D6,"") -> 2.75
A7: B2 | B7: Pain au chocolat (chocolate croissant) | C7: Viennoiserie | D7: ='Batch Costing'!D237 -> 20 | E7: 55 | F7: =IFERROR(E7/60,"") -> 0.91666667 | G7: ='Settings'!$B$16 -> 17.937911 | H7: =IFERROR(F7*G7,"") -> 16.443085 | I7: =IFERROR(H7/D7,"") -> 0.82215427 | J7: ='Batch Costing'!G237 -> 0.41950855 | K7: =IFERROR(I7+J7,"") -> 1.2416628 | L7: 1.6818182 | M7: 0 | N7: =IFERROR(L7/(1+M7),"") -> 1.6818182 | O7: =IFERROR(J7/N7,"") -> 0.24943752 | P7: =IFERROR(1-O7,"") -> 0.75056248 | Q7: =IFERROR(N7-K7,"") -> 0.44015536 | R7: =IFERROR(I7/K7,"") -> 0.66213972 | S7: =IFERROR(E7/D7,"") -> 2.75
A8: B3 | B8: Custard napolitana (cream-filled laminated pastry) | C8: Viennoiserie | D8: ='Batch Costing'!D238 -> 20 | E8: 65 | F8: =IFERROR(E8/60,"") -> 1.0833333 | G8: ='Settings'!$B$16 -> 17.937911 | H8: =IFERROR(F8*G8,"") -> 19.432737 | I8: =IFERROR(H8/D8,"") -> 0.97163686 | J8: ='Batch Costing'!G238 -> 0.35263713 | K8: =IFERROR(I8+J8,"") -> 1.324274 | L8: 1.6818182 | M8: 0 | N8: =IFERROR(L8/(1+M8),"") -> 1.6818182 | O8: =IFERROR(J8/N8,"") -> 0.20967613 | P8: =IFERROR(1-O8,"") -> 0.79032387 | Q8: =IFERROR(N8-K8,"") -> 0.35754419 | R8: =IFERROR(I8/K8,"") -> 0.73371287 | S8: =IFERROR(E8/D8,"") -> 3.25
A9: B4 | B9: Palmier | C9: Viennoiserie | D9: ='Batch Costing'!D239 -> 24 | E9: 40 | F9: =IFERROR(E9/60,"") -> 0.66666667 | G9: ='Settings'!$B$16 -> 17.937911 | H9: =IFERROR(F9*G9,"") -> 11.958608 | I9: =IFERROR(H9/D9,"") -> 0.49827531 | J9: ='Batch Costing'!G239 -> 0.21947063 | K9: =IFERROR(I9+J9,"") -> 0.71774594 | L9: 1.5454545 | M9: 0 | N9: =IFERROR(L9/(1+M9),"") -> 1.5454545 | O9: =IFERROR(J9/N9,"") -> 0.14201041 | P9: =IFERROR(1-O9,"") -> 0.85798959 | Q9: =IFERROR(N9-K9,"") -> 0.82770861 | R9: =IFERROR(I9/K9,"") -> 0.69422241 | S9: =IFERROR(E9/D9,"") -> 1.6666667
A10: B5 | B10: Raisin snail (pain aux raisins) | C10: Viennoiserie | D10: ='Batch Costing'!D240 -> 20 | E10: 60 | F10: =IFERROR(E10/60,"") -> 1 | G10: ='Settings'!$B$16 -> 17.937911 | H10: =IFERROR(F10*G10,"") -> 17.937911 | I10: =IFERROR(H10/D10,"") -> 0.89689557 | J10: ='Batch Costing'!G240 -> 0.30624739 | K10: =IFERROR(I10+J10,"") -> 1.203143 | L10: 1.6818182 | M10: 0 | N10: =IFERROR(L10/(1+M10),"") -> 1.6818182 | O10: =IFERROR(J10/N10,"") -> 0.18209304 | P10: =IFERROR(1-O10,"") -> 0.81790696 | Q10: =IFERROR(N10-K10,"") -> 0.47867523 | R10: =IFERROR(I10/K10,"") -> 0.74546051 | S10: =IFERROR(E10/D10,"") -> 3
A11: B6 | B11: Ensaïmada (Mallorcan spiral pastry) | C11: Viennoiserie | D11: ='Batch Costing'!D241 -> 16 | E11: 70 | F11: =IFERROR(E11/60,"") -> 1.1666667 | G11: ='Settings'!$B$16 -> 17.937911 | H11: =IFERROR(F11*G11,"") -> 20.927563 | I11: =IFERROR(H11/D11,"") -> 1.3079727 | J11: ='Batch Costing'!G241 -> 0.18023428 | K11: =IFERROR(I11+J11,"") -> 1.488207 | L11: 1.7727273 | M11: 0 | N11: =IFERROR(L11/(1+M11),"") -> 1.7727273 | O11: =IFERROR(J11/N11,"") -> 0.10167062 | P11: =IFERROR(1-O11,"") -> 0.89832938 | Q11: =IFERROR(N11-K11,"") -> 0.28452029 | R11: =IFERROR(I11/K11,"") -> 0.87889166 | S11: =IFERROR(E11/D11,"") -> 4.375
A12: PI1 | B12: Napoleon (mille-feuille) | C12: Individual pastries | D12: ='Batch Costing'!D242 -> 18 | E12: 75 | F12: =IFERROR(E12/60,"") -> 1.25 | G12: ='Settings'!$B$16 -> 17.937911 | H12: =IFERROR(F12*G12,"") -> 22.422389 | I12: =IFERROR(H12/D12,"") -> 1.2456883 | J12: ='Batch Costing'!G242 -> 0.44694191 | K12: =IFERROR(I12+J12,"") -> 1.6926302 | L12: 3.2727273 | M12: 0 | N12: =IFERROR(L12/(1+M12),"") -> 3.2727273 | O12: =IFERROR(J12/N12,"") -> 0.13656558 | P12: =IFERROR(1-O12,"") -> 0.86343442 | Q12: =IFERROR(N12-K12,"") -> 1.5800971 | R12: =IFERROR(I12/K12,"") -> 0.73594828 | S12: =IFERROR(E12/D12,"") -> 4.1666667
A13: PI2 | B13: Éclair | C13: Individual pastries | D13: ='Batch Costing'!D243 -> 24 | E13: 65 | F13: =IFERROR(E13/60,"") -> 1.0833333 | G13: ='Settings'!$B$16 -> 17.937911 | H13: =IFERROR(F13*G13,"") -> 19.432737 | I13: =IFERROR(H13/D13,"") -> 0.80969739 | J13: ='Batch Costing'!G243 -> 0.33825574 | K13: =IFERROR(I13+J13,"") -> 1.1479531 | L13: 2.9090909 | M13: 0 | N13: =IFERROR(L13/(1+M13),"") -> 2.9090909 | O13: =IFERROR(J13/N13,"") -> 0.11627541 | P13: =IFERROR(1-O13,"") -> 0.88372459 | Q13: =IFERROR(N13-K13,"") -> 1.7611378 | R13: =IFERROR(I13/K13,"") -> 0.70534011 | S13: =IFERROR(E13/D13,"") -> 2.7083333
A14: PI3 | B14: Raspberry macarons | C14: Individual pastries | D14: ='Batch Costing'!D244 -> 30 | E14: 80 | F14: =IFERROR(E14/60,"") -> 1.3333333 | G14: ='Settings'!$B$16 -> 17.937911 | H14: =IFERROR(F14*G14,"") -> 23.917215 | I14: =IFERROR(H14/D14,"") -> 0.7972405 | J14: ='Batch Costing'!G244 -> 0.19650996 | K14: =IFERROR(I14+J14,"") -> 0.99375046 | L14: 1.9090909 | M14: 0 | N14: =IFERROR(L14/(1+M14),"") -> 1.9090909 | O14: =IFERROR(J14/N14,"") -> 0.10293379 | P14: =IFERROR(1-O14,"") -> 0.89706621 | Q14: =IFERROR(N14-K14,"") -> 0.91534045 | R14: =IFERROR(I14/K14,"") -> 0.80225422 | S14: =IFERROR(E14/D14,"") -> 2.6666667
A15: PI4 | B15: Fruit tart | C15: Individual pastries | D15: ='Batch Costing'!D245 -> 20 | E15: 85 | F15: =IFERROR(E15/60,"") -> 1.4166667 | G15: ='Settings'!$B$16 -> 17.937911 | H15: =IFERROR(F15*G15,"") -> 25.412041 | I15: =IFERROR(H15/D15,"") -> 1.2706021 | J15: ='Batch Costing'!G245 -> 0.52498604 | K15: =IFERROR(I15+J15,"") -> 1.7955881 | L15: 3.4545455 | M15: 0 | N15: =IFERROR(L15/(1+M15),"") -> 3.4545455 | O15: =IFERROR(J15/N15,"") -> 0.15196964 | P15: =IFERROR(1-O15,"") -> 0.84803036 | Q15: =IFERROR(N15-K15,"") -> 1.6589574 | R15: =IFERROR(I15/K15,"") -> 0.70762446 | S15: =IFERROR(E15/D15,"") -> 4.25
A16: PI5 | B16: Cream puff (profiterole) | C16: Individual pastries | D16: ='Batch Costing'!D246 -> 40 | E16: 60 | F16: =IFERROR(E16/60,"") -> 1 | G16: ='Settings'!$B$16 -> 17.937911 | H16: =IFERROR(F16*G16,"") -> 17.937911 | I16: =IFERROR(H16/D16,"") -> 0.44844778 | J16: ='Batch Costing'!G246 -> 0.19817681 | K16: =IFERROR(I16+J16,"") -> 0.64662459 | L16: 2.0909091 | M16: 0 | N16: =IFERROR(L16/(1+M16),"") -> 2.0909091 | O16: =IFERROR(J16/N16,"") -> 0.094780213 | P16: =IFERROR(1-O16,"") -> 0.90521979 | Q16: =IFERROR(N16-K16,"") -> 1.4442845 | R16: =IFERROR(I16/K16,"") -> 0.69352108 | S16: =IFERROR(E16/D16,"") -> 1.5
A17: PI6 | B17: Individual entremet (mousse cake) | C17: Individual pastries | D17: ='Batch Costing'!D247 -> 16 | E17: 95 | F17: =IFERROR(E17/60,"") -> 1.5833333 | G17: ='Settings'!$B$16 -> 17.937911 | H17: =IFERROR(F17*G17,"") -> 28.401693 | I17: =IFERROR(H17/D17,"") -> 1.7751058 | J17: ='Batch Costing'!G247 -> 0.82474126 | K17: =IFERROR(I17+J17,"") -> 2.5998471 | L17: 4.0909091 | M17: 0 | N17: =IFERROR(L17/(1+M17),"") -> 4.0909091 | O17: =IFERROR(J17/N17,"") -> 0.20160342 | P17: =IFERROR(1-O17,"") -> 0.79839658 | Q17: =IFERROR(N17-K17,"") -> 1.491062 | R17: =IFERROR(I17/K17,"") -> 0.68277316 | S17: =IFERROR(E17/D17,"") -> 5.9375
... A35: TP8 | B35: Mona de Pascua (Catalan Easter cake) | C35: Seasonal | D35: ='Batch Costing'!D265 -> 14 | E35: 80 | F35: =IFERROR(E35/60,"") -> 1.3333333 | G35: ='Settings'!$B$16 -> 17.937911 | H35: =IFERROR(F35*G35,"") -> 23.917215 | I35: =IFERROR(H35/D35,"") -> 1.7083725 | J35: ='Batch Costing'!G265 -> 2.0148755 | K35: =IFERROR(I35+J35,"") -> 3.723248 | L35: 12.272727 | M35: 0 | N35: =IFERROR(L35/(1+M35),"") -> 12.272727 | O35: =IFERROR(J35/N35,"") -> 0.16417504 | P35: =IFERROR(1-O35,"") -> 0.83582496 | Q35: =IFERROR(N35-K35,"") -> 8.5494793 | R35: =IFERROR(I35/K35,"") -> 0.4588393 | S35: =IFERROR(E35/D35,"") -> 5.7142857
A36: AVERAGE / TOTAL | H36: =SUM(H6:H35) -> 542.62182 | O36: =IFERROR(AVERAGE(O6:O35),"") -> 0.19140911 | Q36: =IFERROR(AVERAGE(Q6:Q35),"") -> 1.7494637 | R36: =IFERROR(AVERAGE(R6:R35),"") -> 0.63296267
A38: The food cost on this sheet compares INGREDIENTS with the price before tax, which is the industry definition. Labor isn't in food cost: it's in total cost, and it eats the margin. That's why an item can have a great food cost and leave you less money than a worse one: always look at both columns together.
A39: The gross margin in column P is one minus food cost, calculated, not typed. It's the same rule said the other way around, which is why the workbook never asks you for both numbers.
A40: Column R is the one that hurts: on the most labor-intensive items, labor is more than half the cost. You don't win there by cutting the price of flour; you win by changing the process or the price.
A41: Red food cost cells are the ones over your target in "Settings"; red margin cells are the ones that leave no money. What to do with them is on the "Menu Decision" sheet.
A43: Version 1.0 · October 2026 · aichef.pro/en/digital-products/how-to-open-a-pastry-shop · info@aichef.pro

Sheet Egg & TCS Decision
A1: Egg & TCS Decision
A2: AI Chef Pro · aichef.pro — How to Open a Pastry Shop
A3: Two separate outputs: the HOLDING TEMPERATURE (41 °F or below for TCS items, Food Code 3-501.16) and the DATE MARK for TCS items held more than 24 hours (3-501.17). The shelf life is yours to declare.
A5: Ref | B5: Item | C5: Family | D5: Egg route | E5: Filled item? | F5: Shelf-stable at room temperature? | G5: Food Code cold-holding limit (°F), 3-501.16 · filled item | H5: Food Code cold-holding limit (°F), 3-501.16 · egg route | I5: Holding temperature (°F) | J5: Which test applies | K5: Date-mark if held over (hours) | L5: Shelf life you declare (days) | M5: Where it goes at the counter | N5: What that route means | O5: D / F check
A6: B1 | B6: Butter croissant | C6: Viennoiserie | D6: Shelf-stable | E6: No | F6: Yes | G6: =IF(AND($E6="Yes",$F6="No"),'Settings'!$B$28,"") | H6: =IF(AND(OR($D6="Cooked through",$D6="Pasteurized egg product"),$F6="No"),'Settings'!$B$29,"") | I6: =IF(AND(G6="",H6=""),"",IF(G6="",H6,IF(H6="",G6,MIN(G6,H6)))) | J6: =IF(AND(G6="",H6=""),"Neither test applies: shelf-stable at room temperature, so it goes in the room-temperature case.",IF(AND(G6<>"",H6<>""),"Both tests apply and both limits are 41 °F (Food Code 3-501.16): no conflict, the same limit twice.",IF(G6<>"","Filled and not shelf-stable at room temperature: TCS food, hold at 41 °F or below (3-501.16).","Its egg route leaves it needing cold (cooked through or pasteurized egg product, not shelf-stable): TCS food, hold at 41 °F or below (3-501.16)."))) -> Neither test applies: shelf-stable at room temperature, so it goes in the room-temperature case. | K6: =IF(AND(OR($D6="Cooked through",$D6="Pasteurized egg product"),$F6="No"),'Settings'!$B$30,"N/A") -> N/A | L6: Declare in your food safety plan | M6: =IF(I6="","Room-temperature case","Refrigerated case") -> Room-temperature case | N6: Shelf-stable route: the finished item is shelf-stable at room temperature (pH and water activity, Food Code 1-201.10), so it isn't TCS: no cold-holding limit and no date mark, even if it's filled. | O6: =IF(AND($D6="Shelf-stable",$F6="No"),"Mismatch: you chose the shelf-stable route and then said it isn't shelf-stable","")
A7: B2 | B7: Pain au chocolat (chocolate croissant) | C7: Viennoiserie | D7: Shelf-stable | E7: No | F7: Yes | G7: =IF(AND($E7="Yes",$F7="No"),'Settings'!$B$28,"") | H7: =IF(AND(OR($D7="Cooked through",$D7="Pasteurized egg product"),$F7="No"),'Settings'!$B$29,"") | I7: =IF(AND(G7="",H7=""),"",IF(G7="",H7,IF(H7="",G7,MIN(G7,H7)))) | J7: =IF(AND(G7="",H7=""),"Neither test applies: shelf-stable at room temperature, so it goes in the room-temperature case.",IF(AND(G7<>"",H7<>""),"Both tests apply and both limits are 41 °F (Food Code 3-501.16): no conflict, the same limit twice.",IF(G7<>"","Filled and not shelf-stable at room temperature: TCS food, hold at 41 °F or below (3-501.16).","Its egg route leaves it needing cold (cooked through or pasteurized egg product, not shelf-stable): TCS food, hold at 41 °F or below (3-501.16)."))) -> Neither test applies: shelf-stable at room temperature, so it goes in the room-temperature case. | K7: =IF(AND(OR($D7="Cooked through",$D7="Pasteurized egg product"),$F7="No"),'Settings'!$B$30,"N/A") -> N/A | L7: Declare in your food safety plan | M7: =IF(I7="","Room-temperature case","Refrigerated case") -> Room-temperature case | N7: Shelf-stable route: the finished item is shelf-stable at room temperature (pH and water activity, Food Code 1-201.10), so it isn't TCS: no cold-holding limit and no date mark, even if it's filled. | O7: =IF(AND($D7="Shelf-stable",$F7="No"),"Mismatch: you chose the shelf-stable route and then said it isn't shelf-stable","")
A8: B3 | B8: Custard napolitana (cream-filled laminated pastry) | C8: Viennoiserie | D8: Cooked through | E8: Yes | F8: No | G8: =IF(AND($E8="Yes",$F8="No"),'Settings'!$B$28,"") -> 41 | H8: =IF(AND(OR($D8="Cooked through",$D8="Pasteurized egg product"),$F8="No"),'Settings'!$B$29,"") -> 41 | I8: =IF(AND(G8="",H8=""),"",IF(G8="",H8,IF(H8="",G8,MIN(G8,H8)))) -> 41 | J8: =IF(AND(G8="",H8=""),"Neither test applies: shelf-stable at room temperature, so it goes in the room-temperature case.",IF(AND(G8<>"",H8<>""),"Both tests apply and both limits are 41 °F (Food Code 3-501.16): no conflict, the same limit twice.",IF(G8<>"","Filled and not shelf-stable at room temperature: TCS food, hold at 41 °F or below (3-501.16).","Its egg route leaves it needing cold (cooked through or pasteurized egg product, not shelf-stable): TCS food, hold at 41 °F or below (3-501.16)."))) -> Both tests apply and both limits are 41 °F (Food Code 3-501.16): no conflict, the same limit twice. | K8: =IF(AND(OR($D8="Cooked through",$D8="Pasteurized egg product"),$F8="No"),'Settings'!$B$30,"N/A") -> 24 | L8: Declare in your food safety plan | M8: =IF(I8="","Room-temperature case","Refrigerated case") -> Refrigerated case | N8: Egg cooked all the way through in the bake: the finished item carries no raw egg. Whether it needs cold depends on its pH and water activity (1-201.10). | O8: =IF(AND($D8="Shelf-stable",$F8="No"),"Mismatch: you chose the shelf-stable route and then said it isn't shelf-stable","")
A9: B4 | B9: Palmier | C9: Viennoiserie | D9: No egg | E9: No | F9: Yes | G9: =IF(AND($E9="Yes",$F9="No"),'Settings'!$B$28,"") | H9: =IF(AND(OR($D9="Cooked through",$D9="Pasteurized egg product"),$F9="No"),'Settings'!$B$29,"") | I9: =IF(AND(G9="",H9=""),"",IF(G9="",H9,IF(H9="",G9,MIN(G9,H9)))) | J9: =IF(AND(G9="",H9=""),"Neither test applies: shelf-stable at room temperature, so it goes in the room-temperature case.",IF(AND(G9<>"",H9<>""),"Both tests apply and both limits are 41 °F (Food Code 3-501.16): no conflict, the same limit twice.",IF(G9<>"","Filled and not shelf-stable at room temperature: TCS food, hold at 41 °F or below (3-501.16).","Its egg route leaves it needing cold (cooked through or pasteurized egg product, not shelf-stable): TCS food, hold at 41 °F or below (3-501.16)."))) -> Neither test applies: shelf-stable at room temperature, so it goes in the room-temperature case. | K9: =IF(AND(OR($D9="Cooked through",$D9="Pasteurized egg product"),$F9="No"),'Settings'!$B$30,"N/A") -> N/A | L9: Declare in your food safety plan | M9: =IF(I9="","Room-temperature case","Refrigerated case") -> Room-temperature case | N9: No egg in any form: the egg routes don't apply to it. | O9: =IF(AND($D9="Shelf-stable",$F9="No"),"Mismatch: you chose the shelf-stable route and then said it isn't shelf-stable","")
A10: B5 | B10: Raisin snail (pain aux raisins) | C10: Viennoiserie | D10: Cooked through | E10: Yes | F10: No | G10: =IF(AND($E10="Yes",$F10="No"),'Settings'!$B$28,"") -> 41 | H10: =IF(AND(OR($D10="Cooked through",$D10="Pasteurized egg product"),$F10="No"),'Settings'!$B$29,"") -> 41 | I10: =IF(AND(G10="",H10=""),"",IF(G10="",H10,IF(H10="",G10,MIN(G10,H10)))) -> 41 | J10: =IF(AND(G10="",H10=""),"Neither test applies: shelf-stable at room temperature, so it goes in the room-temperature case.",IF(AND(G10<>"",H10<>""),"Both tests apply and both limits are 41 °F (Food Code 3-501.16): no conflict, the same limit twice.",IF(G10<>"","Filled and not shelf-stable at room temperature: TCS food, hold at 41 °F or below (3-501.16).","Its egg route leaves it needing cold (cooked through or pasteurized egg product, not shelf-stable): TCS food, hold at 41 °F or below (3-501.16)."))) -> Both tests apply and both limits are 41 °F (Food Code 3-501.16): no conflict, the same limit twice. | K10: =IF(AND(OR($D10="Cooked through",$D10="Pasteurized egg product"),$F10="No"),'Settings'!$B$30,"N/A") -> 24 | L10: Declare in your food safety plan | M10: =IF(I10="","Room-temperature case","Refrigerated case") -> Refrigerated case | N10: Egg cooked all the way through in the bake: the finished item carries no raw egg. Whether it needs cold depends on its pH and water activity (1-201.10). | O10: =IF(AND($D10="Shelf-stable",$F10="No"),"Mismatch: you chose the shelf-stable route and then said it isn't shelf-stable","")
A11: B6 | B11: Ensaïmada (Mallorcan spiral pastry) | C11: Viennoiserie | D11: Shelf-stable | E11: No | F11: Yes | G11: =IF(AND($E11="Yes",$F11="No"),'Settings'!$B$28,"") | H11: =IF(AND(OR($D11="Cooked through",$D11="Pasteurized egg product"),$F11="No"),'Settings'!$B$29,"") | I11: =IF(AND(G11="",H11=""),"",IF(G11="",H11,IF(H11="",G11,MIN(G11,H11)))) | J11: =IF(AND(G11="",H11=""),"Neither test applies: shelf-stable at room temperature, so it goes in the room-temperature case.",IF(AND(G11<>"",H11<>""),"Both tests apply and both limits are 41 °F (Food Code 3-501.16): no conflict, the same limit twice.",IF(G11<>"","Filled and not shelf-stable at room temperature: TCS food, hold at 41 °F or below (3-501.16).","Its egg route leaves it needing cold (cooked through or pasteurized egg product, not shelf-stable): TCS food, hold at 41 °F or below (3-501.16)."))) -> Neither test applies: shelf-stable at room temperature, so it goes in the room-temperature case. | K11: =IF(AND(OR($D11="Cooked through",$D11="Pasteurized egg product"),$F11="No"),'Settings'!$B$30,"N/A") -> N/A | L11: Declare in your food safety plan | M11: =IF(I11="","Room-temperature case","Refrigerated case") -> Room-temperature case | N11: Shelf-stable route: the finished item is shelf-stable at room temperature (pH and water activity, Food Code 1-201.10), so it isn't TCS: no cold-holding limit and no date mark, even if it's filled. | O11: =IF(AND($D11="Shelf-stable",$F11="No"),"Mismatch: you chose the shelf-stable route and then said it isn't shelf-stable","")
A12: PI1 | B12: Napoleon (mille-feuille) | C12: Individual pastries | D12: Cooked through | E12: Yes | F12: No | G12: =IF(AND($E12="Yes",$F12="No"),'Settings'!$B$28,"") -> 41 | H12: =IF(AND(OR($D12="Cooked through",$D12="Pasteurized egg product"),$F12="No"),'Settings'!$B$29,"") -> 41 | I12: =IF(AND(G12="",H12=""),"",IF(G12="",H12,IF(H12="",G12,MIN(G12,H12)))) -> 41 | J12: =IF(AND(G12="",H12=""),"Neither test applies: shelf-stable at room temperature, so it goes in the room-temperature case.",IF(AND(G12<>"",H12<>""),"Both tests apply and both limits are 41 °F (Food Code 3-501.16): no conflict, the same limit twice.",IF(G12<>"","Filled and not shelf-stable at room temperature: TCS food, hold at 41 °F or below (3-501.16).","Its egg route leaves it needing cold (cooked through or pasteurized egg product, not shelf-stable): TCS food, hold at 41 °F or below (3-501.16)."))) -> Both tests apply and both limits are 41 °F (Food Code 3-501.16): no conflict, the same limit twice. | K12: =IF(AND(OR($D12="Cooked through",$D12="Pasteurized egg product"),$F12="No"),'Settings'!$B$30,"N/A") -> 24 | L12: Declare in your food safety plan | M12: =IF(I12="","Room-temperature case","Refrigerated case") -> Refrigerated case | N12: Egg cooked all the way through in the bake: the finished item carries no raw egg. Whether it needs cold depends on its pH and water activity (1-201.10). | O12: =IF(AND($D12="Shelf-stable",$F12="No"),"Mismatch: you chose the shelf-stable route and then said it isn't shelf-stable","")
A13: PI2 | B13: Éclair | C13: Individual pastries | D13: Cooked through | E13: Yes | F13: No | G13: =IF(AND($E13="Yes",$F13="No"),'Settings'!$B$28,"") -> 41 | H13: =IF(AND(OR($D13="Cooked through",$D13="Pasteurized egg product"),$F13="No"),'Settings'!$B$29,"") -> 41 | I13: =IF(AND(G13="",H13=""),"",IF(G13="",H13,IF(H13="",G13,MIN(G13,H13)))) -> 41 | J13: =IF(AND(G13="",H13=""),"Neither test applies: shelf-stable at room temperature, so it goes in the room-temperature case.",IF(AND(G13<>"",H13<>""),"Both tests apply and both limits are 41 °F (Food Code 3-501.16): no conflict, the same limit twice.",IF(G13<>"","Filled and not shelf-stable at room temperature: TCS food, hold at 41 °F or below (3-501.16).","Its egg route leaves it needing cold (cooked through or pasteurized egg product, not shelf-stable): TCS food, hold at 41 °F or below (3-501.16)."))) -> Both tests apply and both limits are 41 °F (Food Code 3-501.16): no conflict, the same limit twice. | K13: =IF(AND(OR($D13="Cooked through",$D13="Pasteurized egg product"),$F13="No"),'Settings'!$B$30,"N/A") -> 24 | L13: Declare in your food safety plan | M13: =IF(I13="","Room-temperature case","Refrigerated case") -> Refrigerated case | N13: Egg cooked all the way through in the bake: the finished item carries no raw egg. Whether it needs cold depends on its pH and water activity (1-201.10). | O13: =IF(AND($D13="Shelf-stable",$F13="No"),"Mismatch: you chose the shelf-stable route and then said it isn't shelf-stable","")
A14: PI3 | B14: Raspberry macarons | C14: Individual pastries | D14: Cooked through | E14: Yes | F14: No | G14: =IF(AND($E14="Yes",$F14="No"),'Settings'!$B$28,"") -> 41 | H14: =IF(AND(OR($D14="Cooked through",$D14="Pasteurized egg product"),$F14="No"),'Settings'!$B$29,"") -> 41 | I14: =IF(AND(G14="",H14=""),"",IF(G14="",H14,IF(H14="",G14,MIN(G14,H14)))) -> 41 | J14: =IF(AND(G14="",H14=""),"Neither test applies: shelf-stable at room temperature, so it goes in the room-temperature case.",IF(AND(G14<>"",H14<>""),"Both tests apply and both limits are 41 °F (Food Code 3-501.16): no conflict, the same limit twice.",IF(G14<>"","Filled and not shelf-stable at room temperature: TCS food, hold at 41 °F or below (3-501.16).","Its egg route leaves it needing cold (cooked through or pasteurized egg product, not shelf-stable): TCS food, hold at 41 °F or below (3-501.16)."))) -> Both tests apply and both limits are 41 °F (Food Code 3-501.16): no conflict, the same limit twice. | K14: =IF(AND(OR($D14="Cooked through",$D14="Pasteurized egg product"),$F14="No"),'Settings'!$B$30,"N/A") -> 24 | L14: Declare in your food safety plan | M14: =IF(I14="","Room-temperature case","Refrigerated case") -> Refrigerated case | N14: Egg cooked all the way through in the bake: the finished item carries no raw egg. Whether it needs cold depends on its pH and water activity (1-201.10). | O14: =IF(AND($D14="Shelf-stable",$F14="No"),"Mismatch: you chose the shelf-stable route and then said it isn't shelf-stable","")
A15: PI4 | B15: Fruit tart | C15: Individual pastries | D15: Cooked through | E15: Yes | F15: No | G15: =IF(AND($E15="Yes",$F15="No"),'Settings'!$B$28,"") -> 41 | H15: =IF(AND(OR($D15="Cooked through",$D15="Pasteurized egg product"),$F15="No"),'Settings'!$B$29,"") -> 41 | I15: =IF(AND(G15="",H15=""),"",IF(G15="",H15,IF(H15="",G15,MIN(G15,H15)))) -> 41 | J15: =IF(AND(G15="",H15=""),"Neither test applies: shelf-stable at room temperature, so it goes in the room-temperature case.",IF(AND(G15<>"",H15<>""),"Both tests apply and both limits are 41 °F (Food Code 3-501.16): no conflict, the same limit twice.",IF(G15<>"","Filled and not shelf-stable at room temperature: TCS food, hold at 41 °F or below (3-501.16).","Its egg route leaves it needing cold (cooked through or pasteurized egg product, not shelf-stable): TCS food, hold at 41 °F or below (3-501.16)."))) -> Both tests apply and both limits are 41 °F (Food Code 3-501.16): no conflict, the same limit twice. | K15: =IF(AND(OR($D15="Cooked through",$D15="Pasteurized egg product"),$F15="No"),'Settings'!$B$30,"N/A") -> 24 | L15: Declare in your food safety plan | M15: =IF(I15="","Room-temperature case","Refrigerated case") -> Refrigerated case | N15: Egg cooked all the way through in the bake: the finished item carries no raw egg. Whether it needs cold depends on its pH and water activity (1-201.10). | O15: =IF(AND($D15="Shelf-stable",$F15="No"),"Mismatch: you chose the shelf-stable route and then said it isn't shelf-stable","")
A16: PI5 | B16: Cream puff (profiterole) | C16: Individual pastries | D16: Cooked through | E16: Yes | F16: No | G16: =IF(AND($E16="Yes",$F16="No"),'Settings'!$B$28,"") -> 41 | H16: =IF(AND(OR($D16="Cooked through",$D16="Pasteurized egg product"),$F16="No"),'Settings'!$B$29,"") -> 41 | I16: =IF(AND(G16="",H16=""),"",IF(G16="",H16,IF(H16="",G16,MIN(G16,H16)))) -> 41 | J16: =IF(AND(G16="",H16=""),"Neither test applies: shelf-stable at room temperature, so it goes in the room-temperature case.",IF(AND(G16<>"",H16<>""),"Both tests apply and both limits are 41 °F (Food Code 3-501.16): no conflict, the same limit twice.",IF(G16<>"","Filled and not shelf-stable at room temperature: TCS food, hold at 41 °F or below (3-501.16).","Its egg route leaves it needing cold (cooked through or pasteurized egg product, not shelf-stable): TCS food, hold at 41 °F or below (3-501.16)."))) -> Both tests apply and both limits are 41 °F (Food Code 3-501.16): no conflict, the same limit twice. | K16: =IF(AND(OR($D16="Cooked through",$D16="Pasteurized egg product"),$F16="No"),'Settings'!$B$30,"N/A") -> 24 | L16: Declare in your food safety plan | M16: =IF(I16="","Room-temperature case","Refrigerated case") -> Refrigerated case | N16: Egg cooked all the way through in the bake: the finished item carries no raw egg. Whether it needs cold depends on its pH and water activity (1-201.10). | O16: =IF(AND($D16="Shelf-stable",$F16="No"),"Mismatch: you chose the shelf-stable route and then said it isn't shelf-stable","")
A17: PI6 | B17: Individual entremet (mousse cake) | C17: Individual pastries | D17: Pasteurized egg product | E17: Yes | F17: No | G17: =IF(AND($E17="Yes",$F17="No"),'Settings'!$B$28,"") -> 41 | H17: =IF(AND(OR($D17="Cooked through",$D17="Pasteurized egg product"),$F17="No"),'Settings'!$B$29,"") -> 41 | I17: =IF(AND(G17="",H17=""),"",IF(G17="",H17,IF(H17="",G17,MIN(G17,H17)))) -> 41 | J17: =IF(AND(G17="",H17=""),"Neither test applies: shelf-stable at room temperature, so it goes in the room-temperature case.",IF(AND(G17<>"",H17<>""),"Both tests apply and both limits are 41 °F (Food Code 3-501.16): no conflict, the same limit twice.",IF(G17<>"","Filled and not shelf-stable at room temperature: TCS food, hold at 41 °F or below (3-501.16).","Its egg route leaves it needing cold (cooked through or pasteurized egg product, not shelf-stable): TCS food, hold at 41 °F or below (3-501.16)."))) -> Both tests apply and both limits are 41 °F (Food Code 3-501.16): no conflict, the same limit twice. | K17: =IF(AND(OR($D17="Cooked through",$D17="Pasteurized egg product"),$F17="No"),'Settings'!$B$30,"N/A") -> 24 | L17: Declare in your food safety plan | M17: =IF(I17="","Room-temperature case","Refrigerated case") -> Refrigerated case | N17: The item doesn't go through heat after the egg goes in, so raw shell egg is replaced with pasteurized egg product. | O17: =IF(AND($D17="Shelf-stable",$F17="No"),"Mismatch: you chose the shelf-stable route and then said it isn't shelf-stable","")
... A35: TP8 | B35: Mona de Pascua (Catalan Easter cake) | C35: Seasonal | D35: Shelf-stable | E35: No | F35: Yes | G35: =IF(AND($E35="Yes",$F35="No"),'Settings'!$B$28,"") | H35: =IF(AND(OR($D35="Cooked through",$D35="Pasteurized egg product"),$F35="No"),'Settings'!$B$29,"") | I35: =IF(AND(G35="",H35=""),"",IF(G35="",H35,IF(H35="",G35,MIN(G35,H35)))) | J35: =IF(AND(G35="",H35=""),"Neither test applies: shelf-stable at room temperature, so it goes in the room-temperature case.",IF(AND(G35<>"",H35<>""),"Both tests apply and both limits are 41 °F (Food Code 3-501.16): no conflict, the same limit twice.",IF(G35<>"","Filled and not shelf-stable at room temperature: TCS food, hold at 41 °F or below (3-501.16).","Its egg route leaves it needing cold (cooked through or pasteurized egg product, not shelf-stable): TCS food, hold at 41 °F or below (3-501.16)."))) -> Neither test applies: shelf-stable at room temperature, so it goes in the room-temperature case. | K35: =IF(AND(OR($D35="Cooked through",$D35="Pasteurized egg product"),$F35="No"),'Settings'!$B$30,"N/A") -> N/A | L35: Declare in your food safety plan | M35: =IF(I35="","Room-temperature case","Refrigerated case") -> Room-temperature case | N35: Shelf-stable route: the finished item is shelf-stable at room temperature (pH and water activity, Food Code 1-201.10), so it isn't TCS: no cold-holding limit and no date mark, even if it's filled. | O35: =IF(AND($D35="Shelf-stable",$F35="No"),"Mismatch: you chose the shelf-stable route and then said it isn't shelf-stable","")
A37: What this sheet gives you
B38: Items that need the REFRIGERATED case | G38: =COUNTIF(M6:M35,"Refrigerated case") -> 15 | J38: This count, not taste, decides how many feet of refrigerated case you buy.
B39: Items that go in the ROOM-TEMPERATURE case | G39: =COUNTIF(M6:M35,"Room-temperature case") -> 15 | J39: Palmiers, Sachertorte, huesos de santo, almond turrón and the breads. They're the ones you can make ahead and the ones that hold up at a peak.
B40: Items that are filled and not shelf-stable at room temperature | G40: =SUMPRODUCT(--(G6:G35<>"")) -> 13 | J40: Cream, custard and mousse fillings: TCS food, held at 41 °F or below (Food Code 3-501.16).
B41: Items whose egg route leaves them needing cold | G41: =SUMPRODUCT(--(H6:H35<>"")) -> 15 | J41: Egg cooked through in an item that isn't shelf-stable, or pasteurized egg product for what doesn't go through heat.
B42: Items both of those apply to | G42: =SUMPRODUCT(--(G6:G35<>""),--(H6:H35<>"")) -> 13 | J42: Both land on the same 41 °F, so there's no conflict to settle: one ceiling, one temperature.
B43: Items that need a date mark if held more than 24 hours | G43: =SUMPRODUCT(--(K6:K35<>"N/A")) -> 15 | J43: 7 days at most at 41 °F or below, with the day you make it as day 1 (Food Code 3-501.17). It's the obligation almost nobody keeps track of.
B44: Items with no egg in any form | G44: =COUNTIF(D6:D35,"No egg") -> 6 | J44: The egg question doesn't apply to them.
B45: Items served with raw or undercooked egg | G45: =COUNTIF(D6:D35,"Raw or undercooked egg") -> 0 | J45: It should come out zero: that's the route for things like soft-cooked eggs, and it calls for a consumer advisory (Food Code 3-603.11). It's on the list so you know it exists and that it is NOT yours.
A49: Dropdown lists (don't edit)
A50: Cooked through | B50: Egg cooked all the way through in the bake: the finished item carries no raw egg. Whether it needs cold depends on its pH and water activity (1-201.10). | D50: Yes
A51: Raw or undercooked egg | B51: Served with raw or undercooked egg (soft-cooked eggs, for example): it calls for a consumer advisory (Food Code 3-603.11). It isn't a pastry route. | D51: No
A52: Pasteurized egg product | B52: The item doesn't go through heat after the egg goes in, so raw shell egg is replaced with pasteurized egg product.
A53: No egg | B53: No egg in any form: the egg routes don't apply to it.
A54: Shelf-stable | B54: Shelf-stable route: the finished item is shelf-stable at room temperature (pH and water activity, Food Code 1-201.10), so it isn't TCS: no cold-holding limit and no date mark, even if it's filled.
A57: HOW TO READ THIS SHEET. You choose the egg route and say whether the piece is filled and whether the FINISHED item is shelf-stable at room temperature. With that, the workbook gives you the temperature you have to hold it at, which test applies and whether it needs a date mark when held more than 24 hours. Nothing more, and nothing less.
A58: SHELF LIFE IS YOURS. Column L reads "Declare in your food safety plan" on purpose: the Food Code does NOT set shelf lives, and this workbook won't invent them for your 30 items. You set them with your process and your tests, and they go in your food safety plan. The date mark in column K is a different thing: it's a legal ceiling (held more than 24 hours, 7 days at most) and it only covers ready-to-eat TCS food.
A59: WHAT THIS SHEET CHANGES IN YOUR MONEY. Every item that comes out "Refrigerated case" is feet of refrigerated case you have to buy, and every item with a date mark is product on a clock: past 24 hours it needs a date mark, and 7 days is the most it can be held. That's why you read this sheet BEFORE you close the menu and BEFORE you buy the display case.
A60: WHERE THE REST IS. The display-case allergen matrix and the daily temperature log are in the HACCP Food Safety Kit Pro. This workbook doesn't redo them: it makes the decision that comes before.
A61: CHECK YOUR STATE'S EDITION. Your inspector enforces your state's adopted edition of the Food Code, not necessarily the 2022 model; the 2022 rules are the direction of travel, so building to them is the safe choice. Every cell with a legal figure on this sheet carries a note with the section and the link, checked in October 2026.
A62: WHAT THIS SHEET DOESN'T COVER, AND WHY. Cooling and freezing belong to the PROCESS, not the display case: they go in your food safety plan and your temperature logs (cooling: Food Code 3-501.14). The 9 major food allergens have their own dedicated matrix in the HACCP Food Safety Kit Pro: repeating them in this table would mean keeping the same data in two places until they drift apart. And anything you package in the shop ahead of time, like bagged bread, needs a full label (3-602.11(B)), which chapter 3 of the guide covers.
A64: Version 1.0 · October 2026 · aichef.pro/en/digital-products/how-to-open-a-pastry-shop · info@aichef.pro

Sheet Mix and Average Ticket
A1: Mix and Average Ticket
A2: AI Chef Pro · aichef.pro — How to Open a Pastry Shop
A3: We found no reliable published average ticket for bakeries. Yours is calculated from your menu and your mix.
A5: Ref | B5: Item | C5: Family | D5: Mix (% of units) | E5: Menu price ($) | F5: Price before tax ($) | G5: Contribution to the average menu price ($) | H5: Contribution to the average ticket ($) | I5: Relative revenue before tax | J5: Relative ingredient cost | K5: Relative margin | L5: Item food cost | M5: What this item brings in
A6: B1 | B6: Butter croissant | C6: Viennoiserie | D6: 12 | E6: ='Labor Cost per Hour'!L6 -> 1.4545455 | F6: ='Labor Cost per Hour'!N6 -> 1.4545455 | G6: =IFERROR(E6*D6/100,"") -> 0.17454545 | H6: =IFERROR(G6*'Settings'!$B$36,"") -> 0.45381818 | I6: =IFERROR(F6*D6/100,"") -> 0.17454545 | J6: =IFERROR('Batch Costing'!G236*D6/100,"") -> 0.02830021 | K6: =IFERROR('Labor Cost per Hour'!Q6*D6/100,"") -> 0.047586732 | L6: ='Labor Cost per Hour'!O6 -> 0.16213662
A7: B2 | B7: Pain au chocolat (chocolate croissant) | C7: Viennoiserie | D7: 8 | E7: ='Labor Cost per Hour'!L7 -> 1.6818182 | F7: ='Labor Cost per Hour'!N7 -> 1.6818182 | G7: =IFERROR(E7*D7/100,"") -> 0.13454545 | H7: =IFERROR(G7*'Settings'!$B$36,"") -> 0.34981818 | I7: =IFERROR(F7*D7/100,"") -> 0.13454545 | J7: =IFERROR('Batch Costing'!G237*D7/100,"") -> 0.033560684 | K7: =IFERROR('Labor Cost per Hour'!Q7*D7/100,"") -> 0.035212429 | L7: ='Labor Cost per Hour'!O7 -> 0.24943752
A8: B3 | B8: Custard napolitana (cream-filled laminated pastry) | C8: Viennoiserie | D8: 7 | E8: ='Labor Cost per Hour'!L8 -> 1.6818182 | F8: ='Labor Cost per Hour'!N8 -> 1.6818182 | G8: =IFERROR(E8*D8/100,"") -> 0.11772727 | H8: =IFERROR(G8*'Settings'!$B$36,"") -> 0.30609091 | I8: =IFERROR(F8*D8/100,"") -> 0.11772727 | J8: =IFERROR('Batch Costing'!G238*D8/100,"") -> 0.024684599 | K8: =IFERROR('Labor Cost per Hour'!Q8*D8/100,"") -> 0.025028094 | L8: ='Labor Cost per Hour'!O8 -> 0.20967613
A9: B4 | B9: Palmier | C9: Viennoiserie | D9: 4.5 | E9: ='Labor Cost per Hour'!L9 -> 1.5454545 | F9: ='Labor Cost per Hour'!N9 -> 1.5454545 | G9: =IFERROR(E9*D9/100,"") -> 0.069545455 | H9: =IFERROR(G9*'Settings'!$B$36,"") -> 0.18081818 | I9: =IFERROR(F9*D9/100,"") -> 0.069545455 | J9: =IFERROR('Batch Costing'!G239*D9/100,"") -> 0.0098761782 | K9: =IFERROR('Labor Cost per Hour'!Q9*D9/100,"") -> 0.037246887 | L9: ='Labor Cost per Hour'!O9 -> 0.14201041
A10: B5 | B10: Raisin snail (pain aux raisins) | C10: Viennoiserie | D10: 3.5 | E10: ='Labor Cost per Hour'!L10 -> 1.6818182 | F10: ='Labor Cost per Hour'!N10 -> 1.6818182 | G10: =IFERROR(E10*D10/100,"") -> 0.058863636 | H10: =IFERROR(G10*'Settings'!$B$36,"") -> 0.15304545 | I10: =IFERROR(F10*D10/100,"") -> 0.058863636 | J10: =IFERROR('Batch Costing'!G240*D10/100,"") -> 0.010718659 | K10: =IFERROR('Labor Cost per Hour'!Q10*D10/100,"") -> 0.016753633 | L10: ='Labor Cost per Hour'!O10 -> 0.18209304
A11: B6 | B11: Ensaïmada (Mallorcan spiral pastry) | C11: Viennoiserie | D11: 3 | E11: ='Labor Cost per Hour'!L11 -> 1.7727273 | F11: ='Labor Cost per Hour'!N11 -> 1.7727273 | G11: =IFERROR(E11*D11/100,"") -> 0.053181818 | H11: =IFERROR(G11*'Settings'!$B$36,"") -> 0.13827273 | I11: =IFERROR(F11*D11/100,"") -> 0.053181818 | J11: =IFERROR('Batch Costing'!G241*D11/100,"") -> 0.0054070285 | K11: =IFERROR('Labor Cost per Hour'!Q11*D11/100,"") -> 0.0085356088 | L11: ='Labor Cost per Hour'!O11 -> 0.10167062
A12: PI1 | B12: Napoleon (mille-feuille) | C12: Individual pastries | D12: 4 | E12: ='Labor Cost per Hour'!L12 -> 3.2727273 | F12: ='Labor Cost per Hour'!N12 -> 3.2727273 | G12: =IFERROR(E12*D12/100,"") -> 0.13090909 | H12: =IFERROR(G12*'Settings'!$B$36,"") -> 0.34036364 | I12: =IFERROR(F12*D12/100,"") -> 0.13090909 | J12: =IFERROR('Batch Costing'!G242*D12/100,"") -> 0.017877676 | K12: =IFERROR('Labor Cost per Hour'!Q12*D12/100,"") -> 0.063203883 | L12: ='Labor Cost per Hour'!O12 -> 0.13656558
A13: PI2 | B13: Éclair | C13: Individual pastries | D13: 3.5 | E13: ='Labor Cost per Hour'!L13 -> 2.9090909 | F13: ='Labor Cost per Hour'!N13 -> 2.9090909 | G13: =IFERROR(E13*D13/100,"") -> 0.10181818 | H13: =IFERROR(G13*'Settings'!$B$36,"") -> 0.26472727 | I13: =IFERROR(F13*D13/100,"") -> 0.10181818 | J13: =IFERROR('Batch Costing'!G243*D13/100,"") -> 0.011838951 | K13: =IFERROR('Labor Cost per Hour'!Q13*D13/100,"") -> 0.061639823 | L13: ='Labor Cost per Hour'!O13 -> 0.11627541
A14: PI3 | B14: Raspberry macarons | C14: Individual pastries | D14: 7 | E14: ='Labor Cost per Hour'!L14 -> 1.9090909 | F14: ='Labor Cost per Hour'!N14 -> 1.9090909 | G14: =IFERROR(E14*D14/100,"") -> 0.13363636 | H14: =IFERROR(G14*'Settings'!$B$36,"") -> 0.34745455 | I14: =IFERROR(F14*D14/100,"") -> 0.13363636 | J14: =IFERROR('Batch Costing'!G244*D14/100,"") -> 0.013755697 | K14: =IFERROR('Labor Cost per Hour'!Q14*D14/100,"") -> 0.064073831 | L14: ='Labor Cost per Hour'!O14 -> 0.10293379
A15: PI4 | B15: Fruit tart | C15: Individual pastries | D15: 3 | E15: ='Labor Cost per Hour'!L15 -> 3.4545455 | F15: ='Labor Cost per Hour'!N15 -> 3.4545455 | G15: =IFERROR(E15*D15/100,"") -> 0.10363636 | H15: =IFERROR(G15*'Settings'!$B$36,"") -> 0.26945455 | I15: =IFERROR(F15*D15/100,"") -> 0.10363636 | J15: =IFERROR('Batch Costing'!G245*D15/100,"") -> 0.015749581 | K15: =IFERROR('Labor Cost per Hour'!Q15*D15/100,"") -> 0.049768721 | L15: ='Labor Cost per Hour'!O15 -> 0.15196964
A16: PI5 | B16: Cream puff (profiterole) | C16: Individual pastries | D16: 3 | E16: ='Labor Cost per Hour'!L16 -> 2.0909091 | F16: ='Labor Cost per Hour'!N16 -> 2.0909091 | G16: =IFERROR(E16*D16/100,"") -> 0.062727273 | H16: =IFERROR(G16*'Settings'!$B$36,"") -> 0.16309091 | I16: =IFERROR(F16*D16/100,"") -> 0.062727273 | J16: =IFERROR('Batch Costing'!G246*D16/100,"") -> 0.0059453042 | K16: =IFERROR('Labor Cost per Hour'!Q16*D16/100,"") -> 0.043328535 | L16: ='Labor Cost per Hour'!O16 -> 0.094780213
A17: PI6 | B17: Individual entremet (mousse cake) | C17: Individual pastries | D17: 1.5 | E17: ='Labor Cost per Hour'!L17 -> 4.0909091 | F17: ='Labor Cost per Hour'!N17 -> 4.0909091 | G17: =IFERROR(E17*D17/100,"") -> 0.061363636 | H17: =IFERROR(G17*'Settings'!$B$36,"") -> 0.15954545 | I17: =IFERROR(F17*D17/100,"") -> 0.061363636 | J17: =IFERROR('Batch Costing'!G247*D17/100,"") -> 0.012371119 | K17: =IFERROR('Labor Cost per Hour'!Q17*D17/100,"") -> 0.02236593 | L17: ='Labor Cost per Hour'!O17 -> 0.20160342
... A35: TP8 | B35: Mona de Pascua (Catalan Easter cake) | C35: Seasonal | D35: 0.7 | E35: ='Labor Cost per Hour'!L35 -> 12.272727 | F35: ='Labor Cost per Hour'!N35 -> 12.272727 | G35: =IFERROR(E35*D35/100,"") -> 0.085909091 | H35: =IFERROR(G35*'Settings'!$B$36,"") -> 0.22336364 | I35: =IFERROR(F35*D35/100,"") -> 0.085909091 | J35: =IFERROR('Batch Costing'!G265*D35/100,"") -> 0.014104128 | K35: =IFERROR('Labor Cost per Hour'!Q35*D35/100,"") -> 0.059846355 | L35: ='Labor Cost per Hour'!O35 -> 0.16417504
A36: MENU TOTAL | D36: =SUM(D6:D35) -> 100 | G36: =SUM(G6:G35) -> 2.257236 | H36: =SUM(H6:H35) -> 5.8688136 | I36: =SUM(I6:I35) -> 2.257236 | J36: =SUM(J6:J35) -> 0.39624846 | K36: =SUM(K6:K35) -> 1.0710505 | M36: The mix has to add up to 100.00. If it doesn't, the cell turns red: the average ticket below would be lying.
A38: Your pastry shop's average ticket
B39: Weighted average menu price | F39: =IFERROR($G$36,"") -> 2.257236 | I39: Sum of the contributions of the 30 items, weighted by the unit mix.
B40: Pieces per customer | F40: ='Settings'!$B$36 -> 2.6 | I40: Taken from "Settings". It's the only assumption: everything else comes from your menu.
B41: AVERAGE TICKET AT MENU PRICES | F41: =IFERROR($G$36*'Settings'!$B$36,"") -> 5.8688136 | I41: Weighted average menu price times pieces per customer. It isn't copied from any study because we found none: this one is yours, and that's why you can defend it in front of a bank.
B42: Average ticket before sales tax | F42: =IFERROR($I$36*'Settings'!$B$36,"") -> 5.8688136 | I42: The one that goes into the financial plan: the P&L is before sales tax.
B43: Average VAT/GST in your menu prices (0 in the US) | F43: =IFERROR($G$36/$I$36-1,"") -> 0 | I43: It isn't a legal rate: it's what takes you from cash collected to net sales where menu prices include VAT or GST (UK, Australia). In the US, menu prices are before sales tax, so it's 0.
B44: Menu INGREDIENT food cost | F44: =IFERROR($J$36/$I$36,"") -> 0.17554587 | I44: Weighted by dollars sold, which is the real way to weight it, not by pieces.
B45: SERVED food cost (with waste and packaging) | F45: =IFERROR($J$36/$I$36/(1-'Settings'!$B$34)*(1+'Settings'!$B$35),"") -> 0.20326364 | I45: The recipe costing figure plus what's made and not sold, plus the box. It's the one that comes closest to your P&L.
B46: House target food cost | F46: ='Settings'!$B$24 -> 0.32 | I46: The one in "Settings". The industry rule is 30-35%.
B47: Average contribution margin per piece ($) | F47: =IFERROR($K$36/$D$36*100,"") -> 1.0710505 | I47: After ingredients AND labor. It's the dollar left to pay rent, utilities and your own pay.
A50: WHY THE MENU FOOD COST AND THE ONE IN THE FINANCIAL PLAN DON'T MATCH. The recipe costing counts only the ingredients of what you make. The one that reaches the P&L adds four things, in this order of size: THIRD-PARTY products the front counter resells (drinks, coffee, ice cream, bought-in chocolates), which have no costing of their own; real waste, which in fresh product runs above target; packaging; and ingredient price increases, which in butter and cocoa aren't theoretical. That's why the financial plan is projected with the industry rule and not with your recipe costing: it's the conservative assumption. The gap between the two numbers is your cushion.
A51: THE MIX IS MEASURED, NOT GUESSED. The one in the example is an assumption. Yours comes out of your POS in two clicks three months after opening, and until then any average ticket you calculate is a hypothesis. Say so when you take it to the bank.
A53: Version 1.0 · October 2026 · aichef.pro/en/digital-products/how-to-open-a-pastry-shop · info@aichef.pro

Sheet Menu Decision
A1: Menu Decision
A2: AI Chef Pro · aichef.pro — How to Open a Pastry Shop
A3: Margin against turnover: what to keep, what to review the price of and what to drop.
A5: Ref | B5: Item | C5: Family | D5: Food cost | E5: Margin per unit ($) | F5: Mix (% of units) | G5: Weighted margin ($) | H5: Food cost within target? | I5: Turnover above threshold? | J5: Verdict | K5: Why
A6: B1 | B6: Butter croissant | C6: Viennoiserie | D6: ='Labor Cost per Hour'!O6 -> 0.16213662 | E6: ='Labor Cost per Hour'!Q6 -> 0.3965561 | F6: ='Mix and Average Ticket'!D6 -> 12 | G6: =IFERROR(E6*F6/100,"") -> 0.047586732 | H6: =IF(NOT(ISNUMBER(D6)),"",IF(D6<='Settings'!$B$24,"Yes","No")) -> Yes | I6: =IF(NOT(ISNUMBER(F6)),"",IF(F6>='Settings'!$B$37,"Yes","No")) -> Yes | J6: =IF(OR(H6="",I6=""),"",IF(AND(H6="No",I6="No"),"Drop",IF(H6="No","Review price","Keep"))) -> Keep | K6: =IF(J6="","",IF(J6="Drop","Over the target food cost AND barely turns over: it takes up case space, creates waste and doesn't pay for its slot. Off the opening menu.",IF(J6="Review price","Turns over well but runs over the target food cost: raise the price, change the portion weight or renegotiate the ingredient that drives it up. Dropping it would cost you turnover.","Within target and turning over: it's an item that holds up the menu. Watch that its ingredient cost doesn't get away from you."))) -> Within target and turning over: it's an item that holds up the menu. Watch that its ingredient cost doesn't get away from you.
A7: B2 | B7: Pain au chocolat (chocolate croissant) | C7: Viennoiserie | D7: ='Labor Cost per Hour'!O7 -> 0.24943752 | E7: ='Labor Cost per Hour'!Q7 -> 0.44015536 | F7: ='Mix and Average Ticket'!D7 -> 8 | G7: =IFERROR(E7*F7/100,"") -> 0.035212429 | H7: =IF(NOT(ISNUMBER(D7)),"",IF(D7<='Settings'!$B$24,"Yes","No")) -> Yes | I7: =IF(NOT(ISNUMBER(F7)),"",IF(F7>='Settings'!$B$37,"Yes","No")) -> Yes | J7: =IF(OR(H7="",I7=""),"",IF(AND(H7="No",I7="No"),"Drop",IF(H7="No","Review price","Keep"))) -> Keep | K7: =IF(J7="","",IF(J7="Drop","Over the target food cost AND barely turns over: it takes up case space, creates waste and doesn't pay for its slot. Off the opening menu.",IF(J7="Review price","Turns over well but runs over the target food cost: raise the price, change the portion weight or renegotiate the ingredient that drives it up. Dropping it would cost you turnover.","Within target and turning over: it's an item that holds up the menu. Watch that its ingredient cost doesn't get away from you."))) -> Within target and turning over: it's an item that holds up the menu. Watch that its ingredient cost doesn't get away from you.
A8: B3 | B8: Custard napolitana (cream-filled laminated pastry) | C8: Viennoiserie | D8: ='Labor Cost per Hour'!O8 -> 0.20967613 | E8: ='Labor Cost per Hour'!Q8 -> 0.35754419 | F8: ='Mix and Average Ticket'!D8 -> 7 | G8: =IFERROR(E8*F8/100,"") -> 0.025028094 | H8: =IF(NOT(ISNUMBER(D8)),"",IF(D8<='Settings'!$B$24,"Yes","No")) -> Yes | I8: =IF(NOT(ISNUMBER(F8)),"",IF(F8>='Settings'!$B$37,"Yes","No")) -> Yes | J8: =IF(OR(H8="",I8=""),"",IF(AND(H8="No",I8="No"),"Drop",IF(H8="No","Review price","Keep"))) -> Keep | K8: =IF(J8="","",IF(J8="Drop","Over the target food cost AND barely turns over: it takes up case space, creates waste and doesn't pay for its slot. Off the opening menu.",IF(J8="Review price","Turns over well but runs over the target food cost: raise the price, change the portion weight or renegotiate the ingredient that drives it up. Dropping it would cost you turnover.","Within target and turning over: it's an item that holds up the menu. Watch that its ingredient cost doesn't get away from you."))) -> Within target and turning over: it's an item that holds up the menu. Watch that its ingredient cost doesn't get away from you.
A9: B4 | B9: Palmier | C9: Viennoiserie | D9: ='Labor Cost per Hour'!O9 -> 0.14201041 | E9: ='Labor Cost per Hour'!Q9 -> 0.82770861 | F9: ='Mix and Average Ticket'!D9 -> 4.5 | G9: =IFERROR(E9*F9/100,"") -> 0.037246887 | H9: =IF(NOT(ISNUMBER(D9)),"",IF(D9<='Settings'!$B$24,"Yes","No")) -> Yes | I9: =IF(NOT(ISNUMBER(F9)),"",IF(F9>='Settings'!$B$37,"Yes","No")) -> Yes | J9: =IF(OR(H9="",I9=""),"",IF(AND(H9="No",I9="No"),"Drop",IF(H9="No","Review price","Keep"))) -> Keep | K9: =IF(J9="","",IF(J9="Drop","Over the target food cost AND barely turns over: it takes up case space, creates waste and doesn't pay for its slot. Off the opening menu.",IF(J9="Review price","Turns over well but runs over the target food cost: raise the price, change the portion weight or renegotiate the ingredient that drives it up. Dropping it would cost you turnover.","Within target and turning over: it's an item that holds up the menu. Watch that its ingredient cost doesn't get away from you."))) -> Within target and turning over: it's an item that holds up the menu. Watch that its ingredient cost doesn't get away from you.
A10: B5 | B10: Raisin snail (pain aux raisins) | C10: Viennoiserie | D10: ='Labor Cost per Hour'!O10 -> 0.18209304 | E10: ='Labor Cost per Hour'!Q10 -> 0.47867523 | F10: ='Mix and Average Ticket'!D10 -> 3.5 | G10: =IFERROR(E10*F10/100,"") -> 0.016753633 | H10: =IF(NOT(ISNUMBER(D10)),"",IF(D10<='Settings'!$B$24,"Yes","No")) -> Yes | I10: =IF(NOT(ISNUMBER(F10)),"",IF(F10>='Settings'!$B$37,"Yes","No")) -> Yes | J10: =IF(OR(H10="",I10=""),"",IF(AND(H10="No",I10="No"),"Drop",IF(H10="No","Review price","Keep"))) -> Keep | K10: =IF(J10="","",IF(J10="Drop","Over the target food cost AND barely turns over: it takes up case space, creates waste and doesn't pay for its slot. Off the opening menu.",IF(J10="Review price","Turns over well but runs over the target food cost: raise the price, change the portion weight or renegotiate the ingredient that drives it up. Dropping it would cost you turnover.","Within target and turning over: it's an item that holds up the menu. Watch that its ingredient cost doesn't get away from you."))) -> Within target and turning over: it's an item that holds up the menu. Watch that its ingredient cost doesn't get away from you.
A11: B6 | B11: Ensaïmada (Mallorcan spiral pastry) | C11: Viennoiserie | D11: ='Labor Cost per Hour'!O11 -> 0.10167062 | E11: ='Labor Cost per Hour'!Q11 -> 0.28452029 | F11: ='Mix and Average Ticket'!D11 -> 3 | G11: =IFERROR(E11*F11/100,"") -> 0.0085356088 | H11: =IF(NOT(ISNUMBER(D11)),"",IF(D11<='Settings'!$B$24,"Yes","No")) -> Yes | I11: =IF(NOT(ISNUMBER(F11)),"",IF(F11>='Settings'!$B$37,"Yes","No")) -> Yes | J11: =IF(OR(H11="",I11=""),"",IF(AND(H11="No",I11="No"),"Drop",IF(H11="No","Review price","Keep"))) -> Keep | K11: =IF(J11="","",IF(J11="Drop","Over the target food cost AND barely turns over: it takes up case space, creates waste and doesn't pay for its slot. Off the opening menu.",IF(J11="Review price","Turns over well but runs over the target food cost: raise the price, change the portion weight or renegotiate the ingredient that drives it up. Dropping it would cost you turnover.","Within target and turning over: it's an item that holds up the menu. Watch that its ingredient cost doesn't get away from you."))) -> Within target and turning over: it's an item that holds up the menu. Watch that its ingredient cost doesn't get away from you.
A12: PI1 | B12: Napoleon (mille-feuille) | C12: Individual pastries | D12: ='Labor Cost per Hour'!O12 -> 0.13656558 | E12: ='Labor Cost per Hour'!Q12 -> 1.5800971 | F12: ='Mix and Average Ticket'!D12 -> 4 | G12: =IFERROR(E12*F12/100,"") -> 0.063203883 | H12: =IF(NOT(ISNUMBER(D12)),"",IF(D12<='Settings'!$B$24,"Yes","No")) -> Yes | I12: =IF(NOT(ISNUMBER(F12)),"",IF(F12>='Settings'!$B$37,"Yes","No")) -> Yes | J12: =IF(OR(H12="",I12=""),"",IF(AND(H12="No",I12="No"),"Drop",IF(H12="No","Review price","Keep"))) -> Keep | K12: =IF(J12="","",IF(J12="Drop","Over the target food cost AND barely turns over: it takes up case space, creates waste and doesn't pay for its slot. Off the opening menu.",IF(J12="Review price","Turns over well but runs over the target food cost: raise the price, change the portion weight or renegotiate the ingredient that drives it up. Dropping it would cost you turnover.","Within target and turning over: it's an item that holds up the menu. Watch that its ingredient cost doesn't get away from you."))) -> Within target and turning over: it's an item that holds up the menu. Watch that its ingredient cost doesn't get away from you.
A13: PI2 | B13: Éclair | C13: Individual pastries | D13: ='Labor Cost per Hour'!O13 -> 0.11627541 | E13: ='Labor Cost per Hour'!Q13 -> 1.7611378 | F13: ='Mix and Average Ticket'!D13 -> 3.5 | G13: =IFERROR(E13*F13/100,"") -> 0.061639823 | H13: =IF(NOT(ISNUMBER(D13)),"",IF(D13<='Settings'!$B$24,"Yes","No")) -> Yes | I13: =IF(NOT(ISNUMBER(F13)),"",IF(F13>='Settings'!$B$37,"Yes","No")) -> Yes | J13: =IF(OR(H13="",I13=""),"",IF(AND(H13="No",I13="No"),"Drop",IF(H13="No","Review price","Keep"))) -> Keep | K13: =IF(J13="","",IF(J13="Drop","Over the target food cost AND barely turns over: it takes up case space, creates waste and doesn't pay for its slot. Off the opening menu.",IF(J13="Review price","Turns over well but runs over the target food cost: raise the price, change the portion weight or renegotiate the ingredient that drives it up. Dropping it would cost you turnover.","Within target and turning over: it's an item that holds up the menu. Watch that its ingredient cost doesn't get away from you."))) -> Within target and turning over: it's an item that holds up the menu. Watch that its ingredient cost doesn't get away from you.
A14: PI3 | B14: Raspberry macarons | C14: Individual pastries | D14: ='Labor Cost per Hour'!O14 -> 0.10293379 | E14: ='Labor Cost per Hour'!Q14 -> 0.91534045 | F14: ='Mix and Average Ticket'!D14 -> 7 | G14: =IFERROR(E14*F14/100,"") -> 0.064073831 | H14: =IF(NOT(ISNUMBER(D14)),"",IF(D14<='Settings'!$B$24,"Yes","No")) -> Yes | I14: =IF(NOT(ISNUMBER(F14)),"",IF(F14>='Settings'!$B$37,"Yes","No")) -> Yes | J14: =IF(OR(H14="",I14=""),"",IF(AND(H14="No",I14="No"),"Drop",IF(H14="No","Review price","Keep"))) -> Keep | K14: =IF(J14="","",IF(J14="Drop","Over the target food cost AND barely turns over: it takes up case space, creates waste and doesn't pay for its slot. Off the opening menu.",IF(J14="Review price","Turns over well but runs over the target food cost: raise the price, change the portion weight or renegotiate the ingredient that drives it up. Dropping it would cost you turnover.","Within target and turning over: it's an item that holds up the menu. Watch that its ingredient cost doesn't get away from you."))) -> Within target and turning over: it's an item that holds up the menu. Watch that its ingredient cost doesn't get away from you.
A15: PI4 | B15: Fruit tart | C15: Individual pastries | D15: ='Labor Cost per Hour'!O15 -> 0.15196964 | E15: ='Labor Cost per Hour'!Q15 -> 1.6589574 | F15: ='Mix and Average Ticket'!D15 -> 3 | G15: =IFERROR(E15*F15/100,"") -> 0.049768721 | H15: =IF(NOT(ISNUMBER(D15)),"",IF(D15<='Settings'!$B$24,"Yes","No")) -> Yes | I15: =IF(NOT(ISNUMBER(F15)),"",IF(F15>='Settings'!$B$37,"Yes","No")) -> Yes | J15: =IF(OR(H15="",I15=""),"",IF(AND(H15="No",I15="No"),"Drop",IF(H15="No","Review price","Keep"))) -> Keep | K15: =IF(J15="","",IF(J15="Drop","Over the target food cost AND barely turns over: it takes up case space, creates waste and doesn't pay for its slot. Off the opening menu.",IF(J15="Review price","Turns over well but runs over the target food cost: raise the price, change the portion weight or renegotiate the ingredient that drives it up. Dropping it would cost you turnover.","Within target and turning over: it's an item that holds up the menu. Watch that its ingredient cost doesn't get away from you."))) -> Within target and turning over: it's an item that holds up the menu. Watch that its ingredient cost doesn't get away from you.
A16: PI5 | B16: Cream puff (profiterole) | C16: Individual pastries | D16: ='Labor Cost per Hour'!O16 -> 0.094780213 | E16: ='Labor Cost per Hour'!Q16 -> 1.4442845 | F16: ='Mix and Average Ticket'!D16 -> 3 | G16: =IFERROR(E16*F16/100,"") -> 0.043328535 | H16: =IF(NOT(ISNUMBER(D16)),"",IF(D16<='Settings'!$B$24,"Yes","No")) -> Yes | I16: =IF(NOT(ISNUMBER(F16)),"",IF(F16>='Settings'!$B$37,"Yes","No")) -> Yes | J16: =IF(OR(H16="",I16=""),"",IF(AND(H16="No",I16="No"),"Drop",IF(H16="No","Review price","Keep"))) -> Keep | K16: =IF(J16="","",IF(J16="Drop","Over the target food cost AND barely turns over: it takes up case space, creates waste and doesn't pay for its slot. Off the opening menu.",IF(J16="Review price","Turns over well but runs over the target food cost: raise the price, change the portion weight or renegotiate the ingredient that drives it up. Dropping it would cost you turnover.","Within target and turning over: it's an item that holds up the menu. Watch that its ingredient cost doesn't get away from you."))) -> Within target and turning over: it's an item that holds up the menu. Watch that its ingredient cost doesn't get away from you.
A17: PI6 | B17: Individual entremet (mousse cake) | C17: Individual pastries | D17: ='Labor Cost per Hour'!O17 -> 0.20160342 | E17: ='Labor Cost per Hour'!Q17 -> 1.491062 | F17: ='Mix and Average Ticket'!D17 -> 1.5 | G17: =IFERROR(E17*F17/100,"") -> 0.02236593 | H17: =IF(NOT(ISNUMBER(D17)),"",IF(D17<='Settings'!$B$24,"Yes","No")) -> Yes | I17: =IF(NOT(ISNUMBER(F17)),"",IF(F17>='Settings'!$B$37,"Yes","No")) -> Yes | J17: =IF(OR(H17="",I17=""),"",IF(AND(H17="No",I17="No"),"Drop",IF(H17="No","Review price","Keep"))) -> Keep | K17: =IF(J17="","",IF(J17="Drop","Over the target food cost AND barely turns over: it takes up case space, creates waste and doesn't pay for its slot. Off the opening menu.",IF(J17="Review price","Turns over well but runs over the target food cost: raise the price, change the portion weight or renegotiate the ingredient that drives it up. Dropping it would cost you turnover.","Within target and turning over: it's an item that holds up the menu. Watch that its ingredient cost doesn't get away from you."))) -> Within target and turning over: it's an item that holds up the menu. Watch that its ingredient cost doesn't get away from you.
... A35: TP8 | B35: Mona de Pascua (Catalan Easter cake) | C35: Seasonal | D35: ='Labor Cost per Hour'!O35 -> 0.16417504 | E35: ='Labor Cost per Hour'!Q35 -> 8.5494793 | F35: ='Mix and Average Ticket'!D35 -> 0.7 | G35: =IFERROR(E35*F35/100,"") -> 0.059846355 | H35: =IF(NOT(ISNUMBER(D35)),"",IF(D35<='Settings'!$B$24,"Yes","No")) -> Yes | I35: =IF(NOT(ISNUMBER(F35)),"",IF(F35>='Settings'!$B$37,"Yes","No")) -> No | J35: =IF(OR(H35="",I35=""),"",IF(AND(H35="No",I35="No"),"Drop",IF(H35="No","Review price","Keep"))) -> Keep | K35: =IF(J35="","",IF(J35="Drop","Over the target food cost AND barely turns over: it takes up case space, creates waste and doesn't pay for its slot. Off the opening menu.",IF(J35="Review price","Turns over well but runs over the target food cost: raise the price, change the portion weight or renegotiate the ingredient that drives it up. Dropping it would cost you turnover.","Within target and turning over: it's an item that holds up the menu. Watch that its ingredient cost doesn't get away from you."))) -> Within target and turning over: it's an item that holds up the menu. Watch that its ingredient cost doesn't get away from you.
A36: MENU TOTAL | F36: =SUM(F6:F35) -> 100 | G36: =SUM(G6:G35) -> 1.0710505 | K36: The total weighted margin is the average contribution margin per piece sold with this mix.
A38: How the menu looks
B39: Items with a Keep verdict | E39: =COUNTIF(J6:J35,"Keep") -> 27 | F39: =IFERROR(SUMPRODUCT(--(J6:J35="Keep"),G6:G35),"") -> 1.0278667 | G39: dollars of weighted margin they bring in
B40: Items with a Review price verdict | E40: =COUNTIF(J6:J35,"Review price") -> 1 | F40: =IFERROR(SUMPRODUCT(--(J6:J35="Review price"),G6:G35),"") -> 0.011991309 | G40: dollars of weighted margin they bring in
B41: Items with a Drop verdict | E41: =COUNTIF(J6:J35,"Drop") -> 2 | F41: =IFERROR(SUMPRODUCT(--(J6:J35="Drop"),G6:G35),"") -> 0.031192538 | G41: dollars of weighted margin they bring in
B42: Average weighted margin per item ($) | E42: =IFERROR(AVERAGE(G6:G35),"") -> 0.035701684
A45: HOW IT'S DECIDED. Two questions, not four. Is the food cost within your target? Does the item turn over above your threshold? If the margin fails and it doesn't turn over either, it's out. If only the margin fails, the problem is price or process, not the menu: dropping it would cost you turnover. If neither fails, it stays.
A46: THIS ISN'T MENU ENGINEERING. Menu engineering (Kasavana-Smith, Miller, Pavesic, Goal Value) is in the Food Cost + Menu Engineering Guide, with its four methods and how they compare. This is the menu traffic light for an OPENING menu, which is something else: you use it before you've sold anything, with the mix YOU assume.
A47: WHEN TO LOOK AGAIN. Three months after opening, with real POS sales in the mix column, and then every time the season changes. An opening menu that's unchanged after a year is a menu nobody has looked at.
A48: AN ITEM CAN STAY EVEN IF IT LOSES MONEY, AND YOU NEED TO KNOW IT. The baguette is the classic case: thin margin and lots of turnover, but it's what brings the customer in every day. If you decide to keep something the menu traffic light says to drop, write it down and set a date to review it: that's a decision, not an oversight.
A50: Version 1.0 · October 2026 · aichef.pro/en/digital-products/how-to-open-a-pastry-shop · info@aichef.pro
