Workbook

Sheet Instructions
A1: Seasonal Peaks and Campaign Planning
A2: AI Chef Pro · aichef.pro — How to Open a Pastry Shop
A3: Purpose: find out whether you can handle Three Kings Day before it arrives, and how much money each campaign ties up.
A5: How to use it
A6: 1. "Settings" sheet: first, the capacity of your production kitchen in pieces per hour. That number comes from the "Bottleneck" sheet of kitchen-capacity-and-site.xlsx in this same pack: open it, see which machine limits you and copy its pieces per hour here. It comes with a default value so the workbook works from the first minute, but it's an ASSUMPTION, not your production kitchen.
A7: 2. "6-Peak Calendar" sheet: six campaigns with their star product, their days, their price and the units you expect to sell per day inside and outside the campaign. It's the only sheet where you type sales expectations.
A8: 3. "Share of the Year" sheet: spread your annual sales across the twelve months and you'll see what percentage of the year is at stake in each campaign. It's the number that decides whether a campaign is worth setting up.
A9: 4. "Peak Capacity vs Demand" sheet: this is the question of the workbook. Peak demand is your normal-day pieces times the campaign factor; capacity is the hours you can keep the production kitchen running. If there's a shortfall, you have three levers, in this order: more machine hours, production made ahead and frozen, and extra staff.
A10: 5. "Extra Staff and Cash" sheet: what the extra staff costs at the real employer cost (base pay plus payroll taxes, workers' comp and benefits) and, above all, how much money the campaign's ingredient purchase ties up and for how many days. That money leaves your account weeks before the first dollar of the campaign comes in.
A11: 6. Repeat the cycle every January with the real figures from the campaign you just closed: the workbook is only worth what you put into it, which is what really happened, not what you expected to happen.
A13: Green cells = fields you can edit
A15: What to know before you start
... A28: Version 1.0 · October 2026 · aichef.pro/en/digital-products/how-to-open-a-pastry-shop · info@aichef.pro

Sheet Settings
A1: Settings
A2: AI Chef Pro · aichef.pro — How to Open a Pastry Shop
A5: Parameter | B5: Value | C5: Unit | D5: Where it comes from | E5: Note
A6: Steady-state annual sales before sales tax | B6: 322197.87 | C6: $/year | D6: assumption | E6: It comes from La Clara's menu and its assumed foot traffic: customers per day times pieces per customer times weighted average price. It's not industry data. Replace it with the figure from your financial plan.
A7: Pieces per day at cruising speed | B7: 476 | C7: pieces/day | D7: assumption | E7: Customers per day times pieces per customer. It's the base the factor of each campaign multiplies.
A8: Days open per year | B8: 300 | C8: days | D8: assumption | E8: 6 days a week × 52 weeks = 312, minus 12 closing days for a vacation in August = 300. Holidays are NOT subtracted: you choose your own days and hours (check your lease and local rules).
A9: Production kitchen capacity on a normal workday | B9: 480 | C9: pieces/day | D9: kitchen capacity workbook | E9: COPY by hand the result of the "Bottleneck" sheet of kitchen-capacity-and-site.xlsx in this pack: the cell "Pieces per day the whole kitchen allows." In the example it's 480, and the limiting equipment is the 4-tray blast chiller, against 476 pieces at cruising speed: four pieces of cushion. There's no formula between workbooks: if you change equipment, copy it again.
A10: Production kitchen hours per day on a normal workday | B10: 8 | C10: hours | D10: assumption | E10: Clock hours the production kitchen runs on an ordinary day, not the shop's opening hours.
A11: Pieces per clock hour of the limiting equipment | B11: =IFERROR('Settings'!$B$9/'Settings'!$B$10,"") -> 60 | C11: pieces/hour | D11: calculated | E11: A normal workday's capacity divided by its hours. It's per CLOCK hour, with the stops already included: kitchen-capacity-and-site.xlsx already took out the part of the workday that isn't spent at the machine.
A12: Daily surplus over cruising speed | B12: =IFERROR('Settings'!$B$9-'Settings'!$B$7,"") -> 4 | C12: pieces/day | D12: calculated | E12: What you have left over on a normal day. It's the ammunition for getting ahead on production and freezing it before the campaign; if it comes out negative, you're already tight at cruising speed and getting ahead won't fix the peak.
A13: Maximum production kitchen hours per day you accept | B13: 24 | C13: hours | D13: assumption | E13: A ceiling you set yourself. Above this number the sheet turns red: it isn't a legal limit, it's the warning that such a day doesn't exist.
A14: Hours per person per day of the extra staff | B14: 8 | C14: hours | D14: assumption | E14: Workday of the extra staff during the campaign. It's used to work out how many people it takes to cover the machine hours you're short.
A16: Extra staff cost (example wage table)
A17: Monthly pay of the extra staff's pay grade | B17: 1490.525 | C17: $/month | D17: case assumption | E17: Group 5, "Support staff," of the example wage table (the same one used in staff-schedule-and-labor-cost.xlsx). Replace it with the pay for the role you'll hire.
A18: Pay periods per year | B18: 12 | C18: pay periods | D18: case assumption | E18: The model pays 12 periods a year (12 equal monthly payments). The US has no mandatory extra pay months.
A19: Payroll taxes, workers' comp and benefits | B19: 0.33 | C19: on base pay | D19: case assumption | E19: Approximate employer cost on top of base pay: payroll taxes (FICA 7.65%, FUTA and state unemployment), workers' comp and benefits such as health insurance and paid time off. The mandatory part is around 10%; the rest depends on the benefits you offer. Adjust it to your state and your hires.
A20: Annual hours actually worked | B20: 1780 | C20: hours/year | D20: assumption | E20: 40 hours × 52 weeks = 2,080, less paid time off and holidays, comes to about 1,780.
A21: Employer cost per hour worked of the extra staff (Group 5) | B21: =IFERROR('Settings'!$B$17*'Settings'!$B$18*(1+'Settings'!$B$19)/'Settings'!$B$20,"") -> 13.364483 | C21: $/hour | D21: calculated | E21: Monthly pay × 12 × (1 + payroll taxes, workers' comp and benefits), divided by annual hours actually worked. It's the real cost, not the pay. It is NOT the "productive-hour production kitchen cost" of opening-menu-and-recipe-costing.xlsx ($17.94) nor the "average employer cost per hour worked for the team" of staff-schedule-and-labor-cost.xlsx ($14.89): all three are correct and measure a different denominator.
A23: Money, sales tax and thresholds
A24: Annual interest rate on working capital | B24: 0.062 | C24: annual | D24: assumption | E24: Cost of the money you have tied up in campaign raw materials. If you finance the purchase with a line of credit, use your line's rate; if you pay from your own cash, use what it would cost you to borrow it.
A25: Sales tax on pastries sold to go | B25: 0 | C25: on the pre-tax price | D25: your state's rule | E25: 0 by default: in the four example states (CA, TX, NY, FL), bakery items sold to go are generally exempt. Prices in this workbook are before sales tax, so this rate doesn't change any margin.
A26: Sales tax on bread sold to go | B26: 0 | C26: on the pre-tax price | D26: your state's rule | E26: Bread doesn't change your tax: sold to go it follows the same rule as pastries. What it does bring is a full label on any bread you bag yourself (Food Code 3-602.11).
A27: Threshold to flag a campaign as big | B27: 0.05 | C27: of the year | D27: assumption | E27: The share of the year's sales above which the "Share of the Year" sheet highlights the campaign. A house criterion, not an industry one.
A29: Version 1.0 · October 2026 · aichef.pro/en/digital-products/how-to-open-a-pastry-shop · info@aichef.pro

Sheet 6-Peak Calendar
A1: 6-Peak Calendar
A2: AI Chef Pro · aichef.pro — How to Open a Pastry Shop
A3: Your annual task calendar sets the DATES and what to do. This sheet puts the DOLLARS.
A5: # | B5: Campaign | C5: Reference dates | D5: Month | E5: Campaign days | F5: Star product | G5: Sales tax rate | H5: Menu price ($) | I5: Price before sales tax ($) | J5: Units per day outside the campaign | K5: Units per day in the campaign | L5: Incremental units per day | M5: Units over the whole campaign | N5: Campaign sales before sales tax ($) | O5: Incremental sales before sales tax ($) | P5: Factor over the production kitchen | Q5: Purchase lead time (weeks) | R5: What to know about this campaign
A6: 1 | B6: Día de Reyes (Three Kings Day) | C6: January 2–6 | D6: 1 | E6: 5 | F6: Rosca de Reyes | G6: 0 | H6: 15 | I6: =IFERROR(H6/(1+G6),"") -> 15 | J6: 0 | K6: 160 | L6: =IFERROR(K6-J6,"") -> 160 | M6: =IFERROR(K6*E6,"") -> 800 | N6: =IFERROR(M6*I6,"") -> 12000 | O6: =IFERROR(L6*E6*I6,"") -> 12000 | P6: 6 | Q6: 6 | R6: The peak that decides the year. The campaign units are those of the FIVE best-selling days: 160 a day, 800 in total, 47% of the roscas the menu mix assigns to the year (1.2% of the pieces). The rest sell in the week before, outside the campaign window, which is why they aren't in this row. In the US the rosca shares its season with the king cake (Epiphany to Mardi Gras), and searches average about 90,500 a month for "rosca de reyes" and 110,000 for "king cake" (DataForSEO, October 2026): scale references, never price or market share. A cream-filled rosca carries the 41 °F cold-holding limit (Food Code 3-501.16) and date marking (3-501.17) on the biggest production day: that limits production as much as the oven does.
A7: 2 | B7: Valentine's Day | C7: February 13–14 | D7: 2 | E7: 2 | F7: Raspberry macarons | G7: 0 | H7: 1.9090909 | I7: =IFERROR(H7/(1+G7),"") -> 1.9090909 | J7: 95 | K7: 260 | L7: =IFERROR(K7-J7,"") -> 165 | M7: =IFERROR(K7*E7,"") -> 520 | N7: =IFERROR(M7*I7,"") -> 992.72727 | O7: =IFERROR(L7*E7*I7,"") -> 630 | P7: 1.8 | Q7: 3 | R7: Two-day, high-ticket campaign, not volume: you win with boxes and presentation, not with more oven. The special production for this date is heart-shaped cakes, bonbons and macarons.
A8: 3 | B8: Mother's Day | C8: Día de las Madres (May 10) and US Mother's Day (2nd Sunday of May) | D8: 5 | E8: 4 | F8: 70% chocolate cake | G8: 0 | H8: 3.2727273 | I8: =IFERROR(H8/(1+G8),"") -> 3.2727273 | J8: 16 | K8: 96 | L8: =IFERROR(K8-J8,"") -> 80 | M8: =IFERROR(K8*E8,"") -> 384 | N8: =IFERROR(M8*I8,"") -> 1256.7273 | O8: =IFERROR(L8*E8*I8,"") -> 1047.2727 | P8: 1.9 | Q8: 3 | R8: One operating date for Día de las Madres (May 10) and US Mother's Day (2nd Sunday of May): a personalized cake, made to order. What matters to this guide is the load on the production kitchen, not the calendar.
A9: 4 | B9: Easter (Holy Week) | C9: Palm Sunday to Easter Sunday | D9: 4 | E9: 8 | F9: Torrijas | G9: 0 | H9: 2.1818182 | I9: =IFERROR(H9/(1+G9),"") -> 2.1818182 | J9: 0 | K9: 230 | L9: =IFERROR(K9-J9,"") -> 230 | M9: =IFERROR(K9*E9,"") -> 1840 | N9: =IFERROR(M9*I9,"") -> 4014.5455 | O9: =IFERROR(L9*E9*I9,"") -> 4014.5455 | P9: 2.4 | Q9: 4 | R9: Eight days in a row of extra production, more exhausting than the five of Three Kings Day even though the peak is smaller. Torrijas and Easter cakes (monas) at once: one needs a fryer and cold, the other an oven and chocolate. That's 230 torrijas a day and 1,840 over the campaign: 99% of the torrijas the menu mix assigns to the year, because they aren't made outside Holy Week.
A10: 5 | B10: First Communions and graduations | C10: mid-April to mid-June | D10: 5 | E10: 20 | F10: Strawberries-and-cream cake | G10: 0 | H10: 3.1818182 | I10: =IFERROR(H10/(1+G10),"") -> 3.1818182 | J10: 10 | K10: 34 | L10: =IFERROR(K10-J10,"") -> 24 | M10: =IFERROR(K10*E10,"") -> 680 | N10: =IFERROR(M10*I10,"") -> 2163.6364 | O10: =IFERROR(L10*E10*I10,"") -> 1527.2727 | P10: 1.6 | Q10: 5 | R10: It's not a peak, it's a two-month PLATEAU, which is why you carry it with staff and not with overtime. Everything is by custom order: deposit, delivery calendar and cancellation risk (chapter 16).
A11: 6 | B11: All Saints' Day and Día de los Muertos | C11: October 30 – November 1 | D11: 11 | E11: 3 | F11: Buñuelos (cream-filled fritters) | G11: 0 | H11: 1.4545455 | I11: =IFERROR(H11/(1+G11),"") -> 1.4545455 | J11: 0 | K11: 470 | L11: =IFERROR(K11-J11,"") -> 470 | M11: =IFERROR(K11*E11,"") -> 1410 | N11: =IFERROR(M11*I11,"") -> 2050.9091 | O11: =IFERROR(L11*E11*I11,"") -> 2050.9091 | P11: 2.6 | Q11: 4 | R11: Three days with three items that are only made now: buñuelos, huesos de santo and panellets. The buñuelos are cream-filled (41 °F or below, and date-marked if held) and the other two are shelf-stable at room temperature: that's why buñuelos are made the same day and huesos de santo can be made ahead. That food-safety detail IS the campaign planning. It's 470 buñuelos a day and 1,410 over the three days: 99% of the buñuelos the menu mix assigns to the year, because they aren't made outside this date.
B13: TOTAL FOR THE SIX CAMPAIGNS | E13: =SUM(E6:E11) -> 42 | M13: =SUM(M6:M11) -> 5634 | N13: =SUM(N6:N11) -> 22478.545 | O13: =SUM(O6:O11) -> 21270
A15: The campaign factor multiplies the pieces of the WHOLE PRODUCTION KITCHEN, not those of the star product: that's why Three Kings Day carries a 6.0 and Valentine's Day a 1.8, even though both are campaigns. The star product's units are on this sheet; the whole kitchen is handled in "Peak Capacity vs Demand."
A17: Version 1.0 · October 2026 · aichef.pro/en/digital-products/how-to-open-a-pastry-shop · info@aichef.pro

Sheet Share of the Year
A1: Share of the Year
A2: AI Chef Pro · aichef.pro — How to Open a Pastry Shop
A3: What share of the year is at stake in each campaign. It's the number that decides whether it's worth setting one up.
A5: Month | B5: Coefficient over the average month | C5: Month's sales before sales tax ($) | D5: % of the year | E5: Campaigns that fall in the month | F5: Why that coefficient
A6: January | B6: 1.34 | C6: =IFERROR('Settings'!$B$6*B6/$B$18,"") -> 35978.762 | D6: =IFERROR(C6/'Settings'!$B$6,"") -> 0.11166667 | E6: Día de Reyes (Three Kings Day) | F6: Three Kings Day. The highest month of the year and the one that decides the campaign.
A7: February | B7: 0.93 | C7: =IFERROR('Settings'!$B$6*B7/$B$18,"") -> 24970.335 | D7: =IFERROR(C7/'Settings'!$B$6,"") -> 0.0775 | E7: Valentine's Day | F7: Valentine's Day is two days and February has 28: a campaign that short doesn't lift a whole month.
A8: March | B8: 0.97 | C8: =IFERROR('Settings'!$B$6*B8/$B$18,"") -> 26044.328 | D8: =IFERROR(C8/'Settings'!$B$6,"") -> 0.080833333 | E8: Mother's Day | F8: No campaign: March has no major holiday in this model, so it stays a normal month.
A9: April | B9: 1.04 | C9: =IFERROR('Settings'!$B$6*B9/$B$18,"") -> 27923.815 | D9: =IFERROR(C9/'Settings'!$B$6,"") -> 0.086666667 | E9: Easter (Holy Week) | F9: Easter (Holy Week) and the start of the First Communion season.
A10: May | B10: 1.07 | C10: =IFERROR('Settings'!$B$6*B10/$B$18,"") -> 28729.31 | D10: =IFERROR(C10/'Settings'!$B$6,"") -> 0.089166667 | E10: First Communions and graduations | F10: Mother's Day plus the First Communions and graduations plateau: two months of orders.
A11: June | B11: 0.97 | C11: =IFERROR('Settings'!$B$6*B11/$B$18,"") -> 26044.328 | D11: =IFERROR(C11/'Settings'!$B$6,"") -> 0.080833333 | E11: - | F11: End of the communion and graduation season, and spending drops as the weather gets hot.
A12: July | B12: 0.85 | C12: =IFERROR('Settings'!$B$6*B12/$B$18,"") -> 22822.349 | D12: =IFERROR(C12/'Settings'!$B$6,"") -> 0.070833333 | E12: - | F12: Summer: pastry spending drops and ice cream picks up, which isn't on La Clara's menu.
A13: August | B13: 0.65 | C13: =IFERROR('Settings'!$B$6*B13/$B$18,"") -> 17452.385 | D13: =IFERROR(C13/'Settings'!$B$6,"") -> 0.054166667 | E13: - | F13: La Clara closes for two weeks in August (that's where the year's 300 days open come from).
A14: September | B14: 0.91 | C14: =IFERROR('Settings'!$B$6*B14/$B$18,"") -> 24433.338 | D14: =IFERROR(C14/'Settings'!$B$6,"") -> 0.075833333 | E14: - | F14: Back to school and the recommended opening month: outside any peak and with three and a half months of running in before Three Kings Day.
A15: October | B15: 0.95 | C15: =IFERROR('Settings'!$B$6*B15/$B$18,"") -> 25507.331 | D15: =IFERROR(C15/'Settings'!$B$6,"") -> 0.079166667 | E15: - | F15: A transition month; All Saints' Day and Día de los Muertos start on the 30th.
A16: November | B16: 1.08 | C16: =IFERROR('Settings'!$B$6*B16/$B$18,"") -> 28997.808 | D16: =IFERROR(C16/'Settings'!$B$6,"") -> 0.09 | E16: All Saints' Day and Día de los Muertos | F16: All Saints' Day and Día de los Muertos, plus Thanksgiving pies and the start of Christmas production.
A17: December | B17: 1.24 | C17: =IFERROR('Settings'!$B$6*B17/$B$18,"") -> 33293.78 | D17: =IFERROR(C17/'Settings'!$B$6,"") -> 0.10333333 | E17: - | F17: Christmas: turrón, polvorones and the lead-up to Three Kings Day.
A18: YEAR TOTAL | B18: =SUM(B6:B17) -> 12 | C18: =SUM(C6:C17) -> 322197.87 | D18: =SUM(D6:D17) -> 1 | F18: The twelve coefficients are spread over the average month, so their sum has to come to 12.00. If you change one, the split recalculates by itself and the year's sales don't move.
A21: What each campaign weighs
A23: Campaign | B23: Campaign days | C23: Campaign sales before sales tax ($) | D23: % of the year | E23: Incremental sales before sales tax ($) | F23: % incremental over the year | G23: $ per campaign day | H23: $ per average day of the year | I23: Times a normal day
A24: Día de Reyes (Three Kings Day) | B24: ='6-Peak Calendar'!E6 -> 5 | C24: ='6-Peak Calendar'!N6 -> 12000 | D24: =IFERROR(C24/'Settings'!$B$6,"") -> 0.037244194 | E24: ='6-Peak Calendar'!O6 -> 12000 | F24: =IFERROR(E24/'Settings'!$B$6,"") -> 0.037244194 | G24: =IFERROR(C24/B24,"") -> 2400 | H24: =IFERROR('Settings'!$B$6/'Settings'!$B$8,"") -> 1073.9929 | I24: =IFERROR(G24/H24,"") -> 2.2346516
A25: Valentine's Day | B25: ='6-Peak Calendar'!E7 -> 2 | C25: ='6-Peak Calendar'!N7 -> 992.72727 | D25: =IFERROR(C25/'Settings'!$B$6,"") -> 0.0030811106 | E25: ='6-Peak Calendar'!O7 -> 630 | F25: =IFERROR(E25/'Settings'!$B$6,"") -> 0.0019553202 | G25: =IFERROR(C25/B25,"") -> 496.36364 | H25: =IFERROR('Settings'!$B$6/'Settings'!$B$8,"") -> 1073.9929 | I25: =IFERROR(G25/H25,"") -> 0.46216659
A26: Mother's Day | B26: ='6-Peak Calendar'!E8 -> 4 | C26: ='6-Peak Calendar'!N8 -> 1256.7273 | D26: =IFERROR(C26/'Settings'!$B$6,"") -> 0.0039004829 | E26: ='6-Peak Calendar'!O8 -> 1047.2727 | F26: =IFERROR(E26/'Settings'!$B$6,"") -> 0.0032504024 | G26: =IFERROR(C26/B26,"") -> 314.18182 | H26: =IFERROR('Settings'!$B$6/'Settings'!$B$8,"") -> 1073.9929 | I26: =IFERROR(G26/H26,"") -> 0.29253622
A27: Easter (Holy Week) | B27: ='6-Peak Calendar'!E9 -> 8 | C27: ='6-Peak Calendar'!N9 -> 4014.5455 | D27: =IFERROR(C27/'Settings'!$B$6,"") -> 0.012459876 | E27: ='6-Peak Calendar'!O9 -> 4014.5455 | F27: =IFERROR(E27/'Settings'!$B$6,"") -> 0.012459876 | G27: =IFERROR(C27/B27,"") -> 501.81818 | H27: =IFERROR('Settings'!$B$6/'Settings'!$B$8,"") -> 1073.9929 | I27: =IFERROR(G27/H27,"") -> 0.46724534
A28: First Communions and graduations | B28: ='6-Peak Calendar'!E10 -> 20 | C28: ='6-Peak Calendar'!N10 -> 2163.6364 | D28: =IFERROR(C28/'Settings'!$B$6,"") -> 0.0067152411 | E28: ='6-Peak Calendar'!O10 -> 1527.2727 | F28: =IFERROR(E28/'Settings'!$B$6,"") -> 0.0047401702 | G28: =IFERROR(C28/B28,"") -> 108.18182 | H28: =IFERROR('Settings'!$B$6/'Settings'!$B$8,"") -> 1073.9929 | I28: =IFERROR(G28/H28,"") -> 0.10072862
A29: All Saints' Day and Día de los Muertos | B29: ='6-Peak Calendar'!E11 -> 3 | C29: ='6-Peak Calendar'!N11 -> 2050.9091 | D29: =IFERROR(C29/'Settings'!$B$6,"") -> 0.0063653714 | E29: ='6-Peak Calendar'!O11 -> 2050.9091 | F29: =IFERROR(E29/'Settings'!$B$6,"") -> 0.0063653714 | G29: =IFERROR(C29/B29,"") -> 683.63636 | H29: =IFERROR('Settings'!$B$6/'Settings'!$B$8,"") -> 1073.9929 | I29: =IFERROR(G29/H29,"") -> 0.63653714
A30: TOTAL FOR THE SIX CAMPAIGNS | B30: =SUM(B24:B29) -> 42 | C30: =SUM(C24:C29) -> 22478.545 | D30: =SUM(D24:D29) -> 0.069766276 | E30: =SUM(E24:E29) -> 21270 | F30: =SUM(F24:F29) -> 0.066015334
A32: The "campaign sales" count ALL the units of the star product you sell on those days; the "incremental" count only those you wouldn't have sold anyway. To decide whether to set up a campaign, incremental rules. To know whether you can handle it, the total rules.
A34: Version 1.0 · October 2026 · aichef.pro/en/digital-products/how-to-open-a-pastry-shop · info@aichef.pro

Sheet Peak Capacity vs Demand
A1: Peak Capacity vs Demand
A2: AI Chef Pro · aichef.pro — How to Open a Pastry Shop
A3: The question of the workbook: can you handle Three Kings Day with the equipment you're buying?
A5: Campaign | B5: Campaign days | C5: Factor over a normal day | D5: Pieces demanded per day | E5: Demand for the whole campaign | F5: Production kitchen hours per day during the campaign | G5: Capacity during the campaign (pieces per day) | H5: Daily shortfall | I5: Shortfall for the whole campaign | J5: Days of production made ahead | K5: Pieces you can make ahead | L5: Shortfall after making ahead | M5: Kitchen hours per day it would take | N5: Can you handle it? | O5: Kitchen hours you're short | P5: Extra people needed | Q5: Which lever you're missing
A6: Día de Reyes (Three Kings Day) | B6: ='6-Peak Calendar'!E6 -> 5 | C6: ='6-Peak Calendar'!P6 -> 6 | D6: =IFERROR('Settings'!$B$7*C6,"") -> 2856 | E6: =IFERROR(D6*B6,"") -> 14280 | F6: 20 | G6: =IFERROR('Settings'!$B$11*F6,"") -> 1200 | H6: =IFERROR(MAX(0,D6-G6),"") -> 1656 | I6: =IFERROR(H6*B6,"") -> 8280 | J6: 15 | K6: =IFERROR(MIN(I6,MAX(0,'Settings'!$B$12)*J6),"") -> 60 | L6: =IFERROR(MAX(0,I6-K6),"") -> 8220 | M6: =IFERROR((E6-K6)/B6/'Settings'!$B$11,"") -> 47.4 | N6: =IF(L6="","",IF(L6<=0,"Yes","No")) -> No | O6: =IFERROR(L6/'Settings'!$B$11,"") -> 137 | P6: =IFERROR(ROUNDUP(O6/(B6*'Settings'!$B$14),0),"") -> 4 | Q6: =IF(L6="","",IF(L6<=0,"With these hours and this head start, the campaign fits.",IF(M6>'Settings'!$B$13,"It doesn't fit even using the whole day: get further ahead and freeze more, or cut the campaign assortment.","It fits by lengthening the shift with extra staff: see the ""Extra Staff and Cash"" sheet."))) -> It doesn't fit even using the whole day: get further ahead and freeze more, or cut the campaign assortment.
A7: Valentine's Day | B7: ='6-Peak Calendar'!E7 -> 2 | C7: ='6-Peak Calendar'!P7 -> 1.8 | D7: =IFERROR('Settings'!$B$7*C7,"") -> 856.8 | E7: =IFERROR(D7*B7,"") -> 1713.6 | F7: 10 | G7: =IFERROR('Settings'!$B$11*F7,"") -> 600 | H7: =IFERROR(MAX(0,D7-G7),"") -> 256.8 | I7: =IFERROR(H7*B7,"") -> 513.6 | J7: 5 | K7: =IFERROR(MIN(I7,MAX(0,'Settings'!$B$12)*J7),"") -> 20 | L7: =IFERROR(MAX(0,I7-K7),"") -> 493.6 | M7: =IFERROR((E7-K7)/B7/'Settings'!$B$11,"") -> 14.113333 | N7: =IF(L7="","",IF(L7<=0,"Yes","No")) -> No | O7: =IFERROR(L7/'Settings'!$B$11,"") -> 8.2266667 | P7: =IFERROR(ROUNDUP(O7/(B7*'Settings'!$B$14),0),"") -> 1 | Q7: =IF(L7="","",IF(L7<=0,"With these hours and this head start, the campaign fits.",IF(M7>'Settings'!$B$13,"It doesn't fit even using the whole day: get further ahead and freeze more, or cut the campaign assortment.","It fits by lengthening the shift with extra staff: see the ""Extra Staff and Cash"" sheet."))) -> It fits by lengthening the shift with extra staff: see the "Extra Staff and Cash" sheet.
A8: Mother's Day | B8: ='6-Peak Calendar'!E8 -> 4 | C8: ='6-Peak Calendar'!P8 -> 1.9 | D8: =IFERROR('Settings'!$B$7*C8,"") -> 904.4 | E8: =IFERROR(D8*B8,"") -> 3617.6 | F8: 10 | G8: =IFERROR('Settings'!$B$11*F8,"") -> 600 | H8: =IFERROR(MAX(0,D8-G8),"") -> 304.4 | I8: =IFERROR(H8*B8,"") -> 1217.6 | J8: 5 | K8: =IFERROR(MIN(I8,MAX(0,'Settings'!$B$12)*J8),"") -> 20 | L8: =IFERROR(MAX(0,I8-K8),"") -> 1197.6 | M8: =IFERROR((E8-K8)/B8/'Settings'!$B$11,"") -> 14.99 | N8: =IF(L8="","",IF(L8<=0,"Yes","No")) -> No | O8: =IFERROR(L8/'Settings'!$B$11,"") -> 19.96 | P8: =IFERROR(ROUNDUP(O8/(B8*'Settings'!$B$14),0),"") -> 1 | Q8: =IF(L8="","",IF(L8<=0,"With these hours and this head start, the campaign fits.",IF(M8>'Settings'!$B$13,"It doesn't fit even using the whole day: get further ahead and freeze more, or cut the campaign assortment.","It fits by lengthening the shift with extra staff: see the ""Extra Staff and Cash"" sheet."))) -> It fits by lengthening the shift with extra staff: see the "Extra Staff and Cash" sheet.
A9: Easter (Holy Week) | B9: ='6-Peak Calendar'!E9 -> 8 | C9: ='6-Peak Calendar'!P9 -> 2.4 | D9: =IFERROR('Settings'!$B$7*C9,"") -> 1142.4 | E9: =IFERROR(D9*B9,"") -> 9139.2 | F9: 14 | G9: =IFERROR('Settings'!$B$11*F9,"") -> 840 | H9: =IFERROR(MAX(0,D9-G9),"") -> 302.4 | I9: =IFERROR(H9*B9,"") -> 2419.2 | J9: 10 | K9: =IFERROR(MIN(I9,MAX(0,'Settings'!$B$12)*J9),"") -> 40 | L9: =IFERROR(MAX(0,I9-K9),"") -> 2379.2 | M9: =IFERROR((E9-K9)/B9/'Settings'!$B$11,"") -> 18.956667 | N9: =IF(L9="","",IF(L9<=0,"Yes","No")) -> No | O9: =IFERROR(L9/'Settings'!$B$11,"") -> 39.653333 | P9: =IFERROR(ROUNDUP(O9/(B9*'Settings'!$B$14),0),"") -> 1 | Q9: =IF(L9="","",IF(L9<=0,"With these hours and this head start, the campaign fits.",IF(M9>'Settings'!$B$13,"It doesn't fit even using the whole day: get further ahead and freeze more, or cut the campaign assortment.","It fits by lengthening the shift with extra staff: see the ""Extra Staff and Cash"" sheet."))) -> It fits by lengthening the shift with extra staff: see the "Extra Staff and Cash" sheet.
A10: First Communions and graduations | B10: ='6-Peak Calendar'!E10 -> 20 | C10: ='6-Peak Calendar'!P10 -> 1.6 | D10: =IFERROR('Settings'!$B$7*C10,"") -> 761.6 | E10: =IFERROR(D10*B10,"") -> 15232 | F10: 10 | G10: =IFERROR('Settings'!$B$11*F10,"") -> 600 | H10: =IFERROR(MAX(0,D10-G10),"") -> 161.6 | I10: =IFERROR(H10*B10,"") -> 3232 | J10: 0 | K10: =IFERROR(MIN(I10,MAX(0,'Settings'!$B$12)*J10),"") -> 0 | L10: =IFERROR(MAX(0,I10-K10),"") -> 3232 | M10: =IFERROR((E10-K10)/B10/'Settings'!$B$11,"") -> 12.693333 | N10: =IF(L10="","",IF(L10<=0,"Yes","No")) -> No | O10: =IFERROR(L10/'Settings'!$B$11,"") -> 53.866667 | P10: =IFERROR(ROUNDUP(O10/(B10*'Settings'!$B$14),0),"") -> 1 | Q10: =IF(L10="","",IF(L10<=0,"With these hours and this head start, the campaign fits.",IF(M10>'Settings'!$B$13,"It doesn't fit even using the whole day: get further ahead and freeze more, or cut the campaign assortment.","It fits by lengthening the shift with extra staff: see the ""Extra Staff and Cash"" sheet."))) -> It fits by lengthening the shift with extra staff: see the "Extra Staff and Cash" sheet.
A11: All Saints' Day and Día de los Muertos | B11: ='6-Peak Calendar'!E11 -> 3 | C11: ='6-Peak Calendar'!P11 -> 2.6 | D11: =IFERROR('Settings'!$B$7*C11,"") -> 1237.6 | E11: =IFERROR(D11*B11,"") -> 3712.8 | F11: 16 | G11: =IFERROR('Settings'!$B$11*F11,"") -> 960 | H11: =IFERROR(MAX(0,D11-G11),"") -> 277.6 | I11: =IFERROR(H11*B11,"") -> 832.8 | J11: 10 | K11: =IFERROR(MIN(I11,MAX(0,'Settings'!$B$12)*J11),"") -> 40 | L11: =IFERROR(MAX(0,I11-K11),"") -> 792.8 | M11: =IFERROR((E11-K11)/B11/'Settings'!$B$11,"") -> 20.404444 | N11: =IF(L11="","",IF(L11<=0,"Yes","No")) -> No | O11: =IFERROR(L11/'Settings'!$B$11,"") -> 13.213333 | P11: =IFERROR(ROUNDUP(O11/(B11*'Settings'!$B$14),0),"") -> 1 | Q11: =IF(L11="","",IF(L11<=0,"With these hours and this head start, the campaign fits.",IF(M11>'Settings'!$B$13,"It doesn't fit even using the whole day: get further ahead and freeze more, or cut the campaign assortment.","It fits by lengthening the shift with extra staff: see the ""Extra Staff and Cash"" sheet."))) -> It fits by lengthening the shift with extra staff: see the "Extra Staff and Cash" sheet.
A13: TOTAL FOR THE SIX CAMPAIGNS | E13: =SUM(E6:E11) -> 47695.2 | I13: =SUM(I6:I11) -> 16495.2 | K13: =SUM(K6:K11) -> 180 | L13: =SUM(L6:L11) -> 16315.2 | N13: =COUNTIF(N6:N11,"No") -> 6 | O13: campaigns you can't handle
A15: How to read it: peak demand comes from multiplying your normal-day pieces by the campaign factor. Capacity comes from the limiting equipment's pieces per hour times the hours you keep the production kitchen running. The difference is the shortfall, and you attack it in this order: first machine hours, then production made ahead and frozen, and only at the end extra staff, which is what costs money every day of the campaign.
A16: The pieces you can make ahead are limited by the surplus of a normal day: if you're already at the limit at cruising speed, there's nowhere to get them from. And by what fits in your freezer, which this sheet doesn't know. Check the cubic feet before you accept the figure.
A17: What limits how far ahead you can go: anything the Food Code makes you hold at 41 °F or below and date-mark if held over 24 hours (3-501.16, 3-501.17), such as cream fillings. The cream-filled rosca is the textbook case: you make it the same day. Huesos de santo, shelf-stable at room temperature, can be made well ahead. That food-safety detail IS the campaign planning, and the "Egg & TCS Decision" sheet of opening-menu-and-recipe-costing.xlsx tells you which is which.
A19: Version 1.0 · October 2026 · aichef.pro/en/digital-products/how-to-open-a-pastry-shop · info@aichef.pro

Sheet Extra Staff and Cash
A1: Extra Staff and Cash
A2: AI Chef Pro · aichef.pro — How to Open a Pastry Shop
A3: What the extra staff costs with payroll costs included, and how much money each campaign ties up.
A5: Campaign | B5: Extra staff (people) | C5: Hours per person in the campaign | D5: Total extra-staff hours | E5: Employer cost per hour worked ($) | F5: Extra staff cost ($) | G5: People needed | H5: Does the extra staff cover it? | I5: Materials cost per unit ($) | J5: Units over the whole campaign | K5: Campaign ingredient purchase ($) | L5: Purchase lead time (weeks) | M5: Days the cash sits idle | N5: Financing cost of the tied-up cash ($) | O5: Materials for the incremental units ($) | P5: Incremental sales before sales tax ($) | Q5: Incremental result of the campaign ($) | R5: What to look at in this campaign
A6: Día de Reyes (Three Kings Day) | B6: 3 | C6: 40 | D6: =IFERROR(B6*C6,"") -> 120 | E6: ='Settings'!$B$21 -> 13.364483 | F6: =IFERROR(D6*E6,"") -> 1603.7379 | G6: ='Peak Capacity vs Demand'!P6 -> 4 | H6: =IF(G6="","",IF(B6>=G6,"Yes","No")) -> No | I6: 2.5988 | J6: ='6-Peak Calendar'!M6 -> 800 | K6: =IFERROR(I6*J6,"") -> 2079.04 | L6: ='6-Peak Calendar'!Q6 -> 6 | M6: =IFERROR(L6*7+'6-Peak Calendar'!E6,"") -> 47 | N6: =IFERROR(K6*'Settings'!$B$24*M6/365,"") -> 16.598144 | O6: =IFERROR(I6*'6-Peak Calendar'!L6*'6-Peak Calendar'!E6,"") -> 2079.04 | P6: ='6-Peak Calendar'!O6 -> 12000 | Q6: =IFERROR(P6-O6-F6-N6,"") -> 8300.6239 | R6: The campaign that decides the year. Six weeks of purchase lead time: almonds, candied orange and orange blossom water are ordered in November. The cream-filled rosca can't be made ahead: it lives in the cooler at 39 °F and has to be date-marked if held.
A7: Valentine's Day | B7: 0 | C7: 0 | D7: =IFERROR(B7*C7,"") -> 0 | E7: ='Settings'!$B$21 -> 13.364483 | F7: =IFERROR(D7*E7,"") -> 0 | G7: ='Peak Capacity vs Demand'!P7 -> 1 | H7: =IF(G7="","",IF(B7>=G7,"Yes","No")) -> No | I7: 0.1965 | J7: ='6-Peak Calendar'!M7 -> 520 | K7: =IFERROR(I7*J7,"") -> 102.18 | L7: ='6-Peak Calendar'!Q7 -> 3 | M7: =IFERROR(L7*7+'6-Peak Calendar'!E7,"") -> 23 | N7: =IFERROR(K7*'Settings'!$B$24*M7/365,"") -> 0.39920186 | O7: =IFERROR(I7*'6-Peak Calendar'!L7*'6-Peak Calendar'!E7,"") -> 64.845 | P7: ='6-Peak Calendar'!O7 -> 630 | Q7: =IFERROR(P7-O7-F7-N7,"") -> 564.7558 | R7: Two days and a high ticket: you win with boxes and presentation, not with more oven. Extra staff comes out at ZERO people and ZERO dollars on purpose -the person you need is already on the base team-, which is why "Does the extra staff cover it?" says "No": it isn't a bug, it's that you don't hire extra staff here, you cover it with the base team.
A8: Mother's Day | B8: 1 | C8: 16 | D8: =IFERROR(B8*C8,"") -> 16 | E8: ='Settings'!$B$21 -> 13.364483 | F8: =IFERROR(D8*E8,"") -> 213.83172 | G8: ='Peak Capacity vs Demand'!P8 -> 1 | H8: =IF(G8="","",IF(B8>=G8,"Yes","No")) -> Yes | I8: 1.1523 | J8: ='6-Peak Calendar'!M8 -> 384 | K8: =IFERROR(I8*J8,"") -> 442.4832 | L8: ='6-Peak Calendar'!Q8 -> 3 | M8: =IFERROR(L8*7+'6-Peak Calendar'!E8,"") -> 25 | N8: =IFERROR(K8*'Settings'!$B$24*M8/365,"") -> 1.8790382 | O8: =IFERROR(I8*'6-Peak Calendar'!L8*'6-Peak Calendar'!E8,"") -> 368.736 | P8: ='6-Peak Calendar'!O8 -> 1047.2727 | Q8: =IFERROR(P8-O8-F8-N8,"") -> 462.82597 | R8: One operating date for Día de las Madres and US Mother's Day: a personalized cake, made to order.
A9: Easter (Holy Week) | B9: 1 | C9: 40 | D9: =IFERROR(B9*C9,"") -> 40 | E9: ='Settings'!$B$21 -> 13.364483 | F9: =IFERROR(D9*E9,"") -> 534.5793 | G9: ='Peak Capacity vs Demand'!P9 -> 1 | H9: =IF(G9="","",IF(B9>=G9,"Yes","No")) -> Yes | I9: 0.2601 | J9: ='6-Peak Calendar'!M9 -> 1840 | K9: =IFERROR(I9*J9,"") -> 478.584 | L9: ='6-Peak Calendar'!Q9 -> 4 | M9: =IFERROR(L9*7+'6-Peak Calendar'!E9,"") -> 36 | N9: =IFERROR(K9*'Settings'!$B$24*M9/365,"") -> 2.9265739 | O9: =IFERROR(I9*'6-Peak Calendar'!L9*'6-Peak Calendar'!E9,"") -> 478.584 | P9: ='6-Peak Calendar'!O9 -> 4014.5455 | Q9: =IFERROR(P9-O9-F9-N9,"") -> 2998.4556 | R9: Eight days in a row of extra production, more exhausting than the five of Three Kings Day even though the peak is smaller. Torrijas and Easter cakes (monas) at once: one needs a fryer and cold, the other an oven and chocolate.
A10: First Communions and graduations | B10: 1 | C10: 60 | D10: =IFERROR(B10*C10,"") -> 60 | E10: ='Settings'!$B$21 -> 13.364483 | F10: =IFERROR(D10*E10,"") -> 801.86896 | G10: ='Peak Capacity vs Demand'!P10 -> 1 | H10: =IF(G10="","",IF(B10>=G10,"Yes","No")) -> Yes | I10: 0.7584 | J10: ='6-Peak Calendar'!M10 -> 680 | K10: =IFERROR(I10*J10,"") -> 515.712 | L10: ='6-Peak Calendar'!Q10 -> 5 | M10: =IFERROR(L10*7+'6-Peak Calendar'!E10,"") -> 55 | N10: =IFERROR(K10*'Settings'!$B$24*M10/365,"") -> 4.8180217 | O10: =IFERROR(I10*'6-Peak Calendar'!L10*'6-Peak Calendar'!E10,"") -> 364.032 | P10: ='6-Peak Calendar'!O10 -> 1527.2727 | Q10: =IFERROR(P10-O10-F10-N10,"") -> 356.55375 | R10: It's not a peak, it's a two-month plateau: you carry it with staff, not overtime, which is why the days made ahead go to zero. Everything is by custom order, with a deposit and cancellation risk.
A11: All Saints' Day and Día de los Muertos | B11: 2 | C11: 24 | D11: =IFERROR(B11*C11,"") -> 48 | E11: ='Settings'!$B$21 -> 13.364483 | F11: =IFERROR(D11*E11,"") -> 641.49516 | G11: ='Peak Capacity vs Demand'!P11 -> 1 | H11: =IF(G11="","",IF(B11>=G11,"Yes","No")) -> Yes | I11: 0.1695 | J11: ='6-Peak Calendar'!M11 -> 1410 | K11: =IFERROR(I11*J11,"") -> 238.995 | L11: ='6-Peak Calendar'!Q11 -> 4 | M11: =IFERROR(L11*7+'6-Peak Calendar'!E11,"") -> 31 | N11: =IFERROR(K11*'Settings'!$B$24*M11/365,"") -> 1.2584887 | O11: =IFERROR(I11*'6-Peak Calendar'!L11*'6-Peak Calendar'!E11,"") -> 238.995 | P11: ='6-Peak Calendar'!O11 -> 2050.9091 | Q11: =IFERROR(P11-O11-F11-N11,"") -> 1169.1604 | R11: Three days with three items that are only made now. The buñuelos are cream-filled (kept cold and date-marked if held) and the huesos de santo are shelf-stable at room temperature: that's why the huesos de santo can be made ahead and the buñuelos can't.
A13: TOTAL FOR THE YEAR | D13: =SUM(D6:D11) -> 284 | F13: =SUM(F6:F11) -> 3795.5131 | H13: =COUNTIF(H6:H11,"No") -> 2 | I13: campaigns with short extra staff | K13: =SUM(K6:K11) -> 3856.9942 | N13: =SUM(N6:N11) -> 27.879468 | O13: =SUM(O6:O11) -> 3594.232 | P13: =SUM(P6:P11) -> 21270 | Q13: =SUM(Q6:Q11) -> 13852.375
A15: The employer cost per hour isn't the pay: it's the monthly pay times 12 plus payroll taxes, workers' comp and benefits, divided by annual hours actually worked. It comes from the "Settings" sheet and in the example it's about a third more than the pay. Hiring extra staff for less than that number means hiring at a loss.
A16: The "campaign ingredient purchase" is the money that leaves your account BEFORE the first dollar of the campaign comes in. Multiply it by the days it sits idle and by the cost of money, and you have the campaign's financing cost, which almost nobody counts and which on Three Kings Day is real.
A17: The "incremental result" subtracts only what the campaign adds: the materials for the extra units, the extra staff and the financing cost. It doesn't subtract rent or base payroll, which you pay anyway. If it comes out negative, the campaign is costing you money.
A18: Boundary with your task calendar: your annual task calendar tells you WHAT to do and WHEN in each campaign, and your daily task checklists carry the detail of each event. This workbook tells you HOW MUCH it costs and WHETHER you can handle it. If you already track production, replace the unit estimates with your real production data.
A20: Version 1.0 · October 2026 · aichef.pro/en/digital-products/how-to-open-a-pastry-shop · info@aichef.pro
