Workbook

Sheet Instructions
A1: Staff Schedule and Labor Cost
A2: AI Chef Pro · aichef.pro — How to Open a Pastry Shop
A3: Purpose: decide how many people you need, in which roles, on which shift, and what they really cost with payroll taxes, workers' comp and benefits included.
A5: How to use it
A6: 1. "Settings" sheet: the six rows of the example wage table, the pay periods, the employer payroll cost, the full-time week and the month you plan to open. All in green: type the pay you'll actually offer in each row and the whole workbook recalculates.
A7: 2. "Weekly Schedule" sheet: how many hours each person works each day. It comes filled in with the team of the "La Clara" case: five people and 3.5 FTEs. The sheet adds up the hours per person and per day, separates production kitchen from front counter and warns you if any day you're open ends up with nobody at the counter.
A8: 3. "Hours and Cost" sheet: assign each person a pay grade and the sheet calculates the pay adjusted to their hours, the annual pay over 12 pay periods, the employer cost with payroll taxes, workers' comp and benefits included, and the cost per hour worked. It warns you if anyone goes over a full-time week and if a pay grade falls below the minimum wage.
A9: 4. "Hiring Plan" sheet: when you put each person on payroll and what the first year costs, which is NOT the steady-state year because nobody starts on day 1. Below it, the extra staff for the six campaigns: people, hours and cost of each peak.
A10: 5. Take only two numbers to 3-year-financial-plan.xlsx: the staff cost of the steady-state year and of the first year. They're copied by hand, on purpose: in this whole pack there isn't a single formula pointing to another file.
A12: Green cells = fields you can edit
A14: What to know before you start
A15: FROM BASE PAY TO EMPLOYER COST THERE'S A 33% GAP, AND THAT'S THE NUMBER THAT SINKS PLANS. A Bakery Assistant at $1,490.53 a month doesn't cost $1,490.53: with payroll taxes, workers' comp and benefits on top, it costs almost $24,000 a year at full time. The La Clara team -five people, 3.5 FTEs- comes to more than $92,000 a year. That's the number you take to the financial plan.
... A30: Version 1.0 · October 2026 · aichef.pro/en/digital-products/how-to-open-a-pastry-shop · info@aichef.pro

Sheet Settings
A1: Settings: Pay Grades, Payroll Costs and Hours
A2: AI Chef Pro · aichef.pro — How to Open a Pastry Shop
A3: Everything green on this sheet drives the other three. The six monthly pay figures are the example wage table of the modeled case: replace them with the pay you'll offer.
A5: The six pay grades of the example wage table
A6: The modeled case's wage table: an example, not a legal schedule. Replace it with what you'll pay; check federal, state and city minimum wage.
A7: Group | B7: Name | C7: Monthly pay ($) | D7: Annual pay ($) | E7: Functional areas | F7: Roles the table lists | G7: Note
A8: 1 | B8: Office and administration (degree-level) | C8: 2167.35 | D8: 26008.2 | E8: ADMINISTRATION | G8: Base pay, before overtime. Federal law has no night or weekend premium; check your state.
A9: 2 | B9: Management and supervisors | C9: 1784.8625 | D9: 21418.35 | E9: PRODUCTION KITCHEN · FRONT COUNTER · ADMINISTRATION | F9: head of the production kitchen | G9: Base pay, before overtime. Federal law has no night or weekend premium; check your state.
A10: 3 | B10: Skilled specialists | C10: 1721.1375 | D10: 20653.65 | E10: PRODUCTION KITCHEN · FRONT COUNTER | F10: lead production baker, section lead, head counter associate | G10: Base pay, before overtime. Federal law has no night or weekend premium; check your state.
A11: 4 | B11: Qualified staff | C11: 1561.775 | D11: 18741.3 | E11: PRODUCTION KITCHEN · FRONT COUNTER | F11: production baker, lead packer, counter associate, delivery driver | G11: Base pay, before overtime. Federal law has no night or weekend premium; check your state.
A12: 5 | B12: Support staff | C12: 1490.525 | D12: 17886.3 | E12: PRODUCTION KITCHEN · FRONT COUNTER | F12: production assistant, finisher, counter assistant | G12: Base pay, before overtime. Federal law has no night or weekend premium; check your state.
A13: 6 | B13: Auxiliary services | C13: 1490.525 | D13: 17886.3 | E13: PRODUCTION KITCHEN · FRONT COUNTER | F13: general laborer, cleaner, stock clerk | G13: Base pay, before overtime. Federal law has no night or weekend premium; check your state.
A15: Pay periods per year | C15: 12 | E15: 12 equal pay periods: the US has no extra pay months. If you run biweekly payroll, the annual cost is the same; only the size and timing of each check change.
A16: Annual pay of the lowest pay grade ($) | C16: =IFERROR(MIN($C$8:$C$13)*$C$15,"") -> 17886.3 | E16: Calculated from the pay above and the pay periods: it's the number compared with the minimum wage.
A17: Minimum wage, full-time (annual: $7.25 × 2,080 h) | C17: 15080 | E17: Annual figure for a full-time job at the federal minimum ($7.25 × 2,080 hours = $15,080, or $1,256.67 a month). State and city minimums can be higher (California, New York and Florida are): replace it with the one that applies to you.
A18: Wage table or minimum wage? | C18: =IF($C$16="","",IF($C$16>=$C$17,"The wage table is above the minimum wage","WARNING: the lowest group falls below the annual minimum wage")) -> The wage table is above the minimum wage | E18: This flag is here in case you type a different table: no group can fall below the minimum wage on an annual basis. Your state and city may require more than the federal minimum.
A20: Payroll costs, hours and calendar
A21: Payroll taxes, workers' comp and benefits (%) | C21: 0.33 | E21: Approximate employer cost on top of base pay: payroll taxes (FICA 7.65%, FUTA and state unemployment), workers' comp and benefits such as health insurance and paid time off. The mandatory part is around 10%; the rest depends on the benefits you offer. Adjust it to your state and your hires.
A22: Hours per week for a full-time job | C22: 40 | E22: ASSUMPTION: the standard full-time week is 40 hours. Change it to your own policy: it decides who counts as over a full week and how many FTEs you have. Under the FLSA, overtime (1.5×) starts after 40 hours worked in a week.
A23: Annual hours actually worked | C23: 1780 | E23: ASSUMPTION: 40 h × 52 weeks = 2,080, less paid time off and holidays, comes to about 1,780 hours actually worked. It's the divisor of the hourly cost, which is why the hourly cost comes out higher than people expect.
A24: Days open per week | C24: 6 | E24: ASSUMPTION: six days a week, closed on Sunday. Opening days are your decision, not a permit you ask for; check your lease and any local rules.
A25: Planned opening month (1 to 12) | C25: 9 | E25: ASSUMPTION: September. It's none of the six peaks and leaves three and a half months of running in before Three Kings Day, the campaign that decides the year. The realistic date comes from the critical path in permits-and-licenses-checklist.xlsx.
A27: The monthly pay figures and the pay periods are the example wage table of the modeled case (hover over each cell for the note). Everything else on this sheet is an ASSUMPTION and each note says so. A different wage table doesn't change a formula in this workbook: it changes six numbers.
A28: What this sheet leaves out on purpose: overtime, shift or night premiums, bonuses, transportation allowances and hiring tax credits. They're real and they change the cost, but they depend on your state and on each job: when you have them, add them to each group's monthly pay.
A31: Designed by John Guerrero — chef and restaurant consultant since 2010, in the kitchen since age 17.
A32: Version 1.0 · October 2026 · aichef.pro/en/digital-products/how-to-open-a-pastry-shop · info@aichef.pro

Sheet Weekly Schedule
A1: Weekly Schedule
A2: AI Chef Pro · aichef.pro — How to Open a Pastry Shop
A3: Five people and 3.5 FTEs: the staffing of the "La Clara" case. Four roles, with two people as Counter Associate.
A5: Which days is the front counter open?
A6: Day | E6: Mon | F6: Tue | G6: Wed | H6: Thu | I6: Fri | J6: Sat | K6: Sun
A7: Is the front counter open? | E7: Yes | F7: Yes | G7: Yes | H7: Yes | I7: Yes | J7: Yes | K7: No | L7: ASSUMPTION: six days, closed on Sunday. It's your decision, not a permit.
A9: Hours per person per day
A10: ID | B10: Person (role) | C10: Area | D10: Shift | E10: Mon | F10: Tue | G10: Wed | H10: Thu | I10: Fri | J10: Sat | K10: Sun | L10: Planned hours / week | M10: Contracted hours / week | N10: Difference (h) | O10: Note
A11: P1 | B11: Head Pastry Chef | C11: PRODUCTION KITCHEN | D11: Early bake (04:30-12:30) | E11: 0 | F11: 8 | G11: 8 | H11: 8 | I11: 8 | J11: 8 | K11: 0 | L11: =SUM($E11:$K11) -> 40 | M11: 40 | N11: =IFERROR(IF(OR($L11="",$M11=""),"",$L11-$M11),"") -> 0 | O11: Contracted hours: full time. The split of hours is an ASSUMPTION that adds up to that.
A12: P2 | B12: Pastry Cook | C12: PRODUCTION KITCHEN | D12: Early bake (05:00-13:00) | E12: 8 | F12: 8 | G12: 8 | H12: 8 | I12: 8 | J12: 0 | K12: 0 | L12: =SUM($E12:$K12) -> 40 | M12: 40 | N12: =IFERROR(IF(OR($L12="",$M12=""),"",$L12-$M12),"") -> 0 | O12: Contracted hours: full time. The split of hours is an ASSUMPTION that adds up to that.
A13: P3 | B13: Bakery Assistant | C13: PRODUCTION KITCHEN | D13: Morning (07:00-11:00) | E13: 4 | F13: 4 | G13: 4 | H13: 4 | I13: 4 | J13: 0 | K13: 0 | L13: =SUM($E13:$K13) -> 20 | M13: 20 | N13: =IFERROR(IF(OR($L13="",$M13=""),"",$L13-$M13),"") -> 0 | O13: Contracted hours: 50%. The split of hours is an ASSUMPTION that adds up to that.
A14: P4 | B14: Counter Associate A | C14: FRONT COUNTER | D14: Morning (08:00-12:00) | E14: 4 | F14: 4 | G14: 4 | H14: 4 | I14: 4 | J14: 0 | K14: 0 | L14: =SUM($E14:$K14) -> 20 | M14: 20 | N14: =IFERROR(IF(OR($L14="",$M14=""),"",$L14-$M14),"") -> 0 | O14: Contracted hours: 50%. The split of hours is an ASSUMPTION that adds up to that.
A15: P5 | B15: Counter Associate B | C15: FRONT COUNTER | D15: Afternoon (16:30-20:30) | E15: 0 | F15: 4 | G15: 4 | H15: 4 | I15: 4 | J15: 4 | K15: 0 | L15: =SUM($E15:$K15) -> 20 | M15: 20 | N15: =IFERROR(IF(OR($L15="",$M15=""),"",$L15-$M15),"") -> 0 | O15: Contracted hours: 50%. The split of hours is an ASSUMPTION that adds up to that.
A16: TOTAL for the team | E16: =SUM($E$11:$E$15) -> 16 | F16: =SUM($F$11:$F$15) -> 28 | G16: =SUM($G$11:$G$15) -> 28 | H16: =SUM($H$11:$H$15) -> 28 | I16: =SUM($I$11:$I$15) -> 28 | J16: =SUM($J$11:$J$15) -> 12 | K16: =SUM($K$11:$K$15) -> 0 | L16: =SUM($L$11:$L$15) -> 140 | M16: =SUM($M$11:$M$15) -> 140
A17: PRODUCTION KITCHEN hours per day | E17: =SUMPRODUCT(--($C$11:$C$15="PRODUCTION KITCHEN"),$E$11:$E$15) -> 12 | F17: =SUMPRODUCT(--($C$11:$C$15="PRODUCTION KITCHEN"),$F$11:$F$15) -> 20 | G17: =SUMPRODUCT(--($C$11:$C$15="PRODUCTION KITCHEN"),$G$11:$G$15) -> 20 | H17: =SUMPRODUCT(--($C$11:$C$15="PRODUCTION KITCHEN"),$H$11:$H$15) -> 20 | I17: =SUMPRODUCT(--($C$11:$C$15="PRODUCTION KITCHEN"),$I$11:$I$15) -> 20 | J17: =SUMPRODUCT(--($C$11:$C$15="PRODUCTION KITCHEN"),$J$11:$J$15) -> 8 | K17: =SUMPRODUCT(--($C$11:$C$15="PRODUCTION KITCHEN"),$K$11:$K$15) -> 0
A18: FRONT COUNTER hours per day | E18: =SUMPRODUCT(--($C$11:$C$15="FRONT COUNTER"),$E$11:$E$15) -> 4 | F18: =SUMPRODUCT(--($C$11:$C$15="FRONT COUNTER"),$F$11:$F$15) -> 8 | G18: =SUMPRODUCT(--($C$11:$C$15="FRONT COUNTER"),$G$11:$G$15) -> 8 | H18: =SUMPRODUCT(--($C$11:$C$15="FRONT COUNTER"),$H$11:$H$15) -> 8 | I18: =SUMPRODUCT(--($C$11:$C$15="FRONT COUNTER"),$I$11:$I$15) -> 8 | J18: =SUMPRODUCT(--($C$11:$C$15="FRONT COUNTER"),$J$11:$J$15) -> 4 | K18: =SUMPRODUCT(--($C$11:$C$15="FRONT COUNTER"),$K$11:$K$15) -> 0
A19: Counter coverage | E19: =IF($E$7<>"Yes","Closed",IF($E$18=0,"NOBODY","Covered")) -> Covered | F19: =IF($F$7<>"Yes","Closed",IF($F$18=0,"NOBODY","Covered")) -> Covered | G19: =IF($G$7<>"Yes","Closed",IF($G$18=0,"NOBODY","Covered")) -> Covered | H19: =IF($H$7<>"Yes","Closed",IF($H$18=0,"NOBODY","Covered")) -> Covered | I19: =IF($I$7<>"Yes","Closed",IF($I$18=0,"NOBODY","Covered")) -> Covered | J19: =IF($J$7<>"Yes","Closed",IF($J$18=0,"NOBODY","Covered")) -> Covered | K19: =IF($K$7<>"Yes","Closed",IF($K$18=0,"NOBODY","Covered")) -> Closed
A21: Summary of the week
A22: Planned hours per week | E22: =$L$16 -> 140 | H22: It's the standard cruising-speed week, with no campaigns.
A23: FTEs | E23: =IFERROR($L$16/'Settings'!$C$22,"") -> 3.5 | H23: Planned hours divided by the full-time week. The La Clara case is 3.5 FTEs spread across five people.
A24: Production kitchen hours per week | E24: =SUMPRODUCT(--($C$11:$C$15="PRODUCTION KITCHEN"),$E$11:$E$15)+SUMPRODUCT(--($C$11:$C$15="PRODUCTION KITCHEN"),$F$11:$F$15)+SUMPRODUCT(--($C$11:$C$15="PRODUCTION KITCHEN"),$G$11:$G$15)+SUMPRODUCT(--($C$11:$C$15="PRODUCTION KITCHEN"),$H$11:$H$15)+SUMPRODUCT(--($C$11:$C$15="PRODUCTION KITCHEN"),$I$11:$I$15)+SUMPRODUCT(--($C$11:$C$15="PRODUCTION KITCHEN"),$J$11:$J$15)+SUMPRODUCT(--($C$11:$C$15="PRODUCTION KITCHEN"),$K$11:$K$15) -> 100 | H24: These are the hours that have to deliver the production kitchen output that kitchen-capacity-and-site.xlsx calculates. If they don't reach, the problem isn't the oven.
A25: Front counter hours per week | E25: =SUMPRODUCT(--($C$11:$C$15="FRONT COUNTER"),$E$11:$E$15)+SUMPRODUCT(--($C$11:$C$15="FRONT COUNTER"),$F$11:$F$15)+SUMPRODUCT(--($C$11:$C$15="FRONT COUNTER"),$G$11:$G$15)+SUMPRODUCT(--($C$11:$C$15="FRONT COUNTER"),$H$11:$H$15)+SUMPRODUCT(--($C$11:$C$15="FRONT COUNTER"),$I$11:$I$15)+SUMPRODUCT(--($C$11:$C$15="FRONT COUNTER"),$J$11:$J$15)+SUMPRODUCT(--($C$11:$C$15="FRONT COUNTER"),$K$11:$K$15) -> 40 | H25: Counter and customer service. In a neighborhood pastry shop, sales concentrate in two windows and on Saturday.
A26: Days open with nobody at the counter | E26: =COUNTIF($E$19:$K$19,"NOBODY") -> 0 | H26: It has to be zero before you make job offers. It's the costliest sizing mistake and the easiest to see.
A28: List (dropdown source)
A29: No. | B29: Is the front counter open?
A30: 1 | B30: Yes
A31: 2 | B31: No
A33: The split of hours by day is an ASSUMPTION that matches each person's contracted hours to the six days open. Your real split depends on what time the production kitchen starts (here, between 4:30 and 5:00) and where your sales peaks are. What doesn't change is the arithmetic: if you plan more hours than you contract, the "Difference" column says so.
A34: This sheet is neither your day-to-day schedule nor your timekeeping record. The FLSA requires you to keep records of hours worked each day and each week for non-exempt employees (any complete and accurate method works), and that is kept separately. This is the sizing you hire from and calculate the cost with.
A35: What each role does on its shift belongs with your daily task checklists: this workbook doesn't repeat it.
A37: Designed by John Guerrero — chef and restaurant consultant since 2010, in the kitchen since age 17.
A38: Version 1.0 · October 2026 · aichef.pro/en/digital-products/how-to-open-a-pastry-shop · info@aichef.pro

Sheet Hours and Cost
A1: Hours and Labor Cost
A2: AI Chef Pro · aichef.pro — How to Open a Pastry Shop
A3: From the table's pay to the employer cost there's a 33% gap: payroll taxes, workers' comp and benefits. That's the number you take to the financial plan, not the pay.
A5: Cost person by person
A6: ID | B6: Person (role) | C6: Area | D6: Pay grade | E6: Monthly pay of the group ($) | F6: FTE | G6: Hours / week | H6: Adjusted monthly pay ($) | I6: Annual pay ($) | J6: Employer cost per month ($) | K6: Employer cost per year ($) | L6: Employer cost per hour worked ($) | M6: Full-time week check | N6: Minimum wage check
A7: P1 | B7: Head Pastry Chef | C7: PRODUCTION KITCHEN | D7: Management and supervisors | E7: =IFERROR(INDEX('Settings'!$C$8:$C$13,MATCH($D7,'Settings'!$B$8:$B$13,0)),"") -> 1784.8625 | F7: =IFERROR(IF($G7="","",$G7/'Settings'!$C$22),"") -> 1 | G7: ='Weekly Schedule'!$L$11 -> 40 | H7: =IFERROR(IF(OR($E7="",$F7=""),"",$E7*$F7),"") -> 1784.8625 | I7: =IFERROR(IF($H7="","",$H7*'Settings'!$C$15),"") -> 21418.35 | J7: =IFERROR(IF($K7="","",$K7/12),"") -> 2373.8671 | K7: =IFERROR(IF($I7="","",$I7*(1+'Settings'!$C$21)),"") -> 28486.406 | L7: =IFERROR(IF(OR($K7="",$F7=""),"",$K7/('Settings'!$C$23*$F7)),"") -> 16.003599 | M7: =IF($G7="","",IF($G7>'Settings'!$C$22,"Goes over a full-time week","")) | N7: =IFERROR(IF($E7="","",IF($E7*'Settings'!$C$15<'Settings'!$C$17,"Below the annual minimum wage","")),"")
A8: P2 | B8: Pastry Cook | C8: PRODUCTION KITCHEN | D8: Skilled specialists | E8: =IFERROR(INDEX('Settings'!$C$8:$C$13,MATCH($D8,'Settings'!$B$8:$B$13,0)),"") -> 1721.1375 | F8: =IFERROR(IF($G8="","",$G8/'Settings'!$C$22),"") -> 1 | G8: ='Weekly Schedule'!$L$12 -> 40 | H8: =IFERROR(IF(OR($E8="",$F8=""),"",$E8*$F8),"") -> 1721.1375 | I8: =IFERROR(IF($H8="","",$H8*'Settings'!$C$15),"") -> 20653.65 | J8: =IFERROR(IF($K8="","",$K8/12),"") -> 2289.1129 | K8: =IFERROR(IF($I8="","",$I8*(1+'Settings'!$C$21)),"") -> 27469.355 | L8: =IFERROR(IF(OR($K8="",$F8=""),"",$K8/('Settings'!$C$23*$F8)),"") -> 15.432222 | M8: =IF($G8="","",IF($G8>'Settings'!$C$22,"Goes over a full-time week","")) | N8: =IFERROR(IF($E8="","",IF($E8*'Settings'!$C$15<'Settings'!$C$17,"Below the annual minimum wage","")),"")
A9: P3 | B9: Bakery Assistant | C9: PRODUCTION KITCHEN | D9: Support staff | E9: =IFERROR(INDEX('Settings'!$C$8:$C$13,MATCH($D9,'Settings'!$B$8:$B$13,0)),"") -> 1490.525 | F9: =IFERROR(IF($G9="","",$G9/'Settings'!$C$22),"") -> 0.5 | G9: ='Weekly Schedule'!$L$13 -> 20 | H9: =IFERROR(IF(OR($E9="",$F9=""),"",$E9*$F9),"") -> 745.2625 | I9: =IFERROR(IF($H9="","",$H9*'Settings'!$C$15),"") -> 8943.15 | J9: =IFERROR(IF($K9="","",$K9/12),"") -> 991.19913 | K9: =IFERROR(IF($I9="","",$I9*(1+'Settings'!$C$21)),"") -> 11894.39 | L9: =IFERROR(IF(OR($K9="",$F9=""),"",$K9/('Settings'!$C$23*$F9)),"") -> 13.364483 | M9: =IF($G9="","",IF($G9>'Settings'!$C$22,"Goes over a full-time week","")) | N9: =IFERROR(IF($E9="","",IF($E9*'Settings'!$C$15<'Settings'!$C$17,"Below the annual minimum wage","")),"")
A10: P4 | B10: Counter Associate A | C10: FRONT COUNTER | D10: Qualified staff | E10: =IFERROR(INDEX('Settings'!$C$8:$C$13,MATCH($D10,'Settings'!$B$8:$B$13,0)),"") -> 1561.775 | F10: =IFERROR(IF($G10="","",$G10/'Settings'!$C$22),"") -> 0.5 | G10: ='Weekly Schedule'!$L$14 -> 20 | H10: =IFERROR(IF(OR($E10="",$F10=""),"",$E10*$F10),"") -> 780.8875 | I10: =IFERROR(IF($H10="","",$H10*'Settings'!$C$15),"") -> 9370.65 | J10: =IFERROR(IF($K10="","",$K10/12),"") -> 1038.5804 | K10: =IFERROR(IF($I10="","",$I10*(1+'Settings'!$C$21)),"") -> 12462.965 | L10: =IFERROR(IF(OR($K10="",$F10=""),"",$K10/('Settings'!$C$23*$F10)),"") -> 14.003331 | M10: =IF($G10="","",IF($G10>'Settings'!$C$22,"Goes over a full-time week","")) | N10: =IFERROR(IF($E10="","",IF($E10*'Settings'!$C$15<'Settings'!$C$17,"Below the annual minimum wage","")),"")
A11: P5 | B11: Counter Associate B | C11: FRONT COUNTER | D11: Qualified staff | E11: =IFERROR(INDEX('Settings'!$C$8:$C$13,MATCH($D11,'Settings'!$B$8:$B$13,0)),"") -> 1561.775 | F11: =IFERROR(IF($G11="","",$G11/'Settings'!$C$22),"") -> 0.5 | G11: ='Weekly Schedule'!$L$15 -> 20 | H11: =IFERROR(IF(OR($E11="",$F11=""),"",$E11*$F11),"") -> 780.8875 | I11: =IFERROR(IF($H11="","",$H11*'Settings'!$C$15),"") -> 9370.65 | J11: =IFERROR(IF($K11="","",$K11/12),"") -> 1038.5804 | K11: =IFERROR(IF($I11="","",$I11*(1+'Settings'!$C$21)),"") -> 12462.965 | L11: =IFERROR(IF(OR($K11="",$F11=""),"",$K11/('Settings'!$C$23*$F11)),"") -> 14.003331 | M11: =IF($G11="","",IF($G11>'Settings'!$C$22,"Goes over a full-time week","")) | N11: =IFERROR(IF($E11="","",IF($E11*'Settings'!$C$15<'Settings'!$C$17,"Below the annual minimum wage","")),"")
A12: TOTAL for the team | F12: =SUM($F$7:$F$11) -> 3.5 | G12: =SUM($G$7:$G$11) -> 140 | H12: =SUM($H$7:$H$11) -> 5813.0375 | I12: =SUM($I$7:$I$11) -> 69756.45 | J12: =SUM($J$7:$J$11) -> 7731.3399 | K12: =SUM($K$7:$K$11) -> 92776.079
A14: What goes to the financial plan
A15: Staff cost per month ($) | E15: =$J$12 -> 7731.3399 | G15: Employer cost, with payroll taxes, workers' comp and benefits inside. It's one of the two big lines of the fixed costs in 3-year-financial-plan.xlsx.
A16: Staff cost per year ($) | E16: =$K$12 -> 92776.079 | G16: The full steady-state year. The first year costs less because nobody starts on day 1: the "Hiring Plan" sheet calculates that.
A17: FTEs | E17: =$F$12 -> 3.5 | G17: Five people, 3.5 FTEs. Counting people instead of FTEs is the mistake that makes a plan look oversized.
A18: Average employer cost per hour worked for the team ($) | E18: =IFERROR(IF($F$12=0,"",$K$12/('Settings'!$C$23*$F$12)),"") -> 14.891826 | G18: Average for the WHOLE team (production kitchen + front counter), over hours worked. It is NOT the "productive-hour production kitchen cost" of opening-menu-and-recipe-costing.xlsx ($17.94, production kitchen only and productive hours only) nor the "employer cost per hour worked for the extra staff" of seasonal-peaks-planner.xlsx ($13.36, Group 5 only): all three are correct and measure a different denominator.
A19: What payroll taxes, workers' comp and benefits cost per year ($) | E19: =IFERROR($K$12-$I$12,"") -> 23019.629 | G19: The difference between what they earn as pay and what you pay out. It isn't negotiable and it can't be forgotten.
A20: Sum of annual pay ($) | E20: =$I$12 -> 69756.45 | G20: What the five people earn, before payroll taxes, workers' comp and benefits.
A22: Pay grade list (dropdown source)
A23: Group | B23: Name
A24: ='Settings'!$A$8 -> 1 | B24: ='Settings'!$B$8 -> Office and administration (degree-level)
A25: ='Settings'!$A$9 -> 2 | B25: ='Settings'!$B$9 -> Management and supervisors
A26: ='Settings'!$A$10 -> 3 | B26: ='Settings'!$B$10 -> Skilled specialists
A27: ='Settings'!$A$11 -> 4 | B27: ='Settings'!$B$11 -> Qualified staff
A28: ='Settings'!$A$12 -> 5 | B28: ='Settings'!$B$12 -> Support staff
A29: ='Settings'!$A$13 -> 6 | B29: ='Settings'!$B$13 -> Auxiliary services
A31: The hours in column G are read from the "Weekly Schedule" sheet: if you change a shift, the cost changes here. FTE is planned hours divided by the full-time week, so a 20-hour job costs half as much as a 40-hour one in the same group. What doesn't prorate is whatever doesn't depend on hours: work clothes, training and any medical exam cost almost the same for a half-time job as for a full-time one.
A32: The 33% for payroll taxes, workers' comp and benefits is an approximation of your employer cost (FICA, FUTA and state unemployment, workers' comp and benefits). Your real rate depends on your state, your insurer and the benefits you offer: change it in "Settings" and the whole workbook recalculates. In Texas, workers' comp is optional for private employers (non-subscribers); the case keeps it inside the 33%.
A33: This workbook doesn't calculate payroll or exact payroll taxes, and it doesn't replace your accountant or payroll provider: it calculates the SIZING and its cost, which is what you need to know before you sign the lease.
A35: Designed by John Guerrero — chef and restaurant consultant since 2010, in the kitchen since age 17.
A36: Version 1.0 · October 2026 · aichef.pro/en/digital-products/how-to-open-a-pastry-shop · info@aichef.pro

Sheet Hiring Plan
A1: Hiring Plan and Campaign Extra Staff
A2: AI Chef Pro · aichef.pro — How to Open a Pastry Shop
A3: The first year doesn't cost what the steady-state year does: nobody starts on day 1, and campaigns bring extra staff. These are the two numbers that go to the financial plan.
A5: Hires
A6: ID | B6: Person (role) | C6: Planned start date | D6: Start month | E6: Months in year 1 | F6: Employer cost per month ($) | G6: Year 1 cost ($) | H6: Steady-state year cost ($) | I6: Year 1 savings ($) | J6: Why they start when they do | K6: Note
A7: P1 | B7: Head Pastry Chef | C7: 46601 | D7: =IFERROR(IF($C7="","",MONTH($C7)),"") -> 8 | E7: =IFERROR(IF($D7="","",MIN(12,MAX(0,12-($D7-'Settings'!$C$25)))),"") -> 12 | F7: ='Hours and Cost'!$J$7 -> 2373.8671 | G7: =IFERROR(IF(OR($E7="",$F7=""),"",$E7*$F7),"") -> 28486.406 | H7: ='Hours and Cost'!$K$7 -> 28486.406 | I7: =IFERROR(IF(OR($G7="",$H7=""),"",$H7-$G7),"") -> 3.6379788e-12 | J7: A month before opening: finishes the opening menu, runs the production tests and receives the equipment. | K7: Before the first shift: Form I-9, payroll setup and workers' comp (optional in Texas).
A8: P2 | B8: Pastry Cook | C8: 46615 | D8: =IFERROR(IF($C8="","",MONTH($C8)),"") -> 8 | E8: =IFERROR(IF($D8="","",MIN(12,MAX(0,12-($D8-'Settings'!$C$25)))),"") -> 12 | F8: ='Hours and Cost'!$J$8 -> 2289.1129 | G8: =IFERROR(IF(OR($E8="",$F8=""),"",$E8*$F8),"") -> 27469.355 | H8: ='Hours and Cost'!$K$8 -> 27469.355 | I8: =IFERROR(IF(OR($G8="",$H8=""),"",$H8-$G8),"") -> 3.6379788e-12 | J8: Two weeks before: starts once the production kitchen is set up and the batches have to be tried for real. | K8: Before the first shift: Form I-9, payroll setup and workers' comp (optional in Texas).
A9: P3 | B9: Bakery Assistant | C9: 46631 | D9: =IFERROR(IF($C9="","",MONTH($C9)),"") -> 9 | E9: =IFERROR(IF($D9="","",MIN(12,MAX(0,12-($D9-'Settings'!$C$25)))),"") -> 12 | F9: ='Hours and Cost'!$J$9 -> 991.19913 | G9: =IFERROR(IF(OR($E9="",$F9=""),"",$E9*$F9),"") -> 11894.39 | H9: ='Hours and Cost'!$K$9 -> 11894.39 | I9: =IFERROR(IF(OR($G9="",$H9=""),"",$H9-$G9),"") -> 0 | J9: Opening day: until daily production starts there's nothing to help with. | K9: Before the first shift: Form I-9, payroll setup and workers' comp (optional in Texas).
A10: P4 | B10: Counter Associate A | C10: 46631 | D10: =IFERROR(IF($C10="","",MONTH($C10)),"") -> 9 | E10: =IFERROR(IF($D10="","",MIN(12,MAX(0,12-($D10-'Settings'!$C$25)))),"") -> 12 | F10: ='Hours and Cost'!$J$10 -> 1038.5804 | G10: =IFERROR(IF(OR($E10="",$F10=""),"",$E10*$F10),"") -> 12462.965 | H10: ='Hours and Cost'!$K$10 -> 12462.965 | I10: =IFERROR(IF(OR($G10="",$H10=""),"",$H10-$G10),"") -> 0 | J10: Opening day, morning shift. | K10: Before the first shift: Form I-9, payroll setup and workers' comp (optional in Texas).
A11: P5 | B11: Counter Associate B | C11: 46722 | D11: =IFERROR(IF($C11="","",MONTH($C11)),"") -> 12 | E11: =IFERROR(IF($D11="","",MIN(12,MAX(0,12-($D11-'Settings'!$C$25)))),"") -> 9 | F11: ='Hours and Cost'!$J$11 -> 1038.5804 | G11: =IFERROR(IF(OR($E11="",$F11=""),"",$E11*$F11),"") -> 9347.2234 | H11: ='Hours and Cost'!$K$11 -> 12462.965 | I11: =IFERROR(IF(OR($G11="",$H11=""),"",$H11-$G11),"") -> 3115.7411 | J11: Three months after opening: the afternoon shift opens when afternoon sales justify it, and it arrives in time for the Christmas season. | K11: Before the first shift: Form I-9, payroll setup and workers' comp (optional in Texas).
A12: TOTAL for the team | F12: =SUM($F$7:$F$11) -> 7731.3399 | G12: =SUM($G$7:$G$11) -> 89660.337 | H12: =SUM($H$7:$H$11) -> 92776.079 | I12: =SUM($I$7:$I$11) -> 3115.7411
A14: Extra staff for the six campaigns
A15: No. | B15: Campaign | C15: Dates | D15: Month | E15: Extra staff (people) | F15: Hours per person | G15: Pay grade | H15: Employer cost per hour worked ($) | I15: Extra staff cost ($) | J15: Purchase lead time | K15: Note
A16: 1 | B16: Día de Reyes (Three Kings Day) | C16: January 2–6 | D16: 1 | E16: 3 | F16: 40 | G16: Support staff | H16: =IFERROR(INDEX('Settings'!$C$8:$C$13,MATCH($G16,'Settings'!$B$8:$B$13,0))*'Settings'!$C$15*(1+'Settings'!$C$21)/'Settings'!$C$23,"") -> 13.364483 | I16: =IFERROR(IF(OR($E16="",$F16="",$H16=""),"",$E16*$F16*$H16),"") -> 1603.7379 | J16: 6 weeks ahead | K16: The peak that decides the year. The campaign units are those of the FIVE best-selling days: 160 a day, 800 in total, 47% of the roscas the menu mix assigns to the year (1.2% of the pieces). The rest sell in the week before, outside the campaign window, so they aren't in this row.
A17: 2 | B17: Valentine's Day | C17: February 13–14 | D17: 2 | E17: 0 | F17: 0 | G17: Support staff | H17: =IFERROR(INDEX('Settings'!$C$8:$C$13,MATCH($G17,'Settings'!$B$8:$B$13,0))*'Settings'!$C$15*(1+'Settings'!$C$21)/'Settings'!$C$23,"") -> 13.364483 | I17: =IFERROR(IF(OR($E17="",$F17="",$H17=""),"",$E17*$F17*$H17),"") -> 0 | J17: 3 weeks ahead | K17: Two-day, high-ticket campaign, not volume: you win with boxes and presentation, not with more oven. The special production for this date is heart-shaped cakes, bonbons and macarons.
A18: 3 | B18: Mother's Day | C18: Día de las Madres (May 10) and US Mother's Day (2nd Sunday of May) | D18: 5 | E18: 1 | F18: 16 | G18: Support staff | H18: =IFERROR(INDEX('Settings'!$C$8:$C$13,MATCH($G18,'Settings'!$B$8:$B$13,0))*'Settings'!$C$15*(1+'Settings'!$C$21)/'Settings'!$C$23,"") -> 13.364483 | I18: =IFERROR(IF(OR($E18="",$F18="",$H18=""),"",$E18*$F18*$H18),"") -> 213.83172 | J18: 3 weeks ahead | K18: One operating date for Día de las Madres (May 10) and US Mother's Day (2nd Sunday of May): a personalized cake, made to order. What matters to this guide is the load on the production kitchen, not the calendar.
A19: 4 | B19: Easter (Holy Week) | C19: Palm Sunday to Easter Sunday | D19: 4 | E19: 1 | F19: 40 | G19: Support staff | H19: =IFERROR(INDEX('Settings'!$C$8:$C$13,MATCH($G19,'Settings'!$B$8:$B$13,0))*'Settings'!$C$15*(1+'Settings'!$C$21)/'Settings'!$C$23,"") -> 13.364483 | I19: =IFERROR(IF(OR($E19="",$F19="",$H19=""),"",$E19*$F19*$H19),"") -> 534.5793 | J19: 4 weeks ahead | K19: Eight days in a row of extra production, more exhausting than the five of Three Kings Day even though the peak is smaller. Torrijas and Easter cakes (monas) at once: one needs a fryer and cold, the other an oven and chocolate. That's 230 torrijas a day and 1,840 over the campaign: 99% of the torrijas the menu mix assigns to the year.
A20: 5 | B20: First Communions and graduations | C20: mid-April to mid-June | D20: 5 | E20: 1 | F20: 60 | G20: Support staff | H20: =IFERROR(INDEX('Settings'!$C$8:$C$13,MATCH($G20,'Settings'!$B$8:$B$13,0))*'Settings'!$C$15*(1+'Settings'!$C$21)/'Settings'!$C$23,"") -> 13.364483 | I20: =IFERROR(IF(OR($E20="",$F20="",$H20=""),"",$E20*$F20*$H20),"") -> 801.86896 | J20: 5 weeks ahead | K20: It's not a peak, it's a two-month PLATEAU, which is why you carry it with staff and not with overtime. Everything is by custom order: deposit, delivery calendar and cancellation risk (chapter 16).
A21: 6 | B21: All Saints' Day and Día de los Muertos | C21: October 30 – November 1 | D21: 11 | E21: 2 | F21: 24 | G21: Support staff | H21: =IFERROR(INDEX('Settings'!$C$8:$C$13,MATCH($G21,'Settings'!$B$8:$B$13,0))*'Settings'!$C$15*(1+'Settings'!$C$21)/'Settings'!$C$23,"") -> 13.364483 | I21: =IFERROR(IF(OR($E21="",$F21="",$H21=""),"",$E21*$F21*$H21),"") -> 641.49516 | J21: 4 weeks ahead | K21: Three days with three items that are only made now: buñuelos, huesos de santo and panellets. The buñuelos are cream-filled (41 °F or below, and date-marked if held) and the other two are shelf-stable at room temperature: that's why buñuelos are made the same day and huesos de santo can be made ahead. That food-safety detail IS the campaign planning.
A22: TOTAL extra staff for the six campaigns | E22: =SUM($E$16:$E$21) -> 8 | F22: =SUM($F$16:$F$21) -> 180 | I22: =SUM($I$16:$I$21) -> 3795.5131
A24: The two numbers that go to the financial plan
A25: Year 1 staff cost ($) | F25: =$G$12 -> 89660.337 | H25: Only the months each person is on payroll from opening.
A26: Campaign extra staff cost over a year ($) | F26: =$I$22 -> 3795.5131 | H26: The six campaigns together. It's paid in the month of the campaign or the next one: look at the cash flow in 3-year-financial-plan.xlsx right there.
A27: Cumulative staff cost for the first year ($) | F27: =IFERROR($F$25+$F$26,"") -> 93455.85 | H27: This is the year 1 number. It's the one that goes in the plan, not the steady-state one.
A28: Steady-state year staff cost ($) | F28: ='Hours and Cost'!$E$16 -> 92776.079 | H28: Twelve months with the whole team, no extra staff. It's the one used from year 2 on.
A29: Difference between year 1 and the steady-state year ($) | F29: =IFERROR($F$27-$F$28,"") -> 679.77193 | H29: Negative = the first year costs less because not everyone is on board all twelve months.
A30: Start-up verdict | F30: =IF($F$29="","",IF($F$29<0,"The first year saves on staff: don't confuse that with the business going well","Extra staff eats the start-up savings: review the campaigns")) -> Extra staff eats the start-up savings: review the campaigns | H30: In year 1 the staff savings coincide with the months when there are no sales either: the ramp-up in 3-year-financial-plan.xlsx puts it in its place.
A32: Pay grade list (dropdown source)
A33: Group | B33: Name
A34: ='Settings'!$A$8 -> 1 | B34: ='Settings'!$B$8 -> Office and administration (degree-level)
A35: ='Settings'!$A$9 -> 2 | B35: ='Settings'!$B$9 -> Management and supervisors
A36: ='Settings'!$A$10 -> 3 | B36: ='Settings'!$B$10 -> Skilled specialists
A37: ='Settings'!$A$11 -> 4 | B37: ='Settings'!$B$11 -> Qualified staff
A38: ='Settings'!$A$12 -> 5 | B38: ='Settings'!$B$12 -> Support staff
A39: ='Settings'!$A$13 -> 6 | B39: ='Settings'!$B$13 -> Auxiliary services
A41: The start dates provided are ASSUMPTIONS consistent with the opening month in "Settings": the production kitchen starts earlier because the batches have to be rehearsed, and the front counter on opening day. The year 1 month count runs from the opening month, using month arithmetic and no calendar functions.
A42: Campaign extra staff is calculated with the employer cost per hour worked of the pay grade you choose, which already includes payroll taxes, workers' comp and benefits. Valentine's Day comes with zero extra people on purpose: it's two days of high ticket and low volume, and the base team carries it. Three Kings Day comes with three, which is what multiplying production kitchen output by six for five days calls for.
A43: What this workbook doesn't decide: how you classify the extra campaign help (employee, seasonal employee or independent contractor). It depends on the facts of the work and your state, and your accountant or payroll provider has to look at it before the first campaign, not during it.
A45: Designed by John Guerrero — chef and restaurant consultant since 2010, in the kitchen since age 17.
A46: Version 1.0 · October 2026 · aichef.pro/en/digital-products/how-to-open-a-pastry-shop · info@aichef.pro
