Workbook

Sheet 0. Assumptions
A1: ASSUMPTIONS — the RATES and DRIVERS of the model are typed here
A2: Change the GREEN cells: the rest of the workbook recalculates on its own. Expense items are typed on their own tab (also in green) and are not repeated here. Amounts are in your currency.
A3: BUSINESS ACTIVITY
A4: Customers per day (year-1 average) | B4: 165 | C4: Customers served per day, averaged over year 1, at the counter, to go and at the patio: about 400 on a busy July Saturday and about 40 on a January Tuesday (Kit estimate). It comes from dividing projected sales by the average check and the days you are open; compare it with the foot traffic on your own street on a summer afternoon and on a February one
A5: Average check (excl. sales tax) | B5: 7.5 | C5: Excl. sales tax, per person who buys: a double scoop, plus hand-packed pints, ice cream cakes to order and the winter hot chocolate. It is per person, not per register ticket: some people buy for two. The case mixes about 70% doubles in a cup or cone, 15% singles and kids' scoops, 10% pints and quarts and 5% sundaes and coffee (Kit estimate). The menu price incl. sales tax is in the row "Menu price incl. sales tax (calculated)" below
A6: Operating days per year | B6: 310 | C6: 365 days minus three weeks closed in January (vacation and refrigeration maintenance), Thanksgiving, Christmas and the Mondays from November to February. It is the SAME figure for the P&L, the break-even, the scenarios and the staffing hours
A7: Volume growth in year 2 | B7: 0.08 | C7: More repeat customers in the second summer, plus more ice cream cakes to order and catering. It applies to customers; payroll does NOT rise with this percentage: it grows with the hires you declare on the "Staffing" tab
A8: Volume growth in year 3 | B8: 0.05 | C8: On top of year 2. Conservative: the ceiling is set by the 18-flavor dipping cabinets and the July and August evenings
A9: Menu price incl. sales tax (calculated) | B9: =IFERROR(IF($B$5="","",$B$5*(1+SUMPRODUCT('3-Year P&L'!$E$10:$E$11,'3-Year P&L'!$G$10:$G$11))),"") -> 8.1 | C9: =IFERROR("Average check excl. sales tax plus the weighted sales tax of your sales lines ("&TEXT(SUMPRODUCT('3-Year P&L'!$E$10:$E$11,'3-Year P&L'!$G$10:$G$11)*100,"0")&"%), rounded. In the US, menu prices usually exclude sales tax and it is added at the register. "&"The example uses one rate for scoops, pints, cakes and drinks; some states tax packaged pints and whole cakes as groceries: then use your blended rate. In the UK, menu prices include VAT.","") -> Average check excl. sales tax plus the weighted sales tax of your sales lines (8%), rounded. In the US, menu prices usually exclude sales tax and it is added at the register. The example uses one rate for scoops, pints, cakes and drinks; some states tax packaged pints and whole cakes as groceries: then use your blended rate. In the UK, menu prices include VAT.
A10: SALES MIX AND COST OF GOODS SOLD
A11: FOOD share of total sales | B11: 0.9 | C11: Share of FOOD in total sales. It is an INPUT: change it here and the P&L, the cash flow and the sales tax collected recalculate on their own
A12: BEVERAGE share of total sales | B12: =IFERROR(IF(COUNT(B11)=0,"",1-B11),"") -> 0.1 | C12: Calculated as the remainder: food + beverage = 100%
A13: Cost of goods sold on FOOD sales | B13: 0.22 | C13: Cost of the ice cream base, flavorings and mix-ins, cones, tasting spoons and shrink as a share of ice cream sales. The case buys a pasteurized base from a licensed dairy, which costs more than making your own mix. Cost out every flavor every season: pistachio, cocoa and vanilla swing with the market
A14: Cost of goods sold on BEVERAGE sales | B14: 0.25 | C14: Espresso, hot chocolate, shakes, sodas and water as a share of their sales: soft drinks run higher than espresso. No alcohol
A15: Disposables and packaging as % of sales | B15: 0.045 | C15: Cups, cones, spoons, pint and quart containers, cake boxes and napkins. Use paper or other compostable cups for dine-in where your city requires it
A16: Delivery share of total sales | B16: 0.04 | C16: Hand-packed pints and quarts through DoorDash or Uber Eats on summer evenings: a pint travels well, a scoop does not. Pickup orders placed directly with you pay no commission
A17: Delivery platform fee | B17: 0.25 | C17: Average marketplace plan (Basic 15%, Premier 30%): check your contract. If you deliver yourself, enter 0
A18: Card processing fee | B18: 0.03 | C18: Card and mobile wallet (contactless) processing fees on total sales. Ask your POS provider for its rate
A19: LABOR
A20: Employer payroll taxes | B20: 0.1 | C20: FICA (Social Security 6.2% + Medicare 1.45%) + federal and state unemployment taxes (FUTA / SUTA) + workers' comp. About 10% in total: adjust it to your state and your insurance carrier
A21: Monthly pay periods per year (keep 12) | B21: 12 | C21: Annual gross pay = monthly gross pay × this number. Keep 12 in the US: it counts the monthly salaries the model pays in a year, not how often you run payroll (weekly or biweekly payroll pays the same annual amount)
A22: Federal minimum wage, annual full-time | B22: 15080 | C22: US federal minimum wage: 7.25 per hour × 2,080 hours = 15,080 per year for a full-time job. Your state or city may set a higher floor: enter it in the state / local minimum wage cell below. Check the current rates at dol.gov
A23: RENT AND FIXED COSTS
A24: Monthly rent | B24: 2500 | C24: About 1,000 sq ft (93 sq m): a production room of about 250 sq ft (23 sq m), a shop with 18-flavor dipping cabinets and 20 seats, storage and a restroom. Second-generation retail on a neighborhood main street or next to a park or school, at about $30 per sq ft per year (Kit estimate; asking rents average about $24.69 plus NNN). The book itself calculates the weight on sales in the "Rent / Sales" row of the P&L
A25: Security deposit (months of rent) | B25: 2 | C25: Two months of rent: commercial leases commonly ask for one to three, so check it with your attorney
A26: Monthly utilities (electricity, water, gas) | B26: 1300 | C26: Mostly electricity: about 30 kW of service, with the dipping cabinets running 24 hours a day, the batch freezer, the hardening cabinet and the air conditioning. Summer sends the bill up; ask the landlord or the utility for the space's billing history
A27: Insurance (per year) | B27: 4500 | C27: General liability (ask your broker for the per-occurrence limit) plus property insurance WITH equipment breakdown and food spoilage: a cabinet that fails in August is a tub lost for every flavor
A28: Miscellaneous and contingency as % of sales | B28: 0.01 | C28: Cushion for unbudgeted running costs (small repairs, tastings and samples)
A29: FINANCING
A30: Owner's equity contributed | B30: 95000 | C30: Owner's cash. Lenders usually expect an owner equity injection (often around 10% for SBA start-ups; many want 20-30%) toward the cash need
A31: Loan requested | B31: 162000 | C31: Principal requested. The "Financing" tab compares what you put in with the cash need on "Startup Costs" and tells you whether you have a surplus or a shortfall: adjust the loan with that figure. The example is an SBA 7(a) loan, which you apply for through your lender (SBA Microloans go up to $50,000)
A32: Nominal annual interest rate (not APR) | B32: 0.1 | C32: Annual nominal rate, not APR. The example is an SBA 7(a) loan through your lender at 10% (Prime plus a margin that depends on the loan size): ask two lenders for a quote before you set it. Refrigeration equipment is often leased: compare that too
A33: Loan term (years) | B33: 10 | C33: Total years, interest-only period included
A34: Interest-only period (years) | B34: 0 | C34: 0 by default: an SBA 7(a) loan is repaid from the start, so the example has no interest-only period. If your lender grants one, enter the years here and check the cash cushion for that year on the "Break-Even" tab
A35: Working capital (months of fixed costs) | B35: 3 | C35: Three months of fixed costs: the cushion for the first winter, when only about 15% of the year's sales come in from November to February while fixed costs stay flat
A36: TAXES
A37: Effective income tax rate (years 1-2) | B37: 0.25 | C37: Example: 21% federal rate for a C corporation plus state tax, rounded to 25%. If you operate as a sole proprietorship, LLC taxed as a pass-through or S corporation, the business itself pays 0% here and you pay tax on the profit personally: set this to 0 and budget for your personal tax separately. The model applies this rate to the first two years with positive taxable income
A38: Effective income tax rate (from year 3) | B38: 0.25 | C38: From the third year with positive taxable income. Same example rate (21% federal C corporation + state). Confirm the rate that applies to you with your accountant and change it here
A39: Sales tax rate on sales | B39: 0.08 | C39: Example rate: state + local sales tax combined. It varies widely by state and city: look up yours. UK: ice cream is standard-rated at 20% VAT, to take away too
A40: Sales tax rate on alcohol to go | B40: 0.08 | C40: One sales tax rate for the example (8%). Check your state and city: the same rate is used for the sales tax collected and for the menu price incl. sales tax. Recoverable input tax on purchases is 0: there is no credit for sales tax paid on purchases, so the book does not credit anything
A41: Recoverable input tax on purchases and capex | B41: 0 | C41: In the US, the sales tax you pay on purchases is a cost, not a credit: leave this at 0%. UK: 20% if you are VAT-registered
A42: Net operating losses carried forward | B42: 0 | C42: Net operating losses from earlier years still to be offset at the start. Federal rules let you offset up to 80% of taxable income in a year; the model offsets 100% as a simplification
A43: DEPRECIATION
A44: Useful life of build-out and fixtures (years) | B44: 10 | C44: Build-out of the production room and shop, electrical service, plumbing, floor drains, HVAC and signage. Depreciation follows the IRS recovery periods for your assets: confirm the life with your CPA
A45: Useful life of machinery, furniture and equipment (years) | B45: 7 | C45: Batch freezer, hardening cabinet, freezers, dipping cabinets, espresso machine, furniture and POS. Straight-line depreciation over the useful life; confirm the recovery period and any Section 179 election with your CPA
A47: GROWTH AND COST INFLATION
A48: Annual increase in fixed costs | B48: 0 | C48: SET TO ZERO: all three columns are in year-1 prices (real terms). Raise it if you want to project in nominal terms
A49: RAMP-UP AND CAPACITY
A51: Seating capacity of the space (indoor seats, patio not included) | B51: 20 | C51: FOR INFORMATION: most sales happen at the counter and to go. The patio adds 5 more tables in season, with its own sidewalk café permit from the city and not counted here
A52: Month-1 activity as a % of steady-state activity | B52: 0.7 | C52: A shop that opens in March does not sell in month 1 what it sells in month 4: ice cream is an impulse purchase and the neighborhood takes time to find you, and spring is still slow. At 100% the ramp-up disappears
A53: Months to reach steady state | B53: 4 | C53: Four months to reach cruising pace: March to June, just before the summer peak
A54: Months of rent BEFORE opening (build-out and permits) | B54: 2 | C54: Two months of rent before opening: the production room build-out, the electrical upgrade (ask the utility about 3-phase service and amps before signing) and the permits. If your lender funds the loan when construction starts, add the interest for those months, which this book does not count
A55: Contingency on the BUILD-OUT lines of the space block (%) | B55: 0.1 | C55: Cushion on the build-out and the shop installations, where surprises show up (electrical service, floor drains, ventilation for the condenser units). A lender will not fund a renovation without one
A57: RECEIPTS, PAYMENTS AND SALES TAX BREAKDOWN
A58: Average collection days | B58: 2 | C58: Weighted average: the counter collects on the spot (card) and catering customers pay a few days later
A59: Average days to pay suppliers | B59: 14 | C59: Payment terms from your dairy, flavoring, cone and packaging suppliers: what they finance for you. It is the first thing you lose if you pay late
A60: Month of extra pay period 1 (only if pay periods > 12) | B60: 5 | C60: Not used with 12 pay periods: this only counts if you enter more than 12. Month of the CASH FLOW in which the extra payment goes out: July is Month 5, because Month 1 of the plan is March
A61: Month of extra pay period 2 (only if pay periods > 12) | B61: 10 | C61: Not used with 12 pay periods: this only counts if you enter more than 12. Month of the CASH FLOW in which the extra payment goes out: December is Month 10, because Month 1 of the plan is March
A62: ALCOHOLIC beverages as a share of total beverage sales | B62: 0 | C62: Set to ZERO: the beverage menu of this plan is coffee, hot chocolate, shakes, sodas and water, with no alcohol. If you add alcohol, type its share of beverage sales here: it needs a state liquor license, and its sales tax uses the cell below (on site) and B40 (to go)
A63: Sales tax rate on alcohol served on site | B63: 0.08 | C63: NO EFFECT in this plan (the cell above is at 0). If you serve alcohol, type the sales tax rate your state applies to alcohol served on site. With the example, everything pays the same 8% (state + local)
A64: CONTROL THRESHOLDS AND FLOORS
A65: DSCR limit (minimum acceptable) | B65: 1.15 | C65: Below 1.0 the business does not generate enough to repay the loan. Lenders often write a minimum DSCR into the loan covenants: ask yours. Kit default: 1.15×
A66: DSCR target (green) | B66: 1.25 | C66: What lenders commonly look for before approving a loan comfortably. Kit default: 1.25× (editable estimate)
A67: Minimum cushion above break-even | B67: 0.15 | C67: How far you can fall below plan before you start losing money
A68: State / local minimum wage, annual full-time | C68: Leave empty to use your state or local minimum wage (hourly rate x 2,080 hours) whenever it is above the federal $7.25 per hour. Type your own annual figure if your city sets a higher floor. With 0 the traffic light compares only against the federal minimum

Sheet Startup Costs
A1: ICE CREAM SHOP BUSINESS PLAN
A2: Startup costs — ice cream shop with on-site production
A3: US kit example (2026) — replace with your own quotes.
A5: Item | B5: Amount | C5: % of startup costs | D5: Notes | E5: Taxable / recoverable tax?
A6: STARTUP COSTS | B6: =IFERROR(IF(COUNT(B7:B28)=0,"",SUM(B7:B28)),"") -> 204100 | C6: =IFERROR(B6/$B$31,"") -> 0.79456132
A7: Architect, MEP drawings, plan review & permit fees | B7: 9000 | C7: =IFERROR(B7/$B$31,"") -> 0.035037001 | D7: Architect, MEP drawings, plan review with the health department (Food Code 8-201.11) and permit fees | E7: Yes
A8: Build-out of production room & shop (second-generation retail, ~1,000 sq ft) | B8: 48000 | C8: =IFERROR(B8/$B$31,"") -> 0.18686401 | D8: Build-out of a second-generation retail space of about 1,000 sq ft (93 sq m) with a production room of about 250 sq ft (23 sq m): tile or washable walls, non-slip floor, restroom and ceilings. Kit estimate: replace it with contractor quotes | E8: Yes
A9: Electrical service & panel (about 30 kW) | B9: 9000 | C9: =IFERROR(B9/$B$31,"") -> 0.035037001 | D9: About 30 kW for the dipping cabinets, batch freezer, hardening cabinet and air conditioning. Ask the utility about 3-phase service and amps before signing: a new service connection can take weeks | E9: Yes
A10: Plumbing, floor sinks, hand sinks, HVAC & condenser ventilation | B10: 10000 | C10: =IFERROR(B10/$B$31,"") -> 0.038930001 | D10: Floor sinks and drains in the production room, hand sinks and ventilation for the condenser units | E10: Yes
A11: Signage & storefront | B11: 5000 | C11: =IFERROR(B11/$B$31,"") -> 0.019465001 | D11: Say "made here in small batches" on the sign only if you really make it here; "homemade" or "house-made" only if it is true | E11: Yes
A12: Base refrigerator & flavor prep (41 °F or colder, stick blender, scales) | B12: 4500 | C12: =IFERROR(B12/$B$31,"") -> 0.017518501 | D12: Base case: you buy pasteurized base from a licensed dairy, keep it at 41 °F (5 °C) or colder and add only flavorings and mix-ins. Making your own mix adds a batch pasteurizer (about $25,000-45,000: get quotes) and, in many states, a dairy or frozen dessert manufacturer license: ask your state department of agriculture | E12: Yes
A13: Batch freezer (20 qt, horizontal) | B13: 30000 | C13: =IFERROR(B13/$B$31,"") -> 0.11679 | D13: A 20-qt Carpigiani lists at about $40,800; get two quotes before you close the loan, and reconditioned units cost less. Kit estimate on the low side of what is published, because professional brands rarely publish a price. A smaller 3-gallon (11-liter) countertop unit costs less if you start small | E13: Yes
A14: Hardening cabinet / blast freezer | B14: 9000 | C14: =IFERROR(B14/$B$31,"") -> 0.035037001 | D14: Takes the freshly batch-frozen ice cream to 0 °F (−18 °C) or colder in the core before it goes to the dipping cabinet or the freezer. Kit estimate: the sources on price are weak, so get quotes | E14: Yes
A15: Storage freezers (0 °F or colder) | B15: 7000 | C15: =IFERROR(B15/$B$31,"") -> 0.027251001 | D15: Storage freezers at 0 °F (−18 °C) or colder for the finished ice cream and the stock. There is no aging cabinet: the base arrives already aged and pasteurized from the dairy | E15: Yes
A16: Prep tables, 3-compartment sink, hand sinks, scales, pans & smallwares | B16: 8500 | C16: =IFERROR(B16/$B$31,"") -> 0.033090501 | D16: Stainless prep tables and shelves, a 3-compartment sink, hand sinks, scales, probe thermometers, 3-gallon (11-liter) tubs and pans, and strainers | E16: Yes
A17: Dipping cabinets (18 flavors) | B17: 11000 | C17: =IFERROR(B17/$B$31,"") -> 0.042823001 | D17: Two dipping cabinets with room for 18 flavors, plus two spots for the flavor of the day or a reserve. Cabinets for 12 flavors start at about $1,700-2,500 for budget models and reach about $12,300 for premium ones. Run 6-10 °F (−14 to −12 °C) depending on the manufacturer; 18 flavors in summer and 10-12 in winter is enough in a mid-size city | E17: Yes
A18: Front counter, dipper wells, espresso, waffle cone irons & hot fudge warmers | B18: 9000 | C18: =IFERROR(B18/$B$31,"") -> 0.035037001 | D18: Front counter, dipper wells with running water (Food Code 3-304.12), espresso machine and grinder, waffle cone irons and hot fudge warmers. Waffle cone irons usually need no exhaust hood: confirm it with your plan reviewer | E18: Yes
... A25: Opening inventory (base, flavorings, cones, cups, pint containers) | B25: 5000 | C25: =IFERROR(B25/$B$31,"") -> 0.019465001 | D25: Ice cream base, flavorings, cones, cups and pint containers | E25: Yes
A26: Security deposit | B26: =IFERROR(IF('0. Assumptions'!$B$24="","",'0. Assumptions'!$B$24*'0. Assumptions'!$B$25),"") -> 5000 | C26: =IFERROR(B26/$B$31,"") -> 0.019465001 | D26: =IFERROR(""&TEXT('0. Assumptions'!$B$25,"0")&IF('0. Assumptions'!$B$25=1," month"," months")&" of rent, from ""0. Assumptions"". Refundable when the lease ends: it is not depreciated and carries no tax","") -> 2 months of rent, from "0. Assumptions". Refundable when the lease ends: it is not depreciated and carries no tax | E26: No
A27: Rent paid before opening | B27: =IFERROR(IF('0. Assumptions'!$B$24="","",'0. Assumptions'!$B$24*'0. Assumptions'!$B$54),"") -> 5000 | C27: =IFERROR(B27/$B$31,"") -> 0.019465001 | D27: =IFERROR("Rent "&IF('0. Assumptions'!$B$54=1,"for the month","for the "&TEXT('0. Assumptions'!$B$54,"0")&" months")&" of build-out and permits before opening. It does not overlap the P&L, which starts on opening day: its twelve months are twelve trading months","") -> Rent for the 2 months of build-out and permits before opening. It does not overlap the P&L, which starts on opening day: its twelve months are twelve trading months | E27: Yes
A28: Build-out and setup contingency | B28: =IFERROR(IF(COUNT(B7,B8,B9,B10,B11)=0,"",ROUND((B7+B8+B9+B10+B11)*'0. Assumptions'!$B$55,0)),"") -> 8100 | C28: =IFERROR(B28/$B$31,"") -> 0.031533301 | D28: =IFERROR("At "&TEXT('0. Assumptions'!$B$55,"0%")&" of the BUILD-OUT items of this block (architect, MEP drawings, plan review & permit fees; build-out of production room & shop; electrical service & panel; plumbing, floor sinks, hand sinks, HVAC & condenser ventilation; "&"signage & storefront), not of the whole block: the equipment and the other items are left out. No lender funds a build-out without a cushion: the percentage is in ""0. Assumptions""","") -> At 10% of the BUILD-OUT items of this block (architect, MEP drawings, plan review & permit fees; build-out of production room & shop; electrical service & panel; plumbing, floor sinks, hand sinks, HVAC & condenser ventilation; signage & storefront), not of the whole block: the equipment and the other items are left out. No lender funds a build-out without a cushion: the percentage is in "0. Assumptions" | E28: Yes
A29: WORKING CAPITAL | B29: =IFERROR(IF(B30="","",B30),"") -> 52771.3 | C29: =IFERROR(B29/$B$31,"") -> 0.20543868
A30: Operating cushion until break-even | B30: =IFERROR(IF('0. Assumptions'!$B$35*('3-Year P&L'!$B$38-'3-Year P&L'!$B$36)=0,"",'0. Assumptions'!$B$35*('3-Year P&L'!$B$38-'3-Year P&L'!$B$36)/12),"") -> 52771.3 | C30: =IFERROR(B30/$B$31,"") -> 0.20543868 | D30: =IFERROR("Covers "&TEXT('0. Assumptions'!$B$35,"0")&IF('0. Assumptions'!$B$35=1," month"," months")&" of year-1 CASH fixed costs (the P&L fixed costs minus depreciation, which is not paid out), the minimum the Instructions of this workbook ask for","") -> Covers 3 months of year-1 CASH fixed costs (the P&L fixed costs minus depreciation, which is not paid out), the minimum the Instructions of this workbook ask for | E30: No
A31: TOTAL STARTUP COSTS (sum of the blocks) | B31: =IFERROR(B6+B29,"") -> 256871.3 | D31: =IFERROR("The percentages in column C are read on this figure, which includes the working capital ("&TEXT(C29,"0%")&" of the total). To compare the breakdown with another plan, use the CAPEX row below.","") -> The percentages in column C are read on this figure, which includes the working capital (21% of the total). To compare the breakdown with another plan, use the CAPEX row below.
A32: CAPEX (startup costs excluding working capital) | B32: =IFERROR(B31-B29,"") -> 204100 | D32: What you buy: build-out, equipment, launch and formation costs. The cash cushion is not an investment: it is working capital
A33: Recoverable input tax on capex | B33: =IFERROR(IF(B31="","",SUMIF($E$7:$E$28,"Yes",$B$7:$B$28)*'0. Assumptions'!$B$41),"") -> 0 | D33: =IFERROR("At "&TEXT('0. Assumptions'!$B$41,"0%")&" on the items marked ""Yes"" in the tax column. US: the sales tax you pay on equipment is part of its cost and is not recovered, so this rate is 0. UK (VAT-registered): 20%, reclaimed on your VAT return, but you pay it first, so the loan has to cover it","") -> At 0% on the items marked "Yes" in the tax column. US: the sales tax you pay on equipment is part of its cost and is not recovered, so this rate is 0. UK (VAT-registered): 20%, reclaimed on your VAT return, but you pay it first, so the loan has to cover it
A34: TOTAL CASH NEEDED AT LAUNCH | B34: =IFERROR(B31+B33,"") -> 256871.3 | D34: This is the figure the Financing tab has to cover
A35: DEPRECIATION BASES (not added to startup costs)
A36: Build-out, fixtures and setup | B36: =IFERROR(IF(B7="","",B7+B8+B9+B10+B11+B28),"") -> 89100 | D36: =IFERROR("Depreciated over "&TEXT('0. Assumptions'!$B$44,"0")&" years","") -> Depreciated over 10 years
A37: Machinery, furniture and equipment | B37: =IFERROR(IF(B12="","",B12+B13+B14+B15+B16+B17+B18+B19+B20+B21),"") -> 90000 | D37: =IFERROR("Depreciated over "&TEXT('0. Assumptions'!$B$45,"0")&" years","") -> Depreciated over 7 years
A38: Annual depreciation of fixed assets | B38: =IFERROR(B36/MAX(1,'0. Assumptions'!$B$44)+B37/MAX(1,'0. Assumptions'!$B$45),"") -> 21767.143 | D38: =IFERROR("Not depreciated, because they are not fixed assets: ice cream training course; branding, website, photos & launch; LLC, legal, permits & food safety plan; opening inventory; "&"security deposit; pre-opening rent and the working capital reserve. They add up to "&TEXT(B31-B36-B37,"#,##0")&" of the "&TEXT(B31,"#,##0")&" total investment.","") -> Not depreciated, because they are not fixed assets: ice cream training course; branding, website, photos & launch; LLC, legal, permits & food safety plan; opening inventory; security deposit; pre-opening rent and the working capital reserve. They add up to 77771 of the 256871 total investment.

Sheet 3-Year P&L
A1: PROFIT AND LOSS STATEMENT — 3 YEARS
A2: Base case — ice cream shop with on-site production
A4: Item | B4: Year 1 | C4: Year 2 | D4: Year 3 | E4: % of sales (year 1) | F4: Notes | G4: Sales tax rate on the line (%)
A5: REVENUE
A6: Customers per day (average) | B6: =IFERROR(IF('0. Assumptions'!$B$4="","",'0. Assumptions'!$B$4),"") -> 165 | C6: =IFERROR(B6*(1+'0. Assumptions'!$B$7),"") -> 178.2 | D6: =IFERROR(C6*(1+'0. Assumptions'!$B$8),"") -> 187.11 | F6: Growth for years 2 and 3 is set in "0. Assumptions"
A7: Average check (excl. sales tax) | B7: =IFERROR(IF('0. Assumptions'!$B$5="","",'0. Assumptions'!$B$5),"") -> 7.5 | C7: =IFERROR(IF(B7="","",B7),"") -> 7.5 | D7: =IFERROR(IF(C7="","",C7),"") -> 7.5 | F7: Held constant at year-1 prices: a price increase is a separate decision
A8: Operating days per year | B8: =IFERROR(IF('0. Assumptions'!$B$6="","",'0. Assumptions'!$B$6),"") -> 310 | C8: =IFERROR(IF(B8="","",B8),"") -> 310 | D8: =IFERROR(IF(C8="","",C8),"") -> 310
A9: TOTAL REVENUE (excl. sales tax) | B9: =IFERROR(IF(B6*B7*B8=0,"",B6*B7*B8),"") -> 383625 | C9: =IFERROR(IF(C6*C7*C8=0,"",C6*C7*C8),"") -> 414315 | D9: =IFERROR(IF(D6*D7*D8=0,"",D6*D7*D8),"") -> 435030.75 | E9: =IFERROR(IF(B9="","",1),"") -> 1
A10: Ice cream sales (scoops, sundaes, pints & quarts to go, ice cream cakes, catering) | B10: =IFERROR(IF(B9="","",B9*$E$10),"") -> 345262.5 | C10: =IFERROR(IF(C9="","",C9*$E$10),"") -> 372883.5 | D10: =IFERROR(IF(D9="","",D9*$E$10),"") -> 391527.67 | E10: =IFERROR(IF('0. Assumptions'!$B$11="","",'0. Assumptions'!$B$11),"") -> 0.9 | F10: Share of total sales. Within this line, roughly: scoops, cups, cones and sundaes in the shop 65%, hand-packed pints and quarts to go 15%, ice cream cakes and holiday pies 10%, catering 5% and pints through delivery marketplaces the rest (see "Delivery share of total sales"). One sales tax rate in the example; in some states a packaged pint or a whole cake may be taxed as a grocery, so check your state | G10: =IFERROR(IF(B9="","",'0. Assumptions'!$B$39),"") -> 0.08
A11: Coffee & beverages (espresso, hot chocolate, sodas, water) | B11: =IFERROR(IF(B9="","",B9*$E$11),"") -> 38362.5 | C11: =IFERROR(IF(C9="","",C9*$E$11),"") -> 41431.5 | D11: =IFERROR(IF(D9="","",D9*$E$11),"") -> 43503.075 | E11: =IFERROR(IF('0. Assumptions'!$B$12="","",'0. Assumptions'!$B$12),"") -> 0.1 | F11: Espresso, hot chocolate, shakes, sodas and water. No alcohol | G11: =IFERROR(IF(B9="","",('0. Assumptions'!$B$62*((1-'0. Assumptions'!$B$16)*'0. Assumptions'!$B$63+'0. Assumptions'!$B$16*'0. Assumptions'!$B$40)+(1-'0. Assumptions'!$B$62)*'0. Assumptions'!$B$39)),"") -> 0.08
A12: VARIABLE COSTS
A13: Cost of goods sold — food | B13: =IFERROR(IF(B9="","",B9*'0. Assumptions'!$B$11*'0. Assumptions'!$B$13),"") -> 75957.75 | C13: =IFERROR(IF(C9="","",C9*'0. Assumptions'!$B$11*'0. Assumptions'!$B$13),"") -> 82034.37 | D13: =IFERROR(IF(D9="","",D9*'0. Assumptions'!$B$11*'0. Assumptions'!$B$13),"") -> 86136.088 | E13: =IFERROR(B13/$B$9,"") -> 0.198 | F13: =IFERROR("At "&TEXT('0. Assumptions'!$B$13,"0%")&" of FOOD sales (the ice cream line), not of total sales: beverages have their own line · purchased base, flavorings, mix-ins and toppings, cones, "&"tasting samples and production waste: check it against your dairy and distributor invoices","") -> At 22% of FOOD sales (the ice cream line), not of total sales: beverages have their own line · purchased base, flavorings, mix-ins and toppings, cones, tasting samples and production waste: check it against your dairy and distributor invoices | G13: 0
A14: Cost of goods sold — beverage | B14: =IFERROR(IF(B9="","",B9*'0. Assumptions'!$B$12*'0. Assumptions'!$B$14),"") -> 9590.625 | C14: =IFERROR(IF(C9="","",C9*'0. Assumptions'!$B$12*'0. Assumptions'!$B$14),"") -> 10357.875 | D14: =IFERROR(IF(D9="","",D9*'0. Assumptions'!$B$12*'0. Assumptions'!$B$14),"") -> 10875.769 | E14: =IFERROR(B14/$B$9,"") -> 0.025 | F14: =IFERROR("At "&TEXT('0. Assumptions'!$B$14,"0%")&" of BEVERAGE sales","") -> At 25% of BEVERAGE sales | G14: =IFERROR(IF(B9="","",'0. Assumptions'!$B$41),"") -> 0
A15: Disposables and packaging | B15: =IFERROR(IF(B9="","",B9*'0. Assumptions'!$B$15),"") -> 17263.125 | C15: =IFERROR(IF(C9="","",C9*'0. Assumptions'!$B$15),"") -> 18644.175 | D15: =IFERROR(IF(D9="","",D9*'0. Assumptions'!$B$15),"") -> 19576.384 | E15: =IFERROR(B15/$B$9,"") -> 0.045 | G15: =IFERROR(IF(B9="","",'0. Assumptions'!$B$41),"") -> 0
A16: Delivery platform fees | B16: =IFERROR(IF(B9="","",B9*'0. Assumptions'!$B$16*'0. Assumptions'!$B$17),"") -> 3836.25 | C16: =IFERROR(IF(C9="","",C9*'0. Assumptions'!$B$16*'0. Assumptions'!$B$17),"") -> 4143.15 | D16: =IFERROR(IF(D9="","",D9*'0. Assumptions'!$B$16*'0. Assumptions'!$B$17),"") -> 4350.3075 | E16: =IFERROR(B16/$B$9,"") -> 0.01 | F16: Applied to the sales of THAT CHANNEL. With 0% delivery in Assumptions, this line is zero | G16: =IFERROR(IF(B9="","",'0. Assumptions'!$B$41),"") -> 0
A17: Card processing fees | B17: =IFERROR(IF(B9="","",B9*'0. Assumptions'!$B$18),"") -> 11508.75 | C17: =IFERROR(IF(C9="","",C9*'0. Assumptions'!$B$18),"") -> 12429.45 | D17: =IFERROR(IF(D9="","",D9*'0. Assumptions'!$B$18),"") -> 13050.922 | E17: =IFERROR(B17/$B$9,"") -> 0.03 | F17: Card processing fees are not subject to sales tax: no tax is recovered or deducted for them | G17: 0
A18: Miscellaneous and contingency | B18: =IFERROR(IF(B9="","",B9*'0. Assumptions'!$B$28),"") -> 3836.25 | C18: =IFERROR(IF(C9="","",C9*'0. Assumptions'!$B$28),"") -> 4143.15 | D18: =IFERROR(IF(D9="","",D9*'0. Assumptions'!$B$28),"") -> 4350.3075 | E18: =IFERROR(B18/$B$9,"") -> 0.01 | F18: =IFERROR("At "&TEXT('0. Assumptions'!$B$28,"0%")&" of sales. It is a VARIABLE cost: it moves with revenue, so it cannot sit in fixed costs","") -> At 1% of sales. It is a VARIABLE cost: it moves with revenue, so it cannot sit in fixed costs | G18: =IFERROR(IF(B9="","",'0. Assumptions'!$B$41),"") -> 0
A19: TOTAL VARIABLE COSTS | B19: =IFERROR(IF(B9="","",SUM(B13:B18)),"") -> 121992.75 | C19: =IFERROR(IF(C9="","",SUM(C13:C18)),"") -> 131752.17 | D19: =IFERROR(IF(D9="","",SUM(D13:D18)),"") -> 138339.78 | E19: =IFERROR(B19/$B$9,"") -> 0.318
A20: GROSS MARGIN | B20: =IFERROR(IF(B9="","",B9-B19),"") -> 261632.25 | C20: =IFERROR(IF(C9="","",C9-C19),"") -> 282562.83 | D20: =IFERROR(IF(D9="","",D9-D19),"") -> 296690.97 | E20: =IFERROR(B20/$B$9,"") -> 0.682
A21: FIXED COSTS
A22: Rent | B22: =IFERROR(IF(B9="","",'0. Assumptions'!$B$24*12),"") -> 30000 | C22: =IFERROR(IF(C9="","",B22*(1+'0. Assumptions'!$B$48)),"") -> 30000 | D22: =IFERROR(IF(D9="","",C22*(1+'0. Assumptions'!$B$48)),"") -> 30000 | E22: =IFERROR(B22/$B$9,"") -> 0.078201369 | F22: The monthly amount is on the "0. Assumptions" tab; here it is multiplied by twelve. The two months of rent before opening are on the "Startup Costs" tab and are NOT counted twice | G22: =IFERROR(IF(B9="","",'0. Assumptions'!$B$41),"") -> 0
A23: Labor (wages + employer payroll taxes) | B23: =IFERROR(IF(B9="","",Staffing!$G$11),"") -> 128185.2 | C23: =IFERROR(IF(C9="","",Staffing!$B$15),"") -> 136185.2 | D23: =IFERROR(IF(D9="","",Staffing!$B$16),"") -> 144185.2 | E23: =IFERROR(B23/$B$9,"") -> 0.33414194 | F23: Comes from the Staffing tab: it is the SAME number, not a separate estimate. Years 2 and 3 add the new hires declared on that tab, not a percentage of volume | G23: 0
A24: Utilities (electricity, water, gas) | B24: =IFERROR(IF(B9="","",'0. Assumptions'!$B$26*12),"") -> 15600 | C24: =IFERROR(IF(C9="","",B24*(1+'0. Assumptions'!$B$48)),"") -> 15600 | D24: =IFERROR(IF(D9="","",C24*(1+'0. Assumptions'!$B$48)),"") -> 15600 | E24: =IFERROR(B24/$B$9,"") -> 0.040664712 | F24: Enter the monthly bills excl. sales tax. The workbook applies a single tax treatment to this whole line, the one in the column next to it; if one utility is taxed differently in your area, give it its own line | G24: =IFERROR(IF(B9="","",'0. Assumptions'!$B$41),"") -> 0
A25: Insurance (general liability, property, equipment breakdown + food spoilage) | B25: =IFERROR(IF(B9="","",'0. Assumptions'!$B$27),"") -> 4500 | C25: =IFERROR(IF(C9="","",B25*(1+'0. Assumptions'!$B$48)),"") -> 4500 | D25: =IFERROR(IF(D9="","",C25*(1+'0. Assumptions'!$B$48)),"") -> 4500 | E25: =IFERROR(B25/$B$9,"") -> 0.011730205 | F25: Insurance premiums are not subject to sales tax: there is no recoverable tax on them | G25: 0
A26: Accounting & bookkeeping | B26: 3000 | C26: =IFERROR(IF(C9="","",B26*(1+'0. Assumptions'!$B$48)),"") -> 3000 | D26: =IFERROR(IF(D9="","",C26*(1+'0. Assumptions'!$B$48)),"") -> 3000 | E26: =IFERROR(B26/$B$9,"") -> 0.0078201369 | F26: Bookkeeping, income and sales tax returns, and payroll for your seasonal W-2 staff | G26: =IFERROR(IF(B9="","",'0. Assumptions'!$B$41),"") -> 0
A27: Refrigeration service contract (EPA 608-certified tech) | B27: 2400 | C27: =IFERROR(IF(C9="","",B27*(1+'0. Assumptions'!$B$48)),"") -> 2400 | D27: =IFERROR(IF(D9="","",C27*(1+'0. Assumptions'!$B$48)),"") -> 2400 | E27: =IFERROR(B27/$B$9,"") -> 0.0062561095 | F27: Service on the dipping cabinets, hardening cabinet, batch freezer and freezers before summer and during the January closing. Refrigerant is handled only by an EPA 608-certified technician: your staff never tops it up | G27: =IFERROR(IF(B9="","",'0. Assumptions'!$B$41),"") -> 0
A28: Seasonal marketing | B28: 4500 | C28: =IFERROR(IF(C9="","",B28*(1+'0. Assumptions'!$B$48)),"") -> 4500 | D28: =IFERROR(IF(D9="","",C28*(1+'0. Assumptions'!$B$48)),"") -> 4500 | E28: =IFERROR(B28/$B$9,"") -> 0.011730205 | F28: Social media, Google Business Profile, signage and the opening campaign each season, plus the ice cream cake and holiday pie campaign | G28: =IFERROR(IF(B9="","",'0. Assumptions'!$B$41),"") -> 0
A29: Software, POS & phone | B29: 1800 | C29: =IFERROR(IF(C9="","",B29*(1+'0. Assumptions'!$B$48)),"") -> 1800 | D29: =IFERROR(IF(D9="","",C29*(1+'0. Assumptions'!$B$48)),"") -> 1800 | E29: =IFERROR(B29/$B$9,"") -> 0.0046920821 | F29: POS subscription that reports sales tax, phone and internet | G29: =IFERROR(IF(B9="","",'0. Assumptions'!$B$41),"") -> 0
A30: Cleaning supplies, uniforms & laundry | B30: 1500 | C30: =IFERROR(IF(C9="","",B30*(1+'0. Assumptions'!$B$48)),"") -> 1500 | D30: =IFERROR(IF(D9="","",C30*(1+'0. Assumptions'!$B$48)),"") -> 1500 | E30: =IFERROR(B30/$B$9,"") -> 0.0039100684 | F30: Cleaning and sanitizing supplies, uniform laundry, gloves for working at 0 °F (−18 °C) and any lab tests your food safety plan sets | G30: =IFERROR(IF(B9="","",'0. Assumptions'!$B$41),"") -> 0
A31: Sidewalk café / patio permit (your city's fee) | B31: 500 | C31: =IFERROR(IF(C9="","",B31*(1+'0. Assumptions'!$B$48)),"") -> 500 | D31: =IFERROR(IF(D9="","",C31*(1+'0. Assumptions'!$B$48)),"") -> 500 | E31: =IFERROR(B31/$B$9,"") -> 0.0013033561 | F31: Sidewalk space for 5 tables in season. Every city sets its own fee and this plan has not read any: replace this figure with your city's | G31: =IFERROR(IF(B9="","",'0. Assumptions'!$B$41),"") -> 0
A32: Waste & recycling | B32: 1200 | C32: =IFERROR(IF(C9="","",B32*(1+'0. Assumptions'!$B$48)),"") -> 1200 | D32: =IFERROR(IF(D9="","",C32*(1+'0. Assumptions'!$B$48)),"") -> 1200 | E32: =IFERROR(B32/$B$9,"") -> 0.0031280547 | F32: Cardboard, packaging and organic waste from the production room, through a licensed hauler or the city service | G32: =IFERROR(IF(B9="","",'0. Assumptions'!$B$41),"") -> 0
A33: Pest control | B33: 600 | C33: =IFERROR(IF(C9="","",B33*(1+'0. Assumptions'!$B$48)),"") -> 600 | D33: =IFERROR(IF(D9="","",C33*(1+'0. Assumptions'!$B$48)),"") -> 600 | E33: =IFERROR(B33/$B$9,"") -> 0.0015640274 | F33: Licensed pest control company; part of your HACCP-based food safety plan | G33: =IFERROR(IF(B9="","",'0. Assumptions'!$B$41),"") -> 0
A34: Music licensing (ASCAP/BMI/SESAC) | B34: 600 | C34: =IFERROR(IF(C9="","",B34*(1+'0. Assumptions'!$B$48)),"") -> 600 | D34: =IFERROR(IF(D9="","",C34*(1+'0. Assumptions'!$B$48)),"") -> 600 | E34: =IFERROR(B34/$B$9,"") -> 0.0015640274 | F34: ASCAP, BMI and SESAC are separate licensing organizations; the fee depends on the size and capacity of your shop. Only needed if you play music | G34: =IFERROR(IF(B9="","",'0. Assumptions'!$B$41),"") -> 0
A35: Food safety & OSHA training (CFPM, food handler cards, allergens) | B35: 500 | C35: =IFERROR(IF(C9="","",B35*(1+'0. Assumptions'!$B$48)),"") -> 500 | D35: =IFERROR(IF(D9="","",C35*(1+'0. Assumptions'!$B$48)),"") -> 500 | E35: =IFERROR(B35/$B$9,"") -> 0.0013033561 | F35: Certified Food Protection Manager and food handler cards, allergen training and OSHA basics (cold, slips, cuts) | G35: =IFERROR(IF(B9="","",'0. Assumptions'!$B$41),"") -> 0
A36: Depreciation of fixed assets | B36: =IFERROR(IF(B9="","",'Startup Costs'!$B$38),"") -> 21767.143 | C36: =IFERROR(IF(C9="","",B36),"") -> 21767.143 | D36: =IFERROR(IF(D9="","",B36),"") -> 21767.143 | E36: =IFERROR(B36/$B$9,"") -> 0.056740679 | F36: Comes from the depreciation bases on the Startup Costs tab: real fixed assets only. It does NOT rise with inflation: it is a charge on the HISTORICAL cost of the assets | G36: 0
A37: Interest expense (loan interest) | B37: =IFERROR(IF(B9="","",Financing!$B$44),"") -> 16200 | C37: =IFERROR(IF(C9="","",Financing!$B$46),"") -> 15183.525 | D37: =IFERROR(IF(D9="","",Financing!$B$48),"") -> 14065.402 | E37: =IFERROR(B37/$B$9,"") -> 0.042228739 | F37: Only INTEREST is an expense. Principal repaid appears on the cash flow tab | G37: 0
A38: TOTAL FIXED COSTS | B38: =IFERROR(IF(B9="","",SUM(B22:B37)),"") -> 232852.34 | C38: =IFERROR(IF(C9="","",SUM(C22:C37)),"") -> 239835.87 | D38: =IFERROR(IF(D9="","",SUM(D22:D37)),"") -> 246717.74 | E38: =IFERROR(B38/$B$9,"") -> 0.60697906
A39: Recoverable input tax on variable costs | B39: =IFERROR(IF(B9="","",SUMPRODUCT(B13:B18,G13:G18)),"") -> 0 | C39: =IFERROR(IF(C9="","",SUMPRODUCT(C13:C18,G13:G18)),"") -> 0 | D39: =IFERROR(IF(D9="","",SUMPRODUCT(D13:D18,G13:G18)),"") -> 0 | F39: Each line at ITS OWN rate, read from the column next to it. It is what the cash flow tab overpays to suppliers and later deducts (zero wherever no tax is recoverable)
A40: Recoverable input tax on fixed costs | B40: =IFERROR(IF(B9="","",SUMPRODUCT(B22:B37,G22:G37)),"") -> 0 | C40: =IFERROR(IF(C9="","",SUMPRODUCT(C22:C37,G22:G37)),"") -> 0 | D40: =IFERROR(IF(D9="","",SUMPRODUCT(D22:D37,G22:G37)),"") -> 0
A41: PRE-TAX INCOME (EBT) | B41: =IFERROR(IF(B9="","",B20-B38),"") -> 28779.907 | C41: =IFERROR(IF(C9="","",C20-C38),"") -> 42726.963 | D41: =IFERROR(IF(D9="","",D20-D38),"") -> 49973.227 | E41: =IFERROR(B41/$B$9,"") -> 0.075020937
A42: Net operating losses carried forward (opening) | B42: =IFERROR(IF(B9="","",'0. Assumptions'!$B$42),"") -> 0 | C42: =IFERROR(IF(C9="","",B47),"") -> 0 | D42: =IFERROR(IF(D9="","",C47),"") -> 0 | F42: Federal rules let a year's losses offset the profits of later years (the federal limit is 80% of taxable income; this model offsets 100% as a simplification)
A43: Taxable income (after loss offset) | B43: =IFERROR(IF(B9="","",MAX(0,B41-B42)),"") -> 28779.907 | C43: =IFERROR(IF(C9="","",MAX(0,C41-C42)),"") -> 42726.963 | D43: =IFERROR(IF(D9="","",MAX(0,D41-D42)),"") -> 49973.227
A44: Years with positive taxable income (cumulative) | B44: =IFERROR(IF(B9="","",IF(B43>0,1,0)),"") -> 1 | C44: =IFERROR(IF(C9="","",B44+IF(C43>0,1,0)),"") -> 2 | D44: =IFERROR(IF(D9="","",C44+IF(D43>0,1,0)),"") -> 3
A45: Effective income tax rate applied | B45: =IFERROR(IF(B9="","",IF(B43<=0,"",IF(B44<=2,'0. Assumptions'!$B$37,'0. Assumptions'!$B$38))),"") -> 0.25 | C45: =IFERROR(IF(C9="","",IF(C43<=0,"",IF(C44<=2,'0. Assumptions'!$B$37,'0. Assumptions'!$B$38))),"") -> 0.25 | D45: =IFERROR(IF(D9="","",IF(D43<=0,"",IF(D44<=2,'0. Assumptions'!$B$37,'0. Assumptions'!$B$38))),"") -> 0.25 | F45: The "years 1-2" rate applies to the first two years with positive taxable income, not to the first two calendar years of the business. The model approximates this by counting the first two profitable years
A46: Income tax | B46: =IFERROR(IF(B9="","",IF(B45="",0,B43*B45)),"") -> 7194.9768 | C46: =IFERROR(IF(C9="","",IF(C45="",0,C43*C45)),"") -> 10681.741 | D46: =IFERROR(IF(D9="","",IF(D45="",0,D43*D45)),"") -> 12493.307
A47: Net operating losses carried forward (closing) | B47: =IFERROR(IF(B9="","",MAX(0,B42-B41)),"") -> 0 | C47: =IFERROR(IF(C9="","",MAX(0,C42-C41)),"") -> 0 | D47: =IFERROR(IF(D9="","",MAX(0,D42-D41)),"") -> 0
A48: NET INCOME | B48: =IFERROR(IF(B9="","",B41-B46),"") -> 21584.93 | C48: =IFERROR(IF(C9="","",C41-C46),"") -> 32045.222 | D48: =IFERROR(IF(D9="","",D41-D46),"") -> 37479.92 | E48: =IFERROR(B48/$B$9,"") -> 0.056265703
A49: KEY RATIOS
A50: Ratio | B50: Year 1 | C50: Year 2 | D50: Year 3 | E50: Threshold | F50: Comment
A51: Gross margin / Sales | B51: =IFERROR(IF(B9="","",B20/B9),"") -> 0.682 | C51: =IFERROR(IF(C9="","",C20/C9),"") -> 0.682 | D51: =IFERROR(IF(D9="","",D20/D9),"") -> 0.682 | E51: 0.65 | F51: Floor for the margin after ALL variable costs (cost of goods sold, packaging, marketplace, card fees and miscellaneous). An ice cream shop that makes its own ice cream usually clears this floor. Kit estimate
A52: Cost of goods sold (food + beverage) | B52: =IFERROR(IF(B9="","",B13+B14),"") -> 85548.375 | C52: =IFERROR(IF(C9="","",C13+C14),"") -> 92392.245 | D52: =IFERROR(IF(D9="","",D13+D14),"") -> 97011.857
A53: Cost of goods sold / Sales | B53: =IFERROR(IF(B9="","",B52/B9),"") -> 0.223 | C53: =IFERROR(IF(C9="","",C52/C9),"") -> 0.223 | D53: =IFERROR(IF(D9="","",D52/D9),"") -> 0.223 | E53: 0.25 | F53: Ceiling for cost of goods sold over sales; buying the base raises it compared with making your own mix. Pistachio, cocoa and vanilla move it. Kit estimate
A54: Labor cost / Sales | B54: =IFERROR(IF(B9="","",B23/B9),"") -> 0.33414194 | C54: =IFERROR(IF(C9="","",C23/C9),"") -> 0.32869966 | D54: =IFERROR(IF(D9="","",D23/D9),"") -> 0.3314368 | E54: 0.35 | F54: Ceiling for labor over sales, higher than at a coffee shop: the season forces you to reinforce the counter from June to September. Kit estimate
A55: Rent / Sales | B55: =IFERROR(IF(B9="","",B22/B9),"") -> 0.078201369 | C55: =IFERROR(IF(C9="","",C22/C9),"") -> 0.072408675 | D55: =IFERROR(IF(D9="","",D22/D9),"") -> 0.068960642 | E55: 0.1 | F55: Ceiling for rent over sales for a space with a production room. Kit estimate
A56: Net income / Sales | B56: =IFERROR(IF(B9="","",B48/B9),"") -> 0.056265703 | C56: =IFERROR(IF(C9="","",C48/C9),"") -> 0.077345068 | D56: =IFERROR(IF(D9="","",D48/D9),"") -> 0.086154646 | E56: 0.05 | F56: Floor for net profit at cruising pace for the plan to hold up. Kit estimate
A57: Break-even reached | B57: =IFERROR(IF(B9="","",IF(B9>='Break-Even'!$B$16,"Yes","No")),"") -> Yes | C57: =IFERROR(IF(C9="","",IF(C9>='Break-Even'!$C$16,"Yes","No")),"") -> Yes | D57: =IFERROR(IF(D9="","",IF(D9>='Break-Even'!$D$16,"Yes","No")),"") -> Yes | F57: Compares each year's sales with that same year's threshold, which the Break-Even tab calculates with that year's fixed costs
A59: All figures are EXCL. SALES TAX. Years 2 and 3 are in year-1 prices unless you raise cost inflation in the "0. Assumptions" tab. The "Sales tax rate on the line (%)" column shows, on SALES lines, the rate collected on each one and, on COST lines, the rate paid on that item. The cash flow tab reads it: insurance and card fees carry no sales tax, and wages, depreciation and interest carry none either.

Sheet Break-Even
A1: BREAK-EVEN
A2: Break-even — ice cream shop with on-site production
A4: Variable | B4: Year 1 | C4: Year 2 | D4: Year 3 | E4: Notes
A5: BASE DATA BY YEAR
A6: Annual fixed costs | B6: =IFERROR(IF('3-Year P&L'!$B$9="","",'3-Year P&L'!$B$38),"") -> 232852.34 | C6: =IFERROR(IF('3-Year P&L'!$C$9="","",'3-Year P&L'!$C$38),"") -> 239835.87 | D6: =IFERROR(IF('3-Year P&L'!$D$9="","",'3-Year P&L'!$D$38),"") -> 246717.74 | E6: The SAME fixed costs as the P&L. Each year has its own, which is why the threshold cannot be a single one for all three years
A7: Monthly fixed costs | B7: =IFERROR(IF('3-Year P&L'!$B$9="","",B6/12),"") -> 19404.362 | C7: =IFERROR(IF('3-Year P&L'!$C$9="","",C6/12),"") -> 19986.322 | D7: =IFERROR(IF('3-Year P&L'!$D$9="","",D6/12),"") -> 20559.812
A8: Average check (excl. sales tax) | B8: =IFERROR(IF('3-Year P&L'!$B$9="","",'3-Year P&L'!$B$7),"") -> 7.5 | C8: =IFERROR(IF('3-Year P&L'!$C$9="","",'3-Year P&L'!$C$7),"") -> 7.5 | D8: =IFERROR(IF('3-Year P&L'!$D$9="","",'3-Year P&L'!$D$7),"") -> 7.5
A9: Variable cost per customer | B9: =IFERROR(IF('3-Year P&L'!$B$9="","",'3-Year P&L'!$B$19/('3-Year P&L'!$B$6*'3-Year P&L'!$B$8)),"") -> 2.385 | C9: =IFERROR(IF('3-Year P&L'!$C$9="","",'3-Year P&L'!$C$19/('3-Year P&L'!$C$6*'3-Year P&L'!$C$8)),"") -> 2.385 | D9: =IFERROR(IF('3-Year P&L'!$D$9="","",'3-Year P&L'!$D$19/('3-Year P&L'!$D$6*'3-Year P&L'!$D$8)),"") -> 2.385 | E9: Comes from the P&L total variable costs, not from a separate estimate. It includes miscellaneous and contingency, which is a percentage of sales
A10: Contribution margin per customer | B10: =IFERROR(IF('3-Year P&L'!$B$9="","",B8-B9),"") -> 5.115 | C10: =IFERROR(IF('3-Year P&L'!$C$9="","",C8-C9),"") -> 5.115 | D10: =IFERROR(IF('3-Year P&L'!$D$9="","",D8-D9),"") -> 5.115 | E10: Average check minus unit variable cost
A11: Operating days per year | B11: =IFERROR(IF('3-Year P&L'!$B$9="","",'3-Year P&L'!$B$8),"") -> 310 | C11: =IFERROR(IF('3-Year P&L'!$C$9="","",'3-Year P&L'!$C$8),"") -> 310 | D11: =IFERROR(IF('3-Year P&L'!$D$9="","",'3-Year P&L'!$D$8),"") -> 310 | E11: The same calendar as the P&L and the scenarios
A12: Principal repaid in the year | B12: =IFERROR(IF('3-Year P&L'!$B$9="","",Financing!$B$45),"") -> 10164.754 | C12: =IFERROR(IF('3-Year P&L'!$C$9="","",Financing!$B$47),"") -> 11181.229 | D12: =IFERROR(IF('3-Year P&L'!$D$9="","",Financing!$B$49),"") -> 12299.352 | E12: Principal is NOT a P&L expense, but it leaves the cash account. Without it, the published break-even threshold would sit below the real one
A13: ACCOUNTING BREAK-EVEN (includes depreciation)
A14: Customers needed per year | B14: =IFERROR(IF('3-Year P&L'!$B$9="","",IF(B10<=0,"",B6/B10)),"") -> 45523.43 | C14: =IFERROR(IF('3-Year P&L'!$C$9="","",IF(C10<=0,"",C6/C10)),"") -> 46888.733 | D14: =IFERROR(IF('3-Year P&L'!$D$9="","",IF(D10<=0,"",D6/D10)),"") -> 48234.163
A15: Customers needed per day | B15: =IFERROR(IF('3-Year P&L'!$B$9="","",B14/B11),"") -> 146.84977 | C15: =IFERROR(IF('3-Year P&L'!$C$9="","",C14/C11),"") -> 151.25398 | D15: =IFERROR(IF('3-Year P&L'!$D$9="","",D14/D11),"") -> 155.59407
A16: Revenue needed per year | B16: =IFERROR(IF('3-Year P&L'!$B$9="","",B14*B8),"") -> 341425.72 | C16: =IFERROR(IF('3-Year P&L'!$C$9="","",C14*C8),"") -> 351665.49 | D16: =IFERROR(IF('3-Year P&L'!$D$9="","",D14*D8),"") -> 361756.22
A17: CASH BREAK-EVEN (loan payments in, depreciation out)
A18: Cash fixed costs + principal repaid for the year | B18: =IFERROR(IF('3-Year P&L'!$B$9="","",B6-'3-Year P&L'!$B$36+B12),"") -> 221249.95 | C18: =IFERROR(IF('3-Year P&L'!$C$9="","",C6-'3-Year P&L'!$C$36+C12),"") -> 229249.95 | D18: =IFERROR(IF('3-Year P&L'!$D$9="","",D6-'3-Year P&L'!$D$36+D12),"") -> 237249.95 | E18: The P&L fixed costs without depreciation (which is not paid in cash) and WITH principal repaid (which is). This is the threshold that decides whether cash holds up
A19: Customers needed per year (cash) | B19: =IFERROR(IF('3-Year P&L'!$B$9="","",IF(B10<=0,"",B18/B10)),"") -> 43255.123 | C19: =IFERROR(IF('3-Year P&L'!$C$9="","",IF(C10<=0,"",C18/C10)),"") -> 44819.15 | D19: =IFERROR(IF('3-Year P&L'!$D$9="","",IF(D10<=0,"",D18/D10)),"") -> 46383.178
A20: Customers needed per day (cash) | B20: =IFERROR(IF('3-Year P&L'!$B$9="","",B19/B11),"") -> 139.53265 | C20: =IFERROR(IF('3-Year P&L'!$C$9="","",C19/C11),"") -> 144.5779 | D20: =IFERROR(IF('3-Year P&L'!$D$9="","",D19/D11),"") -> 149.62315
A21: Revenue needed per year (cash) | B21: =IFERROR(IF('3-Year P&L'!$B$9="","",B19*B8),"") -> 324413.42 | C21: =IFERROR(IF('3-Year P&L'!$C$9="","",C19*C8),"") -> 336143.63 | D21: =IFERROR(IF('3-Year P&L'!$D$9="","",D19*D8),"") -> 347873.83
A22: COMPARISON WITH THE PLAN
A23: Customers per day forecast in the plan | B23: =IFERROR(IF('3-Year P&L'!$B$9="","",'3-Year P&L'!$B$6),"") -> 165 | C23: =IFERROR(IF('3-Year P&L'!$C$9="","",'3-Year P&L'!$C$6),"") -> 178.2 | D23: =IFERROR(IF('3-Year P&L'!$D$9="","",'3-Year P&L'!$D$6),"") -> 187.11
A24: Cushion above CASH break-even (%) | B24: =IFERROR(IF('3-Year P&L'!$B$9="","",B23/B20-1),"") -> 0.18251889 | C24: =IFERROR(IF('3-Year P&L'!$C$9="","",C23/C20-1),"") -> 0.23255349 | D24: =IFERROR(IF('3-Year P&L'!$D$9="","",D23/D20-1),"") -> 0.25054175 | E24: How far you can fall before you cannot pay the fixed costs and the loan payment. The required minimum is set in the "0. Assumptions" tab
A25: INTERPRETATION
A26: =IFERROR("With the average check excl. sales tax above, you need "&TEXT(ROUNDUP(B15,0),"0")&" customers a day over your "&TEXT(B11,"0")&" opening days to avoid losing money (accounting break-even, depreciation included), and "&TEXT(ROUNDUP(B20,0),"0")&" for cash to hold (cash break-even: depreciation out, because it is not paid, and the year's loan payment in"&IF(B12=0,"; no principal is repaid this year (interest-only period or no loan)","")&"). The ""Revenue needed per year"" rows show the same figures in your currency.","") -> With the average check excl. sales tax above, you need 147 customers a day over your 310 opening days to avoid losing money (accounting break-even, depreciation included), and 140 for cash to hold (cash break-even: depreciation out, because it is not paid, and the year's loan payment in). The "Revenue needed per year" rows show the same figures in your currency.
A28: BREAK-EVEN SENSITIVITY
A29: Customers per day needed to cover costs for each average check (columns) and each variable cost per customer (rows). Green cells are below the customers per day the plan forecasts.
A31: Customers per day needed: average check excl. sales tax (columns) × variable cost per customer (rows) | B31: =IFERROR($B$8-2,"") -> 5.5 | C31: =IFERROR(IF($B$8="","",$B$8),"") -> 7.5 | D31: =IFERROR($B$8+2,"") -> 9.5 | E31: =IFERROR($B$8+4,"") -> 11.5
A32: =IFERROR($B$9*0.85,"") -> 2.02725 | B32: =IFERROR(IF($B$31-$A32<=0,"",$B$6/($B$31-$A32)/$B$11),"") -> 216.29446 | C32: =IFERROR(IF($C$31-$A32<=0,"",$B$6/($C$31-$A32)/$B$11),"") -> 137.2503 | D32: =IFERROR(IF($D$31-$A32<=0,"",$B$6/($D$31-$A32)/$B$11),"") -> 100.51676 | E32: =IFERROR(IF($E$31-$A32<=0,"",$B$6/($E$31-$A32)/$B$11),"") -> 79.294459
A33: =IFERROR($B$9*0.925,"") -> 2.206125 | B33: =IFERROR(IF($B$31-$A33<=0,"",$B$6/($B$31-$A33)/$B$11),"") -> 228.04041 | C33: =IFERROR(IF($C$31-$A33<=0,"",$B$6/($C$31-$A33)/$B$11),"") -> 141.88786 | D33: =IFERROR(IF($D$31-$A33<=0,"",$B$6/($D$31-$A33)/$B$11),"") -> 102.98183 | E33: =IFERROR(IF($E$31-$A33<=0,"",$B$6/($E$31-$A33)/$B$11),"") -> 80.820604
A34: =IFERROR($B$9*1.0,"") -> 2.385 | B34: =IFERROR(IF($B$31-$A34<=0,"",$B$6/($B$31-$A34)/$B$11),"") -> 241.13534 | C34: =IFERROR(IF($C$31-$A34<=0,"",$B$6/($C$31-$A34)/$B$11),"") -> 146.84977 | D34: =IFERROR(IF($D$31-$A34<=0,"",$B$6/($D$31-$A34)/$B$11),"") -> 105.57085 | E34: =IFERROR(IF($E$31-$A34<=0,"",$B$6/($E$31-$A34)/$B$11),"") -> 82.406647
A35: =IFERROR($B$9*1.075,"") -> 2.563875 | B35: =IFERROR(IF($B$31-$A35<=0,"",$B$6/($B$31-$A35)/$B$11),"") -> 255.82582 | C35: =IFERROR(IF($C$31-$A35<=0,"",$B$6/($C$31-$A35)/$B$11),"") -> 152.17131 | D35: =IFERROR(IF($D$31-$A35<=0,"",$B$6/($D$31-$A35)/$B$11),"") -> 108.2934 | E35: =IFERROR(IF($E$31-$A35<=0,"",$B$6/($E$31-$A35)/$B$11),"") -> 84.056187
A36: =IFERROR($B$9*1.15,"") -> 2.74275 | B36: =IFERROR(IF($B$31-$A36<=0,"",$B$6/($B$31-$A36)/$B$11),"") -> 272.42237 | C36: =IFERROR(IF($C$31-$A36<=0,"",$B$6/($C$31-$A36)/$B$11),"") -> 157.89302 | D36: =IFERROR(IF($D$31-$A36<=0,"",$B$6/($D$31-$A36)/$B$11),"") -> 111.1601 | E36: =IFERROR(IF($E$31-$A36<=0,"",$B$6/($E$31-$A36)/$B$11),"") -> 85.773113

Sheet Scenarios
A1: SCENARIOS
A4: Metric | B4: Pessimistic | C4: Base | D4: Optimistic | E4: Notes
A5: Customers per day | B5: 140 | C5: =IFERROR(IF('3-Year P&L'!$B$6="","",'3-Year P&L'!$B$6),"") -> 165 | D5: 190
A6: Average check (excl. sales tax) | B6: 7 | C6: =IFERROR(IF('3-Year P&L'!$B$7="","",'3-Year P&L'!$B$7),"") -> 7.5 | D6: 8
A7: Operating days per year | B7: 300 | C7: =IFERROR(IF('3-Year P&L'!$B$8="","",'3-Year P&L'!$B$8),"") -> 310 | D7: 320
A8: ANNUAL REVENUE (excl. sales tax) | B8: =IFERROR(IF(B5*B6*B7=0,"",B5*B6*B7),"") -> 294000 | C8: =IFERROR(IF(C5*C6*C7=0,"",C5*C6*C7),"") -> 383625 | D8: =IFERROR(IF(D5*D6*D7=0,"",D5*D6*D7),"") -> 486400
A9: Cost of goods sold — food | B9: =IFERROR(IF(B8="","",B8*'0. Assumptions'!$B$11*'0. Assumptions'!$B$13),"") -> 58212 | C9: =IFERROR(IF(C8="","",C8*'0. Assumptions'!$B$11*'0. Assumptions'!$B$13),"") -> 75957.75 | D9: =IFERROR(IF(D8="","",D8*'0. Assumptions'!$B$11*'0. Assumptions'!$B$13),"") -> 96307.2
A10: Cost of goods sold — beverage | B10: =IFERROR(IF(B8="","",B8*'0. Assumptions'!$B$12*'0. Assumptions'!$B$14),"") -> 7350 | C10: =IFERROR(IF(C8="","",C8*'0. Assumptions'!$B$12*'0. Assumptions'!$B$14),"") -> 9590.625 | D10: =IFERROR(IF(D8="","",D8*'0. Assumptions'!$B$12*'0. Assumptions'!$B$14),"") -> 12160
A11: Disposables and packaging | B11: =IFERROR(IF(B8="","",B8*'0. Assumptions'!$B$15),"") -> 13230 | C11: =IFERROR(IF(C8="","",C8*'0. Assumptions'!$B$15),"") -> 17263.125 | D11: =IFERROR(IF(D8="","",D8*'0. Assumptions'!$B$15),"") -> 21888
A12: Delivery platform fees | B12: =IFERROR(IF(B8="","",B8*'0. Assumptions'!$B$16*'0. Assumptions'!$B$17),"") -> 2940 | C12: =IFERROR(IF(C8="","",C8*'0. Assumptions'!$B$16*'0. Assumptions'!$B$17),"") -> 3836.25 | D12: =IFERROR(IF(D8="","",D8*'0. Assumptions'!$B$16*'0. Assumptions'!$B$17),"") -> 4864
A13: Card processing fees | B13: =IFERROR(IF(B8="","",B8*'0. Assumptions'!$B$18),"") -> 8820 | C13: =IFERROR(IF(C8="","",C8*'0. Assumptions'!$B$18),"") -> 11508.75 | D13: =IFERROR(IF(D8="","",D8*'0. Assumptions'!$B$18),"") -> 14592
A14: Miscellaneous and contingency | B14: =IFERROR(IF(B8="","",B8*'0. Assumptions'!$B$28),"") -> 2940 | C14: =IFERROR(IF(C8="","",C8*'0. Assumptions'!$B$28),"") -> 3836.25 | D14: =IFERROR(IF(D8="","",D8*'0. Assumptions'!$B$28),"") -> 4864
A15: TOTAL VARIABLE COSTS | B15: =IFERROR(IF(B8="","",SUM(B9:B14)),"") -> 93492 | C15: =IFERROR(IF(C8="","",SUM(C9:C14)),"") -> 121992.75 | D15: =IFERROR(IF(D8="","",SUM(D9:D14)),"") -> 154675.2
A16: GROSS MARGIN | B16: =IFERROR(IF(B8="","",B8-B15),"") -> 200508 | C16: =IFERROR(IF(C8="","",C8-C15),"") -> 261632.25 | D16: =IFERROR(IF(D8="","",D8-D15),"") -> 331724.8
A17: FIXED COSTS (the P&L's) | B17: =IFERROR(IF(B8="","",'3-Year P&L'!$B$38),"") -> 232852.34 | C17: =IFERROR(IF(C8="","",'3-Year P&L'!$B$38),"") -> 232852.34 | D17: =IFERROR(IF(D8="","",'3-Year P&L'!$B$38),"") -> 232852.34 | E17: Fixed costs do not change with the scenario: that is why they are fixed
A18: PRE-TAX INCOME (EBT) | B18: =IFERROR(IF(B8="","",B16-B17),"") -> -32344.343 | C18: =IFERROR(IF(C8="","",C16-C17),"") -> 28779.907 | D18: =IFERROR(IF(D8="","",D16-D17),"") -> 98872.457
A19: Income tax | B19: =IFERROR(IF(B8="","",MAX(0,B18-'0. Assumptions'!$B$42)*'0. Assumptions'!$B$37),"") -> 0 | C19: =IFERROR(IF(C8="","",MAX(0,C18-'0. Assumptions'!$B$42)*'0. Assumptions'!$B$37),"") -> 7194.9768 | D19: =IFERROR(IF(D8="","",MAX(0,D18-'0. Assumptions'!$B$42)*'0. Assumptions'!$B$37),"") -> 24718.114 | E19: At the "years 1-2" effective income tax rate, offsetting prior net operating losses
A20: NET INCOME | B20: =IFERROR(IF(B8="","",B18-B19),"") -> -32344.343 | C20: =IFERROR(IF(C8="","",C18-C19),"") -> 21584.93 | D20: =IFERROR(IF(D8="","",D18-D19),"") -> 74154.343
A21: Customers per day to break even | B21: =IFERROR(IF(B8="","",IF(B6-B15/(B5*B7)<=0,"",B17/(B6-B15/(B5*B7))/B7)),"") -> 162.58368 | C21: =IFERROR(IF(C8="","",IF(C6-C15/(C5*C7)<=0,"",C17/(C6-C15/(C5*C7))/C7)),"") -> 146.84977 | D21: =IFERROR(IF(D8="","",IF(D6-D15/(D5*D7)<=0,"",D17/(D6-D15/(D5*D7))/D7)),"") -> 133.36942
A22: WHAT EACH SCENARIO DEMANDS
A23: Labor cost / Sales | B23: =IFERROR(IF(B8="","",'3-Year P&L'!$B$23/B8),"") -> 0.43600408 | C23: =IFERROR(IF(C8="","",'3-Year P&L'!$B$23/C8),"") -> 0.33414194 | D23: =IFERROR(IF(D8="","",'3-Year P&L'!$B$23/D8),"") -> 0.26353865 | E23: The SAME staffing in all three scenarios. If labor cost blows up in the pessimistic case, adjust it in the Staffing tab, not here
A24: Customers per year per full-time equivalent | B24: =IFERROR(IF(B8="","",B5*B7/Staffing!$C$11),"") -> 13770.492 | C24: =IFERROR(IF(C8="","",C5*C7/Staffing!$C$11),"") -> 16770.492 | D24: =IFERROR(IF(D8="","",D5*D7/Staffing!$C$11),"") -> 19934.426 | E24: Customers each full-time employee in the Staffing table would have to serve. In the optimistic scenario it tells you whether you need to hire
A25: Year-1 closing cash balance (estimate, same method in all three scenarios) | B25: =IFERROR(IF(B8="","",'Startup Costs'!$B$30+B20+'3-Year P&L'!$B$36-Financing!$B$45),"") -> 32029.346 | C25: =IFERROR(IF(C8="","",'Startup Costs'!$B$30+C20+'3-Year P&L'!$B$36-Financing!$B$45),"") -> 85958.619 | D25: =IFERROR(IF(D8="","",'Startup Costs'!$B$30+D20+'3-Year P&L'!$B$36-Financing!$B$45),"") -> 138528.03 | E25: ESTIMATED balance: working capital plus the year's result, adding back depreciation (which is not paid) and subtracting loan principal. It does not include the timing gap between receipts and payments or the sales tax settlement, so the three columns can be compared with each other. In red, the scenario runs out of cash
A26: Actual month-12 balance from the 12-Month Cash Flow tab (Base case only) | C26: =IFERROR(IF(C8="","",'12-Month Cash Flow'!$M$22),"") -> 97745.907 | E26: The ACTUAL base-case balance, with its timing of receipts and payments and its sales tax settlement. It exists only for the Base scenario, the only one with its own monthly cash flow: that is why it is not in the row above, where it would be compared against two estimates
A28: The "Base" column reads its three inputs from the "0. Assumptions" tab, so it reproduces EXACTLY year 1 of the P&L. The other two scenarios use the same cost rates: only customers, average check and days change. FIXED COSTS are the same in all three: miscellaneous and contingency, a percentage of sales, sit above with the variable costs and each scenario carries its own.

Sheet Staffing
A1: STAFFING AND LABOR COSTS
A2: =IFERROR("Payroll — "&TEXT('0. Assumptions'!$B$21,"0")&" pay periods + employer taxes "&TEXT('0. Assumptions'!$B$20*100,"0")&"%","") -> Payroll — 12 pay periods + employer taxes 10%
A4: Position | B4: People | C4: FTE | D4: Gross pay per month (total for the position) | E4: Employer payroll taxes (total for the position) | F4: Cost per month (total for the position) | G4: Cost per year | H4: Hours per week per person | I4: Hours per year for the position | J4: Notes
A5: Owner / ice cream maker & GM | B5: 1 | C5: 1 | D5: 4000 | E5: =IFERROR(IF(D5="","",D5*'0. Assumptions'!$B$20),"") -> 400 | F5: =IFERROR(IF(D5="","",D5+E5),"") -> 4400 | G5: =IFERROR(IF(D5="","",F5*MAX(12,'0. Assumptions'!$B$21)),"") -> 52800 | H5: =IFERROR(IF(D5="","",C5*$B$18),"") -> 40 | I5: =IFERROR(IF(D5="","",H5*B5*$B$19),"") -> 1840 | J5: Balances recipes, flavors and mix-ins, runs the batch freezer, buys and runs the business. Works as the ice cream maker and GM but does NOT pasteurize: the base is bought from a licensed dairy. Paid below what a hired manager would earn: plan to draw in addition from net profit. The book loads employer payroll taxes on this salary as if it were payroll, which is the prudent side
A6: Shift lead / counter (year-round) | B6: 1 | C6: 1 | D6: 2946 | E6: =IFERROR(IF(D6="","",D6*'0. Assumptions'!$B$20),"") -> 294.6 | F6: =IFERROR(IF(D6="","",D6+E6),"") -> 3240.6 | G6: =IFERROR(IF(D6="","",F6*MAX(12,'0. Assumptions'!$B$21)),"") -> 38887.2 | H6: =IFERROR(IF(D6="","",C6*$B$18),"") -> 40 | I6: =IFERROR(IF(D6="","",H6*B6*$B$19),"") -> 1840 | J6: Counter, register, dipping cabinets and closing; opens and closes when the owner is in the production room. About $17 per hour
A7: Seasonal scooper (part-time, April-September) | B7: 1 | C7: 0.5 | D7: 1300 | E7: =IFERROR(IF(D7="","",D7*'0. Assumptions'!$B$20),"") -> 130 | F7: =IFERROR(IF(D7="","",D7+E7),"") -> 1430 | G7: =IFERROR(IF(D7="","",F7*MAX(12,'0. Assumptions'!$B$21)),"") -> 17160 | H7: =IFERROR(IF(D7="","",C7*$B$18),"") -> 20 | I7: =IFERROR(IF(D7="","",H7*B7*$B$19),"") -> 920 | J7: Seasonal W-2 employee: about 40 hours a week from April to September, which equals half a full-time position over the year (part-time on a yearly basis). Rehire each spring. Scoopers aged 14-15 only within the FLSA hours (29 CFR 570.35)
A8: Summer scooper (part-time, June-August) | B8: 1 | C8: 0.25 | D8: 650 | E8: =IFERROR(IF(D8="","",D8*'0. Assumptions'!$B$20),"") -> 65 | F8: =IFERROR(IF(D8="","",D8+E8),"") -> 715 | G8: =IFERROR(IF(D8="","",F8*MAX(12,'0. Assumptions'!$B$21)),"") -> 8580 | H8: =IFERROR(IF(D8="","",C8*$B$18),"") -> 10 | I8: =IFERROR(IF(D8="","",H8*B8*$B$19),"") -> 460 | J8: Seasonal part-time W-2 employee from June to August, on the evenings of the peak. Never a 1099 contractor if you set the schedule and give the direction: that is misclassification
A9: Production assistant (part-time, May-September) | B9: 1 | C9: 0.2 | D9: 555 | E9: =IFERROR(IF(D9="","",D9*'0. Assumptions'!$B$20),"") -> 55.5 | F9: =IFERROR(IF(D9="","",D9+E9),"") -> 610.5 | G9: =IFERROR(IF(D9="","",F9*MAX(12,'0. Assumptions'!$B$21)),"") -> 7326 | H9: =IFERROR(IF(D9="","",C9*$B$18),"") -> 8 | I9: =IFERROR(IF(D9="","",H9*B9*$B$19),"") -> 368 | J9: Production assistant from May to September: batch freezing, pack-out, cleaning the batch freezer and the tubs, and support on the summer batches
A10: Relief cover (vacations and days off) | B10: 1 | C10: 0.1 | D10: 260 | E10: =IFERROR(IF(D10="","",D10*'0. Assumptions'!$B$20),"") -> 26 | F10: =IFERROR(IF(D10="","",D10+E10),"") -> 286 | G10: =IFERROR(IF(D10="","",F10*MAX(12,'0. Assumptions'!$B$21)),"") -> 3432 | H10: =IFERROR(IF(D10="","",C10*$B$18),"") -> 4 | I10: =IFERROR(IF(D10="","",H10*B10*$B$19),"") -> 184 | J10: Coverage for vacations and the team's days off through the year. Paid sick leave is required by some states and cities: check yours
A11: TOTAL STAFF | B11: =IFERROR(IF(COUNT(D5:D10)=0,"",SUM(B5:B10)),"") -> 6 | C11: =IFERROR(IF(COUNT(D5:D10)=0,"",SUM(C5:C10)),"") -> 3.05 | D11: =IFERROR(IF(COUNT(D5:D10)=0,"",SUM(D5:D10)),"") -> 9711 | E11: =IFERROR(IF(COUNT(D5:D10)=0,"",SUM(E5:E10)),"") -> 971.1 | F11: =IFERROR(IF(COUNT(D5:D10)=0,"",SUM(F5:F10)),"") -> 10682.1 | G11: =IFERROR(IF(COUNT(D5:D10)=0,"",SUM(G5:G10)),"") -> 128185.2 | I11: =IFERROR(IF(COUNT(D5:D10)=0,"",SUM(I5:I10)),"") -> 5612
A12: STAFF GROWTH (stepped cost)
A13: Annual cost of year-2 hires | B13: 8000 | J13: FULL ANNUAL cost (gross pay + employer payroll taxes, over all pay periods) of whoever you hire that year. The P&L adds it to the previous year's cost: staffing grows by people, not by a percentage
A14: Annual cost of year-3 hires | B14: 8000 | J14: FULL ANNUAL cost (gross pay + employer payroll taxes, over all pay periods) of whoever you hire that year. The P&L adds it to the previous year's cost: staffing grows by people, not by a percentage
A15: Labor cost, year 2 | B15: =IFERROR(IF(G11="","",G11*(1+'0. Assumptions'!$B$48)+B13),"") -> 136185.2
A16: Labor cost, year 3 | B16: =IFERROR(IF(B15="","",B15*(1+'0. Assumptions'!$B$48)+B14),"") -> 144185.2
A17: COVERAGE OF SERVICE HOURS
A18: Full-time week (hours per week) | B18: 40 | J18: 40 hours a week is the FLSA overtime threshold for non-exempt employees; some states add daily overtime rules. Change it if your own full-time week is different
A19: Weeks worked per year per person | B19: 46 | J19: 46 weeks: 52 minus about six weeks for vacation, holidays, the January closure and average absences. There is no federal vacation requirement in the US: adjust it to your own policy
A20: Service hours per day to cover | B20: 9.5 | J20: Average shop hours over the year: more in peak season (Memorial Day to Labor Day), fewer from November to February. The production room goes in the row below
A21: People needed at the same time in each shift | B21: 1.6 | J21: Average staff on the floor at once at the counter: 1.8-2 people in summer, 1.3 in spring and fall and 1 in winter. In July and August the schedule is tight: the owner works shifts or a weekend extra comes in
A22: Production hours per day BEFORE opening | B22: 2 | J22: Production runs before opening: flavoring, batch-freezing and hardening, with no processing of raw mix and no aging: the base arrives pasteurized and aged from a licensed dairy. More in July, less in winter
A23: People on the production shift | B23: 1 | J23: The ice cream maker; in summer the production assistant helps
A24: Service hours to cover per year | B24: =IFERROR(IF(OR(B20="",B21="",'0. Assumptions'!$B$6=""),"",B20*B21*'0. Assumptions'!$B$6+B22*B23*'0. Assumptions'!$B$6),"") -> 5332
A25: Hours hired per year | B25: =IFERROR(IF(I11="","",I11),"") -> 5612
A26: Coverage (hired / needed) | B26: =IFERROR(B25/B24,"") -> 1.0525131 | J26: Below 100% the staff cannot cover the hours the plan declares: either hire more or cut the hours
A28: The gross pay, employer payroll taxes, monthly cost and annual cost columns are TOTALS for the row: for a position with two people they include both. "FTE" is the share of a full-time week and is used to compare pay with the legal floor pro rata. The payroll tax rate and the number of pay periods are in the "0. Assumptions" tab. Tips are not modeled: the shift lead and the scoopers are budgeted at a base wage of at least $15/h
A29: The pay floor is the HIGHER of the federal minimum wage and your state / local minimum wage, both in the "0. Assumptions" tab; part-time positions get it in proportion. There is no single national table above the federal floor: the state / local cell is delivered empty so you can enter the rate for your state and city.

Sheet Instructions
A1: HOW TO USE THIS WORKBOOK — Ice Cream Shop Financial Projections
A3: HOW TO USE THIS WORKBOOK
A4: This financial plan is a MODEL: you type only in the GREEN cells and everything else recalculates on its own.
A5: 1. "0. Assumptions" is the control sheet: customers per day, average check excl. sales tax, operating days, food and beverage mix, cost of goods sold, rent, financing and taxes.
A6: 2. Startup cost items, fixed costs and staffing are typed in their own tab, also in green. No number is typed twice.
A7: 3. Only "Break-Even" is derived entirely from the rest. The other three tabs also have green cells you can edit: the pessimistic and optimistic scenarios in "Scenarios", seasonality and the launch ramp-up in "12-Month Cash Flow", and the other funding sources in "Financing" (rows 8-11 count as sources but are not amortized: Your bank or SBA 7(a) loan goes in "Loan requested" on "0. Assumptions"). Everything else is calculated.
A8: 4. All figures are shown EXCL. SALES TAX. To turn a menu price into a price without tax, divide it by 1 + your sales tax rate (8% in the example, so divide by 1.08). A scoop is generally taxed as prepared food; in some states packaged pints and whole cakes may be taxed as groceries, so check your state. The P&L is excl. sales tax and the cash flow uses what is collected, tax included. Input tax on purchases is not recoverable in this book.
A9: 5. If you change the staffing, the P&L reads it on its own: labor cost comes from the "Staffing" tab, not from a separate estimate.
A10: 6. The "12-Month Cash Flow" tab answers the question that decides a loan: in which month does the cash run out? Its Month 1 is MARCH: the plan opens in season so that the summer cash reaches the first winter. The minimum balance of the year can never be red.
A11: 7. The "Financing" tab matches what you need with what you put in and builds the amortization schedule of the loan. If the difference is red, the plan is not funded.
A12: 8. The Word document in this pack uses the figures from this Excel: if you change a green cell, the Excel rules.
A14: RATIOS AUDITED BY THIS WORKBOOK
A15: Thresholds live in the "Threshold" column of the KEY RATIOS block of the P&L: change them there and the traffic light changes with them.
A17: Ratio | B17: Year 1 value | C17: Threshold | D17: Status
A18: Cost of goods sold / Sales | B18: =IFERROR(IF('3-Year P&L'!$B$53="","",'3-Year P&L'!$B$53),"") -> 0.223 | C18: =IFERROR(IF('3-Year P&L'!$E$53="","",'3-Year P&L'!$E$53),"") -> 0.25 | D18: =IFERROR(IF(OR(B18="",C18=""),"",IF(B18<=C18,"OK","REVIEW")),"") -> OK
A19: Labor cost / Sales | B19: =IFERROR(IF('3-Year P&L'!$B$54="","",'3-Year P&L'!$B$54),"") -> 0.33414194 | C19: =IFERROR(IF('3-Year P&L'!$E$54="","",'3-Year P&L'!$E$54),"") -> 0.35 | D19: =IFERROR(IF(OR(B19="",C19=""),"",IF(B19<=C19,"OK","REVIEW")),"") -> OK
A20: Rent / Sales | B20: =IFERROR(IF('3-Year P&L'!$B$55="","",'3-Year P&L'!$B$55),"") -> 0.078201369 | C20: =IFERROR(IF('3-Year P&L'!$E$55="","",'3-Year P&L'!$E$55),"") -> 0.1 | D20: =IFERROR(IF(OR(B20="",C20=""),"",IF(B20<=C20,"OK","REVIEW")),"") -> OK
A21: Net income / Sales | B21: =IFERROR(IF('3-Year P&L'!$B$56="","",'3-Year P&L'!$B$56),"") -> 0.056265703 | C21: =IFERROR(IF('3-Year P&L'!$E$56="","",'3-Year P&L'!$E$56),"") -> 0.05 | D21: =IFERROR(IF(OR(B21="",C21=""),"",IF(B21>=C21,"OK","REVIEW")),"") -> OK
A22: Gross margin / Sales | B22: =IFERROR(IF('3-Year P&L'!$B$51="","",'3-Year P&L'!$B$51),"") -> 0.682 | C22: =IFERROR(IF('3-Year P&L'!$E$51="","",'3-Year P&L'!$E$51),"") -> 0.65 | D22: =IFERROR(IF(OR(B22="",C22=""),"",IF(B22>=C22,"OK","REVIEW")),"") -> OK
A24: THIS PLAN'S KEY FIGURES
A25: Total startup costs (sum of the blocks) | B25: =IFERROR(IF('Startup Costs'!$B$31="","",'Startup Costs'!$B$31),"") -> 256871.3
A26: Total cash needed at launch | B26: =IFERROR(IF('Startup Costs'!$B$34="","",'Startup Costs'!$B$34),"") -> 256871.3
A27: Working capital funded | B27: =IFERROR(IF('Startup Costs'!$B$30="","",'Startup Costs'!$B$30),"") -> 52771.3
A28: Forecast year-1 revenue | B28: =IFERROR(IF('3-Year P&L'!$B$9="","",'3-Year P&L'!$B$9),"") -> 383625
A29: Year-1 net income | B29: =IFERROR(IF('3-Year P&L'!$B$48="","",'3-Year P&L'!$B$48),"") -> 21584.93
A30: Customers per day for the ACCOUNTING break-even (depreciation included) | B30: =IFERROR(IF('Break-Even'!$B$15="","",'Break-Even'!$B$15),"") -> 146.84977
A31: Project payback (years), before debt | B31: =IFERROR(IF('12-Month Cash Flow'!$B$31="","",'12-Month Cash Flow'!$B$31),"") -> Over 3 years
A33: US ICE CREAM SHOP BENCHMARKS (sourced) AND KIT ESTIMATES
A34: Benchmark | B34: Value | C34: Source | D34: Note
A35: Month 1 of the plan | B35: March | C35: Plan decision | D35: Open in season: the first summer pays for the first winter. Opening in fall burns the working capital before the first summer. The seasonality row on the cash flow tab is already shifted to start in March
A36: Peak season | B36: Memorial Day to Labor Day; July is National Ice Cream Month | C36: Presidential Proclamation 5219 (1984); IDFA | D36: July is the month with the most production; National Ice Cream Day is the 3rd Sunday of July. Winter sells ice cream cakes, holiday pies and pints, and hot chocolate
A37: Ice cream cost (food cost) | B37: About 22% of ice cream sales | C37: Kit estimate | D37: Purchased base, flavorings and mix-ins, cones, samples and shrink. Replace it with the invoices from your dairy and your distributor
A38: Menu prices | B38: Single $5.25 · double $7.00 · pint $11 · quart $18 · 8-in cake $45 | C38: Kit estimate (Oct 2026), excl. sales tax | D38: There is no reliable U.S. average for the price of a scoop: use the prices in your area. The average check excl. sales tax for this plan is on the "0. Assumptions" tab
A39: "Ice cream" standard | B39: At least 10% milkfat and 4.5 lb per gallon; frozen custard: 1.4% egg yolk solids | C39: 21 CFR 135.110 (eCFR) | D39: If you call it ice cream, the federal standard applies. Weight is measured in lb per gallon (1 gallon is about 3.8 liters). Check the labeling rules for anything below the standard
A40: Storage and serving temperature | B40: 0 °F (−18 °C) or colder in storage and hardening; dipping cabinet 6-10 °F | C40: FDA Food Code + equipment manufacturer | D40: Cold holding of the purchased base at 41 °F (5 °C) or colder. The cabinet temperature depends on the manufacturer's specification and your food safety plan
A41: Buy a base or make your own mix | B41: Buying pasteurized base: retail permit, plus a frozen dessert license in some states (Vermont); own mix: state dairy / frozen dessert manufacturer license | C41: Vermont Agency of Agriculture; Georgia Rules 40-2-8 | D41: Depends on your state: ask your state department of agriculture. If you pasteurize your own mix (the variant), fats, egg yolks and emulsifiers go in BEFORE pasteurization, never after, and you need licensed equipment and inspections. The case buys the base from a licensed dairy
A42: Labor cost / sales | B42: 28-35% | C42: Kit estimate | D42: Putting the owner on payroll and the season push it to the high end
A43: Rent / sales | B43: 10% or less | C43: Kit estimate | D43: The threshold of the traffic light on the P&L
A44: Production waste | B44: 5-8% | C44: Kit estimate | D44: Flavors that do not turn over, open tubs and samples. Melted or returned ice cream is never refrozen
A45: Electrical service | B45: About 30 kW | C45: Kit estimate | D45: Ask the utility about 3-phase service and amps before signing. Dipping cabinets run 24 hours a day, plus the batch freezer, the hardening cabinet and air conditioning
... A47: Minimum wage | B47: Federal $7.25 per hour + your state; teens 14-15: limited hours | C47: U.S. Department of Labor (29 CFR 570.35) | D47: This plan budgets $15 per hour or more. Type your state's floor on "0. Assumptions"
A49: To edit a cell that is not green: Review → Unprotect Sheet (there is no password).
A50: More templates and kits in the catalog at aichef.pro/en/digital-products
A51: Designed by John Guerrero — chef and restaurant consultant since 2010, in the kitchen since age 17 · johnguerrero.es
A52: Version 2.2 · October 2026 · aichef.pro/en/digital-products/ice-cream-shop-business-plan · info@aichef.pro
A53: Planning tool, not financial, tax or legal advice. Requirements vary by state, county and city — check with your accountant and local authorities.

Sheet 12-Month Cash Flow
A1: CASH FLOW FORECAST — YEAR 1
A2: The P&L tells you whether the business makes money; this tab tells you whether you have cash left to get to the end of the month. It is the first one a lender looks at.
A4: Item | B4: Month 1 | C4: Month 2 | D4: Month 3 | E4: Month 4 | F4: Month 5 | G4: Month 6 | H4: Month 7 | I4: Month 8 | J4: Month 9 | K4: Month 10 | L4: Month 11 | M4: Month 12 | N4: Year
A5: Monthly seasonality (adds up to 100%) | B5: 0.05 | C5: 0.075 | D5: 0.1 | E5: 0.135 | F5: 0.165 | G5: 0.15 | H5: 0.11 | I5: 0.065 | J5: 0.035 | K5: 0.06 | L5: 0.025 | M5: 0.03 | N5: =IFERROR(IF('3-Year P&L'!$B$9="","",SUM(B5:M5)),"") -> 1 | O5: Month 1 = MARCH: open in season so the first winter is paid by the first summer. July (Month 5, National Ice Cream Month) is the peak; January (Month 11) the low point, with a three-week closure. Kit weights for a mid-size US city: replace the weights with your area's pattern (colder states: more weight June-August; Sun Belt: flatter). If you open in another month, rotate the row. It must add up to 100%
A6: Launch ramp-up (% of steady-state activity) | B6: =IFERROR(IF('3-Year P&L'!$B$9="","",MIN(1,'0. Assumptions'!$B$52+(1-'0. Assumptions'!$B$52)*0/MAX(1,'0. Assumptions'!$B$53-1))),"") -> 0.7 | C6: =IFERROR(IF('3-Year P&L'!$B$9="","",MIN(1,'0. Assumptions'!$B$52+(1-'0. Assumptions'!$B$52)*1/MAX(1,'0. Assumptions'!$B$53-1))),"") -> 0.8 | D6: =IFERROR(IF('3-Year P&L'!$B$9="","",MIN(1,'0. Assumptions'!$B$52+(1-'0. Assumptions'!$B$52)*2/MAX(1,'0. Assumptions'!$B$53-1))),"") -> 0.9 | E6: =IFERROR(IF('3-Year P&L'!$B$9="","",MIN(1,'0. Assumptions'!$B$52+(1-'0. Assumptions'!$B$52)*3/MAX(1,'0. Assumptions'!$B$53-1))),"") -> 1 | F6: =IFERROR(IF('3-Year P&L'!$B$9="","",MIN(1,'0. Assumptions'!$B$52+(1-'0. Assumptions'!$B$52)*4/MAX(1,'0. Assumptions'!$B$53-1))),"") -> 1 | G6: =IFERROR(IF('3-Year P&L'!$B$9="","",MIN(1,'0. Assumptions'!$B$52+(1-'0. Assumptions'!$B$52)*5/MAX(1,'0. Assumptions'!$B$53-1))),"") -> 1 | H6: =IFERROR(IF('3-Year P&L'!$B$9="","",MIN(1,'0. Assumptions'!$B$52+(1-'0. Assumptions'!$B$52)*6/MAX(1,'0. Assumptions'!$B$53-1))),"") -> 1 | I6: =IFERROR(IF('3-Year P&L'!$B$9="","",MIN(1,'0. Assumptions'!$B$52+(1-'0. Assumptions'!$B$52)*7/MAX(1,'0. Assumptions'!$B$53-1))),"") -> 1 | J6: =IFERROR(IF('3-Year P&L'!$B$9="","",MIN(1,'0. Assumptions'!$B$52+(1-'0. Assumptions'!$B$52)*8/MAX(1,'0. Assumptions'!$B$53-1))),"") -> 1 | K6: =IFERROR(IF('3-Year P&L'!$B$9="","",MIN(1,'0. Assumptions'!$B$52+(1-'0. Assumptions'!$B$52)*9/MAX(1,'0. Assumptions'!$B$53-1))),"") -> 1 | L6: =IFERROR(IF('3-Year P&L'!$B$9="","",MIN(1,'0. Assumptions'!$B$52+(1-'0. Assumptions'!$B$52)*10/MAX(1,'0. Assumptions'!$B$53-1))),"") -> 1 | M6: =IFERROR(IF('3-Year P&L'!$B$9="","",MIN(1,'0. Assumptions'!$B$52+(1-'0. Assumptions'!$B$52)*11/MAX(1,'0. Assumptions'!$B$53-1))),"") -> 1 | O6: Rises in a straight line from the month-1 percentage to 100% over the number of months you set in Assumptions. With month 1 at 100%, the ramp disappears
A7: Split of activity by month (calculated) | B7: =IFERROR(IF('3-Year P&L'!$B$9="","",B5*B6/SUMPRODUCT($B$5:$M$5,$B$6:$M$6)),"") -> 0.036458333 | C7: =IFERROR(IF('3-Year P&L'!$B$9="","",C5*C6/SUMPRODUCT($B$5:$M$5,$B$6:$M$6)),"") -> 0.0625 | D7: =IFERROR(IF('3-Year P&L'!$B$9="","",D5*D6/SUMPRODUCT($B$5:$M$5,$B$6:$M$6)),"") -> 0.09375 | E7: =IFERROR(IF('3-Year P&L'!$B$9="","",E5*E6/SUMPRODUCT($B$5:$M$5,$B$6:$M$6)),"") -> 0.140625 | F7: =IFERROR(IF('3-Year P&L'!$B$9="","",F5*F6/SUMPRODUCT($B$5:$M$5,$B$6:$M$6)),"") -> 0.171875 | G7: =IFERROR(IF('3-Year P&L'!$B$9="","",G5*G6/SUMPRODUCT($B$5:$M$5,$B$6:$M$6)),"") -> 0.15625 | H7: =IFERROR(IF('3-Year P&L'!$B$9="","",H5*H6/SUMPRODUCT($B$5:$M$5,$B$6:$M$6)),"") -> 0.11458333 | I7: =IFERROR(IF('3-Year P&L'!$B$9="","",I5*I6/SUMPRODUCT($B$5:$M$5,$B$6:$M$6)),"") -> 0.067708333 | ... M7: =IFERROR(IF('3-Year P&L'!$B$9="","",M5*M6/SUMPRODUCT($B$5:$M$5,$B$6:$M$6)),"") -> 0.03125 | N7: =IFERROR(IF('3-Year P&L'!$B$9="","",SUM(B7:M7)),"") -> 1 | O7: Seasonality × ramp-up, normalized to 100%: the YEAR brings in what the P&L says, but split the way a business that has just opened would split it
A8: CASH IN
A9: Sales collected (incl. sales tax collected) | B9: =IFERROR(IF('3-Year P&L'!$B$9="","",('3-Year P&L'!$B$9+'3-Year P&L'!$B$9*SUMPRODUCT('3-Year P&L'!$E$10:$E$11,'3-Year P&L'!$G$10:$G$11))*B7*(1-MIN(30,'0. Assumptions'!$B$58)/30)),"") -> 14098.219 | C9: =IFERROR(IF('3-Year P&L'!$B$9="","",('3-Year P&L'!$B$9+'3-Year P&L'!$B$9*SUMPRODUCT('3-Year P&L'!$E$10:$E$11,'3-Year P&L'!$G$10:$G$11))*(C7*(1-MIN(30,'0. Assumptions'!$B$58)/30)+B7*MIN(30,'0. Assumptions'!$B$58)/30)),"") -> 25175.391 | D9: =IFERROR(IF('3-Year P&L'!$B$9="","",('3-Year P&L'!$B$9+'3-Year P&L'!$B$9*SUMPRODUCT('3-Year P&L'!$E$10:$E$11,'3-Year P&L'!$G$10:$G$11))*(D7*(1-MIN(30,'0. Assumptions'!$B$58)/30)+C7*MIN(30,'0. Assumptions'!$B$58)/30)),"") -> 37978.875 | E9: =IFERROR(IF('3-Year P&L'!$B$9="","",('3-Year P&L'!$B$9+'3-Year P&L'!$B$9*SUMPRODUCT('3-Year P&L'!$E$10:$E$11,'3-Year P&L'!$G$10:$G$11))*(E7*(1-MIN(30,'0. Assumptions'!$B$58)/30)+D7*MIN(30,'0. Assumptions'!$B$58)/30)),"") -> 56968.313 | F9: =IFERROR(IF('3-Year P&L'!$B$9="","",('3-Year P&L'!$B$9+'3-Year P&L'!$B$9*SUMPRODUCT('3-Year P&L'!$E$10:$E$11,'3-Year P&L'!$G$10:$G$11))*(F7*(1-MIN(30,'0. Assumptions'!$B$58)/30)+E7*MIN(30,'0. Assumptions'!$B$58)/30)),"") -> 70347.234 | G9: =IFERROR(IF('3-Year P&L'!$B$9="","",('3-Year P&L'!$B$9+'3-Year P&L'!$B$9*SUMPRODUCT('3-Year P&L'!$E$10:$E$11,'3-Year P&L'!$G$10:$G$11))*(G7*(1-MIN(30,'0. Assumptions'!$B$58)/30)+F7*MIN(30,'0. Assumptions'!$B$58)/30)),"") -> 65168.297 | H9: =IFERROR(IF('3-Year P&L'!$B$9="","",('3-Year P&L'!$B$9+'3-Year P&L'!$B$9*SUMPRODUCT('3-Year P&L'!$E$10:$E$11,'3-Year P&L'!$G$10:$G$11))*(H7*(1-MIN(30,'0. Assumptions'!$B$58)/30)+G7*MIN(30,'0. Assumptions'!$B$58)/30)),"") -> 48624.469 | I9: =IFERROR(IF('3-Year P&L'!$B$9="","",('3-Year P&L'!$B$9+'3-Year P&L'!$B$9*SUMPRODUCT('3-Year P&L'!$E$10:$E$11,'3-Year P&L'!$G$10:$G$11))*(I7*(1-MIN(30,'0. Assumptions'!$B$58)/30)+H7*MIN(30,'0. Assumptions'!$B$58)/30)),"") -> 29347.312 | J9: =IFERROR(IF('3-Year P&L'!$B$9="","",('3-Year P&L'!$B$9+'3-Year P&L'!$B$9*SUMPRODUCT('3-Year P&L'!$E$10:$E$11,'3-Year P&L'!$G$10:$G$11))*(J7*(1-MIN(30,'0. Assumptions'!$B$58)/30)+I7*MIN(30,'0. Assumptions'!$B$58)/30)),"") -> 15968.391 | ... M9: =IFERROR(IF('3-Year P&L'!$B$9="","",('3-Year P&L'!$B$9+'3-Year P&L'!$B$9*SUMPRODUCT('3-Year P&L'!$E$10:$E$11,'3-Year P&L'!$G$10:$G$11))*(M7*(1-MIN(30,'0. Assumptions'!$B$58)/30)+L7*MIN(30,'0. Assumptions'!$B$58)/30)),"") -> 12803.484 | N9: =IFERROR(IF('3-Year P&L'!$B$9="","",SUM(B9:M9)),"") -> 413451.84 | O9: The month's sales plus the sales tax collected, adjusted by the average collection days from the Assumptions tab
A10: CASH OUT
A11: Purchases and variable costs (incl. sales tax) | B11: =IFERROR(IF('3-Year P&L'!$B$9="","",-('3-Year P&L'!$B$13*(1+'3-Year P&L'!$G$13)+'3-Year P&L'!$B$14*(1+'3-Year P&L'!$G$14)+'3-Year P&L'!$B$15*(1+'3-Year P&L'!$G$15)+'3-Year P&L'!$B$16*(1+'3-Year P&L'!$G$16)+'3-Year P&L'!$B$17*(1+'3-Year P&L'!$G$17)+'3-Year P&L'!$B$18*(1+'3-Year P&L'!$G$18))*B7*(1-MIN(30,'0. Assumptions'!$B$59)/30)),"") -> -2372.0812 | C11: =IFERROR(IF('3-Year P&L'!$B$9="","",-('3-Year P&L'!$B$13*(1+'3-Year P&L'!$G$13)+'3-Year P&L'!$B$14*(1+'3-Year P&L'!$G$14)+'3-Year P&L'!$B$15*(1+'3-Year P&L'!$G$15)+'3-Year P&L'!$B$16*(1+'3-Year P&L'!$G$16)+'3-Year P&L'!$B$17*(1+'3-Year P&L'!$G$17)+'3-Year P&L'!$B$18*(1+'3-Year P&L'!$G$18))*(C7*(1-MIN(30,'0. Assumptions'!$B$59)/30)+B7*MIN(30,'0. Assumptions'!$B$59)/30)),"") -> -6141.9961 | D11: =IFERROR(IF('3-Year P&L'!$B$9="","",-('3-Year P&L'!$B$13*(1+'3-Year P&L'!$G$13)+'3-Year P&L'!$B$14*(1+'3-Year P&L'!$G$14)+'3-Year P&L'!$B$15*(1+'3-Year P&L'!$G$15)+'3-Year P&L'!$B$16*(1+'3-Year P&L'!$G$16)+'3-Year P&L'!$B$17*(1+'3-Year P&L'!$G$17)+'3-Year P&L'!$B$18*(1+'3-Year P&L'!$G$18))*(D7*(1-MIN(30,'0. Assumptions'!$B$59)/30)+C7*MIN(30,'0. Assumptions'!$B$59)/30)),"") -> -9657.7594 | E11: =IFERROR(IF('3-Year P&L'!$B$9="","",-('3-Year P&L'!$B$13*(1+'3-Year P&L'!$G$13)+'3-Year P&L'!$B$14*(1+'3-Year P&L'!$G$14)+'3-Year P&L'!$B$15*(1+'3-Year P&L'!$G$15)+'3-Year P&L'!$B$16*(1+'3-Year P&L'!$G$16)+'3-Year P&L'!$B$17*(1+'3-Year P&L'!$G$17)+'3-Year P&L'!$B$18*(1+'3-Year P&L'!$G$18))*(E7*(1-MIN(30,'0. Assumptions'!$B$59)/30)+D7*MIN(30,'0. Assumptions'!$B$59)/30)),"") -> -14486.639 | F11: =IFERROR(IF('3-Year P&L'!$B$9="","",-('3-Year P&L'!$B$13*(1+'3-Year P&L'!$G$13)+'3-Year P&L'!$B$14*(1+'3-Year P&L'!$G$14)+'3-Year P&L'!$B$15*(1+'3-Year P&L'!$G$15)+'3-Year P&L'!$B$16*(1+'3-Year P&L'!$G$16)+'3-Year P&L'!$B$17*(1+'3-Year P&L'!$G$17)+'3-Year P&L'!$B$18*(1+'3-Year P&L'!$G$18))*(F7*(1-MIN(30,'0. Assumptions'!$B$59)/30)+E7*MIN(30,'0. Assumptions'!$B$59)/30)),"") -> -19188.443 | G11: =IFERROR(IF('3-Year P&L'!$B$9="","",-('3-Year P&L'!$B$13*(1+'3-Year P&L'!$G$13)+'3-Year P&L'!$B$14*(1+'3-Year P&L'!$G$14)+'3-Year P&L'!$B$15*(1+'3-Year P&L'!$G$15)+'3-Year P&L'!$B$16*(1+'3-Year P&L'!$G$16)+'3-Year P&L'!$B$17*(1+'3-Year P&L'!$G$17)+'3-Year P&L'!$B$18*(1+'3-Year P&L'!$G$18))*(G7*(1-MIN(30,'0. Assumptions'!$B$59)/30)+F7*MIN(30,'0. Assumptions'!$B$59)/30)),"") -> -19950.898 | H11: =IFERROR(IF('3-Year P&L'!$B$9="","",-('3-Year P&L'!$B$13*(1+'3-Year P&L'!$G$13)+'3-Year P&L'!$B$14*(1+'3-Year P&L'!$G$14)+'3-Year P&L'!$B$15*(1+'3-Year P&L'!$G$15)+'3-Year P&L'!$B$16*(1+'3-Year P&L'!$G$16)+'3-Year P&L'!$B$17*(1+'3-Year P&L'!$G$17)+'3-Year P&L'!$B$18*(1+'3-Year P&L'!$G$18))*(H7*(1-MIN(30,'0. Assumptions'!$B$59)/30)+G7*MIN(30,'0. Assumptions'!$B$59)/30)),"") -> -16350.417 | I11: =IFERROR(IF('3-Year P&L'!$B$9="","",-('3-Year P&L'!$B$13*(1+'3-Year P&L'!$G$13)+'3-Year P&L'!$B$14*(1+'3-Year P&L'!$G$14)+'3-Year P&L'!$B$15*(1+'3-Year P&L'!$G$15)+'3-Year P&L'!$B$16*(1+'3-Year P&L'!$G$16)+'3-Year P&L'!$B$17*(1+'3-Year P&L'!$G$17)+'3-Year P&L'!$B$18*(1+'3-Year P&L'!$G$18))*(I7*(1-MIN(30,'0. Assumptions'!$B$59)/30)+H7*MIN(30,'0. Assumptions'!$B$59)/30)),"") -> -10928.517 | J11: =IFERROR(IF('3-Year P&L'!$B$9="","",-('3-Year P&L'!$B$13*(1+'3-Year P&L'!$G$13)+'3-Year P&L'!$B$14*(1+'3-Year P&L'!$G$14)+'3-Year P&L'!$B$15*(1+'3-Year P&L'!$G$15)+'3-Year P&L'!$B$16*(1+'3-Year P&L'!$G$16)+'3-Year P&L'!$B$17*(1+'3-Year P&L'!$G$17)+'3-Year P&L'!$B$18*(1+'3-Year P&L'!$G$18))*(J7*(1-MIN(30,'0. Assumptions'!$B$59)/30)+I7*MIN(30,'0. Assumptions'!$B$59)/30)),"") -> -6226.7133 | ... M11: =IFERROR(IF('3-Year P&L'!$B$9="","",-('3-Year P&L'!$B$13*(1+'3-Year P&L'!$G$13)+'3-Year P&L'!$B$14*(1+'3-Year P&L'!$G$14)+'3-Year P&L'!$B$15*(1+'3-Year P&L'!$G$15)+'3-Year P&L'!$B$16*(1+'3-Year P&L'!$G$16)+'3-Year P&L'!$B$17*(1+'3-Year P&L'!$G$17)+'3-Year P&L'!$B$18*(1+'3-Year P&L'!$G$18))*(M7*(1-MIN(30,'0. Assumptions'!$B$59)/30)+L7*MIN(30,'0. Assumptions'!$B$59)/30)),"") -> -3515.7633 | N11: =IFERROR(IF('3-Year P&L'!$B$9="","",SUM(B11:M11)),"") -> -120213.69 | O11: =IFERROR("Food and beverage purchases, consumables, fees and contingencies, each at ITS tax rate (column G of the P&L; 0 in the US, where the sales tax you pay is part of the cost) and with the supplier payment days from ""0. Assumptions""."&IF('0. Assumptions'!$B$59=0,""," With "&TEXT('0. Assumptions'!$B$59,"0")&" payment days, the last purchases of the year are paid next year: the ""Year"" column of this row holds "&TEXT(MAX(0,12-ROUNDUP('0. Assumptions'!$B$59/30,0)),"0")&" months of purchases, not the year's cost."),"") -> Food and beverage purchases, consumables, fees and contingencies, each at ITS tax rate (column G of the P&L; 0 in the US, where the sales tax you pay is part of the cost) and with the supplier payment days from "0. Assumptions". With 14 payment days, the last purchases of the year are paid next year: the "Year" column of this row holds 11 months of purchases, not the year's cost.
A12: Operating fixed costs (incl. sales tax) | B12: =IFERROR(IF('3-Year P&L'!$B$9="","",-('3-Year P&L'!$B$38-'3-Year P&L'!$B$23-'3-Year P&L'!$B$36-'3-Year P&L'!$B$37+'3-Year P&L'!$B$40)/12),"") -> -5558.3333 | C12: =IFERROR(IF('3-Year P&L'!$B$9="","",-('3-Year P&L'!$B$38-'3-Year P&L'!$B$23-'3-Year P&L'!$B$36-'3-Year P&L'!$B$37+'3-Year P&L'!$B$40)/12),"") -> -5558.3333 | D12: =IFERROR(IF('3-Year P&L'!$B$9="","",-('3-Year P&L'!$B$38-'3-Year P&L'!$B$23-'3-Year P&L'!$B$36-'3-Year P&L'!$B$37+'3-Year P&L'!$B$40)/12),"") -> -5558.3333 | E12: =IFERROR(IF('3-Year P&L'!$B$9="","",-('3-Year P&L'!$B$38-'3-Year P&L'!$B$23-'3-Year P&L'!$B$36-'3-Year P&L'!$B$37+'3-Year P&L'!$B$40)/12),"") -> -5558.3333 | F12: =IFERROR(IF('3-Year P&L'!$B$9="","",-('3-Year P&L'!$B$38-'3-Year P&L'!$B$23-'3-Year P&L'!$B$36-'3-Year P&L'!$B$37+'3-Year P&L'!$B$40)/12),"") -> -5558.3333 | G12: =IFERROR(IF('3-Year P&L'!$B$9="","",-('3-Year P&L'!$B$38-'3-Year P&L'!$B$23-'3-Year P&L'!$B$36-'3-Year P&L'!$B$37+'3-Year P&L'!$B$40)/12),"") -> -5558.3333 | H12: =IFERROR(IF('3-Year P&L'!$B$9="","",-('3-Year P&L'!$B$38-'3-Year P&L'!$B$23-'3-Year P&L'!$B$36-'3-Year P&L'!$B$37+'3-Year P&L'!$B$40)/12),"") -> -5558.3333 | I12: =IFERROR(IF('3-Year P&L'!$B$9="","",-('3-Year P&L'!$B$38-'3-Year P&L'!$B$23-'3-Year P&L'!$B$36-'3-Year P&L'!$B$37+'3-Year P&L'!$B$40)/12),"") -> -5558.3333 | ... M12: =IFERROR(IF('3-Year P&L'!$B$9="","",-('3-Year P&L'!$B$38-'3-Year P&L'!$B$23-'3-Year P&L'!$B$36-'3-Year P&L'!$B$37+'3-Year P&L'!$B$40)/12),"") -> -5558.3333 | N12: =IFERROR(IF('3-Year P&L'!$B$9="","",SUM(B12:M12)),"") -> -66700 | O12: The fixed costs that leave cash, each with its own tax rate: insurance carries none
A13: Payroll and employer payroll taxes | B13: =IFERROR(IF('3-Year P&L'!$B$9="","",-'3-Year P&L'!$B$23/MAX(12,'0. Assumptions'!$B$21)*(1+IF(1='0. Assumptions'!$B$60,(MAX(12,'0. Assumptions'!$B$21)-12)/2,0)+IF(1='0. Assumptions'!$B$61,(MAX(12,'0. Assumptions'!$B$21)-12)/2,0))),"") -> -10682.1 | C13: =IFERROR(IF('3-Year P&L'!$B$9="","",-'3-Year P&L'!$B$23/MAX(12,'0. Assumptions'!$B$21)*(1+IF(2='0. Assumptions'!$B$60,(MAX(12,'0. Assumptions'!$B$21)-12)/2,0)+IF(2='0. Assumptions'!$B$61,(MAX(12,'0. Assumptions'!$B$21)-12)/2,0))),"") -> -10682.1 | D13: =IFERROR(IF('3-Year P&L'!$B$9="","",-'3-Year P&L'!$B$23/MAX(12,'0. Assumptions'!$B$21)*(1+IF(3='0. Assumptions'!$B$60,(MAX(12,'0. Assumptions'!$B$21)-12)/2,0)+IF(3='0. Assumptions'!$B$61,(MAX(12,'0. Assumptions'!$B$21)-12)/2,0))),"") -> -10682.1 | E13: =IFERROR(IF('3-Year P&L'!$B$9="","",-'3-Year P&L'!$B$23/MAX(12,'0. Assumptions'!$B$21)*(1+IF(4='0. Assumptions'!$B$60,(MAX(12,'0. Assumptions'!$B$21)-12)/2,0)+IF(4='0. Assumptions'!$B$61,(MAX(12,'0. Assumptions'!$B$21)-12)/2,0))),"") -> -10682.1 | F13: =IFERROR(IF('3-Year P&L'!$B$9="","",-'3-Year P&L'!$B$23/MAX(12,'0. Assumptions'!$B$21)*(1+IF(5='0. Assumptions'!$B$60,(MAX(12,'0. Assumptions'!$B$21)-12)/2,0)+IF(5='0. Assumptions'!$B$61,(MAX(12,'0. Assumptions'!$B$21)-12)/2,0))),"") -> -10682.1 | G13: =IFERROR(IF('3-Year P&L'!$B$9="","",-'3-Year P&L'!$B$23/MAX(12,'0. Assumptions'!$B$21)*(1+IF(6='0. Assumptions'!$B$60,(MAX(12,'0. Assumptions'!$B$21)-12)/2,0)+IF(6='0. Assumptions'!$B$61,(MAX(12,'0. Assumptions'!$B$21)-12)/2,0))),"") -> -10682.1 | H13: =IFERROR(IF('3-Year P&L'!$B$9="","",-'3-Year P&L'!$B$23/MAX(12,'0. Assumptions'!$B$21)*(1+IF(7='0. Assumptions'!$B$60,(MAX(12,'0. Assumptions'!$B$21)-12)/2,0)+IF(7='0. Assumptions'!$B$61,(MAX(12,'0. Assumptions'!$B$21)-12)/2,0))),"") -> -10682.1 | I13: =IFERROR(IF('3-Year P&L'!$B$9="","",-'3-Year P&L'!$B$23/MAX(12,'0. Assumptions'!$B$21)*(1+IF(8='0. Assumptions'!$B$60,(MAX(12,'0. Assumptions'!$B$21)-12)/2,0)+IF(8='0. Assumptions'!$B$61,(MAX(12,'0. Assumptions'!$B$21)-12)/2,0))),"") -> -10682.1 | J13: =IFERROR(IF('3-Year P&L'!$B$9="","",-'3-Year P&L'!$B$23/MAX(12,'0. Assumptions'!$B$21)*(1+IF(9='0. Assumptions'!$B$60,(MAX(12,'0. Assumptions'!$B$21)-12)/2,0)+IF(9='0. Assumptions'!$B$61,(MAX(12,'0. Assumptions'!$B$21)-12)/2,0))),"") -> -10682.1 | K13: =IFERROR(IF('3-Year P&L'!$B$9="","",-'3-Year P&L'!$B$23/MAX(12,'0. Assumptions'!$B$21)*(1+IF(10='0. Assumptions'!$B$60,(MAX(12,'0. Assumptions'!$B$21)-12)/2,0)+IF(10='0. Assumptions'!$B$61,(MAX(12,'0. Assumptions'!$B$21)-12)/2,0))),"") -> -10682.1 | L13: =IFERROR(IF('3-Year P&L'!$B$9="","",-'3-Year P&L'!$B$23/MAX(12,'0. Assumptions'!$B$21)*(1+IF(11='0. Assumptions'!$B$60,(MAX(12,'0. Assumptions'!$B$21)-12)/2,0)+IF(11='0. Assumptions'!$B$61,(MAX(12,'0. Assumptions'!$B$21)-12)/2,0))),"") -> -10682.1 | M13: =IFERROR(IF('3-Year P&L'!$B$9="","",-'3-Year P&L'!$B$23/MAX(12,'0. Assumptions'!$B$21)*(1+IF(12='0. Assumptions'!$B$60,(MAX(12,'0. Assumptions'!$B$21)-12)/2,0)+IF(12='0. Assumptions'!$B$61,(MAX(12,'0. Assumptions'!$B$21)-12)/2,0))),"") -> -10682.1 | N13: =IFERROR(IF('3-Year P&L'!$B$9="","",SUM(B13:M13)),"") -> -128185.2 | O13: Twelve monthly payments, with no extra pay months unless you enter more than 12 pay periods on "0. Assumptions". The yearly total matches the P&L. Payroll is spread over twelve months, but seasonal staff only get paid in season, so winter shows up more expensive and summer cheaper than reality: that is the prudent side. March and February barely change, but from June to January your real cash will be lower than on this tab (in the case, by about $13,800 at the end of September)
A14: Loan interest | B14: =IFERROR(IF('3-Year P&L'!$B$9="","",-Financing!$B$44/12),"") -> -1350 | C14: =IFERROR(IF('3-Year P&L'!$B$9="","",-Financing!$B$44/12),"") -> -1350 | D14: =IFERROR(IF('3-Year P&L'!$B$9="","",-Financing!$B$44/12),"") -> -1350 | E14: =IFERROR(IF('3-Year P&L'!$B$9="","",-Financing!$B$44/12),"") -> -1350 | F14: =IFERROR(IF('3-Year P&L'!$B$9="","",-Financing!$B$44/12),"") -> -1350 | G14: =IFERROR(IF('3-Year P&L'!$B$9="","",-Financing!$B$44/12),"") -> -1350 | H14: =IFERROR(IF('3-Year P&L'!$B$9="","",-Financing!$B$44/12),"") -> -1350 | I14: =IFERROR(IF('3-Year P&L'!$B$9="","",-Financing!$B$44/12),"") -> -1350 | ... M14: =IFERROR(IF('3-Year P&L'!$B$9="","",-Financing!$B$44/12),"") -> -1350 | N14: =IFERROR(IF('3-Year P&L'!$B$9="","",SUM(B14:M14)),"") -> -16200
A15: Loan principal repaid | B15: =IFERROR(IF('3-Year P&L'!$B$9="","",-Financing!$B$45/12),"") -> -847.06283 | C15: =IFERROR(IF('3-Year P&L'!$B$9="","",-Financing!$B$45/12),"") -> -847.06283 | D15: =IFERROR(IF('3-Year P&L'!$B$9="","",-Financing!$B$45/12),"") -> -847.06283 | E15: =IFERROR(IF('3-Year P&L'!$B$9="","",-Financing!$B$45/12),"") -> -847.06283 | F15: =IFERROR(IF('3-Year P&L'!$B$9="","",-Financing!$B$45/12),"") -> -847.06283 | G15: =IFERROR(IF('3-Year P&L'!$B$9="","",-Financing!$B$45/12),"") -> -847.06283 | H15: =IFERROR(IF('3-Year P&L'!$B$9="","",-Financing!$B$45/12),"") -> -847.06283 | I15: =IFERROR(IF('3-Year P&L'!$B$9="","",-Financing!$B$45/12),"") -> -847.06283 | ... M15: =IFERROR(IF('3-Year P&L'!$B$9="","",-Financing!$B$45/12),"") -> -847.06283 | N15: =IFERROR(IF('3-Year P&L'!$B$9="","",SUM(B15:M15)),"") -> -10164.754
A16: Sales tax collected (memo) | B16: =IFERROR(IF('3-Year P&L'!$B$9="","",'3-Year P&L'!$B$9*B7*SUMPRODUCT('3-Year P&L'!$E$10:$E$11,'3-Year P&L'!$G$10:$G$11)),"") -> 1118.9062 | C16: =IFERROR(IF('3-Year P&L'!$B$9="","",'3-Year P&L'!$B$9*C7*SUMPRODUCT('3-Year P&L'!$E$10:$E$11,'3-Year P&L'!$G$10:$G$11)),"") -> 1918.125 | D16: =IFERROR(IF('3-Year P&L'!$B$9="","",'3-Year P&L'!$B$9*D7*SUMPRODUCT('3-Year P&L'!$E$10:$E$11,'3-Year P&L'!$G$10:$G$11)),"") -> 2877.1875 | E16: =IFERROR(IF('3-Year P&L'!$B$9="","",'3-Year P&L'!$B$9*E7*SUMPRODUCT('3-Year P&L'!$E$10:$E$11,'3-Year P&L'!$G$10:$G$11)),"") -> 4315.7812 | F16: =IFERROR(IF('3-Year P&L'!$B$9="","",'3-Year P&L'!$B$9*F7*SUMPRODUCT('3-Year P&L'!$E$10:$E$11,'3-Year P&L'!$G$10:$G$11)),"") -> 5274.8438 | G16: =IFERROR(IF('3-Year P&L'!$B$9="","",'3-Year P&L'!$B$9*G7*SUMPRODUCT('3-Year P&L'!$E$10:$E$11,'3-Year P&L'!$G$10:$G$11)),"") -> 4795.3125 | H16: =IFERROR(IF('3-Year P&L'!$B$9="","",'3-Year P&L'!$B$9*H7*SUMPRODUCT('3-Year P&L'!$E$10:$E$11,'3-Year P&L'!$G$10:$G$11)),"") -> 3516.5625 | I16: =IFERROR(IF('3-Year P&L'!$B$9="","",'3-Year P&L'!$B$9*I7*SUMPRODUCT('3-Year P&L'!$E$10:$E$11,'3-Year P&L'!$G$10:$G$11)),"") -> 2077.9688 | ... M16: =IFERROR(IF('3-Year P&L'!$B$9="","",'3-Year P&L'!$B$9*M7*SUMPRODUCT('3-Year P&L'!$E$10:$E$11,'3-Year P&L'!$G$10:$G$11)),"") -> 959.0625 | N16: =IFERROR(IF('3-Year P&L'!$B$9="","",SUM(B16:M16)),"") -> 30690 | O16: Each sales line at ITS rate, read from the sales tax column of the P&L: one example rate for the whole book. Prepared food is taxed at the counter, on the patio and to go; packaged pints and whole cakes may be exempt as groceries in some states, so check yours
A17: Recoverable input tax (memo) | B17: =IFERROR(IF('3-Year P&L'!$B$9="","",'3-Year P&L'!$B$39*B7+'3-Year P&L'!$B$40/12),"") -> 0 | C17: =IFERROR(IF('3-Year P&L'!$B$9="","",'3-Year P&L'!$B$39*C7+'3-Year P&L'!$B$40/12),"") -> 0 | D17: =IFERROR(IF('3-Year P&L'!$B$9="","",'3-Year P&L'!$B$39*D7+'3-Year P&L'!$B$40/12),"") -> 0 | E17: =IFERROR(IF('3-Year P&L'!$B$9="","",'3-Year P&L'!$B$39*E7+'3-Year P&L'!$B$40/12),"") -> 0 | F17: =IFERROR(IF('3-Year P&L'!$B$9="","",'3-Year P&L'!$B$39*F7+'3-Year P&L'!$B$40/12),"") -> 0 | G17: =IFERROR(IF('3-Year P&L'!$B$9="","",'3-Year P&L'!$B$39*G7+'3-Year P&L'!$B$40/12),"") -> 0 | H17: =IFERROR(IF('3-Year P&L'!$B$9="","",'3-Year P&L'!$B$39*H7+'3-Year P&L'!$B$40/12),"") -> 0 | I17: =IFERROR(IF('3-Year P&L'!$B$9="","",'3-Year P&L'!$B$39*I7+'3-Year P&L'!$B$40/12),"") -> 0 | ... M17: =IFERROR(IF('3-Year P&L'!$B$9="","",'3-Year P&L'!$B$39*M7+'3-Year P&L'!$B$40/12),"") -> 0 | N17: =IFERROR(IF('3-Year P&L'!$B$9="","",SUM(B17:M17)),"") -> 0 | O17: Each item at its own rate, read from the tax column of the P&L: insurance and card processing fees carry none
A18: Carried forward (capex input tax included) | E18: =IFERROR(IF('3-Year P&L'!$B$9="","",'Startup Costs'!$B$33),"") -> 0 | H18: =IFERROR(IF('3-Year P&L'!$B$9="","",MAX(0,-E19)),"") -> 0 | K18: =IFERROR(IF('3-Year P&L'!$B$9="","",MAX(0,-H19)),"") -> 0 | O18: Sales tax paid on STARTUP COSTS enters here: it is offset against the tax collected in later quarters until used up. With 0% recoverable input tax (the US default) this line stays at zero
A19: Quarterly sales tax return | E19: =IFERROR(IF('3-Year P&L'!$B$9="","",SUM(B16:D16)-SUM(B17:D17)-E18),"") -> 5914.2188 | H19: =IFERROR(IF('3-Year P&L'!$B$9="","",SUM(E16:G16)-SUM(E17:G17)-H18),"") -> 14385.938 | K19: =IFERROR(IF('3-Year P&L'!$B$9="","",SUM(H16:J16)-SUM(H17:J17)-K18),"") -> 6713.4375 | O19: Sales tax collected minus recoverable input tax for the quarter, minus what was carried forward. If negative, nothing is paid: it is offset in the next quarter. With 0% recoverable input tax (the US default) it equals the sales tax collected in the quarter
A20: Sales tax remitted (quarterly filer) | E20: =IFERROR(IF('3-Year P&L'!$B$9="","",IF(E19<=0,"",-E19)),"") -> -5914.2188 | H20: =IFERROR(IF('3-Year P&L'!$B$9="","",IF(H19<=0,"",-H19)),"") -> -14385.938 | K20: =IFERROR(IF('3-Year P&L'!$B$9="","",IF(K19<=0,"",-K19)),"") -> -6713.4375 | N20: =IFERROR(IF('3-Year P&L'!$B$9="","",SUM(B20:M20)),"") -> -27013.594 | O20: Cash only leaves when the quarter's result is positive. Months without a settlement are left blank, not zero. The cell turns RED when the payment takes more cash than is left that month. The model settles quarterly, in the month after each plan quarter (Months 4, 7 and 10: June, September and December with Month 1 in March; the fourth quarter is remitted in Month 13): if your state requires monthly filing, expect smaller payments every month instead
A21: MONTHLY NET CASH FLOW | B21: =IFERROR(IF('3-Year P&L'!$B$9="","",SUM(B9:B15)+IF(B20="",0,B20)),"") -> -6711.3587 | C21: =IFERROR(IF('3-Year P&L'!$B$9="","",SUM(C9:C15)+IF(C20="",0,C20)),"") -> 595.89837 | D21: =IFERROR(IF('3-Year P&L'!$B$9="","",SUM(D9:D15)+IF(D20="",0,D20)),"") -> 9883.6195 | E21: =IFERROR(IF('3-Year P&L'!$B$9="","",SUM(E9:E15)+IF(E20="",0,E20)),"") -> 18129.959 | F21: =IFERROR(IF('3-Year P&L'!$B$9="","",SUM(F9:F15)+IF(F20="",0,F20)),"") -> 32721.295 | G21: =IFERROR(IF('3-Year P&L'!$B$9="","",SUM(G9:G15)+IF(G20="",0,G20)),"") -> 26779.903 | H21: =IFERROR(IF('3-Year P&L'!$B$9="","",SUM(H9:H15)+IF(H20="",0,H20)),"") -> -549.3821 | I21: =IFERROR(IF('3-Year P&L'!$B$9="","",SUM(I9:I15)+IF(I20="",0,I20)),"") -> -18.700852 | ... M21: =IFERROR(IF('3-Year P&L'!$B$9="","",SUM(M9:M15)+IF(M20="",0,M20)),"") -> -9149.7751 | N21: =IFERROR(IF('3-Year P&L'!$B$9="","",SUM(B21:M21)),"") -> 44974.607
A22: CUMULATIVE CASH BALANCE | B22: =IFERROR(IF('3-Year P&L'!$B$9="","",'Startup Costs'!$B$30+B21),"") -> 46059.941 | C22: =IFERROR(IF('3-Year P&L'!$B$9="","",B22+C21),"") -> 46655.84 | D22: =IFERROR(IF('3-Year P&L'!$B$9="","",C22+D21),"") -> 56539.459 | E22: =IFERROR(IF('3-Year P&L'!$B$9="","",D22+E21),"") -> 74669.418 | F22: =IFERROR(IF('3-Year P&L'!$B$9="","",E22+F21),"") -> 107390.71 | G22: =IFERROR(IF('3-Year P&L'!$B$9="","",F22+G21),"") -> 134170.62 | H22: =IFERROR(IF('3-Year P&L'!$B$9="","",G22+H21),"") -> 133621.23 | I22: =IFERROR(IF('3-Year P&L'!$B$9="","",H22+I21),"") -> 133602.53 | J22: =IFERROR(IF('3-Year P&L'!$B$9="","",I22+J21),"") -> 124906.71 | ... M22: =IFERROR(IF('3-Year P&L'!$B$9="","",L22+M21),"") -> 97745.907
A23: Minimum balance of the year | B23: =IFERROR(IF('3-Year P&L'!$B$9="","",IF(COUNT(B22:M22)=0,"",MIN(B22:M22))),"") -> 46059.941 | D23: If negative, raise working capital or the loan: you run out of cash
A24: Month when cash bottoms out | B24: =IFERROR(IF('3-Year P&L'!$B$9="","",IF(COUNT(B22:M22)=0,"",MATCH(MIN(B22:M22),B22:M22,0))),"") -> 1 | D24: It answers the question that decides a bank deal: in which month the cash runs out
A25: RETURN ON INVESTMENT
A26: Free cash flow before debt, year 1 | B26: =IFERROR(IF('3-Year P&L'!$B$9="","",'3-Year P&L'!$B$48+'3-Year P&L'!$B$36+Financing!$B$44),"") -> 59552.073 | D26: Net income plus depreciation (which is not paid) plus that year's interest: principal is not subtracted because this flow is BEFORE debt. The SAME basis as years 2 and 3, so the payback compares like with like
A27: Free cash flow before debt, year 2 | B27: =IFERROR(IF('3-Year P&L'!$B$9="","",'3-Year P&L'!$C$48+'3-Year P&L'!$C$36+Financing!$B$46),"") -> 68995.889 | D27: Net income plus depreciation (which is not paid) plus that year's interest: principal is not subtracted because this flow is BEFORE debt. Without a monthly table, it is an estimate
A28: Free cash flow before debt, year 3 | B28: =IFERROR(IF('3-Year P&L'!$B$9="","",'3-Year P&L'!$D$48+'3-Year P&L'!$D$36+Financing!$B$48),"") -> 73312.465 | D28: Net income plus depreciation (which is not paid) plus that year's interest: principal is not subtracted because this flow is BEFORE debt. Without a monthly table, it is an estimate
A29: For reference: ACTUAL year-1 cash flow (monthly table, before debt) | B29: =IFERROR(IF('3-Year P&L'!$B$9="","",N21+Financing!$B$44+Financing!$B$45),"") -> 71339.361 | D29: The sum of the twelve monthly net cash flows above, adding back the interest and principal paid that year. It is NOT the one the payback uses: it includes sales tax not yet settled and supplier credit, two things that have to be paid back and that years 2 and 3 do not have
A30: Investment to recover (net of recoverable input tax) | B30: =IFERROR(IF('3-Year P&L'!$B$9="","",'Startup Costs'!$B$34-'Startup Costs'!$B$33),"") -> 256871.3 | D30: CAPEX plus working capital: the total cash needed MINUS the recoverable input tax on startup costs, which is not lost (it is recovered through the quarterly return, and this tab offsets it quarter by quarter; it is zero in the US default). Working capital is recovered when you close, but until then it is tied up
A31: Project payback (years), before debt | B31: =IFERROR(IF('3-Year P&L'!$B$9="","",IF(B26>=B30,ROUND(B30/B26,1),IF(B26+B27>=B30,ROUND(1+(B30-B26)/B27,1),IF(B26+B27+B28>=B30,ROUND(2+(B30-B26-B27)/B28,1),"Over 3 years")))),"") -> Over 3 years | D31: Measures how long the business takes to pay back the investment with what it generates BEFORE paying the lender, on the SAME cash flow basis in all three years; whether you can make the loan payment is answered by the DSCR on the "Financing" tab. The Word business plan quotes this figure; if you change a green cell, this workbook rules
A32: Payback on CAPEX, excluding working capital (years) | B32: =IFERROR(IF('3-Year P&L'!$B$9="","",IF(B26>='Startup Costs'!$B$32,ROUND('Startup Costs'!$B$32/B26,1),IF(B26+B27>='Startup Costs'!$B$32,ROUND(1+('Startup Costs'!$B$32-B26)/B27,1),IF(B26+B27+B28>='Startup Costs'!$B$32,ROUND(2+('Startup Costs'!$B$32-B26-B27)/B28,1),"Over 3 years")))),"") -> Over 3 years | D32: The same calculation on what you BUY (build-out, equipment, launch and formation costs), without working capital: that money is not spent, it is tied up and comes back when the business closes. For reference only: the payback that matters is the one above
A34: The quarters in this sheet are plan quarters, not calendar quarters (March-May, June-August, September-November and December-February): with Month 1 in March, the workbook remits the sales tax of each plan quarter in the month after it. Your state sets the real filing calendar (monthly, quarterly or annual): check it. Income tax for year 1 is paid in year 2. The loan payment is split into twelve equal parts following the ANNUAL schedule in "Financing", and payroll into twelve monthly installments

Sheet Financing
A1: FINANCING PLAN
A2: What you need, where it comes from and what it costs to repay. It is the sheet your lender asks for along with the P&L.
A4: Item | B4: Amount | C4: Notes
A5: SOURCES OF FUNDS
A6: Owner's equity (your own money) | B6: =IFERROR(IF('0. Assumptions'!$B$30="","",'0. Assumptions'!$B$30),"") -> 95000
A7: Loan requested — bank or SBA 7(a) (amortized below) | B7: =IFERROR(IF('0. Assumptions'!$B$31="","",'0. Assumptions'!$B$31),"") -> 162000
A8: Other loan (not in the schedule or the DSCR — enter your loan in row 7) | B8: 0 | C8: A source of funds only: NOT amortized, so it is not in the schedule, the P&L interest or the DSCR. Enter your bank or SBA 7(a) loan in row 7 ("Loan requested" in "0. Assumptions"); use this row only for a second loan
A9: SBA Microloan (not in the schedule or the DSCR — enter your loan in row 7) | B9: 0 | C9: SBA Microloans go up to $50,000 through nonprofit intermediaries. Like row 8, a source of funds only: not in the schedule or the DSCR. If it is your only loan, enter it in row 7 instead
A10: Investors / partners (equity: dilutes, not repaid) | B10: 0 | C10: Equity: it dilutes your ownership and is not repaid
A11: Local grants (usually paid after you spend) | B11: 0 | C11: Usually paid AFTER you document the spending
A12: TOTAL SOURCES OF FUNDS | B12: =IFERROR(IF(COUNT(B6:B11)=0,"",SUM(B6:B11)),"") -> 257000
A13: USES OF FUNDS
A14: Total cash needed at launch | B14: =IFERROR(IF('Startup Costs'!$B$34="","",'Startup Costs'!$B$34),"") -> 256871.3 | C14: Startup costs plus any recoverable tax you have to advance (zero by default in the US)
A15: Difference (sources - uses) | B15: =IFERROR(B12-B14,"") -> 128.7 | C15: In red (negative), the plan is NOT funded. Far above zero is not free either: you pay interest on money you do not use
A16: Difference as a % of uses | B16: =IFERROR(B15/B14,"") -> 0.00050102911 | C16: Amber above the margin you set: it is debt you pay for without needing it
A17: Acceptable over-funding (%) | B17: 0.05 | C17: A small cushion over the need is healthy; 20% extra is interest thrown away
A18: Loan that would match sources to needs | B18: =IFERROR(MAX(0,B14-B12+B7),"") -> 161871.3 | C18: Copy it into "Loan requested" in the "0. Assumptions" tab and the difference goes to zero. Rows 8-11 lower this figure, but only the row-7 loan is amortized and counted in the DSCR
A19: LOAN TERMS
A20: Principal amount | B20: =IFERROR(IF('0. Assumptions'!$B$31=0,"",'0. Assumptions'!$B$31),"") -> 162000
A21: Nominal annual interest rate (not APR) | B21: =IFERROR(IF('0. Assumptions'!$B$32="","",'0. Assumptions'!$B$32),"") -> 0.1
A22: Total term (years) | B22: =IFERROR(IF('0. Assumptions'!$B$33="","",'0. Assumptions'!$B$33),"") -> 10
A23: Interest-only period applied (years) | B23: =IFERROR(IF(OR('0. Assumptions'!$B$34="",'0. Assumptions'!$B$33=""),"",IF('0. Assumptions'!$B$34>='0. Assumptions'!$B$33,0,'0. Assumptions'!$B$34)),"") -> 0 | C23: An interest-only period equal to or longer than the term does not exist: the sheet cancels it at the source
A24: Annual payment during repayment | B24: =IFERROR(IF(B22-B23<=0,"",IF(B21=0,B20/(B22-B23),B20*B21/(1-(1+B21)^-(B22-B23)))),"") -> 26364.754 | C24: Standard amortizing loan with a level annual payment. At a 0% rate it is the principal divided by the repayment years: without that branch the schedule would shut down entirely
A25: AMORTIZATION SCHEDULE
A26: Year | B26: Opening balance | C26: Interest | D26: Principal repaid | E26: Total payment | F26: Closing balance | G26: Cash flow available for debt service (after tax; from year 4 on, year 3 held flat) | H26: DSCR for the year
A27: 1 | B27: =IFERROR(IF(B20="","",B20),"") -> 162000 | C27: =IFERROR(IF(OR(1>B22,B27=""),"",B27*B21),"") -> 16200 | D27: =IFERROR(IF(OR(1>B22,B27=""),"",IF(1<=B23,0,MIN(B27,B24-C27))),"") -> 10164.754 | E27: =IFERROR(IF(C27="","",C27+D27),"") -> 26364.754 | F27: =IFERROR(IF(D27="","",B27-D27),"") -> 151835.25 | G27: =IFERROR(IF(E27="","",'3-Year P&L'!$B$41-'3-Year P&L'!$B$46+'3-Year P&L'!$B$36+'3-Year P&L'!$B$37),"") -> 59552.073 | H27: =IFERROR(IF(OR(E27="",E27=0),"",G27/E27),"") -> 2.258776
A28: 2 | B28: =IFERROR(IF(OR(2>B22,F27=""),"",F27),"") -> 151835.25 | C28: =IFERROR(IF(OR(2>B22,B28=""),"",B28*B21),"") -> 15183.525 | D28: =IFERROR(IF(OR(2>B22,B28=""),"",IF(2<=B23,0,MIN(B28,B24-C28))),"") -> 11181.229 | E28: =IFERROR(IF(C28="","",C28+D28),"") -> 26364.754 | F28: =IFERROR(IF(D28="","",B28-D28),"") -> 140654.02 | G28: =IFERROR(IF(E28="","",'3-Year P&L'!$C$41-'3-Year P&L'!$C$46+'3-Year P&L'!$C$36+'3-Year P&L'!$C$37),"") -> 68995.889 | H28: =IFERROR(IF(OR(E28="",E28=0),"",G28/E28),"") -> 2.6169745
A29: 3 | B29: =IFERROR(IF(OR(3>B22,F28=""),"",F28),"") -> 140654.02 | C29: =IFERROR(IF(OR(3>B22,B29=""),"",B29*B21),"") -> 14065.402 | D29: =IFERROR(IF(OR(3>B22,B29=""),"",IF(3<=B23,0,MIN(B29,B24-C29))),"") -> 12299.352 | E29: =IFERROR(IF(C29="","",C29+D29),"") -> 26364.754 | F29: =IFERROR(IF(D29="","",B29-D29),"") -> 128354.66 | G29: =IFERROR(IF(E29="","",'3-Year P&L'!$D$41-'3-Year P&L'!$D$46+'3-Year P&L'!$D$36+'3-Year P&L'!$D$37),"") -> 73312.465 | H29: =IFERROR(IF(OR(E29="",E29=0),"",G29/E29),"") -> 2.7806997
A30: 4 | B30: =IFERROR(IF(OR(4>B22,F29=""),"",F29),"") -> 128354.66 | C30: =IFERROR(IF(OR(4>B22,B30=""),"",B30*B21),"") -> 12835.466 | D30: =IFERROR(IF(OR(4>B22,B30=""),"",IF(4<=B23,0,MIN(B30,B24-C30))),"") -> 13529.288 | E30: =IFERROR(IF(C30="","",C30+D30),"") -> 26364.754 | F30: =IFERROR(IF(D30="","",B30-D30),"") -> 114825.38 | G30: =IFERROR(IF(E30="","",'3-Year P&L'!$D$41-'3-Year P&L'!$D$46+'3-Year P&L'!$D$36+'3-Year P&L'!$D$37),"") -> 73312.465 | H30: =IFERROR(IF(OR(E30="",E30=0),"",G30/E30),"") -> 2.7806997
A31: 5 | B31: =IFERROR(IF(OR(5>B22,F30=""),"",F30),"") -> 114825.38 | C31: =IFERROR(IF(OR(5>B22,B31=""),"",B31*B21),"") -> 11482.538 | D31: =IFERROR(IF(OR(5>B22,B31=""),"",IF(5<=B23,0,MIN(B31,B24-C31))),"") -> 14882.216 | E31: =IFERROR(IF(C31="","",C31+D31),"") -> 26364.754 | F31: =IFERROR(IF(D31="","",B31-D31),"") -> 99943.161 | G31: =IFERROR(IF(E31="","",'3-Year P&L'!$D$41-'3-Year P&L'!$D$46+'3-Year P&L'!$D$36+'3-Year P&L'!$D$37),"") -> 73312.465 | H31: =IFERROR(IF(OR(E31="",E31=0),"",G31/E31),"") -> 2.7806997
A32: 6 | B32: =IFERROR(IF(OR(6>B22,F31=""),"",F31),"") -> 99943.161 | C32: =IFERROR(IF(OR(6>B22,B32=""),"",B32*B21),"") -> 9994.3161 | D32: =IFERROR(IF(OR(6>B22,B32=""),"",IF(6<=B23,0,MIN(B32,B24-C32))),"") -> 16370.438 | E32: =IFERROR(IF(C32="","",C32+D32),"") -> 26364.754 | F32: =IFERROR(IF(D32="","",B32-D32),"") -> 83572.723 | G32: =IFERROR(IF(E32="","",'3-Year P&L'!$D$41-'3-Year P&L'!$D$46+'3-Year P&L'!$D$36+'3-Year P&L'!$D$37),"") -> 73312.465 | H32: =IFERROR(IF(OR(E32="",E32=0),"",G32/E32),"") -> 2.7806997
A33: 7 | B33: =IFERROR(IF(OR(7>B22,F32=""),"",F32),"") -> 83572.723 | C33: =IFERROR(IF(OR(7>B22,B33=""),"",B33*B21),"") -> 8357.2723 | D33: =IFERROR(IF(OR(7>B22,B33=""),"",IF(7<=B23,0,MIN(B33,B24-C33))),"") -> 18007.482 | E33: =IFERROR(IF(C33="","",C33+D33),"") -> 26364.754 | F33: =IFERROR(IF(D33="","",B33-D33),"") -> 65565.241 | G33: =IFERROR(IF(E33="","",'3-Year P&L'!$D$41-'3-Year P&L'!$D$46+'3-Year P&L'!$D$36+'3-Year P&L'!$D$37),"") -> 73312.465 | H33: =IFERROR(IF(OR(E33="",E33=0),"",G33/E33),"") -> 2.7806997
A34: 8 | B34: =IFERROR(IF(OR(8>B22,F33=""),"",F33),"") -> 65565.241 | C34: =IFERROR(IF(OR(8>B22,B34=""),"",B34*B21),"") -> 6556.5241 | D34: =IFERROR(IF(OR(8>B22,B34=""),"",IF(8<=B23,0,MIN(B34,B24-C34))),"") -> 19808.23 | E34: =IFERROR(IF(C34="","",C34+D34),"") -> 26364.754 | F34: =IFERROR(IF(D34="","",B34-D34),"") -> 45757.011 | G34: =IFERROR(IF(E34="","",'3-Year P&L'!$D$41-'3-Year P&L'!$D$46+'3-Year P&L'!$D$36+'3-Year P&L'!$D$37),"") -> 73312.465 | H34: =IFERROR(IF(OR(E34="",E34=0),"",G34/E34),"") -> 2.7806997
A35: 9 | B35: =IFERROR(IF(OR(9>B22,F34=""),"",F34),"") -> 45757.011 | C35: =IFERROR(IF(OR(9>B22,B35=""),"",B35*B21),"") -> 4575.7011 | D35: =IFERROR(IF(OR(9>B22,B35=""),"",IF(9<=B23,0,MIN(B35,B24-C35))),"") -> 21789.053 | E35: =IFERROR(IF(C35="","",C35+D35),"") -> 26364.754 | F35: =IFERROR(IF(D35="","",B35-D35),"") -> 23967.958 | G35: =IFERROR(IF(E35="","",'3-Year P&L'!$D$41-'3-Year P&L'!$D$46+'3-Year P&L'!$D$36+'3-Year P&L'!$D$37),"") -> 73312.465 | H35: =IFERROR(IF(OR(E35="",E35=0),"",G35/E35),"") -> 2.7806997
A36: 10 | B36: =IFERROR(IF(OR(10>B22,F35=""),"",F35),"") -> 23967.958 | C36: =IFERROR(IF(OR(10>B22,B36=""),"",B36*B21),"") -> 2396.7958 | D36: =IFERROR(IF(OR(10>B22,B36=""),"",IF(10<=B23,0,MIN(B36,B24-C36))),"") -> 23967.958 | E36: =IFERROR(IF(C36="","",C36+D36),"") -> 26364.754 | F36: =IFERROR(IF(D36="","",B36-D36),"") -> 1.8553692e-10 | G36: =IFERROR(IF(E36="","",'3-Year P&L'!$D$41-'3-Year P&L'!$D$46+'3-Year P&L'!$D$36+'3-Year P&L'!$D$37),"") -> 73312.465 | H36: =IFERROR(IF(OR(E36="",E36=0),"",G36/E36),"") -> 2.7806997
A37: 11 | B37: =IFERROR(IF(OR(11>B22,F36=""),"",F36),"") | C37: =IFERROR(IF(OR(11>B22,B37=""),"",B37*B21),"") | D37: =IFERROR(IF(OR(11>B22,B37=""),"",IF(11<=B23,0,MIN(B37,B24-C37))),"") | E37: =IFERROR(IF(C37="","",C37+D37),"") | F37: =IFERROR(IF(D37="","",B37-D37),"") | G37: =IFERROR(IF(E37="","",'3-Year P&L'!$D$41-'3-Year P&L'!$D$46+'3-Year P&L'!$D$36+'3-Year P&L'!$D$37),"") | H37: =IFERROR(IF(OR(E37="",E37=0),"",G37/E37),"")
A38: 12 | B38: =IFERROR(IF(OR(12>B22,F37=""),"",F37),"") | C38: =IFERROR(IF(OR(12>B22,B38=""),"",B38*B21),"") | D38: =IFERROR(IF(OR(12>B22,B38=""),"",IF(12<=B23,0,MIN(B38,B24-C38))),"") | E38: =IFERROR(IF(C38="","",C38+D38),"") | F38: =IFERROR(IF(D38="","",B38-D38),"") | G38: =IFERROR(IF(E38="","",'3-Year P&L'!$D$41-'3-Year P&L'!$D$46+'3-Year P&L'!$D$36+'3-Year P&L'!$D$37),"") | H38: =IFERROR(IF(OR(E38="",E38=0),"",G38/E38),"")
A39: 13 | B39: =IFERROR(IF(OR(13>B22,F38=""),"",F38),"") | C39: =IFERROR(IF(OR(13>B22,B39=""),"",B39*B21),"") | D39: =IFERROR(IF(OR(13>B22,B39=""),"",IF(13<=B23,0,MIN(B39,B24-C39))),"") | E39: =IFERROR(IF(C39="","",C39+D39),"") | F39: =IFERROR(IF(D39="","",B39-D39),"") | G39: =IFERROR(IF(E39="","",'3-Year P&L'!$D$41-'3-Year P&L'!$D$46+'3-Year P&L'!$D$36+'3-Year P&L'!$D$37),"") | H39: =IFERROR(IF(OR(E39="",E39=0),"",G39/E39),"")
A40: 14 | B40: =IFERROR(IF(OR(14>B22,F39=""),"",F39),"") | C40: =IFERROR(IF(OR(14>B22,B40=""),"",B40*B21),"") | D40: =IFERROR(IF(OR(14>B22,B40=""),"",IF(14<=B23,0,MIN(B40,B24-C40))),"") | E40: =IFERROR(IF(C40="","",C40+D40),"") | F40: =IFERROR(IF(D40="","",B40-D40),"") | G40: =IFERROR(IF(E40="","",'3-Year P&L'!$D$41-'3-Year P&L'!$D$46+'3-Year P&L'!$D$36+'3-Year P&L'!$D$37),"") | H40: =IFERROR(IF(OR(E40="",E40=0),"",G40/E40),"")
A41: 15 | B41: =IFERROR(IF(OR(15>B22,F40=""),"",F40),"") | C41: =IFERROR(IF(OR(15>B22,B41=""),"",B41*B21),"") | D41: =IFERROR(IF(OR(15>B22,B41=""),"",IF(15<=B23,0,MIN(B41,B24-C41))),"") | E41: =IFERROR(IF(C41="","",C41+D41),"") | F41: =IFERROR(IF(D41="","",B41-D41),"") | G41: =IFERROR(IF(E41="","",'3-Year P&L'!$D$41-'3-Year P&L'!$D$46+'3-Year P&L'!$D$36+'3-Year P&L'!$D$37),"") | H41: =IFERROR(IF(OR(E41="",E41=0),"",G41/E41),"")
A42: Schedule closing tolerance | B42: 0.01 | C42: Rounding margin. Above it, the schedule does not close and there is principal left unpaid
A43: Balance outstanding at maturity | B43: =IFERROR(IF(B20="","",ROUND(B20-SUM(D27:D41),2)),"") -> 0 | C43: Must be zero: the principal repaid in the schedule has to equal the amount borrowed. If it is positive, the term falls short
A44: Year-1 interest | B44: =IFERROR(IF(B20="","",IF(C27="",0,C27)),"") -> 16200
A45: Year-1 principal repaid | B45: =IFERROR(IF(B20="","",IF(D27="",0,D27)),"") -> 10164.754
A46: Year-2 interest | B46: =IFERROR(IF(B20="","",IF(C28="",0,C28)),"") -> 15183.525
A47: Year-2 principal repaid | B47: =IFERROR(IF(B20="","",IF(D28="",0,D28)),"") -> 11181.229
A48: Year-3 interest | B48: =IFERROR(IF(B20="","",IF(C29="",0,C29)),"") -> 14065.402
A49: Year-3 principal repaid | B49: =IFERROR(IF(B20="","",IF(D29="",0,D29)),"") -> 12299.352
A50: DEBT SERVICE COVERAGE RATIO (DSCR)
A51: Year-1 DSCR | B51: =IFERROR(('3-Year P&L'!$B$41-'3-Year P&L'!$B$46+'3-Year P&L'!$B$36+B44)/(B44+B45),"") -> 2.258776 | C51: An INTEREST-ONLY year, if there is one: with only interest in the denominator the ratio shoots up and does not measure the business
A52: Year-2 DSCR | B52: =IFERROR(('3-Year P&L'!$C$41-'3-Year P&L'!$C$46+'3-Year P&L'!$C$36+B46)/(B46+B47),"") -> 2.6169745
A53: Year-3 DSCR | B53: =IFERROR(('3-Year P&L'!$D$41-'3-Year P&L'!$D$46+'3-Year P&L'!$D$36+B48)/(B48+B49),"") -> 2.7806997
A54: Minimum DSCR across the whole schedule | B54: =IFERROR(IF(COUNT(H27:H41)=0,"",MIN(H27:H41)),"") -> 2.258776 | C54: The worst year of the life of the loan, not the best of the three the P&L projects. It is the number that decides a loan. Mind the scope: years 1 to 3 come from the P&L, and from year 4 on the schedule HOLDS year 3's cash flow, so the minimum over those years is a sustained projection, not a calculated year. The cash flow is after tax
A56: DSCR is calculated BEFORE debt and AFTER tax: income tax is subtracted from pre-tax income, depreciation and interest are added back, and the result is divided by what has to be paid that year. Below the minimum in the "0. Assumptions" tab, the business does not generate enough to repay the loan. In the schedule, the available cash flow from year 4 on is held at year 3's: the P&L projects only three years, and no growth is invented here that has not been calculated.
