Workbook

Sheet Inversión Inicial
A1: Inversión Inicial — Dark Kitchen
A2: AI Chef Pro · aichef.pro — Cómo Montar una Dark Kitchen
A4: Categoría | B4: Concepto | C4: Presupuesto (€) | D4: Real (€) | E4: Notas
A5: Obra Civil | B5: Acondicionamiento del local (suelos, paredes, techos) | C5: 8000
A6: Obra Civil | B6: Instalación eléctrica | C6: 3500
A7: Obra Civil | B7: Fontanería y saneamiento | C7: 1500
A8: Obra Civil | B8: Instalación de gas | C8: 1200
A9: Obra Civil | B9: Extracción de humos y ventilación | C9: 3500
A10: Obra Civil | B10: Sistema contra incendios | C10: 600
A11: Equipamiento | B11: Horno de convección profesional | C11: 3500
A12: Equipamiento | B12: Plancha industrial | C12: 1200
A13: Equipamiento | B13: Freidora industrial | C13: 1200
A14: Equipamiento | B14: Cocina de inducción | C14: 1000
A15: Equipamiento | B15: Cámara frigorífica | C15: 2800
A16: Equipamiento | B16: Congelador industrial | C16: 1500
... A34: Capital Circulante | B34: Fondo de maniobra (2 meses de gastos fijos) | C34: 8000
B35: INVERSIÓN TOTAL | C35: =SUM(C5:C34) -> 57900 | D35: =SUM(D5:D34) -> 0

Sheet P&L Mensual
A1: Cuenta de Resultados Mensual — Dark Kitchen
A2: AI Chef Pro · aichef.pro — Cómo Montar una Dark Kitchen
A4: PARÁMETROS DE ENTRADA
A5: Pedidos por día | B5: 35
A6: Ticket medio (€) | B6: 22
A7: Días operativos al mes | B7: 30
A8: Comisión media plataformas (%) | B8: 0.3
A9: Food cost (%) | B9: 0.3
A10: Coste packaging por pedido (€) | B10: 0.8
A13: CUENTA DE RESULTADOS
A14: Ingresos brutos | B14: =B5*B6*B7 -> 23100
A15: (-) Comisiones de plataformas | B15: =-B5*B6*B7*B8 -> -6930
A16: = Ingresos netos | B16: =B5*B6*B7*(1-B8) -> 16170
A18: (-) Coste de materia prima (food cost) | B18: =-B5*B6*B7*B9 -> -6930
A19: (-) Packaging | B19: =-B5*B7*B10 -> -840
A20: = Margen bruto | B20: =B5*B6*B7*(1-B8-B9)-B5*B7*B10 -> 8400
A22: COSTES FIJOS MENSUALES
A23: Alquiler del local | B23: 1500
A24: Suministros (luz, agua, gas) | B24: 600
A25: Personal (1 jefe cocina + 1 ayudante) | B25: 3800
A26: Seguros | B26: 60
A27: Gestoría/asesoría | B27: 200
A28: Software y tecnología | B28: 150
A29: Limpieza y DDD | B29: 120
A30: Marketing en plataformas (5% ingresos) | B30: =B14*0.05 -> 1155
A32: TOTAL COSTES FIJOS | B32: =SUM(B23:B30) -> 7585
A34: EBITDA MENSUAL | B34: =B20-B32 -> 815
A35: Margen EBITDA (%) | B35: =IF(B14=0,0,B34/B14) -> 0.035281385

Sheet Punto de Equilibrio
A1: Análisis del Punto de Equilibrio — Dark Kitchen
A2: AI Chef Pro · aichef.pro — Cómo Montar una Dark Kitchen
A4: CÁLCULO DEL BREAK-EVEN
A5: Ticket medio (€) | B5: ='P&L Mensual'!B6 -> 22
A6: Comisión media plataformas (%) | B6: ='P&L Mensual'!B8 -> 0.3
A7: Food cost (%) | B7: ='P&L Mensual'!B9 -> 0.3
A8: Packaging por pedido (€) | B8: ='P&L Mensual'!B10 -> 0.8
A9: Total costes fijos mensuales (€) | B9: ='P&L Mensual'!B32 -> 7585
A11: RESULTADOS
A12: Margen de contribución por pedido (€) | B12: =B5*(1-B6-B7)-B8 -> 8
A13: Pedidos necesarios al mes (break-even) | B13: =ROUNDUP(B9/B12,0) -> 949
A14: Pedidos necesarios al día (30 días) | B14: =ROUNDUP(B13/30,0) -> 32
A15: Facturación mensual mínima (€) | B15: =B13*B5 -> 20878
A18: ESCENARIOS DE FACTURACIÓN
B19: Pesimista | C19: Realista | D19: Optimista
A20: Pedidos/día | B20: 20 | C20: 40 | D20: 65
A21: Ticket medio (€) | B21: =B5 -> 22 | C21: =B5 -> 22 | D21: =B5 -> 22
A22: Facturación bruta mensual (€) | B22: =B20*B21*30 -> 13200 | C22: =C20*C21*30 -> 26400 | D22: =D20*D21*30 -> 42900
A23: (-) Comisiones plataformas (€) | B23: =-B22*B6 -> -3960 | C23: =-C22*B6 -> -7920 | D23: =-D22*B6 -> -12870
A24: (-) Food cost (€) | B24: =-B22*B7 -> -3960 | C24: =-C22*B7 -> -7920 | D24: =-D22*B7 -> -12870
A25: (-) Packaging (€) | B25: =-B20*30*B8 -> -480 | C25: =-C20*30*B8 -> -960 | D25: =-D20*30*B8 -> -1560
A26: = Margen bruto (€) | B26: =SUM(B22:B25) -> 4800 | C26: =SUM(C22:C25) -> 9600 | D26: =SUM(D22:D25) -> 15600
A27: (-) Costes fijos (€) | B27: =-B9 -> -7585 | C27: =-B9 -> -7585 | D27: =-B9 -> -7585
A28: = EBITDA mensual (€) | B28: =B26+B27 -> -2785 | C28: =C26+C27 -> 2015 | D28: =D26+D27 -> 8015
A29: Margen EBITDA (%) | B29: =IF(B22=0,0,B28/B22) -> -0.21098485 | C29: =IF(C22=0,0,C28/C22) -> 0.076325758 | D29: =IF(D22=0,0,D28/D22) -> 0.18682984
