Workbook

Sheet Fish Yield
A1: FISH YIELD CALCULATOR — COST PER USABLE LB, PER SLICE, PER CUT AND PER ROLL
A2: Type only in the GREEN cells: everything else is calculated. Amounts are before sales tax. Every default is a Kit estimate, editable: replace it with your distributor's price and, above all, with what you measure on your own fish.
A3: FIXED NOTICE. Parasite destruction (FDA Food Code 2022, 3-402.11): fish served raw or undercooked is frozen at −4 °F or below for 168 hours (7 days), or at −31 °F until solid and held 15 hours, or at −31 °F until solid and held 24 hours at −4 °F. Tuna species are exempt; feed-raised aquaculture fish only with a written statement from the supplier or the farm. Keep the records 90 days (3-402.12). Your county's rules may be stricter. The cleaning minutes (25) have no source: time it.
A5: A. THREE FISH AND ONE FREE COLUMN | B5: Whole farmed Atlantic salmon | C5: Salmon fillet, skin-on, pin-bone out | D5: Yellowfin tuna saku block (frozen) | E5: Other fish (type yours) | F5: Notes
A6: Purchase price ($/lb, before tax) | B6: 7.5 | C6: 20 | D6: 23 | E6: 24.5 | F6: No wholesale price was read for sushi salmon in Oct 2026: NYC auction reports $18-24/lb for sushi salmon (weak source) and yellowfin saku retails at about $22.99/lb (Costco). The kit puts 7.50 · 20.00 · 23.00 · 24.50 $/lb. Kit estimate (Oct 2026): replace with your distributor's price.
A7: Yield: usable loin over the weight you buy | B7: 0.55 | C7: 0.85 | D7: 0.9 | E7: 0.8 | F7: Usable loin is 45-60% of a whole salmon (secondary sources). Measure it with 3 fish (see the "Instructions" sheet). For a saku block it is the share you keep after trimming. Kit estimate, editable.
A8: Trim you reuse (% of the weight you buy) | B8: 0.15 | C8: 0.03 | D8: 0.05 | E8: 0.05 | F8: Trim you reuse (spicy mix, maki, poke), as a % of the weight you buy. What you throw away does not count here. Kit estimate, editable.
A10: B. COMMON INPUTS | B10: Value | C10: Notes
A11: Case shrink (% of cut fish that is not sold) | B11: 0.05 | C11: Fish left in the sushi case or at the pass and thrown out at close. Kit estimate, editable.
A12: Ounces of fish per nigiri slice (oz) | B12: 0.5 | C12: Kit standard: weigh 10 slices and use the average. Kit estimate, editable.
A13: Ounces per sashimi cut (oz) | B13: 0.5 | C13: Weigh 10 cuts and use the average. Kit estimate, editable.
A14: Ounces of fish per roll (oz) | B14: 1.5 | C14: A roll of 6 to 8 pieces with fish inside. Kit estimate, editable.
A15: Cleaning minutes per whole fish (min) | B15: 25 | C15: No source: time it. Time the cleaning of 3 fish and use the average. Kit estimate, editable.
A16: Head sushi chef cost per hour ($/h) | B16: 33 | C16: $5,199 a month × 12 + 10% payroll taxes ÷ 2,080 h ≈ $33/h. Kit estimate, editable.
A17: Weight of a whole fish (lb) | B17: 11 | C17: Whole farmed salmon of about 11 lb. Kit estimate, editable.
A18: Parasite destruction: freezing or statement (dropdown) | B18: I freeze in-house: −4 °F for 7 days or a −31 °F option
A19: Ounces per lb (constant: 16 oz per lb) | B19: 16 | C19: Constant: 1 lb = 16 oz. Not editable.
A20: Minutes per hour (constant: 60 minutes per hour) | B20: 60 | C20: Constant: 1 hour = 60 minutes. Not editable.
A22: C. COST PER USABLE LB AND PER PIECE | B22: =B5 -> Whole farmed Atlantic salmon | C22: =C5 -> Salmon fillet, skin-on, pin-bone out | D22: =D5 -> Yellowfin tuna saku block (frozen) | E22: =E5 -> Other fish (type yours) | F22: Notes
A23: Share used (yield + trim) | B23: =B$7+B$8 -> 0.7 | C23: =C$7+C$8 -> 0.88 | D23: =D$7+D$8 -> 0.95 | E23: =E$7+E$8 -> 0.85 | F23: Loin plus the trim you reuse.
A24: COST PER USABLE LB ($) | B24: =B$6/B$23/(1-$B$11) -> 11.278195 | C24: =C$6/C$23/(1-$B$11) -> 23.923445 | D24: =D$6/D$23/(1-$B$11) -> 25.484765 | E24: =E$6/E$23/(1-$B$11) -> 30.340557 | F24: Price ÷ (yield + trim) ÷ (1 − case shrink).
A25: Cost of a nigiri slice ($) | B25: =B$24*$B$12/$B$19 -> 0.35244361 | C25: =C$24*$B$12/$B$19 -> 0.74760766 | D25: =D$24*$B$12/$B$19 -> 0.79639889 | E25: =E$24*$B$12/$B$19 -> 0.94814241 | F25: Cost per usable lb × ounces ÷ 16.
A26: Cost of a sashimi cut ($) | B26: =B$24*$B$13/$B$19 -> 0.35244361 | C26: =C$24*$B$13/$B$19 -> 0.74760766 | D26: =D$24*$B$13/$B$19 -> 0.79639889 | E26: =E$24*$B$13/$B$19 -> 0.94814241 | F26: Cost per usable lb × ounces ÷ 16.
A27: Cost of the fish in a roll ($) | B27: =B$24*$B$14/$B$19 -> 1.0573308 | C27: =C$24*$B$14/$B$19 -> 2.242823 | D27: =D$24*$B$14/$B$19 -> 2.3891967 | E27: =E$24*$B$14/$B$19 -> 2.8444272 | F27: Cost per usable lb × ounces ÷ 16.
A29: D. WHOLE FISH OR FILLET? | B29: Value | C29: Notes
A30: Cost of cleaning one whole fish ($) | B30: =$B$15/$B$20*$B$16 -> 13.75 | C30: Cleaning minutes ÷ 60 × head sushi chef cost per hour.
A31: Usable lb of one whole fish (lb) | B31: =$B$17*$B$7 -> 6.05 | C31: Weight of the fish × yield of the whole salmon.
A32: CLEANING LABOR PER USABLE LB ($) | B32: =$B$30/$B$31 -> 2.2727273 | C32: Cost of cleaning one fish ÷ usable pounds.
A33: Cost per usable lb of the whole fish with cleaning included ($) | B33: =$B$24+$B$32 -> 13.550923 | C33: Cost per usable lb + cleaning labor per usable lb.
A34: THE WHOLE FISH PAYS OFF AS LONG AS CLEANING COSTS LESS THAN ($ per usable lb) | B34: =$C$24-$B$24 -> 12.645249 | C34: Cost per usable lb of the fillet − cost per usable lb of the whole fish.
A35: Verdict with your labor | B35: =IF($B$32<$B$34,"The whole fish pays off","Buy the fillet") -> The whole fish pays off | C35: The whole fish pays off if cleaning costs less than that difference.
A36: Reminder for your parasite case | B36: =INDEX($B$39:$B$41,MATCH($B$18,$A$39:$A$41,0)) -> FDA Food Code 2022, 3-402.11: −4 °F or below for 168 hours (7 days), or −31 °F until solid and 15 hours, or −31 °F until solid and 24 hours at −4 °F. Log time and temperature of every lot and keep the records 90 days (3-402.12).
A38: PARASITE DROPDOWN LIST | B38: Reminder
A39: I freeze in-house: −4 °F for 7 days or a −31 °F option | B39: FDA Food Code 2022, 3-402.11: −4 °F or below for 168 hours (7 days), or −31 °F until solid and 15 hours, or −31 °F until solid and 24 hours at −4 °F. Log time and temperature of every lot and keep the records 90 days (3-402.12).
A40: Arrives frozen with a supplier letter | B40: Keep the supplier's written agreement or statement for every lot: it must show the freezing time and temperature. Keep it 90 days after you serve the fish (3-402.12).
A41: Exempt: tuna species or feed-raised aquaculture | B41: Tuna (Thunnus species) is exempt; feed-raised aquaculture fish such as farmed salmon is exempt only with a written statement from the supplier or the farm. Keep the tuna invoice that names the species, file the statement and ask again if the source changes.

Sheet Sushi Rice
A1: SUSHI RICE CALCULATOR — HOW MUCH SUSHI RICE 1 LB MAKES, WHAT IT COSTS AND HOW MUCH TO BUY PER DAY
A2: Type only in the GREEN cells: everything else is calculated. Amounts are before sales tax. Every default is a Kit estimate, editable: weigh your rice balls and replace the ounces with yours.
A3: FIXED NOTICE. Time-stamp every batch (TPHC, 4 hours) or, if your county approved a variance, log the pH of every batch in your HACCP plan records.
A5: A. THE RICE AND THE SUSHI RICE | B5: Value | C5: Notes
A6: Raw sushi rice ($/lb, before tax) | B6: 1.04 | C6: 50 lb bag $51.99 = $1.04/lb, webstaurantstore.com, Oct 2026; other medium-grain brands $1.24-1.28/lb.
A7: Raw to cooked factor (×) | B7: 2.2 | C7: 1 lb of raw rice gives 2.2 lb of cooked rice. Kit estimate, editable.
A8: Sushi vinegar (sushi-zu) per lb of cooked rice (fl oz) | B8: 1.5 | C8: Rice vinegar, sugar and salt: about 1.5 fl oz per lb of cooked rice. Kit estimate, editable.
A9: Sushi vinegar ($/gallon, before tax) | B9: 20.5 | C9: Seasoned rice vinegar about $20.50/gal, webstaurantstore.com, Oct 2026.
A10: Ounces of sushi rice per nigiri (oz) | B10: 0.75 | C10: Weigh 10 rice balls and use the average. Kit estimate, editable.
A11: Ounces of sushi rice per maki (thin roll) (oz) | B11: 2.5 | C11: A thin roll of 6 pieces. Kit estimate, editable.
A12: Ounces of sushi rice per inside-out roll (oz) | B12: 3 | C12: A roll of 8 pieces. Kit estimate, editable.
A13: Ounces of sushi rice per hand roll (oz) | B13: 2 | C13: One cone. Kit estimate, editable.
A14: Ounces of sushi rice per poke bowl (oz) | B14: 6 | C14: One bowl. Kit estimate, editable.
A15: Nori ($ per sheet, before tax) | B15: 0.31 | C15: 100 full sheets $31.49, webstaurantstore.com, Oct 2026.
A16: Nori sheets per nigiri | B16: 0.05 | C16: The strip that holds the nigiri. Kit estimate, editable.
A17: Nori sheets per maki | B17: 0.5 | C17: Half a sheet per roll. Kit estimate, editable.
... A25: Fluid ounces per gallon (constant: 128 fl oz per gallon) | B25: 128 | C25: Constant: 1 gallon = 128 fl oz. Not editable.
A27: RESULTS | B27: Value | C27: Notes
A28: LB OF SUSHI RICE PER LB OF RAW RICE (lb) | B28: =$B$7*(1+$B$8/$B$24) -> 2.40625 | C28: Raw to cooked factor × (1 + vinegar fl oz ÷ 16).
A29: COST PER LB OF SUSHI RICE ($) | B29: =($B$6+$B$7*$B$8/$B$25*$B$9)/$B$28 -> 0.65185065 | C29: (Rice + vinegar for 1 lb of raw rice) ÷ lb of sushi rice.
A30: Cost per lb of sushi rice with the close discard ($) | B30: =$B$29/(1-$B$21) -> 0.68615858 | C30: Cost per lb of sushi rice ÷ (1 − rice thrown out). It feeds the costing.
A31: NIGIRI PER LB OF RAW RICE (pieces) | B31: =$B$24*$B$28/$B$10 -> 51.333333 | C31: 16 × lb of sushi rice per lb of raw rice ÷ ounces per nigiri.
A32: Cost of the sushi rice in a nigiri ($) | B32: =$B$10*$B$30/$B$24 -> 0.032163683 | C32: Ounces × cost per lb with discard ÷ 16.
A33: Cost of the sushi rice in a maki ($) | B33: =$B$11*$B$30/$B$24 -> 0.10721228 | C33: Ounces × cost per lb with discard ÷ 16.
A34: Cost of the sushi rice in an inside-out roll ($) | B34: =$B$12*$B$30/$B$24 -> 0.12865473 | C34: Ounces × cost per lb with discard ÷ 16.
A35: Cost of the sushi rice in a hand roll ($) | B35: =$B$13*$B$30/$B$24 -> 0.085769822 | C35: Ounces × cost per lb with discard ÷ 16.
A36: Cost of the sushi rice in a poke bowl ($) | B36: =$B$14*$B$30/$B$24 -> 0.25730947 | C36: Ounces × cost per lb with discard ÷ 16.
A37: Cost of the nori in a nigiri ($) | B37: =$B$16*$B$15 -> 0.0155 | C37: Sheets × price per sheet.
A38: Cost of the nori in a maki ($) | B38: =$B$17*$B$15 -> 0.155 | C38: Sheets × price per sheet.
A39: Cost of the nori in an inside-out roll ($) | B39: =$B$18*$B$15 -> 0.155 | C39: Sheets × price per sheet.
A40: Cost of the nori in a hand roll ($) | B40: =$B$19*$B$15 -> 0.155 | C40: Sheets × price per sheet.
A41: Cost of the nori in a poke bowl ($) | B41: =$B$20*$B$15 -> 0.031 | C41: Sheets × price per sheet.
A42: Sushi rice sold per day (lb) | B42: =$B$22*$B$23/$B$24 -> 35.9375 | C42: Covers × ounces per cover ÷ 16.
A43: LB OF RAW RICE PER DAY | B43: =$B$42/$B$28 -> 14.935065 | C43: Sushi rice sold ÷ lb of sushi rice per lb of raw rice.
A44: Lb of raw rice per day counting what is thrown out | B44: =$B$43/(1-$B$21) -> 15.721121 | C44: Raw rice per day ÷ (1 − rice thrown out).

Sheet Costing
A1: SUSHI MENU COSTING — 14 PRODUCTS, PER PIECE AND PER CHANNEL
A2: Type only in the GREEN cells (names, fish, ounces, nori, menu prices and units). Amounts are before sales tax except the menu price. Every default is a Kit estimate, editable: type yours. The cost of the fish comes from the "Fish Yield" sheet, the cost of the sushi rice and nori from the "Sushi Rice" sheet.
A4: GENERAL INPUTS | B4: Value | D4: Notes
A5: Sales tax included in your menu prices (%) | B5: 0 | D5: US menus usually exclude sales tax: leave 0%. Type your rate only if your prices include it. UK: VAT is 20% dine-in and cold take-out sushi is often zero-rated.
A6: Food cost target (% of the price before tax) | B6: 0.3 | D6: Target for the sushi menu. Kit estimate, editable.
A7: Watch band above the target (points) | B7: 0.05 | D7: Up to this margin above the target the traffic light says "Watch the cost".
A8: To-go packaging per order ($, before tax) | B8: 0.6 | D8: Tray, lid, bag, sauces and chopsticks for one take-out order. Kit estimate, editable.
A9: Marketplace packaging per order ($, before tax) | B9: 1 | D9: Delivery container plus tamper seal. Kit estimate, editable.
A10: Marketplace price markup (%) | B10: 0.15 | D10: How much you raise the price on the marketplace to compensate. Kit estimate, editable.
A11: Marketplace commission (%) | B11: 0.25 | D11: On the price before tax; check your contract. Kit estimate, editable.
A12: Cost per lb of sushi rice with discard ($, from the Sushi Rice sheet) | B12: ='Sushi Rice'!$B$30 -> 0.68615858
A13: Nori ($ per sheet, from the Sushi Rice sheet) | B13: ='Sushi Rice'!$B$15 -> 0.31
A15: PRODUCT | B15: Fish (0 to 4) | C15: Ounces of fish | D15: Ounces of sushi rice | E15: Nori sheets | F15: Other ingredients ($) | G15: Menu price ($) | H15: Units per week | I15: COST ($) | J15: Price before tax ($) | K15: FOOD COST (%) | L15: Traffic light | M15: Suggested menu price ($) | N15: Margin dine-in ($) | O15: Margin take-out / pickup ($) | P15: Margin marketplace ($) | Q15: Rank by margin
A16: Salmon nigiri (2 pcs) | B16: 2 | C16: 1 | D16: 1.5 | E16: 0.1 | F16: 0.05 | G16: 7 | H16: 140 | I16: =C16/'Fish Yield'!$B$19*CHOOSE(B16+1,0,'Fish Yield'!$B$24,'Fish Yield'!$C$24,'Fish Yield'!$D$24,'Fish Yield'!$E$24)+D16/'Fish Yield'!$B$19*$B$12+E16*$B$13+F16 -> 1.6405427 | J16: =G16/(1+$B$5) -> 7 | K16: =I16/J16 -> 0.23436324 | L16: =IF(K16<=$B$6,"On target",IF(K16<=$B$6+$B$7,"Watch the cost","Above target")) -> On target | M16: =I16/$B$6*(1+$B$5) -> 5.4684756 | N16: =J16-I16 -> 5.3594573 | O16: =N16-$B$8 -> 4.7594573 | P16: =J16*(1+$B$10)*(1-$B$11)-I16-$B$9 -> 3.3969573 | Q16: =1+COUNTIF($N$16:$N$29,">"&N16) -> 10
A17: Tuna nigiri (2 pcs) | B17: 3 | C17: 1 | D17: 1.5 | E17: 0.1 | F17: 0.05 | G17: 7.5 | H17: 90 | I17: =C17/'Fish Yield'!$B$19*CHOOSE(B17+1,0,'Fish Yield'!$B$24,'Fish Yield'!$C$24,'Fish Yield'!$D$24,'Fish Yield'!$E$24)+D17/'Fish Yield'!$B$19*$B$12+E17*$B$13+F17 -> 1.7381252 | J17: =G17/(1+$B$5) -> 7.5 | K17: =I17/J17 -> 0.23175002 | L17: =IF(K17<=$B$6,"On target",IF(K17<=$B$6+$B$7,"Watch the cost","Above target")) -> On target | M17: =I17/$B$6*(1+$B$5) -> 5.7937505 | N17: =J17-I17 -> 5.7618748 | O17: =N17-$B$8 -> 5.1618748 | P17: =J17*(1+$B$10)*(1-$B$11)-I17-$B$9 -> 3.7306248 | Q17: =1+COUNTIF($N$16:$N$29,">"&N17) -> 9
A18: Salmon sashimi (5 pcs) | B18: 2 | C18: 2.5 | D18: 0 | E18: 0 | F18: 0.08 | G18: 14 | H18: 50 | I18: =C18/'Fish Yield'!$B$19*CHOOSE(B18+1,0,'Fish Yield'!$B$24,'Fish Yield'!$C$24,'Fish Yield'!$D$24,'Fish Yield'!$E$24)+D18/'Fish Yield'!$B$19*$B$12+E18*$B$13+F18 -> 3.8180383 | J18: =G18/(1+$B$5) -> 14 | K18: =I18/J18 -> 0.27271702 | L18: =IF(K18<=$B$6,"On target",IF(K18<=$B$6+$B$7,"Watch the cost","Above target")) -> On target | M18: =I18/$B$6*(1+$B$5) -> 12.726794 | N18: =J18-I18 -> 10.181962 | O18: =N18-$B$8 -> 9.5819617 | P18: =J18*(1+$B$10)*(1-$B$11)-I18-$B$9 -> 7.2569617 | Q18: =1+COUNTIF($N$16:$N$29,">"&N18) -> 4
A19: Salmon maki (6 pcs) | B19: 2 | C19: 1 | D19: 2.5 | E19: 0.5 | F19: 0.05 | G19: 6.5 | H19: 30 | I19: =C19/'Fish Yield'!$B$19*CHOOSE(B19+1,0,'Fish Yield'!$B$24,'Fish Yield'!$C$24,'Fish Yield'!$D$24,'Fish Yield'!$E$24)+D19/'Fish Yield'!$B$19*$B$12+E19*$B$13+F19 -> 1.8074276 | J19: =G19/(1+$B$5) -> 6.5 | K19: =I19/J19 -> 0.27806578 | L19: =IF(K19<=$B$6,"On target",IF(K19<=$B$6+$B$7,"Watch the cost","Above target")) -> On target | M19: =I19/$B$6*(1+$B$5) -> 6.0247586 | N19: =J19-I19 -> 4.6925724 | O19: =N19-$B$8 -> 4.0925724 | P19: =J19*(1+$B$10)*(1-$B$11)-I19-$B$9 -> 2.7988224 | Q19: =1+COUNTIF($N$16:$N$29,">"&N19) -> 13
A20: California roll (8 pcs) | B20: 0 | C20: 0 | D20: 3 | E20: 0.5 | F20: 0.75 | G20: 8.5 | H20: 120 | I20: =C20/'Fish Yield'!$B$19*CHOOSE(B20+1,0,'Fish Yield'!$B$24,'Fish Yield'!$C$24,'Fish Yield'!$D$24,'Fish Yield'!$E$24)+D20/'Fish Yield'!$B$19*$B$12+E20*$B$13+F20 -> 1.0336547 | J20: =G20/(1+$B$5) -> 8.5 | K20: =I20/J20 -> 0.12160644 | L20: =IF(K20<=$B$6,"On target",IF(K20<=$B$6+$B$7,"Watch the cost","Above target")) -> On target | M20: =I20/$B$6*(1+$B$5) -> 3.4455158 | N20: =J20-I20 -> 7.4663453 | O20: =N20-$B$8 -> 6.8663453 | P20: =J20*(1+$B$10)*(1-$B$11)-I20-$B$9 -> 5.2975953 | Q20: =1+COUNTIF($N$16:$N$29,">"&N20) -> 6
A21: Spicy tuna roll (8 pcs) | B21: 3 | C21: 2 | D21: 3 | E21: 0.5 | F21: 0.25 | G21: 9.5 | H21: 100 | I21: =C21/'Fish Yield'!$B$19*CHOOSE(B21+1,0,'Fish Yield'!$B$24,'Fish Yield'!$C$24,'Fish Yield'!$D$24,'Fish Yield'!$E$24)+D21/'Fish Yield'!$B$19*$B$12+E21*$B$13+F21 -> 3.7192503 | J21: =G21/(1+$B$5) -> 9.5 | K21: =I21/J21 -> 0.39150003 | L21: =IF(K21<=$B$6,"On target",IF(K21<=$B$6+$B$7,"Watch the cost","Above target")) -> Above target | M21: =I21/$B$6*(1+$B$5) -> 12.397501 | N21: =J21-I21 -> 5.7807497 | O21: =N21-$B$8 -> 5.1807497 | P21: =J21*(1+$B$10)*(1-$B$11)-I21-$B$9 -> 3.4744997 | Q21: =1+COUNTIF($N$16:$N$29,">"&N21) -> 8
A22: Shrimp tempura roll (8 pcs) | B22: 0 | C22: 0 | D22: 3 | E22: 0.5 | F22: 2.2 | G22: 11 | H22: 80 | I22: =C22/'Fish Yield'!$B$19*CHOOSE(B22+1,0,'Fish Yield'!$B$24,'Fish Yield'!$C$24,'Fish Yield'!$D$24,'Fish Yield'!$E$24)+D22/'Fish Yield'!$B$19*$B$12+E22*$B$13+F22 -> 2.4836547 | J22: =G22/(1+$B$5) -> 11 | K22: =I22/J22 -> 0.22578679 | L22: =IF(K22<=$B$6,"On target",IF(K22<=$B$6+$B$7,"Watch the cost","Above target")) -> On target | M22: =I22/$B$6*(1+$B$5) -> 8.2788491 | N22: =J22-I22 -> 8.5163453 | O22: =N22-$B$8 -> 7.9163453 | P22: =J22*(1+$B$10)*(1-$B$11)-I22-$B$9 -> 6.0038453 | Q22: =1+COUNTIF($N$16:$N$29,">"&N22) -> 5
A23: Salmon hand roll | B23: 2 | C23: 1 | D23: 2 | E23: 0.5 | F23: 0.3 | G23: 7 | H23: 40 | I23: =C23/'Fish Yield'!$B$19*CHOOSE(B23+1,0,'Fish Yield'!$B$24,'Fish Yield'!$C$24,'Fish Yield'!$D$24,'Fish Yield'!$E$24)+D23/'Fish Yield'!$B$19*$B$12+E23*$B$13+F23 -> 2.0359851 | J23: =G23/(1+$B$5) -> 7 | K23: =I23/J23 -> 0.29085502 | L23: =IF(K23<=$B$6,"On target",IF(K23<=$B$6+$B$7,"Watch the cost","Above target")) -> On target | M23: =I23/$B$6*(1+$B$5) -> 6.7866171 | N23: =J23-I23 -> 4.9640149 | O23: =N23-$B$8 -> 4.3640149 | P23: =J23*(1+$B$10)*(1-$B$11)-I23-$B$9 -> 3.0015149 | Q23: =1+COUNTIF($N$16:$N$29,">"&N23) -> 11
A24: Salmon poke bowl (uses whole-salmon trim) | B24: 1 | C24: 4 | D24: 6 | E24: 0.1 | F24: 1.2 | G24: 16 | H24: 50 | I24: =C24/'Fish Yield'!$B$19*CHOOSE(B24+1,0,'Fish Yield'!$B$24,'Fish Yield'!$C$24,'Fish Yield'!$D$24,'Fish Yield'!$E$24)+D24/'Fish Yield'!$B$19*$B$12+E24*$B$13+F24 -> 4.3078583 | J24: =G24/(1+$B$5) -> 16 | K24: =I24/J24 -> 0.26924115 | L24: =IF(K24<=$B$6,"On target",IF(K24<=$B$6+$B$7,"Watch the cost","Above target")) -> On target | M24: =I24/$B$6*(1+$B$5) -> 14.359528 | N24: =J24-I24 -> 11.692142 | O24: =N24-$B$8 -> 11.092142 | P24: =J24*(1+$B$10)*(1-$B$11)-I24-$B$9 -> 8.4921417 | Q24: =1+COUNTIF($N$16:$N$29,">"&N24) -> 3
A25: Sushi platter, 12 pcs | B25: 2 | C25: 3 | D25: 6 | E25: 0.5 | F25: 0.4 | G25: 22 | H25: 30 | I25: =C25/'Fish Yield'!$B$19*CHOOSE(B25+1,0,'Fish Yield'!$B$24,'Fish Yield'!$C$24,'Fish Yield'!$D$24,'Fish Yield'!$E$24)+D25/'Fish Yield'!$B$19*$B$12+E25*$B$13+F25 -> 5.2979554 | J25: =G25/(1+$B$5) -> 22 | K25: =I25/J25 -> 0.24081615 | L25: =IF(K25<=$B$6,"On target",IF(K25<=$B$6+$B$7,"Watch the cost","Above target")) -> On target | M25: =I25/$B$6*(1+$B$5) -> 17.659851 | N25: =J25-I25 -> 16.702045 | O25: =N25-$B$8 -> 16.102045 | P25: =J25*(1+$B$10)*(1-$B$11)-I25-$B$9 -> 12.677045 | Q25: =1+COUNTIF($N$16:$N$29,">"&N25) -> 2
A26: Party platter, 24 pcs | B26: 2 | C26: 6 | D26: 12 | E26: 1 | F26: 0.6 | G26: 42 | H26: 15 | I26: =C26/'Fish Yield'!$B$19*CHOOSE(B26+1,0,'Fish Yield'!$B$24,'Fish Yield'!$C$24,'Fish Yield'!$D$24,'Fish Yield'!$E$24)+D26/'Fish Yield'!$B$19*$B$12+E26*$B$13+F26 -> 10.395911 | J26: =G26/(1+$B$5) -> 42 | K26: =I26/J26 -> 0.24752169 | L26: =IF(K26<=$B$6,"On target",IF(K26<=$B$6+$B$7,"Watch the cost","Above target")) -> On target | M26: =I26/$B$6*(1+$B$5) -> 34.653036 | N26: =J26-I26 -> 31.604089 | O26: =N26-$B$8 -> 31.004089 | P26: =J26*(1+$B$10)*(1-$B$11)-I26-$B$9 -> 24.829089 | Q26: =1+COUNTIF($N$16:$N$29,">"&N26) -> 1
A27: Gyoza (6 pcs) | B27: 0 | C27: 0 | D27: 0 | E27: 0 | F27: 1.6 | G27: 8 | H27: 60 | I27: =C27/'Fish Yield'!$B$19*CHOOSE(B27+1,0,'Fish Yield'!$B$24,'Fish Yield'!$C$24,'Fish Yield'!$D$24,'Fish Yield'!$E$24)+D27/'Fish Yield'!$B$19*$B$12+E27*$B$13+F27 -> 1.6 | J27: =G27/(1+$B$5) -> 8 | K27: =I27/J27 -> 0.2 | L27: =IF(K27<=$B$6,"On target",IF(K27<=$B$6+$B$7,"Watch the cost","Above target")) -> On target | M27: =I27/$B$6*(1+$B$5) -> 5.3333333 | N27: =J27-I27 -> 6.4 | O27: =N27-$B$8 -> 5.8 | P27: =J27*(1+$B$10)*(1-$B$11)-I27-$B$9 -> 4.3 | Q27: =1+COUNTIF($N$16:$N$29,">"&N27) -> 7
... A29: Mochi ice cream (2 pcs) | B29: 0 | C29: 0 | D29: 0 | E29: 0 | F29: 1.4 | G29: 6 | H29: 40 | I29: =C29/'Fish Yield'!$B$19*CHOOSE(B29+1,0,'Fish Yield'!$B$24,'Fish Yield'!$C$24,'Fish Yield'!$D$24,'Fish Yield'!$E$24)+D29/'Fish Yield'!$B$19*$B$12+E29*$B$13+F29 -> 1.4 | J29: =G29/(1+$B$5) -> 6 | K29: =I29/J29 -> 0.23333333 | L29: =IF(K29<=$B$6,"On target",IF(K29<=$B$6+$B$7,"Watch the cost","Above target")) -> On target | M29: =I29/$B$6*(1+$B$5) -> 4.6666667 | N29: =J29-I29 -> 4.6 | O29: =N29-$B$8 -> 4 | P29: =J29*(1+$B$10)*(1-$B$11)-I29-$B$9 -> 2.775 | Q29: =1+COUNTIF($N$16:$N$29,">"&N29) -> 14
A31: WEIGHTED FOOD COST OF THE WEEK (sum of costs × units ÷ sum of prices before tax × units) | B31: Value
A32: Weekly sales before tax ($) | B32: =SUMPRODUCT($J$16:$J$29,$H$16:$H$29) -> 8820
A33: Cost of the food sold in the week ($) | B33: =SUMPRODUCT($I$16:$I$29,$H$16:$H$29) -> 2131.5976
A34: WEIGHTED FOOD COST (%) | B34: =IF($B$32=0,0,$B$33/$B$32) -> 0.24167773
A35: Traffic light of the weighted food cost | B35: =IF($B$34<=$B$6,"On target",IF($B$34<=$B$6+$B$7,"Watch the cost","Above target")) -> On target
A37: Fish: 0 = none · 1 = Whole farmed Atlantic salmon · 2 = Salmon fillet, skin-on, pin-bone out · 3 = Yellowfin tuna saku block (frozen) · 4 = Other fish (type yours). Other ingredients: imitation crab $1.80/lb, avocado, cucumber, sauces, sesame, tempura shrimp ($16.44/lb, 16/20), wasabi and ginger, at Kit estimate prices. The food cost in the table is the plate served dine-in, without drinks. On a take-out order the packaging is deducted; on the marketplace the price is raised by the markup and the commission is deducted on that price, plus the packaging. Margins are ranked by the dine-in margin. FIXED NOTICE: tempura and gyoza travel badly: keep them off the marketplace menu or warn the guest. This cost is THEORETICAL: the 32% food cost of the plan (sheet "0. Assumptions", cell B13, in the Sushi Restaurant Financial Projections) is the real usage of the whole menu, with case shrink, trim that is not reused, rice and nori thrown out, staff meals and comps, so this weighted theoretical cost comes out lower. Do not copy it into the plan.

Sheet Instructions
A1: INSTRUCTIONS — Sushi Fish, Rice & Costing Calculator
A2: Three tools in one workbook: the "Fish Yield" sheet tells you what a usable lb of whole salmon, salmon fillet and tuna saku costs, what each slice, cut and roll is worth and whether buying the whole fish pays off; the "Sushi Rice" sheet calculates the sushi rice that 1 lb of raw rice makes, its cost, how many nigiri you get per lb and how much rice to buy per day; the "Costing" sheet calculates the cost, food cost, margin and menu price of 14 products, with the margin dine-in, take-out and on the marketplace, and the weighted food cost of your week. You type only in the GREEN cells; everything else is calculated.
A3: Every default is a Kit estimate, editable: coherent examples for the case of the business plan, not anyone's prices. Replace them with your distributor's prices and with what you measure at your counter before you decide menu prices.
A4: HOW THIS FILE FITS THE KIT
A6: This calculator is one of four files: Sushi Restaurant Business Plan, Sushi Restaurant Financial Projections, Sushi Restaurant Startup Checklist and this one. The cost per piece you get here is NOT copied into the plan: the plan uses the real usage of the whole menu (see "From theoretical food cost to the plan's 32%" below).
A7: SHEET "FISH YIELD"
A9: 1. Measure your yield. Weigh 3 whole salmon, break them down, weigh the usable loin from each and divide by the weight of the whole fish; type the average in "Yield". Weigh also the trim you reuse (spicy mix, maki, poke) and type it in "Trim you reuse". Weigh 10 nigiri slices and 10 sashimi cuts and use the average in ounces.
A10: 2. The cost per usable lb is the price ÷ (yield + trim) ÷ (1 − case shrink). It is the number that feeds the costing: with the Kit estimates it comes out at $11.28 per lb for the whole salmon, $23.92 for the fillet and $25.48 for the tuna saku.
A11: 3. Cleaning costs money too. The kit assumes 25 minutes per whole fish, a figure with no source: time it. The head sushi chef cost is estimated at $33.00 an hour: $5,199 a month × 12 + 10% payroll taxes ÷ 2,080 h ≈ $33/h. The sheet tells you up to what cleaning cost per usable lb buying the whole fish still pays off.
A12: 4. Parasite destruction (FDA Food Code 2022, 3-402.11). Fish served raw or undercooked is frozen at −4 °F or below for 168 hours (7 days), or at −31 °F until solid and held 15 hours, or at −31 °F until solid and held 24 hours at −4 °F. Tuna species and feed-raised aquaculture fish such as farmed salmon are exempt; the farmed fish only with a written statement from the supplier or the farm, and the kit also files the tuna invoice that names the species. If the fish arrives frozen, keep the supplier's written agreement or statement for every lot, showing the freezing time and temperature. Keep the records 90 days (3-402.12). "Sushi-grade" has no legal definition: a supplier label is no substitute for the freezing records or the written statement. The dropdown on the sheet is a reminder only: it changes no figure.
A13: 5. Scombrotoxin. Receive tuna, yellowtail and mackerel at 40 °F or below and keep them cold. Raw or undercooked fish needs the consumer advisory (3-603.11) on the menu and on your marketplace listings.
A14: SHEET "SUSHI RICE"
... A35: Planning tool, not financial, tax or legal advice. Requirements vary by state, county and city — check with your accountant and local authorities.
