Workbook

Sheet 0. Assumptions
A1: ASSUMPTIONS — the RATES and DRIVERS of the model are typed here
A2: Change the GREEN cells: the rest of the workbook recalculates on its own. Expense items are typed on their own tab (also in green) and are not repeated here. Amounts are in your currency.
A3: BUSINESS ACTIVITY
A4: Covers per day (year-1 average) | B4: 115 | C4: Equivalent covers per day, year-1 average: about 70 dine-in (sushi bar and tables), about 25 from take-out and pickup (15.6 orders) and about 20 from delivery marketplaces (12.5 orders), counting each order as 1.6 covers. A Friday or Saturday night runs well above the average and a Tuesday well below it (Kit estimate). Compare it with the foot traffic on your street on a Friday night and a Tuesday at lunch
A5: Average check (excl. sales tax) | B5: 32.5 | C5: Per cover, EXCL. sales tax and tip: a dine-in guest spends about $36.00 (food $28.50 plus beverage $7.50); a take-out order averages $41.00 and a marketplace order $46.00 (the menu is about 15% higher there and the order a bit bigger). At 1.6 covers per order, that is $25.60 and $28.75 per cover, and the weighted average of the three channels is $32.48; the example rounds it to $32.50 (Kit estimate). The "Menu price incl. sales tax (calculated)" row below shows the price with your local rate applied
A6: Operating days per year | B6: 310 | C6: 365 days minus 52 Mondays (closed) and three holidays: Thanksgiving, Christmas Day and New Year's Day. It is the SAME figure for the P&L, the break-even, the scenarios and the staffing hours
A7: Volume growth in year 2 | B7: 0.06 | C7: Repeat neighborhood regulars and more pickup in year 2. It applies to covers at the same average check; staffing does NOT rise with this percentage: it comes from the "Staffing" tab
A8: Volume growth in year 3 | B8: 0.04 | C8: On year 2. Conservative: the ceiling is set by the sushi bar (10 seats), the 40 seats on Friday and Saturday nights and what the head sushi chef (itamae) and the sushi team can cut
A9: Menu price incl. sales tax (calculated) | B9: =IFERROR(IF($B$5="","",$B$5*(1+SUMPRODUCT('3-Year P&L'!$E$10:$E$11,'3-Year P&L'!$G$10:$G$11))),"") -> 35.1 | C9: =IFERROR("Average check excl. sales tax plus the weighted sales tax of your sales lines ("&TEXT(SUMPRODUCT('3-Year P&L'!$E$10:$E$11,'3-Year P&L'!$G$10:$G$11)*100,"0")&"%), rounded. In the US, menu prices usually exclude sales tax and it is added at the register; the beverage share in column H of the beverage line of the P&L only moves this average if your state taxes alcohol at another rate. "&"In the UK, menu prices include VAT.","") -> Average check excl. sales tax plus the weighted sales tax of your sales lines (8%), rounded. In the US, menu prices usually exclude sales tax and it is added at the register; the beverage share in column H of the beverage line of the P&L only moves this average if your state taxes alcohol at another rate. In the UK, menu prices include VAT.
A10: SALES MIX AND COST OF GOODS SOLD
A11: FOOD share of total sales | B11: 0.85 | C11: Share of FOOD in total sales. It is an INPUT: change it here and the P&L, the cash flow and the sales tax collected recalculate on their own
A12: BEVERAGE share of total sales | B12: =IFERROR(IF(COUNT(B11)=0,"",1-B11),"") -> 0.15 | C12: Calculated as the remainder: food + beverage = 100%
A13: Cost of goods sold on FOOD sales | B13: 0.32 | C13: Cost of goods sold on food sales: about 32%, on the prudent side. Consulting blogs put sushi food cost at 30-40%. The theoretical cost per piece in the Sushi Fish, Rice & Costing Calculator comes out lower (the salmon nigiri and the California roll are cheap, the spicy tuna is not), but the real number is what you buy against what you sell: it also carries fish that goes unsold in the sushi case, trim that is not reused, rice and nori thrown out at close, staff meals, comps and ordering mistakes, and fish prices are Kit estimates. Measure your usage in the first quarter and change this cell
A14: Cost of goods sold on BEVERAGE sales | B14: 0.24 | C14: Beverage cost of about 24% of menu price (Kit estimate): beer, sake and wine are about 70% of beverage sales, and the rest is soft drinks, water and tea. Ask your distributor for the price of sake and beer in writing: sake often depends on an importer
A15: Disposables and packaging as % of sales | B15: 0.03 | C15: Sushi trays, soy cups, chopsticks, bags, napkins and wipes for every order that leaves the restaurant, plus containers for leftovers. Local packaging ordinances vary (some cities charge for or ban single-use items): check yours before ordering
A16: Delivery share of total sales | B16: 0.15 | C16: Sales through delivery marketplaces (DoorDash, Uber Eats, Grubhub) with their commission, as a share of total sales. Pickup orders placed directly with you (phone or website) pay no commission and do not go here: push them. Rolls and platters travel well; tempura and gyoza arrive worse, so do not go higher without testing
A17: Delivery platform fee | B17: 0.25 | C17: The example uses 25%, a Plus plan on DoorDash or Uber Eats (the Basic plan is about 15% with little visibility, Premier is 30%, and app pickup orders add 6-10%). Check your contract. If you deliver yourself, enter 0 and add the driver to the "Staffing" tab as a W-2 employee, with hired and non-owned auto insurance (check your state)
A18: Card processing fee | B18: 0.03 | C18: Card and mobile wallet (contactless) processing fees on total sales. Ask your POS provider for its rate
A19: LABOR
A20: Employer payroll taxes | B20: 0.1 | C20: FICA (Social Security 6.2% + Medicare 1.45%) + federal and state unemployment taxes (FUTA / SUTA) + workers' comp. About 10% in total: adjust it to your state and your insurance carrier
A21: Monthly pay periods per year (keep 12) | B21: 12 | C21: Annual gross pay = monthly gross pay × this number. Keep 12 in the US: it counts the monthly salaries the model pays in a year, not how often you run payroll (weekly or biweekly payroll pays the same annual amount)
A22: Federal minimum wage, annual full-time | B22: 15080 | C22: US federal minimum wage: 7.25 per hour × 2,080 hours = 15,080 per year for a full-time job. Your state or city may set a higher floor: enter it in the state / local minimum wage cell below. Check the current rates at dol.gov
A23: RENT AND FIXED COSTS
A24: Monthly rent | B24: 4500 | C24: About 1,800 sq ft (167 sq m) of second-generation restaurant space with a Type I hood route to the roof possible: a sushi bar counter in view with 10 seats, a 30-seat dining room, a small hot kitchen, a walk-in cooler and a to-go packing station by the door, in a neighborhood with nightlife in a mid-size city (150,000 to 500,000 people), no key money: about $30 per sq ft a year (Kit estimate, editable). The weight of rent on sales is calculated by the workbook itself in the rent row of the "3-Year P&L"
A25: Security deposit (months of rent) | B25: 2 | C25: Security deposit, in months of rent. The example uses two; commercial leases commonly ask for one to three, and some landlords also want a personal guarantee: check it with your attorney
A26: Monthly utilities (electricity, water, gas) | B26: 1700 | C26: Gas (rice cookers, fryer, range and griddle), electricity (walk-in, reach-ins, freezer and sushi case, hood and HVAC) and water. The example uses $1,700 per month (Kit estimate). Ask the landlord for the space's utility history
A27: Insurance (per year) | B27: 8000 | C27: General liability, product liability (you serve raw fish), liquor liability (beer, sake & wine), property with refrigeration breakdown (spoilage) cover and workers' comp: about $8,000 a year in the example (Kit estimate). Tell your insurance broker you serve raw fish and run a fryer: it changes the premium and the terms
A28: Miscellaneous and contingency as % of sales | B28: 0.01 | C28: Cushion for unbudgeted running costs (small repairs, broken smallwares, menu tests)
A29: FINANCING
A30: Owner's equity contributed | B30: 130000 | C30: Owner's cash. Lenders usually expect an owner equity injection (often around 10% for SBA start-ups; many want 20-30%) toward the cash need
A31: Loan requested | B31: 256000 | C31: Principal requested. The "Financing" tab compares what you put in with the cash need on "Startup Costs" and tells you whether you have a surplus or a shortfall: adjust the loan with that figure. The example is an SBA 7(a) loan, which you apply for through your lender (SBA Microloans go up to $50,000)
A32: Nominal annual interest rate (not APR) | B32: 0.1 | C32: Nominal annual rate, not APR. The example uses 10%. Ask two lenders for a quote before you set it; the refrigeration and the kitchen equipment can also be financed through equipment financing or a lease: compare
A33: Loan term (years) | B33: 10 | C33: Total years, interest-only period included
A34: Interest-only period (years) | B34: 0 | C34: Interest-only period in years. The example uses 0: principal is repaid from the start. If your lender gives you an interest-only period while you build out, enter it here and check the cash cushion of that year on the "Break-Even" tab
A35: Working capital (months of fixed costs) | B35: 3 | C35: Three months of fixed costs: the cushion for the opening ramp-up, which with Month 1 in January runs from January to April, when the calendar is also at its slowest
A36: TAXES
A37: Effective income tax rate (years 1-2) | B37: 0.25 | C37: Example: 21% federal rate for a C corporation plus state tax, rounded to 25%. If you operate as a sole proprietorship, LLC taxed as a pass-through or S corporation, the business itself pays 0% here and you pay tax on the profit personally: set this to 0 and budget for your personal tax separately. The model applies this rate to the first two years with positive taxable income
A38: Effective income tax rate (from year 3) | B38: 0.25 | C38: From the third year with positive taxable income. Same example rate (21% federal C corporation + state). Confirm the rate that applies to you with your accountant and change it here
A39: Sales tax rate on sales | B39: 0.08 | C39: Example rate: state + local sales tax combined. It varies widely by state and city: look up yours. UK: 20% VAT on hot food and dine-in
A40: Sales tax rate on alcohol to go | B40: 0.08 | C40: Rate on alcohol served to go or by delivery. The example uses ONE sales tax rate (8%) for everything, so this cell equals the rate on sales; some states tax food to go or alcohol differently, so check yours. There is no credit for the tax you pay on purchases (see the recoverable input tax cell below)
A41: Recoverable input tax on purchases and capex | B41: 0 | C41: In the US, the sales tax you pay on purchases is a cost, not a credit: leave this at 0%. UK: 20% if you are VAT-registered
A42: Net operating losses carried forward | B42: 0 | C42: Net operating losses from earlier years still to be offset at the start. Federal rules let you offset up to 80% of taxable income in a year; the model offsets 100% as a simplification
A43: DEPRECIATION
A44: Useful life of build-out and fixtures (years) | B44: 10 | C44: Build-out and installations: sushi bar counter, electrical, plumbing, HVAC, Type I hood and exhaust, signage and facade. Ten years straight-line in the example: confirm the tax treatment with your CPA
A45: Useful life of machinery, furniture and equipment (years) | B45: 7 | C45: Sushi case, rice cookers, freezer, hot-line equipment, walk-in and reach-ins, dish machine, smallwares, furniture and POS: seven years straight-line in the example. Confirm the tax life with your CPA
A47: GROWTH AND COST INFLATION
A48: Annual increase in fixed costs | B48: 0 | C48: SET TO ZERO: all three columns are in year-1 prices (real terms). Raise it if you want to project in nominal terms
A49: RAMP-UP AND CAPACITY
A50: Implied seat turns per day (calculated) | B50: =IFERROR($B$4/$B$51,"") -> 2.875 | C50: =IFERROR("That is "&TEXT(INT(ROUND(B50,1)),"0")&"."&TEXT(ROUND(MOD(ROUND(B50,1),1)*10,0),"0")&" seat turns per day on the "&TEXT($B$51,"0")&" seats in the cell below. "&"It includes the take-out and delivery covers (1 order = 1.6 covers), which do not take a seat: the real turns of your dining room are lower (in the example, about six in ten covers eat in). Compare it with the ceiling on seat turns typed in ""Break-Even"".","") -> That is 2.9 seat turns per day on the 40 seats in the cell below. It includes the take-out and delivery covers (1 order = 1.6 covers), which do not take a seat: the real turns of your dining room are lower (in the example, about six in ten covers eat in). Compare it with the ceiling on seat turns typed in "Break-Even".
A51: Seating capacity (seats, sushi bar included) | B51: 40 | C51: Indoor seats: 10 at the sushi bar in front of the sushi case and 30 at tables. Someone who picks up an order or gets it delivered does not take a seat: that is why the seat turns in the row above come out higher than what your dining room really does
A52: Month-1 activity as a % of steady-state activity | B52: 0.75 | C52: A new sushi restaurant draws curious first-timers in its first month, but regulars and your ratings on the delivery apps take a quarter to build: Month 1 (January) brings in 75% of what it will bring in at month four. With 100% the ramp-up is removed
A53: Months to reach steady state | B53: 4 | C53: Four months to reach cruising speed: January to April
A54: Months of rent BEFORE opening (build-out and permits) | B54: 2 | C54: Two months of rent before opening: the sushi bar build-out, the hood and the permits. If the lender funds the loan when construction starts, add the interest of those months, which this workbook does not count, and remember that any interest-only period starts at signing
A55: Contingency on the BUILD-OUT lines of the space block (%) | B55: 0.1 | C55: Cushion on the build-out and installations of the space, which is where surprises show up (the hood route, the electrical service for the kitchen, the grease interceptor). A lender will not finance a renovation without one
A57: RECEIPTS, PAYMENTS AND SALES TAX BREAKDOWN
A58: Average collection days | B58: 2 | C58: Weighted average: dine-in and pickup are paid on the spot, while delivery marketplaces settle weekly what they sell (15% of sales). With weekly payouts that is about 2 days
A59: Average days to pay suppliers | B59: 14 | C59: Payment terms with the fish, rice, nori and beverage suppliers: what they finance for you. Negotiate it in writing: if your fish supplier asks for weekly payment or COD, lower this figure
A60: Month of extra pay period 1 (only if pay periods > 12) | B60: 7 | C60: Month of the 12-Month Cash Flow in which a summer extra payment falls. It only matters if you enter more than 12 pay periods; with 12 there are no extra payments. If you use it, July is Month 7, because Month 1 of the plan is January
A61: Month of extra pay period 2 (only if pay periods > 12) | B61: 12 | C61: Month of the 12-Month Cash Flow in which a holiday extra payment falls. It only matters if you enter more than 12 pay periods; with 12 there are no extra payments. If you use it, December is Month 12, because Month 1 of the plan is January
A62: Alcohol share of beverage purchases (reference only: no input credit in the US) | B62: 0.7 | C62: Reference only: in the US the sales tax you pay on purchases is a cost, not a credit (B41 = 0%), so this share moves no figure in the workbook. The sales tax you COLLECT on beverages is set by the beverage line of the P&L (column H)
A63: Sales tax rate on alcohol served on site | B63: 0.08 | C63: NO EFFECT in this workbook: the sales tax collected on beverages is set by the beverage line of the P&L. With the example, beer, sake, wine, soft drinks and food all pay the same 8% (state + local); if your state taxes alcohol at another rate, type it in B40 and the alcohol share in column H of that line
A64: CONTROL THRESHOLDS AND FLOORS
A65: DSCR limit (minimum acceptable) | B65: 1.15 | C65: Below 1.0 the business does not generate enough to repay the loan. Lenders often write a minimum DSCR into the loan covenants: ask yours. Kit default: 1.15×
A66: DSCR target (green) | B66: 1.25 | C66: What lenders commonly look for before approving a loan comfortably. Kit default: 1.25× (editable estimate)
A67: Minimum cushion above break-even | B67: 0.15 | C67: How far projected sales must exceed cash break-even sales (fixed costs plus the loan payment). The drop you can absorb is a bit smaller: with a 15% cushion, 13% of projected sales
A68: State / local minimum wage, annual full-time | C68: State / local minimum wage; this plan budgets at least $15 per hour for everyone. Enter the full-time annual floor of your state and city if it is higher than the federal one ($7.25 per hour). With 0 the status light compares only against the federal minimum

Sheet Startup Costs
A1: SUSHI RESTAURANT BUSINESS PLAN: SUSHI BAR, TAKE-OUT & DELIVERY
A2: Estimated Startup Costs — sushi restaurant with a sushi bar counter, 40 seats, take-out and delivery
A3: US kit example (2026) — replace with your own quotes.
A5: Item | B5: Amount | C5: % of startup costs | D5: Notes | E5: Taxable / recoverable tax?
A6: STARTUP COSTS | B6: =IFERROR(IF(COUNT(B7:B27)=0,"",SUM(B7:B27)),"") -> 255100 | C6: =IFERROR(B6/$B$30,"") -> 0.66232834
A7: Architect, MEP & hood drawings, plan review & permit fees | B7: 14000 | C7: =IFERROR(B7/$B$30,"") -> 0.03634887 | D7: Architect, MEP and hood drawings, plan review (Food Code 8-201.11) and permit fees. If you choose a variance for the sushi rice, ask your health department for the plan review fee of the HACCP plan: in some counties it can pass $2,000 | E7: Yes
A8: Build-out (second-generation space, 1,800 sq ft) with sushi bar counter, signage & facade | B8: 75000 | C8: =IFERROR(B8/$B$30,"") -> 0.19472609 | D8: Build-out of a second-generation restaurant space of 1,800 sq ft: sushi bar counter in view, finished kitchen, walk-in room, slip-resistant floors, restrooms (one ADA-accessible), ceilings and acoustic insulation, plus signage and facade. Kit estimate: get two quotes | E8: Yes
A9: Type I hood (about 10 ft), UL 300 fire suppression & makeup air | B9: 18000 | C9: =IFERROR(B9/$B$30,"") -> 0.046734262 | D9: Type I hood of about 10 ft with UL 300 fire suppression and makeup air over the tempura fryer, the range and the griddle. Ask the fire marshal and the mechanical inspector in writing what your city requires, and whether the gas rice cookers go under the hood. Installers rarely quote by the foot: ask for an offer with your plans | E9: Yes
A10: Electrical service & panel | B10: 11000 | C10: =IFERROR(B10/$B$30,"") -> 0.028559827 | D10: Electrical service for the walk-in, the sushi case, the hood and the lighting. Ask what service is available BEFORE you sign: a new service takes time | E10: Yes
A11: Plumbing, grease interceptor, HVAC & gas lines | B11: 15000 | C11: =IFERROR(B11/$B$30,"") -> 0.038945218 | D11: Hot and cold water in the kitchen and at the sushi bar, drains with a grease interceptor, HVAC for the dining room and the gas lines for the rice cookers and the fryer | E11: Yes
A12: Refrigerated sushi case (6 ft) | B12: 4000 | C12: =IFERROR(B12/$B$30,"") -> 0.010385391 | D12: The case for the neta (the cut fish that goes on top of the rice), in view of the guest and for service only, not for storing fish. A 6 ft Hoshizaki case (70.9 in) lists around $4,045 (read October 2026); the example uses $4,000 | E12: Yes
A13: Commercial gas rice cookers × 2 & rice warmers | B13: 2500 | C13: =IFERROR(B13/$B$30,"") -> 0.0064908697 | D13: Two commercial gas rice cookers and rice warmers. The hangiri, the wooden tub where the sushi rice is seasoned, goes under smallwares. Kit estimate: ask your equipment dealer for quotes | E13: Yes
A14: Freezer (−4 °F or colder) with temperature logger | B14: 3500 | C14: =IFERROR(B14/$B$30,"") -> 0.0090872176 | D14: The parasite rule (FDA Food Code 3-402.11) asks for raw fish to be frozen at −4 °F or below for 7 days, or at −31 °F until solid plus 15 hours, or at −31 °F until solid plus 24 hours at −4 °F. Tuna and feed-raised aquaculture fish are exempt with a written supplier statement, and records are kept 90 days. This freezer HOLDS the fish you buy already treated, at −4 °F or below with a logger; freezing fish yourself takes a lot of freezer space. Kit estimate: ask for the data sheet | E14: Yes
A15: Fryer, range & griddle (tempura, gyoza, miso) | B15: 6000 | C15: =IFERROR(B15/$B$30,"") -> 0.015578087 | D15: Fryer for the tempura, range for the miso and stocks, and griddle for the gyoza and teriyaki, all under the Type I hood. Kit estimate | E15: Yes
A16: Walk-in cooler (6×8) | B16: 12800 | C16: =IFERROR(B16/$B$30,"") -> 0.033233253 | D16: Walk-in cooler (6×8 ft) for the rice, the vegetables, the sauces and the backup fish stock, with cold holding at 41 °F or below. A 6×8 ft walk-in lists around $12,800 (Norlake Kold Locker, read October 2026) | E16: Yes
A17: Reach-in fish refrigerators (32-34 °F), prep tables, beverage & sake cooler, ice machine | B17: 11000 | C17: =IFERROR(B17/$B$30,"") -> 0.028559827 | D17: Reach-in refrigerators for fish held at 32-34 °F (cold holding is 41 °F or below, and tuna must be received at 40 °F or below), refrigerated prep tables for the sushi bar, a beverage and sake cooler and an ice machine | E17: Yes
A18: 3-comp sink, dish machine, hand sinks, shelving & stainless | B18: 11500 | C18: =IFERROR(B18/$B$30,"") -> 0.029858001 | D18: Three-compartment sink, dish machine, hands-free hand sinks, stainless tables and shelving | E18: Yes
... A24: Opening inventory (fish, rice, nori, sauces, disposables, beverage) | B24: 7000 | C24: =IFERROR(B24/$B$30,"") -> 0.018174435 | D24: Fish (bought already treated or exempt, with the supplier's letter), Calrose sushi rice, nori, sauces, the first order of to-go packaging and the beverages, sake included (order early: it often depends on an importer) | E24: Yes
A25: Security deposit | B25: =IFERROR(IF('0. Assumptions'!$B$24="","",'0. Assumptions'!$B$24*'0. Assumptions'!$B$25),"") -> 9000 | C25: =IFERROR(B25/$B$30,"") -> 0.023367131 | D25: =IFERROR(""&TEXT('0. Assumptions'!$B$25,"0")&IF('0. Assumptions'!$B$25=1," month"," months")&" of rent, from ""0. Assumptions"". Refundable when the lease ends: it is not depreciated and carries no tax","") -> 2 months of rent, from "0. Assumptions". Refundable when the lease ends: it is not depreciated and carries no tax | E25: No
A26: Rent paid before opening | B26: =IFERROR(IF('0. Assumptions'!$B$24="","",'0. Assumptions'!$B$24*'0. Assumptions'!$B$54),"") -> 9000 | C26: =IFERROR(B26/$B$30,"") -> 0.023367131 | D26: =IFERROR("Rent "&IF('0. Assumptions'!$B$54=1,"for the month","for the "&TEXT('0. Assumptions'!$B$54,"0")&" months")&" of build-out and permits before opening. It does not overlap the P&L, which starts on opening day: its twelve months are twelve trading months","") -> Rent for the 2 months of build-out and permits before opening. It does not overlap the P&L, which starts on opening day: its twelve months are twelve trading months | E26: Yes
A27: Build-out and setup contingency | B27: =IFERROR(IF(COUNT(B7,B8,B9,B10,B11)=0,"",ROUND((B7+B8+B9+B10+B11)*'0. Assumptions'!$B$55,0)),"") -> 13300 | C27: =IFERROR(B27/$B$30,"") -> 0.034531427 | D27: =IFERROR("At "&TEXT('0. Assumptions'!$B$55,"0%")&" of the BUILD-OUT items of this block (architect, MEP & hood drawings and permit fees; build-out with the sushi bar counter, signage & facade; Type I hood (about 10 ft), UL 300 fire suppression & makeup air; "&"electrical service & panel; plumbing, grease interceptor, HVAC & gas lines), not of the whole block: the sushi case, the rice cookers, the equipment and the other items are left out. "&"No lender funds a build-out without a cushion: the percentage is in ""0. Assumptions""","") -> At 10% of the BUILD-OUT items of this block (architect, MEP & hood drawings and permit fees; build-out with the sushi bar counter, signage & facade; Type I hood (about 10 ft), UL 300 fire suppression & makeup air; electrical service & panel; plumbing, grease interceptor, HVAC & gas lines), not of the whole block: the sushi case, the rice cookers, the equipment and the other items are left out. No lender funds a build-out without a cushion: the percentage is in "0. Assumptions" | E27: Yes
A28: WORKING CAPITAL | B28: =IFERROR(IF(B29="","",B29),"") -> 130056.4 | C28: =IFERROR(B28/$B$30,"") -> 0.33767166
A29: Operating cushion until break-even | B29: =IFERROR(IF('0. Assumptions'!$B$35*('3-Year P&L'!$B$37-'3-Year P&L'!$B$35)=0,"",'0. Assumptions'!$B$35*('3-Year P&L'!$B$37-'3-Year P&L'!$B$35)/12),"") -> 130056.4 | C29: =IFERROR(B29/$B$30,"") -> 0.33767166 | D29: =IFERROR("Covers "&TEXT('0. Assumptions'!$B$35,"0")&IF('0. Assumptions'!$B$35=1," month"," months")&" of year-1 CASH fixed costs (the P&L fixed costs minus depreciation, which is not paid out), the minimum the Instructions of this workbook ask for","") -> Covers 3 months of year-1 CASH fixed costs (the P&L fixed costs minus depreciation, which is not paid out), the minimum the Instructions of this workbook ask for | E29: No
A30: TOTAL STARTUP COSTS (sum of the blocks) | B30: =IFERROR(B6+B28,"") -> 385156.4 | D30: =IFERROR("The percentages in column C are read on this figure, which includes the working capital ("&TEXT(C28,"0%")&" of the total). To compare the breakdown with another plan, use the CAPEX row below.","") -> The percentages in column C are read on this figure, which includes the working capital (34% of the total). To compare the breakdown with another plan, use the CAPEX row below.
A31: CAPEX (startup costs excluding working capital) | B31: =IFERROR(B30-B28,"") -> 255100 | D31: What you buy: build-out, equipment, launch and formation costs. The cash cushion is not an investment: it is working capital
A32: Recoverable input tax on capex | B32: =IFERROR(IF(B30="","",SUMIF($E$7:$E$27,"Yes",$B$7:$B$27)*'0. Assumptions'!$B$41),"") -> 0 | D32: =IFERROR("At "&TEXT('0. Assumptions'!$B$41,"0%")&" on the items marked ""Yes"" in the tax column. US: the sales tax you pay on equipment is part of its cost and is not recovered, so this rate is 0. UK (VAT-registered): 20%, reclaimed on your VAT return, but you pay it first, so the loan has to cover it","") -> At 0% on the items marked "Yes" in the tax column. US: the sales tax you pay on equipment is part of its cost and is not recovered, so this rate is 0. UK (VAT-registered): 20%, reclaimed on your VAT return, but you pay it first, so the loan has to cover it
A33: TOTAL CASH NEEDED AT LAUNCH | B33: =IFERROR(B30+B32,"") -> 385156.4 | D33: This is the figure the Financing tab has to cover
A34: DEPRECIATION BASES (not added to startup costs)
A35: Build-out, fixtures and setup | B35: =IFERROR(IF(B7="","",B7+B8+B9+B10+B11+B27),"") -> 146300 | D35: =IFERROR("Depreciated over "&TEXT('0. Assumptions'!$B$44,"0")&" years","") -> Depreciated over 10 years
A36: Machinery, furniture and equipment | B36: =IFERROR(IF(B12="","",B12+B13+B14+B15+B16+B17+B18+B19+B20+B21),"") -> 75800 | D36: =IFERROR("Depreciated over "&TEXT('0. Assumptions'!$B$45,"0")&" years","") -> Depreciated over 7 years
A37: Annual depreciation of fixed assets | B37: =IFERROR(B35/MAX(1,'0. Assumptions'!$B$44)+B36/MAX(1,'0. Assumptions'!$B$45),"") -> 25458.571 | D37: =IFERROR("Not depreciated, because they are not fixed assets: LLC, legal and food safety plan; branding, website, photos and launch; opening inventory; security deposit; pre-opening rent and the working capital reserve. They add up to "&TEXT(B30-B35-B36,"#,##0")&" of the "&TEXT(B30,"#,##0")&" total investment.","") -> Not depreciated, because they are not fixed assets: LLC, legal and food safety plan; branding, website, photos and launch; opening inventory; security deposit; pre-opening rent and the working capital reserve. They add up to 163056 of the 385156 total investment.

Sheet 3-Year P&L
A1: PRO FORMA P&L — 3 YEARS
A2: Base case — sushi restaurant: sushi bar and tables, take-out and delivery
A4: Item | B4: Year 1 | C4: Year 2 | D4: Year 3 | E4: % of sales (year 1) | F4: Notes | G4: Sales tax rate on the line (%) | H4: Beverage share taxed at the alcohol rate in B40 (%)
A5: REVENUE
A6: Covers per day (average) | B6: =IFERROR(IF('0. Assumptions'!$B$4="","",'0. Assumptions'!$B$4),"") -> 115 | C6: =IFERROR(B6*(1+'0. Assumptions'!$B$7),"") -> 121.9 | D6: =IFERROR(C6*(1+'0. Assumptions'!$B$8),"") -> 126.776 | F6: Growth for years 2 and 3 is set in "0. Assumptions"
A7: Average check (excl. sales tax) | B7: =IFERROR(IF('0. Assumptions'!$B$5="","",'0. Assumptions'!$B$5),"") -> 32.5 | C7: =IFERROR(IF(B7="","",B7),"") -> 32.5 | D7: =IFERROR(IF(C7="","",C7),"") -> 32.5 | F7: Held constant at year-1 prices: a price increase is a separate decision
A8: Operating days per year | B8: =IFERROR(IF('0. Assumptions'!$B$6="","",'0. Assumptions'!$B$6),"") -> 310 | C8: =IFERROR(IF(B8="","",B8),"") -> 310 | D8: =IFERROR(IF(C8="","",C8),"") -> 310
A9: TOTAL REVENUE (excl. sales tax) | B9: =IFERROR(IF(B6*B7*B8=0,"",B6*B7*B8),"") -> 1158625 | C9: =IFERROR(IF(C6*C7*C8=0,"",C6*C7*C8),"") -> 1228142.5 | D9: =IFERROR(IF(D6*D7*D8=0,"",D6*D7*D8),"") -> 1277268.2 | E9: =IFERROR(IF(B9="","",1),"") -> 1
A10: Food sales (sushi, rolls & kitchen: dine-in, take-out & delivery) | B10: =IFERROR(IF(B9="","",B9*$E$10),"") -> 984831.25 | C10: =IFERROR(IF(C9="","",C9*$E$10),"") -> 1043921.1 | D10: =IFERROR(IF(D9="","",D9*$E$10),"") -> 1085678 | E10: =IFERROR(IF('0. Assumptions'!$B$11="","",'0. Assumptions'!$B$11),"") -> 0.85 | F10: Sushi, rolls, sashimi, poke, appetizers (edamame, gyoza, tempura), miso soup and desserts: about 67% of sales dine-in, 17% take-out and 15% through delivery marketplaces. One sales tax rate in the example, whether it is eaten at the sushi bar or taken away | G10: =IFERROR(IF(B9="","",'0. Assumptions'!$B$39),"") -> 0.08
A11: Beverage sales (beer, sake, wine, soft drinks & tea) | B11: =IFERROR(IF(B9="","",B9*$E$11),"") -> 173793.75 | C11: =IFERROR(IF(C9="","",C9*$E$11),"") -> 184221.38 | D11: =IFERROR(IF(D9="","",D9*$E$11),"") -> 191590.23 | E11: =IFERROR(IF('0. Assumptions'!$B$12="","",'0. Assumptions'!$B$12),"") -> 0.15 | F11: Dine-in beverages and the drinks that go out with orders (beer, sake, wine, soft drinks and tea) · Column H is the share of beverage sales taxed at the alcohol rate in "0. Assumptions" B40. With the example rates (B39 = B40 = 8%: state + local) it changes nothing. Some states tax alcohol differently: type your alcohol rate in B40 and the alcohol share of beverage sales here | G11: =IFERROR(IF(B9="","",H11*'0. Assumptions'!$B$40+(1-H11)*'0. Assumptions'!$B$39),"") -> 0.08 | H11: 0.7
A12: VARIABLE COSTS
A13: Cost of goods sold — food | B13: =IFERROR(IF(B9="","",B9*'0. Assumptions'!$B$11*'0. Assumptions'!$B$13),"") -> 315146 | C13: =IFERROR(IF(C9="","",C9*'0. Assumptions'!$B$11*'0. Assumptions'!$B$13),"") -> 334054.76 | D13: =IFERROR(IF(D9="","",D9*'0. Assumptions'!$B$11*'0. Assumptions'!$B$13),"") -> 347416.95 | E13: =IFERROR(B13/$B$9,"") -> 0.272 | F13: =IFERROR("At "&TEXT('0. Assumptions'!$B$13,"0%")&" of FOOD sales, not of total sales: beverages have their own line · "&"fish and seafood, sushi rice, nori, imitation crab, avocado, produce, sauces and tempura ingredients: check it against your distributor invoices and the Sushi Fish, Rice & Costing Calculator","") -> At 32% of FOOD sales, not of total sales: beverages have their own line · fish and seafood, sushi rice, nori, imitation crab, avocado, produce, sauces and tempura ingredients: check it against your distributor invoices and the Sushi Fish, Rice & Costing Calculator | G13: 0
A14: Cost of goods sold — beverage | B14: =IFERROR(IF(B9="","",B9*'0. Assumptions'!$B$12*'0. Assumptions'!$B$14),"") -> 41710.5 | C14: =IFERROR(IF(C9="","",C9*'0. Assumptions'!$B$12*'0. Assumptions'!$B$14),"") -> 44213.13 | D14: =IFERROR(IF(D9="","",D9*'0. Assumptions'!$B$12*'0. Assumptions'!$B$14),"") -> 45981.655 | E14: =IFERROR(B14/$B$9,"") -> 0.036 | F14: =IFERROR("At "&TEXT('0. Assumptions'!$B$14,"0%")&" of BEVERAGE sales","") -> At 24% of BEVERAGE sales | G14: =IFERROR(IF(B9="","",'0. Assumptions'!$B$41),"") -> 0
A15: Disposables and packaging | B15: =IFERROR(IF(B9="","",B9*'0. Assumptions'!$B$15),"") -> 34758.75 | C15: =IFERROR(IF(C9="","",C9*'0. Assumptions'!$B$15),"") -> 36844.275 | D15: =IFERROR(IF(D9="","",D9*'0. Assumptions'!$B$15),"") -> 38318.046 | E15: =IFERROR(B15/$B$9,"") -> 0.03 | G15: =IFERROR(IF(B9="","",'0. Assumptions'!$B$41),"") -> 0
A16: Delivery platform fees | B16: =IFERROR(IF(B9="","",B9*'0. Assumptions'!$B$16*'0. Assumptions'!$B$17),"") -> 43448.438 | C16: =IFERROR(IF(C9="","",C9*'0. Assumptions'!$B$16*'0. Assumptions'!$B$17),"") -> 46055.344 | D16: =IFERROR(IF(D9="","",D9*'0. Assumptions'!$B$16*'0. Assumptions'!$B$17),"") -> 47897.558 | E16: =IFERROR(B16/$B$9,"") -> 0.0375 | F16: Applied to the sales of THAT CHANNEL. With 0% delivery in Assumptions, this line is zero | G16: =IFERROR(IF(B9="","",'0. Assumptions'!$B$41),"") -> 0
A17: Card processing fees | B17: =IFERROR(IF(B9="","",B9*'0. Assumptions'!$B$18),"") -> 34758.75 | C17: =IFERROR(IF(C9="","",C9*'0. Assumptions'!$B$18),"") -> 36844.275 | D17: =IFERROR(IF(D9="","",D9*'0. Assumptions'!$B$18),"") -> 38318.046 | E17: =IFERROR(B17/$B$9,"") -> 0.03 | F17: Card processing fees are not subject to sales tax: no tax is recovered or deducted for them | G17: 0
A18: Miscellaneous and contingency | B18: =IFERROR(IF(B9="","",B9*'0. Assumptions'!$B$28),"") -> 11586.25 | C18: =IFERROR(IF(C9="","",C9*'0. Assumptions'!$B$28),"") -> 12281.425 | D18: =IFERROR(IF(D9="","",D9*'0. Assumptions'!$B$28),"") -> 12772.682 | E18: =IFERROR(B18/$B$9,"") -> 0.01 | F18: =IFERROR("At "&TEXT('0. Assumptions'!$B$28,"0%")&" of sales. It is a VARIABLE cost: it moves with revenue, so it cannot sit in fixed costs","") -> At 1% of sales. It is a VARIABLE cost: it moves with revenue, so it cannot sit in fixed costs | G18: =IFERROR(IF(B9="","",'0. Assumptions'!$B$41),"") -> 0
A19: TOTAL VARIABLE COSTS | B19: =IFERROR(IF(B9="","",SUM(B13:B18)),"") -> 481408.69 | C19: =IFERROR(IF(C9="","",SUM(C13:C18)),"") -> 510293.21 | D19: =IFERROR(IF(D9="","",SUM(D13:D18)),"") -> 530704.94 | E19: =IFERROR(B19/$B$9,"") -> 0.4155
A20: GROSS MARGIN | B20: =IFERROR(IF(B9="","",B9-B19),"") -> 677216.31 | C20: =IFERROR(IF(C9="","",C9-C19),"") -> 717849.29 | D20: =IFERROR(IF(D9="","",D9-D19),"") -> 746563.26 | E20: =IFERROR(B20/$B$9,"") -> 0.5845
A21: FIXED COSTS
A22: Rent | B22: =IFERROR(IF(B9="","",'0. Assumptions'!$B$24*12),"") -> 54000 | C22: =IFERROR(IF(C9="","",B22*(1+'0. Assumptions'!$B$48)),"") -> 54000 | D22: =IFERROR(IF(D9="","",C22*(1+'0. Assumptions'!$B$48)),"") -> 54000 | E22: =IFERROR(B22/$B$9,"") -> 0.046606969 | F22: The monthly amount is on the "0. Assumptions" tab; here it is multiplied by twelve. The two months of rent before opening are on "Startup Costs" and are NOT counted twice | G22: =IFERROR(IF(B9="","",'0. Assumptions'!$B$41),"") -> 0
A23: Labor (wages + employer payroll taxes) | B23: =IFERROR(IF(B9="","",Staffing!$G$12),"") -> 384225.6 | C23: =IFERROR(IF(C9="","",Staffing!$B$16),"") -> 389225.6 | D23: =IFERROR(IF(D9="","",Staffing!$B$17),"") -> 394225.6 | E23: =IFERROR(B23/$B$9,"") -> 0.33162205 | F23: Comes from the Staffing tab: it is the SAME number, not a separate estimate. Years 2 and 3 add the new hires declared on that tab, not a percentage of volume | G23: 0
A24: Utilities (electricity, water, gas) | B24: =IFERROR(IF(B9="","",'0. Assumptions'!$B$26*12),"") -> 20400 | C24: =IFERROR(IF(C9="","",B24*(1+'0. Assumptions'!$B$48)),"") -> 20400 | D24: =IFERROR(IF(D9="","",C24*(1+'0. Assumptions'!$B$48)),"") -> 20400 | E24: =IFERROR(B24/$B$9,"") -> 0.017607077 | F24: Enter the monthly bills excl. sales tax. The workbook applies a single tax treatment to this whole line, the one in the column next to it; if one utility is taxed differently in your area, give it its own line | G24: =IFERROR(IF(B9="","",'0. Assumptions'!$B$41),"") -> 0
A25: Insurance (general + liquor liability + property + workers' comp) | B25: =IFERROR(IF(B9="","",'0. Assumptions'!$B$27),"") -> 8000 | C25: =IFERROR(IF(C9="","",B25*(1+'0. Assumptions'!$B$48)),"") -> 8000 | D25: =IFERROR(IF(D9="","",C25*(1+'0. Assumptions'!$B$48)),"") -> 8000 | E25: =IFERROR(B25/$B$9,"") -> 0.0069047362 | F25: Insurance premiums are not subject to sales tax: there is no recoverable tax on them | G25: 0
A26: Accounting & bookkeeping | B26: 4200 | C26: =IFERROR(IF(C9="","",B26*(1+'0. Assumptions'!$B$48)),"") -> 4200 | D26: =IFERROR(IF(D9="","",C26*(1+'0. Assumptions'!$B$48)),"") -> 4200 | E26: =IFERROR(B26/$B$9,"") -> 0.0036249865 | F26: Bookkeeping, income tax and payroll filings for the LLC, payroll processing and the staff paperwork (offer letters, I-9, W-4) | G26: =IFERROR(IF(B9="","",'0. Assumptions'!$B$41),"") -> 0
A27: Maintenance (semiannual hood cleaning, refrigeration & freezer, rice cookers) | B27: 3600 | C27: =IFERROR(IF(C9="","",B27*(1+'0. Assumptions'!$B$48)),"") -> 3600 | D27: =IFERROR(IF(D9="","",C27*(1+'0. Assumptions'!$B$48)),"") -> 3600 | E27: =IFERROR(B27/$B$9,"") -> 0.0031071313 | F27: The refrigeration technician for the walk-in, the reach-ins, the sushi case, the rice cookers and the freezer (which must hold −4 °F or below for the parasite records); hood and duct cleaning twice a year (NFPA 96: ask your fire marshal); and the calibration solutions for the pH meter if you use one | G27: =IFERROR(IF(B9="","",'0. Assumptions'!$B$41),"") -> 0
A28: Marketing and advertising | B28: 7000 | C28: =IFERROR(IF(C9="","",B28*(1+'0. Assumptions'!$B$48)),"") -> 7000 | D28: =IFERROR(IF(D9="","",C28*(1+'0. Assumptions'!$B$48)),"") -> 7000 | E28: =IFERROR(B28/$B$9,"") -> 0.0060416442 | F28: Google Business Profile, social media, photos, the delivery marketplaces' promotions and the peak dates (Valentine's Day, New Year's Eve platters and holiday parties); the opening campaign is in startup costs | G28: =IFERROR(IF(B9="","",'0. Assumptions'!$B$41),"") -> 0
A29: Software, POS & online ordering | B29: 3600 | C29: =IFERROR(IF(C9="","",B29*(1+'0. Assumptions'!$B$48)),"") -> 3600 | D29: =IFERROR(IF(D9="","",C29*(1+'0. Assumptions'!$B$48)),"") -> 3600 | E29: =IFERROR(B29/$B$9,"") -> 0.0031071313 | F29: POS subscription (a POS that reports sales tax), online ordering, the delivery tablets, phone and internet | G29: =IFERROR(IF(B9="","",'0. Assumptions'!$B$41),"") -> 0
A30: Cleaning, linens & uniforms | B30: 2400 | C30: =IFERROR(IF(C9="","",B30*(1+'0. Assumptions'!$B$48)),"") -> 2400 | D30: =IFERROR(IF(D9="","",C30*(1+'0. Assumptions'!$B$48)),"") -> 2400 | E30: =IFERROR(B30/$B$9,"") -> 0.0020714209 | F30: Cleaning supplies, uniform and towel laundry, gloves and any lab tests or records your written food safety plan calls for | G30: =IFERROR(IF(B9="","",'0. Assumptions'!$B$41),"") -> 0
A31: Waste, grease & used-oil hauling | B31: 1800 | C31: =IFERROR(IF(C9="","",B31*(1+'0. Assumptions'!$B$48)),"") -> 1800 | D31: =IFERROR(IF(D9="","",C31*(1+'0. Assumptions'!$B$48)),"") -> 1800 | E31: =IFERROR(B31/$B$9,"") -> 0.0015535656 | F31: Trash and cardboard pickup, the grease interceptor service and the used fryer oil, with a licensed waste / grease hauler. Enter the rates of your city | G31: =IFERROR(IF(B9="","",'0. Assumptions'!$B$41),"") -> 0
A32: Pest control | B32: 900 | C32: =IFERROR(IF(C9="","",B32*(1+'0. Assumptions'!$B$48)),"") -> 900 | D32: =IFERROR(IF(D9="","",C32*(1+'0. Assumptions'!$B$48)),"") -> 900 | E32: =IFERROR(B32/$B$9,"") -> 0.00077678282 | F32: Contract with a licensed pest control operator: it is part of the prerequisites of your written food safety plan. | G32: =IFERROR(IF(B9="","",'0. Assumptions'!$B$41),"") -> 0
A33: Music licensing (ASCAP/BMI/SESAC) | B33: 1000 | C33: =IFERROR(IF(C9="","",B33*(1+'0. Assumptions'!$B$48)),"") -> 1000 | D33: =IFERROR(IF(D9="","",C33*(1+'0. Assumptions'!$B$48)),"") -> 1000 | E33: =IFERROR(B33/$B$9,"") -> 0.00086309203 | F33: ASCAP, BMI and SESAC are separate licenses; the fee depends on the square footage and the seating of your restaurant | G33: =IFERROR(IF(B9="","",'0. Assumptions'!$B$41),"") -> 0
A34: Training & permit renewals (CFPM, allergens, HACCP plan or variance, OSHA) | B34: 3500 | C34: =IFERROR(IF(C9="","",B34*(1+'0. Assumptions'!$B$48)),"") -> 3500 | D34: =IFERROR(IF(D9="","",C34*(1+'0. Assumptions'!$B$48)),"") -> 3500 | E34: =IFERROR(B34/$B$9,"") -> 0.0030208221 | F34: Certified Food Protection Manager (CFPM) and food handler cards, allergen and raw fish handling training, the renewal of your HACCP plan or variance if you have one, and OSHA basics: knife cuts, fryer and griddle burns, freezer cold and lifting | G34: =IFERROR(IF(B9="","",'0. Assumptions'!$B$41),"") -> 0
A35: Depreciation of fixed assets | B35: =IFERROR(IF(B9="","",'Startup Costs'!$B$37),"") -> 25458.571 | C35: =IFERROR(IF(C9="","",B35),"") -> 25458.571 | D35: =IFERROR(IF(D9="","",B35),"") -> 25458.571 | E35: =IFERROR(B35/$B$9,"") -> 0.02197309 | F35: Comes from the depreciation bases on the Startup Costs tab: real fixed assets only. It does NOT rise with inflation: it is a charge on the HISTORICAL cost of the assets | G35: 0
A36: Interest expense (loan interest) | B36: =IFERROR(IF(B9="","",Financing!$B$44),"") -> 25600 | C36: =IFERROR(IF(C9="","",Financing!$B$46),"") -> 23993.718 | D36: =IFERROR(IF(D9="","",Financing!$B$48),"") -> 22226.808 | E36: =IFERROR(B36/$B$9,"") -> 0.022095156 | F36: Only INTEREST is an expense. Principal repaid appears on the cash flow tab | G36: 0
A37: TOTAL FIXED COSTS | B37: =IFERROR(IF(B9="","",SUM(B22:B36)),"") -> 545684.17 | C37: =IFERROR(IF(C9="","",SUM(C22:C36)),"") -> 549077.89 | D37: =IFERROR(IF(D9="","",SUM(D22:D36)),"") -> 552310.98 | E37: =IFERROR(B37/$B$9,"") -> 0.47097566
A38: Recoverable input tax on variable costs | B38: =IFERROR(IF(B9="","",SUMPRODUCT(B13:B18,G13:G18)),"") -> 0 | C38: =IFERROR(IF(C9="","",SUMPRODUCT(C13:C18,G13:G18)),"") -> 0 | D38: =IFERROR(IF(D9="","",SUMPRODUCT(D13:D18,G13:G18)),"") -> 0 | F38: Each line at ITS OWN rate, read from the column next to it. It is what the cash flow tab overpays to suppliers and later deducts (zero wherever no tax is recoverable)
A39: Recoverable input tax on fixed costs | B39: =IFERROR(IF(B9="","",SUMPRODUCT(B22:B36,G22:G36)),"") -> 0 | C39: =IFERROR(IF(C9="","",SUMPRODUCT(C22:C36,G22:G36)),"") -> 0 | D39: =IFERROR(IF(D9="","",SUMPRODUCT(D22:D36,G22:G36)),"") -> 0
A40: PRE-TAX INCOME (EBT) | B40: =IFERROR(IF(B9="","",B20-B37),"") -> 131532.14 | C40: =IFERROR(IF(C9="","",C20-C37),"") -> 168771.4 | D40: =IFERROR(IF(D9="","",D20-D37),"") -> 194252.28 | E40: =IFERROR(B40/$B$9,"") -> 0.11352434
A41: Net operating losses carried forward (opening) | B41: =IFERROR(IF(B9="","",'0. Assumptions'!$B$42),"") -> 0 | C41: =IFERROR(IF(C9="","",B46),"") -> 0 | D41: =IFERROR(IF(D9="","",C46),"") -> 0 | F41: Federal rules let a year's losses offset the profits of later years (the federal limit is 80% of taxable income; this model offsets 100% as a simplification)
A42: Taxable income (after loss offset) | B42: =IFERROR(IF(B9="","",MAX(0,B40-B41)),"") -> 131532.14 | C42: =IFERROR(IF(C9="","",MAX(0,C40-C41)),"") -> 168771.4 | D42: =IFERROR(IF(D9="","",MAX(0,D40-D41)),"") -> 194252.28
A43: Years with positive taxable income (cumulative) | B43: =IFERROR(IF(B9="","",IF(B42>0,1,0)),"") -> 1 | C43: =IFERROR(IF(C9="","",B43+IF(C42>0,1,0)),"") -> 2 | D43: =IFERROR(IF(D9="","",C43+IF(D42>0,1,0)),"") -> 3
A44: Effective income tax rate applied | B44: =IFERROR(IF(B9="","",IF(B42<=0,"",IF(B43<=2,'0. Assumptions'!$B$37,'0. Assumptions'!$B$38))),"") -> 0.25 | C44: =IFERROR(IF(C9="","",IF(C42<=0,"",IF(C43<=2,'0. Assumptions'!$B$37,'0. Assumptions'!$B$38))),"") -> 0.25 | D44: =IFERROR(IF(D9="","",IF(D42<=0,"",IF(D43<=2,'0. Assumptions'!$B$37,'0. Assumptions'!$B$38))),"") -> 0.25 | F44: The "years 1-2" rate applies to the first two years with positive taxable income, not to the first two calendar years of the business. The model approximates this by counting the first two profitable years
A45: Income tax | B45: =IFERROR(IF(B9="","",IF(B44="",0,B42*B44)),"") -> 32883.035 | C45: =IFERROR(IF(C9="","",IF(C44="",0,C42*C44)),"") -> 42192.85 | D45: =IFERROR(IF(D9="","",IF(D44="",0,D42*D44)),"") -> 48563.071
A46: Net operating losses carried forward (closing) | B46: =IFERROR(IF(B9="","",MAX(0,B41-B40)),"") -> 0 | C46: =IFERROR(IF(C9="","",MAX(0,C41-C40)),"") -> 0 | D46: =IFERROR(IF(D9="","",MAX(0,D41-D40)),"") -> 0
A47: NET INCOME | B47: =IFERROR(IF(B9="","",B40-B45),"") -> 98649.106 | C47: =IFERROR(IF(C9="","",C40-C45),"") -> 126578.55 | D47: =IFERROR(IF(D9="","",D40-D45),"") -> 145689.21 | E47: =IFERROR(B47/$B$9,"") -> 0.085143257
A48: KEY RATIOS
A49: Ratio | B49: Year 1 | C49: Year 2 | D49: Year 3 | E49: Threshold | F49: Comment
A50: Gross margin / Sales | B50: =IFERROR(IF(B9="","",B20/B9),"") -> 0.5845 | C50: =IFERROR(IF(C9="","",C20/C9),"") -> 0.5845 | D50: =IFERROR(IF(D9="","",D20/D9),"") -> 0.5845 | E50: 0.55 | F50: Floor for the margin after ALL variable costs (food and beverage, packaging, marketplace fees, card fees and miscellaneous). With about 15% of sales through marketplaces, a sushi restaurant leaves less than a dining room alone. Kit estimate
A51: Cost of goods sold (food + beverage) | B51: =IFERROR(IF(B9="","",B13+B14),"") -> 356856.5 | C51: =IFERROR(IF(C9="","",C13+C14),"") -> 378267.89 | D51: =IFERROR(IF(D9="","",D13+D14),"") -> 393398.61
A52: Cost of goods sold / Sales | B52: =IFERROR(IF(B9="","",B51/B9),"") -> 0.308 | C52: =IFERROR(IF(C9="","",C51/C9),"") -> 0.308 | D52: =IFERROR(IF(D9="","",D51/D9),"") -> 0.308 | E52: 0.33 | F52: Ceiling for cost of goods sold on sales: salmon pays for the menu, while tuna, shrimp and sushi case waste make it more expensive. Kit estimate
A53: Labor cost / Sales | B53: =IFERROR(IF(B9="","",B23/B9),"") -> 0.33162205 | C53: =IFERROR(IF(C9="","",C23/C9),"") -> 0.31692218 | D53: =IFERROR(IF(D9="","",D23/D9),"") -> 0.30864747 | E53: 0.36 | F53: Ceiling for labor on sales with a head sushi chef, a sushi chef and table service at lunch and dinner. Servers' tips go on top and are not part of it. Kit estimate
A54: Rent / Sales | B54: =IFERROR(IF(B9="","",B22/B9),"") -> 0.046606969 | C54: =IFERROR(IF(C9="","",C22/C9),"") -> 0.043968839 | D54: =IFERROR(IF(D9="","",D22/D9),"") -> 0.04227773 | E54: 0.1 | F54: Ceiling for rent on sales for a space with a Type I hood and exhaust to the roof: Kit estimate
A55: Net income / Sales | B55: =IFERROR(IF(B9="","",B47/B9),"") -> 0.085143257 | C55: =IFERROR(IF(C9="","",C47/C9),"") -> 0.10306504 | D55: =IFERROR(IF(D9="","",D47/D9),"") -> 0.11406313 | E55: 0.05 | F55: Floor for the net result on sales at full pace so the plan holds up. A well-run sushi restaurant earns around 8-11% in this example. Kit estimate
A56: Break-even reached | B56: =IFERROR(IF(B9="","",IF(B9>='Break-Even'!$B$16,"Yes","No")),"") -> Yes | C56: =IFERROR(IF(C9="","",IF(C9>='Break-Even'!$C$16,"Yes","No")),"") -> Yes | D56: =IFERROR(IF(D9="","",IF(D9>='Break-Even'!$D$16,"Yes","No")),"") -> Yes | F56: Compares each year's sales with that same year's threshold, which the Break-Even tab calculates with that year's fixed costs
A58: All figures are EXCL. SALES TAX. Years 2 and 3 are in year-1 prices unless you raise cost inflation in the "0. Assumptions" tab. The "Sales tax rate on the line (%)" column shows, on SALES lines, the rate collected on each one and, on COST lines, the rate paid on that item. The cash flow tab reads it: insurance and card fees carry no sales tax, and wages, depreciation and interest carry none either.

Sheet Break-Even
A1: BREAK-EVEN ANALYSIS
A2: Monthly and daily break-even — sushi restaurant with sushi bar, tables, take-out and delivery
A4: Variable | B4: Year 1 | C4: Year 2 | D4: Year 3 | E4: Notes
A5: BASE DATA BY YEAR
A6: Annual fixed costs | B6: =IFERROR(IF('3-Year P&L'!$B$9="","",'3-Year P&L'!$B$37),"") -> 545684.17 | C6: =IFERROR(IF('3-Year P&L'!$C$9="","",'3-Year P&L'!$C$37),"") -> 549077.89 | D6: =IFERROR(IF('3-Year P&L'!$D$9="","",'3-Year P&L'!$D$37),"") -> 552310.98 | E6: The SAME fixed costs as the P&L. Each year has its own, which is why the threshold cannot be a single one for all three years
A7: Monthly fixed costs | B7: =IFERROR(IF('3-Year P&L'!$B$9="","",B6/12),"") -> 45473.681 | C7: =IFERROR(IF('3-Year P&L'!$C$9="","",C6/12),"") -> 45756.491 | D7: =IFERROR(IF('3-Year P&L'!$D$9="","",D6/12),"") -> 46025.915
A8: Average check (excl. sales tax) | B8: =IFERROR(IF('3-Year P&L'!$B$9="","",'3-Year P&L'!$B$7),"") -> 32.5 | C8: =IFERROR(IF('3-Year P&L'!$C$9="","",'3-Year P&L'!$C$7),"") -> 32.5 | D8: =IFERROR(IF('3-Year P&L'!$D$9="","",'3-Year P&L'!$D$7),"") -> 32.5
A9: Variable cost per cover | B9: =IFERROR(IF('3-Year P&L'!$B$9="","",'3-Year P&L'!$B$19/('3-Year P&L'!$B$6*'3-Year P&L'!$B$8)),"") -> 13.50375 | C9: =IFERROR(IF('3-Year P&L'!$C$9="","",'3-Year P&L'!$C$19/('3-Year P&L'!$C$6*'3-Year P&L'!$C$8)),"") -> 13.50375 | D9: =IFERROR(IF('3-Year P&L'!$D$9="","",'3-Year P&L'!$D$19/('3-Year P&L'!$D$6*'3-Year P&L'!$D$8)),"") -> 13.50375 | E9: Comes from the P&L total variable costs, not from a separate estimate. It includes miscellaneous and contingency, which is a percentage of sales
A10: Contribution margin per cover | B10: =IFERROR(IF('3-Year P&L'!$B$9="","",B8-B9),"") -> 18.99625 | C10: =IFERROR(IF('3-Year P&L'!$C$9="","",C8-C9),"") -> 18.99625 | D10: =IFERROR(IF('3-Year P&L'!$D$9="","",D8-D9),"") -> 18.99625 | E10: Average check minus unit variable cost
A11: Operating days per year | B11: =IFERROR(IF('3-Year P&L'!$B$9="","",'3-Year P&L'!$B$8),"") -> 310 | C11: =IFERROR(IF('3-Year P&L'!$C$9="","",'3-Year P&L'!$C$8),"") -> 310 | D11: =IFERROR(IF('3-Year P&L'!$D$9="","",'3-Year P&L'!$D$8),"") -> 310 | E11: The same calendar as the P&L and the scenarios
A12: Principal repaid in the year | B12: =IFERROR(IF('3-Year P&L'!$B$9="","",Financing!$B$45),"") -> 16062.821 | C12: =IFERROR(IF('3-Year P&L'!$C$9="","",Financing!$B$47),"") -> 17669.103 | D12: =IFERROR(IF('3-Year P&L'!$D$9="","",Financing!$B$49),"") -> 19436.014 | E12: Principal is NOT a P&L expense, but it leaves the cash account. Without it, the published break-even threshold would sit below the real one
A13: ACCOUNTING BREAK-EVEN (includes depreciation)
A14: Covers needed per year | B14: =IFERROR(IF('3-Year P&L'!$B$9="","",IF(B10<=0,"",B6/B10)),"") -> 28725.889 | C14: =IFERROR(IF('3-Year P&L'!$C$9="","",IF(C10<=0,"",C6/C10)),"") -> 28904.541 | D14: =IFERROR(IF('3-Year P&L'!$D$9="","",IF(D10<=0,"",D6/D10)),"") -> 29074.737
A15: Covers needed per day | B15: =IFERROR(IF('3-Year P&L'!$B$9="","",B14/B11),"") -> 92.664158 | C15: =IFERROR(IF('3-Year P&L'!$C$9="","",C14/C11),"") -> 93.240455 | D15: =IFERROR(IF('3-Year P&L'!$D$9="","",D14/D11),"") -> 93.789475
A16: Revenue needed per year | B16: =IFERROR(IF('3-Year P&L'!$B$9="","",B14*B8),"") -> 933591.4 | C16: =IFERROR(IF('3-Year P&L'!$C$9="","",C14*C8),"") -> 939397.59 | D16: =IFERROR(IF('3-Year P&L'!$D$9="","",D14*D8),"") -> 944928.96
A17: CASH BREAK-EVEN (loan payments in, depreciation out)
A18: Cash fixed costs + principal repaid for the year | B18: =IFERROR(IF('3-Year P&L'!$B$9="","",B6-'3-Year P&L'!$B$35+B12),"") -> 536288.42 | C18: =IFERROR(IF('3-Year P&L'!$C$9="","",C6-'3-Year P&L'!$C$35+C12),"") -> 541288.42 | D18: =IFERROR(IF('3-Year P&L'!$D$9="","",D6-'3-Year P&L'!$D$35+D12),"") -> 546288.42 | E18: The P&L fixed costs without depreciation (which is not paid in cash) and WITH principal repaid (which is). This is the threshold that decides whether cash holds up
A19: Covers needed per year (cash) | B19: =IFERROR(IF('3-Year P&L'!$B$9="","",IF(B10<=0,"",B18/B10)),"") -> 28231.278 | C19: =IFERROR(IF('3-Year P&L'!$C$9="","",IF(C10<=0,"",C18/C10)),"") -> 28494.488 | D19: =IFERROR(IF('3-Year P&L'!$D$9="","",IF(D10<=0,"",D18/D10)),"") -> 28757.698
A20: Covers needed per day (cash) | B20: =IFERROR(IF('3-Year P&L'!$B$9="","",B19/B11),"") -> 91.06864 | C20: =IFERROR(IF('3-Year P&L'!$C$9="","",C19/C11),"") -> 91.917704 | D20: =IFERROR(IF('3-Year P&L'!$D$9="","",D19/D11),"") -> 92.766768
A21: Revenue needed per year (cash) | B21: =IFERROR(IF('3-Year P&L'!$B$9="","",B19*B8),"") -> 917516.55 | C21: =IFERROR(IF('3-Year P&L'!$C$9="","",C19*C8),"") -> 926070.87 | D21: =IFERROR(IF('3-Year P&L'!$D$9="","",D19*D8),"") -> 934625.19
A22: COMPARISON WITH THE PLAN
A23: Covers per day forecast in the plan | B23: =IFERROR(IF('3-Year P&L'!$B$9="","",'3-Year P&L'!$B$6),"") -> 115 | C23: =IFERROR(IF('3-Year P&L'!$C$9="","",'3-Year P&L'!$C$6),"") -> 121.9 | D23: =IFERROR(IF('3-Year P&L'!$D$9="","",'3-Year P&L'!$D$6),"") -> 126.776
A24: Cushion above CASH break-even (%) | B24: =IFERROR(IF('3-Year P&L'!$B$9="","",B23/B20-1),"") -> 0.26278377 | C24: =IFERROR(IF('3-Year P&L'!$C$9="","",C23/C20-1),"") -> 0.32618631 | D24: =IFERROR(IF('3-Year P&L'!$D$9="","",D23/D20-1),"") -> 0.36661008 | E24: How far your projected sales exceed cash break-even sales. The drop you can absorb before you cannot pay the fixed costs and the loan payment is a bit smaller: with a 25% cushion, 20%. The minimum required is on the "0. Assumptions" tab
A25: Maximum seat turns per day the space allows | B25: 3 | E25: Full services per seat per day you can run with lunch, dinner and a second dinner turn on Friday and Saturday (stays of 45-60 minutes). It is the physical ceiling of the space, not a target
A26: Seat turns per day that the cash break-even requires | B26: =IFERROR(IF('3-Year P&L'!$B$9="","",B20/'0. Assumptions'!$B$51),"") -> 2.276716 | C26: =IFERROR(IF('3-Year P&L'!$C$9="","",C20/'0. Assumptions'!$B$51),"") -> 2.2979426 | D26: =IFERROR(IF('3-Year P&L'!$D$9="","",D20/'0. Assumptions'!$B$51),"") -> 2.3191692 | E26: Break-even covers spread across the seats declared on the "0. Assumptions" tab. If it is above the ceiling in the row above, the break-even is out of reach for the space
A27: INTERPRETATION
A28: =IFERROR("With the average check excl. sales tax above, you need "&TEXT(ROUNDUP(B15,0),"0")&" covers a day over your "&TEXT(B11,"0")&" opening days to avoid losing money (accounting break-even, depreciation included), and "&TEXT(ROUNDUP(B20,0),"0")&" for cash to hold (cash break-even: depreciation out, because it is not paid, and the year's loan payment in"&IF(B12=0,"; no principal is repaid this year (interest-only period or no loan)","")&"). The ""Revenue needed per year"" rows show the same figures in your currency.","") -> With the average check excl. sales tax above, you need 93 covers a day over your 310 opening days to avoid losing money (accounting break-even, depreciation included), and 92 for cash to hold (cash break-even: depreciation out, because it is not paid, and the year's loan payment in). The "Revenue needed per year" rows show the same figures in your currency.
A30: BREAK-EVEN SENSITIVITY
A31: Covers per day needed to cover costs for each average check (columns) and each variable cost per cover (rows). Green cells are below the covers per day the plan forecasts.
A33: Covers per day needed: average check excl. sales tax (columns) × variable cost per cover (rows) | B33: =IFERROR($B$8-2,"") -> 30.5 | C33: =IFERROR(IF($B$8="","",$B$8),"") -> 32.5 | D33: =IFERROR($B$8+2,"") -> 34.5 | E33: =IFERROR($B$8+4,"") -> 36.5
A34: =IFERROR($B$9*0.85,"") -> 11.478188 | B34: =IFERROR(IF($B$33-$A34<=0,"",$B$6/($B$33-$A34)/$B$11),"") -> 92.539632 | C34: =IFERROR(IF($C$33-$A34<=0,"",$B$6/($C$33-$A34)/$B$11),"") -> 83.735478 | D34: =IFERROR(IF($D$33-$A34<=0,"",$B$6/($D$33-$A34)/$B$11),"") -> 76.461031 | E34: =IFERROR(IF($E$33-$A34<=0,"",$B$6/($E$33-$A34)/$B$11),"") -> 70.349481
A35: =IFERROR($B$9*0.925,"") -> 12.490969 | B35: =IFERROR(IF($B$33-$A35<=0,"",$B$6/($B$33-$A35)/$B$11),"") -> 97.743821 | C35: =IFERROR(IF($C$33-$A35<=0,"",$B$6/($C$33-$A35)/$B$11),"") -> 87.97385 | D35: =IFERROR(IF($D$33-$A35<=0,"",$B$6/($D$33-$A35)/$B$11),"") -> 79.979509 | E35: =IFERROR(IF($E$33-$A35<=0,"",$B$6/($E$33-$A35)/$B$11),"") -> 73.317057
A36: =IFERROR($B$9*1.0,"") -> 13.50375 | B36: =IFERROR(IF($B$33-$A36<=0,"",$B$6/($B$33-$A36)/$B$11),"") -> 103.56823 | C36: =IFERROR(IF($C$33-$A36<=0,"",$B$6/($C$33-$A36)/$B$11),"") -> 92.664158 | D36: =IFERROR(IF($D$33-$A36<=0,"",$B$6/($D$33-$A36)/$B$11),"") -> 83.837424 | E36: =IFERROR(IF($E$33-$A36<=0,"",$B$6/($E$33-$A36)/$B$11),"") -> 76.546025
A37: =IFERROR($B$9*1.075,"") -> 14.516531 | B37: =IFERROR(IF($B$33-$A37<=0,"",$B$6/($B$33-$A37)/$B$11),"") -> 110.13076 | C37: =IFERROR(IF($C$33-$A37<=0,"",$B$6/($C$33-$A37)/$B$11),"") -> 97.882758 | D37: =IFERROR(IF($D$33-$A37<=0,"",$B$6/($D$33-$A37)/$B$11),"") -> 88.086385 | E37: =IFERROR(IF($E$33-$A37<=0,"",$B$6/($E$33-$A37)/$B$11),"") -> 80.07251
A38: =IFERROR($B$9*1.15,"") -> 15.529312 | B38: =IFERROR(IF($B$33-$A38<=0,"",$B$6/($B$33-$A38)/$B$11),"") -> 117.58121 | C38: =IFERROR(IF($C$33-$A38<=0,"",$B$6/($C$33-$A38)/$B$11),"") -> 103.72423 | D38: =IFERROR(IF($D$33-$A38<=0,"",$B$6/($D$33-$A38)/$B$11),"") -> 92.789021 | E38: =IFERROR(IF($E$33-$A38<=0,"",$B$6/($E$33-$A38)/$B$11),"") -> 83.939619

Sheet Scenarios
A1: SCENARIO ANALYSIS
A2: Pessimistic / Base / Optimistic — Year 1
A4: Metric | B4: Pessimistic | C4: Base | D4: Optimistic | E4: Notes
A5: Covers per day | B5: 95 | C5: =IFERROR(IF('3-Year P&L'!$B$6="","",'3-Year P&L'!$B$6),"") -> 115 | D5: 135
A6: Average check (excl. sales tax) | B6: 30.5 | C6: =IFERROR(IF('3-Year P&L'!$B$7="","",'3-Year P&L'!$B$7),"") -> 32.5 | D6: 34.5
A7: Operating days per year | B7: 305 | C7: =IFERROR(IF('3-Year P&L'!$B$8="","",'3-Year P&L'!$B$8),"") -> 310 | D7: 312
A8: ANNUAL REVENUE (excl. sales tax) | B8: =IFERROR(IF(B5*B6*B7=0,"",B5*B6*B7),"") -> 883737.5 | C8: =IFERROR(IF(C5*C6*C7=0,"",C5*C6*C7),"") -> 1158625 | D8: =IFERROR(IF(D5*D6*D7=0,"",D5*D6*D7),"") -> 1453140
A9: Cost of goods sold — food | B9: =IFERROR(IF(B8="","",B8*'0. Assumptions'!$B$11*'0. Assumptions'!$B$13),"") -> 240376.6 | C9: =IFERROR(IF(C8="","",C8*'0. Assumptions'!$B$11*'0. Assumptions'!$B$13),"") -> 315146 | D9: =IFERROR(IF(D8="","",D8*'0. Assumptions'!$B$11*'0. Assumptions'!$B$13),"") -> 395254.08
A10: Cost of goods sold — beverage | B10: =IFERROR(IF(B8="","",B8*'0. Assumptions'!$B$12*'0. Assumptions'!$B$14),"") -> 31814.55 | C10: =IFERROR(IF(C8="","",C8*'0. Assumptions'!$B$12*'0. Assumptions'!$B$14),"") -> 41710.5 | D10: =IFERROR(IF(D8="","",D8*'0. Assumptions'!$B$12*'0. Assumptions'!$B$14),"") -> 52313.04
A11: Disposables and packaging | B11: =IFERROR(IF(B8="","",B8*'0. Assumptions'!$B$15),"") -> 26512.125 | C11: =IFERROR(IF(C8="","",C8*'0. Assumptions'!$B$15),"") -> 34758.75 | D11: =IFERROR(IF(D8="","",D8*'0. Assumptions'!$B$15),"") -> 43594.2
A12: Delivery platform fees | B12: =IFERROR(IF(B8="","",B8*'0. Assumptions'!$B$16*'0. Assumptions'!$B$17),"") -> 33140.156 | C12: =IFERROR(IF(C8="","",C8*'0. Assumptions'!$B$16*'0. Assumptions'!$B$17),"") -> 43448.438 | D12: =IFERROR(IF(D8="","",D8*'0. Assumptions'!$B$16*'0. Assumptions'!$B$17),"") -> 54492.75
A13: Card processing fees | B13: =IFERROR(IF(B8="","",B8*'0. Assumptions'!$B$18),"") -> 26512.125 | C13: =IFERROR(IF(C8="","",C8*'0. Assumptions'!$B$18),"") -> 34758.75 | D13: =IFERROR(IF(D8="","",D8*'0. Assumptions'!$B$18),"") -> 43594.2
A14: Miscellaneous and contingency | B14: =IFERROR(IF(B8="","",B8*'0. Assumptions'!$B$28),"") -> 8837.375 | C14: =IFERROR(IF(C8="","",C8*'0. Assumptions'!$B$28),"") -> 11586.25 | D14: =IFERROR(IF(D8="","",D8*'0. Assumptions'!$B$28),"") -> 14531.4
A15: TOTAL VARIABLE COSTS | B15: =IFERROR(IF(B8="","",SUM(B9:B14)),"") -> 367192.93 | C15: =IFERROR(IF(C8="","",SUM(C9:C14)),"") -> 481408.69 | D15: =IFERROR(IF(D8="","",SUM(D9:D14)),"") -> 603779.67
A16: GROSS MARGIN | B16: =IFERROR(IF(B8="","",B8-B15),"") -> 516544.57 | C16: =IFERROR(IF(C8="","",C8-C15),"") -> 677216.31 | D16: =IFERROR(IF(D8="","",D8-D15),"") -> 849360.33
A17: FIXED COSTS (the P&L's) | B17: =IFERROR(IF(B8="","",'3-Year P&L'!$B$37),"") -> 545684.17 | C17: =IFERROR(IF(C8="","",'3-Year P&L'!$B$37),"") -> 545684.17 | D17: =IFERROR(IF(D8="","",'3-Year P&L'!$B$37),"") -> 545684.17 | E17: Fixed costs do not change with the scenario: that is why they are fixed
A18: PRE-TAX INCOME (EBT) | B18: =IFERROR(IF(B8="","",B16-B17),"") -> -29139.603 | C18: =IFERROR(IF(C8="","",C16-C17),"") -> 131532.14 | D18: =IFERROR(IF(D8="","",D16-D17),"") -> 303676.16
A19: Income tax | B19: =IFERROR(IF(B8="","",MAX(0,B18-'0. Assumptions'!$B$42)*'0. Assumptions'!$B$37),"") -> 0 | C19: =IFERROR(IF(C8="","",MAX(0,C18-'0. Assumptions'!$B$42)*'0. Assumptions'!$B$37),"") -> 32883.035 | D19: =IFERROR(IF(D8="","",MAX(0,D18-'0. Assumptions'!$B$42)*'0. Assumptions'!$B$37),"") -> 75919.04 | E19: At the "years 1-2" effective income tax rate, offsetting prior net operating losses
A20: NET INCOME | B20: =IFERROR(IF(B8="","",B18-B19),"") -> -29139.603 | C20: =IFERROR(IF(C8="","",C18-C19),"") -> 98649.106 | D20: =IFERROR(IF(D8="","",D18-D19),"") -> 227757.12
A21: Covers per day to break even | B21: =IFERROR(IF(B8="","",IF(B6-B15/(B5*B7)<=0,"",B17/(B6-B15/(B5*B7))/B7)),"") -> 100.35919 | C21: =IFERROR(IF(C8="","",IF(C6-C15/(C5*C7)<=0,"",C17/(C6-C15/(C5*C7))/C7)),"") -> 92.664158 | D21: =IFERROR(IF(D8="","",IF(D6-D15/(D5*D7)<=0,"",D17/(D6-D15/(D5*D7))/D7)),"") -> 86.732757
A22: WHAT EACH SCENARIO DEMANDS
A23: Labor cost / Sales | B23: =IFERROR(IF(B8="","",'3-Year P&L'!$B$23/B8),"") -> 0.43477345 | C23: =IFERROR(IF(C8="","",'3-Year P&L'!$B$23/C8),"") -> 0.33162205 | D23: =IFERROR(IF(D8="","",'3-Year P&L'!$B$23/D8),"") -> 0.26441059 | E23: The SAME staffing in all three scenarios. If labor cost blows up in the pessimistic case, adjust it in the Staffing tab, not here
A24: Covers per year per full-time equivalent | B24: =IFERROR(IF(B8="","",B5*B7/Staffing!$C$12),"") -> 3369.186 | C24: =IFERROR(IF(C8="","",C5*C7/Staffing!$C$12),"") -> 4145.3488 | D24: =IFERROR(IF(D8="","",D5*D7/Staffing!$C$12),"") -> 4897.6744 | E24: Covers each full-time employee in the "Staffing" tab would have to serve. In the optimistic scenario it tells you whether you need to hire
A25: Year-1 closing cash balance (estimate, same method in all three scenarios) | B25: =IFERROR(IF(B8="","",'Startup Costs'!$B$29+B20+'3-Year P&L'!$B$35-Financing!$B$45),"") -> 110312.55 | C25: =IFERROR(IF(C8="","",'Startup Costs'!$B$29+C20+'3-Year P&L'!$B$35-Financing!$B$45),"") -> 238101.26 | D25: =IFERROR(IF(D8="","",'Startup Costs'!$B$29+D20+'3-Year P&L'!$B$35-Financing!$B$45),"") -> 367209.27 | E25: ESTIMATED balance: working capital plus the year's result, adding back depreciation (which is not paid) and subtracting loan principal. It does not include the timing gap between receipts and payments or the sales tax settlement, so the three columns can be compared with each other. In red, the scenario runs out of cash
A26: Actual month-12 balance from the 12-Month Cash Flow tab (Base case only) | C26: =IFERROR(IF(C8="","",'12-Month Cash Flow'!$M$22),"") -> 309463.28 | E26: The ACTUAL base-case balance, with its timing of receipts and payments and its sales tax settlement. It exists only for the Base scenario, the only one with its own monthly cash flow: that is why it is not in the row above, where it would be compared against two estimates
A28: The "Base" column reads its three inputs from the "0. Assumptions" tab, so it reproduces EXACTLY year 1 of the P&L. The other two scenarios use the same cost rates: the only things that change are covers, average check and days. FIXED COSTS are the same in all three: miscellaneous and contingency, which is a percentage of sales, sits at the top with the variable costs and each scenario carries its own.

Sheet Staffing
A1: STAFFING STRUCTURE AND COSTS
A2: =IFERROR("Payroll — "&TEXT('0. Assumptions'!$B$21,"0")&" pay periods + employer taxes "&TEXT('0. Assumptions'!$B$20*100,"0")&"%","") -> Payroll — 12 pay periods + employer taxes 10%
A4: Position | B4: People | C4: FTE | D4: Gross pay per month (total for the position) | E4: Employer payroll taxes (total for the position) | F4: Cost per month (total for the position) | G4: Cost per year | H4: Hours per week per person | I4: Hours per year for the position | J4: Notes
A5: Owner / GM | B5: 1 | C5: 1 | D5: 4500 | E5: =IFERROR(IF(D5="","",D5*'0. Assumptions'!$B$20),"") -> 450 | F5: =IFERROR(IF(D5="","",D5+E5),"") -> 4950 | G5: =IFERROR(IF(D5="","",F5*MAX(12,'0. Assumptions'!$B$21)),"") -> 59400 | H5: =IFERROR(IF(D5="","",C5*$B$19),"") -> 40 | I5: =IFERROR(IF(D5="","",H5*B5*$B$20),"") -> 1840 | J5: Buys from the fish suppliers and files their letters, runs the floor and the delivery marketplaces and manages. In the US the owner is not the one at the sushi bar: you hire the head sushi chef (next row). The workbook imputes a monthly salary as if on payroll, which is the prudent side; confirm with your CPA how you will pay yourself (owner's draw or W-2 under an S corp). The example pays the owner below a manager: owner's draw in addition from net profit
A6: Head sushi chef (itamae) | B6: 1 | C6: 1 | D6: 5199 | E6: =IFERROR(IF(D6="","",D6*'0. Assumptions'!$B$20),"") -> 519.9 | F6: =IFERROR(IF(D6="","",D6+E6),"") -> 5718.9 | G6: =IFERROR(IF(D6="","",F6*MAX(12,'0. Assumptions'!$B$21)),"") -> 68626.8 | H6: =IFERROR(IF(D6="","",C6*$B$19),"") -> 40 | I6: =IFERROR(IF(D6="","",H6*B6*$B$20),"") -> 1840 | J6: The head sushi chef (itamae) buys and cuts the fish, runs the sushi bar, signs off the menu, the sushi rice SOP and the parasite records. About $30 per hour in the example. Hire this person before the build-out: it is an investment, not an expense
A7: Kitchen line cook (tempura, gyoza, rice) | B7: 1 | C7: 1 | D7: 3119 | E7: =IFERROR(IF(D7="","",D7*'0. Assumptions'!$B$20),"") -> 311.9 | F7: =IFERROR(IF(D7="","",D7+E7),"") -> 3430.9 | G7: =IFERROR(IF(D7="","",F7*MAX(12,'0. Assumptions'!$B$21)),"") -> 41170.8 | H7: =IFERROR(IF(D7="","",C7*$B$19),"") -> 40 | I7: =IFERROR(IF(D7="","",H7*B7*$B$20),"") -> 1840 | J7: The rice cookers, gyoza, tempura, miso soup and teriyaki. About $18 per hour in the example
A8: Sushi chef | B8: 1 | C8: 1 | D8: 3639 | E8: =IFERROR(IF(D8="","",D8*'0. Assumptions'!$B$20),"") -> 363.9 | F8: =IFERROR(IF(D8="","",D8+E8),"") -> 4002.9 | G8: =IFERROR(IF(D8="","",F8*MAX(12,'0. Assumptions'!$B$21)),"") -> 48034.8 | H8: =IFERROR(IF(D8="","",C8*$B$19),"") -> 40 | I8: =IFERROR(IF(D8="","",H8*B8*$B$20),"") -> 1840 | J8: Rolls, platters for the delivery marketplaces and the sushi bar when the head sushi chef is off: about $21 per hour (Indeed lists $20.72). With a single person who can cut and build, one absence closes the sushi bar
A9: Servers, host & to-go packing (W-2, tips on top) | B9: 4 | C9: 0.75 | D9: 7798 | E9: =IFERROR(IF(D9="","",D9*'0. Assumptions'!$B$20),"") -> 779.8 | F9: =IFERROR(IF(D9="","",D9+E9),"") -> 8577.8 | G9: =IFERROR(IF(D9="","",F9*MAX(12,'0. Assumptions'!$B$21)),"") -> 102933.6 | H9: =IFERROR(IF(D9="","",C9*$B$19),"") -> 30 | I9: =IFERROR(IF(D9="","",H9*B9*$B$20),"") -> 5520 | J9: Four servers at 0.75 each: dining room, pickup and to-go packing, $15 per hour. Tips go on top and belong to the team
A10: Sushi chef (part-time W-2, weekends & dinner peaks) | B10: 1 | C10: 0.6 | D10: 2080 | E10: =IFERROR(IF(D10="","",D10*'0. Assumptions'!$B$20),"") -> 208 | F10: =IFERROR(IF(D10="","",D10+E10),"") -> 2288 | G10: =IFERROR(IF(D10="","",F10*MAX(12,'0. Assumptions'!$B$21)),"") -> 27456 | H10: =IFERROR(IF(D10="","",C10*$B$19),"") -> 24 | I10: =IFERROR(IF(D10="","",H10*B10*$B$20),"") -> 1104 | J10: Part-time W-2 sushi chef for Friday and Saturday dinners and platters made to order: about $20 per hour, never as a 1099 contractor. This plan has NO in-house delivery: if you add it, the driver is a W-2 employee with hired and non-owned auto insurance
A11: Dish & prep | B11: 1 | C11: 1 | D11: 2773 | E11: =IFERROR(IF(D11="","",D11*'0. Assumptions'!$B$20),"") -> 277.3 | F11: =IFERROR(IF(D11="","",D11+E11),"") -> 3050.3 | G11: =IFERROR(IF(D11="","",F11*MAX(12,'0. Assumptions'!$B$21)),"") -> 36603.6 | H11: =IFERROR(IF(D11="","",C11*$B$19),"") -> 40 | I11: =IFERROR(IF(D11="","",H11*B11*$B$20),"") -> 1840 | J11: Coverage for vacations and the team's days off through the year. Paid sick leave is required by some states and cities: check yours
A12: TOTAL STAFF | B12: =IFERROR(IF(COUNT(D5:D11)=0,"",SUM(B5:B11)),"") -> 10 | C12: =IFERROR(IF(COUNT(D5:D11)=0,"",SUMPRODUCT(B5:B11,C5:C11)),"") -> 8.6 | D12: =IFERROR(IF(COUNT(D5:D11)=0,"",SUM(D5:D11)),"") -> 29108 | E12: =IFERROR(IF(COUNT(D5:D11)=0,"",SUM(E5:E11)),"") -> 2910.8 | F12: =IFERROR(IF(COUNT(D5:D11)=0,"",SUM(F5:F11)),"") -> 32018.8 | G12: =IFERROR(IF(COUNT(D5:D11)=0,"",SUM(G5:G11)),"") -> 384225.6 | I12: =IFERROR(IF(COUNT(D5:D11)=0,"",SUM(I5:I11)),"") -> 15824
A13: STAFF GROWTH (stepped cost)
A14: Annual cost of year-2 hires | B14: 5000 | J14: FULL ANNUAL cost (gross pay + employer payroll taxes, over all pay periods) of whoever you hire that year. The P&L adds it to the previous year's cost: staffing grows by people, not by a percentage
A15: Annual cost of year-3 hires | B15: 5000 | J15: FULL ANNUAL cost (gross pay + employer payroll taxes, over all pay periods) of whoever you hire that year. The P&L adds it to the previous year's cost: staffing grows by people, not by a percentage
A16: Labor cost, year 2 | B16: =IFERROR(IF(G12="","",G12*(1+'0. Assumptions'!$B$48)+B14),"") -> 389225.6
A17: Labor cost, year 3 | B17: =IFERROR(IF(B16="","",B16*(1+'0. Assumptions'!$B$48)+B15),"") -> 394225.6
A18: COVERAGE OF SERVICE HOURS
A19: Full-time week (hours per week) | B19: 40 | J19: 40 hours a week is the FLSA overtime threshold for non-exempt employees; some states add daily overtime rules. Change it if your own full-time week is different
A20: Weeks worked per year per person | B20: 46 | J20: 46 weeks: 52 minus about six weeks for vacation, holidays and average absences. There is no federal vacation requirement in the US: adjust it to your own policy
A21: Service hours per day to cover | B21: 7.5 | J21: Hours the restaurant is open to the public, adding lunch (11:30-14:30) and dinner (17:00-21:30; 22:00 on Friday and Saturday). The afternoon between the two services is not counted
A22: People needed at the same time in each shift | B22: 4.5 | J22: Average number of people at the same time across the sushi bar, the hot line, the dining room and the to-go orders. On Friday and Saturday nights you need more: the part-time sushi chef and the extra servers come in (the annual roster does not see them: put them in the shift)
A23: Production hours per day BEFORE opening | B23: 3 | J23: The day's sushi rice, cutting and cleaning the fish, sauces and mise en place before opening
A24: People on the production shift | B24: 2 | J24: The head sushi chef and the line cook. Closing, cleaning and purchasing are outside this schedule: they are the margin between the hours you hire and the hours you need
A25: Service hours to cover per year | B25: =IFERROR(IF(OR(B21="",B22="",'0. Assumptions'!$B$6=""),"",B21*B22*'0. Assumptions'!$B$6+B23*B24*'0. Assumptions'!$B$6),"") -> 12322.5
A26: Hours hired per year | B26: =IFERROR(IF(I12="","",I12),"") -> 15824
A27: Coverage (hired / needed) | B27: =IFERROR(B26/B25,"") -> 1.284155 | J27: Below 100% the staff cannot cover the hours the plan declares: either hire more or cut the hours
A29: The gross pay, employer payroll taxes, monthly cost and annual cost columns are TOTALS for the row: for a position with several people they include all of them. "FTE" is the share of a full-time week and is used to compare pay with the legal floor pro rata. The payroll tax rate and the number of pay periods are in the "0. Assumptions" tab. Tips are not modeled: every position, servers included, is budgeted at a base wage of at least $15/h, and the tips come on top and belong to the staff, never to the owner or managers. Federal rules allow a $2.13/h cash wage with a tip credit of up to $5.12 where the state permits it; CA, OR, WA, AK, MN, MT and NV do not (DOL)
A30: The pay floor is the HIGHER of the federal minimum wage and your state / local minimum wage, both in the "0. Assumptions" tab; part-time positions get it in proportion. There is no single national table above the federal floor: the state / local cell is delivered empty so you can enter the rate for your state and city.

Sheet Instructions
A1: HOW TO USE THIS WORKBOOK — Sushi Restaurant Financial Projections
A3: HOW TO USE THIS WORKBOOK
A4: This financial plan is a MODEL: you type only in the GREEN cells and everything else recalculates on its own.
A5: 1. "0. Assumptions" is the control sheet: covers per day, average check excl. sales tax, operating days, food and beverage mix, cost of goods sold, rent, financing and taxes.
A6: 2. Startup cost items, fixed costs and staffing are typed in their own tab, also in green. No number is typed twice.
A7: 3. On "Break-Even" you only type the seat-turn ceiling your space allows; everything else derives from the rest. The other three tabs also have green cells you can change: the pessimistic and optimistic scenarios on "Scenarios", the seasonality and the launch ramp-up on "12-Month Cash Flow", and the other financing sources on "Financing" (rows 8-11 count as sources but are not amortized: Your bank or SBA 7(a) loan goes in "Loan requested" on "0. Assumptions"). Everything else is calculated.
A8: 4. All figures are EXCL. SALES TAX. To turn a menu price into a price excl. sales tax, divide it by 1 plus your sales tax rate (a rate of 8% means dividing by 1.08). The example uses ONE rate for everything: dine-in, take-out, delivery and beverages; some states tax food to go or alcohol differently, so check yours. The P&L is excl. sales tax; the "12-Month Cash Flow" tab shows what you actually collect, sales tax included, and the sales tax you remit as a quarterly filer.
A9: 5. If you change the staffing, the P&L reads it on its own: labor cost comes from the "Staffing" tab, not from a separate estimate.
A10: 6. The "12-Month Cash Flow" tab answers the question that decides a bank deal: in which month the cash runs out. Its Month 1 is JANUARY, in calendar order: the opening ramp-up runs from January to April and January is also the slowest month of the calendar, which is why working capital counts. If you open in another month, rotate the seasonality row. The minimum balance of the year can never come out in red.
A11: 7. The "Financing" tab matches what you need with what you put in and builds the amortization schedule of the loan. If the difference is red, the plan is not funded.
A12: 8. The Word business plan in this kit quotes the figures in this Excel: if you change a green cell, the Excel rules. The Sushi Fish, Rice & Costing Calculator is separate: it measures salmon yield and the sushi rice that comes out of each pound of raw rice, and it COSTS each piece by channel. Do not copy the food cost of one nigiri into the "0. Assumptions" tab: the "Cost of goods sold on FOOD sales" cell is the weighted average of the WHOLE menu plus fish waste, thrown-out rice and staff meals, and that is why it comes out higher than the theoretical cost per piece. With the costing of your own menu, check that this average holds.
A14: RATIOS AUDITED BY THIS WORKBOOK
A15: Thresholds live in the "Threshold" column of the KEY RATIOS block of the P&L: change them there and the traffic light changes with them.
A17: Ratio | B17: Year 1 value | C17: Threshold | D17: Status
A18: Cost of goods sold / Sales | B18: =IFERROR(IF('3-Year P&L'!$B$52="","",'3-Year P&L'!$B$52),"") -> 0.308 | C18: =IFERROR(IF('3-Year P&L'!$E$52="","",'3-Year P&L'!$E$52),"") -> 0.33 | D18: =IFERROR(IF(OR(B18="",C18=""),"",IF(B18<=C18,"OK","REVIEW")),"") -> OK
A19: Labor cost / Sales | B19: =IFERROR(IF('3-Year P&L'!$B$53="","",'3-Year P&L'!$B$53),"") -> 0.33162205 | C19: =IFERROR(IF('3-Year P&L'!$E$53="","",'3-Year P&L'!$E$53),"") -> 0.36 | D19: =IFERROR(IF(OR(B19="",C19=""),"",IF(B19<=C19,"OK","REVIEW")),"") -> OK
A20: Rent / Sales | B20: =IFERROR(IF('3-Year P&L'!$B$54="","",'3-Year P&L'!$B$54),"") -> 0.046606969 | C20: =IFERROR(IF('3-Year P&L'!$E$54="","",'3-Year P&L'!$E$54),"") -> 0.1 | D20: =IFERROR(IF(OR(B20="",C20=""),"",IF(B20<=C20,"OK","REVIEW")),"") -> OK
A21: Net income / Sales | B21: =IFERROR(IF('3-Year P&L'!$B$55="","",'3-Year P&L'!$B$55),"") -> 0.085143257 | C21: =IFERROR(IF('3-Year P&L'!$E$55="","",'3-Year P&L'!$E$55),"") -> 0.05 | D21: =IFERROR(IF(OR(B21="",C21=""),"",IF(B21>=C21,"OK","REVIEW")),"") -> OK
A22: Gross margin / Sales | B22: =IFERROR(IF('3-Year P&L'!$B$50="","",'3-Year P&L'!$B$50),"") -> 0.5845 | C22: =IFERROR(IF('3-Year P&L'!$E$50="","",'3-Year P&L'!$E$50),"") -> 0.55 | D22: =IFERROR(IF(OR(B22="",C22=""),"",IF(B22>=C22,"OK","REVIEW")),"") -> OK
A24: THIS PLAN'S KEY FIGURES
A25: Total startup costs (sum of the blocks) | B25: =IFERROR(IF('Startup Costs'!$B$30="","",'Startup Costs'!$B$30),"") -> 385156.4
A26: Total cash needed at launch | B26: =IFERROR(IF('Startup Costs'!$B$33="","",'Startup Costs'!$B$33),"") -> 385156.4
A27: Working capital funded | B27: =IFERROR(IF('Startup Costs'!$B$29="","",'Startup Costs'!$B$29),"") -> 130056.4
A28: Forecast year-1 revenue | B28: =IFERROR(IF('3-Year P&L'!$B$9="","",'3-Year P&L'!$B$9),"") -> 1158625
A29: Year-1 net income | B29: =IFERROR(IF('3-Year P&L'!$B$47="","",'3-Year P&L'!$B$47),"") -> 98649.106
A30: Covers per day for the ACCOUNTING break-even (depreciation included) | B30: =IFERROR(IF('Break-Even'!$B$15="","",'Break-Even'!$B$15),"") -> 92.664158
A31: Project payback (years), before debt | B31: =IFERROR(IF('12-Month Cash Flow'!$B$31="","",'12-Month Cash Flow'!$B$31),"") -> 2.3
A33: US SUSHI RESTAURANT BENCHMARKS (sourced) AND KIT ESTIMATES
A34: Benchmark | B34: Value | C34: Source | D34: Note
A35: Month 1 of the plan | B35: January | C35: Plan decision | D35: In calendar order: the ramp-up falls on January to April, and January is also the slowest month. February (Valentine's Day), May (Mother's Day and graduations) and December (holiday parties) are the peaks. If you open in another month, rotate the seasonality row of the "12-Month Cash Flow" tab
A36: Consumer demand (US searches) | B36: About 201,000 searches a month for "sushi restaurant"; 27,100 for "sushi bar"; 9,900 for "sushi takeout" | C36: DataForSEO, US, Oct 2026 | D36: Consumer demand, not plan buyers. This plan puts 15% of sales through delivery marketplaces
A37: Menu prices in mid-size cities | B37: Nigiri $5-7 a pair; classic roll $7-9; specialty roll $13-18 | C37: Kit estimate (three menus read Oct 2026, +10-20% to 2026 prices) | D37: This plan: dine-in cover of $36.00 (food $28.50 plus beverage $7.50, excl. sales tax and tip)
A38: Cost per piece | B38: Salmon nigiri about 23%, California roll about 12%, spicy tuna roll about 39%; whole menu about 24% | C38: Kit estimate (Sushi Fish, Rice & Costing Calculator) | D38: The plan's 32% is the real usage of the whole menu, with case shrink, trim, rice thrown out and staff meals: it comes out higher than the theoretical cost per piece
A39: Salmon yield | B39: Usable loin 45-60% of a whole fish; a fillet about 85% | C39: Secondary sources (summary) and Kit estimate | D39: Measure yours with 3 fish on the "Fish Yield" tab of the calculator
A40: Sushi rice (Calrose, 50 lb bag) | B40: $51.99 ($1.04/lb) | C40: webstaurantstore.com, read Oct 2026 | D40: Rice is cheap: the cost is in the fish and in the sushi chef's hands
A41: Delivery marketplace commission | B41: DoorDash 15 / 25 / 30% + 6% pickup; Uber Eats 15-30% | C41: merchants.ubereats.com; DoorDash tiers (Oct 2026) | D41: This plan: 25% on 15% of sales. Pickup placed directly with you pays no commission
A42: Sales tax | B42: 8% (example: state + local) | C42: Kit example: look up your state and city rate | D42: One rate in the workbook; some states tax food to go differently
A43: Fish served raw (parasite destruction) | B43: −4 °F for 168 h (7 days), or −31 °F until solid + 15 h, or −31 °F + −4 °F for 24 h; tuna and feed-raised aquaculture fish exempt | C43: FDA Food Code 2022 (3-402.11, 3-402.12) | D43: Buy fish already treated, with the supplier's letter; keep the records 90 days
A44: Sushi rice held at room temperature | B44: TPHC: up to 4 h with the time marked and a written procedure, then discard; or a variance with a HACCP plan (example limit pH < 4.2) | C44: FDA Food Code 2022 (3-501.19, 3-502.11) | D44: Your county decides: ask for it in writing before opening
A45: Minimum wage | B45: Federal $7.25/h + your state | C45: U.S. Department of Labor (dol.gov) | D45: This plan budgets at least $15/h; enter your state's floor in "0. Assumptions"
A46: Labor cost / sales | B46: About 30-35% with table service | C46: Kit estimate | D46: Servers' tips go on top and are not a cost of the restaurant; a good head sushi chef is not cheap
A48: To edit a cell that is not green: Review → Unprotect Sheet (there is no password).
A49: More templates and kits in the catalog at aichef.pro/en/digital-products
A50: Designed by John Guerrero — chef and restaurant consultant since 2010, in the kitchen since age 17 · johnguerrero.es
A51: Version 2.2 · October 2026 · aichef.pro/en/digital-products/sushi-restaurant-business-plan · info@aichef.pro
A52: Planning tool, not financial, tax or legal advice. Requirements vary by state, county and city — check with your accountant and local authorities.

Sheet 12-Month Cash Flow
A1: CASH FLOW FORECAST — YEAR 1
A2: The P&L tells you whether the business makes money; this tab tells you whether you have cash left to get to the end of the month. It is the first one a lender looks at.
A4: Item | B4: Month 1 | C4: Month 2 | D4: Month 3 | E4: Month 4 | F4: Month 5 | G4: Month 6 | H4: Month 7 | I4: Month 8 | J4: Month 9 | K4: Month 10 | L4: Month 11 | M4: Month 12 | N4: Year
A5: Monthly seasonality (adds up to 100%) | B5: 0.078 | C5: 0.086 | D5: 0.084 | E5: 0.082 | F5: 0.086 | G5: 0.084 | H5: 0.082 | I5: 0.08 | J5: 0.08 | K5: 0.084 | L5: 0.082 | M5: 0.092 | N5: =IFERROR(IF('3-Year P&L'!$B$9="","",SUM(B5:M5)),"") -> 1 | O5: Month 1 = JANUARY, in calendar order: January is the slowest month; February (Valentine's Day), May (Mother's Day and graduations) and December (holiday parties and New Year's Eve platters) are the peaks. Kit weights for a mid-size US city: replace them with your area's pattern; if you open in another month, rotate the row. It must add up to 100%
A6: Launch ramp-up (% of steady-state activity) | B6: =IFERROR(IF('3-Year P&L'!$B$9="","",MIN(1,'0. Assumptions'!$B$52+(1-'0. Assumptions'!$B$52)*0/MAX(1,'0. Assumptions'!$B$53-1))),"") -> 0.75 | C6: =IFERROR(IF('3-Year P&L'!$B$9="","",MIN(1,'0. Assumptions'!$B$52+(1-'0. Assumptions'!$B$52)*1/MAX(1,'0. Assumptions'!$B$53-1))),"") -> 0.83333333 | D6: =IFERROR(IF('3-Year P&L'!$B$9="","",MIN(1,'0. Assumptions'!$B$52+(1-'0. Assumptions'!$B$52)*2/MAX(1,'0. Assumptions'!$B$53-1))),"") -> 0.91666667 | E6: =IFERROR(IF('3-Year P&L'!$B$9="","",MIN(1,'0. Assumptions'!$B$52+(1-'0. Assumptions'!$B$52)*3/MAX(1,'0. Assumptions'!$B$53-1))),"") -> 1 | F6: =IFERROR(IF('3-Year P&L'!$B$9="","",MIN(1,'0. Assumptions'!$B$52+(1-'0. Assumptions'!$B$52)*4/MAX(1,'0. Assumptions'!$B$53-1))),"") -> 1 | G6: =IFERROR(IF('3-Year P&L'!$B$9="","",MIN(1,'0. Assumptions'!$B$52+(1-'0. Assumptions'!$B$52)*5/MAX(1,'0. Assumptions'!$B$53-1))),"") -> 1 | H6: =IFERROR(IF('3-Year P&L'!$B$9="","",MIN(1,'0. Assumptions'!$B$52+(1-'0. Assumptions'!$B$52)*6/MAX(1,'0. Assumptions'!$B$53-1))),"") -> 1 | I6: =IFERROR(IF('3-Year P&L'!$B$9="","",MIN(1,'0. Assumptions'!$B$52+(1-'0. Assumptions'!$B$52)*7/MAX(1,'0. Assumptions'!$B$53-1))),"") -> 1 | J6: =IFERROR(IF('3-Year P&L'!$B$9="","",MIN(1,'0. Assumptions'!$B$52+(1-'0. Assumptions'!$B$52)*8/MAX(1,'0. Assumptions'!$B$53-1))),"") -> 1 | K6: =IFERROR(IF('3-Year P&L'!$B$9="","",MIN(1,'0. Assumptions'!$B$52+(1-'0. Assumptions'!$B$52)*9/MAX(1,'0. Assumptions'!$B$53-1))),"") -> 1 | L6: =IFERROR(IF('3-Year P&L'!$B$9="","",MIN(1,'0. Assumptions'!$B$52+(1-'0. Assumptions'!$B$52)*10/MAX(1,'0. Assumptions'!$B$53-1))),"") -> 1 | M6: =IFERROR(IF('3-Year P&L'!$B$9="","",MIN(1,'0. Assumptions'!$B$52+(1-'0. Assumptions'!$B$52)*11/MAX(1,'0. Assumptions'!$B$53-1))),"") -> 1 | O6: Rises in a straight line from the month-1 percentage to 100% over the number of months you set in Assumptions. With month 1 at 100%, the ramp disappears
A7: Split of activity by month (calculated) | B7: =IFERROR(IF('3-Year P&L'!$B$9="","",B5*B6/SUMPRODUCT($B$5:$M$5,$B$6:$M$6)),"") -> 0.060990443 | C7: =IFERROR(IF('3-Year P&L'!$B$9="","",C5*C6/SUMPRODUCT($B$5:$M$5,$B$6:$M$6)),"") -> 0.074717637 | D7: =IFERROR(IF('3-Year P&L'!$B$9="","",D5*D6/SUMPRODUCT($B$5:$M$5,$B$6:$M$6)),"") -> 0.080278019 | E7: =IFERROR(IF('3-Year P&L'!$B$9="","",E5*E6/SUMPRODUCT($B$5:$M$5,$B$6:$M$6)),"") -> 0.085490877 | F7: =IFERROR(IF('3-Year P&L'!$B$9="","",F5*F6/SUMPRODUCT($B$5:$M$5,$B$6:$M$6)),"") -> 0.089661164 | G7: =IFERROR(IF('3-Year P&L'!$B$9="","",G5*G6/SUMPRODUCT($B$5:$M$5,$B$6:$M$6)),"") -> 0.087576021 | H7: =IFERROR(IF('3-Year P&L'!$B$9="","",H5*H6/SUMPRODUCT($B$5:$M$5,$B$6:$M$6)),"") -> 0.085490877 | I7: =IFERROR(IF('3-Year P&L'!$B$9="","",I5*I6/SUMPRODUCT($B$5:$M$5,$B$6:$M$6)),"") -> 0.083405734 | ... M7: =IFERROR(IF('3-Year P&L'!$B$9="","",M5*M6/SUMPRODUCT($B$5:$M$5,$B$6:$M$6)),"") -> 0.095916594 | N7: =IFERROR(IF('3-Year P&L'!$B$9="","",SUM(B7:M7)),"") -> 1 | O7: Seasonality × ramp-up, normalized to 100%: the YEAR brings in what the P&L says, but split the way a business that has just opened would split it
A8: CASH IN
A9: Sales collected (incl. sales tax collected) | B9: =IFERROR(IF('3-Year P&L'!$B$9="","",('3-Year P&L'!$B$9+'3-Year P&L'!$B$9*SUMPRODUCT('3-Year P&L'!$E$10:$E$11,'3-Year P&L'!$G$10:$G$11))*B7*(1-MIN(30,'0. Assumptions'!$B$58)/30)),"") -> 71230.373 | C9: =IFERROR(IF('3-Year P&L'!$B$9="","",('3-Year P&L'!$B$9+'3-Year P&L'!$B$9*SUMPRODUCT('3-Year P&L'!$E$10:$E$11,'3-Year P&L'!$G$10:$G$11))*(C7*(1-MIN(30,'0. Assumptions'!$B$58)/30)+B7*MIN(30,'0. Assumptions'!$B$58)/30)),"") -> 92350.164 | D9: =IFERROR(IF('3-Year P&L'!$B$9="","",('3-Year P&L'!$B$9+'3-Year P&L'!$B$9*SUMPRODUCT('3-Year P&L'!$E$10:$E$11,'3-Year P&L'!$G$10:$G$11))*(D7*(1-MIN(30,'0. Assumptions'!$B$58)/30)+C7*MIN(30,'0. Assumptions'!$B$58)/30)),"") -> 99989.237 | E9: =IFERROR(IF('3-Year P&L'!$B$9="","",('3-Year P&L'!$B$9+'3-Year P&L'!$B$9*SUMPRODUCT('3-Year P&L'!$E$10:$E$11,'3-Year P&L'!$G$10:$G$11))*(E7*(1-MIN(30,'0. Assumptions'!$B$58)/30)+D7*MIN(30,'0. Assumptions'!$B$58)/30)),"") -> 106541.16 | F9: =IFERROR(IF('3-Year P&L'!$B$9="","",('3-Year P&L'!$B$9+'3-Year P&L'!$B$9*SUMPRODUCT('3-Year P&L'!$E$10:$E$11,'3-Year P&L'!$G$10:$G$11))*(F7*(1-MIN(30,'0. Assumptions'!$B$58)/30)+E7*MIN(30,'0. Assumptions'!$B$58)/30)),"") -> 111846.47 | G9: =IFERROR(IF('3-Year P&L'!$B$9="","",('3-Year P&L'!$B$9+'3-Year P&L'!$B$9*SUMPRODUCT('3-Year P&L'!$E$10:$E$11,'3-Year P&L'!$G$10:$G$11))*(G7*(1-MIN(30,'0. Assumptions'!$B$58)/30)+F7*MIN(30,'0. Assumptions'!$B$58)/30)),"") -> 109759.13 | H9: =IFERROR(IF('3-Year P&L'!$B$9="","",('3-Year P&L'!$B$9+'3-Year P&L'!$B$9*SUMPRODUCT('3-Year P&L'!$E$10:$E$11,'3-Year P&L'!$G$10:$G$11))*(H7*(1-MIN(30,'0. Assumptions'!$B$58)/30)+G7*MIN(30,'0. Assumptions'!$B$58)/30)),"") -> 107149.96 | I9: =IFERROR(IF('3-Year P&L'!$B$9="","",('3-Year P&L'!$B$9+'3-Year P&L'!$B$9*SUMPRODUCT('3-Year P&L'!$E$10:$E$11,'3-Year P&L'!$G$10:$G$11))*(I7*(1-MIN(30,'0. Assumptions'!$B$58)/30)+H7*MIN(30,'0. Assumptions'!$B$58)/30)),"") -> 104540.79 | J9: =IFERROR(IF('3-Year P&L'!$B$9="","",('3-Year P&L'!$B$9+'3-Year P&L'!$B$9*SUMPRODUCT('3-Year P&L'!$E$10:$E$11,'3-Year P&L'!$G$10:$G$11))*(J7*(1-MIN(30,'0. Assumptions'!$B$58)/30)+I7*MIN(30,'0. Assumptions'!$B$58)/30)),"") -> 104366.85 | ... M9: =IFERROR(IF('3-Year P&L'!$B$9="","",('3-Year P&L'!$B$9+'3-Year P&L'!$B$9*SUMPRODUCT('3-Year P&L'!$E$10:$E$11,'3-Year P&L'!$G$10:$G$11))*(M7*(1-MIN(30,'0. Assumptions'!$B$58)/30)+L7*MIN(30,'0. Assumptions'!$B$58)/30)),"") -> 119152.15 | N9: =IFERROR(IF('3-Year P&L'!$B$9="","",SUM(B9:M9)),"") -> 1243313.5 | O9: The month's sales plus the sales tax collected, adjusted by the average collection days from the Assumptions tab
A10: CASH OUT
A11: Purchases and variable costs (incl. sales tax) | B11: =IFERROR(IF('3-Year P&L'!$B$9="","",-('3-Year P&L'!$B$13*(1+'3-Year P&L'!$G$13)+'3-Year P&L'!$B$14*(1+'3-Year P&L'!$G$14)+'3-Year P&L'!$B$15*(1+'3-Year P&L'!$G$15)+'3-Year P&L'!$B$16*(1+'3-Year P&L'!$G$16)+'3-Year P&L'!$B$17*(1+'3-Year P&L'!$G$17)+'3-Year P&L'!$B$18*(1+'3-Year P&L'!$G$18))*B7*(1-MIN(30,'0. Assumptions'!$B$59)/30)),"") -> -15659.376 | C11: =IFERROR(IF('3-Year P&L'!$B$9="","",-('3-Year P&L'!$B$13*(1+'3-Year P&L'!$G$13)+'3-Year P&L'!$B$14*(1+'3-Year P&L'!$G$14)+'3-Year P&L'!$B$15*(1+'3-Year P&L'!$G$15)+'3-Year P&L'!$B$16*(1+'3-Year P&L'!$G$16)+'3-Year P&L'!$B$17*(1+'3-Year P&L'!$G$17)+'3-Year P&L'!$B$18*(1+'3-Year P&L'!$G$18))*(C7*(1-MIN(30,'0. Assumptions'!$B$59)/30)+B7*MIN(30,'0. Assumptions'!$B$59)/30)),"") -> -32885.804 | D11: =IFERROR(IF('3-Year P&L'!$B$9="","",-('3-Year P&L'!$B$13*(1+'3-Year P&L'!$G$13)+'3-Year P&L'!$B$14*(1+'3-Year P&L'!$G$14)+'3-Year P&L'!$B$15*(1+'3-Year P&L'!$G$15)+'3-Year P&L'!$B$16*(1+'3-Year P&L'!$G$16)+'3-Year P&L'!$B$17*(1+'3-Year P&L'!$G$17)+'3-Year P&L'!$B$18*(1+'3-Year P&L'!$G$18))*(D7*(1-MIN(30,'0. Assumptions'!$B$59)/30)+C7*MIN(30,'0. Assumptions'!$B$59)/30)),"") -> -37397.355 | E11: =IFERROR(IF('3-Year P&L'!$B$9="","",-('3-Year P&L'!$B$13*(1+'3-Year P&L'!$G$13)+'3-Year P&L'!$B$14*(1+'3-Year P&L'!$G$14)+'3-Year P&L'!$B$15*(1+'3-Year P&L'!$G$15)+'3-Year P&L'!$B$16*(1+'3-Year P&L'!$G$16)+'3-Year P&L'!$B$17*(1+'3-Year P&L'!$G$17)+'3-Year P&L'!$B$18*(1+'3-Year P&L'!$G$18))*(E7*(1-MIN(30,'0. Assumptions'!$B$59)/30)+D7*MIN(30,'0. Assumptions'!$B$59)/30)),"") -> -39984.944 | F11: =IFERROR(IF('3-Year P&L'!$B$9="","",-('3-Year P&L'!$B$13*(1+'3-Year P&L'!$G$13)+'3-Year P&L'!$B$14*(1+'3-Year P&L'!$G$14)+'3-Year P&L'!$B$15*(1+'3-Year P&L'!$G$15)+'3-Year P&L'!$B$16*(1+'3-Year P&L'!$G$16)+'3-Year P&L'!$B$17*(1+'3-Year P&L'!$G$17)+'3-Year P&L'!$B$18*(1+'3-Year P&L'!$G$18))*(F7*(1-MIN(30,'0. Assumptions'!$B$59)/30)+E7*MIN(30,'0. Assumptions'!$B$59)/30)),"") -> -42226.778 | G11: =IFERROR(IF('3-Year P&L'!$B$9="","",-('3-Year P&L'!$B$13*(1+'3-Year P&L'!$G$13)+'3-Year P&L'!$B$14*(1+'3-Year P&L'!$G$14)+'3-Year P&L'!$B$15*(1+'3-Year P&L'!$G$15)+'3-Year P&L'!$B$16*(1+'3-Year P&L'!$G$16)+'3-Year P&L'!$B$17*(1+'3-Year P&L'!$G$17)+'3-Year P&L'!$B$18*(1+'3-Year P&L'!$G$18))*(G7*(1-MIN(30,'0. Assumptions'!$B$59)/30)+F7*MIN(30,'0. Assumptions'!$B$59)/30)),"") -> -42628.3 | H11: =IFERROR(IF('3-Year P&L'!$B$9="","",-('3-Year P&L'!$B$13*(1+'3-Year P&L'!$G$13)+'3-Year P&L'!$B$14*(1+'3-Year P&L'!$G$14)+'3-Year P&L'!$B$15*(1+'3-Year P&L'!$G$15)+'3-Year P&L'!$B$16*(1+'3-Year P&L'!$G$16)+'3-Year P&L'!$B$17*(1+'3-Year P&L'!$G$17)+'3-Year P&L'!$B$18*(1+'3-Year P&L'!$G$18))*(H7*(1-MIN(30,'0. Assumptions'!$B$59)/30)+G7*MIN(30,'0. Assumptions'!$B$59)/30)),"") -> -41624.494 | I11: =IFERROR(IF('3-Year P&L'!$B$9="","",-('3-Year P&L'!$B$13*(1+'3-Year P&L'!$G$13)+'3-Year P&L'!$B$14*(1+'3-Year P&L'!$G$14)+'3-Year P&L'!$B$15*(1+'3-Year P&L'!$G$15)+'3-Year P&L'!$B$16*(1+'3-Year P&L'!$G$16)+'3-Year P&L'!$B$17*(1+'3-Year P&L'!$G$17)+'3-Year P&L'!$B$18*(1+'3-Year P&L'!$G$18))*(I7*(1-MIN(30,'0. Assumptions'!$B$59)/30)+H7*MIN(30,'0. Assumptions'!$B$59)/30)),"") -> -40620.688 | J11: =IFERROR(IF('3-Year P&L'!$B$9="","",-('3-Year P&L'!$B$13*(1+'3-Year P&L'!$G$13)+'3-Year P&L'!$B$14*(1+'3-Year P&L'!$G$14)+'3-Year P&L'!$B$15*(1+'3-Year P&L'!$G$15)+'3-Year P&L'!$B$16*(1+'3-Year P&L'!$G$16)+'3-Year P&L'!$B$17*(1+'3-Year P&L'!$G$17)+'3-Year P&L'!$B$18*(1+'3-Year P&L'!$G$18))*(J7*(1-MIN(30,'0. Assumptions'!$B$59)/30)+I7*MIN(30,'0. Assumptions'!$B$59)/30)),"") -> -40152.245 | ... M11: =IFERROR(IF('3-Year P&L'!$B$9="","",-('3-Year P&L'!$B$13*(1+'3-Year P&L'!$G$13)+'3-Year P&L'!$B$14*(1+'3-Year P&L'!$G$14)+'3-Year P&L'!$B$15*(1+'3-Year P&L'!$G$15)+'3-Year P&L'!$B$16*(1+'3-Year P&L'!$G$16)+'3-Year P&L'!$B$17*(1+'3-Year P&L'!$G$17)+'3-Year P&L'!$B$18*(1+'3-Year P&L'!$G$18))*(M7*(1-MIN(30,'0. Assumptions'!$B$59)/30)+L7*MIN(30,'0. Assumptions'!$B$59)/30)),"") -> -43832.867 | N11: =IFERROR(IF('3-Year P&L'!$B$9="","",SUM(B11:M11)),"") -> -459860.32 | O11: =IFERROR("Food and beverage purchases, consumables, fees and contingencies, each at ITS tax rate (column G of the P&L; 0 in the US, where the sales tax you pay is part of the cost) and with the supplier payment days from ""0. Assumptions""."&IF('0. Assumptions'!$B$59=0,""," With "&TEXT('0. Assumptions'!$B$59,"0")&" payment days, the last purchases of the year are paid next year: the ""Year"" column of this row holds "&TEXT(MAX(0,12-ROUNDUP('0. Assumptions'!$B$59/30,0)),"0")&" months of purchases, not the year's cost."),"") -> Food and beverage purchases, consumables, fees and contingencies, each at ITS tax rate (column G of the P&L; 0 in the US, where the sales tax you pay is part of the cost) and with the supplier payment days from "0. Assumptions". With 14 payment days, the last purchases of the year are paid next year: the "Year" column of this row holds 11 months of purchases, not the year's cost.
A12: Operating fixed costs (incl. sales tax) | B12: =IFERROR(IF('3-Year P&L'!$B$9="","",-('3-Year P&L'!$B$37-'3-Year P&L'!$B$23-'3-Year P&L'!$B$35-'3-Year P&L'!$B$36+'3-Year P&L'!$B$39)/12),"") -> -9200 | C12: =IFERROR(IF('3-Year P&L'!$B$9="","",-('3-Year P&L'!$B$37-'3-Year P&L'!$B$23-'3-Year P&L'!$B$35-'3-Year P&L'!$B$36+'3-Year P&L'!$B$39)/12),"") -> -9200 | D12: =IFERROR(IF('3-Year P&L'!$B$9="","",-('3-Year P&L'!$B$37-'3-Year P&L'!$B$23-'3-Year P&L'!$B$35-'3-Year P&L'!$B$36+'3-Year P&L'!$B$39)/12),"") -> -9200 | E12: =IFERROR(IF('3-Year P&L'!$B$9="","",-('3-Year P&L'!$B$37-'3-Year P&L'!$B$23-'3-Year P&L'!$B$35-'3-Year P&L'!$B$36+'3-Year P&L'!$B$39)/12),"") -> -9200 | F12: =IFERROR(IF('3-Year P&L'!$B$9="","",-('3-Year P&L'!$B$37-'3-Year P&L'!$B$23-'3-Year P&L'!$B$35-'3-Year P&L'!$B$36+'3-Year P&L'!$B$39)/12),"") -> -9200 | G12: =IFERROR(IF('3-Year P&L'!$B$9="","",-('3-Year P&L'!$B$37-'3-Year P&L'!$B$23-'3-Year P&L'!$B$35-'3-Year P&L'!$B$36+'3-Year P&L'!$B$39)/12),"") -> -9200 | H12: =IFERROR(IF('3-Year P&L'!$B$9="","",-('3-Year P&L'!$B$37-'3-Year P&L'!$B$23-'3-Year P&L'!$B$35-'3-Year P&L'!$B$36+'3-Year P&L'!$B$39)/12),"") -> -9200 | I12: =IFERROR(IF('3-Year P&L'!$B$9="","",-('3-Year P&L'!$B$37-'3-Year P&L'!$B$23-'3-Year P&L'!$B$35-'3-Year P&L'!$B$36+'3-Year P&L'!$B$39)/12),"") -> -9200 | ... M12: =IFERROR(IF('3-Year P&L'!$B$9="","",-('3-Year P&L'!$B$37-'3-Year P&L'!$B$23-'3-Year P&L'!$B$35-'3-Year P&L'!$B$36+'3-Year P&L'!$B$39)/12),"") -> -9200 | N12: =IFERROR(IF('3-Year P&L'!$B$9="","",SUM(B12:M12)),"") -> -110400 | O12: The fixed costs that leave cash, each with its own tax rate: insurance carries none
A13: Payroll and employer payroll taxes | B13: =IFERROR(IF('3-Year P&L'!$B$9="","",-'3-Year P&L'!$B$23/MAX(12,'0. Assumptions'!$B$21)*(1+IF(1='0. Assumptions'!$B$60,(MAX(12,'0. Assumptions'!$B$21)-12)/2,0)+IF(1='0. Assumptions'!$B$61,(MAX(12,'0. Assumptions'!$B$21)-12)/2,0))),"") -> -32018.8 | C13: =IFERROR(IF('3-Year P&L'!$B$9="","",-'3-Year P&L'!$B$23/MAX(12,'0. Assumptions'!$B$21)*(1+IF(2='0. Assumptions'!$B$60,(MAX(12,'0. Assumptions'!$B$21)-12)/2,0)+IF(2='0. Assumptions'!$B$61,(MAX(12,'0. Assumptions'!$B$21)-12)/2,0))),"") -> -32018.8 | D13: =IFERROR(IF('3-Year P&L'!$B$9="","",-'3-Year P&L'!$B$23/MAX(12,'0. Assumptions'!$B$21)*(1+IF(3='0. Assumptions'!$B$60,(MAX(12,'0. Assumptions'!$B$21)-12)/2,0)+IF(3='0. Assumptions'!$B$61,(MAX(12,'0. Assumptions'!$B$21)-12)/2,0))),"") -> -32018.8 | E13: =IFERROR(IF('3-Year P&L'!$B$9="","",-'3-Year P&L'!$B$23/MAX(12,'0. Assumptions'!$B$21)*(1+IF(4='0. Assumptions'!$B$60,(MAX(12,'0. Assumptions'!$B$21)-12)/2,0)+IF(4='0. Assumptions'!$B$61,(MAX(12,'0. Assumptions'!$B$21)-12)/2,0))),"") -> -32018.8 | F13: =IFERROR(IF('3-Year P&L'!$B$9="","",-'3-Year P&L'!$B$23/MAX(12,'0. Assumptions'!$B$21)*(1+IF(5='0. Assumptions'!$B$60,(MAX(12,'0. Assumptions'!$B$21)-12)/2,0)+IF(5='0. Assumptions'!$B$61,(MAX(12,'0. Assumptions'!$B$21)-12)/2,0))),"") -> -32018.8 | G13: =IFERROR(IF('3-Year P&L'!$B$9="","",-'3-Year P&L'!$B$23/MAX(12,'0. Assumptions'!$B$21)*(1+IF(6='0. Assumptions'!$B$60,(MAX(12,'0. Assumptions'!$B$21)-12)/2,0)+IF(6='0. Assumptions'!$B$61,(MAX(12,'0. Assumptions'!$B$21)-12)/2,0))),"") -> -32018.8 | H13: =IFERROR(IF('3-Year P&L'!$B$9="","",-'3-Year P&L'!$B$23/MAX(12,'0. Assumptions'!$B$21)*(1+IF(7='0. Assumptions'!$B$60,(MAX(12,'0. Assumptions'!$B$21)-12)/2,0)+IF(7='0. Assumptions'!$B$61,(MAX(12,'0. Assumptions'!$B$21)-12)/2,0))),"") -> -32018.8 | I13: =IFERROR(IF('3-Year P&L'!$B$9="","",-'3-Year P&L'!$B$23/MAX(12,'0. Assumptions'!$B$21)*(1+IF(8='0. Assumptions'!$B$60,(MAX(12,'0. Assumptions'!$B$21)-12)/2,0)+IF(8='0. Assumptions'!$B$61,(MAX(12,'0. Assumptions'!$B$21)-12)/2,0))),"") -> -32018.8 | J13: =IFERROR(IF('3-Year P&L'!$B$9="","",-'3-Year P&L'!$B$23/MAX(12,'0. Assumptions'!$B$21)*(1+IF(9='0. Assumptions'!$B$60,(MAX(12,'0. Assumptions'!$B$21)-12)/2,0)+IF(9='0. Assumptions'!$B$61,(MAX(12,'0. Assumptions'!$B$21)-12)/2,0))),"") -> -32018.8 | K13: =IFERROR(IF('3-Year P&L'!$B$9="","",-'3-Year P&L'!$B$23/MAX(12,'0. Assumptions'!$B$21)*(1+IF(10='0. Assumptions'!$B$60,(MAX(12,'0. Assumptions'!$B$21)-12)/2,0)+IF(10='0. Assumptions'!$B$61,(MAX(12,'0. Assumptions'!$B$21)-12)/2,0))),"") -> -32018.8 | L13: =IFERROR(IF('3-Year P&L'!$B$9="","",-'3-Year P&L'!$B$23/MAX(12,'0. Assumptions'!$B$21)*(1+IF(11='0. Assumptions'!$B$60,(MAX(12,'0. Assumptions'!$B$21)-12)/2,0)+IF(11='0. Assumptions'!$B$61,(MAX(12,'0. Assumptions'!$B$21)-12)/2,0))),"") -> -32018.8 | M13: =IFERROR(IF('3-Year P&L'!$B$9="","",-'3-Year P&L'!$B$23/MAX(12,'0. Assumptions'!$B$21)*(1+IF(12='0. Assumptions'!$B$60,(MAX(12,'0. Assumptions'!$B$21)-12)/2,0)+IF(12='0. Assumptions'!$B$61,(MAX(12,'0. Assumptions'!$B$21)-12)/2,0))),"") -> -32018.8 | N13: =IFERROR(IF('3-Year P&L'!$B$9="","",SUM(B13:M13)),"") -> -384225.6 | O13: Twelve monthly installments plus extra pay periods in the months you set in Assumptions (only if pay periods > 12). The total for the year is the same as the P&L's
A14: Loan interest | B14: =IFERROR(IF('3-Year P&L'!$B$9="","",-Financing!$B$44/12),"") -> -2133.3333 | C14: =IFERROR(IF('3-Year P&L'!$B$9="","",-Financing!$B$44/12),"") -> -2133.3333 | D14: =IFERROR(IF('3-Year P&L'!$B$9="","",-Financing!$B$44/12),"") -> -2133.3333 | E14: =IFERROR(IF('3-Year P&L'!$B$9="","",-Financing!$B$44/12),"") -> -2133.3333 | F14: =IFERROR(IF('3-Year P&L'!$B$9="","",-Financing!$B$44/12),"") -> -2133.3333 | G14: =IFERROR(IF('3-Year P&L'!$B$9="","",-Financing!$B$44/12),"") -> -2133.3333 | H14: =IFERROR(IF('3-Year P&L'!$B$9="","",-Financing!$B$44/12),"") -> -2133.3333 | I14: =IFERROR(IF('3-Year P&L'!$B$9="","",-Financing!$B$44/12),"") -> -2133.3333 | ... M14: =IFERROR(IF('3-Year P&L'!$B$9="","",-Financing!$B$44/12),"") -> -2133.3333 | N14: =IFERROR(IF('3-Year P&L'!$B$9="","",SUM(B14:M14)),"") -> -25600
A15: Loan principal repaid | B15: =IFERROR(IF('3-Year P&L'!$B$9="","",-Financing!$B$45/12),"") -> -1338.5684 | C15: =IFERROR(IF('3-Year P&L'!$B$9="","",-Financing!$B$45/12),"") -> -1338.5684 | D15: =IFERROR(IF('3-Year P&L'!$B$9="","",-Financing!$B$45/12),"") -> -1338.5684 | E15: =IFERROR(IF('3-Year P&L'!$B$9="","",-Financing!$B$45/12),"") -> -1338.5684 | F15: =IFERROR(IF('3-Year P&L'!$B$9="","",-Financing!$B$45/12),"") -> -1338.5684 | G15: =IFERROR(IF('3-Year P&L'!$B$9="","",-Financing!$B$45/12),"") -> -1338.5684 | H15: =IFERROR(IF('3-Year P&L'!$B$9="","",-Financing!$B$45/12),"") -> -1338.5684 | I15: =IFERROR(IF('3-Year P&L'!$B$9="","",-Financing!$B$45/12),"") -> -1338.5684 | ... M15: =IFERROR(IF('3-Year P&L'!$B$9="","",-Financing!$B$45/12),"") -> -1338.5684 | N15: =IFERROR(IF('3-Year P&L'!$B$9="","",SUM(B15:M15)),"") -> -16062.821
A16: Sales tax collected (memo) | B16: =IFERROR(IF('3-Year P&L'!$B$9="","",'3-Year P&L'!$B$9*B7*SUMPRODUCT('3-Year P&L'!$E$10:$E$11,'3-Year P&L'!$G$10:$G$11)),"") -> 5653.2042 | C16: =IFERROR(IF('3-Year P&L'!$B$9="","",'3-Year P&L'!$B$9*C7*SUMPRODUCT('3-Year P&L'!$E$10:$E$11,'3-Year P&L'!$G$10:$G$11)),"") -> 6925.5778 | D16: =IFERROR(IF('3-Year P&L'!$B$9="","",'3-Year P&L'!$B$9*D7*SUMPRODUCT('3-Year P&L'!$E$10:$E$11,'3-Year P&L'!$G$10:$G$11)),"") -> 7440.9696 | E16: =IFERROR(IF('3-Year P&L'!$B$9="","",'3-Year P&L'!$B$9*E7*SUMPRODUCT('3-Year P&L'!$E$10:$E$11,'3-Year P&L'!$G$10:$G$11)),"") -> 7924.1494 | F16: =IFERROR(IF('3-Year P&L'!$B$9="","",'3-Year P&L'!$B$9*F7*SUMPRODUCT('3-Year P&L'!$E$10:$E$11,'3-Year P&L'!$G$10:$G$11)),"") -> 8310.6933 | G16: =IFERROR(IF('3-Year P&L'!$B$9="","",'3-Year P&L'!$B$9*G7*SUMPRODUCT('3-Year P&L'!$E$10:$E$11,'3-Year P&L'!$G$10:$G$11)),"") -> 8117.4214 | H16: =IFERROR(IF('3-Year P&L'!$B$9="","",'3-Year P&L'!$B$9*H7*SUMPRODUCT('3-Year P&L'!$E$10:$E$11,'3-Year P&L'!$G$10:$G$11)),"") -> 7924.1494 | I16: =IFERROR(IF('3-Year P&L'!$B$9="","",'3-Year P&L'!$B$9*I7*SUMPRODUCT('3-Year P&L'!$E$10:$E$11,'3-Year P&L'!$G$10:$G$11)),"") -> 7730.8775 | ... M16: =IFERROR(IF('3-Year P&L'!$B$9="","",'3-Year P&L'!$B$9*M7*SUMPRODUCT('3-Year P&L'!$E$10:$E$11,'3-Year P&L'!$G$10:$G$11)),"") -> 8890.5091 | N16: =IFERROR(IF('3-Year P&L'!$B$9="","",SUM(B16:M16)),"") -> 92690 | O16: Each sales line at ITS rate, read from the tax column of the P&L (one 8% rate in the example)
A17: Recoverable input tax (memo) | B17: =IFERROR(IF('3-Year P&L'!$B$9="","",'3-Year P&L'!$B$38*B7+'3-Year P&L'!$B$39/12),"") -> 0 | C17: =IFERROR(IF('3-Year P&L'!$B$9="","",'3-Year P&L'!$B$38*C7+'3-Year P&L'!$B$39/12),"") -> 0 | D17: =IFERROR(IF('3-Year P&L'!$B$9="","",'3-Year P&L'!$B$38*D7+'3-Year P&L'!$B$39/12),"") -> 0 | E17: =IFERROR(IF('3-Year P&L'!$B$9="","",'3-Year P&L'!$B$38*E7+'3-Year P&L'!$B$39/12),"") -> 0 | F17: =IFERROR(IF('3-Year P&L'!$B$9="","",'3-Year P&L'!$B$38*F7+'3-Year P&L'!$B$39/12),"") -> 0 | G17: =IFERROR(IF('3-Year P&L'!$B$9="","",'3-Year P&L'!$B$38*G7+'3-Year P&L'!$B$39/12),"") -> 0 | H17: =IFERROR(IF('3-Year P&L'!$B$9="","",'3-Year P&L'!$B$38*H7+'3-Year P&L'!$B$39/12),"") -> 0 | I17: =IFERROR(IF('3-Year P&L'!$B$9="","",'3-Year P&L'!$B$38*I7+'3-Year P&L'!$B$39/12),"") -> 0 | ... M17: =IFERROR(IF('3-Year P&L'!$B$9="","",'3-Year P&L'!$B$38*M7+'3-Year P&L'!$B$39/12),"") -> 0 | N17: =IFERROR(IF('3-Year P&L'!$B$9="","",SUM(B17:M17)),"") -> 0 | O17: Each item at its own rate, read from the tax column of the P&L: insurance and card processing fees carry none
A18: Carried forward (capex input tax included) | E18: =IFERROR(IF('3-Year P&L'!$B$9="","",'Startup Costs'!$B$32),"") -> 0 | H18: =IFERROR(IF('3-Year P&L'!$B$9="","",MAX(0,-E19)),"") -> 0 | K18: =IFERROR(IF('3-Year P&L'!$B$9="","",MAX(0,-H19)),"") -> 0 | O18: Sales tax paid on STARTUP COSTS enters here: it is offset against the tax collected in later quarters until used up. With 0% recoverable input tax (the US default) this line stays at zero
A19: Quarterly sales tax return | E19: =IFERROR(IF('3-Year P&L'!$B$9="","",SUM(B16:D16)-SUM(B17:D17)-E18),"") -> 20019.752 | H19: =IFERROR(IF('3-Year P&L'!$B$9="","",SUM(E16:G16)-SUM(E17:G17)-H18),"") -> 24352.264 | K19: =IFERROR(IF('3-Year P&L'!$B$9="","",SUM(H16:J16)-SUM(H17:J17)-K18),"") -> 23385.904 | O19: Sales tax collected minus recoverable input tax for the quarter, minus what was carried forward. If negative, nothing is paid: it is offset in the next quarter. With 0% recoverable input tax (the US default) it equals the sales tax collected in the quarter
A20: Sales tax remitted (quarterly filer) | E20: =IFERROR(IF('3-Year P&L'!$B$9="","",IF(E19<=0,"",-E19)),"") -> -20019.752 | H20: =IFERROR(IF('3-Year P&L'!$B$9="","",IF(H19<=0,"",-H19)),"") -> -24352.264 | K20: =IFERROR(IF('3-Year P&L'!$B$9="","",IF(K19<=0,"",-K19)),"") -> -23385.904 | N20: =IFERROR(IF('3-Year P&L'!$B$9="","",SUM(B20:M20)),"") -> -67757.92 | O20: Cash only leaves when the quarter's result is positive. Months without a settlement are left blank, not zero. The cell turns RED when the payment takes more cash than is left that month. The model settles quarterly, in the month after each plan quarter (Months 4, 7 and 10: April, July and October with Month 1 in January; the fourth quarter is remitted in Month 13, January of the next year): if your state requires monthly filing, expect smaller payments every month instead
A21: MONTHLY NET CASH FLOW | B21: =IFERROR(IF('3-Year P&L'!$B$9="","",SUM(B9:B15)+IF(B20="",0,B20)),"") -> 10880.295 | C21: =IFERROR(IF('3-Year P&L'!$B$9="","",SUM(C9:C15)+IF(C20="",0,C20)),"") -> 14773.658 | D21: =IFERROR(IF('3-Year P&L'!$B$9="","",SUM(D9:D15)+IF(D20="",0,D20)),"") -> 17901.18 | E21: =IFERROR(IF('3-Year P&L'!$B$9="","",SUM(E9:E15)+IF(E20="",0,E20)),"") -> 1845.7583 | F21: =IFERROR(IF('3-Year P&L'!$B$9="","",SUM(F9:F15)+IF(F20="",0,F20)),"") -> 24928.991 | G21: =IFERROR(IF('3-Year P&L'!$B$9="","",SUM(G9:G15)+IF(G20="",0,G20)),"") -> 22440.131 | H21: =IFERROR(IF('3-Year P&L'!$B$9="","",SUM(H9:H15)+IF(H20="",0,H20)),"") -> -3517.4977 | I21: =IFERROR(IF('3-Year P&L'!$B$9="","",SUM(I9:I15)+IF(I20="",0,I20)),"") -> 19229.401 | ... M21: =IFERROR(IF('3-Year P&L'!$B$9="","",SUM(M9:M15)+IF(M20="",0,M20)),"") -> 30628.58 | N21: =IFERROR(IF('3-Year P&L'!$B$9="","",SUM(B21:M21)),"") -> 179406.88
A22: CUMULATIVE CASH BALANCE | B22: =IFERROR(IF('3-Year P&L'!$B$9="","",'Startup Costs'!$B$29+B21),"") -> 140936.7 | C22: =IFERROR(IF('3-Year P&L'!$B$9="","",B22+C21),"") -> 155710.35 | D22: =IFERROR(IF('3-Year P&L'!$B$9="","",C22+D21),"") -> 173611.53 | E22: =IFERROR(IF('3-Year P&L'!$B$9="","",D22+E21),"") -> 175457.29 | F22: =IFERROR(IF('3-Year P&L'!$B$9="","",E22+F21),"") -> 200386.28 | G22: =IFERROR(IF('3-Year P&L'!$B$9="","",F22+G21),"") -> 222826.41 | H22: =IFERROR(IF('3-Year P&L'!$B$9="","",G22+H21),"") -> 219308.92 | I22: =IFERROR(IF('3-Year P&L'!$B$9="","",H22+I21),"") -> 238538.32 | J22: =IFERROR(IF('3-Year P&L'!$B$9="","",I22+J21),"") -> 258062.22 | ... M22: =IFERROR(IF('3-Year P&L'!$B$9="","",L22+M21),"") -> 309463.28
A23: Minimum balance of the year | B23: =IFERROR(IF('3-Year P&L'!$B$9="","",IF(COUNT(B22:M22)=0,"",MIN(B22:M22))),"") -> 140936.7 | D23: If negative, raise working capital or the loan: you run out of cash
A24: Month when cash bottoms out | B24: =IFERROR(IF('3-Year P&L'!$B$9="","",IF(COUNT(B22:M22)=0,"",MATCH(MIN(B22:M22),B22:M22,0))),"") -> 1 | D24: It answers the question that decides a bank deal: in which month the cash runs out
A25: RETURN ON INVESTMENT
A26: Free cash flow before debt, year 1 | B26: =IFERROR(IF('3-Year P&L'!$B$9="","",'3-Year P&L'!$B$47+'3-Year P&L'!$B$35+Financing!$B$44),"") -> 149707.68 | D26: Net income plus depreciation (which is not paid) plus that year's interest: principal is not subtracted because this flow is BEFORE debt. The SAME basis as years 2 and 3, so the payback compares like with like
A27: Free cash flow before debt, year 2 | B27: =IFERROR(IF('3-Year P&L'!$B$9="","",'3-Year P&L'!$C$47+'3-Year P&L'!$C$35+Financing!$B$46),"") -> 176030.84 | D27: Net income plus depreciation (which is not paid) plus that year's interest: principal is not subtracted because this flow is BEFORE debt. Without a monthly table, it is an estimate
A28: Free cash flow before debt, year 3 | B28: =IFERROR(IF('3-Year P&L'!$B$9="","",'3-Year P&L'!$D$47+'3-Year P&L'!$D$35+Financing!$B$48),"") -> 193374.59 | D28: Net income plus depreciation (which is not paid) plus that year's interest: principal is not subtracted because this flow is BEFORE debt. Without a monthly table, it is an estimate
A29: For reference: ACTUAL year-1 cash flow (monthly table, before debt) | B29: =IFERROR(IF('3-Year P&L'!$B$9="","",N21+Financing!$B$44+Financing!$B$45),"") -> 221069.71 | D29: The sum of the twelve monthly net cash flows above, adding back the interest and principal paid that year. It is NOT the one the payback uses: it includes sales tax not yet settled and supplier credit, two things that have to be paid back and that years 2 and 3 do not have
A30: Investment to recover (net of recoverable input tax) | B30: =IFERROR(IF('3-Year P&L'!$B$9="","",'Startup Costs'!$B$33-'Startup Costs'!$B$32),"") -> 385156.4 | D30: CAPEX plus working capital: the total cash needed MINUS the recoverable input tax on startup costs, which is not lost (it is recovered through the quarterly return, and this tab offsets it quarter by quarter; it is zero in the US default). Working capital is recovered when you close, but until then it is tied up
A31: Project payback (years), before debt | B31: =IFERROR(IF('3-Year P&L'!$B$9="","",IF(B26>=B30,ROUND(B30/B26,1),IF(B26+B27>=B30,ROUND(1+(B30-B26)/B27,1),IF(B26+B27+B28>=B30,ROUND(2+(B30-B26-B27)/B28,1),"Over 3 years")))),"") -> 2.3 | D31: Measures how long the business takes to pay back the investment with what it generates BEFORE paying the lender, on the SAME cash flow basis in all three years; whether you can make the loan payment is answered by the DSCR on the "Financing" tab. The Word business plan quotes this figure; if you change a green cell, this workbook rules
A32: Payback on CAPEX, excluding working capital (years) | B32: =IFERROR(IF('3-Year P&L'!$B$9="","",IF(B26>='Startup Costs'!$B$31,ROUND('Startup Costs'!$B$31/B26,1),IF(B26+B27>='Startup Costs'!$B$31,ROUND(1+('Startup Costs'!$B$31-B26)/B27,1),IF(B26+B27+B28>='Startup Costs'!$B$31,ROUND(2+('Startup Costs'!$B$31-B26-B27)/B28,1),"Over 3 years")))),"") -> 1.6 | D32: The same calculation on what you BUY (build-out, equipment, launch and formation costs), without working capital: that money is not spent, it is tied up and comes back when the business closes. For reference only: the payback that matters is the one above
A34: Fourth-quarter sales tax is settled in Month 13 (January of the following year when Month 1 is January), so it does not appear in this table. The model pays year-1 income tax in July of year 2 (a simplification: estimated tax payments are usually quarterly). The loan payment is spread in twelve equal parts following the ANNUAL schedule in the Financing tab, and payroll in twelve monthly installments (plus extra pay periods in their month, only if pay periods > 12).

Sheet Financing
A1: FINANCING PLAN
A2: What you need, where it comes from and what it costs to repay. It is the sheet your lender asks for along with the P&L.
A4: Item | B4: Amount | C4: Notes
A5: SOURCES OF FUNDS
A6: Owner's equity (your own money) | B6: =IFERROR(IF('0. Assumptions'!$B$30="","",'0. Assumptions'!$B$30),"") -> 130000
A7: Loan requested — bank or SBA 7(a) (amortized below) | B7: =IFERROR(IF('0. Assumptions'!$B$31="","",'0. Assumptions'!$B$31),"") -> 256000
A8: Other loan (not in the schedule or the DSCR — enter your loan in row 7) | B8: 0 | C8: A source of funds only: NOT amortized, so it is not in the schedule, the P&L interest or the DSCR. Enter your bank or SBA 7(a) loan in row 7 ("Loan requested" in "0. Assumptions"); use this row only for a second loan
A9: SBA Microloan (not in the schedule or the DSCR — enter your loan in row 7) | B9: 0 | C9: SBA Microloans go up to $50,000 through nonprofit intermediaries. Like row 8, a source of funds only: not in the schedule or the DSCR. If it is your only loan, enter it in row 7 instead
A10: Investors / partners (equity: dilutes, not repaid) | B10: 0 | C10: Equity: it dilutes your ownership and is not repaid
A11: Local grants (usually paid after you spend) | B11: 0 | C11: Usually paid AFTER you document the spending
A12: TOTAL SOURCES OF FUNDS | B12: =IFERROR(IF(COUNT(B6:B11)=0,"",SUM(B6:B11)),"") -> 386000
A13: USES OF FUNDS
A14: Total cash needed at launch | B14: =IFERROR(IF('Startup Costs'!$B$33="","",'Startup Costs'!$B$33),"") -> 385156.4 | C14: Startup costs plus any recoverable tax you have to advance (zero by default in the US)
A15: Difference (sources - uses) | B15: =IFERROR(B12-B14,"") -> 843.6 | C15: In red (negative), the plan is NOT funded. Far above zero is not free either: you pay interest on money you do not use
A16: Difference as a % of uses | B16: =IFERROR(B15/B14,"") -> 0.0021902791 | C16: Amber above the margin you set: it is debt you pay for without needing it
A17: Acceptable over-funding (%) | B17: 0.05 | C17: A small cushion over the need is healthy; 20% extra is interest thrown away
A18: Loan that would match sources to needs | B18: =IFERROR(MAX(0,B14-B12+B7),"") -> 255156.4 | C18: Copy it into "Loan requested" in the "0. Assumptions" tab and the difference goes to zero. Rows 8-11 lower this figure, but only the row-7 loan is amortized and counted in the DSCR
A19: LOAN TERMS
A20: Principal amount | B20: =IFERROR(IF('0. Assumptions'!$B$31=0,"",'0. Assumptions'!$B$31),"") -> 256000
A21: Nominal annual interest rate (not APR) | B21: =IFERROR(IF('0. Assumptions'!$B$32="","",'0. Assumptions'!$B$32),"") -> 0.1
A22: Total term (years) | B22: =IFERROR(IF('0. Assumptions'!$B$33="","",'0. Assumptions'!$B$33),"") -> 10
A23: Interest-only period applied (years) | B23: =IFERROR(IF(OR('0. Assumptions'!$B$34="",'0. Assumptions'!$B$33=""),"",IF('0. Assumptions'!$B$34>='0. Assumptions'!$B$33,0,'0. Assumptions'!$B$34)),"") -> 0 | C23: An interest-only period equal to or longer than the term does not exist: the sheet cancels it at the source
A24: Annual payment during repayment | B24: =IFERROR(IF(B22-B23<=0,"",IF(B21=0,B20/(B22-B23),B20*B21/(1-(1+B21)^-(B22-B23)))),"") -> 41662.821 | C24: Standard amortizing loan with a level annual payment. At a 0% rate it is the principal divided by the repayment years: without that branch the schedule would shut down entirely
A25: AMORTIZATION SCHEDULE
A26: Year | B26: Opening balance | C26: Interest | D26: Principal repaid | E26: Total payment | F26: Closing balance | G26: Cash flow available for debt service (after tax; from year 4 on, year 3 held flat) | H26: DSCR for the year
A27: 1 | B27: =IFERROR(IF(B20="","",B20),"") -> 256000 | C27: =IFERROR(IF(OR(1>B22,B27=""),"",B27*B21),"") -> 25600 | D27: =IFERROR(IF(OR(1>B22,B27=""),"",IF(1<=B23,0,MIN(B27,B24-C27))),"") -> 16062.821 | E27: =IFERROR(IF(C27="","",C27+D27),"") -> 41662.821 | F27: =IFERROR(IF(D27="","",B27-D27),"") -> 239937.18 | G27: =IFERROR(IF(E27="","",'3-Year P&L'!$B$40-'3-Year P&L'!$B$45+'3-Year P&L'!$B$35+'3-Year P&L'!$B$36),"") -> 149707.68 | H27: =IFERROR(IF(OR(E27="",E27=0),"",G27/E27),"") -> 3.5933159
A28: 2 | B28: =IFERROR(IF(OR(2>B22,F27=""),"",F27),"") -> 239937.18 | C28: =IFERROR(IF(OR(2>B22,B28=""),"",B28*B21),"") -> 23993.718 | D28: =IFERROR(IF(OR(2>B22,B28=""),"",IF(2<=B23,0,MIN(B28,B24-C28))),"") -> 17669.103 | E28: =IFERROR(IF(C28="","",C28+D28),"") -> 41662.821 | F28: =IFERROR(IF(D28="","",B28-D28),"") -> 222268.08 | G28: =IFERROR(IF(E28="","",'3-Year P&L'!$C$40-'3-Year P&L'!$C$45+'3-Year P&L'!$C$35+'3-Year P&L'!$C$36),"") -> 176030.84 | H28: =IFERROR(IF(OR(E28="",E28=0),"",G28/E28),"") -> 4.2251301
A29: 3 | B29: =IFERROR(IF(OR(3>B22,F28=""),"",F28),"") -> 222268.08 | C29: =IFERROR(IF(OR(3>B22,B29=""),"",B29*B21),"") -> 22226.808 | D29: =IFERROR(IF(OR(3>B22,B29=""),"",IF(3<=B23,0,MIN(B29,B24-C29))),"") -> 19436.014 | E29: =IFERROR(IF(C29="","",C29+D29),"") -> 41662.821 | F29: =IFERROR(IF(D29="","",B29-D29),"") -> 202832.06 | G29: =IFERROR(IF(E29="","",'3-Year P&L'!$D$40-'3-Year P&L'!$D$45+'3-Year P&L'!$D$35+'3-Year P&L'!$D$36),"") -> 193374.59 | H29: =IFERROR(IF(OR(E29="",E29=0),"",G29/E29),"") -> 4.6414186
A30: 4 | B30: =IFERROR(IF(OR(4>B22,F29=""),"",F29),"") -> 202832.06 | C30: =IFERROR(IF(OR(4>B22,B30=""),"",B30*B21),"") -> 20283.206 | D30: =IFERROR(IF(OR(4>B22,B30=""),"",IF(4<=B23,0,MIN(B30,B24-C30))),"") -> 21379.615 | E30: =IFERROR(IF(C30="","",C30+D30),"") -> 41662.821 | F30: =IFERROR(IF(D30="","",B30-D30),"") -> 181452.45 | G30: =IFERROR(IF(E30="","",'3-Year P&L'!$D$40-'3-Year P&L'!$D$45+'3-Year P&L'!$D$35+'3-Year P&L'!$D$36),"") -> 193374.59 | H30: =IFERROR(IF(OR(E30="",E30=0),"",G30/E30),"") -> 4.6414186
A31: 5 | B31: =IFERROR(IF(OR(5>B22,F30=""),"",F30),"") -> 181452.45 | C31: =IFERROR(IF(OR(5>B22,B31=""),"",B31*B21),"") -> 18145.245 | D31: =IFERROR(IF(OR(5>B22,B31=""),"",IF(5<=B23,0,MIN(B31,B24-C31))),"") -> 23517.576 | E31: =IFERROR(IF(C31="","",C31+D31),"") -> 41662.821 | F31: =IFERROR(IF(D31="","",B31-D31),"") -> 157934.87 | G31: =IFERROR(IF(E31="","",'3-Year P&L'!$D$40-'3-Year P&L'!$D$45+'3-Year P&L'!$D$35+'3-Year P&L'!$D$36),"") -> 193374.59 | H31: =IFERROR(IF(OR(E31="",E31=0),"",G31/E31),"") -> 4.6414186
A32: 6 | B32: =IFERROR(IF(OR(6>B22,F31=""),"",F31),"") -> 157934.87 | C32: =IFERROR(IF(OR(6>B22,B32=""),"",B32*B21),"") -> 15793.487 | D32: =IFERROR(IF(OR(6>B22,B32=""),"",IF(6<=B23,0,MIN(B32,B24-C32))),"") -> 25869.334 | E32: =IFERROR(IF(C32="","",C32+D32),"") -> 41662.821 | F32: =IFERROR(IF(D32="","",B32-D32),"") -> 132065.54 | G32: =IFERROR(IF(E32="","",'3-Year P&L'!$D$40-'3-Year P&L'!$D$45+'3-Year P&L'!$D$35+'3-Year P&L'!$D$36),"") -> 193374.59 | H32: =IFERROR(IF(OR(E32="",E32=0),"",G32/E32),"") -> 4.6414186
A33: 7 | B33: =IFERROR(IF(OR(7>B22,F32=""),"",F32),"") -> 132065.54 | C33: =IFERROR(IF(OR(7>B22,B33=""),"",B33*B21),"") -> 13206.554 | D33: =IFERROR(IF(OR(7>B22,B33=""),"",IF(7<=B23,0,MIN(B33,B24-C33))),"") -> 28456.267 | E33: =IFERROR(IF(C33="","",C33+D33),"") -> 41662.821 | F33: =IFERROR(IF(D33="","",B33-D33),"") -> 103609.27 | G33: =IFERROR(IF(E33="","",'3-Year P&L'!$D$40-'3-Year P&L'!$D$45+'3-Year P&L'!$D$35+'3-Year P&L'!$D$36),"") -> 193374.59 | H33: =IFERROR(IF(OR(E33="",E33=0),"",G33/E33),"") -> 4.6414186
A34: 8 | B34: =IFERROR(IF(OR(8>B22,F33=""),"",F33),"") -> 103609.27 | C34: =IFERROR(IF(OR(8>B22,B34=""),"",B34*B21),"") -> 10360.927 | D34: =IFERROR(IF(OR(8>B22,B34=""),"",IF(8<=B23,0,MIN(B34,B24-C34))),"") -> 31301.894 | E34: =IFERROR(IF(C34="","",C34+D34),"") -> 41662.821 | F34: =IFERROR(IF(D34="","",B34-D34),"") -> 72307.375 | G34: =IFERROR(IF(E34="","",'3-Year P&L'!$D$40-'3-Year P&L'!$D$45+'3-Year P&L'!$D$35+'3-Year P&L'!$D$36),"") -> 193374.59 | H34: =IFERROR(IF(OR(E34="",E34=0),"",G34/E34),"") -> 4.6414186
A35: 9 | B35: =IFERROR(IF(OR(9>B22,F34=""),"",F34),"") -> 72307.375 | C35: =IFERROR(IF(OR(9>B22,B35=""),"",B35*B21),"") -> 7230.7375 | D35: =IFERROR(IF(OR(9>B22,B35=""),"",IF(9<=B23,0,MIN(B35,B24-C35))),"") -> 34432.084 | E35: =IFERROR(IF(C35="","",C35+D35),"") -> 41662.821 | F35: =IFERROR(IF(D35="","",B35-D35),"") -> 37875.292 | G35: =IFERROR(IF(E35="","",'3-Year P&L'!$D$40-'3-Year P&L'!$D$45+'3-Year P&L'!$D$35+'3-Year P&L'!$D$36),"") -> 193374.59 | H35: =IFERROR(IF(OR(E35="",E35=0),"",G35/E35),"") -> 4.6414186
A36: 10 | B36: =IFERROR(IF(OR(10>B22,F35=""),"",F35),"") -> 37875.292 | C36: =IFERROR(IF(OR(10>B22,B36=""),"",B36*B21),"") -> 3787.5292 | D36: =IFERROR(IF(OR(10>B22,B36=""),"",IF(10<=B23,0,MIN(B36,B24-C36))),"") -> 37875.292 | E36: =IFERROR(IF(C36="","",C36+D36),"") -> 41662.821 | F36: =IFERROR(IF(D36="","",B36-D36),"") -> 2.8376235e-10 | G36: =IFERROR(IF(E36="","",'3-Year P&L'!$D$40-'3-Year P&L'!$D$45+'3-Year P&L'!$D$35+'3-Year P&L'!$D$36),"") -> 193374.59 | H36: =IFERROR(IF(OR(E36="",E36=0),"",G36/E36),"") -> 4.6414186
A37: 11 | B37: =IFERROR(IF(OR(11>B22,F36=""),"",F36),"") | C37: =IFERROR(IF(OR(11>B22,B37=""),"",B37*B21),"") | D37: =IFERROR(IF(OR(11>B22,B37=""),"",IF(11<=B23,0,MIN(B37,B24-C37))),"") | E37: =IFERROR(IF(C37="","",C37+D37),"") | F37: =IFERROR(IF(D37="","",B37-D37),"") | G37: =IFERROR(IF(E37="","",'3-Year P&L'!$D$40-'3-Year P&L'!$D$45+'3-Year P&L'!$D$35+'3-Year P&L'!$D$36),"") | H37: =IFERROR(IF(OR(E37="",E37=0),"",G37/E37),"")
A38: 12 | B38: =IFERROR(IF(OR(12>B22,F37=""),"",F37),"") | C38: =IFERROR(IF(OR(12>B22,B38=""),"",B38*B21),"") | D38: =IFERROR(IF(OR(12>B22,B38=""),"",IF(12<=B23,0,MIN(B38,B24-C38))),"") | E38: =IFERROR(IF(C38="","",C38+D38),"") | F38: =IFERROR(IF(D38="","",B38-D38),"") | G38: =IFERROR(IF(E38="","",'3-Year P&L'!$D$40-'3-Year P&L'!$D$45+'3-Year P&L'!$D$35+'3-Year P&L'!$D$36),"") | H38: =IFERROR(IF(OR(E38="",E38=0),"",G38/E38),"")
A39: 13 | B39: =IFERROR(IF(OR(13>B22,F38=""),"",F38),"") | C39: =IFERROR(IF(OR(13>B22,B39=""),"",B39*B21),"") | D39: =IFERROR(IF(OR(13>B22,B39=""),"",IF(13<=B23,0,MIN(B39,B24-C39))),"") | E39: =IFERROR(IF(C39="","",C39+D39),"") | F39: =IFERROR(IF(D39="","",B39-D39),"") | G39: =IFERROR(IF(E39="","",'3-Year P&L'!$D$40-'3-Year P&L'!$D$45+'3-Year P&L'!$D$35+'3-Year P&L'!$D$36),"") | H39: =IFERROR(IF(OR(E39="",E39=0),"",G39/E39),"")
A40: 14 | B40: =IFERROR(IF(OR(14>B22,F39=""),"",F39),"") | C40: =IFERROR(IF(OR(14>B22,B40=""),"",B40*B21),"") | D40: =IFERROR(IF(OR(14>B22,B40=""),"",IF(14<=B23,0,MIN(B40,B24-C40))),"") | E40: =IFERROR(IF(C40="","",C40+D40),"") | F40: =IFERROR(IF(D40="","",B40-D40),"") | G40: =IFERROR(IF(E40="","",'3-Year P&L'!$D$40-'3-Year P&L'!$D$45+'3-Year P&L'!$D$35+'3-Year P&L'!$D$36),"") | H40: =IFERROR(IF(OR(E40="",E40=0),"",G40/E40),"")
A41: 15 | B41: =IFERROR(IF(OR(15>B22,F40=""),"",F40),"") | C41: =IFERROR(IF(OR(15>B22,B41=""),"",B41*B21),"") | D41: =IFERROR(IF(OR(15>B22,B41=""),"",IF(15<=B23,0,MIN(B41,B24-C41))),"") | E41: =IFERROR(IF(C41="","",C41+D41),"") | F41: =IFERROR(IF(D41="","",B41-D41),"") | G41: =IFERROR(IF(E41="","",'3-Year P&L'!$D$40-'3-Year P&L'!$D$45+'3-Year P&L'!$D$35+'3-Year P&L'!$D$36),"") | H41: =IFERROR(IF(OR(E41="",E41=0),"",G41/E41),"")
A42: Schedule closing tolerance | B42: 0.01 | C42: Rounding margin. Above it, the schedule does not close and there is principal left unpaid
A43: Balance outstanding at maturity | B43: =IFERROR(IF(B20="","",ROUND(B20-SUM(D27:D41),2)),"") -> 0 | C43: Must be zero: the principal repaid in the schedule has to equal the amount borrowed. If it is positive, the term falls short
A44: Year-1 interest | B44: =IFERROR(IF(B20="","",IF(C27="",0,C27)),"") -> 25600
A45: Year-1 principal repaid | B45: =IFERROR(IF(B20="","",IF(D27="",0,D27)),"") -> 16062.821
A46: Year-2 interest | B46: =IFERROR(IF(B20="","",IF(C28="",0,C28)),"") -> 23993.718
A47: Year-2 principal repaid | B47: =IFERROR(IF(B20="","",IF(D28="",0,D28)),"") -> 17669.103
A48: Year-3 interest | B48: =IFERROR(IF(B20="","",IF(C29="",0,C29)),"") -> 22226.808
A49: Year-3 principal repaid | B49: =IFERROR(IF(B20="","",IF(D29="",0,D29)),"") -> 19436.014
A50: DEBT SERVICE COVERAGE RATIO (DSCR)
A51: Year-1 DSCR | B51: =IFERROR(('3-Year P&L'!$B$40-'3-Year P&L'!$B$45+'3-Year P&L'!$B$35+B44)/(B44+B45),"") -> 3.5933159 | C51: An INTEREST-ONLY year, if there is one: with only interest in the denominator the ratio shoots up and does not measure the business
A52: Year-2 DSCR | B52: =IFERROR(('3-Year P&L'!$C$40-'3-Year P&L'!$C$45+'3-Year P&L'!$C$35+B46)/(B46+B47),"") -> 4.2251301
A53: Year-3 DSCR | B53: =IFERROR(('3-Year P&L'!$D$40-'3-Year P&L'!$D$45+'3-Year P&L'!$D$35+B48)/(B48+B49),"") -> 4.6414186
A54: Minimum DSCR across the whole schedule | B54: =IFERROR(IF(COUNT(H27:H41)=0,"",MIN(H27:H41)),"") -> 3.5933159 | C54: The worst year of the life of the loan, not the best of the three the P&L projects. It is the number that decides a loan. Mind the scope: years 1 to 3 come from the P&L, and from year 4 on the schedule HOLDS year 3's cash flow, so the minimum over those years is a sustained projection, not a calculated year. The cash flow is after tax
A56: DSCR is calculated BEFORE debt and AFTER tax: income tax is subtracted from pre-tax income, depreciation and interest are added back, and the result is divided by what has to be paid that year. Below the minimum in the "0. Assumptions" tab, the business does not generate enough to repay the loan. In the schedule, the available cash flow from year 4 on is held at year 3's: the P&L projects only three years, and no growth is invented here that has not been calculated.
