Workbook

Sheet Instrucciones
A1: Pedidos de Compra
A2: AI Chef Pro — aichef.pro
A4: Genera pedidos de compra con el IVA correcto en cada línea y con el desglose que pide un albarán.
A5: 1. Rellena una sola vez tus datos de emisor en el bloque verde de la derecha: establecimiento, CIF, dirección de entrega y contacto. Sin ellos, quien recibe el pedido no sabe quién pide ni dónde entregar.
A6: 2. Da de alta a tus proveedores en la hoja 'Proveedores'. El desplegable del pedido, el teléfono y el pedido mínimo de la cabecera salen de esa tabla.
A7: 3. En 'Pedido Actual' escribe producto, categoría, unidad, cantidad y precio. El IVA se rellena solo: primero busca el PRODUCTO en la tabla de excepciones de la hoja Listas y, si no está, aplica el tipo de su categoría. Puedes cambiarlo línea a línea con el desplegable 4 / 10 / 21. Si te dejas la categoría, la casilla del IVA se queda EN BLANCO en vez de caer al 10 % en silencio: en una línea de alcohol o de limpieza eso serían 11 puntos de menos.
A8: 3 bis. Las TRES primeras líneas son un ejemplo con cantidad y precio para que veas el pedido funcionando —base, cuota, total y desglose por los tres tipos—. BÓRRALAS antes de enviar tu primer pedido.
A9: 4. Si escribes cantidad y te dejas el precio, la casilla del subtotal avisa con «falta coste» en vez de valorar la línea en 0,00 € y sumarla al total como si fuera gratis.
A10: 5. Los totales del pedido están en las filas 40 a 42: base imponible, cuota de IVA y total. Justo debajo, en la fila 43, el fichero te dice si el pedido SUPERA EL PEDIDO MÍNIMO de ese proveedor y cuánto te falta si no: es lo que evita que te cobren portes. Y en las filas 45 a 48 tienes el desglose por tipo (4 %, 10 % y 21 %).
A11: 6. Cuando cierres el pedido, copia la fila 4 de 'Historial Pedidos' y pégala como valor: ya viene enlazada al pedido en curso. Esa fila 4 NO suma en el total del periodo, precisamente para que el pedido no se cuente dos veces mientras haces la copia.
A12: 7. La hoja 'Listas' guarda DOS tablas: el tipo de IVA de cada categoría y, al lado, las excepciones por producto (los cereales, las harinas y las legumbres van al 4 % aunque su categoría sea del 10 %; los refrescos con azúcares añadidos, al 21 %). Edítalas si tu caso es distinto: son tablas, no números escondidos dentro de la fórmula.
A13: Para enviarlo: Archivo → Imprimir → PDF. La hoja ya está en A4 apaisado y repite la cabecera de la tabla en cada página.
... A17: Versión 2.0 · agosto 2026 · aichef.pro/kit-inventario · info@aichef.pro

Sheet Pedido Actual
A1: PEDIDO DE COMPRA
A2: EJEMPLO: la cabecera y las tres primeras líneas vienen rellenas para que veas el pedido funcionando (IVA por línea, base, cuota, total, desglose por tipo y aviso de pedido mínimo). BÓRRALAS antes de enviar tu primer pedido.
A3: Proveedor: | C3: Cárnicas del Norte (ejemplo) | D3: Teléfono | E3: =IF($C$3="","",IFERROR(VLOOKUP($C$3,Proveedores!$A$4:$H$23,3,FALSE),"")) -> 948 21 34 55 | F3: Establecimiento
A4: Fecha del pedido: | C4: 46252 | D4: Pedido mín. (€) | E4: =IF($C$3="","",IFERROR(VLOOKUP($C$3,Proveedores!$A$4:$H$23,5,FALSE),"")) -> 150 | F4: CIF / NIF
A5: Fecha de entrega: | C5: 46253 | F5: Entrega en
A6: Nº de pedido: | C6: PED-2026-004 | F6: Contacto
A8: # | B8: Producto | C8: Categoría | D8: Unidad | E8: Cantidad | F8: Precio/ud (€) | G8: Subtotal (€) | H8: IVA % | I8: Total (€)
A9: 1 | B9: Solomillo de ternera | C9: Cárnicos | D9: kg | E9: 5 | F9: 32 | G9: =IF($E9="","",IF($F9="","⚠ falta coste",$E9*$F9)) -> 160 | H9: =IF($B9="","",IFERROR(VLOOKUP($B9,Listas!$E$2:$F$20,2,FALSE),IF($C9="","",IFERROR(VLOOKUP($C9,Listas!$A$2:$B$11,2,FALSE),"")))) -> 10 | I9: =IF(OR($E9="",$F9=""),"",$E9*$F9*(1+$H9/100)) -> 176
A10: 2 | B10: Vino tinto (botella 75 cl) | C10: Bebidas Alcohólicas | D10: ud | E10: 12 | F10: 4.8 | G10: =IF($E10="","",IF($F10="","⚠ falta coste",$E10*$F10)) -> 57.6 | H10: =IF($B10="","",IFERROR(VLOOKUP($B10,Listas!$E$2:$F$20,2,FALSE),IF($C10="","",IFERROR(VLOOKUP($C10,Listas!$A$2:$B$11,2,FALSE),"")))) -> 21 | I10: =IF(OR($E10="",$F10=""),"",$E10*$F10*(1+$H10/100)) -> 69.696
A11: 3 | B11: Lechuga | C11: Verduras/Frutas | D11: ud | E11: 10 | F11: 0.95 | G11: =IF($E11="","",IF($F11="","⚠ falta coste",$E11*$F11)) -> 9.5 | H11: =IF($B11="","",IFERROR(VLOOKUP($B11,Listas!$E$2:$F$20,2,FALSE),IF($C11="","",IFERROR(VLOOKUP($C11,Listas!$A$2:$B$11,2,FALSE),"")))) -> 4 | I11: =IF(OR($E11="",$F11=""),"",$E11*$F11*(1+$H11/100)) -> 9.88
A12: 4 | G12: =IF($E12="","",IF($F12="","⚠ falta coste",$E12*$F12)) | H12: =IF($B12="","",IFERROR(VLOOKUP($B12,Listas!$E$2:$F$20,2,FALSE),IF($C12="","",IFERROR(VLOOKUP($C12,Listas!$A$2:$B$11,2,FALSE),"")))) | I12: =IF(OR($E12="",$F12=""),"",$E12*$F12*(1+$H12/100))
A13: 5 | G13: =IF($E13="","",IF($F13="","⚠ falta coste",$E13*$F13)) | H13: =IF($B13="","",IFERROR(VLOOKUP($B13,Listas!$E$2:$F$20,2,FALSE),IF($C13="","",IFERROR(VLOOKUP($C13,Listas!$A$2:$B$11,2,FALSE),"")))) | I13: =IF(OR($E13="",$F13=""),"",$E13*$F13*(1+$H13/100))
A14: 6 | G14: =IF($E14="","",IF($F14="","⚠ falta coste",$E14*$F14)) | H14: =IF($B14="","",IFERROR(VLOOKUP($B14,Listas!$E$2:$F$20,2,FALSE),IF($C14="","",IFERROR(VLOOKUP($C14,Listas!$A$2:$B$11,2,FALSE),"")))) | I14: =IF(OR($E14="",$F14=""),"",$E14*$F14*(1+$H14/100))
A15: 7 | G15: =IF($E15="","",IF($F15="","⚠ falta coste",$E15*$F15)) | H15: =IF($B15="","",IFERROR(VLOOKUP($B15,Listas!$E$2:$F$20,2,FALSE),IF($C15="","",IFERROR(VLOOKUP($C15,Listas!$A$2:$B$11,2,FALSE),"")))) | I15: =IF(OR($E15="",$F15=""),"",$E15*$F15*(1+$H15/100))
A16: 8 | G16: =IF($E16="","",IF($F16="","⚠ falta coste",$E16*$F16)) | H16: =IF($B16="","",IFERROR(VLOOKUP($B16,Listas!$E$2:$F$20,2,FALSE),IF($C16="","",IFERROR(VLOOKUP($C16,Listas!$A$2:$B$11,2,FALSE),"")))) | I16: =IF(OR($E16="",$F16=""),"",$E16*$F16*(1+$H16/100))
A17: 9 | G17: =IF($E17="","",IF($F17="","⚠ falta coste",$E17*$F17)) | H17: =IF($B17="","",IFERROR(VLOOKUP($B17,Listas!$E$2:$F$20,2,FALSE),IF($C17="","",IFERROR(VLOOKUP($C17,Listas!$A$2:$B$11,2,FALSE),"")))) | I17: =IF(OR($E17="",$F17=""),"",$E17*$F17*(1+$H17/100))
A18: 10 | G18: =IF($E18="","",IF($F18="","⚠ falta coste",$E18*$F18)) | H18: =IF($B18="","",IFERROR(VLOOKUP($B18,Listas!$E$2:$F$20,2,FALSE),IF($C18="","",IFERROR(VLOOKUP($C18,Listas!$A$2:$B$11,2,FALSE),"")))) | I18: =IF(OR($E18="",$F18=""),"",$E18*$F18*(1+$H18/100))
A19: 11 | G19: =IF($E19="","",IF($F19="","⚠ falta coste",$E19*$F19)) | H19: =IF($B19="","",IFERROR(VLOOKUP($B19,Listas!$E$2:$F$20,2,FALSE),IF($C19="","",IFERROR(VLOOKUP($C19,Listas!$A$2:$B$11,2,FALSE),"")))) | I19: =IF(OR($E19="",$F19=""),"",$E19*$F19*(1+$H19/100))
A20: 12 | G20: =IF($E20="","",IF($F20="","⚠ falta coste",$E20*$F20)) | H20: =IF($B20="","",IFERROR(VLOOKUP($B20,Listas!$E$2:$F$20,2,FALSE),IF($C20="","",IFERROR(VLOOKUP($C20,Listas!$A$2:$B$11,2,FALSE),"")))) | I20: =IF(OR($E20="",$F20=""),"",$E20*$F20*(1+$H20/100))
A21: 13 | G21: =IF($E21="","",IF($F21="","⚠ falta coste",$E21*$F21)) | H21: =IF($B21="","",IFERROR(VLOOKUP($B21,Listas!$E$2:$F$20,2,FALSE),IF($C21="","",IFERROR(VLOOKUP($C21,Listas!$A$2:$B$11,2,FALSE),"")))) | I21: =IF(OR($E21="",$F21=""),"",$E21*$F21*(1+$H21/100))
A22: 14 | G22: =IF($E22="","",IF($F22="","⚠ falta coste",$E22*$F22)) | H22: =IF($B22="","",IFERROR(VLOOKUP($B22,Listas!$E$2:$F$20,2,FALSE),IF($C22="","",IFERROR(VLOOKUP($C22,Listas!$A$2:$B$11,2,FALSE),"")))) | I22: =IF(OR($E22="",$F22=""),"",$E22*$F22*(1+$H22/100))
A23: 15 | G23: =IF($E23="","",IF($F23="","⚠ falta coste",$E23*$F23)) | H23: =IF($B23="","",IFERROR(VLOOKUP($B23,Listas!$E$2:$F$20,2,FALSE),IF($C23="","",IFERROR(VLOOKUP($C23,Listas!$A$2:$B$11,2,FALSE),"")))) | I23: =IF(OR($E23="",$F23=""),"",$E23*$F23*(1+$H23/100))
... A38: 30 | G38: =IF($E38="","",IF($F38="","⚠ falta coste",$E38*$F38)) | H38: =IF($B38="","",IFERROR(VLOOKUP($B38,Listas!$E$2:$F$20,2,FALSE),IF($C38="","",IFERROR(VLOOKUP($C38,Listas!$A$2:$B$11,2,FALSE),"")))) | I38: =IF(OR($E38="",$F38=""),"",$E38*$F38*(1+$H38/100))
F40: BASE IMPONIBLE (€) | H40: =SUM($G$9:$G$38) -> 227.1
F41: CUOTA DE IVA (€) | H41: =SUM($I$9:$I$38)-$H$40 -> 28.476
F42: TOTAL DEL PEDIDO (€) | H42: =$H$40+$H$41 -> 255.576
A43: =IF(OR($E$4="",$H$40=""),"",IF($H$40>=$E$4,"✓ El pedido supera el mínimo de este proveedor","⚠ POR DEBAJO DEL PEDIDO MÍNIMO: pueden cobrarte portes")) -> ✓ El pedido supera el mínimo de este proveedor | F43: FALTA PARA EL MÍNIMO (€) | H43: =IF(OR($E$4="",$H$40=""),"",MAX(0,$E$4-$H$40)) -> 0
A45: IVA % | B45: Base (€) | C45: Cuota (€) | D45: Total (€)
A46: 4 | B46: =SUMIF($H$9:$H$38,$A46,$G$9:$G$38) -> 9.5 | C46: =IFERROR($B46*$A46/100,"") -> 0.38 | D46: =$B46+$C46 -> 9.88
A47: 10 | B47: =SUMIF($H$9:$H$38,$A47,$G$9:$G$38) -> 160 | C47: =IFERROR($B47*$A47/100,"") -> 16 | D47: =$B47+$C47 -> 176
A48: 21 | B48: =SUMIF($H$9:$H$38,$A48,$G$9:$G$38) -> 57.6 | C48: =IFERROR($B48*$A48/100,"") -> 12.096 | D48: =$B48+$C48 -> 69.696
A49: Desglose por tipo de IVA: es lo que pide una factura y lo que te permite cuadrar el pedido con el albarán. La suma de la columna Base tiene que coincidir con la BASE IMPONIBLE de arriba.

Sheet Proveedores
A1: PROVEEDORES
A2: Da de alta aquí a tus proveedores: el desplegable de la hoja Pedido Actual y el teléfono y el pedido mínimo de su cabecera salen de esta tabla. Las seis primeras filas son un ejemplo: písalas con las tuyas. ESTA TABLA ES LA COPIA OPERATIVA del Directorio de Proveedores del fichero 02: los nueve libros del kit son ficheros independientes y no se enlazan entre sí a propósito (un .xlsx movido de carpeta rompería la referencia y verías #¡REF!), así que si cambias allí un pedido mínimo o un día de pedido, cámbialo también aquí: es el que de verdad alimenta el pedido.
A3: Proveedor | B3: Categoría principal | C3: Teléfono | D3: Email | E3: Pedido mínimo (€) | F3: Día de pedido | G3: Plazo de entrega (días) | H3: Notas
A4: Cárnicas del Norte (ejemplo) | B4: Cárnicos | C4: 948 21 34 55 | D4: pedidos@ejemplo-carnicas.es | E4: 150 | F4: Lun y jue antes de 12:00 | G4: 1 | H4: Exigir el albarán con el nº de lote y la temperatura de llegada
A5: Pescados Ría Fresca (ejemplo) | B5: Pescados | C5: 986 44 12 09 | D5: pedidos@ejemplo-pescados.es | E5: 120 | F5: Diario antes de 17:00 | G5: 1 | H5: Llega en hielo fundente; rechazar por encima de 2 °C
A6: Frutas y Verduras La Huerta (ejemplo) | B6: Verduras/Frutas | C6: 963 55 71 20 | D6: pedidos@ejemplo-huerta.es | E6: 80 | F6: Lun, mié y vie antes de 18:00 | G6: 1 | H6: Producto de temporada: confirma el precio cada semana
A7: Distribuciones Economato Sur (ejemplo) | B7: Secos/Granos | C7: 954 33 90 41 | D7: pedidos@ejemplo-economato.es | E7: 250 | F7: Mar antes de 14:00 | G7: 2 | H7: Rappel del 2 % a partir de 2.000 € al mes
A8: Bebidas y Distribución Levante (ejemplo) | B8: Bebidas Alcohólicas | C8: 965 12 78 30 | D8: pedidos@ejemplo-bebidas.es | E8: 200 | F8: Lun antes de 12:00 | G8: 2 | H8: Cesión de barriles y CO2: revisar el depósito de envases
A9: Higiene Profesional HORECA (ejemplo) | B9: Limpieza | C9: 916 40 22 18 | D9: pedidos@ejemplo-higiene.es | E9: 100 | F9: Mié antes de 16:00 | G9: 2 | H9: Pedir la ficha de datos de seguridad de cada producto
A25: La ficha COMPLETA de cada proveedor (CIF, nº RGSEAA, condiciones de pago, homologación y comparativa de precios) va en el fichero 02 del kit. Aquí basta con lo que necesita el pedido.

Sheet Historial Pedidos
A1: HISTORIAL DE PEDIDOS
A2: La fila 4 está ENLAZADA al pedido en curso. Cuando lo cierres, copia esa fila y pégala como valor en la primera fila libre; después ya puedes vaciar el pedido.
A3: Fecha | B3: Nº Pedido | C3: Proveedor | D3: Productos | E3: Subtotal (€) | F3: IVA (€) | G3: Total (€) | H3: Estado | I3: Observaciones
A4: =IF('Pedido Actual'!$C$4="","",'Pedido Actual'!$C$4) -> 46252 | B4: =IF('Pedido Actual'!$C$6="","",'Pedido Actual'!$C$6) -> PED-2026-004 | C4: =IF('Pedido Actual'!$C$3="","",'Pedido Actual'!$C$3) -> Cárnicas del Norte (ejemplo) | D4: =IF(COUNTIF('Pedido Actual'!$B$9:$B$38,"<>")=0,"",COUNTIF('Pedido Actual'!$B$9:$B$38,"<>")&" líneas") -> 3 líneas | E4: ='Pedido Actual'!$H$40 -> 227.1 | F4: ='Pedido Actual'!$H$41 -> 28.476 | G4: ='Pedido Actual'!$H$42 -> 255.576 | I4: PEDIDO EN CURSO — esta fila se actualiza sola y NO SUMA en el total del periodo. Cópiala como valor en la primera fila libre cuando cierres el pedido.
A5: 46223 | B5: PED-2026-001 | C5: Cárnicas del Norte (ejemplo) | D5: 6 líneas | E5: 342.8 | F5: 34.28 | G5: 377.08 | H5: Facturado | I5: Sin incidencias (ejemplo)
A6: 46237 | B6: PED-2026-002 | C6: Bebidas y Distribución Levante (ejemplo) | D6: 4 líneas | E6: 218.5 | F6: 45.89 | G6: 264.39 | H6: Recibido | I6: Barril de 30 L en depósito (ejemplo)
A7: 46248 | B7: PED-2026-003 | C7: Frutas y Verduras La Huerta (ejemplo) | D7: 9 líneas | E7: 96.4 | F7: 3.86 | G7: 100.26 | H7: Recibido con incidencia | I7: Dos cajas de tomate retiradas (ejemplo)
D45: TOTAL DEL PERIODO (filas 5 a 43) | E45: =SUM($E$5:$E$43) -> 657.7 | F45: =SUM($F$5:$F$43) -> 84.03 | G45: =SUM($G$5:$G$43) -> 741.73

Sheet Listas
A1: Categoría | B1: IVA % | C1: Nota | E1: Producto | F1: IVA % | G1: Por qué no es el de su categoría
A2: Cárnicos | B2: 10 | C2: Tipo orientativo por categoría: edítalo. El pan común, las harinas panificables, las legumbres, los cereales, la leche, los quesos, los huevos, las frutas y las verduras van al 4 %; los refrescos con azúcares añadidos, al 21 %. En cada línea del pedido puedes cambiar el tipo con el desplegable 4 / 10 / 21. | E2: Arroz redondo | F2: 4 | G2: EXCEPCIONES por producto. El pedido busca PRIMERO el nombre del producto en esta tabla y sólo si no lo encuentra usa el tipo de su categoría. Aquí están únicamente los productos del kit cuyo tipo NO es el de su categoría: los cereales, las harinas y las legumbres van al 4 % aunque su categoría (Secos/Granos) sea del 10 %; la nata y la mantequilla al 10 % aunque Lácteos sea del 4 %; los refrescos con azúcares añadidos al 21 %. Añade los tuyos escribiendo el nombre EXACTO que uses en el pedido.
A3: Pescados | B3: 10 | E3: Harina de trigo | F3: 4
A4: Lácteos | B4: 4 | E4: Huevos M | F4: 4
A5: Verduras/Frutas | B5: 4 | E5: Legumbres secas | F5: 4
A6: Secos/Granos | B6: 10 | E6: Mantequilla | F6: 10
A7: Congelados | B7: 10 | E7: Nata 35 % M.G. | F7: 10
A8: Bebidas Alcohólicas | B8: 21 | E8: Pasta seca | F8: 4
A9: Bebidas No Alcohólicas | B9: 10 | E9: Refresco de cola | F9: 21
A10: Limpieza | B10: 21 | E10: Tónica | F10: 21
A11: Otros | B11: 21
