Workbook

Sheet Instrucciones
A1: Recepción de Mercancías
A2: AI Chef Pro — aichef.pro
A4: Verifica cada entrega y deja registrado lo que un inspector te va a pedir: albarán, lote, temperatura, conformidad y firma.
A5: 1. Cuando llegue un proveedor, abre 'Control Recepción' y anota una línea por producto.
A6: 2. Rellena el nº de albarán y el nº de lote. Son los dos datos que sostienen la trazabilidad hacia atrás: sin ellos el registro no sirve como prerrequisito documental de tu plan APPCC.
A7: 3. Elige la categoría del producto —las mismas 10 del resto del kit— y la columna 'Familia sugerida' te propone sola la familia normativa. AFÍNALA en la columna 'Familia' cuando la línea lo pida: la carne picada (2 °C), los despojos (3 °C), las aves (4 °C) y la comida preparada tienen umbral propio, y no es lo mismo un solomillo que una hamburguesa.
A8: 4. Escribe la temperatura medida: la casilla se pone ROJA y la columna de conformidad dice RECHAZAR en cuanto se sale del rango de su familia. Hay cinco respuestas posibles y conviene conocerlas: CONFORME · RECHAZAR (calor) · RECHAZAR (frío), porque un pescado a -20 °C venía congelado y una lechuga a -2 °C viene quemada por frío · N/A cuando esa familia no se controla por temperatura (huevos, secos, bebidas, no alimentario) · y FAMILIA SIN LÍMITE cuando lo que has escrito en Familia no está en la tabla legal. Esa última no es un fallo: es el fichero negándose a darte un visto bueno que no puede sostener.
A9: 5. La diferencia entre lo pedido y lo recibido se calcula sola, y si pones el precio/ud también su VALOR EN EUROS: es lo que de verdad le reclamas al proveedor. Lo que no aceptes, anótalo en 'Registro Incidencias' con ese importe; la suma de esa columna menos los abonos es lo que te deben.
A10: 6. La hoja 'Verificación Temperaturas' cita la norma de cada límite y trae, a la derecha, el puente entre las 10 categorías de compra del kit y las familias normativas. Edítala sólo si tu autoridad sanitaria te indica otra cosa; está protegida sin contraseña para que no se borre de un clic, porque de ella depende el veredicto de todas las líneas.
A11: Umbrales tomados del Reglamento (CE) 853/2004 (Anexo III), del Reglamento (CE) 589/2008 y del criterio habitual de los planes APPCC para comidas preparadas (el RD 3484/2000, que los fijaba, fue derogado por el RD 1021/2022). Documentan tus registros; no sustituyen a tu plan APPCC ni a un asesor.
A13: Para editar una celda bloqueada: Revisar → Desproteger hoja (no tiene contraseña). Las celdas verdes ya son editables sin desproteger nada.
A14: Diseñado por John Guerrero — chef y consultor gastronómico desde 2010, en cocina desde los 17 años · johnguerrero.es
A15: Versión 2.0 · agosto 2026 · aichef.pro/kit-inventario · info@aichef.pro

Sheet Control Recepción
A1: CONTROL DE RECEPCIÓN DE MERCANCÍAS
A2: Una línea por producto recibido. Las CUATRO primeras son un EJEMPLO y cuentan una sola historia con el Registro de Incidencias: una entrega corta, una rechazada por temperatura, una con mal estado y una sin control de temperatura. Bórralas antes de empezar.
A3: Fecha | B3: Proveedor | C3: Nº albarán/factura | D3: Producto | E3: Categoría (kit) | F3: Familia sugerida | G3: Familia | H3: Nº de lote | I3: Pedido (ud) | J3: Recibido (ud) | K3: Diferencia (ud) | L3: Precio/ud (€) | M3: Valor de la diferencia (€) | N3: Caducidad | O3: Temp. °C | P3: Tª mín. (°C) | Q3: Tª máx. (°C) | R3: Conforme (Tª) | S3: Calidad visual | T3: Incidencia | U3: Receptor | V3: Firma
A4: 46252 | B4: Cárnicas del Norte (ejemplo) | C4: ALB-24518 | D4: Solomillo de ternera (ejemplo) | E4: Cárnicos | F4: =IF($E4="","",IFERROR(VLOOKUP($E4,'Verificación Temperaturas'!$G$4:$H$13,2,FALSE),"")) -> Canal y despiece de ungulados domésticos | G4: Canal y despiece de ungulados domésticos | H4: L-260817 | I4: 12 | J4: 10 | K4: =IF(OR($I4="",$J4=""),"",$J4-$I4) -> -2 | L4: 32 | M4: =IF(OR($K4="",$L4=""),"",$K4*$L4) -> -64 | N4: 46259 | O4: 3 | P4: =IF(IF($G4="",$F4,$G4)="","",IFERROR(VLOOKUP(IF($G4="",$F4,$G4),'Verificación Temperaturas'!$A$4:$E$18,3,FALSE),"")) -> 0 | Q4: =IF(IF($G4="",$F4,$G4)="","",IFERROR(VLOOKUP(IF($G4="",$F4,$G4),'Verificación Temperaturas'!$A$4:$E$18,4,FALSE),"")) -> 7 | R4: =IF(OR($O4="",IF($G4="",$F4,$G4)=""),"",IF($Q4="N/A","N/A",IF($Q4="","⚠ FAMILIA SIN LÍMITE",IF($O4<$P4,"✗ RECHAZAR (frío)",IF($O4<=$Q4,"✓ CONFORME","✗ RECHAZAR (calor)"))))) -> ✓ CONFORME | S4: ✓ | T4: Faltan 2 kg de los 12 pedidos: reclamado por correo el mismo día | U4: Jefe de cocina
A5: 46252 | B5: Pescados Ría Fresca (ejemplo) | C5: ALB-0091 | D5: Merluza fresca (ejemplo) | E5: Pescados | F5: =IF($E5="","",IFERROR(VLOOKUP($E5,'Verificación Temperaturas'!$G$4:$H$13,2,FALSE),"")) -> Pescado fresco y marisco | G5: Pescado fresco y marisco | H5: L-260818 | I5: 8 | J5: 8 | K5: =IF(OR($I5="",$J5=""),"",$J5-$I5) -> 0 | L5: 14 | M5: =IF(OR($K5="",$L5=""),"",$K5*$L5) -> 0 | N5: 46255 | O5: 5 | P5: =IF(IF($G5="",$F5,$G5)="","",IFERROR(VLOOKUP(IF($G5="",$F5,$G5),'Verificación Temperaturas'!$A$4:$E$18,3,FALSE),"")) -> 0 | Q5: =IF(IF($G5="",$F5,$G5)="","",IFERROR(VLOOKUP(IF($G5="",$F5,$G5),'Verificación Temperaturas'!$A$4:$E$18,4,FALSE),"")) -> 2 | R5: =IF(OR($O5="",IF($G5="",$F5,$G5)=""),"",IF($Q5="N/A","N/A",IF($Q5="","⚠ FAMILIA SIN LÍMITE",IF($O5<$P5,"✗ RECHAZAR (frío)",IF($O5<=$Q5,"✓ CONFORME","✗ RECHAZAR (calor)"))))) -> ✗ RECHAZAR (calor) | S5: ✗ | T5: Llega a 5 °C con el límite de su familia en 2 °C: partida completa devuelta al transportista | U5: Segundo de cocina
A6: 46253 | B6: Frutas y Verduras La Huerta (ejemplo) | C6: ALB-7742 | D6: Tomate (ejemplo) | E6: Verduras/Frutas | F6: =IF($E6="","",IFERROR(VLOOKUP($E6,'Verificación Temperaturas'!$G$4:$H$13,2,FALSE),"")) -> Frutas y verduras | G6: Frutas y verduras | H6: L-260819 | I6: 30 | J6: 30 | K6: =IF(OR($I6="",$J6=""),"",$J6-$I6) -> 0 | L6: 1.95 | M6: =IF(OR($K6="",$L6=""),"",$K6*$L6) -> 0 | N6: 46260 | O6: 9 | P6: =IF(IF($G6="",$F6,$G6)="","",IFERROR(VLOOKUP(IF($G6="",$F6,$G6),'Verificación Temperaturas'!$A$4:$E$18,3,FALSE),"")) -> 0 | Q6: =IF(IF($G6="",$F6,$G6)="","",IFERROR(VLOOKUP(IF($G6="",$F6,$G6),'Verificación Temperaturas'!$A$4:$E$18,4,FALSE),"")) -> 12 | R6: =IF(OR($O6="",IF($G6="",$F6,$G6)=""),"",IF($Q6="N/A","N/A",IF($Q6="","⚠ FAMILIA SIN LÍMITE",IF($O6<$P6,"✗ RECHAZAR (frío)",IF($O6<=$Q6,"✓ CONFORME","✗ RECHAZAR (calor)"))))) -> ✓ CONFORME | S6: ✗ | T6: Dos cajas de 10 kg con moho en el fondo: retiradas y anotadas en el control de mermas | U6: Encargado de compras
A7: 46253 | B7: Frutas y Verduras La Huerta (ejemplo) | C7: ALB-7743 | D7: Huevos M, docena (ejemplo) | E7: Otros | F7: =IF($E7="","",IFERROR(VLOOKUP($E7,'Verificación Temperaturas'!$G$4:$H$13,2,FALSE),"")) -> Secos y economato (ambiente) | G7: Huevos | H7: L-260819 | I7: 20 | J7: 20 | K7: =IF(OR($I7="",$J7=""),"",$J7-$I7) -> 0 | L7: 2.2 | M7: =IF(OR($K7="",$L7=""),"",$K7*$L7) -> 0 | N7: 46270 | O7: 17 | P7: =IF(IF($G7="",$F7,$G7)="","",IFERROR(VLOOKUP(IF($G7="",$F7,$G7),'Verificación Temperaturas'!$A$4:$E$18,3,FALSE),"")) -> N/A | Q7: =IF(IF($G7="",$F7,$G7)="","",IFERROR(VLOOKUP(IF($G7="",$F7,$G7),'Verificación Temperaturas'!$A$4:$E$18,4,FALSE),"")) -> N/A | R7: =IF(OR($O7="",IF($G7="",$F7,$G7)=""),"",IF($Q7="N/A","N/A",IF($Q7="","⚠ FAMILIA SIN LÍMITE",IF($O7<$P7,"✗ RECHAZAR (frío)",IF($O7<=$Q7,"✓ CONFORME","✗ RECHAZAR (calor)"))))) -> N/A | S7: ✓ | U7: Encargado de compras
F8: =IF($E8="","",IFERROR(VLOOKUP($E8,'Verificación Temperaturas'!$G$4:$H$13,2,FALSE),"")) | K8: =IF(OR($I8="",$J8=""),"",$J8-$I8) | M8: =IF(OR($K8="",$L8=""),"",$K8*$L8) | P8: =IF(IF($G8="",$F8,$G8)="","",IFERROR(VLOOKUP(IF($G8="",$F8,$G8),'Verificación Temperaturas'!$A$4:$E$18,3,FALSE),"")) | Q8: =IF(IF($G8="",$F8,$G8)="","",IFERROR(VLOOKUP(IF($G8="",$F8,$G8),'Verificación Temperaturas'!$A$4:$E$18,4,FALSE),"")) | R8: =IF(OR($O8="",IF($G8="",$F8,$G8)=""),"",IF($Q8="N/A","N/A",IF($Q8="","⚠ FAMILIA SIN LÍMITE",IF($O8<$P8,"✗ RECHAZAR (frío)",IF($O8<=$Q8,"✓ CONFORME","✗ RECHAZAR (calor)")))))
F9: =IF($E9="","",IFERROR(VLOOKUP($E9,'Verificación Temperaturas'!$G$4:$H$13,2,FALSE),"")) | K9: =IF(OR($I9="",$J9=""),"",$J9-$I9) | M9: =IF(OR($K9="",$L9=""),"",$K9*$L9) | P9: =IF(IF($G9="",$F9,$G9)="","",IFERROR(VLOOKUP(IF($G9="",$F9,$G9),'Verificación Temperaturas'!$A$4:$E$18,3,FALSE),"")) | Q9: =IF(IF($G9="",$F9,$G9)="","",IFERROR(VLOOKUP(IF($G9="",$F9,$G9),'Verificación Temperaturas'!$A$4:$E$18,4,FALSE),"")) | R9: =IF(OR($O9="",IF($G9="",$F9,$G9)=""),"",IF($Q9="N/A","N/A",IF($Q9="","⚠ FAMILIA SIN LÍMITE",IF($O9<$P9,"✗ RECHAZAR (frío)",IF($O9<=$Q9,"✓ CONFORME","✗ RECHAZAR (calor)")))))
F10: =IF($E10="","",IFERROR(VLOOKUP($E10,'Verificación Temperaturas'!$G$4:$H$13,2,FALSE),"")) | K10: =IF(OR($I10="",$J10=""),"",$J10-$I10) | M10: =IF(OR($K10="",$L10=""),"",$K10*$L10) | P10: =IF(IF($G10="",$F10,$G10)="","",IFERROR(VLOOKUP(IF($G10="",$F10,$G10),'Verificación Temperaturas'!$A$4:$E$18,3,FALSE),"")) | Q10: =IF(IF($G10="",$F10,$G10)="","",IFERROR(VLOOKUP(IF($G10="",$F10,$G10),'Verificación Temperaturas'!$A$4:$E$18,4,FALSE),"")) | R10: =IF(OR($O10="",IF($G10="",$F10,$G10)=""),"",IF($Q10="N/A","N/A",IF($Q10="","⚠ FAMILIA SIN LÍMITE",IF($O10<$P10,"✗ RECHAZAR (frío)",IF($O10<=$Q10,"✓ CONFORME","✗ RECHAZAR (calor)")))))
F11: =IF($E11="","",IFERROR(VLOOKUP($E11,'Verificación Temperaturas'!$G$4:$H$13,2,FALSE),"")) | K11: =IF(OR($I11="",$J11=""),"",$J11-$I11) | M11: =IF(OR($K11="",$L11=""),"",$K11*$L11) | P11: =IF(IF($G11="",$F11,$G11)="","",IFERROR(VLOOKUP(IF($G11="",$F11,$G11),'Verificación Temperaturas'!$A$4:$E$18,3,FALSE),"")) | Q11: =IF(IF($G11="",$F11,$G11)="","",IFERROR(VLOOKUP(IF($G11="",$F11,$G11),'Verificación Temperaturas'!$A$4:$E$18,4,FALSE),"")) | R11: =IF(OR($O11="",IF($G11="",$F11,$G11)=""),"",IF($Q11="N/A","N/A",IF($Q11="","⚠ FAMILIA SIN LÍMITE",IF($O11<$P11,"✗ RECHAZAR (frío)",IF($O11<=$Q11,"✓ CONFORME","✗ RECHAZAR (calor)")))))
F12: =IF($E12="","",IFERROR(VLOOKUP($E12,'Verificación Temperaturas'!$G$4:$H$13,2,FALSE),"")) | K12: =IF(OR($I12="",$J12=""),"",$J12-$I12) | M12: =IF(OR($K12="",$L12=""),"",$K12*$L12) | P12: =IF(IF($G12="",$F12,$G12)="","",IFERROR(VLOOKUP(IF($G12="",$F12,$G12),'Verificación Temperaturas'!$A$4:$E$18,3,FALSE),"")) | Q12: =IF(IF($G12="",$F12,$G12)="","",IFERROR(VLOOKUP(IF($G12="",$F12,$G12),'Verificación Temperaturas'!$A$4:$E$18,4,FALSE),"")) | R12: =IF(OR($O12="",IF($G12="",$F12,$G12)=""),"",IF($Q12="N/A","N/A",IF($Q12="","⚠ FAMILIA SIN LÍMITE",IF($O12<$P12,"✗ RECHAZAR (frío)",IF($O12<=$Q12,"✓ CONFORME","✗ RECHAZAR (calor)")))))
F13: =IF($E13="","",IFERROR(VLOOKUP($E13,'Verificación Temperaturas'!$G$4:$H$13,2,FALSE),"")) | K13: =IF(OR($I13="",$J13=""),"",$J13-$I13) | M13: =IF(OR($K13="",$L13=""),"",$K13*$L13) | P13: =IF(IF($G13="",$F13,$G13)="","",IFERROR(VLOOKUP(IF($G13="",$F13,$G13),'Verificación Temperaturas'!$A$4:$E$18,3,FALSE),"")) | Q13: =IF(IF($G13="",$F13,$G13)="","",IFERROR(VLOOKUP(IF($G13="",$F13,$G13),'Verificación Temperaturas'!$A$4:$E$18,4,FALSE),"")) | R13: =IF(OR($O13="",IF($G13="",$F13,$G13)=""),"",IF($Q13="N/A","N/A",IF($Q13="","⚠ FAMILIA SIN LÍMITE",IF($O13<$P13,"✗ RECHAZAR (frío)",IF($O13<=$Q13,"✓ CONFORME","✗ RECHAZAR (calor)")))))
F14: =IF($E14="","",IFERROR(VLOOKUP($E14,'Verificación Temperaturas'!$G$4:$H$13,2,FALSE),"")) | K14: =IF(OR($I14="",$J14=""),"",$J14-$I14) | M14: =IF(OR($K14="",$L14=""),"",$K14*$L14) | P14: =IF(IF($G14="",$F14,$G14)="","",IFERROR(VLOOKUP(IF($G14="",$F14,$G14),'Verificación Temperaturas'!$A$4:$E$18,3,FALSE),"")) | Q14: =IF(IF($G14="",$F14,$G14)="","",IFERROR(VLOOKUP(IF($G14="",$F14,$G14),'Verificación Temperaturas'!$A$4:$E$18,4,FALSE),"")) | R14: =IF(OR($O14="",IF($G14="",$F14,$G14)=""),"",IF($Q14="N/A","N/A",IF($Q14="","⚠ FAMILIA SIN LÍMITE",IF($O14<$P14,"✗ RECHAZAR (frío)",IF($O14<=$Q14,"✓ CONFORME","✗ RECHAZAR (calor)")))))
F15: =IF($E15="","",IFERROR(VLOOKUP($E15,'Verificación Temperaturas'!$G$4:$H$13,2,FALSE),"")) | K15: =IF(OR($I15="",$J15=""),"",$J15-$I15) | M15: =IF(OR($K15="",$L15=""),"",$K15*$L15) | P15: =IF(IF($G15="",$F15,$G15)="","",IFERROR(VLOOKUP(IF($G15="",$F15,$G15),'Verificación Temperaturas'!$A$4:$E$18,3,FALSE),"")) | Q15: =IF(IF($G15="",$F15,$G15)="","",IFERROR(VLOOKUP(IF($G15="",$F15,$G15),'Verificación Temperaturas'!$A$4:$E$18,4,FALSE),"")) | R15: =IF(OR($O15="",IF($G15="",$F15,$G15)=""),"",IF($Q15="N/A","N/A",IF($Q15="","⚠ FAMILIA SIN LÍMITE",IF($O15<$P15,"✗ RECHAZAR (frío)",IF($O15<=$Q15,"✓ CONFORME","✗ RECHAZAR (calor)")))))
F16: =IF($E16="","",IFERROR(VLOOKUP($E16,'Verificación Temperaturas'!$G$4:$H$13,2,FALSE),"")) | K16: =IF(OR($I16="",$J16=""),"",$J16-$I16) | M16: =IF(OR($K16="",$L16=""),"",$K16*$L16) | P16: =IF(IF($G16="",$F16,$G16)="","",IFERROR(VLOOKUP(IF($G16="",$F16,$G16),'Verificación Temperaturas'!$A$4:$E$18,3,FALSE),"")) | Q16: =IF(IF($G16="",$F16,$G16)="","",IFERROR(VLOOKUP(IF($G16="",$F16,$G16),'Verificación Temperaturas'!$A$4:$E$18,4,FALSE),"")) | R16: =IF(OR($O16="",IF($G16="",$F16,$G16)=""),"",IF($Q16="N/A","N/A",IF($Q16="","⚠ FAMILIA SIN LÍMITE",IF($O16<$P16,"✗ RECHAZAR (frío)",IF($O16<=$Q16,"✓ CONFORME","✗ RECHAZAR (calor)")))))
F17: =IF($E17="","",IFERROR(VLOOKUP($E17,'Verificación Temperaturas'!$G$4:$H$13,2,FALSE),"")) | K17: =IF(OR($I17="",$J17=""),"",$J17-$I17) | M17: =IF(OR($K17="",$L17=""),"",$K17*$L17) | P17: =IF(IF($G17="",$F17,$G17)="","",IFERROR(VLOOKUP(IF($G17="",$F17,$G17),'Verificación Temperaturas'!$A$4:$E$18,3,FALSE),"")) | Q17: =IF(IF($G17="",$F17,$G17)="","",IFERROR(VLOOKUP(IF($G17="",$F17,$G17),'Verificación Temperaturas'!$A$4:$E$18,4,FALSE),"")) | R17: =IF(OR($O17="",IF($G17="",$F17,$G17)=""),"",IF($Q17="N/A","N/A",IF($Q17="","⚠ FAMILIA SIN LÍMITE",IF($O17<$P17,"✗ RECHAZAR (frío)",IF($O17<=$Q17,"✓ CONFORME","✗ RECHAZAR (calor)")))))
F18: =IF($E18="","",IFERROR(VLOOKUP($E18,'Verificación Temperaturas'!$G$4:$H$13,2,FALSE),"")) | K18: =IF(OR($I18="",$J18=""),"",$J18-$I18) | M18: =IF(OR($K18="",$L18=""),"",$K18*$L18) | P18: =IF(IF($G18="",$F18,$G18)="","",IFERROR(VLOOKUP(IF($G18="",$F18,$G18),'Verificación Temperaturas'!$A$4:$E$18,3,FALSE),"")) | Q18: =IF(IF($G18="",$F18,$G18)="","",IFERROR(VLOOKUP(IF($G18="",$F18,$G18),'Verificación Temperaturas'!$A$4:$E$18,4,FALSE),"")) | R18: =IF(OR($O18="",IF($G18="",$F18,$G18)=""),"",IF($Q18="N/A","N/A",IF($Q18="","⚠ FAMILIA SIN LÍMITE",IF($O18<$P18,"✗ RECHAZAR (frío)",IF($O18<=$Q18,"✓ CONFORME","✗ RECHAZAR (calor)")))))
F19: =IF($E19="","",IFERROR(VLOOKUP($E19,'Verificación Temperaturas'!$G$4:$H$13,2,FALSE),"")) | K19: =IF(OR($I19="",$J19=""),"",$J19-$I19) | M19: =IF(OR($K19="",$L19=""),"",$K19*$L19) | P19: =IF(IF($G19="",$F19,$G19)="","",IFERROR(VLOOKUP(IF($G19="",$F19,$G19),'Verificación Temperaturas'!$A$4:$E$18,3,FALSE),"")) | Q19: =IF(IF($G19="",$F19,$G19)="","",IFERROR(VLOOKUP(IF($G19="",$F19,$G19),'Verificación Temperaturas'!$A$4:$E$18,4,FALSE),"")) | R19: =IF(OR($O19="",IF($G19="",$F19,$G19)=""),"",IF($Q19="N/A","N/A",IF($Q19="","⚠ FAMILIA SIN LÍMITE",IF($O19<$P19,"✗ RECHAZAR (frío)",IF($O19<=$Q19,"✓ CONFORME","✗ RECHAZAR (calor)")))))
... F43: =IF($E43="","",IFERROR(VLOOKUP($E43,'Verificación Temperaturas'!$G$4:$H$13,2,FALSE),"")) | K43: =IF(OR($I43="",$J43=""),"",$J43-$I43) | M43: =IF(OR($K43="",$L43=""),"",$K43*$L43) | P43: =IF(IF($G43="",$F43,$G43)="","",IFERROR(VLOOKUP(IF($G43="",$F43,$G43),'Verificación Temperaturas'!$A$4:$E$18,3,FALSE),"")) | Q43: =IF(IF($G43="",$F43,$G43)="","",IFERROR(VLOOKUP(IF($G43="",$F43,$G43),'Verificación Temperaturas'!$A$4:$E$18,4,FALSE),"")) | R43: =IF(OR($O43="",IF($G43="",$F43,$G43)=""),"",IF($Q43="N/A","N/A",IF($Q43="","⚠ FAMILIA SIN LÍMITE",IF($O43<$P43,"✗ RECHAZAR (frío)",IF($O43<=$Q43,"✓ CONFORME","✗ RECHAZAR (calor)")))))
B45: Entregas registradas: | D45: =COUNTIF($D$4:$D$43,"<>") -> 4 | F45: Líneas a rechazar: | H45: =COUNTIF($R$4:$R$43,"*RECHAZAR*") -> 1 | I45: Diferencia total (ud): | K45: =SUM($K$4:$K$43) -> -2 | L45: Valor de la diferencia (€): | N45: =SUM($M$4:$M$43) -> -64

Sheet Registro Incidencias
A1: REGISTRO DE INCIDENCIAS — RECEPCIÓN
A2: La suma de «Importe reclamado» menos la de «Abono recibido» es lo que tu proveedor te debe. Las tres primeras líneas son un ejemplo.
A3: Fecha | B3: Nº albarán | C3: Proveedor | D3: Producto | E3: Tipo de incidencia | F3: Descripción | G3: Acción tomada | H3: Responsable | I3: Importe reclamado (€) | J3: Abono recibido (€) | K3: Estado
A4: 46252 | B4: ALB-24518 | C4: Cárnicas del Norte (ejemplo) | D4: Solomillo de ternera (ejemplo) | E4: Cantidad incorrecta | F4: Faltan 2 kg de los 12 pedidos: sólo se reciben 10 | G4: Reclamado por correo el mismo día | H4: Jefe de cocina | I4: 64 | J4: 0 | K4: Reclamada
A5: 46252 | B5: ALB-0091 | C5: Pescados Ría Fresca (ejemplo) | D5: Merluza fresca (ejemplo) | E5: Temperatura fuera de rango | F5: Llega a 5 °C con el límite de su familia en 2 °C | G5: Partida completa (8 kg) devuelta al transportista en el momento | H5: Segundo de cocina | I5: 112 | J5: 112 | K5: Abono recibido
A6: 46253 | B6: ALB-7742 | C6: Frutas y Verduras La Huerta (ejemplo) | D6: Tomate (ejemplo) | E6: Producto en mal estado | F6: Dos cajas de 10 kg con moho en el fondo | G6: Retiradas y anotadas en el control de mermas | H6: Encargado de compras | I6: 39 | J6: 0 | K6: Abierta
H25: TOTALES | I25: =SUM($I$4:$I$23) -> 215 | J25: =SUM($J$4:$J$23) -> 112
H26: PENDIENTE DE ABONO (€) | I26: =IFERROR($I$25-$J$25,"") -> 103

Sheet Verificación Temperaturas
A1: TEMPERATURAS DE RECEPCIÓN — LÍMITES LEGALES
A3: Familia | B3: Tª ideal | C3: Tª mín. aceptable (°C) | D3: Tª máx. aceptable (°C) | E3: Base normativa | G3: Categoría del kit | H3: Familia por defecto
A4: Canal y despiece de ungulados domésticos | B4: 0 a 7 °C | C4: 0 | D4: 7 | E4: Reg. (CE) 853/2004, Anexo III, Secc. I, Cap. VII | G4: Cárnicos | H4: Canal y despiece de ungulados domésticos
A5: Despojos comestibles | B5: 0 a 3 °C | C5: 0 | D5: 3 | E5: Reg. (CE) 853/2004, Anexo III, Secc. I, Cap. VII | G5: Pescados | H5: Pescado fresco y marisco
A6: Aves y lagomorfos | B6: 0 a 4 °C | C6: 0 | D6: 4 | E6: Reg. (CE) 853/2004, Anexo III, Secc. II, Cap. V | G6: Lácteos | H6: Lácteos y otros refrigerados
A7: Preparados de carne | B7: 0 a 4 °C | C7: 0 | D7: 4 | E7: Reg. (CE) 853/2004, Anexo III, Secc. V, Cap. III | G7: Verduras/Frutas | H7: Frutas y verduras
A8: Carne picada | B8: 0 a 2 °C | C8: 0 | D8: 2 | E8: Reg. (CE) 853/2004, Anexo III, Secc. V, Cap. III | G8: Secos/Granos | H8: Secos y economato (ambiente)
A9: Pescado fresco y marisco | B9: 0 a 2 °C, en hielo fundente | C9: 0 | D9: 2 | E9: Reg. (CE) 853/2004, Anexo III, Secc. VIII, Cap. VII | G9: Congelados | H9: Congelados
A10: Congelados | B10: -18 °C en conservación; hasta -15 °C admisible al recibir | C10: -40 | D10: -15 | E10: Reg. (CE) 853/2004; la tolerancia breve de -15 °C en transporte es la que se aplica AL RECIBIR. Mantener a -18 °C una vez almacenado. | G10: Bebidas Alcohólicas | H10: Bebidas y conservas (ambiente)
A11: Comidas preparadas refrigeradas (más de 24 h) | B11: 0 a 4 °C | C11: 0 | D11: 4 | E11: Criterio habitual del plan APPCC (el RD 3484/2000, que lo fijaba, fue derogado por el RD 1021/2022) | G11: Bebidas No Alcohólicas | H11: Bebidas y conservas (ambiente)
A12: Comidas preparadas refrigeradas (menos de 24 h) | B12: 0 a 8 °C | C12: 0 | D12: 8 | E12: Criterio habitual del plan APPCC (el RD 3484/2000, que lo fijaba, fue derogado por el RD 1021/2022) | G12: Limpieza | H12: No alimentario (limpieza, menaje y desechables)
A13: Lácteos y otros refrigerados | B13: 0 a 8 °C o lo que diga la etiqueta | C13: 0 | D13: 8 | E13: Reg. (CE) 853/2004 y etiquetado del fabricante | G13: Otros | H13: Secos y economato (ambiente)
A14: Frutas y verduras | B14: 4 a 12 °C | C14: 0 | D14: 12 | E14: Buenas prácticas; sin límite legal de recepción
A15: Huevos | B15: Temperatura ambiente constante, sin cambios bruscos; no refrigerar antes de la venta | C15: N/A | D15: N/A | E15: Reg. (CE) 589/2008, art. 2 | G15: De aquí sale la columna «Familia sugerida» del registro. AFÍNALA en la columna «Familia» cuando la línea lo pida: la carne picada (2 °C), los despojos (3 °C), las aves (4 °C) y la comida preparada tienen umbral propio, y los huevos tienen su propia familia aunque su categoría de compra sea «Otros».
A16: Secos y economato (ambiente) | B16: Lugar fresco y seco, menos de 25 °C | C16: N/A | D16: N/A | E16: Reg. (CE) 852/2004, Anexo II, Cap. IX
A17: Bebidas y conservas (ambiente) | B17: Lugar fresco y seco; la cerveza de barril, entre 5 y 12 °C | C17: N/A | D17: N/A | E17: Sin límite legal de recepción; sigue la indicación del fabricante
A18: No alimentario (limpieza, menaje y desechables) | B18: Ambiente, en almacén separado de los alimentos | C18: N/A | D18: N/A | E18: Reg. (CE) 852/2004, Anexo II, Cap. IX: los productos químicos van separados y señalizados, nunca junto a alimentos
A20: Las columnas «Tª mín.» y «Tª máx. aceptable» son las que compara la hoja Control Recepción: por eso son números y no «7°C máx.» como en la v1.1, donde el criterio existía en papel y no se podía aplicar a ningún dato. «N/A» significa que esa familia no se controla por temperatura en la recepción. Los congelados llevan -15 °C porque ése es el límite de RECEPCIÓN (tolerancia breve de transporte); una vez almacenados, a -18 °C. Estos umbrales documentan tu registro de recepción; no sustituyen a tu plan APPCC ni a un asesor.
