Workbook

Sheet Instrucciones
A1: FIFO y Caducidades
A2: AI Chef Pro — aichef.pro
A4: Controla la rotación del género y el riesgo de caducidad, lote a lote.
A6: PESTAÑAS:
A7: 1. Control FIFO — un lote por línea: entrada, caducidad, apertura, cantidad y valor en riesgo
A8: 2. Alertas Caducidad — contadores por estado, valor en riesgo y protocolo de actuación
A9: 3. Mapa Almacén — las 11 zonas con su temperatura; alimenta el desplegable de zona. Los químicos y la limpieza tienen su propio almacén, separado de los alimentos, y los huevos su propia zona a temperatura ambiente constante: refrigerarlos y volver a sacarlos provoca condensación en la cáscara
A11: FIFO Y FEFO NO SON LO MISMO:
A12: FIFO (First In First Out) es el criterio de COLOCACIÓN: lo que entra primero se coloca delante.
A13: FEFO (First Expired First Out) es el criterio de SALIDA, y es el que manda en cocina: sale primero lo que antes caduca.
A14: Esta plantilla calcula el estado por FEFO, sobre la fecha límite efectiva. La columna de días en almacén delata el lote olvidado al fondo de la cámara.
A16: CÓMO SE RELLENA CADA LÍNEA:
... A34: Versión 2.0 · agosto 2026 · aichef.pro/kit-inventario · info@aichef.pro

Sheet Control FIFO
A1: CONTROL FIFO — FIRST IN FIRST OUT
A2: Una línea por LOTE, no por producto: dos entregas del mismo género son dos líneas. Las SEIS primeras son un ejemplo y cubren los cinco estados del semáforo (la quinta enseña por qué existe la fecha de apertura): bórralas antes de empezar. Fecha de revisión: ___/___/______ · Responsable: ________________
A4: # | B4: Producto | C4: Categoría | D4: Lote / Ref. | E4: Fecha de entrada | F4: Tipo de fecha | G4: Fecha de caducidad | H4: Fecha de apertura | I4: Vida útil tras abrir (días) | J4: Fecha límite efectiva | K4: Días restantes | L4: Estado | M4: Días en almacén | N4: Cantidad | O4: Unidad | P4: Precio/ud (€) | Q4: Valor en riesgo (€) | R4: Zona de almacén | S4: Posición | T4: Acción
A5: 1 | B5: Merluza fresca (ejemplo) | C5: Pescados | D5: L-2609-014 | E5: 46254 | F5: Caducidad | G5: 46257 | J5: =IF($G5="","",IF($H5="",$G5,IF($I5="",$G5,MIN($G5,$H5+$I5)))) -> 46257 | K5: =IF($J5="","",$J5-TODAY()) -> -1 | L5: =IF($K5="","",IF($K5<0,IF($F5="Consumo preferente","⚠ REVISAR (consumo preferente)","⛔ CADUCADO — RETIRAR"),IF($K5<=2,"🔴 URGENTE",IF($K5<=7,"🟡 PRÓXIMO","🟢 OK")))) -> ⛔ CADUCADO — RETIRAR | M5: =IF($E5="","",TODAY()-$E5) -> 4 | N5: 4 | O5: kg | P5: 14 | Q5: =IF(OR($N5="",$P5=""),"",$N5*$P5) -> 56 | R5: Cámara pescado | S5: Balda 1 | T5: Retirar y anotar en el registro de mermas
A6: 2 | B6: Nata 35 % M.G. (ejemplo) | C6: Lácteos | D6: L-2608-221 | E6: 46249 | F6: Consumo preferente | G6: 46256 | J6: =IF($G6="","",IF($H6="",$G6,IF($I6="",$G6,MIN($G6,$H6+$I6)))) -> 46256 | K6: =IF($J6="","",$J6-TODAY()) -> -2 | L6: =IF($K6="","",IF($K6<0,IF($F6="Consumo preferente","⚠ REVISAR (consumo preferente)","⛔ CADUCADO — RETIRAR"),IF($K6<=2,"🔴 URGENTE",IF($K6<=7,"🟡 PRÓXIMO","🟢 OK")))) -> ⚠ REVISAR (consumo preferente) | M6: =IF($E6="","",TODAY()-$E6) -> 9 | N6: 3 | O6: L | P6: 3.1 | Q6: =IF(OR($N6="",$P6=""),"",$N6*$P6) -> 9.3 | R6: Cámara elaborados | S6: Balda 2 | T6: Revisión organoléptica antes de decidir
A7: 3 | B7: Pechuga de pollo (ejemplo) | C7: Cárnicos | D7: L-2609-107 | E7: 46257 | F7: Caducidad | G7: 46259 | J7: =IF($G7="","",IF($H7="",$G7,IF($I7="",$G7,MIN($G7,$H7+$I7)))) -> 46259 | K7: =IF($J7="","",$J7-TODAY()) -> 1 | L7: =IF($K7="","",IF($K7<0,IF($F7="Consumo preferente","⚠ REVISAR (consumo preferente)","⛔ CADUCADO — RETIRAR"),IF($K7<=2,"🔴 URGENTE",IF($K7<=7,"🟡 PRÓXIMO","🟢 OK")))) -> 🔴 URGENTE | M7: =IF($E7="","",TODAY()-$E7) -> 1 | N7: 6 | O7: kg | P7: 6.5 | Q7: =IF(OR($N7="",$P7=""),"",$N7*$P7) -> 39 | R7: Cámara crudos | S7: Balda 1 | T7: Al servicio de hoy
A8: 4 | B8: Tomate (ejemplo) | C8: Verduras/Frutas | D8: L-2609-088 | E8: 46256 | F8: Caducidad | G8: 46263 | J8: =IF($G8="","",IF($H8="",$G8,IF($I8="",$G8,MIN($G8,$H8+$I8)))) -> 46263 | K8: =IF($J8="","",$J8-TODAY()) -> 5 | L8: =IF($K8="","",IF($K8<0,IF($F8="Consumo preferente","⚠ REVISAR (consumo preferente)","⛔ CADUCADO — RETIRAR"),IF($K8<=2,"🔴 URGENTE",IF($K8<=7,"🟡 PRÓXIMO","🟢 OK")))) -> 🟡 PRÓXIMO | M8: =IF($E8="","",TODAY()-$E8) -> 2 | N8: 10 | O8: kg | P8: 1.95 | Q8: =IF(OR($N8="",$P8=""),"",$N8*$P8) -> 19.5 | R8: Cámara verduras | S8: Cajón 3 | T8: Priorizar en la producción de la semana
A9: 5 | B9: Queso parmesano (ejemplo) | C9: Lácteos | D9: L-2605-330 | E9: 46251 | F9: Caducidad | G9: 46318 | H9: 46253 | I9: 10 | J9: =IF($G9="","",IF($H9="",$G9,IF($I9="",$G9,MIN($G9,$H9+$I9)))) -> 46263 | K9: =IF($J9="","",$J9-TODAY()) -> 5 | L9: =IF($K9="","",IF($K9<0,IF($F9="Consumo preferente","⚠ REVISAR (consumo preferente)","⛔ CADUCADO — RETIRAR"),IF($K9<=2,"🔴 URGENTE",IF($K9<=7,"🟡 PRÓXIMO","🟢 OK")))) -> 🟡 PRÓXIMO | M9: =IF($E9="","",TODAY()-$E9) -> 7 | N9: 2 | O9: kg | P9: 16.5 | Q9: =IF(OR($N9="",$P9=""),"",$N9*$P9) -> 33 | R9: Cámara elaborados | S9: Balda 3 | T9: Abierto: manda la vida útil tras abrir, no la caducidad del envase
A10: 6 | B10: Arroz redondo (ejemplo) | C10: Secos/Granos | D10: L-2604-012 | E10: 46218 | F10: Consumo preferente | G10: 46558 | J10: =IF($G10="","",IF($H10="",$G10,IF($I10="",$G10,MIN($G10,$H10+$I10)))) -> 46558 | K10: =IF($J10="","",$J10-TODAY()) -> 300 | L10: =IF($K10="","",IF($K10<0,IF($F10="Consumo preferente","⚠ REVISAR (consumo preferente)","⛔ CADUCADO — RETIRAR"),IF($K10<=2,"🔴 URGENTE",IF($K10<=7,"🟡 PRÓXIMO","🟢 OK")))) -> 🟢 OK | M10: =IF($E10="","",TODAY()-$E10) -> 40 | N10: 20 | O10: kg | P10: 1.45 | Q10: =IF(OR($N10="",$P10=""),"",$N10*$P10) -> 29 | R10: Economato seco | S10: Estantería 2 | T10: Sin riesgo: colocar detrás de lo que caduca antes
A11: 7 | J11: =IF($G11="","",IF($H11="",$G11,IF($I11="",$G11,MIN($G11,$H11+$I11)))) | K11: =IF($J11="","",$J11-TODAY()) | L11: =IF($K11="","",IF($K11<0,IF($F11="Consumo preferente","⚠ REVISAR (consumo preferente)","⛔ CADUCADO — RETIRAR"),IF($K11<=2,"🔴 URGENTE",IF($K11<=7,"🟡 PRÓXIMO","🟢 OK")))) | M11: =IF($E11="","",TODAY()-$E11) | Q11: =IF(OR($N11="",$P11=""),"",$N11*$P11)
A12: 8 | J12: =IF($G12="","",IF($H12="",$G12,IF($I12="",$G12,MIN($G12,$H12+$I12)))) | K12: =IF($J12="","",$J12-TODAY()) | L12: =IF($K12="","",IF($K12<0,IF($F12="Consumo preferente","⚠ REVISAR (consumo preferente)","⛔ CADUCADO — RETIRAR"),IF($K12<=2,"🔴 URGENTE",IF($K12<=7,"🟡 PRÓXIMO","🟢 OK")))) | M12: =IF($E12="","",TODAY()-$E12) | Q12: =IF(OR($N12="",$P12=""),"",$N12*$P12)
A13: 9 | J13: =IF($G13="","",IF($H13="",$G13,IF($I13="",$G13,MIN($G13,$H13+$I13)))) | K13: =IF($J13="","",$J13-TODAY()) | L13: =IF($K13="","",IF($K13<0,IF($F13="Consumo preferente","⚠ REVISAR (consumo preferente)","⛔ CADUCADO — RETIRAR"),IF($K13<=2,"🔴 URGENTE",IF($K13<=7,"🟡 PRÓXIMO","🟢 OK")))) | M13: =IF($E13="","",TODAY()-$E13) | Q13: =IF(OR($N13="",$P13=""),"",$N13*$P13)
A14: 10 | J14: =IF($G14="","",IF($H14="",$G14,IF($I14="",$G14,MIN($G14,$H14+$I14)))) | K14: =IF($J14="","",$J14-TODAY()) | L14: =IF($K14="","",IF($K14<0,IF($F14="Consumo preferente","⚠ REVISAR (consumo preferente)","⛔ CADUCADO — RETIRAR"),IF($K14<=2,"🔴 URGENTE",IF($K14<=7,"🟡 PRÓXIMO","🟢 OK")))) | M14: =IF($E14="","",TODAY()-$E14) | Q14: =IF(OR($N14="",$P14=""),"",$N14*$P14)
A15: 11 | J15: =IF($G15="","",IF($H15="",$G15,IF($I15="",$G15,MIN($G15,$H15+$I15)))) | K15: =IF($J15="","",$J15-TODAY()) | L15: =IF($K15="","",IF($K15<0,IF($F15="Consumo preferente","⚠ REVISAR (consumo preferente)","⛔ CADUCADO — RETIRAR"),IF($K15<=2,"🔴 URGENTE",IF($K15<=7,"🟡 PRÓXIMO","🟢 OK")))) | M15: =IF($E15="","",TODAY()-$E15) | Q15: =IF(OR($N15="",$P15=""),"",$N15*$P15)
A16: 12 | J16: =IF($G16="","",IF($H16="",$G16,IF($I16="",$G16,MIN($G16,$H16+$I16)))) | K16: =IF($J16="","",$J16-TODAY()) | L16: =IF($K16="","",IF($K16<0,IF($F16="Consumo preferente","⚠ REVISAR (consumo preferente)","⛔ CADUCADO — RETIRAR"),IF($K16<=2,"🔴 URGENTE",IF($K16<=7,"🟡 PRÓXIMO","🟢 OK")))) | M16: =IF($E16="","",TODAY()-$E16) | Q16: =IF(OR($N16="",$P16=""),"",$N16*$P16)
A17: 13 | J17: =IF($G17="","",IF($H17="",$G17,IF($I17="",$G17,MIN($G17,$H17+$I17)))) | K17: =IF($J17="","",$J17-TODAY()) | L17: =IF($K17="","",IF($K17<0,IF($F17="Consumo preferente","⚠ REVISAR (consumo preferente)","⛔ CADUCADO — RETIRAR"),IF($K17<=2,"🔴 URGENTE",IF($K17<=7,"🟡 PRÓXIMO","🟢 OK")))) | M17: =IF($E17="","",TODAY()-$E17) | Q17: =IF(OR($N17="",$P17=""),"",$N17*$P17)
A18: 14 | J18: =IF($G18="","",IF($H18="",$G18,IF($I18="",$G18,MIN($G18,$H18+$I18)))) | K18: =IF($J18="","",$J18-TODAY()) | L18: =IF($K18="","",IF($K18<0,IF($F18="Consumo preferente","⚠ REVISAR (consumo preferente)","⛔ CADUCADO — RETIRAR"),IF($K18<=2,"🔴 URGENTE",IF($K18<=7,"🟡 PRÓXIMO","🟢 OK")))) | M18: =IF($E18="","",TODAY()-$E18) | Q18: =IF(OR($N18="",$P18=""),"",$N18*$P18)
A19: 15 | J19: =IF($G19="","",IF($H19="",$G19,IF($I19="",$G19,MIN($G19,$H19+$I19)))) | K19: =IF($J19="","",$J19-TODAY()) | L19: =IF($K19="","",IF($K19<0,IF($F19="Consumo preferente","⚠ REVISAR (consumo preferente)","⛔ CADUCADO — RETIRAR"),IF($K19<=2,"🔴 URGENTE",IF($K19<=7,"🟡 PRÓXIMO","🟢 OK")))) | M19: =IF($E19="","",TODAY()-$E19) | Q19: =IF(OR($N19="",$P19=""),"",$N19*$P19)
A20: 16 | J20: =IF($G20="","",IF($H20="",$G20,IF($I20="",$G20,MIN($G20,$H20+$I20)))) | K20: =IF($J20="","",$J20-TODAY()) | L20: =IF($K20="","",IF($K20<0,IF($F20="Consumo preferente","⚠ REVISAR (consumo preferente)","⛔ CADUCADO — RETIRAR"),IF($K20<=2,"🔴 URGENTE",IF($K20<=7,"🟡 PRÓXIMO","🟢 OK")))) | M20: =IF($E20="","",TODAY()-$E20) | Q20: =IF(OR($N20="",$P20=""),"",$N20*$P20)
A21: 17 | J21: =IF($G21="","",IF($H21="",$G21,IF($I21="",$G21,MIN($G21,$H21+$I21)))) | K21: =IF($J21="","",$J21-TODAY()) | L21: =IF($K21="","",IF($K21<0,IF($F21="Consumo preferente","⚠ REVISAR (consumo preferente)","⛔ CADUCADO — RETIRAR"),IF($K21<=2,"🔴 URGENTE",IF($K21<=7,"🟡 PRÓXIMO","🟢 OK")))) | M21: =IF($E21="","",TODAY()-$E21) | Q21: =IF(OR($N21="",$P21=""),"",$N21*$P21)
A22: 18 | J22: =IF($G22="","",IF($H22="",$G22,IF($I22="",$G22,MIN($G22,$H22+$I22)))) | K22: =IF($J22="","",$J22-TODAY()) | L22: =IF($K22="","",IF($K22<0,IF($F22="Consumo preferente","⚠ REVISAR (consumo preferente)","⛔ CADUCADO — RETIRAR"),IF($K22<=2,"🔴 URGENTE",IF($K22<=7,"🟡 PRÓXIMO","🟢 OK")))) | M22: =IF($E22="","",TODAY()-$E22) | Q22: =IF(OR($N22="",$P22=""),"",$N22*$P22)
... A54: 50 | J54: =IF($G54="","",IF($H54="",$G54,IF($I54="",$G54,MIN($G54,$H54+$I54)))) | K54: =IF($J54="","",$J54-TODAY()) | L54: =IF($K54="","",IF($K54<0,IF($F54="Consumo preferente","⚠ REVISAR (consumo preferente)","⛔ CADUCADO — RETIRAR"),IF($K54<=2,"🔴 URGENTE",IF($K54<=7,"🟡 PRÓXIMO","🟢 OK")))) | M54: =IF($E54="","",TODAY()-$E54) | Q54: =IF(OR($N54="",$P54=""),"",$N54*$P54)

Sheet Alertas Caducidad
A1: ⚠️ ALERTAS DE CADUCIDAD
A2: Todo se calcula solo desde Control FIFO. Aquí no se escribe nada.
A3: Estado | B3: Nº de lotes | C3: Valor en riesgo (€) | D3: Qué hacer
A4: ⛔ CADUCADO — RETIRAR | B4: =COUNTIF('Control FIFO'!$L$5:$L$54,"*CADUCADO*") -> 1 | C4: =SUMIF('Control FIFO'!$L$5:$L$54,"*CADUCADO*",'Control FIFO'!$Q$5:$Q$54) -> 56 | D4: Retirada obligatoria y registro de merma en la plantilla 05. No se usa bajo ningún concepto.
A5: ⚠ REVISAR (consumo preferente) | B5: =COUNTIF('Control FIFO'!$L$5:$L$54,"*REVISAR*") -> 1 | C5: =SUMIF('Control FIFO'!$L$5:$L$54,"*REVISAR*",'Control FIFO'!$Q$5:$Q$54) -> 9.3 | D5: Consumo preferente vencido: revisión organoléptica (aspecto, olor, textura) antes de decidir. No es automáticamente un desecho.
A6: 🔴 URGENTE | B6: =COUNTIF('Control FIFO'!$L$5:$L$54,"*URGENTE*") -> 1 | C6: =SUMIF('Control FIFO'!$L$5:$L$54,"*URGENTE*",'Control FIFO'!$Q$5:$Q$54) -> 39 | D6: Quedan 2 días o menos: al servicio de hoy.
A7: 🟡 PRÓXIMO | B7: =COUNTIF('Control FIFO'!$L$5:$L$54,"*PRÓXIMO*") -> 2 | C7: =SUMIF('Control FIFO'!$L$5:$L$54,"*PRÓXIMO*",'Control FIFO'!$Q$5:$Q$54) -> 52.5 | D7: Quedan 7 días o menos: priorízalo en la producción de la semana.
A8: 🟢 OK | B8: =COUNTIF('Control FIFO'!$L$5:$L$54,"*OK*") -> 1 | C8: =SUMIF('Control FIFO'!$L$5:$L$54,"*OK*",'Control FIFO'!$Q$5:$Q$54) -> 29 | D8: Fuera de riesgo. Colócalo detrás de lo que caduca antes.
A9: VALOR REALMENTE EN RIESGO (todo menos 🟢 OK) | B9: =SUM($B$4:$B$7) -> 5 | C9: =SUM($C$4:$C$7) -> 156.8 | D9: Es la suma de los cuatro estados de arriba, sin los que están fuera de riesgo. Éste es el número que mueve a alguien.
A10: TOTAL de lotes registrados / valor total del stock | B10: =COUNTIF('Control FIFO'!$B$5:$B$54,"<>") -> 6 | C10: =SUM('Control FIFO'!$Q$5:$Q$54) -> 185.8 | D10: Todo el stock que tienes registrado en Control FIFO, esté o no en riesgo. No lo confundas con la fila de arriba.
A12: PROTOCOLO DE ACTUACIÓN
A13: 1. ⛔ CADUCADO — RETIRAR: retirada obligatoria del producto, baja del stock y registro en la plantilla 05 (Control de Mermas). Un producto con la fecha de caducidad vencida no se usa bajo ningún concepto, ni para personal ni para elaboraciones.
A14: 2. ⚠ REVISAR (consumo preferente): la fecha de consumo preferente vencida NO obliga a tirar. Revisión organoléptica (aspecto, olor, textura) y decisión del responsable; si hay duda, se retira.
A15: 3. 🔴 URGENTE: al servicio de HOY. Anótalo en el briefing y colócalo delante de todo.
A16: 4. 🟡 PRÓXIMO: priorízalo en la producción de la semana y revísalo al inicio de cada turno de mañana.
A18: Para verlos uno a uno: en Control FIFO, flecha del encabezado Estado y filtra por el que quieras. El autofiltro ya está puesto.

Sheet Mapa Almacén
A1: MAPA DE ALMACÉN — ZONAS DE ALMACENAMIENTO
A3: Zona | B3: Temperatura | C3: Qué se guarda aquí | D3: Capacidad | E3: Notas
A4: Cámara crudos | B4: 0-4 °C | C4: Carne, aves y caza crudas; siempre por debajo de todo lo demás | D4: 2 estanterías | E4: Nunca en la misma cámara que producto listo para consumo.
A5: Cámara pescado | B5: 0-2 °C | C5: Pescados y mariscos sobre hielo fundente | D5: 1 mesa fría | E5: Hielo fundente con desagüe; reponer en cada servicio.
A6: Cámara elaborados | B6: 0-4 °C | C6: Lácteos, elaborados propios, 5.ª gama y postres | D6: 3 estanterías | E6: Todo tapado, etiquetado y fechado. Nunca junto a crudos.
A7: Cámara verduras | B7: 4-8 °C | C7: Verduras y frutas | D7: 2 estanterías | E7: Sin lavar hasta el momento de uso; aparta la fruta que emite etileno.
A8: Congelador | B8: ≤ -18 °C | C8: Congelados | D8: 1 arcón | E8: Anota la fecha de congelación. Nunca recongelar lo descongelado.
A9: Descongelación | B9: 0-4 °C | C9: Producto en descongelación, identificado | D9: 1 estantería | E9: Bandeja con rejilla, tapado y etiquetado EN DESCONGELACIÓN con fecha.
A10: Economato seco | B10: Lugar fresco y seco, < 25 °C y HR < 60 % | C10: Secos y granos, conservas y bebidas no alcohólicas | D10: 4 estanterías | E10: Producto a ≥ 10 cm del suelo y separado de la pared.
A11: Bodega | B11: 12-16 °C | C11: Bebidas alcohólicas | D11: 1 botellero | E11: Sin luz directa ni vibraciones; botellas tumbadas.
A12: Residuos | B12: Ambiente, zona separada | C12: Residuos y envases | D12: 3 contenedores | E12: Fuera del circuito de alimentos; cubos con tapa y pedal.
A13: Huevera | B13: Ambiente constante, 12-20 °C | C13: Huevos: NO refrigerar antes de la venta | D13: 1 estantería | E13: Sin cambios bruscos de temperatura: la condensación en la cáscara facilita la entrada de Salmonella (Reg. (CE) 589/2008, art. 2).
A14: Almacén de químicos | B14: Ambiente, zona separada y señalizada | C14: Productos de limpieza, desinfectantes y sus fichas de datos de seguridad | D14: 1 armario | E14: Separado y señalizado; NUNCA sobre ni junto a alimentos ni sobre superficies de trabajo (Reg. (CE) 852/2004, Anexo II, Cap. IX).
A16: Zonas de ejemplo: cámbialas por las tuyas. Los nombres de la columna Zona son los que salen en el desplegable de Control FIFO, así que si los editas, edita también ese desplegable. La separación crudo / elaborado no es opcional, y los productos de limpieza y los químicos NUNCA van en el economato de los alimentos: son las dos primeras cosas que mira una inspección.
