Workbook

Sheet Instrucciones
A1: Análisis de Costes de Compras
A2: AI Chef Pro — aichef.pro
A4: Mira en qué se te va el dinero de las compras y calcula tus KPIs de coste.
A6: TODOS LOS IMPORTES VAN SIN IVA (BASE IMPONIBLE).
A7: El IVA soportado se deduce: no forma parte del food cost. Si copias el total de la factura en vez de la base imponible, tu food cost sale entre un 4 % y un 21 % inflado y todas las decisiones que tomes con él serán erróneas.
A9: PESTAÑAS:
A10: 1. Coste por Categoría — las 10 categorías del kit, mes a mes; es la tabla que alimenta a todas las demás
A11: 2. Evolución Mensual — el total de cada mes, su variación y el acumulado del año
A12: 3. Top 20 Productos — los productos que más dinero se llevan, con la alerta de subida de precio y el ranking Top 5, que se ordena solo (no hace falta que ordenes la tabla)
A13: 4. Dashboard KPIs — food cost, coste por cubierto y variación, calculados de verdad
A15: CÓMO SE USA:
A16: Carga cada mes el gasto por categoría en Coste por Categoría. El resto del libro se calcula solo.
... A26: Versión 2.0 · agosto 2026 · aichef.pro/kit-inventario · info@aichef.pro

Sheet Coste por Categoría
A1: COSTE DE COMPRAS POR CATEGORÍA (€, SIN IVA)
A2: Todos los importes SIN IVA (base imponible). La columna de enero trae datos de ejemplo: bórralos y carga los tuyos.
A3: Categoría | B3: Ene | C3: Feb | D3: Mar | E3: Abr | F3: May | G3: Jun | H3: Jul | I3: Ago | J3: Sep | K3: Oct | L3: Nov | M3: Dic | N3: Total año (€, sin IVA) | O3: % del Total
A4: Cárnicos | B4: 2850 | N4: =SUM(B4:M4) -> 2850 | O4: =IFERROR($N4/$N$14,"") -> 0.27403846
A5: Pescados | B5: 1980 | N5: =SUM(B5:M5) -> 1980 | O5: =IFERROR($N5/$N$14,"") -> 0.19038462
A6: Lácteos | B6: 620 | N6: =SUM(B6:M6) -> 620 | O6: =IFERROR($N6/$N$14,"") -> 0.059615385
A7: Verduras/Frutas | B7: 1150 | N7: =SUM(B7:M7) -> 1150 | O7: =IFERROR($N7/$N$14,"") -> 0.11057692
A8: Secos/Granos | B8: 1240 | N8: =SUM(B8:M8) -> 1240 | O8: =IFERROR($N8/$N$14,"") -> 0.11923077
A9: Congelados | B9: 480 | N9: =SUM(B9:M9) -> 480 | O9: =IFERROR($N9/$N$14,"") -> 0.046153846
A10: Bebidas Alcohólicas | B10: 980 | N10: =SUM(B10:M10) -> 980 | O10: =IFERROR($N10/$N$14,"") -> 0.094230769
A11: Bebidas No Alcohólicas | B11: 540 | N11: =SUM(B11:M11) -> 540 | O11: =IFERROR($N11/$N$14,"") -> 0.051923077
A12: Limpieza | B12: 380 | N12: =SUM(B12:M12) -> 380 | O12: =IFERROR($N12/$N$14,"") -> 0.036538462
A13: Otros | B13: 180 | N13: =SUM(B13:M13) -> 180 | O13: =IFERROR($N13/$N$14,"") -> 0.017307692
A14: TOTAL | B14: =SUM(B4:B13) -> 10400 | C14: =SUM(C4:C13) -> 0 | D14: =SUM(D4:D13) -> 0 | E14: =SUM(E4:E13) -> 0 | F14: =SUM(F4:F13) -> 0 | G14: =SUM(G4:G13) -> 0 | H14: =SUM(H4:H13) -> 0 | I14: =SUM(I4:I13) -> 0 | ... N14: =SUM(N4:N13) -> 10400 | O14: =IFERROR($N14/$N$14,"") -> 1
A16: La fila 14 (TOTAL) es la que lee el Dashboard KPIs. Allí eliges en una casilla verde QUÉ periodo mides: un mes concreto o el año completo. Las ventas, los cubiertos y las existencias que pongas en el dashboard tienen que ser las de ese mismo periodo.

Sheet Evolución Mensual
A1: EVOLUCIÓN MENSUAL DEL GASTO EN COMPRAS (€, SIN IVA)
A2: No se escribe nada aquí: sale entero de la fila TOTAL de Coste por Categoría.
A3: Mes | B3: Compras del mes (€) | C3: Variación vs mes anterior (%) | D3: Acumulado del año (€)
A4: Enero | B4: ='Coste por Categoría'!B$14 -> 10400 | D4: =SUM($B$4:$B4) -> 10400
A5: Febrero | B5: ='Coste por Categoría'!C$14 -> 0 | C5: =IF(OR($B4=0,$B5=0),"",IFERROR($B5/$B4-1,"")) | D5: =SUM($B$4:$B5) -> 10400
A6: Marzo | B6: ='Coste por Categoría'!D$14 -> 0 | C6: =IF(OR($B5=0,$B6=0),"",IFERROR($B6/$B5-1,"")) | D6: =SUM($B$4:$B6) -> 10400
A7: Abril | B7: ='Coste por Categoría'!E$14 -> 0 | C7: =IF(OR($B6=0,$B7=0),"",IFERROR($B7/$B6-1,"")) | D7: =SUM($B$4:$B7) -> 10400
A8: Mayo | B8: ='Coste por Categoría'!F$14 -> 0 | C8: =IF(OR($B7=0,$B8=0),"",IFERROR($B8/$B7-1,"")) | D8: =SUM($B$4:$B8) -> 10400
A9: Junio | B9: ='Coste por Categoría'!G$14 -> 0 | C9: =IF(OR($B8=0,$B9=0),"",IFERROR($B9/$B8-1,"")) | D9: =SUM($B$4:$B9) -> 10400
A10: Julio | B10: ='Coste por Categoría'!H$14 -> 0 | C10: =IF(OR($B9=0,$B10=0),"",IFERROR($B10/$B9-1,"")) | D10: =SUM($B$4:$B10) -> 10400
A11: Agosto | B11: ='Coste por Categoría'!I$14 -> 0 | C11: =IF(OR($B10=0,$B11=0),"",IFERROR($B11/$B10-1,"")) | D11: =SUM($B$4:$B11) -> 10400
A12: Septiembre | B12: ='Coste por Categoría'!J$14 -> 0 | C12: =IF(OR($B11=0,$B12=0),"",IFERROR($B12/$B11-1,"")) | D12: =SUM($B$4:$B12) -> 10400
A13: Octubre | B13: ='Coste por Categoría'!K$14 -> 0 | C13: =IF(OR($B12=0,$B13=0),"",IFERROR($B13/$B12-1,"")) | D13: =SUM($B$4:$B13) -> 10400
A14: Noviembre | B14: ='Coste por Categoría'!L$14 -> 0 | C14: =IF(OR($B13=0,$B14=0),"",IFERROR($B14/$B13-1,"")) | D14: =SUM($B$4:$B14) -> 10400
A15: Diciembre | B15: ='Coste por Categoría'!M$14 -> 0 | C15: =IF(OR($B14=0,$B15=0),"",IFERROR($B15/$B14-1,"")) | D15: =SUM($B$4:$B15) -> 10400
A17: La variación se deja en blanco mientras alguno de los dos meses esté a cero: un mes sin cargar no es una caída del 100 %.

Sheet Top 20 Productos
A1: TOP 20 PRODUCTOS — MAYOR GASTO
A2: Datos de ejemplo; precios orientativos SIN IVA, edítalos con los tuyos. NO hace falta que ordenes la tabla: el ranking Top 5 de abajo la ordena solo con LARGE, escribas en el orden que escribas.
A3: # | B3: Producto | C3: Categoría | D3: Unidad | E3: Gasto mensual (€) | F3: Gasto anual estimado (€) — mes × 12 | G3: % del Top 20 | H3: Precio anterior (€) | I3: Precio actual (€) | J3: Variación de precio (%) | K3: Proveedor
A4: 1 | B4: Solomillo de ternera | C4: Cárnicos | D4: kg | E4: 960 | F4: =IF($E4="","",$E4*12) -> 11520 | G4: =IFERROR($E4/$E$24,"") -> 0.21296042 | H4: 30.5 | I4: 32 | J4: =IF(OR($H4="",$I4=""),"",$I4/$H4-1) -> 0.049180328 | K4: Cárnicas del Norte (ejemplo)
A5: 2 | B5: Salmón fresco | C5: Pescados | D5: kg | E5: 840 | F5: =IF($E5="","",$E5*12) -> 10080 | G5: =IFERROR($E5/$E$24,"") -> 0.18634036 | H5: 12.9 | I5: 14 | J5: =IF(OR($H5="",$I5=""),"",$I5/$H5-1) -> 0.085271318 | K5: Pescados Ría Fresca (ejemplo)
A6: 3 | B6: Gambas | C6: Pescados | D6: kg | E6: 810 | F6: =IF($E6="","",$E6*12) -> 9720 | G6: =IFERROR($E6/$E$24,"") -> 0.17968535 | H6: 17.5 | I6: 18 | J6: =IF(OR($H6="",$I6=""),"",$I6/$H6-1) -> 0.028571429 | K6: Pescados Ría Fresca (ejemplo)
A7: 4 | B7: Pechuga de pollo | C7: Cárnicos | D7: kg | E7: 780 | F7: =IF($E7="","",$E7*12) -> 9360 | G7: =IFERROR($E7/$E$24,"") -> 0.17303034 | H7: 6.2 | I7: 6.5 | J7: =IF(OR($H7="",$I7=""),"",$I7/$H7-1) -> 0.048387097 | K7: Cárnicas del Norte (ejemplo)
A8: 5 | B8: Cerveza de grifo (barril 30 L) | C8: Bebidas Alcohólicas | D8: barril | E8: 412.5 | F8: =IF($E8="","",$E8*12) -> 4950 | G8: =IFERROR($E8/$E$24,"") -> 0.091506429 | H8: 53 | I8: 55 | J8: =IF(OR($H8="",$I8=""),"",$I8/$H8-1) -> 0.037735849 | K8: Bebidas y Distribución Levante (ejemplo)
A9: 6 | B9: Aceite de oliva virgen extra | C9: Secos/Granos | D9: L | E9: 348 | F9: =IF($E9="","",$E9*12) -> 4176 | G9: =IFERROR($E9/$E$24,"") -> 0.077198151 | H9: 5.1 | I9: 5.8 | J9: =IF(OR($H9="",$I9=""),"",$I9/$H9-1) -> 0.1372549 | K9: Distribuciones Economato Sur (ejemplo)
A10: 7 | B10: Queso parmesano | C10: Lácteos | D10: kg | E10: 198 | F10: =IF($E10="","",$E10*12) -> 2376 | G10: =IFERROR($E10/$E$24,"") -> 0.043923086 | H10: 16.2 | I10: 16.5 | J10: =IF(OR($H10="",$I10=""),"",$I10/$H10-1) -> 0.018518519 | K10: Distribuciones Economato Sur (ejemplo)
A11: 8 | B11: Patata | C11: Verduras/Frutas | D11: kg | E11: 159.38 | F11: =IF($E11="","",$E11*12) -> 1912.56 | G11: =IFERROR($E11/$E$24,"") -> 0.035355866 | H11: 0.95 | I11: 0.85 | J11: =IF(OR($H11="",$I11=""),"",$I11/$H11-1) -> -0.10526316 | K11: Frutas y Verduras La Huerta (ejemplo)
A12: 9 | F12: =IF($E12="","",$E12*12) | G12: =IFERROR($E12/$E$24,"") -> 0 | J12: =IF(OR($H12="",$I12=""),"",$I12/$H12-1)
A13: 10 | F13: =IF($E13="","",$E13*12) | G13: =IFERROR($E13/$E$24,"") -> 0 | J13: =IF(OR($H13="",$I13=""),"",$I13/$H13-1)
A14: 11 | F14: =IF($E14="","",$E14*12) | G14: =IFERROR($E14/$E$24,"") -> 0 | J14: =IF(OR($H14="",$I14=""),"",$I14/$H14-1)
A15: 12 | F15: =IF($E15="","",$E15*12) | G15: =IFERROR($E15/$E$24,"") -> 0 | J15: =IF(OR($H15="",$I15=""),"",$I15/$H15-1)
A16: 13 | F16: =IF($E16="","",$E16*12) | G16: =IFERROR($E16/$E$24,"") -> 0 | J16: =IF(OR($H16="",$I16=""),"",$I16/$H16-1)
A17: 14 | F17: =IF($E17="","",$E17*12) | G17: =IFERROR($E17/$E$24,"") -> 0 | J17: =IF(OR($H17="",$I17=""),"",$I17/$H17-1)
A18: 15 | F18: =IF($E18="","",$E18*12) | G18: =IFERROR($E18/$E$24,"") -> 0 | J18: =IF(OR($H18="",$I18=""),"",$I18/$H18-1)
A19: 16 | F19: =IF($E19="","",$E19*12) | G19: =IFERROR($E19/$E$24,"") -> 0 | J19: =IF(OR($H19="",$I19=""),"",$I19/$H19-1)
A20: 17 | F20: =IF($E20="","",$E20*12) | G20: =IFERROR($E20/$E$24,"") -> 0 | J20: =IF(OR($H20="",$I20=""),"",$I20/$H20-1)
A21: 18 | F21: =IF($E21="","",$E21*12) | G21: =IFERROR($E21/$E$24,"") -> 0 | J21: =IF(OR($H21="",$I21=""),"",$I21/$H21-1)
A22: 19 | F22: =IF($E22="","",$E22*12) | G22: =IFERROR($E22/$E$24,"") -> 0 | J22: =IF(OR($H22="",$I22=""),"",$I22/$H22-1)
A23: 20 | F23: =IF($E23="","",$E23*12) | G23: =IFERROR($E23/$E$24,"") -> 0 | J23: =IF(OR($H23="",$I23=""),"",$I23/$H23-1)
A24: TOTAL | E24: =SUM($E$4:$E$23) -> 4507.88 | F24: =SUM($F$4:$F$23) -> 54094.56 | G24: =IFERROR($E$24/$E$24,"") -> 1
L26: Top 5 productos | M26: Gasto mensual (€)
L27: =IFERROR(INDEX($B$4:$B$23,MATCH(LARGE($E$4:$E$23,1),$E$4:$E$23,0)),"") -> Solomillo de ternera | M27: =IFERROR(LARGE($E$4:$E$23,1),"") -> 960
L28: =IFERROR(INDEX($B$4:$B$23,MATCH(LARGE($E$4:$E$23,2),$E$4:$E$23,0)),"") -> Salmón fresco | M28: =IFERROR(LARGE($E$4:$E$23,2),"") -> 840
L29: =IFERROR(INDEX($B$4:$B$23,MATCH(LARGE($E$4:$E$23,3),$E$4:$E$23,0)),"") -> Gambas | M29: =IFERROR(LARGE($E$4:$E$23,3),"") -> 810
L30: =IFERROR(INDEX($B$4:$B$23,MATCH(LARGE($E$4:$E$23,4),$E$4:$E$23,0)),"") -> Pechuga de pollo | M30: =IFERROR(LARGE($E$4:$E$23,4),"") -> 780
L31: =IFERROR(INDEX($B$4:$B$23,MATCH(LARGE($E$4:$E$23,5),$E$4:$E$23,0)),"") -> Cerveza de grifo (barril 30 L) | M31: =IFERROR(LARGE($E$4:$E$23,5),"") -> 412.5
A33: El ranking Top 5 de la derecha se calcula solo con LARGE: no hace falta que ordenes la tabla y, de hecho, la hoja está protegida para que no la desordenes sin querer. Si dos productos gastan exactamente lo mismo, enseña dos veces el primero; cambia un céntimo y se separan.

Sheet Dashboard KPIs
A1: DASHBOARD — KPIs DE COMPRAS
A2: Elige el periodo y rellena las casillas verdes. Todo lo demás se calcula solo, con los importes SIN IVA. La columna Estado te dice de un vistazo si cada KPI está donde tiene que estar.
A3: KPI | B3: Resultado | C3: Objetivo | D3: Cómo se calcula | E3: Estado
A4: Food cost (%) | B4: =IFERROR(($B$14+$B$6-$B$15)/$B$12,"") -> 0.31029412 | C4: 0.32 | D4: (Existencias iniciales + Compras del periodo − Existencias finales) / Ventas. Es CONSUMO, no compras. El rango sano de un restaurante está entre el 28 % y el 32 %: aquí se fija el TECHO, cámbialo por el tuyo. | E4: =IF(OR($B$4="",$C$4=""),"",IF($B$4<=$C$4,"🟢 OK",IF($B$4<=$C$4*1.1,"🟡 REVISAR","🔴 ALERTA"))) -> 🟢 OK
A5: Coste por cubierto (€) | B5: =IFERROR(($B$14+$B$6-$B$15-'Coste por Categoría'!$N$12-'Coste por Categoría'!$N$13)/$B$13,"") -> 6.8896552 | C5: =IFERROR($B$17*0.3,"") -> 7.035 | D5: Consumo de materia prima (sin Limpieza ni Otros) / cubiertos servidos. El objetivo es el 30 % de tu ticket medio, no una cifra fija en euros. | E5: =IF(OR($B$5="",$C$5=""),"",IF($B$5<=$C$5,"🟢 OK",IF($B$5<=$C$5*1.1,"🟡 REVISAR","🔴 ALERTA"))) -> 🟢 OK
A6: Compras del periodo (€) | B6: =IF($B$10="","",IF($B$10="Año completo",'Coste por Categoría'!$N$14,IFERROR(INDEX('Coste por Categoría'!$B$14:$M$14,MATCH($B$10,'Coste por Categoría'!$B$3:$M$3,0)),""))) -> 10400 | C6: — | D6: Total del mes que elijas arriba en la pestaña Coste por Categoría.
A7: Variación vs periodo anterior | B7: =IFERROR($B$6/$B$16-1,"") -> 0.042084168 | C7: 0.05 | D7: Compras del periodo / compras del periodo anterior − 1. Se compara en valor absoluto: una caída del 20 % también hay que explicarla. | E7: =IF(OR($B$7="",$C$7=""),"",IF(ABS($B$7)<=$C$7,"🟢 OK",IF(ABS($B$7)<=$C$7*2,"🟡 REVISAR","🔴 ALERTA"))) -> 🟢 OK
A8: Productos con subida > 5 % | B8: =COUNTIF('Top 20 Productos'!$J$4:$J$23,">0.05") -> 2 | C8: 0 | D8: Líneas del Top 20 cuya variación de precio supera el 5 %. | E8: =IF(OR($B$8="",$C$8=""),"",IF($B$8<=$C$8,"🟢 OK",IF($B$8<=2,"🟡 REVISAR","🔴 ALERTA"))) -> 🟡 REVISAR
A9: Mayor subida de precio | B9: =IFERROR(INDEX('Top 20 Productos'!$B$4:$B$23,MATCH(MAX('Top 20 Productos'!$J$4:$J$23),'Top 20 Productos'!$J$4:$J$23,0)),"") -> Aceite de oliva virgen extra | C9: — | D9: Producto del Top 20 con la variación más alta.
A10: PERIODO QUE SE MIDE | B10: Ene | D10: Elige el mes que has cargado en Coste por Categoría, o «Año completo». Las ventas, los cubiertos y las existencias que pongas abajo tienen que ser las de ESE periodo.
A11: DATOS DEL PERIODO — rellena estas casillas
A12: Ventas del periodo (€, sin IVA) | B12: 34000 | D12: Base imponible, sin IVA. Mismo periodo que las compras cargadas.
A13: Cubiertos servidos | B13: 1450 | D13: Comensales reales del periodo, no reservas.
A14: Existencias iniciales (€) | B14: 4200 | D14: Valor del inventario al empezar el periodo (plantilla 01 o BONUS-08).
A15: Existencias finales (€) | B15: 4050 | D15: Valor del inventario al cerrar el periodo.
A16: Compras del periodo anterior (€) | B16: 9980 | D16: Para la variación. Sin IVA, igual que el resto.
A17: Ticket medio (€) | B17: 23.45 | D17: Ventas / cubiertos. Fija el objetivo de coste por cubierto.
A19: Cifras de ejemplo coherentes con el mes de enero de Coste por Categoría: 10.400 € de compras, 34.000 € de ventas y 1.450 cubiertos dan un food cost del 31,0 %, dentro del objetivo. Cámbialas por las tuyas.
