Workbook

Sheet Instrucciones
A1: BONUS: Calculadora Punto de Pedido
A2: AI Chef Pro — aichef.pro
A4: Calcula cuándo hay que pedir cada producto y cuánto conviene pedir.
A6: LAS DOS FÓRMULAS:
A7: Punto de pedido = consumo diario × lead time + stock de seguridad
A8: Stock de seguridad = consumo diario × días de cobertura (por eso la cobertura se teclea en DÍAS y la columna de al lado la pasa a unidades)
A10: PESTAÑAS:
A11: 1. Calculadora — una línea por producto; las columnas SIN fondo verde se calculan solas (en este kit el verde es siempre lo que escribes tú)
A12: 2. Parámetros — coste de pedido, coste de almacenamiento y factor de vida útil, editables; de ahí salen las EOQ y el tope de la cantidad sugerida
A14: CÓMO SE USA:
A15: Rellena las casillas verdes: consumo diario, lead time, cobertura, precio, vida útil y proveedor.
A16: Cuando el stock caiga hasta el punto de pedido, cursa el pedido. Ni antes ni después.
... A26: Versión 2.0 · agosto 2026 · aichef.pro/kit-inventario · info@aichef.pro

Sheet Calculadora
A1: CALCULADORA — PUNTO DE PEDIDO ÓPTIMO
A2: Datos de ejemplo; precios orientativos SIN IVA, edítalos con los tuyos. El consumo diario y la vida útil son los de TU casa: los de ejemplo son de un restaurante de menú de 60 comensales y salen de la MISMA tabla que los par levels de la plantilla 01, así que el punto de pedido de aquí y el par level de allí son el mismo número.
A3: # | B3: Producto | C3: Categoría | D3: Consumo diario (ud/día) | E3: Lead time (días) | F3: Cobertura de seguridad (días) | G3: Stock de seguridad (ud) | H3: Punto de pedido (ud) | I3: Precio/ud (€) | J3: Vida útil (días) | K3: Stock máximo (ud) — par max del 01 | L3: EOQ teórica (ud) | M3: Cantidad a pedir sugerida (ud) | N3: Frecuencia de pedido (días) | O3: Proveedor
A4: 1 | B4: Pechuga de pollo | C4: Cárnicos | D4: 4 | E4: 1 | F4: 1 | G4: =IF(OR($D4="",$F4=""),"",$D4*$F4) -> 4 | H4: =IF(OR($D4="",$E4="",$F4=""),"",$D4*$E4+$G4) -> 8 | I4: 6.5 | J4: 4 | K4: 20 | L4: =IFERROR(IF(OR($D4="",$D4<=0,$I4="",$I4<=0,Parámetros!$D$4<=0,Parámetros!$D$5<=0),"",ROUND(SQRT(2*$D4*365*Parámetros!$D$4/($I4*Parámetros!$D$5)),0)),"") -> 73 | M4: =IFERROR(IF(OR($L4="",$J4=""),"",MIN($L4,ROUND($D4*$J4*Parámetros!$D$12,0),IF($K4="",$L4,$K4))),"") -> 11 | N4: =IF(OR($D4="",$D4<=0,$M4=""),"",ROUND($M4/$D4,0)) -> 3 | O4: Cárnicas del Norte (ejemplo)
A5: 2 | B5: Solomillo de ternera | C5: Cárnicos | D5: 1 | E5: 2 | F5: 1 | G5: =IF(OR($D5="",$F5=""),"",$D5*$F5) -> 1 | H5: =IF(OR($D5="",$E5="",$F5=""),"",$D5*$E5+$G5) -> 3 | I5: 32 | J5: 8 | K5: 8 | L5: =IFERROR(IF(OR($D5="",$D5<=0,$I5="",$I5<=0,Parámetros!$D$4<=0,Parámetros!$D$5<=0),"",ROUND(SQRT(2*$D5*365*Parámetros!$D$4/($I5*Parámetros!$D$5)),0)),"") -> 17 | M5: =IFERROR(IF(OR($L5="",$J5=""),"",MIN($L5,ROUND($D5*$J5*Parámetros!$D$12,0),IF($K5="",$L5,$K5))),"") -> 6 | N5: =IF(OR($D5="",$D5<=0,$M5=""),"",ROUND($M5/$D5,0)) -> 6 | O5: Cárnicas del Norte (ejemplo)
A6: 3 | B6: Salmón fresco | C6: Pescados | D6: 2 | E6: 1 | F6: 1 | G6: =IF(OR($D6="",$F6=""),"",$D6*$F6) -> 2 | H6: =IF(OR($D6="",$E6="",$F6=""),"",$D6*$E6+$G6) -> 4 | I6: 14 | J6: 3 | K6: 10 | L6: =IFERROR(IF(OR($D6="",$D6<=0,$I6="",$I6<=0,Parámetros!$D$4<=0,Parámetros!$D$5<=0),"",ROUND(SQRT(2*$D6*365*Parámetros!$D$4/($I6*Parámetros!$D$5)),0)),"") -> 35 | M6: =IFERROR(IF(OR($L6="",$J6=""),"",MIN($L6,ROUND($D6*$J6*Parámetros!$D$12,0),IF($K6="",$L6,$K6))),"") -> 4 | N6: =IF(OR($D6="",$D6<=0,$M6=""),"",ROUND($M6/$D6,0)) -> 2 | O6: Pescados Ría Fresca (ejemplo)
A7: 4 | B7: Leche entera | C7: Lácteos | D7: 8 | E7: 2 | F7: 1 | G7: =IF(OR($D7="",$F7=""),"",$D7*$F7) -> 8 | H7: =IF(OR($D7="",$E7="",$F7=""),"",$D7*$E7+$G7) -> 24 | I7: 0.85 | J7: 12 | K7: 60 | L7: =IFERROR(IF(OR($D7="",$D7<=0,$I7="",$I7<=0,Parámetros!$D$4<=0,Parámetros!$D$5<=0),"",ROUND(SQRT(2*$D7*365*Parámetros!$D$4/($I7*Parámetros!$D$5)),0)),"") -> 287 | M7: =IFERROR(IF(OR($L7="",$J7=""),"",MIN($L7,ROUND($D7*$J7*Parámetros!$D$12,0),IF($K7="",$L7,$K7))),"") -> 60 | N7: =IF(OR($D7="",$D7<=0,$M7=""),"",ROUND($M7/$D7,0)) -> 8 | O7: Distribuciones Economato Sur (ejemplo)
A8: 5 | B8: Patata | C8: Verduras/Frutas | D8: 6.25 | E8: 2 | F8: 2 | G8: =IF(OR($D8="",$F8=""),"",$D8*$F8) -> 12.5 | H8: =IF(OR($D8="",$E8="",$F8=""),"",$D8*$E8+$G8) -> 25 | I8: 0.85 | J8: 30 | K8: 60 | L8: =IFERROR(IF(OR($D8="",$D8<=0,$I8="",$I8<=0,Parámetros!$D$4<=0,Parámetros!$D$5<=0),"",ROUND(SQRT(2*$D8*365*Parámetros!$D$4/($I8*Parámetros!$D$5)),0)),"") -> 254 | M8: =IFERROR(IF(OR($L8="",$J8=""),"",MIN($L8,ROUND($D8*$J8*Parámetros!$D$12,0),IF($K8="",$L8,$K8))),"") -> 60 | N8: =IF(OR($D8="",$D8<=0,$M8=""),"",ROUND($M8/$D8,0)) -> 10 | O8: Frutas y Verduras La Huerta (ejemplo)
A9: 6 | B9: Aceite de oliva virgen extra | C9: Secos/Granos | D9: 2 | E9: 4 | F9: 1 | G9: =IF(OR($D9="",$F9=""),"",$D9*$F9) -> 2 | H9: =IF(OR($D9="",$E9="",$F9=""),"",$D9*$E9+$G9) -> 10 | I9: 5.8 | J9: 540 | K9: 25 | L9: =IFERROR(IF(OR($D9="",$D9<=0,$I9="",$I9<=0,Parámetros!$D$4<=0,Parámetros!$D$5<=0),"",ROUND(SQRT(2*$D9*365*Parámetros!$D$4/($I9*Parámetros!$D$5)),0)),"") -> 55 | M9: =IFERROR(IF(OR($L9="",$J9=""),"",MIN($L9,ROUND($D9*$J9*Parámetros!$D$12,0),IF($K9="",$L9,$K9))),"") -> 25 | N9: =IF(OR($D9="",$D9<=0,$M9=""),"",ROUND($M9/$D9,0)) -> 13 | O9: Distribuciones Economato Sur (ejemplo)
A10: 7 | B10: Arroz redondo | C10: Secos/Granos | D10: 2 | E10: 4 | F10: 1 | G10: =IF(OR($D10="",$F10=""),"",$D10*$F10) -> 2 | H10: =IF(OR($D10="",$E10="",$F10=""),"",$D10*$E10+$G10) -> 10 | I10: 1.45 | J10: 720 | K10: 25 | L10: =IFERROR(IF(OR($D10="",$D10<=0,$I10="",$I10<=0,Parámetros!$D$4<=0,Parámetros!$D$5<=0),"",ROUND(SQRT(2*$D10*365*Parámetros!$D$4/($I10*Parámetros!$D$5)),0)),"") -> 110 | M10: =IFERROR(IF(OR($L10="",$J10=""),"",MIN($L10,ROUND($D10*$J10*Parámetros!$D$12,0),IF($K10="",$L10,$K10))),"") -> 25 | N10: =IF(OR($D10="",$D10<=0,$M10=""),"",ROUND($M10/$D10,0)) -> 13 | O10: Distribuciones Economato Sur (ejemplo)
A11: 8 | B11: Cerveza de grifo (barril 30 L) | C11: Bebidas Alcohólicas | D11: 0.25 | E11: 3 | F11: 5 | G11: =IF(OR($D11="",$F11=""),"",$D11*$F11) -> 1.25 | H11: =IF(OR($D11="",$E11="",$F11=""),"",$D11*$E11+$G11) -> 2 | I11: 55 | J11: 120 | K11: 6 | L11: =IFERROR(IF(OR($D11="",$D11<=0,$I11="",$I11<=0,Parámetros!$D$4<=0,Parámetros!$D$5<=0),"",ROUND(SQRT(2*$D11*365*Parámetros!$D$4/($I11*Parámetros!$D$5)),0)),"") -> 6 | M11: =IFERROR(IF(OR($L11="",$J11=""),"",MIN($L11,ROUND($D11*$J11*Parámetros!$D$12,0),IF($K11="",$L11,$K11))),"") -> 6 | N11: =IF(OR($D11="",$D11<=0,$M11=""),"",ROUND($M11/$D11,0)) -> 24 | O11: Bebidas y Distribución Levante (ejemplo)
A12: 9 | G12: =IF(OR($D12="",$F12=""),"",$D12*$F12) | H12: =IF(OR($D12="",$E12="",$F12=""),"",$D12*$E12+$G12) | L12: =IFERROR(IF(OR($D12="",$D12<=0,$I12="",$I12<=0,Parámetros!$D$4<=0,Parámetros!$D$5<=0),"",ROUND(SQRT(2*$D12*365*Parámetros!$D$4/($I12*Parámetros!$D$5)),0)),"") | M12: =IFERROR(IF(OR($L12="",$J12=""),"",MIN($L12,ROUND($D12*$J12*Parámetros!$D$12,0),IF($K12="",$L12,$K12))),"") | N12: =IF(OR($D12="",$D12<=0,$M12=""),"",ROUND($M12/$D12,0))
A13: 10 | G13: =IF(OR($D13="",$F13=""),"",$D13*$F13) | H13: =IF(OR($D13="",$E13="",$F13=""),"",$D13*$E13+$G13) | L13: =IFERROR(IF(OR($D13="",$D13<=0,$I13="",$I13<=0,Parámetros!$D$4<=0,Parámetros!$D$5<=0),"",ROUND(SQRT(2*$D13*365*Parámetros!$D$4/($I13*Parámetros!$D$5)),0)),"") | M13: =IFERROR(IF(OR($L13="",$J13=""),"",MIN($L13,ROUND($D13*$J13*Parámetros!$D$12,0),IF($K13="",$L13,$K13))),"") | N13: =IF(OR($D13="",$D13<=0,$M13=""),"",ROUND($M13/$D13,0))
A14: 11 | G14: =IF(OR($D14="",$F14=""),"",$D14*$F14) | H14: =IF(OR($D14="",$E14="",$F14=""),"",$D14*$E14+$G14) | L14: =IFERROR(IF(OR($D14="",$D14<=0,$I14="",$I14<=0,Parámetros!$D$4<=0,Parámetros!$D$5<=0),"",ROUND(SQRT(2*$D14*365*Parámetros!$D$4/($I14*Parámetros!$D$5)),0)),"") | M14: =IFERROR(IF(OR($L14="",$J14=""),"",MIN($L14,ROUND($D14*$J14*Parámetros!$D$12,0),IF($K14="",$L14,$K14))),"") | N14: =IF(OR($D14="",$D14<=0,$M14=""),"",ROUND($M14/$D14,0))
A15: 12 | G15: =IF(OR($D15="",$F15=""),"",$D15*$F15) | H15: =IF(OR($D15="",$E15="",$F15=""),"",$D15*$E15+$G15) | L15: =IFERROR(IF(OR($D15="",$D15<=0,$I15="",$I15<=0,Parámetros!$D$4<=0,Parámetros!$D$5<=0),"",ROUND(SQRT(2*$D15*365*Parámetros!$D$4/($I15*Parámetros!$D$5)),0)),"") | M15: =IFERROR(IF(OR($L15="",$J15=""),"",MIN($L15,ROUND($D15*$J15*Parámetros!$D$12,0),IF($K15="",$L15,$K15))),"") | N15: =IF(OR($D15="",$D15<=0,$M15=""),"",ROUND($M15/$D15,0))
A16: 13 | G16: =IF(OR($D16="",$F16=""),"",$D16*$F16) | H16: =IF(OR($D16="",$E16="",$F16=""),"",$D16*$E16+$G16) | L16: =IFERROR(IF(OR($D16="",$D16<=0,$I16="",$I16<=0,Parámetros!$D$4<=0,Parámetros!$D$5<=0),"",ROUND(SQRT(2*$D16*365*Parámetros!$D$4/($I16*Parámetros!$D$5)),0)),"") | M16: =IFERROR(IF(OR($L16="",$J16=""),"",MIN($L16,ROUND($D16*$J16*Parámetros!$D$12,0),IF($K16="",$L16,$K16))),"") | N16: =IF(OR($D16="",$D16<=0,$M16=""),"",ROUND($M16/$D16,0))
A17: 14 | G17: =IF(OR($D17="",$F17=""),"",$D17*$F17) | H17: =IF(OR($D17="",$E17="",$F17=""),"",$D17*$E17+$G17) | L17: =IFERROR(IF(OR($D17="",$D17<=0,$I17="",$I17<=0,Parámetros!$D$4<=0,Parámetros!$D$5<=0),"",ROUND(SQRT(2*$D17*365*Parámetros!$D$4/($I17*Parámetros!$D$5)),0)),"") | M17: =IFERROR(IF(OR($L17="",$J17=""),"",MIN($L17,ROUND($D17*$J17*Parámetros!$D$12,0),IF($K17="",$L17,$K17))),"") | N17: =IF(OR($D17="",$D17<=0,$M17=""),"",ROUND($M17/$D17,0))
A18: 15 | G18: =IF(OR($D18="",$F18=""),"",$D18*$F18) | H18: =IF(OR($D18="",$E18="",$F18=""),"",$D18*$E18+$G18) | L18: =IFERROR(IF(OR($D18="",$D18<=0,$I18="",$I18<=0,Parámetros!$D$4<=0,Parámetros!$D$5<=0),"",ROUND(SQRT(2*$D18*365*Parámetros!$D$4/($I18*Parámetros!$D$5)),0)),"") | M18: =IFERROR(IF(OR($L18="",$J18=""),"",MIN($L18,ROUND($D18*$J18*Parámetros!$D$12,0),IF($K18="",$L18,$K18))),"") | N18: =IF(OR($D18="",$D18<=0,$M18=""),"",ROUND($M18/$D18,0))
A19: 16 | G19: =IF(OR($D19="",$F19=""),"",$D19*$F19) | H19: =IF(OR($D19="",$E19="",$F19=""),"",$D19*$E19+$G19) | L19: =IFERROR(IF(OR($D19="",$D19<=0,$I19="",$I19<=0,Parámetros!$D$4<=0,Parámetros!$D$5<=0),"",ROUND(SQRT(2*$D19*365*Parámetros!$D$4/($I19*Parámetros!$D$5)),0)),"") | M19: =IFERROR(IF(OR($L19="",$J19=""),"",MIN($L19,ROUND($D19*$J19*Parámetros!$D$12,0),IF($K19="",$L19,$K19))),"") | N19: =IF(OR($D19="",$D19<=0,$M19=""),"",ROUND($M19/$D19,0))
A20: 17 | G20: =IF(OR($D20="",$F20=""),"",$D20*$F20) | H20: =IF(OR($D20="",$E20="",$F20=""),"",$D20*$E20+$G20) | L20: =IFERROR(IF(OR($D20="",$D20<=0,$I20="",$I20<=0,Parámetros!$D$4<=0,Parámetros!$D$5<=0),"",ROUND(SQRT(2*$D20*365*Parámetros!$D$4/($I20*Parámetros!$D$5)),0)),"") | M20: =IFERROR(IF(OR($L20="",$J20=""),"",MIN($L20,ROUND($D20*$J20*Parámetros!$D$12,0),IF($K20="",$L20,$K20))),"") | N20: =IF(OR($D20="",$D20<=0,$M20=""),"",ROUND($M20/$D20,0))
A21: 18 | G21: =IF(OR($D21="",$F21=""),"",$D21*$F21) | H21: =IF(OR($D21="",$E21="",$F21=""),"",$D21*$E21+$G21) | L21: =IFERROR(IF(OR($D21="",$D21<=0,$I21="",$I21<=0,Parámetros!$D$4<=0,Parámetros!$D$5<=0),"",ROUND(SQRT(2*$D21*365*Parámetros!$D$4/($I21*Parámetros!$D$5)),0)),"") | M21: =IFERROR(IF(OR($L21="",$J21=""),"",MIN($L21,ROUND($D21*$J21*Parámetros!$D$12,0),IF($K21="",$L21,$K21))),"") | N21: =IF(OR($D21="",$D21<=0,$M21=""),"",ROUND($M21/$D21,0))
A22: 19 | G22: =IF(OR($D22="",$F22=""),"",$D22*$F22) | H22: =IF(OR($D22="",$E22="",$F22=""),"",$D22*$E22+$G22) | L22: =IFERROR(IF(OR($D22="",$D22<=0,$I22="",$I22<=0,Parámetros!$D$4<=0,Parámetros!$D$5<=0),"",ROUND(SQRT(2*$D22*365*Parámetros!$D$4/($I22*Parámetros!$D$5)),0)),"") | M22: =IFERROR(IF(OR($L22="",$J22=""),"",MIN($L22,ROUND($D22*$J22*Parámetros!$D$12,0),IF($K22="",$L22,$K22))),"") | N22: =IF(OR($D22="",$D22<=0,$M22=""),"",ROUND($M22/$D22,0))
A23: 20 | G23: =IF(OR($D23="",$F23=""),"",$D23*$F23) | H23: =IF(OR($D23="",$E23="",$F23=""),"",$D23*$E23+$G23) | L23: =IFERROR(IF(OR($D23="",$D23<=0,$I23="",$I23<=0,Parámetros!$D$4<=0,Parámetros!$D$5<=0),"",ROUND(SQRT(2*$D23*365*Parámetros!$D$4/($I23*Parámetros!$D$5)),0)),"") | M23: =IFERROR(IF(OR($L23="",$J23=""),"",MIN($L23,ROUND($D23*$J23*Parámetros!$D$12,0),IF($K23="",$L23,$K23))),"") | N23: =IF(OR($D23="",$D23<=0,$M23=""),"",ROUND($M23/$D23,0))
... A33: 30 | G33: =IF(OR($D33="",$F33=""),"",$D33*$F33) | H33: =IF(OR($D33="",$E33="",$F33=""),"",$D33*$E33+$G33) | L33: =IFERROR(IF(OR($D33="",$D33<=0,$I33="",$I33<=0,Parámetros!$D$4<=0,Parámetros!$D$5<=0),"",ROUND(SQRT(2*$D33*365*Parámetros!$D$4/($I33*Parámetros!$D$5)),0)),"") | M33: =IFERROR(IF(OR($L33="",$J33=""),"",MIN($L33,ROUND($D33*$J33*Parámetros!$D$12,0),IF($K33="",$L33,$K33))),"") | N33: =IF(OR($D33="",$D33<=0,$M33=""),"",ROUND($M33/$D33,0))
A35: Columnas SIN fondo verde (no se tocan): stock de seguridad, punto de pedido, EOQ teórica, cantidad sugerida y frecuencia. Si la frecuencia sale en blanco es que el consumo diario está vacío o a cero, no que la fórmula falle. La cantidad sugerida lleva TRES topes: la EOQ, el 70 % de lo que consumes dentro de la vida útil y tu stock máximo — el más pequeño de los tres es el que manda.

Sheet Parámetros
A1: PARÁMETROS DE REFERENCIA
A3: Parámetro | B3: Rango habitual | C3: Notas | D3: Se usa en la fórmula
A4: Coste de pedido (€) | B4: 2-5 € | C4: Lo que te cuesta CURSAR un pedido: tiempo de hacerlo, recepción, cotejo del albarán y registro de la factura. | D4: 3
A5: Coste de almacenamiento (% anual) | B5: 20-30 % anual | C5: Sobre el VALOR del producto: capital inmovilizado, cámara, seguro y la merma de lo que se estropea esperando. | D5: 0.25
A6: Lead time cárnicos | B6: 1-2 días | C6: Entregas diarias habituales.
A7: Lead time pescado | B7: 1 día | C7: Entrega diaria obligatoria.
A8: Lead time secos | B8: 3-5 días | C8: Pedidos semanales.
A9: Lead time congelados | B9: 2-3 días | C9: Pedidos 2 veces por semana.
A10: Cobertura de seguridad (días) — columna F | B10: 1-3 días | C10: Se teclea en DÍAS. La columna G la convierte en unidades: consumo diario × días de cobertura. Antes se pedía en días aquí y se sumaba como unidades allí, y el punto de pedido salía a la mitad.
A11: Vida útil (días) — columna J | B11: Fresco 2-5 · refrigerado 7-15 · seco 180-720 | C11: Días que aguanta el producto en tu cámara desde que lo recibes.
A12: Factor de vida útil | B12: 0,7 (70 %) | C12: La cantidad sugerida nunca pasa de este porcentaje de lo que consumes dentro de la vida útil: el resto es el margen para un día flojo. RT-08: es una casilla verde de verdad, no un número escondido dentro de las 30 fórmulas. | D12: 0.7
A13: Stock máximo (ud) — columna K | B13: El par MAX de la plantilla 01 | C13: El tercer tope de la cantidad sugerida: por mucho que digan la EOQ y la vida útil, no se pide más de lo que cabe en tu cámara. Déjalo en blanco si no quieres ese tope.
A15: Las TRES casillas verdes entran en las fórmulas: el coste de pedido, el coste de almacenamiento anual y el factor de vida útil. El resto de la tabla es referencia para que sepas qué escribir en cada columna de la Calculadora.
