Workbook

Sheet Instructions
B2: 01 · Restaurant Financial Projections: 3-Year Pro Forma P&L
B4: AI Chef Pro · aichef.pro — Restaurant Financial Plan Kit Pro
B6: How to use this template:
B7: ▸ Enter the monthly revenue and expense figures in each year tab.
B8: ▸ Green cells are editable fields (inputs).
B9: ▸ EBITDA and margins are calculated automatically.
B10: ▸ The Summary tab consolidates the 3 years for presentations to lenders and investors.
B12: Revenue lines:
B13: ▸ Dine-in, Bar, Delivery, Events/Catering.
B15: Expense lines:
B16: ▸ Food Cost, Labor, Rent, Utilities, Marketing, Admin.
B20: ▸ Delivery has its own platform fee line: the % is in row 27 of each year tab.
... B27: Version 2.0 · October 2026 · aichef.pro/en/digital-products/restaurant-financial-plan-templates · info@aichef.pro

Sheet Year 1
A1: Pro Forma P&L — Year 1
A2: AI Chef Pro · aichef.pro — Restaurant Financial Plan Kit Pro
A4: Line item | B4: Jan | C4: Feb | D4: Mar | E4: Apr | F4: May | G4: Jun | H4: Jul | I4: Aug | J4: Sep | K4: Oct | L4: Nov | M4: Dec | N4: YEAR TOTAL
A5: REVENUE
A6: Dine-in (excl. sales tax) | B6: 0 | C6: 0 | D6: 0 | E6: 0 | F6: 0 | G6: 0 | H6: 0 | I6: 0 | J6: 0 | K6: 0 | L6: 0 | M6: 0 | N6: =SUM(B6:M6) -> 0
A7: Bar (excl. sales tax) | B7: 0 | C7: 0 | D7: 0 | E7: 0 | F7: 0 | G7: 0 | H7: 0 | I7: 0 | J7: 0 | K7: 0 | L7: 0 | M7: 0 | N7: =SUM(B7:M7) -> 0
A8: Delivery (excl. sales tax) | B8: 0 | C8: 0 | D8: 0 | E8: 0 | F8: 0 | G8: 0 | H8: 0 | I8: 0 | J8: 0 | K8: 0 | L8: 0 | M8: 0 | N8: =SUM(B8:M8) -> 0
A9: Events / Catering (excl. sales tax) | B9: 0 | C9: 0 | D9: 0 | E9: 0 | F9: 0 | G9: 0 | H9: 0 | I9: 0 | J9: 0 | K9: 0 | L9: 0 | M9: 0 | N9: =SUM(B9:M9) -> 0
A10: TOTAL REVENUE (excl. sales tax) | B10: =SUM(B6:B9) -> 0 | C10: =SUM(C6:C9) -> 0 | D10: =SUM(D6:D9) -> 0 | E10: =SUM(E6:E9) -> 0 | F10: =SUM(F6:F9) -> 0 | G10: =SUM(G6:G9) -> 0 | H10: =SUM(H6:H9) -> 0 | I10: =SUM(I6:I9) -> 0 | ... N10: =SUM(N6:N9) -> 0
A12: EXPENSES
A13: Food cost (raw materials) | B13: 0 | C13: 0 | D13: 0 | E13: 0 | F13: 0 | G13: 0 | H13: 0 | I13: 0 | J13: 0 | K13: 0 | L13: 0 | M13: 0 | N13: =SUM(B13:M13) -> 0
A14: Beverage cost (bar) | B14: 0 | C14: 0 | D14: 0 | E14: 0 | F14: 0 | G14: 0 | H14: 0 | I14: 0 | J14: 0 | K14: 0 | L14: 0 | M14: 0 | N14: =SUM(B14:M14) -> 0
A15: Labor | B15: 0 | C15: 0 | D15: 0 | E15: 0 | F15: 0 | G15: 0 | H15: 0 | I15: 0 | J15: 0 | K15: 0 | L15: 0 | M15: 0 | N15: =SUM(B15:M15) -> 0
A16: Delivery platform fees | B16: =B8*$B$27 -> 0 | C16: =C8*$B$27 -> 0 | D16: =D8*$B$27 -> 0 | E16: =E8*$B$27 -> 0 | F16: =F8*$B$27 -> 0 | G16: =G8*$B$27 -> 0 | H16: =H8*$B$27 -> 0 | I16: =I8*$B$27 -> 0 | ... M16: =M8*$B$27 -> 0 | N16: =SUM(B16:M16) -> 0
A17: Rent | B17: 0 | C17: 0 | D17: 0 | E17: 0 | F17: 0 | G17: 0 | H17: 0 | I17: 0 | J17: 0 | K17: 0 | L17: 0 | M17: 0 | N17: =SUM(B17:M17) -> 0
A18: Utilities | B18: 0 | C18: 0 | D18: 0 | E18: 0 | F18: 0 | G18: 0 | H18: 0 | I18: 0 | J18: 0 | K18: 0 | L18: 0 | M18: 0 | N18: =SUM(B18:M18) -> 0
A19: Marketing | B19: 0 | C19: 0 | D19: 0 | E19: 0 | F19: 0 | G19: 0 | H19: 0 | I19: 0 | J19: 0 | K19: 0 | L19: 0 | M19: 0 | N19: =SUM(B19:M19) -> 0
A20: Admin / Other | B20: 0 | C20: 0 | D20: 0 | E20: 0 | F20: 0 | G20: 0 | H20: 0 | I20: 0 | J20: 0 | K20: 0 | L20: 0 | M20: 0 | N20: =SUM(B20:M20) -> 0
A21: TOTAL EXPENSES | B21: =SUM(B13:B20) -> 0 | C21: =SUM(C13:C20) -> 0 | D21: =SUM(D13:D20) -> 0 | E21: =SUM(E13:E20) -> 0 | F21: =SUM(F13:F20) -> 0 | G21: =SUM(G13:G20) -> 0 | H21: =SUM(H13:H20) -> 0 | I21: =SUM(I13:I20) -> 0 | ... N21: =SUM(N13:N20) -> 0
A23: EBITDA | B23: =B10-B21 -> 0 | C23: =C10-C21 -> 0 | D23: =D10-D21 -> 0 | E23: =E10-E21 -> 0 | F23: =F10-F21 -> 0 | G23: =G10-G21 -> 0 | H23: =H10-H21 -> 0 | I23: =I10-I21 -> 0 | ... N23: =N10-N21 -> 0
A24: EBITDA Margin % | B24: =IF(B10=0,"",B23/B10) | C24: =IF(C10=0,"",C23/C10) | D24: =IF(D10=0,"",D23/D10) | E24: =IF(E10=0,"",E23/E10) | F24: =IF(F10=0,"",F23/F10) | G24: =IF(G10=0,"",G23/G10) | H24: =IF(H10=0,"",H23/H10) | I24: =IF(I10=0,"",I23/I10) | ... N24: =IF(N10=0,"",N23/N10)
A26: ASSUMPTIONS AND NOTES
A27: Delivery platform fee % (on the delivery sales in row 8) | B27: 0.3
A28: Delivery packaging: include it in "Food cost" or in "Admin / Other"; it is not free.
A30: © 2026 AI Chef Pro · aichef.pro

Sheet Year 2
A1: Pro Forma P&L — Year 2
A2: AI Chef Pro · aichef.pro — Restaurant Financial Plan Kit Pro
A4: Line item | B4: Jan | C4: Feb | D4: Mar | E4: Apr | F4: May | G4: Jun | H4: Jul | I4: Aug | J4: Sep | K4: Oct | L4: Nov | M4: Dec | N4: YEAR TOTAL
A5: REVENUE
A6: Dine-in (excl. sales tax) | B6: 0 | C6: 0 | D6: 0 | E6: 0 | F6: 0 | G6: 0 | H6: 0 | I6: 0 | J6: 0 | K6: 0 | L6: 0 | M6: 0 | N6: =SUM(B6:M6) -> 0
A7: Bar (excl. sales tax) | B7: 0 | C7: 0 | D7: 0 | E7: 0 | F7: 0 | G7: 0 | H7: 0 | I7: 0 | J7: 0 | K7: 0 | L7: 0 | M7: 0 | N7: =SUM(B7:M7) -> 0
A8: Delivery (excl. sales tax) | B8: 0 | C8: 0 | D8: 0 | E8: 0 | F8: 0 | G8: 0 | H8: 0 | I8: 0 | J8: 0 | K8: 0 | L8: 0 | M8: 0 | N8: =SUM(B8:M8) -> 0
A9: Events / Catering (excl. sales tax) | B9: 0 | C9: 0 | D9: 0 | E9: 0 | F9: 0 | G9: 0 | H9: 0 | I9: 0 | J9: 0 | K9: 0 | L9: 0 | M9: 0 | N9: =SUM(B9:M9) -> 0
A10: TOTAL REVENUE (excl. sales tax) | B10: =SUM(B6:B9) -> 0 | C10: =SUM(C6:C9) -> 0 | D10: =SUM(D6:D9) -> 0 | E10: =SUM(E6:E9) -> 0 | F10: =SUM(F6:F9) -> 0 | G10: =SUM(G6:G9) -> 0 | H10: =SUM(H6:H9) -> 0 | I10: =SUM(I6:I9) -> 0 | ... N10: =SUM(N6:N9) -> 0
A12: EXPENSES
A13: Food cost (raw materials) | B13: 0 | C13: 0 | D13: 0 | E13: 0 | F13: 0 | G13: 0 | H13: 0 | I13: 0 | J13: 0 | K13: 0 | L13: 0 | M13: 0 | N13: =SUM(B13:M13) -> 0
A14: Beverage cost (bar) | B14: 0 | C14: 0 | D14: 0 | E14: 0 | F14: 0 | G14: 0 | H14: 0 | I14: 0 | J14: 0 | K14: 0 | L14: 0 | M14: 0 | N14: =SUM(B14:M14) -> 0
A15: Labor | B15: 0 | C15: 0 | D15: 0 | E15: 0 | F15: 0 | G15: 0 | H15: 0 | I15: 0 | J15: 0 | K15: 0 | L15: 0 | M15: 0 | N15: =SUM(B15:M15) -> 0
A16: Delivery platform fees | B16: =B8*$B$27 -> 0 | C16: =C8*$B$27 -> 0 | D16: =D8*$B$27 -> 0 | E16: =E8*$B$27 -> 0 | F16: =F8*$B$27 -> 0 | G16: =G8*$B$27 -> 0 | H16: =H8*$B$27 -> 0 | I16: =I8*$B$27 -> 0 | ... M16: =M8*$B$27 -> 0 | N16: =SUM(B16:M16) -> 0
A17: Rent | B17: 0 | C17: 0 | D17: 0 | E17: 0 | F17: 0 | G17: 0 | H17: 0 | I17: 0 | J17: 0 | K17: 0 | L17: 0 | M17: 0 | N17: =SUM(B17:M17) -> 0
A18: Utilities | B18: 0 | C18: 0 | D18: 0 | E18: 0 | F18: 0 | G18: 0 | H18: 0 | I18: 0 | J18: 0 | K18: 0 | L18: 0 | M18: 0 | N18: =SUM(B18:M18) -> 0
A19: Marketing | B19: 0 | C19: 0 | D19: 0 | E19: 0 | F19: 0 | G19: 0 | H19: 0 | I19: 0 | J19: 0 | K19: 0 | L19: 0 | M19: 0 | N19: =SUM(B19:M19) -> 0
A20: Admin / Other | B20: 0 | C20: 0 | D20: 0 | E20: 0 | F20: 0 | G20: 0 | H20: 0 | I20: 0 | J20: 0 | K20: 0 | L20: 0 | M20: 0 | N20: =SUM(B20:M20) -> 0
A21: TOTAL EXPENSES | B21: =SUM(B13:B20) -> 0 | C21: =SUM(C13:C20) -> 0 | D21: =SUM(D13:D20) -> 0 | E21: =SUM(E13:E20) -> 0 | F21: =SUM(F13:F20) -> 0 | G21: =SUM(G13:G20) -> 0 | H21: =SUM(H13:H20) -> 0 | I21: =SUM(I13:I20) -> 0 | ... N21: =SUM(N13:N20) -> 0
A23: EBITDA | B23: =B10-B21 -> 0 | C23: =C10-C21 -> 0 | D23: =D10-D21 -> 0 | E23: =E10-E21 -> 0 | F23: =F10-F21 -> 0 | G23: =G10-G21 -> 0 | H23: =H10-H21 -> 0 | I23: =I10-I21 -> 0 | ... N23: =N10-N21 -> 0
A24: EBITDA Margin % | B24: =IF(B10=0,"",B23/B10) | C24: =IF(C10=0,"",C23/C10) | D24: =IF(D10=0,"",D23/D10) | E24: =IF(E10=0,"",E23/E10) | F24: =IF(F10=0,"",F23/F10) | G24: =IF(G10=0,"",G23/G10) | H24: =IF(H10=0,"",H23/H10) | I24: =IF(I10=0,"",I23/I10) | ... N24: =IF(N10=0,"",N23/N10)
A26: ASSUMPTIONS AND NOTES
A27: Delivery platform fee % (on the delivery sales in row 8) | B27: 0.3
A28: Delivery packaging: include it in "Food cost" or in "Admin / Other"; it is not free.
A30: © 2026 AI Chef Pro · aichef.pro

Sheet Year 3
A1: Pro Forma P&L — Year 3
A2: AI Chef Pro · aichef.pro — Restaurant Financial Plan Kit Pro
A4: Line item | B4: Jan | C4: Feb | D4: Mar | E4: Apr | F4: May | G4: Jun | H4: Jul | I4: Aug | J4: Sep | K4: Oct | L4: Nov | M4: Dec | N4: YEAR TOTAL
A5: REVENUE
A6: Dine-in (excl. sales tax) | B6: 0 | C6: 0 | D6: 0 | E6: 0 | F6: 0 | G6: 0 | H6: 0 | I6: 0 | J6: 0 | K6: 0 | L6: 0 | M6: 0 | N6: =SUM(B6:M6) -> 0
A7: Bar (excl. sales tax) | B7: 0 | C7: 0 | D7: 0 | E7: 0 | F7: 0 | G7: 0 | H7: 0 | I7: 0 | J7: 0 | K7: 0 | L7: 0 | M7: 0 | N7: =SUM(B7:M7) -> 0
A8: Delivery (excl. sales tax) | B8: 0 | C8: 0 | D8: 0 | E8: 0 | F8: 0 | G8: 0 | H8: 0 | I8: 0 | J8: 0 | K8: 0 | L8: 0 | M8: 0 | N8: =SUM(B8:M8) -> 0
A9: Events / Catering (excl. sales tax) | B9: 0 | C9: 0 | D9: 0 | E9: 0 | F9: 0 | G9: 0 | H9: 0 | I9: 0 | J9: 0 | K9: 0 | L9: 0 | M9: 0 | N9: =SUM(B9:M9) -> 0
A10: TOTAL REVENUE (excl. sales tax) | B10: =SUM(B6:B9) -> 0 | C10: =SUM(C6:C9) -> 0 | D10: =SUM(D6:D9) -> 0 | E10: =SUM(E6:E9) -> 0 | F10: =SUM(F6:F9) -> 0 | G10: =SUM(G6:G9) -> 0 | H10: =SUM(H6:H9) -> 0 | I10: =SUM(I6:I9) -> 0 | ... N10: =SUM(N6:N9) -> 0
A12: EXPENSES
A13: Food cost (raw materials) | B13: 0 | C13: 0 | D13: 0 | E13: 0 | F13: 0 | G13: 0 | H13: 0 | I13: 0 | J13: 0 | K13: 0 | L13: 0 | M13: 0 | N13: =SUM(B13:M13) -> 0
A14: Beverage cost (bar) | B14: 0 | C14: 0 | D14: 0 | E14: 0 | F14: 0 | G14: 0 | H14: 0 | I14: 0 | J14: 0 | K14: 0 | L14: 0 | M14: 0 | N14: =SUM(B14:M14) -> 0
A15: Labor | B15: 0 | C15: 0 | D15: 0 | E15: 0 | F15: 0 | G15: 0 | H15: 0 | I15: 0 | J15: 0 | K15: 0 | L15: 0 | M15: 0 | N15: =SUM(B15:M15) -> 0
A16: Delivery platform fees | B16: =B8*$B$27 -> 0 | C16: =C8*$B$27 -> 0 | D16: =D8*$B$27 -> 0 | E16: =E8*$B$27 -> 0 | F16: =F8*$B$27 -> 0 | G16: =G8*$B$27 -> 0 | H16: =H8*$B$27 -> 0 | I16: =I8*$B$27 -> 0 | ... M16: =M8*$B$27 -> 0 | N16: =SUM(B16:M16) -> 0
A17: Rent | B17: 0 | C17: 0 | D17: 0 | E17: 0 | F17: 0 | G17: 0 | H17: 0 | I17: 0 | J17: 0 | K17: 0 | L17: 0 | M17: 0 | N17: =SUM(B17:M17) -> 0
A18: Utilities | B18: 0 | C18: 0 | D18: 0 | E18: 0 | F18: 0 | G18: 0 | H18: 0 | I18: 0 | J18: 0 | K18: 0 | L18: 0 | M18: 0 | N18: =SUM(B18:M18) -> 0
A19: Marketing | B19: 0 | C19: 0 | D19: 0 | E19: 0 | F19: 0 | G19: 0 | H19: 0 | I19: 0 | J19: 0 | K19: 0 | L19: 0 | M19: 0 | N19: =SUM(B19:M19) -> 0
A20: Admin / Other | B20: 0 | C20: 0 | D20: 0 | E20: 0 | F20: 0 | G20: 0 | H20: 0 | I20: 0 | J20: 0 | K20: 0 | L20: 0 | M20: 0 | N20: =SUM(B20:M20) -> 0
A21: TOTAL EXPENSES | B21: =SUM(B13:B20) -> 0 | C21: =SUM(C13:C20) -> 0 | D21: =SUM(D13:D20) -> 0 | E21: =SUM(E13:E20) -> 0 | F21: =SUM(F13:F20) -> 0 | G21: =SUM(G13:G20) -> 0 | H21: =SUM(H13:H20) -> 0 | I21: =SUM(I13:I20) -> 0 | ... N21: =SUM(N13:N20) -> 0
A23: EBITDA | B23: =B10-B21 -> 0 | C23: =C10-C21 -> 0 | D23: =D10-D21 -> 0 | E23: =E10-E21 -> 0 | F23: =F10-F21 -> 0 | G23: =G10-G21 -> 0 | H23: =H10-H21 -> 0 | I23: =I10-I21 -> 0 | ... N23: =N10-N21 -> 0
A24: EBITDA Margin % | B24: =IF(B10=0,"",B23/B10) | C24: =IF(C10=0,"",C23/C10) | D24: =IF(D10=0,"",D23/D10) | E24: =IF(E10=0,"",E23/E10) | F24: =IF(F10=0,"",F23/F10) | G24: =IF(G10=0,"",G23/G10) | H24: =IF(H10=0,"",H23/H10) | I24: =IF(I10=0,"",I23/I10) | ... N24: =IF(N10=0,"",N23/N10)
A26: ASSUMPTIONS AND NOTES
A27: Delivery platform fee % (on the delivery sales in row 8) | B27: 0.3
A28: Delivery packaging: include it in "Food cost" or in "Admin / Other"; it is not free.
A30: © 2026 AI Chef Pro · aichef.pro

Sheet Summary
A1: Executive Summary — 3-Year P&L
A2: AI Chef Pro · aichef.pro — Restaurant Financial Plan Kit Pro
A4: Line item | B4: Year 1 | C4: Year 2 | D4: Year 3 | E4: Growth Y1→Y3 (margin in pts)
A5: Total Revenue (excl. sales tax) | B5: ='Year 1'!N10 -> 0 | C5: ='Year 2'!N10 -> 0 | D5: ='Year 3'!N10 -> 0 | E5: =IFERROR(($D5-$B5)/$B5,"")
A6: Total Expenses | B6: ='Year 1'!N21 -> 0 | C6: ='Year 2'!N21 -> 0 | D6: ='Year 3'!N21 -> 0 | E6: =IFERROR(($D6-$B6)/$B6,"")
A7: EBITDA | B7: ='Year 1'!N23 -> 0 | C7: ='Year 2'!N23 -> 0 | D7: ='Year 3'!N23 -> 0 | E7: =IFERROR(($D7-$B7)/$B7,"")
A8: EBITDA Margin % | B8: =IFERROR($B7/$B5,"") | C8: =IFERROR($C7/$C5,"") | D8: =IFERROR($D7/$D5,"") | E8: =IFERROR($D8-$B8,"")
A12: © 2026 AI Chef Pro · aichef.pro
