Workbook

Sheet Instructions
B2: 02 · Restaurant Break-Even Calculator
B4: AI Chef Pro · aichef.pro — Restaurant Financial Plan Kit Pro
B6: How to use this template:
B7: ▸ "Inputs" holds the OPERATING fixed costs. The loan payment goes separately (row 15): EBITDA is measured before debt service.
B8: ▸ "Break-Even" gives two thresholds: operating (EBITDA = 0) and cash (with the loan payment included), plus the average check needed for your expected covers.
B9: ▸ The "Scenarios" tab shows 3 scenarios (pessimistic, base, optimistic).
B11: Key concepts:
B12: ▸ Fixed costs: rent, fixed labor, insurance, accounting / bookkeeping — they do not change with activity. The loan payment is NOT included: it is financing, not operations.
B13: ▸ Variable Costs (%): food cost, extras, commissions — a share of every sale.
B14: ▸ Contribution Margin = 1 - Variable Cost %.
B16: All figures EXCLUDE sales tax; only file 03 "Cash Flow Forecast" includes it, because it is cash.
B17: To edit a cell that is not green: Review → Unprotect Sheet (there is no password).
... B19: Version 2.0 · October 2026 · aichef.pro/en/digital-products/restaurant-financial-plan-templates · info@aichef.pro

Sheet Inputs
B1: Input Data — Break-Even
B2: AI Chef Pro · aichef.pro — Restaurant Financial Plan Kit Pro
B3: SAMPLE VALUES — replace them with your own
B4: Line item | C4: Value | D4: Notes
B5: MONTHLY FIXED COSTS
B6: Monthly rent | C6: 3000 | D6: per month
B7: Total fixed labor cost (gross wages + employer payroll taxes) | C7: 8800 | D7: per month — ≈ gross wages × 1.10 (more with benefits): the EMPLOYER cost, not gross pay
B8: Insurance | C8: 400 | D8: per month
B9: Utilities (electricity, water, gas) | C9: 1500 | D9: per month
B10: Fixed marketing | C10: 500 | D10: per month
B11: Accounting / Bookkeeping | C11: 300 | D11: per month
B12: The loan payment is NOT an operating fixed cost: it goes in row 15, outside EBITDA.
B13: Other fixed costs | C13: 500 | D13: per month
B14: TOTAL OPERATING FIXED COSTS | C14: =SUM(C6:C11)+C13 -> 15000
B15: Loan payment (debt service) | C15: 800 | D15: Copy it from the amortization schedule: file 07 "Lender & Investor Summary", "Loan Schedule" tab
B16: VARIABLE COSTS
B17: Variable cost % of sales | C17: 0.35 | D17: Food cost + delivery fees + other variable costs (30-40% typical). Does NOT include fixed labor.
B19: AVERAGE CHECK (excl. sales tax)
B20: Average check per guest (excl. sales tax) | C20: 22
B21: Opening days per month | C21: 26
A24: © 2026 AI Chef Pro · aichef.pro

Sheet Break-Even
B1: Break-Even Calculation
B2: AI Chef Pro · aichef.pro — Restaurant Financial Plan Kit Pro
B4: Metric | C4: Result
B5: Total operating fixed costs / month | C5: =Inputs!$C$14 -> 15000
B6: Variable cost % | C6: =Inputs!$C$17 -> 0.35
B7: Contribution margin | C7: =1-Inputs!$C$17 -> 0.65
B8: BREAK-EVEN REVENUE / month (excl. sales tax) | C8: =IFERROR(Inputs!$C$14/(1-Inputs!$C$17),"Check the variable cost % (it cannot be 100%)") -> 23076.923
B9: Break-even revenue / day (excl. sales tax) | C9: =IFERROR($C$8/Inputs!$C$21,"Enter the opening days") -> 887.57396
B10: Covers / day needed | C10: =IFERROR(ROUNDUP($C$9/Inputs!$C$20,0),"Enter the average check") -> 41
B11: Covers / month needed | C11: =IFERROR(ROUNDUP($C$8/Inputs!$C$20,0),"—") -> 1049
B12: Expected covers / day | C12: 55
B13: Average check needed (excl. sales tax) | C13: =IFERROR($C$9/$C$12,"Enter the expected covers/day") -> 16.137708
B15: CASH BREAK-EVEN (includes the loan payment)
B16: Cash break-even revenue / month (excl. sales tax) | C16: =IFERROR((Inputs!$C$14+Inputs!$C$15)/(1-Inputs!$C$17),"Check the variable cost % (it cannot be 100%)") -> 24307.692
B17: Covers / day for cash break-even | C17: =IFERROR(ROUNDUP($C$16/Inputs!$C$21/Inputs!$C$20,0),"Enter the average check") -> 43
A19: CHART HELPER BLOCK — do not edit
A20: Covers / day | B20: Revenue | C20: Total costs | D20: Break-even revenue
A21: =IFERROR(ROUND($C$10*$F21,0),0) -> 10 | B21: =IFERROR($A21*Inputs!$C$20*Inputs!$C$21,0) -> 5720 | C21: =IFERROR(Inputs!$C$14+$B21*Inputs!$C$17,0) -> 17002 | D21: =$C$8 -> 23076.923 | F21: 0.25
A22: =IFERROR(ROUND($C$10*$F22,0),0) -> 21 | B22: =IFERROR($A22*Inputs!$C$20*Inputs!$C$21,0) -> 12012 | C22: =IFERROR(Inputs!$C$14+$B22*Inputs!$C$17,0) -> 19204.2 | D22: =$C$8 -> 23076.923 | F22: 0.5
A23: =IFERROR(ROUND($C$10*$F23,0),0) -> 31 | B23: =IFERROR($A23*Inputs!$C$20*Inputs!$C$21,0) -> 17732 | C23: =IFERROR(Inputs!$C$14+$B23*Inputs!$C$17,0) -> 21206.2 | D23: =$C$8 -> 23076.923 | F23: 0.75
A24: =IFERROR(ROUND($C$10*$F24,0),0) -> 41 | B24: =IFERROR($A24*Inputs!$C$20*Inputs!$C$21,0) -> 23452 | C24: =IFERROR(Inputs!$C$14+$B24*Inputs!$C$17,0) -> 23208.2 | D24: =$C$8 -> 23076.923 | F24: 1
A25: =IFERROR(ROUND($C$10*$F25,0),0) -> 51 | B25: =IFERROR($A25*Inputs!$C$20*Inputs!$C$21,0) -> 29172 | C25: =IFERROR(Inputs!$C$14+$B25*Inputs!$C$17,0) -> 25210.2 | D25: =$C$8 -> 23076.923 | F25: 1.25
A26: =IFERROR(ROUND($C$10*$F26,0),0) -> 62 | B26: =IFERROR($A26*Inputs!$C$20*Inputs!$C$21,0) -> 35464 | C26: =IFERROR(Inputs!$C$14+$B26*Inputs!$C$17,0) -> 27412.4 | D26: =$C$8 -> 23076.923 | F26: 1.5
A27: =IFERROR(ROUND($C$10*$F27,0),0) -> 72 | B27: =IFERROR($A27*Inputs!$C$20*Inputs!$C$21,0) -> 41184 | C27: =IFERROR(Inputs!$C$14+$B27*Inputs!$C$17,0) -> 29414.4 | D27: =$C$8 -> 23076.923 | F27: 1.75
A28: =IFERROR(ROUND($C$10*$F28,0),0) -> 82 | B28: =IFERROR($A28*Inputs!$C$20*Inputs!$C$21,0) -> 46904 | C28: =IFERROR(Inputs!$C$14+$B28*Inputs!$C$17,0) -> 31416.4 | D28: =$C$8 -> 23076.923 | F28: 2
A30: © 2026 AI Chef Pro · aichef.pro

Sheet Scenarios
B1: Scenario Analysis
B3: Metric | C3: Pessimistic | D3: Base | E3: Optimistic
B4: Average check (excl. sales tax) | C4: 18 | D4: 22 | E4: 28
B5: Covers / day | C5: 40 | D5: 55 | E5: 75
B6: Variable cost % (food + fees; does NOT include fixed labor) | C6: 0.4 | D6: 0.35 | E6: 0.3
B7: Operating fixed costs / month (from "Inputs" C14) | C7: =Inputs!$C$14 -> 15000 | D7: =Inputs!$C$14 -> 15000 | E7: =Inputs!$C$14 -> 15000
B9: RESULTS
B10: Monthly revenue (excl. sales tax) | C10: =C4*C5*Inputs!$C$21 -> 18720 | D10: =D4*D5*Inputs!$C$21 -> 31460 | E10: =E4*E5*Inputs!$C$21 -> 54600
B11: Variable Costs | C11: =C10*C6 -> 7488 | D11: =D10*D6 -> 11011 | E11: =E10*E6 -> 16380
B12: Contribution Margin | C12: =C10-C11 -> 11232 | D12: =D10-D11 -> 20449 | E12: =E10-E11 -> 38220
B13: EBITDA | C13: =C12-C7 -> -3768 | D13: =D12-D7 -> 5449 | E13: =E12-E7 -> 23220
B14: Loan payment (debt service) | C14: =Inputs!$C$15 -> 800 | D14: =Inputs!$C$15 -> 800 | E14: =Inputs!$C$15 -> 800
B15: RESULT AFTER DEBT SERVICE | C15: =C13-C14 -> -4568 | D15: =D13-D14 -> 4649 | E15: =E13-E14 -> 22420
B16: EBITDA Margin % | C16: =IF(C10=0,"",C13/C10) -> -0.20128205 | D16: =IF(D10=0,"",D13/D10) -> 0.17320407 | E16: =IF(E10=0,"",E13/E10) -> 0.42527473
B18: The EBITDA in row 13 is BEFORE debt service: it is the one compared with the benchmarks in files 06 and 07.
A20: © 2026 AI Chef Pro · aichef.pro
