Workbook

Sheet Instructions
B2: 03 · Restaurant Cash Flow Forecast (12 Months)
B4: AI Chef Pro · aichef.pro — Restaurant Financial Plan Kit Pro
B6: How to use this template:
B7: ▸ Enter the expected cash receipts and payments month by month.
B8: ▸ Sales tax / VAT is paid once a quarter: the payment row fills itself from the rates in "Assumptions" in April, July and October; January stays as an input because it pays last year's Q4.
B9: ▸ The "Cash Alerts" tab flags in red the months where the balance falls below the safety threshold.
B11: Concepts:
B12: ▸ Receipts = actual cash coming in (sales tax included).
B13: ▸ Payments = actual cash going out (sales tax included).
B14: ▸ Ending Balance = Opening Balance + Receipts - Payments.
B18: ▸ In "Assumptions" you set the share of sales paid by card and its payout delay, the supplier payment terms and the seasonality: your cash flow stops being a wish list.
B20: ▸ The gray block at the bottom ("base data") is not cash: it holds the month's food purchases and accrued employer payroll taxes, which drive supplier payments, next month's payroll tax deposit and the tax rows.
... B25: Version 2.0 · October 2026 · aichef.pro/en/digital-products/restaurant-financial-plan-templates · info@aichef.pro

Sheet Assumptions
B1: Cash Flow Assumptions
B2: AI Chef Pro · aichef.pro — Restaurant Financial Plan Kit Pro
B3: Line item | C3: Value | D3: Notes
B4: % of sales paid by card | C4: 0.8 | D4: Cash comes in the same day; cards arrive with a delay.
B5: Card payout days (D+n) | C5: 2 | D5: How long your POS and card processor take to deposit the money. Typical: D+1 or D+2.
B6: Supplier payment terms (days) | C6: 30 | D6: Whatever you have negotiated. 0 = pay on delivery.
B7: Sales tax / VAT charged on sales (%) | C7: 0.08 | D7: US: your combined state + local rate on meals (8% is the kit's example). UK: 20% VAT.
B8: Recoverable tax on food purchases (%) | C8: 0 | D8: US: 0 (sales tax has no input credit; buy food for resale with a resale certificate). UK: most food is 0%.
B9: Recoverable tax on other expenses (%) | C9: 0 | D9: US: 0. UK (VAT-registered): 20% on most expenses; on rent only if the landlord opted to tax.
B11: SEASONALITY (index by month; 1.00 = typical month)
B12: Month | C12: Index | D12: Suggested sales for the month (incl. sales tax)
B13: Jan | C13: 1 | D13: =$C$26*$C13 -> 0
B14: Feb | C14: 1 | D14: =$C$26*$C14 -> 0
B15: Mar | C15: 1 | D15: =$C$26*$C15 -> 0
B16: Apr | C16: 1 | D16: =$C$26*$C16 -> 0
B17: May | C17: 1 | D17: =$C$26*$C17 -> 0
B18: Jun | C18: 1 | D18: =$C$26*$C18 -> 0
B19: Jul | C19: 1 | D19: =$C$26*$C19 -> 0
B20: Aug | C20: 1 | D20: =$C$26*$C20 -> 0
B21: Sep | C21: 1 | D21: =$C$26*$C21 -> 0
B22: Oct | C22: 1 | D22: =$C$26*$C22 -> 0
B23: Nov | C23: 1 | D23: =$C$26*$C23 -> 0
B24: Dec | C24: 1 | D24: =$C$26*$C24 -> 0
B26: Sales in a typical month (incl. sales tax) | C26: 0 | D26: Type it once and seasonality suggests all twelve months; then copy them into "Monthly Cash Flow".
B28: Quarterly filer: each quarter's tax is paid the month after it ends (April, July, October; January = last year's Q4). Monthly filer? Unprotect the sheet and type each payment. UK VAT: due 1 month and 7 days after your VAT quarter ends.
A31: © 2026 AI Chef Pro · aichef.pro

Sheet Monthly Cash Flow
A1: Cash Flow Forecast — 12 Months
A2: AI Chef Pro · aichef.pro — Restaurant Financial Plan Kit Pro
A3: SAMPLE VALUES — replace them with your own
A4: Line item | B4: Jan | C4: Feb | D4: Mar | E4: Apr | F4: May | G4: Jun | H4: Jul | I4: Aug | J4: Sep | K4: Oct | L4: Nov | M4: Dec
A5: OPENING BALANCE | B5: 15000 | C5: =B29 -> 15000 | D5: =C29 -> 15000 | E5: =D29 -> 15000 | F5: =E29 -> 15000 | G5: =F29 -> 15000 | H5: =G29 -> 15000 | I5: =H29 -> 15000 | J5: =I29 -> 15000 | ... M5: =L29 -> 15000
A6: CASH IN (Receipts)
A7: Dine-in sales (incl. sales tax) | B7: 0 | C7: 0 | D7: 0 | E7: 0 | F7: 0 | G7: 0 | H7: 0 | I7: 0 | J7: 0 | K7: 0 | L7: 0 | M7: 0
A8: Bar sales (incl. sales tax) | B8: 0 | C8: 0 | D8: 0 | E8: 0 | F8: 0 | G8: 0 | H8: 0 | I8: 0 | J8: 0 | K8: 0 | L8: 0 | M8: 0
A9: Delivery sales (incl. sales tax) | B9: 0 | C9: 0 | D9: 0 | E9: 0 | F9: 0 | G9: 0 | H9: 0 | I9: 0 | J9: 0 | K9: 0 | L9: 0 | M9: 0
A10: Events / Catering (incl. sales tax) | B10: 0 | C10: 0 | D10: 0 | E10: 0 | F10: 0 | G10: 0 | H10: 0 | I10: 0 | J10: 0 | K10: 0 | L10: 0 | M10: 0
A11: Other receipts | B11: 0 | C11: 0 | D11: 0 | E11: 0 | F11: 0 | G11: 0 | H11: 0 | I11: 0 | J11: 0 | K11: 0 | L11: 0 | M11: 0
A12: SALES FOR THE MONTH | B12: =SUM(B7:B11) -> 0 | C12: =SUM(C7:C11) -> 0 | D12: =SUM(D7:D11) -> 0 | E12: =SUM(E7:E11) -> 0 | F12: =SUM(F7:F11) -> 0 | G12: =SUM(G7:G11) -> 0 | H12: =SUM(H7:H11) -> 0 | I12: =SUM(I7:I11) -> 0 | ... M12: =SUM(M7:M11) -> 0
A13: Card payouts pending (collected next month) | B13: =IFERROR(B12*Assumptions!$C$4*Assumptions!$C$5/30,0) -> 0 | C13: =IFERROR(C12*Assumptions!$C$4*Assumptions!$C$5/30,0) -> 0 | D13: =IFERROR(D12*Assumptions!$C$4*Assumptions!$C$5/30,0) -> 0 | E13: =IFERROR(E12*Assumptions!$C$4*Assumptions!$C$5/30,0) -> 0 | F13: =IFERROR(F12*Assumptions!$C$4*Assumptions!$C$5/30,0) -> 0 | G13: =IFERROR(G12*Assumptions!$C$4*Assumptions!$C$5/30,0) -> 0 | H13: =IFERROR(H12*Assumptions!$C$4*Assumptions!$C$5/30,0) -> 0 | I13: =IFERROR(I12*Assumptions!$C$4*Assumptions!$C$5/30,0) -> 0 | ... M13: =IFERROR(M12*Assumptions!$C$4*Assumptions!$C$5/30,0) -> 0
A14: TOTAL CASH RECEIVED | B14: =B12-B13 -> 0 | C14: =C12-C13+B13 -> 0 | D14: =D12-D13+C13 -> 0 | E14: =E12-E13+D13 -> 0 | F14: =F12-F13+E13 -> 0 | G14: =G12-G13+F13 -> 0 | H14: =H12-H13+G13 -> 0 | I14: =I12-I13+H13 -> 0 | J14: =J12-J13+I13 -> 0 | ... M14: =M12-M13+L13 -> 0
A15: CASH OUT (Payments)
A16: Supplier payments (per negotiated terms) | B16: =IFERROR(B33*(1-Assumptions!$C$6/30),0) -> 0 | C16: =IFERROR(C33*(1-Assumptions!$C$6/30)+B33*Assumptions!$C$6/30,0) -> 0 | D16: =IFERROR(D33*(1-Assumptions!$C$6/30)+C33*Assumptions!$C$6/30,0) -> 0 | E16: =IFERROR(E33*(1-Assumptions!$C$6/30)+D33*Assumptions!$C$6/30,0) -> 0 | F16: =IFERROR(F33*(1-Assumptions!$C$6/30)+E33*Assumptions!$C$6/30,0) -> 0 | G16: =IFERROR(G33*(1-Assumptions!$C$6/30)+F33*Assumptions!$C$6/30,0) -> 0 | H16: =IFERROR(H33*(1-Assumptions!$C$6/30)+G33*Assumptions!$C$6/30,0) -> 0 | I16: =IFERROR(I33*(1-Assumptions!$C$6/30)+H33*Assumptions!$C$6/30,0) -> 0 | J16: =IFERROR(J33*(1-Assumptions!$C$6/30)+I33*Assumptions!$C$6/30,0) -> 0 | ... M16: =IFERROR(M33*(1-Assumptions!$C$6/30)+L33*Assumptions!$C$6/30,0) -> 0
A17: Payroll (net pay) | B17: 0 | C17: 0 | D17: 0 | E17: 0 | F17: 0 | G17: 0 | H17: 0 | I17: 0 | J17: 0 | K17: 0 | L17: 0 | M17: 0
A18: Employer payroll taxes deposited (last month's) | B18: 0 | C18: =B34 -> 0 | D18: =C34 -> 0 | E18: =D34 -> 0 | F18: =E34 -> 0 | G18: =F34 -> 0 | H18: =G34 -> 0 | I18: =H34 -> 0 | J18: =I34 -> 0 | ... M18: =L34 -> 0
A19: Rent | B19: 0 | C19: 0 | D19: 0 | E19: 0 | F19: 0 | G19: 0 | H19: 0 | I19: 0 | J19: 0 | K19: 0 | L19: 0 | M19: 0
A20: Utilities | B20: 0 | C20: 0 | D20: 0 | E20: 0 | F20: 0 | G20: 0 | H20: 0 | I20: 0 | J20: 0 | K20: 0 | L20: 0 | M20: 0
A21: Marketing | B21: 0 | C21: 0 | D21: 0 | E21: 0 | F21: 0 | G21: 0 | H21: 0 | I21: 0 | J21: 0 | K21: 0 | L21: 0 | M21: 0
A22: Accounting / Admin | B22: 0 | C22: 0 | D22: 0 | E22: 0 | F22: 0 | G22: 0 | H22: 0 | I22: 0 | J22: 0 | K22: 0 | L22: 0 | M22: 0
A23: Loan payment | B23: 0 | C23: 0 | D23: 0 | E23: 0 | F23: 0 | G23: 0 | H23: 0 | I23: 0 | J23: 0 | K23: 0 | L23: 0 | M23: 0
A24: Employee taxes withheld, deposited (income tax + FICA) | B24: 0 | C24: 0 | D24: 0 | E24: 0 | F24: 0 | G24: 0 | H24: 0 | I24: 0 | J24: 0 | K24: 0 | L24: 0 | M24: 0
A25: Sales tax / VAT payment (quarterly) · January = input (last Q4) | B25: 0 | C25: ="" | D25: ="" | E25: =MAX(0,SUM($B$36:$D$36)-SUM($B$37:$D$37)) -> 0 | F25: ="" | G25: ="" | H25: =MAX(0,SUM($E$36:$G$36)-SUM($E$37:$G$37)) -> 0 | I25: ="" | J25: ="" | K25: =MAX(0,SUM($H$36:$J$36)-SUM($H$37:$J$37)) -> 0 | L25: ="" | M25: =""
A26: Delivery platform fees and other payments | B26: 0 | C26: 0 | D26: 0 | E26: 0 | F26: 0 | G26: 0 | H26: 0 | I26: 0 | J26: 0 | K26: 0 | L26: 0 | M26: 0
A27: TOTAL PAYMENTS | B27: =SUM(B16:B26) -> 0 | C27: =SUM(C16:C26) -> 0 | D27: =SUM(D16:D26) -> 0 | E27: =SUM(E16:E26) -> 0 | F27: =SUM(F16:F26) -> 0 | G27: =SUM(G16:G26) -> 0 | H27: =SUM(H16:H26) -> 0 | I27: =SUM(I16:I26) -> 0 | ... M27: =SUM(M16:M26) -> 0
A28: NET CASH FLOW FOR THE MONTH | B28: =B14-B27 -> 0 | C28: =C14-C27 -> 0 | D28: =D14-D27 -> 0 | E28: =E14-E27 -> 0 | F28: =F14-F27 -> 0 | G28: =G14-G27 -> 0 | H28: =H14-H27 -> 0 | I28: =I14-I27 -> 0 | ... M28: =M14-M27 -> 0
A29: ENDING BALANCE | B29: =B5+B28 -> 15000 | C29: =C5+C28 -> 15000 | D29: =D5+D28 -> 15000 | E29: =E5+E28 -> 15000 | F29: =F5+F28 -> 15000 | G29: =G5+G28 -> 15000 | H29: =H5+H28 -> 15000 | I29: =I5+I28 -> 15000 | ... M29: =M5+M28 -> 15000
A31: BASE DATA — not cash, but they feed the rows above
A33: Food purchases for the month (incl. sales tax) | B33: 0 | C33: 0 | D33: 0 | E33: 0 | F33: 0 | G33: 0 | H33: 0 | I33: 0 | J33: 0 | K33: 0 | L33: 0 | M33: 0
A34: Employer payroll taxes accrued this month | B34: 0 | C34: 0 | D34: 0 | E34: 0 | F34: 0 | G34: 0 | H34: 0 | I34: 0 | J34: 0 | K34: 0 | L34: 0 | M34: 0
A36: Sales tax / VAT collected this month | B36: =IFERROR(B12-B12/(1+Assumptions!$C$7),0) -> 0 | C36: =IFERROR(C12-C12/(1+Assumptions!$C$7),0) -> 0 | D36: =IFERROR(D12-D12/(1+Assumptions!$C$7),0) -> 0 | E36: =IFERROR(E12-E12/(1+Assumptions!$C$7),0) -> 0 | F36: =IFERROR(F12-F12/(1+Assumptions!$C$7),0) -> 0 | G36: =IFERROR(G12-G12/(1+Assumptions!$C$7),0) -> 0 | H36: =IFERROR(H12-H12/(1+Assumptions!$C$7),0) -> 0 | I36: =IFERROR(I12-I12/(1+Assumptions!$C$7),0) -> 0 | ... M36: =IFERROR(M12-M12/(1+Assumptions!$C$7),0) -> 0
A37: Recoverable tax paid this month (UK VAT; US: 0) | B37: =IFERROR(B33-B33/(1+Assumptions!$C$8)+(B19+B20+B21+B22)-(B19+B20+B21+B22)/(1+Assumptions!$C$9),0) -> 0 | C37: =IFERROR(C33-C33/(1+Assumptions!$C$8)+(C19+C20+C21+C22)-(C19+C20+C21+C22)/(1+Assumptions!$C$9),0) -> 0 | D37: =IFERROR(D33-D33/(1+Assumptions!$C$8)+(D19+D20+D21+D22)-(D19+D20+D21+D22)/(1+Assumptions!$C$9),0) -> 0 | E37: =IFERROR(E33-E33/(1+Assumptions!$C$8)+(E19+E20+E21+E22)-(E19+E20+E21+E22)/(1+Assumptions!$C$9),0) -> 0 | F37: =IFERROR(F33-F33/(1+Assumptions!$C$8)+(F19+F20+F21+F22)-(F19+F20+F21+F22)/(1+Assumptions!$C$9),0) -> 0 | G37: =IFERROR(G33-G33/(1+Assumptions!$C$8)+(G19+G20+G21+G22)-(G19+G20+G21+G22)/(1+Assumptions!$C$9),0) -> 0 | H37: =IFERROR(H33-H33/(1+Assumptions!$C$8)+(H19+H20+H21+H22)-(H19+H20+H21+H22)/(1+Assumptions!$C$9),0) -> 0 | I37: =IFERROR(I33-I33/(1+Assumptions!$C$8)+(I19+I20+I21+I22)-(I19+I20+I21+I22)/(1+Assumptions!$C$9),0) -> 0 | ... M37: =IFERROR(M33-M33/(1+Assumptions!$C$8)+(M19+M20+M21+M22)-(M19+M20+M21+M22)/(1+Assumptions!$C$9),0) -> 0
A39: Suggested sales by seasonality (for reference) | B39: =Assumptions!$D$13 -> 0 | C39: =Assumptions!$D$14 -> 0 | D39: =Assumptions!$D$15 -> 0 | E39: =Assumptions!$D$16 -> 0 | F39: =Assumptions!$D$17 -> 0 | G39: =Assumptions!$D$18 -> 0 | H39: =Assumptions!$D$19 -> 0 | I39: =Assumptions!$D$20 -> 0 | J39: =Assumptions!$D$21 -> 0 | K39: =Assumptions!$D$22 -> 0 | L39: =Assumptions!$D$23 -> 0 | M39: =Assumptions!$D$24 -> 0
A41: © 2026 AI Chef Pro · aichef.pro

Sheet Cash Alerts
B1: Cash Alerts
B3: Safety threshold: | C3: 5000
B5: Month | C5: Ending Balance | D5: Alert | E5: Threshold
B6: Jan | C6: ='Monthly Cash Flow'!B29 -> 15000 | D6: =IF('Monthly Cash Flow'!B12+'Monthly Cash Flow'!B27=0,"—",IF(C6<$C$3,"⚠️ BELOW MINIMUM","OK")) -> — | E6: =$C$3 -> 5000
B7: Feb | C7: ='Monthly Cash Flow'!C29 -> 15000 | D7: =IF('Monthly Cash Flow'!C12+'Monthly Cash Flow'!C27=0,"—",IF(C7<$C$3,"⚠️ BELOW MINIMUM","OK")) -> — | E7: =$C$3 -> 5000
B8: Mar | C8: ='Monthly Cash Flow'!D29 -> 15000 | D8: =IF('Monthly Cash Flow'!D12+'Monthly Cash Flow'!D27=0,"—",IF(C8<$C$3,"⚠️ BELOW MINIMUM","OK")) -> — | E8: =$C$3 -> 5000
B9: Apr | C9: ='Monthly Cash Flow'!E29 -> 15000 | D9: =IF('Monthly Cash Flow'!E12+'Monthly Cash Flow'!E27=0,"—",IF(C9<$C$3,"⚠️ BELOW MINIMUM","OK")) -> — | E9: =$C$3 -> 5000
B10: May | C10: ='Monthly Cash Flow'!F29 -> 15000 | D10: =IF('Monthly Cash Flow'!F12+'Monthly Cash Flow'!F27=0,"—",IF(C10<$C$3,"⚠️ BELOW MINIMUM","OK")) -> — | E10: =$C$3 -> 5000
B11: Jun | C11: ='Monthly Cash Flow'!G29 -> 15000 | D11: =IF('Monthly Cash Flow'!G12+'Monthly Cash Flow'!G27=0,"—",IF(C11<$C$3,"⚠️ BELOW MINIMUM","OK")) -> — | E11: =$C$3 -> 5000
B12: Jul | C12: ='Monthly Cash Flow'!H29 -> 15000 | D12: =IF('Monthly Cash Flow'!H12+'Monthly Cash Flow'!H27=0,"—",IF(C12<$C$3,"⚠️ BELOW MINIMUM","OK")) -> — | E12: =$C$3 -> 5000
B13: Aug | C13: ='Monthly Cash Flow'!I29 -> 15000 | D13: =IF('Monthly Cash Flow'!I12+'Monthly Cash Flow'!I27=0,"—",IF(C13<$C$3,"⚠️ BELOW MINIMUM","OK")) -> — | E13: =$C$3 -> 5000
B14: Sep | C14: ='Monthly Cash Flow'!J29 -> 15000 | D14: =IF('Monthly Cash Flow'!J12+'Monthly Cash Flow'!J27=0,"—",IF(C14<$C$3,"⚠️ BELOW MINIMUM","OK")) -> — | E14: =$C$3 -> 5000
B15: Oct | C15: ='Monthly Cash Flow'!K29 -> 15000 | D15: =IF('Monthly Cash Flow'!K12+'Monthly Cash Flow'!K27=0,"—",IF(C15<$C$3,"⚠️ BELOW MINIMUM","OK")) -> — | E15: =$C$3 -> 5000
B16: Nov | C16: ='Monthly Cash Flow'!L29 -> 15000 | D16: =IF('Monthly Cash Flow'!L12+'Monthly Cash Flow'!L27=0,"—",IF(C16<$C$3,"⚠️ BELOW MINIMUM","OK")) -> — | E16: =$C$3 -> 5000
B17: Dec | C17: ='Monthly Cash Flow'!M29 -> 15000 | D17: =IF('Monthly Cash Flow'!M12+'Monthly Cash Flow'!M27=0,"—",IF(C17<$C$3,"⚠️ BELOW MINIMUM","OK")) -> — | E17: =$C$3 -> 5000
B19: The "—" status means that month has no receipts or payments yet: the traffic light does not comment on an empty month.
A20: © 2026 AI Chef Pro · aichef.pro
