Workbook

Sheet Instructions
B2: 04 · Restaurant Startup Costs & Capex Budget
B4: AI Chef Pro · aichef.pro — Restaurant Financial Plan Kit Pro
B6: How to use this template:
B7: ▸ Each tab covers one startup cost category.
B8: ▸ Each line has Cost, Recoverable tax % and Tax. US: sales tax is NOT recoverable, so include it in the cost and leave the tax % at 0. UK (VAT-registered): type the net cost and 20%; "Total incl. tax" is the cash you advance.
B9: ▸ Variance is calculated automatically (% over or under budget).
B10: ▸ The Summary tab consolidates all categories.
B12: Categories:
B13: ▸ Build-Out, Kitchen Equipment, Dining Room FF&E, Technology, Licenses.
B17: ▸ Each line has a useful life in years (build-out 10, kitchen equipment 7, furniture 7, technology 5; straight line, book basis): it gives the annual depreciation that file 07 "Lender & Investor Summary" needs. Tax depreciation (MACRS, Section 179, bonus) is a separate calculation for your CPA.
B19: ▸ What is not capex (key money, security deposit, opening inventory, pre-opening payroll, contingency and working capital) goes in the "Other Opening Costs" tab.
B21: To edit a cell that is not green: Review → Unprotect Sheet (there is no password).
... B24: Planning tool, not financial, tax or legal advice. Requirements vary by state and city — check with your accountant and local authorities.

Sheet Build-Out
A1: Startup Costs — Build-Out
A2: AI Chef Pro · aichef.pro — Restaurant Financial Plan Kit Pro
A4: Item | B4: Cost | C4: Recoverable tax % | D4: Tax | E4: Total incl. tax | F4: Actual | G4: Variance % | H4: Useful life (years) | I4: Annual depreciation | J4: Notes
A5: Demolition and strip-out | B5: 0 | C5: 0 | D5: =$B5*$C5 -> 0 | E5: =$B5+$D5 -> 0 | F5: 0 | G5: =IFERROR(($F5-$B5)/$B5,"") | H5: 10 | I5: =IFERROR($B5/$H5,0) -> 0
A6: Masonry and drywall | B6: 0 | C6: 0 | D6: =$B6*$C6 -> 0 | E6: =$B6+$D6 -> 0 | F6: 0 | G6: =IFERROR(($F6-$B6)/$B6,"") | H6: 10 | I6: =IFERROR($B6/$H6,0) -> 0
A7: Plumbing | B7: 0 | C7: 0 | D7: =$B7*$C7 -> 0 | E7: =$B7+$D7 -> 0 | F7: 0 | G7: =IFERROR(($F7-$B7)/$B7,"") | H7: 10 | I7: =IFERROR($B7/$H7,0) -> 0
A8: Electrical | B8: 0 | C8: 0 | D8: =$B8*$C8 -> 0 | E8: =$B8+$D8 -> 0 | F8: 0 | G8: =IFERROR(($F8-$B8)/$B8,"") | H8: 10 | I8: =IFERROR($B8/$H8,0) -> 0
A9: HVAC / Exhaust | B9: 0 | C9: 0 | D9: =$B9*$C9 -> 0 | E9: =$B9+$D9 -> 0 | F9: 0 | G9: =IFERROR(($F9-$B9)/$B9,"") | H9: 10 | I9: =IFERROR($B9/$H9,0) -> 0
A10: Painting and finishes | B10: 0 | C10: 0 | D10: =$B10*$C10 -> 0 | E10: =$B10+$D10 -> 0 | F10: 0 | G10: =IFERROR(($F10-$B10)/$B10,"") | H10: 10 | I10: =IFERROR($B10/$H10,0) -> 0
A11: Flooring | B11: 0 | C11: 0 | D11: =$B11*$C11 -> 0 | E11: =$B11+$D11 -> 0 | F11: 0 | G11: =IFERROR(($F11-$B11)/$B11,"") | H11: 10 | I11: =IFERROR($B11/$H11,0) -> 0
A12: Facade / Signage | B12: 0 | C12: 0 | D12: =$B12*$C12 -> 0 | E12: =$B12+$D12 -> 0 | F12: 0 | G12: =IFERROR(($F12-$B12)/$B12,"") | H12: 10 | I12: =IFERROR($B12/$H12,0) -> 0
A13: Guest restrooms | B13: 0 | C13: 0 | D13: =$B13*$C13 -> 0 | E13: =$B13+$D13 -> 0 | F13: 0 | G13: =IFERROR(($F13-$B13)/$B13,"") | H13: 10 | I13: =IFERROR($B13/$H13,0) -> 0
A14: Staff changing rooms | B14: 0 | C14: 0 | D14: =$B14*$C14 -> 0 | E14: =$B14+$D14 -> 0 | F14: 0 | G14: =IFERROR(($F14-$B14)/$B14,"") | H14: 10 | I14: =IFERROR($B14/$H14,0) -> 0
A15: TOTAL BUILD-OUT | B15: =SUM(B5:B14) -> 0 | D15: =SUM(D5:D14) -> 0 | E15: =SUM(E5:E14) -> 0 | F15: =SUM(F5:F14) -> 0 | G15: =IFERROR(($F15-$B15)/$B15,"") | I15: =SUM(I5:I14) -> 0
A17: © 2026 AI Chef Pro · aichef.pro

Sheet Kitchen Equipment
A1: Startup Costs — Kitchen Equipment
A2: AI Chef Pro · aichef.pro — Restaurant Financial Plan Kit Pro
A4: Item | B4: Cost | C4: Recoverable tax % | D4: Tax | E4: Total incl. tax | F4: Actual | G4: Variance % | H4: Useful life (years) | I4: Annual depreciation | J4: Notes
A5: Commercial range (burners) | B5: 0 | C5: 0 | D5: =$B5*$C5 -> 0 | E5: =$B5+$D5 -> 0 | F5: 0 | G5: =IFERROR(($F5-$B5)/$B5,"") | H5: 7 | I5: =IFERROR($B5/$H5,0) -> 0
A6: Combi oven | B6: 0 | C6: 0 | D6: =$B6*$C6 -> 0 | E6: =$B6+$D6 -> 0 | F6: 0 | G6: =IFERROR(($F6-$B6)/$B6,"") | H6: 7 | I6: =IFERROR($B6/$H6,0) -> 0
A7: Flat-top / Grill | B7: 0 | C7: 0 | D7: =$B7*$C7 -> 0 | E7: =$B7+$D7 -> 0 | F7: 0 | G7: =IFERROR(($F7-$B7)/$B7,"") | H7: 7 | I7: =IFERROR($B7/$H7,0) -> 0
A8: Fryer | B8: 0 | C8: 0 | D8: =$B8*$C8 -> 0 | E8: =$B8+$D8 -> 0 | F8: 0 | G8: =IFERROR(($F8-$B8)/$B8,"") | H8: 7 | I8: =IFERROR($B8/$H8,0) -> 0
A9: Walk-in cooler | B9: 0 | C9: 0 | D9: =$B9*$C9 -> 0 | E9: =$B9+$D9 -> 0 | F9: 0 | G9: =IFERROR(($F9-$B9)/$B9,"") | H9: 7 | I9: =IFERROR($B9/$H9,0) -> 0
A10: Freezer | B10: 0 | C10: 0 | D10: =$B10*$C10 -> 0 | E10: =$B10+$D10 -> 0 | F10: 0 | G10: =IFERROR(($F10-$B10)/$B10,"") | H10: 7 | I10: =IFERROR($B10/$H10,0) -> 0
A11: Stainless steel work table | B11: 0 | C11: 0 | D11: =$B11*$C11 -> 0 | E11: =$B11+$D11 -> 0 | F11: 0 | G11: =IFERROR(($F11-$B11)/$B11,"") | H11: 7 | I11: =IFERROR($B11/$H11,0) -> 0
A12: Commercial dishwasher | B12: 0 | C12: 0 | D12: =$B12*$C12 -> 0 | E12: =$B12+$D12 -> 0 | F12: 0 | G12: =IFERROR(($F12-$B12)/$B12,"") | H12: 7 | I12: =IFERROR($B12/$H12,0) -> 0
A13: Exhaust hood | B13: 0 | C13: 0 | D13: =$B13*$C13 -> 0 | E13: =$B13+$D13 -> 0 | F13: 0 | G13: =IFERROR(($F13-$B13)/$B13,"") | H13: 7 | I13: =IFERROR($B13/$H13,0) -> 0
A14: Small kitchen equipment | B14: 0 | C14: 0 | D14: =$B14*$C14 -> 0 | E14: =$B14+$D14 -> 0 | F14: 0 | G14: =IFERROR(($F14-$B14)/$B14,"") | H14: 7 | I14: =IFERROR($B14/$H14,0) -> 0
A15: Kitchen smallwares and utensils (hotel pans, knives) | B15: 0 | C15: 0 | D15: =$B15*$C15 -> 0 | E15: =$B15+$D15 -> 0 | F15: 0 | G15: =IFERROR(($F15-$B15)/$B15,"") | H15: 7 | I15: =IFERROR($B15/$H15,0) -> 0
A16: Dry storage shelving and beverage cooler | B16: 0 | C16: 0 | D16: =$B16*$C16 -> 0 | E16: =$B16+$D16 -> 0 | F16: 0 | G16: =IFERROR(($F16-$B16)/$B16,"") | H16: 7 | I16: =IFERROR($B16/$H16,0) -> 0
A17: TOTAL KITCHEN EQUIPMENT | B17: =SUM(B5:B16) -> 0 | D17: =SUM(D5:D16) -> 0 | E17: =SUM(E5:E16) -> 0 | F17: =SUM(F5:F16) -> 0 | G17: =IFERROR(($F17-$B17)/$B17,"") | I17: =SUM(I5:I16) -> 0
A19: © 2026 AI Chef Pro · aichef.pro

Sheet Dining Room FF&E
A1: Startup Costs — Dining Room FF&E
A2: AI Chef Pro · aichef.pro — Restaurant Financial Plan Kit Pro
A4: Item | B4: Cost | C4: Recoverable tax % | D4: Tax | E4: Total incl. tax | F4: Actual | G4: Variance % | H4: Useful life (years) | I4: Annual depreciation | J4: Notes
A5: Tables | B5: 0 | C5: 0 | D5: =$B5*$C5 -> 0 | E5: =$B5+$D5 -> 0 | F5: 0 | G5: =IFERROR(($F5-$B5)/$B5,"") | H5: 7 | I5: =IFERROR($B5/$H5,0) -> 0
A6: Chairs | B6: 0 | C6: 0 | D6: =$B6*$C6 -> 0 | E6: =$B6+$D6 -> 0 | F6: 0 | G6: =IFERROR(($F6-$B6)/$B6,"") | H6: 7 | I6: =IFERROR($B6/$H6,0) -> 0
A7: Bar | B7: 0 | C7: 0 | D7: =$B7*$C7 -> 0 | E7: =$B7+$D7 -> 0 | F7: 0 | G7: =IFERROR(($F7-$B7)/$B7,"") | H7: 7 | I7: =IFERROR($B7/$H7,0) -> 0
A8: Bar stools | B8: 0 | C8: 0 | D8: =$B8*$C8 -> 0 | E8: =$B8+$D8 -> 0 | F8: 0 | G8: =IFERROR(($F8-$B8)/$B8,"") | H8: 7 | I8: =IFERROR($B8/$H8,0) -> 0
A9: Shelving / decor | B9: 0 | C9: 0 | D9: =$B9*$C9 -> 0 | E9: =$B9+$D9 -> 0 | F9: 0 | G9: =IFERROR(($F9-$B9)/$B9,"") | H9: 7 | I9: =IFERROR($B9/$H9,0) -> 0
A10: Lighting | B10: 0 | C10: 0 | D10: =$B10*$C10 -> 0 | E10: =$B10+$D10 -> 0 | F10: 0 | G10: =IFERROR(($F10-$B10)/$B10,"") | H10: 7 | I10: =IFERROR($B10/$H10,0) -> 0
A11: Patio (tables + chairs) | B11: 0 | C11: 0 | D11: =$B11*$C11 -> 0 | E11: =$B11+$D11 -> 0 | F11: 0 | G11: =IFERROR(($F11-$B11)/$B11,"") | H11: 7 | I11: =IFERROR($B11/$H11,0) -> 0
A12: Linens (tablecloths, napkins) | B12: 0 | C12: 0 | D12: =$B12*$C12 -> 0 | E12: =$B12+$D12 -> 0 | F12: 0 | G12: =IFERROR(($F12-$B12)/$B12,"") | H12: 7 | I12: =IFERROR($B12/$H12,0) -> 0
A13: Dinnerware, glassware and flatware (with replacement stock) | B13: 0 | C13: 0 | D13: =$B13*$C13 -> 0 | E13: =$B13+$D13 -> 0 | F13: 0 | G13: =IFERROR(($F13-$B13)/$B13,"") | H13: 7 | I13: =IFERROR($B13/$H13,0) -> 0
A14: Uniforms and PPE | B14: 0 | C14: 0 | D14: =$B14*$C14 -> 0 | E14: =$B14+$D14 -> 0 | F14: 0 | G14: =IFERROR(($F14-$B14)/$B14,"") | H14: 7 | I14: =IFERROR($B14/$H14,0) -> 0
A15: TOTAL DINING ROOM FF&E | B15: =SUM(B5:B14) -> 0 | D15: =SUM(D5:D14) -> 0 | E15: =SUM(E5:E14) -> 0 | F15: =SUM(F5:F14) -> 0 | G15: =IFERROR(($F15-$B15)/$B15,"") | I15: =SUM(I5:I14) -> 0
A17: © 2026 AI Chef Pro · aichef.pro

Sheet Technology
A1: Startup Costs — Technology
A2: AI Chef Pro · aichef.pro — Restaurant Financial Plan Kit Pro
A4: Item | B4: Cost | C4: Recoverable tax % | D4: Tax | E4: Total incl. tax | F4: Actual | G4: Variance % | H4: Useful life (years) | I4: Annual depreciation | J4: Notes
A5: POS (hardware + software) | B5: 0 | C5: 0 | D5: =$B5*$C5 -> 0 | E5: =$B5+$D5 -> 0 | F5: 0 | G5: =IFERROR(($F5-$B5)/$B5,"") | H5: 5 | I5: =IFERROR($B5/$H5,0) -> 0
A6: Kitchen ticket printers | B6: 0 | C6: 0 | D6: =$B6*$C6 -> 0 | E6: =$B6+$D6 -> 0 | F6: 0 | G6: =IFERROR(($F6-$B6)/$B6,"") | H6: 5 | I6: =IFERROR($B6/$H6,0) -> 0
A7: Card terminal | B7: 0 | C7: 0 | D7: =$B7*$C7 -> 0 | E7: =$B7+$D7 -> 0 | F7: 0 | G7: =IFERROR(($F7-$B7)/$B7,"") | H7: 5 | I7: =IFERROR($B7/$H7,0) -> 0
A8: Reservation system | B8: 0 | C8: 0 | D8: =$B8*$C8 -> 0 | E8: =$B8+$D8 -> 0 | F8: 0 | G8: =IFERROR(($F8-$B8)/$B8,"") | H8: 5 | I8: =IFERROR($B8/$H8,0) -> 0
A9: Wi-Fi / Network | B9: 0 | C9: 0 | D9: =$B9*$C9 -> 0 | E9: =$B9+$D9 -> 0 | F9: 0 | G9: =IFERROR(($F9-$B9)/$B9,"") | H9: 5 | I9: =IFERROR($B9/$H9,0) -> 0
A10: Screens / Digital signage | B10: 0 | C10: 0 | D10: =$B10*$C10 -> 0 | E10: =$B10+$D10 -> 0 | F10: 0 | G10: =IFERROR(($F10-$B10)/$B10,"") | H10: 5 | I10: =IFERROR($B10/$H10,0) -> 0
A11: Delivery website / app | B11: 0 | C11: 0 | D11: =$B11*$C11 -> 0 | E11: =$B11+$D11 -> 0 | F11: 0 | G11: =IFERROR(($F11-$B11)/$B11,"") | H11: 5 | I11: =IFERROR($B11/$H11,0) -> 0
A12: Security system (cameras) | B12: 0 | C12: 0 | D12: =$B12*$C12 -> 0 | E12: =$B12+$D12 -> 0 | F12: 0 | G12: =IFERROR(($F12-$B12)/$B12,"") | H12: 5 | I12: =IFERROR($B12/$H12,0) -> 0
A13: TOTAL TECHNOLOGY | B13: =SUM(B5:B12) -> 0 | D13: =SUM(D5:D12) -> 0 | E13: =SUM(E5:E12) -> 0 | F13: =SUM(F5:F12) -> 0 | G13: =IFERROR(($F13-$B13)/$B13,"") | I13: =SUM(I5:I12) -> 0
A15: © 2026 AI Chef Pro · aichef.pro

Sheet Licenses & Permits
A1: Startup Costs — Licenses & Permits
A2: AI Chef Pro · aichef.pro — Restaurant Financial Plan Kit Pro
A4: Item | B4: Cost | C4: Recoverable tax % | D4: Tax | E4: Total incl. tax | F4: Actual | G4: Variance % | H4: Useful life (years) | I4: Annual depreciation | J4: Notes
A5: Business license & certificate of occupancy | B5: 0 | C5: 0 | D5: =$B5*$C5 -> 0 | E5: =$B5+$D5 -> 0 | F5: 0 | G5: =IFERROR(($F5-$B5)/$B5,"") | I5: =IFERROR($B5/$H5,0) -> 0
A6: Building permits | B6: 0 | C6: 0 | D6: =$B6*$C6 -> 0 | E6: =$B6+$D6 -> 0 | F6: 0 | G6: =IFERROR(($F6-$B6)/$B6,"") | H6: 10 | I6: =IFERROR($B6/$H6,0) -> 0 | J6: Capitalized with the build-out: same useful life.
A7: Architect / engineer drawings | B7: 0 | C7: 0 | D7: =$B7*$C7 -> 0 | E7: =$B7+$D7 -> 0 | F7: 0 | G7: =IFERROR(($F7-$B7)/$B7,"") | H7: 10 | I7: =IFERROR($B7/$H7,0) -> 0 | J7: Capitalized with the build-out: same useful life.
A8: Health department plan review & permit | B8: 0 | C8: 0 | D8: =$B8*$C8 -> 0 | E8: =$B8+$D8 -> 0 | F8: 0 | G8: =IFERROR(($F8-$B8)/$B8,"") | I8: =IFERROR($B8/$H8,0) -> 0
A9: Fire inspection & occupancy permit | B9: 0 | C9: 0 | D9: =$B9*$C9 -> 0 | E9: =$B9+$D9 -> 0 | F9: 0 | G9: =IFERROR(($F9-$B9)/$B9,"") | I9: =IFERROR($B9/$H9,0) -> 0
A10: Liquor license | B10: 0 | C10: 0 | D10: =$B10*$C10 -> 0 | E10: =$B10+$D10 -> 0 | F10: 0 | G10: =IFERROR(($F10-$B10)/$B10,"") | I10: =IFERROR($B10/$H10,0) -> 0
A11: Sign permit | B11: 0 | C11: 0 | D11: =$B11*$C11 -> 0 | E11: =$B11+$D11 -> 0 | F11: 0 | G11: =IFERROR(($F11-$B11)/$B11,"") | I11: =IFERROR($B11/$H11,0) -> 0
A12: Music licensing (ASCAP, BMI, SESAC) | B12: 0 | C12: 0 | D12: =$B12*$C12 -> 0 | E12: =$B12+$D12 -> 0 | F12: 0 | G12: =IFERROR(($F12-$B12)/$B12,"") | I12: =IFERROR($B12/$H12,0) -> 0
A13: TOTAL LICENSES & PERMITS | B13: =SUM(B5:B12) -> 0 | D13: =SUM(D5:D12) -> 0 | E13: =SUM(E5:E12) -> 0 | F13: =SUM(F5:F12) -> 0 | G13: =IFERROR(($F13-$B13)/$B13,"") | I13: =SUM(I5:I12) -> 0
A15: © 2026 AI Chef Pro · aichef.pro

Sheet Other Opening Costs
A1: Other Opening Costs — what is not capex but still has to be paid
A2: AI Chef Pro · aichef.pro — Restaurant Financial Plan Kit Pro
A4: Line item | B4: Cost | C4: Recoverable tax % | D4: Tax | E4: Total incl. tax | F4: Actual | G4: Variance % | H4: Notes
A5: Key money / business purchase (if any) | B5: 0 | C5: 0 | D5: =$B5*$C5 -> 0 | E5: =$B5+$D5 -> 0 | F5: 0 | G5: =IFERROR(($F5-$B5)/$B5,"")
A6: Security deposit & first rent | B6: 0 | C6: 0 | D6: =$B6*$C6 -> 0 | E6: =$B6+$D6 -> 0 | F6: 0 | G6: =IFERROR(($F6-$B6)/$B6,"") | H6: The deposit is returned when you leave; prepaid rent is not.
A7: Entity formation, legal & filing fees | B7: 0 | C7: 0 | D7: =$B7*$C7 -> 0 | E7: =$B7+$D7 -> 0 | F7: 0 | G7: =IFERROR(($F7-$B7)/$B7,"")
A8: OPENING INVENTORY of pantry and bar | B8: 0 | C8: 0 | D8: =$B8*$C8 -> 0 | E8: =$B8+$D8 -> 0 | F8: 0 | G8: =IFERROR(($F8-$B8)/$B8,"") | H8: Weeks of usage × daily cost of ingredients. In a 60-seat casual restaurant, 2-4 weeks are often 8,000-15,000.
A9: Pre-opening payroll and training | B9: 0 | C9: 0 | D9: =$B9*$C9 -> 0 | E9: =$B9+$D9 -> 0 | F9: 0 | G9: =IFERROR(($F9-$B9)/$B9,"") | H9: The two or three weeks of staff you pay before the first sale.
A10: Launch marketing | B10: 0 | C10: 0 | D10: =$B10*$C10 -> 0 | E10: =$B10+$D10 -> 0 | F10: 0 | G10: =IFERROR(($F10-$B10)/$B10,"")
A11: Insurance (year 1) | B11: 0 | C11: 0 | D11: =$B11*$C11 -> 0 | E11: =$B11+$D11 -> 0 | F11: 0 | G11: =IFERROR(($F11-$B11)/$B11,"") | H11: Prepaid expense, NOT depreciated. It is not capex, and file 02 "Break-Even Calculator" already counts monthly insurance in its "Inputs" tab, so do not count the same premium twice.
A12: Contingency (5-10% of the investment) | B12: 0 | C12: 0 | D12: =$B12*$C12 -> 0 | E12: =$B12+$D12 -> 0 | F12: 0 | G12: =IFERROR(($F12-$B12)/$B12,"") | H12: Usually 5-10% of "TOTAL STARTUP COSTS (CAPEX)" in the "Summary" tab; it is not included in that total.
A13: WORKING CAPITAL (3-6 months of fixed costs) | B13: 0 | C13: 0 | D13: =$B13*$C13 -> 0 | E13: =$B13+$D13 -> 0 | F13: 0 | G13: =IFERROR(($F13-$B13)/$B13,"") | H13: This is the cash cushion that file B09 "Pre-Opening Financial Checklist" asks you to set aside. Guide: monthly fixed costs from file 02 "Break-Even Calculator", "Inputs" tab, cell C14, × 3 to 6.
A14: TOTAL OTHER OPENING COSTS | B14: =SUM(B5:B13) -> 0 | D14: =SUM(D5:D13) -> 0 | E14: =SUM(E5:E13) -> 0 | F14: =SUM(F5:F13) -> 0 | G14: =IFERROR(($F14-$B14)/$B14,"")
A16: None of these items is depreciated: they are expenses for the period or working capital. That is why they have no useful life.
A18: © 2026 AI Chef Pro · aichef.pro

Sheet Summary
A1: Total Startup Costs Summary
A2: AI Chef Pro · aichef.pro — Restaurant Financial Plan Kit Pro
A4: Category | B4: Cost | C4: Tax | D4: Total incl. tax | E4: Actual | F4: Variance % | G4: Annual depreciation
A5: Build-Out | B5: ='Build-Out'!B15 -> 0 | C5: ='Build-Out'!D15 -> 0 | D5: ='Build-Out'!E15 -> 0 | E5: ='Build-Out'!F15 -> 0 | F5: =IFERROR(($E5-$B5)/$B5,"") | G5: ='Build-Out'!I15 -> 0
A6: Kitchen Equipment | B6: ='Kitchen Equipment'!B17 -> 0 | C6: ='Kitchen Equipment'!D17 -> 0 | D6: ='Kitchen Equipment'!E17 -> 0 | E6: ='Kitchen Equipment'!F17 -> 0 | F6: =IFERROR(($E6-$B6)/$B6,"") | G6: ='Kitchen Equipment'!I17 -> 0
A7: Dining Room FF&E | B7: ='Dining Room FF&E'!B15 -> 0 | C7: ='Dining Room FF&E'!D15 -> 0 | D7: ='Dining Room FF&E'!E15 -> 0 | E7: ='Dining Room FF&E'!F15 -> 0 | F7: =IFERROR(($E7-$B7)/$B7,"") | G7: ='Dining Room FF&E'!I15 -> 0
A8: Technology | B8: =Technology!B13 -> 0 | C8: =Technology!D13 -> 0 | D8: =Technology!E13 -> 0 | E8: =Technology!F13 -> 0 | F8: =IFERROR(($E8-$B8)/$B8,"") | G8: =Technology!I13 -> 0
A9: Licenses & Permits | B9: ='Licenses & Permits'!B13 -> 0 | C9: ='Licenses & Permits'!D13 -> 0 | D9: ='Licenses & Permits'!E13 -> 0 | E9: ='Licenses & Permits'!F13 -> 0 | F9: =IFERROR(($E9-$B9)/$B9,"") | G9: ='Licenses & Permits'!I13 -> 0
A10: TOTAL STARTUP COSTS (CAPEX) | B10: =SUM(B5:B9) -> 0 | C10: =SUM(C5:C9) -> 0 | D10: =SUM(D5:D9) -> 0 | E10: =SUM(E5:E9) -> 0 | F10: =IFERROR(($E10-$B10)/$B10,"") | G10: =SUM(G5:G9) -> 0
A11: Other Opening Costs | B11: ='Other Opening Costs'!B14 -> 0 | C11: ='Other Opening Costs'!D14 -> 0 | D11: ='Other Opening Costs'!E14 -> 0 | E11: ='Other Opening Costs'!F14 -> 0 | F11: =IFERROR(($E11-$B11)/$B11,"")
A12: TOTAL OPENING OUTLAY (cost + tax) | B12: =B10+B11 -> 0 | C12: =C10+C11 -> 0 | D12: =D10+D11 -> 0 | E12: =E10+E11 -> 0 | F12: =IFERROR(($E12-$B12)/$B12,"")
A14: Where each figure comes from (how the files connect):
A15: ▸ The "Annual depreciation" in row 10 is the figure you copy into file 07 "Lender & Investor Summary", "Projections" tab, "Depreciation" row.
A16: ▸ The "Tax" in row 12 is recoverable VAT (UK): it comes back on your VAT return, but you pay it FIRST, so the loan has to cover it. US sales tax is not recoverable: it is already inside the cost.
A30: © 2026 AI Chef Pro · aichef.pro
