Workbook

Sheet Instructions
B2: 06 · Restaurant Financial Ratios & KPI Dashboard
B4: AI Chef Pro · aichef.pro — Restaurant Financial Plan Kit Pro
B6: How to use this template:
B7: ▸ Enter your real data in the "Value" column.
B8: ▸ "Food cost — usage" is not the month's invoices: it is opening inventory + purchases - ending inventory. The month you stock up heavily, purchases spike and usage does not.
B9: ▸ The traffic light shows whether each ratio is in the target range (green), acceptable (yellow) or in danger (red).
B11: Key restaurant ratios:
B12: ▸ Food Cost %: target < 28% · danger > 32% (the numbers live in "Benchmarks" F:G).
B13: ▸ Labor Cost %: target < 30% · danger > 35% (the numbers live in "Benchmarks" F:G).
B14: ▸ Prime Cost %: target < 60% · danger > 65% (the numbers live in "Benchmarks" F:G).
B15: ▸ GOP %: target > 20% · danger < 15% (the numbers live in "Benchmarks" F:G).
B19: ▸ RevPASH is measured per SEAT and hour (seating capacity × service hours), not per sq ft. "Service hours" are the hours when guests are seated (e.g. 6 hours/day × 26 days = 156), not the hours the restaurant is open. Sales per sq ft have their own row.
... B24: Version 2.0 · October 2026 · aichef.pro/en/digital-products/restaurant-financial-plan-templates · info@aichef.pro

Sheet Ratios
B1: Financial Ratios Dashboard
B2: AI Chef Pro · aichef.pro — Restaurant Financial Plan Kit Pro
B3: SAMPLE VALUES — replace them with your own
B4: INPUT DATA
B5: Line item | C5: Value | D5: Period
B6: Total sales (excl. sales tax) | C6: 31460 | D6: Monthly
B7: · of which, bar / beverage (excl. sales tax) | C7: 7865 | D7: Monthly
B8: Food cost — usage | C8: =IFERROR($C$33+$C$34-$C$35,0) -> 7078.5 | D8: Calculated
B9: Total operating expenses | C9: =IFERROR($C$8+$C$36+$C$10+$C$37,0) -> 23017.6 | D9: Calculated
B10: Total labor cost | C10: 8808.8 | D10: Monthly
B11: Dining room area (sq ft) | C11: 860
B12: SERVICE hours / month (guests seated) | C12: 156
B13: Number of seats (capacity) | C13: 60
B14: Number of covers served | C14: 1430 | D14: Monthly
B15: CALCULATED RATIOS
B16: Ratio | C16: Your Value | D16: Industry Benchmark | E16: Status | F16: Target
B17: Food Cost % (of food sales) | C17: =IF(($C$6-$C$7)<=0,"Enter sales",$C$8/($C$6-$C$7)) -> 0.3 | D17: =Benchmarks!$D$4 -> 28% - 32% | E17: =IFERROR(IF(ISNUMBER($C17),IF($C17<Benchmarks!$F$4,"✅ Excellent",IF($C17<=Benchmarks!$G$4,"⚠️ Acceptable","🔴 High")),"—"),"—") -> ⚠️ Acceptable | F17: =Benchmarks!$F$4 -> 0.28
B18: Labor Cost % | C18: =IFERROR($C$10/$C$6,"Enter sales") -> 0.28 | D18: =Benchmarks!$D$5 -> 30% - 35% | E18: =IFERROR(IF(ISNUMBER($C18),IF($C18<Benchmarks!$F$5,"✅ Excellent",IF($C18<=Benchmarks!$G$5,"⚠️ Acceptable","🔴 High")),"—"),"—") -> ✅ Excellent | F18: =Benchmarks!$F$5 -> 0.3
B19: Prime Cost % (food + beverage + labor) | C19: =IFERROR(($C$8+$C$36+$C$10)/$C$6,"Enter sales") -> 0.56 | D19: =Benchmarks!$D$6 -> 60% - 65% | E19: =IFERROR(IF(ISNUMBER($C19),IF($C19<Benchmarks!$F$6,"✅ Excellent",IF($C19<=Benchmarks!$G$6,"⚠️ Acceptable","🔴 High")),"—"),"—") -> ✅ Excellent | F19: =Benchmarks!$F$6 -> 0.6
B20: GOP (Gross Operating Profit) % | C20: =IFERROR(($C$6-$C$9)/$C$6,"Enter sales") -> 0.26835346 | D20: =Benchmarks!$D$7 -> 15% - 20% | E20: =IFERROR(IF(ISNUMBER($C20),IF($C20>Benchmarks!$F$7,"✅ Healthy",IF($C20>=Benchmarks!$G$7,"⚠️ Tight","🔴 Danger")),"—"),"—") -> ✅ Healthy | F20: =Benchmarks!$F$7 -> 0.2
B21: Beverage Cost % (of bar sales) | C21: =IFERROR($C$36/$C$7,"Enter bar sales") -> 0.22 | D21: =Benchmarks!$D$12 -> 18% - 24% | E21: =IFERROR(IF(ISNUMBER($C21),IF($C21<Benchmarks!$F$12,"✅ Excellent",IF($C21<=Benchmarks!$G$12,"⚠️ Acceptable","🔴 High")),"—"),"—") -> ⚠️ Acceptable | F21: =Benchmarks!$F$12 -> 0.18
B22: RevPASH (per seat-hour) | C22: =IFERROR($C$6/($C$13*$C$12),"Enter seats and hours") -> 3.3611111 | D22: =Benchmarks!$D$13 -> 3 - 6 | E22: =IFERROR(IF(ISNUMBER($C22),IF($C22>Benchmarks!$F$13,"✅ Healthy",IF($C22>=Benchmarks!$G$13,"⚠️ Tight","🔴 Danger")),"—"),"—") -> ⚠️ Tight | F22: =Benchmarks!$F$13 -> 6
B23: EBITDA % | C23: =IFERROR(($C$6-$C$9-$C$38)/$C$6,"Enter sales") -> 0.17299428 | D23: =Benchmarks!$D$10 -> 10% - 15% | E23: =IFERROR(IF(ISNUMBER($C23),IF($C23>Benchmarks!$F$10,"✅ Healthy",IF($C23>=Benchmarks!$G$10,"⚠️ Tight","🔴 Danger")),"—"),"—") -> ✅ Healthy | F23: =Benchmarks!$F$10 -> 0.15
B24: Cost per cover / Average check | C24: =IFERROR($C$28/$C$29,"Enter covers") -> 0.73164654 | D24: =Benchmarks!$D$11 -> 80% - 85% | E24: =IFERROR(IF(ISNUMBER($C24),IF($C24<Benchmarks!$F$11,"✅ Excellent",IF($C24<=Benchmarks!$G$11,"⚠️ Acceptable","🔴 High")),"—"),"—") -> ✅ Excellent | F24: =Benchmarks!$F$11 -> 0.8
B25: Gross margin % | C25: =IFERROR(($C$6-$C$8-$C$36)/$C$6,"Enter sales") -> 0.72 | D25: =Benchmarks!$D$14 -> 65% - 70% | E25: =IFERROR(IF(ISNUMBER($C25),IF($C25>Benchmarks!$F$14,"✅ Healthy",IF($C25>=Benchmarks!$G$14,"⚠️ Tight","🔴 Danger")),"—"),"—") -> ✅ Healthy | F25: =Benchmarks!$F$14 -> 0.7
B27: OTHER INDICATORS
B28: Cost per cover | C28: =IFERROR($C$9/$C$14,"Enter covers") -> 16.096224
B29: Average check (excl. sales tax) | C29: =IFERROR($C$6/$C$14,"Enter covers") -> 22
B30: Sales per sq ft (excl. sales tax) | C30: =IFERROR($C$6/$C$11,"Enter the dining room sq ft") -> 36.581395
B32: SUPPLEMENTARY DATA (inventory and expense breakdown)
B33: Opening food inventory | C33: 0 | D33: What was in the pantry and walk-in on day 1.
B34: Food purchases for the period | C34: 7078.5 | D34: Food invoices for the period.
B35: Ending food inventory | C35: 0 | D35: Usage = opening inventory + purchases - ending inventory. The month of the big order, purchases spike and usage does NOT.
B36: Beverage cost — usage | C36: 1730.3 | D36: Bar and cellar, separate from food.
B37: Other operating expenses | C37: 5400 | D37: Utilities, marketing, accounting / bookkeeping, delivery platform fees… EXCLUDING rent and depreciation (they go separately, per USALI). With this value the sample EBITDA comes out at 17.3%, the same one shown in file 02 "Break-Even Calculator" and file B08 "What-If Scenario Simulator".
B38: Rent | C38: 3000 | D38: Below GOP: under USALI it is a fixed charge.
B40: GOP is measured BEFORE rent and depreciation (USALI convention): that is why rent has its own line and EBITDA % is calculated separately.
A50: © 2026 AI Chef Pro · aichef.pro

Sheet Benchmarks
B1: Restaurant Industry Benchmarks
B3: Ratio | C3: Target | D3: Acceptable | E3: Danger | F3: Target (no.) | G3: Limit (no.) | H3: Direction
B4: Food Cost % | C4: < 28% | D4: 28% - 32% | E4: > 32% | F4: 0.28 | G4: 0.32 | H4: lower is better
B5: Labor Cost % | C5: < 30% | D5: 30% - 35% | E5: > 35% | F5: 0.3 | G5: 0.35 | H5: lower is better
B6: Prime Cost % | C6: < 60% | D6: 60% - 65% | E6: > 65% | F6: 0.6 | G6: 0.65 | H6: lower is better
B7: GOP % | C7: > 20% | D7: 15% - 20% | E7: < 15% | F7: 0.2 | G7: 0.15 | H7: higher is better
B8: Occupancy (rent) / Sales | C8: < 6% | D8: 6% - 10% | E8: > 10% | F8: 0.06 | G8: 0.1 | H8: lower is better
B9: Marketing / Sales | C9: < 5% | D9: 5% - 8% | E9: > 8% | F9: 0.05 | G9: 0.08 | H9: lower is better
B10: EBITDA % | C10: > 15% | D10: 10% - 15% | E10: < 10% | F10: 0.15 | G10: 0.1 | H10: higher is better
B11: Cost per cover / Check | C11: < 80% | D11: 80% - 85% | E11: > 85% | F11: 0.8 | G11: 0.85 | H11: lower is better
B12: Beverage Cost % | C12: < 18% | D12: 18% - 24% | E12: > 24% | F12: 0.18 | G12: 0.24 | H12: lower is better
B13: RevPASH (per seat-hour) | C13: > 6 | D13: 3 - 6 | E13: < 3 | F13: 6 | G13: 3 | H13: higher is better
B14: Gross margin % | C14: > 70% | D14: 65% - 70% | E14: < 65% | F14: 0.7 | G14: 0.65 | H14: higher is better
B17: The "Target (no.)" and "Limit (no.)" columns are the kit's ONLY source of thresholds: the traffic light in the "Ratios" tab reads them. The text columns on the left are a reading guide: if you edit the numbers, update them too.
A20: © 2026 AI Chef Pro · aichef.pro
