Workbook

Sheet Instructions
B2: 07 · Restaurant Loan Proposal: Lender & Investor Summary
B4: AI Chef Pro · aichef.pro — Restaurant Financial Plan Kit Pro
B6: How to use this template:
B7: ▸ Fill in each tab with your project's data.
B8: ▸ The professional format is ready to hand directly to your lender or investors.
B9: ▸ IRR, NPV and payback period calculate themselves in "Projections" on the project's FREE CASH FLOW (before debt and interest) and the investment from "Executive Summary"; the ability to repay the loan is measured by the DSCR in "Ratios". The discount rate is yours (cell C27).
B10: ▸ Includes a section for collateral and personal guarantees.
B12: Tabs:
B13: ▸ Executive Summary: key project data.
B14: ▸ Projections: P&L + summary cash flow, 5 years.
B15: ▸ Loan Schedule: loan amortization schedule. It feeds the interest in the P&L, the loan payment in the DSCR and the loan payment line of the cash flow in file 03 "Cash Flow Forecast".
B16: ▸ Ratios: solvency and profitability indicators. DSCR compares the project's year 1 free cash flow ("Projections", row 17) with that year's debt service ("Loan Schedule"): it measures whether the business covers the payment.
... B25: Version 2.0 · October 2026 · aichef.pro/en/digital-products/restaurant-financial-plan-templates · info@aichef.pro

Sheet Executive Summary
B1: Executive Summary of the Project
B2: AI Chef Pro · aichef.pro — Restaurant Financial Plan Kit Pro
B3: SAMPLE VALUES — replace them with your own
B4: PROJECT DETAILS
B5: Restaurant name
B6: Concept / Cuisine type
B7: Location
B8: Total area (sq ft)
B9: Seating capacity (covers)
B10: Planned opening date
B12: KEY FINANCIAL DATA
B13: Total investment required
B14: Owner's equity contributed
B15: Financing requested | C15: ='Loan Schedule'!$C$4 -> 0
B16: Requested repayment term (years) | C16: =IF('Loan Schedule'!$C$4=0,"—",'Loan Schedule'!$C$6) -> —
B17: Projected Year 1 revenue (excl. sales tax) | C17: =Projections!$B$4 -> 0
B18: Projected Year 1 EBITDA | C18: =Projections!$B$11 -> 0
B19: Estimated payback period | C19: =Projections!$B$26 -> —
B21: FOUNDING TEAM
B22: Owner / founder name
B23: Restaurant industry experience
B24: Education and training
B25: Other partners
A27: © 2026 AI Chef Pro · aichef.pro
B29: Financing, term, revenue, EBITDA and payback period are calculated from "Loan Schedule" and "Projections": you never type them twice.

Sheet Projections
A1: Financial Projections — 5 Years
A3: Line item | B3: Year 1 | C3: Year 2 | D3: Year 3 | E3: Year 4 | F3: Year 5
A4: Revenue (excl. sales tax) | B4: 0 | C4: 0 | D4: 0 | E4: 0 | F4: 0
A5: Food cost | B5: 0 | C5: 0 | D5: 0 | E5: 0 | F5: 0
A6: Beverage cost | B6: 0 | C6: 0 | D6: 0 | E6: 0 | F6: 0
A7: Labor | B7: 0 | C7: 0 | D7: 0 | E7: 0 | F7: 0
A8: Delivery platform fees | B8: 0 | C8: 0 | D8: 0 | E8: 0 | F8: 0
A9: Other operating expenses | B9: 0 | C9: 0 | D9: 0 | E9: 0 | F9: 0
A10: TOTAL EXPENSES | B10: =SUM(B5:B9) -> 0 | C10: =SUM(C5:C9) -> 0 | D10: =SUM(D5:D9) -> 0 | E10: =SUM(E5:E9) -> 0 | F10: =SUM(F5:F9) -> 0
A11: EBITDA | B11: =B4-B10 -> 0 | C11: =C4-C10 -> 0 | D11: =D4-D10 -> 0 | E11: =E4-E10 -> 0 | F11: =F4-F10 -> 0
A12: Depreciation | B12: 0 | C12: 0 | D12: 0 | E12: 0 | F12: 0 | G12: Copy it from file 04 "Startup Costs & Capex Budget", "Summary" tab: "Annual depreciation" column, "TOTAL STARTUP COSTS (CAPEX)" row.
A13: Interest on debt | B13: ='Loan Schedule'!$D$12 -> 0 | C13: ='Loan Schedule'!$D$13 -> 0 | D13: ='Loan Schedule'!$D$14 -> 0 | E13: ='Loan Schedule'!$D$15 -> 0 | F13: ='Loan Schedule'!$D$16 -> 0
A14: EBT (Earnings Before Tax) | B14: =B11-B12-B13 -> 0 | C14: =C11-C12-C13 -> 0 | D14: =D11-D12-D13 -> 0 | E14: =E11-E12-E13 -> 0 | F14: =F11-F12-F13 -> 0
A15: Income tax | B15: =IF(B14>0,B14*$C$29,0) -> 0 | C15: =IF(C14>0,C14*$C$29,0) -> 0 | D15: =IF(D14>0,D14*$C$29,0) -> 0 | E15: =IF(E14>0,E14*$C$29,0) -> 0 | F15: =IF(F14>0,F14*$C$29,0) -> 0
A16: NET INCOME | B16: =B14-B15 -> 0 | C16: =C14-C15 -> 0 | D16: =D14-D15 -> 0 | E16: =E14-E15 -> 0 | F16: =F14-F15 -> 0
A17: Project free cash flow (no debt) | B17: =B11-MAX(0,(B11-B12)*$C$29) -> 0 | C17: =C11-MAX(0,(C11-C12)*$C$29) -> 0 | D17: =D11-MAX(0,(D11-D12)*$C$29) -> 0 | E17: =E11-MAX(0,(E11-E12)*$C$29) -> 0 | F17: =F11-MAX(0,(F11-F12)*$C$29) -> 0 | G17: EBITDA minus income tax computed WITHOUT interest. This row feeds the IRR, NPV and payback below.
A18: OPERATING CASH FLOW | B18: =B16+B12 -> 0 | C18: =C16+C12 -> 0 | D18: =D16+D12 -> 0 | E18: =E16+E12 -> 0 | F18: =F16+F12 -> 0
A20: PROJECT CASH FLOWS AND RETURN METRICS
A21: Line item | B21: Year 0 | C21: Year 1 | D21: Year 2 | E21: Year 3 | F21: Year 4 | G21: Year 5
A22: Project cash flow | B22: =-'Executive Summary'!$C$13 -> 0 | C22: =B17 -> 0 | D22: =C17 -> 0 | E22: =D17 -> 0 | F22: =E17 -> 0 | G22: =F17 -> 0
A23: Cumulative cash flow | B23: =B22 -> 0 | C23: =$B23+C22 -> 0 | D23: =$C23+D22 -> 0 | E23: =$D23+E22 -> 0 | F23: =$E23+F22 -> 0 | G23: =$F23+G22 -> 0
A24: Project IRR (unlevered) | B24: =IFERROR(IRR($B$22:$G$22),"—") -> —
A25: Project NPV | B25: =IFERROR(NPV($C$27,$C$22:$G$22)+$B$22,"—") -> 0
A26: Project payback period (years) | B26: =IFERROR(IF($G$23<0,"Not paid back within 5 years",COUNTIF($B$23:$G$23,"<0")-1+(-INDEX($B$23:$G$23,COUNTIF($B$23:$G$23,"<0")))/INDEX($B$22:$G$22,COUNTIF($B$23:$G$23,"<0")+1)),"—") -> —
A27: Annual discount rate (%) — used by the NPV | C27: 0.08
A28: It is the return expected by whoever puts in the money. 8% is the kit's starting point; raise it if your risk is higher.
A29: Effective income tax rate (%) | C29: 0.25
A30: US C corp: 21% federal + your state's rate (25% is the kit's example). LLC, S corp or sole proprietor (pass-through): 0 here, the tax is paid on the owners' returns. UK: corporation tax 19% to 25%.
A32: The year 0 investment comes from "Executive Summary": this report goes to a third party, so no sample data comes preloaded looking like real data.
A33: IRR/NPV/payback period are calculated on the project's free cash flow, with no debt or interest: they measure whether the business sustains itself. The ability to repay the loan is measured by the DSCR in the "Ratios" tab.
A45: © 2026 AI Chef Pro · aichef.pro

Sheet Loan Schedule
B1: Loan Schedule — Amortization Schedule
B2: AI Chef Pro · aichef.pro — Restaurant Financial Plan Kit Pro
B3: LOAN DETAILS
B4: Amount requested | C4: 0 | D4: The amount you ask the lender for.
B5: Nominal annual interest rate (%) | C5: 0.1 | D5: Nominal rate, not APR. (example: change it)
B6: Term (years) | C6: 10 | D6: TOTAL term, interest-only period included. SBA 7(a): up to 10 years for equipment and working capital. (example: change it)
B7: Interest-only period (years) | C7: 0 | D7: Initial years in which you pay interest only; afterwards the payment is calculated over the remaining term.
B8: ANNUAL PAYMENT | C8: =IF(($C$6-$C$7)<=0,"The interest-only period must be shorter than the term",IFERROR($C$4*$C$5/(1-(1+$C$5)^(-($C$6-$C$7))),0)) -> 0 | D8: Level annual payment (standard amortization) over the term left after the interest-only period, which must be SHORTER than the term: otherwise no year is left to repay the principal and you get a warning here instead.
B10: AMORTIZATION SCHEDULE (years 1-5)
A11: Year | B11: Opening balance | C11: Annual payment | D11: Interest | E11: Principal repaid | F11: Ending balance
A12: 1 | B12: =$C$4 -> 0 | C12: =IF($C$6<=$C$7,"—",IF($A12>$C$6,0,IF($A12<=$C$7,$B12*$C$5,$C$8))) -> 0 | D12: =IF($A12>$C$6,0,$B12*$C$5) -> 0 | E12: =IF($C$6<=$C$7,0,IF($A12>$C$6,0,$C12-$D12)) -> 0 | F12: =$B12-$E12 -> 0
A13: 2 | B13: =$F$12 -> 0 | C13: =IF($C$6<=$C$7,"—",IF($A13>$C$6,0,IF($A13<=$C$7,$B13*$C$5,$C$8))) -> 0 | D13: =IF($A13>$C$6,0,$B13*$C$5) -> 0 | E13: =IF($C$6<=$C$7,0,IF($A13>$C$6,0,$C13-$D13)) -> 0 | F13: =$B13-$E13 -> 0
A14: 3 | B14: =$F$13 -> 0 | C14: =IF($C$6<=$C$7,"—",IF($A14>$C$6,0,IF($A14<=$C$7,$B14*$C$5,$C$8))) -> 0 | D14: =IF($A14>$C$6,0,$B14*$C$5) -> 0 | E14: =IF($C$6<=$C$7,0,IF($A14>$C$6,0,$C14-$D14)) -> 0 | F14: =$B14-$E14 -> 0
A15: 4 | B15: =$F$14 -> 0 | C15: =IF($C$6<=$C$7,"—",IF($A15>$C$6,0,IF($A15<=$C$7,$B15*$C$5,$C$8))) -> 0 | D15: =IF($A15>$C$6,0,$B15*$C$5) -> 0 | E15: =IF($C$6<=$C$7,0,IF($A15>$C$6,0,$C15-$D15)) -> 0 | F15: =$B15-$E15 -> 0
A16: 5 | B16: =$F$15 -> 0 | C16: =IF($C$6<=$C$7,"—",IF($A16>$C$6,0,IF($A16<=$C$7,$B16*$C$5,$C$8))) -> 0 | D16: =IF($A16>$C$6,0,$B16*$C$5) -> 0 | E16: =IF($C$6<=$C$7,0,IF($A16>$C$6,0,$C16-$D16)) -> 0 | F16: =$B16-$E16 -> 0
B18: The payment in column C is the one copied to file 03 "Cash Flow Forecast", "Monthly Cash Flow" tab, row 23 (divided by 12), and the one that divides the DSCR in the "Ratios" tab.
B19: The interest in column D feeds the "Interest on debt" row of "Projections": do not type it twice.
B20: With an interest-only period, "Principal repaid" shows 0 in the first years and the balance does not go down: that is how an interest-only start really works.
A22: © 2026 AI Chef Pro · aichef.pro

Sheet Ratios
B1: Solvency and Profitability Ratios
B3: Ratio | C3: Value | D3: Lender benchmark | E3: Status | F3: Target (no.) | G3: Limit (no.) | H3: Direction
B4: Debt-to-capital ratio | C4: =IFERROR($C$16/($C$16+$C$15),"Enter debt and equity") -> Enter debt and equity | D4: < 60% | E4: =IFERROR(IF(ISNUMBER($C4),IF($C4<=$F$4,"✅",IF($C4<=$G$4,"⚠️","🔴")),"—"),"—") -> — | F4: 0.6 | G4: 0.7 | H4: lower is better
B5: Debt service coverage (DSCR) | C5: =IFERROR(Projections!$B$17/'Loan Schedule'!$C$12,"Enter the loan") -> Enter the loan | D5: > 1.25x | E5: =IFERROR(IF(ISNUMBER($C5),IF($C5>=$F$5,"✅",IF($C5>=$G$5,"⚠️","🔴")),"—"),"—") -> — | F5: 1.25 | G5: 1.15 | H5: higher is better
B6: Current ratio | C6: =IFERROR($C$13/$C$14,"Enter the balance sheet") -> Enter the balance sheet | D6: > 1.0x | E6: =IFERROR(IF(ISNUMBER($C6),IF($C6>=$F$6,"✅",IF($C6>=$G$6,"⚠️","🔴")),"—"),"—") -> — | F6: 1 | G6: 0.9 | H6: higher is better
B7: EBITDA margin (EBITDA / sales) | C7: =IFERROR(Projections!$B$11/Projections!$B$4,"Enter revenue") -> Enter revenue | D7: > 15% | E7: =IFERROR(IF(ISNUMBER($C7),IF($C7>=$F$7,"✅",IF($C7>=$G$7,"⚠️","🔴")),"—"),"—") -> — | F7: 0.15 | G7: 0.1 | H7: higher is better
B8: ROI (Return on Investment) | C8: =IFERROR(Projections!$B$16/$C$17,"Enter the investment") -> Enter the investment | D8: > 10% | E8: =IFERROR(IF(ISNUMBER($C8),IF($C8>=$F$8,"✅",IF($C8>=$G$8,"⚠️","🔴")),"—"),"—") -> — | F8: 0.1 | G8: 0.05 | H8: higher is better
B9: Owner's equity / Investment | C9: =IFERROR($C$15/$C$17,"Enter the investment") -> Enter the investment | D9: > 30% | E9: =IFERROR(IF(ISNUMBER($C9),IF($C9>=$F$9,"✅",IF($C9>=$G$9,"⚠️","🔴")),"—"),"—") -> — | F9: 0.3 | G9: 0.1 | H9: higher is better
B10: Debt / EBITDA | C10: =IFERROR($C$16/Projections!$B$11,"Enter EBITDA") -> Enter EBITDA | D10: < 3.5x | E10: =IFERROR(IF(ISNUMBER($C10),IF($C10<=$F$10,"✅",IF($C10<=$G$10,"⚠️","🔴")),"—"),"—") -> — | F10: 3.5 | G10: 4.5 | H10: lower is better
B12: BALANCE SHEET AND DEBT DATA
B13: Current assets | C13: 0
B14: Current liabilities | C14: 0
B15: Owner's equity | C15: 0
B16: Outstanding debt | C16: 0
B17: Total project investment | C17: ='Executive Summary'!$C$13 -> 0
B20: The EBITDA margin uses the SAME thresholds as file 06 "KPI & Ratios Dashboard" (target > 15%, tight 10-15%), so the same restaurant gets the same result in both files.
B21: DSCR divides the project's year 1 FREE CASH FLOW ("Projections", row 17: EBITDA minus income tax, computed before interest) by that same year's debt service ("Loan Schedule", column "Annual payment", year 1). The numerator is taken BEFORE debt on purpose: if you subtracted interest from it, you would be counting it twice.
A24: © 2026 AI Chef Pro · aichef.pro

Sheet Collateral
B1: Collateral and Guarantees Offered
B3: Collateral Type | C3: Value | D3: Description
B4: Personal guarantee (SBA: owners of 20%+) | C4: 0
B5: Mortgage on the premises (if owned) | C5: 0
B6: Pledged deposits / cash collateral | C6: 0
B7: Blanket lien on business assets (UCC-1) | C7: 0
B8: Assignment of life insurance (SBA lenders) | C8: 0
B9: Additional deposit | C9: 0
B10: TOTAL COLLATERAL | C10: =SUM(C4:C9) -> 0
A13: © 2026 AI Chef Pro · aichef.pro
