Workbook

Sheet Instructions
B2: BONUS 08 · What-If Scenario Simulator
B4: AI Chef Pro · aichef.pro — Restaurant Financial Plan Kit Pro
B6: How to use this template:
B7: ▸ Change the Average check, Covers / day and Food Cost values in the input area.
B8: ▸ The P&L recalculates instantly for each scenario.
B9: ▸ Compare 3 scenarios side by side: Pessimistic, Base, Optimistic.
B11: Ideal for:
B12: ▸ Building contingency plans.
B13: ▸ Negotiating with investors or partners.
B14: ▸ Testing the impact of price increases or menu changes.
B16: All figures EXCLUDE sales tax; only file 03 "Cash Flow Forecast" includes it, because it is cash.
B17: To edit a cell that is not green: Review → Unprotect Sheet (there is no password).
... B19: Version 2.0 · October 2026 · aichef.pro/en/digital-products/restaurant-financial-plan-templates · info@aichef.pro

Sheet Simulator
A1: Scenario Simulator — What If
A2: AI Chef Pro · aichef.pro — Restaurant Financial Plan Kit Pro
A3: SAMPLE VALUES — replace them with your own
A4: Variable / Result | B4: Pessimistic | C4: Base | D4: Optimistic
A5: INPUT VARIABLES
A6: Average check (excl. sales tax) | B6: 18 | C6: 22 | D6: 28
A7: Covers / day | B7: 40 | C7: 55 | D7: 75
A8: Opening days / month | B8: 25 | C8: 26 | D8: 27
A9: Variable cost % (food + delivery platform fees) | B9: 0.4 | C9: 0.35 | D9: 0.3
A10: Labor Cost % | B10: 0.32 | C10: 0.28 | D10: 0.25
A11: Monthly fixed costs EXCLUDING labor and EXCLUDING the loan payment (rent, utilities, insurance, marketing, accounting / bookkeeping, other) | B11: 6500 | C11: 6200 | D11: 5900
A12: If you copy the fixed costs from file 02 "Break-Even Calculator", SUBTRACT payroll and the loan payment first: labor already enters above as a % of sales, and EBITDA is measured before debt service.
A13: SIMULATED MONTHLY P&L
A14: Monthly revenue (excl. sales tax) | B14: =B6*B7*B8 -> 18000 | C14: =C6*C7*C8 -> 31460 | D14: =D6*D7*D8 -> 56700
A15: Food Cost | B15: =B14*B9 -> 7200 | C15: =C14*C9 -> 11011 | D15: =D14*D9 -> 17010
A16: Labor Cost | B16: =B14*B10 -> 5760 | C16: =C14*C10 -> 8808.8 | D16: =D14*D10 -> 14175
A17: Fixed costs | B17: =B11 -> 6500 | C17: =C11 -> 6200 | D17: =D11 -> 5900
A18: TOTAL EXPENSES | B18: =B15+B16+B17 -> 19460 | C18: =C15+C16+C17 -> 26019.8 | D18: =D15+D16+D17 -> 37085
A19: MONTHLY EBITDA | B19: =B14-B18 -> -1460 | C19: =C14-C18 -> 5440.2 | D19: =D14-D18 -> 19615
A20: EBITDA Margin % | B20: =IF(B14=0,"",B19/B14) -> -0.081111111 | C20: =IF(C14=0,"",C19/C14) -> 0.17292435 | D20: =IF(D14=0,"",D19/D14) -> 0.34594356
A21: ANNUAL EBITDA | B21: =B19*12 -> -17520 | C21: =C19*12 -> 65282.4 | D21: =D19*12 -> 235380
A22: Common base with file 02 "Break-Even Calculator": same average check (22), same covers/day (55), same days (26), same variable cost % (35%) and same fixed costs excluding labor (6,200). The base EBITDA matches: about 17% of sales in both files.
A24: © 2026 AI Chef Pro · aichef.pro

Sheet Comparison
B1: Scenario Comparison — Annual Summary
B3: Metric | C3: Pessimistic | D3: Base | E3: Optimistic
B4: Annual revenue (excl. sales tax) | C4: =Simulator!B14*12 -> 216000 | D4: =Simulator!C14*12 -> 377520 | E4: =Simulator!D14*12 -> 680400
B5: Annual Food Cost | C5: =Simulator!B15*12 -> 86400 | D5: =Simulator!C15*12 -> 132132 | E5: =Simulator!D15*12 -> 204120
B6: Annual Labor Cost | C6: =Simulator!B16*12 -> 69120 | D6: =Simulator!C16*12 -> 105705.6 | E6: =Simulator!D16*12 -> 170100
B7: Annual EBITDA | C7: =Simulator!B21 -> -17520 | D7: =Simulator!C21 -> 65282.4 | E7: =Simulator!D21 -> 235380
B8: EBITDA Margin % | C8: =Simulator!B20 -> -0.081111111 | D8: =Simulator!C20 -> 0.17292435 | E8: =Simulator!D20 -> 0.34594356
A11: © 2026 AI Chef Pro · aichef.pro
