Workbook

Sheet Instrucciones
A1: Carta de Apertura y Escandallo del Obrador de Bombonería
A2: AI Chef Pro · aichef.pro — Cómo Montar una Chocolatería
A3: Para qué sirve: decidir qué vendes, a cuánto, cómo lo puedes llamar y si la caja te gana o te cuesta dinero.
A5: Instrucciones de uso
A6: 1. Hoja «Parámetros». Empieza por el bloque de personal de obrador: el coste de la hora de obrador NO es un dato del sector y no se teclea, se calcula con el bruto de tu convenio, las pagas, la jornada de cada persona y la Seguridad Social a cargo de la empresa. Justo debajo está el bloque del PRECIO DE COBERTURA, que viene del libro 3 y que es la celda más crítica de todo el paquete, y la tabla de precios de compra: es la única tabla donde se tocan los precios, y de ella beben las 42 líneas de las fórmulas de relleno.
A7: 2. Hoja «Denominaciones y Mínimos Legales». Dos capas, y no son lo mismo. La capa (a) la calcula el libro solo, con los gramos que tú metes en el escandallo: el porcentaje de chocolate sobre el PESO TOTAL de la pieza, con el relleno dentro. La capa (b) son tres celdas verdes por cobertura -materia seca total de cacao, manteca de cacao y materia seca desgrasada- que tienes que COPIAR de la ficha técnica de tu proveedor: la bolsa sólo trae el total, y la norma trabaja con las tres.
A8: 3. Hoja «Escandallo por Molde y Tanda». Arriba, las fórmulas de relleno: una línea por ingrediente, con la cantidad que entra en un kilo. Abajo, una fila por referencia con los gramos de chocolate y los gramos de relleno por pieza. El coste de materia sale solo. Las cajas no tienen escandallo propio: se componen de sus bombones.
A9: 4. Hoja «Merma de Templado y Recortes». Dos tasas por referencia, y son distintas a propósito: el chocolate limpio que recortas vuelve a la cuba y no se pierde; el que lleva ganache o fruta va a residuo. La hoja te dice cuántos kilos al año vuelven, cuántos se van y cuánto te cuesta eso.
A10: 5. Hoja «Coste Hora y Mano de Obra». Piezas por molde, moldes por tanda y minutos de la tanda. De ahí salen el coste de mano de obra por pieza, el coste total, el food cost, el margen en euros y el precio que te pide tu propia regla de margen. Es la hoja que enseña a dejar de regalar el trabajo del obrador.
A11: 6. Hoja «Unidad vs Caja». Escribe cuántos bombones de cada tipo lleva cada caja. El libro compara el precio de la caja con la suma de sus unidades sueltas y te dice si la caja te gana o te cuesta dinero. Y aquí sí entra la mano de obra de los bombones de dentro: una caja no cuesta sólo lo que cuesta montarla.
A12: 7. Hoja «Mix y Ticket Medio». Reparte el 100 % de tus unidades entre las 28 referencias, y otra vez para julio y agosto, que no se vende lo mismo. De ahí sale tu ticket medio, que no se copia de ningún estudio porque no existe un ticket medio publicado de chocolatería.
A13: 8. Hoja «Decisión de Surtido». Cruza margen y rotación y te dice qué mantener, a qué revisarle el precio y qué retirar. Repásala a los tres meses de abrir, con ventas reales, y otra vez al cambiar de temporada.
... A33: Versión 1.0 · septiembre 2026 · aichef.pro/guia-chocolateria-obrador · info@aichef.pro

Sheet Parámetros
A1: Parámetros
A2: AI Chef Pro · aichef.pro — Cómo Montar una Chocolatería
A3: Todo lo que el resto de hojas da por sabido vive aquí. Ninguna fórmula de este libro lleva un número dentro.
A5: Personal de obrador y coste de la hora (se CALCULA, no se teclea)
A6: Perfil (nombre literal del Kit de Tareas Chocolatería) | B6: Jornada (1,0 = completa) | C6: Grupo del convenio | D6: Bruto mensual del grupo (EUR) | E6: Bruto anual con pagas y jornada (EUR) | F6: Coste de empresa con Seguridad Social (EUR) | G6: Horas productivas al año | H6: Nota
A7: Encargado | B7: 1 | C7: 2 - Dirección, jefes y encargados | D7: 1427.89 | E7: =D7*'Parámetros'!$B$11*B7 -> 21418.35 | F7: =E7*(1+'Parámetros'!$B$12) -> 28486.406 | G7: ='Parámetros'!$B$13*B7*'Parámetros'!$B$14 -> 1513 | H7: Turno partido (08:00-13:00 y 17:00-20:00). Tabla salarial de Madrid, marcada EJEMPLO: sustitúyela por la de TU convenio.
A8: Chocolatero | B8: 1 | C8: 3 - Personal especialista | D8: 1376.91 | E8: =D8*'Parámetros'!$B$11*B8 -> 20653.65 | F8: =E8*(1+'Parámetros'!$B$12) -> 27469.355 | G8: ='Parámetros'!$B$13*B8*'Parámetros'!$B$14 -> 1513 | H8: Turno mañana (07:00-15:00). Tabla salarial de Madrid, marcada EJEMPLO: sustitúyela por la de TU convenio.
A9: TOTAL del obrador | E9: =SUM(E7:E8) -> 42072 | F9: =SUM(F7:F8) -> 55955.76 | G9: =SUM(G7:G8) -> 3026
A11: Pagas del convenio al año | B11: 15 | C11: pagas | D11: CHN-65b | E11: El convenio de Madrid paga 15, no 14: cambia el coste mes a mes.
A12: Seguridad Social a cargo de la empresa | B12: 0.33 | C12: sobre bruto | D12: motor.PARAMETROS | E12: Cotización empresarial aproximada sobre el bruto: contingencias comunes, desempleo, FOGASA y formación. Ajústala a tus contratos.
A13: Horas anuales de contrato a jornada completa | B13: 1780 | C13: horas/año | D13: supuesto | E13: 40 horas por 52 semanas son 2.080, menos 30 días naturales de vacaciones y los festivos del calendario laboral.
A14: Parte de la jornada que se pasa a pie de mesa | B14: 0.85 | C14: sobre la jornada | D14: supuesto | E14: El resto es recepción, limpieza, formación y reuniones. Repartir el coste entre las horas de contrato en vez de entre las productivas abarata la hora de obrador y sale un margen que no existe.
A15: COSTE DE LA HORA DE OBRADOR | B15: =IFERROR(F9/G9,"") -> 18.491659 | C15: EUR/hora productiva | D15: calculado | E15: Coste de empresa de las personas de obrador entre sus horas PRODUCTIVAS. Del bruto al coste de empresa hay un 33 %, y es el salto que más sorprende. No es el bruto ni el bruto con Seguridad Social.
A17: IVA por familia (regla 3 de la SPEC)
A18: IVA del chocolate (entrega de un bien) | B18: 0.1 | C18: sobre base | D18: CHN-71 | E18: El chocolate va al 10 % POR EXCLUSIÓN, no porque un precepto lo nombre: la lista del 4 % es cerrada y tiene siete letras, y el chocolate no está en ninguna ni entre las dos exclusiones del 10 %.
A19: IVA del chocolate a la taza servido en sala | B19: 0.1 | C19: sobre base | D19: CHN-71c | E19: Servirlo en sala es prestación de servicio de hostelería, no entrega de un bien: va al 10 % por el art. 91.Uno.2.2.º. Si mañana cambia uno de los dos tipos, el libro no se toca: se cambia aquí.
A21: La regla del margen, que es UNA SOLA
A22: Food cost objetivo (coste de materia sobre PVP) | B22: 0.3 | C22: sobre PVP sin IVA | D22: supuesto | E22: SUPUESTO declarado: no existe dato público de food cost de bombonería. Es el ÚNICO de los dos números que se teclea.
A23: Margen bruto objetivo (se DERIVA del anterior) | B23: =1-'Parámetros'!$B$22 -> 0.7 | C23: sobre PVP sin IVA | D23: calculado | E23: Margen bruto y food cost son la misma regla dicha dos veces. Publicarlos como dos reglas independientes es un error de método: se pueden poner incoherentes y nadie se entera.
A25: Precio de cobertura EN BASE IMPONIBLE: trae aquí la cifra de sensibilidad-al-precio-del-cacao.xlsx!Coste de Cobertura!G7 (negra; G8/G9/G10 para origen/leche/blanca en la fila de cada una, columna de base imponible, nunca la de base con IVA) | H25: Cruce 4 <- 3 de la SPEC: celda verde con su valor por defecto declarado y fila de CUADRE. NO hay fórmula entre ficheros.
A26: Cobertura | B26: Precio en BASE IMPONIBLE traído del libro 3 (EUR/kg) | C26: Precio que publica hoy el libro 3 (EUR/kg) | D26: Desviación | E26: Base de IVA de la fuente, y nota | F26: Celda exacta del libro 3
A27: Cobertura de chocolate negro (marca, 54,5 % de cacao) | B27: 22.7455 | C27: 22.7455 | D27: =IFERROR(ABS(B27-C27)/C27,"") -> 0 | E27: Base de la fuente: con IVA. LA CELDA MAS CRITICA DEL PAQUETE. Base CON IVA declarada por la ficha (`CHS-28a`): el libro 3 la publica en las dos bases y lo que viaja al 4 y al 7 es la base imponible. Las tres magnitudes de arriba son SUPUESTO: pidesela a tu proveedor, la bolsa solo trae el total. | F27: Coste de Cobertura!G7 (cacao del 55 al 70 % según el kit)
A28: Cobertura de chocolate de origen (70 % de cacao) | B28: 37.48 | C28: 37.48 | D28: =IFERROR(ABS(B28-C28)/C28,"") -> 0 | E28: Base de la fuente: no declarada. Factor 1,5 frente a la de marca, y es la decisión de posicionamiento mas cara del negocio (decisión 5 del bonus 2). La pagina no declara si el precio lleva IVA: se trata como base imponible y se marca. | F28: Coste de Cobertura!G8 (cacao del 55 al 70 % según el kit)
A29: Cobertura de chocolate con leche (38 % de cacao) | B29: 19.5 | C29: 19.5 | D29: =IFERROR(ABS(B29-C29)/C29,"") -> 0 | E29: Base de la fuente: sin IVA. SUPUESTO declarado: no hay precio verificado de cobertura con leche en el research. Celda verde con valor por defecto (regla 2 de §2.3: ninguna celda verde vacia). | F29: Coste de Cobertura!G9 (cacao del 35 al 40 % según el kit)
A30: Cobertura de chocolate blanco (30 % de cacao) | B30: 21 | C30: 21 | D30: =IFERROR(ABS(B30-C30)/C30,"") -> 0 | E30: Base de la fuente: sin IVA. SUPUESTO declarado. Ojo al chocolate blanco: NO lleva materia seca desgrasada de cacao, y por eso el art. 6.d) del RD 1055/2003 NO le obliga a la mención «cacao: X % mínimo» (`CHN-07`). | F30: Coste de Cobertura!G10 (cacao del 28 al 33 % según el kit)
A31: CUADRE: lo que has traído frente a lo que publica el libro 3 | B31: =MAX(D27:D30) -> 0 | C31: desviación máxima | D31: =IF(NOT(ISNUMBER(B31)),"",IF(B31<='Parámetros'!$B$40,"CUADRA","REVISA: lo que has traído no es lo que publica el libro 3")) -> CUADRA | E31: Si el libro 3 cambia de escenario de precio, cambian las dos columnas. Esta fila existe para que no se quede una sola.
A33: Volumen, packaging y umbrales
A34: Clientes al día en velocidad de crucero | B34: 67 | C34: clientes/día | D34: supuesto | E34: NO es un dato del sector: no existe ticket medio publicado de chocolatería. Mídelo con tu TPV en dos semanas.
A35: Piezas por ticket | B35: 1.4 | C35: piezas/ticket | D35: supuesto | E35: En bombonería es BAJO porque la unidad de venta real es la caja: quien entra a por un regalo se lleva UNA caja, no ocho bombones.
A36: Días de apertura al año | B36: 304 | C36: días | D36: supuesto | E36: 6 días por semana x 52 semanas = 312, menos 8 días de cierre por festivos = 304. En agosto la TIENDA NO CIERRA: lo que para es el obrador (D36, y el literal del kit dice «la tienda abre para el turista aunque el obrador pare»). Una bombonería de menos de 300 m² tiene libertad horaria por el art. 5.2 de la Ley 1/2004, no por el 5.1 (`CHN-77`).
A37: Piezas vendidas al día | B37: =IFERROR('Parámetros'!$B$34*'Parámetros'!$B$35,"") -> 93.8 | C37: piezas/día | D37: calculado | E37: Clientes al día por piezas por ticket.
A38: Piezas vendidas al año | B38: =IFERROR('Parámetros'!$B$37*'Parámetros'!$B$36,"") -> 28515.2 | C38: piezas/año | D38: calculado | E38: Es el volumen con el que la hoja de merma pasa de euros por pieza a euros al año, y el que reparte el mix en unidades.
A39: Packaging sobre el coste de la pieza | B39: 0.12 | C39: sobre el coste | D39: supuesto | E39: En bombonería pesa más que en pastelería: en las campañas de regalo la caja ES el producto. Es lo que separa el food cost de escandallo del food cost servido.
A40: Tolerancia de las filas de CUADRE | B40: 0.02 | C40: desviación | D40: supuesto | E40: Por encima de esta desviación, la fila de CUADRE avisa de que lo que has traído de otro libro ya no es lo que aquel publica.
A41: Food cost por encima del cual la hoja avisa | B41: 0.35 | C41: sobre PVP | D41: supuesto | E41: Criterio de la casa, no del sector. Una referencia por encima no es necesariamente mala: puede ser la que trae gente. Pero tiene que ser una decisión, no un descuido.
A42: Rotación mínima para no revisar una referencia | B42: 2 | C42: % del mix | D42: supuesto | E42: Por debajo de este peso en el mix, la referencia entra en la decisión de surtido aunque tenga buen margen: ocupa molde, cámara y cabeza.
A43: Merma NO recuperable por encima de la cual avisa | B43: 0.05 | C43: sobre la tanda | D43: supuesto | E43: La recuperable no dispara nada: vuelve a la cuba. La que se tira, sí.
A44: Margen mínimo por pieza | B44: 0.9 | C44: EUR/pieza | D44: supuesto | E44: Umbral de la decisión de surtido. Es el margen en EUROS, no el porcentaje: un 70 % sobre una pieza de 0,40 EUR no paga el alquiler.
A46: Precios de compra: la ÚNICA tabla donde se tocan los precios
A47: Ingrediente | B47: Precio de compra SIN IVA (EUR) | C47: Unidad de compra | D47: De dónde sale | E47: Nota
A48: Almendra marcona repelada | B48: 12.4 | C48: kg | D48: supuesto | E48: SUPUESTO declarado: el research no verificó ningún precio de materia prima de relleno. Ponlo de tu albarán.
A49: Almidón de maíz | B49: 2.1 | C49: kg | D49: supuesto | E49: SUPUESTO declarado: el research no verificó ningún precio de materia prima de relleno. Ponlo de tu albarán.
A50: Avellana tostada | B50: 13.9 | C50: kg | D50: supuesto | E50: SUPUESTO declarado: el research no verificó ningún precio de materia prima de relleno. Ponlo de tu albarán.
A51: Azucar | B51: 1.15 | C51: kg | D51: supuesto | E51: SUPUESTO declarado: el research no verificó ningún precio de materia prima de relleno. Ponlo de tu albarán.
A52: Barquillo triturado | B52: 7.6 | C52: kg | D52: supuesto | E52: SUPUESTO declarado: el research no verificó ningún precio de materia prima de relleno. Ponlo de tu albarán.
A53: Cacao en polvo desgrasado | B53: 11.5 | C53: kg | D53: supuesto | E53: SUPUESTO declarado: el research no verificó ningún precio de materia prima de relleno. Ponlo de tu albarán.
A54: Cobertura blanca | B54: =B30 -> 21 | C54: kg | D54: supuesto | E54: Un concepto, una fuente: el precio de esta cobertura vive en el bloque de arriba, que es el que trae la cifra del libro 3. No se teclea dos veces.
A55: Cobertura con leche | B55: =B29 -> 19.5 | C55: kg | D55: supuesto | E55: Un concepto, una fuente: el precio de esta cobertura vive en el bloque de arriba, que es el que trae la cifra del libro 3. No se teclea dos veces.
A56: Cobertura de origen | B56: =B28 -> 37.48 | C56: kg | D56: CHS-28c | E56: Un concepto, una fuente: el precio de esta cobertura vive en el bloque de arriba, que es el que trae la cifra del libro 3. No se teclea dos veces.
A57: Cobertura negra | B57: =B27 -> 22.7455 | C57: kg | D57: CHS-28a | E57: Un concepto, una fuente: el precio de esta cobertura vive en el bloque de arriba, que es el que trae la cifra del libro 3. No se teclea dos veces.
A58: Glucosa | B58: 3.4 | C58: kg | D58: supuesto | E58: SUPUESTO declarado: el research no verificó ningún precio de materia prima de relleno. Ponlo de tu albarán.
A59: Leche en polvo desnatada | B59: 6.4 | C59: kg | D59: supuesto | E59: SUPUESTO declarado: el research no verificó ningún precio de materia prima de relleno. Ponlo de tu albarán.
A60: Manteca de cacao | B60: 18.6 | C60: kg | D60: supuesto | E60: SUPUESTO declarado: el research no verificó ningún precio de materia prima de relleno. Ponlo de tu albarán.
A61: Mantequilla | B61: 9.8 | C61: kg | D61: supuesto | E61: SUPUESTO declarado: el research no verificó ningún precio de materia prima de relleno. Ponlo de tu albarán.
A62: Naranja confitada | B62: 9.2 | C62: kg | D62: supuesto | E62: SUPUESTO declarado: el research no verificó ningún precio de materia prima de relleno. Ponlo de tu albarán.
A63: Nata 35 % MG UHT | B63: 3.1 | C63: L | D63: supuesto | E63: SUPUESTO declarado: el research no verificó ningún precio de materia prima de relleno. Ponlo de tu albarán.
A64: Nata 35 % MG fresca | B64: 4.2 | C64: L | D64: supuesto | E64: SUPUESTO declarado: el research no verificó ningún precio de materia prima de relleno. Ponlo de tu albarán.
A65: Pasta de sésamo | B65: 8.9 | C65: kg | D65: supuesto | E65: SUPUESTO declarado: el research no verificó ningún precio de materia prima de relleno. Ponlo de tu albarán.
A66: Pasta pura de avellana | B66: 22.5 | C66: kg | D66: supuesto | E66: SUPUESTO declarado: el research no verificó ningún precio de materia prima de relleno. Ponlo de tu albarán.
A67: Praline de avellana 50 % | B67: 14.8 | C67: kg | D67: supuesto | E67: SUPUESTO declarado: el research no verificó ningún precio de materia prima de relleno. Ponlo de tu albarán.
A68: Praline de cacahuete 50 % | B68: 9.6 | C68: kg | D68: supuesto | E68: SUPUESTO declarado: el research no verificó ningún precio de materia prima de relleno. Ponlo de tu albarán.
A69: Ron anejo | B69: 16 | C69: L | D69: supuesto | E69: SUPUESTO declarado: el research no verificó ningún precio de materia prima de relleno. Ponlo de tu albarán.
... A73: Yema de huevo pasteurizada | B73: 4.6 | C73: L | D73: supuesto | E73: SUPUESTO declarado: el research no verificó ningún precio de materia prima de relleno. Ponlo de tu albarán.
A75: Versión 1.0 · septiembre 2026 · aichef.pro/guia-chocolateria-obrador · info@aichef.pro

Sheet Denominaciones y Mínimos
A1: Denominaciones y Mínimos Legales
A2: AI Chef Pro · aichef.pro — Cómo Montar una Chocolatería
A3: Capa (a): lo que el escandallo SÍ calcula -el 25 % sobre el PESO TOTAL, relleno incluido-. Capa (b): las tres magnitudes que se COPIAN de la ficha técnica del proveedor, porque la bolsa no las trae.
A5: Capa (a): el mínimo que sale de tus propios gramajes
A6: Id | B6: Referencia | C6: Familia | D6: Denominación legal | E6: Fuente verificada | F6: Mínimo aplicable | G6: ¿Obliga la mención «cacao: X % mínimo»? | H6: Vía de despacho | I6: Gramos de chocolate | J6: Gramos de relleno o materia añadida | K6: Peso total de la pieza (g) | L6: Chocolate sobre el PESO TOTAL | M6: ¿Le aplica el 25 %? | N6: Veredicto | O6: Nota
A7: BC1 | B7: Bombón de ganache de chocolate negro 70 % | C7: Bombones de colección | D7: Bombón de chocolate | E7: CHN-03 | F7: 25 % de chocolate sobre el peso TOTAL | G7: No | H7: a granel | I7: ='Escandallo por Molde y Tanda'!E70 -> 5.5 | J7: ='Escandallo por Molde y Tanda'!F70 -> 6.5 | K7: ='Escandallo por Molde y Tanda'!G70 -> 12 | L7: =IFERROR(I7/K7,"") -> 0.45833333 | M7: Sí | N7: =IF(M7="No","No aplica: su mínimo es el de su denominación",IF(NOT(ISNUMBER(L7)),"",IF(L7>=$B$38,"CUMPLE el 25 % sobre el peso total","NO CUMPLE: no puede llamarse así"))) -> CUMPLE el 25 % sobre el peso total | O7: La referencia que mas margen deja y la que antes caduca. Con 5,5 g de chocolate sobre 12 g de pieza, el chocolate es el 45,8 % del peso total: cumple el 25 % del ap. 1.13 con holgura. En julio y agosto baja a un tercio de su mix: es la primera que sale del catálogo de verano (literal del kit para junio: «menos ganache fresca»).
A8: BC2 | B8: Bombón de ganache de leche y vainilla | C8: Bombones de colección | D8: Bombón de chocolate | E8: CHN-03 | F8: 25 % de chocolate sobre el peso TOTAL | G8: No | H8: a granel | I8: ='Escandallo por Molde y Tanda'!E71 -> 5.5 | J8: ='Escandallo por Molde y Tanda'!F71 -> 6.5 | K8: ='Escandallo por Molde y Tanda'!G71 -> 12 | L8: =IFERROR(I8/K8,"") -> 0.45833333 | M8: Sí | N8: =IF(M8="No","No aplica: su mínimo es el de su denominación",IF(NOT(ISNUMBER(L8)),"",IF(L8>=$B$38,"CUMPLE el 25 % sobre el peso total","NO CUMPLE: no puede llamarse así"))) -> CUMPLE el 25 % sobre el peso total | O8: Misma pieza que BC1 con otra formulación: nata UHT y sorbitol. El kit le da 4-8 semanas frente a los 10-15 días de BC1. Es LA decisión de modelo de negocio del producto, y el libro 5 la cuantifica en euros de merma por caducidad al año.
A9: BC3 | B9: Bombón de praliné de avellana | C9: Bombones de colección | D9: Bombón de chocolate (praliné) | E9: CHN-03 + CHN-82 | F9: 25 % de chocolate sobre el peso TOTAL | G9: No | H9: a granel | I9: ='Escandallo por Molde y Tanda'!E72 -> 5 | J9: ='Escandallo por Molde y Tanda'!F72 -> 7 | K9: ='Escandallo por Molde y Tanda'!G72 -> 12 | L9: =IFERROR(I9/K9,"") -> 0.41666667 | M9: Sí | N9: =IF(M9="No","No aplica: su mínimo es el de su denominación",IF(NOT(ISNUMBER(L9)),"",IF(L9>=$B$38,"CUMPLE el 25 % sobre el peso total","NO CUMPLE: no puede llamarse así"))) -> CUMPLE el 25 % sobre el peso total | O9: «Praline» SI significa algo legalmente: es la denominación de venta europea del bombón de chocolate (`CHN-82`), con el mismo mínimo del 25 %. Escribir lo contrario esta prohibido (§5.1, prohibición 7).
A10: BC4 | B10: Bombón de gianduja de avellana | C10: Bombones de colección | D10: Bombón de chocolate | E10: CHN-03 | F10: 25 % de chocolate sobre el peso TOTAL | G10: No | H10: a granel | I10: ='Escandallo por Molde y Tanda'!E73 -> 5 | J10: ='Escandallo por Molde y Tanda'!F73 -> 7 | K10: ='Escandallo por Molde y Tanda'!G73 -> 12 | L10: =IFERROR(I10/K10,"") -> 0.41666667 | M10: Sí | N10: =IF(M10="No","No aplica: su mínimo es el de su denominación",IF(NOT(ISNUMBER(L10)),"",IF(L10>=$B$38,"CUMPLE el 25 % sobre el peso total","NO CUMPLE: no puede llamarse así"))) -> CUMPLE el 25 % sobre el peso total | O10: La gianduja tiene apartado propio en la norma (1.6.b.3), pero aquí va DENTRO de un bombón: la denominación de venta que manda es la del producto que vendes, no la del relleno.
A11: BC5 | B11: Trufa de chocolate negro al cacao | C11: Bombones de colección | D11: Bombón de chocolate | E11: CHN-03 + CHN-03b | F11: 25 % de chocolate sobre el peso TOTAL | G11: No | H11: a granel | I11: ='Escandallo por Molde y Tanda'!E74 -> 4 | J11: ='Escandallo por Molde y Tanda'!F74 -> 9 | K11: ='Escandallo por Molde y Tanda'!G74 -> 13 | L11: =IFERROR(I11/K11,"") -> 0.30769231 | M11: Sí | N11: =IF(M11="No","No aplica: su mínimo es el de su denominación",IF(NOT(ISNUMBER(L11)),"",IF(L11>=$B$38,"CUMPLE el 25 % sobre el peso total","NO CUMPLE: no puede llamarse así"))) -> CUMPLE el 25 % sobre el peso total | O11: Aquí el 25 % se pelea: 4 g de chocolate sobre 13 g de pieza son el 30,8 %, y bajando el baño un gramo se cae por debajo del mínimo legal. Es el ejemplo con el que el semáforo del libro 4 enseña para que sirve. «Trufa» no es una categoría legal española (`CHN-03b`).
A12: BC6 | B12: Bombón de licor de ron | C12: Bombones de colección | D12: Bombón de chocolate | E12: CHN-03 | F12: 25 % de chocolate sobre el peso TOTAL | G12: No | H12: a granel | I12: ='Escandallo por Molde y Tanda'!E75 -> 6 | J12: ='Escandallo por Molde y Tanda'!F75 -> 8 | K12: ='Escandallo por Molde y Tanda'!G75 -> 14 | L12: =IFERROR(I12/K12,"") -> 0.42857143 | M12: Sí | N12: =IF(M12="No","No aplica: su mínimo es el de su denominación",IF(NOT(ISNUMBER(L12)),"",IF(L12>=$B$38,"CUMPLE el 25 % sobre el peso total","NO CUMPLE: no puede llamarse así"))) -> CUMPLE el 25 % sobre el peso total | O12: Cascara mas gruesa (6 g) porque el licor la ataca. La única del surtido sin leche: si la vendes a granel al lado de las demás, la contaminación cruzada en la pinza se come esa ventaja.
A13: BC7 | B13: Bombón de caramelo salado | C13: Bombones de colección | D13: Bombón de chocolate | E13: CHN-03 | F13: 25 % de chocolate sobre el peso TOTAL | G13: No | H13: a granel | I13: ='Escandallo por Molde y Tanda'!E76 -> 5.5 | J13: ='Escandallo por Molde y Tanda'!F76 -> 6.5 | K13: ='Escandallo por Molde y Tanda'!G76 -> 12 | L13: =IFERROR(I13/K13,"") -> 0.45833333 | M13: Sí | N13: =IF(M13="No","No aplica: su mínimo es el de su denominación",IF(NOT(ISNUMBER(L13)),"",IF(L13>=$B$38,"CUMPLE el 25 % sobre el peso total","NO CUMPLE: no puede llamarse así"))) -> CUMPLE el 25 % sobre el peso total | O13: Azúcar alto y agua baja: aguanta mucho mas que una ganache fresca.
A14: BC8 | B14: Bombón de praliné de cacahuete | C14: Bombones de colección | D14: Bombón de chocolate (praliné) | E14: CHN-03 + CHN-82 | F14: 25 % de chocolate sobre el peso TOTAL | G14: No | H14: a granel | I14: ='Escandallo por Molde y Tanda'!E77 -> 5 | J14: ='Escandallo por Molde y Tanda'!F77 -> 7 | K14: ='Escandallo por Molde y Tanda'!G77 -> 12 | L14: =IFERROR(I14/K14,"") -> 0.41666667 | M14: Sí | N14: =IF(M14="No","No aplica: su mínimo es el de su denominación",IF(NOT(ISNUMBER(L14)),"",IF(L14>=$B$38,"CUMPLE el 25 % sobre el peso total","NO CUMPLE: no puede llamarse así"))) -> CUMPLE el 25 % sobre el peso total | O14: LA REFERENCIA QUE DEMUESTRA POR QUE SON OCHO Y NO CINCO: el cacahuete es el punto 5 del Anexo II y NO es un fruto de cáscara (punto 8). Meterlo dentro de «frutos secos» es un error de etiquetado que puede mandar a alguien al hospital.
A15: BC9 | B15: Bombón crujiente de sésamo y barquillo | C15: Bombones de colección | D15: Bombón de chocolate | E15: CHN-03 | F15: 25 % de chocolate sobre el peso TOTAL | G15: No | H15: a granel | I15: ='Escandallo por Molde y Tanda'!E78 -> 5 | J15: ='Escandallo por Molde y Tanda'!F78 -> 7 | K15: ='Escandallo por Molde y Tanda'!G78 -> 12 | L15: =IFERROR(I15/K15,"") -> 0.41666667 | M15: Sí | N15: =IF(M15="No","No aplica: su mínimo es el de su denominación",IF(NOT(ISNUMBER(L15)),"",IF(L15>=$B$38,"CUMPLE el 25 % sobre el peso total","NO CUMPLE: no puede llamarse así"))) -> CUMPLE el 25 % sobre el peso total | O15: Dos alérgenos mas que sus compañeras, y los dos independientes: granos de sésamo (punto 11) y cereales con gluten del barquillo (punto 1). El kit le da 3-4 semanas, y no por seguridad: pierde el crujiente mucho antes.
A16: BC10 | B16: Bombón de naranja confitada y chocolate negro | C16: Bombones de colección | D16: Bombón de chocolate | E16: CHN-03 | F16: 25 % de chocolate sobre el peso TOTAL | G16: No | H16: a granel | I16: ='Escandallo por Molde y Tanda'!E79 -> 5.5 | J16: ='Escandallo por Molde y Tanda'!F79 -> 6.5 | K16: ='Escandallo por Molde y Tanda'!G79 -> 12 | L16: =IFERROR(I16/K16,"") -> 0.45833333 | M16: Sí | N16: =IF(M16="No","No aplica: su mínimo es el de su denominación",IF(NOT(ISNUMBER(L16)),"",IF(L16>=$B$38,"CUMPLE el 25 % sobre el peso total","NO CUMPLE: no puede llamarse así"))) -> CUMPLE el 25 % sobre el peso total | O16: La única del surtido con SULFITOS, que es el octavo alérgeno y el que mas se olvida: la fruta confitada suele llevarlos y el umbral de declaración es de 10 mg/kg. La fruta además contamina el recorte: su merma NO recuperable es la mas alta de la carta (D40).
A17: TB1 | B17: Tableta de chocolate negro de origen 70 %, 100 g | C17: Tabletas | D17: Chocolate | E17: CHN-02 + CHN-13 | F17: ap. 1.6: mínimos calculados DESCONTANDO los ingredientes añadidos del ap. 3 | G17: Sí | H17: envasado con etiqueta | I17: ='Escandallo por Molde y Tanda'!E80 -> 100 | J17: ='Escandallo por Molde y Tanda'!F80 -> 0 | K17: ='Escandallo por Molde y Tanda'!G80 -> 100 | L17: =IFERROR(I17/K17,"") -> 1 | M17: No | N17: =IF(M17="No","No aplica: su mínimo es el de su denominación",IF(NOT(ISNUMBER(L17)),"",IF(L17>=$B$38,"CUMPLE el 25 % sobre el peso total","NO CUMPLE: no puede llamarse así"))) -> No aplica: su mínimo es el de su denominación | O17: La referencia que vende el posicionamiento: cobertura de origen a 37,48 euros/kg (`CHS-28c`) frente a los 25,02 de la de marca (`CHS-28a`), factor 1,5. Lleva la mención «cacao: X % mínimo» obligatoria (`CHN-07`) y es la que mas sube en verano: no lleva agua, aguanta 12-18 meses y viaja. Y es la referencia con el food cost MAS ALTO de la carta, con diferencia: comprar cobertura de origen y ponerle precio de cobertura de marca es como se regala el trabajo. El libro 3 lo enseña con el escenario de subida del cacao.
A18: TB2 | B18: Tableta de chocolate con leche 38 %, 100 g | C18: Tabletas | D18: Chocolate con leche | E18: CHN-02 + CHN-13 | F18: ap. 1.7: mínimos calculados DESCONTANDO los ingredientes añadidos del ap. 3 | G18: Sí | H18: envasado con etiqueta | I18: ='Escandallo por Molde y Tanda'!E81 -> 100 | J18: ='Escandallo por Molde y Tanda'!F81 -> 0 | K18: ='Escandallo por Molde y Tanda'!G81 -> 100 | L18: =IFERROR(I18/K18,"") -> 1 | M18: No | N18: =IF(M18="No","No aplica: su mínimo es el de su denominación",IF(NOT(ISNUMBER(L18)),"",IF(L18>=$B$38,"CUMPLE el 25 % sobre el peso total","NO CUMPLE: no puede llamarse así"))) -> No aplica: su mínimo es el de su denominación | O18: También lleva la mención «cacao: X % mínimo» (`CHN-07`).
... A30: TF5 | B30: Almendras marcona bañadas en chocolate, bolsa de 150 g | C30: Turrones, figuras y temporada | D30: Grageas o confites de chocolate | E30: CHN-15 | F30: RD 348/2011, ap. 1.3: la denominación de venta se complementa con «relleno», «recubierto» o «grageado» según el caso | G30: No | H30: envasado con etiqueta | I30: ='Escandallo por Molde y Tanda'!E93 -> 88 | J30: ='Escandallo por Molde y Tanda'!F93 -> 62 | K30: ='Escandallo por Molde y Tanda'!G93 -> 150 | L30: =IFERROR(I30/K30,"") -> 0.58666667 | M30: No | N30: =IF(M30="No","No aplica: su mínimo es el de su denominación",IF(NOT(ISNUMBER(L30)),"",IF(L30>=$B$38,"CUMPLE el 25 % sobre el peso total","NO CUMPLE: no puede llamarse así"))) -> No aplica: su mínimo es el de su denominación | O30: La que da nombre a la casa, y su denominación NO sale del RD 1055/2003 sino del RD 348/2011: «grageas o confites de chocolate» (`CHN-15`). Se hace en bombo, no en molde: `moldes_tanda` vale 1 y los 95 minutos son de la tanda entera, de la que salen 40 bolsas. Es la segunda que mas sube en verano: no lleva agua y es souvenir (literal del kit para julio: «packs souvenir y colaboraciones locales»).
A31: CJ1 | B31: Caja surtida de 12 bombones | C31: Cajas y regalo | D31: Chocolates rellenos surtidos | E31: CHN-13 | F31: ap. 6.a) y 6.c): la denominación va por pieza o, si el surtido es de los aps. 1.6 a 1.10 y 1.13, se sustituye por la de surtido, con una única lista de ingredientes. Es una DECISIÓN de etiquetado, no una obligación | G31: No | H31: envasado con etiqueta | I31: ='Escandallo por Molde y Tanda'!E94 -> 62.5 | J31: ='Escandallo por Molde y Tanda'!F94 -> 82.5 | K31: ='Escandallo por Molde y Tanda'!G94 -> 145 | L31: =IFERROR(I31/K31,"") -> 0.43103448 | M31: No | N31: =IF(M31="No","La denominación va por pieza: el 25 % lo comprueba cada bombón en su propia fila, no el agregado de la caja",IF(NOT(ISNUMBER(L31)),"",IF(L31>=$B$38,"CUMPLE el 25 % sobre el peso total","NO CUMPLE: no puede llamarse así"))) -> La denominación va por pieza: el 25 % lo comprueba cada bombón en su propia fila, no el agregado de la caja | O31: PVP de `CHS-29`, precio de MOSTRADOR (con IVA) y base de IVA NO declarada por la fuente: entra con su columna «lleva IVA» y el libro 4 publica el PVP base por fórmula, porque el libro 7 pide el ticket medio SIN IVA. 12 unidades a 20,00 euros son 1,67 euros por bombón. Su coste de materia NO se teclea: se COMPONE de las referencias que lleva dentro (`composicion_caja`), y por eso `g_chocolate` vale 0. Los siete alérgenos son la UNIÓN de lo que va dentro: en un surtido a granel no puedes prometer que una pinza no ha tocado otra cosa.
A32: CJ2 | B32: Caja surtida de 20 bombones | C32: Cajas y regalo | D32: Chocolates rellenos surtidos | E32: CHN-13 | F32: ap. 6.a) y 6.c), igual que CJ1 | G32: No | H32: envasado con etiqueta | I32: ='Escandallo por Molde y Tanda'!E95 -> 102.5 | J32: ='Escandallo por Molde y Tanda'!F95 -> 142.5 | K32: ='Escandallo por Molde y Tanda'!G95 -> 245 | L32: =IFERROR(I32/K32,"") -> 0.41836735 | M32: No | N32: =IF(M32="No","La denominación va por pieza: el 25 % lo comprueba cada bombón en su propia fila, no el agregado de la caja",IF(NOT(ISNUMBER(L32)),"",IF(L32>=$B$38,"CUMPLE el 25 % sobre el peso total","NO CUMPLE: no puede llamarse así"))) -> La denominación va por pieza: el 25 % lo comprueba cada bombón en su propia fila, no el agregado de la caja | O32: 1,40 euros por bombón: un 16 % menos que en la caja de 12.
A33: CJ3 | B33: Caja surtida de 35 bombones | C33: Cajas y regalo | D33: Chocolates rellenos surtidos | E33: CHN-13 | F33: ap. 6.a) y 6.c), igual que CJ1 | G33: No | H33: envasado con etiqueta | I33: ='Escandallo por Molde y Tanda'!E96 -> 181 | J33: ='Escandallo por Molde y Tanda'!F96 -> 247 | K33: ='Escandallo por Molde y Tanda'!G96 -> 428 | L33: =IFERROR(I33/K33,"") -> 0.4228972 | M33: No | N33: =IF(M33="No","La denominación va por pieza: el 25 % lo comprueba cada bombón en su propia fila, no el agregado de la caja",IF(NOT(ISNUMBER(L33)),"",IF(L33>=$B$38,"CUMPLE el 25 % sobre el peso total","NO CUMPLE: no puede llamarse así"))) -> La denominación va por pieza: el 25 % lo comprueba cada bombón en su propia fila, no el agregado de la caja | O33: 1,29 euros por bombón: un 23 % menos que en la caja de 12. Esa escalera es la decisión 4 del bonus 2, y el libro 4 la resuelve comparando el precio de la caja con la suma de sus unidades sueltas.
A34: CJ4 | B34: Estuche corporativo personalizado de 24 bombones | C34: Cajas y regalo | D34: Chocolates rellenos surtidos | E34: CHN-13 | F34: ap. 6.a) y 6.c), igual que CJ1 | G34: No | H34: envasado con etiqueta | I34: ='Escandallo por Molde y Tanda'!E97 -> 123 | J34: ='Escandallo por Molde y Tanda'!F97 -> 170 | K34: ='Escandallo por Molde y Tanda'!G97 -> 293 | L34: =IFERROR(I34/K34,"") -> 0.41979522 | M34: No | N34: =IF(M34="No","La denominación va por pieza: el 25 % lo comprueba cada bombón en su propia fila, no el agregado de la caja",IF(NOT(ISNUMBER(L34)),"",IF(L34>=$B$38,"CUMPLE el 25 % sobre el peso total","NO CUMPLE: no puede llamarse así"))) -> La denominación va por pieza: el 25 % lo comprueba cada bombón en su propia fila, no el agregado de la caja | O34: SUPUESTO: `CHS-29` no cubre el estuche corporativo. Lo que SI esta verificado es su regla operativa: 14 días de plazo mínimo desde la aprobación de la muestra (`CHS-55`), que es lo que decide si aceptas un pedido de empresa en diciembre. Y es el canal que te saca de la nota del epígrafe 644.5 y te mete en la tabla de CLIENTES del art. 5.3.b) del EUDR (`CHN-24`, D48).
A35: ENVASADO CON ETIQUETA: Sale envasado con SU etiqueta. El art. 4.2 del RD 1021/2022 fija la temperatura de conservación POR LA ETIQUETA que pone quien ha producido y envasado: la que tu has escrito te obliga a ti. Y con etiqueta entran además las doce menciones del art. 9.1 del Rgto. 1169/2011 (CHN-35) mas el lote, que NO viene de ese reglamento sino del RD 1808/1991 (CHN-36).
A37: Los mínimos que usa el semáforo
A38: Chocolate mínimo sobre el PESO TOTAL del bombón y del chocolate relleno (aps. 1.10 y 1.13, y la base es el peso total CON el relleno dentro) | B38: 0.25
A39: Materia seca TOTAL de cacao del chocolate a la taza (ap. 1.11) | B39: 0.35
A40: Manteca de cacao del chocolate a la taza (ap. 1.11) | B40: 0.18
A41: Materia seca DESGRASADA de cacao del chocolate a la taza (ap. 1.11) | B41: 0.14
A43: Capa (b): las tres magnitudes que la norma pide y la bolsa no trae. Cópialas de la ficha técnica de tu proveedor
A44: Cobertura | B44: Materia seca TOTAL de cacao | C44: Manteca de cacao | D44: Materia seca DESGRASADA de cacao | E44: ¿Llega a los tres umbrales de materia seca del ap. 1.11? | F44: Qué te dice eso, y qué no | G44: Nota
A45: Cobertura de chocolate negro (marca, 54,5 % de cacao) | B45: 0.545 | C45: 0.31 | D45: 0.235 | E45: =IF(OR(NOT(ISNUMBER(B45)),NOT(ISNUMBER(C45)),NOT(ISNUMBER(D45))),"",IF(AND(B45>=$B$39,C45>=$B$40,D45>=$B$41),"Sí","No")) -> Sí | F45: =IF(E45="","",IF(E45="Sí","Pasa los tres umbrales de materia seca. Eso NO decide la denominación por sí solo: depende además de qué lleva (leche, harina o almidón hasta el 8 %), y lo confirma la ficha técnica de tu proveedor","No llega a los tres umbrales: con esta cobertura no puedes ir por esa denominación")) -> Pasa los tres umbrales de materia seca. Eso NO decide la denominación por sí solo: depende además de qué lleva (leche, harina o almidón hasta el 8 %), y lo confirma la ficha técnica de tu proveedor | G45: LA CELDA MAS CRITICA DEL PAQUETE. Base CON IVA declarada por la ficha (`CHS-28a`): el libro 3 la publica en las dos bases y lo que viaja al 4 y al 7 es la base imponible. Las tres magnitudes de arriba son SUPUESTO: pidesela a tu proveedor, la bolsa solo trae el total.
A46: Cobertura de chocolate de origen (70 % de cacao) | B46: 0.7 | C46: 0.42 | D46: 0.28 | E46: =IF(OR(NOT(ISNUMBER(B46)),NOT(ISNUMBER(C46)),NOT(ISNUMBER(D46))),"",IF(AND(B46>=$B$39,C46>=$B$40,D46>=$B$41),"Sí","No")) -> Sí | F46: =IF(E46="","",IF(E46="Sí","Pasa los tres umbrales de materia seca. Eso NO decide la denominación por sí solo: depende además de qué lleva (leche, harina o almidón hasta el 8 %), y lo confirma la ficha técnica de tu proveedor","No llega a los tres umbrales: con esta cobertura no puedes ir por esa denominación")) -> Pasa los tres umbrales de materia seca. Eso NO decide la denominación por sí solo: depende además de qué lleva (leche, harina o almidón hasta el 8 %), y lo confirma la ficha técnica de tu proveedor | G46: Factor 1,5 frente a la de marca, y es la decisión de posicionamiento mas cara del negocio (decisión 5 del bonus 2). La pagina no declara si el precio lleva IVA: se trata como base imponible y se marca.
A47: Cobertura de chocolate con leche (38 % de cacao) | B47: 0.38 | C47: 0.21 | D47: 0.17 | E47: =IF(OR(NOT(ISNUMBER(B47)),NOT(ISNUMBER(C47)),NOT(ISNUMBER(D47))),"",IF(AND(B47>=$B$39,C47>=$B$40,D47>=$B$41),"Sí","No")) -> Sí | F47: =IF(E47="","",IF(E47="Sí","Pasa los tres umbrales de materia seca. Eso NO decide la denominación por sí solo: depende además de qué lleva (leche, harina o almidón hasta el 8 %), y lo confirma la ficha técnica de tu proveedor","No llega a los tres umbrales: con esta cobertura no puedes ir por esa denominación")) -> Pasa los tres umbrales de materia seca. Eso NO decide la denominación por sí solo: depende además de qué lleva (leche, harina o almidón hasta el 8 %), y lo confirma la ficha técnica de tu proveedor | G47: SUPUESTO declarado: no hay precio verificado de cobertura con leche en el research. Celda verde con valor por defecto (regla 2 de §2.3: ninguna celda verde vacia).
A48: Cobertura de chocolate blanco (30 % de cacao) | B48: 0.3 | C48: 0.3 | D48: 0 | E48: =IF(OR(NOT(ISNUMBER(B48)),NOT(ISNUMBER(C48)),NOT(ISNUMBER(D48))),"",IF(AND(B48>=$B$39,C48>=$B$40,D48>=$B$41),"Sí","No")) -> No | F48: =IF(E48="","",IF(E48="Sí","Pasa los tres umbrales de materia seca. Eso NO decide la denominación por sí solo: depende además de qué lleva (leche, harina o almidón hasta el 8 %), y lo confirma la ficha técnica de tu proveedor","No llega a los tres umbrales: con esta cobertura no puedes ir por esa denominación")) -> No llega a los tres umbrales: con esta cobertura no puedes ir por esa denominación | G48: SUPUESTO declarado. Ojo al chocolate blanco: NO lleva materia seca desgrasada de cacao, y por eso el art. 6.d) del RD 1055/2003 NO le obliga a la mención «cacao: X % mínimo» (`CHN-07`).
A50: Las tres magnitudes de arriba son SUPUESTOS de ejemplo, no un dato de tu proveedor: la bolsa de una cobertura de marca publica un solo número («54,5 %») y la norma necesita tres. Es la misma ficha técnica que te va a pedir el libro de proveedores para el boletín de cadmio, así que se pide una sola vez.
A52: El tope del 40 % de materias añadidas (ap. 3)
A53: Tope de materias añadidas del ap. 3 | B53: 0.4
A55: Id | B55: Referencia | C55: Materia añadida sobre el peso total | D55: Veredicto
A56: TB4 | B56: Tableta de chocolate negro con almendra marcona, 100 g | C56: =IFERROR('Escandallo por Molde y Tanda'!F83/'Escandallo por Molde y Tanda'!G83,"") -> 0.22 | D56: =IF(NOT(ISNUMBER(C56)),"",IF(C56<=$B$53,"CUMPLE el tope del 40 %","NO CUMPLE: revisa el gramaje")) -> CUMPLE el tope del 40 %
A57: TB5 | B57: Tableta de chocolate con leche y avellana, 100 g | C57: =IFERROR('Escandallo por Molde y Tanda'!F84/'Escandallo por Molde y Tanda'!G84,"") -> 0.2 | D57: =IF(NOT(ISNUMBER(C57)),"",IF(C57<=$B$53,"CUMPLE el tope del 40 %","NO CUMPLE: revisa el gramaje")) -> CUMPLE el tope del 40 %
A58: TF2 | B58: Mona de Pascua de chocolate, 400 g | C58: =IFERROR('Escandallo por Molde y Tanda'!F90/'Escandallo por Molde y Tanda'!G90,"") -> 0.05 | D58: =IF(NOT(ISNUMBER(C58)),"",IF(C58<=$B$53,"CUMPLE el tope del 40 %","NO CUMPLE: revisa el gramaje")) -> CUMPLE el tope del 40 %
A59: TF4 | B59: Turrón de chocolate con almendra, 250 g | C59: =IFERROR('Escandallo por Molde y Tanda'!F92/'Escandallo por Molde y Tanda'!G92,"") -> 0.328 | D59: =IF(NOT(ISNUMBER(C59)),"",IF(C59<=$B$53,"CUMPLE el tope del 40 %","NO CUMPLE: revisa el gramaje")) -> CUMPLE el tope del 40 %
A63: Versión 1.0 · septiembre 2026 · aichef.pro/guia-chocolateria-obrador · info@aichef.pro

Sheet Escandallo por Molde y Tanda
A1: Escandallo por Molde y Tanda
A2: AI Chef Pro · aichef.pro — Cómo Montar una Chocolatería
A3: Arriba, lo que cuesta un kilo de cada relleno. Abajo, lo que cuesta una pieza. Las cajas no tienen escandallo propio: se componen de sus bombones.
A5: Fórmulas de relleno: cantidad que entra en UN KILO
A6: Relleno | B6: Ingrediente | C6: Cantidad por kilo | D6: Precio de compra (EUR) | E6: Unidad de compra | F6: Coste de la línea (EUR) | G6: Nota
A7: ganache negra fresca | B7: Nata 35 % MG fresca | C7: 0.4 | D7: =IFERROR(VLOOKUP(B7,'Parámetros'!$A$48:$B$73,2,FALSE),"") -> 4.2 | E7: L | F7: =IFERROR(C7*D7,"") -> 1.68 | G7: Fórmulas de EJEMPLO, declaradas. Este producto NO es un recetario y no publica curvas de templado: una curva mal publicada arruina producción. Lo que hacen estas líneas es dar al libro algo que costear.
A8: ganache negra fresca | B8: Cobertura negra | C8: 0.52 | D8: =IFERROR(VLOOKUP(B8,'Parámetros'!$A$48:$B$73,2,FALSE),"") -> 22.7455 | E8: kg | F8: =IFERROR(C8*D8,"") -> 11.82766
A9: ganache negra fresca | B9: Mantequilla | C9: 0.06 | D9: =IFERROR(VLOOKUP(B9,'Parámetros'!$A$48:$B$73,2,FALSE),"") -> 9.8 | E9: kg | F9: =IFERROR(C9*D9,"") -> 0.588
A10: ganache negra fresca | B10: Glucosa | C10: 0.04 | D10: =IFERROR(VLOOKUP(B10,'Parámetros'!$A$48:$B$73,2,FALSE),"") -> 3.4 | E10: kg | F10: =IFERROR(C10*D10,"") -> 0.136
A11: ganache leche estabilizada | B11: Nata 35 % MG UHT | C11: 0.34 | D11: =IFERROR(VLOOKUP(B11,'Parámetros'!$A$48:$B$73,2,FALSE),"") -> 3.1 | E11: L | F11: =IFERROR(C11*D11,"") -> 1.054
A12: ganache leche estabilizada | B12: Cobertura con leche | C12: 0.56 | D12: =IFERROR(VLOOKUP(B12,'Parámetros'!$A$48:$B$73,2,FALSE),"") -> 19.5 | E12: kg | F12: =IFERROR(C12*D12,"") -> 10.92
A13: ganache leche estabilizada | B13: Sorbitol | C13: 0.06 | D13: =IFERROR(VLOOKUP(B13,'Parámetros'!$A$48:$B$73,2,FALSE),"") -> 6.2 | E13: kg | F13: =IFERROR(C13*D13,"") -> 0.372
A14: ganache leche estabilizada | B14: Mantequilla | C14: 0.05 | D14: =IFERROR(VLOOKUP(B14,'Parámetros'!$A$48:$B$73,2,FALSE),"") -> 9.8 | E14: kg | F14: =IFERROR(C14*D14,"") -> 0.49
A15: praliné avellana | B15: Praline de avellana 50 % | C15: 0.7 | D15: =IFERROR(VLOOKUP(B15,'Parámetros'!$A$48:$B$73,2,FALSE),"") -> 14.8 | E15: kg | F15: =IFERROR(C15*D15,"") -> 10.36
A16: praliné avellana | B16: Cobertura con leche | C16: 0.28 | D16: =IFERROR(VLOOKUP(B16,'Parámetros'!$A$48:$B$73,2,FALSE),"") -> 19.5 | E16: kg | F16: =IFERROR(C16*D16,"") -> 5.46
A17: praliné avellana | B17: Manteca de cacao | C17: 0.04 | D17: =IFERROR(VLOOKUP(B17,'Parámetros'!$A$48:$B$73,2,FALSE),"") -> 18.6 | E17: kg | F17: =IFERROR(C17*D17,"") -> 0.744
A18: gianduja avellana | B18: Pasta pura de avellana | C18: 0.45 | D18: =IFERROR(VLOOKUP(B18,'Parámetros'!$A$48:$B$73,2,FALSE),"") -> 22.5 | E18: kg | F18: =IFERROR(C18*D18,"") -> 10.125
A19: gianduja avellana | B19: Cobertura con leche | C19: 0.4 | D19: =IFERROR(VLOOKUP(B19,'Parámetros'!$A$48:$B$73,2,FALSE),"") -> 19.5 | E19: kg | F19: =IFERROR(C19*D19,"") -> 7.8
... A48: yema tostada | B48: Almidón de maíz | C48: 0.05 | D48: =IFERROR(VLOOKUP(B48,'Parámetros'!$A$48:$B$73,2,FALSE),"") -> 2.1 | E48: kg | F48: =IFERROR(C48*D48,"") -> 0.105
A50: Coste por kilo de cada relleno y de cada materia añadida
A51: Relleno o materia añadida | B51: Coste por kilo (EUR) | C51: Familia de vida útil del kit (se CITA, no se reescribe) | D51: Plazo orientativo que publica el kit | E51: Nota
A52: ganache negra fresca | B52: =SUM(F7:F10) -> 14.23166 | C52: Bombones de ganache con nata fresca | D52: 10-15 días | E52: La ganache que obliga a decidir el modelo de negocio: agua disponible alta, y el kit le da 10-15 días. Es la que manda en la decisión 3 del bonus 2.
A53: ganache leche estabilizada | B53: =SUM(F11:F14) -> 12.836 | C53: Bombones de ganache con nata UHT, sorbato o alcohol | D53: 4-8 semanas | E53: La misma pieza con otra formulación: el kit le da 4-8 semanas. Entre esta y la anterior hay un factor DE TRES A CINCO, y esa es una decisión de modelo de negocio, no técnica.
A54: praliné avellana | B54: =SUM(F15:F17) -> 16.564 | C54: Bombones de praliné, gianduja y frutos secos | D54: 2-4 meses | E54: «Praline» NO es un nombre comercial: el punto 10 de la parte A del Anexo I de la Directiva 2000/36/CE se titula «Bombón de chocolate o praliné» (`CHN-82`), con el mismo mínimo del 25 %.
A55: gianduja avellana | B55: =SUM(F18:F20) -> 18.1205 | C55: Bombones de praliné, gianduja y frutos secos | D55: 2-4 meses | E55: La gianduja tiene su propio apartado en la norma (1.6.b.3), con avellanas entre 20 y 40 g por 100 g. Aquí es RELLENO de un bombón, así que la denominación de venta es la del bombón.
A56: trufa | B56: =SUM(F21:F24) -> 14.12257 | C56: Trufas y rocas recubiertas | D56: 3-4 semanas | E56: «Trufa» no aparece ni una vez en el RD 1055/2003 (`CHN-03b`): es un TIPO de bombón, no una categoría legal ni un sinonimo de bombón.
A57: licor | B57: =SUM(F25:F27) -> 4.552 | C57: Bombones de licor y cristalizados | D57: 3-6 meses | E57: El alcohol baja la actividad de agua. Vigilar la cristalización del azúcar en la cáscara: revienta y gotea (nota literal del kit).
A58: caramelo salado | B58: =SUM(F28:F32) -> 3.9892 | C58: Bombones de ganache con nata UHT, sorbato o alcohol | D58: 4-8 semanas | E58: Azúcar alto y agua baja: aguanta mas que una ganache fresca.
A59: praliné cacahuete | B59: =SUM(F33:F35) -> 12.726 | C59: Bombones de praliné, gianduja y frutos secos | D59: 2-4 meses | E59: EL CACAHUETE ES EL PUNTO 5 DEL ANEXO II y NO es un fruto de cáscara (`CHN-34b`): esta referencia se etiqueta con su propio alérgeno, no dentro de «frutos secos».
A60: crujiente sésamo | B60: =SUM(F36:F38) -> 13.278 | C60: Barquillos y crujientes bañados | D60: 3-4 semanas | E60: DOS alérgenos independientes en una sola pieza: granos de sésamo (punto 11) y cereales con gluten del barquillo (punto 1). El kit le da 3-4 semanas, y no por seguridad: pierde el crujiente mucho antes.
A61: naranja confitada | B61: =SUM(F39:F40) -> 14.34729 | C61: Frutos secos garrapiñados y frutas confitadas bañadas | D61: 1-3 meses | E61: La fruta confitada suele llevar SULFITOS (punto 12 del Anexo II), que es el octavo alérgeno y el que mas se olvida. Pidele a tu proveedor la ficha técnica: el umbral de declaración es 10 mg/kg.
A62: praliné de tableta | B62: =SUM(F41:F42) -> 16.13 | C62: Bombones de praliné, gianduja y frutos secos | D62: 2-4 meses | E62: En una TABLETA RELLENA la denominación es «chocolate relleno» (ap. 1.10) y el exterior tiene que ser al menos el 25 % del peso total (`CHN-04`), calculado SOBRE EL PESO TOTAL con el relleno dentro (`CHN-10`).
A63: masa a la taza | B63: =SUM(F43:F45) -> 4.331 | C63: Tabletas y chocolate sin relleno | D63: 12-18 meses | E63: NO es un relleno: es la otra mitad de la fórmula del chocolate a la taza, que NO se hace solo con cobertura. Va aquí para que el escandallo pueda costearla. El almidón es DE MAÍZ a propósito: la norma admite trigo, arroz o maíz hasta el 8 %, y con el de trigo habría que declarar gluten.
A64: yema tostada | B64: =SUM(F46:F48) -> 2.589 | C64: Bombones de ganache con nata fresca | D64: 10-15 días | E64: La ÚNICA referencia del surtido con huevo, y va con ovoproducto pasteurizado de establecimiento autorizado, que es la tercera vía del art. 9 del RD 1021/2022 (`CHN-31`). Con huevo crudo habría que llegar a 70 °C durante 2 s en el centro.
A65: Almendra marcona repelada | B65: =IFERROR(VLOOKUP(A65,'Parámetros'!$A$48:$B$73,2,FALSE),"") -> 12.4 | C65: No es un relleno: es materia comestible añadida del ap. 3 | D65: la de la referencia que la lleva | E65: Va en la misma tabla para que el escandallo busque en un solo sitio, lleve relleno o lleve almendra.
A66: Avellana tostada | B66: =IFERROR(VLOOKUP(A66,'Parámetros'!$A$48:$B$73,2,FALSE),"") -> 13.9 | C66: No es un relleno: es materia comestible añadida del ap. 3 | D66: la de la referencia que la lleva | E66: Va en la misma tabla para que el escandallo busque en un solo sitio, lleve relleno o lleve almendra.
A68: Escandallo por referencia
A69: Id | B69: Referencia | C69: Familia | D69: Cobertura | E69: Gramos de chocolate por pieza | F69: Gramos de relleno o materia por pieza | G69: Peso total de la pieza (g) | H69: Relleno o materia añadida | I69: Precio de la cobertura (EUR/kg) | J69: Coste del chocolate (EUR) | K69: Coste por kilo del relleno (EUR) | L69: Coste del relleno (EUR) | M69: COSTE DE MATERIA SIN MERMA (EUR) | N69: Merma NO recuperable | O69: COSTE DE MATERIA CON EL RECORTE QUE NO VUELVE (EUR) | P69: Procedencia y nota
A70: BC1 | B70: Bombón de ganache de chocolate negro 70 % | C70: Bombones de colección | D70: Cobertura negra | E70: 5.5 | F70: 6.5 | G70: =IFERROR(E70+F70,"") -> 12 | H70: ganache negra fresca | I70: =IFERROR(VLOOKUP(D70,'Parámetros'!$A$48:$B$73,2,FALSE),"") -> 22.7455 | J70: =IFERROR(E70/1000*I70,"") -> 0.12510025 | K70: =IFERROR(VLOOKUP(H70,'Escandallo por Molde y Tanda'!$A$52:$B$66,2,FALSE),"") -> 14.23166 | L70: =IFERROR(F70/1000*K70,"") -> 0.09250579 | M70: =IFERROR(J70+L70,"") -> 0.21760604 | N70: ='Merma de Templado y Recortes'!E7 -> 0.03 | O70: =IFERROR(M70/(1-N70),"") -> 0.22433612 | P70: La referencia que mas margen deja y la que antes caduca. Con 5,5 g de chocolate sobre 12 g de pieza, el chocolate es el 45,8 % del peso total: cumple el 25 % del ap. 1.13 con holgura. En julio y agosto baja a un tercio de su mix: es la primera que sale del catálogo de verano (literal del kit para junio: «menos ganache fresca»).
A71: BC2 | B71: Bombón de ganache de leche y vainilla | C71: Bombones de colección | D71: Cobertura con leche | E71: 5.5 | F71: 6.5 | G71: =IFERROR(E71+F71,"") -> 12 | H71: ganache leche estabilizada | I71: =IFERROR(VLOOKUP(D71,'Parámetros'!$A$48:$B$73,2,FALSE),"") -> 19.5 | J71: =IFERROR(E71/1000*I71,"") -> 0.10725 | K71: =IFERROR(VLOOKUP(H71,'Escandallo por Molde y Tanda'!$A$52:$B$66,2,FALSE),"") -> 12.836 | L71: =IFERROR(F71/1000*K71,"") -> 0.083434 | M71: =IFERROR(J71+L71,"") -> 0.190684 | N71: ='Merma de Templado y Recortes'!E8 -> 0.03 | O71: =IFERROR(M71/(1-N71),"") -> 0.19658144 | P71: Misma pieza que BC1 con otra formulación: nata UHT y sorbitol. El kit le da 4-8 semanas frente a los 10-15 días de BC1. Es LA decisión de modelo de negocio del producto, y el libro 5 la cuantifica en euros de merma por caducidad al año.
A72: BC3 | B72: Bombón de praliné de avellana | C72: Bombones de colección | D72: Cobertura con leche | E72: 5 | F72: 7 | G72: =IFERROR(E72+F72,"") -> 12 | H72: praliné avellana | I72: =IFERROR(VLOOKUP(D72,'Parámetros'!$A$48:$B$73,2,FALSE),"") -> 19.5 | J72: =IFERROR(E72/1000*I72,"") -> 0.0975 | K72: =IFERROR(VLOOKUP(H72,'Escandallo por Molde y Tanda'!$A$52:$B$66,2,FALSE),"") -> 16.564 | L72: =IFERROR(F72/1000*K72,"") -> 0.115948 | M72: =IFERROR(J72+L72,"") -> 0.213448 | N72: ='Merma de Templado y Recortes'!E9 -> 0.02 | O72: =IFERROR(M72/(1-N72),"") -> 0.21780408 | P72: «Praline» SI significa algo legalmente: es la denominación de venta europea del bombón de chocolate (`CHN-82`), con el mismo mínimo del 25 %. Escribir lo contrario esta prohibido (§5.1, prohibición 7).
A73: BC4 | B73: Bombón de gianduja de avellana | C73: Bombones de colección | D73: Cobertura con leche | E73: 5 | F73: 7 | G73: =IFERROR(E73+F73,"") -> 12 | H73: gianduja avellana | I73: =IFERROR(VLOOKUP(D73,'Parámetros'!$A$48:$B$73,2,FALSE),"") -> 19.5 | J73: =IFERROR(E73/1000*I73,"") -> 0.0975 | K73: =IFERROR(VLOOKUP(H73,'Escandallo por Molde y Tanda'!$A$52:$B$66,2,FALSE),"") -> 18.1205 | L73: =IFERROR(F73/1000*K73,"") -> 0.1268435 | M73: =IFERROR(J73+L73,"") -> 0.2243435 | N73: ='Merma de Templado y Recortes'!E10 -> 0.02 | O73: =IFERROR(M73/(1-N73),"") -> 0.22892194 | P73: La gianduja tiene apartado propio en la norma (1.6.b.3), pero aquí va DENTRO de un bombón: la denominación de venta que manda es la del producto que vendes, no la del relleno.
A74: BC5 | B74: Trufa de chocolate negro al cacao | C74: Bombones de colección | D74: Cobertura negra | E74: 4 | F74: 9 | G74: =IFERROR(E74+F74,"") -> 13 | H74: trufa | I74: =IFERROR(VLOOKUP(D74,'Parámetros'!$A$48:$B$73,2,FALSE),"") -> 22.7455 | J74: =IFERROR(E74/1000*I74,"") -> 0.090982 | K74: =IFERROR(VLOOKUP(H74,'Escandallo por Molde y Tanda'!$A$52:$B$66,2,FALSE),"") -> 14.12257 | L74: =IFERROR(F74/1000*K74,"") -> 0.12710313 | M74: =IFERROR(J74+L74,"") -> 0.21808513 | N74: ='Merma de Templado y Recortes'!E11 -> 0.04 | O74: =IFERROR(M74/(1-N74),"") -> 0.22717201 | P74: Aquí el 25 % se pelea: 4 g de chocolate sobre 13 g de pieza son el 30,8 %, y bajando el baño un gramo se cae por debajo del mínimo legal. Es el ejemplo con el que el semáforo del libro 4 enseña para que sirve. «Trufa» no es una categoría legal española (`CHN-03b`).
A75: BC6 | B75: Bombón de licor de ron | C75: Bombones de colección | D75: Cobertura negra | E75: 6 | F75: 8 | G75: =IFERROR(E75+F75,"") -> 14 | H75: licor | I75: =IFERROR(VLOOKUP(D75,'Parámetros'!$A$48:$B$73,2,FALSE),"") -> 22.7455 | J75: =IFERROR(E75/1000*I75,"") -> 0.136473 | K75: =IFERROR(VLOOKUP(H75,'Escandallo por Molde y Tanda'!$A$52:$B$66,2,FALSE),"") -> 4.552 | L75: =IFERROR(F75/1000*K75,"") -> 0.036416 | M75: =IFERROR(J75+L75,"") -> 0.172889 | N75: ='Merma de Templado y Recortes'!E12 -> 0.04 | O75: =IFERROR(M75/(1-N75),"") -> 0.18009271 | P75: Cascara mas gruesa (6 g) porque el licor la ataca. La única del surtido sin leche: si la vendes a granel al lado de las demás, la contaminación cruzada en la pinza se come esa ventaja.
A76: BC7 | B76: Bombón de caramelo salado | C76: Bombones de colección | D76: Cobertura con leche | E76: 5.5 | F76: 6.5 | G76: =IFERROR(E76+F76,"") -> 12 | H76: caramelo salado | I76: =IFERROR(VLOOKUP(D76,'Parámetros'!$A$48:$B$73,2,FALSE),"") -> 19.5 | J76: =IFERROR(E76/1000*I76,"") -> 0.10725 | K76: =IFERROR(VLOOKUP(H76,'Escandallo por Molde y Tanda'!$A$52:$B$66,2,FALSE),"") -> 3.9892 | L76: =IFERROR(F76/1000*K76,"") -> 0.0259298 | M76: =IFERROR(J76+L76,"") -> 0.1331798 | N76: ='Merma de Templado y Recortes'!E13 -> 0.03 | O76: =IFERROR(M76/(1-N76),"") -> 0.13729876 | P76: Azúcar alto y agua baja: aguanta mucho mas que una ganache fresca.
A77: BC8 | B77: Bombón de praliné de cacahuete | C77: Bombones de colección | D77: Cobertura con leche | E77: 5 | F77: 7 | G77: =IFERROR(E77+F77,"") -> 12 | H77: praliné cacahuete | I77: =IFERROR(VLOOKUP(D77,'Parámetros'!$A$48:$B$73,2,FALSE),"") -> 19.5 | J77: =IFERROR(E77/1000*I77,"") -> 0.0975 | K77: =IFERROR(VLOOKUP(H77,'Escandallo por Molde y Tanda'!$A$52:$B$66,2,FALSE),"") -> 12.726 | L77: =IFERROR(F77/1000*K77,"") -> 0.089082 | M77: =IFERROR(J77+L77,"") -> 0.186582 | N77: ='Merma de Templado y Recortes'!E14 -> 0.02 | O77: =IFERROR(M77/(1-N77),"") -> 0.1903898 | P77: LA REFERENCIA QUE DEMUESTRA POR QUE SON OCHO Y NO CINCO: el cacahuete es el punto 5 del Anexo II y NO es un fruto de cáscara (punto 8). Meterlo dentro de «frutos secos» es un error de etiquetado que puede mandar a alguien al hospital.
A78: BC9 | B78: Bombón crujiente de sésamo y barquillo | C78: Bombones de colección | D78: Cobertura con leche | E78: 5 | F78: 7 | G78: =IFERROR(E78+F78,"") -> 12 | H78: crujiente sésamo | I78: =IFERROR(VLOOKUP(D78,'Parámetros'!$A$48:$B$73,2,FALSE),"") -> 19.5 | J78: =IFERROR(E78/1000*I78,"") -> 0.0975 | K78: =IFERROR(VLOOKUP(H78,'Escandallo por Molde y Tanda'!$A$52:$B$66,2,FALSE),"") -> 13.278 | L78: =IFERROR(F78/1000*K78,"") -> 0.092946 | M78: =IFERROR(J78+L78,"") -> 0.190446 | N78: ='Merma de Templado y Recortes'!E15 -> 0.02 | O78: =IFERROR(M78/(1-N78),"") -> 0.19433265 | P78: Dos alérgenos mas que sus compañeras, y los dos independientes: granos de sésamo (punto 11) y cereales con gluten del barquillo (punto 1). El kit le da 3-4 semanas, y no por seguridad: pierde el crujiente mucho antes.
A79: BC10 | B79: Bombón de naranja confitada y chocolate negro | C79: Bombones de colección | D79: Cobertura negra | E79: 5.5 | F79: 6.5 | G79: =IFERROR(E79+F79,"") -> 12 | H79: naranja confitada | I79: =IFERROR(VLOOKUP(D79,'Parámetros'!$A$48:$B$73,2,FALSE),"") -> 22.7455 | J79: =IFERROR(E79/1000*I79,"") -> 0.12510025 | K79: =IFERROR(VLOOKUP(H79,'Escandallo por Molde y Tanda'!$A$52:$B$66,2,FALSE),"") -> 14.34729 | L79: =IFERROR(F79/1000*K79,"") -> 0.093257385 | M79: =IFERROR(J79+L79,"") -> 0.21835763 | N79: ='Merma de Templado y Recortes'!E16 -> 0.05 | O79: =IFERROR(M79/(1-N79),"") -> 0.22985014 | P79: La única del surtido con SULFITOS, que es el octavo alérgeno y el que mas se olvida: la fruta confitada suele llevarlos y el umbral de declaración es de 10 mg/kg. La fruta además contamina el recorte: su merma NO recuperable es la mas alta de la carta (D40).
A80: TB1 | B80: Tableta de chocolate negro de origen 70 %, 100 g | C80: Tabletas | D80: Cobertura de origen | E80: 100 | F80: 0 | G80: =IFERROR(E80+F80,"") -> 100 | H80: No lleva | I80: =IFERROR(VLOOKUP(D80,'Parámetros'!$A$48:$B$73,2,FALSE),"") -> 37.48 | J80: =IFERROR(E80/1000*I80,"") -> 3.748 | K80: 0 | L80: =IFERROR(F80/1000*K80,"") -> 0 | M80: =IFERROR(J80+L80,"") -> 3.748 | N80: ='Merma de Templado y Recortes'!E17 -> 0.01 | O80: =IFERROR(M80/(1-N80),"") -> 3.7858586 | P80: La referencia que vende el posicionamiento: cobertura de origen a 37,48 euros/kg (`CHS-28c`) frente a los 25,02 de la de marca (`CHS-28a`), factor 1,5. Lleva la mención «cacao: X % mínimo» obligatoria (`CHN-07`) y es la que mas sube en verano: no lleva agua, aguanta 12-18 meses y viaja. Y es la referencia con el food cost MAS ALTO de la carta, con diferencia: comprar cobertura de origen y ponerle precio de cobertura de marca es como se regala el trabajo. El libro 3 lo enseña con el escenario de subida del cacao.
A81: TB2 | B81: Tableta de chocolate con leche 38 %, 100 g | C81: Tabletas | D81: Cobertura con leche | E81: 100 | F81: 0 | G81: =IFERROR(E81+F81,"") -> 100 | H81: No lleva | I81: =IFERROR(VLOOKUP(D81,'Parámetros'!$A$48:$B$73,2,FALSE),"") -> 19.5 | J81: =IFERROR(E81/1000*I81,"") -> 1.95 | K81: 0 | L81: =IFERROR(F81/1000*K81,"") -> 0 | M81: =IFERROR(J81+L81,"") -> 1.95 | N81: ='Merma de Templado y Recortes'!E18 -> 0.01 | O81: =IFERROR(M81/(1-N81),"") -> 1.969697 | P81: También lleva la mención «cacao: X % mínimo» (`CHN-07`).
A82: TB3 | B82: Tableta de chocolate blanco 30 %, 100 g | C82: Tabletas | D82: Cobertura blanca | E82: 100 | F82: 0 | G82: =IFERROR(E82+F82,"") -> 100 | H82: No lleva | I82: =IFERROR(VLOOKUP(D82,'Parámetros'!$A$48:$B$73,2,FALSE),"") -> 21 | J82: =IFERROR(E82/1000*I82,"") -> 2.1 | K82: 0 | L82: =IFERROR(F82/1000*K82,"") -> 0 | M82: =IFERROR(J82+L82,"") -> 2.1 | N82: ='Merma de Templado y Recortes'!E19 -> 0.01 | O82: =IFERROR(M82/(1-N82),"") -> 2.1212121 | P82: El chocolate blanco NO lleva la mención «cacao: X % mínimo»: `CHN-07` acota esa obligación a los apartados 1.4, 1.5, 1.6, 1.7, 1.8, 1.11 y 1.12, y el blanco es el 1.9. Escribir que la mención es obligatoria en todos los chocolates esta prohibido (§5.1, 27).
A83: TB4 | B83: Tableta de chocolate negro con almendra marcona, 100 g | C83: Tabletas | D83: Cobertura negra | E83: 78 | F83: 22 | G83: =IFERROR(E83+F83,"") -> 100 | H83: Almendra marcona repelada | I83: =IFERROR(VLOOKUP(D83,'Parámetros'!$A$48:$B$73,2,FALSE),"") -> 22.7455 | J83: =IFERROR(E83/1000*I83,"") -> 1.774149 | K83: =IFERROR(VLOOKUP(H83,'Escandallo por Molde y Tanda'!$A$52:$B$66,2,FALSE),"") -> 12.4 | L83: =IFERROR(F83/1000*K83,"") -> 0.2728 | M83: =IFERROR(J83+L83,"") -> 2.046949 | N83: ='Merma de Templado y Recortes'!E20 -> 0.02 | O83: =IFERROR(M83/(1-N83),"") -> 2.0887235 | P83: La almendra va en `g_relleno` porque es materia comestible AÑADIDA del ap. 3, y su tope es el 40 % del peso total (`CHN-09`). Con 22 g sobre 100 esta en el 22 %: dentro. La almendra enrancia, y el frío no lo evita: manda la fecha, no el aspecto (nota del kit).
A84: TB5 | B84: Tableta de chocolate con leche y avellana, 100 g | C84: Tabletas | D84: Cobertura con leche | E84: 80 | F84: 20 | G84: =IFERROR(E84+F84,"") -> 100 | H84: Avellana tostada | I84: =IFERROR(VLOOKUP(D84,'Parámetros'!$A$48:$B$73,2,FALSE),"") -> 19.5 | J84: =IFERROR(E84/1000*I84,"") -> 1.56 | K84: =IFERROR(VLOOKUP(H84,'Escandallo por Molde y Tanda'!$A$52:$B$66,2,FALSE),"") -> 13.9 | L84: =IFERROR(F84/1000*K84,"") -> 0.278 | M84: =IFERROR(J84+L84,"") -> 1.838 | N84: ='Merma de Templado y Recortes'!E21 -> 0.02 | O84: =IFERROR(M84/(1-N84),"") -> 1.8755102 | P84: La avellana va como materia añadida del ap. 3, igual que la almendra de TB4.
A85: TB6 | B85: Tableta rellena de praliné, 100 g | C85: Tabletas | D85: Cobertura con leche | E85: 55 | F85: 45 | G85: =IFERROR(E85+F85,"") -> 100 | H85: praliné de tableta | I85: =IFERROR(VLOOKUP(D85,'Parámetros'!$A$48:$B$73,2,FALSE),"") -> 19.5 | J85: =IFERROR(E85/1000*I85,"") -> 1.0725 | K85: =IFERROR(VLOOKUP(H85,'Escandallo por Molde y Tanda'!$A$52:$B$66,2,FALSE),"") -> 16.13 | L85: =IFERROR(F85/1000*K85,"") -> 0.72585 | M85: =IFERROR(J85+L85,"") -> 1.79835 | N85: ='Merma de Templado y Recortes'!E22 -> 0.03 | O85: =IFERROR(M85/(1-N85),"") -> 1.8539691 | P85: La segunda referencia del ap. 1.10, y la que enseña la base de calculo: 55 g de chocolate sobre 100 g de pieza son el 55 %, calculado SOBRE EL PESO TOTAL con el relleno dentro (`CHN-10`). Si alguien lo calculase descontando el relleno le saldria el 100 % y el semáforo dejaría pasar cualquier cosa: por eso invertir las dos bases esta prohibido. Y NO es chocolate relleno lo que lleva interior de panadería, pastelería, galleteria, bollería o helado (`CHN-04`).
A86: CT1 | B86: Tableta de chocolate a la taza, 200 g | C86: Chocolate a la taza | D86: Cobertura negra | E86: 80 | F86: 120 | G86: =IFERROR(E86+F86,"") -> 200 | H86: masa a la taza | I86: =IFERROR(VLOOKUP(D86,'Parámetros'!$A$48:$B$73,2,FALSE),"") -> 22.7455 | J86: =IFERROR(E86/1000*I86,"") -> 1.81964 | K86: =IFERROR(VLOOKUP(H86,'Escandallo por Molde y Tanda'!$A$52:$B$66,2,FALSE),"") -> 4.331 | L86: =IFERROR(F86/1000*K86,"") -> 0.51972 | M86: =IFERROR(J86+L86,"") -> 2.33936 | N86: ='Merma de Templado y Recortes'!E23 -> 0.01 | O86: =IFERROR(M86/(1-N86),"") -> 2.3629899 | P86: El almidón (9,6 g sobre 200, el 4,8 %) esta por debajo del tope del 8 %. Se usa ALMIDÓN DE MAÍZ a propósito: con almidón de TRIGO habría que declarar gluten, y la norma admite los tres. La etiqueta lleva además la expresión «para su consumo cocido» (ap. 6.e): es una ADICION ESPAÑOLA que NO existe en la Directiva 2000/36/CE (`CHN-83`), así que no se escribe que sea un requisito europeo.
A87: CT2 | B87: Caja de 6 sobres monodosis de chocolate a la taza | C87: Chocolate a la taza | D87: Cobertura negra | E87: 72 | F87: 108 | G87: =IFERROR(E87+F87,"") -> 180 | H87: masa a la taza | I87: =IFERROR(VLOOKUP(D87,'Parámetros'!$A$48:$B$73,2,FALSE),"") -> 22.7455 | J87: =IFERROR(E87/1000*I87,"") -> 1.637676 | K87: =IFERROR(VLOOKUP(H87,'Escandallo por Molde y Tanda'!$A$52:$B$66,2,FALSE),"") -> 4.331 | L87: =IFERROR(F87/1000*K87,"") -> 0.467748 | M87: =IFERROR(J87+L87,"") -> 2.105424 | N87: ='Merma de Templado y Recortes'!E24 -> 0.01 | O87: =IFERROR(M87/(1-N87),"") -> 2.1266909 | P87: Seis sobres de 30 g. Ojo al art. 2.2.c) del RD 1808/1991: los envases cuya cara mayor mide menos de 10 cm2 están exentos de lote, pero la CAJA que los contiene no (`CHN-36`).
A88: CT3 | B88: Chocolate a la taza servido en sala, 200 ml | C88: Chocolate a la taza | D88: Cobertura negra | E88: 18 | F88: 27 | G88: =IFERROR(E88+F88,"") -> 45 | H88: masa a la taza | I88: =IFERROR(VLOOKUP(D88,'Parámetros'!$A$48:$B$73,2,FALSE),"") -> 22.7455 | J88: =IFERROR(E88/1000*I88,"") -> 0.409419 | K88: =IFERROR(VLOOKUP(H88,'Escandallo por Molde y Tanda'!$A$52:$B$66,2,FALSE),"") -> 4.331 | L88: =IFERROR(F88/1000*K88,"") -> 0.116937 | M88: =IFERROR(J88+L88,"") -> 0.526356 | N88: ='Merma de Templado y Recortes'!E25 -> 0.06 | O88: =IFERROR(M88/(1-N88),"") -> 0.55995319 | P88: Aquí NO entregas un bien: prestas un servicio de hostelería, y el IVA va al 10 % por el art. 91.Uno.2.2.o (`CHN-71c`). No lleva etiqueta, así que su referencia es tu sistema de autocontrol (D47). Y si pones mesas, el art. 8 de la Ley 1/2025 te obliga a facilitar que el cliente se lleve lo que no ha consumido, aunque seas microempresa: la exclusión del art. 6.6 NO alcanza al art. 8 (`CHN-92`). Es la pieza que sube el ticket del churro un 40-60 % en la variante de taza (`CHS-32`), y es OTRO negocio (D1).
A89: TF1 | B89: Huevo de Pascua de chocolate con leche, 250 g | C89: Turrones, figuras y temporada | D89: Cobertura con leche | E89: 250 | F89: 0 | G89: =IFERROR(E89+F89,"") -> 250 | H89: No lleva | I89: =IFERROR(VLOOKUP(D89,'Parámetros'!$A$48:$B$73,2,FALSE),"") -> 19.5 | J89: =IFERROR(E89/1000*I89,"") -> 4.875 | K89: 0 | L89: =IFERROR(F89/1000*K89,"") -> 0 | M89: =IFERROR(J89+L89,"") -> 4.875 | N89: ='Merma de Templado y Recortes'!E26 -> 0.02 | O89: =IFERROR(M89/(1-N89),"") -> 4.9744898 | P89: La merma recuperable mas alta del catálogo: la pieza hueca se raja con los cambios bruscos de temperatura (nota del kit) y lo que se rompe SIN relleno vuelve entero a la cuba. Cero mix en verano: es de campana.
A90: TF2 | B90: Mona de Pascua de chocolate, 400 g | C90: Turrones, figuras y temporada | D90: Cobertura con leche | E90: 380 | F90: 20 | G90: =IFERROR(E90+F90,"") -> 400 | H90: Almendra marcona repelada | I90: =IFERROR(VLOOKUP(D90,'Parámetros'!$A$48:$B$73,2,FALSE),"") -> 19.5 | J90: =IFERROR(E90/1000*I90,"") -> 7.41 | K90: =IFERROR(VLOOKUP(H90,'Escandallo por Molde y Tanda'!$A$52:$B$66,2,FALSE),"") -> 12.4 | L90: =IFERROR(F90/1000*K90,"") -> 0.248 | M90: =IFERROR(J90+L90,"") -> 7.658 | N90: ='Merma de Templado y Recortes'!E27 -> 0.02 | O90: =IFERROR(M90/(1-N90),"") -> 7.8142857 | P90: Pieza de autor y la que mas minutos de obrador se lleva: 210 por tanda de seis. La decoración va como materia añadida del ap. 3. Es la referencia que pone a prueba la capacidad del libro 1 en abril.
A91: TF3 | B91: Hueso de santo bañado en chocolate | C91: Turrones, figuras y temporada | D91: Cobertura negra | E91: 9 | F91: 21 | G91: =IFERROR(E91+F91,"") -> 30 | H91: yema tostada | I91: =IFERROR(VLOOKUP(D91,'Parámetros'!$A$48:$B$73,2,FALSE),"") -> 22.7455 | J91: =IFERROR(E91/1000*I91,"") -> 0.2047095 | K91: =IFERROR(VLOOKUP(H91,'Escandallo por Molde y Tanda'!$A$52:$B$66,2,FALSE),"") -> 2.589 | L91: =IFERROR(F91/1000*K91,"") -> 0.054369 | M91: =IFERROR(J91+L91,"") -> 0.2590785 | N91: ='Merma de Templado y Recortes'!E28 -> 0.06 | O91: =IFERROR(M91/(1-N91),"") -> 0.27561543 | P91: LA REFERENCIA QUE ROMPE LA REGLA, y por eso esta aquí: 9 g de chocolate sobre 30 g de pieza son el 30 %, pero NO es un bombón de chocolate, porque el 1.13 pide una pieza «del tamaño de un bocado constituida por chocolate», y esto es un producto de confitería RECUBIERTO. Su denominación sale del RD 348/2011 (`CHN-15`), no del RD 1055/2003. La ÚNICA con huevo, por la yema, y va con ovoproducto pasteurizado (`CHN-31`). Esta literalmente en el calendario del kit: «Todos los Santos (1): panellets y huesos de santo bañados».
A92: TF4 | B92: Turrón de chocolate con almendra, 250 g | C92: Turrones, figuras y temporada | D92: Cobertura negra | E92: 168 | F92: 82 | G92: =IFERROR(E92+F92,"") -> 250 | H92: Almendra marcona repelada | I92: =IFERROR(VLOOKUP(D92,'Parámetros'!$A$48:$B$73,2,FALSE),"") -> 22.7455 | J92: =IFERROR(E92/1000*I92,"") -> 3.821244 | K92: =IFERROR(VLOOKUP(H92,'Escandallo por Molde y Tanda'!$A$52:$B$66,2,FALSE),"") -> 12.4 | L92: =IFERROR(F92/1000*K92,"") -> 1.0168 | M92: =IFERROR(J92+L92,"") -> 4.838044 | N92: ='Merma de Templado y Recortes'!E29 -> 0.02 | O92: =IFERROR(M92/(1-N92),"") -> 4.9367796 | P92: HUECO DECLARADO: la denominación que publica este juego de datos es la del RD 1055/2003, porque la norma de calidad de TURRONES no se abrio en la verificación legal del 12-09-2026 y ninguna ficha `CHN-*` la cubre. «Turrón de chocolate con almendra» es el NOMBRE COMERCIAL; antes de imprimir la etiqueta hay que comprobar si la norma de turrones te obliga a otra denominación de venta. La almendra (82 g sobre 250, el 32,8 %) esta dentro del tope del 40 % del ap. 3 (`CHN-09`).
A93: TF5 | B93: Almendras marcona bañadas en chocolate, bolsa de 150 g | C93: Turrones, figuras y temporada | D93: Cobertura negra | E93: 88 | F93: 62 | G93: =IFERROR(E93+F93,"") -> 150 | H93: Almendra marcona repelada | I93: =IFERROR(VLOOKUP(D93,'Parámetros'!$A$48:$B$73,2,FALSE),"") -> 22.7455 | J93: =IFERROR(E93/1000*I93,"") -> 2.001604 | K93: =IFERROR(VLOOKUP(H93,'Escandallo por Molde y Tanda'!$A$52:$B$66,2,FALSE),"") -> 12.4 | L93: =IFERROR(F93/1000*K93,"") -> 0.7688 | M93: =IFERROR(J93+L93,"") -> 2.770404 | N93: ='Merma de Templado y Recortes'!E30 -> 0.02 | O93: =IFERROR(M93/(1-N93),"") -> 2.8269429 | P93: La que da nombre a la casa, y su denominación NO sale del RD 1055/2003 sino del RD 348/2011: «grageas o confites de chocolate» (`CHN-15`). Se hace en bombo, no en molde: `moldes_tanda` vale 1 y los 95 minutos son de la tanda entera, de la que salen 40 bolsas. Es la segunda que mas sube en verano: no lleva agua y es souvenir (literal del kit para julio: «packs souvenir y colaboraciones locales»).
A94: CJ1 | B94: Caja surtida de 12 bombones | C94: Cajas y regalo | D94: No aplica: caja surtida | E94: ='Unidad vs Caja'!C20 -> 62.5 | F94: =IFERROR('Unidad vs Caja'!C21-'Unidad vs Caja'!C20,"") -> 82.5 | G94: =IFERROR(E94+F94,"") -> 145 | H94: Se compone de sus bombones | M94: ='Unidad vs Caja'!C23 -> 2.3233064 | N94: ='Merma de Templado y Recortes'!E31 -> 0.005 | O94: =IFERROR(M94/(1-N94),"") -> 2.3349814 | P94: Una caja no tiene escandallo propio: su coste de materia es el de los bombones que lleva dentro, y se calcula en la hoja «Unidad vs Caja». Lo que sí tiene propio es la merma de montaje y los minutos de montar y lazar.
A95: CJ2 | B95: Caja surtida de 20 bombones | C95: Cajas y regalo | D95: No aplica: caja surtida | E95: ='Unidad vs Caja'!D20 -> 102.5 | F95: =IFERROR('Unidad vs Caja'!D21-'Unidad vs Caja'!D20,"") -> 142.5 | G95: =IFERROR(E95+F95,"") -> 245 | H95: Se compone de sus bombones | M95: ='Unidad vs Caja'!D23 -> 4.0027907 | N95: ='Merma de Templado y Recortes'!E32 -> 0.005 | O95: =IFERROR(M95/(1-N95),"") -> 4.0229053 | P95: Una caja no tiene escandallo propio: su coste de materia es el de los bombones que lleva dentro, y se calcula en la hoja «Unidad vs Caja». Lo que sí tiene propio es la merma de montaje y los minutos de montar y lazar.
A96: CJ3 | B96: Caja surtida de 35 bombones | C96: Cajas y regalo | D96: No aplica: caja surtida | E96: ='Unidad vs Caja'!E20 -> 181 | F96: =IFERROR('Unidad vs Caja'!E21-'Unidad vs Caja'!E20,"") -> 247 | G96: =IFERROR(E96+F96,"") -> 428 | H96: Se compone de sus bombones | M96: ='Unidad vs Caja'!E23 -> 6.9099117 | N96: ='Merma de Templado y Recortes'!E33 -> 0.005 | O96: =IFERROR(M96/(1-N96),"") -> 6.9446349 | P96: Una caja no tiene escandallo propio: su coste de materia es el de los bombones que lleva dentro, y se calcula en la hoja «Unidad vs Caja». Lo que sí tiene propio es la merma de montaje y los minutos de montar y lazar.
A97: CJ4 | B97: Estuche corporativo personalizado de 24 bombones | C97: Cajas y regalo | D97: No aplica: caja surtida | E97: ='Unidad vs Caja'!F20 -> 123 | F97: =IFERROR('Unidad vs Caja'!F21-'Unidad vs Caja'!F20,"") -> 170 | G97: =IFERROR(E97+F97,"") -> 293 | H97: Se compone de sus bombones | M97: ='Unidad vs Caja'!F23 -> 4.7264465 | N97: ='Merma de Templado y Recortes'!E34 -> 0.005 | O97: =IFERROR(M97/(1-N97),"") -> 4.7501975 | P97: Una caja no tiene escandallo propio: su coste de materia es el de los bombones que lleva dentro, y se calcula en la hoja «Unidad vs Caja». Lo que sí tiene propio es la merma de montaje y los minutos de montar y lazar.
A99: Versión 1.0 · septiembre 2026 · aichef.pro/guia-chocolateria-obrador · info@aichef.pro

Sheet Merma de Templado y Recortes
A1: Merma de Templado y Recortes
A2: AI Chef Pro · aichef.pro — Cómo Montar una Chocolatería
A3: DOS tasas por referencia, y la regla es del kit: «El chocolate sin relleno y sin contaminar se puede refundir; el que lleva ganache o fruta, a residuo» (02-partidas-produccion.xlsx, hoja «Moldeado»). Lo que vuelve a la cuba no encarece la materia; lo que se tira, sí.
A6: Id | B6: Referencia | C6: ¿Lleva ganache, relleno o fruta? | D6: Merma RECUPERABLE (vuelve a la cuba) | E6: Merma NO RECUPERABLE (a residuo) | F6: Coste de materia sin merma (EUR) | G6: Coste real con el recorte que vuelve (EUR) | H6: Sobrecoste de la merma (EUR) | I6: Sobrecoste sobre el coste | J6: Chocolate limpio que vuelve a la cuba (g/pieza) | K6: Producto que va a residuo (g/pieza) | L6: Unidades al año | M6: Kilos al año que vuelven a la cuba | N6: Kilos al año a residuo | O6: Coste anual de la merma no recuperable (EUR) | P6: Nota
A7: BC1 | B7: Bombón de ganache de chocolate negro 70 % | C7: Sí | D7: 0.04 | E7: 0.03 | F7: ='Escandallo por Molde y Tanda'!M70 -> 0.21760604 | G7: ='Escandallo por Molde y Tanda'!O70 -> 0.22433612 | H7: =IFERROR(G7-F7,"") -> 0.0067300837 | I7: =IFERROR(H7/F7,"") -> 0.030927835 | J7: =IFERROR('Escandallo por Molde y Tanda'!E70*D7,"") -> 0.22 | K7: =IFERROR('Escandallo por Molde y Tanda'!G70*E7,"") -> 0.36 | L7: ='Mix y Ticket Medio'!K7 -> 1710.912 | M7: =IFERROR(J7*L7/1000,"") -> 0.37640064 | N7: =IFERROR(K7*L7/1000,"") -> 0.61592832 | O7: =IFERROR(H7*L7,"") -> 11.514581 | P7: Lleva ganache, relleno o fruta: lo que se recorta va a residuo y se reparte entre las piezas que salen bien.
A8: BC2 | B8: Bombón de ganache de leche y vainilla | C8: Sí | D8: 0.04 | E8: 0.03 | F8: ='Escandallo por Molde y Tanda'!M71 -> 0.190684 | G8: ='Escandallo por Molde y Tanda'!O71 -> 0.19658144 | H8: =IFERROR(G8-F8,"") -> 0.0058974433 | I8: =IFERROR(H8/F8,"") -> 0.030927835 | J8: =IFERROR('Escandallo por Molde y Tanda'!E71*D8,"") -> 0.22 | K8: =IFERROR('Escandallo por Molde y Tanda'!G71*E8,"") -> 0.36 | L8: ='Mix y Ticket Medio'!K8 -> 1425.76 | M8: =IFERROR(J8*L8/1000,"") -> 0.3136672 | N8: =IFERROR(K8*L8/1000,"") -> 0.5132736 | O8: =IFERROR(H8*L8,"") -> 8.4083388 | P8: Lleva ganache, relleno o fruta: lo que se recorta va a residuo y se reparte entre las piezas que salen bien.
A9: BC3 | B9: Bombón de praliné de avellana | C9: Sí | D9: 0.04 | E9: 0.02 | F9: ='Escandallo por Molde y Tanda'!M72 -> 0.213448 | G9: ='Escandallo por Molde y Tanda'!O72 -> 0.21780408 | H9: =IFERROR(G9-F9,"") -> 0.0043560816 | I9: =IFERROR(H9/F9,"") -> 0.020408163 | J9: =IFERROR('Escandallo por Molde y Tanda'!E72*D9,"") -> 0.2 | K9: =IFERROR('Escandallo por Molde y Tanda'!G72*E9,"") -> 0.24 | L9: ='Mix y Ticket Medio'!K9 -> 1710.912 | M9: =IFERROR(J9*L9/1000,"") -> 0.3421824 | N9: =IFERROR(K9*L9/1000,"") -> 0.41061888 | O9: =IFERROR(H9*L9,"") -> 7.4528723 | P9: Lleva ganache, relleno o fruta: lo que se recorta va a residuo y se reparte entre las piezas que salen bien.
A10: BC4 | B10: Bombón de gianduja de avellana | C10: Sí | D10: 0.04 | E10: 0.02 | F10: ='Escandallo por Molde y Tanda'!M73 -> 0.2243435 | G10: ='Escandallo por Molde y Tanda'!O73 -> 0.22892194 | H10: =IFERROR(G10-F10,"") -> 0.0045784388 | I10: =IFERROR(H10/F10,"") -> 0.020408163 | J10: =IFERROR('Escandallo por Molde y Tanda'!E73*D10,"") -> 0.2 | K10: =IFERROR('Escandallo por Molde y Tanda'!G73*E10,"") -> 0.24 | L10: ='Mix y Ticket Medio'!K10 -> 1140.608 | M10: =IFERROR(J10*L10/1000,"") -> 0.2281216 | N10: =IFERROR(K10*L10/1000,"") -> 0.27374592 | O10: =IFERROR(H10*L10,"") -> 5.2222039 | P10: Lleva ganache, relleno o fruta: lo que se recorta va a residuo y se reparte entre las piezas que salen bien.
A11: BC5 | B11: Trufa de chocolate negro al cacao | C11: Sí | D11: 0.03 | E11: 0.04 | F11: ='Escandallo por Molde y Tanda'!M74 -> 0.21808513 | G11: ='Escandallo por Molde y Tanda'!O74 -> 0.22717201 | H11: =IFERROR(G11-F11,"") -> 0.0090868804 | I11: =IFERROR(H11/F11,"") -> 0.041666667 | J11: =IFERROR('Escandallo por Molde y Tanda'!E74*D11,"") -> 0.12 | K11: =IFERROR('Escandallo por Molde y Tanda'!G74*E11,"") -> 0.52 | L11: ='Mix y Ticket Medio'!K11 -> 1425.76 | M11: =IFERROR(J11*L11/1000,"") -> 0.1710912 | N11: =IFERROR(K11*L11/1000,"") -> 0.7413952 | O11: =IFERROR(H11*L11,"") -> 12.955711 | P11: Lleva ganache, relleno o fruta: lo que se recorta va a residuo y se reparte entre las piezas que salen bien.
A12: BC6 | B12: Bombón de licor de ron | C12: Sí | D12: 0.05 | E12: 0.04 | F12: ='Escandallo por Molde y Tanda'!M75 -> 0.172889 | G12: ='Escandallo por Molde y Tanda'!O75 -> 0.18009271 | H12: =IFERROR(G12-F12,"") -> 0.0072037083 | I12: =IFERROR(H12/F12,"") -> 0.041666667 | J12: =IFERROR('Escandallo por Molde y Tanda'!E75*D12,"") -> 0.3 | K12: =IFERROR('Escandallo por Molde y Tanda'!G75*E12,"") -> 0.56 | L12: ='Mix y Ticket Medio'!K12 -> 855.456 | M12: =IFERROR(J12*L12/1000,"") -> 0.2566368 | N12: =IFERROR(K12*L12/1000,"") -> 0.47905536 | O12: =IFERROR(H12*L12,"") -> 6.1624555 | P12: Lleva ganache, relleno o fruta: lo que se recorta va a residuo y se reparte entre las piezas que salen bien.
A13: BC7 | B13: Bombón de caramelo salado | C13: Sí | D13: 0.04 | E13: 0.03 | F13: ='Escandallo por Molde y Tanda'!M76 -> 0.1331798 | G13: ='Escandallo por Molde y Tanda'!O76 -> 0.13729876 | H13: =IFERROR(G13-F13,"") -> 0.0041189629 | I13: =IFERROR(H13/F13,"") -> 0.030927835 | J13: =IFERROR('Escandallo por Molde y Tanda'!E76*D13,"") -> 0.22 | K13: =IFERROR('Escandallo por Molde y Tanda'!G76*E13,"") -> 0.36 | L13: ='Mix y Ticket Medio'!K13 -> 1140.608 | M13: =IFERROR(J13*L13/1000,"") -> 0.25093376 | N13: =IFERROR(K13*L13/1000,"") -> 0.41061888 | O13: =IFERROR(H13*L13,"") -> 4.698122 | P13: Lleva ganache, relleno o fruta: lo que se recorta va a residuo y se reparte entre las piezas que salen bien.
A14: BC8 | B14: Bombón de praliné de cacahuete | C14: Sí | D14: 0.04 | E14: 0.02 | F14: ='Escandallo por Molde y Tanda'!M77 -> 0.186582 | G14: ='Escandallo por Molde y Tanda'!O77 -> 0.1903898 | H14: =IFERROR(G14-F14,"") -> 0.0038077959 | I14: =IFERROR(H14/F14,"") -> 0.020408163 | J14: =IFERROR('Escandallo por Molde y Tanda'!E77*D14,"") -> 0.2 | K14: =IFERROR('Escandallo por Molde y Tanda'!G77*E14,"") -> 0.24 | L14: ='Mix y Ticket Medio'!K14 -> 855.456 | M14: =IFERROR(J14*L14/1000,"") -> 0.1710912 | N14: =IFERROR(K14*L14/1000,"") -> 0.20530944 | O14: =IFERROR(H14*L14,"") -> 3.2574019 | P14: Lleva ganache, relleno o fruta: lo que se recorta va a residuo y se reparte entre las piezas que salen bien.
A15: BC9 | B15: Bombón crujiente de sésamo y barquillo | C15: Sí | D15: 0.04 | E15: 0.02 | F15: ='Escandallo por Molde y Tanda'!M78 -> 0.190446 | G15: ='Escandallo por Molde y Tanda'!O78 -> 0.19433265 | H15: =IFERROR(G15-F15,"") -> 0.0038866531 | I15: =IFERROR(H15/F15,"") -> 0.020408163 | J15: =IFERROR('Escandallo por Molde y Tanda'!E78*D15,"") -> 0.2 | K15: =IFERROR('Escandallo por Molde y Tanda'!G78*E15,"") -> 0.24 | L15: ='Mix y Ticket Medio'!K15 -> 855.456 | M15: =IFERROR(J15*L15/1000,"") -> 0.1710912 | N15: =IFERROR(K15*L15/1000,"") -> 0.20530944 | O15: =IFERROR(H15*L15,"") -> 3.3248607 | P15: Lleva ganache, relleno o fruta: lo que se recorta va a residuo y se reparte entre las piezas que salen bien.
A16: BC10 | B16: Bombón de naranja confitada y chocolate negro | C16: Sí | D16: 0.03 | E16: 0.05 | F16: ='Escandallo por Molde y Tanda'!M79 -> 0.21835763 | G16: ='Escandallo por Molde y Tanda'!O79 -> 0.22985014 | H16: =IFERROR(G16-F16,"") -> 0.011492507 | I16: =IFERROR(H16/F16,"") -> 0.052631579 | J16: =IFERROR('Escandallo por Molde y Tanda'!E79*D16,"") -> 0.165 | K16: =IFERROR('Escandallo por Molde y Tanda'!G79*E16,"") -> 0.6 | L16: ='Mix y Ticket Medio'!K16 -> 855.456 | M16: =IFERROR(J16*L16/1000,"") -> 0.14115024 | N16: =IFERROR(K16*L16/1000,"") -> 0.5132736 | O16: =IFERROR(H16*L16,"") -> 9.8313342 | P16: Lleva ganache, relleno o fruta: lo que se recorta va a residuo y se reparte entre las piezas que salen bien.
A17: TB1 | B17: Tableta de chocolate negro de origen 70 %, 100 g | C17: No | D17: 0.06 | E17: 0.01 | F17: ='Escandallo por Molde y Tanda'!M80 -> 3.748 | G17: ='Escandallo por Molde y Tanda'!O80 -> 3.7858586 | H17: =IFERROR(G17-F17,"") -> 0.037858586 | I17: =IFERROR(H17/F17,"") -> 0.01010101 | J17: =IFERROR('Escandallo por Molde y Tanda'!E80*D17,"") -> 6 | K17: =IFERROR('Escandallo por Molde y Tanda'!G80*E17,"") -> 1 | L17: ='Mix y Ticket Medio'!K17 -> 1996.064 | M17: =IFERROR(J17*L17/1000,"") -> 11.976384 | N17: =IFERROR(K17*L17/1000,"") -> 1.996064 | O17: =IFERROR(H17*L17,"") -> 75.56816 | P17: El recorte limpio vuelve a la cuba: no es coste de materia, pero hay que volver a templarlo y ese trabajo lo paga la mano de obra.
A18: TB2 | B18: Tableta de chocolate con leche 38 %, 100 g | C18: No | D18: 0.06 | E18: 0.01 | F18: ='Escandallo por Molde y Tanda'!M81 -> 1.95 | G18: ='Escandallo por Molde y Tanda'!O81 -> 1.969697 | H18: =IFERROR(G18-F18,"") -> 0.01969697 | I18: =IFERROR(H18/F18,"") -> 0.01010101 | J18: =IFERROR('Escandallo por Molde y Tanda'!E81*D18,"") -> 6 | K18: =IFERROR('Escandallo por Molde y Tanda'!G81*E18,"") -> 1 | L18: ='Mix y Ticket Medio'!K18 -> 1710.912 | M18: =IFERROR(J18*L18/1000,"") -> 10.265472 | N18: =IFERROR(K18*L18/1000,"") -> 1.710912 | O18: =IFERROR(H18*L18,"") -> 33.699782 | P18: El recorte limpio vuelve a la cuba: no es coste de materia, pero hay que volver a templarlo y ese trabajo lo paga la mano de obra.
... A34: CJ4 | B34: Estuche corporativo personalizado de 24 bombones | C34: Sí | D34: 0 | E34: 0.005 | F34: ='Escandallo por Molde y Tanda'!M97 -> 4.7264465 | G34: ='Escandallo por Molde y Tanda'!O97 -> 4.7501975 | H34: =IFERROR(G34-F34,"") -> 0.023750988 | I34: =IFERROR(H34/F34,"") -> 0.0050251256 | J34: =IFERROR('Escandallo por Molde y Tanda'!E97*D34,"") -> 0 | K34: =IFERROR('Escandallo por Molde y Tanda'!G97*E34,"") -> 1.465 | L34: ='Mix y Ticket Medio'!K34 -> 285.152 | M34: =IFERROR(J34*L34/1000,"") -> 0 | N34: =IFERROR(K34*L34/1000,"") -> 0.41774768 | O34: =IFERROR(H34*L34,"") -> 6.7726416 | P34: Lleva ganache, relleno o fruta: lo que se recorta va a residuo y se reparte entre las piezas que salen bien.
A35: TOTAL del año | M35: =SUM(M7:M34) -> 86.413888 | N35: =SUM(N7:N34) -> 38.314448 | O35: =SUM(O7:O34) -> 718.76662
A37: Los kilos que vuelven a la cuba NO son un ahorro que apuntar en ningún sitio: son chocolate que ya has pagado y que no vuelves a pagar. Lo que sí es una decisión es cuánto recortas: si la columna de residuo se dispara, el problema no es el precio del cacao, es el molde o la mano.
A39: Versión 1.0 · septiembre 2026 · aichef.pro/guia-chocolateria-obrador · info@aichef.pro

Sheet Coste Hora y Mano de Obra
A1: Coste Hora y Mano de Obra
A2: AI Chef Pro · aichef.pro — Cómo Montar una Chocolatería
A3: La unidad de costeo es la TANDA: piezas por molde por moldes por tanda. Los minutos se reparten entre las piezas que SALEN BIEN, no entre las que entran.
A6: Id | B6: Referencia | C6: Piezas por molde | D6: Moldes por tanda | E6: Piezas por tanda | F6: Minutos de la tanda | G6: Piezas buenas por tanda | H6: Minutos por pieza buena | I6: Coste de mano de obra de la tanda o el montaje (EUR) | J6: Coste de mano de obra de las piezas de dentro (EUR) | K6: COSTE DE MANO DE OBRA POR PIEZA (EUR) | L6: Coste de materia con merma (EUR) | M6: COSTE TOTAL POR PIEZA (EUR) | N6: PVP con IVA (EUR) | O6: Tipo de IVA | P6: PVP sin IVA (EUR) | Q6: Food cost | R6: Margen (EUR) | S6: Margen sobre PVP | T6: PVP sin IVA que pide tu regla de margen (EUR) | U6: PVP con IVA que pide tu regla de margen (EUR) | V6: Nota
A7: BC1 | B7: Bombón de ganache de chocolate negro 70 % | C7: 24 | D7: 6 | E7: =C7*D7 -> 144 | F7: 155 | G7: =IFERROR(E7*(1-'Merma de Templado y Recortes'!E7),"") -> 139.68 | H7: =IFERROR(F7/G7,"") -> 1.1096793 | I7: =IFERROR(H7/60*'Parámetros'!$B$15,"") -> 0.34199684 | J7: 0 | K7: =IFERROR(I7+J7,"") -> 0.34199684 | L7: ='Escandallo por Molde y Tanda'!O70 -> 0.22433612 | M7: =IFERROR(K7+L7,"") -> 0.56633297 | N7: 2 | O7: ='Parámetros'!$B$18 -> 0.1 | P7: =IFERROR(N7/(1+O7),"") -> 1.8181818 | Q7: =IFERROR(L7/P7,"") -> 0.12338487 | R7: =IFERROR(P7-M7,"") -> 1.2518489 | S7: =IFERROR(R7/P7,"") -> 0.68851687 | T7: =IFERROR(L7/'Parámetros'!$B$22,"") -> 0.74778708 | U7: =IFERROR(T7*(1+O7),"") -> 0.82256579 | V7: Cero real, no «sin dato»: esta referencia no lleva piezas terminadas dentro.
A8: BC2 | B8: Bombón de ganache de leche y vainilla | C8: 24 | D8: 6 | E8: =C8*D8 -> 144 | F8: 155 | G8: =IFERROR(E8*(1-'Merma de Templado y Recortes'!E8),"") -> 139.68 | H8: =IFERROR(F8/G8,"") -> 1.1096793 | I8: =IFERROR(H8/60*'Parámetros'!$B$15,"") -> 0.34199684 | J8: 0 | K8: =IFERROR(I8+J8,"") -> 0.34199684 | L8: ='Escandallo por Molde y Tanda'!O71 -> 0.19658144 | M8: =IFERROR(K8+L8,"") -> 0.53857829 | N8: 1.95 | O8: ='Parámetros'!$B$18 -> 0.1 | P8: =IFERROR(N8/(1+O8),"") -> 1.7727273 | Q8: =IFERROR(L8/P8,"") -> 0.1108921 | R8: =IFERROR(P8-M8,"") -> 1.234149 | S8: =IFERROR(R8/P8,"") -> 0.69618661 | T8: =IFERROR(L8/'Parámetros'!$B$22,"") -> 0.65527148 | U8: =IFERROR(T8*(1+O8),"") -> 0.72079863 | V8: Cero real, no «sin dato»: esta referencia no lleva piezas terminadas dentro.
A9: BC3 | B9: Bombón de praliné de avellana | C9: 24 | D9: 6 | E9: =C9*D9 -> 144 | F9: 140 | G9: =IFERROR(E9*(1-'Merma de Templado y Recortes'!E9),"") -> 141.12 | H9: =IFERROR(F9/G9,"") -> 0.99206349 | I9: =IFERROR(H9/60*'Parámetros'!$B$15,"") -> 0.30574833 | J9: 0 | K9: =IFERROR(I9+J9,"") -> 0.30574833 | L9: ='Escandallo por Molde y Tanda'!O72 -> 0.21780408 | M9: =IFERROR(K9+L9,"") -> 0.52355241 | N9: 2.1 | O9: ='Parámetros'!$B$18 -> 0.1 | P9: =IFERROR(N9/(1+O9),"") -> 1.9090909 | Q9: =IFERROR(L9/P9,"") -> 0.11408785 | R9: =IFERROR(P9-M9,"") -> 1.3855385 | S9: =IFERROR(R9/P9,"") -> 0.72575826 | T9: =IFERROR(L9/'Parámetros'!$B$22,"") -> 0.72601361 | U9: =IFERROR(T9*(1+O9),"") -> 0.79861497 | V9: Cero real, no «sin dato»: esta referencia no lleva piezas terminadas dentro.
A10: BC4 | B10: Bombón de gianduja de avellana | C10: 24 | D10: 5 | E10: =C10*D10 -> 120 | F10: 130 | G10: =IFERROR(E10*(1-'Merma de Templado y Recortes'!E10),"") -> 117.6 | H10: =IFERROR(F10/G10,"") -> 1.1054422 | I10: =IFERROR(H10/60*'Parámetros'!$B$15,"") -> 0.340691 | J10: 0 | K10: =IFERROR(I10+J10,"") -> 0.340691 | L10: ='Escandallo por Molde y Tanda'!O73 -> 0.22892194 | M10: =IFERROR(K10+L10,"") -> 0.56961293 | N10: 2.1 | O10: ='Parámetros'!$B$18 -> 0.1 | P10: =IFERROR(N10/(1+O10),"") -> 1.9090909 | Q10: =IFERROR(L10/P10,"") -> 0.11991149 | R10: =IFERROR(P10-M10,"") -> 1.339478 | S10: =IFERROR(R10/P10,"") -> 0.70163132 | T10: =IFERROR(L10/'Parámetros'!$B$22,"") -> 0.76307313 | U10: =IFERROR(T10*(1+O10),"") -> 0.83938044 | V10: Cero real, no «sin dato»: esta referencia no lleva piezas terminadas dentro.
A11: BC5 | B11: Trufa de chocolate negro al cacao | C11: 40 | D11: 4 | E11: =C11*D11 -> 160 | F11: 120 | G11: =IFERROR(E11*(1-'Merma de Templado y Recortes'!E11),"") -> 153.6 | H11: =IFERROR(F11/G11,"") -> 0.78125 | I11: =IFERROR(H11/60*'Parámetros'!$B$15,"") -> 0.24077681 | J11: 0 | K11: =IFERROR(I11+J11,"") -> 0.24077681 | L11: ='Escandallo por Molde y Tanda'!O74 -> 0.22717201 | M11: =IFERROR(K11+L11,"") -> 0.46794882 | N11: 1.9 | O11: ='Parámetros'!$B$18 -> 0.1 | P11: =IFERROR(N11/(1+O11),"") -> 1.7272727 | Q11: =IFERROR(L11/P11,"") -> 0.13152064 | R11: =IFERROR(P11-M11,"") -> 1.2593239 | S11: =IFERROR(R11/P11,"") -> 0.72908226 | T11: =IFERROR(L11/'Parámetros'!$B$22,"") -> 0.75724003 | U11: =IFERROR(T11*(1+O11),"") -> 0.83296404 | V11: Cero real, no «sin dato»: esta referencia no lleva piezas terminadas dentro.
A12: BC6 | B12: Bombón de licor de ron | C12: 24 | D12: 4 | E12: =C12*D12 -> 96 | F12: 145 | G12: =IFERROR(E12*(1-'Merma de Templado y Recortes'!E12),"") -> 92.16 | H12: =IFERROR(F12/G12,"") -> 1.5733507 | I12: =IFERROR(H12/60*'Parámetros'!$B$15,"") -> 0.48489774 | J12: 0 | K12: =IFERROR(I12+J12,"") -> 0.48489774 | L12: ='Escandallo por Molde y Tanda'!O75 -> 0.18009271 | M12: =IFERROR(K12+L12,"") -> 0.66499045 | N12: 2.3 | O12: ='Parámetros'!$B$18 -> 0.1 | P12: =IFERROR(N12/(1+O12),"") -> 2.0909091 | Q12: =IFERROR(L12/P12,"") -> 0.086131295 | R12: =IFERROR(P12-M12,"") -> 1.4259186 | S12: =IFERROR(R12/P12,"") -> 0.68196109 | T12: =IFERROR(L12/'Parámetros'!$B$22,"") -> 0.60030903 | U12: =IFERROR(T12*(1+O12),"") -> 0.66033993 | V12: Cero real, no «sin dato»: esta referencia no lleva piezas terminadas dentro.
A13: BC7 | B13: Bombón de caramelo salado | C13: 24 | D13: 6 | E13: =C13*D13 -> 144 | F13: 150 | G13: =IFERROR(E13*(1-'Merma de Templado y Recortes'!E13),"") -> 139.68 | H13: =IFERROR(F13/G13,"") -> 1.0738832 | I13: =IFERROR(H13/60*'Parámetros'!$B$15,"") -> 0.33096469 | J13: 0 | K13: =IFERROR(I13+J13,"") -> 0.33096469 | L13: ='Escandallo por Molde y Tanda'!O76 -> 0.13729876 | M13: =IFERROR(K13+L13,"") -> 0.46826345 | N13: 2 | O13: ='Parámetros'!$B$18 -> 0.1 | P13: =IFERROR(N13/(1+O13),"") -> 1.8181818 | Q13: =IFERROR(L13/P13,"") -> 0.07551432 | R13: =IFERROR(P13-M13,"") -> 1.3499184 | S13: =IFERROR(R13/P13,"") -> 0.7424551 | T13: =IFERROR(L13/'Parámetros'!$B$22,"") -> 0.45766254 | U13: =IFERROR(T13*(1+O13),"") -> 0.5034288 | V13: Cero real, no «sin dato»: esta referencia no lleva piezas terminadas dentro.
A14: BC8 | B14: Bombón de praliné de cacahuete | C14: 24 | D14: 5 | E14: =C14*D14 -> 120 | F14: 135 | G14: =IFERROR(E14*(1-'Merma de Templado y Recortes'!E14),"") -> 117.6 | H14: =IFERROR(F14/G14,"") -> 1.1479592 | I14: =IFERROR(H14/60*'Parámetros'!$B$15,"") -> 0.3537945 | J14: 0 | K14: =IFERROR(I14+J14,"") -> 0.3537945 | L14: ='Escandallo por Molde y Tanda'!O77 -> 0.1903898 | M14: =IFERROR(K14+L14,"") -> 0.54418429 | N14: 1.95 | O14: ='Parámetros'!$B$18 -> 0.1 | P14: =IFERROR(N14/(1+O14),"") -> 1.7727273 | Q14: =IFERROR(L14/P14,"") -> 0.10739937 | R14: =IFERROR(P14-M14,"") -> 1.228543 | S14: =IFERROR(R14/P14,"") -> 0.69302425 | T14: =IFERROR(L14/'Parámetros'!$B$22,"") -> 0.63463265 | U14: =IFERROR(T14*(1+O14),"") -> 0.69809592 | V14: Cero real, no «sin dato»: esta referencia no lleva piezas terminadas dentro.
A15: BC9 | B15: Bombón crujiente de sésamo y barquillo | C15: 24 | D15: 5 | E15: =C15*D15 -> 120 | F15: 140 | G15: =IFERROR(E15*(1-'Merma de Templado y Recortes'!E15),"") -> 117.6 | H15: =IFERROR(F15/G15,"") -> 1.1904762 | I15: =IFERROR(H15/60*'Parámetros'!$B$15,"") -> 0.366898 | J15: 0 | K15: =IFERROR(I15+J15,"") -> 0.366898 | L15: ='Escandallo por Molde y Tanda'!O78 -> 0.19433265 | M15: =IFERROR(K15+L15,"") -> 0.56123065 | N15: 2.05 | O15: ='Parámetros'!$B$18 -> 0.1 | P15: =IFERROR(N15/(1+O15),"") -> 1.8636364 | Q15: =IFERROR(L15/P15,"") -> 0.10427606 | R15: =IFERROR(P15-M15,"") -> 1.3024057 | S15: =IFERROR(R15/P15,"") -> 0.69885185 | T15: =IFERROR(L15/'Parámetros'!$B$22,"") -> 0.64777551 | U15: =IFERROR(T15*(1+O15),"") -> 0.71255306 | V15: Cero real, no «sin dato»: esta referencia no lleva piezas terminadas dentro.
A16: BC10 | B16: Bombón de naranja confitada y chocolate negro | C16: 24 | D16: 5 | E16: =C16*D16 -> 120 | F16: 145 | G16: =IFERROR(E16*(1-'Merma de Templado y Recortes'!E16),"") -> 114 | H16: =IFERROR(F16/G16,"") -> 1.2719298 | I16: =IFERROR(H16/60*'Parámetros'!$B$15,"") -> 0.39200154 | J16: 0 | K16: =IFERROR(I16+J16,"") -> 0.39200154 | L16: ='Escandallo por Molde y Tanda'!O79 -> 0.22985014 | M16: =IFERROR(K16+L16,"") -> 0.62185168 | N16: 2.05 | O16: ='Parámetros'!$B$18 -> 0.1 | P16: =IFERROR(N16/(1+O16),"") -> 1.8636364 | Q16: =IFERROR(L16/P16,"") -> 0.12333422 | R16: =IFERROR(P16-M16,"") -> 1.2417847 | S16: =IFERROR(R16/P16,"") -> 0.66632349 | T16: =IFERROR(L16/'Parámetros'!$B$22,"") -> 0.76616714 | U16: =IFERROR(T16*(1+O16),"") -> 0.84278385 | V16: Cero real, no «sin dato»: esta referencia no lleva piezas terminadas dentro.
A17: TB1 | B17: Tableta de chocolate negro de origen 70 %, 100 g | C17: 3 | D17: 10 | E17: =C17*D17 -> 30 | F17: 55 | G17: =IFERROR(E17*(1-'Merma de Templado y Recortes'!E17),"") -> 29.7 | H17: =IFERROR(F17/G17,"") -> 1.8518519 | I17: =IFERROR(H17/60*'Parámetros'!$B$15,"") -> 0.57073021 | J17: 0 | K17: =IFERROR(I17+J17,"") -> 0.57073021 | L17: ='Escandallo por Molde y Tanda'!O80 -> 3.7858586 | M17: =IFERROR(K17+L17,"") -> 4.3565888 | N17: 8.5 | O17: ='Parámetros'!$B$18 -> 0.1 | P17: =IFERROR(N17/(1+O17),"") -> 7.7272727 | Q17: =IFERROR(L17/P17,"") -> 0.48993464 | R17: =IFERROR(P17-M17,"") -> 3.3706839 | S17: =IFERROR(R17/P17,"") -> 0.43620616 | T17: =IFERROR(L17/'Parámetros'!$B$22,"") -> 12.619529 | U17: =IFERROR(T17*(1+O17),"") -> 13.881481 | V17: Cero real, no «sin dato»: esta referencia no lleva piezas terminadas dentro.
A18: TB2 | B18: Tableta de chocolate con leche 38 %, 100 g | C18: 3 | D18: 10 | E18: =C18*D18 -> 30 | F18: 55 | G18: =IFERROR(E18*(1-'Merma de Templado y Recortes'!E18),"") -> 29.7 | H18: =IFERROR(F18/G18,"") -> 1.8518519 | I18: =IFERROR(H18/60*'Parámetros'!$B$15,"") -> 0.57073021 | J18: 0 | K18: =IFERROR(I18+J18,"") -> 0.57073021 | L18: ='Escandallo por Molde y Tanda'!O81 -> 1.969697 | M18: =IFERROR(K18+L18,"") -> 2.5404272 | N18: 5.9 | O18: ='Parámetros'!$B$18 -> 0.1 | P18: =IFERROR(N18/(1+O18),"") -> 5.3636364 | Q18: =IFERROR(L18/P18,"") -> 0.36723164 | R18: =IFERROR(P18-M18,"") -> 2.8232092 | S18: =IFERROR(R18/P18,"") -> 0.52636103 | T18: =IFERROR(L18/'Parámetros'!$B$22,"") -> 6.5656566 | U18: =IFERROR(T18*(1+O18),"") -> 7.2222222 | V18: Cero real, no «sin dato»: esta referencia no lleva piezas terminadas dentro.
... A24: CT2 | B24: Caja de 6 sobres monodosis de chocolate a la taza | C24: 6 | D24: 6 | E24: =C24*D24 -> 36 | F24: 95 | G24: =IFERROR(E24*(1-'Merma de Templado y Recortes'!E24),"") -> 35.64 | H24: =IFERROR(F24/G24,"") -> 2.6655443 | I24: =IFERROR(H24/60*'Parámetros'!$B$15,"") -> 0.82150561 | J24: 0 | K24: =IFERROR(I24+J24,"") -> 0.82150561 | L24: ='Escandallo por Molde y Tanda'!O87 -> 2.1266909 | M24: =IFERROR(K24+L24,"") -> 2.9481965 | N24: 7.8 | O24: ='Parámetros'!$B$18 -> 0.1 | P24: =IFERROR(N24/(1+O24),"") -> 7.0909091 | Q24: =IFERROR(L24/P24,"") -> 0.29991795 | R24: =IFERROR(P24-M24,"") -> 4.1427126 | S24: =IFERROR(R24/P24,"") -> 0.5842287 | T24: =IFERROR(L24/'Parámetros'!$B$22,"") -> 7.0889697 | U24: =IFERROR(T24*(1+O24),"") -> 7.7978667 | V24: Cero real, no «sin dato»: esta referencia no lleva piezas terminadas dentro.
A25: CT3 | B25: Chocolate a la taza servido en sala, 200 ml | C25: 1 | D25: 1 | E25: =C25*D25 -> 1 | F25: 3 | G25: =IFERROR(E25*(1-'Merma de Templado y Recortes'!E25),"") -> 0.94 | H25: =IFERROR(F25/G25,"") -> 3.1914894 | I25: =IFERROR(H25/60*'Parámetros'!$B$15,"") -> 0.98359888 | J25: 0 | K25: =IFERROR(I25+J25,"") -> 0.98359888 | L25: ='Escandallo por Molde y Tanda'!O88 -> 0.55995319 | M25: =IFERROR(K25+L25,"") -> 1.5435521 | N25: 3.2 | O25: ='Parámetros'!$B$19 -> 0.1 | P25: =IFERROR(N25/(1+O25),"") -> 2.9090909 | Q25: =IFERROR(L25/P25,"") -> 0.19248391 | R25: =IFERROR(P25-M25,"") -> 1.3655388 | S25: =IFERROR(R25/P25,"") -> 0.46940398 | T25: =IFERROR(L25/'Parámetros'!$B$22,"") -> 1.8665106 | U25: =IFERROR(T25*(1+O25),"") -> 2.0531617 | V25: Cero real, no «sin dato»: esta referencia no lleva piezas terminadas dentro.
A26: TF1 | B26: Huevo de Pascua de chocolate con leche, 250 g | C26: 2 | D26: 6 | E26: =C26*D26 -> 12 | F26: 150 | G26: =IFERROR(E26*(1-'Merma de Templado y Recortes'!E26),"") -> 11.76 | H26: =IFERROR(F26/G26,"") -> 12.755102 | I26: =IFERROR(H26/60*'Parámetros'!$B$15,"") -> 3.9310499 | J26: 0 | K26: =IFERROR(I26+J26,"") -> 3.9310499 | L26: ='Escandallo por Molde y Tanda'!O89 -> 4.9744898 | M26: =IFERROR(K26+L26,"") -> 8.9055397 | N26: 18.5 | O26: ='Parámetros'!$B$18 -> 0.1 | P26: =IFERROR(N26/(1+O26),"") -> 16.818182 | Q26: =IFERROR(L26/P26,"") -> 0.29578047 | R26: =IFERROR(P26-M26,"") -> 7.9126421 | S26: =IFERROR(R26/P26,"") -> 0.47048142 | T26: =IFERROR(L26/'Parámetros'!$B$22,"") -> 16.581633 | U26: =IFERROR(T26*(1+O26),"") -> 18.239796 | V26: Cero real, no «sin dato»: esta referencia no lleva piezas terminadas dentro.
A27: TF2 | B27: Mona de Pascua de chocolate, 400 g | C27: 1 | D27: 6 | E27: =C27*D27 -> 6 | F27: 210 | G27: =IFERROR(E27*(1-'Merma de Templado y Recortes'!E27),"") -> 5.88 | H27: =IFERROR(F27/G27,"") -> 35.714286 | I27: =IFERROR(H27/60*'Parámetros'!$B$15,"") -> 11.00694 | J27: 0 | K27: =IFERROR(I27+J27,"") -> 11.00694 | L27: ='Escandallo por Molde y Tanda'!O90 -> 7.8142857 | M27: =IFERROR(K27+L27,"") -> 18.821226 | N27: 26 | O27: ='Parámetros'!$B$18 -> 0.1 | P27: =IFERROR(N27/(1+O27),"") -> 23.636364 | Q27: =IFERROR(L27/P27,"") -> 0.3306044 | R27: =IFERROR(P27-M27,"") -> 4.8151381 | S27: =IFERROR(R27/P27,"") -> 0.20371738 | T27: =IFERROR(L27/'Parámetros'!$B$22,"") -> 26.047619 | U27: =IFERROR(T27*(1+O27),"") -> 28.652381 | V27: Cero real, no «sin dato»: esta referencia no lleva piezas terminadas dentro.
A28: TF3 | B28: Hueso de santo bañado en chocolate | C28: 30 | D28: 4 | E28: =C28*D28 -> 120 | F28: 170 | G28: =IFERROR(E28*(1-'Merma de Templado y Recortes'!E28),"") -> 112.8 | H28: =IFERROR(F28/G28,"") -> 1.5070922 | I28: =IFERROR(H28/60*'Parámetros'!$B$15,"") -> 0.46447725 | J28: 0 | K28: =IFERROR(I28+J28,"") -> 0.46447725 | L28: ='Escandallo por Molde y Tanda'!O91 -> 0.27561543 | M28: =IFERROR(K28+L28,"") -> 0.74009267 | N28: 1.6 | O28: ='Parámetros'!$B$18 -> 0.1 | P28: =IFERROR(N28/(1+O28),"") -> 1.4545455 | Q28: =IFERROR(L28/P28,"") -> 0.18948561 | R28: =IFERROR(P28-M28,"") -> 0.71445278 | S28: =IFERROR(R28/P28,"") -> 0.49118629 | T28: =IFERROR(L28/'Parámetros'!$B$22,"") -> 0.91871809 | U28: =IFERROR(T28*(1+O28),"") -> 1.0105899 | V28: Cero real, no «sin dato»: esta referencia no lleva piezas terminadas dentro.
A29: TF4 | B29: Turrón de chocolate con almendra, 250 g | C29: 4 | D29: 6 | E29: =C29*D29 -> 24 | F29: 120 | G29: =IFERROR(E29*(1-'Merma de Templado y Recortes'!E29),"") -> 23.52 | H29: =IFERROR(F29/G29,"") -> 5.1020408 | I29: =IFERROR(H29/60*'Parámetros'!$B$15,"") -> 1.57242 | J29: 0 | K29: =IFERROR(I29+J29,"") -> 1.57242 | L29: ='Escandallo por Molde y Tanda'!O92 -> 4.9367796 | M29: =IFERROR(K29+L29,"") -> 6.5091996 | N29: 13.5 | O29: ='Parámetros'!$B$18 -> 0.1 | P29: =IFERROR(N29/(1+O29),"") -> 12.272727 | Q29: =IFERROR(L29/P29,"") -> 0.40225611 | R29: =IFERROR(P29-M29,"") -> 5.7635277 | S29: =IFERROR(R29/P29,"") -> 0.46962078 | T29: =IFERROR(L29/'Parámetros'!$B$22,"") -> 16.455932 | U29: =IFERROR(T29*(1+O29),"") -> 18.101525 | V29: Cero real, no «sin dato»: esta referencia no lleva piezas terminadas dentro.
A30: TF5 | B30: Almendras marcona bañadas en chocolate, bolsa de 150 g | C30: 40 | D30: 1 | E30: =C30*D30 -> 40 | F30: 95 | G30: =IFERROR(E30*(1-'Merma de Templado y Recortes'!E30),"") -> 39.2 | H30: =IFERROR(F30/G30,"") -> 2.4234694 | I30: =IFERROR(H30/60*'Parámetros'!$B$15,"") -> 0.74689949 | J30: 0 | K30: =IFERROR(I30+J30,"") -> 0.74689949 | L30: ='Escandallo por Molde y Tanda'!O93 -> 2.8269429 | M30: =IFERROR(K30+L30,"") -> 3.5738423 | N30: 7.4 | O30: ='Parámetros'!$B$18 -> 0.1 | P30: =IFERROR(N30/(1+O30),"") -> 6.7272727 | Q30: =IFERROR(L30/P30,"") -> 0.42022124 | R30: =IFERROR(P30-M30,"") -> 3.1534304 | S30: =IFERROR(R30/P30,"") -> 0.46875316 | T30: =IFERROR(L30/'Parámetros'!$B$22,"") -> 9.4231429 | U30: =IFERROR(T30*(1+O30),"") -> 10.365457 | V30: Cero real, no «sin dato»: esta referencia no lleva piezas terminadas dentro.
A31: CJ1 | B31: Caja surtida de 12 bombones | C31: 1 | D31: 1 | E31: =C31*D31 -> 1 | F31: 4 | G31: =IFERROR(E31*(1-'Merma de Templado y Recortes'!E31),"") -> 0.995 | H31: =IFERROR(F31/G31,"") -> 4.0201005 | I31: =IFERROR(H31/60*'Parámetros'!$B$15,"") -> 1.2389721 | J31: ='Unidad vs Caja'!C26 -> 3.9948842 | K31: =IFERROR(I31+J31,"") -> 5.2338564 | L31: ='Escandallo por Molde y Tanda'!O94 -> 2.3349814 | M31: =IFERROR(K31+L31,"") -> 7.5688377 | N31: 20 | O31: ='Parámetros'!$B$18 -> 0.1 | P31: =IFERROR(N31/(1+O31),"") -> 18.181818 | Q31: =IFERROR(L31/P31,"") -> 0.12842397 | R31: =IFERROR(P31-M31,"") -> 10.61298 | S31: =IFERROR(R31/P31,"") -> 0.58371393 | T31: =IFERROR(L31/'Parámetros'!$B$22,"") -> 7.7832712 | U31: =IFERROR(T31*(1+O31),"") -> 8.5615983 | V31: Una caja cuesta lo que cuesta montarla MÁS lo que cuesta hacer los bombones que lleva. La columna I es sólo el montaje; la J trae el trabajo de dentro desde la hoja «Unidad vs Caja». Sumar sólo el montaje infla el margen de la caja y es el error que hace vender cajas a pérdida.
A32: CJ2 | B32: Caja surtida de 20 bombones | C32: 1 | D32: 1 | E32: =C32*D32 -> 1 | F32: 6 | G32: =IFERROR(E32*(1-'Merma de Templado y Recortes'!E32),"") -> 0.995 | H32: =IFERROR(F32/G32,"") -> 6.0301508 | I32: =IFERROR(H32/60*'Parámetros'!$B$15,"") -> 1.8584582 | J32: ='Unidad vs Caja'!D26 -> 6.6324596 | K32: =IFERROR(I32+J32,"") -> 8.4909178 | L32: ='Escandallo por Molde y Tanda'!O95 -> 4.0229053 | M32: =IFERROR(K32+L32,"") -> 12.513823 | N32: 28 | O32: ='Parámetros'!$B$18 -> 0.1 | P32: =IFERROR(N32/(1+O32),"") -> 25.454545 | Q32: =IFERROR(L32/P32,"") -> 0.15804271 | R32: =IFERROR(P32-M32,"") -> 12.940722 | S32: =IFERROR(R32/P32,"") -> 0.50838552 | T32: =IFERROR(L32/'Parámetros'!$B$22,"") -> 13.409684 | U32: =IFERROR(T32*(1+O32),"") -> 14.750653 | V32: Una caja cuesta lo que cuesta montarla MÁS lo que cuesta hacer los bombones que lleva. La columna I es sólo el montaje; la J trae el trabajo de dentro desde la hoja «Unidad vs Caja». Sumar sólo el montaje infla el margen de la caja y es el error que hace vender cajas a pérdida.
A33: CJ3 | B33: Caja surtida de 35 bombones | C33: 1 | D33: 1 | E33: =C33*D33 -> 1 | F33: 9 | G33: =IFERROR(E33*(1-'Merma de Templado y Recortes'!E33),"") -> 0.995 | H33: =IFERROR(F33/G33,"") -> 9.0452261 | I33: =IFERROR(H33/60*'Parámetros'!$B$15,"") -> 2.7876873 | J33: ='Unidad vs Caja'!E26 -> 11.806727 | K33: =IFERROR(I33+J33,"") -> 14.594414 | L33: ='Escandallo por Molde y Tanda'!O96 -> 6.9446349 | M33: =IFERROR(K33+L33,"") -> 21.539049 | N33: 45 | O33: ='Parámetros'!$B$18 -> 0.1 | P33: =IFERROR(N33/(1+O33),"") -> 40.909091 | Q33: =IFERROR(L33/P33,"") -> 0.16975774 | R33: =IFERROR(P33-M33,"") -> 19.370042 | S33: =IFERROR(R33/P33,"") -> 0.47348991 | T33: =IFERROR(L33/'Parámetros'!$B$22,"") -> 23.148783 | U33: =IFERROR(T33*(1+O33),"") -> 25.463661 | V33: Una caja cuesta lo que cuesta montarla MÁS lo que cuesta hacer los bombones que lleva. La columna I es sólo el montaje; la J trae el trabajo de dentro desde la hoja «Unidad vs Caja». Sumar sólo el montaje infla el margen de la caja y es el error que hace vender cajas a pérdida.
A34: CJ4 | B34: Estuche corporativo personalizado de 24 bombones | C34: 1 | D34: 1 | E34: =C34*D34 -> 1 | F34: 11 | G34: =IFERROR(E34*(1-'Merma de Templado y Recortes'!E34),"") -> 0.995 | H34: =IFERROR(F34/G34,"") -> 11.055276 | I34: =IFERROR(H34/60*'Parámetros'!$B$15,"") -> 3.4071733 | J34: ='Unidad vs Caja'!F26 -> 7.9898651 | K34: =IFERROR(I34+J34,"") -> 11.397038 | L34: ='Escandallo por Molde y Tanda'!O97 -> 4.7501975 | M34: =IFERROR(K34+L34,"") -> 16.147236 | N34: 34 | O34: ='Parámetros'!$B$18 -> 0.1 | P34: =IFERROR(N34/(1+O34),"") -> 30.909091 | Q34: =IFERROR(L34/P34,"") -> 0.15368286 | R34: =IFERROR(P34-M34,"") -> 14.761855 | S34: =IFERROR(R34/P34,"") -> 0.47758942 | T34: =IFERROR(L34/'Parámetros'!$B$22,"") -> 15.833992 | U34: =IFERROR(T34*(1+O34),"") -> 17.417391 | V34: Una caja cuesta lo que cuesta montarla MÁS lo que cuesta hacer los bombones que lleva. La columna I es sólo el montaje; la J trae el trabajo de dentro desde la hoja «Unidad vs Caja». Sumar sólo el montaje infla el margen de la caja y es el error que hace vender cajas a pérdida.
A35: Media de la carta | Q35: =IFERROR(AVERAGE(Q7:Q34),"") -> 0.22972972 | R35: =IFERROR(AVERAGE(R7:R34),"") -> 4.2407246 | S35: =IFERROR(AVERAGE(S7:S34),"") -> 0.55447023
A37: La media de la última fila es una media SIMPLE de las 28 referencias y sirve para ver dispersión, no para decidir: el food cost que hay que mirar es el ponderado por lo que de verdad vendes, y ése lo calcula la hoja «Mix y Ticket Medio».
A39: Versión 1.0 · septiembre 2026 · aichef.pro/guia-chocolateria-obrador · info@aichef.pro

Sheet Unidad vs Caja
A1: Unidad vs Caja
A2: AI Chef Pro · aichef.pro — Cómo Montar una Chocolatería
A3: La caja es la unidad de venta real de una bombonería, y por eso tiene hoja propia: el precio por bombón cae según crece la caja, y el trabajo de hacer esos bombones no desaparece.
A5: Qué lleva dentro cada caja
A6: Id | B6: Bombón | C6: Caja surtida de 12 bombones | D6: Caja surtida de 20 bombones | E6: Caja surtida de 35 bombones | F6: Estuche corporativo personalizado de 24 bombones | G6: PVP suelto con IVA (EUR) | H6: Coste de materia sin merma (EUR) | I6: Coste de mano de obra por pieza (EUR) | J6: Nota
A7: BC1 | B7: Bombón de ganache de chocolate negro 70 % | C7: 2 | D7: 3 | E7: 5 | F7: 3 | G7: ='Coste Hora y Mano de Obra'!N7 -> 2 | H7: ='Escandallo por Molde y Tanda'!M70 -> 0.21760604 | I7: ='Coste Hora y Mano de Obra'!K7 -> 0.34199684 | J7: Un cero aquí es un cero REAL: ese bombón no entra en esa caja. Cambia las cantidades y todo lo de abajo se mueve.
A8: BC2 | B8: Bombón de ganache de leche y vainilla | C8: 2 | D8: 3 | E8: 5 | F8: 3 | G8: ='Coste Hora y Mano de Obra'!N8 -> 1.95 | H8: ='Escandallo por Molde y Tanda'!M71 -> 0.190684 | I8: ='Coste Hora y Mano de Obra'!K8 -> 0.34199684
A9: BC3 | B9: Bombón de praliné de avellana | C9: 2 | D9: 3 | E9: 5 | F9: 4 | G9: ='Coste Hora y Mano de Obra'!N9 -> 2.1 | H9: ='Escandallo por Molde y Tanda'!M72 -> 0.213448 | I9: ='Coste Hora y Mano de Obra'!K9 -> 0.30574833
A10: BC4 | B10: Bombón de gianduja de avellana | C10: 0 | D10: 2 | E10: 3 | F10: 2 | G10: ='Coste Hora y Mano de Obra'!N10 -> 2.1 | H10: ='Escandallo por Molde y Tanda'!M73 -> 0.2243435 | I10: ='Coste Hora y Mano de Obra'!K10 -> 0.340691
A11: BC5 | B11: Trufa de chocolate negro al cacao | C11: 1 | D11: 3 | E11: 4 | F11: 3 | G11: ='Coste Hora y Mano de Obra'!N11 -> 1.9 | H11: ='Escandallo por Molde y Tanda'!M74 -> 0.21808513 | I11: ='Coste Hora y Mano de Obra'!K11 -> 0.24077681
A12: BC6 | B12: Bombón de licor de ron | C12: 0 | D12: 1 | E12: 2 | F12: 1 | G12: ='Coste Hora y Mano de Obra'!N12 -> 2.3 | H12: ='Escandallo por Molde y Tanda'!M75 -> 0.172889 | I12: ='Coste Hora y Mano de Obra'!K12 -> 0.48489774
A13: BC7 | B13: Bombón de caramelo salado | C13: 2 | D13: 2 | E13: 4 | F13: 3 | G13: ='Coste Hora y Mano de Obra'!N13 -> 2 | H13: ='Escandallo por Molde y Tanda'!M76 -> 0.1331798 | I13: ='Coste Hora y Mano de Obra'!K13 -> 0.33096469
A14: BC8 | B14: Bombón de praliné de cacahuete | C14: 1 | D14: 1 | E14: 3 | F14: 2 | G14: ='Coste Hora y Mano de Obra'!N14 -> 1.95 | H14: ='Escandallo por Molde y Tanda'!M77 -> 0.186582 | I14: ='Coste Hora y Mano de Obra'!K14 -> 0.3537945
A15: BC9 | B15: Bombón crujiente de sésamo y barquillo | C15: 1 | D15: 1 | E15: 2 | F15: 2 | G15: ='Coste Hora y Mano de Obra'!N15 -> 2.05 | H15: ='Escandallo por Molde y Tanda'!M78 -> 0.190446 | I15: ='Coste Hora y Mano de Obra'!K15 -> 0.366898
A16: BC10 | B16: Bombón de naranja confitada y chocolate negro | C16: 1 | D16: 1 | E16: 2 | F16: 1 | G16: ='Coste Hora y Mano de Obra'!N16 -> 2.05 | H16: ='Escandallo por Molde y Tanda'!M79 -> 0.21835763 | I16: ='Coste Hora y Mano de Obra'!K16 -> 0.39200154
A18: Lo que sale de cada caja
A19: Unidades que lleva la caja | C19: =SUM(C7:C16) -> 12 | D19: =SUM(D7:D16) -> 20 | E19: =SUM(E7:E16) -> 35 | F19: =SUM(F7:F16) -> 24
A20: Peso de chocolate de la caja (g) | C20: =SUMPRODUCT($C$7:$C$16,'Escandallo por Molde y Tanda'!$E$70:$E$79) -> 62.5 | D20: =SUMPRODUCT($D$7:$D$16,'Escandallo por Molde y Tanda'!$E$70:$E$79) -> 102.5 | E20: =SUMPRODUCT($E$7:$E$16,'Escandallo por Molde y Tanda'!$E$70:$E$79) -> 181 | F20: =SUMPRODUCT($F$7:$F$16,'Escandallo por Molde y Tanda'!$E$70:$E$79) -> 123
A21: Peso total de la caja (g) | C21: =SUMPRODUCT($C$7:$C$16,'Escandallo por Molde y Tanda'!$G$70:$G$79) -> 145 | D21: =SUMPRODUCT($D$7:$D$16,'Escandallo por Molde y Tanda'!$G$70:$G$79) -> 245 | E21: =SUMPRODUCT($E$7:$E$16,'Escandallo por Molde y Tanda'!$G$70:$G$79) -> 428 | F21: =SUMPRODUCT($F$7:$F$16,'Escandallo por Molde y Tanda'!$G$70:$G$79) -> 293
A22: Porcentaje de chocolate sobre el peso TOTAL | C22: =IFERROR(C20/C21,"") -> 0.43103448 | D22: =IFERROR(D20/D21,"") -> 0.41836735 | E22: =IFERROR(E20/E21,"") -> 0.4228972 | F22: =IFERROR(F20/F21,"") -> 0.41979522
A23: Coste de materia de las piezas, sin merma (EUR) | C23: =SUMPRODUCT($C$7:$C$16,$H$7:$H$16) -> 2.3233064 | D23: =SUMPRODUCT($D$7:$D$16,$H$7:$H$16) -> 4.0027907 | E23: =SUMPRODUCT($E$7:$E$16,$H$7:$H$16) -> 6.9099117 | F23: =SUMPRODUCT($F$7:$F$16,$H$7:$H$16) -> 4.7264465
A24: Coste de materia de la caja, con su merma de montaje (EUR) | C24: =IFERROR(C23/(1-'Merma de Templado y Recortes'!E31),"") -> 2.3349814 | D24: =IFERROR(D23/(1-'Merma de Templado y Recortes'!E32),"") -> 4.0229053 | E24: =IFERROR(E23/(1-'Merma de Templado y Recortes'!E33),"") -> 6.9446349 | F24: =IFERROR(F23/(1-'Merma de Templado y Recortes'!E34),"") -> 4.7501975
A25: Coste de materia de esos bombones vendidos sueltos, con su merma (EUR) | C25: =SUMPRODUCT($C$7:$C$16,'Escandallo por Molde y Tanda'!$O$70:$O$79) -> 2.3937854 | D25: =SUMPRODUCT($D$7:$D$16,'Escandallo por Molde y Tanda'!$O$70:$O$79) -> 4.1247877 | E25: =SUMPRODUCT($E$7:$E$16,'Escandallo por Molde y Tanda'!$O$70:$O$79) -> 7.1179775 | F25: =SUMPRODUCT($F$7:$F$16,'Escandallo por Molde y Tanda'!$O$70:$O$79) -> 4.864613
A26: Coste de mano de obra de las piezas que lleva dentro (EUR) | C26: =SUMPRODUCT($C$7:$C$16,$I$7:$I$16) -> 3.9948842 | D26: =SUMPRODUCT($D$7:$D$16,$I$7:$I$16) -> 6.6324596 | E26: =SUMPRODUCT($E$7:$E$16,$I$7:$I$16) -> 11.806727 | F26: =SUMPRODUCT($F$7:$F$16,$I$7:$I$16) -> 7.9898651
A27: Coste de mano de obra del montaje de la caja (EUR) | C27: ='Coste Hora y Mano de Obra'!I31 -> 1.2389721 | D27: ='Coste Hora y Mano de Obra'!I32 -> 1.8584582 | E27: ='Coste Hora y Mano de Obra'!I33 -> 2.7876873 | F27: ='Coste Hora y Mano de Obra'!I34 -> 3.4071733
A28: COSTE TOTAL DE LA CAJA (EUR) | C28: =IFERROR(C24+C26+C27,"") -> 7.5688377 | D28: =IFERROR(D24+D26+D27,"") -> 12.513823 | E28: =IFERROR(E24+E26+E27,"") -> 21.539049 | F28: =IFERROR(F24+F26+F27,"") -> 16.147236
A29: PVP de la caja, con IVA (EUR) | C29: ='Coste Hora y Mano de Obra'!N31 -> 20 | D29: ='Coste Hora y Mano de Obra'!N32 -> 28 | E29: ='Coste Hora y Mano de Obra'!N33 -> 45 | F29: ='Coste Hora y Mano de Obra'!N34 -> 34
A30: PVP de la caja, sin IVA (EUR) | C30: ='Coste Hora y Mano de Obra'!P31 -> 18.181818 | D30: ='Coste Hora y Mano de Obra'!P32 -> 25.454545 | E30: ='Coste Hora y Mano de Obra'!P33 -> 40.909091 | F30: ='Coste Hora y Mano de Obra'!P34 -> 30.909091
A31: PVP de esos bombones vendidos sueltos, con IVA (EUR) | C31: =SUMPRODUCT($C$7:$C$16,$G$7:$G$16) -> 24.05 | D31: =SUMPRODUCT($D$7:$D$16,$G$7:$G$16) -> 40.4 | E31: =SUMPRODUCT($E$7:$E$16,$G$7:$G$16) -> 70.8 | F31: =SUMPRODUCT($F$7:$F$16,$G$7:$G$16) -> 48.5
A32: PVP de esos bombones vendidos sueltos, sin IVA (EUR) | C32: =IFERROR(C31/(1+'Coste Hora y Mano de Obra'!O31),"") -> 21.863636 | D32: =IFERROR(D31/(1+'Coste Hora y Mano de Obra'!O32),"") -> 36.727273 | E32: =IFERROR(E31/(1+'Coste Hora y Mano de Obra'!O33),"") -> 64.363636 | F32: =IFERROR(F31/(1+'Coste Hora y Mano de Obra'!O34),"") -> 44.090909
A33: Precio por bombón EN CAJA, con IVA (EUR) | C33: =IFERROR(C29/C19,"") -> 1.6666667 | D33: =IFERROR(D29/D19,"") -> 1.4 | E33: =IFERROR(E29/E19,"") -> 1.2857143 | F33: =IFERROR(F29/F19,"") -> 1.4166667
A34: Precio por bombón SUELTO, con IVA (EUR) | C34: =IFERROR(C31/C19,"") -> 2.0041667 | D34: =IFERROR(D31/D19,"") -> 2.02 | E34: =IFERROR(E31/E19,"") -> 2.0228571 | F34: =IFERROR(F31/F19,"") -> 2.0208333
A35: Descuento que le haces al cliente por comprar la caja | C35: =IFERROR(1-C33/C34,"") -> 0.16839917 | D35: =IFERROR(1-D33/D34,"") -> 0.30693069 | E35: =IFERROR(1-E33/E34,"") -> 0.36440678 | F35: =IFERROR(1-F33/F34,"") -> 0.29896907
A36: Contraste de mercado: EUR por bombón publicado (CHS-29) | C36: 1.67 | D36: 1.4 | E36: 1.29 | F36: sin dato publicado
A37: MARGEN DE LA CAJA (EUR) | C37: =IFERROR(C30-C28,"") -> 10.61298 | D37: =IFERROR(D30-D28,"") -> 12.940722 | E37: =IFERROR(E30-E28,"") -> 19.370042 | F37: =IFERROR(F30-F28,"") -> 14.761855
A38: Margen vendiendo esos mismos bombones sueltos (EUR) | C38: =IFERROR(C32-C25-C26,"") -> 15.474967 | D38: =IFERROR(D32-D25-D26,"") -> 25.970025 | E38: =IFERROR(E32-E25-E26,"") -> 45.438932 | F38: =IFERROR(F32-F25-F26,"") -> 31.236431
A39: Diferencia de margen: la caja menos el suelto (EUR) | C39: =IFERROR(C37-C38,"") -> -4.8619862 | D39: =IFERROR(D37-D38,"") -> -13.029303 | E39: =IFERROR(E37-E38,"") -> -26.06889 | F39: =IFERROR(F37-F38,"") -> -16.474576
A40: Veredicto | C40: =IF(OR(NOT(ISNUMBER(C39)),NOT(ISNUMBER(C37))),"",IF(C37<=0,"La caja te cuesta dinero: su margen es cero o negativo",IF(C39>=0,"La caja te gana dinero: deja más que vender esos bombones sueltos","Ganas MENOS que vendiendo sueltos: es un descuento, decide si lo quieres"))) -> Ganas MENOS que vendiendo sueltos: es un descuento, decide si lo quieres | D40: =IF(OR(NOT(ISNUMBER(D39)),NOT(ISNUMBER(D37))),"",IF(D37<=0,"La caja te cuesta dinero: su margen es cero o negativo",IF(D39>=0,"La caja te gana dinero: deja más que vender esos bombones sueltos","Ganas MENOS que vendiendo sueltos: es un descuento, decide si lo quieres"))) -> Ganas MENOS que vendiendo sueltos: es un descuento, decide si lo quieres | E40: =IF(OR(NOT(ISNUMBER(E39)),NOT(ISNUMBER(E37))),"",IF(E37<=0,"La caja te cuesta dinero: su margen es cero o negativo",IF(E39>=0,"La caja te gana dinero: deja más que vender esos bombones sueltos","Ganas MENOS que vendiendo sueltos: es un descuento, decide si lo quieres"))) -> Ganas MENOS que vendiendo sueltos: es un descuento, decide si lo quieres | F40: =IF(OR(NOT(ISNUMBER(F39)),NOT(ISNUMBER(F37))),"",IF(F37<=0,"La caja te cuesta dinero: su margen es cero o negativo",IF(F39>=0,"La caja te gana dinero: deja más que vender esos bombones sueltos","Ganas MENOS que vendiendo sueltos: es un descuento, decide si lo quieres"))) -> Ganas MENOS que vendiendo sueltos: es un descuento, decide si lo quieres
A42: El contraste de mercado de la fila «EUR por bombón publicado» no es tu precio: es lo que se ve en el escaparate de otra casa, con IVA, y baja del formato pequeño al grande. Sirve para saber si tu descuento por caja se parece al del mercado, no para copiarlo. Y el estuche corporativo no tiene contraste publicado: se presupuesta por pedido, con su plazo mínimo de 14 días desde que el cliente aprueba la muestra.
A44: Versión 1.0 · septiembre 2026 · aichef.pro/guia-chocolateria-obrador · info@aichef.pro

Sheet Mix y Ticket Medio
A1: Mix y Ticket Medio
A2: AI Chef Pro · aichef.pro — Cómo Montar una Chocolatería
A3: Dos mixes, porque en julio y en agosto no se vende lo mismo: el turista no compra ganache, compra souvenir que viaja. Los dos tienen que sumar 100 %.
A6: Id | B6: Referencia | C6: Familia | D6: Mix de todo el año (%) | E6: Mix de julio y agosto (%) | F6: PVP con IVA (EUR) | G6: PVP sin IVA (EUR) | H6: Coste de materia con merma (EUR) | I6: Aportación al PVP medio del año (EUR) | J6: Aportación al PVP medio de julio y agosto (EUR) | K6: Unidades al año | L6: Nota
A7: BC1 | B7: Bombón de ganache de chocolate negro 70 % | C7: Bombones de colección | D7: 6 | E7: 2 | F7: ='Coste Hora y Mano de Obra'!N7 -> 2 | G7: ='Coste Hora y Mano de Obra'!P7 -> 1.8181818 | H7: ='Coste Hora y Mano de Obra'!L7 -> 0.22433612 | I7: =IFERROR(F7*D7/100,"") -> 0.12 | J7: =IFERROR(F7*E7/100,"") -> 0.04 | K7: =IFERROR('Parámetros'!$B$38*D7/100,"") -> 1710.912
A8: BC2 | B8: Bombón de ganache de leche y vainilla | C8: Bombones de colección | D8: 5 | E8: 4 | F8: ='Coste Hora y Mano de Obra'!N8 -> 1.95 | G8: ='Coste Hora y Mano de Obra'!P8 -> 1.7727273 | H8: ='Coste Hora y Mano de Obra'!L8 -> 0.19658144 | I8: =IFERROR(F8*D8/100,"") -> 0.0975 | J8: =IFERROR(F8*E8/100,"") -> 0.078 | K8: =IFERROR('Parámetros'!$B$38*D8/100,"") -> 1425.76
A9: BC3 | B9: Bombón de praliné de avellana | C9: Bombones de colección | D9: 6 | E9: 5 | F9: ='Coste Hora y Mano de Obra'!N9 -> 2.1 | G9: ='Coste Hora y Mano de Obra'!P9 -> 1.9090909 | H9: ='Coste Hora y Mano de Obra'!L9 -> 0.21780408 | I9: =IFERROR(F9*D9/100,"") -> 0.126 | J9: =IFERROR(F9*E9/100,"") -> 0.105 | K9: =IFERROR('Parámetros'!$B$38*D9/100,"") -> 1710.912
A10: BC4 | B10: Bombón de gianduja de avellana | C10: Bombones de colección | D10: 4 | E10: 3 | F10: ='Coste Hora y Mano de Obra'!N10 -> 2.1 | G10: ='Coste Hora y Mano de Obra'!P10 -> 1.9090909 | H10: ='Coste Hora y Mano de Obra'!L10 -> 0.22892194 | I10: =IFERROR(F10*D10/100,"") -> 0.084 | J10: =IFERROR(F10*E10/100,"") -> 0.063 | K10: =IFERROR('Parámetros'!$B$38*D10/100,"") -> 1140.608
A11: BC5 | B11: Trufa de chocolate negro al cacao | C11: Bombones de colección | D11: 5 | E11: 2 | F11: ='Coste Hora y Mano de Obra'!N11 -> 1.9 | G11: ='Coste Hora y Mano de Obra'!P11 -> 1.7272727 | H11: ='Coste Hora y Mano de Obra'!L11 -> 0.22717201 | I11: =IFERROR(F11*D11/100,"") -> 0.095 | J11: =IFERROR(F11*E11/100,"") -> 0.038 | K11: =IFERROR('Parámetros'!$B$38*D11/100,"") -> 1425.76
A12: BC6 | B12: Bombón de licor de ron | C12: Bombones de colección | D12: 3 | E12: 3 | F12: ='Coste Hora y Mano de Obra'!N12 -> 2.3 | G12: ='Coste Hora y Mano de Obra'!P12 -> 2.0909091 | H12: ='Coste Hora y Mano de Obra'!L12 -> 0.18009271 | I12: =IFERROR(F12*D12/100,"") -> 0.069 | J12: =IFERROR(F12*E12/100,"") -> 0.069 | K12: =IFERROR('Parámetros'!$B$38*D12/100,"") -> 855.456
A13: BC7 | B13: Bombón de caramelo salado | C13: Bombones de colección | D13: 4 | E13: 2 | F13: ='Coste Hora y Mano de Obra'!N13 -> 2 | G13: ='Coste Hora y Mano de Obra'!P13 -> 1.8181818 | H13: ='Coste Hora y Mano de Obra'!L13 -> 0.13729876 | I13: =IFERROR(F13*D13/100,"") -> 0.08 | J13: =IFERROR(F13*E13/100,"") -> 0.04 | K13: =IFERROR('Parámetros'!$B$38*D13/100,"") -> 1140.608
A14: BC8 | B14: Bombón de praliné de cacahuete | C14: Bombones de colección | D14: 3 | E14: 3 | F14: ='Coste Hora y Mano de Obra'!N14 -> 1.95 | G14: ='Coste Hora y Mano de Obra'!P14 -> 1.7727273 | H14: ='Coste Hora y Mano de Obra'!L14 -> 0.1903898 | I14: =IFERROR(F14*D14/100,"") -> 0.0585 | J14: =IFERROR(F14*E14/100,"") -> 0.0585 | K14: =IFERROR('Parámetros'!$B$38*D14/100,"") -> 855.456
A15: BC9 | B15: Bombón crujiente de sésamo y barquillo | C15: Bombones de colección | D15: 3 | E15: 3 | F15: ='Coste Hora y Mano de Obra'!N15 -> 2.05 | G15: ='Coste Hora y Mano de Obra'!P15 -> 1.8636364 | H15: ='Coste Hora y Mano de Obra'!L15 -> 0.19433265 | I15: =IFERROR(F15*D15/100,"") -> 0.0615 | J15: =IFERROR(F15*E15/100,"") -> 0.0615 | K15: =IFERROR('Parámetros'!$B$38*D15/100,"") -> 855.456
A16: BC10 | B16: Bombón de naranja confitada y chocolate negro | C16: Bombones de colección | D16: 3 | E16: 3 | F16: ='Coste Hora y Mano de Obra'!N16 -> 2.05 | G16: ='Coste Hora y Mano de Obra'!P16 -> 1.8636364 | H16: ='Coste Hora y Mano de Obra'!L16 -> 0.22985014 | I16: =IFERROR(F16*D16/100,"") -> 0.0615 | J16: =IFERROR(F16*E16/100,"") -> 0.0615 | K16: =IFERROR('Parámetros'!$B$38*D16/100,"") -> 855.456
A17: TB1 | B17: Tableta de chocolate negro de origen 70 %, 100 g | C17: Tabletas | D17: 7 | E17: 11 | F17: ='Coste Hora y Mano de Obra'!N17 -> 8.5 | G17: ='Coste Hora y Mano de Obra'!P17 -> 7.7272727 | H17: ='Coste Hora y Mano de Obra'!L17 -> 3.7858586 | I17: =IFERROR(F17*D17/100,"") -> 0.595 | J17: =IFERROR(F17*E17/100,"") -> 0.935 | K17: =IFERROR('Parámetros'!$B$38*D17/100,"") -> 1996.064
A18: TB2 | B18: Tableta de chocolate con leche 38 %, 100 g | C18: Tabletas | D18: 6 | E18: 9 | F18: ='Coste Hora y Mano de Obra'!N18 -> 5.9 | G18: ='Coste Hora y Mano de Obra'!P18 -> 5.3636364 | H18: ='Coste Hora y Mano de Obra'!L18 -> 1.969697 | I18: =IFERROR(F18*D18/100,"") -> 0.354 | J18: =IFERROR(F18*E18/100,"") -> 0.531 | K18: =IFERROR('Parámetros'!$B$38*D18/100,"") -> 1710.912
... A34: CJ4 | B34: Estuche corporativo personalizado de 24 bombones | C34: Cajas y regalo | D34: 1 | E34: 1 | F34: ='Coste Hora y Mano de Obra'!N34 -> 34 | G34: ='Coste Hora y Mano de Obra'!P34 -> 30.909091 | H34: ='Coste Hora y Mano de Obra'!L34 -> 4.7501975 | I34: =IFERROR(F34*D34/100,"") -> 0.34 | J34: =IFERROR(F34*E34/100,"") -> 0.34 | K34: =IFERROR('Parámetros'!$B$38*D34/100,"") -> 285.152
A35: TOTAL | D35: =SUM(D7:D34) -> 100 | E35: =SUM(E7:E34) -> 100 | I35: =SUM(I7:I34) -> 7.68 | J35: =SUM(J7:J34) -> 8.5315 | K35: =SUM(K7:K34) -> 28515.2
A37: PVP medio ponderado con IVA (todo el año) | B37: =I35 -> 7.68
A38: PVP medio ponderado con IVA (julio y agosto) | B38: =J35 -> 8.5315
A39: Piezas por ticket | B39: ='Parámetros'!$B$35 -> 1.4
A40: TICKET MEDIO con IVA (todo el año) | B40: =IFERROR(B37*B39,"") -> 10.752
A41: Ticket medio SIN IVA (todo el año) | B41: =IFERROR(B40/(1+'Parámetros'!$B$18),"") -> 9.7745455
A42: Ticket medio con IVA (julio y agosto) | B42: =IFERROR(B38*B39,"") -> 11.9441
A43: Food cost de escandallo de la carta (todo el año) | B43: =IFERROR(SUMPRODUCT(H7:H34,D7:D34)/SUMPRODUCT(G7:G34,D7:D34),"") -> 0.25215678
A44: Food cost de escandallo de la carta (julio y agosto) | B44: =IFERROR(SUMPRODUCT(H7:H34,E7:E34)/SUMPRODUCT(G7:G34,E7:E34),"") -> 0.25781495
A45: Packaging sobre el coste de la pieza | B45: ='Parámetros'!$B$39 -> 0.12
A46: FOOD COST SERVIDO (el que va al plan financiero) | B46: =IFERROR(B43*(1+B45),"") -> 0.28241559
A47: Diferencia entre el de escandallo y el servido | B47: =IFERROR(B46-B43,"") -> 0.030258813
A48: Margen bruto medio con el mix de todo el año | B48: =IFERROR(1-B43,"") -> 0.74784322
A49: Margen bruto medio con el mix de julio y agosto | B49: =IFERROR(1-B44,"") -> 0.74218505
A50: Caída del margen al cambiar el mix en verano | B50: =IFERROR(B49-B48,"") -> -0.0056581772
A51: Comprobación: los dos mixes suman 100 % | B51: =IF(OR(NOT(ISNUMBER(D35)),NOT(ISNUMBER(E35))),"",IF(AND(D35=100,E35=100),"CUADRAN los dos mixes","REVISA: alguno de los dos mixes no suma 100")) -> CUADRAN los dos mixes
A53: El food cost de escandallo y el que llega a la cuenta de resultados NO coinciden, y está bien: al de la pieza hay que sumarle el packaging, que en bombonería pesa porque la caja ES el producto. Esa diferencia es tu colchón, no un error. Y el ticket medio de aquí es el tuyo: no existe un ticket medio publicado de chocolatería, así que mídelo con el TPV en dos semanas y sustitúyelo.
A55: Versión 1.0 · septiembre 2026 · aichef.pro/guia-chocolateria-obrador · info@aichef.pro

Sheet Decisión de Surtido
A1: Decisión de Surtido
A2: AI Chef Pro · aichef.pro — Cómo Montar una Chocolatería
A3: Margen en EUROS por pieza contra rotación. Un 70 % de margen sobre una pieza de 0,40 EUR no paga el alquiler, y una referencia que no rota ocupa molde, cámara y cabeza.
A6: Id | B6: Referencia | C6: Familia | D6: Margen por pieza (EUR) | E6: Margen sobre PVP | F6: Unidades al año | G6: Margen al año (EUR) | H6: Peso en el mix (%) | I6: ¿Margen por encima del umbral? | J6: ¿Rotación por encima del umbral? | K6: Veredicto | L6: Qué hacer
A7: BC1 | B7: Bombón de ganache de chocolate negro 70 % | C7: Bombones de colección | D7: ='Coste Hora y Mano de Obra'!R7 -> 1.2518489 | E7: ='Coste Hora y Mano de Obra'!S7 -> 0.68851687 | F7: ='Mix y Ticket Medio'!K7 -> 1710.912 | G7: =IFERROR(D7*F7,"") -> 2141.8032 | H7: ='Mix y Ticket Medio'!D7 -> 6 | I7: =IF(NOT(ISNUMBER(D7)),"",IF(D7>='Parámetros'!$B$44,"Sí","No")) -> Sí | J7: =IF(NOT(ISNUMBER(H7)),"",IF(H7>='Parámetros'!$B$42,"Sí","No")) -> Sí | K7: =IF(OR(I7="",J7=""),"",IF(AND(I7="Sí",J7="Sí"),"Mantener",IF(I7="Sí","Revisar precio","Retirar"))) -> Mantener | L7: Si sale «Revisar precio», el primer sitio donde mirar es la columna del PVP que pide tu regla de margen, en la hoja de mano de obra.
A8: BC2 | B8: Bombón de ganache de leche y vainilla | C8: Bombones de colección | D8: ='Coste Hora y Mano de Obra'!R8 -> 1.234149 | E8: ='Coste Hora y Mano de Obra'!S8 -> 0.69618661 | F8: ='Mix y Ticket Medio'!K8 -> 1425.76 | G8: =IFERROR(D8*F8,"") -> 1759.6003 | H8: ='Mix y Ticket Medio'!D8 -> 5 | I8: =IF(NOT(ISNUMBER(D8)),"",IF(D8>='Parámetros'!$B$44,"Sí","No")) -> Sí | J8: =IF(NOT(ISNUMBER(H8)),"",IF(H8>='Parámetros'!$B$42,"Sí","No")) -> Sí | K8: =IF(OR(I8="",J8=""),"",IF(AND(I8="Sí",J8="Sí"),"Mantener",IF(I8="Sí","Revisar precio","Retirar"))) -> Mantener | L8: Si sale «Revisar precio», el primer sitio donde mirar es la columna del PVP que pide tu regla de margen, en la hoja de mano de obra.
A9: BC3 | B9: Bombón de praliné de avellana | C9: Bombones de colección | D9: ='Coste Hora y Mano de Obra'!R9 -> 1.3855385 | E9: ='Coste Hora y Mano de Obra'!S9 -> 0.72575826 | F9: ='Mix y Ticket Medio'!K9 -> 1710.912 | G9: =IFERROR(D9*F9,"") -> 2370.5344 | H9: ='Mix y Ticket Medio'!D9 -> 6 | I9: =IF(NOT(ISNUMBER(D9)),"",IF(D9>='Parámetros'!$B$44,"Sí","No")) -> Sí | J9: =IF(NOT(ISNUMBER(H9)),"",IF(H9>='Parámetros'!$B$42,"Sí","No")) -> Sí | K9: =IF(OR(I9="",J9=""),"",IF(AND(I9="Sí",J9="Sí"),"Mantener",IF(I9="Sí","Revisar precio","Retirar"))) -> Mantener | L9: Si sale «Revisar precio», el primer sitio donde mirar es la columna del PVP que pide tu regla de margen, en la hoja de mano de obra.
A10: BC4 | B10: Bombón de gianduja de avellana | C10: Bombones de colección | D10: ='Coste Hora y Mano de Obra'!R10 -> 1.339478 | E10: ='Coste Hora y Mano de Obra'!S10 -> 0.70163132 | F10: ='Mix y Ticket Medio'!K10 -> 1140.608 | G10: =IFERROR(D10*F10,"") -> 1527.8193 | H10: ='Mix y Ticket Medio'!D10 -> 4 | I10: =IF(NOT(ISNUMBER(D10)),"",IF(D10>='Parámetros'!$B$44,"Sí","No")) -> Sí | J10: =IF(NOT(ISNUMBER(H10)),"",IF(H10>='Parámetros'!$B$42,"Sí","No")) -> Sí | K10: =IF(OR(I10="",J10=""),"",IF(AND(I10="Sí",J10="Sí"),"Mantener",IF(I10="Sí","Revisar precio","Retirar"))) -> Mantener | L10: Si sale «Revisar precio», el primer sitio donde mirar es la columna del PVP que pide tu regla de margen, en la hoja de mano de obra.
A11: BC5 | B11: Trufa de chocolate negro al cacao | C11: Bombones de colección | D11: ='Coste Hora y Mano de Obra'!R11 -> 1.2593239 | E11: ='Coste Hora y Mano de Obra'!S11 -> 0.72908226 | F11: ='Mix y Ticket Medio'!K11 -> 1425.76 | G11: =IFERROR(D11*F11,"") -> 1795.4937 | H11: ='Mix y Ticket Medio'!D11 -> 5 | I11: =IF(NOT(ISNUMBER(D11)),"",IF(D11>='Parámetros'!$B$44,"Sí","No")) -> Sí | J11: =IF(NOT(ISNUMBER(H11)),"",IF(H11>='Parámetros'!$B$42,"Sí","No")) -> Sí | K11: =IF(OR(I11="",J11=""),"",IF(AND(I11="Sí",J11="Sí"),"Mantener",IF(I11="Sí","Revisar precio","Retirar"))) -> Mantener | L11: Si sale «Revisar precio», el primer sitio donde mirar es la columna del PVP que pide tu regla de margen, en la hoja de mano de obra.
A12: BC6 | B12: Bombón de licor de ron | C12: Bombones de colección | D12: ='Coste Hora y Mano de Obra'!R12 -> 1.4259186 | E12: ='Coste Hora y Mano de Obra'!S12 -> 0.68196109 | F12: ='Mix y Ticket Medio'!K12 -> 855.456 | G12: =IFERROR(D12*F12,"") -> 1219.8107 | H12: ='Mix y Ticket Medio'!D12 -> 3 | I12: =IF(NOT(ISNUMBER(D12)),"",IF(D12>='Parámetros'!$B$44,"Sí","No")) -> Sí | J12: =IF(NOT(ISNUMBER(H12)),"",IF(H12>='Parámetros'!$B$42,"Sí","No")) -> Sí | K12: =IF(OR(I12="",J12=""),"",IF(AND(I12="Sí",J12="Sí"),"Mantener",IF(I12="Sí","Revisar precio","Retirar"))) -> Mantener | L12: Si sale «Revisar precio», el primer sitio donde mirar es la columna del PVP que pide tu regla de margen, en la hoja de mano de obra.
A13: BC7 | B13: Bombón de caramelo salado | C13: Bombones de colección | D13: ='Coste Hora y Mano de Obra'!R13 -> 1.3499184 | E13: ='Coste Hora y Mano de Obra'!S13 -> 0.7424551 | F13: ='Mix y Ticket Medio'!K13 -> 1140.608 | G13: =IFERROR(D13*F13,"") -> 1539.7277 | H13: ='Mix y Ticket Medio'!D13 -> 4 | I13: =IF(NOT(ISNUMBER(D13)),"",IF(D13>='Parámetros'!$B$44,"Sí","No")) -> Sí | J13: =IF(NOT(ISNUMBER(H13)),"",IF(H13>='Parámetros'!$B$42,"Sí","No")) -> Sí | K13: =IF(OR(I13="",J13=""),"",IF(AND(I13="Sí",J13="Sí"),"Mantener",IF(I13="Sí","Revisar precio","Retirar"))) -> Mantener | L13: Si sale «Revisar precio», el primer sitio donde mirar es la columna del PVP que pide tu regla de margen, en la hoja de mano de obra.
A14: BC8 | B14: Bombón de praliné de cacahuete | C14: Bombones de colección | D14: ='Coste Hora y Mano de Obra'!R14 -> 1.228543 | E14: ='Coste Hora y Mano de Obra'!S14 -> 0.69302425 | F14: ='Mix y Ticket Medio'!K14 -> 855.456 | G14: =IFERROR(D14*F14,"") -> 1050.9645 | H14: ='Mix y Ticket Medio'!D14 -> 3 | I14: =IF(NOT(ISNUMBER(D14)),"",IF(D14>='Parámetros'!$B$44,"Sí","No")) -> Sí | J14: =IF(NOT(ISNUMBER(H14)),"",IF(H14>='Parámetros'!$B$42,"Sí","No")) -> Sí | K14: =IF(OR(I14="",J14=""),"",IF(AND(I14="Sí",J14="Sí"),"Mantener",IF(I14="Sí","Revisar precio","Retirar"))) -> Mantener | L14: Si sale «Revisar precio», el primer sitio donde mirar es la columna del PVP que pide tu regla de margen, en la hoja de mano de obra.
A15: BC9 | B15: Bombón crujiente de sésamo y barquillo | C15: Bombones de colección | D15: ='Coste Hora y Mano de Obra'!R15 -> 1.3024057 | E15: ='Coste Hora y Mano de Obra'!S15 -> 0.69885185 | F15: ='Mix y Ticket Medio'!K15 -> 855.456 | G15: =IFERROR(D15*F15,"") -> 1114.1508 | H15: ='Mix y Ticket Medio'!D15 -> 3 | I15: =IF(NOT(ISNUMBER(D15)),"",IF(D15>='Parámetros'!$B$44,"Sí","No")) -> Sí | J15: =IF(NOT(ISNUMBER(H15)),"",IF(H15>='Parámetros'!$B$42,"Sí","No")) -> Sí | K15: =IF(OR(I15="",J15=""),"",IF(AND(I15="Sí",J15="Sí"),"Mantener",IF(I15="Sí","Revisar precio","Retirar"))) -> Mantener | L15: Si sale «Revisar precio», el primer sitio donde mirar es la columna del PVP que pide tu regla de margen, en la hoja de mano de obra.
A16: BC10 | B16: Bombón de naranja confitada y chocolate negro | C16: Bombones de colección | D16: ='Coste Hora y Mano de Obra'!R16 -> 1.2417847 | E16: ='Coste Hora y Mano de Obra'!S16 -> 0.66632349 | F16: ='Mix y Ticket Medio'!K16 -> 855.456 | G16: =IFERROR(D16*F16,"") -> 1062.2922 | H16: ='Mix y Ticket Medio'!D16 -> 3 | I16: =IF(NOT(ISNUMBER(D16)),"",IF(D16>='Parámetros'!$B$44,"Sí","No")) -> Sí | J16: =IF(NOT(ISNUMBER(H16)),"",IF(H16>='Parámetros'!$B$42,"Sí","No")) -> Sí | K16: =IF(OR(I16="",J16=""),"",IF(AND(I16="Sí",J16="Sí"),"Mantener",IF(I16="Sí","Revisar precio","Retirar"))) -> Mantener | L16: Si sale «Revisar precio», el primer sitio donde mirar es la columna del PVP que pide tu regla de margen, en la hoja de mano de obra.
A17: TB1 | B17: Tableta de chocolate negro de origen 70 %, 100 g | C17: Tabletas | D17: ='Coste Hora y Mano de Obra'!R17 -> 3.3706839 | E17: ='Coste Hora y Mano de Obra'!S17 -> 0.43620616 | F17: ='Mix y Ticket Medio'!K17 -> 1996.064 | G17: =IFERROR(D17*F17,"") -> 6728.1008 | H17: ='Mix y Ticket Medio'!D17 -> 7 | I17: =IF(NOT(ISNUMBER(D17)),"",IF(D17>='Parámetros'!$B$44,"Sí","No")) -> Sí | J17: =IF(NOT(ISNUMBER(H17)),"",IF(H17>='Parámetros'!$B$42,"Sí","No")) -> Sí | K17: =IF(OR(I17="",J17=""),"",IF(AND(I17="Sí",J17="Sí"),"Mantener",IF(I17="Sí","Revisar precio","Retirar"))) -> Mantener | L17: Si sale «Revisar precio», el primer sitio donde mirar es la columna del PVP que pide tu regla de margen, en la hoja de mano de obra.
A18: TB2 | B18: Tableta de chocolate con leche 38 %, 100 g | C18: Tabletas | D18: ='Coste Hora y Mano de Obra'!R18 -> 2.8232092 | E18: ='Coste Hora y Mano de Obra'!S18 -> 0.52636103 | F18: ='Mix y Ticket Medio'!K18 -> 1710.912 | G18: =IFERROR(D18*F18,"") -> 4830.2625 | H18: ='Mix y Ticket Medio'!D18 -> 6 | I18: =IF(NOT(ISNUMBER(D18)),"",IF(D18>='Parámetros'!$B$44,"Sí","No")) -> Sí | J18: =IF(NOT(ISNUMBER(H18)),"",IF(H18>='Parámetros'!$B$42,"Sí","No")) -> Sí | K18: =IF(OR(I18="",J18=""),"",IF(AND(I18="Sí",J18="Sí"),"Mantener",IF(I18="Sí","Revisar precio","Retirar"))) -> Mantener | L18: Si sale «Revisar precio», el primer sitio donde mirar es la columna del PVP que pide tu regla de margen, en la hoja de mano de obra.
... A34: CJ4 | B34: Estuche corporativo personalizado de 24 bombones | C34: Cajas y regalo | D34: ='Coste Hora y Mano de Obra'!R34 -> 14.761855 | E34: ='Coste Hora y Mano de Obra'!S34 -> 0.47758942 | F34: ='Mix y Ticket Medio'!K34 -> 285.152 | G34: =IFERROR(D34*F34,"") -> 4209.3725 | H34: ='Mix y Ticket Medio'!D34 -> 1 | I34: =IF(NOT(ISNUMBER(D34)),"",IF(D34>='Parámetros'!$B$44,"Sí","No")) -> Sí | J34: =IF(NOT(ISNUMBER(H34)),"",IF(H34>='Parámetros'!$B$42,"Sí","No")) -> No | K34: =IF(OR(I34="",J34=""),"",IF(AND(I34="Sí",J34="Sí"),"Mantener",IF(I34="Sí","Revisar precio","Retirar"))) -> Revisar precio | L34: Si sale «Revisar precio», el primer sitio donde mirar es la columna del PVP que pide tu regla de margen, en la hoja de mano de obra.
A35: TOTAL | G35: =SUM(G7:G34) -> 100615.4
A37: Referencias con veredicto «Mantener» | B37: =COUNTIF(K7:K34,"Mantener") -> 25
A38: Referencias con veredicto «Revisar precio» | B38: =COUNTIF(K7:K34,"Revisar precio") -> 2
A39: Referencias con veredicto «Retirar» | B39: =COUNTIF(K7:K34,"Retirar") -> 1
A41: Los dos umbrales están en «Parámetros» y son criterio de la casa, no del sector: súbelos o bájalos con tus números. Lo que no se puede es decidir el surtido con el margen en PORCENTAJE, que es lo que hace parecer rentable lo que sólo es barato.
A43: Versión 1.0 · septiembre 2026 · aichef.pro/guia-chocolateria-obrador · info@aichef.pro
