Workbook

Sheet Carne
A1: CALCULADORA DE LA CARNE — COSTE POR KILO ÚTIL, POR BOLA, BOLAS POR KILO Y KILOS AL DÍA
A2: Escribe solo en las celdas VERDES: todo lo demás se calcula. Importes sin IVA. Todos los valores por defecto son una estimación del kit, editable: cámbialos por los de tu proveedor y, sobre todo, por lo que midas en tus propias bolas.
A3: AVISO FIJO. Carne picada (RD 1021/2022, arts. 4.1, 7.2 y 7.3): comprada picada o picada en el local, se conserva a 2 °C o menos; la bola salada antes de la plancha es un preparado de carne, a 4 °C o menos; la picada en el local es del día y nunca de un día para otro. Nada de carne madurada más de 15 días (Inf26008). Los minutos de limpiar y picar (6) y la merma de cocción no tienen fuente: mídelos.
A5: A. TRES CARNES Y UNA LIBRE | B5: Blend comprado ya picado | C5: Pieza para picar en el local (aguja o falda) | D5: Bolas compradas porcionadas | E5: Otra carne (escribe la tuya) | F5: Notas
A6: Precio de compra (€/kg, sin IVA) | B6: 8.9 | C6: 7.5 | D6: 10.4 | E6: 9.5 | F6: Carne picada de vacuno: la «burger meat» minorista sale a 8,03 €/kg en oferta y el precio profesional no está publicado. El kit pone 8,90 €/kg el blend de aguja, falda y pecho con un 20 % de grasa, 7,50 €/kg la pieza para picar (sin fuente: mídelo) y 10,40 €/kg las bolas porcionadas (sin fuente: pídelo a tu proveedor). Escribe el precio por kilo también de las bolas. Estimación del kit, editable.
A7: Parte útil tras limpiar y picar (% del peso comprado) | B7: 1 | C7: 0.9 | D7: 1 | E7: 1 | F7: Parte de la carne comprada que queda tras limpiar y picar. 100 % si la compras ya picada; 90 % en la pieza (sin fuente: mídelo): pesa la pieza antes y la carne limpia después. Estimación del kit, editable.
A8: Minutos de limpiar y picar un kilo comprado (min) | B8: 0 | C8: 6 | D8: 0 | E8: 0 | F8: Minutos de limpiar y picar un kilo comprado. Sin fuente: mídelo. Cronometra 3 kilos y usa la media. Solo la pieza para picar lleva mano de obra. Estimación del kit, editable.
A9: Grasa de la carne (%, informativo) | B9: 0.2 | C9: 0.2 | D9: 0.2 | E9: 0.2 | F9: Informativo: no cambia ningún cálculo. El blend del plan lleva alrededor de un 20 % de grasa. Estimación del kit, editable.
A11: B. DATOS COMUNES | B11: Valor | C11: Notas
A12: Merma de cierre (% de las bolas, el pan y las salsas que se tiran) | B12: 0.03 | C12: Las bolas que sobran al cierre y no se pueden guardar. Estimación del kit, editable.
A13: Gramos por bola (g) | B13: 100 | C13: Bola de 80-100 g; 100 g es la de Smash Hiro. Pesa 10 bolas y usa la media. Estimación del kit, editable.
A14: Merma de cocción en plancha (% del peso de la bola) | B14: 0.25 | C14: Sin fuente: mídelo. Pesa 10 bolas antes de la plancha y después, y usa la media. Solo cambia los gramos servidos. Estimación del kit, editable.
A15: Coste por hora del cocinero (€/h) | B15: 16 | C15: 22.000 € brutos al año (lo más bajo de un cocinero de cadena, que gana de 22.000 a 25.000 €) + 33 % de cargas ÷ 1.840 h ≈ 16 €/h. Estimación del kit, editable.
A16: Bolas por comensal | B16: 1.6 | C16: Criterio del plan, mídelo: con el 90 % de tus comensales en sencilla o doble y los menús, salen unas 1,6 bolas por comensal. Estimación del kit, editable.
A17: Comensales equivalentes al día | B17: 95 | C17: El del caso del plan de negocio: 95 comensales equivalentes. Cámbialo por el tuyo. Estimación del kit, editable.
A18: ¿Compras la carne picada o la picas en el local? (desplegable) | B18: Compro la carne ya picada
A19: Gramos por kilo (constante) | B19: 1000 | C19: Constante: un kilo son 1.000 gramos. No se edita.
A20: Minutos por hora (constante) | B20: 60 | C20: Constante: una hora son 60 minutos. No se edita.
A22: C. COSTE POR KG ÚTIL Y POR BOLA | B22: =B5 -> Blend comprado ya picado | C22: =C5 -> Pieza para picar en el local (aguja o falda) | D22: =D5 -> Bolas compradas porcionadas | E22: =E5 -> Otra carne (escribe la tuya) | F22: Notas
A23: COSTE POR KG ÚTIL (€) | B23: =B$6/B$7/(1-$B$12) -> 9.1752577 | C23: =C$6/C$7/(1-$B$12) -> 8.5910653 | D23: =D$6/D$7/(1-$B$12) -> 10.721649 | E23: =E$6/E$7/(1-$B$12) -> 9.7938144 | F23: Precio ÷ útil ÷ (1 − merma de cierre).
A24: Coste por kg útil con la mano de obra de limpiar y picar (€) | B24: =(B$6+B$8/$B$20*$B$15)/B$7/(1-$B$12) -> 9.1752577 | C24: =(C$6+C$8/$B$20*$B$15)/C$7/(1-$B$12) -> 10.423826 | D24: =(D$6+D$8/$B$20*$B$15)/D$7/(1-$B$12) -> 10.721649 | E24: =(E$6+E$8/$B$20*$B$15)/E$7/(1-$B$12) -> 9.7938144 | F24: (Precio + minutos ÷ 60 × coste por hora) ÷ útil ÷ (1 − merma de cierre). Alimenta el escandallo.
A25: Coste de la carne de una bola (€) | B25: =B$24*$B$13/$B$19 -> 0.91752577 | C25: =C$24*$B$13/$B$19 -> 1.0423826 | D25: =D$24*$B$13/$B$19 -> 1.0721649 | E25: =E$24*$B$13/$B$19 -> 0.97938144 | F25: Coste por kg útil con mano de obra × gramos ÷ 1.000.
A26: Coste de la carne de una hamburguesa doble (2 bolas, €) | B26: =B$25+B$25 -> 1.8350515 | C26: =C$25+C$25 -> 2.0847652 | D26: =D$25+D$25 -> 2.1443299 | E26: =E$25+E$25 -> 1.9587629 | F26: Dos bolas.
A27: Coste de la carne de una hamburguesa triple (3 bolas, €) | B27: =B$25+B$25+B$25 -> 2.7525773 | C27: =C$25+C$25+C$25 -> 3.1271478 | D27: =D$25+D$25+D$25 -> 3.2164948 | E27: =E$25+E$25+E$25 -> 2.9381443 | F27: Tres bolas.
A29: D. BOLAS POR KILO, KILOS AL DÍA Y ¿PICAR EN EL LOCAL? | B29: Valor | C29: Notas
A30: BOLAS POR KILO EN CRUDO (bolas) | B30: =$B$19/$B$13 -> 10 | C30: 1.000 ÷ gramos por bola. Es la cifra de la ficha técnica del proveedor.
A31: Bolas por kilo contando la merma de cierre (bolas) | B31: =$B$19*(1-$B$12)/$B$13 -> 9.7 | C31: 1.000 × (1 − merma de cierre) ÷ gramos por bola.
A32: Gramos de carne que sirves tras la plancha (g) | B32: =$B$13*(1-$B$14) -> 75 | C32: Gramos por bola × (1 − merma de cocción).
A33: Bolas que vendes al día (bolas) | B33: =$B$17*$B$16 -> 152 | C33: Comensales equivalentes al día × bolas por comensal.
A34: KG DE CARNE AL DÍA | B34: =$B$33*$B$13/$B$19 -> 15.2 | C34: Bolas al día × gramos por bola ÷ 1.000. Dimensiona el pedido diario y el picado del día si picas en el local.
A35: Mano de obra de picar por kg útil de la pieza (€) | B35: =$C$24-$C$23 -> 1.8327606 | C35: Coste por kg útil de la pieza con mano de obra − sin ella.
A36: PICAR EN EL LOCAL TE COMPENSA MIENTRAS LIMPIARLO CUESTE MENOS DE (€ por kg útil) | B36: =$B$24-$C$23 -> 0.58419244 | C36: Coste por kg útil del blend comprado − coste por kg útil de la pieza (sin mano de obra).
A37: Veredicto con tu mano de obra | B37: =IF($B$35<$B$36,"Picar en el local compensa","Compra el blend ya picado") -> Compra el blend ya picado | C37: Picar compensa si limpiarlo y picarlo cuesta menos que esa diferencia.
A38: Recordatorio de tu caso | B38: =INDEX($B$41:$B$43,MATCH($B$18,$A$41:$A$43,0)) -> RD 1021/2022, art. 4.1: la carne picada se conserva a 2 °C o menos y la bola salada antes de la plancha es un preparado de carne: 4 °C o menos. Pide al proveedor la ficha técnica con el blend, el % de grasa y la fecha de sacrificio o de envasado.
A40: LISTA DEL DESPLEGABLE DE CARNE PICADA | B40: Recordatorio
A41: Compro la carne ya picada | B41: RD 1021/2022, art. 4.1: la carne picada se conserva a 2 °C o menos y la bola salada antes de la plancha es un preparado de carne: 4 °C o menos. Pide al proveedor la ficha técnica con el blend, el % de grasa y la fecha de sacrificio o de envasado.
A42: Pico la carne en el local | B42: RD 1021/2022, arts. 7.2 y 7.3: la carne que picas en el local es del día y nunca de un día para otro; músculo sin recortes, con como máximo 6 días desde el sacrificio o 15 si va envasada al vacío. Nada de carne madurada más de 15 días (Inf26008).
A43: Compro bolas porcionadas | B43: La bola salada antes de la plancha es un preparado de carne: 4 °C o menos (RD 1021/2022). Guarda la ficha técnica y la etiqueta con la fecha de cada lote.

Sheet Patatas
A1: CALCULADORA DE LAS PATATAS Y EL ACEITE — COSTE POR RACIÓN, KILOS AL DÍA Y LITROS AL MES
A2: Escribe solo en las celdas VERDES: todo lo demás se calcula. Importes sin IVA. Todos los valores por defecto son una estimación del kit, editable: pesa tus raciones, cronometra el pelado y cambia los datos por los tuyos.
A3: AVISO FIJO. Acrilamida (Reglamento (UE) 2017/2158): fríe a menos de 175 °C, guarda la patata fresca a más de 6 °C, remójala o escáldala antes de freírla y compara el color con la guía de colores de patatas. Aceite (Orden de 26 de enero de 1989): polares por debajo del 25 %, nada ajeno al aceite añadido al baño y el usado, a un gestor autorizado; la norma no obliga a tener un medidor.
A5: A. LA PATATA Y EL ACEITE | B5: Valor | C5: Notas
A6: Patata congelada (€/kg, sin IVA) | B6: 1.5 | C6: Minorista a 1,76 €/kg (2,5 kg), McCain a 3,85 €/kg y el lineal a 2,10 €/kg de media (Circana, marzo de 2024); el kit pone 1,50 €/kg. Estimación del kit, editable.
A7: Gramos de patata congelada por ración (g) | B7: 150 | C7: Pesa 10 raciones y usa la media. Estimación del kit, editable.
A8: Aceite que se queda en la ración congelada (% del peso, 1 g ≈ 1 ml) | B8: 0.05 | C8: Lo que absorbe la patata al freírse. Estimación del kit, editable.
A9: Patata fresca (€/kg, sin IVA) | B9: 0.6 | C9: Sin fuente: precio profesional no publicado. Pídelo a tu proveedor. Estimación del kit, editable.
A10: Gramos de patata fresca ya cortada por ración (g) | B10: 150 | C10: Pesa 10 raciones y usa la media. Estimación del kit, editable.
A11: Aprovechamiento de la patata fresca tras pelar y cortar (%) | B11: 0.75 | C11: Sin fuente: mídelo. Pesa 10 kg sin pelar y lo que queda cortado. Estimación del kit, editable.
A12: Aceite que se queda en la ración fresca (% del peso, 1 g ≈ 1 ml) | B12: 0.1 | C12: La fresca absorbe más aceite que la congelada. Estimación del kit, editable.
A13: Minutos de pelar, cortar y remojar un kilo de patata fresca (min) | B13: 6 | C13: Sin fuente: mídelo. Cronometra 3 kilos y usa la media. Estimación del kit, editable.
A14: Coste por hora del cocinero (€/h) | B14: 16 | C14: Igual que en la hoja Carne. Estimación del kit, editable.
A15: Litros de aceite por cuba (l) | B15: 10 | C15: Una cuba de freidora de 8 a 10 litros. Estimación del kit, editable.
A16: Cubas de la freidora | B16: 2 | C16: Freidora de dos cubas. Estimación del kit, editable.
A17: Aceite de girasol alto oleico (€/l, sin IVA) | B17: 1.8 | C17: Minorista a 2,25 €/l; en garrafa, el kit pone 1,80 €/l. Estimación del kit, editable.
... A23: Minutos por hora (constante) | B23: 60 | C23: Constante: una hora son 60 minutos. No se edita.
A25: RESULTADOS | B25: Valor | C25: Notas
A26: Comensales equivalentes al día (de la hoja Carne) | B26: ='Carne'!$B$17 -> 95 | C26: Se escribe en la hoja Carne.
A27: Coste del aceite de un cambio completo (€) | B27: =$B$15*$B$16*$B$17 -> 36 | C27: Litros por cuba × cubas × €/l.
A28: ACEITE POR RACIÓN CONGELADA (€) | B28: =$B$27/$B$18+$B$7*$B$8/$B$22*$B$17 -> 0.0535 | C28: Cambio de aceite ÷ raciones entre cambios + aceite que se queda en la ración.
A29: Patata de una ración congelada (€) | B29: =$B$7*$B$6/$B$21 -> 0.225 | C29: Gramos × €/kg ÷ 1.000.
A30: COSTE POR RACIÓN CONGELADA (€) | B30: =$B$29+$B$28 -> 0.2785 | C30: Patata + aceite.
A31: Kilos de patata sin pelar por ración fresca (kg) | B31: =$B$10/$B$11/$B$21 -> 0.2 | C31: Gramos cortados ÷ aprovechamiento ÷ 1.000.
A32: Patata de una ración fresca (€) | B32: =$B$31*$B$9 -> 0.12 | C32: Kilos sin pelar × €/kg.
A33: Aceite por ración fresca (€) | B33: =$B$27/$B$18+$B$10*$B$12/$B$22*$B$17 -> 0.067 | C33: Cambio de aceite ÷ raciones entre cambios + aceite que se queda en la ración.
A34: COSTE POR RACIÓN FRESCA, SIN MANO DE OBRA (€) | B34: =$B$32+$B$33 -> 0.187 | C34: Patata + aceite.
A35: Mano de obra de pelar, cortar y remojar una ración fresca (€) | B35: =$B$13/$B$23*$B$14*$B$31 -> 0.32 | C35: Minutos por kilo ÷ 60 × coste por hora × kilos sin pelar.
A36: Coste por ración fresca con la mano de obra (€) | B36: =$B$34+$B$35 -> 0.507 | C36: Alimenta el escandallo si eliges la fresca.
A37: Mano de obra por kilo de patata fresca sin pelar (€) | B37: =$B$13/$B$23*$B$14 -> 1.6 | C37: Minutos por kilo ÷ 60 × coste por hora.
A38: LA FRESCA TE COMPENSA MIENTRAS PELAR Y CORTAR CUESTE MENOS DE (€ por kg sin pelar) | B38: =($B$30-$B$34)/$B$31 -> 0.4575 | C38: (Coste de la ración congelada − coste de la ración fresca sin mano de obra) ÷ kilos sin pelar por ración.
A39: Veredicto con tu mano de obra | B39: =IF($B$37<$B$38,"La fresca compensa","La congelada compensa") -> La congelada compensa | C39: La fresca compensa si pelarla y cortarla cuesta menos que esa diferencia.
A40: RACIONES DE PATATA AL DÍA | B40: =$B$26*$B$19 -> 76 | C40: Comensales equivalentes al día × raciones por comensal.
A41: Kilos de patata congelada al día (kg) | B41: =$B$40*$B$7/$B$21 -> 11.4 | C41: Raciones al día × gramos ÷ 1.000.
A42: Kilos de patata fresca sin pelar al día (kg) | B42: =$B$40*$B$31 -> 15.2 | C42: Raciones al día × kilos sin pelar por ración.
A43: LITROS DE ACEITE AL MES (patata congelada) | B43: =$B$40*$B$20*($B$15*$B$16/$B$18+$B$7*$B$8/$B$22) -> 56.472222 | C43: Raciones al mes × (litros de un cambio ÷ raciones entre cambios + aceite que se queda en la ración).

Sheet Escandallo
A1: ESCANDALLO DE LA HAMBURGUESERÍA — 14 PRODUCTOS, POR PRODUCTO Y POR CANAL
A2: Escribe solo en las celdas VERDES (nombres, bolas, queso, pan, otros ingredientes, patatas, precios de carta y ventas). Importes sin IVA salvo el precio de carta. Todos los valores por defecto son una estimación del kit, editable: pon los tuyos. El coste de la bola viene de la hoja «Carne», el de la ración de patata de la hoja «Patatas».
A4: DATOS GENERALES | B4: Valor | D4: Notas
A5: IVA de la comida (%) | B5: 0.1 | D5: Comida preparada, en sala, para llevar y a domicilio: 10 % (Ley 37/1992, art. 91).
A6: Food cost objetivo (% sobre el precio sin IVA) | B6: 0.28 | D6: El del plan de negocio: 28 %, el lado prudente. Estimación del kit, editable.
A7: Margen de vigilancia sobre el objetivo (puntos) | B7: 0.03 | D7: Hasta este margen por encima del objetivo, el semáforo dice «Vigila el coste».
A8: Carne del escandallo (1 a 4: la columna de la hoja Carne) | B8: 1 | D8: 1 = blend comprado ya picado, 2 = pieza para picar, 3 = bolas porcionadas, 4 = libre.
A9: Patata del escandallo (1 congelada, 2 fresca con mano de obra) | B9: 1 | D9: 1 = ración congelada, 2 = ración fresca con la mano de obra de pelar y cortar.
A10: Pan de hamburguesa (€ por pan, sin IVA) | B10: 0.5 | D10: Brioche minorista a 0,94 € la pieza; el kit pone 0,50 € en compra profesional. Estimación del kit, editable.
A11: Queso cheddar en lonchas (€/kg, sin IVA) | B11: 8 | D11: Minorista de 8,75 a 23 €/kg; el kit pone 8,00 €/kg. Estimación del kit, editable.
A12: Gramos de queso por loncha (g) | B12: 20 | D12: Una loncha de 20 g por bola. Pesa 10 lonchas y usa la media. Estimación del kit, editable.
A13: Caja para llevar por pedido (€, sin IVA) | B13: 0.45 | D13: Caja, bolsa y servilletas de un pedido para llevar. Estimación del kit, editable.
A14: Caja de plataforma por pedido (€, sin IVA) | B14: 0.6 | D14: Envase de reparto más sellado. Estimación del kit, editable.
A15: Recargo de precio en la plataforma (%) | B15: 0.15 | D15: Lo que subes el precio en la plataforma para compensar. Estimación del kit, editable.
A16: Comisión de la plataforma de reparto (%) | B16: 0.3 | D16: Sobre el precio sin IVA del pedido. Revisa tu contrato. Estimación del kit, editable.
A17: Coste de la carne de una bola (€, de la hoja Carne) | B17: =CHOOSE($B$8,'Carne'!$B$25,'Carne'!$C$25,'Carne'!$D$25,'Carne'!$E$25) -> 0.91752577
A18: Coste de una ración de patata (€, de la hoja Patatas) | B18: =CHOOSE($B$9,'Patatas'!$B$30,'Patatas'!$B$36) -> 0.2785
A20: PRODUCTO | B20: Bolas de carne (nº) | C20: Lonchas de queso (nº) | D20: Panes (nº) | E20: Otros ingredientes (€) | F20: Raciones de patata (nº) | G20: PVP con IVA de sala (€) | H20: Vendidos a la semana (nº) | I20: COSTE (€) | J20: PVP sin IVA (€) | K20: FOOD COST (%) | L20: Semáforo | M20: PVP con IVA sugerido (€) | N20: Margen en sala (€) | O20: Margen para llevar (€) | P20: Margen en plataforma (€) | Q20: Puesto por margen
A21: Hamburguesa simple (1 bola) | B21: 1 | C21: 1 | D21: 1 | E21: 0.22 | F21: 0 | G21: 8.9 | H21: 140 | I21: =B21*$B$17+D21*$B$10+C21*$B$12*$B$11/'Carne'!$B$19+E21+F21*$B$18 -> 1.7975258 | J21: =G21/(1+$B$5) -> 8.0909091 | K21: =I21/J21 -> 0.22216611 | L21: =IF(K21<=$B$6,"En objetivo",IF(K21<=$B$6+$B$7,"Vigila el coste","Por encima del objetivo")) -> En objetivo | M21: =I21/$B$6*(1+$B$5) -> 7.0617084 | N21: =J21-I21 -> 6.2933833 | O21: =N21-$B$13 -> 5.8433833 | P21: =J21*(1+$B$15)*(1-$B$16)-I21-$B$14 -> 4.115656 | Q21: =1+COUNTIF($N$21:$N$34,">"&N21) -> 10
A22: Hamburguesa doble (2 bolas) | B22: 2 | C22: 2 | D22: 1 | E22: 0.24 | F22: 0 | G22: 11.9 | H22: 240 | I22: =B22*$B$17+D22*$B$10+C22*$B$12*$B$11/'Carne'!$B$19+E22+F22*$B$18 -> 2.8950515 | J22: =G22/(1+$B$5) -> 10.818182 | K22: =I22/J22 -> 0.26760981 | L22: =IF(K22<=$B$6,"En objetivo",IF(K22<=$B$6+$B$7,"Vigila el coste","Por encima del objetivo")) -> En objetivo | M22: =I22/$B$6*(1+$B$5) -> 11.373417 | N22: =J22-I22 -> 7.9231303 | O22: =N22-$B$13 -> 7.4731303 | P22: =J22*(1+$B$15)*(1-$B$16)-I22-$B$14 -> 5.2135848 | Q22: =1+COUNTIF($N$21:$N$34,">"&N22) -> 7
A23: Hamburguesa triple (3 bolas) | B23: 3 | C23: 3 | D23: 1 | E23: 0.26 | F23: 0 | G23: 14.5 | H23: 40 | I23: =B23*$B$17+D23*$B$10+C23*$B$12*$B$11/'Carne'!$B$19+E23+F23*$B$18 -> 3.9925773 | J23: =G23/(1+$B$5) -> 13.181818 | K23: =I23/J23 -> 0.30288518 | L23: =IF(K23<=$B$6,"En objetivo",IF(K23<=$B$6+$B$7,"Vigila el coste","Por encima del objetivo")) -> Vigila el coste | M23: =I23/$B$6*(1+$B$5) -> 15.685125 | N23: =J23-I23 -> 9.1892409 | O23: =N23-$B$13 -> 8.7392409 | P23: =J23*(1+$B$15)*(1-$B$16)-I23-$B$14 -> 6.0187863 | Q23: =1+COUNTIF($N$21:$N$34,">"&N23) -> 3
A24: Hamburguesa doble con bacon | B24: 2 | C24: 2 | D24: 1 | E24: 0.51 | F24: 0 | G24: 12.9 | H24: 90 | I24: =B24*$B$17+D24*$B$10+C24*$B$12*$B$11/'Carne'!$B$19+E24+F24*$B$18 -> 3.1650515 | J24: =G24/(1+$B$5) -> 11.727273 | K24: =I24/J24 -> 0.26988812 | L24: =IF(K24<=$B$6,"En objetivo",IF(K24<=$B$6+$B$7,"Vigila el coste","Por encima del objetivo")) -> En objetivo | M24: =I24/$B$6*(1+$B$5) -> 12.434131 | N24: =J24-I24 -> 8.5622212 | O24: =N24-$B$13 -> 8.1122212 | P24: =J24*(1+$B$15)*(1-$B$16)-I24-$B$14 -> 5.675403 | Q24: =1+COUNTIF($N$21:$N$34,">"&N24) -> 5
A25: Hamburguesa estilo Oklahoma (2 bolas) | B25: 2 | C25: 2 | D25: 1 | E25: 0.4 | F25: 0 | G25: 12.5 | H25: 50 | I25: =B25*$B$17+D25*$B$10+C25*$B$12*$B$11/'Carne'!$B$19+E25+F25*$B$18 -> 3.0550515 | J25: =G25/(1+$B$5) -> 11.363636 | K25: =I25/J25 -> 0.26884454 | L25: =IF(K25<=$B$6,"En objetivo",IF(K25<=$B$6+$B$7,"Vigila el coste","Por encima del objetivo")) -> En objetivo | M25: =I25/$B$6*(1+$B$5) -> 12.001988 | N25: =J25-I25 -> 8.3085848 | O25: =N25-$B$13 -> 7.8585848 | P25: =J25*(1+$B$15)*(1-$B$16)-I25-$B$14 -> 5.4926757 | Q25: =1+COUNTIF($N$21:$N$34,">"&N25) -> 6
A26: Hamburguesa de la casa (2 bolas) | B26: 2 | C26: 2 | D26: 1 | E26: 0.65 | F26: 0 | G26: 13.5 | H26: 70 | I26: =B26*$B$17+D26*$B$10+C26*$B$12*$B$11/'Carne'!$B$19+E26+F26*$B$18 -> 3.3050515 | J26: =G26/(1+$B$5) -> 12.272727 | K26: =I26/J26 -> 0.2693005 | L26: =IF(K26<=$B$6,"En objetivo",IF(K26<=$B$6+$B$7,"Vigila el coste","Por encima del objetivo")) -> En objetivo | M26: =I26/$B$6*(1+$B$5) -> 12.984131 | N26: =J26-I26 -> 8.9676757 | O26: =N26-$B$13 -> 8.5176757 | P26: =J26*(1+$B$15)*(1-$B$16)-I26-$B$14 -> 5.9744939 | Q26: =1+COUNTIF($N$21:$N$34,">"&N26) -> 4
A27: Hamburguesa de pollo crujiente | B27: 0 | C27: 1 | D27: 1 | E27: 1.75 | F27: 0 | G27: 10.9 | H27: 60 | I27: =B27*$B$17+D27*$B$10+C27*$B$12*$B$11/'Carne'!$B$19+E27+F27*$B$18 -> 2.41 | J27: =G27/(1+$B$5) -> 9.9090909 | K27: =I27/J27 -> 0.24321101 | L27: =IF(K27<=$B$6,"En objetivo",IF(K27<=$B$6+$B$7,"Vigila el coste","Por encima del objetivo")) -> En objetivo | M27: =I27/$B$6*(1+$B$5) -> 9.4678571 | N27: =J27-I27 -> 7.4990909 | O27: =N27-$B$13 -> 7.0490909 | P27: =J27*(1+$B$15)*(1-$B$16)-I27-$B$14 -> 4.9668182 | Q27: =1+COUNTIF($N$21:$N$34,">"&N27) -> 8
A28: Hamburguesa vegetal | B28: 0 | C28: 1 | D28: 1 | E28: 1.55 | F28: 0 | G28: 10.5 | H28: 20 | I28: =B28*$B$17+D28*$B$10+C28*$B$12*$B$11/'Carne'!$B$19+E28+F28*$B$18 -> 2.21 | J28: =G28/(1+$B$5) -> 9.5454545 | K28: =I28/J28 -> 0.23152381 | L28: =IF(K28<=$B$6,"En objetivo",IF(K28<=$B$6+$B$7,"Vigila el coste","Por encima del objetivo")) -> En objetivo | M28: =I28/$B$6*(1+$B$5) -> 8.6821429 | N28: =J28-I28 -> 7.3354545 | O28: =N28-$B$13 -> 6.8854545 | P28: =J28*(1+$B$15)*(1-$B$16)-I28-$B$14 -> 4.8740909 | Q28: =1+COUNTIF($N$21:$N$34,">"&N28) -> 9
A29: Ración de patatas | B29: 0 | C29: 0 | D29: 0 | E29: 0 | F29: 1 | G29: 3.9 | H29: 170 | I29: =B29*$B$17+D29*$B$10+C29*$B$12*$B$11/'Carne'!$B$19+E29+F29*$B$18 -> 0.2785 | J29: =G29/(1+$B$5) -> 3.5454545 | K29: =I29/J29 -> 0.078551282 | L29: =IF(K29<=$B$6,"En objetivo",IF(K29<=$B$6+$B$7,"Vigila el coste","Por encima del objetivo")) -> En objetivo | M29: =I29/$B$6*(1+$B$5) -> 1.0941071 | N29: =J29-I29 -> 3.2669545 | O29: =N29-$B$13 -> 2.8169545 | P29: =J29*(1+$B$15)*(1-$B$16)-I29-$B$14 -> 1.9755909 | Q29: =1+COUNTIF($N$21:$N$34,">"&N29) -> 13
A30: Ración de patatas con queso y bacon | B30: 0 | C30: 0 | D30: 0 | E30: 0.64 | F30: 1 | G30: 6.5 | H30: 90 | I30: =B30*$B$17+D30*$B$10+C30*$B$12*$B$11/'Carne'!$B$19+E30+F30*$B$18 -> 0.9185 | J30: =G30/(1+$B$5) -> 5.9090909 | K30: =I30/J30 -> 0.15543846 | L30: =IF(K30<=$B$6,"En objetivo",IF(K30<=$B$6+$B$7,"Vigila el coste","Por encima del objetivo")) -> En objetivo | M30: =I30/$B$6*(1+$B$5) -> 3.6083929 | N30: =J30-I30 -> 4.9905909 | O30: =N30-$B$13 -> 4.5405909 | P30: =J30*(1+$B$15)*(1-$B$16)-I30-$B$14 -> 3.2383182 | Q30: =1+COUNTIF($N$21:$N$34,">"&N30) -> 11
A31: Batido | B31: 0 | C31: 0 | D31: 0 | E31: 1.15 | F31: 0 | G31: 4.9 | H31: 60 | I31: =B31*$B$17+D31*$B$10+C31*$B$12*$B$11/'Carne'!$B$19+E31+F31*$B$18 -> 1.15 | J31: =G31/(1+$B$5) -> 4.4545455 | K31: =I31/J31 -> 0.25816327 | L31: =IF(K31<=$B$6,"En objetivo",IF(K31<=$B$6+$B$7,"Vigila el coste","Por encima del objetivo")) -> En objetivo | M31: =I31/$B$6*(1+$B$5) -> 4.5178571 | N31: =J31-I31 -> 3.3045455 | O31: =N31-$B$13 -> 2.8545455 | P31: =J31*(1+$B$15)*(1-$B$16)-I31-$B$14 -> 1.8359091 | Q31: =1+COUNTIF($N$21:$N$34,">"&N31) -> 12
A32: Postre | B32: 0 | C32: 0 | D32: 0 | E32: 1 | F32: 0 | G32: 4.5 | H32: 55 | I32: =B32*$B$17+D32*$B$10+C32*$B$12*$B$11/'Carne'!$B$19+E32+F32*$B$18 -> 1 | J32: =G32/(1+$B$5) -> 4.0909091 | K32: =I32/J32 -> 0.24444444 | L32: =IF(K32<=$B$6,"En objetivo",IF(K32<=$B$6+$B$7,"Vigila el coste","Por encima del objetivo")) -> En objetivo | M32: =I32/$B$6*(1+$B$5) -> 3.9285714 | N32: =J32-I32 -> 3.0909091 | O32: =N32-$B$13 -> 2.6409091 | P32: =J32*(1+$B$15)*(1-$B$16)-I32-$B$14 -> 1.6931818 | Q32: =1+COUNTIF($N$21:$N$34,">"&N32) -> 14
... A34: Pedido para dos: 2 dobles + 2 patatas | B34: 4 | C34: 4 | D34: 2 | E34: 0.48 | F34: 2 | G34: 29.9 | H34: 35 | I34: =B34*$B$17+D34*$B$10+C34*$B$12*$B$11/'Carne'!$B$19+E34+F34*$B$18 -> 6.3471031 | J34: =G34/(1+$B$5) -> 27.181818 | K34: =I34/J34 -> 0.23350546 | L34: =IF(K34<=$B$6,"En objetivo",IF(K34<=$B$6+$B$7,"Vigila el coste","Por encima del objetivo")) -> En objetivo | M34: =I34/$B$6*(1+$B$5) -> 24.935048 | N34: =J34-I34 -> 20.834715 | O34: =N34-$B$13 -> 20.384715 | P34: =J34*(1+$B$15)*(1-$B$16)-I34-$B$14 -> 14.934261 | Q34: =1+COUNTIF($N$21:$N$34,">"&N34) -> 1
A36: FOOD COST PONDERADO DE LA SEMANA (suma de costes × ventas ÷ suma de PVP sin IVA × ventas) | B36: Valor
A37: Ventas de la semana sin IVA (€) | B37: =SUMPRODUCT($J$21:$J$34,$H$21:$H$34) -> 13427.273
A38: Coste de la comida vendida en la semana (€) | B38: =SUMPRODUCT($I$21:$I$34,$H$21:$H$34) -> 3273.5054
A39: FOOD COST PONDERADO (%) | B39: =IF($B$37=0,0,$B$38/$B$37) -> 0.24379525
A40: Semáforo del food cost ponderado | B40: =IF($B$39<=$B$6,"En objetivo",IF($B$39<=$B$6+$B$7,"Vigila el coste","Por encima del objetivo")) -> En objetivo
A42: El food cost de la tabla es el del producto servido en sala. En el pedido para llevar se descuenta la caja; en la plataforma, además, se sube el precio con el recargo y se descuenta la comisión sobre ese precio. El margen se ordena por el de sala. AVISO FIJO: las patatas viajan mal; en la plataforma, envase ventilado o déjalas fuera del pedido de reparto. El menú se calcula con un solo IVA, el de la comida; si vendes mucha bebida, separa las dos bases. Este coste es TEÓRICO: el plan de negocio trabaja con un 28 %, el lado prudente; la diferencia entre la receta y la caja está explicada en la hoja «Instrucciones».

Sheet Instrucciones
A1: INSTRUCCIONES DE USO — Calculadora de la carne, las patatas y el escandallo
A2: Tres herramientas en un libro: la hoja «Carne» te dice cuánto cuesta el kilo útil del blend comprado ya picado, de la pieza para picar en el local y de las bolas porcionadas, cuánto vale cada bola, cuántas bolas salen de un kilo, cuántos kilos de carne necesitas al día y si te compensa picar en el local; la hoja «Patatas» calcula el coste de la ración congelada y de la fresca, el aceite por ración, los kilos de patata al día y los litros de aceite al mes; la hoja «Escandallo» calcula el coste, el food cost, el margen y el precio de carta de 14 productos, con el margen en sala, para llevar y en plataforma, y el food cost ponderado de tu semana. Solo se escribe en las celdas VERDES; lo demás se calcula.
A3: Todos los valores por defecto son estimación del kit, editable: son ejemplos coherentes con el caso del plan de negocio, no precios de nadie. Cámbialos por los de tu proveedor y por lo que midas en tu plancha y tu freidora antes de decidir precios.
A4: HOJA «CARNE»
A6: 1. Pesa 10 bolas y usa la media en los gramos por bola. Pesa también 10 bolas antes y después de la plancha para medir la merma de cocción (sin fuente: mídelo). Si picas en el local, pesa la pieza antes de limpiarla y la carne limpia después, y cronometra cuánto tardas en limpiar y picar un kilo.
A7: 2. El coste por kilo útil es el precio ÷ útil ÷ (1 − merma de cierre). Con los valores del kit sale a 9,18 €/kg el blend comprado ya picado y a 8,59 €/kg la pieza para picar, sin contar la mano de obra. El coste de una bola es ese coste por kilo útil con la mano de obra × los gramos ÷ 1.000: 0,918 € con el blend.
A8: 3. Bolas por kilo. En crudo son 1.000 ÷ gramos por bola: 10 bolas de 100 g por kilo, la cifra de la ficha técnica del proveedor. Contando la merma de cierre del 3 % salen 9,7. Con 1,6 bolas por comensal y 95 comensales equivalentes al día, necesitas unos 15,2 kg de carne al día: es el pedido diario y, si picas en el local, el picado del día.
A9: 4. ¿Picar o comprar? Con los valores del kit, picar en el local solo te compensa mientras limpiar y picar un kilo cueste menos de 0,58 € por kilo útil; con 6 minutos por kilo y 16 € la hora cuesta 1,83 €: el veredicto es «Compra el blend ya picado». Mide tus minutos antes de comprar la picadora.
A10: 5. Carne picada (RD 1021/2022, arts. 4.1, 7.2 y 7.3). Comprada picada o picada en el local, se conserva a 2 °C o menos; la bola salada antes de la plancha es un preparado de carne, a 4 °C o menos; la picada en el local es del día y nunca de un día para otro, con músculo sin recortes y como máximo 6 días desde el sacrificio, o 15 si va envasada al vacío. Nada de carne madurada más de 15 días (Inf26008). El desplegable de la hoja es solo un recordatorio: no cambia ningún cálculo.
A11: HOJA «PATATAS»
A13: 1. Pesa 10 raciones de patata y usa la media. Si usas fresca, pesa 10 kg sin pelar y lo que queda cortado para medir el aprovechamiento, y cronometra el pelado, el corte y el remojo de un kilo. Para el aceite, anota cuántas raciones aguanta cada cambio con los polares por debajo del 25 % (sin fuente: mídelo).
A14: 2. Con los valores del kit, una ración congelada cuesta 0,28 € (de ellos, 0,05 € de aceite) y una fresca 0,19 € sin mano de obra y 0,51 € con ella. La fresca solo te compensa mientras pelar y cortar un kilo cueste menos de 0,46 €; con 6 minutos por kilo y 16 € la hora cuesta 1,60 €: el veredicto es «La congelada compensa».
... A35: Versión 1.0 · noviembre 2026 · aichef.pro/plan-negocio-hamburgueseria · info@aichef.pro
