Workbook

Sheet 0. Assumptions
A1: ASSUMPTIONS — the RATES and DRIVERS of the model are typed here
A2: Change the GREEN cells: the rest of the workbook recalculates on its own. Expense items are typed on their own tab (also in green) and are not repeated here. Amounts are in your currency.
A3: BUSINESS ACTIVITY
A4: Customers per day (year-1 average) | B4: 145 | C4: Customers served per day, averaged over the year, counting bar coffee and table brunch. Inside the 100-250 range that the industry benchmarks table of this workbook publishes for a small coffee shop; the seat turns this implies are calculated by the "Implied seat turns per day" cell on this same tab
A5: Average check (excl. sales tax) | B5: 11 | C5: EXCL. SALES TAX. The equivalent menu price is calculated by the "Menu price incl. sales tax (calculated)" cell on this same tab; compare it with the "Combined average check" in the industry benchmarks table, further down on the "Instructions" tab
A6: Operating days per year | B6: 340 | C6: The SAME number feeds the "3-Year P&L", the "Break-Even" tab and the "Scenarios" tab, so all three always work on the same operating calendar
A7: Volume growth in year 2 | B7: 0.07 | C7: Second year, with the neighborhood regulars already loyal. This is peak-hour occupancy, not brand-new customers: year 1 already starts from a steady base of customers per day
A8: Volume growth in year 3 | B8: 0.05 | C8: Third year, close to the seating ceiling during peak hours
A9: Menu price incl. sales tax (calculated) | B9: =IFERROR(IF($B$5="","",$B$5*(1+SUMPRODUCT('3-Year P&L'!$E$10:$E$11,'3-Year P&L'!$G$10:$G$11))),"") -> 11.88 | C9: =IFERROR("Average check excl. sales tax plus the weighted sales tax of your sales lines ("&TEXT(SUMPRODUCT('3-Year P&L'!$E$10:$E$11,'3-Year P&L'!$G$10:$G$11)*100,"0")&"%), rounded. In the US, menu prices usually exclude sales tax and it is added at the register; in the UK, menu prices include VAT.","") -> Average check excl. sales tax plus the weighted sales tax of your sales lines (8%), rounded. In the US, menu prices usually exclude sales tax and it is added at the register; in the UK, menu prices include VAT.
A10: SALES MIX AND COST OF GOODS SOLD
A11: FOOD share of total sales | B11: 0.41 | C11: Share of FOOD in total sales. It is an INPUT: change it here and the P&L, the cash flow and the sales tax collected recalculate on their own
A12: BEVERAGE share of total sales | B12: =IFERROR(IF(COUNT(B11)=0,"",1-B11),"") -> 0.59 | C12: Calculated as the remainder: food + beverage = 100%
A13: Cost of goods sold on FOOD sales | B13: 0.3 | C13: Cost of the food (brunch, pastries, toasts): inside the 30-35% that the industry benchmarks table of this workbook gives for brunch food
A14: Cost of goods sold on BEVERAGE sales | B14: 0.24 | C14: Cost of coffee and beverages (hot and cold) against their own sales: a weighted blend of the coffee and cold-drink ranges in the industry benchmarks table of this workbook
A15: Disposables and packaging as % of sales | B15: 0.03 | C15: Napkins, paper goods, to-go cups and bar cleaning supplies
A16: Delivery share of total sales | B16: 0 | C16: ZERO by default: the checklist for this opening lists delivery as a month 2-3 task ("Launch delivery if there is demand"), not a day-one task. Raise it to the real weight of the channel when you turn it on
A17: Delivery platform fee | B17: 0.25 | C17: Typical DoorDash / Uber Eats commission on orders served through that channel; confirm it in your contract before projecting
A18: Card processing fee | B18: 0.035 | C18: Card and mobile wallet fees on total sales; a counter-service coffee shop takes most tickets by card. The example (3.5%) is a blended rate: a percentage plus a per-transaction fee, which weighs more on small tickets; check your processor's statement and enter your effective rate (kit estimate)
A19: LABOR
A20: Employer payroll taxes | B20: 0.1 | C20: FICA (Social Security 6.2% + Medicare 1.45%) + federal and state unemployment taxes (FUTA / SUTA) + workers' comp. About 10% in total: adjust it to your state and your insurance carrier
A21: Monthly pay periods per year (keep 12) | B21: 12 | C21: Annual gross pay = monthly gross pay × this number. Keep 12 in the US: it counts the monthly salaries the model pays in a year, not how often you run payroll (weekly or biweekly payroll pays the same annual amount)
A22: Federal minimum wage, annual full-time | B22: 15080 | C22: US federal minimum wage: 7.25 per hour × 2,080 hours = 15,080 per year for a full-time job. Your state or city may set a higher floor: enter it in the state / local minimum wage cell below. Check the current rates at dol.gov
A23: RENT AND FIXED COSTS
A24: Monthly rent | B24: 4500 | C24: Space for a coffee shop with brunch: 30-40 indoor seats plus a patio. Include NNN / CAM charges (property tax, building insurance, common-area maintenance) in this cell, not just the base rent. Check it against the 12% of sales threshold in the "3-Year P&L" and the 10% target / 15% maximum in the industry benchmarks table of this workbook
A25: Security deposit (months of rent) | B25: 2 | C25: Months of rent held as a security deposit. It is set in your commercial lease, so check the terms before you sign
A26: Monthly utilities (electricity, water, gas) | B26: 1200 | C26: Electricity, water and gas for a coffee bar with a brunch oven: ask for the space's utility history before you sign
A27: Insurance (per year) | B27: 3500 | C27: General liability (landlords and events often require 1 million per occurrence) and property coverage or a business owner's policy (BOP) for the space
A28: Miscellaneous and contingency as % of sales | B28: 0.02 | C28: Cushion for operating expenses that are not budgeted
A29: FINANCING
A30: Owner's equity contributed | B30: 60000 | C30: Owners' contribution. With too little, lenders pass: they usually expect an owner equity injection (often around 10% for SBA start-ups; many want 20-30%) measured against the cash need calculated on the "Startup Costs" tab
A31: Loan requested | B31: 204000 | C31: Principal requested — bank or SBA 7(a): if your loan is an SBA 7(a), this is the cell. It is the only loan that the amortization schedule, the P&L interest and the DSCR use. The "Financing" tab checks that sources and uses match the cash need calculated on the "Startup Costs" tab, and has a cell that calculates the exact amount that balances them
A32: Nominal annual interest rate (not APR) | B32: 0.1 | C32: Nominal annual rate, not APR; get offers from two lenders, including an SBA-guaranteed loan, before you fix it
A33: Loan term (years) | B33: 10 | C33: Total years, interest-only period included
A34: Interest-only period (years) | B34: 0 | C34: Years in which you pay only interest, usually the first year, when cash is tightest. Zero by default in this workbook
A35: Working capital (months of fixed costs) | B35: 3 | C35: The minimum this workbook requires: a cushion of less than 3 months will not cover a slow season
A36: TAXES
A37: Effective income tax rate (years 1-2) | B37: 0.25 | C37: Example: 21% federal rate for a C corporation plus state tax, rounded to 25%. If you operate as a sole proprietorship, LLC taxed as a pass-through or S corporation, the business itself pays 0% here and you pay tax on the profit personally: set this to 0 and budget for your personal tax separately. The model applies this rate to the first two years with positive taxable income
A38: Effective income tax rate (from year 3) | B38: 0.25 | C38: From the third year with positive taxable income. Same example rate (21% federal C corporation + state). Confirm the rate that applies to you with your accountant and change it here
A39: Sales tax rate on sales | B39: 0.08 | C39: Example rate: state + local sales tax combined. It varies widely by state and city: look up yours. UK: 20% VAT on hot food and dine-in
A40: Sales tax rate on alcohol to go | B40: 0.08 | C40: Same example rate as above. Some states add separate liquor taxes: include them here if they apply to you. Alcohol served on site has its own rate in the sales tax breakdown block, further down. Utilities, equipment and services are handled in the cell below
A41: Recoverable input tax on purchases and capex | B41: 0 | C41: In the US, the sales tax you pay on purchases is a cost, not a credit: leave this at 0%. UK: 20% if you are VAT-registered
A42: Net operating losses carried forward | B42: 0 | C42: Net operating losses from earlier years still to be offset at the start. Federal rules let you offset up to 80% of taxable income in a year; the model offsets 100% as a simplification
A43: DEPRECIATION
A44: Useful life of build-out and fixtures (years) | B44: 10 | C44: Build-out, fixtures and decor of a coffee shop. Book depreciation in this model is straight-line; MACRS and Section 179 are tax treatments handled outside the model, so confirm them with your accountant
A45: Useful life of machinery, furniture and equipment (years) | B45: 7 | C45: Espresso machine, grinder, oven, display cases and furniture. Book depreciation in this model is straight-line; MACRS and Section 179 are tax treatments handled outside the model, so confirm them with your accountant
A47: GROWTH AND COST INFLATION
A48: Annual increase in fixed costs | B48: 0 | C48: SET TO ZERO: all three columns are in year-1 prices (real terms). Raise it if you want to project in nominal terms
A49: RAMP-UP AND CAPACITY
A50: Implied seat turns per day (calculated) | B50: =IFERROR($B$4/$B$51,"") -> 3.2222222 | C50: =IFERROR("That is "&TEXT(INT(ROUND(B50,1)),"0")&"."&TEXT(ROUND(MOD(ROUND(B50,1),1)*10,0),"0")&" seat turns per day on the "&TEXT($B$51,"0")&" seats in the cell below. This workbook assumes 2-3 table turns at weekend brunch: compare this average with your real opening hours before you rely on it.","") -> That is 3.2 seat turns per day on the 45 seats in the cell below. This workbook assumes 2-3 table turns at weekend brunch: compare this average with your real opening hours before you rely on it.
A51: Seating capacity (seats at tables + bar) | B51: 45 | C51: Indoor seats (30-40 according to the "Startup Costs" tab) plus the patio (8-10 tables). The implied turn comes from this: customers per day ÷ seats
A52: Month-1 activity as a % of steady-state activity | B52: 0.55 | C52: A new shop does not sell on day one what it sells six months later. Customers per day above are the year-1 AVERAGE: the ramp only spreads year 1's sales across the months (slower start, stronger finish) and keeps the annual total. At 100% there is no ramp
A53: Months to reach steady state | B53: 6 | C53: The ramp rises in a straight line from the percentage above to 100% over this number of months
A54: Months of rent BEFORE opening (build-out and permits) | B54: 1 | C54: You pay for the space from the day you sign. These months are a startup cost: they do NOT overlap the P&L, which starts on opening day
A55: Contingency on the BUILD-OUT lines of the space block (%) | B55: 0.1 | C55: Cushion on the build-out and fit-out line. A lender will not finance a renovation without it
A57: RECEIPTS, PAYMENTS AND SALES TAX BREAKDOWN
A58: Average collection days | B58: 1 | C58: At 1 day, card settlements reach your bank the next business day. Raise it if you work with reservation or delivery platforms, which usually pay out between the next day and 30 days later
A59: Average days to pay suppliers | B59: 14 | C59: What your suppliers finance for you. It is the first thing you lose if you fall behind on a payment
A60: Month of extra pay period 1 (only if pay periods > 12) | B60: 7 | C60: Month of the year (1-12) when the first extra pay period is paid out. Only used if pay periods > 12
A61: Month of extra pay period 2 (only if pay periods > 12) | B61: 12 | C61: Month of the year (1-12) when the second extra pay period is paid out. Only used if pay periods > 12
A62: ALCOHOLIC beverages as a share of total beverage sales | B62: 0 | C62: Alcohol as a share of total beverage sales: minimal in a coffee shop with brunch (a mimosa or a celebratory sparkling wine). If you serve alcohol, you also need your state liquor license. The rest of the beverages (coffee, juices, smoothies, soft drinks) uses the regular sales tax rate
A63: Sales tax rate on alcohol served on site | B63: 0.08 | C63: Same rate as the rest of on-site sales in this example (8%: state + local). Alcohol rates vary by state and some states add a separate liquor tax: check yours. The workbook applies the alcohol rates only to the ALCOHOLIC part of beverage sales
A64: CONTROL THRESHOLDS AND FLOORS
A65: DSCR limit (minimum acceptable) | B65: 1.15 | C65: Below 1.0 the business does not generate enough to repay the loan. Lenders often write a minimum DSCR into the loan covenants: ask yours. Kit default: 1.15×
A66: DSCR target (green) | B66: 1.25 | C66: What lenders commonly look for before approving a loan comfortably. Kit default: 1.25× (editable estimate)
A67: Minimum cushion above break-even | B67: 0.15 | C67: How far planned sales must sit above cash break-even (fixed costs and the loan payment). The drop you can absorb is somewhat smaller: with a 15% cushion, about 13% of plan
A68: State / local minimum wage, annual full-time | C68: Your STATE or LOCAL minimum wage can be higher than the federal one: enter it here as an annual full-time figure (hourly rate × 2,080 hours). The higher of the two applies. Leave it empty or at 0 and the traffic light compares only against the federal minimum

Sheet Startup Costs
A1: BUSINESS PLAN: COFFEE SHOP WITH BRUNCH
A2: Estimated Startup Costs
A3: Adjust the figures to your project. The amounts are reference prices for a US coffee shop: get local quotes before you commit.
A5: Item | B5: Amount | C5: % of startup costs | D5: Notes | E5: Taxable / recoverable tax?
A6: STARTUP COSTS | B6: =IFERROR(IF(COUNT(B7:B32)=0,"",SUM(B7:B32)),"") -> 193800 | C6: =IFERROR(B6/$B$35,"") -> 0.73496312
A7: LLC formation and legal | B7: 1500 | C7: =IFERROR(B7/$B$35,"") -> 0.005688569 | D7: Articles of organization (state filing fee), registered agent and attorney time for the operating agreement. Fees vary by state | E7: No
A8: Licenses and health plan review | B8: 2000 | C8: =IFERROR(B8/$B$35,"") -> 0.0075847587 | D8: Business license, health permit fees and the health department plan review. Requirements vary by city and county | E8: No
A9: Architect and building permits | B9: 8000 | C9: =IFERROR(B9/$B$35,"") -> 0.030339035 | D9: Required in many places for a build-out or a change of use. Covers drawings, specifications and building permit fees | E9: Yes
A10: Construction / build-out | B10: 40000 | C10: =IFERROR(B10/$B$35,"") -> 0.15169517 | D10: Floors, paint, finishes and an accessible restroom (ADA) | E10: Yes
A11: Electrical and HVAC | B11: 15000 | C11: =IFERROR(B11/$B$35,"") -> 0.05688569 | D11: Minimum 15-20 kW of electrical service for the equipment | E11: Yes
A12: Plumbing (grease interceptor, floor drains, handwashing sinks) | B12: 10000 | C12: =IFERROR(B12/$B$35,"") -> 0.037923794 | D12: Water supply, drains, handwashing sinks and a grease interceptor if you cook; local code decides | E12: Yes
A13: Coffee grinders | B13: 3000 | C13: =IFERROR(B13/$B$35,"") -> 0.011377138 | D13: On-demand grinder, essential for specialty coffee | E13: Yes
A14: Oven | B14: 6000 | C14: =IFERROR(B14/$B$35,"") -> 0.022754276 | D14: For pastries, brunch and hot toasts | E14: Yes
A15: Refrigerated display case | B15: 5000 | C15: =IFERROR(B15/$B$35,"") -> 0.018961897 | D15: For sandwiches, cakes and pastries | E15: Yes
A16: Refrigeration | B16: 6000 | C16: =IFERROR(B16/$B$35,"") -> 0.022754276 | D16: 2-3 under-counter units plus 1 storage refrigerator | E16: Yes
A17: Griddle / panini press | B17: 2000 | C17: =IFERROR(B17/$B$35,"") -> 0.0075847587 | D17: For toasts, paninis and brunch eggs | E17: Yes
A18: Blenders, juicer, toaster | B18: 1500 | C18: =IFERROR(B18/$B$35,"") -> 0.005688569 | D18: Fresh juices, smoothies, toast | E18: Yes
... A29: POS and software | B29: 3000 | C29: =IFERROR(B29/$B$35,"") -> 0.011377138 | D29: Touchscreen POS with cash and inventory control software | E29: Yes
A30: Security deposit | B30: =IFERROR(IF('0. Assumptions'!$B$24="","",'0. Assumptions'!$B$24*'0. Assumptions'!$B$25),"") -> 9000 | C30: =IFERROR(B30/$B$35,"") -> 0.034131414 | D30: =IFERROR(""&TEXT('0. Assumptions'!$B$25,"0")&IF('0. Assumptions'!$B$25=1," month"," months")&" of rent, from ""0. Assumptions"". Refundable when the lease ends: it is not depreciated and carries no tax","") -> 2 months of rent, from "0. Assumptions". Refundable when the lease ends: it is not depreciated and carries no tax | E30: No
A31: Rent paid before opening | B31: =IFERROR(IF('0. Assumptions'!$B$24="","",'0. Assumptions'!$B$24*'0. Assumptions'!$B$54),"") -> 4500 | C31: =IFERROR(B31/$B$35,"") -> 0.017065707 | D31: =IFERROR("Rent "&IF('0. Assumptions'!$B$54=1,"for the month","for the "&TEXT('0. Assumptions'!$B$54,"0")&" months")&" of build-out and permits before opening. It does not overlap the P&L, which starts on opening day: its twelve months are twelve trading months","") -> Rent for the month of build-out and permits before opening. It does not overlap the P&L, which starts on opening day: its twelve months are twelve trading months | E31: Yes
A32: Build-out and setup contingency | B32: =IFERROR(IF(COUNT(B9,B10,B11,B12,B24,B25)=0,"",ROUND((B9+B10+B11+B12+B24+B25)*'0. Assumptions'!$B$55,0)),"") -> 8300 | C32: =IFERROR(B32/$B$35,"") -> 0.031476749 | D32: =IFERROR("At "&TEXT('0. Assumptions'!$B$55,"0%")&" of the BUILD-OUT items of this block (architect and building permits, construction, electrical and HVAC, plumbing, decor and lighting, signage), not of the whole block: the other items are left out. No lender funds a build-out without a "&"cushion: the percentage is in ""0. Assumptions""","") -> At 10% of the BUILD-OUT items of this block (architect and building permits, construction, electrical and HVAC, plumbing, decor and lighting, signage), not of the whole block: the other items are left out. No lender funds a build-out without a cushion: the percentage is in "0. Assumptions" | E32: Yes
A33: WORKING CAPITAL | B33: =IFERROR(IF(B34="","",B34),"") -> 69886.7 | C33: =IFERROR(B33/$B$35,"") -> 0.26503688
A34: Operating cushion until break-even | B34: =IFERROR(IF('0. Assumptions'!$B$35*('3-Year P&L'!$B$37-'3-Year P&L'!$B$35)=0,"",'0. Assumptions'!$B$35*('3-Year P&L'!$B$37-'3-Year P&L'!$B$35)/12),"") -> 69886.7 | C34: =IFERROR(B34/$B$35,"") -> 0.26503688 | D34: =IFERROR("Covers "&TEXT('0. Assumptions'!$B$35,"0")&IF('0. Assumptions'!$B$35=1," month"," months")&" of year-1 CASH fixed costs (the P&L fixed costs minus depreciation, which is not paid out), the minimum the Instructions of this workbook ask for","") -> Covers 3 months of year-1 CASH fixed costs (the P&L fixed costs minus depreciation, which is not paid out), the minimum the Instructions of this workbook ask for | E34: No
A35: TOTAL STARTUP COSTS (sum of the blocks) | B35: =IFERROR(B6+B33,"") -> 263686.7 | D35: =IFERROR("The percentages in column C are read on this figure, which includes the working capital ("&TEXT(C33,"0%")&" of the total). To compare the breakdown with another plan, use the CAPEX row below.","") -> The percentages in column C are read on this figure, which includes the working capital (27% of the total). To compare the breakdown with another plan, use the CAPEX row below.
A36: CAPEX (startup costs excluding working capital) | B36: =IFERROR(B35-B33,"") -> 193800 | D36: What you buy: build-out, equipment, launch and formation costs. The cash cushion is not an investment: it is working capital
A37: Recoverable input tax on capex | B37: =IFERROR(IF(B35="","",SUMIF($E$7:$E$32,"Yes",$B$7:$B$32)*'0. Assumptions'!$B$41),"") -> 0 | D37: =IFERROR("At "&TEXT('0. Assumptions'!$B$41,"0%")&" on the items marked ""Yes"" in the tax column. US: the sales tax you pay on equipment is part of its cost and is not recovered, so this rate is 0. UK (VAT-registered): 20%, reclaimed on your VAT return, but you pay it first, so the loan has to cover it","") -> At 0% on the items marked "Yes" in the tax column. US: the sales tax you pay on equipment is part of its cost and is not recovered, so this rate is 0. UK (VAT-registered): 20%, reclaimed on your VAT return, but you pay it first, so the loan has to cover it
A38: TOTAL CASH NEEDED AT LAUNCH | B38: =IFERROR(B35+B37,"") -> 263686.7 | D38: This is the figure the Financing tab has to cover
A39: DEPRECIATION BASES (not added to startup costs)
A40: Build-out, fixtures and setup | B40: =IFERROR(IF(B9="","",B9+B10+B11+B12+B24+B25+B32),"") -> 91300 | D40: =IFERROR("Depreciated over "&TEXT('0. Assumptions'!$B$44,"0")&" years","") -> Depreciated over 10 years
A41: Machinery, furniture and equipment | B41: =IFERROR(IF(B13="","",B13+B14+B15+B16+B17+B18+B19+B20+B21+B22+B23+B28+B29),"") -> 76500 | D41: =IFERROR("Depreciated over "&TEXT('0. Assumptions'!$B$45,"0")&" years","") -> Depreciated over 7 years
A42: Annual depreciation of fixed assets | B42: =IFERROR(B40/MAX(1,'0. Assumptions'!$B$44)+B41/MAX(1,'0. Assumptions'!$B$45),"") -> 20058.571 | D42: =IFERROR("Not depreciated, because they are not fixed assets: entity formation and legal, licenses and health plan review, launch marketing, opening inventory, security deposit, pre-opening rent and the working capital reserve. They add up to "&TEXT(B35-B40-B41,"#,##0")&" of the "&TEXT(B35,"#,##0")&" total investment.","") -> Not depreciated, because they are not fixed assets: entity formation and legal, licenses and health plan review, launch marketing, opening inventory, security deposit, pre-opening rent and the working capital reserve. They add up to 95887 of the 263687 total investment.

Sheet 3-Year P&L
A1: PRO FORMA P&L — 3 YEARS
A2: Base scenario — Coffee shop with brunch, 35-40 seats
A4: Item | B4: Year 1 | C4: Year 2 | D4: Year 3 | E4: % of sales (year 1) | F4: Notes | G4: Sales tax rate on the line (%)
A5: REVENUE
A6: Customers per day (average) | B6: =IFERROR(IF('0. Assumptions'!$B$4="","",'0. Assumptions'!$B$4),"") -> 145 | C6: =IFERROR(B6*(1+'0. Assumptions'!$B$7),"") -> 155.15 | D6: =IFERROR(C6*(1+'0. Assumptions'!$B$8),"") -> 162.9075 | F6: Growth for years 2 and 3 is set in "0. Assumptions"
A7: Average check (excl. sales tax) | B7: =IFERROR(IF('0. Assumptions'!$B$5="","",'0. Assumptions'!$B$5),"") -> 11 | C7: =IFERROR(IF(B7="","",B7),"") -> 11 | D7: =IFERROR(IF(C7="","",C7),"") -> 11 | F7: Held constant at year-1 prices: a price increase is a separate decision
A8: Operating days per year | B8: =IFERROR(IF('0. Assumptions'!$B$6="","",'0. Assumptions'!$B$6),"") -> 340 | C8: =IFERROR(IF(B8="","",B8),"") -> 340 | D8: =IFERROR(IF(C8="","",C8),"") -> 340
A9: TOTAL REVENUE (excl. sales tax) | B9: =IFERROR(IF(B6*B7*B8=0,"",B6*B7*B8),"") -> 542300 | C9: =IFERROR(IF(C6*C7*C8=0,"",C6*C7*C8),"") -> 580261 | D9: =IFERROR(IF(D6*D7*D8=0,"",D6*D7*D8),"") -> 609274.05 | E9: =IFERROR(IF(B9="","",1),"") -> 1
A10: Food sales (brunch, pastries, toasts and other) | B10: =IFERROR(IF(B9="","",B9*$E$10),"") -> 222343 | C10: =IFERROR(IF(C9="","",C9*$E$10),"") -> 237907.01 | D10: =IFERROR(IF(D9="","",D9*$E$10),"") -> 249802.36 | E10: =IFERROR(IF('0. Assumptions'!$B$11="","",'0. Assumptions'!$B$11),"") -> 0.41 | F10: Weekend brunch, pastries and toasts from the morning service, plus smaller seasonal sales (extra takeout, mini catering, merchandise) | G10: =IFERROR(IF(B9="","",'0. Assumptions'!$B$39),"") -> 0.08
A11: Beverage sales (coffee, hot and cold drinks) | B11: =IFERROR(IF(B9="","",B9*$E$11),"") -> 319957 | C11: =IFERROR(IF(C9="","",C9*$E$11),"") -> 342353.99 | D11: =IFERROR(IF(D9="","",D9*$E$11),"") -> 359471.69 | E11: =IFERROR(IF('0. Assumptions'!$B$12="","",'0. Assumptions'!$B$12),"") -> 0.59 | F11: Espresso, milk drinks, teas and brewed drinks from the bar, plus fresh juices and smoothies, which carry the highest cost because they use fresh product | G11: =IFERROR(IF(B9="","",('0. Assumptions'!$B$62*((1-'0. Assumptions'!$B$16)*'0. Assumptions'!$B$63+'0. Assumptions'!$B$16*'0. Assumptions'!$B$40)+(1-'0. Assumptions'!$B$62)*'0. Assumptions'!$B$39)),"") -> 0.08
A12: VARIABLE COSTS
A13: Cost of goods sold — food | B13: =IFERROR(IF(B9="","",B9*'0. Assumptions'!$B$11*'0. Assumptions'!$B$13),"") -> 66702.9 | C13: =IFERROR(IF(C9="","",C9*'0. Assumptions'!$B$11*'0. Assumptions'!$B$13),"") -> 71372.103 | D13: =IFERROR(IF(D9="","",D9*'0. Assumptions'!$B$11*'0. Assumptions'!$B$13),"") -> 74940.708 | E13: =IFERROR(B13/$B$9,"") -> 0.123 | F13: =IFERROR("At "&TEXT('0. Assumptions'!$B$13,"0%")&" of FOOD sales, not of total sales: beverages have their own line","") -> At 30% of FOOD sales, not of total sales: beverages have their own line | G13: =IFERROR(IF(B9="","",'0. Assumptions'!$B$41),"") -> 0
A14: Cost of goods sold — beverage | B14: =IFERROR(IF(B9="","",B9*'0. Assumptions'!$B$12*'0. Assumptions'!$B$14),"") -> 76789.68 | C14: =IFERROR(IF(C9="","",C9*'0. Assumptions'!$B$12*'0. Assumptions'!$B$14),"") -> 82164.958 | D14: =IFERROR(IF(D9="","",D9*'0. Assumptions'!$B$12*'0. Assumptions'!$B$14),"") -> 86273.205 | E14: =IFERROR(B14/$B$9,"") -> 0.1416 | F14: =IFERROR("At "&TEXT('0. Assumptions'!$B$14,"0%")&" of BEVERAGE sales","") -> At 24% of BEVERAGE sales | G14: =IFERROR(IF(B9="","",'0. Assumptions'!$B$41),"") -> 0
A15: Disposables and packaging | B15: =IFERROR(IF(B9="","",B9*'0. Assumptions'!$B$15),"") -> 16269 | C15: =IFERROR(IF(C9="","",C9*'0. Assumptions'!$B$15),"") -> 17407.83 | D15: =IFERROR(IF(D9="","",D9*'0. Assumptions'!$B$15),"") -> 18278.221 | E15: =IFERROR(B15/$B$9,"") -> 0.03 | G15: =IFERROR(IF(B9="","",'0. Assumptions'!$B$41),"") -> 0
A16: Delivery platform fees | B16: =IFERROR(IF(B9="","",B9*'0. Assumptions'!$B$16*'0. Assumptions'!$B$17),"") -> 0 | C16: =IFERROR(IF(C9="","",C9*'0. Assumptions'!$B$16*'0. Assumptions'!$B$17),"") -> 0 | D16: =IFERROR(IF(D9="","",D9*'0. Assumptions'!$B$16*'0. Assumptions'!$B$17),"") -> 0 | E16: =IFERROR(B16/$B$9,"") -> 0 | F16: Applied to the sales of THAT CHANNEL. With 0% delivery in Assumptions, this line is zero | G16: =IFERROR(IF(B9="","",'0. Assumptions'!$B$41),"") -> 0
A17: Card processing fees | B17: =IFERROR(IF(B9="","",B9*'0. Assumptions'!$B$18),"") -> 18980.5 | C17: =IFERROR(IF(C9="","",C9*'0. Assumptions'!$B$18),"") -> 20309.135 | D17: =IFERROR(IF(D9="","",D9*'0. Assumptions'!$B$18),"") -> 21324.592 | E17: =IFERROR(B17/$B$9,"") -> 0.035 | F17: Card processing fees are not subject to sales tax: no tax is recovered or deducted for them | G17: 0
A18: Miscellaneous and contingency | B18: =IFERROR(IF(B9="","",B9*'0. Assumptions'!$B$28),"") -> 10846 | C18: =IFERROR(IF(C9="","",C9*'0. Assumptions'!$B$28),"") -> 11605.22 | D18: =IFERROR(IF(D9="","",D9*'0. Assumptions'!$B$28),"") -> 12185.481 | E18: =IFERROR(B18/$B$9,"") -> 0.02 | F18: =IFERROR("At "&TEXT('0. Assumptions'!$B$28,"0%")&" of sales. It is a VARIABLE cost: it moves with revenue, so it cannot sit in fixed costs","") -> At 2% of sales. It is a VARIABLE cost: it moves with revenue, so it cannot sit in fixed costs | G18: =IFERROR(IF(B9="","",'0. Assumptions'!$B$41),"") -> 0
A19: TOTAL VARIABLE COSTS | B19: =IFERROR(IF(B9="","",SUM(B13:B18)),"") -> 189588.08 | C19: =IFERROR(IF(C9="","",SUM(C13:C18)),"") -> 202859.25 | D19: =IFERROR(IF(D9="","",SUM(D13:D18)),"") -> 213002.21 | E19: =IFERROR(B19/$B$9,"") -> 0.3496
A20: GROSS MARGIN | B20: =IFERROR(IF(B9="","",B9-B19),"") -> 352711.92 | C20: =IFERROR(IF(C9="","",C9-C19),"") -> 377401.75 | D20: =IFERROR(IF(D9="","",D9-D19),"") -> 396271.84 | E20: =IFERROR(B20/$B$9,"") -> 0.6504
A21: FIXED COSTS
A22: Rent | B22: =IFERROR(IF(B9="","",'0. Assumptions'!$B$24*12),"") -> 54000 | C22: =IFERROR(IF(C9="","",B22*(1+'0. Assumptions'!$B$48)),"") -> 54000 | D22: =IFERROR(IF(D9="","",C22*(1+'0. Assumptions'!$B$48)),"") -> 54000 | E22: =IFERROR(B22/$B$9,"") -> 0.099575881 | F22: The monthly amount is on the "0. Assumptions" tab; here it is multiplied by twelve. Rent for the build-out months, which comes before opening, is on the "Startup Costs" tab and is NOT counted twice | G22: =IFERROR(IF(B9="","",'0. Assumptions'!$B$41),"") -> 0
A23: Labor (wages + employer payroll taxes) | B23: =IFERROR(IF(B9="","",Staffing!$G$11),"") -> 168946.8 | C23: =IFERROR(IF(C9="","",Staffing!$B$15),"") -> 174946.8 | D23: =IFERROR(IF(D9="","",Staffing!$B$16),"") -> 180946.8 | E23: =IFERROR(B23/$B$9,"") -> 0.31153753 | F23: Comes from the Staffing tab: it is the SAME number, not a separate estimate. Years 2 and 3 add the new hires declared on that tab, not a percentage of volume | G23: 0
A24: Utilities (electricity, water, gas) | B24: =IFERROR(IF(B9="","",'0. Assumptions'!$B$26*12),"") -> 14400 | C24: =IFERROR(IF(C9="","",B24*(1+'0. Assumptions'!$B$48)),"") -> 14400 | D24: =IFERROR(IF(D9="","",C24*(1+'0. Assumptions'!$B$48)),"") -> 14400 | E24: =IFERROR(B24/$B$9,"") -> 0.026553568 | F24: Enter the monthly bills excl. sales tax. The workbook applies a single tax treatment to this whole line, the one in the column next to it; if one utility is taxed differently in your area, give it its own line | G24: =IFERROR(IF(B9="","",'0. Assumptions'!$B$41),"") -> 0
A25: Insurance (general liability + property / auto) | B25: =IFERROR(IF(B9="","",'0. Assumptions'!$B$27),"") -> 3500 | C25: =IFERROR(IF(C9="","",B25*(1+'0. Assumptions'!$B$48)),"") -> 3500 | D25: =IFERROR(IF(D9="","",C25*(1+'0. Assumptions'!$B$48)),"") -> 3500 | E25: =IFERROR(B25/$B$9,"") -> 0.0064539923 | F25: Insurance premiums are not subject to sales tax: there is no recoverable tax on them | G25: 0
A26: Accounting / bookkeeping | B26: 3000 | C26: =IFERROR(IF(C9="","",B26*(1+'0. Assumptions'!$B$48)),"") -> 3000 | D26: =IFERROR(IF(D9="","",C26*(1+'0. Assumptions'!$B$48)),"") -> 3000 | E26: =IFERROR(B26/$B$9,"") -> 0.0055319934 | G26: =IFERROR(IF(B9="","",'0. Assumptions'!$B$41),"") -> 0
A27: Equipment maintenance | B27: 2000 | C27: =IFERROR(IF(C9="","",B27*(1+'0. Assumptions'!$B$48)),"") -> 2000 | D27: =IFERROR(IF(D9="","",C27*(1+'0. Assumptions'!$B$48)),"") -> 2000 | E27: =IFERROR(B27/$B$9,"") -> 0.0036879956 | G27: =IFERROR(IF(B9="","",'0. Assumptions'!$B$41),"") -> 0
A28: Marketing and advertising | B28: 6000 | C28: =IFERROR(IF(C9="","",B28*(1+'0. Assumptions'!$B$48)),"") -> 6000 | D28: =IFERROR(IF(D9="","",C28*(1+'0. Assumptions'!$B$48)),"") -> 6000 | E28: =IFERROR(B28/$B$9,"") -> 0.011063987 | G28: =IFERROR(IF(B9="","",'0. Assumptions'!$B$41),"") -> 0
A29: Software (POS, website, delivery) | B29: 1800 | C29: =IFERROR(IF(C9="","",B29*(1+'0. Assumptions'!$B$48)),"") -> 1800 | D29: =IFERROR(IF(D9="","",C29*(1+'0. Assumptions'!$B$48)),"") -> 1800 | E29: =IFERROR(B29/$B$9,"") -> 0.003319196 | G29: =IFERROR(IF(B9="","",'0. Assumptions'!$B$41),"") -> 0
A30: Cleaning supplies | B30: 2400 | C30: =IFERROR(IF(C9="","",B30*(1+'0. Assumptions'!$B$48)),"") -> 2400 | D30: =IFERROR(IF(D9="","",C30*(1+'0. Assumptions'!$B$48)),"") -> 2400 | E30: =IFERROR(B30/$B$9,"") -> 0.0044255947 | G30: =IFERROR(IF(B9="","",'0. Assumptions'!$B$41),"") -> 0
A31: Waste and recycling (organic waste, cardboard and used oil if you fry) | B31: 1200 | C31: =IFERROR(IF(C9="","",B31*(1+'0. Assumptions'!$B$48)),"") -> 1200 | D31: =IFERROR(IF(D9="","",C31*(1+'0. Assumptions'!$B$48)),"") -> 1200 | E31: =IFERROR(B31/$B$9,"") -> 0.0022127973 | F31: Licensed waste / grease hauler; the checklist asks for the contract before you open. This coffee shop has no frying line, so the volume is lower than a restaurant's: get a quote in your area | G31: =IFERROR(IF(B9="","",'0. Assumptions'!$B$41),"") -> 0
A32: Pest control | B32: 800 | C32: =IFERROR(IF(C9="","",B32*(1+'0. Assumptions'!$B$48)),"") -> 800 | D32: =IFERROR(IF(D9="","",C32*(1+'0. Assumptions'!$B$48)),"") -> 800 | E32: =IFERROR(B32/$B$9,"") -> 0.0014751982 | F32: Licensed pest control company; part of the HACCP-based food safety plan that the checklist already requires | G32: =IFERROR(IF(B9="","",'0. Assumptions'!$B$41),"") -> 0
A33: Music licensing (ASCAP, BMI, SESAC) | B33: 600 | C33: =IFERROR(IF(C9="","",B33*(1+'0. Assumptions'!$B$48)),"") -> 600 | D33: =IFERROR(IF(D9="","",C33*(1+'0. Assumptions'!$B$48)),"") -> 600 | E33: =IFERROR(B33/$B$9,"") -> 0.0011063987 | F33: ASCAP, BMI and SESAC are separate licensing organizations; the fee depends on the size and capacity of your space | G33: =IFERROR(IF(B9="","",'0. Assumptions'!$B$41),"") -> 0
A34: Training and certifications | B34: 500 | C34: =IFERROR(IF(C9="","",B34*(1+'0. Assumptions'!$B$48)),"") -> 500 | D34: =IFERROR(IF(D9="","",C34*(1+'0. Assumptions'!$B$48)),"") -> 500 | E34: =IFERROR(B34/$B$9,"") -> 0.00092199889 | F34: Food handler cards, Certified Food Protection Manager certification (for example ServSafe) and basic workplace safety training for the team. Requirements vary by state and county | G34: =IFERROR(IF(B9="","",'0. Assumptions'!$B$41),"") -> 0
A35: Depreciation of fixed assets | B35: =IFERROR(IF(B9="","",'Startup Costs'!$B$42),"") -> 20058.571 | C35: =IFERROR(IF(C9="","",B35),"") -> 20058.571 | D35: =IFERROR(IF(D9="","",B35),"") -> 20058.571 | E35: =IFERROR(B35/$B$9,"") -> 0.036987961 | F35: Comes from the depreciation bases on the Startup Costs tab: real fixed assets only. It does NOT rise with inflation: it is a charge on the HISTORICAL cost of the assets | G35: 0
A36: Interest expense (loan interest) | B36: =IFERROR(IF(B9="","",Financing!$B$44),"") -> 20400 | C36: =IFERROR(IF(C9="","",Financing!$B$46),"") -> 19119.994 | D36: =IFERROR(IF(D9="","",Financing!$B$48),"") -> 17711.987 | E36: =IFERROR(B36/$B$9,"") -> 0.037617555 | F36: Only INTEREST is an expense. Principal repaid appears on the cash flow tab | G36: 0
A37: TOTAL FIXED COSTS | B37: =IFERROR(IF(B9="","",SUM(B22:B36)),"") -> 299605.37 | C37: =IFERROR(IF(C9="","",SUM(C22:C36)),"") -> 304325.37 | D37: =IFERROR(IF(D9="","",SUM(D22:D36)),"") -> 308917.36 | E37: =IFERROR(B37/$B$9,"") -> 0.55247164
A38: Recoverable input tax on variable costs | B38: =IFERROR(IF(B9="","",SUMPRODUCT(B13:B18,G13:G18)),"") -> 0 | C38: =IFERROR(IF(C9="","",SUMPRODUCT(C13:C18,G13:G18)),"") -> 0 | D38: =IFERROR(IF(D9="","",SUMPRODUCT(D13:D18,G13:G18)),"") -> 0 | F38: Each line at ITS OWN rate, read from the column next to it. It is what the cash flow tab overpays to suppliers and later deducts (zero wherever no tax is recoverable)
A39: Recoverable input tax on fixed costs | B39: =IFERROR(IF(B9="","",SUMPRODUCT(B22:B36,G22:G36)),"") -> 0 | C39: =IFERROR(IF(C9="","",SUMPRODUCT(C22:C36,G22:G36)),"") -> 0 | D39: =IFERROR(IF(D9="","",SUMPRODUCT(D22:D36,G22:G36)),"") -> 0
A40: PRE-TAX INCOME (EBT) | B40: =IFERROR(IF(B9="","",B20-B37),"") -> 53106.549 | C40: =IFERROR(IF(C9="","",C20-C37),"") -> 73076.389 | D40: =IFERROR(IF(D9="","",D20-D37),"") -> 87354.483 | E40: =IFERROR(B40/$B$9,"") -> 0.097928358
A41: Net operating losses carried forward (opening) | B41: =IFERROR(IF(B9="","",'0. Assumptions'!$B$42),"") -> 0 | C41: =IFERROR(IF(C9="","",B46),"") -> 0 | D41: =IFERROR(IF(D9="","",C46),"") -> 0 | F41: Federal rules let a year's losses offset the profits of later years (the federal limit is 80% of taxable income; this model offsets 100% as a simplification)
A42: Taxable income (after loss offset) | B42: =IFERROR(IF(B9="","",MAX(0,B40-B41)),"") -> 53106.549 | C42: =IFERROR(IF(C9="","",MAX(0,C40-C41)),"") -> 73076.389 | D42: =IFERROR(IF(D9="","",MAX(0,D40-D41)),"") -> 87354.483
A43: Years with positive taxable income (cumulative) | B43: =IFERROR(IF(B9="","",IF(B42>0,1,0)),"") -> 1 | C43: =IFERROR(IF(C9="","",B43+IF(C42>0,1,0)),"") -> 2 | D43: =IFERROR(IF(D9="","",C43+IF(D42>0,1,0)),"") -> 3
A44: Effective income tax rate applied | B44: =IFERROR(IF(B9="","",IF(B42<=0,"",IF(B43<=2,'0. Assumptions'!$B$37,'0. Assumptions'!$B$38))),"") -> 0.25 | C44: =IFERROR(IF(C9="","",IF(C42<=0,"",IF(C43<=2,'0. Assumptions'!$B$37,'0. Assumptions'!$B$38))),"") -> 0.25 | D44: =IFERROR(IF(D9="","",IF(D42<=0,"",IF(D43<=2,'0. Assumptions'!$B$37,'0. Assumptions'!$B$38))),"") -> 0.25 | F44: The "years 1-2" rate applies to the first two years with positive taxable income, not to the first two calendar years of the business. The model approximates this by counting the first two profitable years
A45: Income tax | B45: =IFERROR(IF(B9="","",IF(B44="",0,B42*B44)),"") -> 13276.637 | C45: =IFERROR(IF(C9="","",IF(C44="",0,C42*C44)),"") -> 18269.097 | D45: =IFERROR(IF(D9="","",IF(D44="",0,D42*D44)),"") -> 21838.621
A46: Net operating losses carried forward (closing) | B46: =IFERROR(IF(B9="","",MAX(0,B41-B40)),"") -> 0 | C46: =IFERROR(IF(C9="","",MAX(0,C41-C40)),"") -> 0 | D46: =IFERROR(IF(D9="","",MAX(0,D41-D40)),"") -> 0
A47: NET INCOME | B47: =IFERROR(IF(B9="","",B40-B45),"") -> 39829.911 | C47: =IFERROR(IF(C9="","",C40-C45),"") -> 54807.292 | D47: =IFERROR(IF(D9="","",D40-D45),"") -> 65515.863 | E47: =IFERROR(B47/$B$9,"") -> 0.073446269
A48: KEY RATIOS
A49: Ratio | B49: Year 1 | C49: Year 2 | D49: Year 3 | E49: Threshold | F49: Comment
A50: Gross margin / Sales | B50: =IFERROR(IF(B9="","",B20/B9),"") -> 0.6504 | C50: =IFERROR(IF(C9="","",C20/C9),"") -> 0.6504 | D50: =IFERROR(IF(D9="","",D20/D9),"") -> 0.6504 | E50: 0.65 | F50: Kit benchmark (editable estimate): the mirror image of the 35% cost-of-goods ceiling, so gross margin should stay above 65%
A51: Cost of goods sold (food + beverage) | B51: =IFERROR(IF(B9="","",B13+B14),"") -> 143492.58 | C51: =IFERROR(IF(C9="","",C13+C14),"") -> 153537.06 | D51: =IFERROR(IF(D9="","",D13+D14),"") -> 161213.91
A52: Cost of goods sold / Sales | B52: =IFERROR(IF(B9="","",B51/B9),"") -> 0.2646 | C52: =IFERROR(IF(C9="","",C51/C9),"") -> 0.2646 | D52: =IFERROR(IF(D9="","",D51/D9),"") -> 0.2646 | E52: 0.35 | F52: Kit benchmark (editable estimate): top of the 25-35% cost-of-goods range for a coffee shop, which here blends brunch food (30-35%) with coffee and cold drinks
A53: Labor cost / Sales | B53: =IFERROR(IF(B9="","",B23/B9),"") -> 0.31153753 | C53: =IFERROR(IF(C9="","",C23/C9),"") -> 0.30149674 | D53: =IFERROR(IF(D9="","",D23/D9),"") -> 0.29698754 | E53: 0.35 | F53: Kit benchmark (editable estimate): the ceiling of the 30-35% labor-cost range in the industry benchmarks table; above 40% is an alarm
A54: Rent / Sales | B54: =IFERROR(IF(B9="","",B22/B9),"") -> 0.099575881 | C54: =IFERROR(IF(C9="","",C22/C9),"") -> 0.093061571 | D54: =IFERROR(IF(D9="","",D22/D9),"") -> 0.088630067 | E54: 0.12 | F54: Kit benchmark (editable estimate): rent up to 12% of sales, between the 10% target and the 15% maximum in the industry benchmarks table
A55: Net income / Sales | B55: =IFERROR(IF(B9="","",B47/B9),"") -> 0.073446269 | C55: =IFERROR(IF(C9="","",C47/C9),"") -> 0.094452827 | D55: =IFERROR(IF(D9="","",D47/D9),"") -> 0.10753102 | E55: 0.06 | F55: Kit benchmark (editable estimate): below 6% net margin points to a structural problem; healthy coffee shops net about 8-12% (industry benchmarks table)
A56: Break-even reached | B56: =IFERROR(IF(B9="","",IF(B9>='Break-Even'!$B$16,"Yes","No")),"") -> Yes | C56: =IFERROR(IF(C9="","",IF(C9>='Break-Even'!$C$16,"Yes","No")),"") -> Yes | D56: =IFERROR(IF(D9="","",IF(D9>='Break-Even'!$D$16,"Yes","No")),"") -> Yes | F56: Compares each year's sales with that same year's threshold, which the Break-Even tab calculates with that year's fixed costs
A58: All figures are EXCL. SALES TAX. Years 2 and 3 are in year-1 prices unless you raise cost inflation in the "0. Assumptions" tab. The "Sales tax rate on the line (%)" column shows, on SALES lines, the rate collected on each one and, on COST lines, the rate paid on that item. The cash flow tab reads it: insurance and card fees carry no sales tax, and wages, depreciation and interest carry none either.

Sheet Break-Even
A1: BREAK-EVEN ANALYSIS
A2: Monthly and daily break-even — Coffee shop with brunch
A4: Variable | B4: Year 1 | C4: Year 2 | D4: Year 3 | E4: Notes
A5: BASE DATA BY YEAR
A6: Annual fixed costs | B6: =IFERROR(IF('3-Year P&L'!$B$9="","",'3-Year P&L'!$B$37),"") -> 299605.37 | C6: =IFERROR(IF('3-Year P&L'!$C$9="","",'3-Year P&L'!$C$37),"") -> 304325.37 | D6: =IFERROR(IF('3-Year P&L'!$D$9="","",'3-Year P&L'!$D$37),"") -> 308917.36 | E6: The SAME fixed costs as the P&L. Each year has its own, which is why the threshold cannot be a single one for all three years
A7: Monthly fixed costs | B7: =IFERROR(IF('3-Year P&L'!$B$9="","",B6/12),"") -> 24967.114 | C7: =IFERROR(IF('3-Year P&L'!$C$9="","",C6/12),"") -> 25360.447 | D7: =IFERROR(IF('3-Year P&L'!$D$9="","",D6/12),"") -> 25743.113
A8: Average check (excl. sales tax) | B8: =IFERROR(IF('3-Year P&L'!$B$9="","",'3-Year P&L'!$B$7),"") -> 11 | C8: =IFERROR(IF('3-Year P&L'!$C$9="","",'3-Year P&L'!$C$7),"") -> 11 | D8: =IFERROR(IF('3-Year P&L'!$D$9="","",'3-Year P&L'!$D$7),"") -> 11
A9: Variable cost per customer | B9: =IFERROR(IF('3-Year P&L'!$B$9="","",'3-Year P&L'!$B$19/('3-Year P&L'!$B$6*'3-Year P&L'!$B$8)),"") -> 3.8456 | C9: =IFERROR(IF('3-Year P&L'!$C$9="","",'3-Year P&L'!$C$19/('3-Year P&L'!$C$6*'3-Year P&L'!$C$8)),"") -> 3.8456 | D9: =IFERROR(IF('3-Year P&L'!$D$9="","",'3-Year P&L'!$D$19/('3-Year P&L'!$D$6*'3-Year P&L'!$D$8)),"") -> 3.8456 | E9: Comes from the P&L total variable costs, not from a separate estimate. It includes miscellaneous and contingency, which is a percentage of sales
A10: Contribution margin per customer | B10: =IFERROR(IF('3-Year P&L'!$B$9="","",B8-B9),"") -> 7.1544 | C10: =IFERROR(IF('3-Year P&L'!$C$9="","",C8-C9),"") -> 7.1544 | D10: =IFERROR(IF('3-Year P&L'!$D$9="","",D8-D9),"") -> 7.1544 | E10: Average check minus unit variable cost
A11: Operating days per year | B11: =IFERROR(IF('3-Year P&L'!$B$9="","",'3-Year P&L'!$B$8),"") -> 340 | C11: =IFERROR(IF('3-Year P&L'!$C$9="","",'3-Year P&L'!$C$8),"") -> 340 | D11: =IFERROR(IF('3-Year P&L'!$D$9="","",'3-Year P&L'!$D$8),"") -> 340 | E11: The same calendar as the P&L and the scenarios
A12: Principal repaid in the year | B12: =IFERROR(IF('3-Year P&L'!$B$9="","",Financing!$B$45),"") -> 12800.061 | C12: =IFERROR(IF('3-Year P&L'!$C$9="","",Financing!$B$47),"") -> 14080.067 | D12: =IFERROR(IF('3-Year P&L'!$D$9="","",Financing!$B$49),"") -> 15488.073 | E12: Principal is NOT a P&L expense, but it leaves the cash account. Without it, the published break-even threshold would sit below the real one
A13: ACCOUNTING BREAK-EVEN (includes depreciation)
A14: Customers needed per year | B14: =IFERROR(IF('3-Year P&L'!$B$9="","",IF(B10<=0,"",B6/B10)),"") -> 41877.079 | C14: =IFERROR(IF('3-Year P&L'!$C$9="","",IF(C10<=0,"",C6/C10)),"") -> 42536.812 | D14: =IFERROR(IF('3-Year P&L'!$D$9="","",IF(D10<=0,"",D6/D10)),"") -> 43178.654
A15: Customers needed per day | B15: =IFERROR(IF('3-Year P&L'!$B$9="","",B14/B11),"") -> 123.16788 | C15: =IFERROR(IF('3-Year P&L'!$C$9="","",C14/C11),"") -> 125.10827 | D15: =IFERROR(IF('3-Year P&L'!$D$9="","",D14/D11),"") -> 126.99604
A16: Revenue needed per year | B16: =IFERROR(IF('3-Year P&L'!$B$9="","",B14*B8),"") -> 460647.87 | C16: =IFERROR(IF('3-Year P&L'!$C$9="","",C14*C8),"") -> 467904.93 | D16: =IFERROR(IF('3-Year P&L'!$D$9="","",D14*D8),"") -> 474965.19
A17: CASH BREAK-EVEN (loan payments in, depreciation out)
A18: Cash fixed costs + principal repaid for the year | B18: =IFERROR(IF('3-Year P&L'!$B$9="","",B6-'3-Year P&L'!$B$35+B12),"") -> 292346.86 | C18: =IFERROR(IF('3-Year P&L'!$C$9="","",C6-'3-Year P&L'!$C$35+C12),"") -> 298346.86 | D18: =IFERROR(IF('3-Year P&L'!$D$9="","",D6-'3-Year P&L'!$D$35+D12),"") -> 304346.86 | E18: The P&L fixed costs without depreciation (which is not paid in cash) and WITH principal repaid (which is). This is the threshold that decides whether cash holds up
A19: Customers needed per year (cash) | B19: =IFERROR(IF('3-Year P&L'!$B$9="","",IF(B10<=0,"",B18/B10)),"") -> 40862.527 | C19: =IFERROR(IF('3-Year P&L'!$C$9="","",IF(C10<=0,"",C18/C10)),"") -> 41701.171 | D19: =IFERROR(IF('3-Year P&L'!$D$9="","",IF(D10<=0,"",D18/D10)),"") -> 42539.816
A20: Customers needed per day (cash) | B20: =IFERROR(IF('3-Year P&L'!$B$9="","",B19/B11),"") -> 120.1839 | C20: =IFERROR(IF('3-Year P&L'!$C$9="","",C19/C11),"") -> 122.6505 | D20: =IFERROR(IF('3-Year P&L'!$D$9="","",D19/D11),"") -> 125.11711
A21: Revenue needed per year (cash) | B21: =IFERROR(IF('3-Year P&L'!$B$9="","",B19*B8),"") -> 449487.79 | C21: =IFERROR(IF('3-Year P&L'!$C$9="","",C19*C8),"") -> 458712.89 | D21: =IFERROR(IF('3-Year P&L'!$D$9="","",D19*D8),"") -> 467937.98
A22: COMPARISON WITH THE PLAN
A23: Customers per day forecast in the plan | B23: =IFERROR(IF('3-Year P&L'!$B$9="","",'3-Year P&L'!$B$6),"") -> 145 | C23: =IFERROR(IF('3-Year P&L'!$C$9="","",'3-Year P&L'!$C$6),"") -> 155.15 | D23: =IFERROR(IF('3-Year P&L'!$D$9="","",'3-Year P&L'!$D$6),"") -> 162.9075
A24: Cushion above CASH break-even (%) | B24: =IFERROR(IF('3-Year P&L'!$B$9="","",B23/B20-1),"") -> 0.20648438 | C24: =IFERROR(IF('3-Year P&L'!$C$9="","",C23/C20-1),"") -> 0.26497646 | D24: =IFERROR(IF('3-Year P&L'!$D$9="","",D23/D20-1),"") -> 0.30204018 | E24: How far planned sales sit above cash break-even. The drop you can absorb before you cannot pay the fixed costs and the loan payment is somewhat smaller: with a 25% cushion, 20%. The required minimum is set in the "0. Assumptions" tab
A25: Maximum seat turns per day the space allows | B25: 3 | E25: Full table services per seat per day that your opening hours allow. It is the physical ceiling of the space, not a target
A26: Seat turns per day that the cash break-even requires | B26: =IFERROR(IF('3-Year P&L'!$B$9="","",B20/'0. Assumptions'!$B$51),"") -> 2.6707534 | C26: =IFERROR(IF('3-Year P&L'!$C$9="","",C20/'0. Assumptions'!$B$51),"") -> 2.7255668 | D26: =IFERROR(IF('3-Year P&L'!$D$9="","",D20/'0. Assumptions'!$B$51),"") -> 2.7803801 | E26: Break-even customers spread across the seats declared on the "0. Assumptions" tab. If it is above the ceiling in the row above, the break-even is out of reach for the space
A27: INTERPRETATION
A28: =IFERROR("With the average check excl. sales tax above, you need "&TEXT(ROUNDUP(B15,0),"0")&" customers a day over your "&TEXT(B11,"0")&" opening days to avoid losing money (accounting break-even, depreciation included), and "&TEXT(ROUNDUP(B20,0),"0")&" for cash to hold (cash break-even: depreciation out, because it is not paid, and the year's loan payment in"&IF(B12=0,"; no principal is repaid this year (interest-only period or no loan)","")&"). The ""Revenue needed per year"" rows show the same figures in your currency.","") -> With the average check excl. sales tax above, you need 124 customers a day over your 340 opening days to avoid losing money (accounting break-even, depreciation included), and 121 for cash to hold (cash break-even: depreciation out, because it is not paid, and the year's loan payment in). The "Revenue needed per year" rows show the same figures in your currency.
A30: BREAK-EVEN SENSITIVITY
A31: Customers per day needed to cover costs for each average check (columns) and each variable cost per customer (rows). Green cells are below the customers per day the plan forecasts.
A33: Customers per day needed: average check excl. sales tax (columns) × variable cost per customer (rows) | B33: =IFERROR($B$8-2,"") -> 9 | C33: =IFERROR(IF($B$8="","",$B$8),"") -> 11 | D33: =IFERROR($B$8+2,"") -> 13 | E33: =IFERROR($B$8+4,"") -> 15
A34: =IFERROR($B$9*0.85,"") -> 3.26876 | B34: =IFERROR(IF($B$33-$A34<=0,"",$B$6/($B$33-$A34)/$B$11),"") -> 153.75246 | C34: =IFERROR(IF($C$33-$A34<=0,"",$B$6/($C$33-$A34)/$B$11),"") -> 113.97813 | D34: =IFERROR(IF($D$33-$A34<=0,"",$B$6/($D$33-$A34)/$B$11),"") -> 90.552927 | E34: =IFERROR(IF($E$33-$A34<=0,"",$B$6/($E$33-$A34)/$B$11),"") -> 75.115015
A35: =IFERROR($B$9*0.925,"") -> 3.55718 | B35: =IFERROR(IF($B$33-$A35<=0,"",$B$6/($B$33-$A35)/$B$11),"") -> 161.89995 | C35: =IFERROR(IF($C$33-$A35<=0,"",$B$6/($C$33-$A35)/$B$11),"") -> 118.39495 | D35: =IFERROR(IF($D$33-$A35<=0,"",$B$6/($D$33-$A35)/$B$11),"") -> 93.318762 | E35: =IFERROR(IF($E$33-$A35<=0,"",$B$6/($E$33-$A35)/$B$11),"") -> 77.008313
A36: =IFERROR($B$9*1.0,"") -> 3.8456 | B36: =IFERROR(IF($B$33-$A36<=0,"",$B$6/($B$33-$A36)/$B$11),"") -> 170.95923 | C36: =IFERROR(IF($C$33-$A36<=0,"",$B$6/($C$33-$A36)/$B$11),"") -> 123.16788 | D36: =IFERROR(IF($D$33-$A36<=0,"",$B$6/($D$33-$A36)/$B$11),"") -> 96.258878 | E36: =IFERROR(IF($E$33-$A36<=0,"",$B$6/($E$33-$A36)/$B$11),"") -> 78.999522
A37: =IFERROR($B$9*1.075,"") -> 4.13402 | B37: =IFERROR(IF($B$33-$A37<=0,"",$B$6/($B$33-$A37)/$B$11),"") -> 181.09246 | C37: =IFERROR(IF($C$33-$A37<=0,"",$B$6/($C$33-$A37)/$B$11),"") -> 128.34181 | D37: =IFERROR(IF($D$33-$A37<=0,"",$B$6/($D$33-$A37)/$B$11),"") -> 99.390284 | E37: =IFERROR(IF($E$33-$A37<=0,"",$B$6/($E$33-$A37)/$B$11),"") -> 81.096438
A38: =IFERROR($B$9*1.15,"") -> 4.42244 | B38: =IFERROR(IF($B$33-$A38<=0,"",$B$6/($B$33-$A38)/$B$11),"") -> 192.50261 | C38: =IFERROR(IF($C$33-$A38<=0,"",$B$6/($C$33-$A38)/$B$11),"") -> 133.96948 | D38: =IFERROR(IF($D$33-$A38<=0,"",$B$6/($D$33-$A38)/$B$11),"") -> 102.73228 | E38: =IFERROR(IF($E$33-$A38<=0,"",$B$6/($E$33-$A38)/$B$11),"") -> 83.307707

Sheet Scenarios
A1: SCENARIO ANALYSIS
A2: Pessimistic / Base / Optimistic — Year 1
A4: Metric | B4: Pessimistic | C4: Base | D4: Optimistic | E4: Notes
A5: Customers per day | B5: 116 | C5: =IFERROR(IF('3-Year P&L'!$B$6="","",'3-Year P&L'!$B$6),"") -> 145 | D5: 167
A6: Average check (excl. sales tax) | B6: 10.33 | C6: =IFERROR(IF('3-Year P&L'!$B$7="","",'3-Year P&L'!$B$7),"") -> 11 | D6: 11.67
A7: Operating days per year | B7: 329 | C7: =IFERROR(IF('3-Year P&L'!$B$8="","",'3-Year P&L'!$B$8),"") -> 340 | D7: 351
A8: ANNUAL REVENUE (excl. sales tax) | B8: =IFERROR(IF(B5*B6*B7=0,"",B5*B6*B7),"") -> 394234.12 | C8: =IFERROR(IF(C5*C6*C7=0,"",C5*C6*C7),"") -> 542300 | D8: =IFERROR(IF(D5*D6*D7=0,"",D5*D6*D7),"") -> 684060.39
A9: Cost of goods sold — food | B9: =IFERROR(IF(B8="","",B8*'0. Assumptions'!$B$11*'0. Assumptions'!$B$13),"") -> 48490.797 | C9: =IFERROR(IF(C8="","",C8*'0. Assumptions'!$B$11*'0. Assumptions'!$B$13),"") -> 66702.9 | D9: =IFERROR(IF(D8="","",D8*'0. Assumptions'!$B$11*'0. Assumptions'!$B$13),"") -> 84139.428
A10: Cost of goods sold — beverage | B10: =IFERROR(IF(B8="","",B8*'0. Assumptions'!$B$12*'0. Assumptions'!$B$14),"") -> 55823.551 | C10: =IFERROR(IF(C8="","",C8*'0. Assumptions'!$B$12*'0. Assumptions'!$B$14),"") -> 76789.68 | D10: =IFERROR(IF(D8="","",D8*'0. Assumptions'!$B$12*'0. Assumptions'!$B$14),"") -> 96862.951
A11: Disposables and packaging | B11: =IFERROR(IF(B8="","",B8*'0. Assumptions'!$B$15),"") -> 11827.024 | C11: =IFERROR(IF(C8="","",C8*'0. Assumptions'!$B$15),"") -> 16269 | D11: =IFERROR(IF(D8="","",D8*'0. Assumptions'!$B$15),"") -> 20521.812
A12: Delivery platform fees | B12: =IFERROR(IF(B8="","",B8*'0. Assumptions'!$B$16*'0. Assumptions'!$B$17),"") -> 0 | C12: =IFERROR(IF(C8="","",C8*'0. Assumptions'!$B$16*'0. Assumptions'!$B$17),"") -> 0 | D12: =IFERROR(IF(D8="","",D8*'0. Assumptions'!$B$16*'0. Assumptions'!$B$17),"") -> 0
A13: Card processing fees | B13: =IFERROR(IF(B8="","",B8*'0. Assumptions'!$B$18),"") -> 13798.194 | C13: =IFERROR(IF(C8="","",C8*'0. Assumptions'!$B$18),"") -> 18980.5 | D13: =IFERROR(IF(D8="","",D8*'0. Assumptions'!$B$18),"") -> 23942.114
A14: Miscellaneous and contingency | B14: =IFERROR(IF(B8="","",B8*'0. Assumptions'!$B$28),"") -> 7884.6824 | C14: =IFERROR(IF(C8="","",C8*'0. Assumptions'!$B$28),"") -> 10846 | D14: =IFERROR(IF(D8="","",D8*'0. Assumptions'!$B$28),"") -> 13681.208
A15: TOTAL VARIABLE COSTS | B15: =IFERROR(IF(B8="","",SUM(B9:B14)),"") -> 137824.25 | C15: =IFERROR(IF(C8="","",SUM(C9:C14)),"") -> 189588.08 | D15: =IFERROR(IF(D8="","",SUM(D9:D14)),"") -> 239147.51
A16: GROSS MARGIN | B16: =IFERROR(IF(B8="","",B8-B15),"") -> 256409.87 | C16: =IFERROR(IF(C8="","",C8-C15),"") -> 352711.92 | D16: =IFERROR(IF(D8="","",D8-D15),"") -> 444912.88
A17: FIXED COSTS (the P&L's) | B17: =IFERROR(IF(B8="","",'3-Year P&L'!$B$37),"") -> 299605.37 | C17: =IFERROR(IF(C8="","",'3-Year P&L'!$B$37),"") -> 299605.37 | D17: =IFERROR(IF(D8="","",'3-Year P&L'!$B$37),"") -> 299605.37 | E17: Fixed costs do not change with the scenario: that is why they are fixed
A18: PRE-TAX INCOME (EBT) | B18: =IFERROR(IF(B8="","",B16-B17),"") -> -43195.5 | C18: =IFERROR(IF(C8="","",C16-C17),"") -> 53106.549 | D18: =IFERROR(IF(D8="","",D16-D17),"") -> 145307.51
A19: Income tax | B19: =IFERROR(IF(B8="","",MAX(0,B18-'0. Assumptions'!$B$42)*'0. Assumptions'!$B$37),"") -> 0 | C19: =IFERROR(IF(C8="","",MAX(0,C18-'0. Assumptions'!$B$42)*'0. Assumptions'!$B$37),"") -> 13276.637 | D19: =IFERROR(IF(D8="","",MAX(0,D18-'0. Assumptions'!$B$42)*'0. Assumptions'!$B$37),"") -> 36326.877 | E19: At the "years 1-2" effective income tax rate, offsetting prior net operating losses
A20: NET INCOME | B20: =IFERROR(IF(B8="","",B18-B19),"") -> -43195.5 | C20: =IFERROR(IF(C8="","",C18-C19),"") -> 39829.911 | D20: =IFERROR(IF(D8="","",D18-D19),"") -> 108980.63
A21: Customers per day to break even | B21: =IFERROR(IF(B8="","",IF(B6-B15/(B5*B7)<=0,"",B17/(B6-B15/(B5*B7))/B7)),"") -> 135.54167 | C21: =IFERROR(IF(C8="","",IF(C6-C15/(C5*C7)<=0,"",C17/(C6-C15/(C5*C7))/C7)),"") -> 123.16788 | D21: =IFERROR(IF(D8="","",IF(D6-D15/(D5*D7)<=0,"",D17/(D6-D15/(D5*D7))/D7)),"") -> 112.45819
A22: WHAT EACH SCENARIO DEMANDS
A23: Labor cost / Sales | B23: =IFERROR(IF(B8="","",'3-Year P&L'!$B$23/B8),"") -> 0.42854434 | C23: =IFERROR(IF(C8="","",'3-Year P&L'!$B$23/C8),"") -> 0.31153753 | D23: =IFERROR(IF(D8="","",'3-Year P&L'!$B$23/D8),"") -> 0.24697644 | E23: The SAME staffing in all three scenarios. If labor cost blows up in the pessimistic case, adjust it in the Staffing tab, not here
A24: Customers per year per full-time equivalent | B24: =IFERROR(IF(B8="","",B5*B7/Staffing!$C$11),"") -> 8773.3333 | C24: =IFERROR(IF(C8="","",C5*C7/Staffing!$C$11),"") -> 11333.333 | D24: =IFERROR(IF(D8="","",D5*D7/Staffing!$C$11),"") -> 13475.172 | E24: Customers each full-time employee in the Staffing table would have to serve. In the optimistic scenario it tells you whether you need to hire
A25: Year-1 closing cash balance (estimate, same method in all three scenarios) | B25: =IFERROR(IF(B8="","",'Startup Costs'!$B$34+B20+'3-Year P&L'!$B$35-Financing!$B$45),"") -> 33949.711 | C25: =IFERROR(IF(C8="","",'Startup Costs'!$B$34+C20+'3-Year P&L'!$B$35-Financing!$B$45),"") -> 116975.12 | D25: =IFERROR(IF(D8="","",'Startup Costs'!$B$34+D20+'3-Year P&L'!$B$35-Financing!$B$45),"") -> 186125.84 | E25: ESTIMATED balance: working capital plus the year's result, adding back depreciation (which is not paid) and subtracting loan principal. It does not include the timing gap between receipts and payments or the sales tax settlement, so the three columns can be compared with each other. In red, the scenario runs out of cash
A26: Actual month-12 balance from the 12-Month Cash Flow tab (Base case only) | C26: =IFERROR(IF(C8="","",'12-Month Cash Flow'!$M$22),"") -> 152229.56 | E26: The ACTUAL base-case balance, with its timing of receipts and payments and its sales tax settlement. It exists only for the Base scenario, the only one with its own monthly cash flow: that is why it is not in the row above, where it would be compared against two estimates
A28: The "Base" column reads its three inputs from the "0. Assumptions" tab, so it reproduces EXACTLY year 1 of the P&L. The other two scenarios use the same cost rates: only customers, average check and days change. FIXED COSTS are the same in all three: miscellaneous and contingency, a percentage of sales, sit above with the variable costs and each scenario carries its own.

Sheet Staffing
A1: STAFFING STRUCTURE AND COSTS
A2: =IFERROR("Payroll — "&TEXT('0. Assumptions'!$B$21,"0")&" pay periods + employer taxes "&TEXT('0. Assumptions'!$B$20*100,"0")&"%","") -> Payroll — 12 pay periods + employer taxes 10%
A4: Position | B4: People | C4: FTE | D4: Gross pay per month (total for the position) | E4: Employer payroll taxes (total for the position) | F4: Cost per month (total for the position) | G4: Cost per year | H4: Hours per week per person | I4: Hours per year for the position | J4: Notes
A5: Owner and lead barista | B5: 1 | C5: 1 | D5: 3500 | E5: =IFERROR(IF(D5="","",D5*'0. Assumptions'!$B$20),"") -> 350 | F5: =IFERROR(IF(D5="","",D5+E5),"") -> 3850 | G5: =IFERROR(IF(D5="","",F5*MAX(12,'0. Assumptions'!$B$21)),"") -> 46200 | H5: =IFERROR(IF(D5="","",C5*$B$18),"") -> 40 | I5: =IFERROR(IF(D5="","",H5*B5*$B$19),"") -> 2000 | J5: Works the bar during the busy morning shift: purchasing, register, suppliers and social media
A6: Morning barista / floor server | B6: 1 | C6: 1 | D6: 2773 | E6: =IFERROR(IF(D6="","",D6*'0. Assumptions'!$B$20),"") -> 277.3 | F6: =IFERROR(IF(D6="","",D6+E6),"") -> 3050.3 | G6: =IFERROR(IF(D6="","",F6*MAX(12,'0. Assumptions'!$B$21)),"") -> 36603.6 | H6: =IFERROR(IF(D6="","",C6*$B$18),"") -> 40 | I6: =IFERROR(IF(D6="","",H6*B6*$B$19),"") -> 2000 | J6: Coffee specialist with latte art skills. Morning is the strongest shift of a coffee shop: bar coffee, breakfast and pastries
A7: Afternoon barista-server (bar and floor) | B7: 1 | C7: 1 | D7: 2600 | E7: =IFERROR(IF(D7="","",D7*'0. Assumptions'!$B$20),"") -> 260 | F7: =IFERROR(IF(D7="","",D7+E7),"") -> 2860 | G7: =IFERROR(IF(D7="","",F7*MAX(12,'0. Assumptions'!$B$21)),"") -> 34320 | H7: =IFERROR(IF(D7="","",C7*$B$18),"") -> 40 | I7: =IFERROR(IF(D7="","",H7*B7*$B$19),"") -> 2000 | J7: Closes the afternoon service and preps for the next day. Without this position the shop cannot open the hours that this workbook declares
A8: Brunch cook (4 days, weekends included) | B8: 1 | C8: 0.8 | D8: 2496 | E8: =IFERROR(IF(D8="","",D8*'0. Assumptions'!$B$20),"") -> 249.6 | F8: =IFERROR(IF(D8="","",D8+E8),"") -> 2745.6 | G8: =IFERROR(IF(D8="","",F8*MAX(12,'0. Assumptions'!$B$21)),"") -> 32947.2 | H8: =IFERROR(IF(D8="","",C8*$B$18),"") -> 32 | I8: =IFERROR(IF(D8="","",H8*B8*$B$19),"") -> 1600 | J8: Brunch and light kitchen 4 days a week (0.8 FTE = 32 hours), always including Saturday and Sunday, the busiest service, with two or three table turns
A9: Weekend extra (bar and floor) | B9: 1 | C9: 0.45 | D9: 1170 | E9: =IFERROR(IF(D9="","",D9*'0. Assumptions'!$B$20),"") -> 117 | F9: =IFERROR(IF(D9="","",D9+E9),"") -> 1287 | G9: =IFERROR(IF(D9="","",F9*MAX(12,'0. Assumptions'!$B$21)),"") -> 15444 | H9: =IFERROR(IF(D9="","",C9*$B$18),"") -> 18 | I9: =IFERROR(IF(D9="","",H9*B9*$B$19),"") -> 900 | J9: Reinforcement for the Saturday and Sunday peaks, when occupancy rises to 70-90% according to the references in this workbook
A10: Vacation and day-off relief | B10: 1 | C10: 0.1 | D10: 260 | E10: =IFERROR(IF(D10="","",D10*'0. Assumptions'!$B$20),"") -> 26 | F10: =IFERROR(IF(D10="","",D10+E10),"") -> 286 | G10: =IFERROR(IF(D10="","",F10*MAX(12,'0. Assumptions'!$B$21)),"") -> 3432 | H10: =IFERROR(IF(D10="","",C10*$B$18),"") -> 4 | I10: =IFERROR(IF(D10="","",H10*B10*$B$19),"") -> 200 | J10: Covers vacation, paid time off and the weekly day off for the team
A11: TOTAL STAFF | B11: =IFERROR(IF(COUNT(D5:D10)=0,"",SUM(B5:B10)),"") -> 6 | C11: =IFERROR(IF(COUNT(D5:D10)=0,"",SUM(C5:C10)),"") -> 4.35 | D11: =IFERROR(IF(COUNT(D5:D10)=0,"",SUM(D5:D10)),"") -> 12799 | E11: =IFERROR(IF(COUNT(D5:D10)=0,"",SUM(E5:E10)),"") -> 1279.9 | F11: =IFERROR(IF(COUNT(D5:D10)=0,"",SUM(F5:F10)),"") -> 14078.9 | G11: =IFERROR(IF(COUNT(D5:D10)=0,"",SUM(G5:G10)),"") -> 168946.8 | I11: =IFERROR(IF(COUNT(D5:D10)=0,"",SUM(I5:I10)),"") -> 8700
A12: STAFF GROWTH (stepped cost)
A13: Annual cost of year-2 hires | B13: 6000 | J13: FULL ANNUAL cost (gross pay + employer payroll taxes, over all pay periods) of whoever you hire that year. The P&L adds it to the previous year's cost: staffing grows by people, not by a percentage
A14: Annual cost of year-3 hires | B14: 6000 | J14: FULL ANNUAL cost (gross pay + employer payroll taxes, over all pay periods) of whoever you hire that year. The P&L adds it to the previous year's cost: staffing grows by people, not by a percentage
A15: Labor cost, year 2 | B15: =IFERROR(IF(G11="","",G11*(1+'0. Assumptions'!$B$48)+B13),"") -> 174946.8
A16: Labor cost, year 3 | B16: =IFERROR(IF(B15="","",B15*(1+'0. Assumptions'!$B$48)+B14),"") -> 180946.8
A17: COVERAGE OF SERVICE HOURS
A18: Full-time week (hours per week) | B18: 40 | J18: 40 hours a week is the FLSA overtime threshold for non-exempt employees; some states add daily overtime rules. Change it if your own full-time week is different
A19: Weeks worked per year per person | B19: 50 | J19: 50 weeks: 52 minus about two weeks of vacation, holidays and average absences. There is no federal vacation requirement in the US: adjust it to your own policy
A20: Service hours per day to cover | B20: 13 | J20: From opening to closing, bar included. Count them on your real schedule
A21: People needed at the same time in each shift | B21: 2 | J21: Average number of people present at the same time across kitchen, bar and floor. The two busy services need more and mid-afternoon needs fewer
A22: Service hours to cover per year | B22: =IFERROR(IF(OR(B20="",B21="",'0. Assumptions'!$B$6=""),"",B20*B21*'0. Assumptions'!$B$6),"") -> 8840
A23: Hours hired per year | B23: =IFERROR(IF(I11="","",I11),"") -> 8700
A24: Coverage (hired / needed) | B24: =IFERROR(B23/B22,"") -> 0.9841629 | J24: Below 100% the staff cannot cover the hours the plan declares: either hire more or cut the hours
A26: The gross pay, employer payroll taxes, monthly cost and annual cost columns are TOTALS for the row: for a position with two people they include both. FTE is the share of a full-time week, and it is used to compare pay with the legal minimum in proportion. The payroll tax rate and the number of pay periods are in the "0. Assumptions" tab.
A27: The pay floor is the HIGHER of the federal minimum wage and your state / local minimum wage, both in the "0. Assumptions" tab; part-time positions get it in proportion. There is no single national table above the federal floor: the state / local cell is delivered empty so you can enter the rate for your state and city.

Sheet Instructions
A1: INSTRUCTIONS FOR USE — Coffee Shop Financial Projections
A3: HOW TO USE THIS WORKBOOK
A4: This financial plan is a MODEL: you type only in the GREEN cells and everything else recalculates on its own.
A5: 1. "0. Assumptions" is the control sheet: customers per day, average check excl. sales tax, operating days, food and beverage mix, cost of goods sold, rent, financing and taxes.
A6: 2. Startup cost items, fixed costs and staffing are typed in their own tab, also in green. No number is typed twice.
A7: 3. On "Break-Even" you only type the seat-turn ceiling your space allows; everything else derives from the rest. The other three tabs also have green cells you can change: the pessimistic and optimistic scenarios on "Scenarios", the seasonality and the launch ramp-up on "12-Month Cash Flow", and the other financing sources on "Financing" (rows 8-11 count as sources but are not amortized: Your bank or SBA 7(a) loan goes in "Loan requested" on "0. Assumptions"). Everything else is calculated.
A8: 4. All figures are EXCL. SALES TAX. To turn a menu price into a price excl. sales tax, divide it by 1 + your sales tax rate (with an 8% rate, divide by 1.08); if an item is taxed at a different rate (alcohol to go, for instance), use that rate. The rate of each sales line is in the "Sales tax rate on the line (%)" column of the P&L, and from it come the receipts, the sales tax collected and the equivalent menu price incl. sales tax. With the default 0% recoverable input tax, the sales tax you pay on purchases and startup costs is treated as a cost; in the UK, enter 20% if you are VAT-registered.
A9: 5. If you change the staffing, the P&L reads it on its own: labor cost comes from the "Staffing" tab, not from a separate estimate.
A10: 6. The "12-Month Cash Flow" tab answers the question that decides a bank deal: in which month the cash runs out. The minimum balance of the year can never be in red.
A11: 7. The "Financing" tab matches what you need with what you put in and builds the amortization schedule of the loan. If the difference is red, the plan is not funded.
A12: 8. In this workbook, "the P&L" means the "3-Year P&L" tab: the same profit and loss statement, with one column for each of the three years.
A13: 9. The Word business plan that comes with these financial projections uses the same example figures as this workbook. If you change the workbook, update the figures in the Word document too.
... A16: Thresholds live in the "Threshold" column of the KEY RATIOS block of the P&L: change them there and the traffic light changes with them.
A18: Ratio | B18: Year 1 value | C18: Threshold | D18: Status
A19: Cost of goods sold / Sales | B19: =IFERROR(IF('3-Year P&L'!$B$52="","",'3-Year P&L'!$B$52),"") -> 0.2646 | C19: =IFERROR(IF('3-Year P&L'!$E$52="","",'3-Year P&L'!$E$52),"") -> 0.35 | D19: =IFERROR(IF(OR(B19="",C19=""),"",IF(B19<=C19,"OK","REVIEW")),"") -> OK
A20: Labor cost / Sales | B20: =IFERROR(IF('3-Year P&L'!$B$53="","",'3-Year P&L'!$B$53),"") -> 0.31153753 | C20: =IFERROR(IF('3-Year P&L'!$E$53="","",'3-Year P&L'!$E$53),"") -> 0.35 | D20: =IFERROR(IF(OR(B20="",C20=""),"",IF(B20<=C20,"OK","REVIEW")),"") -> OK
A21: Rent / Sales | B21: =IFERROR(IF('3-Year P&L'!$B$54="","",'3-Year P&L'!$B$54),"") -> 0.099575881 | C21: =IFERROR(IF('3-Year P&L'!$E$54="","",'3-Year P&L'!$E$54),"") -> 0.12 | D21: =IFERROR(IF(OR(B21="",C21=""),"",IF(B21<=C21,"OK","REVIEW")),"") -> OK
A22: Net income / Sales | B22: =IFERROR(IF('3-Year P&L'!$B$55="","",'3-Year P&L'!$B$55),"") -> 0.073446269 | C22: =IFERROR(IF('3-Year P&L'!$E$55="","",'3-Year P&L'!$E$55),"") -> 0.06 | D22: =IFERROR(IF(OR(B22="",C22=""),"",IF(B22>=C22,"OK","REVIEW")),"") -> OK
A23: Gross margin / Sales | B23: =IFERROR(IF('3-Year P&L'!$B$50="","",'3-Year P&L'!$B$50),"") -> 0.6504 | C23: =IFERROR(IF('3-Year P&L'!$E$50="","",'3-Year P&L'!$E$50),"") -> 0.65 | D23: =IFERROR(IF(OR(B23="",C23=""),"",IF(B23>=C23,"OK","REVIEW")),"") -> OK
A25: THIS PLAN'S KEY FIGURES
A26: Total startup costs (sum of the blocks) | B26: =IFERROR(IF('Startup Costs'!$B$35="","",'Startup Costs'!$B$35),"") -> 263686.7
A27: Total cash needed at launch | B27: =IFERROR(IF('Startup Costs'!$B$38="","",'Startup Costs'!$B$38),"") -> 263686.7
A28: Working capital funded | B28: =IFERROR(IF('Startup Costs'!$B$34="","",'Startup Costs'!$B$34),"") -> 69886.7
A29: Forecast year-1 revenue | B29: =IFERROR(IF('3-Year P&L'!$B$9="","",'3-Year P&L'!$B$9),"") -> 542300
A30: Year-1 net income | B30: =IFERROR(IF('3-Year P&L'!$B$47="","",'3-Year P&L'!$B$47),"") -> 39829.911
A31: Customers per day for the ACCOUNTING break-even (depreciation included) | B31: =IFERROR(IF('Break-Even'!$B$15="","",'Break-Even'!$B$15),"") -> 123.16788
A32: Project payback (years), before debt | B32: =IFERROR(IF('12-Month Cash Flow'!$B$31="","",'12-Month Cash Flow'!$B$31),"") -> 2.9
A34: WHY THIS MODEL IS BUILT THIS WAY
A35: Item | B35: Common shortcut | C35: This workbook | D35: Why
A36: Labor cost in the P&L | B36: A typed-in number, disconnected from the staffing tab | C36: The total of the "Staffing" tab, by formula | D36: When the P&L and the staffing tab disagree, nobody knows which one to trust. Here both say the same thing, and if you change a salary the result changes on its own.
A37: Staffing | B37: A handful of full-time positions sized by guesswork | C37: Positions, including part-time lines, sized to the service hours you declare | D37: Labor is sized to the hours of service this workbook declares, so the payroll comes from the schedule and is then tested against the labor-cost ceiling in the industry benchmarks table.
A38: Example staff wages | B38: No check against the minimum wage | C38: Every row is compared with the federal minimum wage (and with your state or local rate, if you enter one), in proportion to its FTE | D38: The "Staffing" tab checks row by row and warns in red if you go below that floor. A workbook that proposes wages below the legal minimum cannot be shown to a lender.
A39: Schedule coverage | B39: Staffing is not linked to opening hours | C39: The tab compares the hours your team covers with the service hours you declare | D39: Opening hours multiplied by the people needed at the same time give the hours you need per year. The workbook counts them and warns in red if the roster does not reach them.
A40: Customers per day | B40: Backed out of a revenue target | C40: Typed in as an input and tested against the seat count | D40: Customers per day is a driver, not a plug. Compare it with the range in the industry benchmarks table below and with the seat turns calculated on the "0. Assumptions" tab.
A41: Average check | B41: A single number, without saying whether it includes sales tax | C41: Entered excl. sales tax; the "0. Assumptions" tab calculates the equivalent menu price incl. sales tax | D41: Revenue is booked excl. sales tax, as it appears in your P&L. Declaring the basis avoids comparing a tax-inclusive menu price with a net average check.
A42: Rent | B42: A monthly figure with no link to sales | C42: A monthly rent on the "0. Assumptions" tab, tested as a percentage of sales | D42: The "3-Year P&L" shows rent against the 12% of sales threshold, so you see right away whether the location is viable.
A43: Opening calendar | B43: Two different calendars in the same workbook: a monthly day count on one tab and an annual count on another | C43: A single operating-days input on the "0. Assumptions" tab | D43: The daily break-even, the P&L and the scenarios all use the same number of days, so the daily break-even matches the days you actually plan to open.
A44: Working capital | B44: A round number with a "3 months" label | C44: 3 months of cash fixed costs, by formula | D44: A typed figure can cover far fewer months than its label says. A formula recalculates by itself whenever you change any expense.
A45: Depreciation | B45: One flat period over the WHOLE investment, working capital and opening inventory included | C45: Only on the build-out and the equipment, each with its own useful life | D45: The cash cushion, inventory, security deposit, pre-opening rent and the formation, license and launch costs are not fixed assets: depreciating them would inflate expenses and distort the tax line. Build-out contingency IS depreciated, because it is part of the cost of the renovation.
A46: Build-out contingency | B46: A fixed amount with a percentage written inside the label | C46: A formula on the build-out lines, with the percentage on the "0. Assumptions" tab | D46: A percentage hidden in a label stops being true as soon as one line changes. Here it is an input and the amount recalculates.
... A50: Financing requested | B50: Typed in, with nothing to reconcile it | C50: Owner equity and loan, reconciled against the cash need on the "Financing" tab | D50: Sources should cover the cash need that this workbook calculates, with only a small surplus: borrowing more means paying interest on money you do not use. The "Financing" tab calculates the exact loan amount that sets the gap to zero.
A52: INDUSTRY BENCHMARKS
A53: Benchmark | B53: Value | C53: Source | D53: Note
A54: Beverage cost: coffee | B54: 20-30% | C54: Kit estimate | D54: Specialty coffee reaches the low end of the range with a good supplier and tight waste control
A55: Food cost: brunch | B55: 30-35% | C55: Kit estimate | D55: Portion control and waste tracking decide it
A56: Beverage cost: cold drinks | B56: 28-32% | C56: Kit estimate | D56: Juices and smoothies: high cost because they use fresh product
A57: Labor cost / Sales | B57: 30-35% (alarm above 40%) | C57: Bellwether Coffee (bellwethercoffee.com) | D57: The kit applies the top of this range (35%) as the ceiling in the "3-Year P&L"
A58: Rent / Sales | B58: 10% target, 15% maximum | C58: Kit estimate | D58: The "3-Year P&L" flags rent above 12% of sales
A59: Average check: coffee and breakfast | B59: 4-6 | C59: Kit estimate | D59: Coffee and basic pastries only
A60: Average check: full brunch | B60: 14-20 | C60: Kit estimate | D60: Main dish, drink and a dessert or coffee
A61: Combined average check | B61: 7.81-11.11 | C61: Dojo Business (dojobusiness.com) | D61: Weighted average of all services. The average check excl. sales tax of this projection and its menu-price equivalent are calculated on the "0. Assumptions" tab
A62: Customers per day (small coffee shop) | B62: 100-250 | C62: Dojo Business (dojobusiness.com) | D62: Depends heavily on the location and the foot traffic
A63: Average occupancy on weekdays | B63: 40-60% | C63: Kit estimate | D63: Morning is the peak; afternoon is the slowest shift
A64: Average occupancy on weekends | B64: 70-90% | C64: Kit estimate | D64: It is what justifies the Saturday and Sunday reinforcement on the "Staffing" tab
A65: Table turns at weekend brunch | B65: 2-3 turns | C65: Kit estimate | D65: With the seats declared on the "0. Assumptions" tab, it is the reference that supports the customers per day of the base case
A66: Target gross margin | B66: > 65% | C66: Kit estimate
A67: Net margin (healthy coffee shop) | B67: 8-12% (under 6%: structural problem) | C67: Bellwether Coffee (bellwethercoffee.com) | D67: The "3-Year P&L" flags a net margin below 6% of sales. Year 1 usually lands at the low end because volume is still growing and loan interest is at its highest (the ramp-up only moves sales between months, it does not lower the year): compare it with Net income / Sales on that tab.
A68: Payback period | B68: 24-36 months | C68: Kit estimate | D68: An industry reference measured on what the owner puts in. The "12-Month Cash Flow" tab publishes the PROJECT payback, before payments to the lender: compare that cell with this range. For the return on YOUR money, divide your equity by the project free cash flow on that same tab
A69: Applicable state / local minimum wage | B69: State and local minimum wage | C69: DOL (dol.gov/agencies/whd/minimum-wage) | D69: There is no single national table above the federal floor: look up the rate for your state and city and enter it on the "0. Assumptions" tab
A70: Federal minimum wage | B70: 7.25 per hour (15,080 per year full-time) | C70: DOL (dol.gov/agencies/whd/minimum-wage) | D70: Legal floor for covered employees at 2,080 hours a year. Part-time positions get it in proportion; the traffic light on the "Staffing" tab checks it row by row. State and local rates are often higher, and the higher one applies. If you present the plan in another year, check the current rate
A72: To edit a cell that is not green: Review → Unprotect Sheet (there is no password).
A73: More templates and kits in the catalog at aichef.pro/en/digital-products
A74: Designed by John Guerrero — chef and restaurant consultant since 2010, in the kitchen since age 17 · johnguerrero.es
A75: Version 2.2 · October 2026 · aichef.pro/en/digital-products/coffee-shop-business-plan · info@aichef.pro
A76: Planning tool, not financial, tax or legal advice. Requirements vary by state, county and city — check with your accountant and local authorities.

Sheet 12-Month Cash Flow
A1: CASH FLOW FORECAST — YEAR 1
A2: The P&L tells you whether the business makes money; this tab tells you whether you have cash left to get to the end of the month. It is the first one a lender looks at.
A4: Item | B4: Month 1 | C4: Month 2 | D4: Month 3 | E4: Month 4 | F4: Month 5 | G4: Month 6 | H4: Month 7 | I4: Month 8 | J4: Month 9 | K4: Month 10 | L4: Month 11 | M4: Month 12 | N4: Year
A5: Monthly seasonality (adds up to 100%) | B5: 0.075 | C5: 0.075 | D5: 0.085 | E5: 0.088 | F5: 0.09 | G5: 0.085 | H5: 0.075 | I5: 0.06 | J5: 0.085 | K5: 0.09 | L5: 0.085 | M5: 0.107 | N5: =IFERROR(IF('3-Year P&L'!$B$9="","",SUM(B5:M5)),"") -> 1 | O5: Profile for your area: adjust it to your own slow and busy months (weather, tourism, events). It must add up to 100%
A6: Launch ramp-up (% of steady-state activity) | B6: =IFERROR(IF('3-Year P&L'!$B$9="","",MIN(1,'0. Assumptions'!$B$52+(1-'0. Assumptions'!$B$52)*0/MAX(1,'0. Assumptions'!$B$53-1))),"") -> 0.55 | C6: =IFERROR(IF('3-Year P&L'!$B$9="","",MIN(1,'0. Assumptions'!$B$52+(1-'0. Assumptions'!$B$52)*1/MAX(1,'0. Assumptions'!$B$53-1))),"") -> 0.64 | D6: =IFERROR(IF('3-Year P&L'!$B$9="","",MIN(1,'0. Assumptions'!$B$52+(1-'0. Assumptions'!$B$52)*2/MAX(1,'0. Assumptions'!$B$53-1))),"") -> 0.73 | E6: =IFERROR(IF('3-Year P&L'!$B$9="","",MIN(1,'0. Assumptions'!$B$52+(1-'0. Assumptions'!$B$52)*3/MAX(1,'0. Assumptions'!$B$53-1))),"") -> 0.82 | F6: =IFERROR(IF('3-Year P&L'!$B$9="","",MIN(1,'0. Assumptions'!$B$52+(1-'0. Assumptions'!$B$52)*4/MAX(1,'0. Assumptions'!$B$53-1))),"") -> 0.91 | G6: =IFERROR(IF('3-Year P&L'!$B$9="","",MIN(1,'0. Assumptions'!$B$52+(1-'0. Assumptions'!$B$52)*5/MAX(1,'0. Assumptions'!$B$53-1))),"") -> 1 | H6: =IFERROR(IF('3-Year P&L'!$B$9="","",MIN(1,'0. Assumptions'!$B$52+(1-'0. Assumptions'!$B$52)*6/MAX(1,'0. Assumptions'!$B$53-1))),"") -> 1 | I6: =IFERROR(IF('3-Year P&L'!$B$9="","",MIN(1,'0. Assumptions'!$B$52+(1-'0. Assumptions'!$B$52)*7/MAX(1,'0. Assumptions'!$B$53-1))),"") -> 1 | J6: =IFERROR(IF('3-Year P&L'!$B$9="","",MIN(1,'0. Assumptions'!$B$52+(1-'0. Assumptions'!$B$52)*8/MAX(1,'0. Assumptions'!$B$53-1))),"") -> 1 | K6: =IFERROR(IF('3-Year P&L'!$B$9="","",MIN(1,'0. Assumptions'!$B$52+(1-'0. Assumptions'!$B$52)*9/MAX(1,'0. Assumptions'!$B$53-1))),"") -> 1 | L6: =IFERROR(IF('3-Year P&L'!$B$9="","",MIN(1,'0. Assumptions'!$B$52+(1-'0. Assumptions'!$B$52)*10/MAX(1,'0. Assumptions'!$B$53-1))),"") -> 1 | M6: =IFERROR(IF('3-Year P&L'!$B$9="","",MIN(1,'0. Assumptions'!$B$52+(1-'0. Assumptions'!$B$52)*11/MAX(1,'0. Assumptions'!$B$53-1))),"") -> 1 | O6: Rises in a straight line from the month-1 percentage to 100% over the number of months you set in Assumptions. With month 1 at 100%, the ramp disappears
A7: Split of activity by month (calculated) | B7: =IFERROR(IF('3-Year P&L'!$B$9="","",B5*B6/SUMPRODUCT($B$5:$M$5,$B$6:$M$6)),"") -> 0.046225738 | C7: =IFERROR(IF('3-Year P&L'!$B$9="","",C5*C6/SUMPRODUCT($B$5:$M$5,$B$6:$M$6)),"") -> 0.05378995 | D7: =IFERROR(IF('3-Year P&L'!$B$9="","",D5*D6/SUMPRODUCT($B$5:$M$5,$B$6:$M$6)),"") -> 0.069534717 | E7: =IFERROR(IF('3-Year P&L'!$B$9="","",E5*E6/SUMPRODUCT($B$5:$M$5,$B$6:$M$6)),"") -> 0.080864225 | F7: =IFERROR(IF('3-Year P&L'!$B$9="","",F5*F6/SUMPRODUCT($B$5:$M$5,$B$6:$M$6)),"") -> 0.091779103 | G7: =IFERROR(IF('3-Year P&L'!$B$9="","",G5*G6/SUMPRODUCT($B$5:$M$5,$B$6:$M$6)),"") -> 0.095253037 | H7: =IFERROR(IF('3-Year P&L'!$B$9="","",H5*H6/SUMPRODUCT($B$5:$M$5,$B$6:$M$6)),"") -> 0.084046797 | I7: =IFERROR(IF('3-Year P&L'!$B$9="","",I5*I6/SUMPRODUCT($B$5:$M$5,$B$6:$M$6)),"") -> 0.067237438 | ... M7: =IFERROR(IF('3-Year P&L'!$B$9="","",M5*M6/SUMPRODUCT($B$5:$M$5,$B$6:$M$6)),"") -> 0.11990676 | N7: =IFERROR(IF('3-Year P&L'!$B$9="","",SUM(B7:M7)),"") -> 1 | O7: Seasonality × ramp-up, normalized to 100%: the YEAR brings in what the P&L says, but split the way a business that has just opened would split it
A8: CASH IN
A9: Sales collected (incl. sales tax collected) | B9: =IFERROR(IF('3-Year P&L'!$B$9="","",('3-Year P&L'!$B$9+'3-Year P&L'!$B$9*SUMPRODUCT('3-Year P&L'!$E$10:$E$11,'3-Year P&L'!$G$10:$G$11))*B7*(1-MIN(30,'0. Assumptions'!$B$58)/30)),"") -> 26171.22 | C9: =IFERROR(IF('3-Year P&L'!$B$9="","",('3-Year P&L'!$B$9+'3-Year P&L'!$B$9*SUMPRODUCT('3-Year P&L'!$E$10:$E$11,'3-Year P&L'!$G$10:$G$11))*(C7*(1-MIN(30,'0. Assumptions'!$B$58)/30)+B7*MIN(30,'0. Assumptions'!$B$58)/30)),"") -> 31356.239 | D9: =IFERROR(IF('3-Year P&L'!$B$9="","",('3-Year P&L'!$B$9+'3-Year P&L'!$B$9*SUMPRODUCT('3-Year P&L'!$E$10:$E$11,'3-Year P&L'!$G$10:$G$11))*(D7*(1-MIN(30,'0. Assumptions'!$B$58)/30)+C7*MIN(30,'0. Assumptions'!$B$58)/30)),"") -> 40417.989 | E9: =IFERROR(IF('3-Year P&L'!$B$9="","",('3-Year P&L'!$B$9+'3-Year P&L'!$B$9*SUMPRODUCT('3-Year P&L'!$E$10:$E$11,'3-Year P&L'!$G$10:$G$11))*(E7*(1-MIN(30,'0. Assumptions'!$B$58)/30)+D7*MIN(30,'0. Assumptions'!$B$58)/30)),"") -> 47139.699 | F9: =IFERROR(IF('3-Year P&L'!$B$9="","",('3-Year P&L'!$B$9+'3-Year P&L'!$B$9*SUMPRODUCT('3-Year P&L'!$E$10:$E$11,'3-Year P&L'!$G$10:$G$11))*(F7*(1-MIN(30,'0. Assumptions'!$B$58)/30)+E7*MIN(30,'0. Assumptions'!$B$58)/30)),"") -> 53540.463 | G9: =IFERROR(IF('3-Year P&L'!$B$9="","",('3-Year P&L'!$B$9+'3-Year P&L'!$B$9*SUMPRODUCT('3-Year P&L'!$E$10:$E$11,'3-Year P&L'!$G$10:$G$11))*(G7*(1-MIN(30,'0. Assumptions'!$B$58)/30)+F7*MIN(30,'0. Assumptions'!$B$58)/30)),"") -> 55720.359 | H9: =IFERROR(IF('3-Year P&L'!$B$9="","",('3-Year P&L'!$B$9+'3-Year P&L'!$B$9*SUMPRODUCT('3-Year P&L'!$E$10:$E$11,'3-Year P&L'!$G$10:$G$11))*(H7*(1-MIN(30,'0. Assumptions'!$B$58)/30)+G7*MIN(30,'0. Assumptions'!$B$58)/30)),"") -> 49443.642 | I9: =IFERROR(IF('3-Year P&L'!$B$9="","",('3-Year P&L'!$B$9+'3-Year P&L'!$B$9*SUMPRODUCT('3-Year P&L'!$E$10:$E$11,'3-Year P&L'!$G$10:$G$11))*(I7*(1-MIN(30,'0. Assumptions'!$B$58)/30)+H7*MIN(30,'0. Assumptions'!$B$58)/30)),"") -> 39708.057 | J9: =IFERROR(IF('3-Year P&L'!$B$9="","",('3-Year P&L'!$B$9+'3-Year P&L'!$B$9*SUMPRODUCT('3-Year P&L'!$E$10:$E$11,'3-Year P&L'!$G$10:$G$11))*(J7*(1-MIN(30,'0. Assumptions'!$B$58)/30)+I7*MIN(30,'0. Assumptions'!$B$58)/30)),"") -> 55241.237 | ... M9: =IFERROR(IF('3-Year P&L'!$B$9="","",('3-Year P&L'!$B$9+'3-Year P&L'!$B$9*SUMPRODUCT('3-Year P&L'!$E$10:$E$11,'3-Year P&L'!$G$10:$G$11))*(M7*(1-MIN(30,'0. Assumptions'!$B$58)/30)+L7*MIN(30,'0. Assumptions'!$B$58)/30)),"") -> 69746.163 | N9: =IFERROR(IF('3-Year P&L'!$B$9="","",SUM(B9:M9)),"") -> 583343.08 | O9: The month's sales plus the sales tax collected, adjusted by the average collection days from the Assumptions tab
A10: CASH OUT
A11: Purchases and variable costs (incl. sales tax) | B11: =IFERROR(IF('3-Year P&L'!$B$9="","",-('3-Year P&L'!$B$13*(1+'3-Year P&L'!$G$13)+'3-Year P&L'!$B$14*(1+'3-Year P&L'!$G$14)+'3-Year P&L'!$B$15*(1+'3-Year P&L'!$G$15)+'3-Year P&L'!$B$16*(1+'3-Year P&L'!$G$16)+'3-Year P&L'!$B$17*(1+'3-Year P&L'!$G$17)+'3-Year P&L'!$B$18*(1+'3-Year P&L'!$G$18))*B7*(1-MIN(30,'0. Assumptions'!$B$59)/30)),"") -> -4674.0528 | C11: =IFERROR(IF('3-Year P&L'!$B$9="","",-('3-Year P&L'!$B$13*(1+'3-Year P&L'!$G$13)+'3-Year P&L'!$B$14*(1+'3-Year P&L'!$G$14)+'3-Year P&L'!$B$15*(1+'3-Year P&L'!$G$15)+'3-Year P&L'!$B$16*(1+'3-Year P&L'!$G$16)+'3-Year P&L'!$B$17*(1+'3-Year P&L'!$G$17)+'3-Year P&L'!$B$18*(1+'3-Year P&L'!$G$18))*(C7*(1-MIN(30,'0. Assumptions'!$B$59)/30)+B7*MIN(30,'0. Assumptions'!$B$59)/30)),"") -> -9528.694 | D11: =IFERROR(IF('3-Year P&L'!$B$9="","",-('3-Year P&L'!$B$13*(1+'3-Year P&L'!$G$13)+'3-Year P&L'!$B$14*(1+'3-Year P&L'!$G$14)+'3-Year P&L'!$B$15*(1+'3-Year P&L'!$G$15)+'3-Year P&L'!$B$16*(1+'3-Year P&L'!$G$16)+'3-Year P&L'!$B$17*(1+'3-Year P&L'!$G$17)+'3-Year P&L'!$B$18*(1+'3-Year P&L'!$G$18))*(D7*(1-MIN(30,'0. Assumptions'!$B$59)/30)+C7*MIN(30,'0. Assumptions'!$B$59)/30)),"") -> -11789.944 | E11: =IFERROR(IF('3-Year P&L'!$B$9="","",-('3-Year P&L'!$B$13*(1+'3-Year P&L'!$G$13)+'3-Year P&L'!$B$14*(1+'3-Year P&L'!$G$14)+'3-Year P&L'!$B$15*(1+'3-Year P&L'!$G$15)+'3-Year P&L'!$B$16*(1+'3-Year P&L'!$G$16)+'3-Year P&L'!$B$17*(1+'3-Year P&L'!$G$17)+'3-Year P&L'!$B$18*(1+'3-Year P&L'!$G$18))*(E7*(1-MIN(30,'0. Assumptions'!$B$59)/30)+D7*MIN(30,'0. Assumptions'!$B$59)/30)),"") -> -14328.521 | F11: =IFERROR(IF('3-Year P&L'!$B$9="","",-('3-Year P&L'!$B$13*(1+'3-Year P&L'!$G$13)+'3-Year P&L'!$B$14*(1+'3-Year P&L'!$G$14)+'3-Year P&L'!$B$15*(1+'3-Year P&L'!$G$15)+'3-Year P&L'!$B$16*(1+'3-Year P&L'!$G$16)+'3-Year P&L'!$B$17*(1+'3-Year P&L'!$G$17)+'3-Year P&L'!$B$18*(1+'3-Year P&L'!$G$18))*(F7*(1-MIN(30,'0. Assumptions'!$B$59)/30)+E7*MIN(30,'0. Assumptions'!$B$59)/30)),"") -> -16434.536 | G11: =IFERROR(IF('3-Year P&L'!$B$9="","",-('3-Year P&L'!$B$13*(1+'3-Year P&L'!$G$13)+'3-Year P&L'!$B$14*(1+'3-Year P&L'!$G$14)+'3-Year P&L'!$B$15*(1+'3-Year P&L'!$G$15)+'3-Year P&L'!$B$16*(1+'3-Year P&L'!$G$16)+'3-Year P&L'!$B$17*(1+'3-Year P&L'!$G$17)+'3-Year P&L'!$B$18*(1+'3-Year P&L'!$G$18))*(G7*(1-MIN(30,'0. Assumptions'!$B$59)/30)+F7*MIN(30,'0. Assumptions'!$B$59)/30)),"") -> -17751.486 | H11: =IFERROR(IF('3-Year P&L'!$B$9="","",-('3-Year P&L'!$B$13*(1+'3-Year P&L'!$G$13)+'3-Year P&L'!$B$14*(1+'3-Year P&L'!$G$14)+'3-Year P&L'!$B$15*(1+'3-Year P&L'!$G$15)+'3-Year P&L'!$B$16*(1+'3-Year P&L'!$G$16)+'3-Year P&L'!$B$17*(1+'3-Year P&L'!$G$17)+'3-Year P&L'!$B$18*(1+'3-Year P&L'!$G$18))*(H7*(1-MIN(30,'0. Assumptions'!$B$59)/30)+G7*MIN(30,'0. Assumptions'!$B$59)/30)),"") -> -16925.737 | I11: =IFERROR(IF('3-Year P&L'!$B$9="","",-('3-Year P&L'!$B$13*(1+'3-Year P&L'!$G$13)+'3-Year P&L'!$B$14*(1+'3-Year P&L'!$G$14)+'3-Year P&L'!$B$15*(1+'3-Year P&L'!$G$15)+'3-Year P&L'!$B$16*(1+'3-Year P&L'!$G$16)+'3-Year P&L'!$B$17*(1+'3-Year P&L'!$G$17)+'3-Year P&L'!$B$18*(1+'3-Year P&L'!$G$18))*(I7*(1-MIN(30,'0. Assumptions'!$B$59)/30)+H7*MIN(30,'0. Assumptions'!$B$59)/30)),"") -> -14234.615 | J11: =IFERROR(IF('3-Year P&L'!$B$9="","",-('3-Year P&L'!$B$13*(1+'3-Year P&L'!$G$13)+'3-Year P&L'!$B$14*(1+'3-Year P&L'!$G$14)+'3-Year P&L'!$B$15*(1+'3-Year P&L'!$G$15)+'3-Year P&L'!$B$16*(1+'3-Year P&L'!$G$16)+'3-Year P&L'!$B$17*(1+'3-Year P&L'!$G$17)+'3-Year P&L'!$B$18*(1+'3-Year P&L'!$G$18))*(J7*(1-MIN(30,'0. Assumptions'!$B$59)/30)+I7*MIN(30,'0. Assumptions'!$B$59)/30)),"") -> -15580.176 | ... M11: =IFERROR(IF('3-Year P&L'!$B$9="","",-('3-Year P&L'!$B$13*(1+'3-Year P&L'!$G$13)+'3-Year P&L'!$B$14*(1+'3-Year P&L'!$G$14)+'3-Year P&L'!$B$15*(1+'3-Year P&L'!$G$15)+'3-Year P&L'!$B$16*(1+'3-Year P&L'!$G$16)+'3-Year P&L'!$B$17*(1+'3-Year P&L'!$G$17)+'3-Year P&L'!$B$18*(1+'3-Year P&L'!$G$18))*(M7*(1-MIN(30,'0. Assumptions'!$B$59)/30)+L7*MIN(30,'0. Assumptions'!$B$59)/30)),"") -> -20551.669 | N11: =IFERROR(IF('3-Year P&L'!$B$9="","",SUM(B11:M11)),"") -> -178979.4 | O11: =IFERROR("Food and beverage purchases, consumables, fees and contingencies, each at ITS tax rate (column G of the P&L; 0 in the US, where the sales tax you pay is part of the cost) and with the supplier payment days from ""0. Assumptions""."&IF('0. Assumptions'!$B$59=0,""," With "&TEXT('0. Assumptions'!$B$59,"0")&" payment days, the last purchases of the year are paid next year: the ""Year"" column of this row holds "&TEXT(MAX(0,12-ROUNDUP('0. Assumptions'!$B$59/30,0)),"0")&" months of purchases, not the year's cost."),"") -> Food and beverage purchases, consumables, fees and contingencies, each at ITS tax rate (column G of the P&L; 0 in the US, where the sales tax you pay is part of the cost) and with the supplier payment days from "0. Assumptions". With 14 payment days, the last purchases of the year are paid next year: the "Year" column of this row holds 11 months of purchases, not the year's cost.
A12: Operating fixed costs (incl. sales tax) | B12: =IFERROR(IF('3-Year P&L'!$B$9="","",-('3-Year P&L'!$B$37-'3-Year P&L'!$B$23-'3-Year P&L'!$B$35-'3-Year P&L'!$B$36+'3-Year P&L'!$B$39)/12),"") -> -7516.6667 | C12: =IFERROR(IF('3-Year P&L'!$B$9="","",-('3-Year P&L'!$B$37-'3-Year P&L'!$B$23-'3-Year P&L'!$B$35-'3-Year P&L'!$B$36+'3-Year P&L'!$B$39)/12),"") -> -7516.6667 | D12: =IFERROR(IF('3-Year P&L'!$B$9="","",-('3-Year P&L'!$B$37-'3-Year P&L'!$B$23-'3-Year P&L'!$B$35-'3-Year P&L'!$B$36+'3-Year P&L'!$B$39)/12),"") -> -7516.6667 | E12: =IFERROR(IF('3-Year P&L'!$B$9="","",-('3-Year P&L'!$B$37-'3-Year P&L'!$B$23-'3-Year P&L'!$B$35-'3-Year P&L'!$B$36+'3-Year P&L'!$B$39)/12),"") -> -7516.6667 | F12: =IFERROR(IF('3-Year P&L'!$B$9="","",-('3-Year P&L'!$B$37-'3-Year P&L'!$B$23-'3-Year P&L'!$B$35-'3-Year P&L'!$B$36+'3-Year P&L'!$B$39)/12),"") -> -7516.6667 | G12: =IFERROR(IF('3-Year P&L'!$B$9="","",-('3-Year P&L'!$B$37-'3-Year P&L'!$B$23-'3-Year P&L'!$B$35-'3-Year P&L'!$B$36+'3-Year P&L'!$B$39)/12),"") -> -7516.6667 | H12: =IFERROR(IF('3-Year P&L'!$B$9="","",-('3-Year P&L'!$B$37-'3-Year P&L'!$B$23-'3-Year P&L'!$B$35-'3-Year P&L'!$B$36+'3-Year P&L'!$B$39)/12),"") -> -7516.6667 | I12: =IFERROR(IF('3-Year P&L'!$B$9="","",-('3-Year P&L'!$B$37-'3-Year P&L'!$B$23-'3-Year P&L'!$B$35-'3-Year P&L'!$B$36+'3-Year P&L'!$B$39)/12),"") -> -7516.6667 | ... M12: =IFERROR(IF('3-Year P&L'!$B$9="","",-('3-Year P&L'!$B$37-'3-Year P&L'!$B$23-'3-Year P&L'!$B$35-'3-Year P&L'!$B$36+'3-Year P&L'!$B$39)/12),"") -> -7516.6667 | N12: =IFERROR(IF('3-Year P&L'!$B$9="","",SUM(B12:M12)),"") -> -90200 | O12: The fixed costs that leave cash, each with its own tax rate: insurance carries none
A13: Payroll and employer payroll taxes | B13: =IFERROR(IF('3-Year P&L'!$B$9="","",-'3-Year P&L'!$B$23/MAX(12,'0. Assumptions'!$B$21)*(1+IF(1='0. Assumptions'!$B$60,(MAX(12,'0. Assumptions'!$B$21)-12)/2,0)+IF(1='0. Assumptions'!$B$61,(MAX(12,'0. Assumptions'!$B$21)-12)/2,0))),"") -> -14078.9 | C13: =IFERROR(IF('3-Year P&L'!$B$9="","",-'3-Year P&L'!$B$23/MAX(12,'0. Assumptions'!$B$21)*(1+IF(2='0. Assumptions'!$B$60,(MAX(12,'0. Assumptions'!$B$21)-12)/2,0)+IF(2='0. Assumptions'!$B$61,(MAX(12,'0. Assumptions'!$B$21)-12)/2,0))),"") -> -14078.9 | D13: =IFERROR(IF('3-Year P&L'!$B$9="","",-'3-Year P&L'!$B$23/MAX(12,'0. Assumptions'!$B$21)*(1+IF(3='0. Assumptions'!$B$60,(MAX(12,'0. Assumptions'!$B$21)-12)/2,0)+IF(3='0. Assumptions'!$B$61,(MAX(12,'0. Assumptions'!$B$21)-12)/2,0))),"") -> -14078.9 | E13: =IFERROR(IF('3-Year P&L'!$B$9="","",-'3-Year P&L'!$B$23/MAX(12,'0. Assumptions'!$B$21)*(1+IF(4='0. Assumptions'!$B$60,(MAX(12,'0. Assumptions'!$B$21)-12)/2,0)+IF(4='0. Assumptions'!$B$61,(MAX(12,'0. Assumptions'!$B$21)-12)/2,0))),"") -> -14078.9 | F13: =IFERROR(IF('3-Year P&L'!$B$9="","",-'3-Year P&L'!$B$23/MAX(12,'0. Assumptions'!$B$21)*(1+IF(5='0. Assumptions'!$B$60,(MAX(12,'0. Assumptions'!$B$21)-12)/2,0)+IF(5='0. Assumptions'!$B$61,(MAX(12,'0. Assumptions'!$B$21)-12)/2,0))),"") -> -14078.9 | G13: =IFERROR(IF('3-Year P&L'!$B$9="","",-'3-Year P&L'!$B$23/MAX(12,'0. Assumptions'!$B$21)*(1+IF(6='0. Assumptions'!$B$60,(MAX(12,'0. Assumptions'!$B$21)-12)/2,0)+IF(6='0. Assumptions'!$B$61,(MAX(12,'0. Assumptions'!$B$21)-12)/2,0))),"") -> -14078.9 | H13: =IFERROR(IF('3-Year P&L'!$B$9="","",-'3-Year P&L'!$B$23/MAX(12,'0. Assumptions'!$B$21)*(1+IF(7='0. Assumptions'!$B$60,(MAX(12,'0. Assumptions'!$B$21)-12)/2,0)+IF(7='0. Assumptions'!$B$61,(MAX(12,'0. Assumptions'!$B$21)-12)/2,0))),"") -> -14078.9 | I13: =IFERROR(IF('3-Year P&L'!$B$9="","",-'3-Year P&L'!$B$23/MAX(12,'0. Assumptions'!$B$21)*(1+IF(8='0. Assumptions'!$B$60,(MAX(12,'0. Assumptions'!$B$21)-12)/2,0)+IF(8='0. Assumptions'!$B$61,(MAX(12,'0. Assumptions'!$B$21)-12)/2,0))),"") -> -14078.9 | J13: =IFERROR(IF('3-Year P&L'!$B$9="","",-'3-Year P&L'!$B$23/MAX(12,'0. Assumptions'!$B$21)*(1+IF(9='0. Assumptions'!$B$60,(MAX(12,'0. Assumptions'!$B$21)-12)/2,0)+IF(9='0. Assumptions'!$B$61,(MAX(12,'0. Assumptions'!$B$21)-12)/2,0))),"") -> -14078.9 | K13: =IFERROR(IF('3-Year P&L'!$B$9="","",-'3-Year P&L'!$B$23/MAX(12,'0. Assumptions'!$B$21)*(1+IF(10='0. Assumptions'!$B$60,(MAX(12,'0. Assumptions'!$B$21)-12)/2,0)+IF(10='0. Assumptions'!$B$61,(MAX(12,'0. Assumptions'!$B$21)-12)/2,0))),"") -> -14078.9 | L13: =IFERROR(IF('3-Year P&L'!$B$9="","",-'3-Year P&L'!$B$23/MAX(12,'0. Assumptions'!$B$21)*(1+IF(11='0. Assumptions'!$B$60,(MAX(12,'0. Assumptions'!$B$21)-12)/2,0)+IF(11='0. Assumptions'!$B$61,(MAX(12,'0. Assumptions'!$B$21)-12)/2,0))),"") -> -14078.9 | M13: =IFERROR(IF('3-Year P&L'!$B$9="","",-'3-Year P&L'!$B$23/MAX(12,'0. Assumptions'!$B$21)*(1+IF(12='0. Assumptions'!$B$60,(MAX(12,'0. Assumptions'!$B$21)-12)/2,0)+IF(12='0. Assumptions'!$B$61,(MAX(12,'0. Assumptions'!$B$21)-12)/2,0))),"") -> -14078.9 | N13: =IFERROR(IF('3-Year P&L'!$B$9="","",SUM(B13:M13)),"") -> -168946.8 | O13: Twelve monthly installments plus extra pay periods in the months you set in Assumptions (only if pay periods > 12). The total for the year is the same as the P&L's
A14: Loan interest | B14: =IFERROR(IF('3-Year P&L'!$B$9="","",-Financing!$B$44/12),"") -> -1700 | C14: =IFERROR(IF('3-Year P&L'!$B$9="","",-Financing!$B$44/12),"") -> -1700 | D14: =IFERROR(IF('3-Year P&L'!$B$9="","",-Financing!$B$44/12),"") -> -1700 | E14: =IFERROR(IF('3-Year P&L'!$B$9="","",-Financing!$B$44/12),"") -> -1700 | F14: =IFERROR(IF('3-Year P&L'!$B$9="","",-Financing!$B$44/12),"") -> -1700 | G14: =IFERROR(IF('3-Year P&L'!$B$9="","",-Financing!$B$44/12),"") -> -1700 | H14: =IFERROR(IF('3-Year P&L'!$B$9="","",-Financing!$B$44/12),"") -> -1700 | I14: =IFERROR(IF('3-Year P&L'!$B$9="","",-Financing!$B$44/12),"") -> -1700 | ... M14: =IFERROR(IF('3-Year P&L'!$B$9="","",-Financing!$B$44/12),"") -> -1700 | N14: =IFERROR(IF('3-Year P&L'!$B$9="","",SUM(B14:M14)),"") -> -20400
A15: Loan principal repaid | B15: =IFERROR(IF('3-Year P&L'!$B$9="","",-Financing!$B$45/12),"") -> -1066.6717 | C15: =IFERROR(IF('3-Year P&L'!$B$9="","",-Financing!$B$45/12),"") -> -1066.6717 | D15: =IFERROR(IF('3-Year P&L'!$B$9="","",-Financing!$B$45/12),"") -> -1066.6717 | E15: =IFERROR(IF('3-Year P&L'!$B$9="","",-Financing!$B$45/12),"") -> -1066.6717 | F15: =IFERROR(IF('3-Year P&L'!$B$9="","",-Financing!$B$45/12),"") -> -1066.6717 | G15: =IFERROR(IF('3-Year P&L'!$B$9="","",-Financing!$B$45/12),"") -> -1066.6717 | H15: =IFERROR(IF('3-Year P&L'!$B$9="","",-Financing!$B$45/12),"") -> -1066.6717 | I15: =IFERROR(IF('3-Year P&L'!$B$9="","",-Financing!$B$45/12),"") -> -1066.6717 | ... M15: =IFERROR(IF('3-Year P&L'!$B$9="","",-Financing!$B$45/12),"") -> -1066.6717 | N15: =IFERROR(IF('3-Year P&L'!$B$9="","",SUM(B15:M15)),"") -> -12800.061
A16: Sales tax collected (memo) | B16: =IFERROR(IF('3-Year P&L'!$B$9="","",'3-Year P&L'!$B$9*B7*SUMPRODUCT('3-Year P&L'!$E$10:$E$11,'3-Year P&L'!$G$10:$G$11)),"") -> 2005.4574 | C16: =IFERROR(IF('3-Year P&L'!$B$9="","",'3-Year P&L'!$B$9*C7*SUMPRODUCT('3-Year P&L'!$E$10:$E$11,'3-Year P&L'!$G$10:$G$11)),"") -> 2333.6232 | D16: =IFERROR(IF('3-Year P&L'!$B$9="","",'3-Year P&L'!$B$9*D7*SUMPRODUCT('3-Year P&L'!$E$10:$E$11,'3-Year P&L'!$G$10:$G$11)),"") -> 3016.6942 | E16: =IFERROR(IF('3-Year P&L'!$B$9="","",'3-Year P&L'!$B$9*E7*SUMPRODUCT('3-Year P&L'!$E$10:$E$11,'3-Year P&L'!$G$10:$G$11)),"") -> 3508.2135 | F16: =IFERROR(IF('3-Year P&L'!$B$9="","",'3-Year P&L'!$B$9*F7*SUMPRODUCT('3-Year P&L'!$E$10:$E$11,'3-Year P&L'!$G$10:$G$11)),"") -> 3981.7446 | G16: =IFERROR(IF('3-Year P&L'!$B$9="","",'3-Year P&L'!$B$9*G7*SUMPRODUCT('3-Year P&L'!$E$10:$E$11,'3-Year P&L'!$G$10:$G$11)),"") -> 4132.4578 | H16: =IFERROR(IF('3-Year P&L'!$B$9="","",'3-Year P&L'!$B$9*H7*SUMPRODUCT('3-Year P&L'!$E$10:$E$11,'3-Year P&L'!$G$10:$G$11)),"") -> 3646.2863 | I16: =IFERROR(IF('3-Year P&L'!$B$9="","",'3-Year P&L'!$B$9*I7*SUMPRODUCT('3-Year P&L'!$E$10:$E$11,'3-Year P&L'!$G$10:$G$11)),"") -> 2917.029 | ... M16: =IFERROR(IF('3-Year P&L'!$B$9="","",'3-Year P&L'!$B$9*M7*SUMPRODUCT('3-Year P&L'!$E$10:$E$11,'3-Year P&L'!$G$10:$G$11)),"") -> 5202.0351 | N16: =IFERROR(IF('3-Year P&L'!$B$9="","",SUM(B16:M16)),"") -> 43384 | O16: Each sales line at ITS OWN rate, read from the sales tax column of the P&L (alcohol to go has its own rate cell in the Assumptions tab)
A17: Recoverable input tax (memo) | B17: =IFERROR(IF('3-Year P&L'!$B$9="","",'3-Year P&L'!$B$38*B7+'3-Year P&L'!$B$39/12),"") -> 0 | C17: =IFERROR(IF('3-Year P&L'!$B$9="","",'3-Year P&L'!$B$38*C7+'3-Year P&L'!$B$39/12),"") -> 0 | D17: =IFERROR(IF('3-Year P&L'!$B$9="","",'3-Year P&L'!$B$38*D7+'3-Year P&L'!$B$39/12),"") -> 0 | E17: =IFERROR(IF('3-Year P&L'!$B$9="","",'3-Year P&L'!$B$38*E7+'3-Year P&L'!$B$39/12),"") -> 0 | F17: =IFERROR(IF('3-Year P&L'!$B$9="","",'3-Year P&L'!$B$38*F7+'3-Year P&L'!$B$39/12),"") -> 0 | G17: =IFERROR(IF('3-Year P&L'!$B$9="","",'3-Year P&L'!$B$38*G7+'3-Year P&L'!$B$39/12),"") -> 0 | H17: =IFERROR(IF('3-Year P&L'!$B$9="","",'3-Year P&L'!$B$38*H7+'3-Year P&L'!$B$39/12),"") -> 0 | I17: =IFERROR(IF('3-Year P&L'!$B$9="","",'3-Year P&L'!$B$38*I7+'3-Year P&L'!$B$39/12),"") -> 0 | ... M17: =IFERROR(IF('3-Year P&L'!$B$9="","",'3-Year P&L'!$B$38*M7+'3-Year P&L'!$B$39/12),"") -> 0 | N17: =IFERROR(IF('3-Year P&L'!$B$9="","",SUM(B17:M17)),"") -> 0 | O17: Each item at its own rate, read from the tax column of the P&L: insurance and card processing fees carry none
A18: Carried forward (capex input tax included) | E18: =IFERROR(IF('3-Year P&L'!$B$9="","",'Startup Costs'!$B$37),"") -> 0 | H18: =IFERROR(IF('3-Year P&L'!$B$9="","",MAX(0,-E19)),"") -> 0 | K18: =IFERROR(IF('3-Year P&L'!$B$9="","",MAX(0,-H19)),"") -> 0 | O18: Sales tax paid on STARTUP COSTS enters here: it is offset against the tax collected in later quarters until used up. With 0% recoverable input tax (the US default) this line stays at zero
A19: Quarterly sales tax return | E19: =IFERROR(IF('3-Year P&L'!$B$9="","",SUM(B16:D16)-SUM(B17:D17)-E18),"") -> 7355.7748 | H19: =IFERROR(IF('3-Year P&L'!$B$9="","",SUM(E16:G16)-SUM(E17:G17)-H18),"") -> 11622.416 | K19: =IFERROR(IF('3-Year P&L'!$B$9="","",SUM(H16:J16)-SUM(H17:J17)-K18),"") -> 10695.773 | O19: Sales tax collected minus recoverable input tax for the quarter, minus what was carried forward. If negative, nothing is paid: it is offset in the next quarter. With 0% recoverable input tax (the US default) it equals the sales tax collected in the quarter
A20: Sales tax remitted (quarterly filer) | E20: =IFERROR(IF('3-Year P&L'!$B$9="","",IF(E19<=0,"",-E19)),"") -> -7355.7748 | H20: =IFERROR(IF('3-Year P&L'!$B$9="","",IF(H19<=0,"",-H19)),"") -> -11622.416 | K20: =IFERROR(IF('3-Year P&L'!$B$9="","",IF(K19<=0,"",-K19)),"") -> -10695.773 | N20: =IFERROR(IF('3-Year P&L'!$B$9="","",SUM(B20:M20)),"") -> -29673.964 | O20: Cash only leaves when the quarter's result is positive. Months without a settlement are left blank, not zero. The cell turns RED when the payment takes more cash than is left that month. The model settles quarterly, in the month after each plan quarter (Months 4, 7 and 10, and the fourth quarter in Month 13: April, July, October and January when Month 1 is January): if your state requires monthly filing, expect smaller payments every month instead
A21: MONTHLY NET CASH FLOW | B21: =IFERROR(IF('3-Year P&L'!$B$9="","",SUM(B9:B15)+IF(B20="",0,B20)),"") -> -2865.0716 | C21: =IFERROR(IF('3-Year P&L'!$B$9="","",SUM(C9:C15)+IF(C20="",0,C20)),"") -> -2534.6938 | D21: =IFERROR(IF('3-Year P&L'!$B$9="","",SUM(D9:D15)+IF(D20="",0,D20)),"") -> 4265.8067 | E21: =IFERROR(IF('3-Year P&L'!$B$9="","",SUM(E9:E15)+IF(E20="",0,E20)),"") -> 1093.1646 | F21: =IFERROR(IF('3-Year P&L'!$B$9="","",SUM(F9:F15)+IF(F20="",0,F20)),"") -> 12743.688 | G21: =IFERROR(IF('3-Year P&L'!$B$9="","",SUM(G9:G15)+IF(G20="",0,G20)),"") -> 13606.634 | H21: =IFERROR(IF('3-Year P&L'!$B$9="","",SUM(H9:H15)+IF(H20="",0,H20)),"") -> -3466.7494 | I21: =IFERROR(IF('3-Year P&L'!$B$9="","",SUM(I9:I15)+IF(I20="",0,I20)),"") -> 1111.2035 | ... M21: =IFERROR(IF('3-Year P&L'!$B$9="","",SUM(M9:M15)+IF(M20="",0,M20)),"") -> 24832.257 | N21: =IFERROR(IF('3-Year P&L'!$B$9="","",SUM(B21:M21)),"") -> 82342.863
A22: CUMULATIVE CASH BALANCE | B22: =IFERROR(IF('3-Year P&L'!$B$9="","",'Startup Costs'!$B$34+B21),"") -> 67021.628 | C22: =IFERROR(IF('3-Year P&L'!$B$9="","",B22+C21),"") -> 64486.935 | D22: =IFERROR(IF('3-Year P&L'!$B$9="","",C22+D21),"") -> 68752.741 | E22: =IFERROR(IF('3-Year P&L'!$B$9="","",D22+E21),"") -> 69845.906 | F22: =IFERROR(IF('3-Year P&L'!$B$9="","",E22+F21),"") -> 82589.594 | G22: =IFERROR(IF('3-Year P&L'!$B$9="","",F22+G21),"") -> 96196.229 | H22: =IFERROR(IF('3-Year P&L'!$B$9="","",G22+H21),"") -> 92729.479 | I22: =IFERROR(IF('3-Year P&L'!$B$9="","",H22+I21),"") -> 93840.683 | J22: =IFERROR(IF('3-Year P&L'!$B$9="","",I22+J21),"") -> 109139.51 | ... M22: =IFERROR(IF('3-Year P&L'!$B$9="","",L22+M21),"") -> 152229.56
A23: Minimum balance of the year | B23: =IFERROR(IF('3-Year P&L'!$B$9="","",IF(COUNT(B22:M22)=0,"",MIN(B22:M22))),"") -> 64486.935 | D23: If negative, raise working capital or the loan: you run out of cash
A24: Month when cash bottoms out | B24: =IFERROR(IF('3-Year P&L'!$B$9="","",IF(COUNT(B22:M22)=0,"",MATCH(MIN(B22:M22),B22:M22,0))),"") -> 2 | D24: It answers the question that decides a bank deal: in which month the cash runs out
A25: RETURN ON INVESTMENT
A26: Free cash flow before debt, year 1 | B26: =IFERROR(IF('3-Year P&L'!$B$9="","",'3-Year P&L'!$B$47+'3-Year P&L'!$B$35+Financing!$B$44),"") -> 80288.483 | D26: Net income plus depreciation (which is not paid) plus that year's interest: principal is not subtracted because this flow is BEFORE debt. The SAME basis as years 2 and 3, so the payback compares like with like
A27: Free cash flow before debt, year 2 | B27: =IFERROR(IF('3-Year P&L'!$B$9="","",'3-Year P&L'!$C$47+'3-Year P&L'!$C$35+Financing!$B$46),"") -> 93985.857 | D27: Net income plus depreciation (which is not paid) plus that year's interest: principal is not subtracted because this flow is BEFORE debt. Without a monthly table, it is an estimate
A28: Free cash flow before debt, year 3 | B28: =IFERROR(IF('3-Year P&L'!$B$9="","",'3-Year P&L'!$D$47+'3-Year P&L'!$D$35+Financing!$B$48),"") -> 103286.42 | D28: Net income plus depreciation (which is not paid) plus that year's interest: principal is not subtracted because this flow is BEFORE debt. Without a monthly table, it is an estimate
A29: For reference: ACTUAL year-1 cash flow (monthly table, before debt) | B29: =IFERROR(IF('3-Year P&L'!$B$9="","",N21+Financing!$B$44+Financing!$B$45),"") -> 115542.92 | D29: The sum of the twelve monthly net cash flows above, adding back the interest and principal paid that year. It is NOT the one the payback uses: it includes sales tax not yet settled and supplier credit, two things that have to be paid back and that years 2 and 3 do not have
A30: Investment to recover (net of recoverable input tax) | B30: =IFERROR(IF('3-Year P&L'!$B$9="","",'Startup Costs'!$B$38-'Startup Costs'!$B$37),"") -> 263686.7 | D30: CAPEX plus working capital: the total cash needed MINUS the recoverable input tax on startup costs, which is not lost (it is recovered through the quarterly return, and this tab offsets it quarter by quarter; it is zero in the US default). Working capital is recovered when you close, but until then it is tied up
A31: Project payback (years), before debt | B31: =IFERROR(IF('3-Year P&L'!$B$9="","",IF(B26>=B30,ROUND(B30/B26,1),IF(B26+B27>=B30,ROUND(1+(B30-B26)/B27,1),IF(B26+B27+B28>=B30,ROUND(2+(B30-B26-B27)/B28,1),"Over 3 years")))),"") -> 2.9 | D31: Measures how long the business takes to repay the investment with what it generates BEFORE paying the lender, on the SAME cash flow basis in all three years. Whether you can afford the loan payment is shown by the DSCR in the Financing tab
A32: Payback on CAPEX, excluding working capital (years) | B32: =IFERROR(IF('3-Year P&L'!$B$9="","",IF(B26>='Startup Costs'!$B$36,ROUND('Startup Costs'!$B$36/B26,1),IF(B26+B27>='Startup Costs'!$B$36,ROUND(1+('Startup Costs'!$B$36-B26)/B27,1),IF(B26+B27+B28>='Startup Costs'!$B$36,ROUND(2+('Startup Costs'!$B$36-B26-B27)/B28,1),"Over 3 years")))),"") -> 2.2 | D32: The same calculation on what you BUY (build-out, equipment, launch and formation costs), without working capital: that money is not spent, it is tied up and comes back when the business closes. For reference only: the payback that matters is the one above
A34: Fourth-quarter sales tax is settled in Month 13 (January of the following year when Month 1 is January), so it does not appear in this table. The model pays year-1 income tax in July of year 2 (a simplification: estimated tax payments are usually quarterly). The loan payment is spread in twelve equal parts following the ANNUAL schedule in the Financing tab, and payroll in twelve monthly installments (plus extra pay periods in their month, only if pay periods > 12).

Sheet Financing
A1: FINANCING PLAN
A2: What you need, where it comes from and what it costs to repay. It is the sheet your lender asks for along with the P&L.
A4: Item | B4: Amount | C4: Notes
A5: SOURCES OF FUNDS
A6: Owner's equity (your own money) | B6: =IFERROR(IF('0. Assumptions'!$B$30="","",'0. Assumptions'!$B$30),"") -> 60000
A7: Loan requested — bank or SBA 7(a) (amortized below) | B7: =IFERROR(IF('0. Assumptions'!$B$31="","",'0. Assumptions'!$B$31),"") -> 204000
A8: Other loan (not in the schedule or the DSCR — enter your loan in row 7) | B8: 0 | C8: A source of funds only: NOT amortized, so it is not in the schedule, the P&L interest or the DSCR. Enter your bank or SBA 7(a) loan in row 7 ("Loan requested" in "0. Assumptions"); use this row only for a second loan
A9: SBA Microloan (not in the schedule or the DSCR — enter your loan in row 7) | B9: 0 | C9: SBA Microloans go up to $50,000 through nonprofit intermediaries. Like row 8, a source of funds only: not in the schedule or the DSCR. If it is your only loan, enter it in row 7 instead
A10: Investors / partners (equity: dilutes, not repaid) | B10: 0 | C10: Equity: it dilutes your ownership and is not repaid
A11: Local grants (usually paid after you spend) | B11: 0 | C11: Usually paid AFTER you document the spending
A12: TOTAL SOURCES OF FUNDS | B12: =IFERROR(IF(COUNT(B6:B11)=0,"",SUM(B6:B11)),"") -> 264000
A13: USES OF FUNDS
A14: Total cash needed at launch | B14: =IFERROR(IF('Startup Costs'!$B$38="","",'Startup Costs'!$B$38),"") -> 263686.7 | C14: Startup costs plus any recoverable tax you have to advance (zero by default in the US)
A15: Difference (sources - uses) | B15: =IFERROR(B12-B14,"") -> 313.3 | C15: In red (negative), the plan is NOT funded. Far above zero is not free either: you pay interest on money you do not use
A16: Difference as a % of uses | B16: =IFERROR(B15/B14,"") -> 0.0011881525 | C16: Amber above the margin you set: it is debt you pay for without needing it
A17: Acceptable over-funding (%) | B17: 0.05 | C17: A small cushion over the need is healthy; 20% extra is interest thrown away
A18: Loan that would match sources to needs | B18: =IFERROR(MAX(0,B14-B12+B7),"") -> 203686.7 | C18: Copy it into "Loan requested" in the "0. Assumptions" tab and the difference goes to zero. Rows 8-11 lower this figure, but only the row-7 loan is amortized and counted in the DSCR
A19: LOAN TERMS
A20: Principal amount | B20: =IFERROR(IF('0. Assumptions'!$B$31=0,"",'0. Assumptions'!$B$31),"") -> 204000
A21: Nominal annual interest rate (not APR) | B21: =IFERROR(IF('0. Assumptions'!$B$32="","",'0. Assumptions'!$B$32),"") -> 0.1
A22: Total term (years) | B22: =IFERROR(IF('0. Assumptions'!$B$33="","",'0. Assumptions'!$B$33),"") -> 10
A23: Interest-only period applied (years) | B23: =IFERROR(IF(OR('0. Assumptions'!$B$34="",'0. Assumptions'!$B$33=""),"",IF('0. Assumptions'!$B$34>='0. Assumptions'!$B$33,0,'0. Assumptions'!$B$34)),"") -> 0 | C23: An interest-only period equal to or longer than the term does not exist: the sheet cancels it at the source
A24: Annual payment during repayment | B24: =IFERROR(IF(B22-B23<=0,"",IF(B21=0,B20/(B22-B23),B20*B21/(1-(1+B21)^-(B22-B23)))),"") -> 33200.061 | C24: Standard amortizing loan with a level annual payment. At a 0% rate it is the principal divided by the repayment years: without that branch the schedule would shut down entirely
A25: AMORTIZATION SCHEDULE
A26: Year | B26: Opening balance | C26: Interest | D26: Principal repaid | E26: Total payment | F26: Closing balance | G26: Cash flow available for debt service (after tax; from year 4 on, year 3 held flat) | H26: DSCR for the year
A27: 1 | B27: =IFERROR(IF(B20="","",B20),"") -> 204000 | C27: =IFERROR(IF(OR(1>B22,B27=""),"",B27*B21),"") -> 20400 | D27: =IFERROR(IF(OR(1>B22,B27=""),"",IF(1<=B23,0,MIN(B27,B24-C27))),"") -> 12800.061 | E27: =IFERROR(IF(C27="","",C27+D27),"") -> 33200.061 | F27: =IFERROR(IF(D27="","",B27-D27),"") -> 191199.94 | G27: =IFERROR(IF(E27="","",'3-Year P&L'!$B$40-'3-Year P&L'!$B$45+'3-Year P&L'!$B$35+'3-Year P&L'!$B$36),"") -> 80288.483 | H27: =IFERROR(IF(OR(E27="",E27=0),"",G27/E27),"") -> 2.4183234
A28: 2 | B28: =IFERROR(IF(OR(2>B22,F27=""),"",F27),"") -> 191199.94 | C28: =IFERROR(IF(OR(2>B22,B28=""),"",B28*B21),"") -> 19119.994 | D28: =IFERROR(IF(OR(2>B22,B28=""),"",IF(2<=B23,0,MIN(B28,B24-C28))),"") -> 14080.067 | E28: =IFERROR(IF(C28="","",C28+D28),"") -> 33200.061 | F28: =IFERROR(IF(D28="","",B28-D28),"") -> 177119.87 | G28: =IFERROR(IF(E28="","",'3-Year P&L'!$C$40-'3-Year P&L'!$C$45+'3-Year P&L'!$C$35+'3-Year P&L'!$C$36),"") -> 93985.857 | H28: =IFERROR(IF(OR(E28="",E28=0),"",G28/E28),"") -> 2.8308941
A29: 3 | B29: =IFERROR(IF(OR(3>B22,F28=""),"",F28),"") -> 177119.87 | C29: =IFERROR(IF(OR(3>B22,B29=""),"",B29*B21),"") -> 17711.987 | D29: =IFERROR(IF(OR(3>B22,B29=""),"",IF(3<=B23,0,MIN(B29,B24-C29))),"") -> 15488.073 | E29: =IFERROR(IF(C29="","",C29+D29),"") -> 33200.061 | F29: =IFERROR(IF(D29="","",B29-D29),"") -> 161631.8 | G29: =IFERROR(IF(E29="","",'3-Year P&L'!$D$40-'3-Year P&L'!$D$45+'3-Year P&L'!$D$35+'3-Year P&L'!$D$36),"") -> 103286.42 | H29: =IFERROR(IF(OR(E29="",E29=0),"",G29/E29),"") -> 3.1110311
A30: 4 | B30: =IFERROR(IF(OR(4>B22,F29=""),"",F29),"") -> 161631.8 | C30: =IFERROR(IF(OR(4>B22,B30=""),"",B30*B21),"") -> 16163.18 | D30: =IFERROR(IF(OR(4>B22,B30=""),"",IF(4<=B23,0,MIN(B30,B24-C30))),"") -> 17036.881 | E30: =IFERROR(IF(C30="","",C30+D30),"") -> 33200.061 | F30: =IFERROR(IF(D30="","",B30-D30),"") -> 144594.92 | G30: =IFERROR(IF(E30="","",'3-Year P&L'!$D$40-'3-Year P&L'!$D$45+'3-Year P&L'!$D$35+'3-Year P&L'!$D$36),"") -> 103286.42 | H30: =IFERROR(IF(OR(E30="",E30=0),"",G30/E30),"") -> 3.1110311
A31: 5 | B31: =IFERROR(IF(OR(5>B22,F30=""),"",F30),"") -> 144594.92 | C31: =IFERROR(IF(OR(5>B22,B31=""),"",B31*B21),"") -> 14459.492 | D31: =IFERROR(IF(OR(5>B22,B31=""),"",IF(5<=B23,0,MIN(B31,B24-C31))),"") -> 18740.569 | E31: =IFERROR(IF(C31="","",C31+D31),"") -> 33200.061 | F31: =IFERROR(IF(D31="","",B31-D31),"") -> 125854.35 | G31: =IFERROR(IF(E31="","",'3-Year P&L'!$D$40-'3-Year P&L'!$D$45+'3-Year P&L'!$D$35+'3-Year P&L'!$D$36),"") -> 103286.42 | H31: =IFERROR(IF(OR(E31="",E31=0),"",G31/E31),"") -> 3.1110311
A32: 6 | B32: =IFERROR(IF(OR(6>B22,F31=""),"",F31),"") -> 125854.35 | C32: =IFERROR(IF(OR(6>B22,B32=""),"",B32*B21),"") -> 12585.435 | D32: =IFERROR(IF(OR(6>B22,B32=""),"",IF(6<=B23,0,MIN(B32,B24-C32))),"") -> 20614.626 | E32: =IFERROR(IF(C32="","",C32+D32),"") -> 33200.061 | F32: =IFERROR(IF(D32="","",B32-D32),"") -> 105239.72 | G32: =IFERROR(IF(E32="","",'3-Year P&L'!$D$40-'3-Year P&L'!$D$45+'3-Year P&L'!$D$35+'3-Year P&L'!$D$36),"") -> 103286.42 | H32: =IFERROR(IF(OR(E32="",E32=0),"",G32/E32),"") -> 3.1110311
A33: 7 | B33: =IFERROR(IF(OR(7>B22,F32=""),"",F32),"") -> 105239.72 | C33: =IFERROR(IF(OR(7>B22,B33=""),"",B33*B21),"") -> 10523.972 | D33: =IFERROR(IF(OR(7>B22,B33=""),"",IF(7<=B23,0,MIN(B33,B24-C33))),"") -> 22676.088 | E33: =IFERROR(IF(C33="","",C33+D33),"") -> 33200.061 | F33: =IFERROR(IF(D33="","",B33-D33),"") -> 82563.637 | G33: =IFERROR(IF(E33="","",'3-Year P&L'!$D$40-'3-Year P&L'!$D$45+'3-Year P&L'!$D$35+'3-Year P&L'!$D$36),"") -> 103286.42 | H33: =IFERROR(IF(OR(E33="",E33=0),"",G33/E33),"") -> 3.1110311
A34: 8 | B34: =IFERROR(IF(OR(8>B22,F33=""),"",F33),"") -> 82563.637 | C34: =IFERROR(IF(OR(8>B22,B34=""),"",B34*B21),"") -> 8256.3637 | D34: =IFERROR(IF(OR(8>B22,B34=""),"",IF(8<=B23,0,MIN(B34,B24-C34))),"") -> 24943.697 | E34: =IFERROR(IF(C34="","",C34+D34),"") -> 33200.061 | F34: =IFERROR(IF(D34="","",B34-D34),"") -> 57619.94 | G34: =IFERROR(IF(E34="","",'3-Year P&L'!$D$40-'3-Year P&L'!$D$45+'3-Year P&L'!$D$35+'3-Year P&L'!$D$36),"") -> 103286.42 | H34: =IFERROR(IF(OR(E34="",E34=0),"",G34/E34),"") -> 3.1110311
A35: 9 | B35: =IFERROR(IF(OR(9>B22,F34=""),"",F34),"") -> 57619.94 | C35: =IFERROR(IF(OR(9>B22,B35=""),"",B35*B21),"") -> 5761.994 | D35: =IFERROR(IF(OR(9>B22,B35=""),"",IF(9<=B23,0,MIN(B35,B24-C35))),"") -> 27438.067 | E35: =IFERROR(IF(C35="","",C35+D35),"") -> 33200.061 | F35: =IFERROR(IF(D35="","",B35-D35),"") -> 30181.873 | G35: =IFERROR(IF(E35="","",'3-Year P&L'!$D$40-'3-Year P&L'!$D$45+'3-Year P&L'!$D$35+'3-Year P&L'!$D$36),"") -> 103286.42 | H35: =IFERROR(IF(OR(E35="",E35=0),"",G35/E35),"") -> 3.1110311
A36: 10 | B36: =IFERROR(IF(OR(10>B22,F35=""),"",F35),"") -> 30181.873 | C36: =IFERROR(IF(OR(10>B22,B36=""),"",B36*B21),"") -> 3018.1873 | D36: =IFERROR(IF(OR(10>B22,B36=""),"",IF(10<=B23,0,MIN(B36,B24-C36))),"") -> 30181.873 | E36: =IFERROR(IF(C36="","",C36+D36),"") -> 33200.061 | F36: =IFERROR(IF(D36="","",B36-D36),"") -> 2.7284841e-10 | G36: =IFERROR(IF(E36="","",'3-Year P&L'!$D$40-'3-Year P&L'!$D$45+'3-Year P&L'!$D$35+'3-Year P&L'!$D$36),"") -> 103286.42 | H36: =IFERROR(IF(OR(E36="",E36=0),"",G36/E36),"") -> 3.1110311
A37: 11 | B37: =IFERROR(IF(OR(11>B22,F36=""),"",F36),"") | C37: =IFERROR(IF(OR(11>B22,B37=""),"",B37*B21),"") | D37: =IFERROR(IF(OR(11>B22,B37=""),"",IF(11<=B23,0,MIN(B37,B24-C37))),"") | E37: =IFERROR(IF(C37="","",C37+D37),"") | F37: =IFERROR(IF(D37="","",B37-D37),"") | G37: =IFERROR(IF(E37="","",'3-Year P&L'!$D$40-'3-Year P&L'!$D$45+'3-Year P&L'!$D$35+'3-Year P&L'!$D$36),"") | H37: =IFERROR(IF(OR(E37="",E37=0),"",G37/E37),"")
A38: 12 | B38: =IFERROR(IF(OR(12>B22,F37=""),"",F37),"") | C38: =IFERROR(IF(OR(12>B22,B38=""),"",B38*B21),"") | D38: =IFERROR(IF(OR(12>B22,B38=""),"",IF(12<=B23,0,MIN(B38,B24-C38))),"") | E38: =IFERROR(IF(C38="","",C38+D38),"") | F38: =IFERROR(IF(D38="","",B38-D38),"") | G38: =IFERROR(IF(E38="","",'3-Year P&L'!$D$40-'3-Year P&L'!$D$45+'3-Year P&L'!$D$35+'3-Year P&L'!$D$36),"") | H38: =IFERROR(IF(OR(E38="",E38=0),"",G38/E38),"")
A39: 13 | B39: =IFERROR(IF(OR(13>B22,F38=""),"",F38),"") | C39: =IFERROR(IF(OR(13>B22,B39=""),"",B39*B21),"") | D39: =IFERROR(IF(OR(13>B22,B39=""),"",IF(13<=B23,0,MIN(B39,B24-C39))),"") | E39: =IFERROR(IF(C39="","",C39+D39),"") | F39: =IFERROR(IF(D39="","",B39-D39),"") | G39: =IFERROR(IF(E39="","",'3-Year P&L'!$D$40-'3-Year P&L'!$D$45+'3-Year P&L'!$D$35+'3-Year P&L'!$D$36),"") | H39: =IFERROR(IF(OR(E39="",E39=0),"",G39/E39),"")
A40: 14 | B40: =IFERROR(IF(OR(14>B22,F39=""),"",F39),"") | C40: =IFERROR(IF(OR(14>B22,B40=""),"",B40*B21),"") | D40: =IFERROR(IF(OR(14>B22,B40=""),"",IF(14<=B23,0,MIN(B40,B24-C40))),"") | E40: =IFERROR(IF(C40="","",C40+D40),"") | F40: =IFERROR(IF(D40="","",B40-D40),"") | G40: =IFERROR(IF(E40="","",'3-Year P&L'!$D$40-'3-Year P&L'!$D$45+'3-Year P&L'!$D$35+'3-Year P&L'!$D$36),"") | H40: =IFERROR(IF(OR(E40="",E40=0),"",G40/E40),"")
A41: 15 | B41: =IFERROR(IF(OR(15>B22,F40=""),"",F40),"") | C41: =IFERROR(IF(OR(15>B22,B41=""),"",B41*B21),"") | D41: =IFERROR(IF(OR(15>B22,B41=""),"",IF(15<=B23,0,MIN(B41,B24-C41))),"") | E41: =IFERROR(IF(C41="","",C41+D41),"") | F41: =IFERROR(IF(D41="","",B41-D41),"") | G41: =IFERROR(IF(E41="","",'3-Year P&L'!$D$40-'3-Year P&L'!$D$45+'3-Year P&L'!$D$35+'3-Year P&L'!$D$36),"") | H41: =IFERROR(IF(OR(E41="",E41=0),"",G41/E41),"")
A42: Schedule closing tolerance | B42: 0.01 | C42: Rounding margin. Above it, the schedule does not close and there is principal left unpaid
A43: Balance outstanding at maturity | B43: =IFERROR(IF(B20="","",ROUND(B20-SUM(D27:D41),2)),"") -> 0 | C43: Must be zero: the principal repaid in the schedule has to equal the amount borrowed. If it is positive, the term falls short
A44: Year-1 interest | B44: =IFERROR(IF(B20="","",IF(C27="",0,C27)),"") -> 20400
A45: Year-1 principal repaid | B45: =IFERROR(IF(B20="","",IF(D27="",0,D27)),"") -> 12800.061
A46: Year-2 interest | B46: =IFERROR(IF(B20="","",IF(C28="",0,C28)),"") -> 19119.994
A47: Year-2 principal repaid | B47: =IFERROR(IF(B20="","",IF(D28="",0,D28)),"") -> 14080.067
A48: Year-3 interest | B48: =IFERROR(IF(B20="","",IF(C29="",0,C29)),"") -> 17711.987
A49: Year-3 principal repaid | B49: =IFERROR(IF(B20="","",IF(D29="",0,D29)),"") -> 15488.073
A50: DEBT SERVICE COVERAGE RATIO (DSCR)
A51: Year-1 DSCR | B51: =IFERROR(('3-Year P&L'!$B$40-'3-Year P&L'!$B$45+'3-Year P&L'!$B$35+B44)/(B44+B45),"") -> 2.4183234 | C51: An INTEREST-ONLY year, if there is one: with only interest in the denominator the ratio shoots up and does not measure the business
A52: Year-2 DSCR | B52: =IFERROR(('3-Year P&L'!$C$40-'3-Year P&L'!$C$45+'3-Year P&L'!$C$35+B46)/(B46+B47),"") -> 2.8308941
A53: Year-3 DSCR | B53: =IFERROR(('3-Year P&L'!$D$40-'3-Year P&L'!$D$45+'3-Year P&L'!$D$35+B48)/(B48+B49),"") -> 3.1110311
A54: Minimum DSCR across the whole schedule | B54: =IFERROR(IF(COUNT(H27:H41)=0,"",MIN(H27:H41)),"") -> 2.4183234 | C54: The worst year of the life of the loan, not the best of the three the P&L projects. It is the number that decides a loan. Mind the scope: years 1 to 3 come from the P&L, and from year 4 on the schedule HOLDS year 3's cash flow, so the minimum over those years is a sustained projection, not a calculated year. The cash flow is after tax
A56: DSCR is calculated BEFORE debt and AFTER tax: income tax is subtracted from pre-tax income, depreciation and interest are added back, and the result is divided by what has to be paid that year. Below the minimum in the "0. Assumptions" tab, the business does not generate enough to repay the loan. In the schedule, the available cash flow from year 4 on is held at year 3's: the P&L projects only three years, and no growth is invented here that has not been calculated.
