Workbook

Sheet Instructions
B2: 02 · Overtime Tracker & Time Log (FLSA 40-Hour Week)
B4: How to use this template:
B5: ▸ Log clock-in, clock-out and BREAK. The break is what makes a split shift loggable: 10:00 AM → 11:00 PM with a 4 h break is 9 h worked, not 13. Use one row per person per day (two rows on the same date double-count weekly overtime).
B6: ▸ A NIGHT shift is logged the same way: 11:00 PM → 7:00 AM is 8 h. The formula handles the midnight crossing.
B7: ▸ The "Monthly OT Summary" adds up each employee's hours with SUMIF: nothing to copy by hand.
B8: ▸ This sheet has 300 rows: 30 people clocking in 6 days a week fill 180 per workweek; a team of 10 fits a whole month. Use one copy of the file per period (weekly or biweekly payroll: one per pay period). Each copy must hold WHOLE workweeks starting on the day in B3 of the "Time Log" (2 = Monday by default, the same week as the schedule in file 01). Keep a week that crosses months in one copy, or its overtime will be lost. Need more rows? Unprotect the sheet, insert them above row 304 and fill the formulas down: rows added below 304 are not counted.
B10: What federal law says (FLSA):
B11: ▸ FLSA, 29 U.S.C. 207(a)(1): overtime is every hour over 40 in the workweek, paid at 1.5× the regular rate. Federal law sets no yearly cap on overtime: the 80 h budget ("Monthly OT Summary", F3) is a kit rule you can change.
B12: ▸ Some states add a daily rule (California: over 8 h in a day at 1.5×, over 12 h at 2×; Labor Code §510(a)). Type your state's daily threshold in F3 above the log; leave it blank for the federal rule only. UK: no legal overtime premium (gov.uk/overtime-your-rights).
B13: ▸ That is why the multiplier is a green cell (D3 of the "Monthly OT Summary") and not a number inside a formula. Keep it at 1.5, the FLSA rate for non-exempt staff: California double time applies only over 12 h in a day and over 8 h on the 7th consecutive day of the workweek (Labor Code §510(a)), so do not set 2× for every hour; price those hours apart. Raise it only if your contract pays more than 1.5× on all overtime. Tipped staff: overtime is owed on the full minimum wage, not on the cash wage (29 CFR 531.60).
B14: ▸ You may require overtime from non-exempt staff, but every hour worked must be paid, including overtime nobody approved (29 CFR 785.11-785.13).
B16: Log columns:
... B29: Version 2.0 · October 2026 · aichef.pro/en/digital-products/restaurant-schedule-templates · info@aichef.pro

Sheet Time Log
A1: Time Log — Workweeks from ___/___/___ to ___/___/___
A2: AI Chef Pro · aichef.pro — Restaurant Staff Scheduling Kit Pro
A3: Workweek starts (1=Sun, 2=Mon): | B3: 2 | C3: Weekly OT after (h): | D3: 40 | E3: Daily OT after (h):
A4: Employee | B4: Date | C4: Clock-in | D4: Clock-out | E4: Break (h) | F4: Hours worked | G4: Scheduled hours | H4: OT hours (FLSA) | I4: OT type | J4: Alert
F5: =IF(OR($C5="",$D5=""),"",IF(OR($C5>=1,$D5>=1,$C5=$D5,IF($E5="",0,$E5)>MOD($D5-$C5,1)*24),"",ROUND(MOD($D5-$C5,1)*24-IF($E5="",0,$E5),2))) | G5: 8 | H5: =IF(OR($A5="",$B5="",$F5=""),"",ROUND(IF($F$3="",0,MAX(0,$F5-$F$3))+IF($D$3="",0,MIN($F5-IF($F$3="",0,MAX(0,$F5-$F$3)),MAX(0,SUMIFS($F$5:$F$304,$A$5:$A$304,$A5&"",$B$5:$B$304,">="&($B5-MOD(WEEKDAY($B5)-$B$3,7)),$B$5:$B$304,"<="&$B5)-IF($F$3="",0,SUMIFS($F$5:$F$304,$A$5:$A$304,$A5&"",$B$5:$B$304,">="&($B5-MOD(WEEKDAY($B5)-$B$3,7)),$B$5:$B$304,"<="&$B5,$F$5:$F$304,">"&$F$3)-$F$3*COUNTIFS($A$5:$A$304,$A5&"",$B$5:$B$304,">="&($B5-MOD(WEEKDAY($B5)-$B$3,7)),$B$5:$B$304,"<="&$B5,$F$5:$F$304,">"&$F$3))-$D$3))),2)) | J5: =IF(AND($A5="",$C5="",$D5=""),"",IF(OR($C5>=1,$D5>=1),"⚠ type the time with a colon: 9:00 AM, not 9",IF(AND($C5<>"",$C5=$D5),"⚠ clock-in equals clock-out: the shift adds 0 h",IF(AND($C5<>"",$D5<>"",IF($E5="",0,$E5)>MOD($D5-$C5,1)*24),"⚠ the break is longer than the shift",IF(AND($A5<>"",COUNTIF('Monthly OT Summary'!$A$6:$A$35,$A5&"")=0),"⚠ name not in Monthly OT Summary: its hours are not added","")))))
F6: =IF(OR($C6="",$D6=""),"",IF(OR($C6>=1,$D6>=1,$C6=$D6,IF($E6="",0,$E6)>MOD($D6-$C6,1)*24),"",ROUND(MOD($D6-$C6,1)*24-IF($E6="",0,$E6),2))) | G6: 8 | H6: =IF(OR($A6="",$B6="",$F6=""),"",ROUND(IF($F$3="",0,MAX(0,$F6-$F$3))+IF($D$3="",0,MIN($F6-IF($F$3="",0,MAX(0,$F6-$F$3)),MAX(0,SUMIFS($F$5:$F$304,$A$5:$A$304,$A6&"",$B$5:$B$304,">="&($B6-MOD(WEEKDAY($B6)-$B$3,7)),$B$5:$B$304,"<="&$B6)-IF($F$3="",0,SUMIFS($F$5:$F$304,$A$5:$A$304,$A6&"",$B$5:$B$304,">="&($B6-MOD(WEEKDAY($B6)-$B$3,7)),$B$5:$B$304,"<="&$B6,$F$5:$F$304,">"&$F$3)-$F$3*COUNTIFS($A$5:$A$304,$A6&"",$B$5:$B$304,">="&($B6-MOD(WEEKDAY($B6)-$B$3,7)),$B$5:$B$304,"<="&$B6,$F$5:$F$304,">"&$F$3))-$D$3))),2)) | J6: =IF(AND($A6="",$C6="",$D6=""),"",IF(OR($C6>=1,$D6>=1),"⚠ type the time with a colon: 9:00 AM, not 9",IF(AND($C6<>"",$C6=$D6),"⚠ clock-in equals clock-out: the shift adds 0 h",IF(AND($C6<>"",$D6<>"",IF($E6="",0,$E6)>MOD($D6-$C6,1)*24),"⚠ the break is longer than the shift",IF(AND($A6<>"",COUNTIF('Monthly OT Summary'!$A$6:$A$35,$A6&"")=0),"⚠ name not in Monthly OT Summary: its hours are not added","")))))
F7: =IF(OR($C7="",$D7=""),"",IF(OR($C7>=1,$D7>=1,$C7=$D7,IF($E7="",0,$E7)>MOD($D7-$C7,1)*24),"",ROUND(MOD($D7-$C7,1)*24-IF($E7="",0,$E7),2))) | G7: 8 | H7: =IF(OR($A7="",$B7="",$F7=""),"",ROUND(IF($F$3="",0,MAX(0,$F7-$F$3))+IF($D$3="",0,MIN($F7-IF($F$3="",0,MAX(0,$F7-$F$3)),MAX(0,SUMIFS($F$5:$F$304,$A$5:$A$304,$A7&"",$B$5:$B$304,">="&($B7-MOD(WEEKDAY($B7)-$B$3,7)),$B$5:$B$304,"<="&$B7)-IF($F$3="",0,SUMIFS($F$5:$F$304,$A$5:$A$304,$A7&"",$B$5:$B$304,">="&($B7-MOD(WEEKDAY($B7)-$B$3,7)),$B$5:$B$304,"<="&$B7,$F$5:$F$304,">"&$F$3)-$F$3*COUNTIFS($A$5:$A$304,$A7&"",$B$5:$B$304,">="&($B7-MOD(WEEKDAY($B7)-$B$3,7)),$B$5:$B$304,"<="&$B7,$F$5:$F$304,">"&$F$3))-$D$3))),2)) | J7: =IF(AND($A7="",$C7="",$D7=""),"",IF(OR($C7>=1,$D7>=1),"⚠ type the time with a colon: 9:00 AM, not 9",IF(AND($C7<>"",$C7=$D7),"⚠ clock-in equals clock-out: the shift adds 0 h",IF(AND($C7<>"",$D7<>"",IF($E7="",0,$E7)>MOD($D7-$C7,1)*24),"⚠ the break is longer than the shift",IF(AND($A7<>"",COUNTIF('Monthly OT Summary'!$A$6:$A$35,$A7&"")=0),"⚠ name not in Monthly OT Summary: its hours are not added","")))))
F8: =IF(OR($C8="",$D8=""),"",IF(OR($C8>=1,$D8>=1,$C8=$D8,IF($E8="",0,$E8)>MOD($D8-$C8,1)*24),"",ROUND(MOD($D8-$C8,1)*24-IF($E8="",0,$E8),2))) | G8: 8 | H8: =IF(OR($A8="",$B8="",$F8=""),"",ROUND(IF($F$3="",0,MAX(0,$F8-$F$3))+IF($D$3="",0,MIN($F8-IF($F$3="",0,MAX(0,$F8-$F$3)),MAX(0,SUMIFS($F$5:$F$304,$A$5:$A$304,$A8&"",$B$5:$B$304,">="&($B8-MOD(WEEKDAY($B8)-$B$3,7)),$B$5:$B$304,"<="&$B8)-IF($F$3="",0,SUMIFS($F$5:$F$304,$A$5:$A$304,$A8&"",$B$5:$B$304,">="&($B8-MOD(WEEKDAY($B8)-$B$3,7)),$B$5:$B$304,"<="&$B8,$F$5:$F$304,">"&$F$3)-$F$3*COUNTIFS($A$5:$A$304,$A8&"",$B$5:$B$304,">="&($B8-MOD(WEEKDAY($B8)-$B$3,7)),$B$5:$B$304,"<="&$B8,$F$5:$F$304,">"&$F$3))-$D$3))),2)) | J8: =IF(AND($A8="",$C8="",$D8=""),"",IF(OR($C8>=1,$D8>=1),"⚠ type the time with a colon: 9:00 AM, not 9",IF(AND($C8<>"",$C8=$D8),"⚠ clock-in equals clock-out: the shift adds 0 h",IF(AND($C8<>"",$D8<>"",IF($E8="",0,$E8)>MOD($D8-$C8,1)*24),"⚠ the break is longer than the shift",IF(AND($A8<>"",COUNTIF('Monthly OT Summary'!$A$6:$A$35,$A8&"")=0),"⚠ name not in Monthly OT Summary: its hours are not added","")))))
F9: =IF(OR($C9="",$D9=""),"",IF(OR($C9>=1,$D9>=1,$C9=$D9,IF($E9="",0,$E9)>MOD($D9-$C9,1)*24),"",ROUND(MOD($D9-$C9,1)*24-IF($E9="",0,$E9),2))) | G9: 8 | H9: =IF(OR($A9="",$B9="",$F9=""),"",ROUND(IF($F$3="",0,MAX(0,$F9-$F$3))+IF($D$3="",0,MIN($F9-IF($F$3="",0,MAX(0,$F9-$F$3)),MAX(0,SUMIFS($F$5:$F$304,$A$5:$A$304,$A9&"",$B$5:$B$304,">="&($B9-MOD(WEEKDAY($B9)-$B$3,7)),$B$5:$B$304,"<="&$B9)-IF($F$3="",0,SUMIFS($F$5:$F$304,$A$5:$A$304,$A9&"",$B$5:$B$304,">="&($B9-MOD(WEEKDAY($B9)-$B$3,7)),$B$5:$B$304,"<="&$B9,$F$5:$F$304,">"&$F$3)-$F$3*COUNTIFS($A$5:$A$304,$A9&"",$B$5:$B$304,">="&($B9-MOD(WEEKDAY($B9)-$B$3,7)),$B$5:$B$304,"<="&$B9,$F$5:$F$304,">"&$F$3))-$D$3))),2)) | J9: =IF(AND($A9="",$C9="",$D9=""),"",IF(OR($C9>=1,$D9>=1),"⚠ type the time with a colon: 9:00 AM, not 9",IF(AND($C9<>"",$C9=$D9),"⚠ clock-in equals clock-out: the shift adds 0 h",IF(AND($C9<>"",$D9<>"",IF($E9="",0,$E9)>MOD($D9-$C9,1)*24),"⚠ the break is longer than the shift",IF(AND($A9<>"",COUNTIF('Monthly OT Summary'!$A$6:$A$35,$A9&"")=0),"⚠ name not in Monthly OT Summary: its hours are not added","")))))
F10: =IF(OR($C10="",$D10=""),"",IF(OR($C10>=1,$D10>=1,$C10=$D10,IF($E10="",0,$E10)>MOD($D10-$C10,1)*24),"",ROUND(MOD($D10-$C10,1)*24-IF($E10="",0,$E10),2))) | G10: 8 | H10: =IF(OR($A10="",$B10="",$F10=""),"",ROUND(IF($F$3="",0,MAX(0,$F10-$F$3))+IF($D$3="",0,MIN($F10-IF($F$3="",0,MAX(0,$F10-$F$3)),MAX(0,SUMIFS($F$5:$F$304,$A$5:$A$304,$A10&"",$B$5:$B$304,">="&($B10-MOD(WEEKDAY($B10)-$B$3,7)),$B$5:$B$304,"<="&$B10)-IF($F$3="",0,SUMIFS($F$5:$F$304,$A$5:$A$304,$A10&"",$B$5:$B$304,">="&($B10-MOD(WEEKDAY($B10)-$B$3,7)),$B$5:$B$304,"<="&$B10,$F$5:$F$304,">"&$F$3)-$F$3*COUNTIFS($A$5:$A$304,$A10&"",$B$5:$B$304,">="&($B10-MOD(WEEKDAY($B10)-$B$3,7)),$B$5:$B$304,"<="&$B10,$F$5:$F$304,">"&$F$3))-$D$3))),2)) | J10: =IF(AND($A10="",$C10="",$D10=""),"",IF(OR($C10>=1,$D10>=1),"⚠ type the time with a colon: 9:00 AM, not 9",IF(AND($C10<>"",$C10=$D10),"⚠ clock-in equals clock-out: the shift adds 0 h",IF(AND($C10<>"",$D10<>"",IF($E10="",0,$E10)>MOD($D10-$C10,1)*24),"⚠ the break is longer than the shift",IF(AND($A10<>"",COUNTIF('Monthly OT Summary'!$A$6:$A$35,$A10&"")=0),"⚠ name not in Monthly OT Summary: its hours are not added","")))))
F11: =IF(OR($C11="",$D11=""),"",IF(OR($C11>=1,$D11>=1,$C11=$D11,IF($E11="",0,$E11)>MOD($D11-$C11,1)*24),"",ROUND(MOD($D11-$C11,1)*24-IF($E11="",0,$E11),2))) | G11: 8 | H11: =IF(OR($A11="",$B11="",$F11=""),"",ROUND(IF($F$3="",0,MAX(0,$F11-$F$3))+IF($D$3="",0,MIN($F11-IF($F$3="",0,MAX(0,$F11-$F$3)),MAX(0,SUMIFS($F$5:$F$304,$A$5:$A$304,$A11&"",$B$5:$B$304,">="&($B11-MOD(WEEKDAY($B11)-$B$3,7)),$B$5:$B$304,"<="&$B11)-IF($F$3="",0,SUMIFS($F$5:$F$304,$A$5:$A$304,$A11&"",$B$5:$B$304,">="&($B11-MOD(WEEKDAY($B11)-$B$3,7)),$B$5:$B$304,"<="&$B11,$F$5:$F$304,">"&$F$3)-$F$3*COUNTIFS($A$5:$A$304,$A11&"",$B$5:$B$304,">="&($B11-MOD(WEEKDAY($B11)-$B$3,7)),$B$5:$B$304,"<="&$B11,$F$5:$F$304,">"&$F$3))-$D$3))),2)) | J11: =IF(AND($A11="",$C11="",$D11=""),"",IF(OR($C11>=1,$D11>=1),"⚠ type the time with a colon: 9:00 AM, not 9",IF(AND($C11<>"",$C11=$D11),"⚠ clock-in equals clock-out: the shift adds 0 h",IF(AND($C11<>"",$D11<>"",IF($E11="",0,$E11)>MOD($D11-$C11,1)*24),"⚠ the break is longer than the shift",IF(AND($A11<>"",COUNTIF('Monthly OT Summary'!$A$6:$A$35,$A11&"")=0),"⚠ name not in Monthly OT Summary: its hours are not added","")))))
F12: =IF(OR($C12="",$D12=""),"",IF(OR($C12>=1,$D12>=1,$C12=$D12,IF($E12="",0,$E12)>MOD($D12-$C12,1)*24),"",ROUND(MOD($D12-$C12,1)*24-IF($E12="",0,$E12),2))) | G12: 8 | H12: =IF(OR($A12="",$B12="",$F12=""),"",ROUND(IF($F$3="",0,MAX(0,$F12-$F$3))+IF($D$3="",0,MIN($F12-IF($F$3="",0,MAX(0,$F12-$F$3)),MAX(0,SUMIFS($F$5:$F$304,$A$5:$A$304,$A12&"",$B$5:$B$304,">="&($B12-MOD(WEEKDAY($B12)-$B$3,7)),$B$5:$B$304,"<="&$B12)-IF($F$3="",0,SUMIFS($F$5:$F$304,$A$5:$A$304,$A12&"",$B$5:$B$304,">="&($B12-MOD(WEEKDAY($B12)-$B$3,7)),$B$5:$B$304,"<="&$B12,$F$5:$F$304,">"&$F$3)-$F$3*COUNTIFS($A$5:$A$304,$A12&"",$B$5:$B$304,">="&($B12-MOD(WEEKDAY($B12)-$B$3,7)),$B$5:$B$304,"<="&$B12,$F$5:$F$304,">"&$F$3))-$D$3))),2)) | J12: =IF(AND($A12="",$C12="",$D12=""),"",IF(OR($C12>=1,$D12>=1),"⚠ type the time with a colon: 9:00 AM, not 9",IF(AND($C12<>"",$C12=$D12),"⚠ clock-in equals clock-out: the shift adds 0 h",IF(AND($C12<>"",$D12<>"",IF($E12="",0,$E12)>MOD($D12-$C12,1)*24),"⚠ the break is longer than the shift",IF(AND($A12<>"",COUNTIF('Monthly OT Summary'!$A$6:$A$35,$A12&"")=0),"⚠ name not in Monthly OT Summary: its hours are not added","")))))
F13: =IF(OR($C13="",$D13=""),"",IF(OR($C13>=1,$D13>=1,$C13=$D13,IF($E13="",0,$E13)>MOD($D13-$C13,1)*24),"",ROUND(MOD($D13-$C13,1)*24-IF($E13="",0,$E13),2))) | G13: 8 | H13: =IF(OR($A13="",$B13="",$F13=""),"",ROUND(IF($F$3="",0,MAX(0,$F13-$F$3))+IF($D$3="",0,MIN($F13-IF($F$3="",0,MAX(0,$F13-$F$3)),MAX(0,SUMIFS($F$5:$F$304,$A$5:$A$304,$A13&"",$B$5:$B$304,">="&($B13-MOD(WEEKDAY($B13)-$B$3,7)),$B$5:$B$304,"<="&$B13)-IF($F$3="",0,SUMIFS($F$5:$F$304,$A$5:$A$304,$A13&"",$B$5:$B$304,">="&($B13-MOD(WEEKDAY($B13)-$B$3,7)),$B$5:$B$304,"<="&$B13,$F$5:$F$304,">"&$F$3)-$F$3*COUNTIFS($A$5:$A$304,$A13&"",$B$5:$B$304,">="&($B13-MOD(WEEKDAY($B13)-$B$3,7)),$B$5:$B$304,"<="&$B13,$F$5:$F$304,">"&$F$3))-$D$3))),2)) | J13: =IF(AND($A13="",$C13="",$D13=""),"",IF(OR($C13>=1,$D13>=1),"⚠ type the time with a colon: 9:00 AM, not 9",IF(AND($C13<>"",$C13=$D13),"⚠ clock-in equals clock-out: the shift adds 0 h",IF(AND($C13<>"",$D13<>"",IF($E13="",0,$E13)>MOD($D13-$C13,1)*24),"⚠ the break is longer than the shift",IF(AND($A13<>"",COUNTIF('Monthly OT Summary'!$A$6:$A$35,$A13&"")=0),"⚠ name not in Monthly OT Summary: its hours are not added","")))))
F14: =IF(OR($C14="",$D14=""),"",IF(OR($C14>=1,$D14>=1,$C14=$D14,IF($E14="",0,$E14)>MOD($D14-$C14,1)*24),"",ROUND(MOD($D14-$C14,1)*24-IF($E14="",0,$E14),2))) | G14: 8 | H14: =IF(OR($A14="",$B14="",$F14=""),"",ROUND(IF($F$3="",0,MAX(0,$F14-$F$3))+IF($D$3="",0,MIN($F14-IF($F$3="",0,MAX(0,$F14-$F$3)),MAX(0,SUMIFS($F$5:$F$304,$A$5:$A$304,$A14&"",$B$5:$B$304,">="&($B14-MOD(WEEKDAY($B14)-$B$3,7)),$B$5:$B$304,"<="&$B14)-IF($F$3="",0,SUMIFS($F$5:$F$304,$A$5:$A$304,$A14&"",$B$5:$B$304,">="&($B14-MOD(WEEKDAY($B14)-$B$3,7)),$B$5:$B$304,"<="&$B14,$F$5:$F$304,">"&$F$3)-$F$3*COUNTIFS($A$5:$A$304,$A14&"",$B$5:$B$304,">="&($B14-MOD(WEEKDAY($B14)-$B$3,7)),$B$5:$B$304,"<="&$B14,$F$5:$F$304,">"&$F$3))-$D$3))),2)) | J14: =IF(AND($A14="",$C14="",$D14=""),"",IF(OR($C14>=1,$D14>=1),"⚠ type the time with a colon: 9:00 AM, not 9",IF(AND($C14<>"",$C14=$D14),"⚠ clock-in equals clock-out: the shift adds 0 h",IF(AND($C14<>"",$D14<>"",IF($E14="",0,$E14)>MOD($D14-$C14,1)*24),"⚠ the break is longer than the shift",IF(AND($A14<>"",COUNTIF('Monthly OT Summary'!$A$6:$A$35,$A14&"")=0),"⚠ name not in Monthly OT Summary: its hours are not added","")))))
F15: =IF(OR($C15="",$D15=""),"",IF(OR($C15>=1,$D15>=1,$C15=$D15,IF($E15="",0,$E15)>MOD($D15-$C15,1)*24),"",ROUND(MOD($D15-$C15,1)*24-IF($E15="",0,$E15),2))) | G15: 8 | H15: =IF(OR($A15="",$B15="",$F15=""),"",ROUND(IF($F$3="",0,MAX(0,$F15-$F$3))+IF($D$3="",0,MIN($F15-IF($F$3="",0,MAX(0,$F15-$F$3)),MAX(0,SUMIFS($F$5:$F$304,$A$5:$A$304,$A15&"",$B$5:$B$304,">="&($B15-MOD(WEEKDAY($B15)-$B$3,7)),$B$5:$B$304,"<="&$B15)-IF($F$3="",0,SUMIFS($F$5:$F$304,$A$5:$A$304,$A15&"",$B$5:$B$304,">="&($B15-MOD(WEEKDAY($B15)-$B$3,7)),$B$5:$B$304,"<="&$B15,$F$5:$F$304,">"&$F$3)-$F$3*COUNTIFS($A$5:$A$304,$A15&"",$B$5:$B$304,">="&($B15-MOD(WEEKDAY($B15)-$B$3,7)),$B$5:$B$304,"<="&$B15,$F$5:$F$304,">"&$F$3))-$D$3))),2)) | J15: =IF(AND($A15="",$C15="",$D15=""),"",IF(OR($C15>=1,$D15>=1),"⚠ type the time with a colon: 9:00 AM, not 9",IF(AND($C15<>"",$C15=$D15),"⚠ clock-in equals clock-out: the shift adds 0 h",IF(AND($C15<>"",$D15<>"",IF($E15="",0,$E15)>MOD($D15-$C15,1)*24),"⚠ the break is longer than the shift",IF(AND($A15<>"",COUNTIF('Monthly OT Summary'!$A$6:$A$35,$A15&"")=0),"⚠ name not in Monthly OT Summary: its hours are not added","")))))
F16: =IF(OR($C16="",$D16=""),"",IF(OR($C16>=1,$D16>=1,$C16=$D16,IF($E16="",0,$E16)>MOD($D16-$C16,1)*24),"",ROUND(MOD($D16-$C16,1)*24-IF($E16="",0,$E16),2))) | G16: 8 | H16: =IF(OR($A16="",$B16="",$F16=""),"",ROUND(IF($F$3="",0,MAX(0,$F16-$F$3))+IF($D$3="",0,MIN($F16-IF($F$3="",0,MAX(0,$F16-$F$3)),MAX(0,SUMIFS($F$5:$F$304,$A$5:$A$304,$A16&"",$B$5:$B$304,">="&($B16-MOD(WEEKDAY($B16)-$B$3,7)),$B$5:$B$304,"<="&$B16)-IF($F$3="",0,SUMIFS($F$5:$F$304,$A$5:$A$304,$A16&"",$B$5:$B$304,">="&($B16-MOD(WEEKDAY($B16)-$B$3,7)),$B$5:$B$304,"<="&$B16,$F$5:$F$304,">"&$F$3)-$F$3*COUNTIFS($A$5:$A$304,$A16&"",$B$5:$B$304,">="&($B16-MOD(WEEKDAY($B16)-$B$3,7)),$B$5:$B$304,"<="&$B16,$F$5:$F$304,">"&$F$3))-$D$3))),2)) | J16: =IF(AND($A16="",$C16="",$D16=""),"",IF(OR($C16>=1,$D16>=1),"⚠ type the time with a colon: 9:00 AM, not 9",IF(AND($C16<>"",$C16=$D16),"⚠ clock-in equals clock-out: the shift adds 0 h",IF(AND($C16<>"",$D16<>"",IF($E16="",0,$E16)>MOD($D16-$C16,1)*24),"⚠ the break is longer than the shift",IF(AND($A16<>"",COUNTIF('Monthly OT Summary'!$A$6:$A$35,$A16&"")=0),"⚠ name not in Monthly OT Summary: its hours are not added","")))))
... F304: =IF(OR($C304="",$D304=""),"",IF(OR($C304>=1,$D304>=1,$C304=$D304,IF($E304="",0,$E304)>MOD($D304-$C304,1)*24),"",ROUND(MOD($D304-$C304,1)*24-IF($E304="",0,$E304),2))) | G304: 8 | H304: =IF(OR($A304="",$B304="",$F304=""),"",ROUND(IF($F$3="",0,MAX(0,$F304-$F$3))+IF($D$3="",0,MIN($F304-IF($F$3="",0,MAX(0,$F304-$F$3)),MAX(0,SUMIFS($F$5:$F$304,$A$5:$A$304,$A304&"",$B$5:$B$304,">="&($B304-MOD(WEEKDAY($B304)-$B$3,7)),$B$5:$B$304,"<="&$B304)-IF($F$3="",0,SUMIFS($F$5:$F$304,$A$5:$A$304,$A304&"",$B$5:$B$304,">="&($B304-MOD(WEEKDAY($B304)-$B$3,7)),$B$5:$B$304,"<="&$B304,$F$5:$F$304,">"&$F$3)-$F$3*COUNTIFS($A$5:$A$304,$A304&"",$B$5:$B$304,">="&($B304-MOD(WEEKDAY($B304)-$B$3,7)),$B$5:$B$304,"<="&$B304,$F$5:$F$304,">"&$F$3))-$D$3))),2)) | J304: =IF(AND($A304="",$C304="",$D304=""),"",IF(OR($C304>=1,$D304>=1),"⚠ type the time with a colon: 9:00 AM, not 9",IF(AND($C304<>"",$C304=$D304),"⚠ clock-in equals clock-out: the shift adds 0 h",IF(AND($C304<>"",$D304<>"",IF($E304="",0,$E304)>MOD($D304-$C304,1)*24),"⚠ the break is longer than the shift",IF(AND($A304<>"",COUNTIF('Monthly OT Summary'!$A$6:$A$35,$A304&"")=0),"⚠ name not in Monthly OT Summary: its hours are not added","")))))
A306: © 2026 AI Chef Pro · aichef.pro

Sheet Monthly OT Summary
A1: Overtime Summary — Workweeks in this copy
A2: AI Chef Pro · aichef.pro — Restaurant Staff Scheduling Kit Pro
A3: Hourly rate for the OT cost estimate: | B3: 15 | C3: Overtime multiplier (FLSA: 1.5×): | D3: 1.5 | E3: Annual OT budget per person (h): | F3: 80
A5: Employee | B5: Total OT hours (this copy) | C5: Unapproved OT hours (still payable) | D5: Approved OT hours | E5: OT hours year to date | F5: Status vs. annual OT budget | G5: Overtime cost | H5: Worked − scheduled hours (this copy)
B6: =IF($A6="","",ROUND(SUMIF('Time Log'!$A$5:$A$304,$A6&"",'Time Log'!$H$5:$H$304),2)) | C6: =IF($A6="","",ROUND(SUMIFS('Time Log'!$H$5:$H$304,'Time Log'!$A$5:$A$304,$A6&"",'Time Log'!$I$5:$I$304,"Not approved"),2)) | D6: =IF($A6="","",ROUND($B6-$C6,2)) | F6: =IF($E6="","",IF($E6>$F$3,"⛔ OVER BUDGET ("&TEXT($E6-$F$3,"0")&" h)",IF($E6>$F$3*0.8,"⚠ near budget","✓ within budget"))) | G6: =IF($B6="","",ROUND($B6*$B$3*$D$3,2)) | H6: =IF($A6="","",IF(COUNTIF('Time Log'!$A$5:$A$304,$A6&"")=0,"",ROUND(SUMIF('Time Log'!$A$5:$A$304,$A6&"",'Time Log'!$F$5:$F$304)-SUMIF('Time Log'!$A$5:$A$304,$A6&"",'Time Log'!$G$5:$G$304),2)))
B7: =IF($A7="","",ROUND(SUMIF('Time Log'!$A$5:$A$304,$A7&"",'Time Log'!$H$5:$H$304),2)) | C7: =IF($A7="","",ROUND(SUMIFS('Time Log'!$H$5:$H$304,'Time Log'!$A$5:$A$304,$A7&"",'Time Log'!$I$5:$I$304,"Not approved"),2)) | D7: =IF($A7="","",ROUND($B7-$C7,2)) | F7: =IF($E7="","",IF($E7>$F$3,"⛔ OVER BUDGET ("&TEXT($E7-$F$3,"0")&" h)",IF($E7>$F$3*0.8,"⚠ near budget","✓ within budget"))) | G7: =IF($B7="","",ROUND($B7*$B$3*$D$3,2)) | H7: =IF($A7="","",IF(COUNTIF('Time Log'!$A$5:$A$304,$A7&"")=0,"",ROUND(SUMIF('Time Log'!$A$5:$A$304,$A7&"",'Time Log'!$F$5:$F$304)-SUMIF('Time Log'!$A$5:$A$304,$A7&"",'Time Log'!$G$5:$G$304),2)))
B8: =IF($A8="","",ROUND(SUMIF('Time Log'!$A$5:$A$304,$A8&"",'Time Log'!$H$5:$H$304),2)) | C8: =IF($A8="","",ROUND(SUMIFS('Time Log'!$H$5:$H$304,'Time Log'!$A$5:$A$304,$A8&"",'Time Log'!$I$5:$I$304,"Not approved"),2)) | D8: =IF($A8="","",ROUND($B8-$C8,2)) | F8: =IF($E8="","",IF($E8>$F$3,"⛔ OVER BUDGET ("&TEXT($E8-$F$3,"0")&" h)",IF($E8>$F$3*0.8,"⚠ near budget","✓ within budget"))) | G8: =IF($B8="","",ROUND($B8*$B$3*$D$3,2)) | H8: =IF($A8="","",IF(COUNTIF('Time Log'!$A$5:$A$304,$A8&"")=0,"",ROUND(SUMIF('Time Log'!$A$5:$A$304,$A8&"",'Time Log'!$F$5:$F$304)-SUMIF('Time Log'!$A$5:$A$304,$A8&"",'Time Log'!$G$5:$G$304),2)))
B9: =IF($A9="","",ROUND(SUMIF('Time Log'!$A$5:$A$304,$A9&"",'Time Log'!$H$5:$H$304),2)) | C9: =IF($A9="","",ROUND(SUMIFS('Time Log'!$H$5:$H$304,'Time Log'!$A$5:$A$304,$A9&"",'Time Log'!$I$5:$I$304,"Not approved"),2)) | D9: =IF($A9="","",ROUND($B9-$C9,2)) | F9: =IF($E9="","",IF($E9>$F$3,"⛔ OVER BUDGET ("&TEXT($E9-$F$3,"0")&" h)",IF($E9>$F$3*0.8,"⚠ near budget","✓ within budget"))) | G9: =IF($B9="","",ROUND($B9*$B$3*$D$3,2)) | H9: =IF($A9="","",IF(COUNTIF('Time Log'!$A$5:$A$304,$A9&"")=0,"",ROUND(SUMIF('Time Log'!$A$5:$A$304,$A9&"",'Time Log'!$F$5:$F$304)-SUMIF('Time Log'!$A$5:$A$304,$A9&"",'Time Log'!$G$5:$G$304),2)))
B10: =IF($A10="","",ROUND(SUMIF('Time Log'!$A$5:$A$304,$A10&"",'Time Log'!$H$5:$H$304),2)) | C10: =IF($A10="","",ROUND(SUMIFS('Time Log'!$H$5:$H$304,'Time Log'!$A$5:$A$304,$A10&"",'Time Log'!$I$5:$I$304,"Not approved"),2)) | D10: =IF($A10="","",ROUND($B10-$C10,2)) | F10: =IF($E10="","",IF($E10>$F$3,"⛔ OVER BUDGET ("&TEXT($E10-$F$3,"0")&" h)",IF($E10>$F$3*0.8,"⚠ near budget","✓ within budget"))) | G10: =IF($B10="","",ROUND($B10*$B$3*$D$3,2)) | H10: =IF($A10="","",IF(COUNTIF('Time Log'!$A$5:$A$304,$A10&"")=0,"",ROUND(SUMIF('Time Log'!$A$5:$A$304,$A10&"",'Time Log'!$F$5:$F$304)-SUMIF('Time Log'!$A$5:$A$304,$A10&"",'Time Log'!$G$5:$G$304),2)))
B11: =IF($A11="","",ROUND(SUMIF('Time Log'!$A$5:$A$304,$A11&"",'Time Log'!$H$5:$H$304),2)) | C11: =IF($A11="","",ROUND(SUMIFS('Time Log'!$H$5:$H$304,'Time Log'!$A$5:$A$304,$A11&"",'Time Log'!$I$5:$I$304,"Not approved"),2)) | D11: =IF($A11="","",ROUND($B11-$C11,2)) | F11: =IF($E11="","",IF($E11>$F$3,"⛔ OVER BUDGET ("&TEXT($E11-$F$3,"0")&" h)",IF($E11>$F$3*0.8,"⚠ near budget","✓ within budget"))) | G11: =IF($B11="","",ROUND($B11*$B$3*$D$3,2)) | H11: =IF($A11="","",IF(COUNTIF('Time Log'!$A$5:$A$304,$A11&"")=0,"",ROUND(SUMIF('Time Log'!$A$5:$A$304,$A11&"",'Time Log'!$F$5:$F$304)-SUMIF('Time Log'!$A$5:$A$304,$A11&"",'Time Log'!$G$5:$G$304),2)))
B12: =IF($A12="","",ROUND(SUMIF('Time Log'!$A$5:$A$304,$A12&"",'Time Log'!$H$5:$H$304),2)) | C12: =IF($A12="","",ROUND(SUMIFS('Time Log'!$H$5:$H$304,'Time Log'!$A$5:$A$304,$A12&"",'Time Log'!$I$5:$I$304,"Not approved"),2)) | D12: =IF($A12="","",ROUND($B12-$C12,2)) | F12: =IF($E12="","",IF($E12>$F$3,"⛔ OVER BUDGET ("&TEXT($E12-$F$3,"0")&" h)",IF($E12>$F$3*0.8,"⚠ near budget","✓ within budget"))) | G12: =IF($B12="","",ROUND($B12*$B$3*$D$3,2)) | H12: =IF($A12="","",IF(COUNTIF('Time Log'!$A$5:$A$304,$A12&"")=0,"",ROUND(SUMIF('Time Log'!$A$5:$A$304,$A12&"",'Time Log'!$F$5:$F$304)-SUMIF('Time Log'!$A$5:$A$304,$A12&"",'Time Log'!$G$5:$G$304),2)))
B13: =IF($A13="","",ROUND(SUMIF('Time Log'!$A$5:$A$304,$A13&"",'Time Log'!$H$5:$H$304),2)) | C13: =IF($A13="","",ROUND(SUMIFS('Time Log'!$H$5:$H$304,'Time Log'!$A$5:$A$304,$A13&"",'Time Log'!$I$5:$I$304,"Not approved"),2)) | D13: =IF($A13="","",ROUND($B13-$C13,2)) | F13: =IF($E13="","",IF($E13>$F$3,"⛔ OVER BUDGET ("&TEXT($E13-$F$3,"0")&" h)",IF($E13>$F$3*0.8,"⚠ near budget","✓ within budget"))) | G13: =IF($B13="","",ROUND($B13*$B$3*$D$3,2)) | H13: =IF($A13="","",IF(COUNTIF('Time Log'!$A$5:$A$304,$A13&"")=0,"",ROUND(SUMIF('Time Log'!$A$5:$A$304,$A13&"",'Time Log'!$F$5:$F$304)-SUMIF('Time Log'!$A$5:$A$304,$A13&"",'Time Log'!$G$5:$G$304),2)))
B14: =IF($A14="","",ROUND(SUMIF('Time Log'!$A$5:$A$304,$A14&"",'Time Log'!$H$5:$H$304),2)) | C14: =IF($A14="","",ROUND(SUMIFS('Time Log'!$H$5:$H$304,'Time Log'!$A$5:$A$304,$A14&"",'Time Log'!$I$5:$I$304,"Not approved"),2)) | D14: =IF($A14="","",ROUND($B14-$C14,2)) | F14: =IF($E14="","",IF($E14>$F$3,"⛔ OVER BUDGET ("&TEXT($E14-$F$3,"0")&" h)",IF($E14>$F$3*0.8,"⚠ near budget","✓ within budget"))) | G14: =IF($B14="","",ROUND($B14*$B$3*$D$3,2)) | H14: =IF($A14="","",IF(COUNTIF('Time Log'!$A$5:$A$304,$A14&"")=0,"",ROUND(SUMIF('Time Log'!$A$5:$A$304,$A14&"",'Time Log'!$F$5:$F$304)-SUMIF('Time Log'!$A$5:$A$304,$A14&"",'Time Log'!$G$5:$G$304),2)))
B15: =IF($A15="","",ROUND(SUMIF('Time Log'!$A$5:$A$304,$A15&"",'Time Log'!$H$5:$H$304),2)) | C15: =IF($A15="","",ROUND(SUMIFS('Time Log'!$H$5:$H$304,'Time Log'!$A$5:$A$304,$A15&"",'Time Log'!$I$5:$I$304,"Not approved"),2)) | D15: =IF($A15="","",ROUND($B15-$C15,2)) | F15: =IF($E15="","",IF($E15>$F$3,"⛔ OVER BUDGET ("&TEXT($E15-$F$3,"0")&" h)",IF($E15>$F$3*0.8,"⚠ near budget","✓ within budget"))) | G15: =IF($B15="","",ROUND($B15*$B$3*$D$3,2)) | H15: =IF($A15="","",IF(COUNTIF('Time Log'!$A$5:$A$304,$A15&"")=0,"",ROUND(SUMIF('Time Log'!$A$5:$A$304,$A15&"",'Time Log'!$F$5:$F$304)-SUMIF('Time Log'!$A$5:$A$304,$A15&"",'Time Log'!$G$5:$G$304),2)))
B16: =IF($A16="","",ROUND(SUMIF('Time Log'!$A$5:$A$304,$A16&"",'Time Log'!$H$5:$H$304),2)) | C16: =IF($A16="","",ROUND(SUMIFS('Time Log'!$H$5:$H$304,'Time Log'!$A$5:$A$304,$A16&"",'Time Log'!$I$5:$I$304,"Not approved"),2)) | D16: =IF($A16="","",ROUND($B16-$C16,2)) | F16: =IF($E16="","",IF($E16>$F$3,"⛔ OVER BUDGET ("&TEXT($E16-$F$3,"0")&" h)",IF($E16>$F$3*0.8,"⚠ near budget","✓ within budget"))) | G16: =IF($B16="","",ROUND($B16*$B$3*$D$3,2)) | H16: =IF($A16="","",IF(COUNTIF('Time Log'!$A$5:$A$304,$A16&"")=0,"",ROUND(SUMIF('Time Log'!$A$5:$A$304,$A16&"",'Time Log'!$F$5:$F$304)-SUMIF('Time Log'!$A$5:$A$304,$A16&"",'Time Log'!$G$5:$G$304),2)))
B17: =IF($A17="","",ROUND(SUMIF('Time Log'!$A$5:$A$304,$A17&"",'Time Log'!$H$5:$H$304),2)) | C17: =IF($A17="","",ROUND(SUMIFS('Time Log'!$H$5:$H$304,'Time Log'!$A$5:$A$304,$A17&"",'Time Log'!$I$5:$I$304,"Not approved"),2)) | D17: =IF($A17="","",ROUND($B17-$C17,2)) | F17: =IF($E17="","",IF($E17>$F$3,"⛔ OVER BUDGET ("&TEXT($E17-$F$3,"0")&" h)",IF($E17>$F$3*0.8,"⚠ near budget","✓ within budget"))) | G17: =IF($B17="","",ROUND($B17*$B$3*$D$3,2)) | H17: =IF($A17="","",IF(COUNTIF('Time Log'!$A$5:$A$304,$A17&"")=0,"",ROUND(SUMIF('Time Log'!$A$5:$A$304,$A17&"",'Time Log'!$F$5:$F$304)-SUMIF('Time Log'!$A$5:$A$304,$A17&"",'Time Log'!$G$5:$G$304),2)))
... B35: =IF($A35="","",ROUND(SUMIF('Time Log'!$A$5:$A$304,$A35&"",'Time Log'!$H$5:$H$304),2)) | C35: =IF($A35="","",ROUND(SUMIFS('Time Log'!$H$5:$H$304,'Time Log'!$A$5:$A$304,$A35&"",'Time Log'!$I$5:$I$304,"Not approved"),2)) | D35: =IF($A35="","",ROUND($B35-$C35,2)) | F35: =IF($E35="","",IF($E35>$F$3,"⛔ OVER BUDGET ("&TEXT($E35-$F$3,"0")&" h)",IF($E35>$F$3*0.8,"⚠ near budget","✓ within budget"))) | G35: =IF($B35="","",ROUND($B35*$B$3*$D$3,2)) | H35: =IF($A35="","",IF(COUNTIF('Time Log'!$A$5:$A$304,$A35&"")=0,"",ROUND(SUMIF('Time Log'!$A$5:$A$304,$A35&"",'Time Log'!$F$5:$F$304)-SUMIF('Time Log'!$A$5:$A$304,$A35&"",'Time Log'!$G$5:$G$304),2)))
A37: TOTALS | B37: =IF(COUNT(B6:B35)=0,"",ROUND(SUM(B6:B35),2)) | C37: =IF(COUNT(C6:C35)=0,"",ROUND(SUM(C6:C35),2)) | D37: =IF(COUNT(D6:D35)=0,"",ROUND(SUM(D6:D35),2)) | G37: =IF(COUNT(G6:G35)=0,"",ROUND(SUM(G6:G35),2)) | H37: =IF(COUNT(H6:H35)=0,"",ROUND(SUM(H6:H35),2))
A39: © 2026 AI Chef Pro · aichef.pro
