Workbook

Sheet Calculadora
A1: CALCULADORA DE PRECIOS DE PARRILLADA Y ASADO PARA EVENTOS — DE LA CARNE AL PRESUPUESTO
A2: Escribe sólo en las celdas VERDES: todo lo demás se calcula. Importes sin IVA salvo donde la fila diga lo contrario. Los valores por defecto son estimaciones del kit: cámbialos por los tuyos.
A4: DATOS DEL EVENTO | B4: Valor | C4: Notas
A5: Cliente | B5: Particular | C5: Particular, Empresa o Ayuntamiento: cambian el margen objetivo, el cobro y los tramos de cancelación (tabla del final). Las comisiones de fiestas y las peñas cuentan como Empresa.
A6: Invitados previstos | B6: 100 | C6: Número entero de invitados a los que sirves.
A7: Formato del servicio | B7: Asado completo | C7: Fija los gramos de carne cruda por invitado con la tabla del final. No cambia el precio: la materia prima de la experiencia ya trae su carta habitual.
A8: Experiencia | B8: 01 Asado argentino | C8: Las 10 experiencias del kit y la chuletada de fiesta: fijan la materia prima por invitado con la tabla del final.
A9: Estilo de servicio | B9: Cortes en mesa | C9: Buffet: un parrillero por cada 60-80 invitados. Cortes en mesa: uno por cada 40-50.
A10: Bebida por invitado (coste) | B10: 4 | C10: Cerveza, refrescos y vino que pones tú. 0 si la bebida la pone el cliente.
A11: Coste de menaje, desechables y consumibles por invitado | B11: 0.6 | C11: Estimación del kit: platos y cubiertos compostables, aluminio, pan y hielo. Pon 0 si el cliente pone el menaje.
A12: Horas por persona (carga, viaje, montaje, brasa, servicio y recogida) | B12: 9 | C12: Estimación del kit: pon las horas reales de tu equipo.
A13: Coste bruto por hora del personal | B13: 13 | C13: Estimación del kit. Copia tu convenio provincial de hostelería.
A14: Seguridad Social a cargo de la empresa | B14: 0.33 | C14: 30,65 % de contingencias, desempleo, FOGASA, formación y MEI, más AT/EP (fijos discontinuos, art. 16 ET).
A15: Importe de alquileres repercutidos (carpa, mesas, sillas, parrilla extra) | B15: 400 | C15: Lo que te cobra el alquilador para este evento. Si lo facturas aparte sin ser accesorio, ese importe va al 21 % de IVA.
A16: Kilómetros de ida (cocina de apoyo → espacio) | B16: 35 | C16: Se cobran ida y vuelta, en una línea aparte.
A17: Tarifa por kilómetro de desplazamiento | B17: 0.95 | C17: La del contrato del kit: se cobra ida y vuelta y va sin margen.
A18: Importe del suplemento de show de fuego por invitado | B18: 0 | C18: De 8 a 15 € por invitado si abres con provoletas y chorizos flambeados a la vista (experiencia 09). 0 si no hay show. Se suma al precio sin margen objetivo: cubre su materia prima extra y el tiempo del parrillero.
A19: IVA del servicio de comidas | B19: 0.1 | C19: Ley 37/1992, art. 91.Uno.2.2.º: comida y bebida para consumir en el acto, alcohol incluido. Lo que facturas aparte sin ser accesorio (carpa, mobiliario) va al 21 %.
A21: CÁLCULO | B21: Valor | C21: Notas
A22: Carne cruda por invitado (g, de la tabla) | B22: =INDEX('Calculadora'!$B$72:$B$75,MATCH($B$7,'Calculadora'!$A$72:$A$75,0)) -> 500 | C22: Busca el formato en la tabla del final.
A23: Coste de materia prima por invitado de la experiencia (tabla) | B23: =INDEX('Calculadora'!$B$78:$B$88,MATCH($B$8,'Calculadora'!$A$78:$A$88,0)) -> 9.5 | C23: Busca la experiencia en la tabla del final. Cámbiala si tu escandallo es otro.
A24: Invitados por parrillero (del estilo de servicio) | B24: =INDEX('Calculadora'!$B$67:$B$69,MATCH($B$9,'Calculadora'!$A$67:$A$69,0)) -> 45
A25: Invitados por ayudante (del estilo de servicio) | B25: =INDEX('Calculadora'!$C$67:$C$69,MATCH($B$9,'Calculadora'!$A$67:$A$69,0)) -> 50
A26: Margen objetivo del cliente elegido | B26: =INDEX('Calculadora'!$B$91:$D$91,MATCH($B$5,'Calculadora'!$B$90:$D$90,0)) -> 0.42 | C26: De la tabla por cliente del final.
A27: Carne cruda total (kg) | B27: =$B$6*$B$22/1000 -> 50 | C27: Invitados × gramos por invitado.
A28: Carne servida total (kg) | B28: =$B$27*(1-'Calculadora'!$B$63) -> 35 | C28: Carne cruda menos la merma de cocción.
A29: Parrillas necesarias | B29: =MAX(1,ROUNDUP($B$27/'Calculadora'!$B$60,0)) -> 2 | C29: Carne cruda entre lo que asa una parrilla de 120 × 60 cm, hacia arriba. Si no las tienes, alquílalas.
A30: Parrilleros necesarios | B30: =MAX(1,ROUNDUP($B$6/$B$24,0)) -> 3 | C30: Invitados entre invitados por parrillero, hacia arriba.
A31: Ayudantes necesarios | B31: =IF($B$6<'Calculadora'!$B$64,0,ROUNDUP($B$6/$B$25,0)) -> 2 | C31: Desde el mínimo de invitados de la tabla; el resto, invitados entre invitados por ayudante, hacia arriba.
A32: Carbón total (kg) | B32: =$B$27*'Calculadora'!$B$61 -> 40 | C32: Kg de carne cruda × kg de carbón por kg de carne.
A33: Coste de materia prima | B33: =$B$23*$B$6 -> 950
A34: Coste de bebida | B34: =$B$10*$B$6 -> 400
A35: Coste de menaje, desechables y consumibles | B35: =$B$11*$B$6 -> 60
A36: Coste del carbón | B36: =$B$32*'Calculadora'!$B$62 -> 60
A37: Coste de personal (salario + Seguridad Social) | B37: =($B$30+$B$31)*$B$12*$B$13*(1+$B$14) -> 778.05 | C37: Parrilleros y ayudantes. Si el dueño cocina, se cuenta a precio de hora: es su coste de oportunidad.
A38: Importe de alquileres | B38: =$B$15 -> 400
A39: Coste directo total | B39: =$B$33+$B$34+$B$35+$B$36+$B$37+$B$38 -> 2648.05
A40: Coste directo por invitado | B40: =$B$39/$B$6 -> 26.4805
A41: PRECIO POR INVITADO SIN IVA | B41: =ROUNDUP($B$39/(1-$B$26)/$B$6*2,0)/2+$B$18 -> 46 | C41: Coste ÷ (1 − margen) ÷ invitados, redondeado a los 0,50 € de arriba, más el suplemento de show. Es el precio de las empresas («+ IVA»).
A42: PRECIO POR INVITADO CON IVA | B42: =$B$41*(1+$B$19) -> 50.6 | C42: Es el que ve un particular: en una oferta a consumidores el precio va con impuestos incluidos.
A43: Subtotal de comida sin IVA | B43: =$B$41*$B$6 -> 4600 | C43: Precio por invitado × invitados.
A44: Desplazamiento (ida y vuelta, sin margen) | B44: =$B$16*2*$B$17 -> 66.5 | C44: Línea aparte del presupuesto.
A45: Base imponible | B45: =$B$43+$B$44 -> 4666.5
A46: IVA | B46: =$B$45*$B$19 -> 466.65
A47: TOTAL DEL PRESUPUESTO (con IVA) | B47: =$B$45+$B$46 -> 5133.15
A48: Importe del cobro 1: señal al firmar | B48: =$B$47*INDEX('Calculadora'!$B$92:$D$92,MATCH($B$5,'Calculadora'!$B$90:$D$90,0)) -> 1539.945 | C48: Con la firma del contrato; en un ayuntamiento, nada.
A49: Importe del cobro 2: a siete días del evento | B49: =$B$47*INDEX('Calculadora'!$B$93:$D$93,MATCH($B$5,'Calculadora'!$B$90:$D$90,0)) -> 2053.26 | C49: Sólo el contrato Particular.
A50: Importe del cobro 3: a las 48 horas del evento | B50: =$B$47*INDEX('Calculadora'!$B$94:$D$94,MATCH($B$5,'Calculadora'!$B$90:$D$90,0)) -> 1539.945 | C50: Sólo el contrato Particular.
A51: Importe del cobro 4: a 30 días de la factura | B51: =$B$47*INDEX('Calculadora'!$B$95:$D$95,MATCH($B$5,'Calculadora'!$B$90:$D$90,0)) -> 0 | C51: Empresa: el resto. Ayuntamiento: todo, desde la conformidad. Factura de cada pago, también de la señal.
A52: Margen bruto en euros | B52: =$B$43-$B$39 -> 1951.95 | C52: Sobre el subtotal de comida, sin el desplazamiento.
A53: Margen bruto (calculado) | B53: =IF($B$43=0,0,$B$52/$B$43) -> 0.42433696 | C53: Sale de los costes, nunca se teclea. Queda igual o por encima del objetivo por el redondeo del precio y el show.
A54: Importe retenido si cancela: tramo 1 | B54: =$B$47*INDEX('Calculadora'!$B$96:$D$96,MATCH($B$5,'Calculadora'!$B$90:$D$90,0)) -> 1539.945 | C54: Particular: 60 días o más. Empresa: 30 días o más.
A55: Importe retenido si cancela: tramo 2 | B55: =$B$47*INDEX('Calculadora'!$B$97:$D$97,MATCH($B$5,'Calculadora'!$B$90:$D$90,0)) -> 2566.575 | C55: Particular: de 30 a 59 días. Empresa: de 15 a 29 días.
A56: Importe retenido si cancela: tramo 3 | B56: =$B$47*INDEX('Calculadora'!$B$98:$D$98,MATCH($B$5,'Calculadora'!$B$90:$D$90,0)) -> 3849.8625 | C56: Particular: de 7 a 29 días. Empresa: de 7 a 14 días.
A57: Importe retenido si cancela: tramo 4 | B57: =$B$47*INDEX('Calculadora'!$B$99:$D$99,MATCH($B$5,'Calculadora'!$B$90:$D$90,0)) -> 5133.15 | C57: Particular y Empresa: menos de 7 días o no presentación.
A59: REGLAS DE ESCALADO (tabla de la sección 8 del manual técnico del kit) | B59: Valor
A60: Carne cruda que asa una parrilla de 120 × 60 cm en un servicio (kg) | B60: 32 | C60: 12-15 kg por tanda y 2-3 tandas: se toma 13 kg × 2,5 tandas, que son 60-80 invitados con 400 g.
A61: Carbón por kg de carne cruda (kg) | B61: 0.8 | C61: Entre 0,7 y 1 kg de carbón por kg de carne cruda: unos 0,3-0,45 kg por invitado. Para el asado a la cruz suma 2-3 kg de leña por kg de carne.
A62: Precio del carbón (€ por kg) | B62: 1.5 | C62: Tarifa profesional de 1,3 a 2,0 € por kg (encina, marabú o quebracho; saco de 15 kg).
A63: Merma de cocción (de crudo a servido) | B63: 0.3 | C63: Vacuno y cerdo a la brasa pierden el 25-35 %; el brisket ahumado, el 40-50 %.
A64: Ayudante desde (invitados) | B64: 40 | C64: Por debajo de este número de invitados el parrillero trabaja sin ayudante.
A66: ESTILO DE SERVICIO → PERSONAL | B66: Invitados por parrillero | C66: Invitados por ayudante
A67: Buffet | B67: 70 | C67: 60 | D67: Buffet: 60-80 invitados por parrillero. Cortes en mesa: 40-50. Fiesta de volumen: estimación del kit.
A68: Cortes en mesa | B68: 45 | C68: 50
A69: Fiesta de volumen | B69: 150 | C69: 100
A71: FORMATO → CARNE CRUDA POR INVITADO | B71: Gramos
A72: Asado completo | B72: 500 | C72: Asado sin entrantes: 500-600 g. Con entrantes: 350-450 g. Chuletada de fiesta: 300 g. Brunch: estimación del kit. Sin hueso, un 20 % menos; los niños, la mitad.
A73: Plato principal | B73: 400
A74: Brunch | B74: 200
A75: Chuletada de fiesta | B75: 300
A77: EXPERIENCIA → MATERIA PRIMA POR INVITADO (sin IVA, sin bebida) | B77: Euros
A78: 01 Asado argentino | B78: 9.5 | C78: Estimación del kit con precios de mayorista de 2025-2026 (lomo bajo de vaca, entraña, picanha, costilla, ibérico). La 11 no es de las 10 experiencias: sale del escandallo del caso de fiestas. Cambia la cifra por tu escandallo.
A79: 02 Asador a la cruz | B79: 11
A80: 03 Parrilla uruguaya | B80: 8.5
A81: 04 BBQ texano | B81: 8
A82: 05 Rodizio brasileño | B82: 8.5
A83: 06 Asador criollo-castellano | B83: 11
A84: 07 Parrilla mediterránea | B84: 9
A85: 08 Asador llanero | B85: 6.5
A86: 09 Show de fuego (corte premium) | B86: 14
A87: 10 Brunch parrillero corporativo | B87: 5.5
A88: 11 Chuletada o costillada de fiesta | B88: 2.5
A90: POLÍTICA POR CLIENTE | B90: Particular | C90: Empresa | D90: Ayuntamiento
A91: Margen bruto objetivo sobre el subtotal | B91: 0.42 | C91: 0.4 | D91: 0.4 | E91: Parte del subtotal que queda tras los costes directos. Estimación del kit: la boda particular lleva más margen que la empresa; el ayuntamiento paga por volumen.
A92: Cobro: señal al firmar (% del total) | B92: 0.3 | C92: 0.3 | D92: 0 | E92: Particular y Empresa, el 30 % al firmar. Un ayuntamiento no anticipa: compra por contrato menor.
A93: Cobro: pago a siete días del evento (% del total) | B93: 0.4 | C93: 0 | D93: 0 | E93: Sólo el contrato Particular.
A94: Cobro: pago a las 48 horas del evento (% del total) | B94: 0.3 | C94: 0 | D94: 0 | E94: Sólo el contrato Particular.
A95: Cobro: pago a 30 días de la factura (% del total) | B95: 0 | C95: 0.7 | D95: 1 | E95: Empresa, el 70 % restante; Ayuntamiento, el 100 % desde la conformidad (art. 198.4 de la Ley 9/2017).
A96: Cancelación tramo 1 (% del total que retienes) | B96: 0.3 | C96: 0.2 | D96: 0 | E96: Particular: 60 días o más, retienes la señal (el 30 %). Empresa: 30 días o más, el 20 % del pedido.
A97: Cancelación tramo 2 (% del total que retienes) | B97: 0.5 | C97: 0.5 | D97: 0 | E97: Particular: de 30 a 59 días. Empresa: de 15 a 29 días.
A98: Cancelación tramo 3 (% del total que retienes) | B98: 0.75 | C98: 0.75 | D98: 0 | E98: Particular: de 7 a 29 días. Empresa: de 7 a 14 días.
A99: Cancelación tramo 4 (% del total que retienes) | B99: 1 | C99: 1 | D99: 0 | E99: Particular y Empresa: con menos de 7 días o no presentación, el 100 %. A un ayuntamiento no se le aplican estos tramos: se rige por su pliego o su contrato menor.
A101: TABLA DE ESCALADO (plato principal de 400 g, estilo Buffet) | B101: 40 | C101: 80 | D101: 150 | E101: 300
A102: Carne cruda (kg) | B102: =B$101*$B$73/1000 -> 16 | C102: =C$101*$B$73/1000 -> 32 | D102: =D$101*$B$73/1000 -> 60 | E102: =E$101*$B$73/1000 -> 120
A103: Carne servida (kg) | B103: =B$101*$B$73/1000*(1-$B$63) -> 11.2 | C103: =C$101*$B$73/1000*(1-$B$63) -> 22.4 | D103: =D$101*$B$73/1000*(1-$B$63) -> 42 | E103: =E$101*$B$73/1000*(1-$B$63) -> 84
A104: Parrillas | B104: =MAX(1,ROUNDUP(B$101*$B$73/1000/$B$60,0)) -> 1 | C104: =MAX(1,ROUNDUP(C$101*$B$73/1000/$B$60,0)) -> 1 | D104: =MAX(1,ROUNDUP(D$101*$B$73/1000/$B$60,0)) -> 2 | E104: =MAX(1,ROUNDUP(E$101*$B$73/1000/$B$60,0)) -> 4
A105: Parrilleros | B105: =MAX(1,ROUNDUP(B$101/$B$67,0)) -> 1 | C105: =MAX(1,ROUNDUP(C$101/$B$67,0)) -> 2 | D105: =MAX(1,ROUNDUP(D$101/$B$67,0)) -> 3 | E105: =MAX(1,ROUNDUP(E$101/$B$67,0)) -> 5
A106: Ayudantes | B106: =IF(B$101<$B$64,0,ROUNDUP(B$101/$C$67,0)) -> 1 | C106: =IF(C$101<$B$64,0,ROUNDUP(C$101/$C$67,0)) -> 2 | D106: =IF(D$101<$B$64,0,ROUNDUP(D$101/$C$67,0)) -> 3 | E106: =IF(E$101<$B$64,0,ROUNDUP(E$101/$C$67,0)) -> 5
A107: Carbón (kg) | B107: =B$101*$B$73/1000*$B$61 -> 12.8 | C107: =C$101*$B$73/1000*$B$61 -> 25.6 | D107: =D$101*$B$73/1000*$B$61 -> 48 | E107: =E$101*$B$73/1000*$B$61 -> 96
A108: Es la misma tabla que la sección 8 del manual técnico. Una parrilla de 120 × 60 cm asa 12-15 kg por tanda; un parrillero atiende 60-80 invitados en buffet y 40-50 con cortes en mesa; el ayudante entra desde 40 invitados.

Sheet Ejemplos
A1: 3 PRESUPUESTOS DE EJEMPLO — con las mismas fórmulas de la hoja «Calculadora»
A2: Estimaciones del kit para ilustrar el cálculo, no precios de mercado: cambia los datos en «Calculadora» para presupuestar tus eventos. Las tablas (margen y cobro por cliente, materia prima, escalado) están al final de esa hoja y también mueven estos ejemplos.
A4: DATOS DEL EVENTO | B4: Boda particular con show de fuego | C4: Team building de empresa con BBQ texano | D4: Fiesta o feria municipal de volumen
A5: Cliente | B5: Particular | C5: Empresa | D5: Ayuntamiento
A6: Invitados previstos | B6: 110 | C6: 70 | D6: 300
A7: Formato del servicio | B7: Asado completo | C7: Plato principal | D7: Chuletada de fiesta
A8: Experiencia | B8: 01 Asado argentino | C8: 04 BBQ texano | D8: 11 Chuletada o costillada de fiesta
A9: Estilo de servicio | B9: Cortes en mesa | C9: Buffet | D9: Fiesta de volumen
A10: Bebida por invitado (coste) | B10: 4 | C10: 3 | D10: 0
A11: Coste de menaje, desechables y consumibles por invitado | B11: 0.6 | C11: 0.6 | D11: 0.4
A12: Horas por persona (carga, viaje, montaje, brasa, servicio y recogida) | B12: 9 | C12: 8 | D12: 9
A13: Coste bruto por hora del personal | B13: 13 | C13: 13 | D13: 13
A14: Seguridad Social a cargo de la empresa | B14: 0.33 | C14: 0.33 | D14: 0.33
A15: Importe de alquileres repercutidos (carpa, mesas, sillas, parrilla extra) | B15: 0 | C15: 0 | D15: 0
A16: Kilómetros de ida (cocina de apoyo → espacio) | B16: 35 | C16: 25 | D16: 30
A17: Tarifa por kilómetro de desplazamiento | B17: 0.95 | C17: 0.95 | D17: 0.95
A18: Importe del suplemento de show de fuego por invitado | B18: 2 | C18: 0 | D18: 0
A19: IVA del servicio de comidas | B19: 0.1 | C19: 0.1 | D19: 0.1
A21: RESULTADO | B21: Boda particular con show de fuego | C21: Team building de empresa con BBQ texano | D21: Fiesta o feria municipal de volumen
A22: Carne cruda por invitado (g, de la tabla) | B22: =INDEX('Calculadora'!$B$72:$B$75,MATCH($B$7,'Calculadora'!$A$72:$A$75,0)) -> 500 | C22: =INDEX('Calculadora'!$B$72:$B$75,MATCH($C$7,'Calculadora'!$A$72:$A$75,0)) -> 400 | D22: =INDEX('Calculadora'!$B$72:$B$75,MATCH($D$7,'Calculadora'!$A$72:$A$75,0)) -> 300
A23: Coste de materia prima por invitado de la experiencia (tabla) | B23: =INDEX('Calculadora'!$B$78:$B$88,MATCH($B$8,'Calculadora'!$A$78:$A$88,0)) -> 9.5 | C23: =INDEX('Calculadora'!$B$78:$B$88,MATCH($C$8,'Calculadora'!$A$78:$A$88,0)) -> 8 | D23: =INDEX('Calculadora'!$B$78:$B$88,MATCH($D$8,'Calculadora'!$A$78:$A$88,0)) -> 2.5
A24: Invitados por parrillero (del estilo de servicio) | B24: =INDEX('Calculadora'!$B$67:$B$69,MATCH($B$9,'Calculadora'!$A$67:$A$69,0)) -> 45 | C24: =INDEX('Calculadora'!$B$67:$B$69,MATCH($C$9,'Calculadora'!$A$67:$A$69,0)) -> 70 | D24: =INDEX('Calculadora'!$B$67:$B$69,MATCH($D$9,'Calculadora'!$A$67:$A$69,0)) -> 150
A25: Invitados por ayudante (del estilo de servicio) | B25: =INDEX('Calculadora'!$C$67:$C$69,MATCH($B$9,'Calculadora'!$A$67:$A$69,0)) -> 50 | C25: =INDEX('Calculadora'!$C$67:$C$69,MATCH($C$9,'Calculadora'!$A$67:$A$69,0)) -> 60 | D25: =INDEX('Calculadora'!$C$67:$C$69,MATCH($D$9,'Calculadora'!$A$67:$A$69,0)) -> 100
A26: Margen objetivo del cliente elegido | B26: =INDEX('Calculadora'!$B$91:$D$91,MATCH($B$5,'Calculadora'!$B$90:$D$90,0)) -> 0.42 | C26: =INDEX('Calculadora'!$B$91:$D$91,MATCH($C$5,'Calculadora'!$B$90:$D$90,0)) -> 0.4 | D26: =INDEX('Calculadora'!$B$91:$D$91,MATCH($D$5,'Calculadora'!$B$90:$D$90,0)) -> 0.4
A27: Carne cruda total (kg) | B27: =$B$6*$B$22/1000 -> 55 | C27: =$C$6*$C$22/1000 -> 28 | D27: =$D$6*$D$22/1000 -> 90
A28: Carne servida total (kg) | B28: =$B$27*(1-'Calculadora'!$B$63) -> 38.5 | C28: =$C$27*(1-'Calculadora'!$B$63) -> 19.6 | D28: =$D$27*(1-'Calculadora'!$B$63) -> 63
A29: Parrillas necesarias | B29: =MAX(1,ROUNDUP($B$27/'Calculadora'!$B$60,0)) -> 2 | C29: =MAX(1,ROUNDUP($C$27/'Calculadora'!$B$60,0)) -> 1 | D29: =MAX(1,ROUNDUP($D$27/'Calculadora'!$B$60,0)) -> 3
A30: Parrilleros necesarios | B30: =MAX(1,ROUNDUP($B$6/$B$24,0)) -> 3 | C30: =MAX(1,ROUNDUP($C$6/$C$24,0)) -> 1 | D30: =MAX(1,ROUNDUP($D$6/$D$24,0)) -> 2
A31: Ayudantes necesarios | B31: =IF($B$6<'Calculadora'!$B$64,0,ROUNDUP($B$6/$B$25,0)) -> 3 | C31: =IF($C$6<'Calculadora'!$B$64,0,ROUNDUP($C$6/$C$25,0)) -> 2 | D31: =IF($D$6<'Calculadora'!$B$64,0,ROUNDUP($D$6/$D$25,0)) -> 3
A32: Carbón total (kg) | B32: =$B$27*'Calculadora'!$B$61 -> 44 | C32: =$C$27*'Calculadora'!$B$61 -> 22.4 | D32: =$D$27*'Calculadora'!$B$61 -> 72
A33: Coste de materia prima | B33: =$B$23*$B$6 -> 1045 | C33: =$C$23*$C$6 -> 560 | D33: =$D$23*$D$6 -> 750
A34: Coste de bebida | B34: =$B$10*$B$6 -> 440 | C34: =$C$10*$C$6 -> 210 | D34: =$D$10*$D$6 -> 0
A35: Coste de menaje, desechables y consumibles | B35: =$B$11*$B$6 -> 66 | C35: =$C$11*$C$6 -> 42 | D35: =$D$11*$D$6 -> 120
A36: Coste del carbón | B36: =$B$32*'Calculadora'!$B$62 -> 66 | C36: =$C$32*'Calculadora'!$B$62 -> 33.6 | D36: =$D$32*'Calculadora'!$B$62 -> 108
A37: Coste de personal (salario + Seguridad Social) | B37: =($B$30+$B$31)*$B$12*$B$13*(1+$B$14) -> 933.66 | C37: =($C$30+$C$31)*$C$12*$C$13*(1+$C$14) -> 414.96 | D37: =($D$30+$D$31)*$D$12*$D$13*(1+$D$14) -> 778.05
A38: Importe de alquileres | B38: =$B$15 -> 0 | C38: =$C$15 -> 0 | D38: =$D$15 -> 0
A39: Coste directo total | B39: =$B$33+$B$34+$B$35+$B$36+$B$37+$B$38 -> 2550.66 | C39: =$C$33+$C$34+$C$35+$C$36+$C$37+$C$38 -> 1260.56 | D39: =$D$33+$D$34+$D$35+$D$36+$D$37+$D$38 -> 1756.05
A40: Coste directo por invitado | B40: =$B$39/$B$6 -> 23.187818 | C40: =$C$39/$C$6 -> 18.008 | D40: =$D$39/$D$6 -> 5.8535
A41: PRECIO POR INVITADO SIN IVA | B41: =ROUNDUP($B$39/(1-$B$26)/$B$6*2,0)/2+$B$18 -> 42 | C41: =ROUNDUP($C$39/(1-$C$26)/$C$6*2,0)/2+$C$18 -> 30.5 | D41: =ROUNDUP($D$39/(1-$D$26)/$D$6*2,0)/2+$D$18 -> 10
A42: PRECIO POR INVITADO CON IVA | B42: =$B$41*(1+$B$19) -> 46.2 | C42: =$C$41*(1+$C$19) -> 33.55 | D42: =$D$41*(1+$D$19) -> 11
A43: Subtotal de comida sin IVA | B43: =$B$41*$B$6 -> 4620 | C43: =$C$41*$C$6 -> 2135 | D43: =$D$41*$D$6 -> 3000
A44: Desplazamiento (ida y vuelta, sin margen) | B44: =$B$16*2*$B$17 -> 66.5 | C44: =$C$16*2*$C$17 -> 47.5 | D44: =$D$16*2*$D$17 -> 57
A45: Base imponible | B45: =$B$43+$B$44 -> 4686.5 | C45: =$C$43+$C$44 -> 2182.5 | D45: =$D$43+$D$44 -> 3057
A46: IVA | B46: =$B$45*$B$19 -> 468.65 | C46: =$C$45*$C$19 -> 218.25 | D46: =$D$45*$D$19 -> 305.7
A47: TOTAL DEL PRESUPUESTO (con IVA) | B47: =$B$45+$B$46 -> 5155.15 | C47: =$C$45+$C$46 -> 2400.75 | D47: =$D$45+$D$46 -> 3362.7
A48: Importe del cobro 1: señal al firmar | B48: =$B$47*INDEX('Calculadora'!$B$92:$D$92,MATCH($B$5,'Calculadora'!$B$90:$D$90,0)) -> 1546.545 | C48: =$C$47*INDEX('Calculadora'!$B$92:$D$92,MATCH($C$5,'Calculadora'!$B$90:$D$90,0)) -> 720.225 | D48: =$D$47*INDEX('Calculadora'!$B$92:$D$92,MATCH($D$5,'Calculadora'!$B$90:$D$90,0)) -> 0
A49: Importe del cobro 2: a siete días del evento | B49: =$B$47*INDEX('Calculadora'!$B$93:$D$93,MATCH($B$5,'Calculadora'!$B$90:$D$90,0)) -> 2062.06 | C49: =$C$47*INDEX('Calculadora'!$B$93:$D$93,MATCH($C$5,'Calculadora'!$B$90:$D$90,0)) -> 0 | D49: =$D$47*INDEX('Calculadora'!$B$93:$D$93,MATCH($D$5,'Calculadora'!$B$90:$D$90,0)) -> 0
A50: Importe del cobro 3: a las 48 horas del evento | B50: =$B$47*INDEX('Calculadora'!$B$94:$D$94,MATCH($B$5,'Calculadora'!$B$90:$D$90,0)) -> 1546.545 | C50: =$C$47*INDEX('Calculadora'!$B$94:$D$94,MATCH($C$5,'Calculadora'!$B$90:$D$90,0)) -> 0 | D50: =$D$47*INDEX('Calculadora'!$B$94:$D$94,MATCH($D$5,'Calculadora'!$B$90:$D$90,0)) -> 0
A51: Importe del cobro 4: a 30 días de la factura | B51: =$B$47*INDEX('Calculadora'!$B$95:$D$95,MATCH($B$5,'Calculadora'!$B$90:$D$90,0)) -> 0 | C51: =$C$47*INDEX('Calculadora'!$B$95:$D$95,MATCH($C$5,'Calculadora'!$B$90:$D$90,0)) -> 1680.525 | D51: =$D$47*INDEX('Calculadora'!$B$95:$D$95,MATCH($D$5,'Calculadora'!$B$90:$D$90,0)) -> 3362.7
A52: Margen bruto en euros | B52: =$B$43-$B$39 -> 2069.34 | C52: =$C$43-$C$39 -> 874.44 | D52: =$D$43-$D$39 -> 1243.95
A53: Margen bruto (calculado) | B53: =IF($B$43=0,0,$B$52/$B$43) -> 0.44790909 | C53: =IF($C$43=0,0,$C$52/$C$43) -> 0.40957377 | D53: =IF($D$43=0,0,$D$52/$D$43) -> 0.41465
A54: Importe retenido si cancela: tramo 1 | B54: =$B$47*INDEX('Calculadora'!$B$96:$D$96,MATCH($B$5,'Calculadora'!$B$90:$D$90,0)) -> 1546.545 | C54: =$C$47*INDEX('Calculadora'!$B$96:$D$96,MATCH($C$5,'Calculadora'!$B$90:$D$90,0)) -> 480.15 | D54: =$D$47*INDEX('Calculadora'!$B$96:$D$96,MATCH($D$5,'Calculadora'!$B$90:$D$90,0)) -> 0
A55: Importe retenido si cancela: tramo 2 | B55: =$B$47*INDEX('Calculadora'!$B$97:$D$97,MATCH($B$5,'Calculadora'!$B$90:$D$90,0)) -> 2577.575 | C55: =$C$47*INDEX('Calculadora'!$B$97:$D$97,MATCH($C$5,'Calculadora'!$B$90:$D$90,0)) -> 1200.375 | D55: =$D$47*INDEX('Calculadora'!$B$97:$D$97,MATCH($D$5,'Calculadora'!$B$90:$D$90,0)) -> 0
A56: Importe retenido si cancela: tramo 3 | B56: =$B$47*INDEX('Calculadora'!$B$98:$D$98,MATCH($B$5,'Calculadora'!$B$90:$D$90,0)) -> 3866.3625 | C56: =$C$47*INDEX('Calculadora'!$B$98:$D$98,MATCH($C$5,'Calculadora'!$B$90:$D$90,0)) -> 1800.5625 | D56: =$D$47*INDEX('Calculadora'!$B$98:$D$98,MATCH($D$5,'Calculadora'!$B$90:$D$90,0)) -> 0
A57: Importe retenido si cancela: tramo 4 | B57: =$B$47*INDEX('Calculadora'!$B$99:$D$99,MATCH($B$5,'Calculadora'!$B$90:$D$90,0)) -> 5155.15 | C57: =$C$47*INDEX('Calculadora'!$B$99:$D$99,MATCH($C$5,'Calculadora'!$B$90:$D$90,0)) -> 2400.75 | D57: =$D$47*INDEX('Calculadora'!$B$99:$D$99,MATCH($D$5,'Calculadora'!$B$90:$D$90,0)) -> 0
A59: QUÉ ENSEÑA CADA EJEMPLO
A60: Boda particular con show de fuego | B60: Particular, 110 invitados (la boda del caso del plan financiero), asado argentino de 500 g de carne cruda por invitado con cortes en mesa, bebida incluida y un suplemento de 2 € por invitado por el show de fuego. El precio con IVA es el que ve el particular; cobro en tres pagos (30 % al firmar, 40 % a siete días, 30 % a las 48 horas).
A61: Team building de empresa con BBQ texano | B61: Empresa, 70 invitados, BBQ texano en buffet con 400 g de carne cruda, refrescos y cerveza incluidos y presupuesto «+ IVA». Cobro del 30 % al firmar y el 70 % a 30 días de la factura; los tramos de cancelación son los del contrato B2B.
A62: Fiesta o feria municipal de volumen | B62: 300 invitados en una chuletada de 300 g por persona con servicio de volumen: el precio queda cerca de los 10 € por invitado. Sin anticipo: el ayuntamiento paga a 30 días desde la conformidad (art. 198.4 de la Ley 9/2017) y los tramos de cancelación de los contratos del kit no se le aplican (contrata con su pliego o su contrato menor). Tres parrillas: las dos del kit y el remolque.

Sheet Instrucciones
A1: INSTRUCCIONES DE USO — Calculadora de precios de parrillada y asado para eventos
A2: Convierte tu escandallo en un precio por invitado y en un presupuesto completo: kilos de carne, parrillas, parrilleros, ayudantes y carbón, subtotal, IVA, total, cobro por pagos y lo que retienes si el cliente cancela. Sólo se escribe en las celdas VERDES; el margen se calcula.
A3: 1. Elige el cliente (Particular, Empresa o Ayuntamiento; las comisiones de fiestas y las peñas cuentan como Empresa), los invitados, el formato del servicio, la experiencia y el estilo de servicio.
A4: 2. La tabla de escalado y las demás tablas del final de la primera hoja dan los gramos de carne cruda por invitado, la materia prima de la experiencia y los invitados por parrillero y por ayudante. Las parrillas salen de dividir los kilos de carne cruda entre lo que asa una parrilla; los parrilleros, de dividir los invitados entre los que atiende cada uno.
A5: 3. Escribe la bebida que pones tú (0 si la pone el cliente) y el menaje y los consumibles por invitado. El carbón se calcula con los kilos de carne.
A6: 4. Escribe las horas por persona, el coste bruto por hora y la Seguridad Social. Si cocinas tú, cuéntate a precio de hora: es tu coste de oportunidad.
A7: 5. Escribe los alquileres que repercutes y los kilómetros de ida: el desplazamiento se cobra ida y vuelta, en una línea aparte y sin margen.
A8: 6. El margen objetivo de cada cliente está en la tabla «Política por cliente» del final: cámbialo ahí. El precio por invitado es el coste directo dividido entre (1 − margen), redondeado a los 0,50 € de arriba, más el suplemento de show de fuego si lo hay: el margen calculado queda igual o por encima del objetivo.
A9: 7. A una empresa se le presupuesta el precio SIN IVA («+ IVA»); a un particular, el precio CON IVA, porque en una oferta a consumidores el precio va con los impuestos incluidos.
A10: IVA, PROPINAS Y COBROS
A12: El servicio de comidas para consumir en el acto va al 10 % de IVA, bebida y alcohol incluidos (Ley 37/1992, art. 91.Uno.2.2.º). Lo que facturas aparte sin ser accesorio, como la carpa o el mobiliario, va al 21 %. En las facturas a empresas no se practica retención de IRPF por esta actividad.
A13: La propina voluntaria es decisión del cliente y es del equipo: no entra en el precio, en la base imponible ni en el total.
... A29: Versión 2.2 · septiembre 2026 · aichef.pro/plan-negocio-parrillero-asador-eventos · info@aichef.pro
