Workbook

Sheet 0. Supuestos
A1: SUPUESTOS — aquí se teclean las TASAS y los DRIVERS del modelo
A2: Cambia las celdas VERDES: el resto del libro se recalcula solo. Las partidas de gasto se teclean en su hoja (también en verde) y no se repiten aquí.
A3: ACTIVIDAD
A4: Invitados por evento (media del año 1) | B4: 80 | C4: Invitados de media por evento en el año 1. Sale de la mezcla de cuatro tipos de evento de la tabla de referencias de la hoja de Instrucciones: bodas de 110, eventos de empresa de 70, celebraciones privadas de 40 y fiestas o ferias de 300
A5: Precio medio por invitado SIN IVA (€) | B5: 25 | C5: SIN IVA, por invitado. Media ponderada de la misma mezcla: 42 € la boda (entrantes, tres o cuatro cortes con vacuno madurado, guarniciones y postre a la brasa), 31 € el evento de empresa, 25 € la celebración privada y 10 € la chuletada o costillada de una fiesta. Por eso la media baja: no es el precio de una boda. El precio con IVA (10 % en un servicio de comidas) está en la fila «PVP equivalente con IVA» de abajo
A6: Eventos al año | B6: 95 | C6: Eventos servidos en el año: 12 bodas, 30 de empresa (comidas, team building, show cooking y Navidad), 45 celebraciones privadas (cumpleaños, comuniones, peñas, urbanizaciones) y 8 fiestas o ferias por encargo. Es el MISMO dato para la cuenta de resultados, el punto de equilibrio, los escenarios y las horas de personal
A7: Crecimiento de volumen del año 2 | B7: 0.08 | C7: Más volumen el segundo año: empresas que repiten, bodas que llegan por recomendación y planners que ya te conocen. El libro lo aplica a los invitados por evento con los mismos eventos; en euros da lo mismo que hacer más eventos del mismo tamaño
A8: Crecimiento de volumen del año 3 | B8: 0.05 | C8: Sobre el año 2. Conservador: el techo lo ponen los fines de semana de temporada y un solo parrillero titular
A9: PVP equivalente con IVA (calculado) | B9: =IFERROR(IF($B$5="","",$B$5*(1+SUMPRODUCT('PyG 3 Años'!$E$10:$E$11,'PyG 3 Años'!$G$10:$G$11))),"") -> 27.5099 | C9: =IFERROR("Precio por invitado sin IVA más el IVA medio ponderado de tus líneas de venta: "&TEXT(SUMPRODUCT('PyG 3 Años'!$E$10:$E$11,'PyG 3 Años'!$G$10:$G$11)*100,"0")&" %. En el servicio de parrilla todo va al 10 % (art. 91.Uno.2.2.º de la Ley 37/1992, alcohol incluido); el alcohol que sale en el asado para llevar mueve la media. Aquí va redondeado. Compáralo con el rango del sector, que va con IVA.","") -> Precio por invitado sin IVA más el IVA medio ponderado de tus líneas de venta: 10 %. En el servicio de parrilla todo va al 10 % (art. 91.Uno.2.2.º de la Ley 37/1992, alcohol incluido); el alcohol que sale en el asado para llevar mueve la media. Aquí va redondeado. Compáralo con el rango del sector, que va con IVA.
A10: MIX Y COSTE DE MERCANCÍA
A11: Ventas de COMIDA sobre el total | B11: 0.88 | C11: Peso de la COMIDA sobre el total de ventas. Es un INPUT: cámbialo aquí y el P&L, la tesorería y el IVA repercutido se recalculan solos
A12: Ventas de BEBIDA sobre el total | B12: =IFERROR(IF(COUNT(B11)=0,"",1-B11),"") -> 0.12 | C12: Se calcula como el resto: comida + bebida = 100 %
A13: Coste de mercancía sobre las ventas de COMIDA | B13: 0.32 | C13: Materia prima de la comida sobre las ventas de comida: carne (350-450 g crudos por invitado con entrantes), achuras y embutido, verdura, pan, salsas y postre. El escandallo de la mezcla sale al 29,8 %; el plan suma dos puntos por la volatilidad del vacuno y las compras de seguridad. Escandalla cada evento con la calculadora de este kit
A14: Coste de mercancía sobre las ventas de BEBIDA | B14: 0.3 | C14: Bebida sobre las ventas de bebida: cerveza, refrescos, agua y vino del pack. Si el cliente pone la bebida, esta línea baja
A15: Consumibles sobre ventas | B15: 0.045 | C15: Carbón, leña, pastillas de encendido, gas del plan B, papel de aluminio, desechables compostables y hielo: algo más de 1 € por invitado. Se gastan 0,7-1 kg de carbón por kg de carne cruda, y el carbón cuesta de 1,3 a 2 € el kilo
A16: Ventas de asado para llevar (sin servicio) sobre el total | B16: 0.05 | C16: Parte de las ventas que se entrega SIN servicio: asado para llevar en bandejas (cordero, cochinillo, costillar), sin parrillero en el evento. Es entrega de bienes: la comida va al 10 % y el alcohol y los refrescos, zumos y gaseosas con azúcares o edulcorantes añadidos, al 21 % (art. 91.Uno.1.1.º de la Ley 37/1992); el libro lo aplica al alcohol de esta parte
A17: Comisión de la plataforma de pedidos | B17: 0.1 | C17: Comisión media de la parte del asado para llevar que entra por plataformas de pedidos o intermediarios. Si todos los pedidos los vendes tú, pon 0
A18: Comisión de los medios de pago | B18: 0.005 | C18: Casi todo se cobra por transferencia (señales y facturas de empresas y ayuntamientos); el datáfono queda para los cobros del día del evento
A19: PERSONAL
A20: Seguridad Social a cargo de la empresa | B20: 0.33 | C20: Contingencias comunes + AT/EP + desempleo + FOGASA + FP; ajusta a tu convenio y bonificaciones
A21: Número de pagas anuales | B21: 14 | C21: Salario bruto anual = bruto mensual × pagas
A22: SMI anual de referencia (€) | B22: 17094 | C22: SMI 2026: 17.094 € al año (1.221 €/mes en 14 pagas), suelo legal por jornada completa. Comprueba el importe vigente si presentas el plan en otro ejercicio
A23: COCINA DE APOYO Y FIJOS
A24: Cuota mensual de la cocina de apoyo (€) | B24: 1000 | C24: Cuota de una cocina de apoyo compartida y autorizada: unas 30 horas al mes de marinados, salmueras y porcionado, cámara para la carne y almacén de parrillas, carbón y remolque. La carne se asa en el evento, pero lo que se prepara antes no se puede hacer en casa (art. 13.5.b del RD 1021/2022). No hay tarifa pública: pide dos presupuestos en tu zona
A25: Fianza de la cocina de apoyo (meses) | B25: 2 | C25: Dos cuotas de fianza, lo habitual en un contrato de uso de cocina compartida
A26: Suministros mensuales (consumos propios fuera de la cuota) (€) | B26: 50 | C26: Consumos propios fuera de la cuota de la cocina (datos móviles, luz del almacén). El carbón y el gas van en los consumibles, porque suben y bajan con los eventos
A27: Seguros (€/año) | B27: 1950 | C27: Responsabilidad civil de explotación con incendio (brasas y chispas sobre carpas, césped y pavimento) y de producto con intoxicación alimentaria de al menos 600.000 € (unos 750 €); seguro de la furgoneta de uso comercial (900 €), del remolque (150 €) y de los equipos que salen a cada evento (150 €). La cancelación por una prohibición de fuego no se asegura: va en la cláusula de fuerza mayor del contrato, con el plan B de gas
A28: Varios e imprevistos sobre ventas | B28: 0.05 | C28: Combustible de la furgoneta y del remolque (2 puntos), imprevistos (1,5 puntos) y el canon que algunas fincas y wedding planners cobran al proveedor externo (1,5 puntos). Es variable: sube y baja con los eventos
A29: FINANCIACIÓN
A30: Recursos propios aportados (€) | B30: 22000 | C30: Aportación del socio. Un banco pide entre el 25 y el 30 % de la necesidad de caja con dinero propio
A31: Préstamo bancario solicitado (€) | B31: 65400 | C31: Principal solicitado. La hoja de Financiación compara lo que aportas con la necesidad de caja de la hoja de inversión y te dice si sobra o falta: ajústalo con ese dato
A32: Tipo de interés nominal anual | B32: 0.065 | C32: Tipo nominal anual de un préstamo de empresa sin garantía inmobiliaria. Pide oferta a dos entidades y a una línea ICO o ENISA antes de fijarlo
A33: Plazo del préstamo (años) | B33: 6 | C33: Años totales, carencia incluida: el plazo de vida de la furgoneta y del equipo
A34: Carencia de principal (años) | B34: 1 | C34: El primer año sólo intereses: es cuando la caja está más tensa, con la agenda de bodas y empresas aún por llenar. Desde el segundo año se devuelve el principal: mira la holgura de caja de ese año en el Punto de Equilibrio
A35: Fondo de maniobra (meses de costes fijos) | B35: 3 | C35: Tres meses de costes fijos: cubren el invierno (enero, febrero y noviembre son los meses más bajos del año) y los 30 días que tardan en pagar empresas y ayuntamientos
A36: FISCAL
A37: Impuesto de Sociedades, nueva creación | B37: 0.15 | C37: Art. 29.1 LIS: el PRIMER ejercicio con base imponible positiva y el SIGUIENTE. El libro lo aproxima contando los dos primeros ejercicios con base positiva: coincide con la ley salvo que entre ellos haya un ejercicio en pérdidas
A38: Impuesto de Sociedades, tipo general | B38: 0.25 | C38: A partir del tercer ejercicio con base positiva. Es el tipo general del art. 29.1 LIS: si tu cifra de negocios queda por debajo de 1 M € (microempresa) o de 10 M € (reducida dimensión), desde 2025 hay tipos más bajos que se implantan de forma gradual; confirma el de tu ejercicio con tu asesor y cámbialo aquí
A39: IVA repercutido de restauración | B39: 0.1 | C39: Tipo reducido de hostelería
A40: IVA repercutido/soportado general | B40: 0.21 | C40: Tipo general. En este libro lo usan dos cosas: el IVA que soportas al comprar el alcohol (el proveedor lo factura al 21 %) y el que repercutes por el alcohol que sale por asado para llevar (es una entrega de bienes). El alcohol servido en el servicio de parrilla va al reducido: su tipo está en el bloque de desglose del IVA. Suministros, equipamiento y servicios tienen su tipo en la celda de abajo. El libro manda al general sólo el alcohol: si compras refrescos, zumos y gaseosas con azúcares o edulcorantes añadidos, su factura también va al 21 % (art. 91.Uno.1.1.º de la Ley 37/1992)
A41: IVA soportado en compras e inversión | B41: 0.21 | C41: Recuperable vía modelo 303, pero hay que adelantarlo
A42: Bases negativas de ejercicios anteriores (€) | B42: 0 | C42: Pérdidas pendientes de compensar al empezar (art. 26 LIS)
A43: AMORTIZACIÓN
A44: Vida útil de la furgoneta y su rotulación (años) | B44: 8 | C44: La furgoneta frigorífica y su rotulación se amortizan en ocho años, el 12,5 % anual, por debajo del 16 % máximo para elementos de transporte de la tabla del art. 12.1 de la Ley del Impuesto sobre Sociedades. Confírmalo con tu asesor
A45: Vida útil de maquinaria y mobiliario (años) | B45: 10 | C45: Remolque-parrilla, parrillas, cruces, ahumador, plan B de gas, equipos de frío, carpa, utensilios y equipos informáticos: el coeficiente máximo de la tabla del art. 12.1 de la Ley del Impuesto sobre Sociedades es del 12 % para maquinaria y del 10 % para mobiliario
A47: CRECIMIENTO Y ACTUALIZACIÓN DE COSTES
A48: Subida anual de los costes fijos | B48: 0 | C48: A CERO: las tres columnas están en euros del año 1 (términos reales). Súbela si quieres proyectar en euros corrientes
A49: ARRANQUE Y CAPACIDAD
A51: Capacidad máxima por evento (invitados) | B51: 350 | C51: DATO INFORMATIVO: no entra en ningún cálculo. Es el evento más grande que puedes servir con dos parrilleros, el remolque-parrilla, las dos parrillas móviles, los dos auxiliares y un tercero de tu bolsa de fijos discontinuos o de una ETT
A52: Actividad del mes 1 sobre la de crucero | B52: 0.55 | C52: Un negocio de parrilla para eventos que arranca factura poco el primer mes: las bodas se reservan con meses de antelación y las empresas tardan en repetir. Con 100 % se elimina la rampa
A53: Meses hasta alcanzar el régimen de crucero | B53: 6 | C53: Seis meses hasta el ritmo de crucero: una temporada de bodas y eventos de empresa
A54: Meses de cuota de la cocina de apoyo ANTES del primer evento | B54: 1 | C54: Un mes de cuota para montar el almacén, probar los marinados y hacer las primeras degustaciones antes de facturar
A55: Imprevistos sobre la compra y la preparación de la furgoneta (%) | B55: 0.08 | C55: Se calcula sobre la furgoneta y su rotulación: es donde aparecen las sorpresas (revisión del equipo de frío o del certificado ATP, anclajes de las botellas de gas y del carbón)
A57: COBROS, PAGOS Y DESGLOSE DEL IVA
A58: Días medios de cobro | B58: 15 | C58: Media ponderada: los particulares pagan el 30 % de señal al firmar, el 40 % siete días antes y el 30 % en las 48 horas siguientes al evento (contratos del kit); las empresas, a 30 días de la factura, y los ayuntamientos, a 30 días desde la conformidad (art. 198.4 de la Ley 9/2017). Empresas y fiestas son el 47 % de las ventas. El libro no admite días negativos, así que las señales no se modelan: tu caja real será algo MEJOR que la de la hoja de Tesorería
A59: Días medios de pago a proveedor | B59: 15 | C59: Plazo de pago a proveedores: la carne fresca se paga a plazo corto (el carnicero, a 7-15 días); el carbón y los desechables, a 30 días
A60: Mes de la paga extra de verano | B60: 7 | C60: Mes del año (1-12) en el que sale de caja la primera paga extra
A61: Mes de la paga extra de Navidad | B61: 12 | C61: Mes del año (1-12) en el que sale de caja la segunda paga extra
A62: Bebida ALCOHÓLICA sobre el total de bebida | B62: 0.6 | C62: Parte ALCOHÓLICA de la bebida (cerveza y vino del pack). Reparte el IVA que soportas al comprarla (21 % el alcohol) y el que repercutes en el asado para llevar
A63: IVA de la bebida ALCOHÓLICA servida en el evento | B63: 0.1 | C63: 10 %: el art. 91.Uno.2.2.º de la Ley 37/1992 grava al tipo reducido el «suministro de comidas y bebidas para consumir en el acto», sin excluir el alcohol, y un servicio de parrilla en directo lo es. El libro aplica el 21 % sólo al alcohol del asado para llevar, que no se sirve
A64: UMBRALES Y SUELOS DE CONTROL
A65: DSCR mínimo aceptable | B65: 1 | C65: Por debajo de 1 el negocio no genera para pagar el préstamo. Ponlo en el covenant que te exija tu banco
A66: DSCR objetivo (verde) | B66: 1.25 | C66: Lo que suele pedir una entidad para dar el préstamo sin garantías adicionales
A67: Holgura mínima sobre el punto de equilibrio | B67: 0.15 | C67: Cuánto deben superar las ventas previstas a las del punto de equilibrio. La caída que aguantas antes de entrar en pérdidas es algo menor: con un 15 % de holgura, un 13 % de lo previsto
A68: Suelo salarial anual del convenio provincial (€) | B68: 0 | C68: El servicio de comidas para eventos está dentro del convenio de hostelería (art. 4 del V Acuerdo Laboral de ámbito Estatal para el sector de Hostelería): copia aquí el salario base del grupo más bajo de la tabla de TU provincia. Con 0 el semáforo compara sólo contra el SMI

Sheet Inversión Inicial
A1: PLAN DE NEGOCIO: PARRILLERO / ASADOR PARA EVENTOS
A2: Inversión inicial estimada — parrilla y asado en directo para eventos
A3: Ajusta las cifras a tu proyecto.
A5: Concepto | B5: Importe | C5: % s/inversión | D5: Notas | E5: ¿Lleva IVA?
A6: INVERSIÓN | B6: =IFERROR(IF(COUNT(B7:B23)=0,"",SUM(B7:B23)),"") -> 54596 | C6: =IFERROR(B6/$B$26,"") -> 0.71346877
A7: Furgoneta frigorífica usada con certificado ATP | B7: 20000 | C7: =IFERROR(B7/$B$26,"") -> 0.26136302 | D7: Furgoneta usada con caja frigorífica y certificado ATP vigente (RD 237/2000) para llevar la carne a 7 °C o menos. Estimación del kit (18.000-21.950 € en el mercado de ocasión) | E7: Sí
A8: Rotulación, estanterías y anclajes | B8: 1200 | C8: =IFERROR(B8/$B$26,"") -> 0.015681781 | D8: Rotulación con la marca, estanterías con amarres y anclajes para llevar en pie y sujetas las botellas de gas y los sacos de carbón | E8: Sí
A9: Remolque-parrilla homologado con cruz | B9: 7000 | C9: =IFERROR(B9/$B$26,"") -> 0.091477057 | D9: Remolque de hasta 750 kg con parrilla y soporte de cruz: la pieza de las bodas y las fiestas. Estimación del kit (6.000-9.000 €); no hay precio público de referencia | E9: Sí
A10: Parrillas móviles inox de 120 cm y brasero | B10: 3200 | C10: =IFERROR(B10/$B$26,"") -> 0.041818083 | D10: Dos parrillas móviles de carbón y leña de 120 cm (cada una sirve 60-80 invitados en dos o tres tandas) y un brasero para tener brasa de reserva | E10: Sí
A11: Cruces, kit de costillar y ahumador pequeño | B11: 1800 | C11: =IFERROR(B11/$B$26,"") -> 0.023522672 | D11: Cuatro cruces para cordero o cochinillo, el kit de costillar y un ahumador offset pequeño para el BBQ texano | E11: Sí
A12: Plan B de gas y seguridad contra incendios | B12: 2200 | C12: =IFERROR(B12/$B$26,"") -> 0.028749932 | D12: Plancha o parrilla de piedra volcánica de gas con sus botellas y reguladores (una botella de menos de 15 kg por aparato), tres extintores ABC y uno de CO2, mantas ignífugas, contenedor metálico de cenizas y EPI térmicos | E12: Sí
A13: Frío: armario refrigerado portátil, isotermos, acumuladores y sondas | B13: 1800 | C13: =IFERROR(B13/$B$26,"") -> 0.023522672 | D13: Cadena de frío de la carne desde la cocina de apoyo hasta el evento, y sondas para las temperaturas del APPCC | E13: Sí
A14: Carpa, mesas, lavamanos portátil y protector de césped | B14: 1800 | C14: =IFERROR(B14/$B$26,"") -> 0.023522672 | D14: Zona de parrilla bajo carpa (a 3 m o más de la parrilla), mesa de corte y de servicio, lavamanos para el personal y protector del césped o del pavimento | E14: Sí
A15: Cuchillería, tablas de colores, básculas, GN y uniformes | B15: 1900 | C15: =IFERROR(B15/$B$26,"") -> 0.024829487 | D15: Cuchillos de deshuese y de trinchar, tablas por colores, básculas, cubetas GN y uniformes de la plantilla | E15: Sí
A16: Marca, web, fotos, dossier y lanzamiento | B16: 4500 | C16: =IFERROR(B16/$B$26,"") -> 0.058806679 | D16: Identidad, web con formulario de presupuesto, sesión de fotos y vídeo de la brasa, dossier para bodas y empresas, y degustaciones de lanzamiento | E16: Sí
A17: Software, tablet y datáfono | B17: 800 | C17: =IFERROR(B17/$B$26,"") -> 0.010454521 | D17: Presupuestos, agenda y facturación conforme a Veri*factu | E17: Sí
A18: Constitución SL + notaría + registro | B18: 1000 | C18: =IFERROR(B18/$B$26,"") -> 0.013068151 | D18: SL unipersonal. Las tasas y el arancel del Registro no llevan IVA; los honorarios del notario y de la gestoría sí: cambia la columna de al lado a «Sí» si tu presupuesto es sobre todo de honorarios | E18: No
... A20: Stock inicial de producto | B20: 1500 | C20: =IFERROR(B20/$B$26,"") -> 0.019602226 | D20: Primer pedido de carbón y leña, especias, salsas, desechables compostables y la primera carga de gas | E20: Sí
A21: Fianza de la cocina de apoyo | B21: =IFERROR(IF('0. Supuestos'!$B$24="","",'0. Supuestos'!$B$24*'0. Supuestos'!$B$25),"") -> 2000 | C21: =IFERROR(B21/$B$26,"") -> 0.026136302 | D21: =IFERROR(""&TEXT('0. Supuestos'!$B$25,"0")&" meses de renta, al tipo de la hoja de Supuestos. Es un activo recuperable al cerrar: ni se amortiza ni lleva IVA","") -> 2 meses de renta, al tipo de la hoja de Supuestos. Es un activo recuperable al cerrar: ni se amortiza ni lleva IVA | E21: No
A22: Cuota de la cocina de apoyo de los meses previos al arranque | B22: =IFERROR(IF('0. Supuestos'!$B$24="","",'0. Supuestos'!$B$24*'0. Supuestos'!$B$54),"") -> 1000 | C22: =IFERROR(B22/$B$26,"") -> 0.013068151 | D22: =IFERROR("Renta "&IF('0. Supuestos'!$B$54=1,"del mes","de los "&TEXT('0. Supuestos'!$B$54,"0")&" meses")&" de puesta en marcha (pruebas de menú y degustaciones). NO se solapa con el P&L, que arranca el día de la apertura: los doce meses del P&L son los doce de explotación","") -> Renta del mes de puesta en marcha (pruebas de menú y degustaciones). NO se solapa con el P&L, que arranca el día de la apertura: los doce meses del P&L son los doce de explotación | E22: Sí
A23: Imprevistos de la compra y preparación de la furgoneta | B23: =IFERROR(IF(COUNT(B7,B8)=0,"",ROUND((B7+B8)*'0. Supuestos'!$B$55,0)),"") -> 1696 | C23: =IFERROR(B23/$B$26,"") -> 0.022163584 | D23: =IFERROR("Al "&TEXT('0. Supuestos'!$B$55,"0%")&" de las partidas de la furgoneta de este bloque (Furgoneta frigorífica usada con certificado ATP y Rotulación, estanterías y anclajes), no del bloque entero: el resto de partidas del bloque quedan fuera. Un banco no financia una compra así "&"sin colchón: el porcentaje está en la hoja de Supuestos","") -> Al 8% de las partidas de la furgoneta de este bloque (Furgoneta frigorífica usada con certificado ATP y Rotulación, estanterías y anclajes), no del bloque entero: el resto de partidas del bloque quedan fuera. Un banco no financia una compra así sin colchón: el porcentaje está en la hoja de Supuestos | E23: Sí
A24: FONDO DE MANIOBRA | B24: =IFERROR(IF(B25="","",B25),"") -> 21925.92 | C24: =IFERROR(B24/$B$26,"") -> 0.28653123
A25: Colchón operativo hasta alcanzar el equilibrio | B25: =IFERROR(IF('0. Supuestos'!$B$35*('PyG 3 Años'!$B$38-'PyG 3 Años'!$B$36)=0,"",'0. Supuestos'!$B$35*('PyG 3 Años'!$B$38-'PyG 3 Años'!$B$36)/12),"") -> 21925.92 | C25: =IFERROR(B25/$B$26,"") -> 0.28653123 | D25: =IFERROR("Cubre "&TEXT('0. Supuestos'!$B$35,"0")&IF('0. Supuestos'!$B$35=1," mes"," meses")&" de costes fijos DE CAJA del año 1 (los del P&L menos la amortización, que no se paga), que es el mínimo que exigen las Instrucciones de este libro","") -> Cubre 3 meses de costes fijos DE CAJA del año 1 (los del P&L menos la amortización, que no se paga), que es el mínimo que exigen las Instrucciones de este libro | E25: No
A26: INVERSIÓN TOTAL (suma de los bloques) | B26: =IFERROR(B6+B24,"") -> 76521.92 | D26: =IFERROR("Los porcentajes de la columna C se leen sobre esta cifra, que incluye el fondo de maniobra ("&TEXT(C24,"0%")&" del total). Para comparar el desglose con otro plan, usa la fila de CAPEX de abajo.","") -> Los porcentajes de la columna C se leen sobre esta cifra, que incluye el fondo de maniobra (29% del total). Para comparar el desglose con otro plan, usa la fila de CAPEX de abajo.
A27: CAPEX (inversión sin el fondo de maniobra) | B27: =IFERROR(B26-B24,"") -> 54596 | D27: Es lo que se compra: furgoneta, equipamiento, lanzamiento y gastos de constitución. El colchón de caja no es inversión, es circulante
A28: IVA soportado sobre la inversión (recuperable) | B28: =IFERROR(IF(B26="","",SUMIF($E$7:$E$23,"Sí",$B$7:$B$23)*'0. Supuestos'!$B$41),"") -> 10835.16 | D28: =IFERROR("Al "&TEXT('0. Supuestos'!$B$41,"0%")&" sobre las partidas marcadas con «Sí» en la columna de IVA. Las tasas y licencias no están sujetas y los seguros están exentos (art. 20.Uno.16 LIVA). Las tasas y aranceles registrales no llevan IVA; los honorarios de notaría y gestoría sí "&"(21 %, deducible). Se recupera con el modelo 303, pero hay que adelantarlo","") -> Al 21% sobre las partidas marcadas con «Sí» en la columna de IVA. Las tasas y licencias no están sujetas y los seguros están exentos (art. 20.Uno.16 LIVA). Las tasas y aranceles registrales no llevan IVA; los honorarios de notaría y gestoría sí (21 %, deducible). Se recupera con el modelo 303, pero hay que adelantarlo
A29: NECESIDAD TOTAL DE CAJA AL ARRANQUE | B29: =IFERROR(B26+B28,"") -> 87357.08 | D29: Es la cifra que tiene que cubrir la hoja de Financiación
A30: BASES DE AMORTIZACIÓN (no suman a la inversión)
A31: Furgoneta, rotulación e imprevistos | B31: =IFERROR(IF(B7="","",B7+B8+B23),"") -> 22896 | D31: =IFERROR("Se amortiza en "&TEXT('0. Supuestos'!$B$44,"0")&" años","") -> Se amortiza en 8 años
A32: Maquinaria, mobiliario y equipos | B32: =IFERROR(IF(B9="","",B9+B10+B11+B12+B13+B14+B15+B17),"") -> 20500 | D32: =IFERROR("Se amortiza en "&TEXT('0. Supuestos'!$B$45,"0")&" años","") -> Se amortiza en 10 años
A33: Amortización anual del inmovilizado | B33: =IFERROR(B31/MAX(1,'0. Supuestos'!$B$44)+B32/MAX(1,'0. Supuestos'!$B$45),"") -> 4912 | D33: =IFERROR("No se amortizan, por no ser inmovilizado, Marca, web, fotos, dossier y lanzamiento, Constitución SL + notaría + registro, Declaración responsable, plan APPCC, alérgenos y formación, Stock inicial de producto, Fianza de la cocina de apoyo, "&"Cuota de la cocina de apoyo de los meses previos al arranque ni Colchón operativo hasta alcanzar el equilibrio. Suman "&TEXT(B26-B31-B32,"0")&" € de los "&TEXT(B26,"0")&" € de inversión.","") -> No se amortizan, por no ser inmovilizado, Marca, web, fotos, dossier y lanzamiento, Constitución SL + notaría + registro, Declaración responsable, plan APPCC, alérgenos y formación, Stock inicial de producto, Fianza de la cocina de apoyo, Cuota de la cocina de apoyo de los meses previos al arranque ni Colchón operativo hasta alcanzar el equilibrio. Suman 33126 € de los 76522 € de inversión.

Sheet PyG 3 Años
A1: CUENTA DE RESULTADOS PREVISIONAL — 3 AÑOS
A2: Escenario realista — parrillero / asador para eventos
A4: Concepto | B4: Año 1 | C4: Año 2 | D4: Año 3 | E4: % s/ventas (año 1) | F4: Notas | G4: Tipo de IVA de la línea (%)
A5: INGRESOS
A6: Invitados por evento (media) | B6: =IFERROR(IF('0. Supuestos'!$B$4="","",'0. Supuestos'!$B$4),"") -> 80 | C6: =IFERROR(B6*(1+'0. Supuestos'!$B$7),"") -> 86.4 | D6: =IFERROR(C6*(1+'0. Supuestos'!$B$8),"") -> 90.72 | F6: El crecimiento de los años 2 y 3 está en la hoja de Supuestos
A7: Precio medio por invitado sin IVA | B7: =IFERROR(IF('0. Supuestos'!$B$5="","",'0. Supuestos'!$B$5),"") -> 25 | C7: =IFERROR(IF(B7="","",B7),"") -> 25 | D7: =IFERROR(IF(C7="","",C7),"") -> 25 | F7: Constante en euros del año 1: una subida de precios es una decisión aparte
A8: Eventos al año | B8: =IFERROR(IF('0. Supuestos'!$B$6="","",'0. Supuestos'!$B$6),"") -> 95 | C8: =IFERROR(IF(B8="","",B8),"") -> 95 | D8: =IFERROR(IF(C8="","",C8),"") -> 95
A9: INGRESOS TOTALES (sin IVA) | B9: =IFERROR(IF(B6*B7*B8=0,"",B6*B7*B8),"") -> 190000 | C9: =IFERROR(IF(C6*C7*C8=0,"",C6*C7*C8),"") -> 205200 | D9: =IFERROR(IF(D6*D7*D8=0,"",D6*D7*D8),"") -> 215460 | E9: =IFERROR(IF(B9="","",1),"") -> 1
A10: Ventas de comida (parrilla y asado en directo, entrantes y postre) | B10: =IFERROR(IF(B9="","",B9*$E$10),"") -> 167200 | C10: =IFERROR(IF(C9="","",C9*$E$10),"") -> 180576 | D10: =IFERROR(IF(D9="","",D9*$E$10),"") -> 189604.8 | E10: =IFERROR(IF('0. Supuestos'!$B$11="","",'0. Supuestos'!$B$11),"") -> 0.88 | F10: Carne a la brasa cocinada en el evento, con show de fuego cuando se contrata, entrantes, guarniciones, pan, salsas y postre. Las fiestas son chuletada o costillada por invitado | G10: =IFERROR(IF(B9="","",'0. Supuestos'!$B$39),"") -> 0.1
A11: Ventas de bebida (pack de cerveza, refrescos y vino) | B11: =IFERROR(IF(B9="","",B9*$E$11),"") -> 22800 | C11: =IFERROR(IF(C9="","",C9*$E$11),"") -> 24624 | D11: =IFERROR(IF(D9="","",D9*$E$11),"") -> 25855.2 | E11: =IFERROR(IF('0. Supuestos'!$B$12="","",'0. Supuestos'!$B$12),"") -> 0.12 | F11: Pack de bebida que contratan sobre todo las celebraciones privadas y las empresas; en las bodas y en las fiestas la bebida suele ponerla el cliente o el recinto | G11: =IFERROR(IF(B9="","",('0. Supuestos'!$B$62*((1-'0. Supuestos'!$B$16)*'0. Supuestos'!$B$63+'0. Supuestos'!$B$16*'0. Supuestos'!$B$40)+(1-'0. Supuestos'!$B$62)*'0. Supuestos'!$B$39)),"") -> 0.1033
A12: COSTES VARIABLES
A13: Coste de mercancía — comida | B13: =IFERROR(IF(B9="","",B9*'0. Supuestos'!$B$11*'0. Supuestos'!$B$13),"") -> 53504 | C13: =IFERROR(IF(C9="","",C9*'0. Supuestos'!$B$11*'0. Supuestos'!$B$13),"") -> 57784.32 | D13: =IFERROR(IF(D9="","",D9*'0. Supuestos'!$B$11*'0. Supuestos'!$B$13),"") -> 60673.536 | E13: =IFERROR(B13/$B$9,"") -> 0.2816 | F13: =IFERROR("Al "&TEXT('0. Supuestos'!$B$13,"0%")&" de las ventas de COMIDA, no del total: la bebida tiene su propia línea","") -> Al 32% de las ventas de COMIDA, no del total: la bebida tiene su propia línea | G13: =IFERROR(IF(B9="","",'0. Supuestos'!$B$39),"") -> 0.1
A14: Coste de mercancía — bebida | B14: =IFERROR(IF(B9="","",B9*'0. Supuestos'!$B$12*'0. Supuestos'!$B$14),"") -> 6840 | C14: =IFERROR(IF(C9="","",C9*'0. Supuestos'!$B$12*'0. Supuestos'!$B$14),"") -> 7387.2 | D14: =IFERROR(IF(D9="","",D9*'0. Supuestos'!$B$12*'0. Supuestos'!$B$14),"") -> 7756.56 | E14: =IFERROR(B14/$B$9,"") -> 0.036 | F14: =IFERROR("Al "&TEXT('0. Supuestos'!$B$14,"0%")&" de las ventas de BEBIDA","") -> Al 30% de las ventas de BEBIDA | G14: =IFERROR(IF(B9="","",('0. Supuestos'!$B$62*'0. Supuestos'!$B$40+(1-'0. Supuestos'!$B$62)*'0. Supuestos'!$B$39)),"") -> 0.166
A15: Consumibles y envases | B15: =IFERROR(IF(B9="","",B9*'0. Supuestos'!$B$15),"") -> 8550 | C15: =IFERROR(IF(C9="","",C9*'0. Supuestos'!$B$15),"") -> 9234 | D15: =IFERROR(IF(D9="","",D9*'0. Supuestos'!$B$15),"") -> 9695.7 | E15: =IFERROR(B15/$B$9,"") -> 0.045 | G15: =IFERROR(IF(B9="","",'0. Supuestos'!$B$41),"") -> 0.21
A16: Comisiones del asado para llevar | B16: =IFERROR(IF(B9="","",B9*'0. Supuestos'!$B$16*'0. Supuestos'!$B$17),"") -> 950 | C16: =IFERROR(IF(C9="","",C9*'0. Supuestos'!$B$16*'0. Supuestos'!$B$17),"") -> 1026 | D16: =IFERROR(IF(D9="","",D9*'0. Supuestos'!$B$16*'0. Supuestos'!$B$17),"") -> 1077.3 | E16: =IFERROR(B16/$B$9,"") -> 0.005 | F16: Sobre las ventas DEL CANAL. Con 0 % de asado para llevar en Supuestos, esta línea vale cero | G16: =IFERROR(IF(B9="","",'0. Supuestos'!$B$41),"") -> 0.21
A17: Comisiones de los medios de pago | B17: =IFERROR(IF(B9="","",B9*'0. Supuestos'!$B$18),"") -> 950 | C17: =IFERROR(IF(C9="","",C9*'0. Supuestos'!$B$18),"") -> 1026 | D17: =IFERROR(IF(D9="","",D9*'0. Supuestos'!$B$18),"") -> 1077.3 | E17: =IFERROR(B17/$B$9,"") -> 0.005 | F17: Las comisiones de los medios de pago están EXENTAS de IVA (art. 20.Uno.18 LIVA): no se deduce nada por ellas | G17: 0
A18: Varios e imprevistos | B18: =IFERROR(IF(B9="","",B9*'0. Supuestos'!$B$28),"") -> 9500 | C18: =IFERROR(IF(C9="","",C9*'0. Supuestos'!$B$28),"") -> 10260 | D18: =IFERROR(IF(D9="","",D9*'0. Supuestos'!$B$28),"") -> 10773 | E18: =IFERROR(B18/$B$9,"") -> 0.05 | F18: =IFERROR("Al "&TEXT('0. Supuestos'!$B$28,"0%")&" de las ventas. Es un coste VARIABLE: sube y baja con la facturación, así que no puede vivir en los costes fijos","") -> Al 5% de las ventas. Es un coste VARIABLE: sube y baja con la facturación, así que no puede vivir en los costes fijos | G18: =IFERROR(IF(B9="","",'0. Supuestos'!$B$41),"") -> 0.21
A19: TOTAL COSTES VARIABLES | B19: =IFERROR(IF(B9="","",SUM(B13:B18)),"") -> 80294 | C19: =IFERROR(IF(C9="","",SUM(C13:C18)),"") -> 86717.52 | D19: =IFERROR(IF(D9="","",SUM(D13:D18)),"") -> 91053.396 | E19: =IFERROR(B19/$B$9,"") -> 0.4226
A20: MARGEN BRUTO | B20: =IFERROR(IF(B9="","",B9-B19),"") -> 109706 | C20: =IFERROR(IF(C9="","",C9-C19),"") -> 118482.48 | D20: =IFERROR(IF(D9="","",D9-D19),"") -> 124406.6 | E20: =IFERROR(B20/$B$9,"") -> 0.5774
A21: COSTES FIJOS
A22: Cuota de la cocina de apoyo compartida | B22: =IFERROR(IF(B9="","",'0. Supuestos'!$B$24*12),"") -> 12000 | C22: =IFERROR(IF(C9="","",B22*(1+'0. Supuestos'!$B$48)),"") -> 12000 | D22: =IFERROR(IF(D9="","",C22*(1+'0. Supuestos'!$B$48)),"") -> 12000 | E22: =IFERROR(B22/$B$9,"") -> 0.063157895 | F22: El importe mensual está en la hoja de Supuestos; aquí se multiplica por doce. Es el contrato de uso de una cocina de apoyo compartida y autorizada (horas de cocina, cámara para la carne y almacén de parrillas, carbón y remolque). El mes previo al primer evento está en la hoja de Inversión y NO se cuenta dos veces | G22: =IFERROR(IF(B9="","",'0. Supuestos'!$B$41),"") -> 0.21
A23: Personal (nóminas + Seguridad Social) | B23: =IFERROR(IF(B9="","",'Personal'!$G$9),"") -> 57982.68 | C23: =IFERROR(IF(C9="","",'Personal'!$B$13),"") -> 63982.68 | D23: =IFERROR(IF(D9="","",'Personal'!$B$14),"") -> 69982.68 | E23: =IFERROR(B23/$B$9,"") -> 0.305172 | F23: Sale de la hoja de Personal: es el MISMO número, no una estimación aparte. Los años 2 y 3 suman las INCORPORACIONES declaradas en esa hoja, no un porcentaje de volumen | G23: 0
A24: Suministros (consumos propios fuera de la cuota) | B24: =IFERROR(IF(B9="","",'0. Supuestos'!$B$26*12),"") -> 600 | C24: =IFERROR(IF(C9="","",B24*(1+'0. Supuestos'!$B$48)),"") -> 600 | D24: =IFERROR(IF(D9="","",C24*(1+'0. Supuestos'!$B$48)),"") -> 600 | E24: =IFERROR(B24/$B$9,"") -> 0.0031578947 | F24: Consumos propios fuera de la cuota de la cocina. El carbón y el gas del plan B van en los consumibles. Va al 21 % de IVA | G24: =IFERROR(IF(B9="","",'0. Supuestos'!$B$41),"") -> 0.21
A25: Seguros (RC + multirriesgo) | B25: =IFERROR(IF(B9="","",'0. Supuestos'!$B$27),"") -> 1950 | C25: =IFERROR(IF(C9="","",B25*(1+'0. Supuestos'!$B$48)),"") -> 1950 | D25: =IFERROR(IF(D9="","",C25*(1+'0. Supuestos'!$B$48)),"") -> 1950 | E25: =IFERROR(B25/$B$9,"") -> 0.010263158 | F25: Las operaciones de seguro están EXENTAS de IVA (art. 20.Uno.16 LIVA): la prima no lleva IVA deducible | G25: 0
A26: Asesoría fiscal y laboral (nóminas de fijos discontinuos) | B26: 1800 | C26: =IFERROR(IF(C9="","",B26*(1+'0. Supuestos'!$B$48)),"") -> 1800 | D26: =IFERROR(IF(D9="","",C26*(1+'0. Supuestos'!$B$48)),"") -> 1800 | E26: =IFERROR(B26/$B$9,"") -> 0.0094736842 | F26: Contabilidad, impuestos de la SL y nóminas de los fijos discontinuos de cada mes con llamamientos | G26: =IFERROR(IF(B9="","",'0. Supuestos'!$B$41),"") -> 0.21
A27: Furgoneta y remolque: mantenimiento, ITV e inspección ATP | B27: 1400 | C27: =IFERROR(IF(C9="","",B27*(1+'0. Supuestos'!$B$48)),"") -> 1400 | D27: =IFERROR(IF(D9="","",C27*(1+'0. Supuestos'!$B$48)),"") -> 1400 | E27: =IFERROR(B27/$B$9,"") -> 0.0073684211 | F27: Taller, neumáticos, ITV de la furgoneta y del remolque y la inspección periódica del certificado ATP del equipo de frío (RD 237/2000) | G27: =IFERROR(IF(B9="","",'0. Supuestos'!$B$41),"") -> 0.21
A28: Marketing y publicidad | B28: 4500 | C28: =IFERROR(IF(C9="","",B28*(1+'0. Supuestos'!$B$48)),"") -> 4500 | D28: =IFERROR(IF(D9="","",C28*(1+'0. Supuestos'!$B$48)),"") -> 4500 | E28: =IFERROR(B28/$B$9,"") -> 0.023684211 | F28: Directorios de bodas, Google Ads local, redes sociales y una feria al año | G28: =IFERROR(IF(B9="","",'0. Supuestos'!$B$41),"") -> 0.21
A29: Software de gestión comercial, CRM y teléfono | B29: 900 | C29: =IFERROR(IF(C9="","",B29*(1+'0. Supuestos'!$B$48)),"") -> 900 | D29: =IFERROR(IF(D9="","",C29*(1+'0. Supuestos'!$B$48)),"") -> 900 | E29: =IFERROR(B29/$B$9,"") -> 0.0047368421 | F29: Presupuestos, agenda de eventos, CRM de clientes y línea de teléfono | G29: =IFERROR(IF(B9="","",'0. Supuestos'!$B$41),"") -> 0.21
A30: Mantenimiento de extintores y revisión del gas | B30: 170 | C30: =IFERROR(IF(C9="","",B30*(1+'0. Supuestos'!$B$48)),"") -> 170 | D30: =IFERROR(IF(D9="","",C30*(1+'0. Supuestos'!$B$48)),"") -> 170 | E30: =IFERROR(B30/$B$9,"") -> 0.00089473684 | F30: Mantenimiento anual de los extintores por una empresa mantenedora y revisión de reguladores y tubos flexibles del plan B de gas. Estimación del kit | G30: =IFERROR(IF(B9="","",'0. Supuestos'!$B$41),"") -> 0.21
A31: Uniformes, EPI y lavandería | B31: 500 | C31: =IFERROR(IF(C9="","",B31*(1+'0. Supuestos'!$B$48)),"") -> 500 | D31: =IFERROR(IF(D9="","",C31*(1+'0. Supuestos'!$B$48)),"") -> 500 | E31: =IFERROR(B31/$B$9,"") -> 0.0026315789 | F31: Chaquetas, delantales de cuero, guantes térmicos y paños: lavado y reposición | G31: =IFERROR(IF(B9="","",'0. Supuestos'!$B$41),"") -> 0.21
A32: Gestión de residuos (cenizas, grasa y aceite) | B32: 250 | C32: =IFERROR(IF(C9="","",B32*(1+'0. Supuestos'!$B$48)),"") -> 250 | D32: =IFERROR(IF(D9="","",C32*(1+'0. Supuestos'!$B$48)),"") -> 250 | E32: =IFERROR(B32/$B$9,"") -> 0.0013157895 | F32: Retirada de cenizas frías y grasa, y gestor autorizado del aceite usado, salvo que la cocina de apoyo lo incluya en la cuota | G32: =IFERROR(IF(B9="","",'0. Supuestos'!$B$41),"") -> 0.21
A33: Prevención de riesgos laborales y vigilancia de la salud | B33: 400 | C33: =IFERROR(IF(C9="","",B33*(1+'0. Supuestos'!$B$48)),"") -> 400 | D33: =IFERROR(IF(D9="","",C33*(1+'0. Supuestos'!$B$48)),"") -> 400 | E33: =IFERROR(B33/$B$9,"") -> 0.0021052632 | F33: Plan de prevención obligatorio (Ley 31/1995): quemaduras, humo, calor y cargas, y reconocimientos médicos de la plantilla | G33: =IFERROR(IF(B9="","",'0. Supuestos'!$B$41),"") -> 0.21
A34: Degustaciones comerciales y pruebas de menú | B34: 800 | C34: =IFERROR(IF(C9="","",B34*(1+'0. Supuestos'!$B$48)),"") -> 800 | D34: =IFERROR(IF(D9="","",C34*(1+'0. Supuestos'!$B$48)),"") -> 800 | E34: =IFERROR(B34/$B$9,"") -> 0.0042105263 | F34: Carne y horas de las pruebas de menú para novios y de las degustaciones a planners y empresas que no se cobran | G34: =IFERROR(IF(B9="","",'0. Supuestos'!$B$41),"") -> 0.21
A35: Afilado y reposición de cuchillería | B35: 200 | C35: =IFERROR(IF(C9="","",B35*(1+'0. Supuestos'!$B$48)),"") -> 200 | D35: =IFERROR(IF(D9="","",C35*(1+'0. Supuestos'!$B$48)),"") -> 200 | E35: =IFERROR(B35/$B$9,"") -> 0.0010526316 | F35: Afilado profesional periódico y reposición de cuchillos y tablas de corte | G35: =IFERROR(IF(B9="","",'0. Supuestos'!$B$41),"") -> 0.21
A36: Amortización del inmovilizado | B36: =IFERROR(IF(B9="","",'Inversión Inicial'!$B$33),"") -> 4912 | C36: =IFERROR(IF(C9="","",B36),"") -> 4912 | D36: =IFERROR(IF(D9="","",B36),"") -> 4912 | E36: =IFERROR(B36/$B$9,"") -> 0.025852632 | F36: Sale de las bases de amortización de la hoja de Inversión: sólo inmovilizado real. NO sube con el IPC: es una cuota sobre el coste HISTÓRICO del inmovilizado | G36: 0
A37: Gastos financieros (intereses del préstamo) | B37: =IFERROR(IF(B9="","",'Financiación'!$B$44),"") -> 4251 | C37: =IFERROR(IF(C9="","",'Financiación'!$B$46),"") -> 4251 | D37: =IFERROR(IF(D9="","",'Financiación'!$B$48),"") -> 3504.3776 | E37: =IFERROR(B37/$B$9,"") -> 0.022373684 | F37: Sólo los INTERESES son gasto. La devolución del principal va en la hoja de Tesorería | G37: 0
A38: TOTAL COSTES FIJOS | B38: =IFERROR(IF(B9="","",SUM(B22:B37)),"") -> 92615.68 | C38: =IFERROR(IF(C9="","",SUM(C22:C37)),"") -> 98615.68 | D38: =IFERROR(IF(D9="","",SUM(D22:D37)),"") -> 103869.06 | E38: =IFERROR(B38/$B$9,"") -> 0.48745095
A39: IVA soportado de los costes variables | B39: =IFERROR(IF(B9="","",SUMPRODUCT(B13:B18,G13:G18)),"") -> 10475.84 | C39: =IFERROR(IF(C9="","",SUMPRODUCT(C13:C18,G13:G18)),"") -> 11313.907 | D39: =IFERROR(IF(D9="","",SUMPRODUCT(D13:D18,G13:G18)),"") -> 11879.603 | F39: Cada línea a SU tipo, leído de la columna de al lado. Es lo que la hoja de Tesorería paga de más a los proveedores y luego se deduce
A40: IVA soportado de los costes fijos | B40: =IFERROR(IF(B9="","",SUMPRODUCT(B22:B37,G22:G37)),"") -> 4939.2 | C40: =IFERROR(IF(C9="","",SUMPRODUCT(C22:C37,G22:G37)),"") -> 4939.2 | D40: =IFERROR(IF(D9="","",SUMPRODUCT(D22:D37,G22:G37)),"") -> 4939.2
A41: RESULTADO ANTES DE IMPUESTOS | B41: =IFERROR(IF(B9="","",B20-B38),"") -> 17090.32 | C41: =IFERROR(IF(C9="","",C20-C38),"") -> 19866.8 | D41: =IFERROR(IF(D9="","",D20-D38),"") -> 20537.546 | E41: =IFERROR(B41/$B$9,"") -> 0.089949053
A42: Bases negativas pendientes al inicio | B42: =IFERROR(IF(B9="","",'0. Supuestos'!$B$42),"") -> 0 | C42: =IFERROR(IF(C9="","",B47),"") -> 0 | D42: =IFERROR(IF(D9="","",C47),"") -> 0 | F42: Art. 26 LIS: las pérdidas de un ejercicio se compensan con los beneficios de los siguientes
A43: Base imponible (después de compensar) | B43: =IFERROR(IF(B9="","",MAX(0,B41-B42)),"") -> 17090.32 | C43: =IFERROR(IF(C9="","",MAX(0,C41-C42)),"") -> 19866.8 | D43: =IFERROR(IF(D9="","",MAX(0,D41-D42)),"") -> 20537.546
A44: Ejercicios con base positiva (acumulado) | B44: =IFERROR(IF(B9="","",IF(B43>0,1,0)),"") -> 1 | C44: =IFERROR(IF(C9="","",B44+IF(C43>0,1,0)),"") -> 2 | D44: =IFERROR(IF(D9="","",C44+IF(D43>0,1,0)),"") -> 3
A45: Tipo de Impuesto de Sociedades aplicado | B45: =IFERROR(IF(B9="","",IF(B43<=0,"",IF(B44<=2,'0. Supuestos'!$B$37,'0. Supuestos'!$B$38))),"") -> 0.15 | C45: =IFERROR(IF(C9="","",IF(C43<=0,"",IF(C44<=2,'0. Supuestos'!$B$37,'0. Supuestos'!$B$38))),"") -> 0.15 | D45: =IFERROR(IF(D9="","",IF(D43<=0,"",IF(D44<=2,'0. Supuestos'!$B$37,'0. Supuestos'!$B$38))),"") -> 0.25 | F45: Art. 29.1 LIS: el 15 % de entidad de nueva creación se aplica al PRIMER ejercicio con base positiva y al SIGUIENTE, no al primer año de vida. El libro lo aproxima contando los dos primeros ejercicios con base positiva
A46: Impuesto de Sociedades | B46: =IFERROR(IF(B9="","",IF(B45="",0,B43*B45)),"") -> 2563.548 | C46: =IFERROR(IF(C9="","",IF(C45="",0,C43*C45)),"") -> 2980.02 | D46: =IFERROR(IF(D9="","",IF(D45="",0,D43*D45)),"") -> 5134.3866
A47: Bases negativas pendientes al cierre | B47: =IFERROR(IF(B9="","",MAX(0,B42-B41)),"") -> 0 | C47: =IFERROR(IF(C9="","",MAX(0,C42-C41)),"") -> 0 | D47: =IFERROR(IF(D9="","",MAX(0,D42-D41)),"") -> 0
A48: RESULTADO NETO | B48: =IFERROR(IF(B9="","",B41-B46),"") -> 14526.772 | C48: =IFERROR(IF(C9="","",C41-C46),"") -> 16886.78 | D48: =IFERROR(IF(D9="","",D41-D46),"") -> 15403.16 | E48: =IFERROR(B48/$B$9,"") -> 0.076456695
A49: RATIOS CLAVE
A50: Ratio | B50: Año 1 | C50: Año 2 | D50: Año 3 | E50: Umbral | F50: Comentario
A51: Margen bruto / Ventas | B51: =IFERROR(IF(B9="","",B20/B9),"") -> 0.5774 | C51: =IFERROR(IF(C9="","",C20/C9),"") -> 0.5774 | D51: =IFERROR(IF(D9="","",D20/D9),"") -> 0.5774 | E51: 0.55 | F51: Los costes variables de la parrilla incluyen carbón, leña, desechables, combustible y cánones de fincas además de la mercancía: un margen bruto por debajo del 55 % no paga la plantilla. Estimación del kit
A52: Coste de mercancía (comida + bebida) | B52: =IFERROR(IF(B9="","",B13+B14),"") -> 60344 | C52: =IFERROR(IF(C9="","",C13+C14),"") -> 65171.52 | D52: =IFERROR(IF(D9="","",D13+D14),"") -> 68430.096
A53: Coste de mercancía / Ventas | B53: =IFERROR(IF(B9="","",B52/B9),"") -> 0.3176 | C53: =IFERROR(IF(C9="","",C52/C9),"") -> 0.3176 | D53: =IFERROR(IF(D9="","",D52/D9),"") -> 0.3176 | E53: 0.34 | F53: Techo de la mercancía (comida y bebida) sobre ventas: el vacuno es caro y su precio se mueve. Estimación del kit
A54: Coste de personal / Ventas | B54: =IFERROR(IF(B9="","",B23/B9),"") -> 0.305172 | C54: =IFERROR(IF(C9="","",C23/C9),"") -> 0.31180643 | D54: =IFERROR(IF(D9="","",D23/D9),"") -> 0.3248059 | E54: 0.36 | F54: Techo del personal sobre ventas: montaje, brasa, servicio y recogida en cada evento. Estimación del kit
A55: Cocina de apoyo / Ventas | B55: =IFERROR(IF(B9="","",B22/B9),"") -> 0.063157895 | C55: =IFERROR(IF(C9="","",C22/C9),"") -> 0.058479532 | D55: =IFERROR(IF(D9="","",D22/D9),"") -> 0.055694793 | E55: 0.08 | F55: Techo de la cuota de la cocina de apoyo sobre las ventas: estimación del kit
A56: Resultado neto / Ventas | B56: =IFERROR(IF(B9="","",B48/B9),"") -> 0.076456695 | C56: =IFERROR(IF(C9="","",C48/C9),"") -> 0.08229425 | D56: =IFERROR(IF(D9="","",D48/D9),"") -> 0.071489649 | E56: 0.04 | F56: Suelo de resultado neto para que el plan se sostenga: estimación del kit
A57: Punto de equilibrio alcanzado | B57: =IFERROR(IF(B9="","",IF(B9>='Punto Equilibrio'!$B$16,"Sí","No")),"") -> Sí | C57: =IFERROR(IF(C9="","",IF(C9>='Punto Equilibrio'!$C$16,"Sí","No")),"") -> Sí | D57: =IFERROR(IF(D9="","",IF(D9>='Punto Equilibrio'!$D$16,"Sí","No")),"") -> Sí | F57: Compara las ventas de CADA año con el umbral de ese mismo año, que calcula la hoja de Punto de Equilibrio con los costes fijos del año
A59: Todas las cifras van SIN IVA. Las columnas de los años 2 y 3 están en euros del año 1 salvo que subas la actualización de costes en la hoja de Supuestos. La columna «Tipo de IVA de la línea» dice, en las líneas de VENTA, a qué tipo se repercute cada una, y en las de COSTE a qué tipo se compra la partida. La lee la hoja de Tesorería: los seguros y las comisiones de los medios de pago están exentos, y las nóminas, la amortización y los intereses no llevan IVA.

Sheet Punto Equilibrio
A1: ANÁLISIS DE PUNTO DE EQUILIBRIO
A2: Punto de equilibrio — parrillero / asador para eventos
A4: Variable | B4: Año 1 | C4: Año 2 | D4: Año 3 | E4: Notas
A5: DATOS BASE POR AÑO
A6: Costes fijos anuales | B6: =IFERROR(IF('PyG 3 Años'!$B$9="","",'PyG 3 Años'!$B$38),"") -> 92615.68 | C6: =IFERROR(IF('PyG 3 Años'!$C$9="","",'PyG 3 Años'!$C$38),"") -> 98615.68 | D6: =IFERROR(IF('PyG 3 Años'!$D$9="","",'PyG 3 Años'!$D$38),"") -> 103869.06 | E6: Los MISMOS costes fijos del P&L. Cada año tiene los suyos: por eso el umbral no puede ser uno solo para los tres
A7: Costes fijos mensuales | B7: =IFERROR(IF('PyG 3 Años'!$B$9="","",B6/12),"") -> 7717.9733 | C7: =IFERROR(IF('PyG 3 Años'!$C$9="","",C6/12),"") -> 8217.9733 | D7: =IFERROR(IF('PyG 3 Años'!$D$9="","",D6/12),"") -> 8655.7548
A8: Precio medio por invitado sin IVA | B8: =IFERROR(IF('PyG 3 Años'!$B$9="","",'PyG 3 Años'!$B$7),"") -> 25 | C8: =IFERROR(IF('PyG 3 Años'!$C$9="","",'PyG 3 Años'!$C$7),"") -> 25 | D8: =IFERROR(IF('PyG 3 Años'!$D$9="","",'PyG 3 Años'!$D$7),"") -> 25
A9: Coste variable por invitado | B9: =IFERROR(IF('PyG 3 Años'!$B$9="","",'PyG 3 Años'!$B$19/('PyG 3 Años'!$B$6*'PyG 3 Años'!$B$8)),"") -> 10.565 | C9: =IFERROR(IF('PyG 3 Años'!$C$9="","",'PyG 3 Años'!$C$19/('PyG 3 Años'!$C$6*'PyG 3 Años'!$C$8)),"") -> 10.565 | D9: =IFERROR(IF('PyG 3 Años'!$D$9="","",'PyG 3 Años'!$D$19/('PyG 3 Años'!$D$6*'PyG 3 Años'!$D$8)),"") -> 10.565 | E9: Sale del total de costes variables del P&L, no de una estimación aparte. Incluye los varios e imprevistos, que son un porcentaje de las ventas
A10: Margen de contribución por invitado | B10: =IFERROR(IF('PyG 3 Años'!$B$9="","",B8-B9),"") -> 14.435 | C10: =IFERROR(IF('PyG 3 Años'!$C$9="","",C8-C9),"") -> 14.435 | D10: =IFERROR(IF('PyG 3 Años'!$D$9="","",D8-D9),"") -> 14.435 | E10: Precio por invitado menos coste variable unitario
A11: Eventos al año | B11: =IFERROR(IF('PyG 3 Años'!$B$9="","",'PyG 3 Años'!$B$8),"") -> 95 | C11: =IFERROR(IF('PyG 3 Años'!$C$9="","",'PyG 3 Años'!$C$8),"") -> 95 | D11: =IFERROR(IF('PyG 3 Años'!$D$9="","",'PyG 3 Años'!$D$8),"") -> 95 | E11: El mismo calendario que el P&L y que los escenarios
A12: Devolución de principal del año (cuota) | B12: =IFERROR(IF('PyG 3 Años'!$B$9="","",'Financiación'!$B$45),"") -> 0 | C12: =IFERROR(IF('PyG 3 Años'!$C$9="","",'Financiación'!$B$47),"") -> 11486.499 | D12: =IFERROR(IF('PyG 3 Años'!$D$9="","",'Financiación'!$B$49),"") -> 12233.121 | E12: El principal NO es gasto del P&L, pero sale de la caja. Sin él, el umbral de equilibrio se publica por debajo del real
A13: PUNTO DE EQUILIBRIO CONTABLE (incluye amortización)
A14: Invitados necesarios al año | B14: =IFERROR(IF('PyG 3 Años'!$B$9="","",IF(B10<=0,"",B6/B10)),"") -> 6416.0499 | C14: =IFERROR(IF('PyG 3 Años'!$C$9="","",IF(C10<=0,"",C6/C10)),"") -> 6831.7063 | D14: =IFERROR(IF('PyG 3 Años'!$D$9="","",IF(D10<=0,"",D6/D10)),"") -> 7195.6396
A15: Invitados necesarios por evento | B15: =IFERROR(IF('PyG 3 Años'!$B$9="","",B14/B11),"") -> 67.537367 | C15: =IFERROR(IF('PyG 3 Años'!$C$9="","",C14/C11),"") -> 71.912698 | D15: =IFERROR(IF('PyG 3 Años'!$D$9="","",D14/D11),"") -> 75.743575
A16: Ingresos necesarios al año | B16: =IFERROR(IF('PyG 3 Años'!$B$9="","",B14*B8),"") -> 160401.25 | C16: =IFERROR(IF('PyG 3 Años'!$C$9="","",C14*C8),"") -> 170792.66 | D16: =IFERROR(IF('PyG 3 Años'!$D$9="","",D14*D8),"") -> 179890.99
A17: PUNTO DE EQUILIBRIO DE CAJA (incluye la cuota del préstamo)
A18: Costes fijos de caja + principal del año | B18: =IFERROR(IF('PyG 3 Años'!$B$9="","",B6-'PyG 3 Años'!$B$36+B12),"") -> 87703.68 | C18: =IFERROR(IF('PyG 3 Años'!$C$9="","",C6-'PyG 3 Años'!$C$36+C12),"") -> 105190.18 | D18: =IFERROR(IF('PyG 3 Años'!$D$9="","",D6-'PyG 3 Años'!$D$36+D12),"") -> 111190.18 | E18: Los fijos del P&L sin la amortización (que no se paga) y CON la devolución de principal (que sí). Es el umbral que decide si la caja aguanta
A19: Invitados necesarios al año (caja) | B19: =IFERROR(IF('PyG 3 Años'!$B$9="","",IF(B10<=0,"",B18/B10)),"") -> 6075.7658 | C19: =IFERROR(IF('PyG 3 Años'!$C$9="","",IF(C10<=0,"",C18/C10)),"") -> 7287.1617 | D19: =IFERROR(IF('PyG 3 Años'!$D$9="","",IF(D10<=0,"",D18/D10)),"") -> 7702.8181
A20: Invitados necesarios por evento (caja) | B20: =IFERROR(IF('PyG 3 Años'!$B$9="","",B19/B11),"") -> 63.95543 | C20: =IFERROR(IF('PyG 3 Años'!$C$9="","",C19/C11),"") -> 76.706965 | D20: =IFERROR(IF('PyG 3 Años'!$D$9="","",D19/D11),"") -> 81.082295
A21: Ingresos necesarios al año (caja) | B21: =IFERROR(IF('PyG 3 Años'!$B$9="","",B19*B8),"") -> 151894.15 | C21: =IFERROR(IF('PyG 3 Años'!$C$9="","",C19*C8),"") -> 182179.04 | D21: =IFERROR(IF('PyG 3 Años'!$D$9="","",D19*D8),"") -> 192570.45
A22: CONTRASTE CON EL PLAN
A23: Invitados por evento previstos en el plan | B23: =IFERROR(IF('PyG 3 Años'!$B$9="","",'PyG 3 Años'!$B$6),"") -> 80 | C23: =IFERROR(IF('PyG 3 Años'!$C$9="","",'PyG 3 Años'!$C$6),"") -> 86.4 | D23: =IFERROR(IF('PyG 3 Años'!$D$9="","",'PyG 3 Años'!$D$6),"") -> 90.72
A24: Holgura sobre el equilibrio de CAJA (%) | B24: =IFERROR(IF('PyG 3 Años'!$B$9="","",B23/B20-1),"") -> 0.25087112 | C24: =IFERROR(IF('PyG 3 Años'!$C$9="","",C23/C20-1),"") -> 0.12636447 | D24: =IFERROR(IF('PyG 3 Años'!$D$9="","",D23/D20-1),"") -> 0.11886324 | E24: Cuánto superan tus ventas previstas a las del equilibrio de caja. La caída que aguantas antes de no poder pagar los costes fijos y la cuota es algo menor: con un 25 % de holgura, un 20 %. El mínimo exigible está en la hoja de Supuestos
A25: INTERPRETACIÓN
A26: =IFERROR("Con el precio medio por invitado sin IVA de la fila de arriba necesitas "&TEXT(ROUNDUP(B15,0),"0")&" invitados por evento durante los "&TEXT(B11,"0")&" eventos del año para no perder dinero (equilibrio contable, con la amortización dentro), y "&TEXT(ROUNDUP(B20,0),"0")&" para que la caja aguante (equilibrio de caja: sin la amortización, que no se paga, y con la cuota del préstamo del año"&IF(B12=0,"; este año sólo intereses, porque el préstamo está en carencia","")&"). En las filas «Ingresos necesarios al año» tienes esas mismas cifras en euros.","") -> Con el precio medio por invitado sin IVA de la fila de arriba necesitas 68 invitados por evento durante los 95 eventos del año para no perder dinero (equilibrio contable, con la amortización dentro), y 64 para que la caja aguante (equilibrio de caja: sin la amortización, que no se paga, y con la cuota del préstamo del año; este año sólo intereses, porque el préstamo está en carencia). En las filas «Ingresos necesarios al año» tienes esas mismas cifras en euros.
A28: SENSIBILIDAD DEL PUNTO DE EQUILIBRIO
A29: Invitados por evento necesarios para cubrir costes según el precio medio por invitado (columnas) y el coste variable por invitado (filas). En verde, los que están por debajo de los invitados que prevé el plan.
A31: Invitados por evento necesarios: precio medio por invitado sin IVA (columnas) × coste variable por invitado (filas) | B31: =IFERROR($B$8-2,"") -> 23 | C31: =IFERROR(IF($B$8="","",$B$8),"") -> 25 | D31: =IFERROR($B$8+2,"") -> 27 | E31: =IFERROR($B$8+4,"") -> 29
A32: =IFERROR($B$9*0.85,"") -> 8.98025 | B32: =IFERROR(IF($B$31-$A32<=0,"",$B$6/($B$31-$A32)/$B$11),"") -> 69.537752 | C32: =IFERROR(IF($C$31-$A32<=0,"",$B$6/($C$31-$A32)/$B$11),"") -> 60.856249 | D32: =IFERROR(IF($D$31-$A32<=0,"",$B$6/($D$31-$A32)/$B$11),"") -> 54.101855 | E32: =IFERROR(IF($E$31-$A32<=0,"",$B$6/($E$31-$A32)/$B$11),"") -> 48.697006
A33: =IFERROR($B$9*0.925,"") -> 9.772625 | B33: =IFERROR(IF($B$31-$A33<=0,"",$B$6/($B$31-$A33)/$B$11),"") -> 73.703353 | C33: =IFERROR(IF($C$31-$A33<=0,"",$B$6/($C$31-$A33)/$B$11),"") -> 64.022978 | D33: =IFERROR(IF($D$31-$A33<=0,"",$B$6/($D$31-$A33)/$B$11),"") -> 56.590275 | E33: =IFERROR(IF($E$31-$A33<=0,"",$B$6/($E$31-$A33)/$B$11),"") -> 50.703848
A34: =IFERROR($B$9*1.0,"") -> 10.565 | B34: =IFERROR(IF($B$31-$A34<=0,"",$B$6/($B$31-$A34)/$B$11),"") -> 78.399831 | C34: =IFERROR(IF($C$31-$A34<=0,"",$B$6/($C$31-$A34)/$B$11),"") -> 67.537367 | D34: =IFERROR(IF($D$31-$A34<=0,"",$B$6/($D$31-$A34)/$B$11),"") -> 59.318643 | E34: =IFERROR(IF($E$31-$A34<=0,"",$B$6/($E$31-$A34)/$B$11),"") -> 52.883206
A35: =IFERROR($B$9*1.075,"") -> 11.357375 | B35: =IFERROR(IF($B$31-$A35<=0,"",$B$6/($B$31-$A35)/$B$11),"") -> 83.735575 | C35: =IFERROR(IF($C$31-$A35<=0,"",$B$6/($C$31-$A35)/$B$11),"") -> 71.459994 | D35: =IFERROR(IF($D$31-$A35<=0,"",$B$6/($D$31-$A35)/$B$11),"") -> 62.32342 | E35: =IFERROR(IF($E$31-$A35<=0,"",$B$6/($E$31-$A35)/$B$11),"") -> 55.258324
A36: =IFERROR($B$9*1.15,"") -> 12.14975 | B36: =IFERROR(IF($B$31-$A36<=0,"",$B$6/($B$31-$A36)/$B$11),"") -> 89.850639 | C36: =IFERROR(IF($C$31-$A36<=0,"",$B$6/($C$31-$A36)/$B$11),"") -> 75.866376 | D36: =IFERROR(IF($D$31-$A36<=0,"",$B$6/($D$31-$A36)/$B$11),"") -> 65.648854 | E36: =IFERROR(IF($E$31-$A36<=0,"",$B$6/($E$31-$A36)/$B$11),"") -> 57.856821

Sheet Escenarios
A1: ANÁLISIS DE ESCENARIOS
A4: Métrica | B4: Pesimista | C4: Realista | D4: Optimista | E4: Notas
A5: Invitados por evento | B5: 75 | C5: =IFERROR(IF('PyG 3 Años'!$B$6="","",'PyG 3 Años'!$B$6),"") -> 80 | D5: 85
A6: Precio medio por invitado sin IVA | B6: 23 | C6: =IFERROR(IF('PyG 3 Años'!$B$7="","",'PyG 3 Años'!$B$7),"") -> 25 | D6: 26
A7: Eventos al año | B7: 80 | C7: =IFERROR(IF('PyG 3 Años'!$B$8="","",'PyG 3 Años'!$B$8),"") -> 95 | D7: 110
A8: INGRESOS ANUALES (sin IVA) | B8: =IFERROR(IF(B5*B6*B7=0,"",B5*B6*B7),"") -> 138000 | C8: =IFERROR(IF(C5*C6*C7=0,"",C5*C6*C7),"") -> 190000 | D8: =IFERROR(IF(D5*D6*D7=0,"",D5*D6*D7),"") -> 243100
A9: Coste de mercancía — comida | B9: =IFERROR(IF(B8="","",B8*'0. Supuestos'!$B$11*'0. Supuestos'!$B$13),"") -> 38860.8 | C9: =IFERROR(IF(C8="","",C8*'0. Supuestos'!$B$11*'0. Supuestos'!$B$13),"") -> 53504 | D9: =IFERROR(IF(D8="","",D8*'0. Supuestos'!$B$11*'0. Supuestos'!$B$13),"") -> 68456.96
A10: Coste de mercancía — bebida | B10: =IFERROR(IF(B8="","",B8*'0. Supuestos'!$B$12*'0. Supuestos'!$B$14),"") -> 4968 | C10: =IFERROR(IF(C8="","",C8*'0. Supuestos'!$B$12*'0. Supuestos'!$B$14),"") -> 6840 | D10: =IFERROR(IF(D8="","",D8*'0. Supuestos'!$B$12*'0. Supuestos'!$B$14),"") -> 8751.6
A11: Consumibles y envases | B11: =IFERROR(IF(B8="","",B8*'0. Supuestos'!$B$15),"") -> 6210 | C11: =IFERROR(IF(C8="","",C8*'0. Supuestos'!$B$15),"") -> 8550 | D11: =IFERROR(IF(D8="","",D8*'0. Supuestos'!$B$15),"") -> 10939.5
A12: Comisiones del asado para llevar | B12: =IFERROR(IF(B8="","",B8*'0. Supuestos'!$B$16*'0. Supuestos'!$B$17),"") -> 690 | C12: =IFERROR(IF(C8="","",C8*'0. Supuestos'!$B$16*'0. Supuestos'!$B$17),"") -> 950 | D12: =IFERROR(IF(D8="","",D8*'0. Supuestos'!$B$16*'0. Supuestos'!$B$17),"") -> 1215.5
A13: Comisiones de los medios de pago | B13: =IFERROR(IF(B8="","",B8*'0. Supuestos'!$B$18),"") -> 690 | C13: =IFERROR(IF(C8="","",C8*'0. Supuestos'!$B$18),"") -> 950 | D13: =IFERROR(IF(D8="","",D8*'0. Supuestos'!$B$18),"") -> 1215.5
A14: Varios e imprevistos | B14: =IFERROR(IF(B8="","",B8*'0. Supuestos'!$B$28),"") -> 6900 | C14: =IFERROR(IF(C8="","",C8*'0. Supuestos'!$B$28),"") -> 9500 | D14: =IFERROR(IF(D8="","",D8*'0. Supuestos'!$B$28),"") -> 12155
A15: TOTAL COSTES VARIABLES | B15: =IFERROR(IF(B8="","",SUM(B9:B14)),"") -> 58318.8 | C15: =IFERROR(IF(C8="","",SUM(C9:C14)),"") -> 80294 | D15: =IFERROR(IF(D8="","",SUM(D9:D14)),"") -> 102734.06
A16: MARGEN BRUTO | B16: =IFERROR(IF(B8="","",B8-B15),"") -> 79681.2 | C16: =IFERROR(IF(C8="","",C8-C15),"") -> 109706 | D16: =IFERROR(IF(D8="","",D8-D15),"") -> 140365.94
A17: COSTES FIJOS (los del P&L) | B17: =IFERROR(IF(B8="","",'PyG 3 Años'!$B$38),"") -> 92615.68 | C17: =IFERROR(IF(C8="","",'PyG 3 Años'!$B$38),"") -> 92615.68 | D17: =IFERROR(IF(D8="","",'PyG 3 Años'!$B$38),"") -> 92615.68 | E17: Los costes fijos no cambian con el escenario: por eso son fijos
A18: RESULTADO ANTES DE IMPUESTOS | B18: =IFERROR(IF(B8="","",B16-B17),"") -> -12934.48 | C18: =IFERROR(IF(C8="","",C16-C17),"") -> 17090.32 | D18: =IFERROR(IF(D8="","",D16-D17),"") -> 47750.26
A19: Impuesto de Sociedades | B19: =IFERROR(IF(B8="","",MAX(0,B18-'0. Supuestos'!$B$42)*'0. Supuestos'!$B$37),"") -> 0 | C19: =IFERROR(IF(C8="","",MAX(0,C18-'0. Supuestos'!$B$42)*'0. Supuestos'!$B$37),"") -> 2563.548 | D19: =IFERROR(IF(D8="","",MAX(0,D18-'0. Supuestos'!$B$42)*'0. Supuestos'!$B$37),"") -> 7162.539 | E19: Al tipo de entidad de nueva creación, compensando las bases negativas anteriores
A20: RESULTADO NETO | B20: =IFERROR(IF(B8="","",B18-B19),"") -> -12934.48 | C20: =IFERROR(IF(C8="","",C18-C19),"") -> 14526.772 | D20: =IFERROR(IF(D8="","",D18-D19),"") -> 40587.721
A21: Invitados por evento para el equilibrio | B21: =IFERROR(IF(B8="","",IF(B6-B15/(B5*B7)<=0,"",B17/(B6-B15/(B5*B7))/B7)),"") -> 87.174591 | C21: =IFERROR(IF(C8="","",IF(C6-C15/(C5*C7)<=0,"",C17/(C6-C15/(C5*C7))/C7)),"") -> 67.537367 | D21: =IFERROR(IF(D8="","",IF(D6-D15/(D5*D7)<=0,"",D17/(D6-D15/(D5*D7))/D7)),"") -> 56.084352
A22: LO QUE CADA ESCENARIO EXIGE
A23: Coste de personal / Ventas | B23: =IFERROR(IF(B8="","",'PyG 3 Años'!$B$23/B8),"") -> 0.42016435 | C23: =IFERROR(IF(C8="","",'PyG 3 Años'!$B$23/C8),"") -> 0.305172 | D23: =IFERROR(IF(D8="","",'PyG 3 Años'!$B$23/D8),"") -> 0.2385137 | E23: La MISMA plantilla en los tres escenarios. Si en el pesimista se dispara, el ajuste hay que hacerlo en la hoja de Personal, no aquí
A24: Invitados al año por jornada equivalente | B24: =IFERROR(IF(B8="","",B5*B7/'Personal'!$C$9),"") -> 3092.7835 | C24: =IFERROR(IF(C8="","",C5*C7/'Personal'!$C$9),"") -> 3917.5258 | D24: =IFERROR(IF(D8="","",D5*D7/'Personal'!$C$9),"") -> 4819.5876 | E24: Invitados que tendría que servir cada jornada completa del cuadro de Personal. En el optimista dice si hace falta contratar
A25: Saldo de caja al cierre del año 1 (estimado, el mismo método en los tres escenarios) | B25: =IFERROR(IF(B8="","",'Inversión Inicial'!$B$25+B20+'PyG 3 Años'!$B$36-'Financiación'!$B$45),"") -> 13903.44 | C25: =IFERROR(IF(C8="","",'Inversión Inicial'!$B$25+C20+'PyG 3 Años'!$B$36-'Financiación'!$B$45),"") -> 41364.692 | D25: =IFERROR(IF(D8="","",'Inversión Inicial'!$B$25+D20+'PyG 3 Años'!$B$36-'Financiación'!$B$45),"") -> 67425.641 | E25: Saldo ESTIMADO: fondo de maniobra más el resultado del año, devolviendo la amortización (que no se paga) y restando el principal del préstamo. No incluye el desfase de cobros y pagos ni la liquidación del IVA, así que las tres columnas se pueden comparar entre sí. En rojo, el escenario se queda sin caja
A26: Saldo real del mes 12 de la hoja de Tesorería (sólo realista) | C26: =IFERROR(IF(C8="","",'Tesorería 12 meses'!$M$22),"") -> 42559.785 | E26: El saldo REAL del caso base, con su desfase de cobros y pagos y su liquidación de IVA. Sólo existe para el escenario realista, que es el único con tesorería mensual propia: por eso no está en la fila de arriba, donde se compararía contra dos estimaciones
A28: La columna «Realista» lee sus tres datos de la hoja de Supuestos, así que reproduce EXACTAMENTE el año 1 del P&L. Los otros dos escenarios usan las mismas tasas de coste: lo único que cambia son los invitados, el precio por invitado y los eventos. Los COSTES FIJOS sí son los mismos en los tres: los varios e imprevistos, que son un porcentaje de las ventas, van arriba con los variables y cada escenario carga los suyos.

Sheet Personal
A1: ESTRUCTURA DE PERSONAL Y COSTES
A2: =IFERROR("Convenio Hostelería — "&TEXT('0. Supuestos'!$B$21,"0")&" pagas + SS "&TEXT('0. Supuestos'!$B$20*100,"0")&" %","") -> Convenio Hostelería — 14 pagas + SS 33 %
A4: Puesto | B4: Personas | C4: Jornada | D4: Bruto mes (€, total del puesto) | E4: Seg. Social a cargo de la empresa (€) | F4: Coste mes (€, total del puesto) | G4: Coste año (€) | H4: Horas/semana por persona | I4: Horas/año del puesto | J4: Notas
A5: Propietario/a — parrillero titular, ventas y compras | B5: 1 | C5: 1 | D5: 1800 | E5: =IFERROR(IF(D5="","",D5*'0. Supuestos'!$B$20),"") -> 594 | F5: =IFERROR(IF(D5="","",D5+E5),"") -> 2394 | G5: =IFERROR(IF(D5="","",F5*MAX(12,'0. Supuestos'!$B$21)),"") -> 33516 | H5: =IFERROR(IF(D5="","",C5*$B$16),"") -> 40 | I5: =IFERROR(IF(D5="","",H5*B5*$B$17),"") -> 1840 | J5: Asa en cada evento, vende, compra la carne y lleva la agenda. Como administrador de la SL cotiza en el régimen de autónomos: confirma con tu gestoría la cuota y si te aplica la reducida de inicio
A6: Segundo parrillero y ayudante (fijo discontinuo) | B6: 1 | C6: 0.3 | D6: 450 | E6: =IFERROR(IF(D6="","",D6*'0. Supuestos'!$B$20),"") -> 148.5 | F6: =IFERROR(IF(D6="","",D6+E6),"") -> 598.5 | G6: =IFERROR(IF(D6="","",F6*MAX(12,'0. Supuestos'!$B$21)),"") -> 8379 | H6: =IFERROR(IF(D6="","",C6*$B$16),"") -> 12 | I6: =IFERROR(IF(D6="","",H6*B6*$B$17),"") -> 552 | J6: Contrato fijo discontinuo (art. 16 del Estatuto de los Trabajadores) al 30 % de jornada en cómputo anual: segunda parrilla en bodas, empresas y fiestas, y preparación en la cocina de apoyo. Bruto a jornada completa: 1.500 € en 14 pagas
A7: Auxiliar de parrilla y montaje (fijo discontinuo) | B7: 1 | C7: 0.32 | D7: 432 | E7: =IFERROR(IF(D7="","",D7*'0. Supuestos'!$B$20),"") -> 142.56 | F7: =IFERROR(IF(D7="","",D7+E7),"") -> 574.56 | G7: =IFERROR(IF(D7="","",F7*MAX(12,'0. Supuestos'!$B$21)),"") -> 8043.84 | H7: =IFERROR(IF(D7="","",C7*$B$16),"") -> 12.8 | I7: =IFERROR(IF(D7="","",H7*B7*$B$17),"") -> 588.8 | J7: Llamado para los eventos medianos y grandes: carga, montaje, brasa, emplatado de la carne y recogida. Bruto a jornada completa: 1.350 €. Nunca como autónomo que te factura: con tu horario y tu dirección es falso autónomo (art. 1.1 ET)
A8: Auxiliar de servicio y emplatado (fijo discontinuo) | B8: 1 | C8: 0.32 | D8: 432 | E8: =IFERROR(IF(D8="","",D8*'0. Supuestos'!$B$20),"") -> 142.56 | F8: =IFERROR(IF(D8="","",D8+E8),"") -> 574.56 | G8: =IFERROR(IF(D8="","",F8*MAX(12,'0. Supuestos'!$B$21)),"") -> 8043.84 | H8: =IFERROR(IF(D8="","",C8*$B$16),"") -> 12.8 | I8: =IFERROR(IF(D8="","",H8*B8*$B$17),"") -> 588.8 | J8: Mismo contrato y mismas horas que el anterior: sirve, repone guarniciones y salsas y recoge. Por encima del SMI en proporción a su jornada
A9: TOTAL PLANTILLA | B9: =IFERROR(IF(COUNT(D5:D8)=0,"",SUM(B5:B8)),"") -> 4 | C9: =IFERROR(IF(COUNT(D5:D8)=0,"",SUM(C5:C8)),"") -> 1.94 | D9: =IFERROR(IF(COUNT(D5:D8)=0,"",SUM(D5:D8)),"") -> 3114 | E9: =IFERROR(IF(COUNT(D5:D8)=0,"",SUM(E5:E8)),"") -> 1027.62 | F9: =IFERROR(IF(COUNT(D5:D8)=0,"",SUM(F5:F8)),"") -> 4141.62 | G9: =IFERROR(IF(COUNT(D5:D8)=0,"",SUM(G5:G8)),"") -> 57982.68 | I9: =IFERROR(IF(COUNT(D5:D8)=0,"",SUM(I5:I8)),"") -> 3569.6
A10: CRECIMIENTO DE LA PLANTILLA (coste escalonado)
A11: Coste anual de las incorporaciones del año 2 (€) | B11: 6000 | J11: Coste ANUAL completo (bruto + Seguridad Social × pagas) de lo que se contrate ese año. El P&L lo suma al coste del año anterior: la plantilla no crece con un porcentaje, crece con personas
A12: Coste anual de las incorporaciones del año 3 (€) | B12: 6000 | J12: Coste ANUAL completo (bruto + Seguridad Social × pagas) de lo que se contrate ese año. El P&L lo suma al coste del año anterior: la plantilla no crece con un porcentaje, crece con personas
A13: Coste de personal del año 2 | B13: =IFERROR(IF(G9="","",G9*(1+'0. Supuestos'!$B$48)+B11),"") -> 63982.68
A14: Coste de personal del año 3 | B14: =IFERROR(IF(B13="","",B13*(1+'0. Supuestos'!$B$48)+B12),"") -> 69982.68
A15: COBERTURA POR HORAS DE SERVICIO
A16: Jornada completa del convenio (horas/semana) | B16: 40 | J16: Art. 34.1 del Estatuto de los Trabajadores; tu convenio provincial puede fijar menos
A17: Semanas trabajadas al año por persona | B17: 46 | J17: 46 semanas: 52 menos las vacaciones (30 días naturales, art. 38 ET), los festivos y las ausencias medias
A18: Horas de trabajo por evento que hay que cubrir | B18: 8 | J18: Horas por evento y persona: carga, viaje, montaje, encendido de la brasa, cocción, servicio, recogida de las cenizas y descarga. Los marinados y el porcionado en la cocina de apoyo van aparte
A19: Personas necesarias a la vez en cada evento | B19: 3 | J19: Personas trabajando a la vez en un evento medio de 80 invitados: el parrillero titular, el segundo parrillero y un auxiliar. En bodas y fiestas entran los dos auxiliares (y un tercero de la bolsa o de una ETT si hace falta); en una celebración privada pequeña bastan dos personas: ajústalo y la hoja te dice si llega la plantilla
A20: Horas de servicio a cubrir al año | B20: =IFERROR(IF(OR(B18="",B19="",'0. Supuestos'!$B$6=""),"",B18*B19*'0. Supuestos'!$B$6),"") -> 2280
A21: Horas contratadas al año | B21: =IFERROR(IF(I9="","",I9),"") -> 3569.6
A22: Cobertura (contratadas / necesarias) | B22: =IFERROR(B21/B20,"") -> 1.565614 | J22: Por debajo del 100 % la plantilla no llega a cubrir el horario que declara el plan: o se contrata más o se recorta el horario
A24: Las columnas «Bruto mes», «Seg. Social», «Coste mes» y «Coste año» son TOTALES de la fila: en un puesto con dos personas incluyen a las dos. «Jornada» es el porcentaje sobre la jornada completa del convenio y sirve para comparar el salario con el suelo legal en proporción. El tipo de Seguridad Social y el número de pagas están en la hoja «0. Supuestos».
A25: El suelo salarial es el MAYOR entre el SMI y el salario de convenio, los dos en la hoja «0. Supuestos»; las jornadas parciales lo llevan en proporción. El convenio aplicable es el PROVINCIAL de hostelería: no existe una tabla salarial estatal única, así que la celda del convenio se entrega vacía para que copies la de tu provincia.

Sheet Instrucciones
A1: INSTRUCCIONES DE USO — Plan financiero Parrillero / Asador para Eventos
A3: CÓMO SE USA ESTE LIBRO
A4: Este plan financiero es un MODELO: sólo se teclea en las celdas VERDES y el resto se recalcula solo.
A5: 1. «0. Supuestos» es la hoja de mando: invitados, precio por invitado sin IVA, eventos, mezcla de comida y bebida, coste de mercancía, alquiler, financiación e impuestos.
A6: 2. Las partidas de la inversión, los costes fijos y la plantilla se teclean en su propia hoja, también en verde. Ningún número se escribe dos veces.
A7: 3. Sólo «Punto Equilibrio» se deriva entera de lo anterior. En las otras tres hojas también hay celdas verdes que puedes tocar: el escenario pesimista y el optimista en «Escenarios», la estacionalidad y la rampa de arranque en «Tesorería 12 meses», y las cuatro fuentes alternativas de financiación en «Financiación». Todo lo demás se calcula.
A8: 4. Todas las cifras van SIN IVA. Para pasar un PVP a precio sin IVA, divide por el tipo que le corresponda: entre 1,10 en el servicio de parrilla (comida y bebida, alcohol incluido: art. 91.Uno.2.2.º de la Ley 37/1992 del IVA) y, cuando se venden para llevar, los alimentos, que son productos alimenticios al tipo reducido por el art. 91.Uno.1.1.º; y entre 1,21 el tipo general, que en hostelería sólo alcanza a lo que sale de la cocina de apoyo como entrega de bienes excluida del reducido: el alcohol y los refrescos, zumos y gaseosas con azúcares o edulcorantes añadidos para llevar o a domicilio (la comida para llevar sigue al 10 %); el libro lo aplica al alcohol del canal de asado para llevar. El tipo de cada línea de venta está en la columna «Tipo de IVA de la línea» del P&L y de ahí salen los cobros, el IVA repercutido y el PVP equivalente. El IVA de la inversión se adelanta y se recupera con el modelo 303.
A9: 5. Si cambias la plantilla, el P&L la lee sola: el coste de personal sale de la hoja «Personal», no de una estimación aparte.
A10: 6. La hoja «Tesorería 12 meses» responde la pregunta que decide una operación bancaria: en qué mes se agota la caja. El saldo mínimo del año nunca puede salir en rojo. Las señales de los particulares (30 % al firmar y 40 % siete días antes) no se modelan: tu caja real será algo mejor.
A11: 7. La hoja «Financiación» cuadra lo que hace falta con lo que se aporta y monta el cuadro de amortización del préstamo. Si la diferencia sale en rojo, el plan no está financiado.
A12: 8. El documento Word de este pack y la calculadora de presupuestos usan las cifras de este Excel: si cambias una celda verde, el Excel manda.
A14: RATIOS QUE AUDITA EL LIBRO
A15: Los umbrales viven en la columna «Umbral» del bloque RATIOS CLAVE del P&L: cámbialos ahí y el semáforo cambia con ellos.
A17: Ratio | B17: Valor del año 1 | C17: Umbral | D17: Estado
A18: Coste de mercancía / Ventas | B18: =IFERROR(IF('PyG 3 Años'!$B$53="","",'PyG 3 Años'!$B$53),"") -> 0.3176 | C18: =IFERROR(IF('PyG 3 Años'!$E$53="","",'PyG 3 Años'!$E$53),"") -> 0.34 | D18: =IFERROR(IF(OR(B18="",C18=""),"",IF(B18<=C18,"CUMPLE","REVISAR")),"") -> CUMPLE
A19: Coste de personal / Ventas | B19: =IFERROR(IF('PyG 3 Años'!$B$54="","",'PyG 3 Años'!$B$54),"") -> 0.305172 | C19: =IFERROR(IF('PyG 3 Años'!$E$54="","",'PyG 3 Años'!$E$54),"") -> 0.36 | D19: =IFERROR(IF(OR(B19="",C19=""),"",IF(B19<=C19,"CUMPLE","REVISAR")),"") -> CUMPLE
A20: Cocina de apoyo / Ventas | B20: =IFERROR(IF('PyG 3 Años'!$B$55="","",'PyG 3 Años'!$B$55),"") -> 0.063157895 | C20: =IFERROR(IF('PyG 3 Años'!$E$55="","",'PyG 3 Años'!$E$55),"") -> 0.08 | D20: =IFERROR(IF(OR(B20="",C20=""),"",IF(B20<=C20,"CUMPLE","REVISAR")),"") -> CUMPLE
A21: Resultado neto / Ventas | B21: =IFERROR(IF('PyG 3 Años'!$B$56="","",'PyG 3 Años'!$B$56),"") -> 0.076456695 | C21: =IFERROR(IF('PyG 3 Años'!$E$56="","",'PyG 3 Años'!$E$56),"") -> 0.04 | D21: =IFERROR(IF(OR(B21="",C21=""),"",IF(B21>=C21,"CUMPLE","REVISAR")),"") -> CUMPLE
A22: Margen bruto / Ventas | B22: =IFERROR(IF('PyG 3 Años'!$B$51="","",'PyG 3 Años'!$B$51),"") -> 0.5774 | C22: =IFERROR(IF('PyG 3 Años'!$E$51="","",'PyG 3 Años'!$E$51),"") -> 0.55 | D22: =IFERROR(IF(OR(B22="",C22=""),"",IF(B22>=C22,"CUMPLE","REVISAR")),"") -> CUMPLE
A24: CIFRAS DE ESTE PLAN
A25: Inversión total (suma de los bloques) | B25: =IFERROR(IF('Inversión Inicial'!$B$26="","",'Inversión Inicial'!$B$26),"") -> 76521.92
A26: Necesidad total de caja al arranque | B26: =IFERROR(IF('Inversión Inicial'!$B$29="","",'Inversión Inicial'!$B$29),"") -> 87357.08
A27: Fondo de maniobra dotado | B27: =IFERROR(IF('Inversión Inicial'!$B$25="","",'Inversión Inicial'!$B$25),"") -> 21925.92
A28: Facturación prevista del año 1 | B28: =IFERROR(IF('PyG 3 Años'!$B$9="","",'PyG 3 Años'!$B$9),"") -> 190000
A29: Resultado neto del año 1 | B29: =IFERROR(IF('PyG 3 Años'!$B$48="","",'PyG 3 Años'!$B$48),"") -> 14526.772
A30: Invitados por evento para el punto de equilibrio CONTABLE (con la amortización dentro) | B30: =IFERROR(IF('Punto Equilibrio'!$B$15="","",'Punto Equilibrio'!$B$15),"") -> 67.537367
A31: Payback del proyecto (años), antes de la deuda | B31: =IFERROR(IF('Tesorería 12 meses'!$B$31="","",'Tesorería 12 meses'!$B$31),"") -> Más de 3 años
A33: QUÉ HA CAMBIADO RESPECTO DE LA VERSIÓN 1.1
A34: Concepto | B34: v1.1 | C34: v2.2 | D34: Por qué
A35: Modelo de ingresos | B35: eventos y facturación tecleados, con una cuenta de resultados cuyas fórmulas no sumaban las filas correctas | C35: invitados por evento × precio por invitado × eventos al año, en la hoja de Supuestos | D35: Ahora cualquier cambio de precio o de volumen recalcula todo el libro
A36: Cocina | B36: no había ninguna: la mise en place del día anterior no tenía sitio | C36: cuota de una cocina de apoyo compartida y autorizada | D36: Lo que se prepara para un evento no se puede hacer en casa (art. 13.5.b del RD 1021/2022)
A37: Personal | B37: ayudantes subcontratados por jornada y ningún sueldo para el parrillero | C37: plantilla con el sueldo del titular, fijos discontinuos y Seguridad Social | D37: Las facturas de autónomo con horario y dirección del empresario son falso autónomo (art. 1.1 ET)
A38: Punto de equilibrio | B38: 5,4 eventos al año, sin amortización, sueldos ni cocina | C38: con todos los costes fijos, en invitados por evento, en ingresos y en caja | D38: El anterior salía irrealmente bajo; éste es el que mira un banco
A39: Impuestos, caja y financiación | B39: no había IVA, Impuesto de Sociedades, tesorería ni préstamo | C39: IVA al 10 %, Impuesto de Sociedades, tesorería de 12 meses y préstamo con su cuadro y su DSCR | D39: Es lo que pide cualquier entidad para estudiar la operación
A41: DATOS DE REFERENCIA DEL SECTOR
A42: Referencia | B42: Valor | C42: Fuente | D42: Nota
A43: Mezcla de eventos del plan | B43: 95 eventos: 12 bodas, 30 de empresa, 45 celebraciones privadas y 8 fiestas | C43: Estimación del kit | D43: Bodas (12 eventos × 110 invitados × 42 €), empresa (30 × 70 × 31 €), celebraciones privadas (45 × 40 × 25 €) y fiestas o ferias por encargo (8 × 300 × 10 €), precios sin IVA. Media: 80 invitados a 25 €
A44: Barbacoa para eventos (directorio) | B44: 18-30 € básica · 30-55 € completa · 55-90 € premium | C44: artistealo.com (estimación del directorio) | D44: Por persona; el directorio no indica si lleva IVA
A45: Buffet de barbacoa en Madrid | B45: 15,95-19,95 € + IVA por persona | C45: Tarifa publicada de un proveedor (2026) | D45: Desde 50 personas, con 500 g de carne cruda por invitado, parrilleros y desechables; desplazamiento aparte
A46: Asado argentino para bodas | B46: 40-100 € por invitado | C46: Ficha de un proveedor en Bodas.net | D46: Entre 50 y 200 invitados, con el 50 % por adelantado
A47: Carne cruda por invitado | B47: 350-450 g con entrantes · 500-600 g sin entrantes | C47: Calculadoras de asado y tarifas publicadas | D47: Sin hueso, un 20 % menos; los niños, la mitad
A48: Escalado por evento | B48: 1 parrilla de 120 cm y 1 parrillero por cada 60-80 invitados | C48: Estimación del kit (manual técnico y calculadora) | D48: Ayudante desde 40 invitados; con cortes servidos en mesa, 1 parrillero por cada 40-50
A49: Carbón por evento | B49: 0,7-1 kg por kg de carne cruda | C49: Estimación del kit | D49: Unos 0,3-0,45 kg por invitado; de 1,3 a 2 € el kilo de carbón o encina
A50: Plan B de gas si hay alerta de incendios | B50: Una botella de menos de 15 kg por aparato | C50: RD 919/2006, art. 2.1.h | D50: Plancha o parrilla de piedra volcánica: así no es una instalación y la conectas tú, con regulador y tubo flexible en fecha
A51: IVA de un servicio de parrilla en el evento | B51: 10 % | C51: Ley 37/1992, art. 91.Uno.2.2.º | D51: Alcohol incluido. Asado para llevar: comida al 10 % y alcohol al 21 %
A52: Retención de IRPF en tus facturas | B52: Ninguna | C52: Reglamento del IRPF, art. 95.6 | D52: El epígrafe 677.9 es una actividad empresarial: tus facturas a empresas no llevan retención
A53: Pago de los ayuntamientos | B53: 30 días desde la conformidad | C53: Ley 9/2017, art. 198.4 | D53: Contrato menor de servicios por debajo de 15.000 € (art. 118), sin anticipo, y factura electrónica por FACe si eres SL, salvo que exima las de hasta 5.000 € (Ley 25/2013, art. 4)
... A55: Convenio colectivo aplicable | B55: Provincial de hostelería | C55: V Acuerdo Laboral de ámbito Estatal para el sector de Hostelería, art. 4 | D55: Copia tu tabla salarial en la celda de Supuestos
A57: Para editar una celda que no esté en verde: Revisar → Desproteger hoja (no tiene contraseña).
A58: Más plantillas y kits del catálogo en aichef.pro/productos-digitales
A59: Diseñado por John Guerrero — chef y consultor gastronómico desde 2010, en cocina desde los 17 años · johnguerrero.es
A60: Versión 2.2 · octubre 2026 · aichef.pro/plan-negocio-parrillero-asador-eventos · info@aichef.pro

Sheet Tesorería 12 meses
A1: PREVISIÓN DE TESORERÍA — AÑO 1
A2: El P&L dice si el negocio gana dinero; esta hoja dice si le queda caja para llegar a fin de mes. Es la primera que mira un banco.
A4: Concepto | B4: Mes 1 (€) | C4: Mes 2 (€) | D4: Mes 3 (€) | E4: Mes 4 (€) | F4: Mes 5 (€) | G4: Mes 6 (€) | H4: Mes 7 (€) | I4: Mes 8 (€) | J4: Mes 9 (€) | K4: Mes 10 (€) | L4: Mes 11 (€) | M4: Mes 12 (€) | N4: Año (€)
A5: Estacionalidad del mes (suma 100 %) | B5: 0.025 | C5: 0.03 | D5: 0.05 | E5: 0.07 | F5: 0.12 | G5: 0.14 | H5: 0.11 | I5: 0.08 | J5: 0.15 | K5: 0.1 | L5: 0.045 | M5: 0.08 | N5: =IFERROR(IF('PyG 3 Años'!$B$9="","",SUM(B5:M5)),"") -> 1 | O5: Perfil de tu zona: agosto flojo en ciudad y fuerte en costa. Tiene que sumar 100 %
A6: Rampa de arranque (% de la actividad de crucero) | B6: =IFERROR(IF('PyG 3 Años'!$B$9="","",MIN(1,'0. Supuestos'!$B$52+(1-'0. Supuestos'!$B$52)*0/MAX(1,'0. Supuestos'!$B$53-1))),"") -> 0.55 | C6: =IFERROR(IF('PyG 3 Años'!$B$9="","",MIN(1,'0. Supuestos'!$B$52+(1-'0. Supuestos'!$B$52)*1/MAX(1,'0. Supuestos'!$B$53-1))),"") -> 0.64 | D6: =IFERROR(IF('PyG 3 Años'!$B$9="","",MIN(1,'0. Supuestos'!$B$52+(1-'0. Supuestos'!$B$52)*2/MAX(1,'0. Supuestos'!$B$53-1))),"") -> 0.73 | E6: =IFERROR(IF('PyG 3 Años'!$B$9="","",MIN(1,'0. Supuestos'!$B$52+(1-'0. Supuestos'!$B$52)*3/MAX(1,'0. Supuestos'!$B$53-1))),"") -> 0.82 | F6: =IFERROR(IF('PyG 3 Años'!$B$9="","",MIN(1,'0. Supuestos'!$B$52+(1-'0. Supuestos'!$B$52)*4/MAX(1,'0. Supuestos'!$B$53-1))),"") -> 0.91 | G6: =IFERROR(IF('PyG 3 Años'!$B$9="","",MIN(1,'0. Supuestos'!$B$52+(1-'0. Supuestos'!$B$52)*5/MAX(1,'0. Supuestos'!$B$53-1))),"") -> 1 | H6: =IFERROR(IF('PyG 3 Años'!$B$9="","",MIN(1,'0. Supuestos'!$B$52+(1-'0. Supuestos'!$B$52)*6/MAX(1,'0. Supuestos'!$B$53-1))),"") -> 1 | I6: =IFERROR(IF('PyG 3 Años'!$B$9="","",MIN(1,'0. Supuestos'!$B$52+(1-'0. Supuestos'!$B$52)*7/MAX(1,'0. Supuestos'!$B$53-1))),"") -> 1 | J6: =IFERROR(IF('PyG 3 Años'!$B$9="","",MIN(1,'0. Supuestos'!$B$52+(1-'0. Supuestos'!$B$52)*8/MAX(1,'0. Supuestos'!$B$53-1))),"") -> 1 | K6: =IFERROR(IF('PyG 3 Años'!$B$9="","",MIN(1,'0. Supuestos'!$B$52+(1-'0. Supuestos'!$B$52)*9/MAX(1,'0. Supuestos'!$B$53-1))),"") -> 1 | L6: =IFERROR(IF('PyG 3 Años'!$B$9="","",MIN(1,'0. Supuestos'!$B$52+(1-'0. Supuestos'!$B$52)*10/MAX(1,'0. Supuestos'!$B$53-1))),"") -> 1 | M6: =IFERROR(IF('PyG 3 Años'!$B$9="","",MIN(1,'0. Supuestos'!$B$52+(1-'0. Supuestos'!$B$52)*11/MAX(1,'0. Supuestos'!$B$53-1))),"") -> 1 | O6: Sube en línea recta desde el porcentaje del mes 1 hasta el 100 % en los meses que digas en Supuestos. Con el mes 1 al 100 % la rampa desaparece
A7: Reparto de la actividad por mes (calculado) | B7: =IFERROR(IF('PyG 3 Años'!$B$9="","",B5*B6/SUMPRODUCT($B$5:$M$5,$B$6:$M$6)),"") -> 0.014611338 | C7: =IFERROR(IF('PyG 3 Años'!$B$9="","",C5*C6/SUMPRODUCT($B$5:$M$5,$B$6:$M$6)),"") -> 0.020402742 | D7: =IFERROR(IF('PyG 3 Años'!$B$9="","",D5*D6/SUMPRODUCT($B$5:$M$5,$B$6:$M$6)),"") -> 0.038786462 | E7: =IFERROR(IF('PyG 3 Años'!$B$9="","",E5*E6/SUMPRODUCT($B$5:$M$5,$B$6:$M$6)),"") -> 0.060995696 | F7: =IFERROR(IF('PyG 3 Años'!$B$9="","",F5*F6/SUMPRODUCT($B$5:$M$5,$B$6:$M$6)),"") -> 0.11604059 | G7: =IFERROR(IF('PyG 3 Años'!$B$9="","",G5*G6/SUMPRODUCT($B$5:$M$5,$B$6:$M$6)),"") -> 0.14876999 | H7: =IFERROR(IF('PyG 3 Años'!$B$9="","",H5*H6/SUMPRODUCT($B$5:$M$5,$B$6:$M$6)),"") -> 0.11689071 | I7: =IFERROR(IF('PyG 3 Años'!$B$9="","",I5*I6/SUMPRODUCT($B$5:$M$5,$B$6:$M$6)),"") -> 0.085011423 | ... M7: =IFERROR(IF('PyG 3 Años'!$B$9="","",M5*M6/SUMPRODUCT($B$5:$M$5,$B$6:$M$6)),"") -> 0.085011423 | N7: =IFERROR(IF('PyG 3 Años'!$B$9="","",SUM(B7:M7)),"") -> 1 | O7: Estacionalidad × rampa, normalizado a 100 %: el AÑO factura lo que dice el P&L, pero repartido como lo reparte un negocio de parrilla para eventos que acaba de arrancar
A8: COBROS
A9: Ventas cobradas (con IVA repercutido) | B9: =IFERROR(IF('PyG 3 Años'!$B$9="","",('PyG 3 Años'!$B$9+'PyG 3 Años'!$B$9*SUMPRODUCT('PyG 3 Años'!$E$10:$E$11,'PyG 3 Años'!$G$10:$G$11))*B7*(1-MIN(30,'0. Supuestos'!$B$58)/30)),"") -> 1527.4345 | C9: =IFERROR(IF('PyG 3 Años'!$B$9="","",('PyG 3 Años'!$B$9+'PyG 3 Años'!$B$9*SUMPRODUCT('PyG 3 Años'!$E$10:$E$11,'PyG 3 Años'!$G$10:$G$11))*(C7*(1-MIN(30,'0. Supuestos'!$B$58)/30)+B7*MIN(30,'0. Supuestos'!$B$58)/30)),"") -> 3660.2886 | D9: =IFERROR(IF('PyG 3 Años'!$B$9="","",('PyG 3 Años'!$B$9+'PyG 3 Años'!$B$9*SUMPRODUCT('PyG 3 Años'!$E$10:$E$11,'PyG 3 Años'!$G$10:$G$11))*(D7*(1-MIN(30,'0. Supuestos'!$B$58)/30)+C7*MIN(30,'0. Supuestos'!$B$58)/30)),"") -> 6187.4985 | E9: =IFERROR(IF('PyG 3 Años'!$B$9="","",('PyG 3 Años'!$B$9+'PyG 3 Años'!$B$9*SUMPRODUCT('PyG 3 Años'!$E$10:$E$11,'PyG 3 Años'!$G$10:$G$11))*(E7*(1-MIN(30,'0. Supuestos'!$B$58)/30)+D7*MIN(30,'0. Supuestos'!$B$58)/30)),"") -> 10430.989 | F9: =IFERROR(IF('PyG 3 Años'!$B$9="","",('PyG 3 Años'!$B$9+'PyG 3 Años'!$B$9*SUMPRODUCT('PyG 3 Años'!$E$10:$E$11,'PyG 3 Años'!$G$10:$G$11))*(F7*(1-MIN(30,'0. Supuestos'!$B$58)/30)+E7*MIN(30,'0. Supuestos'!$B$58)/30)),"") -> 18506.952 | G9: =IFERROR(IF('PyG 3 Años'!$B$9="","",('PyG 3 Años'!$B$9+'PyG 3 Años'!$B$9*SUMPRODUCT('PyG 3 Años'!$E$10:$E$11,'PyG 3 Años'!$G$10:$G$11))*(G7*(1-MIN(30,'0. Supuestos'!$B$58)/30)+F7*MIN(30,'0. Supuestos'!$B$58)/30)),"") -> 27682.668 | H9: =IFERROR(IF('PyG 3 Años'!$B$9="","",('PyG 3 Años'!$B$9+'PyG 3 Años'!$B$9*SUMPRODUCT('PyG 3 Años'!$E$10:$E$11,'PyG 3 Años'!$G$10:$G$11))*(H7*(1-MIN(30,'0. Supuestos'!$B$58)/30)+G7*MIN(30,'0. Supuestos'!$B$58)/30)),"") -> 27771.537 | I9: =IFERROR(IF('PyG 3 Años'!$B$9="","",('PyG 3 Años'!$B$9+'PyG 3 Años'!$B$9*SUMPRODUCT('PyG 3 Años'!$E$10:$E$11,'PyG 3 Años'!$G$10:$G$11))*(I7*(1-MIN(30,'0. Supuestos'!$B$58)/30)+H7*MIN(30,'0. Supuestos'!$B$58)/30)),"") -> 21106.368 | J9: =IFERROR(IF('PyG 3 Años'!$B$9="","",('PyG 3 Años'!$B$9+'PyG 3 Años'!$B$9*SUMPRODUCT('PyG 3 Años'!$E$10:$E$11,'PyG 3 Años'!$G$10:$G$11))*(J7*(1-MIN(30,'0. Supuestos'!$B$58)/30)+I7*MIN(30,'0. Supuestos'!$B$58)/30)),"") -> 25549.814 | ... M9: =IFERROR(IF('PyG 3 Años'!$B$9="","",('PyG 3 Años'!$B$9+'PyG 3 Años'!$B$9*SUMPRODUCT('PyG 3 Años'!$E$10:$E$11,'PyG 3 Años'!$G$10:$G$11))*(M7*(1-MIN(30,'0. Supuestos'!$B$58)/30)+L7*MIN(30,'0. Supuestos'!$B$58)/30)),"") -> 13885.769 | N9: =IFERROR(IF('PyG 3 Años'!$B$9="","",SUM(B9:M9)),"") -> 200188.35 | O9: Ventas del mes con el IVA repercutido, corregidas por los días medios de cobro de la hoja de Supuestos
A10: PAGOS
A11: Compras y costes variables (IVA incluido) | B11: =IFERROR(IF('PyG 3 Años'!$B$9="","",-('PyG 3 Años'!$B$13*(1+'PyG 3 Años'!$G$13)+'PyG 3 Años'!$B$14*(1+'PyG 3 Años'!$G$14)+'PyG 3 Años'!$B$15*(1+'PyG 3 Años'!$G$15)+'PyG 3 Años'!$B$16*(1+'PyG 3 Años'!$G$16)+'PyG 3 Años'!$B$17*(1+'PyG 3 Años'!$G$17)+'PyG 3 Años'!$B$18*(1+'PyG 3 Años'!$G$18))*B7*(1-MIN(30,'0. Supuestos'!$B$59)/30)),"") -> -663.13442 | C11: =IFERROR(IF('PyG 3 Años'!$B$9="","",-('PyG 3 Años'!$B$13*(1+'PyG 3 Años'!$G$13)+'PyG 3 Años'!$B$14*(1+'PyG 3 Años'!$G$14)+'PyG 3 Años'!$B$15*(1+'PyG 3 Años'!$G$15)+'PyG 3 Años'!$B$16*(1+'PyG 3 Años'!$G$16)+'PyG 3 Años'!$B$17*(1+'PyG 3 Años'!$G$17)+'PyG 3 Años'!$B$18*(1+'PyG 3 Años'!$G$18))*(C7*(1-MIN(30,'0. Supuestos'!$B$59)/30)+B7*MIN(30,'0. Supuestos'!$B$59)/30)),"") -> -1589.1112 | D11: =IFERROR(IF('PyG 3 Años'!$B$9="","",-('PyG 3 Años'!$B$13*(1+'PyG 3 Años'!$G$13)+'PyG 3 Años'!$B$14*(1+'PyG 3 Años'!$G$14)+'PyG 3 Años'!$B$15*(1+'PyG 3 Años'!$G$15)+'PyG 3 Años'!$B$16*(1+'PyG 3 Años'!$G$16)+'PyG 3 Años'!$B$17*(1+'PyG 3 Años'!$G$17)+'PyG 3 Años'!$B$18*(1+'PyG 3 Años'!$G$18))*(D7*(1-MIN(30,'0. Supuestos'!$B$59)/30)+C7*MIN(30,'0. Supuestos'!$B$59)/30)),"") -> -2686.2973 | E11: =IFERROR(IF('PyG 3 Años'!$B$9="","",-('PyG 3 Años'!$B$13*(1+'PyG 3 Años'!$G$13)+'PyG 3 Años'!$B$14*(1+'PyG 3 Años'!$G$14)+'PyG 3 Años'!$B$15*(1+'PyG 3 Años'!$G$15)+'PyG 3 Años'!$B$16*(1+'PyG 3 Años'!$G$16)+'PyG 3 Años'!$B$17*(1+'PyG 3 Años'!$G$17)+'PyG 3 Años'!$B$18*(1+'PyG 3 Años'!$G$18))*(E7*(1-MIN(30,'0. Supuestos'!$B$59)/30)+D7*MIN(30,'0. Supuestos'!$B$59)/30)),"") -> -4528.6053 | F11: =IFERROR(IF('PyG 3 Años'!$B$9="","",-('PyG 3 Años'!$B$13*(1+'PyG 3 Años'!$G$13)+'PyG 3 Años'!$B$14*(1+'PyG 3 Años'!$G$14)+'PyG 3 Años'!$B$15*(1+'PyG 3 Años'!$G$15)+'PyG 3 Años'!$B$16*(1+'PyG 3 Años'!$G$16)+'PyG 3 Años'!$B$17*(1+'PyG 3 Años'!$G$17)+'PyG 3 Años'!$B$18*(1+'PyG 3 Años'!$G$18))*(F7*(1-MIN(30,'0. Supuestos'!$B$59)/30)+E7*MIN(30,'0. Supuestos'!$B$59)/30)),"") -> -8034.7778 | G11: =IFERROR(IF('PyG 3 Años'!$B$9="","",-('PyG 3 Años'!$B$13*(1+'PyG 3 Años'!$G$13)+'PyG 3 Años'!$B$14*(1+'PyG 3 Años'!$G$14)+'PyG 3 Años'!$B$15*(1+'PyG 3 Años'!$G$15)+'PyG 3 Años'!$B$16*(1+'PyG 3 Años'!$G$16)+'PyG 3 Años'!$B$17*(1+'PyG 3 Años'!$G$17)+'PyG 3 Años'!$B$18*(1+'PyG 3 Años'!$G$18))*(G7*(1-MIN(30,'0. Supuestos'!$B$59)/30)+F7*MIN(30,'0. Supuestos'!$B$59)/30)),"") -> -12018.407 | H11: =IFERROR(IF('PyG 3 Años'!$B$9="","",-('PyG 3 Años'!$B$13*(1+'PyG 3 Años'!$G$13)+'PyG 3 Años'!$B$14*(1+'PyG 3 Años'!$G$14)+'PyG 3 Años'!$B$15*(1+'PyG 3 Años'!$G$15)+'PyG 3 Años'!$B$16*(1+'PyG 3 Años'!$G$16)+'PyG 3 Años'!$B$17*(1+'PyG 3 Años'!$G$17)+'PyG 3 Años'!$B$18*(1+'PyG 3 Años'!$G$18))*(H7*(1-MIN(30,'0. Supuestos'!$B$59)/30)+G7*MIN(30,'0. Supuestos'!$B$59)/30)),"") -> -12056.99 | I11: =IFERROR(IF('PyG 3 Años'!$B$9="","",-('PyG 3 Años'!$B$13*(1+'PyG 3 Años'!$G$13)+'PyG 3 Años'!$B$14*(1+'PyG 3 Años'!$G$14)+'PyG 3 Años'!$B$15*(1+'PyG 3 Años'!$G$15)+'PyG 3 Años'!$B$16*(1+'PyG 3 Años'!$G$16)+'PyG 3 Años'!$B$17*(1+'PyG 3 Años'!$G$17)+'PyG 3 Años'!$B$18*(1+'PyG 3 Años'!$G$18))*(I7*(1-MIN(30,'0. Supuestos'!$B$59)/30)+H7*MIN(30,'0. Supuestos'!$B$59)/30)),"") -> -9163.312 | J11: =IFERROR(IF('PyG 3 Años'!$B$9="","",-('PyG 3 Años'!$B$13*(1+'PyG 3 Años'!$G$13)+'PyG 3 Años'!$B$14*(1+'PyG 3 Años'!$G$14)+'PyG 3 Años'!$B$15*(1+'PyG 3 Años'!$G$15)+'PyG 3 Años'!$B$16*(1+'PyG 3 Años'!$G$16)+'PyG 3 Años'!$B$17*(1+'PyG 3 Años'!$G$17)+'PyG 3 Años'!$B$18*(1+'PyG 3 Años'!$G$18))*(J7*(1-MIN(30,'0. Supuestos'!$B$59)/30)+I7*MIN(30,'0. Supuestos'!$B$59)/30)),"") -> -11092.43 | ... M11: =IFERROR(IF('PyG 3 Años'!$B$9="","",-('PyG 3 Años'!$B$13*(1+'PyG 3 Años'!$G$13)+'PyG 3 Años'!$B$14*(1+'PyG 3 Años'!$G$14)+'PyG 3 Años'!$B$15*(1+'PyG 3 Años'!$G$15)+'PyG 3 Años'!$B$16*(1+'PyG 3 Años'!$G$16)+'PyG 3 Años'!$B$17*(1+'PyG 3 Años'!$G$17)+'PyG 3 Años'!$B$18*(1+'PyG 3 Años'!$G$18))*(M7*(1-MIN(30,'0. Supuestos'!$B$59)/30)+L7*MIN(30,'0. Supuestos'!$B$59)/30)),"") -> -6028.4948 | N11: =IFERROR(IF('PyG 3 Años'!$B$9="","",SUM(B11:M11)),"") -> -86911.603 | O11: =IFERROR("Materia prima, consumibles, comisiones e imprevistos, cada uno con SU tipo de IVA (la columna del P&L) y con los días de pago a proveedor de Supuestos."&IF('0. Supuestos'!$B$59=0,""," Con "&TEXT('0. Supuestos'!$B$59,"0")&" días de pago, las primeras compras se pagan ya en el año siguiente: la columna «Año» de esta fila recoge "&TEXT(MAX(0,12-ROUNDUP('0. Supuestos'!$B$59/30,0)),"0")&" mensualidades de compra, no el coste del ejercicio."),"") -> Materia prima, consumibles, comisiones e imprevistos, cada uno con SU tipo de IVA (la columna del P&L) y con los días de pago a proveedor de Supuestos. Con 15 días de pago, las primeras compras se pagan ya en el año siguiente: la columna «Año» de esta fila recoge 11 mensualidades de compra, no el coste del ejercicio.
A12: Costes fijos de explotación (IVA incluido) | B12: =IFERROR(IF('PyG 3 Años'!$B$9="","",-('PyG 3 Años'!$B$38-'PyG 3 Años'!$B$23-'PyG 3 Años'!$B$36-'PyG 3 Años'!$B$37+'PyG 3 Años'!$B$40)/12),"") -> -2534.1 | C12: =IFERROR(IF('PyG 3 Años'!$B$9="","",-('PyG 3 Años'!$B$38-'PyG 3 Años'!$B$23-'PyG 3 Años'!$B$36-'PyG 3 Años'!$B$37+'PyG 3 Años'!$B$40)/12),"") -> -2534.1 | D12: =IFERROR(IF('PyG 3 Años'!$B$9="","",-('PyG 3 Años'!$B$38-'PyG 3 Años'!$B$23-'PyG 3 Años'!$B$36-'PyG 3 Años'!$B$37+'PyG 3 Años'!$B$40)/12),"") -> -2534.1 | E12: =IFERROR(IF('PyG 3 Años'!$B$9="","",-('PyG 3 Años'!$B$38-'PyG 3 Años'!$B$23-'PyG 3 Años'!$B$36-'PyG 3 Años'!$B$37+'PyG 3 Años'!$B$40)/12),"") -> -2534.1 | F12: =IFERROR(IF('PyG 3 Años'!$B$9="","",-('PyG 3 Años'!$B$38-'PyG 3 Años'!$B$23-'PyG 3 Años'!$B$36-'PyG 3 Años'!$B$37+'PyG 3 Años'!$B$40)/12),"") -> -2534.1 | G12: =IFERROR(IF('PyG 3 Años'!$B$9="","",-('PyG 3 Años'!$B$38-'PyG 3 Años'!$B$23-'PyG 3 Años'!$B$36-'PyG 3 Años'!$B$37+'PyG 3 Años'!$B$40)/12),"") -> -2534.1 | H12: =IFERROR(IF('PyG 3 Años'!$B$9="","",-('PyG 3 Años'!$B$38-'PyG 3 Años'!$B$23-'PyG 3 Años'!$B$36-'PyG 3 Años'!$B$37+'PyG 3 Años'!$B$40)/12),"") -> -2534.1 | I12: =IFERROR(IF('PyG 3 Años'!$B$9="","",-('PyG 3 Años'!$B$38-'PyG 3 Años'!$B$23-'PyG 3 Años'!$B$36-'PyG 3 Años'!$B$37+'PyG 3 Años'!$B$40)/12),"") -> -2534.1 | ... M12: =IFERROR(IF('PyG 3 Años'!$B$9="","",-('PyG 3 Años'!$B$38-'PyG 3 Años'!$B$23-'PyG 3 Años'!$B$36-'PyG 3 Años'!$B$37+'PyG 3 Años'!$B$40)/12),"") -> -2534.1 | N12: =IFERROR(IF('PyG 3 Años'!$B$9="","",SUM(B12:M12)),"") -> -30409.2 | O12: Los fijos que salen de caja, cada uno con su tipo de IVA: los seguros están exentos y no llevan
A13: Nóminas y Seguridad Social | B13: =IFERROR(IF('PyG 3 Años'!$B$9="","",-'PyG 3 Años'!$B$23/MAX(12,'0. Supuestos'!$B$21)*(1+IF(1='0. Supuestos'!$B$60,(MAX(12,'0. Supuestos'!$B$21)-12)/2,0)+IF(1='0. Supuestos'!$B$61,(MAX(12,'0. Supuestos'!$B$21)-12)/2,0))),"") -> -4141.62 | C13: =IFERROR(IF('PyG 3 Años'!$B$9="","",-'PyG 3 Años'!$B$23/MAX(12,'0. Supuestos'!$B$21)*(1+IF(2='0. Supuestos'!$B$60,(MAX(12,'0. Supuestos'!$B$21)-12)/2,0)+IF(2='0. Supuestos'!$B$61,(MAX(12,'0. Supuestos'!$B$21)-12)/2,0))),"") -> -4141.62 | D13: =IFERROR(IF('PyG 3 Años'!$B$9="","",-'PyG 3 Años'!$B$23/MAX(12,'0. Supuestos'!$B$21)*(1+IF(3='0. Supuestos'!$B$60,(MAX(12,'0. Supuestos'!$B$21)-12)/2,0)+IF(3='0. Supuestos'!$B$61,(MAX(12,'0. Supuestos'!$B$21)-12)/2,0))),"") -> -4141.62 | E13: =IFERROR(IF('PyG 3 Años'!$B$9="","",-'PyG 3 Años'!$B$23/MAX(12,'0. Supuestos'!$B$21)*(1+IF(4='0. Supuestos'!$B$60,(MAX(12,'0. Supuestos'!$B$21)-12)/2,0)+IF(4='0. Supuestos'!$B$61,(MAX(12,'0. Supuestos'!$B$21)-12)/2,0))),"") -> -4141.62 | F13: =IFERROR(IF('PyG 3 Años'!$B$9="","",-'PyG 3 Años'!$B$23/MAX(12,'0. Supuestos'!$B$21)*(1+IF(5='0. Supuestos'!$B$60,(MAX(12,'0. Supuestos'!$B$21)-12)/2,0)+IF(5='0. Supuestos'!$B$61,(MAX(12,'0. Supuestos'!$B$21)-12)/2,0))),"") -> -4141.62 | G13: =IFERROR(IF('PyG 3 Años'!$B$9="","",-'PyG 3 Años'!$B$23/MAX(12,'0. Supuestos'!$B$21)*(1+IF(6='0. Supuestos'!$B$60,(MAX(12,'0. Supuestos'!$B$21)-12)/2,0)+IF(6='0. Supuestos'!$B$61,(MAX(12,'0. Supuestos'!$B$21)-12)/2,0))),"") -> -4141.62 | H13: =IFERROR(IF('PyG 3 Años'!$B$9="","",-'PyG 3 Años'!$B$23/MAX(12,'0. Supuestos'!$B$21)*(1+IF(7='0. Supuestos'!$B$60,(MAX(12,'0. Supuestos'!$B$21)-12)/2,0)+IF(7='0. Supuestos'!$B$61,(MAX(12,'0. Supuestos'!$B$21)-12)/2,0))),"") -> -8283.24 | I13: =IFERROR(IF('PyG 3 Años'!$B$9="","",-'PyG 3 Años'!$B$23/MAX(12,'0. Supuestos'!$B$21)*(1+IF(8='0. Supuestos'!$B$60,(MAX(12,'0. Supuestos'!$B$21)-12)/2,0)+IF(8='0. Supuestos'!$B$61,(MAX(12,'0. Supuestos'!$B$21)-12)/2,0))),"") -> -4141.62 | J13: =IFERROR(IF('PyG 3 Años'!$B$9="","",-'PyG 3 Años'!$B$23/MAX(12,'0. Supuestos'!$B$21)*(1+IF(9='0. Supuestos'!$B$60,(MAX(12,'0. Supuestos'!$B$21)-12)/2,0)+IF(9='0. Supuestos'!$B$61,(MAX(12,'0. Supuestos'!$B$21)-12)/2,0))),"") -> -4141.62 | K13: =IFERROR(IF('PyG 3 Años'!$B$9="","",-'PyG 3 Años'!$B$23/MAX(12,'0. Supuestos'!$B$21)*(1+IF(10='0. Supuestos'!$B$60,(MAX(12,'0. Supuestos'!$B$21)-12)/2,0)+IF(10='0. Supuestos'!$B$61,(MAX(12,'0. Supuestos'!$B$21)-12)/2,0))),"") -> -4141.62 | L13: =IFERROR(IF('PyG 3 Años'!$B$9="","",-'PyG 3 Años'!$B$23/MAX(12,'0. Supuestos'!$B$21)*(1+IF(11='0. Supuestos'!$B$60,(MAX(12,'0. Supuestos'!$B$21)-12)/2,0)+IF(11='0. Supuestos'!$B$61,(MAX(12,'0. Supuestos'!$B$21)-12)/2,0))),"") -> -4141.62 | M13: =IFERROR(IF('PyG 3 Años'!$B$9="","",-'PyG 3 Años'!$B$23/MAX(12,'0. Supuestos'!$B$21)*(1+IF(12='0. Supuestos'!$B$60,(MAX(12,'0. Supuestos'!$B$21)-12)/2,0)+IF(12='0. Supuestos'!$B$61,(MAX(12,'0. Supuestos'!$B$21)-12)/2,0))),"") -> -8283.24 | N13: =IFERROR(IF('PyG 3 Años'!$B$9="","",SUM(B13:M13)),"") -> -57982.68 | O13: Doce mensualidades más las pagas extra en los meses que digas en Supuestos. La suma del año es la misma que la del P&L
A14: Intereses del préstamo | B14: =IFERROR(IF('PyG 3 Años'!$B$9="","",-'Financiación'!$B$44/12),"") -> -354.25 | C14: =IFERROR(IF('PyG 3 Años'!$B$9="","",-'Financiación'!$B$44/12),"") -> -354.25 | D14: =IFERROR(IF('PyG 3 Años'!$B$9="","",-'Financiación'!$B$44/12),"") -> -354.25 | E14: =IFERROR(IF('PyG 3 Años'!$B$9="","",-'Financiación'!$B$44/12),"") -> -354.25 | F14: =IFERROR(IF('PyG 3 Años'!$B$9="","",-'Financiación'!$B$44/12),"") -> -354.25 | G14: =IFERROR(IF('PyG 3 Años'!$B$9="","",-'Financiación'!$B$44/12),"") -> -354.25 | H14: =IFERROR(IF('PyG 3 Años'!$B$9="","",-'Financiación'!$B$44/12),"") -> -354.25 | I14: =IFERROR(IF('PyG 3 Años'!$B$9="","",-'Financiación'!$B$44/12),"") -> -354.25 | ... M14: =IFERROR(IF('PyG 3 Años'!$B$9="","",-'Financiación'!$B$44/12),"") -> -354.25 | N14: =IFERROR(IF('PyG 3 Años'!$B$9="","",SUM(B14:M14)),"") -> -4251
A15: Devolución de principal del préstamo | B15: =IFERROR(IF('PyG 3 Años'!$B$9="","",-'Financiación'!$B$45/12),"") -> 0 | C15: =IFERROR(IF('PyG 3 Años'!$B$9="","",-'Financiación'!$B$45/12),"") -> 0 | D15: =IFERROR(IF('PyG 3 Años'!$B$9="","",-'Financiación'!$B$45/12),"") -> 0 | E15: =IFERROR(IF('PyG 3 Años'!$B$9="","",-'Financiación'!$B$45/12),"") -> 0 | F15: =IFERROR(IF('PyG 3 Años'!$B$9="","",-'Financiación'!$B$45/12),"") -> 0 | G15: =IFERROR(IF('PyG 3 Años'!$B$9="","",-'Financiación'!$B$45/12),"") -> 0 | H15: =IFERROR(IF('PyG 3 Años'!$B$9="","",-'Financiación'!$B$45/12),"") -> 0 | I15: =IFERROR(IF('PyG 3 Años'!$B$9="","",-'Financiación'!$B$45/12),"") -> 0 | ... M15: =IFERROR(IF('PyG 3 Años'!$B$9="","",-'Financiación'!$B$45/12),"") -> 0 | N15: =IFERROR(IF('PyG 3 Años'!$B$9="","",SUM(B15:M15)),"") -> 0
A16: IVA repercutido del mes (memoria) | B16: =IFERROR(IF('PyG 3 Años'!$B$9="","",'PyG 3 Años'!$B$9*B7*SUMPRODUCT('PyG 3 Años'!$E$10:$E$11,'PyG 3 Años'!$G$10:$G$11)),"") -> 278.71479 | C16: =IFERROR(IF('PyG 3 Años'!$B$9="","",'PyG 3 Años'!$B$9*C7*SUMPRODUCT('PyG 3 Años'!$E$10:$E$11,'PyG 3 Años'!$G$10:$G$11)),"") -> 389.18719 | D16: =IFERROR(IF('PyG 3 Años'!$B$9="","",'PyG 3 Años'!$B$9*D7*SUMPRODUCT('PyG 3 Años'!$E$10:$E$11,'PyG 3 Años'!$G$10:$G$11)),"") -> 739.86107 | E16: =IFERROR(IF('PyG 3 Años'!$B$9="","",'PyG 3 Años'!$B$9*E7*SUMPRODUCT('PyG 3 Años'!$E$10:$E$11,'PyG 3 Años'!$G$10:$G$11)),"") -> 1163.5075 | F16: =IFERROR(IF('PyG 3 Años'!$B$9="","",'PyG 3 Años'!$B$9*F7*SUMPRODUCT('PyG 3 Años'!$E$10:$E$11,'PyG 3 Años'!$G$10:$G$11)),"") -> 2213.5022 | G16: =IFERROR(IF('PyG 3 Años'!$B$9="","",'PyG 3 Años'!$B$9*G7*SUMPRODUCT('PyG 3 Años'!$E$10:$E$11,'PyG 3 Años'!$G$10:$G$11)),"") -> 2837.8233 | H16: =IFERROR(IF('PyG 3 Años'!$B$9="","",'PyG 3 Años'!$B$9*H7*SUMPRODUCT('PyG 3 Años'!$E$10:$E$11,'PyG 3 Años'!$G$10:$G$11)),"") -> 2229.7183 | I16: =IFERROR(IF('PyG 3 Años'!$B$9="","",'PyG 3 Años'!$B$9*I7*SUMPRODUCT('PyG 3 Años'!$E$10:$E$11,'PyG 3 Años'!$G$10:$G$11)),"") -> 1621.6133 | ... M16: =IFERROR(IF('PyG 3 Años'!$B$9="","",'PyG 3 Años'!$B$9*M7*SUMPRODUCT('PyG 3 Años'!$E$10:$E$11,'PyG 3 Años'!$G$10:$G$11)),"") -> 1621.6133 | N16: =IFERROR(IF('PyG 3 Años'!$B$9="","",SUM(B16:M16)),"") -> 19075.24 | O16: Cada línea de venta a SU tipo, leído de la columna de IVA del P&L: en el servicio de parrilla, alcohol incluido, el reducido (art. 91.Uno.2.2.º de la Ley 37/1992 del IVA); el alcohol que sale por asado para llevar, al general; la carpa o el mobiliario facturados aparte, al general (art. 90)
A17: IVA soportado del mes (memoria) | B17: =IFERROR(IF('PyG 3 Años'!$B$9="","",'PyG 3 Años'!$B$39*B7+'PyG 3 Años'!$B$40/12),"") -> 564.66604 | C17: =IFERROR(IF('PyG 3 Años'!$B$9="","",'PyG 3 Años'!$B$39*C7+'PyG 3 Años'!$B$40/12),"") -> 625.33586 | D17: =IFERROR(IF('PyG 3 Años'!$B$9="","",'PyG 3 Años'!$B$39*D7+'PyG 3 Años'!$B$40/12),"") -> 817.92077 | E17: =IFERROR(IF('PyG 3 Años'!$B$9="","",'PyG 3 Años'!$B$39*E7+'PyG 3 Años'!$B$40/12),"") -> 1050.5812 | F17: =IFERROR(IF('PyG 3 Años'!$B$9="","",'PyG 3 Años'!$B$39*F7+'PyG 3 Años'!$B$40/12),"") -> 1627.2227 | G17: =IFERROR(IF('PyG 3 Años'!$B$9="","",'PyG 3 Años'!$B$39*G7+'PyG 3 Años'!$B$40/12),"") -> 1970.0906 | H17: =IFERROR(IF('PyG 3 Años'!$B$9="","",'PyG 3 Años'!$B$39*H7+'PyG 3 Años'!$B$40/12),"") -> 1636.1283 | I17: =IFERROR(IF('PyG 3 Años'!$B$9="","",'PyG 3 Años'!$B$39*I7+'PyG 3 Años'!$B$40/12),"") -> 1302.1661 | ... M17: =IFERROR(IF('PyG 3 Años'!$B$9="","",'PyG 3 Años'!$B$39*M7+'PyG 3 Años'!$B$40/12),"") -> 1302.1661 | N17: =IFERROR(IF('PyG 3 Años'!$B$9="","",SUM(B17:M17)),"") -> 15415.04 | O17: Cada partida a su tipo, leído de la columna de IVA del P&L: los seguros y las comisiones de los medios de pago están exentos
A18: IVA a compensar arrastrado (inversión incluida) | E18: =IFERROR(IF('PyG 3 Años'!$B$9="","",'Inversión Inicial'!$B$28),"") -> 10835.16 | H18: =IFERROR(IF('PyG 3 Años'!$B$9="","",MAX(0,-E19)),"") -> 11435.32 | K18: =IFERROR(IF('PyG 3 Años'!$B$9="","",MAX(0,-H19)),"") -> 9868.3811 | O18: El IVA soportado de la INVERSIÓN entra aquí: se compensa contra el repercutido de los trimestres siguientes hasta agotarlo (modelo 303)
A19: Resultado de la liquidación trimestral | E19: =IFERROR(IF('PyG 3 Años'!$B$9="","",SUM(B16:D16)-SUM(B17:D17)-E18),"") -> -11435.32 | H19: =IFERROR(IF('PyG 3 Años'!$B$9="","",SUM(E16:G16)-SUM(E17:G17)-H18),"") -> -9868.3811 | K19: =IFERROR(IF('PyG 3 Años'!$B$9="","",SUM(H16:J16)-SUM(H17:J17)-K18),"") -> -7996.2303 | O19: Repercutido menos soportado del trimestre menos lo que venía arrastrado. En negativo NO se paga: se compensa en el trimestre siguiente
A20: Pago del IVA (modelo 303) | E20: =IFERROR(IF('PyG 3 Años'!$B$9="","",IF(E19<=0,"",-E19)),"") | H20: =IFERROR(IF('PyG 3 Años'!$B$9="","",IF(H19<=0,"",-H19)),"") | K20: =IFERROR(IF('PyG 3 Años'!$B$9="","",IF(K19<=0,"",-K19)),"") | N20: =IFERROR(IF('PyG 3 Años'!$B$9="","",SUM(B20:M20)),"") -> 0 | O20: Sólo sale caja cuando el resultado del trimestre es positivo. Los meses sin liquidación van en blanco, no a cero. La celda se pinta en ROJO cuando el pago del 303 se lleva más caja de la que queda ese mes
A21: FLUJO DEL MES | B21: =IFERROR(IF('PyG 3 Años'!$B$9="","",SUM(B9:B15)+IF(B20="",0,B20)),"") -> -6165.6699 | C21: =IFERROR(IF('PyG 3 Años'!$B$9="","",SUM(C9:C15)+IF(C20="",0,C20)),"") -> -4958.7926 | D21: =IFERROR(IF('PyG 3 Años'!$B$9="","",SUM(D9:D15)+IF(D20="",0,D20)),"") -> -3528.7688 | E21: =IFERROR(IF('PyG 3 Años'!$B$9="","",SUM(E9:E15)+IF(E20="",0,E20)),"") -> -1127.5859 | F21: =IFERROR(IF('PyG 3 Años'!$B$9="","",SUM(F9:F15)+IF(F20="",0,F20)),"") -> 3442.2045 | G21: =IFERROR(IF('PyG 3 Años'!$B$9="","",SUM(G9:G15)+IF(G20="",0,G20)),"") -> 8634.291 | H21: =IFERROR(IF('PyG 3 Años'!$B$9="","",SUM(H9:H15)+IF(H20="",0,H20)),"") -> 4542.9576 | I21: =IFERROR(IF('PyG 3 Años'!$B$9="","",SUM(I9:I15)+IF(I20="",0,I20)),"") -> 4913.0862 | ... M21: =IFERROR(IF('PyG 3 Años'!$B$9="","",SUM(M9:M15)+IF(M20="",0,M20)),"") -> -3314.3162 | N21: =IFERROR(IF('PyG 3 Años'!$B$9="","",SUM(B21:M21)),"") -> 20633.865
A22: SALDO ACUMULADO DE CAJA | B22: =IFERROR(IF('PyG 3 Años'!$B$9="","",'Inversión Inicial'!$B$25+B21),"") -> 15760.25 | C22: =IFERROR(IF('PyG 3 Años'!$B$9="","",B22+C21),"") -> 10801.457 | D22: =IFERROR(IF('PyG 3 Años'!$B$9="","",C22+D21),"") -> 7272.6887 | E22: =IFERROR(IF('PyG 3 Años'!$B$9="","",D22+E21),"") -> 6145.1028 | F22: =IFERROR(IF('PyG 3 Años'!$B$9="","",E22+F21),"") -> 9587.3073 | G22: =IFERROR(IF('PyG 3 Años'!$B$9="","",F22+G21),"") -> 18221.598 | H22: =IFERROR(IF('PyG 3 Años'!$B$9="","",G22+H21),"") -> 22764.556 | I22: =IFERROR(IF('PyG 3 Años'!$B$9="","",H22+I21),"") -> 27677.642 | J22: =IFERROR(IF('PyG 3 Años'!$B$9="","",I22+J21),"") -> 35105.056 | ... M22: =IFERROR(IF('PyG 3 Años'!$B$9="","",L22+M21),"") -> 42559.785
A23: Saldo mínimo del año | B23: =IFERROR(IF('PyG 3 Años'!$B$9="","",IF(COUNT(B22:M22)=0,"",MIN(B22:M22))),"") -> 6145.1028 | D23: Si es negativo, sube el fondo de maniobra o el préstamo: te quedas sin caja
A24: Mes en el que la caja toca fondo | B24: =IFERROR(IF('PyG 3 Años'!$B$9="","",IF(COUNT(B22:M22)=0,"",MATCH(MIN(B22:M22),B22:M22,0))),"") -> 4 | D24: Es la respuesta a la pregunta que decide una operación bancaria: en qué mes se agota la caja
A25: RETORNO DE LA INVERSIÓN
A26: Flujo de caja libre antes de la deuda, año 1 | B26: =IFERROR(IF('PyG 3 Años'!$B$9="","",'PyG 3 Años'!$B$48+'PyG 3 Años'!$B$36+'Financiación'!$B$44),"") -> 23689.772 | D26: Resultado neto más amortización (que no se paga) más los intereses de ese año: el principal no se resta porque este flujo es ANTES de la deuda. La MISMA base que los años 2 y 3, para que el payback compare peras con peras
A27: Flujo de caja libre antes de la deuda, año 2 | B27: =IFERROR(IF('PyG 3 Años'!$B$9="","",'PyG 3 Años'!$C$48+'PyG 3 Años'!$C$36+'Financiación'!$B$46),"") -> 26049.78 | D27: Resultado neto más amortización (que no se paga) más los intereses de ese año: el principal no se resta porque este flujo es ANTES de la deuda. Sin tabla mensual, es una estimación
A28: Flujo de caja libre antes de la deuda, año 3 | B28: =IFERROR(IF('PyG 3 Años'!$B$9="","",'PyG 3 Años'!$D$48+'PyG 3 Años'!$D$36+'Financiación'!$B$48),"") -> 23819.537 | D28: Resultado neto más amortización (que no se paga) más los intereses de ese año: el principal no se resta porque este flujo es ANTES de la deuda. Sin tabla mensual, es una estimación
A29: Informativo: flujo REAL de caja del año 1 (tabla mensual, antes de la deuda) | B29: =IFERROR(IF('PyG 3 Años'!$B$9="","",N21+'Financiación'!$B$44+'Financiación'!$B$45),"") -> 24884.865 | D29: La suma de los doce FLUJO DEL MES de arriba, devolviéndole los intereses y el principal que se pagaron ese año. NO es la que usa el payback: lleva dentro el IVA que todavía no se ha liquidado y el crédito del proveedor, dos cosas que hay que devolver y que los años 2 y 3 no tienen
A30: Inversión a recuperar (sin el IVA, que se recupera por el 303) | B30: =IFERROR(IF('PyG 3 Años'!$B$9="","",'Inversión Inicial'!$B$29-'Inversión Inicial'!$B$28),"") -> 76521.92 | D30: CAPEX más fondo de maniobra: la necesidad total de caja MENOS el IVA soportado de la inversión, que no se pierde (se recupera con el modelo 303 y esta misma hoja lo compensa trimestre a trimestre). El fondo de maniobra sí se recupera al cerrar, pero hasta entonces está inmovilizado
A31: Payback del proyecto (años), antes de la deuda | B31: =IFERROR(IF('PyG 3 Años'!$B$9="","",IF(B26>=B30,ROUND(B30/B26,1),IF(B26+B27>=B30,ROUND(1+(B30-B26)/B27,1),IF(B26+B27+B28>=B30,ROUND(2+(B30-B26-B27)/B28,1),"Más de 3 años")))),"") -> Más de 3 años | D31: Mide cuánto tarda el negocio en devolver la inversión con lo que genera ANTES de pagar al banco, con la MISMA base de flujo en los tres años; si puedes pagar la cuota lo dice el DSCR de la hoja de Financiación. El plan de negocio en Word cita esta cifra; si cambias una celda verde, manda este libro
A32: Payback sobre el CAPEX, sin fondo de maniobra (años) | B32: =IFERROR(IF('PyG 3 Años'!$B$9="","",IF(B26>='Inversión Inicial'!$B$27,ROUND('Inversión Inicial'!$B$27/B26,1),IF(B26+B27>='Inversión Inicial'!$B$27,ROUND(1+('Inversión Inicial'!$B$27-B26)/B27,1),IF(B26+B27+B28>='Inversión Inicial'!$B$27,ROUND(2+('Inversión Inicial'!$B$27-B26-B27)/B28,1),"Más de 3 años")))),"") -> 2.2 | D32: El mismo cálculo sobre lo que se COMPRA (furgoneta, equipamiento, lanzamiento y constitución), sin el fondo de maniobra: ese dinero no se gasta, se inmoviliza y vuelve al cerrar el negocio. Informativo: el payback que se publica es el de arriba
A34: El IVA del cuarto trimestre se liquida en enero del año siguiente, así que no aparece en este cuadro. El Impuesto de Sociedades del año 1 se paga en julio del año 2. La cuota del préstamo se reparte en doce partes iguales siguiendo el cuadro ANUAL de la hoja de Financiación, y las nóminas en doce mensualidades más las dos pagas extra en su mes.

Sheet Financiación
A1: PLAN DE FINANCIACIÓN
A2: Qué hace falta, de dónde sale y cuánto cuesta devolverlo. Es la hoja que el banco pide junto con el P&L.
A4: Concepto | B4: Importe | C4: Notas
A5: ORIGEN DE FONDOS
A6: Recursos propios de los socios | B6: =IFERROR(IF('0. Supuestos'!$B$30="","",'0. Supuestos'!$B$30),"") -> 22000
A7: Préstamo bancario | B7: =IFERROR(IF('0. Supuestos'!$B$31="","",'0. Supuestos'!$B$31),"") -> 65400
A8: Línea ICO (avalada por el ICO, la concede tu banco) | B8: 0 | C8: Consulta las líneas del ejercicio en curso en ico.es
A9: Préstamo participativo ENISA | B9: 0 | C9: Para sociedades; sin garantías personales
A10: Business angels o socios inversores | B10: 0 | C10: Entra en el capital: diluye, no se devuelve
A11: Subvenciones autonómicas o locales | B11: 0 | C11: Suelen cobrarse DESPUÉS de justificar el gasto
A12: TOTAL ORIGEN DE FONDOS | B12: =IFERROR(IF(COUNT(B6:B11)=0,"",SUM(B6:B11)),"") -> 87400
A13: USOS
A14: Necesidad total de caja al arranque | B14: =IFERROR(IF('Inversión Inicial'!$B$29="","",'Inversión Inicial'!$B$29),"") -> 87357.08 | C14: Inversión más el IVA que hay que adelantar
A15: Diferencia (origen - usos) | B15: =IFERROR(B12-B14,"") -> 42.92 | C15: En rojo (negativa) el plan NO está financiado. Muy por encima de cero tampoco es gratis: se pagan intereses por un dinero que no se usa
A16: Diferencia sobre los usos (%) | B16: =IFERROR(B15/B14,"") -> 0.00049131679 | C16: Ámbar por encima del margen que fijes: es deuda que pagas sin necesitarla
A17: Exceso de financiación admisible (%) | B17: 0.05 | C17: Un pequeño colchón sobre la necesidad es sano; un 20 % de más son intereses tirados
A18: Préstamo que ajustaría el origen a la necesidad | B18: =IFERROR(MAX(0,B14-B12+B7),"") -> 65357.08 | C18: Cópialo en «Préstamo bancario solicitado» de la hoja de Supuestos y la diferencia se pone a cero
A19: CONDICIONES DEL PRÉSTAMO
A20: Importe del principal | B20: =IFERROR(IF('0. Supuestos'!$B$31=0,"",'0. Supuestos'!$B$31),"") -> 65400
A21: Tipo de interés nominal anual | B21: =IFERROR(IF('0. Supuestos'!$B$32="","",'0. Supuestos'!$B$32),"") -> 0.065
A22: Plazo total (años) | B22: =IFERROR(IF('0. Supuestos'!$B$33="","",'0. Supuestos'!$B$33),"") -> 6
A23: Carencia de principal aplicada (años) | B23: =IFERROR(IF(OR('0. Supuestos'!$B$34="",'0. Supuestos'!$B$33=""),"",IF('0. Supuestos'!$B$34>='0. Supuestos'!$B$33,0,'0. Supuestos'!$B$34)),"") -> 1 | C23: Una carencia igual o mayor que el plazo no existe: la hoja la anula en origen
A24: Cuota anual durante la amortización | B24: =IFERROR(IF(B22-B23<=0,"",IF(B21=0,B20/(B22-B23),B20*B21/(1-(1+B21)^-(B22-B23)))),"") -> 15737.499 | C24: Sistema francés, anualidad algebraica. Con el tipo al 0 % es el principal entre los años de amortización: sin esa rama el cuadro se apagaba entero
A25: CUADRO DE AMORTIZACIÓN
A26: Año | B26: Capital pendiente | C26: Intereses | D26: Amortización de principal | E26: Cuota total | F26: Capital al cierre | G26: Flujo disponible para la deuda (después de impuestos; del año 4 en adelante, el del año 3 mantenido) | H26: DSCR del año
A27: 1 | B27: =IFERROR(IF(B20="","",B20),"") -> 65400 | C27: =IFERROR(IF(OR(1>B22,B27=""),"",B27*B21),"") -> 4251 | D27: =IFERROR(IF(OR(1>B22,B27=""),"",IF(1<=B23,0,MIN(B27,B24-C27))),"") -> 0 | E27: =IFERROR(IF(C27="","",C27+D27),"") -> 4251 | F27: =IFERROR(IF(D27="","",B27-D27),"") -> 65400 | G27: =IFERROR(IF(E27="","",'PyG 3 Años'!$B$41-'PyG 3 Años'!$B$46+'PyG 3 Años'!$B$36+'PyG 3 Años'!$B$37),"") -> 23689.772 | H27: =IFERROR(IF(OR(E27="",E27=0),"",G27/E27),"") -> 5.5727528
A28: 2 | B28: =IFERROR(IF(OR(2>B22,F27=""),"",F27),"") -> 65400 | C28: =IFERROR(IF(OR(2>B22,B28=""),"",B28*B21),"") -> 4251 | D28: =IFERROR(IF(OR(2>B22,B28=""),"",IF(2<=B23,0,MIN(B28,B24-C28))),"") -> 11486.499 | E28: =IFERROR(IF(C28="","",C28+D28),"") -> 15737.499 | F28: =IFERROR(IF(D28="","",B28-D28),"") -> 53913.501 | G28: =IFERROR(IF(E28="","",'PyG 3 Años'!$C$41-'PyG 3 Años'!$C$46+'PyG 3 Años'!$C$36+'PyG 3 Años'!$C$37),"") -> 26049.78 | H28: =IFERROR(IF(OR(E28="",E28=0),"",G28/E28),"") -> 1.6552681
A29: 3 | B29: =IFERROR(IF(OR(3>B22,F28=""),"",F28),"") -> 53913.501 | C29: =IFERROR(IF(OR(3>B22,B29=""),"",B29*B21),"") -> 3504.3776 | D29: =IFERROR(IF(OR(3>B22,B29=""),"",IF(3<=B23,0,MIN(B29,B24-C29))),"") -> 12233.121 | E29: =IFERROR(IF(C29="","",C29+D29),"") -> 15737.499 | F29: =IFERROR(IF(D29="","",B29-D29),"") -> 41680.38 | G29: =IFERROR(IF(E29="","",'PyG 3 Años'!$D$41-'PyG 3 Años'!$D$46+'PyG 3 Años'!$D$36+'PyG 3 Años'!$D$37),"") -> 23819.537 | H29: =IFERROR(IF(OR(E29="",E29=0),"",G29/E29),"") -> 1.5135529
A30: 4 | B30: =IFERROR(IF(OR(4>B22,F29=""),"",F29),"") -> 41680.38 | C30: =IFERROR(IF(OR(4>B22,B30=""),"",B30*B21),"") -> 2709.2247 | D30: =IFERROR(IF(OR(4>B22,B30=""),"",IF(4<=B23,0,MIN(B30,B24-C30))),"") -> 13028.274 | E30: =IFERROR(IF(C30="","",C30+D30),"") -> 15737.499 | F30: =IFERROR(IF(D30="","",B30-D30),"") -> 28652.106 | G30: =IFERROR(IF(E30="","",'PyG 3 Años'!$D$41-'PyG 3 Años'!$D$46+'PyG 3 Años'!$D$36+'PyG 3 Años'!$D$37),"") -> 23819.537 | H30: =IFERROR(IF(OR(E30="",E30=0),"",G30/E30),"") -> 1.5135529
A31: 5 | B31: =IFERROR(IF(OR(5>B22,F30=""),"",F30),"") -> 28652.106 | C31: =IFERROR(IF(OR(5>B22,B31=""),"",B31*B21),"") -> 1862.3869 | D31: =IFERROR(IF(OR(5>B22,B31=""),"",IF(5<=B23,0,MIN(B31,B24-C31))),"") -> 13875.112 | E31: =IFERROR(IF(C31="","",C31+D31),"") -> 15737.499 | F31: =IFERROR(IF(D31="","",B31-D31),"") -> 14776.994 | G31: =IFERROR(IF(E31="","",'PyG 3 Años'!$D$41-'PyG 3 Años'!$D$46+'PyG 3 Años'!$D$36+'PyG 3 Años'!$D$37),"") -> 23819.537 | H31: =IFERROR(IF(OR(E31="",E31=0),"",G31/E31),"") -> 1.5135529
A32: 6 | B32: =IFERROR(IF(OR(6>B22,F31=""),"",F31),"") -> 14776.994 | C32: =IFERROR(IF(OR(6>B22,B32=""),"",B32*B21),"") -> 960.50462 | D32: =IFERROR(IF(OR(6>B22,B32=""),"",IF(6<=B23,0,MIN(B32,B24-C32))),"") -> 14776.994 | E32: =IFERROR(IF(C32="","",C32+D32),"") -> 15737.499 | F32: =IFERROR(IF(D32="","",B32-D32),"") -> 0 | G32: =IFERROR(IF(E32="","",'PyG 3 Años'!$D$41-'PyG 3 Años'!$D$46+'PyG 3 Años'!$D$36+'PyG 3 Años'!$D$37),"") -> 23819.537 | H32: =IFERROR(IF(OR(E32="",E32=0),"",G32/E32),"") -> 1.5135529
A33: 7 | B33: =IFERROR(IF(OR(7>B22,F32=""),"",F32),"") | C33: =IFERROR(IF(OR(7>B22,B33=""),"",B33*B21),"") | D33: =IFERROR(IF(OR(7>B22,B33=""),"",IF(7<=B23,0,MIN(B33,B24-C33))),"") | E33: =IFERROR(IF(C33="","",C33+D33),"") | F33: =IFERROR(IF(D33="","",B33-D33),"") | G33: =IFERROR(IF(E33="","",'PyG 3 Años'!$D$41-'PyG 3 Años'!$D$46+'PyG 3 Años'!$D$36+'PyG 3 Años'!$D$37),"") | H33: =IFERROR(IF(OR(E33="",E33=0),"",G33/E33),"")
A34: 8 | B34: =IFERROR(IF(OR(8>B22,F33=""),"",F33),"") | C34: =IFERROR(IF(OR(8>B22,B34=""),"",B34*B21),"") | D34: =IFERROR(IF(OR(8>B22,B34=""),"",IF(8<=B23,0,MIN(B34,B24-C34))),"") | E34: =IFERROR(IF(C34="","",C34+D34),"") | F34: =IFERROR(IF(D34="","",B34-D34),"") | G34: =IFERROR(IF(E34="","",'PyG 3 Años'!$D$41-'PyG 3 Años'!$D$46+'PyG 3 Años'!$D$36+'PyG 3 Años'!$D$37),"") | H34: =IFERROR(IF(OR(E34="",E34=0),"",G34/E34),"")
A35: 9 | B35: =IFERROR(IF(OR(9>B22,F34=""),"",F34),"") | C35: =IFERROR(IF(OR(9>B22,B35=""),"",B35*B21),"") | D35: =IFERROR(IF(OR(9>B22,B35=""),"",IF(9<=B23,0,MIN(B35,B24-C35))),"") | E35: =IFERROR(IF(C35="","",C35+D35),"") | F35: =IFERROR(IF(D35="","",B35-D35),"") | G35: =IFERROR(IF(E35="","",'PyG 3 Años'!$D$41-'PyG 3 Años'!$D$46+'PyG 3 Años'!$D$36+'PyG 3 Años'!$D$37),"") | H35: =IFERROR(IF(OR(E35="",E35=0),"",G35/E35),"")
A36: 10 | B36: =IFERROR(IF(OR(10>B22,F35=""),"",F35),"") | C36: =IFERROR(IF(OR(10>B22,B36=""),"",B36*B21),"") | D36: =IFERROR(IF(OR(10>B22,B36=""),"",IF(10<=B23,0,MIN(B36,B24-C36))),"") | E36: =IFERROR(IF(C36="","",C36+D36),"") | F36: =IFERROR(IF(D36="","",B36-D36),"") | G36: =IFERROR(IF(E36="","",'PyG 3 Años'!$D$41-'PyG 3 Años'!$D$46+'PyG 3 Años'!$D$36+'PyG 3 Años'!$D$37),"") | H36: =IFERROR(IF(OR(E36="",E36=0),"",G36/E36),"")
A37: 11 | B37: =IFERROR(IF(OR(11>B22,F36=""),"",F36),"") | C37: =IFERROR(IF(OR(11>B22,B37=""),"",B37*B21),"") | D37: =IFERROR(IF(OR(11>B22,B37=""),"",IF(11<=B23,0,MIN(B37,B24-C37))),"") | E37: =IFERROR(IF(C37="","",C37+D37),"") | F37: =IFERROR(IF(D37="","",B37-D37),"") | G37: =IFERROR(IF(E37="","",'PyG 3 Años'!$D$41-'PyG 3 Años'!$D$46+'PyG 3 Años'!$D$36+'PyG 3 Años'!$D$37),"") | H37: =IFERROR(IF(OR(E37="",E37=0),"",G37/E37),"")
A38: 12 | B38: =IFERROR(IF(OR(12>B22,F37=""),"",F37),"") | C38: =IFERROR(IF(OR(12>B22,B38=""),"",B38*B21),"") | D38: =IFERROR(IF(OR(12>B22,B38=""),"",IF(12<=B23,0,MIN(B38,B24-C38))),"") | E38: =IFERROR(IF(C38="","",C38+D38),"") | F38: =IFERROR(IF(D38="","",B38-D38),"") | G38: =IFERROR(IF(E38="","",'PyG 3 Años'!$D$41-'PyG 3 Años'!$D$46+'PyG 3 Años'!$D$36+'PyG 3 Años'!$D$37),"") | H38: =IFERROR(IF(OR(E38="",E38=0),"",G38/E38),"")
A39: 13 | B39: =IFERROR(IF(OR(13>B22,F38=""),"",F38),"") | C39: =IFERROR(IF(OR(13>B22,B39=""),"",B39*B21),"") | D39: =IFERROR(IF(OR(13>B22,B39=""),"",IF(13<=B23,0,MIN(B39,B24-C39))),"") | E39: =IFERROR(IF(C39="","",C39+D39),"") | F39: =IFERROR(IF(D39="","",B39-D39),"") | G39: =IFERROR(IF(E39="","",'PyG 3 Años'!$D$41-'PyG 3 Años'!$D$46+'PyG 3 Años'!$D$36+'PyG 3 Años'!$D$37),"") | H39: =IFERROR(IF(OR(E39="",E39=0),"",G39/E39),"")
A40: 14 | B40: =IFERROR(IF(OR(14>B22,F39=""),"",F39),"") | C40: =IFERROR(IF(OR(14>B22,B40=""),"",B40*B21),"") | D40: =IFERROR(IF(OR(14>B22,B40=""),"",IF(14<=B23,0,MIN(B40,B24-C40))),"") | E40: =IFERROR(IF(C40="","",C40+D40),"") | F40: =IFERROR(IF(D40="","",B40-D40),"") | G40: =IFERROR(IF(E40="","",'PyG 3 Años'!$D$41-'PyG 3 Años'!$D$46+'PyG 3 Años'!$D$36+'PyG 3 Años'!$D$37),"") | H40: =IFERROR(IF(OR(E40="",E40=0),"",G40/E40),"")
A41: 15 | B41: =IFERROR(IF(OR(15>B22,F40=""),"",F40),"") | C41: =IFERROR(IF(OR(15>B22,B41=""),"",B41*B21),"") | D41: =IFERROR(IF(OR(15>B22,B41=""),"",IF(15<=B23,0,MIN(B41,B24-C41))),"") | E41: =IFERROR(IF(C41="","",C41+D41),"") | F41: =IFERROR(IF(D41="","",B41-D41),"") | G41: =IFERROR(IF(E41="","",'PyG 3 Años'!$D$41-'PyG 3 Años'!$D$46+'PyG 3 Años'!$D$36+'PyG 3 Años'!$D$37),"") | H41: =IFERROR(IF(OR(E41="",E41=0),"",G41/E41),"")
A42: Tolerancia de cierre del cuadro (€) | B42: 0.01 | C42: Margen por redondeo. Por encima, el cuadro no cierra y hay capital sin devolver
A43: Capital pendiente al vencimiento | B43: =IFERROR(IF(B20="","",ROUND(B20-SUM(D27:D41),2)),"") -> 0 | C43: Tiene que ser cero: el principal devuelto en el cuadro tiene que ser el prestado. Si sale positivo, el plazo no llega
A44: Intereses del año 1 | B44: =IFERROR(IF(B20="","",IF(C27="",0,C27)),"") -> 4251
A45: Devolución de principal del año 1 | B45: =IFERROR(IF(B20="","",IF(D27="",0,D27)),"") -> 0
A46: Intereses del año 2 | B46: =IFERROR(IF(B20="","",IF(C28="",0,C28)),"") -> 4251
A47: Devolución de principal del año 2 | B47: =IFERROR(IF(B20="","",IF(D28="",0,D28)),"") -> 11486.499
A48: Intereses del año 3 | B48: =IFERROR(IF(B20="","",IF(C29="",0,C29)),"") -> 3504.3776
A49: Devolución de principal del año 3 | B49: =IFERROR(IF(B20="","",IF(D29="",0,D29)),"") -> 12233.121
A50: COBERTURA DEL SERVICIO DE LA DEUDA (DSCR)
A51: DSCR del año 1 | B51: =IFERROR(('PyG 3 Años'!$B$41-'PyG 3 Años'!$B$46+'PyG 3 Años'!$B$36+B44)/(B44+B45),"") -> 5.5727528 | C51: Año de CARENCIA si la hay: con sólo intereses en el denominador el ratio se dispara y no mide el negocio
A52: DSCR del año 2 | B52: =IFERROR(('PyG 3 Años'!$C$41-'PyG 3 Años'!$C$46+'PyG 3 Años'!$C$36+B46)/(B46+B47),"") -> 1.6552681
A53: DSCR del año 3 | B53: =IFERROR(('PyG 3 Años'!$D$41-'PyG 3 Años'!$D$46+'PyG 3 Años'!$D$36+B48)/(B48+B49),"") -> 1.5135529
A54: DSCR mínimo de todo el cuadro | B54: =IFERROR(IF(COUNT(H27:H41)=0,"",MIN(H27:H41)),"") -> 1.5135529 | C54: El peor año de los que dura el préstamo, no el mejor de los tres que proyecta el P&L. Es el número que decide una operación. Ojo al alcance: los años 1 a 3 salen del P&L y del año 4 en adelante el cuadro MANTIENE el flujo del año 3, así que el mínimo de esos años es una proyección sostenida, no un año calculado. El flujo va después de impuestos
A56: El DSCR se calcula ANTES de la deuda y DESPUÉS de impuestos: al resultado antes de impuestos se le resta el Impuesto de Sociedades y se le devuelven la amortización contable y los intereses; el resultado se divide entre lo que hay que pagar ese año. Por debajo del mínimo de la hoja de Supuestos, el negocio no genera para pagar el préstamo. En el cuadro, el flujo de caja disponible de los años 4 en adelante se mantiene en el del año 3: el P&L sólo proyecta tres, y aquí no se inventa un crecimiento que no está calculado.
