Workbook

Sheet Instrucciones
A1: Cuadro de mando semanal del manager
A2: AI Chef Pro · aichef.pro — Manual del Manager de Restaurante
A3: Para qué sirve: ver la semana mala mientras todavía puedes hacer algo con ella.
A5: Instrucciones de uso
A6: 1. Hoja «Parámetros»: elige tu tipo de negocio (sala o salón, según el país, o barra y autoservicio). Los tres objetivos en vigor (food cost, labor cost y prime cost) cambian solos, y los seis de la tabla son celdas verdes que puedes ajustar a tu casa.
A7: 2. Revisa la cotización a la Seguridad Social a cargo de la empresa. Viene al 33 %, que es la convención de la casa; debajo tienes el desglose partida por partida para ajustarlo a tus contratos.
A8: 3. Hoja «Semana»: una fila por semana ISO. Rellena las celdas verdes con lo que te dé el TPV y la nómina (planilla, en el uso de otros países): ventas de comida y de bebida, stock inicial, compras, stock final, salarios brutos, otros costes de personal, cubiertos, tickets, horas de apertura y horas trabajadas. Todo sin IVA.
A9: 4. El consumo de materia prima se calcula solo: stock inicial + compras menos stock final. No son las compras de la semana; una semana con un pedido grande no es una semana cara.
A10: 5. Mira la columna «Prime cost»: si se sale del objetivo, se pone en rojo y la columna de al lado lo dice con palabras. El gráfico del final enseña las 52 semanas contra la línea del objetivo.
A11: 6. Las columnas de la derecha son las de servicio: ticket medio, gasto medio por cubierto, cubiertos por hora de apertura y ventas por hora trabajada. Son las que explican POR QUÉ se movió el prime cost.
A12: 7. La fila TOTAL / MEDIA no hace la media de los 52 porcentajes: divide los totales del año, que es la media ponderada y la única correcta.
A13: 8. Hoja «KPI y Definiciones»: qué mide cada indicador, en qué unidad, con qué cadencia y cuál es el error típico al calcularlo. Es la hoja que se consulta cuando dos personas dan dos números distintos para lo mismo.
... A30: Versión 1.0 · septiembre 2026 · aichef.pro/manual-manager-restaurante · info@aichef.pro

Sheet Parámetros
A1: Parámetros del cuadro de mando semanal
A2: AI Chef Pro · aichef.pro — Manual del Manager de Restaurante
A4: TIPO DE NEGOCIO Y OBJETIVOS DE LA CASA
A5: Tipo de negocio | B5: Sala
A7: Tipo de negocio | B7: Objetivo de food cost (%) | C7: Objetivo de labor cost (%) | D7: Objetivo de prime cost (%)
A8: Sala | B8: 0.3 | C8: 0.33 | D8: 0.65
A9: Barra o autoservicio | B9: 0.3 | C9: 0.25 | D9: 0.55
A11: Objetivo de food cost en vigor (%) | B11: =IFERROR(INDEX($B$8:$B$9,MATCH($B$5,$A$8:$A$9,0)),"") -> 0.3
A12: Objetivo de labor cost en vigor (%) | B12: =IFERROR(INDEX($C$8:$C$9,MATCH($B$5,$A$8:$A$9,0)),"") -> 0.33
A13: Objetivo de prime cost en vigor (%) | B13: =IFERROR(INDEX($D$8:$D$9,MATCH($B$5,$A$8:$A$9,0)),"") -> 0.65
A15: El objetivo en vigor se busca en la tabla con INDEX y MATCH: si mañana añades un tercer tipo de negocio a la lista, basta con ampliar la tabla y la lista desplegable de arriba.
A16: De dónde salen estos objetivos: la estructura de costes de referencia para la restauración española sitúa la materia prima en torno al 30 % y el personal en el 30-35 % con servicio en mesa. De ahí el criterio de la casa: prime cost por debajo del 65 % con servicio en mesa y del 55 % en barra o autoservicio.
A17: Ese 65 % / 55 % es CRITERIO DE LA CASA derivado de esa estructura, no una cifra publicada por nadie: la horquilla de 15-25 % de coste de personal en barra o autoservicio que sostiene el 55 % es también criterio de la casa, no un dato de CaixaBankLab. Son celdas verdes: si tu convenio, tu horario o tu modelo de servicio son otros, cámbialas y el semáforo de la hoja «Semana» se recalcula.
A18: Fuente de la estructura de referencia: CaixaBankLab con elBullifoundation, «Consumos y beneficios de un restaurante» (sin fecha visible en la página; revisada en 2022). https://caixabanklab.com/elbullifoundation/es/consumos-beneficios-restaurante/
A20: COTIZACIÓN A LA SEGURIDAD SOCIAL A CARGO DE LA EMPRESA
A21: Parámetro | B21: Valor
A22: Seguridad Social a cargo de la empresa (%) | B22: 0.33
A24: Partida | B24: Tipo | C24: Nota
A25: Contingencias comunes | B25: 0.236 | C25: A cargo de la empresa (el trabajador aporta el 4,70 %). MM-17
A26: Desempleo (contrato indefinido) | B26: 0.055 | C26: Los contratos temporales cotizan más
A27: FOGASA | B27: 0.002
A28: Formación profesional | B28: 0.006
A29: Accidentes de trabajo y enfermedades profesionales | B29: 0.015 | C29: Tarifa de primas de la DA 61.ª TRLGSS, epígrafe del CNAE 56 «Servicios de comidas y bebidas»; comprueba el epígrafe de tu actividad
A30: MEI 2026 (parte empresarial) | B30: 0.0075 | C30: Mecanismo de Equidad Intergeneracional. Orden PJC/297/2026, art. 16
A31: TOTAL a cargo de la empresa en hostelería 2026 | B31: =IFERROR(SUM($B$25:$B$30),"") -> 0.3215 | C31: 32,15 % con contrato indefinido a tiempo completo y 33,35 % con contrato de duración determinada (MM-53). El 33 % de más arriba (celda editable) redondea esta cifra como convención de la casa (SPEC D5).
A32: Verificado el 04-09-2026 · Arts. 4.a), 4.b), 16 y 33.2 de la Orden PJC/297/2026, de 30 de marzo, y DA 61.ª del TRLGSS (tarifa de primas de AT y EP) · https://www.boe.es/diario_boe/txt.php?id=BOE-A-2026-7296
A33: ATENCIÓN, es el error caro: el 23,60 % es SOLO la cotización por contingencias comunes y no debe rotularse «coste de la Seguridad Social a cargo de la empresa». El total empresarial suma además desempleo, FOGASA, formación profesional, MEI y accidentes de trabajo. Verificado el 04-09-2026 · Art. 4.a) de la Orden PJC/297/2026, de 30 de marzo (cotización 2026) · https://www.boe.es/diario_boe/txt.php?id=BOE-A-2026-7296
A35: APERTURA AL PÚBLICO
A37: Horas de apertura de una semana completa (referencia) | B37: 42
A38: Horas de apertura previstas en las semanas registradas | B38: =IFERROR(IF(OR($B$37="",COUNT(Semana!$A$5:$A$56)=0),"",$B$37*COUNT(Semana!$A$5:$A$56)),"") -> 2184
A39: Horas de apertura realmente registradas en la hoja «Semana» | B39: =IF(COUNT(Semana!$W$5:$W$56)=0,"",SUM(Semana!$W$5:$W$56)) -> 2177
A40: Si las horas registradas y las previstas se separan mucho es que has abierto (o cerrado) más de lo que creías: festivos, vacaciones y jornadas partidas. El dato bueno es el registrado.

Sheet Semana
A1: Las 52 semanas ISO del año
A2: AI Chef Pro · aichef.pro — Manual del Manager de Restaurante
A3: Todas las cifras van sin IVA. El consumo es stock inicial + compras menos stock final, no las compras de la semana.
A4: Semana ISO | B4: Lunes de la semana | C4: Ventas netas de comida (€) | D4: Ventas netas de bebida (€) | E4: Ventas netas totales (€) | F4: Stock inicial de materia prima (€) | G4: Compras de la semana (€) | H4: Stock final de materia prima (€) | I4: Consumo de materia prima (€) | J4: Food cost (%) | K4: Salarios brutos (€) | L4: Otros costes de personal (€) | M4: Coste de personal con Seguridad Social (€) | N4: Labor cost (%) | O4: Prime cost (%) | P4: Objetivo de prime cost (%) | Q4: Lectura del prime cost | R4: Margen tras prime cost (€) | S4: Cubiertos | T4: Tickets (mesas cobradas) | U4: Ticket medio (€) | V4: Gasto medio por cubierto (€) | W4: Horas de apertura al público | X4: Cubiertos por hora de apertura | Y4: Horas trabajadas por la plantilla | Z4: Ventas por hora trabajada (€)
A5: 1 | B5: 46020 | C5: 12327 | D5: 9119 | E5: =IFERROR(IF(AND($C5="",$D5=""),"",IF($C5="",0,$C5)+IF($D5="",0,$D5)),"") -> 21446 | F5: 9700 | G5: 6762 | H5: 9834 | I5: =IFERROR(IF(OR($F5="",$G5="",$H5=""),"",$F5+$G5-$H5),"") -> 6628 | J5: =IFERROR(IF(OR($I5="",$E5="",$E5=0),"",$I5/$E5),"") -> 0.3090553 | K5: 4898 | L5: 286 | M5: =IFERROR(IF($K5="","",$K5*(1+Parámetros!$B$22)+IF($L5="",0,$L5)),"") -> 6800.34 | N5: =IFERROR(IF(OR($M5="",$E5="",$E5=0),"",$M5/$E5),"") -> 0.3170913 | O5: =IFERROR(IF(OR($I5="",$M5="",$E5="",$E5=0),"",($I5+$M5)/$E5),"") -> 0.6261466 | P5: =IF(Parámetros!$B$13="","",Parámetros!$B$13) -> 0.65 | Q5: =IF(OR($O5="",$P5=""),"",IF($O5<=$P5,"En objetivo","Por encima del objetivo")) -> En objetivo | R5: =IFERROR(IF(OR($E5="",$I5="",$M5=""),"",$E5-$I5-$M5),"") -> 8017.66 | S5: 829 | T5: 382 | U5: =IFERROR(IF(OR($E5="",$T5="",$T5=0),"",$E5/$T5),"") -> 56.141361 | V5: =IFERROR(IF(OR($E5="",$S5="",$S5=0),"",$E5/$S5),"") -> 25.869723 | W5: 35 | X5: =IFERROR(IF(OR($S5="",$W5="",$W5=0),"",$S5/$W5),"") -> 23.685714 | Y5: 433 | Z5: =IFERROR(IF(OR($E5="",$Y5="",$Y5=0),"",$E5/$Y5),"") -> 49.528868
A6: 2 | B6: 46027 | C6: 11513 | D6: 8517 | E6: =IFERROR(IF(AND($C6="",$D6=""),"",IF($C6="",0,$C6)+IF($D6="",0,$D6)),"") -> 20030 | F6: 9834 | G6: 5622 | H6: 9266 | I6: =IFERROR(IF(OR($F6="",$G6="",$H6=""),"",$F6+$G6-$H6),"") -> 6190 | J6: =IFERROR(IF(OR($I6="",$E6="",$E6=0),"",$I6/$E6),"") -> 0.30903645 | K6: 4732 | L6: 276 | M6: =IFERROR(IF($K6="","",$K6*(1+Parámetros!$B$22)+IF($L6="",0,$L6)),"") -> 6569.56 | N6: =IFERROR(IF(OR($M6="",$E6="",$E6=0),"",$M6/$E6),"") -> 0.32798602 | O6: =IFERROR(IF(OR($I6="",$M6="",$E6="",$E6=0),"",($I6+$M6)/$E6),"") -> 0.63702247 | P6: =IF(Parámetros!$B$13="","",Parámetros!$B$13) -> 0.65 | Q6: =IF(OR($O6="",$P6=""),"",IF($O6<=$P6,"En objetivo","Por encima del objetivo")) -> En objetivo | R6: =IFERROR(IF(OR($E6="",$I6="",$M6=""),"",$E6-$I6-$M6),"") -> 7270.44 | S6: 785 | T6: 357 | U6: =IFERROR(IF(OR($E6="",$T6="",$T6=0),"",$E6/$T6),"") -> 56.106443 | V6: =IFERROR(IF(OR($E6="",$S6="",$S6=0),"",$E6/$S6),"") -> 25.515924 | W6: 42 | X6: =IFERROR(IF(OR($S6="",$W6="",$W6=0),"",$S6/$W6),"") -> 18.690476 | Y6: 421 | Z6: =IFERROR(IF(OR($E6="",$Y6="",$Y6=0),"",$E6/$Y6),"") -> 47.577197
A7: 3 | B7: 46034 | C7: 11164 | D7: 8259 | E7: =IFERROR(IF(AND($C7="",$D7=""),"",IF($C7="",0,$C7)+IF($D7="",0,$D7)),"") -> 19423 | F7: 9266 | G7: 6570 | H7: 9834 | I7: =IFERROR(IF(OR($F7="",$G7="",$H7=""),"",$F7+$G7-$H7),"") -> 6002 | J7: =IFERROR(IF(OR($I7="",$E7="",$E7=0),"",$I7/$E7),"") -> 0.30901509 | K7: 4660 | L7: 272 | M7: =IFERROR(IF($K7="","",$K7*(1+Parámetros!$B$22)+IF($L7="",0,$L7)),"") -> 6469.8 | N7: =IFERROR(IF(OR($M7="",$E7="",$E7=0),"",$M7/$E7),"") -> 0.33309993 | O7: =IFERROR(IF(OR($I7="",$M7="",$E7="",$E7=0),"",($I7+$M7)/$E7),"") -> 0.64211502 | P7: =IF(Parámetros!$B$13="","",Parámetros!$B$13) -> 0.65 | Q7: =IF(OR($O7="",$P7=""),"",IF($O7<=$P7,"En objetivo","Por encima del objetivo")) -> En objetivo | R7: =IFERROR(IF(OR($E7="",$I7="",$M7=""),"",$E7-$I7-$M7),"") -> 6951.2 | S7: 764 | T7: 353 | U7: =IFERROR(IF(OR($E7="",$T7="",$T7=0),"",$E7/$T7),"") -> 55.022663 | V7: =IFERROR(IF(OR($E7="",$S7="",$S7=0),"",$E7/$S7),"") -> 25.422775 | W7: 42 | X7: =IFERROR(IF(OR($S7="",$W7="",$W7=0),"",$S7/$W7),"") -> 18.190476 | Y7: 415 | Z7: =IFERROR(IF(OR($E7="",$Y7="",$Y7=0),"",$E7/$Y7),"") -> 46.80241
A8: 4 | B8: 46041 | C8: 11629 | D8: 8603 | E8: =IFERROR(IF(AND($C8="",$D8=""),"",IF($C8="",0,$C8)+IF($D8="",0,$D8)),"") -> 20232 | F8: 9834 | G8: 5685 | H8: 9266 | I8: =IFERROR(IF(OR($F8="",$G8="",$H8=""),"",$F8+$G8-$H8),"") -> 6253 | J8: =IFERROR(IF(OR($I8="",$E8="",$E8=0),"",$I8/$E8),"") -> 0.30906485 | K8: 4755 | L8: 277 | M8: =IFERROR(IF($K8="","",$K8*(1+Parámetros!$B$22)+IF($L8="",0,$L8)),"") -> 6601.15 | N8: =IFERROR(IF(OR($M8="",$E8="",$E8=0),"",$M8/$E8),"") -> 0.32627274 | O8: =IFERROR(IF(OR($I8="",$M8="",$E8="",$E8=0),"",($I8+$M8)/$E8),"") -> 0.63533758 | P8: =IF(Parámetros!$B$13="","",Parámetros!$B$13) -> 0.65 | Q8: =IF(OR($O8="",$P8=""),"",IF($O8<=$P8,"En objetivo","Por encima del objetivo")) -> En objetivo | R8: =IFERROR(IF(OR($E8="",$I8="",$M8=""),"",$E8-$I8-$M8),"") -> 7377.85 | S8: 792 | T8: 378 | U8: =IFERROR(IF(OR($E8="",$T8="",$T8=0),"",$E8/$T8),"") -> 53.52381 | V8: =IFERROR(IF(OR($E8="",$S8="",$S8=0),"",$E8/$S8),"") -> 25.545455 | W8: 42 | X8: =IFERROR(IF(OR($S8="",$W8="",$W8=0),"",$S8/$W8),"") -> 18.857143 | Y8: 422 | Z8: =IFERROR(IF(OR($E8="",$Y8="",$Y8=0),"",$E8/$Y8),"") -> 47.943128
A9: 5 | B9: 46048 | C9: 11513 | D9: 8517 | E9: =IFERROR(IF(AND($C9="",$D9=""),"",IF($C9="",0,$C9)+IF($D9="",0,$D9)),"") -> 20030 | F9: 9266 | G9: 6324 | H9: 9400 | I9: =IFERROR(IF(OR($F9="",$G9="",$H9=""),"",$F9+$G9-$H9),"") -> 6190 | J9: =IFERROR(IF(OR($I9="",$E9="",$E9=0),"",$I9/$E9),"") -> 0.30903645 | K9: 4732 | L9: 276 | M9: =IFERROR(IF($K9="","",$K9*(1+Parámetros!$B$22)+IF($L9="",0,$L9)),"") -> 6569.56 | N9: =IFERROR(IF(OR($M9="",$E9="",$E9=0),"",$M9/$E9),"") -> 0.32798602 | O9: =IFERROR(IF(OR($I9="",$M9="",$E9="",$E9=0),"",($I9+$M9)/$E9),"") -> 0.63702247 | P9: =IF(Parámetros!$B$13="","",Parámetros!$B$13) -> 0.65 | Q9: =IF(OR($O9="",$P9=""),"",IF($O9<=$P9,"En objetivo","Por encima del objetivo")) -> En objetivo | R9: =IFERROR(IF(OR($E9="",$I9="",$M9=""),"",$E9-$I9-$M9),"") -> 7270.44 | S9: 774 | T9: 382 | U9: =IFERROR(IF(OR($E9="",$T9="",$T9=0),"",$E9/$T9),"") -> 52.434555 | V9: =IFERROR(IF(OR($E9="",$S9="",$S9=0),"",$E9/$S9),"") -> 25.878553 | W9: 42 | X9: =IFERROR(IF(OR($S9="",$W9="",$W9=0),"",$S9/$W9),"") -> 18.428571 | Y9: 421 | Z9: =IFERROR(IF(OR($E9="",$Y9="",$Y9=0),"",$E9/$Y9),"") -> 47.577197
A10: 6 | B10: 46055 | C10: 12221 | D10: 9014 | E10: =IFERROR(IF(AND($C10="",$D10=""),"",IF($C10="",0,$C10)+IF($D10="",0,$D10)),"") -> 21235 | F10: 9400 | G10: 6548 | H10: 9558 | I10: =IFERROR(IF(OR($F10="",$G10="",$H10=""),"",$F10+$G10-$H10),"") -> 6390 | J10: =IFERROR(IF(OR($I10="",$E10="",$E10=0),"",$I10/$E10),"") -> 0.3009183 | K10: 5291 | L10: 292 | M10: =IFERROR(IF($K10="","",$K10*(1+Parámetros!$B$22)+IF($L10="",0,$L10)),"") -> 7329.03 | N10: =IFERROR(IF(OR($M10="",$E10="",$E10=0),"",$M10/$E10),"") -> 0.34513916 | O10: =IFERROR(IF(OR($I10="",$M10="",$E10="",$E10=0),"",($I10+$M10)/$E10),"") -> 0.64605745 | P10: =IF(Parámetros!$B$13="","",Parámetros!$B$13) -> 0.65 | Q10: =IF(OR($O10="",$P10=""),"",IF($O10<=$P10,"En objetivo","Por encima del objetivo")) -> En objetivo | R10: =IFERROR(IF(OR($E10="",$I10="",$M10=""),"",$E10-$I10-$M10),"") -> 7515.97 | S10: 807 | T10: 403 | U10: =IFERROR(IF(OR($E10="",$T10="",$T10=0),"",$E10/$T10),"") -> 52.692308 | V10: =IFERROR(IF(OR($E10="",$S10="",$S10=0),"",$E10/$S10),"") -> 26.313507 | W10: 42 | X10: =IFERROR(IF(OR($S10="",$W10="",$W10=0),"",$S10/$W10),"") -> 19.214286 | Y10: 431 | Z10: =IFERROR(IF(OR($E10="",$Y10="",$Y10=0),"",$E10/$Y10),"") -> 49.269142
A11: 7 | B11: 46062 | C11: 11616 | D11: 8568 | E11: =IFERROR(IF(AND($C11="",$D11=""),"",IF($C11="",0,$C11)+IF($D11="",0,$D11)),"") -> 20184 | F11: 9558 | G11: 6747 | H11: 8920 | I11: =IFERROR(IF(OR($F11="",$G11="",$H11=""),"",$F11+$G11-$H11),"") -> 7385 | J11: =IFERROR(IF(OR($I11="",$E11="",$E11=0),"",$I11/$E11),"") -> 0.36588387 | K11: 5160 | L11: 284 | M11: =IFERROR(IF($K11="","",$K11*(1+Parámetros!$B$22)+IF($L11="",0,$L11)),"") -> 7146.8 | N11: =IFERROR(IF(OR($M11="",$E11="",$E11=0),"",$M11/$E11),"") -> 0.35408244 | O11: =IFERROR(IF(OR($I11="",$M11="",$E11="",$E11=0),"",($I11+$M11)/$E11),"") -> 0.71996631 | P11: =IF(Parámetros!$B$13="","",Parámetros!$B$13) -> 0.65 | Q11: =IF(OR($O11="",$P11=""),"",IF($O11<=$P11,"En objetivo","Por encima del objetivo")) -> Por encima del objetivo | R11: =IFERROR(IF(OR($E11="",$I11="",$M11=""),"",$E11-$I11-$M11),"") -> 5652.2 | S11: 753 | T11: 370 | U11: =IFERROR(IF(OR($E11="",$T11="",$T11=0),"",$E11/$T11),"") -> 54.551351 | V11: =IFERROR(IF(OR($E11="",$S11="",$S11=0),"",$E11/$S11),"") -> 26.804781 | W11: 42 | X11: =IFERROR(IF(OR($S11="",$W11="",$W11=0),"",$S11/$W11),"") -> 17.928571 | Y11: 422 | Z11: =IFERROR(IF(OR($E11="",$Y11="",$Y11=0),"",$E11/$Y11),"") -> 47.829384
A12: 8 | B12: 46069 | C12: 12100 | D12: 8925 | E12: =IFERROR(IF(AND($C12="",$D12=""),"",IF($C12="",0,$C12)+IF($D12="",0,$D12)),"") -> 21025 | F12: 8920 | G12: 6815 | H12: 9408 | I12: =IFERROR(IF(OR($F12="",$G12="",$H12=""),"",$F12+$G12-$H12),"") -> 6327 | J12: =IFERROR(IF(OR($I12="",$E12="",$E12=0),"",$I12/$E12),"") -> 0.30092747 | K12: 5265 | L12: 290 | M12: =IFERROR(IF($K12="","",$K12*(1+Parámetros!$B$22)+IF($L12="",0,$L12)),"") -> 7292.45 | N12: =IFERROR(IF(OR($M12="",$E12="",$E12=0),"",$M12/$E12),"") -> 0.34684661 | O12: =IFERROR(IF(OR($I12="",$M12="",$E12="",$E12=0),"",($I12+$M12)/$E12),"") -> 0.64777408 | P12: =IF(Parámetros!$B$13="","",Parámetros!$B$13) -> 0.65 | Q12: =IF(OR($O12="",$P12=""),"",IF($O12<=$P12,"En objetivo","Por encima del objetivo")) -> En objetivo | R12: =IFERROR(IF(OR($E12="",$I12="",$M12=""),"",$E12-$I12-$M12),"") -> 7405.55 | S12: 775 | T12: 367 | U12: =IFERROR(IF(OR($E12="",$T12="",$T12=0),"",$E12/$T12),"") -> 57.288828 | V12: =IFERROR(IF(OR($E12="",$S12="",$S12=0),"",$E12/$S12),"") -> 27.129032 | W12: 42 | X12: =IFERROR(IF(OR($S12="",$W12="",$W12=0),"",$S12/$W12),"") -> 18.452381 | Y12: 429 | Z12: =IFERROR(IF(OR($E12="",$Y12="",$Y12=0),"",$E12/$Y12),"") -> 49.009324
A13: 9 | B13: 46076 | C13: 12463 | D13: 9193 | E13: =IFERROR(IF(AND($C13="",$D13=""),"",IF($C13="",0,$C13)+IF($D13="",0,$D13)),"") -> 21656 | F13: 9408 | G13: 6208 | H13: 9100 | I13: =IFERROR(IF(OR($F13="",$G13="",$H13=""),"",$F13+$G13-$H13),"") -> 6516 | J13: =IFERROR(IF(OR($I13="",$E13="",$E13=0),"",$I13/$E13),"") -> 0.30088659 | K13: 5344 | L13: 294 | M13: =IFERROR(IF($K13="","",$K13*(1+Parámetros!$B$22)+IF($L13="",0,$L13)),"") -> 7401.52 | N13: =IFERROR(IF(OR($M13="",$E13="",$E13=0),"",$M13/$E13),"") -> 0.34177687 | O13: =IFERROR(IF(OR($I13="",$M13="",$E13="",$E13=0),"",($I13+$M13)/$E13),"") -> 0.64266347 | P13: =IF(Parámetros!$B$13="","",Parámetros!$B$13) -> 0.65 | Q13: =IF(OR($O13="",$P13=""),"",IF($O13<=$P13,"En objetivo","Por encima del objetivo")) -> En objetivo | R13: =IFERROR(IF(OR($E13="",$I13="",$M13=""),"",$E13-$I13-$M13),"") -> 7738.48 | S13: 795 | T13: 365 | U13: =IFERROR(IF(OR($E13="",$T13="",$T13=0),"",$E13/$T13),"") -> 59.331507 | V13: =IFERROR(IF(OR($E13="",$S13="",$S13=0),"",$E13/$S13),"") -> 27.240252 | W13: 42 | X13: =IFERROR(IF(OR($S13="",$W13="",$W13=0),"",$S13/$W13),"") -> 18.928571 | Y13: 434 | Z13: =IFERROR(IF(OR($E13="",$Y13="",$Y13=0),"",$E13/$Y13),"") -> 49.898618
A14: 10 | B14: 46083 | C14: 12105 | D14: 8962 | E14: =IFERROR(IF(AND($C14="",$D14=""),"",IF($C14="",0,$C14)+IF($D14="",0,$D14)),"") -> 21067 | F14: 9100 | G14: 6871 | H14: 9433 | I14: =IFERROR(IF(OR($F14="",$G14="",$H14=""),"",$F14+$G14-$H14),"") -> 6538 | J14: =IFERROR(IF(OR($I14="",$E14="",$E14=0),"",$I14/$E14),"") -> 0.31034319 | K14: 4925 | L14: 278 | M14: =IFERROR(IF($K14="","",$K14*(1+Parámetros!$B$22)+IF($L14="",0,$L14)),"") -> 6828.25 | N14: =IFERROR(IF(OR($M14="",$E14="",$E14=0),"",$M14/$E14),"") -> 0.32412066 | O14: =IFERROR(IF(OR($I14="",$M14="",$E14="",$E14=0),"",($I14+$M14)/$E14),"") -> 0.63446385 | P14: =IF(Parámetros!$B$13="","",Parámetros!$B$13) -> 0.65 | Q14: =IF(OR($O14="",$P14=""),"",IF($O14<=$P14,"En objetivo","Por encima del objetivo")) -> En objetivo | R14: =IFERROR(IF(OR($E14="",$I14="",$M14=""),"",$E14-$I14-$M14),"") -> 7700.75 | S14: 776 | T14: 353 | U14: =IFERROR(IF(OR($E14="",$T14="",$T14=0),"",$E14/$T14),"") -> 59.679887 | V14: =IFERROR(IF(OR($E14="",$S14="",$S14=0),"",$E14/$S14),"") -> 27.148196 | W14: 42 | X14: =IFERROR(IF(OR($S14="",$W14="",$W14=0),"",$S14/$W14),"") -> 18.47619 | Y14: 429 | Z14: =IFERROR(IF(OR($E14="",$Y14="",$Y14=0),"",$E14/$Y14),"") -> 49.107226
A15: 11 | B15: 46090 | C15: 12352 | D15: 9145 | E15: =IFERROR(IF(AND($C15="",$D15=""),"",IF($C15="",0,$C15)+IF($D15="",0,$D15)),"") -> 21497 | F15: 9433 | G15: 6208 | H15: 8970 | I15: =IFERROR(IF(OR($F15="",$G15="",$H15=""),"",$F15+$G15-$H15),"") -> 6671 | J15: =IFERROR(IF(OR($I15="",$E15="",$E15=0),"",$I15/$E15),"") -> 0.31032237 | K15: 4975 | L15: 281 | M15: =IFERROR(IF($K15="","",$K15*(1+Parámetros!$B$22)+IF($L15="",0,$L15)),"") -> 6897.75 | N15: =IFERROR(IF(OR($M15="",$E15="",$E15=0),"",$M15/$E15),"") -> 0.32087035 | O15: =IFERROR(IF(OR($I15="",$M15="",$E15="",$E15=0),"",($I15+$M15)/$E15),"") -> 0.63119272 | P15: =IF(Parámetros!$B$13="","",Parámetros!$B$13) -> 0.65 | Q15: =IF(OR($O15="",$P15=""),"",IF($O15<=$P15,"En objetivo","Por encima del objetivo")) -> En objetivo | R15: =IFERROR(IF(OR($E15="",$I15="",$M15=""),"",$E15-$I15-$M15),"") -> 7928.25 | S15: 802 | T15: 372 | U15: =IFERROR(IF(OR($E15="",$T15="",$T15=0),"",$E15/$T15),"") -> 57.787634 | V15: =IFERROR(IF(OR($E15="",$S15="",$S15=0),"",$E15/$S15),"") -> 26.804239 | W15: 42 | X15: =IFERROR(IF(OR($S15="",$W15="",$W15=0),"",$S15/$W15),"") -> 19.095238 | Y15: 433 | Z15: =IFERROR(IF(OR($E15="",$Y15="",$Y15=0),"",$E15/$Y15),"") -> 49.646651
A16: 12 | B16: 46097 | C16: 12475 | D16: 9237 | E16: =IFERROR(IF(AND($C16="",$D16=""),"",IF($C16="",0,$C16)+IF($D16="",0,$D16)),"") -> 21712 | F16: 8970 | G16: 7401 | H16: 9633 | I16: =IFERROR(IF(OR($F16="",$G16="",$H16=""),"",$F16+$G16-$H16),"") -> 6738 | J16: =IFERROR(IF(OR($I16="",$E16="",$E16=0),"",$I16/$E16),"") -> 0.3103353 | K16: 5000 | L16: 283 | M16: =IFERROR(IF($K16="","",$K16*(1+Parámetros!$B$22)+IF($L16="",0,$L16)),"") -> 6933 | N16: =IFERROR(IF(OR($M16="",$E16="",$E16=0),"",$M16/$E16),"") -> 0.31931651 | O16: =IFERROR(IF(OR($I16="",$M16="",$E16="",$E16=0),"",($I16+$M16)/$E16),"") -> 0.62965181 | P16: =IF(Parámetros!$B$13="","",Parámetros!$B$13) -> 0.65 | Q16: =IF(OR($O16="",$P16=""),"",IF($O16<=$P16,"En objetivo","Por encima del objetivo")) -> En objetivo | R16: =IFERROR(IF(OR($E16="",$I16="",$M16=""),"",$E16-$I16-$M16),"") -> 8041 | S16: 824 | T16: 396 | U16: =IFERROR(IF(OR($E16="",$T16="",$T16=0),"",$E16/$T16),"") -> 54.828283 | V16: =IFERROR(IF(OR($E16="",$S16="",$S16=0),"",$E16/$S16),"") -> 26.349515 | W16: 42 | X16: =IFERROR(IF(OR($S16="",$W16="",$W16=0),"",$S16/$W16),"") -> 19.619048 | Y16: 435 | Z16: =IFERROR(IF(OR($E16="",$Y16="",$Y16=0),"",$E16/$Y16),"") -> 49.912644
... A56: 52 | B56: 46377 | C56: 16692 | D56: 12329 | E56: =IFERROR(IF(AND($C56="",$D56=""),"",IF($C56="",0,$C56)+IF($D56="",0,$D56)),"") -> 29021 | F56: 10458 | G56: 9046 | H56: 10400 | I56: =IFERROR(IF(OR($F56="",$G56="",$H56=""),"",$F56+$G56-$H56),"") -> 9104 | J56: =IFERROR(IF(OR($I56="",$E56="",$E56=0),"",$I56/$E56),"") -> 0.31370387 | K56: 5694 | L56: 389 | M56: =IFERROR(IF($K56="","",$K56*(1+Parámetros!$B$22)+IF($L56="",0,$L56)),"") -> 7962.02 | N56: =IFERROR(IF(OR($M56="",$E56="",$E56=0),"",$M56/$E56),"") -> 0.27435374 | O56: =IFERROR(IF(OR($I56="",$M56="",$E56="",$E56=0),"",($I56+$M56)/$E56),"") -> 0.58805761 | P56: =IF(Parámetros!$B$13="","",Parámetros!$B$13) -> 0.65 | Q56: =IF(OR($O56="",$P56=""),"",IF($O56<=$P56,"En objetivo","Por encima del objetivo")) -> En objetivo | R56: =IFERROR(IF(OR($E56="",$I56="",$M56=""),"",$E56-$I56-$M56),"") -> 11954.98 | S56: 1140 | T56: 561 | U56: =IFERROR(IF(OR($E56="",$T56="",$T56=0),"",$E56/$T56),"") -> 51.730838 | V56: =IFERROR(IF(OR($E56="",$S56="",$S56=0),"",$E56/$S56),"") -> 25.457018 | W56: 35 | X56: =IFERROR(IF(OR($S56="",$W56="",$W56=0),"",$S56/$W56),"") -> 32.571429 | Y56: 498 | Z56: =IFERROR(IF(OR($E56="",$Y56="",$Y56=0),"",$E56/$Y56),"") -> 58.2751
A57: TOTAL / MEDIA | C57: =IF(COUNT(C5:C56)=0,"",SUM(C5:C56)) -> 705109 | D57: =IF(COUNT(D5:D56)=0,"",SUM(D5:D56)) -> 521552 | E57: =IF(COUNT(E5:E56)=0,"",SUM(E5:E56)) -> 1226661 | G57: =IF(COUNT(G5:G56)=0,"",SUM(G5:G56)) -> 390164 | I57: =IF(COUNT(I5:I56)=0,"",SUM(I5:I56)) -> 389464 | J57: =IFERROR(IF(OR($I$57="",$E$57="",$E$57=0),"",$I$57/$E$57),"") -> 0.31749929 | K57: =IF(COUNT(K5:K56)=0,"",SUM(K5:K56)) -> 273910 | L57: =IF(COUNT(L5:L56)=0,"",SUM(L5:L56)) -> 16231 | M57: =IF(COUNT(M5:M56)=0,"",SUM(M5:M56)) -> 380531.3 | N57: =IFERROR(IF(OR($M$57="",$E$57="",$E$57=0),"",$M$57/$E$57),"") -> 0.31021717 | O57: =IFERROR(IF(OR($I$57="",$M$57="",$E$57="",$E$57=0),"",($I$57+$M$57)/$E$57),"") -> 0.62771646 | P57: =IF(Parámetros!$B$13="","",Parámetros!$B$13) -> 0.65 | Q57: =IF(OR($O$57="",$P$57=""),"",IF($O$57<=$P$57,"En objetivo","Por encima del objetivo")) -> En objetivo | R57: =IF(COUNT(R5:R56)=0,"",SUM(R5:R56)) -> 456665.7 | S57: =IF(COUNT(S5:S56)=0,"",SUM(S5:S56)) -> 46737 | T57: =IF(COUNT(T5:T56)=0,"",SUM(T5:T56)) -> 22263 | U57: =IFERROR(IF(OR($E$57="",$T$57="",$T$57=0),"",$E$57/$T$57),"") -> 55.098639 | V57: =IFERROR(IF(OR($E$57="",$S$57="",$S$57=0),"",$E$57/$S$57),"") -> 26.246036 | W57: =IF(COUNT(W5:W56)=0,"",SUM(W5:W56)) -> 2177 | X57: =IFERROR(IF(OR($S$57="",$W$57="",$W$57=0),"",$S$57/$W$57),"") -> 21.468535 | Y57: =IF(COUNT(Y5:Y56)=0,"",SUM(Y5:Y56)) -> 23462 | Z57: =IFERROR(IF(OR($E$57="",$Y$57="",$Y$57=0),"",$E$57/$Y$57),"") -> 52.282883
A58: En la fila TOTAL no se suman los stocks: el consumo del año es la suma de los consumos de las 52 semanas, y los porcentajes son medias ponderadas sobre las ventas del año, no la media de los 52 porcentajes.
A61: PARÁMETROS EN VIGOR — se leen de la hoja «Parámetros»; cámbialos allí, no aquí
A62: Tipo de negocio | E62: =Parámetros!$B$5 -> Sala
A63: Objetivo de food cost (%) | E63: =IF(Parámetros!$B$11="","",Parámetros!$B$11) -> 0.3
A64: Objetivo de labor cost (%) | E64: =IF(Parámetros!$B$12="","",Parámetros!$B$12) -> 0.33
A65: Objetivo de prime cost (%) | E65: =IF(Parámetros!$B$13="","",Parámetros!$B$13) -> 0.65
A66: Seguridad Social a cargo de la empresa (%) | E66: =IF(Parámetros!$B$22="","",Parámetros!$B$22) -> 0.33

Sheet KPI y Definiciones
A1: KPI y definiciones
A2: AI Chef Pro · aichef.pro — Manual del Manager de Restaurante
A3: La columna «Error típico» es la que evita las discusiones: casi siempre que dos personas dan dos números distintos para lo mismo, una de las dos está cometiendo el error de esa columna.
A4: Indicador | B4: Cómo se calcula | C4: Unidad | D4: Error típico | E4: Cadencia
A5: Ventas netas | B5: Lo cobrado por comida y bebida SIN IVA, después de descuentos e invitaciones | C5: € | D5: Usar la cifra con IVA: infla las ventas un 10 % y hace parecer bueno un food cost que no lo es | E5: Semanal
A6: Consumo de materia prima | B6: Stock inicial + compras del periodo - stock final | C6: € | D6: Usar las compras en lugar del consumo: una semana con un pedido grande sale disparada y la siguiente, regalada | E6: Semanal
A7: Food cost % | B7: Consumo de materia prima ÷ ventas netas | C7: % | D7: Calcularlo sin contar el inventario, o mezclando comida y bebida cuando el objetivo de cada una es distinto | E7: Semanal
A8: Coste de personal | B8: Salarios brutos × (1 + Seguridad Social a cargo de la empresa) + otros costes de personal | C8: € | D8: Quedarse en el bruto y olvidar la cotización: se deja fuera aproximadamente un tercio del coste | E8: Semanal
A9: Labor cost % | B9: Coste de personal ÷ ventas netas | C9: % | D9: Compararlo con el de otro local sin mirar si aquel es de sala o de barra: no juegan la misma liga | E9: Semanal
A10: Prime cost % | B10: Food cost % + labor cost % | C10: % | D10: Mirar sólo el food cost: un 28 % de producto no salva un 40 % de personal | E10: Semanal
A11: Margen tras prime cost | B11: Ventas netas - consumo de materia prima - coste de personal | C11: € | D11: Confundirlo con el beneficio: de aquí todavía salen alquiler, suministros, amortización e impuestos | E11: Semanal
A12: Ticket medio | B12: Ventas netas ÷ número de tickets (mesas cobradas) | C12: € | D12: Llamarle ticket medio al gasto por cubierto: en una mesa de dos, el ticket es el doble | E12: Semanal
A13: Gasto medio por cubierto | B13: Ventas netas ÷ número de cubiertos (comensales) | C13: € | D13: Contar como cubierto a quien sólo toma café: distorsiona la serie y hace ilegible la comparación | E13: Semanal
A14: Cubiertos por hora de apertura | B14: Cubiertos ÷ horas de apertura al público | C14: cubiertos/h | D14: Usarlo para medir a la sala: mide la demanda y el aforo, no el rendimiento del equipo | E14: Semanal
A15: Ventas por hora trabajada | B15: Ventas netas ÷ horas realmente trabajadas por toda la plantilla | C15: €/h | D15: Alimentarlo con las horas del contrato en lugar de las del registro de jornada | E15: Semanal
... A18: Cobertura por estación | B18: Personas a nivel 2 o 3 en la estación ÷ personas de esa área | C18: % | D18: Dar por cubierta una estación porque «todos han estado alguna vez»: nivel 1 no cubre un servicio | E18: Trimestral
A20: Los ocho primeros indicadores salen de la hoja «Semana» de este mismo libro. La rotación, el absentismo y la cobertura por estación se miden con otras herramientas del pack y con otra cadencia: por eso no tienen columna aquí.
A21: Ninguno de estos indicadores se compara con el de otro local sin mirar antes si aquel es de sala o de barra, si abre mediodía y noche y con qué convenio: comparar por comparar es la forma más rápida de tomar una decisión mala con un número bueno.
