Workbook

Sheet Calculadora
A1: CALCULADORA DE PRESUPUESTO DEL ESPACIO PARA BODAS Y EVENTOS EN FINCA
A2: Escribe sólo en las celdas VERDES: todo lo demás se calcula. Importes sin IVA salvo donde la fila diga lo contrario. Los valores por defecto son estimaciones de ejemplo del kit: cámbialos por los de tu finca.
A4: DATOS DEL EVENTO | B4: Valor | C4: Notas
A5: Cliente | B5: Particular | C5: Particular o Empresa: cambian el calendario de cobros y los tramos de cancelación (tabla del final). Una empresa recibe el presupuesto «más IVA»; un particular, con el IVA incluido.
A6: Tipología del evento | B6: Boda | C6: Boda, empresa (jornada, comida, Navidad), celebración privada (comunión, bautizo, cumpleaños) o celebración pequeña (preboda, brunch, boda íntima). Fija la tarifa del espacio, el menú del catering y el coste directo con las tablas del final.
A7: Fecha del evento | B7: 46557 | C7: Escribe la fecha completa (dd/mm/aaaa). Fija la temporada y el tipo de día con las tablas de meses y de días de la semana.
A8: Invitados previstos | B8: 110 | C8: Número entero de invitados. Se garantiza el mayor entre este número y el mínimo de la temporada.
A9: Ceremonias en la finca (nº) | B9: 1 | C9: Civil o simbólica, a precio de la tabla de servicios extra.
A10: Horas extra de uso del espacio (nº) | B10: 2 | C10: Las horas que pasan del horario base de tu contrato.
A11: Montajes premium (nº) | B11: 1 | C11: Decoración, mobiliario y luces por encima del montaje básico.
A12: Alojamiento: habitaciones-noche (nº) | B12: 0 | C12: 0 si la finca no tiene habitaciones. Ejemplo: 6 habitaciones × 2 noches = 12.
A13: Horas de personal de la finca en el evento (coordinación y auxiliares) | B13: 16 | C13: Estimación del kit: pon las horas reales de tu equipo (no incluye cocina ni sala: las pone el catering).
A14: Coste bruto por hora del personal | B14: 13 | C14: Estimación del kit. Copia tu convenio provincial de hostelería.
A15: Seguridad Social a cargo de la empresa | B15: 0.33 | C15: 30,65 % de contingencias, desempleo, FOGASA, formación y MEI, más AT/EP (fijos discontinuos, art. 16 ET).
A16: Coste directo de los servicios extra (% sobre su precio) | B16: 0.4 | C16: Estimación del kit: lo que te cuesta prestar la ceremonia, el montaje, las horas extra y el alojamiento.
A17: Redondeo del precio del espacio (múltiplo, en euros) | B17: 50 | C17: El precio del espacio se redondea a este múltiplo, al más cercano.
A18: Canon del catering exclusivo (% de lo que factura el catering) | B18: 0.12 | C18: SUPUESTO editable, no un dato: negócialo con tu catering. Informativo: lo paga el catering a la finca, no el cliente.
... A20: IVA del menú del catering (solo orientativo) | B20: 0.1 | C20: El menú lo factura el catering, no la finca (comida y bebida para consumir en el acto, art. 91.Uno.2.2.º de la Ley 37/1992).
A22: CÁLCULO | B22: Valor | C22: Notas
A23: Temporada de la fecha (de la tabla de meses) | B23: =INDEX('Calculadora'!$B$83:$B$94,MONTH($B$7)) -> Alta | C23: Busca el mes de la fecha en la tabla del final.
A24: Tipo de día (de la tabla de días de la semana) | B24: =INDEX('Calculadora'!$B$97:$B$103,WEEKDAY($B$7)) -> Sábado | C24: Busca el día de la semana de la fecha en la tabla del final.
A25: Ajuste de temporada (suplemento + / descuento −) | B25: =INDEX('Calculadora'!$B$73:$B$75,MATCH($B$23,'Calculadora'!$A$73:$A$75,0)) -> 0.2 | C25: De la tabla de temporadas.
A26: Ajuste de día (suplemento + / descuento −) | B26: =INDEX('Calculadora'!$B$78:$B$80,MATCH($B$24,'Calculadora'!$A$78:$A$80,0)) -> 0 | C26: De la tabla de días.
A27: Tarifa del espacio de la tipología (sábado, temporada media) | B27: =INDEX('Calculadora'!$B$67:$B$70,MATCH($B$6,'Calculadora'!$A$67:$A$70,0)) -> 3600 | C27: De la tabla de tipologías.
A28: ALQUILER DEL ESPACIO SIN IVA | B28: =ROUND($B$27*(1+$B$25)*(1+$B$26)/$B$17,0)*$B$17 -> 4300 | C28: Tarifa × (1 + ajuste de temporada) × (1 + ajuste de día), redondeada al múltiplo elegido.
A29: Mínimo de invitados de la temporada | B29: =INDEX('Calculadora'!$C$73:$C$75,MATCH($B$23,'Calculadora'!$A$73:$A$75,0)) -> 80 | C29: De la tabla de temporadas.
A30: Invitados garantizados | B30: =MAX($B$8,$B$29) -> 110 | C30: El mayor entre los invitados previstos y el mínimo de la temporada.
A31: Aviso del mínimo | B31: =IF($B$8<$B$29,"Por debajo del mínimo: se garantiza el mínimo de la temporada","Cumple el mínimo") -> Cumple el mínimo
A32: Ceremonias | B32: =$B$9*'Calculadora'!$B$106 -> 450 | C32: Nº × precio de la tabla de servicios extra.
A33: Horas extra | B33: =$B$10*'Calculadora'!$B$107 -> 600
A34: Montajes premium | B34: =$B$11*'Calculadora'!$B$108 -> 600
A35: Alojamiento | B35: =$B$12*'Calculadora'!$B$109 -> 0
A36: Servicios extra sin IVA | B36: =$B$32+$B$33+$B$34+$B$35 -> 1650
A37: Base imponible (espacio + servicios) | B37: =$B$28+$B$36 -> 5950
A38: IVA de la finca | B38: =$B$37*$B$19 -> 1249.5
A39: TOTAL DE LA FINCA (con IVA) | B39: =$B$37+$B$38 -> 7199.5 | C39: No incluye el menú ni la bebida: los factura el catering exclusivo, aparte.
A40: Importe que presupuestas (Particular: con IVA · Empresa: más IVA) | B40: =IF($B$5="Particular",$B$39,$B$37) -> 7199.5 | C40: A una empresa se le presupuesta sin IVA («+ IVA»); a un particular, con los impuestos incluidos.
A41: Precio del espacio y servicios por invitado garantizado (sin IVA) | B41: =$B$37/$B$30 -> 54.090909 | C41: Para comparar con otras fincas.
A42: Importe del cobro 1: reserva | B42: =$B$39*INDEX('Calculadora'!$B$112:$C$112,MATCH($B$5,'Calculadora'!$B$111:$C$111,0)) -> 1799.875 | C42: Al firmar el contrato.
A43: Importe del cobro 2: segundo pago | B43: =$B$39*INDEX('Calculadora'!$B$113:$C$113,MATCH($B$5,'Calculadora'!$B$111:$C$111,0)) -> 2519.825
A44: Fecha límite del segundo pago | B44: =$B$7-INDEX('Calculadora'!$B$115:$C$115,MATCH($B$5,'Calculadora'!$B$111:$C$111,0)) -> 46377 | C44: Fecha del evento menos los días de la tabla.
A45: Importe del cobro 3: liquidación | B45: =$B$39*INDEX('Calculadora'!$B$114:$C$114,MATCH($B$5,'Calculadora'!$B$111:$C$111,0)) -> 2879.8
A46: Fecha límite de la liquidación | B46: =$B$7-INDEX('Calculadora'!$B$116:$C$116,MATCH($B$5,'Calculadora'!$B$111:$C$111,0)) -> 46527 | C46: Fecha del evento menos los días de la tabla.
A47: Importe del menú del catering sin IVA (estimado, invitados garantizados) | B47: =INDEX('Calculadora'!$C$67:$C$70,MATCH($B$6,'Calculadora'!$A$67:$A$70,0))*$B$30 -> 12100 | C47: INFORMATIVO. Menú por invitado de la tabla de tipologías × invitados garantizados. No es ingreso de la finca.
A48: CANON ESTIMADO DEL CATERING sin IVA (informativo) | B48: =$B$47*$B$18 -> 1452 | C48: Lo paga el catering exclusivo a la finca, no el cliente. Es un supuesto: negócialo.
A49: Canon estimado con IVA | B49: =$B$48*(1+$B$19) -> 1756.92 | C49: La finca factura el canon al catering con IVA.
A50: Menú del catering con IVA (orientativo, lo cobra el catering) | B50: =$B$47*(1+$B$20) -> 13310 | C50: Para que el cliente vea el coste completo.
A51: Importe orientativo completo para el cliente (finca con IVA + menú) | B51: =$B$39+$B$50 -> 20509.5 | C51: Suma lo que paga a la finca y lo que paga al catering.
A52: Coste directo del evento: limpieza, aseos, gasoil, vigilancia y música | B52: =INDEX('Calculadora'!$D$67:$D$70,MATCH($B$6,'Calculadora'!$A$67:$A$70,0)) -> 650 | C52: De la tabla de tipologías (estimación del kit, sin tarifas públicas).
A53: Coste de personal de la finca (salario + Seguridad Social) | B53: =$B$13*$B$14*(1+$B$15) -> 276.64
A54: Coste directo de los servicios extra | B54: =$B$36*$B$16 -> 660
A55: Coste directo total del evento | B55: =$B$52+$B$53+$B$54 -> 1586.64
A56: Ingresos de la finca por el evento (sin IVA, con canon) | B56: =$B$37+$B$48 -> 7402 | C56: Espacio + servicios + canon estimado.
A57: Margen del evento para la finca (euros) | B57: =$B$56-$B$55 -> 5815.36 | C57: Contribución: antes de la renta, el personal fijo, los suministros, los seguros y la estructura del plan financiero.
A58: Margen del evento (calculado) | B58: =IF($B$56=0,0,$B$57/$B$56) -> 0.78564712 | C58: Sale de los costes, nunca se teclea.
A59: Margen del evento sin el canon (euros) | B59: =$B$37-$B$55 -> 4363.36 | C59: Cuánto dejaría el evento si el catering no pagara canon.
A60: Importe retenido si cancela: tramo 1 | B60: =$B$39*INDEX('Calculadora'!$B$117:$C$117,MATCH($B$5,'Calculadora'!$B$111:$C$111,0)) -> 719.95 | C60: Tramo más lejano al evento (ver tabla de tramos). Si cancela la finca: devuelve lo cobrado y paga lo mismo.
A61: Importe retenido si cancela: tramo 2 | B61: =$B$39*INDEX('Calculadora'!$B$118:$C$118,MATCH($B$5,'Calculadora'!$B$111:$C$111,0)) -> 1799.875
A62: Importe retenido si cancela: tramo 3 | B62: =$B$39*INDEX('Calculadora'!$B$119:$C$119,MATCH($B$5,'Calculadora'!$B$111:$C$111,0)) -> 3599.75
A63: Importe retenido si cancela: tramo 4 | B63: =$B$39*INDEX('Calculadora'!$B$120:$C$120,MATCH($B$5,'Calculadora'!$B$111:$C$111,0)) -> 5399.625
A64: Importe retenido si cancela: tramo 5 | B64: =$B$39*INDEX('Calculadora'!$B$121:$C$121,MATCH($B$5,'Calculadora'!$B$111:$C$111,0)) -> 7199.5 | C64: Último tramo, hasta el día del evento.
A66: TIPOLOGÍA → TARIFA, MENÚ DEL CATERING Y COSTE DIRECTO (sin IVA) | B66: Tarifa del espacio (sábado, temporada media) | C66: Menú del catering por invitado | D66: Coste directo del evento
A67: Boda | B67: 3600 | C67: 110 | D67: 650 | E67: Cifras de EJEMPLO del kit (precios de escaparate y estimaciones, no tarifas de mercado). Coste directo: limpieza, aseos, gasoil del grupo, vigilancia y música (SGAE/AGEDI).
A68: Empresa | B68: 2300 | C68: 42 | D68: 350
A69: Celebración privada | B69: 1600 | C69: 50 | D69: 300
A70: Celebración pequeña | B70: 1050 | C70: 33 | D70: 150
A72: TEMPORADA → AJUSTE DE TARIFA Y MÍNIMO DE INVITADOS | B72: Ajuste (+ suplemento / − descuento) | C72: Mínimo de invitados
A73: Alta | B73: 0.2 | C73: 80 | D73: Ejemplo del kit. La temporada alta cobra suplemento y la baja descuenta; la tarifa de las tipologías es la de un sábado de temporada media.
A74: Media | B74: 0 | C74: 60
A75: Baja | B75: -0.2 | C75: 40
A77: TIPO DE DÍA → AJUSTE DE TARIFA | B77: Ajuste (+ suplemento / − descuento)
A78: Sábado | B78: 0 | C78: Ejemplo del kit: las fichas de fincas publican descuentos de hasta el 30 % en viernes, domingo y de noviembre a marzo. Los ajustes se multiplican entre sí.
A79: Viernes o domingo | B79: -0.2
A80: Entre semana | B80: -0.3
A82: MES → TEMPORADA | B82: Temporada
A83: Enero | B83: Baja | C83: Mayo-octubre concentra el 63,7 % de los matrimonios y septiembre y junio son los picos (INE, 2024). Ajusta los meses a tu zona.
A84: Febrero | B84: Baja
A85: Marzo | B85: Baja
A86: Abril | B86: Media
A87: Mayo | B87: Alta
A88: Junio | B88: Alta
A89: Julio | B89: Media
A90: Agosto | B90: Media
A91: Septiembre | B91: Alta
A92: Octubre | B92: Alta
A93: Noviembre | B93: Baja
A94: Diciembre | B94: Baja
A96: DÍA DE LA SEMANA → TIPO DE DÍA | B96: Tipo de día
... A105: SERVICIOS EXTRA DE LA FINCA (precio sin IVA) | B105: Precio
A106: Ceremonia civil o simbólica en la finca (por ceremonia) | B106: 450 | C106: Precios de EJEMPLO del kit: pon los de tu finca. El alojamiento sólo si la finca tiene habitaciones.
A107: Hora extra de uso del espacio (por hora) | B107: 300
A108: Montaje premium: decoración, mobiliario y luces (por montaje) | B108: 600
A109: Alojamiento, si la finca lo tiene (por habitación y noche) | B109: 150
A111: POLÍTICA POR CLIENTE | B111: Particular | C111: Empresa
A112: Cobro 1: reserva de la fecha (% del total) | B112: 0.25 | C112: 0.3 | D112: Al firmar. Es la señal: tiene que ser proporcionada al coste de bloquear la fecha (art. 85.6 del TRLGDCU).
A113: Cobro 2: segundo pago (% del total) | B113: 0.35 | C113: 0.3 | D113: Pago intermedio, en la fecha de la fila siguiente.
A114: Cobro 3: liquidación antes del evento (% del total) | B114: 0.4 | C114: 0.4 | D114: El resto, antes del evento. Emite factura de cada pago, también de la reserva.
A115: Segundo pago: días antes del evento | B115: 180 | C115: 60 | D115: Particular, unos seis meses antes; empresa, dos meses. Si firman con menos antelación, se cobran juntos.
A116: Liquidación: días antes del evento | B116: 30 | C116: 15 | D116: Particular, 30 días antes; empresa, 15.
A117: Cancelación tramo 1: lo que retienes (% del total) | B117: 0.1 | C117: 0.05 | D117: Tramo más lejano del evento. Nunca más de lo cobrado en la reserva.
...

Sheet Ejemplos
A1: 3 PRESUPUESTOS DE EJEMPLO — con las mismas fórmulas de la hoja «Calculadora»
A2: Estimaciones del kit para ilustrar el cálculo, no precios de mercado: cambia los datos en «Calculadora» para presupuestar tus eventos. Las tablas (tarifas, temporadas, días, extras, cobros y cancelación) están al final de esa hoja y también mueven estos ejemplos.
A4: DATOS DEL EVENTO | B4: Boda de sábado en temporada alta | C4: Boda de viernes en temporada media | D4: Jornada de empresa entre semana
A5: Cliente | B5: Particular | C5: Particular | D5: Empresa
A6: Tipología del evento | B6: Boda | C6: Boda | D6: Empresa
A7: Fecha del evento | B7: 46557 | C7: 46584 | D7: 46498
A8: Invitados previstos | B8: 110 | C8: 90 | D8: 50
A9: Ceremonias en la finca (nº) | B9: 1 | C9: 1 | D9: 0
A10: Horas extra de uso del espacio (nº) | B10: 2 | C10: 0 | D10: 1
A11: Montajes premium (nº) | B11: 1 | C11: 0 | D11: 0
A12: Alojamiento: habitaciones-noche (nº) | B12: 0 | C12: 12 | D12: 0
A13: Horas de personal de la finca en el evento (coordinación y auxiliares) | B13: 16 | C13: 14 | D13: 10
A14: Coste bruto por hora del personal | B14: 13 | C14: 13 | D14: 13
A15: Seguridad Social a cargo de la empresa | B15: 0.33 | C15: 0.33 | D15: 0.33
A16: Coste directo de los servicios extra (% sobre su precio) | B16: 0.4 | C16: 0.4 | D16: 0.4
A17: Redondeo del precio del espacio (múltiplo, en euros) | B17: 50 | C17: 50 | D17: 50
A18: Canon del catering exclusivo (% de lo que factura el catering) | B18: 0.12 | C18: 0.12 | D18: 0.12
... A20: IVA del menú del catering (solo orientativo) | B20: 0.1 | C20: 0.1 | D20: 0.1
A22: RESULTADO | B22: Boda de sábado en temporada alta | C22: Boda de viernes en temporada media | D22: Jornada de empresa entre semana
A23: Temporada de la fecha (de la tabla de meses) | B23: =INDEX('Calculadora'!$B$83:$B$94,MONTH($B$7)) -> Alta | C23: =INDEX('Calculadora'!$B$83:$B$94,MONTH($C$7)) -> Media | D23: =INDEX('Calculadora'!$B$83:$B$94,MONTH($D$7)) -> Media
A24: Tipo de día (de la tabla de días de la semana) | B24: =INDEX('Calculadora'!$B$97:$B$103,WEEKDAY($B$7)) -> Sábado | C24: =INDEX('Calculadora'!$B$97:$B$103,WEEKDAY($C$7)) -> Viernes o domingo | D24: =INDEX('Calculadora'!$B$97:$B$103,WEEKDAY($D$7)) -> Entre semana
A25: Ajuste de temporada (suplemento + / descuento −) | B25: =INDEX('Calculadora'!$B$73:$B$75,MATCH($B$23,'Calculadora'!$A$73:$A$75,0)) -> 0.2 | C25: =INDEX('Calculadora'!$B$73:$B$75,MATCH($C$23,'Calculadora'!$A$73:$A$75,0)) -> 0 | D25: =INDEX('Calculadora'!$B$73:$B$75,MATCH($D$23,'Calculadora'!$A$73:$A$75,0)) -> 0
A26: Ajuste de día (suplemento + / descuento −) | B26: =INDEX('Calculadora'!$B$78:$B$80,MATCH($B$24,'Calculadora'!$A$78:$A$80,0)) -> 0 | C26: =INDEX('Calculadora'!$B$78:$B$80,MATCH($C$24,'Calculadora'!$A$78:$A$80,0)) -> -0.2 | D26: =INDEX('Calculadora'!$B$78:$B$80,MATCH($D$24,'Calculadora'!$A$78:$A$80,0)) -> -0.3
A27: Tarifa del espacio de la tipología (sábado, temporada media) | B27: =INDEX('Calculadora'!$B$67:$B$70,MATCH($B$6,'Calculadora'!$A$67:$A$70,0)) -> 3600 | C27: =INDEX('Calculadora'!$B$67:$B$70,MATCH($C$6,'Calculadora'!$A$67:$A$70,0)) -> 3600 | D27: =INDEX('Calculadora'!$B$67:$B$70,MATCH($D$6,'Calculadora'!$A$67:$A$70,0)) -> 2300
A28: ALQUILER DEL ESPACIO SIN IVA | B28: =ROUND($B$27*(1+$B$25)*(1+$B$26)/$B$17,0)*$B$17 -> 4300 | C28: =ROUND($C$27*(1+$C$25)*(1+$C$26)/$C$17,0)*$C$17 -> 2900 | D28: =ROUND($D$27*(1+$D$25)*(1+$D$26)/$D$17,0)*$D$17 -> 1600
A29: Mínimo de invitados de la temporada | B29: =INDEX('Calculadora'!$C$73:$C$75,MATCH($B$23,'Calculadora'!$A$73:$A$75,0)) -> 80 | C29: =INDEX('Calculadora'!$C$73:$C$75,MATCH($C$23,'Calculadora'!$A$73:$A$75,0)) -> 60 | D29: =INDEX('Calculadora'!$C$73:$C$75,MATCH($D$23,'Calculadora'!$A$73:$A$75,0)) -> 60
A30: Invitados garantizados | B30: =MAX($B$8,$B$29) -> 110 | C30: =MAX($C$8,$C$29) -> 90 | D30: =MAX($D$8,$D$29) -> 60
A31: Aviso del mínimo | B31: =IF($B$8<$B$29,"Por debajo del mínimo: se garantiza el mínimo de la temporada","Cumple el mínimo") -> Cumple el mínimo | C31: =IF($C$8<$C$29,"Por debajo del mínimo: se garantiza el mínimo de la temporada","Cumple el mínimo") -> Cumple el mínimo | D31: =IF($D$8<$D$29,"Por debajo del mínimo: se garantiza el mínimo de la temporada","Cumple el mínimo") -> Por debajo del mínimo: se garantiza el mínimo de la temporada
A32: Ceremonias | B32: =$B$9*'Calculadora'!$B$106 -> 450 | C32: =$C$9*'Calculadora'!$B$106 -> 450 | D32: =$D$9*'Calculadora'!$B$106 -> 0
A33: Horas extra | B33: =$B$10*'Calculadora'!$B$107 -> 600 | C33: =$C$10*'Calculadora'!$B$107 -> 0 | D33: =$D$10*'Calculadora'!$B$107 -> 300
A34: Montajes premium | B34: =$B$11*'Calculadora'!$B$108 -> 600 | C34: =$C$11*'Calculadora'!$B$108 -> 0 | D34: =$D$11*'Calculadora'!$B$108 -> 0
A35: Alojamiento | B35: =$B$12*'Calculadora'!$B$109 -> 0 | C35: =$C$12*'Calculadora'!$B$109 -> 1800 | D35: =$D$12*'Calculadora'!$B$109 -> 0
A36: Servicios extra sin IVA | B36: =$B$32+$B$33+$B$34+$B$35 -> 1650 | C36: =$C$32+$C$33+$C$34+$C$35 -> 2250 | D36: =$D$32+$D$33+$D$34+$D$35 -> 300
A37: Base imponible (espacio + servicios) | B37: =$B$28+$B$36 -> 5950 | C37: =$C$28+$C$36 -> 5150 | D37: =$D$28+$D$36 -> 1900
A38: IVA de la finca | B38: =$B$37*$B$19 -> 1249.5 | C38: =$C$37*$C$19 -> 1081.5 | D38: =$D$37*$D$19 -> 399
A39: TOTAL DE LA FINCA (con IVA) | B39: =$B$37+$B$38 -> 7199.5 | C39: =$C$37+$C$38 -> 6231.5 | D39: =$D$37+$D$38 -> 2299
A40: Importe que presupuestas (Particular: con IVA · Empresa: más IVA) | B40: =IF($B$5="Particular",$B$39,$B$37) -> 7199.5 | C40: =IF($C$5="Particular",$C$39,$C$37) -> 6231.5 | D40: =IF($D$5="Particular",$D$39,$D$37) -> 1900
A41: Precio del espacio y servicios por invitado garantizado (sin IVA) | B41: =$B$37/$B$30 -> 54.090909 | C41: =$C$37/$C$30 -> 57.222222 | D41: =$D$37/$D$30 -> 31.666667
A42: Importe del cobro 1: reserva | B42: =$B$39*INDEX('Calculadora'!$B$112:$C$112,MATCH($B$5,'Calculadora'!$B$111:$C$111,0)) -> 1799.875 | C42: =$C$39*INDEX('Calculadora'!$B$112:$C$112,MATCH($C$5,'Calculadora'!$B$111:$C$111,0)) -> 1557.875 | D42: =$D$39*INDEX('Calculadora'!$B$112:$C$112,MATCH($D$5,'Calculadora'!$B$111:$C$111,0)) -> 689.7
A43: Importe del cobro 2: segundo pago | B43: =$B$39*INDEX('Calculadora'!$B$113:$C$113,MATCH($B$5,'Calculadora'!$B$111:$C$111,0)) -> 2519.825 | C43: =$C$39*INDEX('Calculadora'!$B$113:$C$113,MATCH($C$5,'Calculadora'!$B$111:$C$111,0)) -> 2181.025 | D43: =$D$39*INDEX('Calculadora'!$B$113:$C$113,MATCH($D$5,'Calculadora'!$B$111:$C$111,0)) -> 689.7
A44: Fecha límite del segundo pago | B44: =$B$7-INDEX('Calculadora'!$B$115:$C$115,MATCH($B$5,'Calculadora'!$B$111:$C$111,0)) -> 46377 | C44: =$C$7-INDEX('Calculadora'!$B$115:$C$115,MATCH($C$5,'Calculadora'!$B$111:$C$111,0)) -> 46404 | D44: =$D$7-INDEX('Calculadora'!$B$115:$C$115,MATCH($D$5,'Calculadora'!$B$111:$C$111,0)) -> 46438
A45: Importe del cobro 3: liquidación | B45: =$B$39*INDEX('Calculadora'!$B$114:$C$114,MATCH($B$5,'Calculadora'!$B$111:$C$111,0)) -> 2879.8 | C45: =$C$39*INDEX('Calculadora'!$B$114:$C$114,MATCH($C$5,'Calculadora'!$B$111:$C$111,0)) -> 2492.6 | D45: =$D$39*INDEX('Calculadora'!$B$114:$C$114,MATCH($D$5,'Calculadora'!$B$111:$C$111,0)) -> 919.6
A46: Fecha límite de la liquidación | B46: =$B$7-INDEX('Calculadora'!$B$116:$C$116,MATCH($B$5,'Calculadora'!$B$111:$C$111,0)) -> 46527 | C46: =$C$7-INDEX('Calculadora'!$B$116:$C$116,MATCH($C$5,'Calculadora'!$B$111:$C$111,0)) -> 46554 | D46: =$D$7-INDEX('Calculadora'!$B$116:$C$116,MATCH($D$5,'Calculadora'!$B$111:$C$111,0)) -> 46483
A47: Importe del menú del catering sin IVA (estimado, invitados garantizados) | B47: =INDEX('Calculadora'!$C$67:$C$70,MATCH($B$6,'Calculadora'!$A$67:$A$70,0))*$B$30 -> 12100 | C47: =INDEX('Calculadora'!$C$67:$C$70,MATCH($C$6,'Calculadora'!$A$67:$A$70,0))*$C$30 -> 9900 | D47: =INDEX('Calculadora'!$C$67:$C$70,MATCH($D$6,'Calculadora'!$A$67:$A$70,0))*$D$30 -> 2520
A48: CANON ESTIMADO DEL CATERING sin IVA (informativo) | B48: =$B$47*$B$18 -> 1452 | C48: =$C$47*$C$18 -> 1188 | D48: =$D$47*$D$18 -> 302.4
A49: Canon estimado con IVA | B49: =$B$48*(1+$B$19) -> 1756.92 | C49: =$C$48*(1+$C$19) -> 1437.48 | D49: =$D$48*(1+$D$19) -> 365.904
A50: Menú del catering con IVA (orientativo, lo cobra el catering) | B50: =$B$47*(1+$B$20) -> 13310 | C50: =$C$47*(1+$C$20) -> 10890 | D50: =$D$47*(1+$D$20) -> 2772
A51: Importe orientativo completo para el cliente (finca con IVA + menú) | B51: =$B$39+$B$50 -> 20509.5 | C51: =$C$39+$C$50 -> 17121.5 | D51: =$D$39+$D$50 -> 5071
A52: Coste directo del evento: limpieza, aseos, gasoil, vigilancia y música | B52: =INDEX('Calculadora'!$D$67:$D$70,MATCH($B$6,'Calculadora'!$A$67:$A$70,0)) -> 650 | C52: =INDEX('Calculadora'!$D$67:$D$70,MATCH($C$6,'Calculadora'!$A$67:$A$70,0)) -> 650 | D52: =INDEX('Calculadora'!$D$67:$D$70,MATCH($D$6,'Calculadora'!$A$67:$A$70,0)) -> 350
A53: Coste de personal de la finca (salario + Seguridad Social) | B53: =$B$13*$B$14*(1+$B$15) -> 276.64 | C53: =$C$13*$C$14*(1+$C$15) -> 242.06 | D53: =$D$13*$D$14*(1+$D$15) -> 172.9
A54: Coste directo de los servicios extra | B54: =$B$36*$B$16 -> 660 | C54: =$C$36*$C$16 -> 900 | D54: =$D$36*$D$16 -> 120
A55: Coste directo total del evento | B55: =$B$52+$B$53+$B$54 -> 1586.64 | C55: =$C$52+$C$53+$C$54 -> 1792.06 | D55: =$D$52+$D$53+$D$54 -> 642.9
A56: Ingresos de la finca por el evento (sin IVA, con canon) | B56: =$B$37+$B$48 -> 7402 | C56: =$C$37+$C$48 -> 6338 | D56: =$D$37+$D$48 -> 2202.4
A57: Margen del evento para la finca (euros) | B57: =$B$56-$B$55 -> 5815.36 | C57: =$C$56-$C$55 -> 4545.94 | D57: =$D$56-$D$55 -> 1559.5
A58: Margen del evento (calculado) | B58: =IF($B$56=0,0,$B$57/$B$56) -> 0.78564712 | C58: =IF($C$56=0,0,$C$57/$C$56) -> 0.7172515 | D58: =IF($D$56=0,0,$D$57/$D$56) -> 0.70809117
A59: Margen del evento sin el canon (euros) | B59: =$B$37-$B$55 -> 4363.36 | C59: =$C$37-$C$55 -> 3357.94 | D59: =$D$37-$D$55 -> 1257.1
A60: Importe retenido si cancela: tramo 1 | B60: =$B$39*INDEX('Calculadora'!$B$117:$C$117,MATCH($B$5,'Calculadora'!$B$111:$C$111,0)) -> 719.95 | C60: =$C$39*INDEX('Calculadora'!$B$117:$C$117,MATCH($C$5,'Calculadora'!$B$111:$C$111,0)) -> 623.15 | D60: =$D$39*INDEX('Calculadora'!$B$117:$C$117,MATCH($D$5,'Calculadora'!$B$111:$C$111,0)) -> 114.95
A61: Importe retenido si cancela: tramo 2 | B61: =$B$39*INDEX('Calculadora'!$B$118:$C$118,MATCH($B$5,'Calculadora'!$B$111:$C$111,0)) -> 1799.875 | C61: =$C$39*INDEX('Calculadora'!$B$118:$C$118,MATCH($C$5,'Calculadora'!$B$111:$C$111,0)) -> 1557.875 | D61: =$D$39*INDEX('Calculadora'!$B$118:$C$118,MATCH($D$5,'Calculadora'!$B$111:$C$111,0)) -> 344.85
A62: Importe retenido si cancela: tramo 3 | B62: =$B$39*INDEX('Calculadora'!$B$119:$C$119,MATCH($B$5,'Calculadora'!$B$111:$C$111,0)) -> 3599.75 | C62: =$C$39*INDEX('Calculadora'!$B$119:$C$119,MATCH($C$5,'Calculadora'!$B$111:$C$111,0)) -> 3115.75 | D62: =$D$39*INDEX('Calculadora'!$B$119:$C$119,MATCH($D$5,'Calculadora'!$B$111:$C$111,0)) -> 804.65
A63: Importe retenido si cancela: tramo 4 | B63: =$B$39*INDEX('Calculadora'!$B$120:$C$120,MATCH($B$5,'Calculadora'!$B$111:$C$111,0)) -> 5399.625 | C63: =$C$39*INDEX('Calculadora'!$B$120:$C$120,MATCH($C$5,'Calculadora'!$B$111:$C$111,0)) -> 4673.625 | D63: =$D$39*INDEX('Calculadora'!$B$120:$C$120,MATCH($D$5,'Calculadora'!$B$111:$C$111,0)) -> 1379.4
A64: Importe retenido si cancela: tramo 5 | B64: =$B$39*INDEX('Calculadora'!$B$121:$C$121,MATCH($B$5,'Calculadora'!$B$111:$C$111,0)) -> 7199.5 | C64: =$C$39*INDEX('Calculadora'!$B$121:$C$121,MATCH($C$5,'Calculadora'!$B$111:$C$111,0)) -> 6231.5 | D64: =$D$39*INDEX('Calculadora'!$B$121:$C$121,MATCH($D$5,'Calculadora'!$B$111:$C$111,0)) -> 2299
A66: QUÉ ENSEÑA CADA EJEMPLO
A67: Boda de sábado en temporada alta | B67: Particular, 110 invitados, un sábado de junio: temporada alta (+20 %) y día de referencia (sábado, sin ajuste). Lleva ceremonia en la finca, dos horas extra y montaje premium. El precio con IVA es el que ve el particular. El canon es lo que el catering exclusivo pagaría a la finca con un 12 % (supuesto): no lo paga el novio. Cobro en tres pagos: reserva, segundo pago seis meses antes y liquidación 30 días antes.
A68: Boda de viernes en temporada media | B68: Particular, 90 invitados, un viernes de julio: temporada media (sin ajuste) y viernes (−20 %). Lleva ceremonia y 12 habitaciones-noche de alojamiento (6 habitaciones, 2 noches). Mismo calendario de cobros y mismos tramos que la anterior: cambia solo la tarifa del espacio.
A69: Jornada de empresa entre semana | B69: Empresa, 50 invitados, un miércoles de abril: temporada media y día entre semana (−30 %). Los 50 invitados quedan por debajo del mínimo de la temporada (60): se garantizan 60 y el canon se calcula sobre ellos. Se presupuesta «más IVA» y se cobra con otro calendario (30 % al reservar, 30 % a dos meses y 40 % a 15 días) y otros tramos de cancelación.

Sheet Instrucciones
A1: INSTRUCCIONES DE USO — Calculadora de presupuesto del espacio para bodas y eventos en finca
A2: Convierte tu tarifa de alquiler en un presupuesto completo para un evento concreto: temporada y día de la fecha, mínimo de invitados, servicios extra, IVA, total, calendario de cobros, canon estimado del catering, margen del evento y lo que retienes si el cliente cancela. Sólo se escribe en las celdas VERDES; el margen se calcula.
A3: 1. Elige el cliente (Particular o Empresa), la tipología del evento, la fecha completa y los invitados previstos.
A4: 2. La fecha fija la temporada (tabla de meses) y el tipo de día (tabla de días de la semana). Cada una lleva un suplemento o un descuento visible en su tabla; los dos se multiplican con la tarifa de la tipología.
A5: 3. Cada temporada tiene un mínimo de invitados: se garantiza el mayor entre los previstos y el mínimo, y sobre esos invitados garantizados se estima el canon.
A6: 4. Escribe cuántos servicios extra llevas (ceremonia, horas extra, montaje premium, alojamiento). Sus precios están en la tabla «Servicios extra de la finca» y son de ejemplo: pon los tuyos.
A7: 5. Escribe las horas de personal de la finca, el coste bruto por hora, la Seguridad Social y el coste directo de los extras. El coste directo del evento (limpieza, aseos, gasoil, vigilancia y música) está en la tabla de tipologías.
A8: IVA, CANON Y MENÚ
A10: La finca factura el espacio y los servicios con precio propio al 21 %. El menú y la bebida los factura el catering exclusivo: comida y bebida para consumir en el acto van al 10 % (Ley 37/1992, art. 91.Uno.2.2.º), y no son ingreso de la finca. La calculadora los muestra sólo como orientación para el cliente. Si vendes un paquete que mezcla ambos, consúltalo con tu asesoría.
A11: El canon es lo que el catering exclusivo paga a la finca por tener la exclusiva. Aquí es un supuesto editable (12 % de lo que factura el catering): no es un dato de mercado, negócialo. Lo paga el catering, no el cliente; la finca lo factura con IVA.
A12: El margen del evento es una contribución: no descuenta la renta, el personal fijo, los suministros, los seguros ni la estructura. Eso está en el plan financiero.
A13: COBRO Y CANCELACIÓN
... A25: Versión 1.0 · noviembre 2026 · aichef.pro/plan-negocio-finca-eventos-bodas · info@aichef.pro
