Workbook

Sheet 0. Supuestos
A1: SUPUESTOS — aquí se teclean las TASAS y los DRIVERS del modelo
A2: Cambia las celdas VERDES: el resto del libro se recalcula solo. Las partidas de gasto se teclean en su hoja (también en verde) y no se repiten aquí.
A3: ACTIVIDAD
A4: Invitados por evento (media del año 1) | B4: 82 | C4: Invitados de media por evento en el año 1. Sale de la mezcla de la tabla de referencias de la hoja de Instrucciones: bodas de 120, eventos de empresa de 80, celebraciones privadas de 70 y eventos pequeños de 40. Es una media: el aforo de la finca está más abajo
A5: Precio medio por invitado SIN IVA (€) | B5: 37 | C5: SIN IVA, por invitado: lo que factura la FINCA, no lo que pagan los novios por la boda entera. Suma el espacio y los servicios (ceremonia, montaje, coordinación, limpieza y aparcamiento) y el canon que te paga el catering por cada invitado. Media de la mezcla: 47 € la boda, 34 € el evento de empresa, 29 € la celebración privada y 30 € el evento pequeño. El precio con IVA (21 %) está en la fila de abajo
A6: Eventos al año | B6: 120 | C6: Eventos celebrados en el año: 30 bodas, 35 de empresa (jornadas, comidas, Navidad), 40 celebraciones privadas (comuniones, bautizos, cumpleaños) y 15 pequeños (preboda, brunch, bodas íntimas). Es el MISMO dato para la cuenta de resultados, el punto de equilibrio, los escenarios y las horas de personal
A7: Crecimiento de volumen del año 2 | B7: 0.08 | C7: Más actividad el segundo año: bodas que llegan por recomendación, empresas que repiten y planners que ya te conocen. El libro lo aplica a los invitados por evento con los mismos eventos; en euros es lo mismo que un 8 % más de eventos del mismo tamaño (unos 130). El personal no sube con este porcentaje: crece con las incorporaciones de la hoja Personal
A8: Crecimiento de volumen del año 3 | B8: 0.05 | C8: Sobre el año 2 (unos 136 eventos equivalentes). Conservador: el techo lo ponen los sábados de temporada y el aforo de la finca
A9: PVP equivalente con IVA (calculado) | B9: =IFERROR(IF($B$5="","",$B$5*(1+SUMPRODUCT('PyG 3 Años'!$E$10:$E$11,'PyG 3 Años'!$G$10:$G$11))),"") -> 44.77 | C9: =IFERROR("Precio por invitado sin IVA más el IVA medio ponderado de tus líneas de venta: "&TEXT(SUMPRODUCT('PyG 3 Años'!$E$10:$E$11,'PyG 3 Años'!$G$10:$G$11)*100,"0")&" %. La finca factura el espacio, los servicios y el canon al 21 %, el tipo general; el menú y la barra los factura el catering a los novios, al 10 % (art. 91.Uno.2.2.º de la Ley 37/1992), y no entran en este libro. Aquí va redondeado. "&"Compáralo con el rango del sector, que va con IVA.","") -> Precio por invitado sin IVA más el IVA medio ponderado de tus líneas de venta: 21 %. La finca factura el espacio, los servicios y el canon al 21 %, el tipo general; el menú y la barra los factura el catering a los novios, al 10 % (art. 91.Uno.2.2.º de la Ley 37/1992), y no entran en este libro. Aquí va redondeado. Compáralo con el rango del sector, que va con IVA.
A10: MEZCLA DE VENTAS Y COSTE DIRECTO
A11: Ventas de ESPACIO Y SERVICIOS sobre el total | B11: 0.78 | C11: Peso del ESPACIO Y LOS SERVICIOS sobre el total de ventas. Es un INPUT: cámbialo aquí y el P&L, la tesorería y el IVA repercutido se recalculan solos
A12: Ventas del CANON DEL CATERING sobre el total | B12: =IFERROR(IF(COUNT(B11)=0,"",1-B11),"") -> 0.22 | C12: Se calcula como el resto: espacio y servicios + canon = 100 %
A13: Coste directo del evento sobre las ventas de ESPACIO Y SERVICIOS | B13: 0.163 | C13: Coste directo del evento sobre las ventas de espacio y servicios: limpieza tras el evento, reposición de aseos y consumibles, gasoil del grupo electrógeno, vigilancia y aparcamiento, y la tarifa de SGAE y AGEDI-AIE de cada evento. Unos 650 € por boda, 350 € por evento de empresa, 300 € por celebración privada y 150 € por evento pequeño: 46.000 € al año
A14: Coste del canon sobre las ventas del CANON | B14: 0 | C14: A CERO: el canon no tiene coste para la finca. La comida y la bebida las compra el catering, que es quien las vende a los novios
A15: Consumibles sobre ventas | B15: 0.02 | C15: Velas, flores base, papel y productos de los aseos, y los pequeños consumibles de cada montaje
A16: Ventas que llegan por wedding planners y agencias sobre el total | B16: 0.2 | C16: Parte de las ventas que llega por un wedding planner o una agencia de eventos, que cobra una comisión. No cambia el IVA: todo lo que factura la finca va al 21 %
A17: Comisión de los wedding planners y agencias | B17: 0.125 | C17: Comisión media sobre lo que vende ese canal: el punto medio de un 10-15 %. Si todas las reservas te llegan directas, pon 0
A18: Comisión de los medios de pago | B18: 0.003 | C18: Casi todo se cobra por transferencia (señales, pagos de los novios y facturas de empresa); el datáfono queda para los extras del día
A19: PERSONAL
A20: Seguridad Social a cargo de la empresa | B20: 0.33 | C20: Contingencias comunes + AT/EP + desempleo + FOGASA + FP; ajusta a tu convenio y bonificaciones
A21: Número de pagas anuales | B21: 14 | C21: Salario bruto anual = bruto mensual × pagas
A22: SMI anual de referencia (€) | B22: 17094 | C22: SMI 2026: 17.094 € al año (1.221 €/mes en 14 pagas), suelo legal por jornada completa. Comprueba el importe vigente si presentas el plan en otro ejercicio
A23: FINCA Y FIJOS
A24: Renta mensual de la finca (€) | B24: 3500 | C24: Renta de mercado de una finca con edificaciones existentes (salón, aseos y office) arrendada a una SL, con contrato de quince años o más. Lleva IVA al 21 %. Si la finca es de tu familia, la renta tiene que ser la de mercado igual. El peso sobre las ventas lo calcula el libro en la fila «Renta de la finca / Ventas» del P&L
A25: Fianza del arrendamiento (meses) | B25: 2 | C25: Dos meses de renta como fianza, lo habitual en un arrendamiento de uso distinto del de vivienda; los avales o garantías adicionales se negocian aparte. Compruébalo con tu abogado antes de firmar
A26: Suministros mensuales (luz, agua, gasoil y teléfono) (€) | B26: 1600 | C26: Luz con potencia para el salón y el exterior, agua de riego, gasoil del grupo electrógeno fuera de los eventos y teléfono. Pide al propietario el histórico de consumos
A27: Seguros (€/año) | B27: 5500 | C27: Responsabilidad civil de la actividad con el capital que fije tu comunidad por aforo (en Andalucía, 526.000 € para 101-300 personas), daños a las mejoras de la finca, pérdida de beneficio y accidentes. Exige además al catering su propio seguro de responsabilidad civil e intoxicación
A28: Varios e imprevistos sobre ventas | B28: 0.02 | C28: Roturas, imprevistos de cada montaje y desplazamientos comerciales (ferias y visitas a planners)
A29: FINANCIACIÓN
A30: Recursos propios aportados (€) | B30: 100000 | C30: Aportación de los socios. Un banco pide entre el 25 y el 30 % de la necesidad de caja con dinero propio
A31: Préstamo bancario solicitado (€) | B31: 263000 | C31: Principal solicitado. La hoja de Financiación compara lo que aportas con la necesidad de caja de la hoja de inversión y te dice si sobra o falta: ajústalo con ese dato. La finca no es tuya, así que no hay garantía inmobiliaria: pregunta por avales y por líneas públicas
A32: Tipo de interés nominal anual | B32: 0.065 | C32: Tipo nominal anual de un préstamo de empresa sin garantía inmobiliaria. Pide oferta a dos entidades y a una línea ICO antes de fijarlo
A33: Plazo del préstamo (años) | B33: 8 | C33: Años totales, carencia incluida. Con seis años la cuota no cabe en un negocio con tanta estructura fija
A34: Carencia de principal (años) | B34: 1 | C34: El primer año, sólo intereses: es el año de arranque y la caja va más justa. Desde el segundo año se devuelve el principal: mira la holgura de caja de ese año en el Punto de Equilibrio
A35: Fondo de maniobra (meses de costes fijos) | B35: 3 | C35: Tres meses de costes fijos: son el colchón de los primeros meses, recién pagada la inversión y antes de las bodas de mayo y junio. En un año normal, de noviembre a febrero entra alrededor del 23 % de la venta con la renta y la plantilla planas: ese invierno se pasa con la caja de la temporada
A36: FISCAL
A37: Impuesto de Sociedades, nueva creación | B37: 0.15 | C37: Art. 29.1 LIS: el PRIMER ejercicio con base imponible positiva y el SIGUIENTE. El libro lo aproxima contando los dos primeros ejercicios con base positiva: coincide con la ley salvo que entre ellos haya un ejercicio en pérdidas
A38: Impuesto de Sociedades, tipo general | B38: 0.25 | C38: A partir del tercer ejercicio con base positiva. Es el tipo general del art. 29.1 LIS: si tu cifra de negocios queda por debajo de 1 M € (microempresa) o de 10 M € (reducida dimensión), desde 2025 hay tipos más bajos que se implantan de forma gradual; confirma el de tu ejercicio con tu asesor y cámbialo aquí
A39: IVA repercutido de restauración | B39: 0.1 | C39: No se usa en este plan: la finca no vende comida ni bebida. Es el tipo del menú del catering
A40: IVA repercutido/soportado general | B40: 0.21 | C40: Tipo general. En este plan es el de todo lo que factura la finca (espacio, servicios y canon) y el de casi todo lo que compra; suministros, equipamiento y servicios tienen su tipo en la celda de abajo. La finca no vende comida ni bebida: el menú y la barra los factura el catering, al 10 % (art. 91.Uno.2.2.º de la Ley 37/1992)
A41: IVA soportado en compras e inversión | B41: 0.21 | C41: Recuperable vía modelo 303, pero hay que adelantarlo
A42: Bases negativas de ejercicios anteriores (€) | B42: 0 | C42: Pérdidas pendientes de compensar al empezar (art. 26 LIS)
A43: AMORTIZACIÓN
A44: Vida útil de obra e instalaciones (años) | B44: 15 | C44: Obra en una finca ARRENDADA: se amortiza en el plazo del contrato si es menor que la vida útil del bien. Por eso el plan pide un arrendamiento de quince años o más; con un contrato más corto, la amortización anual sube. Confírmalo con tu asesoría
A45: Vida útil de maquinaria y mobiliario (años) | B45: 10 | C45: Carpa, grupo electrógeno, mobiliario y sonido: un 10 % anual, dentro del coeficiente máximo de la tabla del art. 12.1 de la Ley del Impuesto sobre Sociedades para el mobiliario. Confírmalo con tu asesoría
A47: CRECIMIENTO Y ACTUALIZACIÓN DE COSTES
A48: Subida anual de los costes fijos | B48: 0 | C48: A CERO: las tres columnas están en euros del año 1 (términos reales). Súbela si quieres proyectar en euros corrientes
A49: ARRANQUE Y AFORO
A51: Aforo de la finca (invitados sentados en el salón y la carpa) | B51: 300 | C51: DATO INFORMATIVO: no entra en ningún cálculo. Es el banquete más grande que caben sentado entre el salón y la carpa; el aforo legal lo fija tu licencia. Con 300 invitados la finca queda por debajo del plan de autoprotección estatal (Orden INT/1068/2026: 1.000 personas en edificio cerrado o carpa)
A52: Actividad del mes 1 sobre la de crucero | B52: 0.45 | C52: Una finca que acaba de abrir no factura el primer mes lo que factura al año: las bodas se reservan con 12-18 meses de antelación y la primera temporada sólo trae lo que se reservó, condicionado a la licencia, durante la tramitación y la obra. Con 100 % se elimina la rampa
A53: Meses hasta alcanzar el régimen de crucero | B53: 12 | C53: Doce meses hasta el ritmo de crucero: la primera temporada entera
A54: Meses de renta ANTES de abrir (obra y licencias) | B54: 1 | C54: Un mes de renta antes de abrir. La carencia de renta durante la obra y la licencia se negocia aparte en el arrendamiento: sin ella, súmale los meses que dure la tramitación (de 6 a 12 o más en suelo rústico)
A55: Imprevistos sobre las partidas de OBRA del bloque de la finca (%) | B55: 0.08 | C55: Colchón sobre la obra y las instalaciones de unas edificaciones que no son nuevas, que es donde aparecen las sorpresas (tejados, acometida eléctrica, saneamiento y agua). Un banco no financia una reforma sin él
A57: COBROS, PAGOS Y DESGLOSE DEL IVA
A58: Días medios de cobro | B58: 10 | C58: Media ponderada: los novios pagan la señal y el resto antes de la boda, y las empresas a 30-45 días de la factura. El libro no admite días negativos, así que las señales no se modelan: tu caja real será algo MEJOR que la de la hoja de Tesorería
A59: Días medios de pago a proveedor | B59: 30 | C59: Plazo de pago a proveedores de limpieza, mantenimiento y consumibles: lo que te financian. Es lo primero que se pierde si te retrasas en un pago
A60: Mes de la paga extra de verano | B60: 5 | C60: Mes de la TESORERÍA en el que sale la paga extra de verano: julio es el Mes 5, porque el Mes 1 del plan es marzo
A61: Mes de la paga extra de Navidad | B61: 10 | C61: Mes de la TESORERÍA en el que sale la paga extra de Navidad: diciembre es el Mes 10, porque el Mes 1 del plan es marzo
A62: Bebida ALCOHÓLICA vendida por la finca (no la vende: a cero) | B62: 0 | C62: A CERO: la finca no vende bebida. La barra es del catering, que la factura él; la segunda línea de ventas del P&L es el canon que te paga
A63: IVA de la bebida ALCOHÓLICA (la finca no la vende) | B63: 0.21 | C63: Esta celda no mueve nada en este plan: la finca no vende bebida (la vende el catering, que la factura él) y la línea del canon lleva su propio tipo, el 21 %, en el P&L
A64: UMBRALES Y SUELOS DE CONTROL
A65: DSCR mínimo aceptable | B65: 1 | C65: Por debajo de 1 el negocio no genera para pagar el préstamo. Ponlo en el covenant que te exija tu banco
A66: DSCR objetivo (verde) | B66: 1.25 | C66: Lo que suele pedir una entidad para dar el préstamo sin garantías adicionales
A67: Holgura mínima sobre el punto de equilibrio | B67: 0.15 | C67: Cuánto deben superar las ventas previstas a las del punto de equilibrio. La caída que aguantas antes de entrar en pérdidas es algo menor: con un 15 % de holgura, un 13 % de lo previsto
A68: Suelo salarial anual del convenio provincial (€) | B68: 0 | C68: El VI Acuerdo Laboral de ámbito Estatal para el sector de Hostelería (art. 4) nombra el catering, pero no el alquiler de espacios, y su lista no es exhaustiva: usa el convenio provincial de hostelería como referencia prudente y confírmalo con tu asesoría. Copia aquí el salario base del grupo más bajo de tu provincia. Con 0 el semáforo compara sólo contra el SMI

Sheet Inversión Inicial
A1: PLAN DE NEGOCIO: FINCA DE EVENTOS Y BODAS
A2: Inversión inicial estimada — finca arrendada con edificaciones existentes y catering exclusivo concesionado
A3: Ajusta las cifras a tu proyecto.
A5: Concepto | B5: Importe | C5: % s/inversión | D5: Notas | E5: ¿Lleva IVA?
A6: INVERSIÓN | B6: =IFERROR(IF(COUNT(B7:B28)=0,"",SUM(B7:B28)),"") -> 251780 | C6: =IFERROR(B6/$B$31,"") -> 0.80851935
A7: Proyecto técnico y dirección de obra | B7: 7000 | C7: =IFERROR(B7/$B$31,"") -> 0.022478495 | D7: Proyecto de adecuación y de la actividad, dirección de obra y certificado final. Es la base de la calificación o autorización urbanística y de la licencia | E7: Sí
A8: Licencias, tasas, calificación urbanística y prestación compensatoria o canon | B8: 10000 | C8: =IFERROR(B8/$B$31,"") -> 0.032112136 | D8: Lo que cobra la administración en suelo rústico, distinto en cada comunidad: en Andalucía, prestación compensatoria del 10 % de las obras sin maquinaria (LISTA, art. 22.5); en la C. Valenciana, canon del 2 % (TRLOTUP, art. 221). En Andalucía, sólo la prestación serían unos 13.000 € con la obra del caso: súbela si es tu comunidad. No lleva IVA. Ajusta esta partida a la tuya: compruébalo en tu ayuntamiento y en tu comunidad | E8: No
A9: Adecuación del salón: suelos, cerramientos, carpintería y pintura | B9: 30000 | C9: =IFERROR(B9/$B$31,"") -> 0.096336407 | D9: Sobre edificaciones EXISTENTES: en suelo rústico es lo que exigen Madrid y Cataluña y la vía rápida de la C. Valenciana. Pide dos presupuestos sobre el proyecto | E9: Sí
A10: Acústica y aislamiento del salón | B10: 9000 | C10: =IFERROR(B10/$B$31,"") -> 0.028900922 | D10: Para que el baile final pueda ir dentro y cumplir los 45 dBA de noche al exterior en zona residencial (RD 1367/2007, anexo III) | E10: Sí
A11: Carpa estructural o pérgola para ceremonia y cóctel | B11: 28000 | C11: =IFERROR(B11/$B$31,"") -> 0.08991398 | D11: Es el plan B de lluvia: inversión, no extra. Una carpa es una instalación desmontable: para el plan de autoprotección estatal tiene el mismo umbral que un edificio cerrado, 1.000 personas (Orden INT/1068/2026) | E11: Sí
A12: Aseos: dos bloques y uno adaptado | B12: 22000 | C12: =IFERROR(B12/$B$31,"") -> 0.070646698 | D12: Con un aseo adaptado e itinerario accesible: compruébalo con tu técnico sobre el Código Técnico. Incluye la conexión al saneamiento (fosa séptica o depuradora); si hay que hacerla nueva o ampliarla para el aforo, súbela | E12: Sí
A13: Instalación eléctrica: cuadro, alumbrado exterior y de emergencia | B13: 15000 | C13: =IFERROR(B13/$B$31,"") -> 0.048168203 | D13: Potencia para el salón, la carpa, el office y el exterior, con su boletín. Pregunta la potencia disponible ANTES de firmar: una acometida nueva en el campo tarda | E13: Sí
A14: Grupo electrógeno | B14: 10000 | C14: =IFERROR(B14/$B$31,"") -> 0.032112136 | D14: Respaldo si la red falla o no llega la potencia: un corte de luz en mitad de una boda no tiene arreglo | E14: Sí
A15: Climatización del salón | B15: 17000 | C15: =IFERROR(B15/$B$31,"") -> 0.05459063 | D15: Frío y calor para usar el salón todo el año, también en las bodas de agosto | E15: Sí
A16: Office del catering: cámara, fregaderos, mesas inox, agua y desagüe | B16: 16000 | C16: =IFERROR(B16/$B$31,"") -> 0.051379417 | D16: El espacio donde el catering emplata y friega. La cocina de producción la pone él: por eso el plan no lleva cocina. Lo inscribe en el registro sanitario quien lo usa; compruébalo en tu comunidad | E16: Sí
A17: Mobiliario de ceremonia y banquete: mesas, sillas y mantelería base | B17: 18000 | C17: =IFERROR(B17/$B$31,"") -> 0.057801844 | D17: Mesas redondas e imperiales, 300 sillas y mantelería base. La decoración especial la contratan los novios | E17: Sí
A18: Zona chill-out y decoración base | B18: 4000 | C18: =IFERROR(B18/$B$31,"") -> 0.012844854 | D18: Sofás, iluminación ambiental y elementos fijos de decoración | E18: Sí
... A25: Lanzamiento: feria nupcial, puertas abiertas y escaparate premium | B25: 6000 | C25: =IFERROR(B25/$B$31,"") -> 0.019267281 | D25: La primera feria de novios, la jornada de puertas abiertas con el catering y el escaparate de pago en un portal de bodas durante el primer año | E25: Sí
A26: Fianza del arrendamiento | B26: =IFERROR(IF('0. Supuestos'!$B$24="","",'0. Supuestos'!$B$24*'0. Supuestos'!$B$25),"") -> 7000 | C26: =IFERROR(B26/$B$31,"") -> 0.022478495 | D26: =IFERROR(""&TEXT('0. Supuestos'!$B$25,"0")&" meses de renta, al tipo de la hoja de Supuestos. Es un activo recuperable al cerrar: ni se amortiza ni lleva IVA","") -> 2 meses de renta, al tipo de la hoja de Supuestos. Es un activo recuperable al cerrar: ni se amortiza ni lleva IVA | E26: No
A27: Renta de la finca durante la obra | B27: =IFERROR(IF('0. Supuestos'!$B$24="","",'0. Supuestos'!$B$24*'0. Supuestos'!$B$54),"") -> 3500 | C27: =IFERROR(B27/$B$31,"") -> 0.011239247 | D27: =IFERROR("Renta "&IF('0. Supuestos'!$B$54=1,"del mes","de los "&TEXT('0. Supuestos'!$B$54,"0")&" meses")&" de obra y licencias. NO se solapa con el P&L, que arranca el día de la apertura: los doce meses del P&L son los doce de explotación","") -> Renta del mes de obra y licencias. NO se solapa con el P&L, que arranca el día de la apertura: los doce meses del P&L son los doce de explotación | E27: Sí
A28: Imprevistos de obra y acondicionamiento | B28: =IFERROR(IF(COUNT(B7,B9,B10,B12,B13,B15,B16,B20,B21,B22)=0,"",ROUND((B7+B9+B10+B12+B13+B15+B16+B20+B21+B22)*'0. Supuestos'!$B$55,0)),"") -> 11280 | C28: =IFERROR(B28/$B$31,"") -> 0.036222489 | D28: =IFERROR("Al "&TEXT('0. Supuestos'!$B$55,"0%")&" de las partidas de OBRA Y ACONDICIONAMIENTO de este bloque (Proyecto técnico y dirección de obra, Adecuación del salón: suelos, cerramientos, carpintería y pintura, Acústica y aislamiento del salón, Aseos: dos bloques y uno adaptado, "&"Instalación eléctrica: cuadro, alumbrado exterior y de emergencia, Climatización del salón, Office del catering: cámara, fregaderos, mesas inox, agua y desagüe, Aparcamiento y caminos: zahorra, señalización e iluminación, Jardinería, "&"paisajismo y riego inicial y Protección contra incendios, señalización de evacuación y accesibilidad), no del bloque entero: el resto de partidas del bloque quedan fuera. Un banco no financia una reforma sin colchón: el porcentaje está en "&"la hoja de Supuestos","") -> Al 8% de las partidas de OBRA Y ACONDICIONAMIENTO de este bloque (Proyecto técnico y dirección de obra, Adecuación del salón: suelos, cerramientos, carpintería y pintura, Acústica y aislamiento del salón, Aseos: dos bloques y uno adaptado, Instalación eléctrica: cuadro, alumbrado exterior y de emergencia, Climatización del salón, Office del catering: cámara, fregaderos, mesas inox, agua y desagüe, Aparcamiento y caminos: zahorra, señalización e iluminación, Jardinería, paisajismo y riego inicial y Protección contra incendios, señalización de evacuación y accesibilidad), no del bloque entero: el resto de partidas del bloque quedan fuera. Un banco no financia una reforma sin colchón: el porcentaje está en la hoja de Supuestos | E28: Sí
A29: FONDO DE MANIOBRA | B29: =IFERROR(IF(B30="","",B30),"") -> 59628.75 | C29: =IFERROR(B29/$B$31,"") -> 0.19148065
A30: Colchón operativo hasta alcanzar el equilibrio | B30: =IFERROR(IF('0. Supuestos'!$B$35*('PyG 3 Años'!$B$38-'PyG 3 Años'!$B$36)=0,"",'0. Supuestos'!$B$35*('PyG 3 Años'!$B$38-'PyG 3 Años'!$B$36)/12),"") -> 59628.75 | C30: =IFERROR(B30/$B$31,"") -> 0.19148065 | D30: =IFERROR("Cubre "&TEXT('0. Supuestos'!$B$35,"0")&IF('0. Supuestos'!$B$35=1," mes"," meses")&" de costes fijos DE CAJA del año 1 (los del P&L menos la amortización, que no se paga), que es el mínimo que exigen las Instrucciones de este libro","") -> Cubre 3 meses de costes fijos DE CAJA del año 1 (los del P&L menos la amortización, que no se paga), que es el mínimo que exigen las Instrucciones de este libro | E30: No
A31: INVERSIÓN TOTAL (suma de los bloques) | B31: =IFERROR(B6+B29,"") -> 311408.75 | D31: =IFERROR("Los porcentajes de la columna C se leen sobre esta cifra, que incluye el fondo de maniobra ("&TEXT(C29,"0%")&" del total). Para comparar el desglose con otro plan, usa la fila de CAPEX de abajo.","") -> Los porcentajes de la columna C se leen sobre esta cifra, que incluye el fondo de maniobra (19% del total). Para comparar el desglose con otro plan, usa la fila de CAPEX de abajo.
A32: CAPEX (inversión sin el fondo de maniobra) | B32: =IFERROR(B31-B29,"") -> 251780 | D32: Es lo que se compra: obra, equipamiento, lanzamiento y gastos de constitución. El colchón de caja no es inversión, es circulante
A33: IVA soportado sobre la inversión (recuperable) | B33: =IFERROR(IF(B31="","",SUMIF($E$7:$E$28,"Sí",$B$7:$B$28)*'0. Supuestos'!$B$41),"") -> 49093.8 | D33: =IFERROR("Al "&TEXT('0. Supuestos'!$B$41,"0%")&" sobre las partidas marcadas con «Sí» en la columna de IVA. Las tasas y licencias no están sujetas y los seguros están exentos (art. 20.Uno.16 LIVA). Las tasas y aranceles registrales no llevan IVA; los honorarios de notaría y gestoría sí "&"(21 %, deducible). Se recupera con el modelo 303, pero hay que adelantarlo","") -> Al 21% sobre las partidas marcadas con «Sí» en la columna de IVA. Las tasas y licencias no están sujetas y los seguros están exentos (art. 20.Uno.16 LIVA). Las tasas y aranceles registrales no llevan IVA; los honorarios de notaría y gestoría sí (21 %, deducible). Se recupera con el modelo 303, pero hay que adelantarlo
A34: NECESIDAD TOTAL DE CAJA AL ARRANQUE | B34: =IFERROR(B31+B33,"") -> 360502.55 | D34: Es la cifra que tiene que cubrir la hoja de Financiación
A35: BASES DE AMORTIZACIÓN (no suman a la inversión)
A36: Obra, instalaciones y acondicionamiento | B36: =IFERROR(IF(B7="","",B7+B9+B10+B12+B13+B15+B16+B20+B21+B22+B28),"") -> 152280 | D36: =IFERROR("Se amortiza en "&TEXT('0. Supuestos'!$B$44,"0")&" años","") -> Se amortiza en 15 años
A37: Maquinaria, mobiliario y equipos | B37: =IFERROR(IF(B11="","",B11+B14+B17+B18+B19),"") -> 66000 | D37: =IFERROR("Se amortiza en "&TEXT('0. Supuestos'!$B$45,"0")&" años","") -> Se amortiza en 10 años
A38: Amortización anual del inmovilizado | B38: =IFERROR(B36/MAX(1,'0. Supuestos'!$B$44)+B37/MAX(1,'0. Supuestos'!$B$45),"") -> 16752 | D38: =IFERROR("No se amortizan, por no ser inmovilizado, Licencias, tasas, calificación urbanística y prestación compensatoria o canon, Web, fotos, vídeo y marca, Constitución de la SL, Lanzamiento: feria nupcial, puertas abiertas y escaparate premium, "&"Fianza del arrendamiento, Renta de la finca durante la obra ni Colchón operativo hasta alcanzar el equilibrio. Suman "&TEXT(B31-B36-B37,"0")&" € de los "&TEXT(B31,"0")&" € de inversión.","") -> No se amortizan, por no ser inmovilizado, Licencias, tasas, calificación urbanística y prestación compensatoria o canon, Web, fotos, vídeo y marca, Constitución de la SL, Lanzamiento: feria nupcial, puertas abiertas y escaparate premium, Fianza del arrendamiento, Renta de la finca durante la obra ni Colchón operativo hasta alcanzar el equilibrio. Suman 93129 € de los 311409 € de inversión.

Sheet PyG 3 Años
A1: CUENTA DE RESULTADOS — 3 AÑOS
A2: Escenario realista — finca de eventos y bodas
A4: Concepto | B4: Año 1 | C4: Año 2 | D4: Año 3 | E4: % s/ventas (año 1) | F4: Notas | G4: Tipo de IVA de la línea (%)
A5: INGRESOS
A6: Invitados por evento (media) | B6: =IFERROR(IF('0. Supuestos'!$B$4="","",'0. Supuestos'!$B$4),"") -> 82 | C6: =IFERROR(B6*(1+'0. Supuestos'!$B$7),"") -> 88.56 | D6: =IFERROR(C6*(1+'0. Supuestos'!$B$8),"") -> 92.988 | F6: El crecimiento de los años 2 y 3 está en la hoja de Supuestos
A7: Precio medio por invitado sin IVA | B7: =IFERROR(IF('0. Supuestos'!$B$5="","",'0. Supuestos'!$B$5),"") -> 37 | C7: =IFERROR(IF(B7="","",B7),"") -> 37 | D7: =IFERROR(IF(C7="","",C7),"") -> 37 | F7: Constante en euros del año 1: una subida de precios es una decisión aparte
A8: Eventos al año | B8: =IFERROR(IF('0. Supuestos'!$B$6="","",'0. Supuestos'!$B$6),"") -> 120 | C8: =IFERROR(IF(B8="","",B8),"") -> 120 | D8: =IFERROR(IF(C8="","",C8),"") -> 120
A9: INGRESOS TOTALES (sin IVA) | B9: =IFERROR(IF(B6*B7*B8=0,"",B6*B7*B8),"") -> 364080 | C9: =IFERROR(IF(C6*C7*C8=0,"",C6*C7*C8),"") -> 393206.4 | D9: =IFERROR(IF(D6*D7*D8=0,"",D6*D7*D8),"") -> 412866.72 | E9: =IFERROR(IF(B9="","",1),"") -> 1
A10: Ventas de alquiler del espacio y servicios del evento | B10: =IFERROR(IF(B9="","",B9*$E$10),"") -> 283982.4 | C10: =IFERROR(IF(C9="","",C9*$E$10),"") -> 306700.99 | D10: =IFERROR(IF(D9="","",D9*$E$10),"") -> 322036.04 | E10: =IFERROR(IF('0. Supuestos'!$B$11="","",'0. Supuestos'!$B$11),"") -> 0.78 | F10: Lo que pagan los novios y las empresas a la finca: el espacio, la ceremonia, el montaje, la coordinación del día, la limpieza y el aparcamiento. Con precio propio va al 21 % · El tipo de IVA que REPERCUTE esta línea es un input (celda verde de la derecha): cámbialo sólo si tu asesoría te confirma otro tipo. | G10: 0.21
A11: Canon del catering exclusivo | B11: =IFERROR(IF(B9="","",B9*$E$11),"") -> 80097.6 | C11: =IFERROR(IF(C9="","",C9*$E$11),"") -> 86505.408 | D11: =IFERROR(IF(D9="","",D9*$E$11),"") -> 90830.678 | E11: =IFERROR(IF('0. Supuestos'!$B$12="","",'0. Supuestos'!$B$12),"") -> 0.22 | F11: Lo que te paga el catering de la casa por servir en la finca. El plan supone el 12 % de lo que factura en ella, unos 13 € por invitado en una boda: es un supuesto, negócialo. Factura de la finca al catering, al 21 % · El tipo de IVA que REPERCUTE esta línea es un input (celda verde de la derecha): cámbialo sólo si tu asesoría te confirma otro tipo. | G11: 0.21
A12: COSTES VARIABLES
A13: Coste directo del evento | B13: =IFERROR(IF(B9="","",B9*'0. Supuestos'!$B$11*'0. Supuestos'!$B$13),"") -> 46289.131 | C13: =IFERROR(IF(C9="","",C9*'0. Supuestos'!$B$11*'0. Supuestos'!$B$13),"") -> 49992.262 | D13: =IFERROR(IF(D9="","",D9*'0. Supuestos'!$B$11*'0. Supuestos'!$B$13),"") -> 52491.875 | E13: =IFERROR(B13/$B$9,"") -> 0.12714 | F13: =IFERROR("Al "&TEXT('0. Supuestos'!$B$13,"0%")&" de las ventas de ESPACIO Y SERVICIOS, no del total: el canon tiene su propia línea · El IVA que SOPORTAS en el coste directo del evento: limpieza, consumibles, gasoil, vigilancia y la tarifa de SGAE van al 21 %. Ajústalo a tus facturas","") -> Al 16% de las ventas de ESPACIO Y SERVICIOS, no del total: el canon tiene su propia línea · El IVA que SOPORTAS en el coste directo del evento: limpieza, consumibles, gasoil, vigilancia y la tarifa de SGAE van al 21 %. Ajústalo a tus facturas | G13: 0.21
A14: Coste del canon (no tiene) | B14: =IFERROR(IF(B9="","",B9*'0. Supuestos'!$B$12*'0. Supuestos'!$B$14),"") -> 0 | C14: =IFERROR(IF(C9="","",C9*'0. Supuestos'!$B$12*'0. Supuestos'!$B$14),"") -> 0 | D14: =IFERROR(IF(D9="","",D9*'0. Supuestos'!$B$12*'0. Supuestos'!$B$14),"") -> 0 | E14: =IFERROR(B14/$B$9,"") -> 0 | F14: =IFERROR("Al "&TEXT('0. Supuestos'!$B$14,"0%")&" de las ventas del CANON","") -> Al 0% de las ventas del CANON | G14: =IFERROR(IF(B9="","",('0. Supuestos'!$B$62*'0. Supuestos'!$B$40+(1-'0. Supuestos'!$B$62)*'0. Supuestos'!$B$39)),"") -> 0.1
A15: Consumibles de los montajes | B15: =IFERROR(IF(B9="","",B9*'0. Supuestos'!$B$15),"") -> 7281.6 | C15: =IFERROR(IF(C9="","",C9*'0. Supuestos'!$B$15),"") -> 7864.128 | D15: =IFERROR(IF(D9="","",D9*'0. Supuestos'!$B$15),"") -> 8257.3344 | E15: =IFERROR(B15/$B$9,"") -> 0.02 | G15: =IFERROR(IF(B9="","",'0. Supuestos'!$B$41),"") -> 0.21
A16: Comisiones de wedding planners y agencias | B16: =IFERROR(IF(B9="","",B9*'0. Supuestos'!$B$16*'0. Supuestos'!$B$17),"") -> 9102 | C16: =IFERROR(IF(C9="","",C9*'0. Supuestos'!$B$16*'0. Supuestos'!$B$17),"") -> 9830.16 | D16: =IFERROR(IF(D9="","",D9*'0. Supuestos'!$B$16*'0. Supuestos'!$B$17),"") -> 10321.668 | E16: =IFERROR(B16/$B$9,"") -> 0.025 | F16: Sobre las ventas DEL CANAL. Con 0 % de intermediarios en Supuestos, esta línea vale cero | G16: =IFERROR(IF(B9="","",'0. Supuestos'!$B$41),"") -> 0.21
A17: Comisiones de los medios de pago | B17: =IFERROR(IF(B9="","",B9*'0. Supuestos'!$B$18),"") -> 1092.24 | C17: =IFERROR(IF(C9="","",C9*'0. Supuestos'!$B$18),"") -> 1179.6192 | D17: =IFERROR(IF(D9="","",D9*'0. Supuestos'!$B$18),"") -> 1238.6002 | E17: =IFERROR(B17/$B$9,"") -> 0.003 | F17: Las comisiones de los medios de pago están EXENTAS de IVA (art. 20.Uno.18 LIVA): no se deduce nada por ellas | G17: 0
A18: Varios e imprevistos | B18: =IFERROR(IF(B9="","",B9*'0. Supuestos'!$B$28),"") -> 7281.6 | C18: =IFERROR(IF(C9="","",C9*'0. Supuestos'!$B$28),"") -> 7864.128 | D18: =IFERROR(IF(D9="","",D9*'0. Supuestos'!$B$28),"") -> 8257.3344 | E18: =IFERROR(B18/$B$9,"") -> 0.02 | F18: =IFERROR("Al "&TEXT('0. Supuestos'!$B$28,"0%")&" de las ventas. Es un coste VARIABLE: sube y baja con la facturación, así que no puede vivir en los costes fijos","") -> Al 2% de las ventas. Es un coste VARIABLE: sube y baja con la facturación, así que no puede vivir en los costes fijos | G18: =IFERROR(IF(B9="","",'0. Supuestos'!$B$41),"") -> 0.21
A19: TOTAL COSTES VARIABLES | B19: =IFERROR(IF(B9="","",SUM(B13:B18)),"") -> 71046.571 | C19: =IFERROR(IF(C9="","",SUM(C13:C18)),"") -> 76730.297 | D19: =IFERROR(IF(D9="","",SUM(D13:D18)),"") -> 80566.812 | E19: =IFERROR(B19/$B$9,"") -> 0.19514
A20: MARGEN BRUTO | B20: =IFERROR(IF(B9="","",B9-B19),"") -> 293033.43 | C20: =IFERROR(IF(C9="","",C9-C19),"") -> 316476.1 | D20: =IFERROR(IF(D9="","",D9-D19),"") -> 332299.91 | E20: =IFERROR(B20/$B$9,"") -> 0.80486
A21: COSTES FIJOS
A22: Renta de la finca | B22: =IFERROR(IF(B9="","",'0. Supuestos'!$B$24*12),"") -> 42000 | C22: =IFERROR(IF(C9="","",B22*(1+'0. Supuestos'!$B$48)),"") -> 42000 | D22: =IFERROR(IF(D9="","",C22*(1+'0. Supuestos'!$B$48)),"") -> 42000 | E22: =IFERROR(B22/$B$9,"") -> 0.11535926 | F22: El importe mensual está en la hoja de Supuestos; aquí se multiplica por doce. Lleva IVA al 21 %. El mes de renta previo a la apertura está en la hoja de Inversión y NO se cuenta dos veces | G22: =IFERROR(IF(B9="","",'0. Supuestos'!$B$41),"") -> 0.21
A23: Personal (nóminas + Seguridad Social) | B23: =IFERROR(IF(B9="","",'Personal'!$G$11),"") -> 111720 | C23: =IFERROR(IF(C9="","",'Personal'!$B$15),"") -> 117720 | D23: =IFERROR(IF(D9="","",'Personal'!$B$16),"") -> 123720 | E23: =IFERROR(B23/$B$9,"") -> 0.30685564 | F23: Sale de la hoja de Personal: es el MISMO número, no una estimación aparte. Los años 2 y 3 suman las INCORPORACIONES declaradas en esa hoja, no un porcentaje de volumen | G23: 0
A24: Suministros (luz, agua, gasoil y teléfono) | B24: =IFERROR(IF(B9="","",'0. Supuestos'!$B$26*12),"") -> 19200 | C24: =IFERROR(IF(C9="","",B24*(1+'0. Supuestos'!$B$48)),"") -> 19200 | D24: =IFERROR(IF(D9="","",C24*(1+'0. Supuestos'!$B$48)),"") -> 19200 | E24: =IFERROR(B24/$B$9,"") -> 0.052735662 | F24: Luz y gas van al 21 %; la factura del agua, al 10 %. El libro aplica a toda esta partida el tipo de la columna de al lado (21 %): si el agua pesa mucho en tu finca, sepárala en su línea | G24: =IFERROR(IF(B9="","",'0. Supuestos'!$B$41),"") -> 0.21
A25: Seguros (RC + multirriesgo) | B25: =IFERROR(IF(B9="","",'0. Supuestos'!$B$27),"") -> 5500 | C25: =IFERROR(IF(C9="","",B25*(1+'0. Supuestos'!$B$48)),"") -> 5500 | D25: =IFERROR(IF(D9="","",C25*(1+'0. Supuestos'!$B$48)),"") -> 5500 | E25: =IFERROR(B25/$B$9,"") -> 0.01510657 | F25: Las operaciones de seguro están EXENTAS de IVA (art. 20.Uno.16 LIVA): la prima no lleva IVA deducible | G25: 0
A26: Marketing: portales de bodas, Google Ads y redes | B26: 12000 | C26: =IFERROR(IF(C9="","",B26*(1+'0. Supuestos'!$B$48)),"") -> 12000 | D26: =IFERROR(IF(D9="","",C26*(1+'0. Supuestos'!$B$48)),"") -> 12000 | E26: =IFERROR(B26/$B$9,"") -> 0.032959789 | F26: Escaparate en los portales de bodas, Google Ads y redes sociales. Mide el coste por contacto de cada canal antes de renovar el escaparate premium | G26: =IFERROR(IF(B9="","",'0. Supuestos'!$B$41),"") -> 0.21
A27: Ferias nupciales y jornadas de puertas abiertas | B27: 6000 | C27: =IFERROR(IF(C9="","",B27*(1+'0. Supuestos'!$B$48)),"") -> 6000 | D27: =IFERROR(IF(D9="","",C27*(1+'0. Supuestos'!$B$48)),"") -> 6000 | E27: =IFERROR(B27/$B$9,"") -> 0.016479895 | F27: Dos ferias de novios al año y las jornadas de puertas abiertas de la finca, con el catering | G27: =IFERROR(IF(B9="","",'0. Supuestos'!$B$41),"") -> 0.21
A28: Jardinería y mantenimiento externo (poda, césped y riego) | B28: 8000 | C28: =IFERROR(IF(C9="","",B28*(1+'0. Supuestos'!$B$48)),"") -> 8000 | D28: =IFERROR(IF(D9="","",C28*(1+'0. Supuestos'!$B$48)),"") -> 8000 | E28: =IFERROR(B28/$B$9,"") -> 0.021973193 | F28: Los trabajos grandes que no hace el personal propio: poda, césped, riego y tratamientos | G28: =IFERROR(IF(B9="","",'0. Supuestos'!$B$41),"") -> 0.21
A29: Reparaciones, pintura y reposición de mobiliario | B29: 6000 | C29: =IFERROR(IF(C9="","",B29*(1+'0. Supuestos'!$B$48)),"") -> 6000 | D29: =IFERROR(IF(D9="","",C29*(1+'0. Supuestos'!$B$48)),"") -> 6000 | E29: =IFERROR(B29/$B$9,"") -> 0.016479895 | F29: Pintura, pequeñas obras entre temporadas y reposición de sillas, mesas y mantelería | G29: =IFERROR(IF(B9="","",'0. Supuestos'!$B$41),"") -> 0.21
A30: Gestoría laboral, fiscal y contable | B30: 3000 | C30: =IFERROR(IF(C9="","",B30*(1+'0. Supuestos'!$B$48)),"") -> 3000 | D30: =IFERROR(IF(D9="","",C30*(1+'0. Supuestos'!$B$48)),"") -> 3000 | E30: =IFERROR(B30/$B$9,"") -> 0.0082399473 | F30: Contabilidad, impuestos de la SL y nóminas de los fijos discontinuos, con sus llamamientos de cada temporada | G30: =IFERROR(IF(B9="","",'0. Supuestos'!$B$41),"") -> 0.21
A31: Software de reservas, CRM, web y teléfono | B31: 1800 | C31: =IFERROR(IF(C9="","",B31*(1+'0. Supuestos'!$B$48)),"") -> 1800 | D31: =IFERROR(IF(D9="","",C31*(1+'0. Supuestos'!$B$48)),"") -> 1800 | E31: =IFERROR(B31/$B$9,"") -> 0.0049439684 | F31: Calendario de fechas, presupuestos, CRM de novios y empresas, alojamiento de la web y teléfono | G31: =IFERROR(IF(B9="","",'0. Supuestos'!$B$41),"") -> 0.21
A32: Prevención de riesgos laborales y vigilancia de la salud | B32: 500 | C32: =IFERROR(IF(C9="","",B32*(1+'0. Supuestos'!$B$48)),"") -> 500 | D32: =IFERROR(IF(D9="","",C32*(1+'0. Supuestos'!$B$48)),"") -> 500 | E32: =IFERROR(B32/$B$9,"") -> 0.0013733245 | F32: El plan de prevención es obligatorio (Ley 31/1995): montaje, cargas, trabajo en altura y jardinería, y reconocimientos médicos de la plantilla | G32: =IFERROR(IF(B9="","",'0. Supuestos'!$B$41),"") -> 0.21
A33: Tasas municipales e IBI repercutido | B33: 2500 | C33: =IFERROR(IF(C9="","",B33*(1+'0. Supuestos'!$B$48)),"") -> 2500 | D33: =IFERROR(IF(D9="","",C33*(1+'0. Supuestos'!$B$48)),"") -> 2500 | E33: =IFERROR(B33/$B$9,"") -> 0.0068666227 | F33: Basuras y otras tasas municipales y el IBI que el propietario te repercuta según el contrato. Pon las de tu ayuntamiento | G33: =IFERROR(IF(B9="","",'0. Supuestos'!$B$41),"") -> 0.21
A34: Revisiones de baja tensión, protección contra incendios y grupo electrógeno | B34: 1200 | C34: =IFERROR(IF(C9="","",B34*(1+'0. Supuestos'!$B$48)),"") -> 1200 | D34: =IFERROR(IF(D9="","",C34*(1+'0. Supuestos'!$B$48)),"") -> 1200 | E34: =IFERROR(B34/$B$9,"") -> 0.0032959789 | F34: Inspecciones periódicas de la instalación eléctrica, mantenimiento de extintores y del sistema contra incendios por una empresa mantenedora y revisión del grupo electrógeno | G34: =IFERROR(IF(B9="","",'0. Supuestos'!$B$41),"") -> 0.21
A35: Limpieza general, desinsectación y desratización (DDD) | B35: 2000 | C35: =IFERROR(IF(C9="","",B35*(1+'0. Supuestos'!$B$48)),"") -> 2000 | D35: =IFERROR(IF(D9="","",C35*(1+'0. Supuestos'!$B$48)),"") -> 2000 | E35: =IFERROR(B35/$B$9,"") -> 0.0054932982 | F35: Limpieza a fondo de temporada, productos y control de plagas por una empresa inscrita | G35: =IFERROR(IF(B9="","",'0. Supuestos'!$B$41),"") -> 0.21
A36: Amortización del inmovilizado | B36: =IFERROR(IF(B9="","",'Inversión Inicial'!$B$38),"") -> 16752 | C36: =IFERROR(IF(C9="","",B36),"") -> 16752 | D36: =IFERROR(IF(D9="","",B36),"") -> 16752 | E36: =IFERROR(B36/$B$9,"") -> 0.046011866 | F36: Sale de las bases de amortización de la hoja de Inversión: sólo inmovilizado real. NO sube con el IPC: es una cuota sobre el coste HISTÓRICO del inmovilizado | G36: 0
A37: Gastos financieros (intereses del préstamo) | B37: =IFERROR(IF(B9="","",'Financiación'!$B$44),"") -> 17095 | C37: =IFERROR(IF(C9="","",'Financiación'!$B$46),"") -> 17095 | D37: =IFERROR(IF(D9="","",'Financiación'!$B$48),"") -> 15089.22 | E37: =IFERROR(B37/$B$9,"") -> 0.046953966 | F37: Sólo los INTERESES son gasto. La devolución del principal va en la hoja de Tesorería | G37: 0
A38: TOTAL COSTES FIJOS | B38: =IFERROR(IF(B9="","",SUM(B22:B37)),"") -> 255267 | C38: =IFERROR(IF(C9="","",SUM(C22:C37)),"") -> 261267 | D38: =IFERROR(IF(D9="","",SUM(D22:D37)),"") -> 265261.22 | E38: =IFERROR(B38/$B$9,"") -> 0.70112887
A39: IVA soportado de los costes variables | B39: =IFERROR(IF(B9="","",SUMPRODUCT(B13:B18,G13:G18)),"") -> 14690.41 | C39: =IFERROR(IF(C9="","",SUMPRODUCT(C13:C18,G13:G18)),"") -> 15865.642 | D39: =IFERROR(IF(D9="","",SUMPRODUCT(D13:D18,G13:G18)),"") -> 16658.924 | F39: Cada línea a SU tipo, leído de la columna de al lado. Es lo que la hoja de Tesorería paga de más a los proveedores y luego se deduce
A40: IVA soportado de los costes fijos | B40: =IFERROR(IF(B9="","",SUMPRODUCT(B22:B37,G22:G37)),"") -> 21882 | C40: =IFERROR(IF(C9="","",SUMPRODUCT(C22:C37,G22:G37)),"") -> 21882 | D40: =IFERROR(IF(D9="","",SUMPRODUCT(D22:D37,G22:G37)),"") -> 21882
A41: RESULTADO ANTES DE IMPUESTOS | B41: =IFERROR(IF(B9="","",B20-B38),"") -> 37766.429 | C41: =IFERROR(IF(C9="","",C20-C38),"") -> 55209.103 | D41: =IFERROR(IF(D9="","",D20-D38),"") -> 67038.688 | E41: =IFERROR(B41/$B$9,"") -> 0.10373113
A42: Bases negativas pendientes al inicio | B42: =IFERROR(IF(B9="","",'0. Supuestos'!$B$42),"") -> 0 | C42: =IFERROR(IF(C9="","",B47),"") -> 0 | D42: =IFERROR(IF(D9="","",C47),"") -> 0 | F42: Art. 26 LIS: las pérdidas de un ejercicio se compensan con los beneficios de los siguientes
A43: Base imponible (después de compensar) | B43: =IFERROR(IF(B9="","",MAX(0,B41-B42)),"") -> 37766.429 | C43: =IFERROR(IF(C9="","",MAX(0,C41-C42)),"") -> 55209.103 | D43: =IFERROR(IF(D9="","",MAX(0,D41-D42)),"") -> 67038.688
A44: Ejercicios con base positiva (acumulado) | B44: =IFERROR(IF(B9="","",IF(B43>0,1,0)),"") -> 1 | C44: =IFERROR(IF(C9="","",B44+IF(C43>0,1,0)),"") -> 2 | D44: =IFERROR(IF(D9="","",C44+IF(D43>0,1,0)),"") -> 3
A45: Tipo de Impuesto de Sociedades aplicado | B45: =IFERROR(IF(B9="","",IF(B43<=0,"",IF(B44<=2,'0. Supuestos'!$B$37,'0. Supuestos'!$B$38))),"") -> 0.15 | C45: =IFERROR(IF(C9="","",IF(C43<=0,"",IF(C44<=2,'0. Supuestos'!$B$37,'0. Supuestos'!$B$38))),"") -> 0.15 | D45: =IFERROR(IF(D9="","",IF(D43<=0,"",IF(D44<=2,'0. Supuestos'!$B$37,'0. Supuestos'!$B$38))),"") -> 0.25 | F45: Art. 29.1 LIS: el 15 % de entidad de nueva creación se aplica al PRIMER ejercicio con base positiva y al SIGUIENTE, no al primer año de vida. El libro lo aproxima contando los dos primeros ejercicios con base positiva
A46: Impuesto de Sociedades | B46: =IFERROR(IF(B9="","",IF(B45="",0,B43*B45)),"") -> 5664.9643 | C46: =IFERROR(IF(C9="","",IF(C45="",0,C43*C45)),"") -> 8281.3655 | D46: =IFERROR(IF(D9="","",IF(D45="",0,D43*D45)),"") -> 16759.672
A47: Bases negativas pendientes al cierre | B47: =IFERROR(IF(B9="","",MAX(0,B42-B41)),"") -> 0 | C47: =IFERROR(IF(C9="","",MAX(0,C42-C41)),"") -> 0 | D47: =IFERROR(IF(D9="","",MAX(0,D42-D41)),"") -> 0
A48: RESULTADO NETO | B48: =IFERROR(IF(B9="","",B41-B46),"") -> 32101.464 | C48: =IFERROR(IF(C9="","",C41-C46),"") -> 46927.738 | D48: =IFERROR(IF(D9="","",D41-D46),"") -> 50279.016 | E48: =IFERROR(B48/$B$9,"") -> 0.088171458
A49: RATIOS CLAVE
A50: Ratio | B50: Año 1 | C50: Año 2 | D50: Año 3 | E50: Umbral | F50: Comentario
A51: Margen bruto / Ventas | B51: =IFERROR(IF(B9="","",B20/B9),"") -> 0.80486 | C51: =IFERROR(IF(C9="","",C20/C9),"") -> 0.80486 | D51: =IFERROR(IF(D9="","",D20/D9),"") -> 0.80486 | E51: 0.75 | F51: Suelo del margen tras TODOS los costes variables (coste directo del evento, consumibles, comisiones, medios de pago y varios): sin mercancía que comprar, una finca deja más del 75 %. Estimación del kit
A52: Coste directo del evento (el canon no tiene coste) | B52: =IFERROR(IF(B9="","",B13+B14),"") -> 46289.131 | C52: =IFERROR(IF(C9="","",C13+C14),"") -> 49992.262 | D52: =IFERROR(IF(D9="","",D13+D14),"") -> 52491.875
A53: Coste directo del evento / Ventas | B53: =IFERROR(IF(B9="","",B52/B9),"") -> 0.12714 | C53: =IFERROR(IF(C9="","",C52/C9),"") -> 0.12714 | D53: =IFERROR(IF(D9="","",D52/D9),"") -> 0.12714 | E53: 0.14 | F53: Limpieza, aseos, gasoil, vigilancia y SGAE de cada evento sobre las ventas. Por encima del 14 %, algo se escapa en cada montaje. Estimación del kit
A54: Coste de personal / Ventas | B54: =IFERROR(IF(B9="","",B23/B9),"") -> 0.30685564 | C54: =IFERROR(IF(C9="","",C23/C9),"") -> 0.29938475 | D54: =IFERROR(IF(D9="","",D23/D9),"") -> 0.29966087 | E54: 0.33 | F54: Techo del personal propio sobre ventas, sin camareros ni cocina (los pone el catering). Estimación del kit
A55: Renta de la finca / Ventas | B55: =IFERROR(IF(B9="","",B22/B9),"") -> 0.11535926 | C55: =IFERROR(IF(C9="","",C22/C9),"") -> 0.10681413 | D55: =IFERROR(IF(D9="","",D22/D9),"") -> 0.10172774 | E55: 0.13 | F55: Techo de la renta de la finca sobre las ventas: por encima, la ocupación tiene que ser altísima para pagarla. Estimación del kit
A56: Resultado neto / Ventas | B56: =IFERROR(IF(B9="","",B48/B9),"") -> 0.088171458 | C56: =IFERROR(IF(C9="","",C48/C9),"") -> 0.11934632 | D56: =IFERROR(IF(D9="","",D48/D9),"") -> 0.12178026 | E56: 0.05 | F56: Suelo de resultado neto a régimen para que el plan se sostenga: estimación del kit
A57: Punto de equilibrio alcanzado | B57: =IFERROR(IF(B9="","",IF(B9>='Punto Equilibrio'!$B$16,"Sí","No")),"") -> Sí | C57: =IFERROR(IF(C9="","",IF(C9>='Punto Equilibrio'!$C$16,"Sí","No")),"") -> Sí | D57: =IFERROR(IF(D9="","",IF(D9>='Punto Equilibrio'!$D$16,"Sí","No")),"") -> Sí | F57: Compara las ventas de CADA año con el umbral de ese mismo año, que calcula la hoja de Punto de Equilibrio con los costes fijos del año
A59: Todas las cifras van SIN IVA. Las columnas de los años 2 y 3 están en euros del año 1 salvo que subas la actualización de costes en la hoja de Supuestos. La columna «Tipo de IVA de la línea» dice, en las líneas de VENTA, a qué tipo se repercute cada una, y en las de COSTE a qué tipo se compra la partida. La lee la hoja de Tesorería: los seguros y las comisiones de los medios de pago están exentos, y las nóminas, la amortización y los intereses no llevan IVA.

Sheet Punto Equilibrio
A1: PUNTO DE EQUILIBRIO
A2: Punto de equilibrio — finca de eventos y bodas
A4: Variable | B4: Año 1 | C4: Año 2 | D4: Año 3 | E4: Notas
A5: DATOS BASE POR AÑO
A6: Costes fijos anuales | B6: =IFERROR(IF('PyG 3 Años'!$B$9="","",'PyG 3 Años'!$B$38),"") -> 255267 | C6: =IFERROR(IF('PyG 3 Años'!$C$9="","",'PyG 3 Años'!$C$38),"") -> 261267 | D6: =IFERROR(IF('PyG 3 Años'!$D$9="","",'PyG 3 Años'!$D$38),"") -> 265261.22 | E6: Los MISMOS costes fijos del P&L. Cada año tiene los suyos: por eso el umbral no puede ser uno solo para los tres
A7: Costes fijos mensuales | B7: =IFERROR(IF('PyG 3 Años'!$B$9="","",B6/12),"") -> 21272.25 | C7: =IFERROR(IF('PyG 3 Años'!$C$9="","",C6/12),"") -> 21772.25 | D7: =IFERROR(IF('PyG 3 Años'!$D$9="","",D6/12),"") -> 22105.102
A8: Precio medio por invitado sin IVA | B8: =IFERROR(IF('PyG 3 Años'!$B$9="","",'PyG 3 Años'!$B$7),"") -> 37 | C8: =IFERROR(IF('PyG 3 Años'!$C$9="","",'PyG 3 Años'!$C$7),"") -> 37 | D8: =IFERROR(IF('PyG 3 Años'!$D$9="","",'PyG 3 Años'!$D$7),"") -> 37
A9: Coste variable por invitado | B9: =IFERROR(IF('PyG 3 Años'!$B$9="","",'PyG 3 Años'!$B$19/('PyG 3 Años'!$B$6*'PyG 3 Años'!$B$8)),"") -> 7.22018 | C9: =IFERROR(IF('PyG 3 Años'!$C$9="","",'PyG 3 Años'!$C$19/('PyG 3 Años'!$C$6*'PyG 3 Años'!$C$8)),"") -> 7.22018 | D9: =IFERROR(IF('PyG 3 Años'!$D$9="","",'PyG 3 Años'!$D$19/('PyG 3 Años'!$D$6*'PyG 3 Años'!$D$8)),"") -> 7.22018 | E9: Sale del total de costes variables del P&L, no de una estimación aparte. Incluye los varios e imprevistos, que son un porcentaje de las ventas
A10: Margen de contribución por invitado | B10: =IFERROR(IF('PyG 3 Años'!$B$9="","",B8-B9),"") -> 29.77982 | C10: =IFERROR(IF('PyG 3 Años'!$C$9="","",C8-C9),"") -> 29.77982 | D10: =IFERROR(IF('PyG 3 Años'!$D$9="","",D8-D9),"") -> 29.77982 | E10: Precio por invitado menos coste variable unitario
A11: Eventos al año | B11: =IFERROR(IF('PyG 3 Años'!$B$9="","",'PyG 3 Años'!$B$8),"") -> 120 | C11: =IFERROR(IF('PyG 3 Años'!$C$9="","",'PyG 3 Años'!$C$8),"") -> 120 | D11: =IFERROR(IF('PyG 3 Años'!$D$9="","",'PyG 3 Años'!$D$8),"") -> 120 | E11: El mismo calendario que el P&L y que los escenarios
A12: Devolución de principal del año (cuota) | B12: =IFERROR(IF('PyG 3 Años'!$B$9="","",'Financiación'!$B$45),"") -> 0 | C12: =IFERROR(IF('PyG 3 Años'!$C$9="","",'Financiación'!$B$47),"") -> 30858.15 | D12: =IFERROR(IF('PyG 3 Años'!$D$9="","",'Financiación'!$B$49),"") -> 32863.93 | E12: El principal NO es gasto del P&L, pero sale de la caja. Sin él, el umbral de equilibrio se publica por debajo del real
A13: PUNTO DE EQUILIBRIO CONTABLE (incluye amortización)
A14: Invitados necesarios al año | B14: =IFERROR(IF('PyG 3 Años'!$B$9="","",IF(B10<=0,"",B6/B10)),"") -> 8571.8114 | C14: =IFERROR(IF('PyG 3 Años'!$C$9="","",IF(C10<=0,"",C6/C10)),"") -> 8773.2901 | D14: =IFERROR(IF('PyG 3 Años'!$D$9="","",IF(D10<=0,"",D6/D10)),"") -> 8907.4152
A15: Invitados necesarios por evento | B15: =IFERROR(IF('PyG 3 Años'!$B$9="","",B14/B11),"") -> 71.431762 | C15: =IFERROR(IF('PyG 3 Años'!$C$9="","",C14/C11),"") -> 73.110751 | D15: =IFERROR(IF('PyG 3 Años'!$D$9="","",D14/D11),"") -> 74.22846
A16: Ingresos necesarios al año | B16: =IFERROR(IF('PyG 3 Años'!$B$9="","",B14*B8),"") -> 317157.02 | C16: =IFERROR(IF('PyG 3 Años'!$C$9="","",C14*C8),"") -> 324611.73 | D16: =IFERROR(IF('PyG 3 Años'!$D$9="","",D14*D8),"") -> 329574.36
A17: PUNTO DE EQUILIBRIO DE CAJA (incluye la cuota del préstamo)
A18: Costes fijos de caja + principal del año | B18: =IFERROR(IF('PyG 3 Años'!$B$9="","",B6-'PyG 3 Años'!$B$36+B12),"") -> 238515 | C18: =IFERROR(IF('PyG 3 Años'!$C$9="","",C6-'PyG 3 Años'!$C$36+C12),"") -> 275373.15 | D18: =IFERROR(IF('PyG 3 Años'!$D$9="","",D6-'PyG 3 Años'!$D$36+D12),"") -> 281373.15 | E18: Los fijos del P&L sin la amortización (que no se paga) y CON la devolución de principal (que sí). Es el umbral que decide si la caja aguanta
A19: Invitados necesarios al año (caja) | B19: =IFERROR(IF('PyG 3 Años'!$B$9="","",IF(B10<=0,"",B18/B10)),"") -> 8009.2828 | C19: =IFERROR(IF('PyG 3 Años'!$C$9="","",IF(C10<=0,"",C18/C10)),"") -> 9246.9716 | D19: =IFERROR(IF('PyG 3 Años'!$D$9="","",IF(D10<=0,"",D18/D10)),"") -> 9448.4503
A20: Invitados necesarios por evento (caja) | B20: =IFERROR(IF('PyG 3 Años'!$B$9="","",B19/B11),"") -> 66.744023 | C20: =IFERROR(IF('PyG 3 Años'!$C$9="","",C19/C11),"") -> 77.058097 | D20: =IFERROR(IF('PyG 3 Años'!$D$9="","",D19/D11),"") -> 78.737086
A21: Ingresos necesarios al año (caja) | B21: =IFERROR(IF('PyG 3 Años'!$B$9="","",B19*B8),"") -> 296343.46 | C21: =IFERROR(IF('PyG 3 Años'!$C$9="","",C19*C8),"") -> 342137.95 | D21: =IFERROR(IF('PyG 3 Años'!$D$9="","",D19*D8),"") -> 349592.66
A22: CONTRASTE CON EL PLAN
A23: Invitados por evento previstos en el plan | B23: =IFERROR(IF('PyG 3 Años'!$B$9="","",'PyG 3 Años'!$B$6),"") -> 82 | C23: =IFERROR(IF('PyG 3 Años'!$C$9="","",'PyG 3 Años'!$C$6),"") -> 88.56 | D23: =IFERROR(IF('PyG 3 Años'!$D$9="","",'PyG 3 Años'!$D$6),"") -> 92.988
A24: Holgura sobre el equilibrio de CAJA (%) | B24: =IFERROR(IF('PyG 3 Años'!$B$9="","",B23/B20-1),"") -> 0.22857442 | C24: =IFERROR(IF('PyG 3 Años'!$C$9="","",C23/C20-1),"") -> 0.14926275 | D24: =IFERROR(IF('PyG 3 Años'!$D$9="","",D23/D20-1),"") -> 0.18099367 | E24: Cuánto superan tus ventas previstas a las del equilibrio de caja. La caída que aguantas antes de no poder pagar los costes fijos y la cuota es algo menor: con un 25 % de holgura, un 20 %. El mínimo exigible está en la hoja de Supuestos
A25: INTERPRETACIÓN
A26: =IFERROR("Con el precio medio por invitado sin IVA de la fila de arriba necesitas "&TEXT(ROUNDUP(B15,0),"0")&" invitados por evento durante los "&TEXT(B11,"0")&" eventos del año para no perder dinero (equilibrio contable, con la amortización dentro), y "&TEXT(ROUNDUP(B20,0),"0")&" para que la caja aguante (equilibrio de caja: sin la amortización, que no se paga, y con la cuota del préstamo del año"&IF(B12=0,"; este año sólo intereses, porque el préstamo está en carencia","")&"). En las filas «Ingresos necesarios al año» tienes esas mismas cifras en euros.","") -> Con el precio medio por invitado sin IVA de la fila de arriba necesitas 72 invitados por evento durante los 120 eventos del año para no perder dinero (equilibrio contable, con la amortización dentro), y 67 para que la caja aguante (equilibrio de caja: sin la amortización, que no se paga, y con la cuota del préstamo del año; este año sólo intereses, porque el préstamo está en carencia). En las filas «Ingresos necesarios al año» tienes esas mismas cifras en euros.
A28: SENSIBILIDAD DEL PUNTO DE EQUILIBRIO
A29: Invitados por evento necesarios para cubrir costes según el precio medio por invitado (columnas) y el coste variable por invitado (filas). En verde, los que están por debajo de los invitados que prevé el plan.
A31: Invitados por evento necesarios: precio medio por invitado sin IVA (columnas) × coste variable por invitado (filas) | B31: =IFERROR($B$8-2,"") -> 35 | C31: =IFERROR(IF($B$8="","",$B$8),"") -> 37 | D31: =IFERROR($B$8+2,"") -> 39 | E31: =IFERROR($B$8+4,"") -> 41
A32: =IFERROR($B$9*0.85,"") -> 6.137153 | B32: =IFERROR(IF($B$31-$A32<=0,"",$B$6/($B$31-$A32)/$B$11),"") -> 73.701149 | C32: =IFERROR(IF($C$31-$A32<=0,"",$B$6/($C$31-$A32)/$B$11),"") -> 68.925106 | D32: =IFERROR(IF($D$31-$A32<=0,"",$B$6/($D$31-$A32)/$B$11),"") -> 64.730393 | E32: =IFERROR(IF($E$31-$A32<=0,"",$B$6/($E$31-$A32)/$B$11),"") -> 61.016962
A33: =IFERROR($B$9*0.925,"") -> 6.6786665 | B33: =IFERROR(IF($B$31-$A33<=0,"",$B$6/($B$31-$A33)/$B$11),"") -> 75.11034 | C33: =IFERROR(IF($C$31-$A33<=0,"",$B$6/($C$31-$A33)/$B$11),"") -> 70.15605 | D33: =IFERROR(IF($D$31-$A33<=0,"",$B$6/($D$31-$A33)/$B$11),"") -> 65.81489 | E33: =IFERROR(IF($E$31-$A33<=0,"",$B$6/($E$31-$A33)/$B$11),"") -> 61.979672
A34: =IFERROR($B$9*1.0,"") -> 7.22018 | B34: =IFERROR(IF($B$31-$A34<=0,"",$B$6/($B$31-$A34)/$B$11),"") -> 76.57447 | C34: =IFERROR(IF($C$31-$A34<=0,"",$B$6/($C$31-$A34)/$B$11),"") -> 71.431762 | D34: =IFERROR(IF($D$31-$A34<=0,"",$B$6/($D$31-$A34)/$B$11),"") -> 66.936345 | E34: =IFERROR(IF($E$31-$A34<=0,"",$B$6/($E$31-$A34)/$B$11),"") -> 62.973249
A35: =IFERROR($B$9*1.075,"") -> 7.7616935 | B35: =IFERROR(IF($B$31-$A35<=0,"",$B$6/($B$31-$A35)/$B$11),"") -> 78.096816 | C35: =IFERROR(IF($C$31-$A35<=0,"",$B$6/($C$31-$A35)/$B$11),"") -> 72.754727 | D35: =IFERROR(IF($D$31-$A35<=0,"",$B$6/($D$31-$A35)/$B$11),"") -> 68.096681 | E35: =IFERROR(IF($E$31-$A35<=0,"",$B$6/($E$31-$A35)/$B$11),"") -> 63.999199
A36: =IFERROR($B$9*1.15,"") -> 8.303207 | B36: =IFERROR(IF($B$31-$A36<=0,"",$B$6/($B$31-$A36)/$B$11),"") -> 79.680919 | C36: =IFERROR(IF($C$31-$A36<=0,"",$B$6/($C$31-$A36)/$B$11),"") -> 74.127621 | D36: =IFERROR(IF($D$31-$A36<=0,"",$B$6/($D$31-$A36)/$B$11),"") -> 69.297956 | E36: =IFERROR(IF($E$31-$A36<=0,"",$B$6/($E$31-$A36)/$B$11),"") -> 65.059133

Sheet Escenarios
A1: ESCENARIOS
A4: Métrica | B4: Pesimista | C4: Realista | D4: Optimista | E4: Notas
A5: Invitados por evento | B5: 78 | C5: =IFERROR(IF('PyG 3 Años'!$B$6="","",'PyG 3 Años'!$B$6),"") -> 82 | D5: 85
A6: Precio medio por invitado sin IVA | B6: 34 | C6: =IFERROR(IF('PyG 3 Años'!$B$7="","",'PyG 3 Años'!$B$7),"") -> 37 | D6: 39
A7: Eventos al año | B7: 100 | C7: =IFERROR(IF('PyG 3 Años'!$B$8="","",'PyG 3 Años'!$B$8),"") -> 120 | D7: 135
A8: INGRESOS ANUALES (sin IVA) | B8: =IFERROR(IF(B5*B6*B7=0,"",B5*B6*B7),"") -> 265200 | C8: =IFERROR(IF(C5*C6*C7=0,"",C5*C6*C7),"") -> 364080 | D8: =IFERROR(IF(D5*D6*D7=0,"",D5*D6*D7),"") -> 447525
A9: Coste directo del evento | B9: =IFERROR(IF(B8="","",B8*'0. Supuestos'!$B$11*'0. Supuestos'!$B$13),"") -> 33717.528 | C9: =IFERROR(IF(C8="","",C8*'0. Supuestos'!$B$11*'0. Supuestos'!$B$13),"") -> 46289.131 | D9: =IFERROR(IF(D8="","",D8*'0. Supuestos'!$B$11*'0. Supuestos'!$B$13),"") -> 56898.329
A10: Coste del canon (no tiene) | B10: =IFERROR(IF(B8="","",B8*'0. Supuestos'!$B$12*'0. Supuestos'!$B$14),"") -> 0 | C10: =IFERROR(IF(C8="","",C8*'0. Supuestos'!$B$12*'0. Supuestos'!$B$14),"") -> 0 | D10: =IFERROR(IF(D8="","",D8*'0. Supuestos'!$B$12*'0. Supuestos'!$B$14),"") -> 0
A11: Consumibles de los montajes | B11: =IFERROR(IF(B8="","",B8*'0. Supuestos'!$B$15),"") -> 5304 | C11: =IFERROR(IF(C8="","",C8*'0. Supuestos'!$B$15),"") -> 7281.6 | D11: =IFERROR(IF(D8="","",D8*'0. Supuestos'!$B$15),"") -> 8950.5
A12: Comisiones de wedding planners y agencias | B12: =IFERROR(IF(B8="","",B8*'0. Supuestos'!$B$16*'0. Supuestos'!$B$17),"") -> 6630 | C12: =IFERROR(IF(C8="","",C8*'0. Supuestos'!$B$16*'0. Supuestos'!$B$17),"") -> 9102 | D12: =IFERROR(IF(D8="","",D8*'0. Supuestos'!$B$16*'0. Supuestos'!$B$17),"") -> 11188.125
A13: Comisiones de los medios de pago | B13: =IFERROR(IF(B8="","",B8*'0. Supuestos'!$B$18),"") -> 795.6 | C13: =IFERROR(IF(C8="","",C8*'0. Supuestos'!$B$18),"") -> 1092.24 | D13: =IFERROR(IF(D8="","",D8*'0. Supuestos'!$B$18),"") -> 1342.575
A14: Varios e imprevistos | B14: =IFERROR(IF(B8="","",B8*'0. Supuestos'!$B$28),"") -> 5304 | C14: =IFERROR(IF(C8="","",C8*'0. Supuestos'!$B$28),"") -> 7281.6 | D14: =IFERROR(IF(D8="","",D8*'0. Supuestos'!$B$28),"") -> 8950.5
A15: TOTAL COSTES VARIABLES | B15: =IFERROR(IF(B8="","",SUM(B9:B14)),"") -> 51751.128 | C15: =IFERROR(IF(C8="","",SUM(C9:C14)),"") -> 71046.571 | D15: =IFERROR(IF(D8="","",SUM(D9:D14)),"") -> 87330.029
A16: MARGEN BRUTO | B16: =IFERROR(IF(B8="","",B8-B15),"") -> 213448.87 | C16: =IFERROR(IF(C8="","",C8-C15),"") -> 293033.43 | D16: =IFERROR(IF(D8="","",D8-D15),"") -> 360194.97
A17: COSTES FIJOS (los del P&L) | B17: =IFERROR(IF(B8="","",'PyG 3 Años'!$B$38),"") -> 255267 | C17: =IFERROR(IF(C8="","",'PyG 3 Años'!$B$38),"") -> 255267 | D17: =IFERROR(IF(D8="","",'PyG 3 Años'!$B$38),"") -> 255267 | E17: Los costes fijos no cambian con el escenario: por eso son fijos
A18: RESULTADO ANTES DE IMPUESTOS | B18: =IFERROR(IF(B8="","",B16-B17),"") -> -41818.128 | C18: =IFERROR(IF(C8="","",C16-C17),"") -> 37766.429 | D18: =IFERROR(IF(D8="","",D16-D17),"") -> 104927.97
A19: Impuesto de Sociedades | B19: =IFERROR(IF(B8="","",MAX(0,B18-'0. Supuestos'!$B$42)*'0. Supuestos'!$B$37),"") -> 0 | C19: =IFERROR(IF(C8="","",MAX(0,C18-'0. Supuestos'!$B$42)*'0. Supuestos'!$B$37),"") -> 5664.9643 | D19: =IFERROR(IF(D8="","",MAX(0,D18-'0. Supuestos'!$B$42)*'0. Supuestos'!$B$37),"") -> 15739.196 | E19: Al tipo de entidad de nueva creación, compensando las bases negativas anteriores
A20: RESULTADO NETO | B20: =IFERROR(IF(B8="","",B18-B19),"") -> -41818.128 | C20: =IFERROR(IF(C8="","",C18-C19),"") -> 32101.464 | D20: =IFERROR(IF(D8="","",D18-D19),"") -> 89188.776
A21: Invitados por evento para el equilibrio | B21: =IFERROR(IF(B8="","",IF(B6-B15/(B5*B7)<=0,"",B17/(B6-B15/(B5*B7))/B7)),"") -> 93.281477 | C21: =IFERROR(IF(C8="","",IF(C6-C15/(C5*C7)<=0,"",C17/(C6-C15/(C5*C7))/C7)),"") -> 71.431762 | D21: =IFERROR(IF(D8="","",IF(D6-D15/(D5*D7)<=0,"",D17/(D6-D15/(D5*D7))/D7)),"") -> 60.23875
A22: LO QUE CADA ESCENARIO EXIGE
A23: Coste de personal / Ventas | B23: =IFERROR(IF(B8="","",'PyG 3 Años'!$B$23/B8),"") -> 0.42126697 | C23: =IFERROR(IF(C8="","",'PyG 3 Años'!$B$23/C8),"") -> 0.30685564 | D23: =IFERROR(IF(D8="","",'PyG 3 Años'!$B$23/D8),"") -> 0.24963968 | E23: La MISMA plantilla en los tres escenarios. Si en el pesimista se dispara, el ajuste hay que hacerlo en la hoja de Personal, no aquí
A24: Invitados al año por jornada equivalente | B24: =IFERROR(IF(B8="","",B5*B7/'Personal'!$C$11),"") -> 2328.3582 | C24: =IFERROR(IF(C8="","",C5*C7/'Personal'!$C$11),"") -> 2937.3134 | D24: =IFERROR(IF(D8="","",D5*D7/'Personal'!$C$11),"") -> 3425.3731 | E24: Invitados que tendría que recibir cada jornada completa del cuadro de Personal. En el optimista dice si hace falta contratar
A25: Saldo de caja al cierre del año 1 (estimado, el mismo método en los tres escenarios) | B25: =IFERROR(IF(B8="","",'Inversión Inicial'!$B$30+B20+'PyG 3 Años'!$B$36-'Financiación'!$B$45),"") -> 34562.622 | C25: =IFERROR(IF(C8="","",'Inversión Inicial'!$B$30+C20+'PyG 3 Años'!$B$36-'Financiación'!$B$45),"") -> 108482.21 | D25: =IFERROR(IF(D8="","",'Inversión Inicial'!$B$30+D20+'PyG 3 Años'!$B$36-'Financiación'!$B$45),"") -> 165569.53 | E25: Saldo ESTIMADO: fondo de maniobra más el resultado del año, devolviendo la amortización (que no se paga) y restando el principal del préstamo. No incluye el desfase de cobros y pagos ni la liquidación del IVA, así que las tres columnas se pueden comparar entre sí. En rojo, el escenario se queda sin caja
A26: Saldo real del mes 12 de la hoja de Tesorería (sólo realista) | C26: =IFERROR(IF(C8="","",'Tesorería 12 meses'!$M$22),"") -> 149910.01 | E26: El saldo REAL del caso base, con su desfase de cobros y pagos y su liquidación de IVA. Sólo existe para el escenario realista, que es el único con tesorería mensual propia: por eso no está en la fila de arriba, donde se compararía contra dos estimaciones
A28: La columna «Realista» lee sus tres datos de la hoja de Supuestos, así que reproduce EXACTAMENTE el año 1 del P&L. Los otros dos escenarios usan las mismas tasas de coste: lo único que cambia son los invitados, el precio por invitado y los eventos. Los COSTES FIJOS sí son los mismos en los tres: los varios e imprevistos, que son un porcentaje de las ventas, van arriba con los variables y cada escenario carga los suyos.

Sheet Personal
A1: PERSONAL Y COSTES
A2: =IFERROR("Convenio Hostelería — "&TEXT('0. Supuestos'!$B$21,"0")&" pagas + SS "&TEXT('0. Supuestos'!$B$20*100,"0")&" %","") -> Convenio Hostelería — 14 pagas + SS 33 %
A4: Puesto | B4: Personas | C4: Jornada | D4: Bruto mes (€, total del puesto) | E4: Seg. Social a cargo de la empresa (€) | F4: Coste mes (€, total del puesto) | G4: Coste año (€) | H4: Horas/semana por persona | I4: Horas/año del puesto | J4: Notas
A5: Titular — gerencia, ventas y visitas | B5: 1 | C5: 1 | D5: 2000 | E5: =IFERROR(IF(D5="","",D5*'0. Supuestos'!$B$20),"") -> 660 | F5: =IFERROR(IF(D5="","",D5+E5),"") -> 2660 | G5: =IFERROR(IF(D5="","",F5*MAX(12,'0. Supuestos'!$B$21)),"") -> 37240 | H5: =IFERROR(IF(D5="","",C5*$B$18),"") -> 40 | I5: =IFERROR(IF(D5="","",H5*B5*$B$19),"") -> 1840 | J5: Vende, enseña la finca, firma los contratos, lleva el calendario y coordina al catering. Como administrador de la SL cotiza en el régimen de autónomos: el libro le imputa el 33 % de Seguridad Social sobre 14 pagas como si fuera nómina, que es el lado prudente. Confirma con tu gestoría la cuota real
A6: Coordinación de bodas y celebraciones (fijo discontinuo, marzo-noviembre) | B6: 1 | C6: 0.75 | D6: 1240 | E6: =IFERROR(IF(D6="","",D6*'0. Supuestos'!$B$20),"") -> 409.2 | F6: =IFERROR(IF(D6="","",D6+E6),"") -> 1649.2 | G6: =IFERROR(IF(D6="","",F6*MAX(12,'0. Supuestos'!$B$21)),"") -> 23088.8 | H6: =IFERROR(IF(D6="","",C6*$B$18),"") -> 30 | I6: =IFERROR(IF(D6="","",H6*B6*$B$19),"") -> 1380 | J6: Contrato fijo discontinuo (art. 16 del Estatuto de los Trabajadores) a jornada completa de marzo a noviembre: equivale al 75 % en cómputo anual. Prepara cada evento con los novios y el catering y lo dirige el día. De diciembre a febrero (comidas de Navidad y eventos de invierno) coordina el titular. Bruto a jornada completa: unos 1.650 €
A7: Mantenimiento y jardinería | B7: 1 | C7: 0.8 | D7: 1120 | E7: =IFERROR(IF(D7="","",D7*'0. Supuestos'!$B$20),"") -> 369.6 | F7: =IFERROR(IF(D7="","",D7+E7),"") -> 1489.6 | G7: =IFERROR(IF(D7="","",F7*MAX(12,'0. Supuestos'!$B$21)),"") -> 20854.4 | H7: =IFERROR(IF(D7="","",C7*$B$18),"") -> 32 | I7: =IFERROR(IF(D7="","",H7*B7*$B$19),"") -> 1472 | J7: Jardines, riego, caminos, pequeñas reparaciones, grupo electrógeno y puesta a punto del salón y de la carpa. Al 80 % de jornada; lo grande (poda, pintura) va en los costes fijos. Bruto a jornada completa: 1.400 €
A8: Auxiliares de montaje, acceso y aseos (fijos discontinuos) | B8: 2 | C8: 0.4 | D8: 1080 | E8: =IFERROR(IF(D8="","",D8*'0. Supuestos'!$B$20),"") -> 356.4 | F8: =IFERROR(IF(D8="","",D8+E8),"") -> 1436.4 | G8: =IFERROR(IF(D8="","",F8*MAX(12,'0. Supuestos'!$B$21)),"") -> 20109.6 | H8: =IFERROR(IF(D8="","",C8*$B$18),"") -> 16 | I8: =IFERROR(IF(D8="","",H8*B8*$B$19),"") -> 1472 | J8: Dos personas al 40 % de jornada en cómputo anual: montaje, control de acceso y aparcamiento, reposición de aseos y recogida. Dos en cada boda y una en el resto. Nunca como autónomos que te facturan: con tu horario y tu dirección es falso autónomo (art. 1.1 ET). Bruto a jornada completa: 1.350 €
A9: Comercial de bodas a tiempo parcial | B9: 1 | C9: 0.2 | D9: 300 | E9: =IFERROR(IF(D9="","",D9*'0. Supuestos'!$B$20),"") -> 99 | F9: =IFERROR(IF(D9="","",D9+E9),"") -> 399 | G9: =IFERROR(IF(D9="","",F9*MAX(12,'0. Supuestos'!$B$21)),"") -> 5586 | H9: =IFERROR(IF(D9="","",C9*$B$18),"") -> 8 | I9: =IFERROR(IF(D9="","",H9*B9*$B$19),"") -> 368 | J9: Al 20 % de jornada: visitas de los sábados por la mañana, ferias nupciales y seguimiento de las peticiones de los portales. Bruto a jornada completa: 1.500 €
A10: Limpieza y puesta a punto a tiempo parcial | B10: 1 | C10: 0.2 | D10: 260 | E10: =IFERROR(IF(D10="","",D10*'0. Supuestos'!$B$20),"") -> 85.8 | F10: =IFERROR(IF(D10="","",D10+E10),"") -> 345.8 | G10: =IFERROR(IF(D10="","",F10*MAX(12,'0. Supuestos'!$B$21)),"") -> 4841.2 | H10: =IFERROR(IF(D10="","",C10*$B$18),"") -> 8 | I10: =IFERROR(IF(D10="","",H10*B10*$B$19),"") -> 368 | J10: Al 20 % de jornada: limpieza entre eventos del salón, los aseos y el office. La limpieza a fondo tras cada boda va en el coste directo del evento. Bruto a jornada completa: 1.300 €
A11: TOTAL PLANTILLA | B11: =IFERROR(IF(COUNT(D5:D10)=0,"",SUM(B5:B10)),"") -> 7 | C11: =IFERROR(IF(COUNT(D5:D10)=0,"",SUM(C5:C10)),"") -> 3.35 | D11: =IFERROR(IF(COUNT(D5:D10)=0,"",SUM(D5:D10)),"") -> 6000 | E11: =IFERROR(IF(COUNT(D5:D10)=0,"",SUM(E5:E10)),"") -> 1980 | F11: =IFERROR(IF(COUNT(D5:D10)=0,"",SUM(F5:F10)),"") -> 7980 | G11: =IFERROR(IF(COUNT(D5:D10)=0,"",SUM(G5:G10)),"") -> 111720 | I11: =IFERROR(IF(COUNT(D5:D10)=0,"",SUM(I5:I10)),"") -> 6900
A12: CRECIMIENTO DE LA PLANTILLA (coste escalonado)
A13: Coste anual de las incorporaciones del año 2 (€) | B13: 6000 | J13: Coste ANUAL completo (bruto + Seguridad Social × pagas) de lo que se contrate ese año. El P&L lo suma al coste del año anterior: la plantilla no crece con un porcentaje, crece con personas
A14: Coste anual de las incorporaciones del año 3 (€) | B14: 6000 | J14: Coste ANUAL completo (bruto + Seguridad Social × pagas) de lo que se contrate ese año. El P&L lo suma al coste del año anterior: la plantilla no crece con un porcentaje, crece con personas
A15: Coste de personal del año 2 | B15: =IFERROR(IF(G11="","",G11*(1+'0. Supuestos'!$B$48)+B13),"") -> 117720
A16: Coste de personal del año 3 | B16: =IFERROR(IF(B15="","",B15*(1+'0. Supuestos'!$B$48)+B14),"") -> 123720
A17: COBERTURA POR HORAS DE SERVICIO
A18: Jornada completa del convenio (horas/semana) | B18: 40 | J18: Art. 34.1 del Estatuto de los Trabajadores; tu convenio provincial puede fijar menos
A19: Semanas trabajadas al año por persona | B19: 46 | J19: 46 semanas: 52 menos las vacaciones (30 días naturales, art. 38 ET), los festivos y las ausencias medias
A20: Horas de trabajo por evento que hay que cubrir | B20: 9.2 | J20: Media del día del evento, de montaje a recogida: boda 13 h, empresa 9 h, celebración privada 8 h y evento pequeño 5 h (9,2 h de media con la mezcla del plan)
A21: Personas necesarias a la vez en cada evento | B21: 2.3 | J21: Personal de la finca a la vez en el evento: coordinación y dos auxiliares en las bodas, y coordinación y un auxiliar en el resto (2,3 de media). Camareros y cocina los pone el catering
A22: Horas de estructura por evento, fuera del día del evento | B22: 12 | J22: Horas por evento fuera del día del evento: visitas y reuniones con los novios, preparación con el catering, mantenimiento, jardín, limpieza y gestión. Es la parte de la plantilla que trabaja todo el año, repartida entre los eventos
A23: Personas de estructura por evento | B23: 3 | J23: Gerencia, mantenimiento y apoyo (comercial o limpieza) a la vez
A24: Horas de servicio a cubrir al año | B24: =IFERROR(IF(OR(B20="",B21="",'0. Supuestos'!$B$6=""),"",B20*B21*'0. Supuestos'!$B$6+B22*B23*'0. Supuestos'!$B$6),"") -> 6859.2
A25: Horas contratadas al año | B25: =IFERROR(IF(I11="","",I11),"") -> 6900
A26: Cobertura (contratadas / necesarias) | B26: =IFERROR(B25/B24,"") -> 1.0059482 | J26: Por debajo del 100 % la plantilla no llega a cubrir el horario que declara el plan: o se contrata más o se recorta el horario
A28: Las columnas «Bruto mes», «Seg. Social», «Coste mes» y «Coste año» son TOTALES de la fila: en un puesto con dos personas incluyen a las dos. «Jornada» es el porcentaje sobre la jornada completa del convenio y sirve para comparar el salario con el suelo legal en proporción. El tipo de Seguridad Social y el número de pagas están en la hoja «0. Supuestos».
A29: El suelo salarial es el MAYOR entre el SMI y el salario de convenio, los dos en la hoja «0. Supuestos»; las jornadas parciales lo llevan en proporción. El convenio aplicable es el PROVINCIAL de hostelería: no existe una tabla salarial estatal única, así que la celda del convenio se entrega vacía para que copies la de tu provincia.

Sheet Instrucciones
A1: INSTRUCCIONES DE USO — Plan financiero Finca de Eventos y Bodas
A3: CÓMO SE USA ESTE LIBRO
A4: Este plan financiero es un MODELO: sólo se teclea en las celdas VERDES y el resto se recalcula solo.
A5: 1. «0. Supuestos» es la hoja de mando: invitados, precio por invitado sin IVA, eventos, mezcla de espacio y canon, coste directo del evento, renta de la finca, financiación e impuestos.
A6: 2. Las partidas de la inversión, los costes fijos y la plantilla se teclean en su propia hoja, también en verde. Ningún número se escribe dos veces.
A7: 3. Sólo «Punto Equilibrio» se deriva entera de lo anterior. En las otras tres hojas también hay celdas verdes que puedes tocar: el escenario pesimista y el optimista en «Escenarios», la estacionalidad y la rampa de arranque en «Tesorería 12 meses», y las cuatro fuentes alternativas de financiación en «Financiación». Todo lo demás se calcula.
A8: 4. Todas las cifras van SIN IVA. Para pasar un PVP a precio sin IVA, divide entre 1,21: todo lo que factura la finca —espacio, servicios y canon— va al tipo general. El menú y la barra los factura el catering a los novios, al 10 % (art. 91.Uno.2.2.º de la Ley 37/1992), y no entran en este libro. El tipo de cada línea de venta está en la columna «Tipo de IVA de la línea» del P&L y de ahí salen los cobros, el IVA repercutido y el PVP equivalente. El IVA de la inversión se adelanta y se recupera con el modelo 303.
A9: 5. Si cambias la plantilla, el P&L la lee sola: el coste de personal sale de la hoja «Personal», no de una estimación aparte.
A10: 6. La hoja «Tesorería 12 meses» responde la pregunta que decide una operación bancaria: en qué mes se agota la caja. Su Mes 1 es MARZO: la finca abre en primavera y llega al primer invierno con la caja de la temporada. El saldo mínimo del año nunca puede salir en rojo. Las señales de los novios no se modelan: tu caja real será algo mejor.
A11: 7. La hoja «Financiación» cuadra lo que hace falta con lo que se aporta y monta el cuadro de amortización del préstamo. Si la diferencia sale en rojo, el plan no está financiado.
A12: 8. El documento Word de este pack usa las cifras de este Excel; la calculadora de presupuestos y los modelos de contrato usan los mismos porcentajes de cobro y de cancelación. Si cambias una celda verde, el Excel manda.
A14: RATIOS QUE AUDITA EL LIBRO
A15: Los umbrales viven en la columna «Umbral» del bloque RATIOS CLAVE del P&L: cámbialos ahí y el semáforo cambia con ellos.
A17: Ratio | B17: Valor del año 1 | C17: Umbral | D17: Estado
A18: Coste directo del evento / Ventas | B18: =IFERROR(IF('PyG 3 Años'!$B$53="","",'PyG 3 Años'!$B$53),"") -> 0.12714 | C18: =IFERROR(IF('PyG 3 Años'!$E$53="","",'PyG 3 Años'!$E$53),"") -> 0.14 | D18: =IFERROR(IF(OR(B18="",C18=""),"",IF(B18<=C18,"CUMPLE","REVISAR")),"") -> CUMPLE
A19: Coste de personal / Ventas | B19: =IFERROR(IF('PyG 3 Años'!$B$54="","",'PyG 3 Años'!$B$54),"") -> 0.30685564 | C19: =IFERROR(IF('PyG 3 Años'!$E$54="","",'PyG 3 Años'!$E$54),"") -> 0.33 | D19: =IFERROR(IF(OR(B19="",C19=""),"",IF(B19<=C19,"CUMPLE","REVISAR")),"") -> CUMPLE
A20: Renta de la finca / Ventas | B20: =IFERROR(IF('PyG 3 Años'!$B$55="","",'PyG 3 Años'!$B$55),"") -> 0.11535926 | C20: =IFERROR(IF('PyG 3 Años'!$E$55="","",'PyG 3 Años'!$E$55),"") -> 0.13 | D20: =IFERROR(IF(OR(B20="",C20=""),"",IF(B20<=C20,"CUMPLE","REVISAR")),"") -> CUMPLE
A21: Resultado neto / Ventas | B21: =IFERROR(IF('PyG 3 Años'!$B$56="","",'PyG 3 Años'!$B$56),"") -> 0.088171458 | C21: =IFERROR(IF('PyG 3 Años'!$E$56="","",'PyG 3 Años'!$E$56),"") -> 0.05 | D21: =IFERROR(IF(OR(B21="",C21=""),"",IF(B21>=C21,"CUMPLE","REVISAR")),"") -> CUMPLE
A22: Margen bruto / Ventas | B22: =IFERROR(IF('PyG 3 Años'!$B$51="","",'PyG 3 Años'!$B$51),"") -> 0.80486 | C22: =IFERROR(IF('PyG 3 Años'!$E$51="","",'PyG 3 Años'!$E$51),"") -> 0.75 | D22: =IFERROR(IF(OR(B22="",C22=""),"",IF(B22>=C22,"CUMPLE","REVISAR")),"") -> CUMPLE
A24: CIFRAS DE ESTE PLAN
A25: Inversión total (suma de los bloques) | B25: =IFERROR(IF('Inversión Inicial'!$B$31="","",'Inversión Inicial'!$B$31),"") -> 311408.75
A26: Necesidad total de caja al arranque | B26: =IFERROR(IF('Inversión Inicial'!$B$34="","",'Inversión Inicial'!$B$34),"") -> 360502.55
A27: Fondo de maniobra dotado | B27: =IFERROR(IF('Inversión Inicial'!$B$30="","",'Inversión Inicial'!$B$30),"") -> 59628.75
A28: Facturación prevista del año 1 | B28: =IFERROR(IF('PyG 3 Años'!$B$9="","",'PyG 3 Años'!$B$9),"") -> 364080
A29: Resultado neto del año 1 | B29: =IFERROR(IF('PyG 3 Años'!$B$48="","",'PyG 3 Años'!$B$48),"") -> 32101.464
A30: Invitados por evento para el punto de equilibrio CONTABLE (con la amortización dentro) | B30: =IFERROR(IF('Punto Equilibrio'!$B$15="","",'Punto Equilibrio'!$B$15),"") -> 71.431762
A31: Payback del proyecto (años), antes de la deuda | B31: =IFERROR(IF('Tesorería 12 meses'!$B$31="","",'Tesorería 12 meses'!$B$31),"") -> Más de 3 años
A33: DATOS DE REFERENCIA DEL SECTOR
A34: Referencia | B34: Valor | C34: Fuente | D34: Nota
A35: Mes 1 del plan | B35: Marzo | C35: Decisión del plan | D35: La licencia (de 6 a 12 meses o más) y la obra se cierran durante el invierno anterior, y se abre con las comuniones y la empresa de primavera. La fila de estacionalidad de la Tesorería ya va girada
A36: Mezcla de eventos del plan | B36: 120 eventos: 30 bodas, 35 de empresa, 40 celebraciones privadas y 15 pequeños | C36: Estimación del kit | D36: Bodas (30 × 120 invitados × 47 €), empresa (35 × 80 × 34 €), celebraciones privadas (40 × 70 × 29 €) y pequeños (15 × 40 × 30 €), sin IVA, de espacio, servicios y canon. Media: 82 invitados a 37 €
A37: Techo de fechas | B37: Unos 26 sábados de mayo a octubre | C37: Estimación del kit | D37: Las 30 bodas son unas 24 en sábados de temporada (el 80 %) y el resto en viernes, domingos o fuera de temporada. El libro no comprueba este techo: compruébalo tú en tu calendario
A38: Bodas en España en 2024 | B38: 175.364, el 83,6 % civiles | C38: INE, Movimiento Natural de la Población 2024 | D38: De mayo a octubre se celebra el 63,7 %; septiembre (13,1 %) y junio (12,8 %) son los picos y enero se queda en el 3,8 %
A39: Antelación de la reserva de una boda | B39: 12-18 meses (13 de media) | C39: Bodas.net, Informe del Sector Nupcial 2026 | D39: Por eso la primera temporada se reserva antes de abrir, condicionada a la licencia, y la rampa del plan dura 12 meses
A40: Coste directo por evento | B40: 650 € boda · 350 € empresa · 300 € celebración · 150 € pequeño | C40: Estimación del kit | D40: Limpieza tras el evento, reposición de aseos y consumibles, gasoil del grupo electrógeno, vigilancia y aparcamiento, y la tarifa de SGAE y AGEDI-AIE de cada evento
A41: Canon del catering exclusivo | B41: 12 % de lo que factura el catering en la finca | C41: Supuesto del kit, sin fuente pública | D41: Unos 13 € por invitado en una boda. Negócialo y pon el tuyo: en este plan, cada punto de canon son unos 6.700 € de ventas al año
A42: Personal de la finca en un evento | B42: Coordinación y 1 auxiliar (2 en las bodas) | C42: Estimación del kit | D42: Boda: 2 auxiliares × 13 h · empresa 1 × 9 h · celebración 1 × 8 h · pequeño 1 × 5 h. Camareros y cocina los pone el catering
A43: IVA de lo que factura la finca | B43: 21 % | C43: Ley 37/1992 del IVA | D43: El espacio y los servicios con precio propio y el canon que cobras al catering, al tipo general. El menú lo factura el catering a los novios, al 10 % (art. 91.Uno.2.2.º). Meter el espacio al 10 % dentro de un pack es arriesgado: confírmalo con tu asesoría o pide una consulta vinculante
A44: Plan de autoprotección | B44: Desde 1.000 personas en edificio cerrado o carpa · 5.000 al aire libre en recinto delimitado | C44: Orden INT/1068/2026, Directriz Básica de Autoprotección (BOE del 10-10-2026) | D44: Una finca de 300 invitados queda por debajo de la norma estatal; tu comunidad o tu ayuntamiento pueden pedir más, por ejemplo en un entorno forestal
A45: Ruido al exterior en zona residencial | B45: 55 dBA de día y de tarde · 45 dBA de noche | C45: RD 1367/2007, art. 24 y anexo III | D45: Limitador-registrador, baile final dentro y altavoces de espaldas a las viviendas. El horario de la música lo fijan tu comunidad y la ordenanza de tu ayuntamiento: compruébalo
... A48: Convenio colectivo de referencia | B48: Provincial de hostelería | C48: VI Acuerdo Laboral de ámbito Estatal para el sector de Hostelería, art. 4 | D48: Su lista nombra el catering, no el alquiler de espacios, y no es exhaustiva: es la referencia salarial prudente. Confírmalo con tu asesoría
A50: Para editar una celda que no esté en verde: Revisar → Desproteger hoja (no tiene contraseña).
A51: Más plantillas y kits del catálogo en aichef.pro/productos-digitales
A52: Diseñado por John Guerrero — chef y consultor gastronómico desde 2010, en cocina desde los 17 años · johnguerrero.es
A53: Versión 1.0 · noviembre 2026 · aichef.pro/plan-negocio-finca-eventos-bodas · info@aichef.pro

Sheet Tesorería 12 meses
A1: PREVISIÓN DE TESORERÍA — AÑO 1
A2: El P&L dice si el negocio gana dinero; esta hoja dice si le queda caja para llegar a fin de mes. Es la primera que mira un banco.
A4: Concepto | B4: Mes 1 (€) | C4: Mes 2 (€) | D4: Mes 3 (€) | E4: Mes 4 (€) | F4: Mes 5 (€) | G4: Mes 6 (€) | H4: Mes 7 (€) | I4: Mes 8 (€) | J4: Mes 9 (€) | K4: Mes 10 (€) | L4: Mes 11 (€) | M4: Mes 12 (€) | N4: Año (€)
A5: Estacionalidad del mes (suma 100 %) | B5: 0.063 | C5: 0.084 | D5: 0.124 | E5: 0.135 | F5: 0.078 | G5: 0.055 | H5: 0.122 | I5: 0.111 | J5: 0.073 | K5: 0.077 | L5: 0.031 | M5: 0.047 | N5: =IFERROR(IF('PyG 3 Años'!$B$9="","",SUM(B5:M5)),"") -> 1 | O5: Mes 1 = MARZO: la licencia (de 6 a 12 meses o más) y la obra se cierran durante el invierno anterior, y se abre con las comuniones y la empresa de primavera. Los picos son junio (Mes 4) y septiembre (Mes 7); el valle, enero (Mes 11). Si abres en otro mes, gira la fila. Tiene que sumar 100 %
A6: Rampa de arranque (% de la actividad de crucero) | B6: =IFERROR(IF('PyG 3 Años'!$B$9="","",MIN(1,'0. Supuestos'!$B$52+(1-'0. Supuestos'!$B$52)*0/MAX(1,'0. Supuestos'!$B$53-1))),"") -> 0.45 | C6: =IFERROR(IF('PyG 3 Años'!$B$9="","",MIN(1,'0. Supuestos'!$B$52+(1-'0. Supuestos'!$B$52)*1/MAX(1,'0. Supuestos'!$B$53-1))),"") -> 0.5 | D6: =IFERROR(IF('PyG 3 Años'!$B$9="","",MIN(1,'0. Supuestos'!$B$52+(1-'0. Supuestos'!$B$52)*2/MAX(1,'0. Supuestos'!$B$53-1))),"") -> 0.55 | E6: =IFERROR(IF('PyG 3 Años'!$B$9="","",MIN(1,'0. Supuestos'!$B$52+(1-'0. Supuestos'!$B$52)*3/MAX(1,'0. Supuestos'!$B$53-1))),"") -> 0.6 | F6: =IFERROR(IF('PyG 3 Años'!$B$9="","",MIN(1,'0. Supuestos'!$B$52+(1-'0. Supuestos'!$B$52)*4/MAX(1,'0. Supuestos'!$B$53-1))),"") -> 0.65 | G6: =IFERROR(IF('PyG 3 Años'!$B$9="","",MIN(1,'0. Supuestos'!$B$52+(1-'0. Supuestos'!$B$52)*5/MAX(1,'0. Supuestos'!$B$53-1))),"") -> 0.7 | H6: =IFERROR(IF('PyG 3 Años'!$B$9="","",MIN(1,'0. Supuestos'!$B$52+(1-'0. Supuestos'!$B$52)*6/MAX(1,'0. Supuestos'!$B$53-1))),"") -> 0.75 | I6: =IFERROR(IF('PyG 3 Años'!$B$9="","",MIN(1,'0. Supuestos'!$B$52+(1-'0. Supuestos'!$B$52)*7/MAX(1,'0. Supuestos'!$B$53-1))),"") -> 0.8 | J6: =IFERROR(IF('PyG 3 Años'!$B$9="","",MIN(1,'0. Supuestos'!$B$52+(1-'0. Supuestos'!$B$52)*8/MAX(1,'0. Supuestos'!$B$53-1))),"") -> 0.85 | K6: =IFERROR(IF('PyG 3 Años'!$B$9="","",MIN(1,'0. Supuestos'!$B$52+(1-'0. Supuestos'!$B$52)*9/MAX(1,'0. Supuestos'!$B$53-1))),"") -> 0.9 | L6: =IFERROR(IF('PyG 3 Años'!$B$9="","",MIN(1,'0. Supuestos'!$B$52+(1-'0. Supuestos'!$B$52)*10/MAX(1,'0. Supuestos'!$B$53-1))),"") -> 0.95 | M6: =IFERROR(IF('PyG 3 Años'!$B$9="","",MIN(1,'0. Supuestos'!$B$52+(1-'0. Supuestos'!$B$52)*11/MAX(1,'0. Supuestos'!$B$53-1))),"") -> 1 | O6: Sube en línea recta desde el porcentaje del mes 1 hasta el 100 % en los meses que digas en Supuestos. Con el mes 1 al 100 % la rampa desaparece
A7: Reparto de la actividad por mes (calculado) | B7: =IFERROR(IF('PyG 3 Años'!$B$9="","",B5*B6/SUMPRODUCT($B$5:$M$5,$B$6:$M$6)),"") -> 0.040683074 | C7: =IFERROR(IF('PyG 3 Años'!$B$9="","",C5*C6/SUMPRODUCT($B$5:$M$5,$B$6:$M$6)),"") -> 0.06027122 | D7: =IFERROR(IF('PyG 3 Años'!$B$9="","",D5*D6/SUMPRODUCT($B$5:$M$5,$B$6:$M$6)),"") -> 0.097868982 | E7: =IFERROR(IF('PyG 3 Años'!$B$9="","",E5*E6/SUMPRODUCT($B$5:$M$5,$B$6:$M$6)),"") -> 0.11623735 | F7: =IFERROR(IF('PyG 3 Años'!$B$9="","",F5*F6/SUMPRODUCT($B$5:$M$5,$B$6:$M$6)),"") -> 0.072755973 | G7: =IFERROR(IF('PyG 3 Años'!$B$9="","",G5*G6/SUMPRODUCT($B$5:$M$5,$B$6:$M$6)),"") -> 0.055248619 | H7: =IFERROR(IF('PyG 3 Años'!$B$9="","",H5*H6/SUMPRODUCT($B$5:$M$5,$B$6:$M$6)),"") -> 0.13130516 | I7: =IFERROR(IF('PyG 3 Años'!$B$9="","",I5*I6/SUMPRODUCT($B$5:$M$5,$B$6:$M$6)),"") -> 0.12743058 | ... M7: =IFERROR(IF('PyG 3 Años'!$B$9="","",M5*M6/SUMPRODUCT($B$5:$M$5,$B$6:$M$6)),"") -> 0.067446366 | N7: =IFERROR(IF('PyG 3 Años'!$B$9="","",SUM(B7:M7)),"") -> 1 | O7: Estacionalidad × rampa, normalizado a 100 %: el AÑO factura lo que dice el P&L, pero repartido como lo reparte una finca que acaba de abrir
A8: COBROS
A9: Ventas cobradas (con IVA repercutido) | B9: =IFERROR(IF('PyG 3 Años'!$B$9="","",('PyG 3 Años'!$B$9+'PyG 3 Años'!$B$9*SUMPRODUCT('PyG 3 Años'!$E$10:$E$11,'PyG 3 Años'!$G$10:$G$11))*B7*(1-MIN(30,'0. Supuestos'!$B$58)/30)),"") -> 11948.261 | C9: =IFERROR(IF('PyG 3 Años'!$B$9="","",('PyG 3 Años'!$B$9+'PyG 3 Años'!$B$9*SUMPRODUCT('PyG 3 Años'!$E$10:$E$11,'PyG 3 Años'!$G$10:$G$11))*(C7*(1-MIN(30,'0. Supuestos'!$B$58)/30)+B7*MIN(30,'0. Supuestos'!$B$58)/30)),"") -> 23675.257 | D9: =IFERROR(IF('PyG 3 Años'!$B$9="","",('PyG 3 Años'!$B$9+'PyG 3 Años'!$B$9*SUMPRODUCT('PyG 3 Años'!$E$10:$E$11,'PyG 3 Años'!$G$10:$G$11))*(D7*(1-MIN(30,'0. Supuestos'!$B$58)/30)+C7*MIN(30,'0. Supuestos'!$B$58)/30)),"") -> 37593.822 | E9: =IFERROR(IF('PyG 3 Años'!$B$9="","",('PyG 3 Años'!$B$9+'PyG 3 Años'!$B$9*SUMPRODUCT('PyG 3 Años'!$E$10:$E$11,'PyG 3 Años'!$G$10:$G$11))*(E7*(1-MIN(30,'0. Supuestos'!$B$58)/30)+D7*MIN(30,'0. Supuestos'!$B$58)/30)),"") -> 48509.517 | F9: =IFERROR(IF('PyG 3 Años'!$B$9="","",('PyG 3 Años'!$B$9+'PyG 3 Años'!$B$9*SUMPRODUCT('PyG 3 Años'!$E$10:$E$11,'PyG 3 Años'!$G$10:$G$11))*(F7*(1-MIN(30,'0. Supuestos'!$B$58)/30)+E7*MIN(30,'0. Supuestos'!$B$58)/30)),"") -> 38436.733 | G9: =IFERROR(IF('PyG 3 Años'!$B$9="","",('PyG 3 Años'!$B$9+'PyG 3 Años'!$B$9*SUMPRODUCT('PyG 3 Años'!$E$10:$E$11,'PyG 3 Años'!$G$10:$G$11))*(G7*(1-MIN(30,'0. Supuestos'!$B$58)/30)+F7*MIN(30,'0. Supuestos'!$B$58)/30)),"") -> 26909.928 | H9: =IFERROR(IF('PyG 3 Años'!$B$9="","",('PyG 3 Años'!$B$9+'PyG 3 Años'!$B$9*SUMPRODUCT('PyG 3 Años'!$E$10:$E$11,'PyG 3 Años'!$G$10:$G$11))*(H7*(1-MIN(30,'0. Supuestos'!$B$58)/30)+G7*MIN(30,'0. Supuestos'!$B$58)/30)),"") -> 46676.186 | I9: =IFERROR(IF('PyG 3 Años'!$B$9="","",('PyG 3 Años'!$B$9+'PyG 3 Años'!$B$9*SUMPRODUCT('PyG 3 Años'!$E$10:$E$11,'PyG 3 Años'!$G$10:$G$11))*(I7*(1-MIN(30,'0. Supuestos'!$B$58)/30)+H7*MIN(30,'0. Supuestos'!$B$58)/30)),"") -> 56706.825 | J9: =IFERROR(IF('PyG 3 Años'!$B$9="","",('PyG 3 Años'!$B$9+'PyG 3 Años'!$B$9*SUMPRODUCT('PyG 3 Años'!$E$10:$E$11,'PyG 3 Años'!$G$10:$G$11))*(J7*(1-MIN(30,'0. Supuestos'!$B$58)/30)+I7*MIN(30,'0. Supuestos'!$B$58)/30)),"") -> 44863.928 | ... M9: =IFERROR(IF('PyG 3 Años'!$B$9="","",('PyG 3 Años'!$B$9+'PyG 3 Años'!$B$9*SUMPRODUCT('PyG 3 Años'!$E$10:$E$11,'PyG 3 Años'!$G$10:$G$11))*(M7*(1-MIN(30,'0. Supuestos'!$B$58)/30)+L7*MIN(30,'0. Supuestos'!$B$58)/30)),"") -> 26014.335 | N9: =IFERROR(IF('PyG 3 Años'!$B$9="","",SUM(B9:M9)),"") -> 430632.6 | O9: Ventas del mes con el IVA repercutido, corregidas por los días medios de cobro de la hoja de Supuestos
A10: PAGOS
A11: Compras y costes variables (IVA incluido) | B11: =IFERROR(IF('PyG 3 Años'!$B$9="","",-('PyG 3 Años'!$B$13*(1+'PyG 3 Años'!$G$13)+'PyG 3 Años'!$B$14*(1+'PyG 3 Años'!$G$14)+'PyG 3 Años'!$B$15*(1+'PyG 3 Años'!$G$15)+'PyG 3 Años'!$B$16*(1+'PyG 3 Años'!$G$16)+'PyG 3 Años'!$B$17*(1+'PyG 3 Años'!$G$17)+'PyG 3 Años'!$B$18*(1+'PyG 3 Años'!$G$18))*B7*(1-MIN(30,'0. Supuestos'!$B$59)/30)),"") -> 0 | C11: =IFERROR(IF('PyG 3 Años'!$B$9="","",-('PyG 3 Años'!$B$13*(1+'PyG 3 Años'!$G$13)+'PyG 3 Años'!$B$14*(1+'PyG 3 Años'!$G$14)+'PyG 3 Años'!$B$15*(1+'PyG 3 Años'!$G$15)+'PyG 3 Años'!$B$16*(1+'PyG 3 Años'!$G$16)+'PyG 3 Años'!$B$17*(1+'PyG 3 Años'!$G$17)+'PyG 3 Años'!$B$18*(1+'PyG 3 Años'!$G$18))*(C7*(1-MIN(30,'0. Supuestos'!$B$59)/30)+B7*MIN(30,'0. Supuestos'!$B$59)/30)),"") -> -3488.0439 | D11: =IFERROR(IF('PyG 3 Años'!$B$9="","",-('PyG 3 Años'!$B$13*(1+'PyG 3 Años'!$G$13)+'PyG 3 Años'!$B$14*(1+'PyG 3 Años'!$G$14)+'PyG 3 Años'!$B$15*(1+'PyG 3 Años'!$G$15)+'PyG 3 Años'!$B$16*(1+'PyG 3 Años'!$G$16)+'PyG 3 Años'!$B$17*(1+'PyG 3 Años'!$G$17)+'PyG 3 Años'!$B$18*(1+'PyG 3 Años'!$G$18))*(D7*(1-MIN(30,'0. Supuestos'!$B$59)/30)+C7*MIN(30,'0. Supuestos'!$B$59)/30)),"") -> -5167.4725 | E11: =IFERROR(IF('PyG 3 Años'!$B$9="","",-('PyG 3 Años'!$B$13*(1+'PyG 3 Años'!$G$13)+'PyG 3 Años'!$B$14*(1+'PyG 3 Años'!$G$14)+'PyG 3 Años'!$B$15*(1+'PyG 3 Años'!$G$15)+'PyG 3 Años'!$B$16*(1+'PyG 3 Años'!$G$16)+'PyG 3 Años'!$B$17*(1+'PyG 3 Años'!$G$17)+'PyG 3 Años'!$B$18*(1+'PyG 3 Años'!$G$18))*(E7*(1-MIN(30,'0. Supuestos'!$B$59)/30)+D7*MIN(30,'0. Supuestos'!$B$59)/30)),"") -> -8390.991 | F11: =IFERROR(IF('PyG 3 Años'!$B$9="","",-('PyG 3 Años'!$B$13*(1+'PyG 3 Años'!$G$13)+'PyG 3 Años'!$B$14*(1+'PyG 3 Años'!$G$14)+'PyG 3 Años'!$B$15*(1+'PyG 3 Años'!$G$15)+'PyG 3 Años'!$B$16*(1+'PyG 3 Años'!$G$16)+'PyG 3 Años'!$B$17*(1+'PyG 3 Años'!$G$17)+'PyG 3 Años'!$B$18*(1+'PyG 3 Años'!$G$18))*(F7*(1-MIN(30,'0. Supuestos'!$B$59)/30)+E7*MIN(30,'0. Supuestos'!$B$59)/30)),"") -> -9965.8398 | G11: =IFERROR(IF('PyG 3 Años'!$B$9="","",-('PyG 3 Años'!$B$13*(1+'PyG 3 Años'!$G$13)+'PyG 3 Años'!$B$14*(1+'PyG 3 Años'!$G$14)+'PyG 3 Años'!$B$15*(1+'PyG 3 Años'!$G$15)+'PyG 3 Años'!$B$16*(1+'PyG 3 Años'!$G$16)+'PyG 3 Años'!$B$17*(1+'PyG 3 Años'!$G$17)+'PyG 3 Años'!$B$18*(1+'PyG 3 Años'!$G$18))*(G7*(1-MIN(30,'0. Supuestos'!$B$59)/30)+F7*MIN(30,'0. Supuestos'!$B$59)/30)),"") -> -6237.8775 | H11: =IFERROR(IF('PyG 3 Años'!$B$9="","",-('PyG 3 Años'!$B$13*(1+'PyG 3 Años'!$G$13)+'PyG 3 Años'!$B$14*(1+'PyG 3 Años'!$G$14)+'PyG 3 Años'!$B$15*(1+'PyG 3 Años'!$G$15)+'PyG 3 Años'!$B$16*(1+'PyG 3 Años'!$G$16)+'PyG 3 Años'!$B$17*(1+'PyG 3 Años'!$G$17)+'PyG 3 Años'!$B$18*(1+'PyG 3 Años'!$G$18))*(H7*(1-MIN(30,'0. Supuestos'!$B$59)/30)+G7*MIN(30,'0. Supuestos'!$B$59)/30)),"") -> -4736.8498 | I11: =IFERROR(IF('PyG 3 Años'!$B$9="","",-('PyG 3 Años'!$B$13*(1+'PyG 3 Años'!$G$13)+'PyG 3 Años'!$B$14*(1+'PyG 3 Años'!$G$14)+'PyG 3 Años'!$B$15*(1+'PyG 3 Años'!$G$15)+'PyG 3 Años'!$B$16*(1+'PyG 3 Años'!$G$16)+'PyG 3 Años'!$B$17*(1+'PyG 3 Años'!$G$17)+'PyG 3 Años'!$B$18*(1+'PyG 3 Años'!$G$18))*(I7*(1-MIN(30,'0. Supuestos'!$B$59)/30)+H7*MIN(30,'0. Supuestos'!$B$59)/30)),"") -> -11257.708 | J11: =IFERROR(IF('PyG 3 Años'!$B$9="","",-('PyG 3 Años'!$B$13*(1+'PyG 3 Años'!$G$13)+'PyG 3 Años'!$B$14*(1+'PyG 3 Años'!$G$14)+'PyG 3 Años'!$B$15*(1+'PyG 3 Años'!$G$15)+'PyG 3 Años'!$B$16*(1+'PyG 3 Años'!$G$16)+'PyG 3 Años'!$B$17*(1+'PyG 3 Años'!$G$17)+'PyG 3 Años'!$B$18*(1+'PyG 3 Años'!$G$18))*(J7*(1-MIN(30,'0. Supuestos'!$B$59)/30)+I7*MIN(30,'0. Supuestos'!$B$59)/30)),"") -> -10925.513 | ... M11: =IFERROR(IF('PyG 3 Años'!$B$9="","",-('PyG 3 Años'!$B$13*(1+'PyG 3 Años'!$G$13)+'PyG 3 Años'!$B$14*(1+'PyG 3 Años'!$G$14)+'PyG 3 Años'!$B$15*(1+'PyG 3 Años'!$G$15)+'PyG 3 Años'!$B$16*(1+'PyG 3 Años'!$G$16)+'PyG 3 Años'!$B$17*(1+'PyG 3 Años'!$G$17)+'PyG 3 Años'!$B$18*(1+'PyG 3 Años'!$G$18))*(M7*(1-MIN(30,'0. Supuestos'!$B$59)/30)+L7*MIN(30,'0. Supuestos'!$B$59)/30)),"") -> -3623.3825 | N11: =IFERROR(IF('PyG 3 Años'!$B$9="","",SUM(B11:M11)),"") -> -79954.333 | O11: =IFERROR("Coste directo del evento, consumibles, comisiones e imprevistos, cada uno con SU tipo de IVA (la columna del P&L) y con los días de pago a proveedor de Supuestos."&IF('0. Supuestos'!$B$59=0,""," Con "&TEXT('0. Supuestos'!$B$59,"0")&" días de pago, las primeras compras se pagan ya en el año siguiente: la columna «Año» de esta fila recoge "&TEXT(MAX(0,12-ROUNDUP('0. Supuestos'!$B$59/30,0)),"0")&" mensualidades de compra, no el coste del ejercicio."),"") -> Coste directo del evento, consumibles, comisiones e imprevistos, cada uno con SU tipo de IVA (la columna del P&L) y con los días de pago a proveedor de Supuestos. Con 30 días de pago, las primeras compras se pagan ya en el año siguiente: la columna «Año» de esta fila recoge 11 mensualidades de compra, no el coste del ejercicio.
A12: Costes fijos de explotación (IVA incluido) | B12: =IFERROR(IF('PyG 3 Años'!$B$9="","",-('PyG 3 Años'!$B$38-'PyG 3 Años'!$B$23-'PyG 3 Años'!$B$36-'PyG 3 Años'!$B$37+'PyG 3 Años'!$B$40)/12),"") -> -10965.167 | C12: =IFERROR(IF('PyG 3 Años'!$B$9="","",-('PyG 3 Años'!$B$38-'PyG 3 Años'!$B$23-'PyG 3 Años'!$B$36-'PyG 3 Años'!$B$37+'PyG 3 Años'!$B$40)/12),"") -> -10965.167 | D12: =IFERROR(IF('PyG 3 Años'!$B$9="","",-('PyG 3 Años'!$B$38-'PyG 3 Años'!$B$23-'PyG 3 Años'!$B$36-'PyG 3 Años'!$B$37+'PyG 3 Años'!$B$40)/12),"") -> -10965.167 | E12: =IFERROR(IF('PyG 3 Años'!$B$9="","",-('PyG 3 Años'!$B$38-'PyG 3 Años'!$B$23-'PyG 3 Años'!$B$36-'PyG 3 Años'!$B$37+'PyG 3 Años'!$B$40)/12),"") -> -10965.167 | F12: =IFERROR(IF('PyG 3 Años'!$B$9="","",-('PyG 3 Años'!$B$38-'PyG 3 Años'!$B$23-'PyG 3 Años'!$B$36-'PyG 3 Años'!$B$37+'PyG 3 Años'!$B$40)/12),"") -> -10965.167 | G12: =IFERROR(IF('PyG 3 Años'!$B$9="","",-('PyG 3 Años'!$B$38-'PyG 3 Años'!$B$23-'PyG 3 Años'!$B$36-'PyG 3 Años'!$B$37+'PyG 3 Años'!$B$40)/12),"") -> -10965.167 | H12: =IFERROR(IF('PyG 3 Años'!$B$9="","",-('PyG 3 Años'!$B$38-'PyG 3 Años'!$B$23-'PyG 3 Años'!$B$36-'PyG 3 Años'!$B$37+'PyG 3 Años'!$B$40)/12),"") -> -10965.167 | I12: =IFERROR(IF('PyG 3 Años'!$B$9="","",-('PyG 3 Años'!$B$38-'PyG 3 Años'!$B$23-'PyG 3 Años'!$B$36-'PyG 3 Años'!$B$37+'PyG 3 Años'!$B$40)/12),"") -> -10965.167 | ... M12: =IFERROR(IF('PyG 3 Años'!$B$9="","",-('PyG 3 Años'!$B$38-'PyG 3 Años'!$B$23-'PyG 3 Años'!$B$36-'PyG 3 Años'!$B$37+'PyG 3 Años'!$B$40)/12),"") -> -10965.167 | N12: =IFERROR(IF('PyG 3 Años'!$B$9="","",SUM(B12:M12)),"") -> -131582 | O12: Los fijos que salen de caja, cada uno con su tipo de IVA: los seguros están exentos y no llevan
A13: Nóminas y Seguridad Social | B13: =IFERROR(IF('PyG 3 Años'!$B$9="","",-'PyG 3 Años'!$B$23/MAX(12,'0. Supuestos'!$B$21)*(1+IF(1='0. Supuestos'!$B$60,(MAX(12,'0. Supuestos'!$B$21)-12)/2,0)+IF(1='0. Supuestos'!$B$61,(MAX(12,'0. Supuestos'!$B$21)-12)/2,0))),"") -> -7980 | C13: =IFERROR(IF('PyG 3 Años'!$B$9="","",-'PyG 3 Años'!$B$23/MAX(12,'0. Supuestos'!$B$21)*(1+IF(2='0. Supuestos'!$B$60,(MAX(12,'0. Supuestos'!$B$21)-12)/2,0)+IF(2='0. Supuestos'!$B$61,(MAX(12,'0. Supuestos'!$B$21)-12)/2,0))),"") -> -7980 | D13: =IFERROR(IF('PyG 3 Años'!$B$9="","",-'PyG 3 Años'!$B$23/MAX(12,'0. Supuestos'!$B$21)*(1+IF(3='0. Supuestos'!$B$60,(MAX(12,'0. Supuestos'!$B$21)-12)/2,0)+IF(3='0. Supuestos'!$B$61,(MAX(12,'0. Supuestos'!$B$21)-12)/2,0))),"") -> -7980 | E13: =IFERROR(IF('PyG 3 Años'!$B$9="","",-'PyG 3 Años'!$B$23/MAX(12,'0. Supuestos'!$B$21)*(1+IF(4='0. Supuestos'!$B$60,(MAX(12,'0. Supuestos'!$B$21)-12)/2,0)+IF(4='0. Supuestos'!$B$61,(MAX(12,'0. Supuestos'!$B$21)-12)/2,0))),"") -> -7980 | F13: =IFERROR(IF('PyG 3 Años'!$B$9="","",-'PyG 3 Años'!$B$23/MAX(12,'0. Supuestos'!$B$21)*(1+IF(5='0. Supuestos'!$B$60,(MAX(12,'0. Supuestos'!$B$21)-12)/2,0)+IF(5='0. Supuestos'!$B$61,(MAX(12,'0. Supuestos'!$B$21)-12)/2,0))),"") -> -15960 | G13: =IFERROR(IF('PyG 3 Años'!$B$9="","",-'PyG 3 Años'!$B$23/MAX(12,'0. Supuestos'!$B$21)*(1+IF(6='0. Supuestos'!$B$60,(MAX(12,'0. Supuestos'!$B$21)-12)/2,0)+IF(6='0. Supuestos'!$B$61,(MAX(12,'0. Supuestos'!$B$21)-12)/2,0))),"") -> -7980 | H13: =IFERROR(IF('PyG 3 Años'!$B$9="","",-'PyG 3 Años'!$B$23/MAX(12,'0. Supuestos'!$B$21)*(1+IF(7='0. Supuestos'!$B$60,(MAX(12,'0. Supuestos'!$B$21)-12)/2,0)+IF(7='0. Supuestos'!$B$61,(MAX(12,'0. Supuestos'!$B$21)-12)/2,0))),"") -> -7980 | I13: =IFERROR(IF('PyG 3 Años'!$B$9="","",-'PyG 3 Años'!$B$23/MAX(12,'0. Supuestos'!$B$21)*(1+IF(8='0. Supuestos'!$B$60,(MAX(12,'0. Supuestos'!$B$21)-12)/2,0)+IF(8='0. Supuestos'!$B$61,(MAX(12,'0. Supuestos'!$B$21)-12)/2,0))),"") -> -7980 | J13: =IFERROR(IF('PyG 3 Años'!$B$9="","",-'PyG 3 Años'!$B$23/MAX(12,'0. Supuestos'!$B$21)*(1+IF(9='0. Supuestos'!$B$60,(MAX(12,'0. Supuestos'!$B$21)-12)/2,0)+IF(9='0. Supuestos'!$B$61,(MAX(12,'0. Supuestos'!$B$21)-12)/2,0))),"") -> -7980 | K13: =IFERROR(IF('PyG 3 Años'!$B$9="","",-'PyG 3 Años'!$B$23/MAX(12,'0. Supuestos'!$B$21)*(1+IF(10='0. Supuestos'!$B$60,(MAX(12,'0. Supuestos'!$B$21)-12)/2,0)+IF(10='0. Supuestos'!$B$61,(MAX(12,'0. Supuestos'!$B$21)-12)/2,0))),"") -> -15960 | L13: =IFERROR(IF('PyG 3 Años'!$B$9="","",-'PyG 3 Años'!$B$23/MAX(12,'0. Supuestos'!$B$21)*(1+IF(11='0. Supuestos'!$B$60,(MAX(12,'0. Supuestos'!$B$21)-12)/2,0)+IF(11='0. Supuestos'!$B$61,(MAX(12,'0. Supuestos'!$B$21)-12)/2,0))),"") -> -7980 | M13: =IFERROR(IF('PyG 3 Años'!$B$9="","",-'PyG 3 Años'!$B$23/MAX(12,'0. Supuestos'!$B$21)*(1+IF(12='0. Supuestos'!$B$60,(MAX(12,'0. Supuestos'!$B$21)-12)/2,0)+IF(12='0. Supuestos'!$B$61,(MAX(12,'0. Supuestos'!$B$21)-12)/2,0))),"") -> -7980 | N13: =IFERROR(IF('PyG 3 Años'!$B$9="","",SUM(B13:M13)),"") -> -111720 | O13: Doce mensualidades más las pagas extra en los meses que digas en Supuestos. La suma del año es la misma que la del P&L. El personal se reparte en doce meses, pero la coordinación y los auxiliares fijos discontinuos sólo trabajan de marzo a noviembre: aquí la temporada sale más barata y el invierno más caro que en la realidad. A final de noviembre tu caja real será unos 9.000 € menor que la de esta hoja (tres mensualidades de esos dos puestos), y en febrero se iguala
A14: Intereses del préstamo | B14: =IFERROR(IF('PyG 3 Años'!$B$9="","",-'Financiación'!$B$44/12),"") -> -1424.5833 | C14: =IFERROR(IF('PyG 3 Años'!$B$9="","",-'Financiación'!$B$44/12),"") -> -1424.5833 | D14: =IFERROR(IF('PyG 3 Años'!$B$9="","",-'Financiación'!$B$44/12),"") -> -1424.5833 | E14: =IFERROR(IF('PyG 3 Años'!$B$9="","",-'Financiación'!$B$44/12),"") -> -1424.5833 | F14: =IFERROR(IF('PyG 3 Años'!$B$9="","",-'Financiación'!$B$44/12),"") -> -1424.5833 | G14: =IFERROR(IF('PyG 3 Años'!$B$9="","",-'Financiación'!$B$44/12),"") -> -1424.5833 | H14: =IFERROR(IF('PyG 3 Años'!$B$9="","",-'Financiación'!$B$44/12),"") -> -1424.5833 | I14: =IFERROR(IF('PyG 3 Años'!$B$9="","",-'Financiación'!$B$44/12),"") -> -1424.5833 | ... M14: =IFERROR(IF('PyG 3 Años'!$B$9="","",-'Financiación'!$B$44/12),"") -> -1424.5833 | N14: =IFERROR(IF('PyG 3 Años'!$B$9="","",SUM(B14:M14)),"") -> -17095
A15: Devolución de principal del préstamo | B15: =IFERROR(IF('PyG 3 Años'!$B$9="","",-'Financiación'!$B$45/12),"") -> 0 | C15: =IFERROR(IF('PyG 3 Años'!$B$9="","",-'Financiación'!$B$45/12),"") -> 0 | D15: =IFERROR(IF('PyG 3 Años'!$B$9="","",-'Financiación'!$B$45/12),"") -> 0 | E15: =IFERROR(IF('PyG 3 Años'!$B$9="","",-'Financiación'!$B$45/12),"") -> 0 | F15: =IFERROR(IF('PyG 3 Años'!$B$9="","",-'Financiación'!$B$45/12),"") -> 0 | G15: =IFERROR(IF('PyG 3 Años'!$B$9="","",-'Financiación'!$B$45/12),"") -> 0 | H15: =IFERROR(IF('PyG 3 Años'!$B$9="","",-'Financiación'!$B$45/12),"") -> 0 | I15: =IFERROR(IF('PyG 3 Años'!$B$9="","",-'Financiación'!$B$45/12),"") -> 0 | ... M15: =IFERROR(IF('PyG 3 Años'!$B$9="","",-'Financiación'!$B$45/12),"") -> 0 | N15: =IFERROR(IF('PyG 3 Años'!$B$9="","",SUM(B15:M15)),"") -> 0
A16: IVA repercutido del mes (memoria) | B16: =IFERROR(IF('PyG 3 Años'!$B$9="","",'PyG 3 Años'!$B$9*B7*SUMPRODUCT('PyG 3 Años'!$E$10:$E$11,'PyG 3 Años'!$G$10:$G$11)),"") -> 3110.4976 | C16: =IFERROR(IF('PyG 3 Años'!$B$9="","",'PyG 3 Años'!$B$9*C7*SUMPRODUCT('PyG 3 Años'!$E$10:$E$11,'PyG 3 Años'!$G$10:$G$11)),"") -> 4608.1447 | D16: =IFERROR(IF('PyG 3 Años'!$B$9="","",'PyG 3 Años'!$B$9*D7*SUMPRODUCT('PyG 3 Años'!$E$10:$E$11,'PyG 3 Años'!$G$10:$G$11)),"") -> 7482.7492 | E16: =IFERROR(IF('PyG 3 Años'!$B$9="","",'PyG 3 Años'!$B$9*E7*SUMPRODUCT('PyG 3 Años'!$E$10:$E$11,'PyG 3 Años'!$G$10:$G$11)),"") -> 8887.1361 | F16: =IFERROR(IF('PyG 3 Años'!$B$9="","",'PyG 3 Años'!$B$9*F7*SUMPRODUCT('PyG 3 Años'!$E$10:$E$11,'PyG 3 Años'!$G$10:$G$11)),"") -> 5562.6889 | G16: =IFERROR(IF('PyG 3 Años'!$B$9="","",'PyG 3 Años'!$B$9*G7*SUMPRODUCT('PyG 3 Años'!$E$10:$E$11,'PyG 3 Años'!$G$10:$G$11)),"") -> 4224.1326 | H16: =IFERROR(IF('PyG 3 Años'!$B$9="","",'PyG 3 Años'!$B$9*H7*SUMPRODUCT('PyG 3 Años'!$E$10:$E$11,'PyG 3 Años'!$G$10:$G$11)),"") -> 10039.172 | I16: =IFERROR(IF('PyG 3 Años'!$B$9="","",'PyG 3 Años'!$B$9*I7*SUMPRODUCT('PyG 3 Años'!$E$10:$E$11,'PyG 3 Años'!$G$10:$G$11)),"") -> 9742.9344 | ... M16: =IFERROR(IF('PyG 3 Años'!$B$9="","",'PyG 3 Años'!$B$9*M7*SUMPRODUCT('PyG 3 Años'!$E$10:$E$11,'PyG 3 Años'!$G$10:$G$11)),"") -> 5156.7333 | N16: =IFERROR(IF('PyG 3 Años'!$B$9="","",SUM(B16:M16)),"") -> 76456.8 | O16: Cada línea de venta a SU tipo, leído de la columna de IVA del P&L: el espacio, los servicios y el canon de la finca, al general (21 %). La finca no vende comida ni bebida: el menú y la barra los factura el catering, al 10 % (art. 91.Uno.2.2.º de la Ley 37/1992)
A17: IVA soportado del mes (memoria) | B17: =IFERROR(IF('PyG 3 Años'!$B$9="","",'PyG 3 Años'!$B$39*B7+'PyG 3 Años'!$B$40/12),"") -> 2421.151 | C17: =IFERROR(IF('PyG 3 Años'!$B$9="","",'PyG 3 Años'!$B$39*C7+'PyG 3 Años'!$B$40/12),"") -> 2708.9089 | D17: =IFERROR(IF('PyG 3 Años'!$B$9="","",'PyG 3 Años'!$B$39*D7+'PyG 3 Años'!$B$40/12),"") -> 3261.2354 | E17: =IFERROR(IF('PyG 3 Años'!$B$9="","",'PyG 3 Años'!$B$39*E7+'PyG 3 Años'!$B$40/12),"") -> 3531.0743 | F17: =IFERROR(IF('PyG 3 Años'!$B$9="","",'PyG 3 Años'!$B$39*F7+'PyG 3 Años'!$B$40/12),"") -> 2892.315 | G17: =IFERROR(IF('PyG 3 Años'!$B$9="","",'PyG 3 Años'!$B$39*G7+'PyG 3 Años'!$B$40/12),"") -> 2635.1248 | H17: =IFERROR(IF('PyG 3 Años'!$B$9="","",'PyG 3 Años'!$B$39*H7+'PyG 3 Años'!$B$40/12),"") -> 3752.4266 | I17: =IFERROR(IF('PyG 3 Años'!$B$9="","",'PyG 3 Años'!$B$39*I7+'PyG 3 Años'!$B$40/12),"") -> 3695.5074 | ... M17: =IFERROR(IF('PyG 3 Años'!$B$9="","",'PyG 3 Años'!$B$39*M7+'PyG 3 Años'!$B$40/12),"") -> 2814.3147 | N17: =IFERROR(IF('PyG 3 Años'!$B$9="","",SUM(B17:M17)),"") -> 36572.41 | O17: Cada partida a su tipo, leído de la columna de IVA del P&L: los seguros y las comisiones de los medios de pago están exentos
A18: IVA a compensar arrastrado (inversión incluida) | E18: =IFERROR(IF('PyG 3 Años'!$B$9="","",'Inversión Inicial'!$B$33),"") -> 49093.8 | H18: =IFERROR(IF('PyG 3 Años'!$B$9="","",MAX(0,-E19)),"") -> 42283.704 | K18: =IFERROR(IF('PyG 3 Años'!$B$9="","",MAX(0,-H19)),"") -> 32668.26 | O18: El IVA soportado de la INVERSIÓN entra aquí: se compensa contra el repercutido de los trimestres siguientes hasta agotarlo (modelo 303)
A19: Resultado de la liquidación trimestral | E19: =IFERROR(IF('PyG 3 Años'!$B$9="","",SUM(B16:D16)-SUM(B17:D17)-E18),"") -> -42283.704 | H19: =IFERROR(IF('PyG 3 Años'!$B$9="","",SUM(E16:G16)-SUM(E17:G17)-H18),"") -> -32668.26 | K19: =IFERROR(IF('PyG 3 Años'!$B$9="","",SUM(H16:J16)-SUM(H17:J17)-K18),"") -> -16657.689 | O19: Repercutido menos soportado del trimestre menos lo que venía arrastrado. En negativo NO se paga: se compensa en el trimestre siguiente
A20: Pago del IVA (modelo 303) | E20: =IFERROR(IF('PyG 3 Años'!$B$9="","",IF(E19<=0,"",-E19)),"") | H20: =IFERROR(IF('PyG 3 Años'!$B$9="","",IF(H19<=0,"",-H19)),"") | K20: =IFERROR(IF('PyG 3 Años'!$B$9="","",IF(K19<=0,"",-K19)),"") | N20: =IFERROR(IF('PyG 3 Años'!$B$9="","",SUM(B20:M20)),"") -> 0 | O20: Sólo sale caja cuando el resultado del trimestre es positivo. Los meses sin liquidación van en blanco, no a cero. La celda se pinta en ROJO cuando el pago del 303 se lleva más caja de la que queda ese mes
A21: FLUJO DEL MES | B21: =IFERROR(IF('PyG 3 Años'!$B$9="","",SUM(B9:B15)+IF(B20="",0,B20)),"") -> -8421.4892 | C21: =IFERROR(IF('PyG 3 Años'!$B$9="","",SUM(C9:C15)+IF(C20="",0,C20)),"") -> -182.53646 | D21: =IFERROR(IF('PyG 3 Años'!$B$9="","",SUM(D9:D15)+IF(D20="",0,D20)),"") -> 12056.6 | E21: =IFERROR(IF('PyG 3 Años'!$B$9="","",SUM(E9:E15)+IF(E20="",0,E20)),"") -> 19748.776 | F21: =IFERROR(IF('PyG 3 Años'!$B$9="","",SUM(F9:F15)+IF(F20="",0,F20)),"") -> 121.1433 | G21: =IFERROR(IF('PyG 3 Años'!$B$9="","",SUM(G9:G15)+IF(G20="",0,G20)),"") -> 302.30022 | H21: =IFERROR(IF('PyG 3 Años'!$B$9="","",SUM(H9:H15)+IF(H20="",0,H20)),"") -> 21569.587 | I21: =IFERROR(IF('PyG 3 Años'!$B$9="","",SUM(I9:I15)+IF(I20="",0,I20)),"") -> 25079.367 | ... M21: =IFERROR(IF('PyG 3 Años'!$B$9="","",SUM(M9:M15)+IF(M20="",0,M20)),"") -> 2021.2025 | N21: =IFERROR(IF('PyG 3 Años'!$B$9="","",SUM(B21:M21)),"") -> 90281.265
A22: SALDO ACUMULADO DE CAJA | B22: =IFERROR(IF('PyG 3 Años'!$B$9="","",'Inversión Inicial'!$B$30+B21),"") -> 51207.261 | C22: =IFERROR(IF('PyG 3 Años'!$B$9="","",B22+C21),"") -> 51024.724 | D22: =IFERROR(IF('PyG 3 Años'!$B$9="","",C22+D21),"") -> 63081.324 | E22: =IFERROR(IF('PyG 3 Años'!$B$9="","",D22+E21),"") -> 82830.1 | F22: =IFERROR(IF('PyG 3 Años'!$B$9="","",E22+F21),"") -> 82951.244 | G22: =IFERROR(IF('PyG 3 Años'!$B$9="","",F22+G21),"") -> 83253.544 | H22: =IFERROR(IF('PyG 3 Años'!$B$9="","",G22+H21),"") -> 104823.13 | I22: =IFERROR(IF('PyG 3 Años'!$B$9="","",H22+I21),"") -> 129902.5 | J22: =IFERROR(IF('PyG 3 Años'!$B$9="","",I22+J21),"") -> 143471.16 | ... M22: =IFERROR(IF('PyG 3 Años'!$B$9="","",L22+M21),"") -> 149910.01
A23: Saldo mínimo del año | B23: =IFERROR(IF('PyG 3 Años'!$B$9="","",IF(COUNT(B22:M22)=0,"",MIN(B22:M22))),"") -> 51024.724 | D23: Si es negativo, sube el fondo de maniobra o el préstamo: te quedas sin caja
A24: Mes en el que la caja toca fondo | B24: =IFERROR(IF('PyG 3 Años'!$B$9="","",IF(COUNT(B22:M22)=0,"",MATCH(MIN(B22:M22),B22:M22,0))),"") -> 2 | D24: Es la respuesta a la pregunta que decide una operación bancaria: en qué mes se agota la caja
A25: RETORNO DE LA INVERSIÓN
A26: Flujo de caja libre antes de la deuda, año 1 | B26: =IFERROR(IF('PyG 3 Años'!$B$9="","",'PyG 3 Años'!$B$48+'PyG 3 Años'!$B$36+'Financiación'!$B$44),"") -> 65948.464 | D26: Resultado neto más amortización (que no se paga) más los intereses de ese año: el principal no se resta porque este flujo es ANTES de la deuda. La MISMA base que los años 2 y 3, para que el payback compare peras con peras
A27: Flujo de caja libre antes de la deuda, año 2 | B27: =IFERROR(IF('PyG 3 Años'!$B$9="","",'PyG 3 Años'!$C$48+'PyG 3 Años'!$C$36+'Financiación'!$B$46),"") -> 80774.738 | D27: Resultado neto más amortización (que no se paga) más los intereses de ese año: el principal no se resta porque este flujo es ANTES de la deuda. Sin tabla mensual, es una estimación
A28: Flujo de caja libre antes de la deuda, año 3 | B28: =IFERROR(IF('PyG 3 Años'!$B$9="","",'PyG 3 Años'!$D$48+'PyG 3 Años'!$D$36+'Financiación'!$B$48),"") -> 82120.236 | D28: Resultado neto más amortización (que no se paga) más los intereses de ese año: el principal no se resta porque este flujo es ANTES de la deuda. Sin tabla mensual, es una estimación
A29: Informativo: flujo REAL de caja del año 1 (tabla mensual, antes de la deuda) | B29: =IFERROR(IF('PyG 3 Años'!$B$9="","",N21+'Financiación'!$B$44+'Financiación'!$B$45),"") -> 107376.26 | D29: La suma de los doce FLUJO DEL MES de arriba, devolviéndole los intereses y el principal que se pagaron ese año. NO es la que usa el payback: lleva dentro el IVA que todavía no se ha liquidado y el crédito del proveedor, dos cosas que hay que devolver y que los años 2 y 3 no tienen
A30: Inversión a recuperar (sin el IVA, que se recupera por el 303) | B30: =IFERROR(IF('PyG 3 Años'!$B$9="","",'Inversión Inicial'!$B$34-'Inversión Inicial'!$B$33),"") -> 311408.75 | D30: CAPEX más fondo de maniobra: la necesidad total de caja MENOS el IVA soportado de la inversión, que no se pierde (se recupera con el modelo 303 y esta misma hoja lo compensa trimestre a trimestre). El fondo de maniobra sí se recupera al cerrar, pero hasta entonces está inmovilizado
A31: Payback del proyecto (años), antes de la deuda | B31: =IFERROR(IF('PyG 3 Años'!$B$9="","",IF(B26>=B30,ROUND(B30/B26,1),IF(B26+B27>=B30,ROUND(1+(B30-B26)/B27,1),IF(B26+B27+B28>=B30,ROUND(2+(B30-B26-B27)/B28,1),"Más de 3 años")))),"") -> Más de 3 años | D31: Mide cuánto tarda el negocio en devolver la inversión con lo que genera ANTES de pagar al banco, con la MISMA base de flujo en los tres años; si puedes pagar la cuota lo dice el DSCR de la hoja de Financiación. El plan de negocio en Word cita esta cifra; si cambias una celda verde, manda este libro
A32: Payback sobre el CAPEX, sin fondo de maniobra (años) | B32: =IFERROR(IF('PyG 3 Años'!$B$9="","",IF(B26>='Inversión Inicial'!$B$32,ROUND('Inversión Inicial'!$B$32/B26,1),IF(B26+B27>='Inversión Inicial'!$B$32,ROUND(1+('Inversión Inicial'!$B$32-B26)/B27,1),IF(B26+B27+B28>='Inversión Inicial'!$B$32,ROUND(2+('Inversión Inicial'!$B$32-B26-B27)/B28,1),"Más de 3 años")))),"") -> Más de 3 años | D32: El mismo cálculo sobre lo que se COMPRA (obra, equipamiento, lanzamiento y constitución), sin el fondo de maniobra: ese dinero no se gasta, se inmoviliza y vuelve al cerrar el negocio. Informativo: el payback que se publica es el de arriba
A34: Los trimestres de esta hoja son de tres meses del plan (marzo-mayo, junio-agosto y septiembre-noviembre), no los naturales: con el Mes 1 en marzo, el modelo 303 se presenta en abril (por marzo), julio, octubre y enero (por octubre-diciembre, ya en el Mes 11). En el caso todos los trimestres salen a compensar y la finca no paga IVA en su primer año: el de la obra se descuenta de lo que repercutes, y tras el tercer trimestre del plan aún quedan unos 16.660 € por compensar. El Impuesto de Sociedades del año 1 se paga en julio del año 2. La cuota del préstamo se reparte en doce partes iguales siguiendo el cuadro ANUAL de la hoja de Financiación, y las nóminas en doce mensualidades más las dos pagas extra en su mes.

Sheet Financiación
A1: PLAN DE FINANCIACIÓN
A2: Qué hace falta, de dónde sale y cuánto cuesta devolverlo. Es la hoja que el banco pide junto con el P&L.
A4: Concepto | B4: Importe | C4: Notas
A5: ORIGEN DE FONDOS
A6: Recursos propios de los socios | B6: =IFERROR(IF('0. Supuestos'!$B$30="","",'0. Supuestos'!$B$30),"") -> 100000
A7: Préstamo bancario | B7: =IFERROR(IF('0. Supuestos'!$B$31="","",'0. Supuestos'!$B$31),"") -> 263000
A8: Línea ICO (avalada por el ICO, la concede tu banco) | B8: 0 | C8: Consulta las líneas del ejercicio en curso en ico.es
A9: Préstamo participativo ENISA | B9: 0 | C9: Para sociedades; sin garantías personales
A10: Business angels o socios inversores | B10: 0 | C10: Entra en el capital: diluye, no se devuelve
A11: Subvenciones autonómicas o locales | B11: 0 | C11: Suelen cobrarse DESPUÉS de justificar el gasto
A12: TOTAL ORIGEN DE FONDOS | B12: =IFERROR(IF(COUNT(B6:B11)=0,"",SUM(B6:B11)),"") -> 363000
A13: USOS
A14: Necesidad total de caja al arranque | B14: =IFERROR(IF('Inversión Inicial'!$B$34="","",'Inversión Inicial'!$B$34),"") -> 360502.55 | C14: Inversión más el IVA que hay que adelantar
A15: Diferencia (origen - usos) | B15: =IFERROR(B12-B14,"") -> 2497.45 | C15: En rojo (negativa) el plan NO está financiado. Muy por encima de cero tampoco es gratis: se pagan intereses por un dinero que no se usa
A16: Diferencia sobre los usos (%) | B16: =IFERROR(B15/B14,"") -> 0.0069276902 | C16: Ámbar por encima del margen que fijes: es deuda que pagas sin necesitarla
A17: Exceso de financiación admisible (%) | B17: 0.05 | C17: Un pequeño colchón sobre la necesidad es sano; un 20 % de más son intereses tirados
A18: Préstamo que ajustaría el origen a la necesidad | B18: =IFERROR(MAX(0,B14-B12+B7),"") -> 260502.55 | C18: Cópialo en «Préstamo bancario solicitado» de la hoja de Supuestos y la diferencia se pone a cero
A19: CONDICIONES DEL PRÉSTAMO
A20: Importe del principal | B20: =IFERROR(IF('0. Supuestos'!$B$31=0,"",'0. Supuestos'!$B$31),"") -> 263000
A21: Tipo de interés nominal anual | B21: =IFERROR(IF('0. Supuestos'!$B$32="","",'0. Supuestos'!$B$32),"") -> 0.065
A22: Plazo total (años) | B22: =IFERROR(IF('0. Supuestos'!$B$33="","",'0. Supuestos'!$B$33),"") -> 8
A23: Carencia de principal aplicada (años) | B23: =IFERROR(IF(OR('0. Supuestos'!$B$34="",'0. Supuestos'!$B$33=""),"",IF('0. Supuestos'!$B$34>='0. Supuestos'!$B$33,0,'0. Supuestos'!$B$34)),"") -> 1 | C23: Una carencia igual o mayor que el plazo no existe: la hoja la anula en origen
A24: Cuota anual durante la amortización | B24: =IFERROR(IF(B22-B23<=0,"",IF(B21=0,B20/(B22-B23),B20*B21/(1-(1+B21)^-(B22-B23)))),"") -> 47953.15 | C24: Sistema francés, anualidad algebraica. Con el tipo al 0 % es el principal entre los años de amortización: sin esa rama el cuadro se apagaba entero
A25: CUADRO DE AMORTIZACIÓN
A26: Año | B26: Capital pendiente | C26: Intereses | D26: Amortización de principal | E26: Cuota total | F26: Capital al cierre | G26: Flujo disponible para la deuda (después de impuestos; del año 4 en adelante, el del año 3 mantenido) | H26: DSCR del año
A27: 1 | B27: =IFERROR(IF(B20="","",B20),"") -> 263000 | C27: =IFERROR(IF(OR(1>B22,B27=""),"",B27*B21),"") -> 17095 | D27: =IFERROR(IF(OR(1>B22,B27=""),"",IF(1<=B23,0,MIN(B27,B24-C27))),"") -> 0 | E27: =IFERROR(IF(C27="","",C27+D27),"") -> 17095 | F27: =IFERROR(IF(D27="","",B27-D27),"") -> 263000 | G27: =IFERROR(IF(E27="","",'PyG 3 Años'!$B$41-'PyG 3 Años'!$B$46+'PyG 3 Años'!$B$36+'PyG 3 Años'!$B$37),"") -> 65948.464 | H27: =IFERROR(IF(OR(E27="",E27=0),"",G27/E27),"") -> 3.8577634
A28: 2 | B28: =IFERROR(IF(OR(2>B22,F27=""),"",F27),"") -> 263000 | C28: =IFERROR(IF(OR(2>B22,B28=""),"",B28*B21),"") -> 17095 | D28: =IFERROR(IF(OR(2>B22,B28=""),"",IF(2<=B23,0,MIN(B28,B24-C28))),"") -> 30858.15 | E28: =IFERROR(IF(C28="","",C28+D28),"") -> 47953.15 | F28: =IFERROR(IF(D28="","",B28-D28),"") -> 232141.85 | G28: =IFERROR(IF(E28="","",'PyG 3 Años'!$C$41-'PyG 3 Años'!$C$46+'PyG 3 Años'!$C$36+'PyG 3 Años'!$C$37),"") -> 80774.738 | H28: =IFERROR(IF(OR(E28="",E28=0),"",G28/E28),"") -> 1.6844511
A29: 3 | B29: =IFERROR(IF(OR(3>B22,F28=""),"",F28),"") -> 232141.85 | C29: =IFERROR(IF(OR(3>B22,B29=""),"",B29*B21),"") -> 15089.22 | D29: =IFERROR(IF(OR(3>B22,B29=""),"",IF(3<=B23,0,MIN(B29,B24-C29))),"") -> 32863.93 | E29: =IFERROR(IF(C29="","",C29+D29),"") -> 47953.15 | F29: =IFERROR(IF(D29="","",B29-D29),"") -> 199277.92 | G29: =IFERROR(IF(E29="","",'PyG 3 Años'!$D$41-'PyG 3 Años'!$D$46+'PyG 3 Años'!$D$36+'PyG 3 Años'!$D$37),"") -> 82120.236 | H29: =IFERROR(IF(OR(E29="",E29=0),"",G29/E29),"") -> 1.7125097
A30: 4 | B30: =IFERROR(IF(OR(4>B22,F29=""),"",F29),"") -> 199277.92 | C30: =IFERROR(IF(OR(4>B22,B30=""),"",B30*B21),"") -> 12953.065 | D30: =IFERROR(IF(OR(4>B22,B30=""),"",IF(4<=B23,0,MIN(B30,B24-C30))),"") -> 35000.085 | E30: =IFERROR(IF(C30="","",C30+D30),"") -> 47953.15 | F30: =IFERROR(IF(D30="","",B30-D30),"") -> 164277.83 | G30: =IFERROR(IF(E30="","",'PyG 3 Años'!$D$41-'PyG 3 Años'!$D$46+'PyG 3 Años'!$D$36+'PyG 3 Años'!$D$37),"") -> 82120.236 | H30: =IFERROR(IF(OR(E30="",E30=0),"",G30/E30),"") -> 1.7125097
A31: 5 | B31: =IFERROR(IF(OR(5>B22,F30=""),"",F30),"") -> 164277.83 | C31: =IFERROR(IF(OR(5>B22,B31=""),"",B31*B21),"") -> 10678.059 | D31: =IFERROR(IF(OR(5>B22,B31=""),"",IF(5<=B23,0,MIN(B31,B24-C31))),"") -> 37275.091 | E31: =IFERROR(IF(C31="","",C31+D31),"") -> 47953.15 | F31: =IFERROR(IF(D31="","",B31-D31),"") -> 127002.74 | G31: =IFERROR(IF(E31="","",'PyG 3 Años'!$D$41-'PyG 3 Años'!$D$46+'PyG 3 Años'!$D$36+'PyG 3 Años'!$D$37),"") -> 82120.236 | H31: =IFERROR(IF(OR(E31="",E31=0),"",G31/E31),"") -> 1.7125097
A32: 6 | B32: =IFERROR(IF(OR(6>B22,F31=""),"",F31),"") -> 127002.74 | C32: =IFERROR(IF(OR(6>B22,B32=""),"",B32*B21),"") -> 8255.1783 | D32: =IFERROR(IF(OR(6>B22,B32=""),"",IF(6<=B23,0,MIN(B32,B24-C32))),"") -> 39697.972 | E32: =IFERROR(IF(C32="","",C32+D32),"") -> 47953.15 | F32: =IFERROR(IF(D32="","",B32-D32),"") -> 87304.772 | G32: =IFERROR(IF(E32="","",'PyG 3 Años'!$D$41-'PyG 3 Años'!$D$46+'PyG 3 Años'!$D$36+'PyG 3 Años'!$D$37),"") -> 82120.236 | H32: =IFERROR(IF(OR(E32="",E32=0),"",G32/E32),"") -> 1.7125097
A33: 7 | B33: =IFERROR(IF(OR(7>B22,F32=""),"",F32),"") -> 87304.772 | C33: =IFERROR(IF(OR(7>B22,B33=""),"",B33*B21),"") -> 5674.8102 | D33: =IFERROR(IF(OR(7>B22,B33=""),"",IF(7<=B23,0,MIN(B33,B24-C33))),"") -> 42278.34 | E33: =IFERROR(IF(C33="","",C33+D33),"") -> 47953.15 | F33: =IFERROR(IF(D33="","",B33-D33),"") -> 45026.432 | G33: =IFERROR(IF(E33="","",'PyG 3 Años'!$D$41-'PyG 3 Años'!$D$46+'PyG 3 Años'!$D$36+'PyG 3 Años'!$D$37),"") -> 82120.236 | H33: =IFERROR(IF(OR(E33="",E33=0),"",G33/E33),"") -> 1.7125097
A34: 8 | B34: =IFERROR(IF(OR(8>B22,F33=""),"",F33),"") -> 45026.432 | C34: =IFERROR(IF(OR(8>B22,B34=""),"",B34*B21),"") -> 2926.7181 | D34: =IFERROR(IF(OR(8>B22,B34=""),"",IF(8<=B23,0,MIN(B34,B24-C34))),"") -> 45026.432 | E34: =IFERROR(IF(C34="","",C34+D34),"") -> 47953.15 | F34: =IFERROR(IF(D34="","",B34-D34),"") -> 0 | G34: =IFERROR(IF(E34="","",'PyG 3 Años'!$D$41-'PyG 3 Años'!$D$46+'PyG 3 Años'!$D$36+'PyG 3 Años'!$D$37),"") -> 82120.236 | H34: =IFERROR(IF(OR(E34="",E34=0),"",G34/E34),"") -> 1.7125097
A35: 9 | B35: =IFERROR(IF(OR(9>B22,F34=""),"",F34),"") | C35: =IFERROR(IF(OR(9>B22,B35=""),"",B35*B21),"") | D35: =IFERROR(IF(OR(9>B22,B35=""),"",IF(9<=B23,0,MIN(B35,B24-C35))),"") | E35: =IFERROR(IF(C35="","",C35+D35),"") | F35: =IFERROR(IF(D35="","",B35-D35),"") | G35: =IFERROR(IF(E35="","",'PyG 3 Años'!$D$41-'PyG 3 Años'!$D$46+'PyG 3 Años'!$D$36+'PyG 3 Años'!$D$37),"") | H35: =IFERROR(IF(OR(E35="",E35=0),"",G35/E35),"")
A36: 10 | B36: =IFERROR(IF(OR(10>B22,F35=""),"",F35),"") | C36: =IFERROR(IF(OR(10>B22,B36=""),"",B36*B21),"") | D36: =IFERROR(IF(OR(10>B22,B36=""),"",IF(10<=B23,0,MIN(B36,B24-C36))),"") | E36: =IFERROR(IF(C36="","",C36+D36),"") | F36: =IFERROR(IF(D36="","",B36-D36),"") | G36: =IFERROR(IF(E36="","",'PyG 3 Años'!$D$41-'PyG 3 Años'!$D$46+'PyG 3 Años'!$D$36+'PyG 3 Años'!$D$37),"") | H36: =IFERROR(IF(OR(E36="",E36=0),"",G36/E36),"")
A37: 11 | B37: =IFERROR(IF(OR(11>B22,F36=""),"",F36),"") | C37: =IFERROR(IF(OR(11>B22,B37=""),"",B37*B21),"") | D37: =IFERROR(IF(OR(11>B22,B37=""),"",IF(11<=B23,0,MIN(B37,B24-C37))),"") | E37: =IFERROR(IF(C37="","",C37+D37),"") | F37: =IFERROR(IF(D37="","",B37-D37),"") | G37: =IFERROR(IF(E37="","",'PyG 3 Años'!$D$41-'PyG 3 Años'!$D$46+'PyG 3 Años'!$D$36+'PyG 3 Años'!$D$37),"") | H37: =IFERROR(IF(OR(E37="",E37=0),"",G37/E37),"")
A38: 12 | B38: =IFERROR(IF(OR(12>B22,F37=""),"",F37),"") | C38: =IFERROR(IF(OR(12>B22,B38=""),"",B38*B21),"") | D38: =IFERROR(IF(OR(12>B22,B38=""),"",IF(12<=B23,0,MIN(B38,B24-C38))),"") | E38: =IFERROR(IF(C38="","",C38+D38),"") | F38: =IFERROR(IF(D38="","",B38-D38),"") | G38: =IFERROR(IF(E38="","",'PyG 3 Años'!$D$41-'PyG 3 Años'!$D$46+'PyG 3 Años'!$D$36+'PyG 3 Años'!$D$37),"") | H38: =IFERROR(IF(OR(E38="",E38=0),"",G38/E38),"")
A39: 13 | B39: =IFERROR(IF(OR(13>B22,F38=""),"",F38),"") | C39: =IFERROR(IF(OR(13>B22,B39=""),"",B39*B21),"") | D39: =IFERROR(IF(OR(13>B22,B39=""),"",IF(13<=B23,0,MIN(B39,B24-C39))),"") | E39: =IFERROR(IF(C39="","",C39+D39),"") | F39: =IFERROR(IF(D39="","",B39-D39),"") | G39: =IFERROR(IF(E39="","",'PyG 3 Años'!$D$41-'PyG 3 Años'!$D$46+'PyG 3 Años'!$D$36+'PyG 3 Años'!$D$37),"") | H39: =IFERROR(IF(OR(E39="",E39=0),"",G39/E39),"")
A40: 14 | B40: =IFERROR(IF(OR(14>B22,F39=""),"",F39),"") | C40: =IFERROR(IF(OR(14>B22,B40=""),"",B40*B21),"") | D40: =IFERROR(IF(OR(14>B22,B40=""),"",IF(14<=B23,0,MIN(B40,B24-C40))),"") | E40: =IFERROR(IF(C40="","",C40+D40),"") | F40: =IFERROR(IF(D40="","",B40-D40),"") | G40: =IFERROR(IF(E40="","",'PyG 3 Años'!$D$41-'PyG 3 Años'!$D$46+'PyG 3 Años'!$D$36+'PyG 3 Años'!$D$37),"") | H40: =IFERROR(IF(OR(E40="",E40=0),"",G40/E40),"")
A41: 15 | B41: =IFERROR(IF(OR(15>B22,F40=""),"",F40),"") | C41: =IFERROR(IF(OR(15>B22,B41=""),"",B41*B21),"") | D41: =IFERROR(IF(OR(15>B22,B41=""),"",IF(15<=B23,0,MIN(B41,B24-C41))),"") | E41: =IFERROR(IF(C41="","",C41+D41),"") | F41: =IFERROR(IF(D41="","",B41-D41),"") | G41: =IFERROR(IF(E41="","",'PyG 3 Años'!$D$41-'PyG 3 Años'!$D$46+'PyG 3 Años'!$D$36+'PyG 3 Años'!$D$37),"") | H41: =IFERROR(IF(OR(E41="",E41=0),"",G41/E41),"")
A42: Tolerancia de cierre del cuadro (€) | B42: 0.01 | C42: Margen por redondeo. Por encima, el cuadro no cierra y hay capital sin devolver
A43: Capital pendiente al vencimiento | B43: =IFERROR(IF(B20="","",ROUND(B20-SUM(D27:D41),2)),"") -> 0 | C43: Tiene que ser cero: el principal devuelto en el cuadro tiene que ser el prestado. Si sale positivo, el plazo no llega
A44: Intereses del año 1 | B44: =IFERROR(IF(B20="","",IF(C27="",0,C27)),"") -> 17095
A45: Devolución de principal del año 1 | B45: =IFERROR(IF(B20="","",IF(D27="",0,D27)),"") -> 0
A46: Intereses del año 2 | B46: =IFERROR(IF(B20="","",IF(C28="",0,C28)),"") -> 17095
A47: Devolución de principal del año 2 | B47: =IFERROR(IF(B20="","",IF(D28="",0,D28)),"") -> 30858.15
A48: Intereses del año 3 | B48: =IFERROR(IF(B20="","",IF(C29="",0,C29)),"") -> 15089.22
A49: Devolución de principal del año 3 | B49: =IFERROR(IF(B20="","",IF(D29="",0,D29)),"") -> 32863.93
A50: COBERTURA DEL SERVICIO DE LA DEUDA (DSCR)
A51: DSCR del año 1 | B51: =IFERROR(('PyG 3 Años'!$B$41-'PyG 3 Años'!$B$46+'PyG 3 Años'!$B$36+B44)/(B44+B45),"") -> 3.8577634 | C51: Año de CARENCIA si la hay: con sólo intereses en el denominador el ratio se dispara y no mide el negocio
A52: DSCR del año 2 | B52: =IFERROR(('PyG 3 Años'!$C$41-'PyG 3 Años'!$C$46+'PyG 3 Años'!$C$36+B46)/(B46+B47),"") -> 1.6844511
A53: DSCR del año 3 | B53: =IFERROR(('PyG 3 Años'!$D$41-'PyG 3 Años'!$D$46+'PyG 3 Años'!$D$36+B48)/(B48+B49),"") -> 1.7125097
A54: DSCR mínimo de todo el cuadro | B54: =IFERROR(IF(COUNT(H27:H41)=0,"",MIN(H27:H41)),"") -> 1.6844511 | C54: El peor año de los que dura el préstamo, no el mejor de los tres que proyecta el P&L. Es el número que decide una operación. Ojo al alcance: los años 1 a 3 salen del P&L y del año 4 en adelante el cuadro MANTIENE el flujo del año 3, así que el mínimo de esos años es una proyección sostenida, no un año calculado. El flujo va después de impuestos
A56: El DSCR se calcula ANTES de la deuda y DESPUÉS de impuestos: al resultado antes de impuestos se le resta el Impuesto de Sociedades y se le devuelven la amortización contable y los intereses; el resultado se divide entre lo que hay que pagar ese año. Por debajo del mínimo de la hoja de Supuestos, el negocio no genera para pagar el préstamo. En el cuadro, el flujo de caja disponible de los años 4 en adelante se mantiene en el del año 3: el P&L sólo proyecta tres, y aquí no se inventa un crecimiento que no está calculado.
