Workbook

Sheet 0. Supuestos
A1: SUPUESTOS — aquí se teclean las TASAS y los DRIVERS del modelo
A2: Cambia las celdas VERDES: el resto del libro se recalcula solo. Las partidas de gasto se teclean en su hoja (también en verde) y no se repiten aquí.
A3: ACTIVIDAD
A4: Comensales/día (media del año 1) | B4: 77 | C4: Comensales equivalentes al día, media del año: unos 57 en sala (la terraza incluida de abril a octubre) y unos 20 de para llevar y domicilio, que son los pedidos (unos 15 al día de unos 20,50 € sin IVA) divididos por el ticket. Un sábado, unos 125 con los pedidos; un martes, unos 55. Contrástalo con el paso de gente de tu calle un viernes por la noche y un martes a mediodía
A5: Ticket medio SIN IVA (€) | B5: 15.5 | C5: SIN IVA, por comensal: una orden de 3 tacos (8,50 € con IVA), medio taco suelto, algo de gringa o quesadilla, algún entrante, 1,1 bebidas y algún postre suman unos 17,40 € con IVA en sala; el caso se queda en 15,50 € sin IVA por los combos de mediodía. El taco al pastor del caso cuesta 3,00 € con IVA, dentro de la franja de 2,50-3,50 € de las taquerías casuales de ciudad (cartas leídas en octubre de 2026). El precio con IVA está en la fila «PVP equivalente con IVA» de abajo
A6: Días de apertura al año | B6: 300 | C6: 365 días menos los 52 lunes de cierre, 12 días de cierre en enero (mantenimiento y vacaciones) y el 25 de diciembre. Es el MISMO dato para la cuenta de resultados, el punto de equilibrio, los escenarios y las horas de personal
A7: Crecimiento de volumen del año 2 | B7: 0.06 | C7: Clientela que repite y más pedidos para llevar el segundo año. Se aplica a los comensales con el mismo ticket; el personal NO sube con este porcentaje: sale de la hoja Personal
A8: Crecimiento de volumen del año 3 | B8: 0.04 | C8: Sobre el año 2. Conservador: el techo lo ponen el trompo, la plancha y las 32 plazas los viernes y los sábados por la noche
A9: PVP equivalente con IVA (calculado) | B9: =IFERROR(IF($B$5="","",$B$5*(1+SUMPRODUCT('PyG 3 Años'!$E$10:$E$11,'PyG 3 Años'!$G$10:$G$11))),"") -> 17.075575 | C9: =IFERROR("Ticket sin IVA más el IVA medio ponderado de tus líneas de venta: "&TEXT(SUMPRODUCT('PyG 3 Años'!$E$10:$E$11,'PyG 3 Años'!$G$10:$G$11)*100,"0")&" %. En sala todo va al 10 % (art. 91.Uno.2.2.º de la Ley 37/1992, alcohol incluido); la bebida que sale para llevar o a domicilio (columna H de su línea en el P&L) mueve la media. Aquí va redondeado. Compáralo con el rango del sector, que va con IVA.","") -> Ticket sin IVA más el IVA medio ponderado de tus líneas de venta: 10 %. En sala todo va al 10 % (art. 91.Uno.2.2.º de la Ley 37/1992, alcohol incluido); la bebida que sale para llevar o a domicilio (columna H de su línea en el P&L) mueve la media. Aquí va redondeado. Compáralo con el rango del sector, que va con IVA.
A10: MIX Y COSTE DE MERCANCÍA
A11: Ventas de COMIDA sobre el total | B11: 0.8 | C11: Peso de la COMIDA sobre el total de ventas. Es un INPUT: cámbialo aquí y el P&L, la tesorería y el IVA repercutido se recalculan solos
A12: Ventas de BEBIDA sobre el total | B12: =IFERROR(IF(COUNT(B11)=0,"",1-B11),"") -> 0.2 | C12: Se calcula como el resto: comida + bebida = 100 %
A13: Coste de mercancía sobre las ventas de COMIDA | B13: 0.27 | C13: Materia prima de la comida sobre sus ventas: el taco al pastor sale a un 22,5 % (un 24 % en la orden de 3), las carnitas, el suadero y la barbacoa a un 26-30 %, la gringa a un 23 % y el guacamole a un 22-28 % según el aguacate: un 25 % de media, más 1,5 puntos de merma (el sobrante del trompo y las salsas crudas que se tiran) y medio punto de prudencia, porque la carne y la tortilla son precios estimados por el kit. Escandalla cada taco con la calculadora del pack
A14: Coste de mercancía sobre las ventas de BEBIDA | B14: 0.26 | C14: Aguas frescas al 12 %, cerveza mexicana al 33 %, mezcal y tequila al 28 % y refrescos y agua al 30 % de su precio de venta, en una mezcla de 30/45/10/15. Si la cervecera te cede el equipo de tiraje, pide el precio del barril por escrito
A15: Consumibles sobre ventas | B15: 0.035 | C15: Envases para llevar y a domicilio, tarrinas de salsa, papel, servilletas, guantes y los envases para que el cliente se lleve lo que no consuma (Ley 1/2025, art. 8). El envase de plástico de un solo uso se cobra aparte en el tique (Ley 7/2022, art. 55)
A16: Ventas por delivery sobre el total | B16: 0.12 | C16: Ventas por PLATAFORMA con su reparto (Glovo, Just Eat, Uber Eats) sobre el total. Lo que se recoge en el local NO paga comisión y no va aquí. La tortilla llega peor tras el viaje: la orden «para armar» lo aguanta, pero no subas de aquí sin probarlo
A17: Comisión de la plataforma de delivery | B17: 0.3 | C17: Comisión de la plataforma con su reparto sobre lo que vende ese canal: el plan básico de Uber Eats ronda el 30 % más IVA, Glovo va del 15 al 35 % según la zona y Just Eat, del 25 al 35 % con su reparto. Compruébala en tu contrato. Si repartes tú, pon 0 y suma el repartidor, con contrato laboral, a la hoja Personal
A18: Comisión de los medios de pago | B18: 0.008 | C18: Tarjeta y bizum sobre el total facturado
A19: PERSONAL
A20: Seguridad Social a cargo de la empresa | B20: 0.33 | C20: Contingencias comunes + AT/EP + desempleo + FOGASA + FP; ajusta a tu convenio y bonificaciones
A21: Número de pagas anuales | B21: 14 | C21: Salario bruto anual = bruto mensual × pagas
A22: SMI anual de referencia (€) | B22: 17094 | C22: SMI 2026: 17.094 € al año (1.221 €/mes en 14 pagas), suelo legal por jornada completa. Comprueba el importe vigente si presentas el plan en otro ejercicio
A23: LOCAL Y FIJOS
A24: Alquiler mensual del local (€) | B24: 1450 | C24: Local de 80 m² con salida de humos a cubierta posible (es el filtro del local): sala de 45 m² con 24 plazas en mesa y 8 en barra, cocina de 20 m² a la vista con el trompo, la plancha y el comal, aseos (uno adaptado) y almacén, en una calle con paso cerca de una zona universitaria o de ocio de una ciudad media, sin traspaso: unos 18 € el m². El peso sobre las ventas lo calcula el propio libro en la fila «Alquiler / Ventas» del P&L
A25: Fianza del alquiler (meses) | B25: 2 | C25: Dos meses de renta, lo habitual en un contrato de local de negocio: compruébalo con tu abogado
A26: Suministros mensuales de luz, agua y gas (€) | B26: 850 | C26: Luz (frío, extracción, climatización y cafetera), el gas del trompo, la plancha, el comal y los fogones, y el agua. Pide el histórico del local
A27: Seguros (€/año) | B27: 1400 | C27: Responsabilidad civil de al menos 300.000 € y multirriesgo con incendio y avería del frío. Dile a la aseguradora que trabajas con trompo, plancha y freidora a gas: cambia la prima y las condiciones
A28: Varios e imprevistos sobre ventas | B28: 0.02 | C28: Colchón de gasto corriente no presupuestado (pequeñas reparaciones, utillaje que se rompe, pruebas de carta)
A29: FINANCIACIÓN
A30: Recursos propios aportados (€) | B30: 55000 | C30: Aportación de los socios. Un banco pide entre el 25 y el 30 % de la necesidad de caja con dinero propio
A31: Préstamo bancario solicitado (€) | B31: 118000 | C31: Principal solicitado. La hoja de Financiación compara lo que aportas con la necesidad de caja de la hoja de inversión y te dice si sobra o falta: ajústalo con ese dato
A32: Tipo de interés nominal anual | B32: 0.06 | C32: Tipo nominal anual. Pide oferta a dos entidades y a una línea ICO antes de fijarlo; el frío y el equipo de cocina se pueden pagar con leasing o renting: compáralo
A33: Plazo del préstamo (años) | B33: 7 | C33: Años totales, carencia incluida
A34: Carencia de principal (años) | B34: 1 | C34: El primer año sólo intereses: obra, conducto de humos y cocina antes de facturar. Desde el segundo año se devuelve el principal: mira la holgura de caja de ese año en el Punto de Equilibrio
A35: Fondo de maniobra (meses de costes fijos) | B35: 3 | C35: Tres meses de costes fijos: el colchón para la rampa del arranque, que con el Mes 1 en enero cae sobre los meses más flojos del año (enero y febrero)
A36: FISCAL
A37: Impuesto de Sociedades, nueva creación | B37: 0.15 | C37: Art. 29.1 LIS: el PRIMER ejercicio con base imponible positiva y el SIGUIENTE. El libro lo aproxima contando los dos primeros ejercicios con base positiva: coincide con la ley salvo que entre ellos haya un ejercicio en pérdidas
A38: Impuesto de Sociedades, tipo general | B38: 0.25 | C38: A partir del tercer ejercicio con base positiva. Es el tipo general del art. 29.1 LIS: si tu cifra de negocios queda por debajo de 1 M € (microempresa) o de 10 M € (reducida dimensión), desde 2025 hay tipos más bajos que se implantan de forma gradual; confirma el de tu ejercicio con tu asesor y cámbialo aquí
A39: IVA repercutido de restauración | B39: 0.1 | C39: Tipo reducido de hostelería
A40: IVA repercutido/soportado general | B40: 0.21 | C40: Tipo general. En este libro lo usan dos cosas: el IVA que soportas al comprar el alcohol (el proveedor lo factura al 21 %) y el que repercutes por la bebida que sale para llevar o a domicilio (es una entrega de bienes). El alcohol servido en sala va al reducido, como fija la línea de bebida del P&L. Suministros, equipamiento y servicios tienen su tipo en la celda de abajo. En las compras, el libro manda al general la parte de la bebida que declara la celda «Bebida que compras al 21 %» de esta hoja: la cerveza, el mezcal, el tequila y los refrescos con azúcares o edulcorantes añadidos, cuya factura va al 21 % (art. 91.Uno.1.1.º de la Ley 37/1992)
A41: IVA soportado en compras e inversión | B41: 0.21 | C41: Recuperable vía modelo 303, pero hay que adelantarlo
A42: Bases negativas de ejercicios anteriores (€) | B42: 0 | C42: Pérdidas pendientes de compensar al empezar (art. 26 LIS)
A43: AMORTIZACIÓN
A44: Vida útil de obra e instalaciones (años) | B44: 10 | C44: Obra, conducto de extracción hasta cubierta, instalación eléctrica, fontanería, gas, climatización, rótulo y fachada. Coeficientes de la tabla del art. 12.1 de la Ley del Impuesto sobre Sociedades: confírmalo con tu asesor
A45: Vida útil de maquinaria y mobiliario (años) | B45: 10 | C45: Trompo, plancha y comal, freidora, campana extractora, frío, lavavajillas, barra, mobiliario y TPV: un 10 % anual, dentro del coeficiente máximo de la tabla del art. 12.1 de la Ley del Impuesto sobre Sociedades para la maquinaria (12 %) y para el mobiliario (10 %). Confírmalo con tu asesor
A47: CRECIMIENTO Y ACTUALIZACIÓN DE COSTES
A48: Subida anual de los costes fijos | B48: 0 | C48: A CERO: las tres columnas están en euros del año 1 (términos reales). Súbela si quieres proyectar en euros corrientes
A49: ARRANQUE Y AFORO
A50: Rotaciones al día implícitas (calculado) | B50: =IFERROR($B$4/$B$51,"") -> 2.40625 | C50: =IFERROR("Son "&TEXT(INT(ROUND(B50,1)),"0")&","&TEXT(ROUND(MOD(ROUND(B50,1),1)*10,0),"0")&" servicios por plaza y día sobre las "&TEXT($B$51,"0")&" plazas de la celda de arriba. Incluye a quien se lleva los tacos o los recibe en casa, que no ocupa mesa: la rotación real de tu sala es menor (en el caso, unos 57 comensales de sala, 1,8 por plaza y día).","") -> Son 2,4 servicios por plaza y día sobre las 32 plazas de la celda de arriba. Incluye a quien se lleva los tacos o los recibe en casa, que no ocupa mesa: la rotación real de tu sala es menor (en el caso, unos 57 comensales de sala, 1,8 por plaza y día).
A51: Aforo del local (plazas sentadas, sin la terraza) | B51: 32 | C51: Plazas interiores: 24 en mesa y 8 en barra. La terraza suma 16 plazas de abril a octubre, con su autorización municipal aparte, y quien se lleva los tacos o los recibe en casa no ocupa mesa: por eso la rotación de la fila de arriba es más alta que la real de tu sala
A52: Actividad del mes 1 sobre la de crucero | B52: 0.75 | C52: Una taquería que abre trae curiosos el primer mes, pero la clientela fija tarda un trimestre: el Mes 1 (enero) factura un 75 % de lo que facturará a los cuatro meses. Con 100 % se elimina la rampa
A53: Meses hasta alcanzar el régimen de crucero | B53: 4 | C53: Cuatro meses hasta el ritmo de crucero: de enero a abril, para llegar a la terraza de primavera con clientela
A54: Meses de alquiler ANTES de abrir (obra y licencias) | B54: 2 | C54: Dos meses de renta antes de abrir: la obra, el conducto de humos y la licencia. Si el banco te da el préstamo al empezar la obra, súmale los intereses de esos meses, que este libro no cuenta, y ten en cuenta que la carencia corre desde la firma
A55: Imprevistos sobre las partidas de OBRA del bloque de local (%) | B55: 0.1 | C55: Colchón sobre la obra y las instalaciones del local, que es donde aparecen las sorpresas (el conducto hasta cubierta, la instalación de gas, el separador de grasas). Un banco no financia una reforma sin él
A57: COBROS, PAGOS Y DESGLOSE DEL IVA
A58: Días medios de cobro | B58: 2 | C58: Media ponderada: la sala y lo que se recoge en el local cobran al momento y la plataforma liquida cada 7-15 días lo que vende por ella (un 12 % de las ventas)
A59: Días medios de pago a proveedor | B59: 30 | C59: Plazo de pago a los proveedores de carne, tortilla, verdura y bebida: lo que te financian. Es lo primero que se pierde si te retrasas en un pago
A60: Mes de la paga extra de verano | B60: 7 | C60: Mes de la TESORERÍA en el que sale la paga extra de verano: julio es el Mes 7, porque el Mes 1 del plan es enero
A61: Mes de la paga extra de Navidad | B61: 12 | C61: Mes de la TESORERÍA en el que sale la paga extra de Navidad: diciembre es el Mes 12, porque el Mes 1 del plan es enero
A62: Bebida que compras al 21 % (cerveza, mezcal, tequila y refrescos azucarados o edulcorados) sobre el total de bebida | B62: 0.75 | C62: Sólo mueve el IVA que SOPORTAS al comprar la bebida: la cerveza, el mezcal, el tequila y los refrescos con azúcares o edulcorantes añadidos te los facturan al 21 %; el agua y los ingredientes de las aguas frescas que preparas tú, al 10 % (la fruta fresca, al 4 %). Con un 75 % sale un 18,3 %. El IVA que REPERCUTES lo fija la línea de bebida del P&L (columna H)
A63: IVA de la bebida ALCOHÓLICA servida en sala | B63: 0.1 | C63: SIN EFECTO en este libro: el IVA que repercute la bebida lo fija su línea del P&L. En sala, todo al 10 % (art. 91.Uno.2.2.º de la Ley 37/1992); para llevar o a domicilio, el alcohol y las aguas frescas y los refrescos con azúcares o edulcorantes añadidos, al 21 %, en la columna H de esa línea
A64: UMBRALES Y SUELOS DE CONTROL
A65: DSCR mínimo aceptable | B65: 1 | C65: Por debajo de 1 el negocio no genera para pagar el préstamo. Ponlo en el covenant que te exija tu banco
A66: DSCR objetivo (verde) | B66: 1.25 | C66: Lo que suele pedir una entidad para dar el préstamo sin garantías adicionales
A67: Holgura mínima sobre el punto de equilibrio | B67: 0.15 | C67: Cuánto puedes caer sobre lo previsto antes de entrar en pérdidas
A68: Suelo salarial anual del convenio provincial (€) | B68: 0 | C68: Las taquerías van al convenio PROVINCIAL de hostelería: el art. 4 del VI Acuerdo Laboral de ámbito Estatal para el sector de Hostelería no nombra la palabra «taquería», pero incluye los restaurantes y el reparto de comidas preparadas. Copia aquí el salario base del grupo más bajo de la tabla de TU provincia. Con 0 el semáforo compara sólo contra el SMI

Sheet Inversión Inicial
A1: PLAN DE NEGOCIO: TAQUERÍA
A2: Inversión inicial estimada — taquería con trompo, barra de salsas, 32 plazas y terraza
A3: Ajusta las cifras a tu proyecto: son las de un caso tipo en una ciudad media, sin traspaso. Pon tus presupuestos reales en las celdas de importe.
A5: Concepto | B5: Importe | C5: % s/inversión | D5: Notas | E5: ¿Lleva IVA?
A6: INVERSIÓN | B6: =IFERROR(IF(COUNT(B7:B27)=0,"",SUM(B7:B27)),"") -> 106150 | C6: =IFERROR(B6/$B$30,"") -> 0.70297929
A7: Proyecto técnico de actividad y de salida de humos, y dirección de obra | B7: 3500 | C7: =IFERROR(B7/$B$30,"") -> 0.02317878 | D7: Proyecto de la actividad y del conducto de humos, memoria para la licencia o la declaración responsable y certificado final de obra | E7: Sí
A8: Obra y acondicionamiento del local, rótulo y fachada | B8: 26500 | C8: =IFERROR(B8/$B$30,"") -> 0.17549648 | D8: Cocina alicatada, suelo antideslizante, aseos (uno adaptado), falsos techos y aislamiento acústico, más el rótulo y la fachada (unos 2.500 €). Estimación del kit: pide dos presupuestos | E8: Sí
A9: Conducto de extracción exclusivo hasta cubierta | B9: 6000 | C9: =IFERROR(B9/$B$30,"") -> 0.039735052 | D9: Conducto exclusivo hasta la cubierta para el trompo, la plancha, el comal y la freidora: Madrid pide superar en 1 m lo que haya en 15 m (Ordenanza 4/2021). Con trompo o parrilla de carbón, además, filtro de partículas. Ningún fabricante da precio por metro: pide oferta con tu proyecto | E9: Sí
A10: Instalación eléctrica, cuadro y boletín | B10: 4500 | C10: =IFERROR(B10/$B$30,"") -> 0.029801289 | D10: Frío, extracción, climatización, lavavajillas y cafetera. Pregunta la potencia disponible ANTES de firmar: una acometida nueva tarda | E10: Sí
A11: Fontanería, separador de grasas, climatización e instalación de gas | B11: 8000 | C11: =IFERROR(B11/$B$30,"") -> 0.052980069 | D11: Agua fría y caliente en la cocina, desagües con separador de grasas, climatización de la sala y la instalación de gas del trompo, la plancha, el comal y los fogones por empresa instaladora habilitada, con su certificado (RD 919/2006) | E11: Sí
A12: Trompo: asador vertical de gas de cuatro quemadores | B12: 1800 | C12: =IFERROR(B12/$B$30,"") -> 0.011920516 | D12: Para conos de 30-35 kg, con bandeja, cuchillos de corte y base para la piña. En el catálogo de un distribuidor de hostelería, de 1.279 a 1.784 € sin IVA (octubre de 2026) | E12: Sí
A13: Plancha de acero a gas y comal | B13: 3000 | C13: =IFERROR(B13/$B$30,"") -> 0.019867526 | D13: Plancha lisa de acero para las carnes y comal para calentar la tortilla. Una plancha a gas de 40 cm ronda los 1.040 €; la de 80 cm a gas no tiene precio de referencia: estimación del kit, pide oferta | E13: Sí
A14: Freidora, fogón de carnitas, baño maría y mantenedor de tortillas | B14: 3700 | C14: =IFERROR(B14/$B$30,"") -> 0.024503282 | D14: Freidora para los totopos y los tacos dorados, fogón para las carnitas y los guisados, baño maría GN y mantenedor de tortillas. Estimación del kit | E14: Sí
A15: Campana extractora con motor y filtros | B15: 1500 | C15: =IFERROR(B15/$B$30,"") -> 0.009933763 | D15: Campana extractora de 2,5 m con motor y filtros de grasa sobre el trompo, la plancha, el comal y la freidora (una de 1,5-2 m ronda los 815 € sin IVA) | E15: Sí
A16: Frío: armarios, congelador y mesa refrigerada de salsas | B16: 4500 | C16: =IFERROR(B16/$B$30,"") -> 0.029801289 | D16: Armarios refrigerados (unos 900 € sin IVA el de 400 l), congelador y mesa refrigerada de granito para la barra de salsas y las guarniciones (de 1.180 a 1.950 € sin IVA) | E16: Sí
A17: Lavavajillas de capota, fregaderos, lavamanos, mesas inox y estanterías | B17: 5500 | C17: =IFERROR(B17/$B$30,"") -> 0.036423798 | D17: Lavavajillas, fregaderos, lavamanos de accionamiento no manual, mesas de acero inoxidable y estanterías | E17: Sí
A18: Utillaje y menaje: licuadora, molcajetes, sondas y prensa de tortillas | B18: 3500 | C18: =IFERROR(B18/$B$30,"") -> 0.02317878 | D18: Licuadora industrial para las salsas, molcajetes, termómetros sonda, básculas, recipientes GN, vajilla, cestas, vitroleros para las aguas frescas, una prensa de tortillas (unos 48 € con IVA) y la cartelería de alérgenos | E18: Sí
... A24: Stock inicial: carnes, chiles, tortillas, bebida y envases | B24: 3500 | C24: =IFERROR(B24/$B$30,"") -> 0.02317878 | D24: Carnes, chiles secos y producto mexicano importado (pídelo con su plazo de entrega: tarda semanas), tortillas, bebida, mezcal y envases para llevar | E24: Sí
A25: Fianza del alquiler | B25: =IFERROR(IF('0. Supuestos'!$B$24="","",'0. Supuestos'!$B$24*'0. Supuestos'!$B$25),"") -> 2900 | C25: =IFERROR(B25/$B$30,"") -> 0.019205275 | D25: =IFERROR(""&TEXT('0. Supuestos'!$B$25,"0")&" meses de renta, al tipo de la hoja de Supuestos. Es un activo recuperable al cerrar: ni se amortiza ni lleva IVA","") -> 2 meses de renta, al tipo de la hoja de Supuestos. Es un activo recuperable al cerrar: ni se amortiza ni lleva IVA | E25: No
A26: Alquiler de los meses previos a la apertura | B26: =IFERROR(IF('0. Supuestos'!$B$24="","",'0. Supuestos'!$B$24*'0. Supuestos'!$B$54),"") -> 2900 | C26: =IFERROR(B26/$B$30,"") -> 0.019205275 | D26: =IFERROR("Renta "&IF('0. Supuestos'!$B$54=1,"del mes","de los "&TEXT('0. Supuestos'!$B$54,"0")&" meses")&" de obra y licencias. NO se solapa con el P&L, que arranca el día de la apertura: los doce meses del P&L son los doce de explotación","") -> Renta de los 2 meses de obra y licencias. NO se solapa con el P&L, que arranca el día de la apertura: los doce meses del P&L son los doce de explotación | E26: Sí
A27: Imprevistos de obra y acondicionamiento | B27: =IFERROR(IF(COUNT(B7,B8,B9,B10,B11)=0,"",ROUND((B7+B8+B9+B10+B11)*'0. Supuestos'!$B$55,0)),"") -> 4850 | C27: =IFERROR(B27/$B$30,"") -> 0.032119167 | D27: =IFERROR("Al "&TEXT('0. Supuestos'!$B$55,"0%")&" de las partidas de OBRA Y ACONDICIONAMIENTO de este bloque (Proyecto técnico de actividad y de salida de humos, y dirección de obra, Obra y acondicionamiento del local, rótulo y fachada, Conducto de extracción exclusivo hasta cubierta, Instalación eléctrica, cuadro y boletín y Fontanería, separador de grasas, climatización e instalación de gas), no del bloque entero: el resto de partidas del bloque quedan fuera. Un banco no financia una reforma sin colchón: el porcentaje está en la hoja de Supuestos","") -> Al 10% de las partidas de OBRA Y ACONDICIONAMIENTO de este bloque (Proyecto técnico de actividad y de salida de humos, y dirección de obra, Obra y acondicionamiento del local, rótulo y fachada, Conducto de extracción exclusivo hasta cubierta, Instalación eléctrica, cuadro y boletín y Fontanería, separador de grasas, climatización e instalación de gas), no del bloque entero: el resto de partidas del bloque quedan fuera. Un banco no financia una reforma sin colchón: el porcentaje está en la hoja de Supuestos | E27: Sí
A28: FONDO DE MANIOBRA | B28: =IFERROR(IF(B29="","",B29),"") -> 44850.18 | C28: =IFERROR(B28/$B$30,"") -> 0.29702071
A29: Colchón operativo hasta alcanzar el equilibrio | B29: =IFERROR(IF('0. Supuestos'!$B$35*('PyG 3 Años'!$B$37-'PyG 3 Años'!$B$35)=0,"",'0. Supuestos'!$B$35*('PyG 3 Años'!$B$37-'PyG 3 Años'!$B$35)/12),"") -> 44850.18 | C29: =IFERROR(B29/$B$30,"") -> 0.29702071 | D29: =IFERROR("Cubre "&TEXT('0. Supuestos'!$B$35,"0")&IF('0. Supuestos'!$B$35=1," mes"," meses")&" de costes fijos DE CAJA del año 1 (los del P&L menos la amortización, que no se paga), que es el mínimo que exigen las Instrucciones de este libro","") -> Cubre 3 meses de costes fijos DE CAJA del año 1 (los del P&L menos la amortización, que no se paga), que es el mínimo que exigen las Instrucciones de este libro | E29: No
A30: INVERSIÓN TOTAL (suma de los bloques) | B30: =IFERROR(B6+B28,"") -> 151000.18 | D30: =IFERROR("Los porcentajes de la columna C se leen sobre esta cifra, que incluye el fondo de maniobra ("&TEXT(C28,"0%")&" del total). Para comparar el desglose con otro plan, usa la fila de CAPEX de abajo.","") -> Los porcentajes de la columna C se leen sobre esta cifra, que incluye el fondo de maniobra (30% del total). Para comparar el desglose con otro plan, usa la fila de CAPEX de abajo.
A31: CAPEX (inversión sin el fondo de maniobra) | B31: =IFERROR(B30-B28,"") -> 106150 | D31: Es lo que se compra: obra, equipamiento, lanzamiento y gastos de constitución. El colchón de caja no es inversión, es circulante
A32: IVA soportado sobre la inversión (recuperable) | B32: =IFERROR(IF(B30="","",SUMIF($E$7:$E$27,"Sí",$B$7:$B$27)*'0. Supuestos'!$B$41),"") -> 21052.5 | D32: =IFERROR("Al "&TEXT('0. Supuestos'!$B$41,"0%")&" sobre las partidas marcadas con «Sí» en la columna de IVA. Las tasas y licencias no están sujetas y los seguros están exentos (art. 20.Uno.16 LIVA). Las tasas y aranceles registrales no llevan IVA; los honorarios de notaría y gestoría sí (21 %, deducible). Se recupera con el modelo 303, pero hay que adelantarlo","") -> Al 21% sobre las partidas marcadas con «Sí» en la columna de IVA. Las tasas y licencias no están sujetas y los seguros están exentos (art. 20.Uno.16 LIVA). Las tasas y aranceles registrales no llevan IVA; los honorarios de notaría y gestoría sí (21 %, deducible). Se recupera con el modelo 303, pero hay que adelantarlo
A33: NECESIDAD TOTAL DE CAJA AL ARRANQUE | B33: =IFERROR(B30+B32,"") -> 172052.68 | D33: Es la cifra que tiene que cubrir la hoja de Financiación
A34: BASES DE AMORTIZACIÓN (no suman a la inversión)
A35: Obra, instalaciones y acondicionamiento | B35: =IFERROR(IF(B7="","",B7+B8+B9+B10+B11+B27),"") -> 53350 | D35: =IFERROR("Se amortiza en "&TEXT('0. Supuestos'!$B$44,"0")&" años","") -> Se amortiza en 10 años
A36: Maquinaria, mobiliario y equipos | B36: =IFERROR(IF(B12="","",B12+B13+B14+B15+B16+B17+B18+B19+B20+B21),"") -> 36000 | D36: =IFERROR("Se amortiza en "&TEXT('0. Supuestos'!$B$45,"0")&" años","") -> Se amortiza en 10 años
A37: Amortización anual del inmovilizado | B37: =IFERROR(B35/MAX(1,'0. Supuestos'!$B$44)+B36/MAX(1,'0. Supuestos'!$B$45),"") -> 8935 | D37: =IFERROR("No se amortizan, por no ser inmovilizado, Constitución de la SL, licencia, tasas, registro sanitario y APPCC, Marca, web, fotos y lanzamiento, Stock inicial: carnes, chiles, tortillas, bebida y envases, Fianza del alquiler, Alquiler de los meses previos a la apertura ni Colchón operativo hasta alcanzar el equilibrio. Suman "&TEXT(B30-B35-B36,"0")&" € de los "&TEXT(B30,"0")&" € de inversión.","") -> No se amortizan, por no ser inmovilizado, Constitución de la SL, licencia, tasas, registro sanitario y APPCC, Marca, web, fotos y lanzamiento, Stock inicial: carnes, chiles, tortillas, bebida y envases, Fianza del alquiler, Alquiler de los meses previos a la apertura ni Colchón operativo hasta alcanzar el equilibrio. Suman 61650 € de los 151000 € de inversión.

Sheet PyG 3 Años
A1: CUENTA DE RESULTADOS PREVISIONAL — 3 AÑOS
A2: Escenario realista — taquería con trompo, barra de salsas y para llevar
A4: Concepto | B4: Año 1 | C4: Año 2 | D4: Año 3 | E4: % s/ventas (año 1) | F4: Notas | G4: Tipo de IVA de la línea (%) | H4: Bebida para llevar o a domicilio al 21 % (%)
A5: INGRESOS
A6: Comensales/día (media) | B6: =IFERROR(IF('0. Supuestos'!$B$4="","",'0. Supuestos'!$B$4),"") -> 77 | C6: =IFERROR(B6*(1+'0. Supuestos'!$B$7),"") -> 81.62 | D6: =IFERROR(C6*(1+'0. Supuestos'!$B$8),"") -> 84.8848 | F6: El crecimiento de los años 2 y 3 está en la hoja de Supuestos
A7: Ticket medio sin IVA | B7: =IFERROR(IF('0. Supuestos'!$B$5="","",'0. Supuestos'!$B$5),"") -> 15.5 | C7: =IFERROR(IF(B7="","",B7),"") -> 15.5 | D7: =IFERROR(IF(C7="","",C7),"") -> 15.5 | F7: Constante en euros del año 1: una subida de precios es una decisión aparte
A8: Días de apertura al año | B8: =IFERROR(IF('0. Supuestos'!$B$6="","",'0. Supuestos'!$B$6),"") -> 300 | C8: =IFERROR(IF(B8="","",B8),"") -> 300 | D8: =IFERROR(IF(C8="","",C8),"") -> 300
A9: INGRESOS TOTALES (sin IVA) | B9: =IFERROR(IF(B6*B7*B8=0,"",B6*B7*B8),"") -> 358050 | C9: =IFERROR(IF(C6*C7*C8=0,"",C6*C7*C8),"") -> 379533 | D9: =IFERROR(IF(D6*D7*D8=0,"",D6*D7*D8),"") -> 394714.32 | E9: =IFERROR(IF(B9="","",1),"") -> 1
A10: Ventas de taquería y cocina (sala, para llevar y a domicilio) | B10: =IFERROR(IF(B9="","",B9*$E$10),"") -> 286440 | C10: =IFERROR(IF(C9="","",C9*$E$10),"") -> 303626.4 | D10: =IFERROR(IF(D9="","",D9*$E$10),"") -> 315771.46 | E10: =IFERROR(IF('0. Supuestos'!$B$11="","",'0. Supuestos'!$B$11),"") -> 0.8 | F10: Tacos, gringas y quesadillas, entrantes y postres: en sala unos 74 % de las ventas, para llevar unos 14 % y por plataforma un 12 %. Todo al 10 % de IVA, se coma en la mesa o salga del local (art. 91.Uno.1.1.º y 2.2.º de la Ley 37/1992) | G10: =IFERROR(IF(B9="","",'0. Supuestos'!$B$39),"") -> 0.1
A11: Ventas de bebida (aguas frescas, cerveza, mezcal y tequila, refrescos y agua) | B11: =IFERROR(IF(B9="","",B9*$E$11),"") -> 71610 | C11: =IFERROR(IF(C9="","",C9*$E$11),"") -> 75906.6 | D11: =IFERROR(IF(D9="","",D9*$E$11),"") -> 78942.864 | E11: =IFERROR(IF('0. Supuestos'!$B$12="","",'0. Supuestos'!$B$12),"") -> 0.2 | F11: Bebida de sala y la que sale con los pedidos · La columna H es la parte de la bebida que sale del local y va al 21 %: el alcohol y las aguas frescas y los refrescos con azúcares o edulcorantes añadidos (art. 91.Uno.1.1.º a y b de la Ley 37/1992); el agua y lo que no lleve azúcares ni edulcorantes añadidos, y toda la bebida en sala, al 10 %. Un 7,5 % = un 1,5 % de las ventas | G11: =IFERROR(IF(B9="","",H11*0.21+(1-H11)*'0. Supuestos'!$B$39),"") -> 0.10825 | H11: 0.075
A12: COSTES VARIABLES
A13: Coste de mercancía — comida | B13: =IFERROR(IF(B9="","",B9*'0. Supuestos'!$B$11*'0. Supuestos'!$B$13),"") -> 77338.8 | C13: =IFERROR(IF(C9="","",C9*'0. Supuestos'!$B$11*'0. Supuestos'!$B$13),"") -> 81979.128 | D13: =IFERROR(IF(D9="","",D9*'0. Supuestos'!$B$11*'0. Supuestos'!$B$13),"") -> 85258.293 | E13: =IFERROR(B13/$B$9,"") -> 0.216 | F13: =IFERROR("Al "&TEXT('0. Supuestos'!$B$13,"0%")&" de las ventas de COMIDA, no del total: la bebida tiene su propia línea · Carne, tortilla, chiles y especias al 10 %; verdura, fruta, aguacate y quesos al 4 % (art. 91.Dos.1.1.º de la Ley 37/1992). Ajústalo a tus facturas","") -> Al 27% de las ventas de COMIDA, no del total: la bebida tiene su propia línea · Carne, tortilla, chiles y especias al 10 %; verdura, fruta, aguacate y quesos al 4 % (art. 91.Dos.1.1.º de la Ley 37/1992). Ajústalo a tus facturas | G13: 0.085
A14: Coste de mercancía — bebida | B14: =IFERROR(IF(B9="","",B9*'0. Supuestos'!$B$12*'0. Supuestos'!$B$14),"") -> 18618.6 | C14: =IFERROR(IF(C9="","",C9*'0. Supuestos'!$B$12*'0. Supuestos'!$B$14),"") -> 19735.716 | D14: =IFERROR(IF(D9="","",D9*'0. Supuestos'!$B$12*'0. Supuestos'!$B$14),"") -> 20525.145 | E14: =IFERROR(B14/$B$9,"") -> 0.052 | F14: =IFERROR("Al "&TEXT('0. Supuestos'!$B$14,"0%")&" de las ventas de BEBIDA","") -> Al 26% de las ventas de BEBIDA | G14: =IFERROR(IF(B9="","",('0. Supuestos'!$B$62*'0. Supuestos'!$B$40+(1-'0. Supuestos'!$B$62)*'0. Supuestos'!$B$39)),"") -> 0.1825
A15: Consumibles y envases | B15: =IFERROR(IF(B9="","",B9*'0. Supuestos'!$B$15),"") -> 12531.75 | C15: =IFERROR(IF(C9="","",C9*'0. Supuestos'!$B$15),"") -> 13283.655 | D15: =IFERROR(IF(D9="","",D9*'0. Supuestos'!$B$15),"") -> 13815.001 | E15: =IFERROR(B15/$B$9,"") -> 0.035 | G15: =IFERROR(IF(B9="","",'0. Supuestos'!$B$41),"") -> 0.21
A16: Comisiones de delivery | B16: =IFERROR(IF(B9="","",B9*'0. Supuestos'!$B$16*'0. Supuestos'!$B$17),"") -> 12889.8 | C16: =IFERROR(IF(C9="","",C9*'0. Supuestos'!$B$16*'0. Supuestos'!$B$17),"") -> 13663.188 | D16: =IFERROR(IF(D9="","",D9*'0. Supuestos'!$B$16*'0. Supuestos'!$B$17),"") -> 14209.716 | E16: =IFERROR(B16/$B$9,"") -> 0.036 | F16: Sobre las ventas DEL CANAL. Con 0 % de delivery en Supuestos, esta línea vale cero | G16: =IFERROR(IF(B9="","",'0. Supuestos'!$B$41),"") -> 0.21
A17: Comisiones de los medios de pago | B17: =IFERROR(IF(B9="","",B9*'0. Supuestos'!$B$18),"") -> 2864.4 | C17: =IFERROR(IF(C9="","",C9*'0. Supuestos'!$B$18),"") -> 3036.264 | D17: =IFERROR(IF(D9="","",D9*'0. Supuestos'!$B$18),"") -> 3157.7146 | E17: =IFERROR(B17/$B$9,"") -> 0.008 | F17: Las comisiones de los medios de pago están EXENTAS de IVA (art. 20.Uno.18 LIVA): no se deduce nada por ellas | G17: 0
A18: Varios e imprevistos | B18: =IFERROR(IF(B9="","",B9*'0. Supuestos'!$B$28),"") -> 7161 | C18: =IFERROR(IF(C9="","",C9*'0. Supuestos'!$B$28),"") -> 7590.66 | D18: =IFERROR(IF(D9="","",D9*'0. Supuestos'!$B$28),"") -> 7894.2864 | E18: =IFERROR(B18/$B$9,"") -> 0.02 | F18: =IFERROR("Al "&TEXT('0. Supuestos'!$B$28,"0%")&" de las ventas. Es un coste VARIABLE: sube y baja con la facturación, así que no puede vivir en los costes fijos","") -> Al 2% de las ventas. Es un coste VARIABLE: sube y baja con la facturación, así que no puede vivir en los costes fijos | G18: =IFERROR(IF(B9="","",'0. Supuestos'!$B$41),"") -> 0.21
A19: TOTAL COSTES VARIABLES | B19: =IFERROR(IF(B9="","",SUM(B13:B18)),"") -> 131404.35 | C19: =IFERROR(IF(C9="","",SUM(C13:C18)),"") -> 139288.61 | D19: =IFERROR(IF(D9="","",SUM(D13:D18)),"") -> 144860.16 | E19: =IFERROR(B19/$B$9,"") -> 0.367
A20: MARGEN BRUTO | B20: =IFERROR(IF(B9="","",B9-B19),"") -> 226645.65 | C20: =IFERROR(IF(C9="","",C9-C19),"") -> 240244.39 | D20: =IFERROR(IF(D9="","",D9-D19),"") -> 249854.16 | E20: =IFERROR(B20/$B$9,"") -> 0.633
A21: COSTES FIJOS
A22: Alquiler del local | B22: =IFERROR(IF(B9="","",'0. Supuestos'!$B$24*12),"") -> 17400 | C22: =IFERROR(IF(C9="","",B22*(1+'0. Supuestos'!$B$48)),"") -> 17400 | D22: =IFERROR(IF(D9="","",C22*(1+'0. Supuestos'!$B$48)),"") -> 17400 | E22: =IFERROR(B22/$B$9,"") -> 0.048596565 | F22: El importe mensual está en la hoja de Supuestos; aquí se multiplica por doce. Los dos meses de renta previos a la apertura están en la hoja de Inversión y NO se cuentan dos veces | G22: =IFERROR(IF(B9="","",'0. Supuestos'!$B$41),"") -> 0.21
A23: Personal (nóminas + Seguridad Social) | B23: =IFERROR(IF(B9="","",'Personal'!$G$12),"") -> 129520.72 | C23: =IFERROR(IF(C9="","",'Personal'!$B$16),"") -> 135520.72 | D23: =IFERROR(IF(D9="","",'Personal'!$B$17),"") -> 141520.72 | E23: =IFERROR(B23/$B$9,"") -> 0.3617392 | F23: Sale de la hoja de Personal: es el MISMO número, no una estimación aparte. Los años 2 y 3 suman las INCORPORACIONES declaradas en esa hoja, no un porcentaje de volumen | G23: 0
A24: Suministros (luz, agua, gas) | B24: =IFERROR(IF(B9="","",'0. Supuestos'!$B$26*12),"") -> 10200 | C24: =IFERROR(IF(C9="","",B24*(1+'0. Supuestos'!$B$48)),"") -> 10200 | D24: =IFERROR(IF(D9="","",C24*(1+'0. Supuestos'!$B$48)),"") -> 10200 | E24: =IFERROR(B24/$B$9,"") -> 0.028487641 | F24: Luz y gas van al 21 %; la factura del agua, al 10 %. El libro aplica a toda esta partida el tipo de la columna de al lado (21 %): si el agua pesa mucho en tu local, sepárala en su línea | G24: =IFERROR(IF(B9="","",'0. Supuestos'!$B$41),"") -> 0.21
A25: Seguros (RC + multirriesgo) | B25: =IFERROR(IF(B9="","",'0. Supuestos'!$B$27),"") -> 1400 | C25: =IFERROR(IF(C9="","",B25*(1+'0. Supuestos'!$B$48)),"") -> 1400 | D25: =IFERROR(IF(D9="","",C25*(1+'0. Supuestos'!$B$48)),"") -> 1400 | E25: =IFERROR(B25/$B$9,"") -> 0.0039100684 | F25: Las operaciones de seguro están EXENTAS de IVA (art. 20.Uno.16 LIVA): la prima no lleva IVA deducible | G25: 0
A26: Gestoría laboral, fiscal y contable | B26: 2400 | C26: =IFERROR(IF(C9="","",B26*(1+'0. Supuestos'!$B$48)),"") -> 2400 | D26: =IFERROR(IF(D9="","",C26*(1+'0. Supuestos'!$B$48)),"") -> 2400 | E26: =IFERROR(B26/$B$9,"") -> 0.0067029744 | F26: Contabilidad, impuestos de la SL, nóminas y contratos de la plantilla | G26: =IFERROR(IF(B9="","",'0. Supuestos'!$B$41),"") -> 0.21
A27: Mantenimiento de la campana extractora, el gas y el frío | B27: 1800 | C27: =IFERROR(IF(C9="","",B27*(1+'0. Supuestos'!$B$48)),"") -> 1800 | D27: =IFERROR(IF(D9="","",C27*(1+'0. Supuestos'!$B$48)),"") -> 1800 | E27: =IFERROR(B27/$B$9,"") -> 0.0050272308 | F27: Limpieza de la campana extractora y del conducto al menos una vez al año (Madrid lo exige en su Ordenanza 4/2021, art. 23; mira la de tu ayuntamiento), revisión del gas y del trompo y el frigorista | G27: =IFERROR(IF(B9="","",'0. Supuestos'!$B$41),"") -> 0.21
A28: Marketing y publicidad | B28: 3500 | C28: =IFERROR(IF(C9="","",B28*(1+'0. Supuestos'!$B$48)),"") -> 3500 | D28: =IFERROR(IF(D9="","",C28*(1+'0. Supuestos'!$B$48)),"") -> 3500 | E28: =IFERROR(B28/$B$9,"") -> 0.0097751711 | F28: Ficha de Google Business, redes sociales, fotos y las fechas mexicanas (la Independencia en septiembre, el Día de Muertos en noviembre); la campaña de apertura va en la inversión | G28: =IFERROR(IF(B9="","",'0. Supuestos'!$B$41),"") -> 0.21
A29: Software, TPV, teléfono e internet | B29: 1500 | C29: =IFERROR(IF(C9="","",B29*(1+'0. Supuestos'!$B$48)),"") -> 1500 | D29: =IFERROR(IF(D9="","",C29*(1+'0. Supuestos'!$B$48)),"") -> 1500 | E29: =IFERROR(B29/$B$9,"") -> 0.004189359 | F29: Cuota del TPV con Veri*factu, la tablet de las plataformas, teléfono e internet | G29: =IFERROR(IF(B9="","",'0. Supuestos'!$B$41),"") -> 0.21
A30: Limpieza, lavandería, EPI y análisis de autocontrol | B30: 1200 | C30: =IFERROR(IF(C9="","",B30*(1+'0. Supuestos'!$B$48)),"") -> 1200 | D30: =IFERROR(IF(D9="","",C30*(1+'0. Supuestos'!$B$48)),"") -> 1200 | E30: =IFERROR(B30/$B$9,"") -> 0.0033514872 | F30: Productos de limpieza, lavado de uniformes y paños, guantes y los análisis de autocontrol que fije tu APPCC | G30: =IFERROR(IF(B9="","",'0. Supuestos'!$B$41),"") -> 0.21
A31: Tasa de terraza y gestión de residuos (pon las de tu ayuntamiento) | B31: 1700 | C31: =IFERROR(IF(C9="","",B31*(1+'0. Supuestos'!$B$48)),"") -> 1700 | D31: =IFERROR(IF(D9="","",C31*(1+'0. Supuestos'!$B$48)),"") -> 1700 | E31: =IFERROR(B31/$B$9,"") -> 0.0047479402 | F31: La ocupación de la vía pública con 4 mesas de abril a octubre (unos 1.200 € de ejemplo: cada ayuntamiento tiene su ordenanza fiscal y este plan no ha leído ninguna) y la tasa de basuras, el cartón y el aceite y la grasa usados con gestor autorizado (unos 500 €). Pon las de tu ayuntamiento | G31: =IFERROR(IF(B9="","",'0. Supuestos'!$B$41),"") -> 0.21
A32: Desinsectación, desratización y desinfección (DDD) | B32: 450 | C32: =IFERROR(IF(C9="","",B32*(1+'0. Supuestos'!$B$48)),"") -> 450 | D32: =IFERROR(IF(D9="","",C32*(1+'0. Supuestos'!$B$48)),"") -> 450 | E32: =IFERROR(B32/$B$9,"") -> 0.0012568077 | F32: Contrato con una empresa inscrita en el ROESB: forma parte de los prerrequisitos del APPCC | G32: =IFERROR(IF(B9="","",'0. Supuestos'!$B$41),"") -> 0.21
A33: Derechos de autor por música ambiental (SGAE y AGEDI-AIE) | B33: 500 | C33: =IFERROR(IF(C9="","",B33*(1+'0. Supuestos'!$B$48)),"") -> 500 | D33: =IFERROR(IF(D9="","",C33*(1+'0. Supuestos'!$B$48)),"") -> 500 | E33: =IFERROR(B33/$B$9,"") -> 0.001396453 | F33: SGAE y AGEDI-AIE son dos licencias distintas; el importe depende de los metros y del aforo de tu sala | G33: =IFERROR(IF(B9="","",'0. Supuestos'!$B$41),"") -> 0.21
A34: Prevención de riesgos laborales, vigilancia de la salud y formación | B34: 750 | C34: =IFERROR(IF(C9="","",B34*(1+'0. Supuestos'!$B$48)),"") -> 750 | D34: =IFERROR(IF(D9="","",C34*(1+'0. Supuestos'!$B$48)),"") -> 750 | E34: =IFERROR(B34/$B$9,"") -> 0.0020946795 | F34: El plan de prevención es obligatorio (Ley 31/1995): cortes en el trompo, quemaduras de la plancha y la freidora, gas y calor; los reconocimientos médicos de la plantilla y la formación en higiene y alérgenos | G34: =IFERROR(IF(B9="","",'0. Supuestos'!$B$41),"") -> 0.21
A35: Amortización del inmovilizado | B35: =IFERROR(IF(B9="","",'Inversión Inicial'!$B$37),"") -> 8935 | C35: =IFERROR(IF(C9="","",B35),"") -> 8935 | D35: =IFERROR(IF(D9="","",B35),"") -> 8935 | E35: =IFERROR(B35/$B$9,"") -> 0.024954615 | F35: Sale de las bases de amortización de la hoja de Inversión: sólo inmovilizado real. NO sube con el IPC: es una cuota sobre el coste HISTÓRICO del inmovilizado | G35: 0
A36: Gastos financieros (intereses del préstamo) | B36: =IFERROR(IF(B9="","",'Financiación'!$B$44),"") -> 7080 | C36: =IFERROR(IF(C9="","",'Financiación'!$B$46),"") -> 7080 | D36: =IFERROR(IF(D9="","",'Financiación'!$B$48),"") -> 6064.9926 | E36: =IFERROR(B36/$B$9,"") -> 0.019773775 | F36: Sólo los INTERESES son gasto. La devolución del principal va en la hoja de Tesorería | G36: 0
A37: TOTAL COSTES FIJOS | B37: =IFERROR(IF(B9="","",SUM(B22:B36)),"") -> 188335.72 | C37: =IFERROR(IF(C9="","",SUM(C22:C36)),"") -> 194335.72 | D37: =IFERROR(IF(D9="","",SUM(D22:D36)),"") -> 199320.71 | E37: =IFERROR(B37/$B$9,"") -> 0.52600397
A38: IVA soportado de los costes variables | B38: =IFERROR(IF(B9="","",SUMPRODUCT(B13:B18,G13:G18)),"") -> 16814.028 | C38: =IFERROR(IF(C9="","",SUMPRODUCT(C13:C18,G13:G18)),"") -> 17822.87 | D38: =IFERROR(IF(D9="","",SUMPRODUCT(D13:D18,G13:G18)),"") -> 18535.784 | F38: Cada línea a SU tipo, leído de la columna de al lado. Es lo que la hoja de Tesorería paga de más a los proveedores y luego se deduce
A39: IVA soportado de los costes fijos | B39: =IFERROR(IF(B9="","",SUMPRODUCT(B22:B36,G22:G36)),"") -> 8694 | C39: =IFERROR(IF(C9="","",SUMPRODUCT(C22:C36,G22:G36)),"") -> 8694 | D39: =IFERROR(IF(D9="","",SUMPRODUCT(D22:D36,G22:G36)),"") -> 8694
A40: RESULTADO ANTES DE IMPUESTOS | B40: =IFERROR(IF(B9="","",B20-B37),"") -> 38309.93 | C40: =IFERROR(IF(C9="","",C20-C37),"") -> 45908.669 | D40: =IFERROR(IF(D9="","",D20-D37),"") -> 50533.452 | E40: =IFERROR(B40/$B$9,"") -> 0.10699603
A41: Bases negativas pendientes al inicio | B41: =IFERROR(IF(B9="","",'0. Supuestos'!$B$42),"") -> 0 | C41: =IFERROR(IF(C9="","",B46),"") -> 0 | D41: =IFERROR(IF(D9="","",C46),"") -> 0 | F41: Art. 26 LIS: las pérdidas de un ejercicio se compensan con los beneficios de los siguientes
A42: Base imponible (después de compensar) | B42: =IFERROR(IF(B9="","",MAX(0,B40-B41)),"") -> 38309.93 | C42: =IFERROR(IF(C9="","",MAX(0,C40-C41)),"") -> 45908.669 | D42: =IFERROR(IF(D9="","",MAX(0,D40-D41)),"") -> 50533.452
A43: Ejercicios con base positiva (acumulado) | B43: =IFERROR(IF(B9="","",IF(B42>0,1,0)),"") -> 1 | C43: =IFERROR(IF(C9="","",B43+IF(C42>0,1,0)),"") -> 2 | D43: =IFERROR(IF(D9="","",C43+IF(D42>0,1,0)),"") -> 3
A44: Tipo de Impuesto de Sociedades aplicado | B44: =IFERROR(IF(B9="","",IF(B42<=0,"",IF(B43<=2,'0. Supuestos'!$B$37,'0. Supuestos'!$B$38))),"") -> 0.15 | C44: =IFERROR(IF(C9="","",IF(C42<=0,"",IF(C43<=2,'0. Supuestos'!$B$37,'0. Supuestos'!$B$38))),"") -> 0.15 | D44: =IFERROR(IF(D9="","",IF(D42<=0,"",IF(D43<=2,'0. Supuestos'!$B$37,'0. Supuestos'!$B$38))),"") -> 0.25 | F44: Art. 29.1 LIS: el 15 % de entidad de nueva creación se aplica al PRIMER ejercicio con base positiva y al SIGUIENTE, no al primer año de vida. El libro lo aproxima contando los dos primeros ejercicios con base positiva
A45: Impuesto de Sociedades | B45: =IFERROR(IF(B9="","",IF(B44="",0,B42*B44)),"") -> 5746.4895 | C45: =IFERROR(IF(C9="","",IF(C44="",0,C42*C44)),"") -> 6886.3004 | D45: =IFERROR(IF(D9="","",IF(D44="",0,D42*D44)),"") -> 12633.363
A46: Bases negativas pendientes al cierre | B46: =IFERROR(IF(B9="","",MAX(0,B41-B40)),"") -> 0 | C46: =IFERROR(IF(C9="","",MAX(0,C41-C40)),"") -> 0 | D46: =IFERROR(IF(D9="","",MAX(0,D41-D40)),"") -> 0
A47: RESULTADO NETO | B47: =IFERROR(IF(B9="","",B40-B45),"") -> 32563.44 | C47: =IFERROR(IF(C9="","",C40-C45),"") -> 39022.369 | D47: =IFERROR(IF(D9="","",D40-D45),"") -> 37900.089 | E47: =IFERROR(B47/$B$9,"") -> 0.090946629
A48: RATIOS CLAVE
A49: Ratio | B49: Año 1 | C49: Año 2 | D49: Año 3 | E49: Umbral | F49: Comentario
A50: Margen bruto / Ventas | B50: =IFERROR(IF(B9="","",B20/B9),"") -> 0.633 | C50: =IFERROR(IF(C9="","",C20/C9),"") -> 0.633 | D50: =IFERROR(IF(D9="","",D20/D9),"") -> 0.633 | E50: 0.6 | F50: Suelo del margen tras TODOS los costes variables (mercancía, envases, plataforma, medios de pago y varios). Sólo con la mercancía, una taquería deja en torno a un 73 %. Estimación del kit
A51: Coste de mercancía (comida + bebida) | B51: =IFERROR(IF(B9="","",B13+B14),"") -> 95957.4 | C51: =IFERROR(IF(C9="","",C13+C14),"") -> 101714.84 | D51: =IFERROR(IF(D9="","",D13+D14),"") -> 105783.44
A52: Coste de mercancía / Ventas | B52: =IFERROR(IF(B9="","",B51/B9),"") -> 0.268 | C52: =IFERROR(IF(C9="","",C51/C9),"") -> 0.268 | D52: =IFERROR(IF(D9="","",D51/D9),"") -> 0.268 | E52: 0.29 | F52: Techo de la materia prima sobre ventas: el taco al pastor sale a un 22,5 % y las carnitas, el suadero, la barbacoa y el aguacate la suben. Estimación del kit
A53: Coste de personal / Ventas | B53: =IFERROR(IF(B9="","",B23/B9),"") -> 0.3617392 | C53: =IFERROR(IF(C9="","",C23/C9),"") -> 0.3570723 | D53: =IFERROR(IF(D9="","",D23/D9),"") -> 0.35853961 | E53: 0.38 | F53: Techo del personal sobre ventas con dos taqueros y una sala de dos servicios. Estimación del kit
A54: Alquiler / Ventas | B54: =IFERROR(IF(B9="","",B22/B9),"") -> 0.048596565 | C54: =IFERROR(IF(C9="","",C22/C9),"") -> 0.045845816 | D54: =IFERROR(IF(D9="","",D22/D9),"") -> 0.044082515 | E54: 0.1 | F54: Techo del alquiler sobre ventas para un local con salida de humos a cubierta: estimación del kit
A55: Resultado neto / Ventas | B55: =IFERROR(IF(B9="","",B47/B9),"") -> 0.090946629 | C55: =IFERROR(IF(C9="","",C47/C9),"") -> 0.1028168 | D55: =IFERROR(IF(D9="","",D47/D9),"") -> 0.096019037 | E55: 0.05 | F55: Suelo de resultado neto a régimen para que el plan se sostenga. Una taquería bien llevada deja en torno a un 9 %. Estimación del kit
A56: Punto de equilibrio alcanzado | B56: =IFERROR(IF(B9="","",IF(B9>='Punto Equilibrio'!$B$16,"Sí","No")),"") -> Sí | C56: =IFERROR(IF(C9="","",IF(C9>='Punto Equilibrio'!$C$16,"Sí","No")),"") -> Sí | D56: =IFERROR(IF(D9="","",IF(D9>='Punto Equilibrio'!$D$16,"Sí","No")),"") -> Sí | F56: Compara las ventas de CADA año con el umbral de ese mismo año, que calcula la hoja de Punto de Equilibrio con los costes fijos del año
A58: Todas las cifras van SIN IVA. Las columnas de los años 2 y 3 están en euros del año 1 salvo que subas la actualización de costes en la hoja de Supuestos. La columna «Tipo de IVA de la línea» dice, en las líneas de VENTA, a qué tipo se repercute cada una, y en las de COSTE a qué tipo se compra la partida. La lee la hoja de Tesorería: los seguros y las comisiones de los medios de pago están exentos, y las nóminas, la amortización y los intereses no llevan IVA.

Sheet Punto Equilibrio
A1: ANÁLISIS DE PUNTO DE EQUILIBRIO
A2: Punto de equilibrio mensual y diario — taquería con trompo
A4: Variable | B4: Año 1 | C4: Año 2 | D4: Año 3 | E4: Notas
A5: DATOS BASE POR AÑO
A6: Costes fijos anuales | B6: =IFERROR(IF('PyG 3 Años'!$B$9="","",'PyG 3 Años'!$B$37),"") -> 188335.72 | C6: =IFERROR(IF('PyG 3 Años'!$C$9="","",'PyG 3 Años'!$C$37),"") -> 194335.72 | D6: =IFERROR(IF('PyG 3 Años'!$D$9="","",'PyG 3 Años'!$D$37),"") -> 199320.71 | E6: Los MISMOS costes fijos del P&L. Cada año tiene los suyos: por eso el umbral no puede ser uno solo para los tres
A7: Costes fijos mensuales | B7: =IFERROR(IF('PyG 3 Años'!$B$9="","",B6/12),"") -> 15694.643 | C7: =IFERROR(IF('PyG 3 Años'!$C$9="","",C6/12),"") -> 16194.643 | D7: =IFERROR(IF('PyG 3 Años'!$D$9="","",D6/12),"") -> 16610.059
A8: Ticket medio sin IVA | B8: =IFERROR(IF('PyG 3 Años'!$B$9="","",'PyG 3 Años'!$B$7),"") -> 15.5 | C8: =IFERROR(IF('PyG 3 Años'!$C$9="","",'PyG 3 Años'!$C$7),"") -> 15.5 | D8: =IFERROR(IF('PyG 3 Años'!$D$9="","",'PyG 3 Años'!$D$7),"") -> 15.5
A9: Coste variable por comensal | B9: =IFERROR(IF('PyG 3 Años'!$B$9="","",'PyG 3 Años'!$B$19/('PyG 3 Años'!$B$6*'PyG 3 Años'!$B$8)),"") -> 5.6885 | C9: =IFERROR(IF('PyG 3 Años'!$C$9="","",'PyG 3 Años'!$C$19/('PyG 3 Años'!$C$6*'PyG 3 Años'!$C$8)),"") -> 5.6885 | D9: =IFERROR(IF('PyG 3 Años'!$D$9="","",'PyG 3 Años'!$D$19/('PyG 3 Años'!$D$6*'PyG 3 Años'!$D$8)),"") -> 5.6885 | E9: Sale del total de costes variables del P&L, no de una estimación aparte. Incluye los varios e imprevistos, que son un porcentaje de las ventas
A10: Margen de contribución por comensal | B10: =IFERROR(IF('PyG 3 Años'!$B$9="","",B8-B9),"") -> 9.8115 | C10: =IFERROR(IF('PyG 3 Años'!$C$9="","",C8-C9),"") -> 9.8115 | D10: =IFERROR(IF('PyG 3 Años'!$D$9="","",D8-D9),"") -> 9.8115 | E10: Ticket menos coste variable unitario
A11: Días de apertura al año | B11: =IFERROR(IF('PyG 3 Años'!$B$9="","",'PyG 3 Años'!$B$8),"") -> 300 | C11: =IFERROR(IF('PyG 3 Años'!$C$9="","",'PyG 3 Años'!$C$8),"") -> 300 | D11: =IFERROR(IF('PyG 3 Años'!$D$9="","",'PyG 3 Años'!$D$8),"") -> 300 | E11: El mismo calendario que el P&L y que los escenarios
A12: Devolución de principal del año (cuota) | B12: =IFERROR(IF('PyG 3 Años'!$B$9="","",'Financiación'!$B$45),"") -> 0 | C12: =IFERROR(IF('PyG 3 Años'!$C$9="","",'Financiación'!$B$47),"") -> 16916.79 | D12: =IFERROR(IF('PyG 3 Años'!$D$9="","",'Financiación'!$B$49),"") -> 17931.798 | E12: El principal NO es gasto del P&L, pero sale de la caja. Sin él, el umbral de equilibrio se publica por debajo del real
A13: PUNTO DE EQUILIBRIO CONTABLE (incluye amortización)
A14: Comensales necesarios al año | B14: =IFERROR(IF('PyG 3 Años'!$B$9="","",IF(B10<=0,"",B6/B10)),"") -> 19195.405 | C14: =IFERROR(IF('PyG 3 Años'!$C$9="","",IF(C10<=0,"",C6/C10)),"") -> 19806.933 | D14: =IFERROR(IF('PyG 3 Años'!$D$9="","",IF(D10<=0,"",D6/D10)),"") -> 20315.009
A15: Comensales necesarios al día | B15: =IFERROR(IF('PyG 3 Años'!$B$9="","",B14/B11),"") -> 63.984685 | C15: =IFERROR(IF('PyG 3 Años'!$C$9="","",C14/C11),"") -> 66.023109 | D15: =IFERROR(IF('PyG 3 Años'!$D$9="","",D14/D11),"") -> 67.716697
A16: Ingresos necesarios al año | B16: =IFERROR(IF('PyG 3 Años'!$B$9="","",B14*B8),"") -> 297528.78 | C16: =IFERROR(IF('PyG 3 Años'!$C$9="","",C14*C8),"") -> 307007.46 | D16: =IFERROR(IF('PyG 3 Años'!$D$9="","",D14*D8),"") -> 314882.64
A17: PUNTO DE EQUILIBRIO DE CAJA (incluye la cuota del préstamo)
A18: Costes fijos de caja + principal del año | B18: =IFERROR(IF('PyG 3 Años'!$B$9="","",B6-'PyG 3 Años'!$B$35+B12),"") -> 179400.72 | C18: =IFERROR(IF('PyG 3 Años'!$C$9="","",C6-'PyG 3 Años'!$C$35+C12),"") -> 202317.51 | D18: =IFERROR(IF('PyG 3 Años'!$D$9="","",D6-'PyG 3 Años'!$D$35+D12),"") -> 208317.51 | E18: Los fijos del P&L sin la amortización (que no se paga) y CON la devolución de principal (que sí). Es el umbral que decide si la caja aguanta
A19: Comensales necesarios al año (caja) | B19: =IFERROR(IF('PyG 3 Años'!$B$9="","",IF(B10<=0,"",B18/B10)),"") -> 18284.739 | C19: =IFERROR(IF('PyG 3 Años'!$C$9="","",IF(C10<=0,"",C18/C10)),"") -> 20620.446 | D19: =IFERROR(IF('PyG 3 Años'!$D$9="","",IF(D10<=0,"",D18/D10)),"") -> 21231.974
A20: Comensales necesarios al día (caja) | B20: =IFERROR(IF('PyG 3 Años'!$B$9="","",B19/B11),"") -> 60.949131 | C20: =IFERROR(IF('PyG 3 Años'!$C$9="","",C19/C11),"") -> 68.734821 | D20: =IFERROR(IF('PyG 3 Años'!$D$9="","",D19/D11),"") -> 70.773246
A21: Ingresos necesarios al año (caja) | B21: =IFERROR(IF('PyG 3 Años'!$B$9="","",B19*B8),"") -> 283413.46 | C21: =IFERROR(IF('PyG 3 Años'!$C$9="","",C19*C8),"") -> 319616.92 | D21: =IFERROR(IF('PyG 3 Años'!$D$9="","",D19*D8),"") -> 329095.59
A22: CONTRASTE CON EL PLAN
A23: Comensales/día previstos en el plan | B23: =IFERROR(IF('PyG 3 Años'!$B$9="","",'PyG 3 Años'!$B$6),"") -> 77 | C23: =IFERROR(IF('PyG 3 Años'!$C$9="","",'PyG 3 Años'!$C$6),"") -> 81.62 | D23: =IFERROR(IF('PyG 3 Años'!$D$9="","",'PyG 3 Años'!$D$6),"") -> 84.8848
A24: Holgura sobre el equilibrio de CAJA (%) | B24: =IFERROR(IF('PyG 3 Años'!$B$9="","",B23/B20-1),"") -> 0.26334861 | C24: =IFERROR(IF('PyG 3 Años'!$C$9="","",C23/C20-1),"") -> 0.18746217 | D24: =IFERROR(IF('PyG 3 Años'!$D$9="","",D23/D20-1),"") -> 0.19939109 | E24: Cuánto puedes caer antes de no poder pagar los costes fijos y la cuota. El mínimo exigible está en la hoja de Supuestos
A25: Rotaciones al día que da el local como máximo | B25: 3 | E25: Servicios completos por plaza y día que puedes hacer con comidas, cenas y un segundo turno de cena el sábado (estancias de 35-45 minutos). Es el techo físico del local, no un objetivo
A26: Rotaciones al día que exige el equilibrio de caja | B26: =IFERROR(IF('PyG 3 Años'!$B$9="","",B20/'0. Supuestos'!$B$51),"") -> 1.9046603 | C26: =IFERROR(IF('PyG 3 Años'!$C$9="","",C20/'0. Supuestos'!$B$51),"") -> 2.1479632 | D26: =IFERROR(IF('PyG 3 Años'!$D$9="","",D20/'0. Supuestos'!$B$51),"") -> 2.2116639 | E26: Comensales de equilibrio entre las plazas que declara la hoja de Supuestos. Por encima del techo de arriba, el punto de equilibrio está fuera del alcance del local
A27: INTERPRETACIÓN
A28: =IFERROR("Con el ticket medio sin IVA de la fila de arriba necesitas "&TEXT(ROUNDUP(B15,0),"0")&" comensales al día durante los "&TEXT(B11,"0")&" días que abres para no perder dinero (equilibrio contable, con la amortización dentro), y "&TEXT(ROUNDUP(B20,0),"0")&" para que la caja aguante (equilibrio de caja: sin la amortización, que no se paga, y con la cuota del préstamo del año"&IF(B12=0,"; este año sólo intereses, porque el préstamo está en carencia","")&"). En las filas «Ingresos necesarios al año» tienes esas mismas cifras en euros.","") -> Con el ticket medio sin IVA de la fila de arriba necesitas 64 comensales al día durante los 300 días que abres para no perder dinero (equilibrio contable, con la amortización dentro), y 61 para que la caja aguante (equilibrio de caja: sin la amortización, que no se paga, y con la cuota del préstamo del año; este año sólo intereses, porque el préstamo está en carencia). En las filas «Ingresos necesarios al año» tienes esas mismas cifras en euros.
A30: SENSIBILIDAD DEL PUNTO DE EQUILIBRIO
A31: Comensales/día necesarios para cubrir costes según el ticket medio (columnas) y el coste variable por comensal (filas). En verde, los que están por debajo de los comensales que prevé el plan.
A33: Comensales/día necesarios: ticket medio sin IVA (columnas) × coste variable por comensal (filas) | B33: =IFERROR($B$8-2,"") -> 13.5 | C33: =IFERROR(IF($B$8="","",$B$8),"") -> 15.5 | D33: =IFERROR($B$8+2,"") -> 17.5 | E33: =IFERROR($B$8+4,"") -> 19.5
A34: =IFERROR($B$9*0.85,"") -> 4.835225 | B34: =IFERROR(IF($B$33-$A34<=0,"",$B$6/($B$33-$A34)/$B$11),"") -> 72.45263 | C34: =IFERROR(IF($C$33-$A34<=0,"",$B$6/($C$33-$A34)/$B$11),"") -> 58.865352 | D34: =IFERROR(IF($D$33-$A34<=0,"",$B$6/($D$33-$A34)/$B$11),"") -> 49.569434 | E34: =IFERROR(IF($E$33-$A34<=0,"",$B$6/($E$33-$A34)/$B$11),"") -> 42.809094
A35: =IFERROR($B$9*0.925,"") -> 5.2618625 | B35: =IFERROR(IF($B$33-$A35<=0,"",$B$6/($B$33-$A35)/$B$11),"") -> 76.204814 | C35: =IFERROR(IF($C$33-$A35<=0,"",$B$6/($C$33-$A35)/$B$11),"") -> 61.318353 | D35: =IFERROR(IF($D$33-$A35<=0,"",$B$6/($D$33-$A35)/$B$11),"") -> 51.29749 | E35: =IFERROR(IF($E$33-$A35<=0,"",$B$6/($E$33-$A35)/$B$11),"") -> 44.091844
A36: =IFERROR($B$9*1.0,"") -> 5.6885 | B36: =IFERROR(IF($B$33-$A36<=0,"",$B$6/($B$33-$A36)/$B$11),"") -> 80.366861 | C36: =IFERROR(IF($C$33-$A36<=0,"",$B$6/($C$33-$A36)/$B$11),"") -> 63.984685 | D36: =IFERROR(IF($D$33-$A36<=0,"",$B$6/($D$33-$A36)/$B$11),"") -> 53.150382 | E36: =IFERROR(IF($E$33-$A36<=0,"",$B$6/($E$33-$A36)/$B$11),"") -> 45.453842
A37: =IFERROR($B$9*1.075,"") -> 6.1151375 | B37: =IFERROR(IF($B$33-$A37<=0,"",$B$6/($B$33-$A37)/$B$11),"") -> 85.009807 | C37: =IFERROR(IF($C$33-$A37<=0,"",$B$6/($C$33-$A37)/$B$11),"") -> 66.89344 | D37: =IFERROR(IF($D$33-$A37<=0,"",$B$6/($D$33-$A37)/$B$11),"") -> 55.142145 | E37: =IFERROR(IF($E$33-$A37<=0,"",$B$6/($E$33-$A37)/$B$11),"") -> 46.902666
A38: =IFERROR($B$9*1.15,"") -> 6.541775 | B38: =IFERROR(IF($B$33-$A38<=0,"",$B$6/($B$33-$A38)/$B$11),"") -> 90.222109 | C38: =IFERROR(IF($C$33-$A38<=0,"",$B$6/($C$33-$A38)/$B$11),"") -> 70.079255 | D38: =IFERROR(IF($D$33-$A38<=0,"",$B$6/($D$33-$A38)/$B$11),"") -> 57.288998 | E38: =IFERROR(IF($E$33-$A38<=0,"",$B$6/($E$33-$A38)/$B$11),"") -> 48.446892

Sheet Escenarios
A1: ANÁLISIS DE ESCENARIOS
A2: Pesimista / Realista / Optimista — Año 1
A4: Métrica | B4: Pesimista | C4: Realista | D4: Optimista | E4: Notas
A5: Comensales/día | B5: 65 | C5: =IFERROR(IF('PyG 3 Años'!$B$6="","",'PyG 3 Años'!$B$6),"") -> 77 | D5: 88
A6: Ticket medio sin IVA | B6: 14.75 | C6: =IFERROR(IF('PyG 3 Años'!$B$7="","",'PyG 3 Años'!$B$7),"") -> 15.5 | D6: 16.5
A7: Días de apertura al año | B7: 295 | C7: =IFERROR(IF('PyG 3 Años'!$B$8="","",'PyG 3 Años'!$B$8),"") -> 300 | D7: 305
A8: INGRESOS ANUALES (sin IVA) | B8: =IFERROR(IF(B5*B6*B7=0,"",B5*B6*B7),"") -> 282831.25 | C8: =IFERROR(IF(C5*C6*C7=0,"",C5*C6*C7),"") -> 358050 | D8: =IFERROR(IF(D5*D6*D7=0,"",D5*D6*D7),"") -> 442860
A9: Coste de mercancía — comida | B9: =IFERROR(IF(B8="","",B8*'0. Supuestos'!$B$11*'0. Supuestos'!$B$13),"") -> 61091.55 | C9: =IFERROR(IF(C8="","",C8*'0. Supuestos'!$B$11*'0. Supuestos'!$B$13),"") -> 77338.8 | D9: =IFERROR(IF(D8="","",D8*'0. Supuestos'!$B$11*'0. Supuestos'!$B$13),"") -> 95657.76
A10: Coste de mercancía — bebida | B10: =IFERROR(IF(B8="","",B8*'0. Supuestos'!$B$12*'0. Supuestos'!$B$14),"") -> 14707.225 | C10: =IFERROR(IF(C8="","",C8*'0. Supuestos'!$B$12*'0. Supuestos'!$B$14),"") -> 18618.6 | D10: =IFERROR(IF(D8="","",D8*'0. Supuestos'!$B$12*'0. Supuestos'!$B$14),"") -> 23028.72
A11: Consumibles y envases | B11: =IFERROR(IF(B8="","",B8*'0. Supuestos'!$B$15),"") -> 9899.0938 | C11: =IFERROR(IF(C8="","",C8*'0. Supuestos'!$B$15),"") -> 12531.75 | D11: =IFERROR(IF(D8="","",D8*'0. Supuestos'!$B$15),"") -> 15500.1
A12: Comisiones de delivery | B12: =IFERROR(IF(B8="","",B8*'0. Supuestos'!$B$16*'0. Supuestos'!$B$17),"") -> 10181.925 | C12: =IFERROR(IF(C8="","",C8*'0. Supuestos'!$B$16*'0. Supuestos'!$B$17),"") -> 12889.8 | D12: =IFERROR(IF(D8="","",D8*'0. Supuestos'!$B$16*'0. Supuestos'!$B$17),"") -> 15942.96
A13: Comisiones de los medios de pago | B13: =IFERROR(IF(B8="","",B8*'0. Supuestos'!$B$18),"") -> 2262.65 | C13: =IFERROR(IF(C8="","",C8*'0. Supuestos'!$B$18),"") -> 2864.4 | D13: =IFERROR(IF(D8="","",D8*'0. Supuestos'!$B$18),"") -> 3542.88
A14: Varios e imprevistos | B14: =IFERROR(IF(B8="","",B8*'0. Supuestos'!$B$28),"") -> 5656.625 | C14: =IFERROR(IF(C8="","",C8*'0. Supuestos'!$B$28),"") -> 7161 | D14: =IFERROR(IF(D8="","",D8*'0. Supuestos'!$B$28),"") -> 8857.2
A15: TOTAL COSTES VARIABLES | B15: =IFERROR(IF(B8="","",SUM(B9:B14)),"") -> 103799.07 | C15: =IFERROR(IF(C8="","",SUM(C9:C14)),"") -> 131404.35 | D15: =IFERROR(IF(D8="","",SUM(D9:D14)),"") -> 162529.62
A16: MARGEN BRUTO | B16: =IFERROR(IF(B8="","",B8-B15),"") -> 179032.18 | C16: =IFERROR(IF(C8="","",C8-C15),"") -> 226645.65 | D16: =IFERROR(IF(D8="","",D8-D15),"") -> 280330.38
A17: COSTES FIJOS (los del P&L) | B17: =IFERROR(IF(B8="","",'PyG 3 Años'!$B$37),"") -> 188335.72 | C17: =IFERROR(IF(C8="","",'PyG 3 Años'!$B$37),"") -> 188335.72 | D17: =IFERROR(IF(D8="","",'PyG 3 Años'!$B$37),"") -> 188335.72 | E17: Los costes fijos no cambian con el escenario: por eso son fijos
A18: RESULTADO ANTES DE IMPUESTOS | B18: =IFERROR(IF(B8="","",B16-B17),"") -> -9303.5388 | C18: =IFERROR(IF(C8="","",C16-C17),"") -> 38309.93 | D18: =IFERROR(IF(D8="","",D16-D17),"") -> 91994.66
A19: Impuesto de Sociedades | B19: =IFERROR(IF(B8="","",MAX(0,B18-'0. Supuestos'!$B$42)*'0. Supuestos'!$B$37),"") -> 0 | C19: =IFERROR(IF(C8="","",MAX(0,C18-'0. Supuestos'!$B$42)*'0. Supuestos'!$B$37),"") -> 5746.4895 | D19: =IFERROR(IF(D8="","",MAX(0,D18-'0. Supuestos'!$B$42)*'0. Supuestos'!$B$37),"") -> 13799.199 | E19: Al tipo de entidad de nueva creación, compensando las bases negativas anteriores
A20: RESULTADO NETO | B20: =IFERROR(IF(B8="","",B18-B19),"") -> -9303.5388 | C20: =IFERROR(IF(C8="","",C18-C19),"") -> 32563.44 | D20: =IFERROR(IF(D8="","",D18-D19),"") -> 78195.461
A21: Comensales/día para el equilibrio | B21: =IFERROR(IF(B8="","",IF(B6-B15/(B5*B7)<=0,"",B17/(B6-B15/(B5*B7))/B7)),"") -> 68.377773 | C21: =IFERROR(IF(C8="","",IF(C6-C15/(C5*C7)<=0,"",C17/(C6-C15/(C5*C7))/C7)),"") -> 63.984685 | D21: =IFERROR(IF(D8="","",IF(D6-D15/(D5*D7)<=0,"",D17/(D6-D15/(D5*D7))/D7)),"") -> 59.121467
A22: LO QUE CADA ESCENARIO EXIGE
A23: Coste de personal / Ventas | B23: =IFERROR(IF(B8="","",'PyG 3 Años'!$B$23/B8),"") -> 0.45794346 | C23: =IFERROR(IF(C8="","",'PyG 3 Años'!$B$23/C8),"") -> 0.3617392 | D23: =IFERROR(IF(D8="","",'PyG 3 Años'!$B$23/D8),"") -> 0.29246426 | E23: La MISMA plantilla en los tres escenarios. Si en el pesimista se dispara, el ajuste hay que hacerlo en la hoja de Personal, no aquí
A24: Comensales al año por jornada equivalente | B24: =IFERROR(IF(B8="","",B5*B7/'Personal'!$C$12),"") -> 4168.4783 | C24: =IFERROR(IF(C8="","",C5*C7/'Personal'!$C$12),"") -> 5021.7391 | D24: =IFERROR(IF(D8="","",D5*D7/'Personal'!$C$12),"") -> 5834.7826 | E24: Comensales que tendría que sacar cada jornada completa del cuadro de Personal. En el optimista dice si hace falta contratar
A25: Saldo de caja al cierre del año 1 (estimado, el mismo método en los tres escenarios) | B25: =IFERROR(IF(B8="","",'Inversión Inicial'!$B$29+B20+'PyG 3 Años'!$B$35-'Financiación'!$B$45),"") -> 44481.641 | C25: =IFERROR(IF(C8="","",'Inversión Inicial'!$B$29+C20+'PyG 3 Años'!$B$35-'Financiación'!$B$45),"") -> 86348.62 | D25: =IFERROR(IF(D8="","",'Inversión Inicial'!$B$29+D20+'PyG 3 Años'!$B$35-'Financiación'!$B$45),"") -> 131980.64 | E25: Saldo ESTIMADO: fondo de maniobra más el resultado del año, devolviendo la amortización (que no se paga) y restando el principal del préstamo. No incluye el desfase de cobros y pagos ni la liquidación del IVA, así que las tres columnas se pueden comparar entre sí. En rojo, el escenario se queda sin caja
A26: Saldo real del mes 12 de la hoja de Tesorería (sólo realista) | C26: =IFERROR(IF(C8="","",'Tesorería 12 meses'!$M$22),"") -> 115132.88 | E26: El saldo REAL del caso base, con su desfase de cobros y pagos y su liquidación de IVA. Sólo existe para el escenario realista, que es el único con tesorería mensual propia: por eso no está en la fila de arriba, donde se compararía contra dos estimaciones
A28: La columna «Realista» lee sus tres datos de la hoja de Supuestos, así que reproduce EXACTAMENTE el año 1 del P&L. Los otros dos escenarios usan las mismas tasas de coste: lo único que cambia son los comensales, el ticket y los días. Los COSTES FIJOS sí son los mismos en los tres: los varios e imprevistos, que son un porcentaje de las ventas, van arriba con los variables y cada escenario carga los suyos.

Sheet Personal
A1: ESTRUCTURA DE PERSONAL Y COSTES
A2: =IFERROR("Convenio Hostelería — "&TEXT('0. Supuestos'!$B$21,"0")&" pagas + SS "&TEXT('0. Supuestos'!$B$20*100,"0")&" %","") -> Convenio Hostelería — 14 pagas + SS 33 %
A4: Puesto | B4: Personas | C4: Jornada | D4: Bruto mes (€, total del puesto) | E4: Seg. Social a cargo de la empresa (€) | F4: Coste mes (€, total del puesto) | G4: Coste año (€) | H4: Horas/semana por persona | I4: Horas/año del puesto | J4: Notas
A5: Titular — taquero/a jefe: marinado, trompo, compras y gestión | B5: 1 | C5: 1 | D5: 1900 | E5: =IFERROR(IF(D5="","",D5*'0. Supuestos'!$B$20),"") -> 627 | F5: =IFERROR(IF(D5="","",D5+E5),"") -> 2527 | G5: =IFERROR(IF(D5="","",F5*MAX(12,'0. Supuestos'!$B$21)),"") -> 35378 | H5: =IFERROR(IF(D5="","",C5*$B$19),"") -> 40 | I5: =IFERROR(IF(D5="","",H5*B5*$B$20),"") -> 1840 | J5: Marina y monta el trompo, lleva el corte en el turno fuerte, compra (el importador de chiles y producto mexicano incluido) y gestiona. Como administrador de la SL cotiza en el régimen de autónomos: el libro le imputa el 33 % de Seguridad Social sobre 14 pagas como si fuera nómina, que es el lado prudente. Confirma con tu gestoría la cuota real y si te aplica la reducida de inicio
A6: Taquero/a de trompo, plancha y comal | B6: 1 | C6: 1 | D6: 1450 | E6: =IFERROR(IF(D6="","",D6*'0. Supuestos'!$B$20),"") -> 478.5 | F6: =IFERROR(IF(D6="","",D6+E6),"") -> 1928.5 | G6: =IFERROR(IF(D6="","",F6*MAX(12,'0. Supuestos'!$B$21)),"") -> 26999 | H6: =IFERROR(IF(D6="","",C6*$B$19),"") -> 40 | I6: =IFERROR(IF(D6="","",H6*B6*$B$20),"") -> 1840 | J6: Corta el trompo, lleva la plancha y el comal y sabe marinar con el titular. Es inversión, no gasto: si sólo el titular sabe marinar y cortar el trompo, una baja cierra la taquería
A7: Cocinero/a de producción y salsas | B7: 1 | C7: 0.75 | D7: 1013 | E7: =IFERROR(IF(D7="","",D7*'0. Supuestos'!$B$20),"") -> 334.29 | F7: =IFERROR(IF(D7="","",D7+E7),"") -> 1347.29 | G7: =IFERROR(IF(D7="","",F7*MAX(12,'0. Supuestos'!$B$21)),"") -> 18862.06 | H7: =IFERROR(IF(D7="","",C7*$B$19),"") -> 30 | I7: =IFERROR(IF(D7="","",H7*B7*$B$20),"") -> 1380 | J7: Carnitas y guisados, salsas, aguas frescas, mise en place y friegue, 30 horas a la semana
A8: Encargado/a de sala, barra y mostrador | B8: 1 | C8: 1 | D8: 1450 | E8: =IFERROR(IF(D8="","",D8*'0. Supuestos'!$B$20),"") -> 478.5 | F8: =IFERROR(IF(D8="","",D8+E8),"") -> 1928.5 | G8: =IFERROR(IF(D8="","",F8*MAX(12,'0. Supuestos'!$B$21)),"") -> 26999 | H8: =IFERROR(IF(D8="","",C8*$B$19),"") -> 40 | I8: =IFERROR(IF(D8="","",H8*B8*$B$20),"") -> 1840 | J8: Todo el año: sala, barra, caja, pedidos para llevar, la tablet de las plataformas y la información de alérgenos
A9: Camarero/a de cenas y fines de semana | B9: 1 | C9: 0.5 | D9: 675 | E9: =IFERROR(IF(D9="","",D9*'0. Supuestos'!$B$20),"") -> 222.75 | F9: =IFERROR(IF(D9="","",D9+E9),"") -> 897.75 | G9: =IFERROR(IF(D9="","",F9*MAX(12,'0. Supuestos'!$B$21)),"") -> 12568.5 | H9: =IFERROR(IF(D9="","",C9*$B$19),"") -> 20 | I9: =IFERROR(IF(D9="","",H9*B9*$B$20),"") -> 920 | J9: 20 horas a la semana: las cenas y el fin de semana, cuando la sala se llena
A10: Refuerzo de viernes a domingo: barra, terraza y recogidas | B10: 1 | C10: 0.25 | D10: 338 | E10: =IFERROR(IF(D10="","",D10*'0. Supuestos'!$B$20),"") -> 111.54 | F10: =IFERROR(IF(D10="","",D10+E10),"") -> 449.54 | G10: =IFERROR(IF(D10="","",F10*MAX(12,'0. Supuestos'!$B$21)),"") -> 6293.56 | H10: =IFERROR(IF(D10="","",C10*$B$19),"") -> 10 | I10: =IFERROR(IF(D10="","",H10*B10*$B$20),"") -> 460 | J10: Barra y terraza en temporada y el mostrador de recogidas. Este plan NO tiene reparto propio: si lo pones, el repartidor va con contrato laboral del convenio de hostelería, nunca como autónomo
A11: Suplencias de vacaciones y descansos | B11: 1 | C11: 0.1 | D11: 130 | E11: =IFERROR(IF(D11="","",D11*'0. Supuestos'!$B$20),"") -> 42.9 | F11: =IFERROR(IF(D11="","",D11+E11),"") -> 172.9 | G11: =IFERROR(IF(D11="","",F11*MAX(12,'0. Supuestos'!$B$21)),"") -> 2420.6 | H11: =IFERROR(IF(D11="","",C11*$B$19),"") -> 4 | I11: =IFERROR(IF(D11="","",H11*B11*$B$20),"") -> 184 | J11: Cobertura de los 30 días de vacaciones (art. 38 ET) y del descanso semanal del equipo de todo el año
A12: TOTAL PLANTILLA | B12: =IFERROR(IF(COUNT(D5:D11)=0,"",SUM(B5:B11)),"") -> 7 | C12: =IFERROR(IF(COUNT(D5:D11)=0,"",SUM(C5:C11)),"") -> 4.6 | D12: =IFERROR(IF(COUNT(D5:D11)=0,"",SUM(D5:D11)),"") -> 6956 | E12: =IFERROR(IF(COUNT(D5:D11)=0,"",SUM(E5:E11)),"") -> 2295.48 | F12: =IFERROR(IF(COUNT(D5:D11)=0,"",SUM(F5:F11)),"") -> 9251.48 | G12: =IFERROR(IF(COUNT(D5:D11)=0,"",SUM(G5:G11)),"") -> 129520.72 | I12: =IFERROR(IF(COUNT(D5:D11)=0,"",SUM(I5:I11)),"") -> 8464
A13: CRECIMIENTO DE LA PLANTILLA (coste escalonado)
A14: Coste anual de las incorporaciones del año 2 (€) | B14: 6000 | J14: Coste ANUAL completo (bruto + Seguridad Social × pagas) de lo que se contrate ese año. El P&L lo suma al coste del año anterior: la plantilla no crece con un porcentaje, crece con personas
A15: Coste anual de las incorporaciones del año 3 (€) | B15: 6000 | J15: Coste ANUAL completo (bruto + Seguridad Social × pagas) de lo que se contrate ese año. El P&L lo suma al coste del año anterior: la plantilla no crece con un porcentaje, crece con personas
A16: Coste de personal del año 2 | B16: =IFERROR(IF(G12="","",G12*(1+'0. Supuestos'!$B$48)+B14),"") -> 135520.72
A17: Coste de personal del año 3 | B17: =IFERROR(IF(B16="","",B16*(1+'0. Supuestos'!$B$48)+B15),"") -> 141520.72
A18: COBERTURA POR HORAS DE SERVICIO
A19: Jornada completa del convenio (horas/semana) | B19: 40 | J19: Art. 34.1 del Estatuto de los Trabajadores; tu convenio provincial puede fijar menos
A20: Semanas trabajadas al año por persona | B20: 46 | J20: 46 semanas: 52 menos las vacaciones (30 días naturales, art. 38 ET), los festivos y las ausencias medias
A21: Horas de servicio al día que hay que cubrir | B21: 8.5 | J21: Horas con el local abierto al público, sumando las comidas (13:30-16:30) y las cenas (20:00-23:30) y la preparación de cada servicio. La tarde de cierre entre los dos no se cuenta
A22: Personas necesarias a la vez en cada franja | B22: 2.7 | J22: Presencia media a la vez entre el trompo, la plancha o el comal, la sala y el mostrador. El sábado por la noche hacen falta cinco: entran el refuerzo y el camarero de cenas (el cuadrante anual no lo ve: ponlo en el turno)
A23: Horas de producción al día ANTES de abrir | B23: 2.5 | J23: Marinado del día siguiente, montaje del cono, carnitas y guisados, salsas y mise en place antes de abrir
A24: Personas en el turno de producción | B24: 1.5 | J24: El titular con el cocinero de producción. El cierre, la limpieza y las compras quedan fuera de este cuadrante: son el margen entre las horas contratadas y las necesarias
A25: Horas de servicio a cubrir al año | B25: =IFERROR(IF(OR(B21="",B22="",'0. Supuestos'!$B$6=""),"",B21*B22*'0. Supuestos'!$B$6+B23*B24*'0. Supuestos'!$B$6),"") -> 8010
A26: Horas contratadas al año | B26: =IFERROR(IF(I12="","",I12),"") -> 8464
A27: Cobertura (contratadas / necesarias) | B27: =IFERROR(B26/B25,"") -> 1.0566792 | J27: Por debajo del 100 % la plantilla no llega a cubrir el horario que declara el plan: o se contrata más o se recorta el horario
A29: Las columnas «Bruto mes», «Seg. Social», «Coste mes» y «Coste año» son TOTALES de la fila: en un puesto con dos personas incluyen a las dos. «Jornada» es el porcentaje sobre la jornada completa del convenio y sirve para comparar el salario con el suelo legal en proporción. El tipo de Seguridad Social y el número de pagas están en la hoja «0. Supuestos».
A30: El suelo salarial es el MAYOR entre el SMI y el salario de convenio, los dos en la hoja «0. Supuestos»; las jornadas parciales lo llevan en proporción. El convenio aplicable es el PROVINCIAL de hostelería: no existe una tabla salarial estatal única, así que la celda del convenio se entrega vacía para que copies la de tu provincia.

Sheet Instrucciones
A1: INSTRUCCIONES DE USO — Plan financiero Taquería
A3: CÓMO SE USA ESTE LIBRO
A4: Este plan financiero es un MODELO: sólo se teclea en las celdas VERDES y el resto se recalcula solo.
A5: 1. «0. Supuestos» es la hoja de mando: comensales, ticket sin IVA, días de apertura, mezcla de comida y bebida, coste de mercancía, alquiler, financiación e impuestos.
A6: 2. Las partidas de la inversión, los costes fijos y la plantilla se teclean en su propia hoja, también en verde. Ningún número se escribe dos veces.
A7: 3. En «Punto Equilibrio» sólo se teclea el techo de rotaciones que da tu local; todo lo demás se deriva de lo anterior. En las otras tres hojas también hay celdas verdes que puedes tocar: el escenario pesimista y el optimista en «Escenarios», la estacionalidad y la rampa de arranque en «Tesorería 12 meses», y las cuatro fuentes alternativas de financiación en «Financiación». Todo lo demás se calcula.
A8: 4. Todas las cifras van SIN IVA. Para pasar un PVP a precio sin IVA, divide por el tipo que le corresponda: entre 1,10 en sala (comida y bebida, alcohol incluido: art. 91.Uno.2.2.º de la Ley 37/1992 del IVA) y, cuando se venden para llevar, los alimentos —los tacos incluidos—, que son productos alimenticios al tipo reducido por el art. 91.Uno.1.1.º; y entre 1,21 el tipo general, que en hostelería sólo alcanza a lo que sale del local como entrega de bienes excluida del reducido: el alcohol y las aguas frescas, los refrescos o los zumos con azúcares o edulcorantes añadidos para llevar o a domicilio (la comida para llevar sigue al 10 %); el libro lo aplica a la parte de la bebida que declara la columna H de su línea en el P&L. El tipo de cada línea de venta está en la columna «Tipo de IVA de la línea» del P&L y de ahí salen los cobros, el IVA repercutido y el PVP equivalente. El IVA de la inversión se adelanta y se recupera con el modelo 303.
A9: 5. Si cambias la plantilla, el P&L la lee sola: el coste de personal sale de la hoja «Personal», no de una estimación aparte.
A10: 6. La hoja «Tesorería 12 meses» responde la pregunta que decide una operación bancaria: en qué mes se agota la caja. Su Mes 1 es ENERO, en el orden del calendario: la rampa del arranque cae sobre enero y febrero, los meses más flojos, y por eso el fondo de maniobra cuenta. Si abres en otro mes, gira la fila de estacionalidad. El saldo mínimo del año nunca puede salir en rojo.
A11: 7. La hoja «Financiación» cuadra lo que hace falta con lo que se aporta y monta el cuadro de amortización del préstamo. Si la diferencia sale en rojo, el plan no está financiado.
A12: 8. El plan de negocio en Word de este pack cita las cifras de este Excel: si cambias una celda verde, el Excel manda. La calculadora del trompo y escandallo del pack va aparte y sirve para medir el rendimiento del cono y ESCANDALLAR cada taco: no copies el food cost de un taco en la hoja de Supuestos. La celda «Coste de mercancía sobre las ventas de COMIDA» es la media ponderada de TODA la carta (tacos, gringas, guisados, guacamole y postres, cada uno por lo que vende) más la merma, y por eso sale más alta que el food cost del taco al pastor. Con los escandallos de tu carta, comprueba que esa media cuadra.
A14: RATIOS QUE AUDITA EL LIBRO
A15: Los umbrales viven en la columna «Umbral» del bloque RATIOS CLAVE del P&L: cámbialos ahí y el semáforo cambia con ellos.
A17: Ratio | B17: Valor del año 1 | C17: Umbral | D17: Estado
A18: Coste de mercancía / Ventas | B18: =IFERROR(IF('PyG 3 Años'!$B$52="","",'PyG 3 Años'!$B$52),"") -> 0.268 | C18: =IFERROR(IF('PyG 3 Años'!$E$52="","",'PyG 3 Años'!$E$52),"") -> 0.29 | D18: =IFERROR(IF(OR(B18="",C18=""),"",IF(B18<=C18,"CUMPLE","REVISAR")),"") -> CUMPLE
A19: Coste de personal / Ventas | B19: =IFERROR(IF('PyG 3 Años'!$B$53="","",'PyG 3 Años'!$B$53),"") -> 0.3617392 | C19: =IFERROR(IF('PyG 3 Años'!$E$53="","",'PyG 3 Años'!$E$53),"") -> 0.38 | D19: =IFERROR(IF(OR(B19="",C19=""),"",IF(B19<=C19,"CUMPLE","REVISAR")),"") -> CUMPLE
A20: Alquiler / Ventas | B20: =IFERROR(IF('PyG 3 Años'!$B$54="","",'PyG 3 Años'!$B$54),"") -> 0.048596565 | C20: =IFERROR(IF('PyG 3 Años'!$E$54="","",'PyG 3 Años'!$E$54),"") -> 0.1 | D20: =IFERROR(IF(OR(B20="",C20=""),"",IF(B20<=C20,"CUMPLE","REVISAR")),"") -> CUMPLE
A21: Resultado neto / Ventas | B21: =IFERROR(IF('PyG 3 Años'!$B$55="","",'PyG 3 Años'!$B$55),"") -> 0.090946629 | C21: =IFERROR(IF('PyG 3 Años'!$E$55="","",'PyG 3 Años'!$E$55),"") -> 0.05 | D21: =IFERROR(IF(OR(B21="",C21=""),"",IF(B21>=C21,"CUMPLE","REVISAR")),"") -> CUMPLE
A22: Margen bruto / Ventas | B22: =IFERROR(IF('PyG 3 Años'!$B$50="","",'PyG 3 Años'!$B$50),"") -> 0.633 | C22: =IFERROR(IF('PyG 3 Años'!$E$50="","",'PyG 3 Años'!$E$50),"") -> 0.6 | D22: =IFERROR(IF(OR(B22="",C22=""),"",IF(B22>=C22,"CUMPLE","REVISAR")),"") -> CUMPLE
A24: CIFRAS DE ESTE PLAN
A25: Inversión total (suma de los bloques) | B25: =IFERROR(IF('Inversión Inicial'!$B$30="","",'Inversión Inicial'!$B$30),"") -> 151000.18
A26: Necesidad total de caja al arranque | B26: =IFERROR(IF('Inversión Inicial'!$B$33="","",'Inversión Inicial'!$B$33),"") -> 172052.68
A27: Fondo de maniobra dotado | B27: =IFERROR(IF('Inversión Inicial'!$B$29="","",'Inversión Inicial'!$B$29),"") -> 44850.18
A28: Facturación prevista del año 1 | B28: =IFERROR(IF('PyG 3 Años'!$B$9="","",'PyG 3 Años'!$B$9),"") -> 358050
A29: Resultado neto del año 1 | B29: =IFERROR(IF('PyG 3 Años'!$B$47="","",'PyG 3 Años'!$B$47),"") -> 32563.44
A30: Comensales/día para el punto de equilibrio CONTABLE (con la amortización dentro) | B30: =IFERROR(IF('Punto Equilibrio'!$B$15="","",'Punto Equilibrio'!$B$15),"") -> 63.984685
A31: Payback del proyecto (años), antes de la deuda | B31: =IFERROR(IF('Tesorería 12 meses'!$B$31="","",'Tesorería 12 meses'!$B$31),"") -> 2.9
A33: DATOS DE REFERENCIA DEL SECTOR
A34: Referencia | B34: Valor | C34: Fuente | D34: Nota
A35: Mes 1 del plan | B35: Enero | C35: Decisión del plan | D35: En el orden del calendario: la rampa cae sobre los meses más flojos y el fondo de maniobra lo cubre. Si abres en otro mes, gira la fila de estacionalidad de la Tesorería
A36: Taco al pastor en carta | B36: 2,50-3,50 € con IVA | C36: Cartas de taquerías casuales de Madrid, Valencia y Bilbao leídas en octubre de 2026 | D36: El caso lo pone a 3,00 € (la orden de 3, a 8,50 €). La taquería de volumen baja a 1-1,50 € y la de autor sube a 7-8 €
A37: Coste del taco al pastor | B37: Un 22,5 % de su precio sin IVA (un 24 % en la orden de 3) | C37: Estimación del kit con los gramajes de la calculadora del pack (editables) | D37: Tortilla, 35 g de carne servida, piña, cebolla, cilantro, lima y salsa, con un 5 % de merma. La carne y la tortilla no tienen precio profesional publicado: pon los de tu proveedor
A38: Rendimiento del trompo | B38: Unos 25 tacos por kg de carne cruda | C38: Puesto de Ciudad de México citado por Milenio (prensa) | D38: Con 35 g servidos y un 65 % de rendimiento salen unos 18-19 tacos por kg crudo: mide el tuyo con la calculadora del pack
A39: Trompo: asador vertical de gas de cuatro quemadores | B39: 1.279-1.784 € sin IVA | C39: Catálogo de asadores verticales de un distribuidor de hostelería, octubre de 2026 | D39: Para conos de 30-35 kg. El caso cuenta 1.800 € con la bandeja, los cuchillos y la base de la piña
A40: Comisión de la plataforma con su reparto | B40: 15-35 % más IVA | C40: Guías del sector, 2025-2026: compruébalo en tu contrato | D40: El plan básico de Uber Eats ronda el 30 %. Lo que se recoge en el local no paga comisión
A41: IVA de los tacos | B41: 10 % | C41: Ley 37/1992, art. 91.Uno.1.1.º y 2.2.º | D41: En sala, para llevar y a domicilio. El alcohol y las aguas frescas y los refrescos con azúcares o edulcorantes añadidos que salen del local, al 21 %
A42: Comidas preparadas en caliente y en frío | B42: ≥ 63 °C · 60 → 10 °C en < 2 h · 74 °C 15 s | C42: Real Decreto 1086/2020, art. 30, en la redacción del Real Decreto 1021/2022 | D42: Caliente a 63 °C o más; enfriado de 60 a 10 °C en menos de 2 h; recalentado a 74 °C durante 15 s en el centro, en la hora siguiente a sacarlo del frío; refrigeradas a 4 °C o menos (8 °C si duran menos de 24 h). El pastor marinado es preparado de carne: 4 °C o menos en cámara (Real Decreto 1021/2022, art. 4.1)
A43: Salario mínimo interprofesional 2026 | B43: 1.221 € al mes en 14 pagas | C43: Real Decreto 126/2026 | D43: A prorrata en jornada parcial
A44: Coste de personal sobre ventas | B44: 34-38 % | C44: Estimación del kit | D44: Con el titular de taquero jefe y un segundo taquero: el taquero único es un riesgo, no un ahorro
A45: Alquiler sobre ventas | B45: 5-10 % | C45: Estimación del kit | D45: Un local con salida de humos a cubierta cuesta más encontrarlo que pagarlo
A46: Convenio colectivo aplicable | B46: Provincial de hostelería | C46: VI Acuerdo Laboral de ámbito Estatal para el sector de Hostelería, art. 4 | D46: No nombra la «taquería»: entra como restaurante. Copia tu tabla salarial en la celda de Supuestos
A48: Para editar una celda que no esté en verde: Revisar → Desproteger hoja (no tiene contraseña).
A49: Más plantillas y kits del catálogo en aichef.pro/productos-digitales
A50: Diseñado por John Guerrero — chef y consultor gastronómico desde 2010, en cocina desde los 17 años · johnguerrero.es
A51: Versión 1.0 · noviembre 2026 · aichef.pro/plan-negocio-taqueria · info@aichef.pro

Sheet Tesorería 12 meses
A1: PREVISIÓN DE TESORERÍA — AÑO 1
A2: El P&L dice si el negocio gana dinero; esta hoja dice si le queda caja para llegar a fin de mes. Es la primera que mira un banco.
A4: Concepto | B4: Mes 1 (€) | C4: Mes 2 (€) | D4: Mes 3 (€) | E4: Mes 4 (€) | F4: Mes 5 (€) | G4: Mes 6 (€) | H4: Mes 7 (€) | I4: Mes 8 (€) | J4: Mes 9 (€) | K4: Mes 10 (€) | L4: Mes 11 (€) | M4: Mes 12 (€) | N4: Año (€)
A5: Estacionalidad del mes (suma 100 %) | B5: 0.07 | C5: 0.074 | D5: 0.082 | E5: 0.086 | F5: 0.088 | G5: 0.088 | H5: 0.084 | I5: 0.07 | J5: 0.088 | K5: 0.088 | L5: 0.086 | M5: 0.096 | N5: =IFERROR(IF('PyG 3 Años'!$B$9="","",SUM(B5:M5)),"") -> 1 | O5: Mes 1 = ENERO, en el orden del calendario: enero y agosto son los meses más flojos y los picos llegan en septiembre (Independencia de México, 15 y 16), noviembre (Día de Muertos) y diciembre. Si abres en otro mes, gira la fila. Tiene que sumar 100 %
A6: Rampa de arranque (% de la actividad de crucero) | B6: =IFERROR(IF('PyG 3 Años'!$B$9="","",MIN(1,'0. Supuestos'!$B$52+(1-'0. Supuestos'!$B$52)*0/MAX(1,'0. Supuestos'!$B$53-1))),"") -> 0.75 | C6: =IFERROR(IF('PyG 3 Años'!$B$9="","",MIN(1,'0. Supuestos'!$B$52+(1-'0. Supuestos'!$B$52)*1/MAX(1,'0. Supuestos'!$B$53-1))),"") -> 0.83333333 | D6: =IFERROR(IF('PyG 3 Años'!$B$9="","",MIN(1,'0. Supuestos'!$B$52+(1-'0. Supuestos'!$B$52)*2/MAX(1,'0. Supuestos'!$B$53-1))),"") -> 0.91666667 | E6: =IFERROR(IF('PyG 3 Años'!$B$9="","",MIN(1,'0. Supuestos'!$B$52+(1-'0. Supuestos'!$B$52)*3/MAX(1,'0. Supuestos'!$B$53-1))),"") -> 1 | F6: =IFERROR(IF('PyG 3 Años'!$B$9="","",MIN(1,'0. Supuestos'!$B$52+(1-'0. Supuestos'!$B$52)*4/MAX(1,'0. Supuestos'!$B$53-1))),"") -> 1 | G6: =IFERROR(IF('PyG 3 Años'!$B$9="","",MIN(1,'0. Supuestos'!$B$52+(1-'0. Supuestos'!$B$52)*5/MAX(1,'0. Supuestos'!$B$53-1))),"") -> 1 | H6: =IFERROR(IF('PyG 3 Años'!$B$9="","",MIN(1,'0. Supuestos'!$B$52+(1-'0. Supuestos'!$B$52)*6/MAX(1,'0. Supuestos'!$B$53-1))),"") -> 1 | I6: =IFERROR(IF('PyG 3 Años'!$B$9="","",MIN(1,'0. Supuestos'!$B$52+(1-'0. Supuestos'!$B$52)*7/MAX(1,'0. Supuestos'!$B$53-1))),"") -> 1 | J6: =IFERROR(IF('PyG 3 Años'!$B$9="","",MIN(1,'0. Supuestos'!$B$52+(1-'0. Supuestos'!$B$52)*8/MAX(1,'0. Supuestos'!$B$53-1))),"") -> 1 | K6: =IFERROR(IF('PyG 3 Años'!$B$9="","",MIN(1,'0. Supuestos'!$B$52+(1-'0. Supuestos'!$B$52)*9/MAX(1,'0. Supuestos'!$B$53-1))),"") -> 1 | L6: =IFERROR(IF('PyG 3 Años'!$B$9="","",MIN(1,'0. Supuestos'!$B$52+(1-'0. Supuestos'!$B$52)*10/MAX(1,'0. Supuestos'!$B$53-1))),"") -> 1 | M6: =IFERROR(IF('PyG 3 Años'!$B$9="","",MIN(1,'0. Supuestos'!$B$52+(1-'0. Supuestos'!$B$52)*11/MAX(1,'0. Supuestos'!$B$53-1))),"") -> 1 | O6: Sube en línea recta desde el porcentaje del mes 1 hasta el 100 % en los meses que digas en Supuestos. Con el mes 1 al 100 % la rampa desaparece
A7: Reparto de la actividad por mes (calculado) | B7: =IFERROR(IF('PyG 3 Años'!$B$9="","",B5*B6/SUMPRODUCT($B$5:$M$5,$B$6:$M$6)),"") -> 0.05449827 | C7: =IFERROR(IF('PyG 3 Años'!$B$9="","",C5*C6/SUMPRODUCT($B$5:$M$5,$B$6:$M$6)),"") -> 0.064013841 | D7: =IFERROR(IF('PyG 3 Años'!$B$9="","",D5*D6/SUMPRODUCT($B$5:$M$5,$B$6:$M$6)),"") -> 0.078027682 | E7: =IFERROR(IF('PyG 3 Años'!$B$9="","",E5*E6/SUMPRODUCT($B$5:$M$5,$B$6:$M$6)),"") -> 0.089273356 | F7: =IFERROR(IF('PyG 3 Años'!$B$9="","",F5*F6/SUMPRODUCT($B$5:$M$5,$B$6:$M$6)),"") -> 0.091349481 | G7: =IFERROR(IF('PyG 3 Años'!$B$9="","",G5*G6/SUMPRODUCT($B$5:$M$5,$B$6:$M$6)),"") -> 0.091349481 | H7: =IFERROR(IF('PyG 3 Años'!$B$9="","",H5*H6/SUMPRODUCT($B$5:$M$5,$B$6:$M$6)),"") -> 0.087197232 | I7: =IFERROR(IF('PyG 3 Años'!$B$9="","",I5*I6/SUMPRODUCT($B$5:$M$5,$B$6:$M$6)),"") -> 0.07266436 | ... M7: =IFERROR(IF('PyG 3 Años'!$B$9="","",M5*M6/SUMPRODUCT($B$5:$M$5,$B$6:$M$6)),"") -> 0.099653979 | N7: =IFERROR(IF('PyG 3 Años'!$B$9="","",SUM(B7:M7)),"") -> 1 | O7: Estacionalidad × rampa, normalizado a 100 %: el AÑO factura lo que dice el P&L, pero repartido como lo reparte un local que acaba de abrir
A8: COBROS
A9: Ventas cobradas (con IVA repercutido) | B9: =IFERROR(IF('PyG 3 Años'!$B$9="","",('PyG 3 Años'!$B$9+'PyG 3 Años'!$B$9*SUMPRODUCT('PyG 3 Años'!$E$10:$E$11,'PyG 3 Años'!$G$10:$G$11))*B7*(1-MIN(30,'0. Supuestos'!$B$58)/30)),"") -> 20063.505 | C9: =IFERROR(IF('PyG 3 Años'!$B$9="","",('PyG 3 Años'!$B$9+'PyG 3 Años'!$B$9*SUMPRODUCT('PyG 3 Años'!$E$10:$E$11,'PyG 3 Años'!$G$10:$G$11))*(C7*(1-MIN(30,'0. Supuestos'!$B$58)/30)+B7*MIN(30,'0. Supuestos'!$B$58)/30)),"") -> 24999.764 | D9: =IFERROR(IF('PyG 3 Años'!$B$9="","",('PyG 3 Años'!$B$9+'PyG 3 Años'!$B$9*SUMPRODUCT('PyG 3 Años'!$E$10:$E$11,'PyG 3 Años'!$G$10:$G$11))*(D7*(1-MIN(30,'0. Supuestos'!$B$58)/30)+C7*MIN(30,'0. Supuestos'!$B$58)/30)),"") -> 30409.177 | E9: =IFERROR(IF('PyG 3 Años'!$B$9="","",('PyG 3 Años'!$B$9+'PyG 3 Años'!$B$9*SUMPRODUCT('PyG 3 Años'!$E$10:$E$11,'PyG 3 Años'!$G$10:$G$11))*(E7*(1-MIN(30,'0. Supuestos'!$B$58)/30)+D7*MIN(30,'0. Supuestos'!$B$58)/30)),"") -> 34917.778 | F9: =IFERROR(IF('PyG 3 Años'!$B$9="","",('PyG 3 Años'!$B$9+'PyG 3 Años'!$B$9*SUMPRODUCT('PyG 3 Años'!$E$10:$E$11,'PyG 3 Años'!$G$10:$G$11))*(F7*(1-MIN(30,'0. Supuestos'!$B$58)/30)+E7*MIN(30,'0. Supuestos'!$B$58)/30)),"") -> 35977.823 | G9: =IFERROR(IF('PyG 3 Años'!$B$9="","",('PyG 3 Años'!$B$9+'PyG 3 Años'!$B$9*SUMPRODUCT('PyG 3 Años'!$E$10:$E$11,'PyG 3 Años'!$G$10:$G$11))*(G7*(1-MIN(30,'0. Supuestos'!$B$58)/30)+F7*MIN(30,'0. Supuestos'!$B$58)/30)),"") -> 36032.418 | H9: =IFERROR(IF('PyG 3 Años'!$B$9="","",('PyG 3 Años'!$B$9+'PyG 3 Años'!$B$9*SUMPRODUCT('PyG 3 Años'!$E$10:$E$11,'PyG 3 Años'!$G$10:$G$11))*(H7*(1-MIN(30,'0. Supuestos'!$B$58)/30)+G7*MIN(30,'0. Supuestos'!$B$58)/30)),"") -> 34503.769 | I9: =IFERROR(IF('PyG 3 Años'!$B$9="","",('PyG 3 Años'!$B$9+'PyG 3 Años'!$B$9*SUMPRODUCT('PyG 3 Años'!$E$10:$E$11,'PyG 3 Años'!$G$10:$G$11))*(I7*(1-MIN(30,'0. Supuestos'!$B$58)/30)+H7*MIN(30,'0. Supuestos'!$B$58)/30)),"") -> 29044.312 | J9: =IFERROR(IF('PyG 3 Años'!$B$9="","",('PyG 3 Años'!$B$9+'PyG 3 Años'!$B$9*SUMPRODUCT('PyG 3 Años'!$E$10:$E$11,'PyG 3 Años'!$G$10:$G$11))*(J7*(1-MIN(30,'0. Supuestos'!$B$58)/30)+I7*MIN(30,'0. Supuestos'!$B$58)/30)),"") -> 35541.066 | ... M9: =IFERROR(IF('PyG 3 Años'!$B$9="","",('PyG 3 Años'!$B$9+'PyG 3 Años'!$B$9*SUMPRODUCT('PyG 3 Años'!$E$10:$E$11,'PyG 3 Años'!$G$10:$G$11))*(M7*(1-MIN(30,'0. Supuestos'!$B$58)/30)+L7*MIN(30,'0. Supuestos'!$B$58)/30)),"") -> 39035.119 | N9: =IFERROR(IF('PyG 3 Años'!$B$9="","",SUM(B9:M9)),"") -> 391825.24 | O9: Ventas del mes con el IVA repercutido, corregidas por los días medios de cobro de la hoja de Supuestos
A10: PAGOS
A11: Compras y costes variables (IVA incluido) | B11: =IFERROR(IF('PyG 3 Años'!$B$9="","",-('PyG 3 Años'!$B$13*(1+'PyG 3 Años'!$G$13)+'PyG 3 Años'!$B$14*(1+'PyG 3 Años'!$G$14)+'PyG 3 Años'!$B$15*(1+'PyG 3 Años'!$G$15)+'PyG 3 Años'!$B$16*(1+'PyG 3 Años'!$G$16)+'PyG 3 Años'!$B$17*(1+'PyG 3 Años'!$G$17)+'PyG 3 Años'!$B$18*(1+'PyG 3 Años'!$G$18))*B7*(1-MIN(30,'0. Supuestos'!$B$59)/30)),"") -> 0 | C11: =IFERROR(IF('PyG 3 Años'!$B$9="","",-('PyG 3 Años'!$B$13*(1+'PyG 3 Años'!$G$13)+'PyG 3 Años'!$B$14*(1+'PyG 3 Años'!$G$14)+'PyG 3 Años'!$B$15*(1+'PyG 3 Años'!$G$15)+'PyG 3 Años'!$B$16*(1+'PyG 3 Años'!$G$16)+'PyG 3 Años'!$B$17*(1+'PyG 3 Años'!$G$17)+'PyG 3 Años'!$B$18*(1+'PyG 3 Años'!$G$18))*(C7*(1-MIN(30,'0. Supuestos'!$B$59)/30)+B7*MIN(30,'0. Supuestos'!$B$59)/30)),"") -> -8077.6452 | D11: =IFERROR(IF('PyG 3 Años'!$B$9="","",-('PyG 3 Años'!$B$13*(1+'PyG 3 Años'!$G$13)+'PyG 3 Años'!$B$14*(1+'PyG 3 Años'!$G$14)+'PyG 3 Años'!$B$15*(1+'PyG 3 Años'!$G$15)+'PyG 3 Años'!$B$16*(1+'PyG 3 Años'!$G$16)+'PyG 3 Años'!$B$17*(1+'PyG 3 Años'!$G$17)+'PyG 3 Años'!$B$18*(1+'PyG 3 Años'!$G$18))*(D7*(1-MIN(30,'0. Supuestos'!$B$59)/30)+C7*MIN(30,'0. Supuestos'!$B$59)/30)),"") -> -9488.0277 | E11: =IFERROR(IF('PyG 3 Años'!$B$9="","",-('PyG 3 Años'!$B$13*(1+'PyG 3 Años'!$G$13)+'PyG 3 Años'!$B$14*(1+'PyG 3 Años'!$G$14)+'PyG 3 Años'!$B$15*(1+'PyG 3 Años'!$G$15)+'PyG 3 Años'!$B$16*(1+'PyG 3 Años'!$G$16)+'PyG 3 Años'!$B$17*(1+'PyG 3 Años'!$G$17)+'PyG 3 Años'!$B$18*(1+'PyG 3 Años'!$G$18))*(E7*(1-MIN(30,'0. Supuestos'!$B$59)/30)+D7*MIN(30,'0. Supuestos'!$B$59)/30)),"") -> -11565.136 | F11: =IFERROR(IF('PyG 3 Años'!$B$9="","",-('PyG 3 Años'!$B$13*(1+'PyG 3 Años'!$G$13)+'PyG 3 Años'!$B$14*(1+'PyG 3 Años'!$G$14)+'PyG 3 Años'!$B$15*(1+'PyG 3 Años'!$G$15)+'PyG 3 Años'!$B$16*(1+'PyG 3 Años'!$G$16)+'PyG 3 Años'!$B$17*(1+'PyG 3 Años'!$G$17)+'PyG 3 Años'!$B$18*(1+'PyG 3 Años'!$G$18))*(F7*(1-MIN(30,'0. Supuestos'!$B$59)/30)+E7*MIN(30,'0. Supuestos'!$B$59)/30)),"") -> -13231.952 | G11: =IFERROR(IF('PyG 3 Años'!$B$9="","",-('PyG 3 Años'!$B$13*(1+'PyG 3 Años'!$G$13)+'PyG 3 Años'!$B$14*(1+'PyG 3 Años'!$G$14)+'PyG 3 Años'!$B$15*(1+'PyG 3 Años'!$G$15)+'PyG 3 Años'!$B$16*(1+'PyG 3 Años'!$G$16)+'PyG 3 Años'!$B$17*(1+'PyG 3 Años'!$G$17)+'PyG 3 Años'!$B$18*(1+'PyG 3 Años'!$G$18))*(G7*(1-MIN(30,'0. Supuestos'!$B$59)/30)+F7*MIN(30,'0. Supuestos'!$B$59)/30)),"") -> -13539.672 | H11: =IFERROR(IF('PyG 3 Años'!$B$9="","",-('PyG 3 Años'!$B$13*(1+'PyG 3 Años'!$G$13)+'PyG 3 Años'!$B$14*(1+'PyG 3 Años'!$G$14)+'PyG 3 Años'!$B$15*(1+'PyG 3 Años'!$G$15)+'PyG 3 Años'!$B$16*(1+'PyG 3 Años'!$G$16)+'PyG 3 Años'!$B$17*(1+'PyG 3 Años'!$G$17)+'PyG 3 Años'!$B$18*(1+'PyG 3 Años'!$G$18))*(H7*(1-MIN(30,'0. Supuestos'!$B$59)/30)+G7*MIN(30,'0. Supuestos'!$B$59)/30)),"") -> -13539.672 | I11: =IFERROR(IF('PyG 3 Años'!$B$9="","",-('PyG 3 Años'!$B$13*(1+'PyG 3 Años'!$G$13)+'PyG 3 Años'!$B$14*(1+'PyG 3 Años'!$G$14)+'PyG 3 Años'!$B$15*(1+'PyG 3 Años'!$G$15)+'PyG 3 Años'!$B$16*(1+'PyG 3 Años'!$G$16)+'PyG 3 Años'!$B$17*(1+'PyG 3 Años'!$G$17)+'PyG 3 Años'!$B$18*(1+'PyG 3 Años'!$G$18))*(I7*(1-MIN(30,'0. Supuestos'!$B$59)/30)+H7*MIN(30,'0. Supuestos'!$B$59)/30)),"") -> -12924.232 | J11: =IFERROR(IF('PyG 3 Años'!$B$9="","",-('PyG 3 Años'!$B$13*(1+'PyG 3 Años'!$G$13)+'PyG 3 Años'!$B$14*(1+'PyG 3 Años'!$G$14)+'PyG 3 Años'!$B$15*(1+'PyG 3 Años'!$G$15)+'PyG 3 Años'!$B$16*(1+'PyG 3 Años'!$G$16)+'PyG 3 Años'!$B$17*(1+'PyG 3 Años'!$G$17)+'PyG 3 Años'!$B$18*(1+'PyG 3 Años'!$G$18))*(J7*(1-MIN(30,'0. Supuestos'!$B$59)/30)+I7*MIN(30,'0. Supuestos'!$B$59)/30)),"") -> -10770.194 | ... M11: =IFERROR(IF('PyG 3 Años'!$B$9="","",-('PyG 3 Años'!$B$13*(1+'PyG 3 Años'!$G$13)+'PyG 3 Años'!$B$14*(1+'PyG 3 Años'!$G$14)+'PyG 3 Años'!$B$15*(1+'PyG 3 Años'!$G$15)+'PyG 3 Años'!$B$16*(1+'PyG 3 Años'!$G$16)+'PyG 3 Años'!$B$17*(1+'PyG 3 Años'!$G$17)+'PyG 3 Años'!$B$18*(1+'PyG 3 Años'!$G$18))*(M7*(1-MIN(30,'0. Supuestos'!$B$59)/30)+L7*MIN(30,'0. Supuestos'!$B$59)/30)),"") -> -13231.952 | N11: =IFERROR(IF('PyG 3 Años'!$B$9="","",SUM(B11:M11)),"") -> -133447.83 | O11: =IFERROR("Materia prima, consumibles, comisiones e imprevistos, cada uno con SU tipo de IVA (la columna del P&L) y con los días de pago a proveedor de Supuestos."&IF('0. Supuestos'!$B$59=0,""," Con "&TEXT('0. Supuestos'!$B$59,"0")&" días de pago, las primeras compras se pagan ya en el año siguiente: la columna «Año» de esta fila recoge "&TEXT(MAX(0,12-ROUNDUP('0. Supuestos'!$B$59/30,0)),"0")&" mensualidades de compra, no el coste del ejercicio."),"") -> Materia prima, consumibles, comisiones e imprevistos, cada uno con SU tipo de IVA (la columna del P&L) y con los días de pago a proveedor de Supuestos. Con 30 días de pago, las primeras compras se pagan ya en el año siguiente: la columna «Año» de esta fila recoge 11 mensualidades de compra, no el coste del ejercicio.
A12: Costes fijos de explotación (IVA incluido) | B12: =IFERROR(IF('PyG 3 Años'!$B$9="","",-('PyG 3 Años'!$B$37-'PyG 3 Años'!$B$23-'PyG 3 Años'!$B$35-'PyG 3 Años'!$B$36+'PyG 3 Años'!$B$39)/12),"") -> -4291.1667 | C12: =IFERROR(IF('PyG 3 Años'!$B$9="","",-('PyG 3 Años'!$B$37-'PyG 3 Años'!$B$23-'PyG 3 Años'!$B$35-'PyG 3 Años'!$B$36+'PyG 3 Años'!$B$39)/12),"") -> -4291.1667 | D12: =IFERROR(IF('PyG 3 Años'!$B$9="","",-('PyG 3 Años'!$B$37-'PyG 3 Años'!$B$23-'PyG 3 Años'!$B$35-'PyG 3 Años'!$B$36+'PyG 3 Años'!$B$39)/12),"") -> -4291.1667 | E12: =IFERROR(IF('PyG 3 Años'!$B$9="","",-('PyG 3 Años'!$B$37-'PyG 3 Años'!$B$23-'PyG 3 Años'!$B$35-'PyG 3 Años'!$B$36+'PyG 3 Años'!$B$39)/12),"") -> -4291.1667 | F12: =IFERROR(IF('PyG 3 Años'!$B$9="","",-('PyG 3 Años'!$B$37-'PyG 3 Años'!$B$23-'PyG 3 Años'!$B$35-'PyG 3 Años'!$B$36+'PyG 3 Años'!$B$39)/12),"") -> -4291.1667 | G12: =IFERROR(IF('PyG 3 Años'!$B$9="","",-('PyG 3 Años'!$B$37-'PyG 3 Años'!$B$23-'PyG 3 Años'!$B$35-'PyG 3 Años'!$B$36+'PyG 3 Años'!$B$39)/12),"") -> -4291.1667 | H12: =IFERROR(IF('PyG 3 Años'!$B$9="","",-('PyG 3 Años'!$B$37-'PyG 3 Años'!$B$23-'PyG 3 Años'!$B$35-'PyG 3 Años'!$B$36+'PyG 3 Años'!$B$39)/12),"") -> -4291.1667 | I12: =IFERROR(IF('PyG 3 Años'!$B$9="","",-('PyG 3 Años'!$B$37-'PyG 3 Años'!$B$23-'PyG 3 Años'!$B$35-'PyG 3 Años'!$B$36+'PyG 3 Años'!$B$39)/12),"") -> -4291.1667 | ... M12: =IFERROR(IF('PyG 3 Años'!$B$9="","",-('PyG 3 Años'!$B$37-'PyG 3 Años'!$B$23-'PyG 3 Años'!$B$35-'PyG 3 Años'!$B$36+'PyG 3 Años'!$B$39)/12),"") -> -4291.1667 | N12: =IFERROR(IF('PyG 3 Años'!$B$9="","",SUM(B12:M12)),"") -> -51494 | O12: Los fijos que salen de caja, cada uno con su tipo de IVA: los seguros están exentos y no llevan
A13: Nóminas y Seguridad Social | B13: =IFERROR(IF('PyG 3 Años'!$B$9="","",-'PyG 3 Años'!$B$23/MAX(12,'0. Supuestos'!$B$21)*(1+IF(1='0. Supuestos'!$B$60,(MAX(12,'0. Supuestos'!$B$21)-12)/2,0)+IF(1='0. Supuestos'!$B$61,(MAX(12,'0. Supuestos'!$B$21)-12)/2,0))),"") -> -9251.48 | C13: =IFERROR(IF('PyG 3 Años'!$B$9="","",-'PyG 3 Años'!$B$23/MAX(12,'0. Supuestos'!$B$21)*(1+IF(2='0. Supuestos'!$B$60,(MAX(12,'0. Supuestos'!$B$21)-12)/2,0)+IF(2='0. Supuestos'!$B$61,(MAX(12,'0. Supuestos'!$B$21)-12)/2,0))),"") -> -9251.48 | D13: =IFERROR(IF('PyG 3 Años'!$B$9="","",-'PyG 3 Años'!$B$23/MAX(12,'0. Supuestos'!$B$21)*(1+IF(3='0. Supuestos'!$B$60,(MAX(12,'0. Supuestos'!$B$21)-12)/2,0)+IF(3='0. Supuestos'!$B$61,(MAX(12,'0. Supuestos'!$B$21)-12)/2,0))),"") -> -9251.48 | E13: =IFERROR(IF('PyG 3 Años'!$B$9="","",-'PyG 3 Años'!$B$23/MAX(12,'0. Supuestos'!$B$21)*(1+IF(4='0. Supuestos'!$B$60,(MAX(12,'0. Supuestos'!$B$21)-12)/2,0)+IF(4='0. Supuestos'!$B$61,(MAX(12,'0. Supuestos'!$B$21)-12)/2,0))),"") -> -9251.48 | F13: =IFERROR(IF('PyG 3 Años'!$B$9="","",-'PyG 3 Años'!$B$23/MAX(12,'0. Supuestos'!$B$21)*(1+IF(5='0. Supuestos'!$B$60,(MAX(12,'0. Supuestos'!$B$21)-12)/2,0)+IF(5='0. Supuestos'!$B$61,(MAX(12,'0. Supuestos'!$B$21)-12)/2,0))),"") -> -9251.48 | G13: =IFERROR(IF('PyG 3 Años'!$B$9="","",-'PyG 3 Años'!$B$23/MAX(12,'0. Supuestos'!$B$21)*(1+IF(6='0. Supuestos'!$B$60,(MAX(12,'0. Supuestos'!$B$21)-12)/2,0)+IF(6='0. Supuestos'!$B$61,(MAX(12,'0. Supuestos'!$B$21)-12)/2,0))),"") -> -9251.48 | H13: =IFERROR(IF('PyG 3 Años'!$B$9="","",-'PyG 3 Años'!$B$23/MAX(12,'0. Supuestos'!$B$21)*(1+IF(7='0. Supuestos'!$B$60,(MAX(12,'0. Supuestos'!$B$21)-12)/2,0)+IF(7='0. Supuestos'!$B$61,(MAX(12,'0. Supuestos'!$B$21)-12)/2,0))),"") -> -18502.96 | I13: =IFERROR(IF('PyG 3 Años'!$B$9="","",-'PyG 3 Años'!$B$23/MAX(12,'0. Supuestos'!$B$21)*(1+IF(8='0. Supuestos'!$B$60,(MAX(12,'0. Supuestos'!$B$21)-12)/2,0)+IF(8='0. Supuestos'!$B$61,(MAX(12,'0. Supuestos'!$B$21)-12)/2,0))),"") -> -9251.48 | J13: =IFERROR(IF('PyG 3 Años'!$B$9="","",-'PyG 3 Años'!$B$23/MAX(12,'0. Supuestos'!$B$21)*(1+IF(9='0. Supuestos'!$B$60,(MAX(12,'0. Supuestos'!$B$21)-12)/2,0)+IF(9='0. Supuestos'!$B$61,(MAX(12,'0. Supuestos'!$B$21)-12)/2,0))),"") -> -9251.48 | K13: =IFERROR(IF('PyG 3 Años'!$B$9="","",-'PyG 3 Años'!$B$23/MAX(12,'0. Supuestos'!$B$21)*(1+IF(10='0. Supuestos'!$B$60,(MAX(12,'0. Supuestos'!$B$21)-12)/2,0)+IF(10='0. Supuestos'!$B$61,(MAX(12,'0. Supuestos'!$B$21)-12)/2,0))),"") -> -9251.48 | L13: =IFERROR(IF('PyG 3 Años'!$B$9="","",-'PyG 3 Años'!$B$23/MAX(12,'0. Supuestos'!$B$21)*(1+IF(11='0. Supuestos'!$B$60,(MAX(12,'0. Supuestos'!$B$21)-12)/2,0)+IF(11='0. Supuestos'!$B$61,(MAX(12,'0. Supuestos'!$B$21)-12)/2,0))),"") -> -9251.48 | M13: =IFERROR(IF('PyG 3 Años'!$B$9="","",-'PyG 3 Años'!$B$23/MAX(12,'0. Supuestos'!$B$21)*(1+IF(12='0. Supuestos'!$B$60,(MAX(12,'0. Supuestos'!$B$21)-12)/2,0)+IF(12='0. Supuestos'!$B$61,(MAX(12,'0. Supuestos'!$B$21)-12)/2,0))),"") -> -18502.96 | N13: =IFERROR(IF('PyG 3 Años'!$B$9="","",SUM(B13:M13)),"") -> -129520.72 | O13: Doce mensualidades más las pagas extra en los meses que digas en Supuestos. La suma del año es la misma que la del P&L
A14: Intereses del préstamo | B14: =IFERROR(IF('PyG 3 Años'!$B$9="","",-'Financiación'!$B$44/12),"") -> -590 | C14: =IFERROR(IF('PyG 3 Años'!$B$9="","",-'Financiación'!$B$44/12),"") -> -590 | D14: =IFERROR(IF('PyG 3 Años'!$B$9="","",-'Financiación'!$B$44/12),"") -> -590 | E14: =IFERROR(IF('PyG 3 Años'!$B$9="","",-'Financiación'!$B$44/12),"") -> -590 | F14: =IFERROR(IF('PyG 3 Años'!$B$9="","",-'Financiación'!$B$44/12),"") -> -590 | G14: =IFERROR(IF('PyG 3 Años'!$B$9="","",-'Financiación'!$B$44/12),"") -> -590 | H14: =IFERROR(IF('PyG 3 Años'!$B$9="","",-'Financiación'!$B$44/12),"") -> -590 | I14: =IFERROR(IF('PyG 3 Años'!$B$9="","",-'Financiación'!$B$44/12),"") -> -590 | ... M14: =IFERROR(IF('PyG 3 Años'!$B$9="","",-'Financiación'!$B$44/12),"") -> -590 | N14: =IFERROR(IF('PyG 3 Años'!$B$9="","",SUM(B14:M14)),"") -> -7080
A15: Devolución de principal del préstamo | B15: =IFERROR(IF('PyG 3 Años'!$B$9="","",-'Financiación'!$B$45/12),"") -> 0 | C15: =IFERROR(IF('PyG 3 Años'!$B$9="","",-'Financiación'!$B$45/12),"") -> 0 | D15: =IFERROR(IF('PyG 3 Años'!$B$9="","",-'Financiación'!$B$45/12),"") -> 0 | E15: =IFERROR(IF('PyG 3 Años'!$B$9="","",-'Financiación'!$B$45/12),"") -> 0 | F15: =IFERROR(IF('PyG 3 Años'!$B$9="","",-'Financiación'!$B$45/12),"") -> 0 | G15: =IFERROR(IF('PyG 3 Años'!$B$9="","",-'Financiación'!$B$45/12),"") -> 0 | H15: =IFERROR(IF('PyG 3 Años'!$B$9="","",-'Financiación'!$B$45/12),"") -> 0 | I15: =IFERROR(IF('PyG 3 Años'!$B$9="","",-'Financiación'!$B$45/12),"") -> 0 | ... M15: =IFERROR(IF('PyG 3 Años'!$B$9="","",-'Financiación'!$B$45/12),"") -> 0 | N15: =IFERROR(IF('PyG 3 Años'!$B$9="","",SUM(B15:M15)),"") -> 0
A16: IVA repercutido del mes (memoria) | B16: =IFERROR(IF('PyG 3 Años'!$B$9="","",'PyG 3 Años'!$B$9*B7*SUMPRODUCT('PyG 3 Años'!$E$10:$E$11,'PyG 3 Años'!$G$10:$G$11)),"") -> 1983.5072 | C16: =IFERROR(IF('PyG 3 Años'!$B$9="","",'PyG 3 Años'!$B$9*C7*SUMPRODUCT('PyG 3 Años'!$E$10:$E$11,'PyG 3 Años'!$G$10:$G$11)),"") -> 2329.8338 | D16: =IFERROR(IF('PyG 3 Años'!$B$9="","",'PyG 3 Años'!$B$9*D7*SUMPRODUCT('PyG 3 Años'!$E$10:$E$11,'PyG 3 Años'!$G$10:$G$11)),"") -> 2839.8785 | E16: =IFERROR(IF('PyG 3 Años'!$B$9="","",'PyG 3 Años'!$B$9*E7*SUMPRODUCT('PyG 3 Años'!$E$10:$E$11,'PyG 3 Años'!$G$10:$G$11)),"") -> 3249.1737 | F16: =IFERROR(IF('PyG 3 Años'!$B$9="","",'PyG 3 Años'!$B$9*F7*SUMPRODUCT('PyG 3 Años'!$E$10:$E$11,'PyG 3 Años'!$G$10:$G$11)),"") -> 3324.7358 | G16: =IFERROR(IF('PyG 3 Años'!$B$9="","",'PyG 3 Años'!$B$9*G7*SUMPRODUCT('PyG 3 Años'!$E$10:$E$11,'PyG 3 Años'!$G$10:$G$11)),"") -> 3324.7358 | H16: =IFERROR(IF('PyG 3 Años'!$B$9="","",'PyG 3 Años'!$B$9*H7*SUMPRODUCT('PyG 3 Años'!$E$10:$E$11,'PyG 3 Años'!$G$10:$G$11)),"") -> 3173.6115 | I16: =IFERROR(IF('PyG 3 Años'!$B$9="","",'PyG 3 Años'!$B$9*I7*SUMPRODUCT('PyG 3 Años'!$E$10:$E$11,'PyG 3 Años'!$G$10:$G$11)),"") -> 2644.6762 | ... M16: =IFERROR(IF('PyG 3 Años'!$B$9="","",'PyG 3 Años'!$B$9*M7*SUMPRODUCT('PyG 3 Años'!$E$10:$E$11,'PyG 3 Años'!$G$10:$G$11)),"") -> 3626.9846 | N16: =IFERROR(IF('PyG 3 Años'!$B$9="","",SUM(B16:M16)),"") -> 36395.783 | O16: Cada línea de venta a SU tipo, leído de la columna de IVA del P&L: en sala, alcohol incluido, el reducido (art. 91.Uno.2.2.º de la Ley 37/1992 del IVA); la parte de la bebida que sale para llevar o a domicilio y declara la columna H de su línea (alcohol y aguas frescas o refrescos con azúcares o edulcorantes añadidos), al general (art. 91.Uno.1.1.º)
A17: IVA soportado del mes (memoria) | B17: =IFERROR(IF('PyG 3 Años'!$B$9="","",'PyG 3 Años'!$B$38*B7+'PyG 3 Años'!$B$39/12),"") -> 1640.8354 | C17: =IFERROR(IF('PyG 3 Años'!$B$9="","",'PyG 3 Años'!$B$38*C7+'PyG 3 Años'!$B$39/12),"") -> 1800.8305 | D17: =IFERROR(IF('PyG 3 Años'!$B$9="","",'PyG 3 Años'!$B$38*D7+'PyG 3 Años'!$B$39/12),"") -> 2036.4596 | E17: =IFERROR(IF('PyG 3 Años'!$B$9="","",'PyG 3 Años'!$B$38*E7+'PyG 3 Años'!$B$39/12),"") -> 2225.5447 | F17: =IFERROR(IF('PyG 3 Años'!$B$9="","",'PyG 3 Años'!$B$38*F7+'PyG 3 Años'!$B$39/12),"") -> 2260.4527 | G17: =IFERROR(IF('PyG 3 Años'!$B$9="","",'PyG 3 Años'!$B$38*G7+'PyG 3 Años'!$B$39/12),"") -> 2260.4527 | H17: =IFERROR(IF('PyG 3 Años'!$B$9="","",'PyG 3 Años'!$B$38*H7+'PyG 3 Años'!$B$39/12),"") -> 2190.6367 | I17: =IFERROR(IF('PyG 3 Años'!$B$9="","",'PyG 3 Años'!$B$38*I7+'PyG 3 Años'!$B$39/12),"") -> 1946.2806 | ... M17: =IFERROR(IF('PyG 3 Años'!$B$9="","",'PyG 3 Años'!$B$38*M7+'PyG 3 Años'!$B$39/12),"") -> 2400.0848 | N17: =IFERROR(IF('PyG 3 Años'!$B$9="","",SUM(B17:M17)),"") -> 25508.028 | O17: Cada partida a su tipo, leído de la columna de IVA del P&L: los seguros y las comisiones de los medios de pago están exentos
A18: IVA a compensar arrastrado (inversión incluida) | E18: =IFERROR(IF('PyG 3 Años'!$B$9="","",'Inversión Inicial'!$B$32),"") -> 21052.5 | H18: =IFERROR(IF('PyG 3 Años'!$B$9="","",MAX(0,-E19)),"") -> 19377.406 | K18: =IFERROR(IF('PyG 3 Años'!$B$9="","",MAX(0,-H19)),"") -> 16225.211 | O18: El IVA soportado de la INVERSIÓN entra aquí: se compensa contra el repercutido de los trimestres siguientes hasta agotarlo (modelo 303)
A19: Resultado de la liquidación trimestral | E19: =IFERROR(IF('PyG 3 Años'!$B$9="","",SUM(B16:D16)-SUM(B17:D17)-E18),"") -> -19377.406 | H19: =IFERROR(IF('PyG 3 Años'!$B$9="","",SUM(E16:G16)-SUM(E17:G17)-H18),"") -> -16225.211 | K19: =IFERROR(IF('PyG 3 Años'!$B$9="","",SUM(H16:J16)-SUM(H17:J17)-K18),"") -> -13479.557 | O19: Repercutido menos soportado del trimestre menos lo que venía arrastrado. En negativo NO se paga: se compensa en el trimestre siguiente
A20: Pago del IVA (modelo 303) | E20: =IFERROR(IF('PyG 3 Años'!$B$9="","",IF(E19<=0,"",-E19)),"") | H20: =IFERROR(IF('PyG 3 Años'!$B$9="","",IF(H19<=0,"",-H19)),"") | K20: =IFERROR(IF('PyG 3 Años'!$B$9="","",IF(K19<=0,"",-K19)),"") | N20: =IFERROR(IF('PyG 3 Años'!$B$9="","",SUM(B20:M20)),"") -> 0 | O20: Sólo sale caja cuando el resultado del trimestre es positivo. Los meses sin liquidación van en blanco, no a cero. La celda se pinta en ROJO cuando el pago del 303 se lleva más caja de la que queda ese mes
A21: FLUJO DEL MES | B21: =IFERROR(IF('PyG 3 Años'!$B$9="","",SUM(B9:B15)+IF(B20="",0,B20)),"") -> 5930.8585 | C21: =IFERROR(IF('PyG 3 Años'!$B$9="","",SUM(C9:C15)+IF(C20="",0,C20)),"") -> 2789.4726 | D21: =IFERROR(IF('PyG 3 Años'!$B$9="","",SUM(D9:D15)+IF(D20="",0,D20)),"") -> 6788.5023 | E21: =IFERROR(IF('PyG 3 Años'!$B$9="","",SUM(E9:E15)+IF(E20="",0,E20)),"") -> 9219.9952 | F21: =IFERROR(IF('PyG 3 Años'!$B$9="","",SUM(F9:F15)+IF(F20="",0,F20)),"") -> 8613.2242 | G21: =IFERROR(IF('PyG 3 Años'!$B$9="","",SUM(G9:G15)+IF(G20="",0,G20)),"") -> 8360.0989 | H21: =IFERROR(IF('PyG 3 Años'!$B$9="","",SUM(H9:H15)+IF(H20="",0,H20)),"") -> -2420.0291 | I21: =IFERROR(IF('PyG 3 Años'!$B$9="","",SUM(I9:I15)+IF(I20="",0,I20)),"") -> 1987.4334 | ... M21: =IFERROR(IF('PyG 3 Años'!$B$9="","",SUM(M9:M15)+IF(M20="",0,M20)),"") -> 2419.0402 | N21: =IFERROR(IF('PyG 3 Años'!$B$9="","",SUM(B21:M21)),"") -> 70282.696
A22: SALDO ACUMULADO DE CAJA | B22: =IFERROR(IF('PyG 3 Años'!$B$9="","",'Inversión Inicial'!$B$29+B21),"") -> 50781.039 | C22: =IFERROR(IF('PyG 3 Años'!$B$9="","",B22+C21),"") -> 53570.511 | D22: =IFERROR(IF('PyG 3 Años'!$B$9="","",C22+D21),"") -> 60359.013 | E22: =IFERROR(IF('PyG 3 Años'!$B$9="","",D22+E21),"") -> 69579.009 | F22: =IFERROR(IF('PyG 3 Años'!$B$9="","",E22+F21),"") -> 78192.233 | G22: =IFERROR(IF('PyG 3 Años'!$B$9="","",F22+G21),"") -> 86552.332 | H22: =IFERROR(IF('PyG 3 Años'!$B$9="","",G22+H21),"") -> 84132.303 | I22: =IFERROR(IF('PyG 3 Años'!$B$9="","",H22+I21),"") -> 86119.736 | J22: =IFERROR(IF('PyG 3 Años'!$B$9="","",I22+J21),"") -> 96757.962 | ... M22: =IFERROR(IF('PyG 3 Años'!$B$9="","",L22+M21),"") -> 115132.88
A23: Saldo mínimo del año | B23: =IFERROR(IF('PyG 3 Años'!$B$9="","",IF(COUNT(B22:M22)=0,"",MIN(B22:M22))),"") -> 50781.039 | D23: Si es negativo, sube el fondo de maniobra o el préstamo: te quedas sin caja
A24: Mes en el que la caja toca fondo | B24: =IFERROR(IF('PyG 3 Años'!$B$9="","",IF(COUNT(B22:M22)=0,"",MATCH(MIN(B22:M22),B22:M22,0))),"") -> 1 | D24: Es la respuesta a la pregunta que decide una operación bancaria: en qué mes se agota la caja
A25: RETORNO DE LA INVERSIÓN
A26: Flujo de caja libre antes de la deuda, año 1 | B26: =IFERROR(IF('PyG 3 Años'!$B$9="","",'PyG 3 Años'!$B$47+'PyG 3 Años'!$B$35+'Financiación'!$B$44),"") -> 48578.44 | D26: Resultado neto más amortización (que no se paga) más los intereses de ese año: el principal no se resta porque este flujo es ANTES de la deuda. La MISMA base que los años 2 y 3, para que el payback compare peras con peras
A27: Flujo de caja libre antes de la deuda, año 2 | B27: =IFERROR(IF('PyG 3 Años'!$B$9="","",'PyG 3 Años'!$C$47+'PyG 3 Años'!$C$35+'Financiación'!$B$46),"") -> 55037.369 | D27: Resultado neto más amortización (que no se paga) más los intereses de ese año: el principal no se resta porque este flujo es ANTES de la deuda. Sin tabla mensual, es una estimación
A28: Flujo de caja libre antes de la deuda, año 3 | B28: =IFERROR(IF('PyG 3 Años'!$B$9="","",'PyG 3 Años'!$D$47+'PyG 3 Años'!$D$35+'Financiación'!$B$48),"") -> 52900.082 | D28: Resultado neto más amortización (que no se paga) más los intereses de ese año: el principal no se resta porque este flujo es ANTES de la deuda. Sin tabla mensual, es una estimación
A29: Informativo: flujo REAL de caja del año 1 (tabla mensual, antes de la deuda) | B29: =IFERROR(IF('PyG 3 Años'!$B$9="","",N21+'Financiación'!$B$44+'Financiación'!$B$45),"") -> 77362.696 | D29: La suma de los doce FLUJO DEL MES de arriba, devolviéndole los intereses y el principal que se pagaron ese año. NO es la que usa el payback: lleva dentro el IVA que todavía no se ha liquidado y el crédito del proveedor, dos cosas que hay que devolver y que los años 2 y 3 no tienen
A30: Inversión a recuperar (sin el IVA, que se recupera por el 303) | B30: =IFERROR(IF('PyG 3 Años'!$B$9="","",'Inversión Inicial'!$B$33-'Inversión Inicial'!$B$32),"") -> 151000.18 | D30: CAPEX más fondo de maniobra: la necesidad total de caja MENOS el IVA soportado de la inversión, que no se pierde (se recupera con el modelo 303 y esta misma hoja lo compensa trimestre a trimestre). El fondo de maniobra sí se recupera al cerrar, pero hasta entonces está inmovilizado
A31: Payback del proyecto (años), antes de la deuda | B31: =IFERROR(IF('PyG 3 Años'!$B$9="","",IF(B26>=B30,ROUND(B30/B26,1),IF(B26+B27>=B30,ROUND(1+(B30-B26)/B27,1),IF(B26+B27+B28>=B30,ROUND(2+(B30-B26-B27)/B28,1),"Más de 3 años")))),"") -> 2.9 | D31: Mide cuánto tarda el negocio en devolver la inversión con lo que genera ANTES de pagar al banco, con la MISMA base de flujo en los tres años; si puedes pagar la cuota lo dice el DSCR de la hoja de Financiación. El plan de negocio en Word cita esta cifra; si cambias una celda verde, manda este libro
A32: Payback sobre el CAPEX, sin fondo de maniobra (años) | B32: =IFERROR(IF('PyG 3 Años'!$B$9="","",IF(B26>='Inversión Inicial'!$B$31,ROUND('Inversión Inicial'!$B$31/B26,1),IF(B26+B27>='Inversión Inicial'!$B$31,ROUND(1+('Inversión Inicial'!$B$31-B26)/B27,1),IF(B26+B27+B28>='Inversión Inicial'!$B$31,ROUND(2+('Inversión Inicial'!$B$31-B26-B27)/B28,1),"Más de 3 años")))),"") -> 2 | D32: El mismo cálculo sobre lo que se COMPRA (obra, equipamiento, lanzamiento y constitución), sin el fondo de maniobra: ese dinero no se gasta, se inmoviliza y vuelve al cerrar el negocio. Informativo: el payback que se publica es el de arriba
A34: El IVA del cuarto trimestre se liquida en enero del año siguiente, así que no aparece en este cuadro. El Impuesto de Sociedades del año 1 se paga en julio del año 2. La cuota del préstamo se reparte en doce partes iguales siguiendo el cuadro ANUAL de la hoja de Financiación, y las nóminas en doce mensualidades más las dos pagas extra en su mes.

Sheet Financiación
A1: PLAN DE FINANCIACIÓN
A2: Qué hace falta, de dónde sale y cuánto cuesta devolverlo. Es la hoja que el banco pide junto con el P&L.
A4: Concepto | B4: Importe | C4: Notas
A5: ORIGEN DE FONDOS
A6: Recursos propios de los socios | B6: =IFERROR(IF('0. Supuestos'!$B$30="","",'0. Supuestos'!$B$30),"") -> 55000
A7: Préstamo bancario | B7: =IFERROR(IF('0. Supuestos'!$B$31="","",'0. Supuestos'!$B$31),"") -> 118000
A8: Línea ICO (avalada por el ICO, la concede tu banco) | B8: 0 | C8: Consulta las líneas del ejercicio en curso en ico.es
A9: Préstamo participativo ENISA | B9: 0 | C9: Para sociedades; sin garantías personales
A10: Business angels o socios inversores | B10: 0 | C10: Entra en el capital: diluye, no se devuelve
A11: Subvenciones autonómicas o locales | B11: 0 | C11: Suelen cobrarse DESPUÉS de justificar el gasto
A12: TOTAL ORIGEN DE FONDOS | B12: =IFERROR(IF(COUNT(B6:B11)=0,"",SUM(B6:B11)),"") -> 173000
A13: USOS
A14: Necesidad total de caja al arranque | B14: =IFERROR(IF('Inversión Inicial'!$B$33="","",'Inversión Inicial'!$B$33),"") -> 172052.68 | C14: Inversión más el IVA que hay que adelantar
A15: Diferencia (origen - usos) | B15: =IFERROR(B12-B14,"") -> 947.32 | C15: En rojo (negativa) el plan NO está financiado. Muy por encima de cero tampoco es gratis: se pagan intereses por un dinero que no se usa
A16: Diferencia sobre los usos (%) | B16: =IFERROR(B15/B14,"") -> 0.005505988 | C16: Ámbar por encima del margen que fijes: es deuda que pagas sin necesitarla
A17: Exceso de financiación admisible (%) | B17: 0.05 | C17: Un pequeño colchón sobre la necesidad es sano; un 20 % de más son intereses tirados
A18: Préstamo que ajustaría el origen a la necesidad | B18: =IFERROR(MAX(0,B14-B12+B7),"") -> 117052.68 | C18: Cópialo en «Préstamo bancario solicitado» de la hoja de Supuestos y la diferencia se pone a cero
A19: CONDICIONES DEL PRÉSTAMO
A20: Importe del principal | B20: =IFERROR(IF('0. Supuestos'!$B$31=0,"",'0. Supuestos'!$B$31),"") -> 118000
A21: Tipo de interés nominal anual | B21: =IFERROR(IF('0. Supuestos'!$B$32="","",'0. Supuestos'!$B$32),"") -> 0.06
A22: Plazo total (años) | B22: =IFERROR(IF('0. Supuestos'!$B$33="","",'0. Supuestos'!$B$33),"") -> 7
A23: Carencia de principal aplicada (años) | B23: =IFERROR(IF(OR('0. Supuestos'!$B$34="",'0. Supuestos'!$B$33=""),"",IF('0. Supuestos'!$B$34>='0. Supuestos'!$B$33,0,'0. Supuestos'!$B$34)),"") -> 1 | C23: Una carencia igual o mayor que el plazo no existe: la hoja la anula en origen
A24: Cuota anual durante la amortización | B24: =IFERROR(IF(B22-B23<=0,"",IF(B21=0,B20/(B22-B23),B20*B21/(1-(1+B21)^-(B22-B23)))),"") -> 23996.79 | C24: Sistema francés, anualidad algebraica. Con el tipo al 0 % es el principal entre los años de amortización: sin esa rama el cuadro se apagaba entero
A25: CUADRO DE AMORTIZACIÓN
A26: Año | B26: Capital pendiente | C26: Intereses | D26: Amortización de principal | E26: Cuota total | F26: Capital al cierre | G26: Flujo disponible para la deuda (después de impuestos; del año 4 en adelante, el del año 3 mantenido) | H26: DSCR del año
A27: 1 | B27: =IFERROR(IF(B20="","",B20),"") -> 118000 | C27: =IFERROR(IF(OR(1>B22,B27=""),"",B27*B21),"") -> 7080 | D27: =IFERROR(IF(OR(1>B22,B27=""),"",IF(1<=B23,0,MIN(B27,B24-C27))),"") -> 0 | E27: =IFERROR(IF(C27="","",C27+D27),"") -> 7080 | F27: =IFERROR(IF(D27="","",B27-D27),"") -> 118000 | G27: =IFERROR(IF(E27="","",'PyG 3 Años'!$B$40-'PyG 3 Años'!$B$45+'PyG 3 Años'!$B$35+'PyG 3 Años'!$B$36),"") -> 48578.44 | H27: =IFERROR(IF(OR(E27="",E27=0),"",G27/E27),"") -> 6.8613617
A28: 2 | B28: =IFERROR(IF(OR(2>B22,F27=""),"",F27),"") -> 118000 | C28: =IFERROR(IF(OR(2>B22,B28=""),"",B28*B21),"") -> 7080 | D28: =IFERROR(IF(OR(2>B22,B28=""),"",IF(2<=B23,0,MIN(B28,B24-C28))),"") -> 16916.79 | E28: =IFERROR(IF(C28="","",C28+D28),"") -> 23996.79 | F28: =IFERROR(IF(D28="","",B28-D28),"") -> 101083.21 | G28: =IFERROR(IF(E28="","",'PyG 3 Años'!$C$40-'PyG 3 Años'!$C$45+'PyG 3 Años'!$C$35+'PyG 3 Años'!$C$36),"") -> 55037.369 | H28: =IFERROR(IF(OR(E28="",E28=0),"",G28/E28),"") -> 2.2935304
A29: 3 | B29: =IFERROR(IF(OR(3>B22,F28=""),"",F28),"") -> 101083.21 | C29: =IFERROR(IF(OR(3>B22,B29=""),"",B29*B21),"") -> 6064.9926 | D29: =IFERROR(IF(OR(3>B22,B29=""),"",IF(3<=B23,0,MIN(B29,B24-C29))),"") -> 17931.798 | E29: =IFERROR(IF(C29="","",C29+D29),"") -> 23996.79 | F29: =IFERROR(IF(D29="","",B29-D29),"") -> 83151.412 | G29: =IFERROR(IF(E29="","",'PyG 3 Años'!$D$40-'PyG 3 Años'!$D$45+'PyG 3 Años'!$D$35+'PyG 3 Años'!$D$36),"") -> 52900.082 | H29: =IFERROR(IF(OR(E29="",E29=0),"",G29/E29),"") -> 2.2044649
A30: 4 | B30: =IFERROR(IF(OR(4>B22,F29=""),"",F29),"") -> 83151.412 | C30: =IFERROR(IF(OR(4>B22,B30=""),"",B30*B21),"") -> 4989.0847 | D30: =IFERROR(IF(OR(4>B22,B30=""),"",IF(4<=B23,0,MIN(B30,B24-C30))),"") -> 19007.705 | E30: =IFERROR(IF(C30="","",C30+D30),"") -> 23996.79 | F30: =IFERROR(IF(D30="","",B30-D30),"") -> 64143.707 | G30: =IFERROR(IF(E30="","",'PyG 3 Años'!$D$40-'PyG 3 Años'!$D$45+'PyG 3 Años'!$D$35+'PyG 3 Años'!$D$36),"") -> 52900.082 | H30: =IFERROR(IF(OR(E30="",E30=0),"",G30/E30),"") -> 2.2044649
A31: 5 | B31: =IFERROR(IF(OR(5>B22,F30=""),"",F30),"") -> 64143.707 | C31: =IFERROR(IF(OR(5>B22,B31=""),"",B31*B21),"") -> 3848.6224 | D31: =IFERROR(IF(OR(5>B22,B31=""),"",IF(5<=B23,0,MIN(B31,B24-C31))),"") -> 20148.168 | E31: =IFERROR(IF(C31="","",C31+D31),"") -> 23996.79 | F31: =IFERROR(IF(D31="","",B31-D31),"") -> 43995.539 | G31: =IFERROR(IF(E31="","",'PyG 3 Años'!$D$40-'PyG 3 Años'!$D$45+'PyG 3 Años'!$D$35+'PyG 3 Años'!$D$36),"") -> 52900.082 | H31: =IFERROR(IF(OR(E31="",E31=0),"",G31/E31),"") -> 2.2044649
A32: 6 | B32: =IFERROR(IF(OR(6>B22,F31=""),"",F31),"") -> 43995.539 | C32: =IFERROR(IF(OR(6>B22,B32=""),"",B32*B21),"") -> 2639.7323 | D32: =IFERROR(IF(OR(6>B22,B32=""),"",IF(6<=B23,0,MIN(B32,B24-C32))),"") -> 21357.058 | E32: =IFERROR(IF(C32="","",C32+D32),"") -> 23996.79 | F32: =IFERROR(IF(D32="","",B32-D32),"") -> 22638.481 | G32: =IFERROR(IF(E32="","",'PyG 3 Años'!$D$40-'PyG 3 Años'!$D$45+'PyG 3 Años'!$D$35+'PyG 3 Años'!$D$36),"") -> 52900.082 | H32: =IFERROR(IF(OR(E32="",E32=0),"",G32/E32),"") -> 2.2044649
A33: 7 | B33: =IFERROR(IF(OR(7>B22,F32=""),"",F32),"") -> 22638.481 | C33: =IFERROR(IF(OR(7>B22,B33=""),"",B33*B21),"") -> 1358.3089 | D33: =IFERROR(IF(OR(7>B22,B33=""),"",IF(7<=B23,0,MIN(B33,B24-C33))),"") -> 22638.481 | E33: =IFERROR(IF(C33="","",C33+D33),"") -> 23996.79 | F33: =IFERROR(IF(D33="","",B33-D33),"") -> 1.1277734e-10 | G33: =IFERROR(IF(E33="","",'PyG 3 Años'!$D$40-'PyG 3 Años'!$D$45+'PyG 3 Años'!$D$35+'PyG 3 Años'!$D$36),"") -> 52900.082 | H33: =IFERROR(IF(OR(E33="",E33=0),"",G33/E33),"") -> 2.2044649
A34: 8 | B34: =IFERROR(IF(OR(8>B22,F33=""),"",F33),"") | C34: =IFERROR(IF(OR(8>B22,B34=""),"",B34*B21),"") | D34: =IFERROR(IF(OR(8>B22,B34=""),"",IF(8<=B23,0,MIN(B34,B24-C34))),"") | E34: =IFERROR(IF(C34="","",C34+D34),"") | F34: =IFERROR(IF(D34="","",B34-D34),"") | G34: =IFERROR(IF(E34="","",'PyG 3 Años'!$D$40-'PyG 3 Años'!$D$45+'PyG 3 Años'!$D$35+'PyG 3 Años'!$D$36),"") | H34: =IFERROR(IF(OR(E34="",E34=0),"",G34/E34),"")
A35: 9 | B35: =IFERROR(IF(OR(9>B22,F34=""),"",F34),"") | C35: =IFERROR(IF(OR(9>B22,B35=""),"",B35*B21),"") | D35: =IFERROR(IF(OR(9>B22,B35=""),"",IF(9<=B23,0,MIN(B35,B24-C35))),"") | E35: =IFERROR(IF(C35="","",C35+D35),"") | F35: =IFERROR(IF(D35="","",B35-D35),"") | G35: =IFERROR(IF(E35="","",'PyG 3 Años'!$D$40-'PyG 3 Años'!$D$45+'PyG 3 Años'!$D$35+'PyG 3 Años'!$D$36),"") | H35: =IFERROR(IF(OR(E35="",E35=0),"",G35/E35),"")
A36: 10 | B36: =IFERROR(IF(OR(10>B22,F35=""),"",F35),"") | C36: =IFERROR(IF(OR(10>B22,B36=""),"",B36*B21),"") | D36: =IFERROR(IF(OR(10>B22,B36=""),"",IF(10<=B23,0,MIN(B36,B24-C36))),"") | E36: =IFERROR(IF(C36="","",C36+D36),"") | F36: =IFERROR(IF(D36="","",B36-D36),"") | G36: =IFERROR(IF(E36="","",'PyG 3 Años'!$D$40-'PyG 3 Años'!$D$45+'PyG 3 Años'!$D$35+'PyG 3 Años'!$D$36),"") | H36: =IFERROR(IF(OR(E36="",E36=0),"",G36/E36),"")
A37: 11 | B37: =IFERROR(IF(OR(11>B22,F36=""),"",F36),"") | C37: =IFERROR(IF(OR(11>B22,B37=""),"",B37*B21),"") | D37: =IFERROR(IF(OR(11>B22,B37=""),"",IF(11<=B23,0,MIN(B37,B24-C37))),"") | E37: =IFERROR(IF(C37="","",C37+D37),"") | F37: =IFERROR(IF(D37="","",B37-D37),"") | G37: =IFERROR(IF(E37="","",'PyG 3 Años'!$D$40-'PyG 3 Años'!$D$45+'PyG 3 Años'!$D$35+'PyG 3 Años'!$D$36),"") | H37: =IFERROR(IF(OR(E37="",E37=0),"",G37/E37),"")
A38: 12 | B38: =IFERROR(IF(OR(12>B22,F37=""),"",F37),"") | C38: =IFERROR(IF(OR(12>B22,B38=""),"",B38*B21),"") | D38: =IFERROR(IF(OR(12>B22,B38=""),"",IF(12<=B23,0,MIN(B38,B24-C38))),"") | E38: =IFERROR(IF(C38="","",C38+D38),"") | F38: =IFERROR(IF(D38="","",B38-D38),"") | G38: =IFERROR(IF(E38="","",'PyG 3 Años'!$D$40-'PyG 3 Años'!$D$45+'PyG 3 Años'!$D$35+'PyG 3 Años'!$D$36),"") | H38: =IFERROR(IF(OR(E38="",E38=0),"",G38/E38),"")
A39: 13 | B39: =IFERROR(IF(OR(13>B22,F38=""),"",F38),"") | C39: =IFERROR(IF(OR(13>B22,B39=""),"",B39*B21),"") | D39: =IFERROR(IF(OR(13>B22,B39=""),"",IF(13<=B23,0,MIN(B39,B24-C39))),"") | E39: =IFERROR(IF(C39="","",C39+D39),"") | F39: =IFERROR(IF(D39="","",B39-D39),"") | G39: =IFERROR(IF(E39="","",'PyG 3 Años'!$D$40-'PyG 3 Años'!$D$45+'PyG 3 Años'!$D$35+'PyG 3 Años'!$D$36),"") | H39: =IFERROR(IF(OR(E39="",E39=0),"",G39/E39),"")
A40: 14 | B40: =IFERROR(IF(OR(14>B22,F39=""),"",F39),"") | C40: =IFERROR(IF(OR(14>B22,B40=""),"",B40*B21),"") | D40: =IFERROR(IF(OR(14>B22,B40=""),"",IF(14<=B23,0,MIN(B40,B24-C40))),"") | E40: =IFERROR(IF(C40="","",C40+D40),"") | F40: =IFERROR(IF(D40="","",B40-D40),"") | G40: =IFERROR(IF(E40="","",'PyG 3 Años'!$D$40-'PyG 3 Años'!$D$45+'PyG 3 Años'!$D$35+'PyG 3 Años'!$D$36),"") | H40: =IFERROR(IF(OR(E40="",E40=0),"",G40/E40),"")
A41: 15 | B41: =IFERROR(IF(OR(15>B22,F40=""),"",F40),"") | C41: =IFERROR(IF(OR(15>B22,B41=""),"",B41*B21),"") | D41: =IFERROR(IF(OR(15>B22,B41=""),"",IF(15<=B23,0,MIN(B41,B24-C41))),"") | E41: =IFERROR(IF(C41="","",C41+D41),"") | F41: =IFERROR(IF(D41="","",B41-D41),"") | G41: =IFERROR(IF(E41="","",'PyG 3 Años'!$D$40-'PyG 3 Años'!$D$45+'PyG 3 Años'!$D$35+'PyG 3 Años'!$D$36),"") | H41: =IFERROR(IF(OR(E41="",E41=0),"",G41/E41),"")
A42: Tolerancia de cierre del cuadro (€) | B42: 0.01 | C42: Margen por redondeo. Por encima, el cuadro no cierra y hay capital sin devolver
A43: Capital pendiente al vencimiento | B43: =IFERROR(IF(B20="","",ROUND(B20-SUM(D27:D41),2)),"") -> 0 | C43: Tiene que ser cero: el principal devuelto en el cuadro tiene que ser el prestado. Si sale positivo, el plazo no llega
A44: Intereses del año 1 | B44: =IFERROR(IF(B20="","",IF(C27="",0,C27)),"") -> 7080
A45: Devolución de principal del año 1 | B45: =IFERROR(IF(B20="","",IF(D27="",0,D27)),"") -> 0
A46: Intereses del año 2 | B46: =IFERROR(IF(B20="","",IF(C28="",0,C28)),"") -> 7080
A47: Devolución de principal del año 2 | B47: =IFERROR(IF(B20="","",IF(D28="",0,D28)),"") -> 16916.79
A48: Intereses del año 3 | B48: =IFERROR(IF(B20="","",IF(C29="",0,C29)),"") -> 6064.9926
A49: Devolución de principal del año 3 | B49: =IFERROR(IF(B20="","",IF(D29="",0,D29)),"") -> 17931.798
A50: COBERTURA DEL SERVICIO DE LA DEUDA (DSCR)
A51: DSCR del año 1 | B51: =IFERROR(('PyG 3 Años'!$B$40-'PyG 3 Años'!$B$45+'PyG 3 Años'!$B$35+B44)/(B44+B45),"") -> 6.8613617 | C51: Año de CARENCIA si la hay: con sólo intereses en el denominador el ratio se dispara y no mide el negocio
A52: DSCR del año 2 | B52: =IFERROR(('PyG 3 Años'!$C$40-'PyG 3 Años'!$C$45+'PyG 3 Años'!$C$35+B46)/(B46+B47),"") -> 2.2935304
A53: DSCR del año 3 | B53: =IFERROR(('PyG 3 Años'!$D$40-'PyG 3 Años'!$D$45+'PyG 3 Años'!$D$35+B48)/(B48+B49),"") -> 2.2044649
A54: DSCR mínimo de todo el cuadro | B54: =IFERROR(IF(COUNT(H27:H41)=0,"",MIN(H27:H41)),"") -> 2.2044649 | C54: El peor año de los que dura el préstamo, no el mejor de los tres que proyecta el P&L. Es el número que decide una operación. Ojo al alcance: los años 1 a 3 salen del P&L y del año 4 en adelante el cuadro MANTIENE el flujo del año 3, así que el mínimo de esos años es una proyección sostenida, no un año calculado. El flujo va después de impuestos
A56: El DSCR se calcula ANTES de la deuda y DESPUÉS de impuestos: al resultado antes de impuestos se le resta el Impuesto de Sociedades y se le devuelven la amortización contable y los intereses; el resultado se divide entre lo que hay que pagar ese año. Por debajo del mínimo de la hoja de Supuestos, el negocio no genera para pagar el préstamo. En el cuadro, el flujo de caja disponible de los años 4 en adelante se mantiene en el del año 3: el P&L sólo proyecta tres, y aquí no se inventa un crecimiento que no está calculado.
