Workbook

Sheet 0. Supuestos
A1: SUPUESTOS — aquí se teclean las TASAS y los DRIVERS del modelo
A2: Cambia las celdas VERDES: el resto del libro se recalcula solo. Las partidas de gasto se teclean en su hoja (también en verde) y no se repiten aquí.
A3: ACTIVIDAD
A4: Invitados por evento (media del año 1) | B4: 94 | C4: Invitados (raciones) de media por evento en el año 1. Sale de la mezcla de cuatro tipos de evento de la tabla de referencias de la hoja de Instrucciones: bodas de 120, comidas de empresa de 70, fiestas privadas de 40 y fiestas populares de 400 raciones
A5: Precio medio por invitado SIN IVA (€) | B5: 16 | C5: SIN IVA, por ración. Media ponderada de la misma mezcla: 28 € la boda (dos variedades y entrantes), 24 € la comida de empresa, 18 € la fiesta privada y 5 € la ración de una fiesta popular. Por eso la media baja: no es el precio de un menú de boda. El precio con IVA (10 % en un servicio de comidas) está en la fila «PVP equivalente con IVA» de abajo
A6: Eventos al año | B6: 105 | C6: Eventos servidos en el año: 15 bodas, 30 comidas de empresa, 50 fiestas privadas (cumpleaños, comuniones, peñas, urbanizaciones) y 10 fiestas populares. Es el MISMO dato para la cuenta de resultados, el punto de equilibrio, los escenarios y las horas de personal
A7: Crecimiento de volumen del año 2 | B7: 0.1 | C7: Más volumen el segundo año: repetición de empresas, peñas y comisiones de fiestas, y bodas que llegan por recomendación. El libro lo aplica a las raciones por evento con los mismos eventos; en euros da lo mismo que hacer más eventos del mismo tamaño
A8: Crecimiento de volumen del año 3 | B8: 0.06 | C8: Sobre el año 2. Conservador: el techo lo ponen los fines de semana de temporada y un solo paellero titular
A9: PVP equivalente con IVA (calculado) | B9: =IFERROR(IF($B$5="","",$B$5*(1+SUMPRODUCT('PyG 3 Años'!$E$10:$E$11,'PyG 3 Años'!$G$10:$G$11))),"") -> 17.60352 | C9: =IFERROR("Precio por invitado sin IVA más el IVA medio ponderado de tus líneas de venta: "&TEXT(SUMPRODUCT('PyG 3 Años'!$E$10:$E$11,'PyG 3 Años'!$G$10:$G$11)*100,"0")&" %. En el servicio de paella todo va al 10 % (art. 91.Uno.2.2.º de la Ley 37/1992, alcohol incluido); el alcohol que sale en la paella para recoger mueve la media. Aquí va redondeado. Compáralo con el rango del sector, que va con IVA.","") -> Precio por invitado sin IVA más el IVA medio ponderado de tus líneas de venta: 10 %. En el servicio de paella todo va al 10 % (art. 91.Uno.2.2.º de la Ley 37/1992, alcohol incluido); el alcohol que sale en la paella para recoger mueve la media. Aquí va redondeado. Compáralo con el rango del sector, que va con IVA.
A10: MIX Y COSTE DE MERCANCÍA
A11: Ventas de COMIDA sobre el total | B11: 0.92 | C11: Peso de la COMIDA sobre el total de ventas. Es un INPUT: cámbialo aquí y el P&L, la tesorería y el IVA repercutido se recalculan solos
A12: Ventas de BEBIDA sobre el total | B12: =IFERROR(IF(COUNT(B11)=0,"",1-B11),"") -> 0.08 | C12: Se calcula como el resto: comida + bebida = 100 %
A13: Coste de mercancía sobre las ventas de COMIDA | B13: 0.28 | C13: Materia prima de la comida sobre las ventas de comida: arroz, carne, marisco, verdura, caldo, azafrán, aceite, entrantes y pan. En las fiestas populares sube al 45 % (paella sola a precio de volumen); la media de la mezcla queda en el 28 %. Escandalla cada arroz con la calculadora de este kit
A14: Coste de mercancía sobre las ventas de BEBIDA | B14: 0.3 | C14: Bebida sobre las ventas de bebida: el pack opcional de vino, cerveza, refrescos y agua. Si el cliente pone la bebida, esta línea baja
A15: Consumibles sobre ventas | B15: 0.03 | C15: Gas, leña, desechables, hielo y papel: unos 45 € por evento. Una paellera de 90 cm gasta 1-1,5 kg de gas por cocción (propano de 35 kg a 78,80 € en julio de 2026, boletín del IDAE)
A16: Ventas de paella para recoger (sin servicio) sobre el total | B16: 0.05 | C16: Parte de las ventas que se entrega SIN servicio: paella para recoger o entregada en su paellera, sin paellero en el evento. Es entrega de bienes: la comida va al 10 % y el alcohol y los refrescos, zumos y gaseosas con azúcares o edulcorantes añadidos, al 21 % (art. 91.Uno.1.1.º de la Ley 37/1992); el libro lo aplica al alcohol de esta parte
A17: Comisión de la plataforma de pedidos | B17: 0.1 | C17: Comisión media de la parte de la paella para recoger que entra por plataformas de pedidos o intermediarios. Si todos los pedidos los vendes tú, pon 0
A18: Comisión de los medios de pago | B18: 0.005 | C18: Casi todo se cobra por transferencia (anticipos y facturas de empresas y ayuntamientos); el datáfono queda para los cobros del día del evento
A19: PERSONAL
A20: Seguridad Social a cargo de la empresa | B20: 0.33 | C20: Contingencias comunes + AT/EP + desempleo + FOGASA + FP; ajusta a tu convenio y bonificaciones
A21: Número de pagas anuales | B21: 14 | C21: Salario bruto anual = bruto mensual × pagas
A22: SMI anual de referencia (€) | B22: 17094 | C22: SMI 2026: 17.094 € al año (1.221 €/mes en 14 pagas), suelo legal por jornada completa. Comprueba el importe vigente si presentas el plan en otro ejercicio
A23: COCINA DE APOYO Y FIJOS
A24: Cuota mensual de la cocina de apoyo (€) | B24: 900 | C24: Cuota de una cocina de apoyo compartida y autorizada: unas 35 horas al mes para caldos, sofritos y preparación, cámara frigorífica y almacén de paelleras y quemadores. La paella se cocina en el evento, pero lo que se prepara antes no se puede hacer en casa (art. 13.5.b del RD 1021/2022). No hay tarifa pública: pide dos presupuestos en tu zona
A25: Fianza de la cocina de apoyo (meses) | B25: 2 | C25: Dos cuotas de fianza, lo habitual en un contrato de uso de cocina compartida
A26: Suministros mensuales (consumos propios fuera de la cuota) (€) | B26: 50 | C26: Consumos propios fuera de la cuota de la cocina (datos móviles, luz del almacén). El gas de las paellas va en los consumibles, porque sube y baja con los eventos
A27: Seguros (€/año) | B27: 1750 | C27: Responsabilidad civil de explotación con incendio y explosión (por el gas) y daños al recinto, y de producto con intoxicación alimentaria de al menos 600.000 € (unos 700 €); seguro de la furgoneta de uso comercial (900 €) y de los equipos que salen a cada evento (150 €). La cancelación por una prohibición de fuego no se asegura: va en la cláusula de fuerza mayor del contrato
A28: Varios e imprevistos sobre ventas | B28: 0.045 | C28: Combustible de la furgoneta e imprevistos (3 puntos) y el canon que algunas fincas y wedding planners cobran al proveedor externo (1,5 puntos). Es variable: sube y baja con los eventos
A29: FINANCIACIÓN
A30: Recursos propios aportados (€) | B30: 20000 | C30: Aportación del socio. Un banco pide entre el 25 y el 30 % de la necesidad de caja con dinero propio
A31: Préstamo bancario solicitado (€) | B31: 51600 | C31: Principal solicitado. La hoja de Financiación compara lo que aportas con la necesidad de caja de la hoja de inversión y te dice si sobra o falta: ajústalo con ese dato
A32: Tipo de interés nominal anual | B32: 0.065 | C32: Tipo nominal anual de un préstamo de empresa sin garantía inmobiliaria. Pide oferta a dos entidades y a una línea ICO o ENISA antes de fijarlo
A33: Plazo del préstamo (años) | B33: 6 | C33: Años totales, carencia incluida: el plazo de vida de la furgoneta y del equipo
A34: Carencia de principal (años) | B34: 1 | C34: El primer año sólo intereses: es cuando la caja está más tensa, con la agenda de bodas y fiestas aún por llenar. Desde el segundo año se devuelve el principal: mira la holgura de caja de ese año en el Punto de Equilibrio
A35: Fondo de maniobra (meses de costes fijos) | B35: 3 | C35: Tres meses de costes fijos: cubren el invierno (enero, febrero y noviembre son los meses más bajos del año) y los 30 días que tardan en pagar empresas y ayuntamientos
A36: FISCAL
A37: Impuesto de Sociedades, nueva creación | B37: 0.15 | C37: Art. 29.1 LIS: el PRIMER ejercicio con base imponible positiva y el SIGUIENTE. El libro lo aproxima contando los dos primeros ejercicios con base positiva: coincide con la ley salvo que entre ellos haya un ejercicio en pérdidas
A38: Impuesto de Sociedades, tipo general | B38: 0.25 | C38: A partir del tercer ejercicio con base positiva. Es el tipo general del art. 29.1 LIS: si tu cifra de negocios queda por debajo de 1 M € (microempresa) o de 10 M € (reducida dimensión), desde 2025 hay tipos más bajos que se implantan de forma gradual; confirma el de tu ejercicio con tu asesor y cámbialo aquí
A39: IVA repercutido de restauración | B39: 0.1 | C39: Tipo reducido de hostelería
A40: IVA repercutido/soportado general | B40: 0.21 | C40: Tipo general. En este libro lo usan dos cosas: el IVA que soportas al comprar el alcohol (el proveedor lo factura al 21 %) y el que repercutes por el alcohol que sale por paella para recoger (es una entrega de bienes). El alcohol servido en el servicio de paella va al reducido: su tipo está en el bloque de desglose del IVA. Suministros, equipamiento y servicios tienen su tipo en la celda de abajo. El libro manda al general sólo el alcohol: si compras refrescos, zumos y gaseosas con azúcares o edulcorantes añadidos, su factura también va al 21 % (art. 91.Uno.1.1.º de la Ley 37/1992)
A41: IVA soportado en compras e inversión | B41: 0.21 | C41: Recuperable vía modelo 303, pero hay que adelantarlo
A42: Bases negativas de ejercicios anteriores (€) | B42: 0 | C42: Pérdidas pendientes de compensar al empezar (art. 26 LIS)
A43: AMORTIZACIÓN
A44: Vida útil de la furgoneta y su rotulación (años) | B44: 8 | C44: La furgoneta isoterma y su rotulación se amortizan en ocho años, el 12,5 % anual, por debajo del 16 % máximo para elementos de transporte de la tabla del art. 12.1 de la Ley del Impuesto sobre Sociedades. Confírmalo con tu asesor
A45: Vida útil de maquinaria y mobiliario (años) | B45: 10 | C45: Paelleras, quemadores, equipos de frío, carpa, utensilios y equipos informáticos: el coeficiente máximo de la tabla del art. 12.1 de la Ley del Impuesto sobre Sociedades es del 12 % para maquinaria y del 10 % para mobiliario
A47: CRECIMIENTO Y ACTUALIZACIÓN DE COSTES
A48: Subida anual de los costes fijos | B48: 0 | C48: A CERO: las tres columnas están en euros del año 1 (términos reales). Súbela si quieres proyectar en euros corrientes
A49: ARRANQUE Y CAPACIDAD
A51: Capacidad máxima por evento (invitados) | B51: 500 | C51: DATO INFORMATIVO: no entra en ningún cálculo. Es la fiesta más grande que puedes servir con dos paelleros, los dos auxiliares y tus paelleras (incluida la de 150 cm, de 90-120 raciones)
A52: Actividad del mes 1 sobre la de crucero | B52: 0.55 | C52: Un negocio de paellas que arranca factura poco el primer mes: las bodas se reservan con meses de antelación y las empresas y ayuntamientos tardan en repetir. Con 100 % se elimina la rampa
A53: Meses hasta alcanzar el régimen de crucero | B53: 6 | C53: Seis meses hasta el ritmo de crucero: una temporada de bodas y fiestas
A54: Meses de cuota de la cocina de apoyo ANTES del primer evento | B54: 1 | C54: Un mes de cuota para montar el almacén, probar los caldos y hacer las primeras degustaciones antes de facturar
A55: Imprevistos sobre la compra y la preparación de la furgoneta (%) | B55: 0.08 | C55: Se calcula sobre la furgoneta y su rotulación: es donde aparecen las sorpresas (revisión del equipo de frío o del certificado ATP, anclajes de las botellas de gas)
A57: COBROS, PAGOS Y DESGLOSE DEL IVA
A58: Días medios de cobro | B58: 20 | C58: Media ponderada: los particulares pagan el 30 % al firmar y el 70 % el día del evento (contratos del kit); las empresas, a 30 días de la factura, y los ayuntamientos, a 30 días desde la conformidad (art. 198.4 de la Ley 9/2017), unos 45 días en la práctica. Empresas y ayuntamientos son el 45 % de las ventas. El libro no admite días negativos, así que los anticipos no se modelan: tu caja real será algo MEJOR que la de la hoja de Tesorería
A59: Días medios de pago a proveedor | B59: 20 | C59: Plazo de pago a proveedores: el marisco y la carne se pagan a plazo corto; el arroz y el gas, a 30 días
A60: Mes de la paga extra de verano | B60: 7 | C60: Mes del año (1-12) en el que sale de caja la primera paga extra
A61: Mes de la paga extra de Navidad | B61: 12 | C61: Mes del año (1-12) en el que sale de caja la segunda paga extra
A62: Bebida ALCOHÓLICA sobre el total de bebida | B62: 0.5 | C62: Parte ALCOHÓLICA de la bebida (vino y cerveza del pack). Reparte el IVA que soportas al comprarla (21 % el alcohol) y el que repercutes en la paella para recoger
A63: IVA de la bebida ALCOHÓLICA servida en el evento | B63: 0.1 | C63: 10 %: el art. 91.Uno.2.2.º de la Ley 37/1992 grava al tipo reducido el «suministro de comidas y bebidas para consumir en el acto», sin excluir el alcohol, y un servicio de paella en directo lo es. El libro aplica el 21 % sólo al alcohol de la paella para recoger, que no se sirve
A64: UMBRALES Y SUELOS DE CONTROL
A65: DSCR mínimo aceptable | B65: 1 | C65: Por debajo de 1 el negocio no genera para pagar el préstamo. Ponlo en el covenant que te exija tu banco
A66: DSCR objetivo (verde) | B66: 1.25 | C66: Lo que suele pedir una entidad para dar el préstamo sin garantías adicionales
A67: Holgura mínima sobre el punto de equilibrio | B67: 0.15 | C67: Cuánto puedes caer sobre lo previsto antes de entrar en pérdidas
A68: Suelo salarial anual del convenio provincial (€) | B68: 0 | C68: El servicio de comidas para eventos está dentro del convenio de hostelería (art. 4 del V Acuerdo Laboral de ámbito Estatal para el sector de Hostelería): copia aquí el salario base del grupo más bajo de la tabla de TU provincia. Con 0 el semáforo compara sólo contra el SMI

Sheet Inversión Inicial
A1: PLAN DE NEGOCIO: PAELLERO / PAELLA PARA EVENTOS
A2: Inversión inicial estimada — paella y arroces en directo para eventos
A3: Ajusta las cifras a tu proyecto.
A5: Concepto | B5: Importe | C5: % s/inversión | D5: Notas | E5: ¿Lleva IVA?
A6: INVERSIÓN | B6: =IFERROR(IF(COUNT(B7:B23)=0,"",SUM(B7:B23)),"") -> 42686 | C6: =IFERROR(B6/$B$26,"") -> 0.67636231
A7: Furgoneta isoterma usada con certificado ATP | B7: 18000 | C7: =IFERROR(B7/$B$26,"") -> 0.28521111 | D7: Furgoneta usada con caja isoterma y equipo de frío, con el certificado ATP vigente (RD 237/2000) para llevar carne y marisco. Estimación del kit | E7: Sí
A8: Rotulación, estanterías y anclajes de botellas | B8: 1200 | C8: =IFERROR(B8/$B$26,"") -> 0.019014074 | D8: Rotulación con la marca, estanterías con amarres y anclajes para llevar las botellas de gas en pie y sujetas | E8: Sí
A9: Paelleras de 60 a 150 cm | B9: 2400 | C9: =IFERROR(B9/$B$26,"") -> 0.038028149 | D9: Diez paelleras de 60 a 120 cm y una de 150 cm para fiestas populares (90-120 raciones). Una de 90 cm ronda los 61 € (ManoMano, octubre de 2026) | E9: Sí
A10: Quemadores de anillos, patas y trípodes de leña | B10: 2100 | C10: =IFERROR(B10/$B$26,"") -> 0.03327463 | D10: Quemadores de 2 a 5 anillos con sus patas y dos trípodes para cocinar con leña donde esté permitido | E10: Sí
A11: Gas y seguridad: reguladores, flexibles, extintores y manta ignífuga | B11: 950 | C11: =IFERROR(B11/$B$26,"") -> 0.015052809 | D11: Reguladores, tubos flexibles en fecha, tres extintores de polvo ABC, manta ignífuga, cortavientos y el depósito de los envases de propano | E11: Sí
A12: Neveras, isotermos GN, sondas y acumuladores | B12: 1500 | C12: =IFERROR(B12/$B$26,"") -> 0.023767593 | D12: Cadena de frío del marisco y la carne desde la cocina de apoyo hasta el evento, y sondas para el registro del APPCC | E12: Sí
A13: Carpa, mesas plegables, lavamanos portátil y protector de suelo | B13: 1800 | C13: =IFERROR(B13/$B$26,"") -> 0.028521111 | D13: Zona de cocción bajo carpa, mesa de show cooking, lavamanos para el personal y protector del césped o del pavimento | E13: Sí
A14: Utensilios, ollas de caldo, cuchillería y básculas | B14: 1600 | C14: =IFERROR(B14/$B$26,"") -> 0.025352099 | D14: Paletas, cucharas, ollas de caldo de 50 litros, cuchillería, tablas de colores y básculas | E14: Sí
A15: Uniformes y EPI térmicos | B15: 400 | C15: =IFERROR(B15/$B$26,"") -> 0.0063380248 | D15: Chaquetas, delantales y guantes resistentes al calor | E15: Sí
A16: Marca, web, fotos, dossier y lanzamiento | B16: 4500 | C16: =IFERROR(B16/$B$26,"") -> 0.071302779 | D16: Identidad, web con formulario de presupuesto, sesión de fotos y vídeo, dossier para bodas, empresas y ayuntamientos, y degustaciones de lanzamiento | E16: Sí
A17: Software, tablet y datáfono | B17: 800 | C17: =IFERROR(B17/$B$26,"") -> 0.01267605 | D17: Presupuestos, agenda y facturación conforme a Veri*factu | E17: Sí
A18: Constitución SL + notaría + registro | B18: 1000 | C18: =IFERROR(B18/$B$26,"") -> 0.015845062 | D18: SL unipersonal. Las tasas y el arancel del Registro no llevan IVA; los honorarios del notario y de la gestoría sí: cambia la columna de al lado a «Sí» si tu presupuesto es sobre todo de honorarios | E18: No
... A20: Stock inicial de producto | B20: 1000 | C20: =IFERROR(B20/$B$26,"") -> 0.015845062 | D20: Arroz, especias, aceite, desechables y la primera carga de gas | E20: Sí
A21: Fianza de la cocina de apoyo | B21: =IFERROR(IF('0. Supuestos'!$B$24="","",'0. Supuestos'!$B$24*'0. Supuestos'!$B$25),"") -> 1800 | C21: =IFERROR(B21/$B$26,"") -> 0.028521111 | D21: =IFERROR(""&TEXT('0. Supuestos'!$B$25,"0")&" meses de renta, al tipo de la hoja de Supuestos. Es un activo recuperable al cerrar: ni se amortiza ni lleva IVA","") -> 2 meses de renta, al tipo de la hoja de Supuestos. Es un activo recuperable al cerrar: ni se amortiza ni lleva IVA | E21: No
A22: Cuota de la cocina de apoyo de los meses previos al arranque | B22: =IFERROR(IF('0. Supuestos'!$B$24="","",'0. Supuestos'!$B$24*'0. Supuestos'!$B$54),"") -> 900 | C22: =IFERROR(B22/$B$26,"") -> 0.014260556 | D22: =IFERROR("Renta "&IF('0. Supuestos'!$B$54=1,"del mes","de los "&TEXT('0. Supuestos'!$B$54,"0")&" meses")&" de puesta en marcha (pruebas de arroz y degustaciones). NO se solapa con el P&L, que arranca el día de la apertura: los doce meses del P&L son los doce de explotación","") -> Renta del mes de puesta en marcha (pruebas de arroz y degustaciones). NO se solapa con el P&L, que arranca el día de la apertura: los doce meses del P&L son los doce de explotación | E22: Sí
A23: Imprevistos de la compra y preparación de la furgoneta | B23: =IFERROR(IF(COUNT(B7,B8)=0,"",ROUND((B7+B8)*'0. Supuestos'!$B$55,0)),"") -> 1536 | C23: =IFERROR(B23/$B$26,"") -> 0.024338015 | D23: =IFERROR("Al "&TEXT('0. Supuestos'!$B$55,"0%")&" de las partidas de la furgoneta de este bloque (Furgoneta isoterma usada con certificado ATP y Rotulación, estanterías y anclajes de botellas), no del bloque entero: el resto de partidas del bloque quedan fuera. Un banco no financia una compra así sin colchón: el porcentaje está en la hoja de Supuestos","") -> Al 8% de las partidas de la furgoneta de este bloque (Furgoneta isoterma usada con certificado ATP y Rotulación, estanterías y anclajes de botellas), no del bloque entero: el resto de partidas del bloque quedan fuera. Un banco no financia una compra así sin colchón: el porcentaje está en la hoja de Supuestos | E23: Sí
A24: FONDO DE MANIOBRA | B24: =IFERROR(IF(B25="","",B25),"") -> 20425.145 | C24: =IFERROR(B24/$B$26,"") -> 0.32363769
A25: Colchón operativo hasta alcanzar el equilibrio | B25: =IFERROR(IF('0. Supuestos'!$B$35*('PyG 3 Años'!$B$38-'PyG 3 Años'!$B$36)=0,"",'0. Supuestos'!$B$35*('PyG 3 Años'!$B$38-'PyG 3 Años'!$B$36)/12),"") -> 20425.145 | C25: =IFERROR(B25/$B$26,"") -> 0.32363769 | D25: =IFERROR("Cubre "&TEXT('0. Supuestos'!$B$35,"0")&IF('0. Supuestos'!$B$35=1," mes"," meses")&" de costes fijos DE CAJA del año 1 (los del P&L menos la amortización, que no se paga), que es el mínimo que exigen las Instrucciones de este libro","") -> Cubre 3 meses de costes fijos DE CAJA del año 1 (los del P&L menos la amortización, que no se paga), que es el mínimo que exigen las Instrucciones de este libro | E25: No
A26: INVERSIÓN TOTAL (suma de los bloques) | B26: =IFERROR(B6+B24,"") -> 63111.145 | D26: =IFERROR("Los porcentajes de la columna C se leen sobre esta cifra, que incluye el fondo de maniobra ("&TEXT(C24,"0%")&" del total). Para comparar el desglose con otro plan, usa la fila de CAPEX de abajo.","") -> Los porcentajes de la columna C se leen sobre esta cifra, que incluye el fondo de maniobra (32% del total). Para comparar el desglose con otro plan, usa la fila de CAPEX de abajo.
A27: CAPEX (inversión sin el fondo de maniobra) | B27: =IFERROR(B26-B24,"") -> 42686 | D27: Es lo que se compra: furgoneta, equipamiento, lanzamiento y gastos de constitución. El colchón de caja no es inversión, es circulante
A28: IVA soportado sobre la inversión (recuperable) | B28: =IFERROR(IF(B26="","",SUMIF($E$7:$E$23,"Sí",$B$7:$B$23)*'0. Supuestos'!$B$41),"") -> 8376.06 | D28: =IFERROR("Al "&TEXT('0. Supuestos'!$B$41,"0%")&" sobre las partidas marcadas con «Sí» en la columna de IVA. Las tasas y licencias no están sujetas y los seguros están exentos (art. 20.Uno.16 LIVA). Las tasas y aranceles registrales no llevan IVA; los honorarios de notaría y gestoría sí (21 %, deducible). Se recupera con el modelo 303, pero hay que adelantarlo","") -> Al 21% sobre las partidas marcadas con «Sí» en la columna de IVA. Las tasas y licencias no están sujetas y los seguros están exentos (art. 20.Uno.16 LIVA). Las tasas y aranceles registrales no llevan IVA; los honorarios de notaría y gestoría sí (21 %, deducible). Se recupera con el modelo 303, pero hay que adelantarlo
A29: NECESIDAD TOTAL DE CAJA AL ARRANQUE | B29: =IFERROR(B26+B28,"") -> 71487.205 | D29: Es la cifra que tiene que cubrir la hoja de Financiación
A30: BASES DE AMORTIZACIÓN (no suman a la inversión)
A31: Furgoneta, rotulación e imprevistos | B31: =IFERROR(IF(B7="","",B7+B8+B23),"") -> 20736 | D31: =IFERROR("Se amortiza en "&TEXT('0. Supuestos'!$B$44,"0")&" años","") -> Se amortiza en 8 años
A32: Maquinaria, mobiliario y equipos | B32: =IFERROR(IF(B9="","",B9+B10+B11+B12+B13+B14+B15+B17),"") -> 11550 | D32: =IFERROR("Se amortiza en "&TEXT('0. Supuestos'!$B$45,"0")&" años","") -> Se amortiza en 10 años
A33: Amortización anual del inmovilizado | B33: =IFERROR(B31/MAX(1,'0. Supuestos'!$B$44)+B32/MAX(1,'0. Supuestos'!$B$45),"") -> 3747 | D33: =IFERROR("No se amortizan, por no ser inmovilizado, Marca, web, fotos, dossier y lanzamiento, Constitución SL + notaría + registro, Declaración responsable, plan APPCC, alérgenos y formación, Stock inicial de producto, Fianza de la cocina de apoyo, Cuota de la cocina de apoyo de los meses previos al arranque ni Colchón operativo hasta alcanzar el equilibrio. Suman "&TEXT(B26-B31-B32,"0")&" € de los "&TEXT(B26,"0")&" € de inversión.","") -> No se amortizan, por no ser inmovilizado, Marca, web, fotos, dossier y lanzamiento, Constitución SL + notaría + registro, Declaración responsable, plan APPCC, alérgenos y formación, Stock inicial de producto, Fianza de la cocina de apoyo, Cuota de la cocina de apoyo de los meses previos al arranque ni Colchón operativo hasta alcanzar el equilibrio. Suman 30825 € de los 63111 € de inversión.

Sheet PyG 3 Años
A1: CUENTA DE RESULTADOS PREVISIONAL — 3 AÑOS
A2: Escenario realista — paellero para eventos
A4: Concepto | B4: Año 1 | C4: Año 2 | D4: Año 3 | E4: % s/ventas (año 1) | F4: Notas | G4: Tipo de IVA de la línea (%)
A5: INGRESOS
A6: Invitados por evento (media) | B6: =IFERROR(IF('0. Supuestos'!$B$4="","",'0. Supuestos'!$B$4),"") -> 94 | C6: =IFERROR(B6*(1+'0. Supuestos'!$B$7),"") -> 103.4 | D6: =IFERROR(C6*(1+'0. Supuestos'!$B$8),"") -> 109.604 | F6: El crecimiento de los años 2 y 3 está en la hoja de Supuestos
A7: Precio medio por invitado sin IVA | B7: =IFERROR(IF('0. Supuestos'!$B$5="","",'0. Supuestos'!$B$5),"") -> 16 | C7: =IFERROR(IF(B7="","",B7),"") -> 16 | D7: =IFERROR(IF(C7="","",C7),"") -> 16 | F7: Constante en euros del año 1: una subida de precios es una decisión aparte
A8: Eventos al año | B8: =IFERROR(IF('0. Supuestos'!$B$6="","",'0. Supuestos'!$B$6),"") -> 105 | C8: =IFERROR(IF(B8="","",B8),"") -> 105 | D8: =IFERROR(IF(C8="","",C8),"") -> 105
A9: INGRESOS TOTALES (sin IVA) | B9: =IFERROR(IF(B6*B7*B8=0,"",B6*B7*B8),"") -> 157920 | C9: =IFERROR(IF(C6*C7*C8=0,"",C6*C7*C8),"") -> 173712 | D9: =IFERROR(IF(D6*D7*D8=0,"",D6*D7*D8),"") -> 184134.72 | E9: =IFERROR(IF(B9="","",1),"") -> 1
A10: Ventas de comida (paellas y arroces en directo, entrantes y postre) | B10: =IFERROR(IF(B9="","",B9*$E$10),"") -> 145286.4 | C10: =IFERROR(IF(C9="","",C9*$E$10),"") -> 159815.04 | D10: =IFERROR(IF(D9="","",D9*$E$10),"") -> 169403.94 | E10: =IFERROR(IF('0. Supuestos'!$B$11="","",'0. Supuestos'!$B$11),"") -> 0.92 | F10: Paellas y arroces cocinados en el evento, con show cooking cuando se contrata, entrantes, pan, alioli y postre. Las fiestas populares son paella sola por ración | G10: =IFERROR(IF(B9="","",'0. Supuestos'!$B$39),"") -> 0.1
A11: Ventas de bebida (pack opcional de vino, cerveza y refrescos) | B11: =IFERROR(IF(B9="","",B9*$E$11),"") -> 12633.6 | C11: =IFERROR(IF(C9="","",C9*$E$11),"") -> 13896.96 | D11: =IFERROR(IF(D9="","",D9*$E$11),"") -> 14730.778 | E11: =IFERROR(IF('0. Supuestos'!$B$12="","",'0. Supuestos'!$B$12),"") -> 0.08 | F11: Pack de bebida que algunos clientes contratan con la paella; en muchas fiestas la bebida la pone el cliente | G11: =IFERROR(IF(B9="","",('0. Supuestos'!$B$62*((1-'0. Supuestos'!$B$16)*'0. Supuestos'!$B$63+'0. Supuestos'!$B$16*'0. Supuestos'!$B$40)+(1-'0. Supuestos'!$B$62)*'0. Supuestos'!$B$39)),"") -> 0.10275
A12: COSTES VARIABLES
A13: Coste de mercancía — comida | B13: =IFERROR(IF(B9="","",B9*'0. Supuestos'!$B$11*'0. Supuestos'!$B$13),"") -> 40680.192 | C13: =IFERROR(IF(C9="","",C9*'0. Supuestos'!$B$11*'0. Supuestos'!$B$13),"") -> 44748.211 | D13: =IFERROR(IF(D9="","",D9*'0. Supuestos'!$B$11*'0. Supuestos'!$B$13),"") -> 47433.104 | E13: =IFERROR(B13/$B$9,"") -> 0.2576 | F13: =IFERROR("Al "&TEXT('0. Supuestos'!$B$13,"0%")&" de las ventas de COMIDA, no del total: la bebida tiene su propia línea","") -> Al 28% de las ventas de COMIDA, no del total: la bebida tiene su propia línea | G13: =IFERROR(IF(B9="","",'0. Supuestos'!$B$39),"") -> 0.1
A14: Coste de mercancía — bebida | B14: =IFERROR(IF(B9="","",B9*'0. Supuestos'!$B$12*'0. Supuestos'!$B$14),"") -> 3790.08 | C14: =IFERROR(IF(C9="","",C9*'0. Supuestos'!$B$12*'0. Supuestos'!$B$14),"") -> 4169.088 | D14: =IFERROR(IF(D9="","",D9*'0. Supuestos'!$B$12*'0. Supuestos'!$B$14),"") -> 4419.2333 | E14: =IFERROR(B14/$B$9,"") -> 0.024 | F14: =IFERROR("Al "&TEXT('0. Supuestos'!$B$14,"0%")&" de las ventas de BEBIDA","") -> Al 30% de las ventas de BEBIDA | G14: =IFERROR(IF(B9="","",('0. Supuestos'!$B$62*'0. Supuestos'!$B$40+(1-'0. Supuestos'!$B$62)*'0. Supuestos'!$B$39)),"") -> 0.155
A15: Consumibles y envases | B15: =IFERROR(IF(B9="","",B9*'0. Supuestos'!$B$15),"") -> 4737.6 | C15: =IFERROR(IF(C9="","",C9*'0. Supuestos'!$B$15),"") -> 5211.36 | D15: =IFERROR(IF(D9="","",D9*'0. Supuestos'!$B$15),"") -> 5524.0416 | E15: =IFERROR(B15/$B$9,"") -> 0.03 | G15: =IFERROR(IF(B9="","",'0. Supuestos'!$B$41),"") -> 0.21
A16: Comisiones de la paella para recoger | B16: =IFERROR(IF(B9="","",B9*'0. Supuestos'!$B$16*'0. Supuestos'!$B$17),"") -> 789.6 | C16: =IFERROR(IF(C9="","",C9*'0. Supuestos'!$B$16*'0. Supuestos'!$B$17),"") -> 868.56 | D16: =IFERROR(IF(D9="","",D9*'0. Supuestos'!$B$16*'0. Supuestos'!$B$17),"") -> 920.6736 | E16: =IFERROR(B16/$B$9,"") -> 0.005 | F16: Sobre las ventas DEL CANAL. Con 0 % de paella para recoger en Supuestos, esta línea vale cero | G16: =IFERROR(IF(B9="","",'0. Supuestos'!$B$41),"") -> 0.21
A17: Comisiones de los medios de pago | B17: =IFERROR(IF(B9="","",B9*'0. Supuestos'!$B$18),"") -> 789.6 | C17: =IFERROR(IF(C9="","",C9*'0. Supuestos'!$B$18),"") -> 868.56 | D17: =IFERROR(IF(D9="","",D9*'0. Supuestos'!$B$18),"") -> 920.6736 | E17: =IFERROR(B17/$B$9,"") -> 0.005 | F17: Las comisiones de los medios de pago están EXENTAS de IVA (art. 20.Uno.18 LIVA): no se deduce nada por ellas | G17: 0
A18: Varios e imprevistos | B18: =IFERROR(IF(B9="","",B9*'0. Supuestos'!$B$28),"") -> 7106.4 | C18: =IFERROR(IF(C9="","",C9*'0. Supuestos'!$B$28),"") -> 7817.04 | D18: =IFERROR(IF(D9="","",D9*'0. Supuestos'!$B$28),"") -> 8286.0624 | E18: =IFERROR(B18/$B$9,"") -> 0.045 | F18: =IFERROR("Al "&TEXT('0. Supuestos'!$B$28,"0%")&" de las ventas. Es un coste VARIABLE: sube y baja con la facturación, así que no puede vivir en los costes fijos","") -> Al 4% de las ventas. Es un coste VARIABLE: sube y baja con la facturación, así que no puede vivir en los costes fijos | G18: =IFERROR(IF(B9="","",'0. Supuestos'!$B$41),"") -> 0.21
A19: TOTAL COSTES VARIABLES | B19: =IFERROR(IF(B9="","",SUM(B13:B18)),"") -> 57893.472 | C19: =IFERROR(IF(C9="","",SUM(C13:C18)),"") -> 63682.819 | D19: =IFERROR(IF(D9="","",SUM(D13:D18)),"") -> 67503.788 | E19: =IFERROR(B19/$B$9,"") -> 0.3666
A20: MARGEN BRUTO | B20: =IFERROR(IF(B9="","",B9-B19),"") -> 100026.53 | C20: =IFERROR(IF(C9="","",C9-C19),"") -> 110029.18 | D20: =IFERROR(IF(D9="","",D9-D19),"") -> 116630.93 | E20: =IFERROR(B20/$B$9,"") -> 0.6334
A21: COSTES FIJOS
A22: Cuota de la cocina de apoyo compartida | B22: =IFERROR(IF(B9="","",'0. Supuestos'!$B$24*12),"") -> 10800 | C22: =IFERROR(IF(C9="","",B22*(1+'0. Supuestos'!$B$48)),"") -> 10800 | D22: =IFERROR(IF(D9="","",C22*(1+'0. Supuestos'!$B$48)),"") -> 10800 | E22: =IFERROR(B22/$B$9,"") -> 0.068389058 | F22: El importe mensual está en la hoja de Supuestos; aquí se multiplica por doce. Es el contrato de uso de una cocina de apoyo compartida y autorizada (horas de cocina, cámara y almacén de paelleras y quemadores). El mes previo al primer evento está en la hoja de Inversión y NO se cuenta dos veces | G22: =IFERROR(IF(B9="","",'0. Supuestos'!$B$41),"") -> 0.21
A23: Personal (nóminas + Seguridad Social) | B23: =IFERROR(IF(B9="","",'Personal'!$G$9),"") -> 55096.58 | C23: =IFERROR(IF(C9="","",'Personal'!$B$13),"") -> 61096.58 | D23: =IFERROR(IF(D9="","",'Personal'!$B$14),"") -> 67096.58 | E23: =IFERROR(B23/$B$9,"") -> 0.34888918 | F23: Sale de la hoja de Personal: es el MISMO número, no una estimación aparte. Los años 2 y 3 suman las INCORPORACIONES declaradas en esa hoja, no un porcentaje de volumen | G23: 0
A24: Suministros (consumos propios fuera de la cuota) | B24: =IFERROR(IF(B9="","",'0. Supuestos'!$B$26*12),"") -> 600 | C24: =IFERROR(IF(C9="","",B24*(1+'0. Supuestos'!$B$48)),"") -> 600 | D24: =IFERROR(IF(D9="","",C24*(1+'0. Supuestos'!$B$48)),"") -> 600 | E24: =IFERROR(B24/$B$9,"") -> 0.0037993921 | F24: Consumos propios fuera de la cuota de la cocina. El gas de las paellas va en los consumibles. Va al 21 % de IVA | G24: =IFERROR(IF(B9="","",'0. Supuestos'!$B$41),"") -> 0.21
A25: Seguros (RC + multirriesgo) | B25: =IFERROR(IF(B9="","",'0. Supuestos'!$B$27),"") -> 1750 | C25: =IFERROR(IF(C9="","",B25*(1+'0. Supuestos'!$B$48)),"") -> 1750 | D25: =IFERROR(IF(D9="","",C25*(1+'0. Supuestos'!$B$48)),"") -> 1750 | E25: =IFERROR(B25/$B$9,"") -> 0.01108156 | F25: Las operaciones de seguro están EXENTAS de IVA (art. 20.Uno.16 LIVA): la prima no lleva IVA deducible | G25: 0
A26: Asesoría fiscal y laboral (nóminas de fijos discontinuos) | B26: 1800 | C26: =IFERROR(IF(C9="","",B26*(1+'0. Supuestos'!$B$48)),"") -> 1800 | D26: =IFERROR(IF(D9="","",C26*(1+'0. Supuestos'!$B$48)),"") -> 1800 | E26: =IFERROR(B26/$B$9,"") -> 0.011398176 | F26: Contabilidad, impuestos de la SL y nóminas de los fijos discontinuos de cada mes con llamamientos | G26: =IFERROR(IF(B9="","",'0. Supuestos'!$B$41),"") -> 0.21
A27: Furgoneta: mantenimiento, ITV e inspección ATP | B27: 1200 | C27: =IFERROR(IF(C9="","",B27*(1+'0. Supuestos'!$B$48)),"") -> 1200 | D27: =IFERROR(IF(D9="","",C27*(1+'0. Supuestos'!$B$48)),"") -> 1200 | E27: =IFERROR(B27/$B$9,"") -> 0.0075987842 | F27: Taller, neumáticos, ITV y la inspección periódica del certificado ATP del equipo de frío (RD 237/2000) | G27: =IFERROR(IF(B9="","",'0. Supuestos'!$B$41),"") -> 0.21
A28: Marketing y publicidad | B28: 4000 | C28: =IFERROR(IF(C9="","",B28*(1+'0. Supuestos'!$B$48)),"") -> 4000 | D28: =IFERROR(IF(D9="","",C28*(1+'0. Supuestos'!$B$48)),"") -> 4000 | E28: =IFERROR(B28/$B$9,"") -> 0.025329281 | F28: Google Ads local, un escaparate de bodas, redes sociales y una feria al año | G28: =IFERROR(IF(B9="","",'0. Supuestos'!$B$41),"") -> 0.21
A29: Software de gestión comercial, CRM y teléfono | B29: 900 | C29: =IFERROR(IF(C9="","",B29*(1+'0. Supuestos'!$B$48)),"") -> 900 | D29: =IFERROR(IF(D9="","",C29*(1+'0. Supuestos'!$B$48)),"") -> 900 | E29: =IFERROR(B29/$B$9,"") -> 0.0056990881 | F29: Presupuestos, agenda de eventos, CRM de clientes y línea de teléfono | G29: =IFERROR(IF(B9="","",'0. Supuestos'!$B$41),"") -> 0.21
A30: Revisión de gas por instaladora y mantenimiento de extintores | B30: 400 | C30: =IFERROR(IF(C9="","",B30*(1+'0. Supuestos'!$B$48)),"") -> 400 | D30: =IFERROR(IF(D9="","",C30*(1+'0. Supuestos'!$B$48)),"") -> 400 | E30: =IFERROR(B30/$B$9,"") -> 0.0025329281 | F30: Revisión de reguladores, flexibles y quemadores por una empresa instaladora de gas y mantenimiento anual de los extintores por una empresa mantenedora. Estimación del kit | G30: =IFERROR(IF(B9="","",'0. Supuestos'!$B$41),"") -> 0.21
A31: Uniformes y lavandería | B31: 400 | C31: =IFERROR(IF(C9="","",B31*(1+'0. Supuestos'!$B$48)),"") -> 400 | D31: =IFERROR(IF(D9="","",C31*(1+'0. Supuestos'!$B$48)),"") -> 400 | E31: =IFERROR(B31/$B$9,"") -> 0.0025329281 | F31: Chaquetas, delantales y paños: lavado y reposición | G31: =IFERROR(IF(B9="","",'0. Supuestos'!$B$41),"") -> 0.21
A32: Gestión de residuos (orgánico y aceite usado) | B32: 200 | C32: =IFERROR(IF(C9="","",B32*(1+'0. Supuestos'!$B$48)),"") -> 200 | D32: =IFERROR(IF(D9="","",C32*(1+'0. Supuestos'!$B$48)),"") -> 200 | E32: =IFERROR(B32/$B$9,"") -> 0.001266464 | F32: Gestor autorizado del aceite usado, salvo que la cocina de apoyo lo incluya en la cuota | G32: =IFERROR(IF(B9="","",'0. Supuestos'!$B$41),"") -> 0.21
A33: Prevención de riesgos laborales y vigilancia de la salud | B33: 400 | C33: =IFERROR(IF(C9="","",B33*(1+'0. Supuestos'!$B$48)),"") -> 400 | D33: =IFERROR(IF(D9="","",C33*(1+'0. Supuestos'!$B$48)),"") -> 400 | E33: =IFERROR(B33/$B$9,"") -> 0.0025329281 | F33: Plan de prevención obligatorio (Ley 31/1995): quemaduras, gas, calor y cargas, y reconocimientos médicos de la plantilla | G33: =IFERROR(IF(B9="","",'0. Supuestos'!$B$41),"") -> 0.21
A34: Pruebas de arroz y degustaciones comerciales | B34: 600 | C34: =IFERROR(IF(C9="","",B34*(1+'0. Supuestos'!$B$48)),"") -> 600 | D34: =IFERROR(IF(D9="","",C34*(1+'0. Supuestos'!$B$48)),"") -> 600 | E34: =IFERROR(B34/$B$9,"") -> 0.0037993921 | F34: Producto y horas de las pruebas para novios y de las degustaciones a empresas y comisiones de fiestas que no se cobran | G34: =IFERROR(IF(B9="","",'0. Supuestos'!$B$41),"") -> 0.21
A35: Permisos y autorizaciones municipales | B35: 200 | C35: =IFERROR(IF(C9="","",B35*(1+'0. Supuestos'!$B$48)),"") -> 200 | D35: =IFERROR(IF(D9="","",C35*(1+'0. Supuestos'!$B$48)),"") -> 200 | E35: =IFERROR(B35/$B$9,"") -> 0.001266464 | F35: Autorizaciones de ocupación de la vía pública o de uso del fuego y tasas que no repercutes al cliente. Estimación del kit: varía mucho por municipio | G35: =IFERROR(IF(B9="","",'0. Supuestos'!$B$41),"") -> 0.21
A36: Amortización del inmovilizado | B36: =IFERROR(IF(B9="","",'Inversión Inicial'!$B$33),"") -> 3747 | C36: =IFERROR(IF(C9="","",B36),"") -> 3747 | D36: =IFERROR(IF(D9="","",B36),"") -> 3747 | E36: =IFERROR(B36/$B$9,"") -> 0.023727204 | F36: Sale de las bases de amortización de la hoja de Inversión: sólo inmovilizado real. NO sube con el IPC: es una cuota sobre el coste HISTÓRICO del inmovilizado | G36: 0
A37: Gastos financieros (intereses del préstamo) | B37: =IFERROR(IF(B9="","",'Financiación'!$B$44),"") -> 3354 | C37: =IFERROR(IF(C9="","",'Financiación'!$B$46),"") -> 3354 | D37: =IFERROR(IF(D9="","",'Financiación'!$B$48),"") -> 2764.9218 | E37: =IFERROR(B37/$B$9,"") -> 0.021238602 | F37: Sólo los INTERESES son gasto. La devolución del principal va en la hoja de Tesorería | G37: 0
A38: TOTAL COSTES FIJOS | B38: =IFERROR(IF(B9="","",SUM(B22:B37)),"") -> 85447.58 | C38: =IFERROR(IF(C9="","",SUM(C22:C37)),"") -> 91447.58 | D38: =IFERROR(IF(D9="","",SUM(D22:D37)),"") -> 96858.502 | E38: =IFERROR(B38/$B$9,"") -> 0.54108143
A39: IVA soportado de los costes variables | B39: =IFERROR(IF(B9="","",SUMPRODUCT(B13:B18,G13:G18)),"") -> 7308.5376 | C39: =IFERROR(IF(C9="","",SUMPRODUCT(C13:C18,G13:G18)),"") -> 8039.3914 | D39: =IFERROR(IF(D9="","",SUMPRODUCT(D13:D18,G13:G18)),"") -> 8521.7548 | F39: Cada línea a SU tipo, leído de la columna de al lado. Es lo que la hoja de Tesorería paga de más a los proveedores y luego se deduce
A40: IVA soportado de los costes fijos | B40: =IFERROR(IF(B9="","",SUMPRODUCT(B22:B37,G22:G37)),"") -> 4515 | C40: =IFERROR(IF(C9="","",SUMPRODUCT(C22:C37,G22:G37)),"") -> 4515 | D40: =IFERROR(IF(D9="","",SUMPRODUCT(D22:D37,G22:G37)),"") -> 4515
A41: RESULTADO ANTES DE IMPUESTOS | B41: =IFERROR(IF(B9="","",B20-B38),"") -> 14578.948 | C41: =IFERROR(IF(C9="","",C20-C38),"") -> 18581.601 | D41: =IFERROR(IF(D9="","",D20-D38),"") -> 19772.43 | E41: =IFERROR(B41/$B$9,"") -> 0.092318566
A42: Bases negativas pendientes al inicio | B42: =IFERROR(IF(B9="","",'0. Supuestos'!$B$42),"") -> 0 | C42: =IFERROR(IF(C9="","",B47),"") -> 0 | D42: =IFERROR(IF(D9="","",C47),"") -> 0 | F42: Art. 26 LIS: las pérdidas de un ejercicio se compensan con los beneficios de los siguientes
A43: Base imponible (después de compensar) | B43: =IFERROR(IF(B9="","",MAX(0,B41-B42)),"") -> 14578.948 | C43: =IFERROR(IF(C9="","",MAX(0,C41-C42)),"") -> 18581.601 | D43: =IFERROR(IF(D9="","",MAX(0,D41-D42)),"") -> 19772.43
A44: Ejercicios con base positiva (acumulado) | B44: =IFERROR(IF(B9="","",IF(B43>0,1,0)),"") -> 1 | C44: =IFERROR(IF(C9="","",B44+IF(C43>0,1,0)),"") -> 2 | D44: =IFERROR(IF(D9="","",C44+IF(D43>0,1,0)),"") -> 3
A45: Tipo de Impuesto de Sociedades aplicado | B45: =IFERROR(IF(B9="","",IF(B43<=0,"",IF(B44<=2,'0. Supuestos'!$B$37,'0. Supuestos'!$B$38))),"") -> 0.15 | C45: =IFERROR(IF(C9="","",IF(C43<=0,"",IF(C44<=2,'0. Supuestos'!$B$37,'0. Supuestos'!$B$38))),"") -> 0.15 | D45: =IFERROR(IF(D9="","",IF(D43<=0,"",IF(D44<=2,'0. Supuestos'!$B$37,'0. Supuestos'!$B$38))),"") -> 0.25 | F45: Art. 29.1 LIS: el 15 % de entidad de nueva creación se aplica al PRIMER ejercicio con base positiva y al SIGUIENTE, no al primer año de vida. El libro lo aproxima contando los dos primeros ejercicios con base positiva
A46: Impuesto de Sociedades | B46: =IFERROR(IF(B9="","",IF(B45="",0,B43*B45)),"") -> 2186.8422 | C46: =IFERROR(IF(C9="","",IF(C45="",0,C43*C45)),"") -> 2787.2401 | D46: =IFERROR(IF(D9="","",IF(D45="",0,D43*D45)),"") -> 4943.1075
A47: Bases negativas pendientes al cierre | B47: =IFERROR(IF(B9="","",MAX(0,B42-B41)),"") -> 0 | C47: =IFERROR(IF(C9="","",MAX(0,C42-C41)),"") -> 0 | D47: =IFERROR(IF(D9="","",MAX(0,D42-D41)),"") -> 0
A48: RESULTADO NETO | B48: =IFERROR(IF(B9="","",B41-B46),"") -> 12392.106 | C48: =IFERROR(IF(C9="","",C41-C46),"") -> 15794.361 | D48: =IFERROR(IF(D9="","",D41-D46),"") -> 14829.322 | E48: =IFERROR(B48/$B$9,"") -> 0.078470781
A49: RATIOS CLAVE
A50: Ratio | B50: Año 1 | C50: Año 2 | D50: Año 3 | E50: Umbral | F50: Comentario
A51: Margen bruto / Ventas | B51: =IFERROR(IF(B9="","",B20/B9),"") -> 0.6334 | C51: =IFERROR(IF(C9="","",C20/C9),"") -> 0.6334 | D51: =IFERROR(IF(D9="","",D20/D9),"") -> 0.6334 | E51: 0.6 | F51: Los costes variables de la paella incluyen gas, desechables, combustible y cánones de fincas además de la mercancía: un margen bruto por debajo del 60 % no paga la plantilla
A52: Coste de mercancía (comida + bebida) | B52: =IFERROR(IF(B9="","",B13+B14),"") -> 44470.272 | C52: =IFERROR(IF(C9="","",C13+C14),"") -> 48917.299 | D52: =IFERROR(IF(D9="","",D13+D14),"") -> 51852.337
A53: Coste de mercancía / Ventas | B53: =IFERROR(IF(B9="","",B52/B9),"") -> 0.2816 | C53: =IFERROR(IF(C9="","",C52/C9),"") -> 0.2816 | D53: =IFERROR(IF(D9="","",D52/D9),"") -> 0.2816 | E53: 0.32 | F53: Techo de la mercancía (comida y bebida) sobre ventas: estimación del kit
A54: Coste de personal / Ventas | B54: =IFERROR(IF(B9="","",B23/B9),"") -> 0.34888918 | C54: =IFERROR(IF(C9="","",C23/C9),"") -> 0.35171191 | D54: =IFERROR(IF(D9="","",D23/D9),"") -> 0.36438853 | E54: 0.38 | F54: Techo del personal sobre ventas: montaje, cocción, servicio y recogida en cada evento. Estimación del kit
A55: Cocina de apoyo / Ventas | B55: =IFERROR(IF(B9="","",B22/B9),"") -> 0.068389058 | C55: =IFERROR(IF(C9="","",C22/C9),"") -> 0.062171871 | D55: =IFERROR(IF(D9="","",D22/D9),"") -> 0.058652708 | E55: 0.08 | F55: Techo de la cuota de la cocina de apoyo sobre las ventas: estimación del kit
A56: Resultado neto / Ventas | B56: =IFERROR(IF(B9="","",B48/B9),"") -> 0.078470781 | C56: =IFERROR(IF(C9="","",C48/C9),"") -> 0.090922681 | D56: =IFERROR(IF(D9="","",D48/D9),"") -> 0.080535178 | E56: 0.04 | F56: Suelo de resultado neto para que el plan se sostenga: estimación del kit
A57: Punto de equilibrio alcanzado | B57: =IFERROR(IF(B9="","",IF(B9>='Punto Equilibrio'!$B$16,"Sí","No")),"") -> Sí | C57: =IFERROR(IF(C9="","",IF(C9>='Punto Equilibrio'!$C$16,"Sí","No")),"") -> Sí | D57: =IFERROR(IF(D9="","",IF(D9>='Punto Equilibrio'!$D$16,"Sí","No")),"") -> Sí | F57: Compara las ventas de CADA año con el umbral de ese mismo año, que calcula la hoja de Punto de Equilibrio con los costes fijos del año
A59: Todas las cifras van SIN IVA. Las columnas de los años 2 y 3 están en euros del año 1 salvo que subas la actualización de costes en la hoja de Supuestos. La columna «Tipo de IVA de la línea» dice, en las líneas de VENTA, a qué tipo se repercute cada una, y en las de COSTE a qué tipo se compra la partida. La lee la hoja de Tesorería: los seguros y las comisiones de los medios de pago están exentos, y las nóminas, la amortización y los intereses no llevan IVA.

Sheet Punto Equilibrio
A1: ANÁLISIS DE PUNTO DE EQUILIBRIO
A2: Punto de equilibrio — paellero para eventos
A4: Variable | B4: Año 1 | C4: Año 2 | D4: Año 3 | E4: Notas
A5: DATOS BASE POR AÑO
A6: Costes fijos anuales | B6: =IFERROR(IF('PyG 3 Años'!$B$9="","",'PyG 3 Años'!$B$38),"") -> 85447.58 | C6: =IFERROR(IF('PyG 3 Años'!$C$9="","",'PyG 3 Años'!$C$38),"") -> 91447.58 | D6: =IFERROR(IF('PyG 3 Años'!$D$9="","",'PyG 3 Años'!$D$38),"") -> 96858.502 | E6: Los MISMOS costes fijos del P&L. Cada año tiene los suyos: por eso el umbral no puede ser uno solo para los tres
A7: Costes fijos mensuales | B7: =IFERROR(IF('PyG 3 Años'!$B$9="","",B6/12),"") -> 7120.6317 | C7: =IFERROR(IF('PyG 3 Años'!$C$9="","",C6/12),"") -> 7620.6317 | D7: =IFERROR(IF('PyG 3 Años'!$D$9="","",D6/12),"") -> 8071.5418
A8: Precio medio por invitado sin IVA | B8: =IFERROR(IF('PyG 3 Años'!$B$9="","",'PyG 3 Años'!$B$7),"") -> 16 | C8: =IFERROR(IF('PyG 3 Años'!$C$9="","",'PyG 3 Años'!$C$7),"") -> 16 | D8: =IFERROR(IF('PyG 3 Años'!$D$9="","",'PyG 3 Años'!$D$7),"") -> 16
A9: Coste variable por invitado | B9: =IFERROR(IF('PyG 3 Años'!$B$9="","",'PyG 3 Años'!$B$19/('PyG 3 Años'!$B$6*'PyG 3 Años'!$B$8)),"") -> 5.8656 | C9: =IFERROR(IF('PyG 3 Años'!$C$9="","",'PyG 3 Años'!$C$19/('PyG 3 Años'!$C$6*'PyG 3 Años'!$C$8)),"") -> 5.8656 | D9: =IFERROR(IF('PyG 3 Años'!$D$9="","",'PyG 3 Años'!$D$19/('PyG 3 Años'!$D$6*'PyG 3 Años'!$D$8)),"") -> 5.8656 | E9: Sale del total de costes variables del P&L, no de una estimación aparte. Incluye los varios e imprevistos, que son un porcentaje de las ventas
A10: Margen de contribución por invitado | B10: =IFERROR(IF('PyG 3 Años'!$B$9="","",B8-B9),"") -> 10.1344 | C10: =IFERROR(IF('PyG 3 Años'!$C$9="","",C8-C9),"") -> 10.1344 | D10: =IFERROR(IF('PyG 3 Años'!$D$9="","",D8-D9),"") -> 10.1344 | E10: Precio por invitado menos coste variable unitario
A11: Eventos al año | B11: =IFERROR(IF('PyG 3 Años'!$B$9="","",'PyG 3 Años'!$B$8),"") -> 105 | C11: =IFERROR(IF('PyG 3 Años'!$C$9="","",'PyG 3 Años'!$C$8),"") -> 105 | D11: =IFERROR(IF('PyG 3 Años'!$D$9="","",'PyG 3 Años'!$D$8),"") -> 105 | E11: El mismo calendario que el P&L y que los escenarios
A12: Devolución de principal del año (cuota) | B12: =IFERROR(IF('PyG 3 Años'!$B$9="","",'Financiación'!$B$45),"") -> 0 | C12: =IFERROR(IF('PyG 3 Años'!$C$9="","",'Financiación'!$B$47),"") -> 9062.7421 | D12: =IFERROR(IF('PyG 3 Años'!$D$9="","",'Financiación'!$B$49),"") -> 9651.8204 | E12: El principal NO es gasto del P&L, pero sale de la caja. Sin él, el umbral de equilibrio se publica por debajo del real
A13: PUNTO DE EQUILIBRIO CONTABLE (incluye amortización)
A14: Invitados necesarios al año | B14: =IFERROR(IF('PyG 3 Años'!$B$9="","",IF(B10<=0,"",B6/B10)),"") -> 8431.4395 | C14: =IFERROR(IF('PyG 3 Años'!$C$9="","",IF(C10<=0,"",C6/C10)),"") -> 9023.4824 | D14: =IFERROR(IF('PyG 3 Años'!$D$9="","",IF(D10<=0,"",D6/D10)),"") -> 9557.3987
A15: Invitados necesarios por evento | B15: =IFERROR(IF('PyG 3 Años'!$B$9="","",B14/B11),"") -> 80.299423 | C15: =IFERROR(IF('PyG 3 Años'!$C$9="","",C14/C11),"") -> 85.937928 | D15: =IFERROR(IF('PyG 3 Años'!$D$9="","",D14/D11),"") -> 91.022845
A16: Ingresos necesarios al año | B16: =IFERROR(IF('PyG 3 Años'!$B$9="","",B14*B8),"") -> 134903.03 | C16: =IFERROR(IF('PyG 3 Años'!$C$9="","",C14*C8),"") -> 144375.72 | D16: =IFERROR(IF('PyG 3 Años'!$D$9="","",D14*D8),"") -> 152918.38
A17: PUNTO DE EQUILIBRIO DE CAJA (incluye la cuota del préstamo)
A18: Costes fijos de caja + principal del año | B18: =IFERROR(IF('PyG 3 Años'!$B$9="","",B6-'PyG 3 Años'!$B$36+B12),"") -> 81700.58 | C18: =IFERROR(IF('PyG 3 Años'!$C$9="","",C6-'PyG 3 Años'!$C$36+C12),"") -> 96763.322 | D18: =IFERROR(IF('PyG 3 Años'!$D$9="","",D6-'PyG 3 Años'!$D$36+D12),"") -> 102763.32 | E18: Los fijos del P&L sin la amortización (que no se paga) y CON la devolución de principal (que sí). Es el umbral que decide si la caja aguanta
A19: Invitados necesarios al año (caja) | B19: =IFERROR(IF('PyG 3 Años'!$B$9="","",IF(B10<=0,"",B18/B10)),"") -> 8061.7086 | C19: =IFERROR(IF('PyG 3 Años'!$C$9="","",IF(C10<=0,"",C18/C10)),"") -> 9548.007 | D19: =IFERROR(IF('PyG 3 Años'!$D$9="","",IF(D10<=0,"",D18/D10)),"") -> 10140.05
A20: Invitados necesarios por evento (caja) | B20: =IFERROR(IF('PyG 3 Años'!$B$9="","",B19/B11),"") -> 76.778177 | C20: =IFERROR(IF('PyG 3 Años'!$C$9="","",C19/C11),"") -> 90.9334 | D20: =IFERROR(IF('PyG 3 Años'!$D$9="","",D19/D11),"") -> 96.571904
A21: Ingresos necesarios al año (caja) | B21: =IFERROR(IF('PyG 3 Años'!$B$9="","",B19*B8),"") -> 128987.34 | C21: =IFERROR(IF('PyG 3 Años'!$C$9="","",C19*C8),"") -> 152768.11 | D21: =IFERROR(IF('PyG 3 Años'!$D$9="","",D19*D8),"") -> 162240.8
A22: CONTRASTE CON EL PLAN
A23: Invitados por evento previstos en el plan | B23: =IFERROR(IF('PyG 3 Años'!$B$9="","",'PyG 3 Años'!$B$6),"") -> 94 | C23: =IFERROR(IF('PyG 3 Años'!$C$9="","",'PyG 3 Años'!$C$6),"") -> 103.4 | D23: =IFERROR(IF('PyG 3 Años'!$D$9="","",'PyG 3 Años'!$D$6),"") -> 109.604
A24: Holgura sobre el equilibrio de CAJA (%) | B24: =IFERROR(IF('PyG 3 Años'!$B$9="","",B23/B20-1),"") -> 0.22430622 | C24: =IFERROR(IF('PyG 3 Años'!$C$9="","",C23/C20-1),"") -> 0.13709594 | D24: =IFERROR(IF('PyG 3 Años'!$D$9="","",D23/D20-1),"") -> 0.13494707 | E24: Cuánto puedes caer antes de no poder pagar los costes fijos y la cuota. El mínimo exigible está en la hoja de Supuestos
A25: INTERPRETACIÓN
A26: =IFERROR("Con el precio medio por invitado sin IVA de la fila de arriba necesitas "&TEXT(ROUNDUP(B15,0),"0")&" invitados por evento durante los "&TEXT(B11,"0")&" eventos del año para no perder dinero (equilibrio contable, con la amortización dentro), y "&TEXT(ROUNDUP(B20,0),"0")&" para que la caja aguante (equilibrio de caja: sin la amortización, que no se paga, y con la cuota del préstamo del año"&IF(B12=0,"; este año sólo intereses, porque el préstamo está en carencia","")&"). En las filas «Ingresos necesarios al año» tienes esas mismas cifras en euros.","") -> Con el precio medio por invitado sin IVA de la fila de arriba necesitas 81 invitados por evento durante los 105 eventos del año para no perder dinero (equilibrio contable, con la amortización dentro), y 77 para que la caja aguante (equilibrio de caja: sin la amortización, que no se paga, y con la cuota del préstamo del año; este año sólo intereses, porque el préstamo está en carencia). En las filas «Ingresos necesarios al año» tienes esas mismas cifras en euros.
A28: SENSIBILIDAD DEL PUNTO DE EQUILIBRIO
A29: Invitados por evento necesarios para cubrir costes según el precio medio por invitado (columnas) y el coste variable por invitado (filas). En verde, los que están por debajo de los invitados que prevé el plan.
A31: Invitados por evento necesarios: precio medio por invitado sin IVA (columnas) × coste variable por invitado (filas) | B31: =IFERROR($B$8-2,"") -> 14 | C31: =IFERROR(IF($B$8="","",$B$8),"") -> 16 | D31: =IFERROR($B$8+2,"") -> 18 | E31: =IFERROR($B$8+4,"") -> 20
A32: =IFERROR($B$9*0.85,"") -> 4.98576 | B32: =IFERROR(IF($B$31-$A32<=0,"",$B$6/($B$31-$A32)/$B$11),"") -> 90.27788 | C32: =IFERROR(IF($C$31-$A32<=0,"",$B$6/($C$31-$A32)/$B$11),"") -> 73.884941 | D32: =IFERROR(IF($D$31-$A32<=0,"",$B$6/($D$31-$A32)/$B$11),"") -> 62.530465 | E32: =IFERROR(IF($E$31-$A32<=0,"",$B$6/($E$31-$A32)/$B$11),"") -> 54.200977
A33: =IFERROR($B$9*0.925,"") -> 5.42568 | B33: =IFERROR(IF($B$31-$A33<=0,"",$B$6/($B$31-$A33)/$B$11),"") -> 94.909739 | C33: =IFERROR(IF($C$31-$A33<=0,"",$B$6/($C$31-$A33)/$B$11),"") -> 76.958753 | D33: =IFERROR(IF($D$31-$A33<=0,"",$B$6/($D$31-$A33)/$B$11),"") -> 64.71813 | E33: =IFERROR(IF($E$31-$A33<=0,"",$B$6/($E$31-$A33)/$B$11),"") -> 55.837012
A34: =IFERROR($B$9*1.0,"") -> 5.8656 | B34: =IFERROR(IF($B$31-$A34<=0,"",$B$6/($B$31-$A34)/$B$11),"") -> 100.04259 | C34: =IFERROR(IF($C$31-$A34<=0,"",$B$6/($C$31-$A34)/$B$11),"") -> 80.299423 | D34: =IFERROR(IF($D$31-$A34<=0,"",$B$6/($D$31-$A34)/$B$11),"") -> 67.064418 | E34: =IFERROR(IF($E$31-$A34<=0,"",$B$6/($E$31-$A34)/$B$11),"") -> 57.574887
A35: =IFERROR($B$9*1.075,"") -> 6.30552 | B35: =IFERROR(IF($B$31-$A35<=0,"",$B$6/($B$31-$A35)/$B$11),"") -> 105.76237 | C35: =IFERROR(IF($C$31-$A35<=0,"",$B$6/($C$31-$A35)/$B$11),"") -> 83.943283 | D35: =IFERROR(IF($D$31-$A35<=0,"",$B$6/($D$31-$A35)/$B$11),"") -> 69.587231 | E35: =IFERROR(IF($E$31-$A35<=0,"",$B$6/($E$31-$A35)/$B$11),"") -> 59.424416
A36: =IFERROR($B$9*1.15,"") -> 6.74544 | B36: =IFERROR(IF($B$31-$A36<=0,"",$B$6/($B$31-$A36)/$B$11),"") -> 112.17586 | C36: =IFERROR(IF($C$31-$A36<=0,"",$B$6/($C$31-$A36)/$B$11),"") -> 87.933567 | D36: =IFERROR(IF($D$31-$A36<=0,"",$B$6/($D$31-$A36)/$B$11),"") -> 72.307267 | E36: =IFERROR(IF($E$31-$A36<=0,"",$B$6/($E$31-$A36)/$B$11),"") -> 61.396718

Sheet Escenarios
A1: ANÁLISIS DE ESCENARIOS
A4: Métrica | B4: Pesimista | C4: Realista | D4: Optimista | E4: Notas
A5: Invitados por evento | B5: 85 | C5: =IFERROR(IF('PyG 3 Años'!$B$6="","",'PyG 3 Años'!$B$6),"") -> 94 | D5: 100
A6: Precio medio por invitado sin IVA | B6: 15 | C6: =IFERROR(IF('PyG 3 Años'!$B$7="","",'PyG 3 Años'!$B$7),"") -> 16 | D6: 17
A7: Eventos al año | B7: 85 | C7: =IFERROR(IF('PyG 3 Años'!$B$8="","",'PyG 3 Años'!$B$8),"") -> 105 | D7: 125
A8: INGRESOS ANUALES (sin IVA) | B8: =IFERROR(IF(B5*B6*B7=0,"",B5*B6*B7),"") -> 108375 | C8: =IFERROR(IF(C5*C6*C7=0,"",C5*C6*C7),"") -> 157920 | D8: =IFERROR(IF(D5*D6*D7=0,"",D5*D6*D7),"") -> 212500
A9: Coste de mercancía — comida | B9: =IFERROR(IF(B8="","",B8*'0. Supuestos'!$B$11*'0. Supuestos'!$B$13),"") -> 27917.4 | C9: =IFERROR(IF(C8="","",C8*'0. Supuestos'!$B$11*'0. Supuestos'!$B$13),"") -> 40680.192 | D9: =IFERROR(IF(D8="","",D8*'0. Supuestos'!$B$11*'0. Supuestos'!$B$13),"") -> 54740
A10: Coste de mercancía — bebida | B10: =IFERROR(IF(B8="","",B8*'0. Supuestos'!$B$12*'0. Supuestos'!$B$14),"") -> 2601 | C10: =IFERROR(IF(C8="","",C8*'0. Supuestos'!$B$12*'0. Supuestos'!$B$14),"") -> 3790.08 | D10: =IFERROR(IF(D8="","",D8*'0. Supuestos'!$B$12*'0. Supuestos'!$B$14),"") -> 5100
A11: Consumibles y envases | B11: =IFERROR(IF(B8="","",B8*'0. Supuestos'!$B$15),"") -> 3251.25 | C11: =IFERROR(IF(C8="","",C8*'0. Supuestos'!$B$15),"") -> 4737.6 | D11: =IFERROR(IF(D8="","",D8*'0. Supuestos'!$B$15),"") -> 6375
A12: Comisiones de la paella para recoger | B12: =IFERROR(IF(B8="","",B8*'0. Supuestos'!$B$16*'0. Supuestos'!$B$17),"") -> 541.875 | C12: =IFERROR(IF(C8="","",C8*'0. Supuestos'!$B$16*'0. Supuestos'!$B$17),"") -> 789.6 | D12: =IFERROR(IF(D8="","",D8*'0. Supuestos'!$B$16*'0. Supuestos'!$B$17),"") -> 1062.5
A13: Comisiones de los medios de pago | B13: =IFERROR(IF(B8="","",B8*'0. Supuestos'!$B$18),"") -> 541.875 | C13: =IFERROR(IF(C8="","",C8*'0. Supuestos'!$B$18),"") -> 789.6 | D13: =IFERROR(IF(D8="","",D8*'0. Supuestos'!$B$18),"") -> 1062.5
A14: Varios e imprevistos | B14: =IFERROR(IF(B8="","",B8*'0. Supuestos'!$B$28),"") -> 4876.875 | C14: =IFERROR(IF(C8="","",C8*'0. Supuestos'!$B$28),"") -> 7106.4 | D14: =IFERROR(IF(D8="","",D8*'0. Supuestos'!$B$28),"") -> 9562.5
A15: TOTAL COSTES VARIABLES | B15: =IFERROR(IF(B8="","",SUM(B9:B14)),"") -> 39730.275 | C15: =IFERROR(IF(C8="","",SUM(C9:C14)),"") -> 57893.472 | D15: =IFERROR(IF(D8="","",SUM(D9:D14)),"") -> 77902.5
A16: MARGEN BRUTO | B16: =IFERROR(IF(B8="","",B8-B15),"") -> 68644.725 | C16: =IFERROR(IF(C8="","",C8-C15),"") -> 100026.53 | D16: =IFERROR(IF(D8="","",D8-D15),"") -> 134597.5
A17: COSTES FIJOS (los del P&L) | B17: =IFERROR(IF(B8="","",'PyG 3 Años'!$B$38),"") -> 85447.58 | C17: =IFERROR(IF(C8="","",'PyG 3 Años'!$B$38),"") -> 85447.58 | D17: =IFERROR(IF(D8="","",'PyG 3 Años'!$B$38),"") -> 85447.58 | E17: Los costes fijos no cambian con el escenario: por eso son fijos
A18: RESULTADO ANTES DE IMPUESTOS | B18: =IFERROR(IF(B8="","",B16-B17),"") -> -16802.855 | C18: =IFERROR(IF(C8="","",C16-C17),"") -> 14578.948 | D18: =IFERROR(IF(D8="","",D16-D17),"") -> 49149.92
A19: Impuesto de Sociedades | B19: =IFERROR(IF(B8="","",MAX(0,B18-'0. Supuestos'!$B$42)*'0. Supuestos'!$B$37),"") -> 0 | C19: =IFERROR(IF(C8="","",MAX(0,C18-'0. Supuestos'!$B$42)*'0. Supuestos'!$B$37),"") -> 2186.8422 | D19: =IFERROR(IF(D8="","",MAX(0,D18-'0. Supuestos'!$B$42)*'0. Supuestos'!$B$37),"") -> 7372.488 | E19: Al tipo de entidad de nueva creación, compensando las bases negativas anteriores
A20: RESULTADO NETO | B20: =IFERROR(IF(B8="","",B18-B19),"") -> -16802.855 | C20: =IFERROR(IF(C8="","",C18-C19),"") -> 12392.106 | D20: =IFERROR(IF(D8="","",D18-D19),"") -> 41777.432
A21: Invitados por evento para el equilibrio | B21: =IFERROR(IF(B8="","",IF(B6-B15/(B5*B7)<=0,"",B17/(B6-B15/(B5*B7))/B7)),"") -> 105.8063 | C21: =IFERROR(IF(C8="","",IF(C6-C15/(C5*C7)<=0,"",C17/(C6-C15/(C5*C7))/C7)),"") -> 80.299423 | D21: =IFERROR(IF(D8="","",IF(D6-D15/(D5*D7)<=0,"",D17/(D6-D15/(D5*D7))/D7)),"") -> 63.483779
A22: LO QUE CADA ESCENARIO EXIGE
A23: Coste de personal / Ventas | B23: =IFERROR(IF(B8="","",'PyG 3 Años'!$B$23/B8),"") -> 0.50838828 | C23: =IFERROR(IF(C8="","",'PyG 3 Años'!$B$23/C8),"") -> 0.34888918 | D23: =IFERROR(IF(D8="","",'PyG 3 Años'!$B$23/D8),"") -> 0.25927802 | E23: La MISMA plantilla en los tres escenarios. Si en el pesimista se dispara, el ajuste hay que hacerlo en la hoja de Personal, no aquí
A24: Invitados al año por jornada equivalente | B24: =IFERROR(IF(B8="","",B5*B7/'Personal'!$C$9),"") -> 3991.7127 | C24: =IFERROR(IF(C8="","",C5*C7/'Personal'!$C$9),"") -> 5453.0387 | D24: =IFERROR(IF(D8="","",D5*D7/'Personal'!$C$9),"") -> 6906.0773 | E24: Raciones que tendría que servir cada jornada completa del cuadro de Personal. En el optimista dice si hace falta contratar
A25: Saldo de caja al cierre del año 1 (estimado, el mismo método en los tres escenarios) | B25: =IFERROR(IF(B8="","",'Inversión Inicial'!$B$25+B20+'PyG 3 Años'!$B$36-'Financiación'!$B$45),"") -> 7369.29 | C25: =IFERROR(IF(C8="","",'Inversión Inicial'!$B$25+C20+'PyG 3 Años'!$B$36-'Financiación'!$B$45),"") -> 36564.251 | D25: =IFERROR(IF(D8="","",'Inversión Inicial'!$B$25+D20+'PyG 3 Años'!$B$36-'Financiación'!$B$45),"") -> 65949.577 | E25: Saldo ESTIMADO: fondo de maniobra más el resultado del año, devolviendo la amortización (que no se paga) y restando el principal del préstamo. No incluye el desfase de cobros y pagos ni la liquidación del IVA, así que las tres columnas se pueden comparar entre sí. En rojo, el escenario se queda sin caja
A26: Saldo real del mes 12 de la hoja de Tesorería (sólo realista) | C26: =IFERROR(IF(C8="","",'Tesorería 12 meses'!$M$22),"") -> 37724.78 | E26: El saldo REAL del caso base, con su desfase de cobros y pagos y su liquidación de IVA. Sólo existe para el escenario realista, que es el único con tesorería mensual propia: por eso no está en la fila de arriba, donde se compararía contra dos estimaciones
A28: La columna «Realista» lee sus tres datos de la hoja de Supuestos, así que reproduce EXACTAMENTE el año 1 del P&L. Los otros dos escenarios usan las mismas tasas de coste: lo único que cambia son los invitados, el precio por invitado y los eventos. Los COSTES FIJOS sí son los mismos en los tres: los varios e imprevistos, que son un porcentaje de las ventas, van arriba con los variables y cada escenario carga los suyos.

Sheet Personal
A1: ESTRUCTURA DE PERSONAL Y COSTES
A2: =IFERROR("Convenio Hostelería — "&TEXT('0. Supuestos'!$B$21,"0")&" pagas + SS "&TEXT('0. Supuestos'!$B$20*100,"0")&" %","") -> Convenio Hostelería — 14 pagas + SS 33 %
A4: Puesto | B4: Personas | C4: Jornada | D4: Bruto mes (€, total del puesto) | E4: Seg. Social a cargo de la empresa (€) | F4: Coste mes (€, total del puesto) | G4: Coste año (€) | H4: Horas/semana por persona | I4: Horas/año del puesto | J4: Notas
A5: Propietario/a — paellero titular, ventas y compras | B5: 1 | C5: 1 | D5: 1800 | E5: =IFERROR(IF(D5="","",D5*'0. Supuestos'!$B$20),"") -> 594 | F5: =IFERROR(IF(D5="","",D5+E5),"") -> 2394 | G5: =IFERROR(IF(D5="","",F5*MAX(12,'0. Supuestos'!$B$21)),"") -> 33516 | H5: =IFERROR(IF(D5="","",C5*$B$16),"") -> 40 | I5: =IFERROR(IF(D5="","",H5*B5*$B$17),"") -> 1840 | J5: Cocina en cada evento, vende, compra el producto y lleva la agenda. Como administrador de la SL cotiza en el régimen de autónomos: confirma con tu gestoría la cuota y si te aplica la reducida de inicio
A6: Ayudante de cocina y 2.º paellero (fijo discontinuo) | B6: 1 | C6: 0.65 | D6: 943 | E6: =IFERROR(IF(D6="","",D6*'0. Supuestos'!$B$20),"") -> 311.19 | F6: =IFERROR(IF(D6="","",D6+E6),"") -> 1254.19 | G6: =IFERROR(IF(D6="","",F6*MAX(12,'0. Supuestos'!$B$21)),"") -> 17558.66 | H6: =IFERROR(IF(D6="","",C6*$B$16),"") -> 26 | I6: =IFERROR(IF(D6="","",H6*B6*$B$17),"") -> 1196 | J6: Contrato fijo discontinuo (art. 16 del Estatuto de los Trabajadores) al 65 % de jornada en cómputo anual: caldos y preparación en la cocina de apoyo, montaje, fuegos y la segunda tanda de paelleras. Bruto a jornada completa: 1.450 € en 14 pagas
A7: Auxiliar de evento: montaje y caldo (fijo discontinuo) | B7: 1 | C7: 0.08 | D7: 108 | E7: =IFERROR(IF(D7="","",D7*'0. Supuestos'!$B$20),"") -> 35.64 | F7: =IFERROR(IF(D7="","",D7+E7),"") -> 143.64 | G7: =IFERROR(IF(D7="","",F7*MAX(12,'0. Supuestos'!$B$21)),"") -> 2010.96 | H7: =IFERROR(IF(D7="","",C7*$B$16),"") -> 3.2 | I7: =IFERROR(IF(D7="","",H7*B7*$B$17),"") -> 147.2 | J7: Llamado para las bodas y las fiestas populares (unas 140 horas al año). Bruto a jornada completa: 1.350 €. Nunca como autónomo que te factura: con tu horario y tu dirección es falso autónomo (art. 1.1 ET)
A8: Auxiliar de evento: emplatado y servicio (fijo discontinuo) | B8: 1 | C8: 0.08 | D8: 108 | E8: =IFERROR(IF(D8="","",D8*'0. Supuestos'!$B$20),"") -> 35.64 | F8: =IFERROR(IF(D8="","",D8+E8),"") -> 143.64 | G8: =IFERROR(IF(D8="","",F8*MAX(12,'0. Supuestos'!$B$21)),"") -> 2010.96 | H8: =IFERROR(IF(D8="","",C8*$B$16),"") -> 3.2 | I8: =IFERROR(IF(D8="","",H8*B8*$B$17),"") -> 147.2 | J8: Mismo contrato y mismas horas que el anterior: sirve la paella, repone y recoge. Por encima del SMI en proporción a su jornada
A9: TOTAL PLANTILLA | B9: =IFERROR(IF(COUNT(D5:D8)=0,"",SUM(B5:B8)),"") -> 4 | C9: =IFERROR(IF(COUNT(D5:D8)=0,"",SUM(C5:C8)),"") -> 1.81 | D9: =IFERROR(IF(COUNT(D5:D8)=0,"",SUM(D5:D8)),"") -> 2959 | E9: =IFERROR(IF(COUNT(D5:D8)=0,"",SUM(E5:E8)),"") -> 976.47 | F9: =IFERROR(IF(COUNT(D5:D8)=0,"",SUM(F5:F8)),"") -> 3935.47 | G9: =IFERROR(IF(COUNT(D5:D8)=0,"",SUM(G5:G8)),"") -> 55096.58 | I9: =IFERROR(IF(COUNT(D5:D8)=0,"",SUM(I5:I8)),"") -> 3330.4
A10: CRECIMIENTO DE LA PLANTILLA (coste escalonado)
A11: Coste anual de las incorporaciones del año 2 (€) | B11: 6000 | J11: Coste ANUAL completo (bruto + Seguridad Social × pagas) de lo que se contrate ese año. El P&L lo suma al coste del año anterior: la plantilla no crece con un porcentaje, crece con personas
A12: Coste anual de las incorporaciones del año 3 (€) | B12: 6000 | J12: Coste ANUAL completo (bruto + Seguridad Social × pagas) de lo que se contrate ese año. El P&L lo suma al coste del año anterior: la plantilla no crece con un porcentaje, crece con personas
A13: Coste de personal del año 2 | B13: =IFERROR(IF(G9="","",G9*(1+'0. Supuestos'!$B$48)+B11),"") -> 61096.58
A14: Coste de personal del año 3 | B14: =IFERROR(IF(B13="","",B13*(1+'0. Supuestos'!$B$48)+B12),"") -> 67096.58
A15: COBERTURA POR HORAS DE SERVICIO
A16: Jornada completa del convenio (horas/semana) | B16: 40 | J16: Art. 34.1 del Estatuto de los Trabajadores; tu convenio provincial puede fijar menos
A17: Semanas trabajadas al año por persona | B17: 46 | J17: 46 semanas: 52 menos las vacaciones (30 días naturales, art. 38 ET), los festivos y las ausencias medias
A18: Horas de trabajo por evento que hay que cubrir | B18: 8 | J18: Horas por evento y persona: carga, viaje, montaje, encendido, cocción, servicio, recogida y descarga. Los caldos y la preparación en la cocina de apoyo van aparte
A19: Personas necesarias a la vez en cada evento | B19: 2 | J19: Personas trabajando a la vez en un evento medio de 94 raciones: el paellero titular y el ayudante. En bodas y fiestas populares entran uno o dos auxiliares: súbelo y la hoja te dice si llega la plantilla
A20: Horas de servicio a cubrir al año | B20: =IFERROR(IF(OR(B18="",B19="",'0. Supuestos'!$B$6=""),"",B18*B19*'0. Supuestos'!$B$6),"") -> 1680
A21: Horas contratadas al año | B21: =IFERROR(IF(I9="","",I9),"") -> 3330.4
A22: Cobertura (contratadas / necesarias) | B22: =IFERROR(B21/B20,"") -> 1.982381 | J22: Por debajo del 100 % la plantilla no llega a cubrir el horario que declara el plan: o se contrata más o se recorta el horario
A24: Las columnas «Bruto mes», «Seg. Social», «Coste mes» y «Coste año» son TOTALES de la fila: en un puesto con dos personas incluyen a las dos. «Jornada» es el porcentaje sobre la jornada completa del convenio y sirve para comparar el salario con el suelo legal en proporción. El tipo de Seguridad Social y el número de pagas están en la hoja «0. Supuestos».
A25: El suelo salarial es el MAYOR entre el SMI y el salario de convenio, los dos en la hoja «0. Supuestos»; las jornadas parciales lo llevan en proporción. El convenio aplicable es el PROVINCIAL de hostelería: no existe una tabla salarial estatal única, así que la celda del convenio se entrega vacía para que copies la de tu provincia.

Sheet Instrucciones
A1: INSTRUCCIONES DE USO — Plan financiero Paellero / Paella para Eventos
A3: CÓMO SE USA ESTE LIBRO
A4: Este plan financiero es un MODELO: sólo se teclea en las celdas VERDES y el resto se recalcula solo.
A5: 1. «0. Supuestos» es la hoja de mando: invitados, precio por invitado sin IVA, eventos, mezcla de comida y bebida, coste de mercancía, alquiler, financiación e impuestos.
A6: 2. Las partidas de la inversión, los costes fijos y la plantilla se teclean en su propia hoja, también en verde. Ningún número se escribe dos veces.
A7: 3. Sólo «Punto Equilibrio» se deriva entera de lo anterior. En las otras tres hojas también hay celdas verdes que puedes tocar: el escenario pesimista y el optimista en «Escenarios», la estacionalidad y la rampa de arranque en «Tesorería 12 meses», y las cuatro fuentes alternativas de financiación en «Financiación». Todo lo demás se calcula.
A8: 4. Todas las cifras van SIN IVA. Para pasar un PVP a precio sin IVA, divide por el tipo que le corresponda: entre 1,10 en el servicio de paella (comida y bebida, alcohol incluido: art. 91.Uno.2.2.º de la Ley 37/1992 del IVA) y, cuando se venden para llevar, los alimentos, que son productos alimenticios al tipo reducido por el art. 91.Uno.1.1.º; y entre 1,21 el tipo general, que en hostelería sólo alcanza a lo que sale de la cocina de apoyo como entrega de bienes excluida del reducido: el alcohol y los refrescos, zumos y gaseosas con azúcares o edulcorantes añadidos para llevar o a domicilio (la comida para llevar sigue al 10 %); el libro lo aplica al alcohol del canal de paella para recoger. El tipo de cada línea de venta está en la columna «Tipo de IVA de la línea» del P&L y de ahí salen los cobros, el IVA repercutido y el PVP equivalente. El IVA de la inversión se adelanta y se recupera con el modelo 303.
A9: 5. Si cambias la plantilla, el P&L la lee sola: el coste de personal sale de la hoja «Personal», no de una estimación aparte.
A10: 6. La hoja «Tesorería 12 meses» responde la pregunta que decide una operación bancaria: en qué mes se agota la caja. El saldo mínimo del año nunca puede salir en rojo. Los anticipos de los particulares (30 % al firmar) no se modelan: tu caja real será algo mejor.
A11: 7. La hoja «Financiación» cuadra lo que hace falta con lo que se aporta y monta el cuadro de amortización del préstamo. Si la diferencia sale en rojo, el plan no está financiado.
A12: 8. El documento Word de este pack y la calculadora de precios usan las cifras de este Excel: si cambias una celda verde, el Excel manda.
A14: RATIOS QUE AUDITA EL LIBRO
A15: Los umbrales viven en la columna «Umbral» del bloque RATIOS CLAVE del P&L: cámbialos ahí y el semáforo cambia con ellos.
A17: Ratio | B17: Valor del año 1 | C17: Umbral | D17: Estado
A18: Coste de mercancía / Ventas | B18: =IFERROR(IF('PyG 3 Años'!$B$53="","",'PyG 3 Años'!$B$53),"") -> 0.2816 | C18: =IFERROR(IF('PyG 3 Años'!$E$53="","",'PyG 3 Años'!$E$53),"") -> 0.32 | D18: =IFERROR(IF(OR(B18="",C18=""),"",IF(B18<=C18,"CUMPLE","REVISAR")),"") -> CUMPLE
A19: Coste de personal / Ventas | B19: =IFERROR(IF('PyG 3 Años'!$B$54="","",'PyG 3 Años'!$B$54),"") -> 0.34888918 | C19: =IFERROR(IF('PyG 3 Años'!$E$54="","",'PyG 3 Años'!$E$54),"") -> 0.38 | D19: =IFERROR(IF(OR(B19="",C19=""),"",IF(B19<=C19,"CUMPLE","REVISAR")),"") -> CUMPLE
A20: Cocina de apoyo / Ventas | B20: =IFERROR(IF('PyG 3 Años'!$B$55="","",'PyG 3 Años'!$B$55),"") -> 0.068389058 | C20: =IFERROR(IF('PyG 3 Años'!$E$55="","",'PyG 3 Años'!$E$55),"") -> 0.08 | D20: =IFERROR(IF(OR(B20="",C20=""),"",IF(B20<=C20,"CUMPLE","REVISAR")),"") -> CUMPLE
A21: Resultado neto / Ventas | B21: =IFERROR(IF('PyG 3 Años'!$B$56="","",'PyG 3 Años'!$B$56),"") -> 0.078470781 | C21: =IFERROR(IF('PyG 3 Años'!$E$56="","",'PyG 3 Años'!$E$56),"") -> 0.04 | D21: =IFERROR(IF(OR(B21="",C21=""),"",IF(B21>=C21,"CUMPLE","REVISAR")),"") -> CUMPLE
A22: Margen bruto / Ventas | B22: =IFERROR(IF('PyG 3 Años'!$B$51="","",'PyG 3 Años'!$B$51),"") -> 0.6334 | C22: =IFERROR(IF('PyG 3 Años'!$E$51="","",'PyG 3 Años'!$E$51),"") -> 0.6 | D22: =IFERROR(IF(OR(B22="",C22=""),"",IF(B22>=C22,"CUMPLE","REVISAR")),"") -> CUMPLE
A24: CIFRAS DE ESTE PLAN
A25: Inversión total (suma de los bloques) | B25: =IFERROR(IF('Inversión Inicial'!$B$26="","",'Inversión Inicial'!$B$26),"") -> 63111.145
A26: Necesidad total de caja al arranque | B26: =IFERROR(IF('Inversión Inicial'!$B$29="","",'Inversión Inicial'!$B$29),"") -> 71487.205
A27: Fondo de maniobra dotado | B27: =IFERROR(IF('Inversión Inicial'!$B$25="","",'Inversión Inicial'!$B$25),"") -> 20425.145
A28: Facturación prevista del año 1 | B28: =IFERROR(IF('PyG 3 Años'!$B$9="","",'PyG 3 Años'!$B$9),"") -> 157920
A29: Resultado neto del año 1 | B29: =IFERROR(IF('PyG 3 Años'!$B$48="","",'PyG 3 Años'!$B$48),"") -> 12392.106
A30: Invitados por evento para el punto de equilibrio CONTABLE (con la amortización dentro) | B30: =IFERROR(IF('Punto Equilibrio'!$B$15="","",'Punto Equilibrio'!$B$15),"") -> 80.299423
A31: Payback del proyecto (años), antes de la deuda | B31: =IFERROR(IF('Tesorería 12 meses'!$B$31="","",'Tesorería 12 meses'!$B$31),"") -> 3
A33: QUÉ HA CAMBIADO RESPECTO DE LA VERSIÓN 1.2
A34: Concepto | B34: v1.2 | C34: v2.2 | D34: Por qué
A35: Modelo de ingresos | B35: eventos y tickets medios tecleados, con un margen neto irreal (la mitad de las ventas) | C35: invitados (raciones) por evento × precio por invitado × eventos al año, en la hoja de Supuestos | D35: Ahora cualquier cambio de precio o de volumen recalcula todo el libro
A36: Cocina | B36: no había ninguna: la mise en place se hacía en casa | C36: cuota de una cocina de apoyo compartida y autorizada | D36: Lo que se prepara para un evento no se puede hacer en casa (art. 13.5.b del RD 1021/2022)
A37: Personal | B37: un 12 % de ayudantes subcontratados sobre las ventas y ningún sueldo para el paellero | C37: plantilla con el sueldo del titular, fijos discontinuos y Seguridad Social | D37: Las facturas de autónomo con horario y dirección del empresario son falso autónomo (art. 1.1 ET)
A38: Punto de equilibrio | B38: 10 eventos al año, sin amortización, sueldos ni cocina | C38: con todos los costes fijos, en invitados por evento, en ingresos y en caja | D38: El anterior salía irrealmente bajo; éste es el que mira un banco
A39: Impuestos, caja y financiación | B39: no había IVA, Impuesto de Sociedades, tesorería ni préstamo | C39: IVA al 10 %, Impuesto de Sociedades, tesorería de 12 meses y préstamo con su cuadro y su DSCR | D39: Es lo que pide cualquier entidad para estudiar la operación
A41: DATOS DE REFERENCIA DEL SECTOR
A42: Referencia | B42: Valor | C42: Fuente | D42: Nota
A43: Mezcla de eventos del plan | B43: 105 eventos: 15 bodas, 30 de empresa, 50 fiestas privadas y 10 populares | C43: Estimación del kit | D43: Bodas (15 eventos × 120 raciones × 28 €), comidas de empresa (30 × 70 × 24 €), fiestas privadas (50 × 40 × 18 €) y fiestas populares (10 × 400 × 5 €), precios sin IVA. Media: 94 raciones a 16 €
A44: Fiesta popular contratada por un ayuntamiento | B44: 400 raciones por 1.480 € | C44: Plataforma de Contratación del Sector Público (contrato menor de Sayalonga, 2025) | D44: Paella mixta con menaje, pan y servicio: unos 3,70 € por ración
A45: Paella sola para grupos | B45: 11-14 € por persona | C45: Tarifa publicada de un proveedor de Cataluña (2026) | D45: 14 € de 30 a 49 personas, 12 € de 50 a 99 y 11 € a partir de 100; desplazamiento aparte
A46: Paella en directo con experiencia | B46: 20-39 € por persona | C46: Fichas de proveedores en plataformas de eventos | D46: Con show cooking y mínimo de servicio
A47: Raciones por paellera | B47: 90 cm: 30-40 · 120 cm: 60-80 · 150 cm: 90-120 | C47: Manual técnico de este kit (cartas de capacidad de los fabricantes) | D47: 100 g de arroz por ración de evento
A48: Personal por evento | B48: 1 paellero hasta 3 paelleras; ayudante desde 4 paelleras u 80 invitados | C48: Manual técnico de este kit | D48: Segundo paellero a partir de unos 150 invitados
A49: Coste de mercancía sobre ventas | B49: 25-28 % con entrantes; 45 % en fiestas populares | C49: Estimación del kit | D49: El plan usa el 28 % en comida y el 30 % en bebida
A50: Gas por evento de 100 invitados | B50: 4-6 kg de propano (10-15 €) | C50: Boletín de precios del IDAE, julio de 2026 | D50: Propano de 35 kg a 78,80 € (≈ 2,25 €/kg); 1-1,5 kg por paellera de 90 cm
A51: Botellas de gas | B51: Una botella de menos de 15 kg por quemador | C51: RD 919/2006, art. 2.1.h | D51: Así no es una instalación y la conectas tú, con regulador y tubo flexible en fecha. Con botellas de 35 kg o varias conectadas, la monta una empresa instaladora (ITC-ICG 06)
A52: IVA de un servicio de paella en el evento | B52: 10 % | C52: Ley 37/1992, art. 91.Uno.2.2.º | D52: Alcohol incluido. Paella para recoger: comida al 10 % y alcohol al 21 %
A53: Pago de los ayuntamientos | B53: 30 días desde la conformidad | C53: Ley 9/2017, art. 198.4 | D53: Contrato menor de servicios por debajo de 15.000 € (art. 118) y factura electrónica por FACe si eres SL (Ley 25/2013, art. 4)
... A55: Convenio colectivo aplicable | B55: Provincial de hostelería | C55: V Acuerdo Laboral de ámbito Estatal para el sector de Hostelería, art. 4 | D55: Copia tu tabla salarial en la celda de Supuestos
A57: Para editar una celda que no esté en verde: Revisar → Desproteger hoja (no tiene contraseña).
A58: Más plantillas y kits del catálogo en aichef.pro/productos-digitales
A59: Diseñado por John Guerrero — chef y consultor gastronómico desde 2010, en cocina desde los 17 años · johnguerrero.es
A60: Versión 2.2 · septiembre 2026 · aichef.pro/plan-negocio-paellero-eventos · info@aichef.pro

Sheet Tesorería 12 meses
A1: PREVISIÓN DE TESORERÍA — AÑO 1
A2: El P&L dice si el negocio gana dinero; esta hoja dice si le queda caja para llegar a fin de mes. Es la primera que mira un banco.
A4: Concepto | B4: Mes 1 (€) | C4: Mes 2 (€) | D4: Mes 3 (€) | E4: Mes 4 (€) | F4: Mes 5 (€) | G4: Mes 6 (€) | H4: Mes 7 (€) | I4: Mes 8 (€) | J4: Mes 9 (€) | K4: Mes 10 (€) | L4: Mes 11 (€) | M4: Mes 12 (€) | N4: Año (€)
A5: Estacionalidad del mes (suma 100 %) | B5: 0.03 | C5: 0.035 | D5: 0.06 | E5: 0.07 | F5: 0.11 | G5: 0.13 | H5: 0.12 | I5: 0.12 | J5: 0.13 | K5: 0.09 | L5: 0.04 | M5: 0.065 | N5: =IFERROR(IF('PyG 3 Años'!$B$9="","",SUM(B5:M5)),"") -> 1 | O5: Perfil de tu zona: agosto flojo en ciudad y fuerte en costa. Tiene que sumar 100 %
A6: Rampa de arranque (% de la actividad de crucero) | B6: =IFERROR(IF('PyG 3 Años'!$B$9="","",MIN(1,'0. Supuestos'!$B$52+(1-'0. Supuestos'!$B$52)*0/MAX(1,'0. Supuestos'!$B$53-1))),"") -> 0.55 | C6: =IFERROR(IF('PyG 3 Años'!$B$9="","",MIN(1,'0. Supuestos'!$B$52+(1-'0. Supuestos'!$B$52)*1/MAX(1,'0. Supuestos'!$B$53-1))),"") -> 0.64 | D6: =IFERROR(IF('PyG 3 Años'!$B$9="","",MIN(1,'0. Supuestos'!$B$52+(1-'0. Supuestos'!$B$52)*2/MAX(1,'0. Supuestos'!$B$53-1))),"") -> 0.73 | E6: =IFERROR(IF('PyG 3 Años'!$B$9="","",MIN(1,'0. Supuestos'!$B$52+(1-'0. Supuestos'!$B$52)*3/MAX(1,'0. Supuestos'!$B$53-1))),"") -> 0.82 | F6: =IFERROR(IF('PyG 3 Años'!$B$9="","",MIN(1,'0. Supuestos'!$B$52+(1-'0. Supuestos'!$B$52)*4/MAX(1,'0. Supuestos'!$B$53-1))),"") -> 0.91 | G6: =IFERROR(IF('PyG 3 Años'!$B$9="","",MIN(1,'0. Supuestos'!$B$52+(1-'0. Supuestos'!$B$52)*5/MAX(1,'0. Supuestos'!$B$53-1))),"") -> 1 | H6: =IFERROR(IF('PyG 3 Años'!$B$9="","",MIN(1,'0. Supuestos'!$B$52+(1-'0. Supuestos'!$B$52)*6/MAX(1,'0. Supuestos'!$B$53-1))),"") -> 1 | I6: =IFERROR(IF('PyG 3 Años'!$B$9="","",MIN(1,'0. Supuestos'!$B$52+(1-'0. Supuestos'!$B$52)*7/MAX(1,'0. Supuestos'!$B$53-1))),"") -> 1 | J6: =IFERROR(IF('PyG 3 Años'!$B$9="","",MIN(1,'0. Supuestos'!$B$52+(1-'0. Supuestos'!$B$52)*8/MAX(1,'0. Supuestos'!$B$53-1))),"") -> 1 | K6: =IFERROR(IF('PyG 3 Años'!$B$9="","",MIN(1,'0. Supuestos'!$B$52+(1-'0. Supuestos'!$B$52)*9/MAX(1,'0. Supuestos'!$B$53-1))),"") -> 1 | L6: =IFERROR(IF('PyG 3 Años'!$B$9="","",MIN(1,'0. Supuestos'!$B$52+(1-'0. Supuestos'!$B$52)*10/MAX(1,'0. Supuestos'!$B$53-1))),"") -> 1 | M6: =IFERROR(IF('PyG 3 Años'!$B$9="","",MIN(1,'0. Supuestos'!$B$52+(1-'0. Supuestos'!$B$52)*11/MAX(1,'0. Supuestos'!$B$53-1))),"") -> 1 | O6: Sube en línea recta desde el porcentaje del mes 1 hasta el 100 % en los meses que digas en Supuestos. Con el mes 1 al 100 % la rampa desaparece
A7: Reparto de la actividad por mes (calculado) | B7: =IFERROR(IF('PyG 3 Años'!$B$9="","",B5*B6/SUMPRODUCT($B$5:$M$5,$B$6:$M$6)),"") -> 0.017643285 | C7: =IFERROR(IF('PyG 3 Años'!$B$9="","",C5*C6/SUMPRODUCT($B$5:$M$5,$B$6:$M$6)),"") -> 0.023952096 | D7: =IFERROR(IF('PyG 3 Años'!$B$9="","",D5*D6/SUMPRODUCT($B$5:$M$5,$B$6:$M$6)),"") -> 0.046834902 | E7: =IFERROR(IF('PyG 3 Años'!$B$9="","",E5*E6/SUMPRODUCT($B$5:$M$5,$B$6:$M$6)),"") -> 0.061377246 | F7: =IFERROR(IF('PyG 3 Años'!$B$9="","",F5*F6/SUMPRODUCT($B$5:$M$5,$B$6:$M$6)),"") -> 0.10703593 | G7: =IFERROR(IF('PyG 3 Años'!$B$9="","",G5*G6/SUMPRODUCT($B$5:$M$5,$B$6:$M$6)),"") -> 0.1390077 | H7: =IFERROR(IF('PyG 3 Años'!$B$9="","",H5*H6/SUMPRODUCT($B$5:$M$5,$B$6:$M$6)),"") -> 0.1283148 | I7: =IFERROR(IF('PyG 3 Años'!$B$9="","",I5*I6/SUMPRODUCT($B$5:$M$5,$B$6:$M$6)),"") -> 0.1283148 | ... M7: =IFERROR(IF('PyG 3 Años'!$B$9="","",M5*M6/SUMPRODUCT($B$5:$M$5,$B$6:$M$6)),"") -> 0.069503849 | N7: =IFERROR(IF('PyG 3 Años'!$B$9="","",SUM(B7:M7)),"") -> 1 | O7: Estacionalidad × rampa, normalizado a 100 %: el AÑO factura lo que dice el P&L, pero repartido como lo reparte un negocio de paellas que acaba de arrancar
A8: COBROS
A9: Ventas cobradas (con IVA repercutido) | B9: =IFERROR(IF('PyG 3 Años'!$B$9="","",('PyG 3 Años'!$B$9+'PyG 3 Años'!$B$9*SUMPRODUCT('PyG 3 Años'!$E$10:$E$11,'PyG 3 Años'!$G$10:$G$11))*B7*(1-MIN(30,'0. Supuestos'!$B$58)/30)),"") -> 1021.8211 | C9: =IFERROR(IF('PyG 3 Años'!$B$9="","",('PyG 3 Años'!$B$9+'PyG 3 Años'!$B$9*SUMPRODUCT('PyG 3 Años'!$E$10:$E$11,'PyG 3 Años'!$G$10:$G$11))*(C7*(1-MIN(30,'0. Supuestos'!$B$58)/30)+B7*MIN(30,'0. Supuestos'!$B$58)/30)),"") -> 3430.8417 | D9: =IFERROR(IF('PyG 3 Años'!$B$9="","",('PyG 3 Años'!$B$9+'PyG 3 Años'!$B$9*SUMPRODUCT('PyG 3 Años'!$E$10:$E$11,'PyG 3 Años'!$G$10:$G$11))*(D7*(1-MIN(30,'0. Supuestos'!$B$58)/30)+C7*MIN(30,'0. Supuestos'!$B$58)/30)),"") -> 5486.8696 | E9: =IFERROR(IF('PyG 3 Años'!$B$9="","",('PyG 3 Años'!$B$9+'PyG 3 Años'!$B$9*SUMPRODUCT('PyG 3 Años'!$E$10:$E$11,'PyG 3 Años'!$G$10:$G$11))*(E7*(1-MIN(30,'0. Supuestos'!$B$58)/30)+D7*MIN(30,'0. Supuestos'!$B$58)/30)),"") -> 8979.6399 | F9: =IFERROR(IF('PyG 3 Años'!$B$9="","",('PyG 3 Años'!$B$9+'PyG 3 Años'!$B$9*SUMPRODUCT('PyG 3 Años'!$E$10:$E$11,'PyG 3 Años'!$G$10:$G$11))*(F7*(1-MIN(30,'0. Supuestos'!$B$58)/30)+E7*MIN(30,'0. Supuestos'!$B$58)/30)),"") -> 13308.446 | G9: =IFERROR(IF('PyG 3 Años'!$B$9="","",('PyG 3 Años'!$B$9+'PyG 3 Años'!$B$9*SUMPRODUCT('PyG 3 Años'!$E$10:$E$11,'PyG 3 Años'!$G$10:$G$11))*(G7*(1-MIN(30,'0. Supuestos'!$B$58)/30)+F7*MIN(30,'0. Supuestos'!$B$58)/30)),"") -> 20448.808 | H9: =IFERROR(IF('PyG 3 Años'!$B$9="","",('PyG 3 Años'!$B$9+'PyG 3 Años'!$B$9*SUMPRODUCT('PyG 3 Años'!$E$10:$E$11,'PyG 3 Años'!$G$10:$G$11))*(H7*(1-MIN(30,'0. Supuestos'!$B$58)/30)+G7*MIN(30,'0. Supuestos'!$B$58)/30)),"") -> 23532.849 | I9: =IFERROR(IF('PyG 3 Años'!$B$9="","",('PyG 3 Años'!$B$9+'PyG 3 Años'!$B$9*SUMPRODUCT('PyG 3 Años'!$E$10:$E$11,'PyG 3 Años'!$G$10:$G$11))*(I7*(1-MIN(30,'0. Supuestos'!$B$58)/30)+H7*MIN(30,'0. Supuestos'!$B$58)/30)),"") -> 22294.278 | J9: =IFERROR(IF('PyG 3 Años'!$B$9="","",('PyG 3 Años'!$B$9+'PyG 3 Años'!$B$9*SUMPRODUCT('PyG 3 Años'!$E$10:$E$11,'PyG 3 Años'!$G$10:$G$11))*(J7*(1-MIN(30,'0. Supuestos'!$B$58)/30)+I7*MIN(30,'0. Supuestos'!$B$58)/30)),"") -> 22913.564 | ... M9: =IFERROR(IF('PyG 3 Años'!$B$9="","",('PyG 3 Años'!$B$9+'PyG 3 Años'!$B$9*SUMPRODUCT('PyG 3 Años'!$E$10:$E$11,'PyG 3 Años'!$G$10:$G$11))*(M7*(1-MIN(30,'0. Supuestos'!$B$58)/30)+L7*MIN(30,'0. Supuestos'!$B$58)/30)),"") -> 8979.6399 | N9: =IFERROR(IF('PyG 3 Años'!$B$9="","",SUM(B9:M9)),"") -> 165696.03 | O9: Ventas del mes con el IVA repercutido, corregidas por los días medios de cobro de la hoja de Supuestos
A10: PAGOS
A11: Compras y costes variables (IVA incluido) | B11: =IFERROR(IF('PyG 3 Años'!$B$9="","",-('PyG 3 Años'!$B$13*(1+'PyG 3 Años'!$G$13)+'PyG 3 Años'!$B$14*(1+'PyG 3 Años'!$G$14)+'PyG 3 Años'!$B$15*(1+'PyG 3 Años'!$G$15)+'PyG 3 Años'!$B$16*(1+'PyG 3 Años'!$G$16)+'PyG 3 Años'!$B$17*(1+'PyG 3 Años'!$G$17)+'PyG 3 Años'!$B$18*(1+'PyG 3 Años'!$G$18))*B7*(1-MIN(30,'0. Supuestos'!$B$59)/30)),"") -> -383.45921 | C11: =IFERROR(IF('PyG 3 Años'!$B$9="","",-('PyG 3 Años'!$B$13*(1+'PyG 3 Años'!$G$13)+'PyG 3 Años'!$B$14*(1+'PyG 3 Años'!$G$14)+'PyG 3 Años'!$B$15*(1+'PyG 3 Años'!$G$15)+'PyG 3 Años'!$B$16*(1+'PyG 3 Años'!$G$16)+'PyG 3 Años'!$B$17*(1+'PyG 3 Años'!$G$17)+'PyG 3 Años'!$B$18*(1+'PyG 3 Años'!$G$18))*(C7*(1-MIN(30,'0. Supuestos'!$B$59)/30)+B7*MIN(30,'0. Supuestos'!$B$59)/30)),"") -> -1287.4933 | D11: =IFERROR(IF('PyG 3 Años'!$B$9="","",-('PyG 3 Años'!$B$13*(1+'PyG 3 Años'!$G$13)+'PyG 3 Años'!$B$14*(1+'PyG 3 Años'!$G$14)+'PyG 3 Años'!$B$15*(1+'PyG 3 Años'!$G$15)+'PyG 3 Años'!$B$16*(1+'PyG 3 Años'!$G$16)+'PyG 3 Años'!$B$17*(1+'PyG 3 Años'!$G$17)+'PyG 3 Años'!$B$18*(1+'PyG 3 Años'!$G$18))*(D7*(1-MIN(30,'0. Supuestos'!$B$59)/30)+C7*MIN(30,'0. Supuestos'!$B$59)/30)),"") -> -2059.0598 | E11: =IFERROR(IF('PyG 3 Años'!$B$9="","",-('PyG 3 Años'!$B$13*(1+'PyG 3 Años'!$G$13)+'PyG 3 Años'!$B$14*(1+'PyG 3 Años'!$G$14)+'PyG 3 Años'!$B$15*(1+'PyG 3 Años'!$G$15)+'PyG 3 Años'!$B$16*(1+'PyG 3 Años'!$G$16)+'PyG 3 Años'!$B$17*(1+'PyG 3 Años'!$G$17)+'PyG 3 Años'!$B$18*(1+'PyG 3 Años'!$G$18))*(E7*(1-MIN(30,'0. Supuestos'!$B$59)/30)+D7*MIN(30,'0. Supuestos'!$B$59)/30)),"") -> -3369.7931 | F11: =IFERROR(IF('PyG 3 Años'!$B$9="","",-('PyG 3 Años'!$B$13*(1+'PyG 3 Años'!$G$13)+'PyG 3 Años'!$B$14*(1+'PyG 3 Años'!$G$14)+'PyG 3 Años'!$B$15*(1+'PyG 3 Años'!$G$15)+'PyG 3 Años'!$B$16*(1+'PyG 3 Años'!$G$16)+'PyG 3 Años'!$B$17*(1+'PyG 3 Años'!$G$17)+'PyG 3 Años'!$B$18*(1+'PyG 3 Años'!$G$18))*(F7*(1-MIN(30,'0. Supuestos'!$B$59)/30)+E7*MIN(30,'0. Supuestos'!$B$59)/30)),"") -> -4994.2657 | G11: =IFERROR(IF('PyG 3 Años'!$B$9="","",-('PyG 3 Años'!$B$13*(1+'PyG 3 Años'!$G$13)+'PyG 3 Años'!$B$14*(1+'PyG 3 Años'!$G$14)+'PyG 3 Años'!$B$15*(1+'PyG 3 Años'!$G$15)+'PyG 3 Años'!$B$16*(1+'PyG 3 Años'!$G$16)+'PyG 3 Años'!$B$17*(1+'PyG 3 Años'!$G$17)+'PyG 3 Años'!$B$18*(1+'PyG 3 Años'!$G$18))*(G7*(1-MIN(30,'0. Supuestos'!$B$59)/30)+F7*MIN(30,'0. Supuestos'!$B$59)/30)),"") -> -7673.8322 | H11: =IFERROR(IF('PyG 3 Años'!$B$9="","",-('PyG 3 Años'!$B$13*(1+'PyG 3 Años'!$G$13)+'PyG 3 Años'!$B$14*(1+'PyG 3 Años'!$G$14)+'PyG 3 Años'!$B$15*(1+'PyG 3 Años'!$G$15)+'PyG 3 Años'!$B$16*(1+'PyG 3 Años'!$G$16)+'PyG 3 Años'!$B$17*(1+'PyG 3 Años'!$G$17)+'PyG 3 Años'!$B$18*(1+'PyG 3 Años'!$G$18))*(H7*(1-MIN(30,'0. Supuestos'!$B$59)/30)+G7*MIN(30,'0. Supuestos'!$B$59)/30)),"") -> -8831.1818 | I11: =IFERROR(IF('PyG 3 Años'!$B$9="","",-('PyG 3 Años'!$B$13*(1+'PyG 3 Años'!$G$13)+'PyG 3 Años'!$B$14*(1+'PyG 3 Años'!$G$14)+'PyG 3 Años'!$B$15*(1+'PyG 3 Años'!$G$15)+'PyG 3 Años'!$B$16*(1+'PyG 3 Años'!$G$16)+'PyG 3 Años'!$B$17*(1+'PyG 3 Años'!$G$17)+'PyG 3 Años'!$B$18*(1+'PyG 3 Años'!$G$18))*(I7*(1-MIN(30,'0. Supuestos'!$B$59)/30)+H7*MIN(30,'0. Supuestos'!$B$59)/30)),"") -> -8366.3828 | J11: =IFERROR(IF('PyG 3 Años'!$B$9="","",-('PyG 3 Años'!$B$13*(1+'PyG 3 Años'!$G$13)+'PyG 3 Años'!$B$14*(1+'PyG 3 Años'!$G$14)+'PyG 3 Años'!$B$15*(1+'PyG 3 Años'!$G$15)+'PyG 3 Años'!$B$16*(1+'PyG 3 Años'!$G$16)+'PyG 3 Años'!$B$17*(1+'PyG 3 Años'!$G$17)+'PyG 3 Años'!$B$18*(1+'PyG 3 Años'!$G$18))*(J7*(1-MIN(30,'0. Supuestos'!$B$59)/30)+I7*MIN(30,'0. Supuestos'!$B$59)/30)),"") -> -8598.7823 | ... M11: =IFERROR(IF('PyG 3 Años'!$B$9="","",-('PyG 3 Años'!$B$13*(1+'PyG 3 Años'!$G$13)+'PyG 3 Años'!$B$14*(1+'PyG 3 Años'!$G$14)+'PyG 3 Años'!$B$15*(1+'PyG 3 Años'!$G$15)+'PyG 3 Años'!$B$16*(1+'PyG 3 Años'!$G$16)+'PyG 3 Años'!$B$17*(1+'PyG 3 Años'!$G$17)+'PyG 3 Años'!$B$18*(1+'PyG 3 Años'!$G$18))*(M7*(1-MIN(30,'0. Supuestos'!$B$59)/30)+L7*MIN(30,'0. Supuestos'!$B$59)/30)),"") -> -3369.7931 | N11: =IFERROR(IF('PyG 3 Años'!$B$9="","",SUM(B11:M11)),"") -> -62180.816 | O11: =IFERROR("Materia prima, consumibles, comisiones e imprevistos, cada uno con SU tipo de IVA (la columna del P&L) y con los días de pago a proveedor de Supuestos."&IF('0. Supuestos'!$B$59=0,""," Con "&TEXT('0. Supuestos'!$B$59,"0")&" días de pago, las primeras compras se pagan ya en el año siguiente: la columna «Año» de esta fila recoge "&TEXT(MAX(0,12-ROUNDUP('0. Supuestos'!$B$59/30,0)),"0")&" mensualidades de compra, no el coste del ejercicio."),"") -> Materia prima, consumibles, comisiones e imprevistos, cada uno con SU tipo de IVA (la columna del P&L) y con los días de pago a proveedor de Supuestos. Con 20 días de pago, las primeras compras se pagan ya en el año siguiente: la columna «Año» de esta fila recoge 11 mensualidades de compra, no el coste del ejercicio.
A12: Costes fijos de explotación (IVA incluido) | B12: =IFERROR(IF('PyG 3 Años'!$B$9="","",-('PyG 3 Años'!$B$38-'PyG 3 Años'!$B$23-'PyG 3 Años'!$B$36-'PyG 3 Años'!$B$37+'PyG 3 Años'!$B$40)/12),"") -> -2313.75 | C12: =IFERROR(IF('PyG 3 Años'!$B$9="","",-('PyG 3 Años'!$B$38-'PyG 3 Años'!$B$23-'PyG 3 Años'!$B$36-'PyG 3 Años'!$B$37+'PyG 3 Años'!$B$40)/12),"") -> -2313.75 | D12: =IFERROR(IF('PyG 3 Años'!$B$9="","",-('PyG 3 Años'!$B$38-'PyG 3 Años'!$B$23-'PyG 3 Años'!$B$36-'PyG 3 Años'!$B$37+'PyG 3 Años'!$B$40)/12),"") -> -2313.75 | E12: =IFERROR(IF('PyG 3 Años'!$B$9="","",-('PyG 3 Años'!$B$38-'PyG 3 Años'!$B$23-'PyG 3 Años'!$B$36-'PyG 3 Años'!$B$37+'PyG 3 Años'!$B$40)/12),"") -> -2313.75 | F12: =IFERROR(IF('PyG 3 Años'!$B$9="","",-('PyG 3 Años'!$B$38-'PyG 3 Años'!$B$23-'PyG 3 Años'!$B$36-'PyG 3 Años'!$B$37+'PyG 3 Años'!$B$40)/12),"") -> -2313.75 | G12: =IFERROR(IF('PyG 3 Años'!$B$9="","",-('PyG 3 Años'!$B$38-'PyG 3 Años'!$B$23-'PyG 3 Años'!$B$36-'PyG 3 Años'!$B$37+'PyG 3 Años'!$B$40)/12),"") -> -2313.75 | H12: =IFERROR(IF('PyG 3 Años'!$B$9="","",-('PyG 3 Años'!$B$38-'PyG 3 Años'!$B$23-'PyG 3 Años'!$B$36-'PyG 3 Años'!$B$37+'PyG 3 Años'!$B$40)/12),"") -> -2313.75 | I12: =IFERROR(IF('PyG 3 Años'!$B$9="","",-('PyG 3 Años'!$B$38-'PyG 3 Años'!$B$23-'PyG 3 Años'!$B$36-'PyG 3 Años'!$B$37+'PyG 3 Años'!$B$40)/12),"") -> -2313.75 | ... M12: =IFERROR(IF('PyG 3 Años'!$B$9="","",-('PyG 3 Años'!$B$38-'PyG 3 Años'!$B$23-'PyG 3 Años'!$B$36-'PyG 3 Años'!$B$37+'PyG 3 Años'!$B$40)/12),"") -> -2313.75 | N12: =IFERROR(IF('PyG 3 Años'!$B$9="","",SUM(B12:M12)),"") -> -27765 | O12: Los fijos que salen de caja, cada uno con su tipo de IVA: los seguros están exentos y no llevan
A13: Nóminas y Seguridad Social | B13: =IFERROR(IF('PyG 3 Años'!$B$9="","",-'PyG 3 Años'!$B$23/MAX(12,'0. Supuestos'!$B$21)*(1+IF(1='0. Supuestos'!$B$60,(MAX(12,'0. Supuestos'!$B$21)-12)/2,0)+IF(1='0. Supuestos'!$B$61,(MAX(12,'0. Supuestos'!$B$21)-12)/2,0))),"") -> -3935.47 | C13: =IFERROR(IF('PyG 3 Años'!$B$9="","",-'PyG 3 Años'!$B$23/MAX(12,'0. Supuestos'!$B$21)*(1+IF(2='0. Supuestos'!$B$60,(MAX(12,'0. Supuestos'!$B$21)-12)/2,0)+IF(2='0. Supuestos'!$B$61,(MAX(12,'0. Supuestos'!$B$21)-12)/2,0))),"") -> -3935.47 | D13: =IFERROR(IF('PyG 3 Años'!$B$9="","",-'PyG 3 Años'!$B$23/MAX(12,'0. Supuestos'!$B$21)*(1+IF(3='0. Supuestos'!$B$60,(MAX(12,'0. Supuestos'!$B$21)-12)/2,0)+IF(3='0. Supuestos'!$B$61,(MAX(12,'0. Supuestos'!$B$21)-12)/2,0))),"") -> -3935.47 | E13: =IFERROR(IF('PyG 3 Años'!$B$9="","",-'PyG 3 Años'!$B$23/MAX(12,'0. Supuestos'!$B$21)*(1+IF(4='0. Supuestos'!$B$60,(MAX(12,'0. Supuestos'!$B$21)-12)/2,0)+IF(4='0. Supuestos'!$B$61,(MAX(12,'0. Supuestos'!$B$21)-12)/2,0))),"") -> -3935.47 | F13: =IFERROR(IF('PyG 3 Años'!$B$9="","",-'PyG 3 Años'!$B$23/MAX(12,'0. Supuestos'!$B$21)*(1+IF(5='0. Supuestos'!$B$60,(MAX(12,'0. Supuestos'!$B$21)-12)/2,0)+IF(5='0. Supuestos'!$B$61,(MAX(12,'0. Supuestos'!$B$21)-12)/2,0))),"") -> -3935.47 | G13: =IFERROR(IF('PyG 3 Años'!$B$9="","",-'PyG 3 Años'!$B$23/MAX(12,'0. Supuestos'!$B$21)*(1+IF(6='0. Supuestos'!$B$60,(MAX(12,'0. Supuestos'!$B$21)-12)/2,0)+IF(6='0. Supuestos'!$B$61,(MAX(12,'0. Supuestos'!$B$21)-12)/2,0))),"") -> -3935.47 | H13: =IFERROR(IF('PyG 3 Años'!$B$9="","",-'PyG 3 Años'!$B$23/MAX(12,'0. Supuestos'!$B$21)*(1+IF(7='0. Supuestos'!$B$60,(MAX(12,'0. Supuestos'!$B$21)-12)/2,0)+IF(7='0. Supuestos'!$B$61,(MAX(12,'0. Supuestos'!$B$21)-12)/2,0))),"") -> -7870.94 | I13: =IFERROR(IF('PyG 3 Años'!$B$9="","",-'PyG 3 Años'!$B$23/MAX(12,'0. Supuestos'!$B$21)*(1+IF(8='0. Supuestos'!$B$60,(MAX(12,'0. Supuestos'!$B$21)-12)/2,0)+IF(8='0. Supuestos'!$B$61,(MAX(12,'0. Supuestos'!$B$21)-12)/2,0))),"") -> -3935.47 | J13: =IFERROR(IF('PyG 3 Años'!$B$9="","",-'PyG 3 Años'!$B$23/MAX(12,'0. Supuestos'!$B$21)*(1+IF(9='0. Supuestos'!$B$60,(MAX(12,'0. Supuestos'!$B$21)-12)/2,0)+IF(9='0. Supuestos'!$B$61,(MAX(12,'0. Supuestos'!$B$21)-12)/2,0))),"") -> -3935.47 | K13: =IFERROR(IF('PyG 3 Años'!$B$9="","",-'PyG 3 Años'!$B$23/MAX(12,'0. Supuestos'!$B$21)*(1+IF(10='0. Supuestos'!$B$60,(MAX(12,'0. Supuestos'!$B$21)-12)/2,0)+IF(10='0. Supuestos'!$B$61,(MAX(12,'0. Supuestos'!$B$21)-12)/2,0))),"") -> -3935.47 | L13: =IFERROR(IF('PyG 3 Años'!$B$9="","",-'PyG 3 Años'!$B$23/MAX(12,'0. Supuestos'!$B$21)*(1+IF(11='0. Supuestos'!$B$60,(MAX(12,'0. Supuestos'!$B$21)-12)/2,0)+IF(11='0. Supuestos'!$B$61,(MAX(12,'0. Supuestos'!$B$21)-12)/2,0))),"") -> -3935.47 | M13: =IFERROR(IF('PyG 3 Años'!$B$9="","",-'PyG 3 Años'!$B$23/MAX(12,'0. Supuestos'!$B$21)*(1+IF(12='0. Supuestos'!$B$60,(MAX(12,'0. Supuestos'!$B$21)-12)/2,0)+IF(12='0. Supuestos'!$B$61,(MAX(12,'0. Supuestos'!$B$21)-12)/2,0))),"") -> -7870.94 | N13: =IFERROR(IF('PyG 3 Años'!$B$9="","",SUM(B13:M13)),"") -> -55096.58 | O13: Doce mensualidades más las pagas extra en los meses que digas en Supuestos. La suma del año es la misma que la del P&L
A14: Intereses del préstamo | B14: =IFERROR(IF('PyG 3 Años'!$B$9="","",-'Financiación'!$B$44/12),"") -> -279.5 | C14: =IFERROR(IF('PyG 3 Años'!$B$9="","",-'Financiación'!$B$44/12),"") -> -279.5 | D14: =IFERROR(IF('PyG 3 Años'!$B$9="","",-'Financiación'!$B$44/12),"") -> -279.5 | E14: =IFERROR(IF('PyG 3 Años'!$B$9="","",-'Financiación'!$B$44/12),"") -> -279.5 | F14: =IFERROR(IF('PyG 3 Años'!$B$9="","",-'Financiación'!$B$44/12),"") -> -279.5 | G14: =IFERROR(IF('PyG 3 Años'!$B$9="","",-'Financiación'!$B$44/12),"") -> -279.5 | H14: =IFERROR(IF('PyG 3 Años'!$B$9="","",-'Financiación'!$B$44/12),"") -> -279.5 | I14: =IFERROR(IF('PyG 3 Años'!$B$9="","",-'Financiación'!$B$44/12),"") -> -279.5 | ... M14: =IFERROR(IF('PyG 3 Años'!$B$9="","",-'Financiación'!$B$44/12),"") -> -279.5 | N14: =IFERROR(IF('PyG 3 Años'!$B$9="","",SUM(B14:M14)),"") -> -3354
A15: Devolución de principal del préstamo | B15: =IFERROR(IF('PyG 3 Años'!$B$9="","",-'Financiación'!$B$45/12),"") -> 0 | C15: =IFERROR(IF('PyG 3 Años'!$B$9="","",-'Financiación'!$B$45/12),"") -> 0 | D15: =IFERROR(IF('PyG 3 Años'!$B$9="","",-'Financiación'!$B$45/12),"") -> 0 | E15: =IFERROR(IF('PyG 3 Años'!$B$9="","",-'Financiación'!$B$45/12),"") -> 0 | F15: =IFERROR(IF('PyG 3 Años'!$B$9="","",-'Financiación'!$B$45/12),"") -> 0 | G15: =IFERROR(IF('PyG 3 Años'!$B$9="","",-'Financiación'!$B$45/12),"") -> 0 | H15: =IFERROR(IF('PyG 3 Años'!$B$9="","",-'Financiación'!$B$45/12),"") -> 0 | I15: =IFERROR(IF('PyG 3 Años'!$B$9="","",-'Financiación'!$B$45/12),"") -> 0 | ... M15: =IFERROR(IF('PyG 3 Años'!$B$9="","",-'Financiación'!$B$45/12),"") -> 0 | N15: =IFERROR(IF('PyG 3 Años'!$B$9="","",SUM(B15:M15)),"") -> 0
A16: IVA repercutido del mes (memoria) | B16: =IFERROR(IF('PyG 3 Años'!$B$9="","",'PyG 3 Años'!$B$9*B7*SUMPRODUCT('PyG 3 Años'!$E$10:$E$11,'PyG 3 Años'!$G$10:$G$11)),"") -> 279.23572 | C16: =IFERROR(IF('PyG 3 Años'!$B$9="","",'PyG 3 Años'!$B$9*C7*SUMPRODUCT('PyG 3 Años'!$E$10:$E$11,'PyG 3 Años'!$G$10:$G$11)),"") -> 379.08365 | D16: =IFERROR(IF('PyG 3 Años'!$B$9="","",'PyG 3 Años'!$B$9*D7*SUMPRODUCT('PyG 3 Años'!$E$10:$E$11,'PyG 3 Años'!$G$10:$G$11)),"") -> 741.24392 | E16: =IFERROR(IF('PyG 3 Años'!$B$9="","",'PyG 3 Años'!$B$9*E7*SUMPRODUCT('PyG 3 Años'!$E$10:$E$11,'PyG 3 Años'!$G$10:$G$11)),"") -> 971.40185 | F16: =IFERROR(IF('PyG 3 Años'!$B$9="","",'PyG 3 Años'!$B$9*F7*SUMPRODUCT('PyG 3 Años'!$E$10:$E$11,'PyG 3 Años'!$G$10:$G$11)),"") -> 1694.0301 | G16: =IFERROR(IF('PyG 3 Años'!$B$9="","",'PyG 3 Años'!$B$9*G7*SUMPRODUCT('PyG 3 Años'!$E$10:$E$11,'PyG 3 Años'!$G$10:$G$11)),"") -> 2200.039 | H16: =IFERROR(IF('PyG 3 Años'!$B$9="","",'PyG 3 Años'!$B$9*H7*SUMPRODUCT('PyG 3 Años'!$E$10:$E$11,'PyG 3 Años'!$G$10:$G$11)),"") -> 2030.8053 | I16: =IFERROR(IF('PyG 3 Años'!$B$9="","",'PyG 3 Años'!$B$9*I7*SUMPRODUCT('PyG 3 Años'!$E$10:$E$11,'PyG 3 Años'!$G$10:$G$11)),"") -> 2030.8053 | ... M16: =IFERROR(IF('PyG 3 Años'!$B$9="","",'PyG 3 Años'!$B$9*M7*SUMPRODUCT('PyG 3 Años'!$E$10:$E$11,'PyG 3 Años'!$G$10:$G$11)),"") -> 1100.0195 | N16: =IFERROR(IF('PyG 3 Años'!$B$9="","",SUM(B16:M16)),"") -> 15826.742 | O16: Cada línea de venta a SU tipo, leído de la columna de IVA del P&L: en el servicio de paella, alcohol incluido, el reducido (art. 91.Uno.2.2.º de la Ley 37/1992 del IVA); el alcohol que sale por paella para recoger, al general; la carpa o el mobiliario facturados aparte, al general (art. 90)
A17: IVA soportado del mes (memoria) | B17: =IFERROR(IF('PyG 3 Años'!$B$9="","",'PyG 3 Años'!$B$39*B7+'PyG 3 Años'!$B$40/12),"") -> 505.19661 | C17: =IFERROR(IF('PyG 3 Años'!$B$9="","",'PyG 3 Años'!$B$39*C7+'PyG 3 Años'!$B$40/12),"") -> 551.30479 | D17: =IFERROR(IF('PyG 3 Años'!$B$9="","",'PyG 3 Años'!$B$39*D7+'PyG 3 Años'!$B$40/12),"") -> 718.54464 | E17: =IFERROR(IF('PyG 3 Años'!$B$9="","",'PyG 3 Años'!$B$39*E7+'PyG 3 Años'!$B$40/12),"") -> 824.82791 | F17: =IFERROR(IF('PyG 3 Años'!$B$9="","",'PyG 3 Años'!$B$39*F7+'PyG 3 Años'!$B$40/12),"") -> 1158.5261 | G17: =IFERROR(IF('PyG 3 Años'!$B$9="","",'PyG 3 Años'!$B$39*G7+'PyG 3 Años'!$B$40/12),"") -> 1392.193 | H17: =IFERROR(IF('PyG 3 Años'!$B$9="","",'PyG 3 Años'!$B$39*H7+'PyG 3 Años'!$B$40/12),"") -> 1314.0435 | I17: =IFERROR(IF('PyG 3 Años'!$B$9="","",'PyG 3 Años'!$B$39*I7+'PyG 3 Años'!$B$40/12),"") -> 1314.0435 | ... M17: =IFERROR(IF('PyG 3 Años'!$B$9="","",'PyG 3 Años'!$B$39*M7+'PyG 3 Años'!$B$40/12),"") -> 884.2215 | N17: =IFERROR(IF('PyG 3 Años'!$B$9="","",SUM(B17:M17)),"") -> 11823.538 | O17: Cada partida a su tipo, leído de la columna de IVA del P&L: los seguros y las comisiones de los medios de pago están exentos
A18: IVA a compensar arrastrado (inversión incluida) | E18: =IFERROR(IF('PyG 3 Años'!$B$9="","",'Inversión Inicial'!$B$28),"") -> 8376.06 | H18: =IFERROR(IF('PyG 3 Años'!$B$9="","",MAX(0,-E19)),"") -> 8751.5427 | K18: =IFERROR(IF('PyG 3 Años'!$B$9="","",MAX(0,-H19)),"") -> 7261.6188 | O18: El IVA soportado de la INVERSIÓN entra aquí: se compensa contra el repercutido de los trimestres siguientes hasta agotarlo (modelo 303)
A19: Resultado de la liquidación trimestral | E19: =IFERROR(IF('PyG 3 Años'!$B$9="","",SUM(B16:D16)-SUM(B17:D17)-E18),"") -> -8751.5427 | H19: =IFERROR(IF('PyG 3 Años'!$B$9="","",SUM(E16:G16)-SUM(E17:G17)-H18),"") -> -7261.6188 | K19: =IFERROR(IF('PyG 3 Años'!$B$9="","",SUM(H16:J16)-SUM(H17:J17)-K18),"") -> -5020.2493 | O19: Repercutido menos soportado del trimestre menos lo que venía arrastrado. En negativo NO se paga: se compensa en el trimestre siguiente
A20: Pago del IVA (modelo 303) | E20: =IFERROR(IF('PyG 3 Años'!$B$9="","",IF(E19<=0,"",-E19)),"") | H20: =IFERROR(IF('PyG 3 Años'!$B$9="","",IF(H19<=0,"",-H19)),"") | K20: =IFERROR(IF('PyG 3 Años'!$B$9="","",IF(K19<=0,"",-K19)),"") | N20: =IFERROR(IF('PyG 3 Años'!$B$9="","",SUM(B20:M20)),"") -> 0 | O20: Sólo sale caja cuando el resultado del trimestre es positivo. Los meses sin liquidación van en blanco, no a cero. La celda se pinta en ROJO cuando el pago del 303 se lleva más caja de la que queda ese mes
A21: FLUJO DEL MES | B21: =IFERROR(IF('PyG 3 Años'!$B$9="","",SUM(B9:B15)+IF(B20="",0,B20)),"") -> -5890.3581 | C21: =IFERROR(IF('PyG 3 Años'!$B$9="","",SUM(C9:C15)+IF(C20="",0,C20)),"") -> -4385.3716 | D21: =IFERROR(IF('PyG 3 Años'!$B$9="","",SUM(D9:D15)+IF(D20="",0,D20)),"") -> -3100.9101 | E21: =IFERROR(IF('PyG 3 Años'!$B$9="","",SUM(E9:E15)+IF(E20="",0,E20)),"") -> -918.87317 | F21: =IFERROR(IF('PyG 3 Años'!$B$9="","",SUM(F9:F15)+IF(F20="",0,F20)),"") -> 1785.4599 | G21: =IFERROR(IF('PyG 3 Años'!$B$9="","",SUM(G9:G15)+IF(G20="",0,G20)),"") -> 6246.2553 | H21: =IFERROR(IF('PyG 3 Años'!$B$9="","",SUM(H9:H15)+IF(H20="",0,H20)),"") -> 4237.4775 | I21: =IFERROR(IF('PyG 3 Años'!$B$9="","",SUM(I9:I15)+IF(I20="",0,I20)),"") -> 7399.1756 | ... M21: =IFERROR(IF('PyG 3 Años'!$B$9="","",SUM(M9:M15)+IF(M20="",0,M20)),"") -> -4854.3432 | N21: =IFERROR(IF('PyG 3 Años'!$B$9="","",SUM(B21:M21)),"") -> 17299.635
A22: SALDO ACUMULADO DE CAJA | B22: =IFERROR(IF('PyG 3 Años'!$B$9="","",'Inversión Inicial'!$B$25+B21),"") -> 14534.787 | C22: =IFERROR(IF('PyG 3 Años'!$B$9="","",B22+C21),"") -> 10149.415 | D22: =IFERROR(IF('PyG 3 Años'!$B$9="","",C22+D21),"") -> 7048.5051 | E22: =IFERROR(IF('PyG 3 Años'!$B$9="","",D22+E21),"") -> 6129.6319 | F22: =IFERROR(IF('PyG 3 Años'!$B$9="","",E22+F21),"") -> 7915.0918 | G22: =IFERROR(IF('PyG 3 Años'!$B$9="","",F22+G21),"") -> 14161.347 | H22: =IFERROR(IF('PyG 3 Años'!$B$9="","",G22+H21),"") -> 18398.825 | I22: =IFERROR(IF('PyG 3 Años'!$B$9="","",H22+I21),"") -> 25798 | J22: =IFERROR(IF('PyG 3 Años'!$B$9="","",I22+J21),"") -> 33584.062 | ... M22: =IFERROR(IF('PyG 3 Años'!$B$9="","",L22+M21),"") -> 37724.78
A23: Saldo mínimo del año | B23: =IFERROR(IF('PyG 3 Años'!$B$9="","",IF(COUNT(B22:M22)=0,"",MIN(B22:M22))),"") -> 6129.6319 | D23: Si es negativo, sube el fondo de maniobra o el préstamo: te quedas sin caja
A24: Mes en el que la caja toca fondo | B24: =IFERROR(IF('PyG 3 Años'!$B$9="","",IF(COUNT(B22:M22)=0,"",MATCH(MIN(B22:M22),B22:M22,0))),"") -> 4 | D24: Es la respuesta a la pregunta que decide una operación bancaria: en qué mes se agota la caja
A25: RETORNO DE LA INVERSIÓN
A26: Flujo de caja libre antes de la deuda, año 1 | B26: =IFERROR(IF('PyG 3 Años'!$B$9="","",'PyG 3 Años'!$B$48+'PyG 3 Años'!$B$36+'Financiación'!$B$44),"") -> 19493.106 | D26: Resultado neto más amortización (que no se paga) más los intereses de ese año: el principal no se resta porque este flujo es ANTES de la deuda. La MISMA base que los años 2 y 3, para que el payback compare peras con peras
A27: Flujo de caja libre antes de la deuda, año 2 | B27: =IFERROR(IF('PyG 3 Años'!$B$9="","",'PyG 3 Años'!$C$48+'PyG 3 Años'!$C$36+'Financiación'!$B$46),"") -> 22895.361 | D27: Resultado neto más amortización (que no se paga) más los intereses de ese año: el principal no se resta porque este flujo es ANTES de la deuda. Sin tabla mensual, es una estimación
A28: Flujo de caja libre antes de la deuda, año 3 | B28: =IFERROR(IF('PyG 3 Años'!$B$9="","",'PyG 3 Años'!$D$48+'PyG 3 Años'!$D$36+'Financiación'!$B$48),"") -> 21341.244 | D28: Resultado neto más amortización (que no se paga) más los intereses de ese año: el principal no se resta porque este flujo es ANTES de la deuda. Sin tabla mensual, es una estimación
A29: Informativo: flujo REAL de caja del año 1 (tabla mensual, antes de la deuda) | B29: =IFERROR(IF('PyG 3 Años'!$B$9="","",N21+'Financiación'!$B$44+'Financiación'!$B$45),"") -> 20653.635 | D29: La suma de los doce FLUJO DEL MES de arriba, devolviéndole los intereses y el principal que se pagaron ese año. NO es la que usa el payback: lleva dentro el IVA que todavía no se ha liquidado y el crédito del proveedor, dos cosas que hay que devolver y que los años 2 y 3 no tienen
A30: Inversión a recuperar (sin el IVA, que se recupera por el 303) | B30: =IFERROR(IF('PyG 3 Años'!$B$9="","",'Inversión Inicial'!$B$29-'Inversión Inicial'!$B$28),"") -> 63111.145 | D30: CAPEX más fondo de maniobra: la necesidad total de caja MENOS el IVA soportado de la inversión, que no se pierde (se recupera con el modelo 303 y esta misma hoja lo compensa trimestre a trimestre). El fondo de maniobra sí se recupera al cerrar, pero hasta entonces está inmovilizado
A31: Payback del proyecto (años), antes de la deuda | B31: =IFERROR(IF('PyG 3 Años'!$B$9="","",IF(B26>=B30,ROUND(B30/B26,1),IF(B26+B27>=B30,ROUND(1+(B30-B26)/B27,1),IF(B26+B27+B28>=B30,ROUND(2+(B30-B26-B27)/B28,1),"Más de 3 años")))),"") -> 3 | D31: Mide cuánto tarda el negocio en devolver la inversión con lo que genera ANTES de pagar al banco, con la MISMA base de flujo en los tres años; si puedes pagar la cuota lo dice el DSCR de la hoja de Financiación. El plan de negocio en Word cita esta cifra; si cambias una celda verde, manda este libro
A32: Payback sobre el CAPEX, sin fondo de maniobra (años) | B32: =IFERROR(IF('PyG 3 Años'!$B$9="","",IF(B26>='Inversión Inicial'!$B$27,ROUND('Inversión Inicial'!$B$27/B26,1),IF(B26+B27>='Inversión Inicial'!$B$27,ROUND(1+('Inversión Inicial'!$B$27-B26)/B27,1),IF(B26+B27+B28>='Inversión Inicial'!$B$27,ROUND(2+('Inversión Inicial'!$B$27-B26-B27)/B28,1),"Más de 3 años")))),"") -> 2 | D32: El mismo cálculo sobre lo que se COMPRA (furgoneta, equipamiento, lanzamiento y constitución), sin el fondo de maniobra: ese dinero no se gasta, se inmoviliza y vuelve al cerrar el negocio. Informativo: el payback que se publica es el de arriba
A34: El IVA del cuarto trimestre se liquida en enero del año siguiente, así que no aparece en este cuadro. El Impuesto de Sociedades del año 1 se paga en julio del año 2. La cuota del préstamo se reparte en doce partes iguales siguiendo el cuadro ANUAL de la hoja de Financiación, y las nóminas en doce mensualidades más las dos pagas extra en su mes.

Sheet Financiación
A1: PLAN DE FINANCIACIÓN
A2: Qué hace falta, de dónde sale y cuánto cuesta devolverlo. Es la hoja que el banco pide junto con el P&L.
A4: Concepto | B4: Importe | C4: Notas
A5: ORIGEN DE FONDOS
A6: Recursos propios de los socios | B6: =IFERROR(IF('0. Supuestos'!$B$30="","",'0. Supuestos'!$B$30),"") -> 20000
A7: Préstamo bancario | B7: =IFERROR(IF('0. Supuestos'!$B$31="","",'0. Supuestos'!$B$31),"") -> 51600
A8: Línea ICO (avalada por el ICO, la concede tu banco) | B8: 0 | C8: Consulta las líneas del ejercicio en curso en ico.es
A9: Préstamo participativo ENISA | B9: 0 | C9: Para sociedades; sin garantías personales
A10: Business angels o socios inversores | B10: 0 | C10: Entra en el capital: diluye, no se devuelve
A11: Subvenciones autonómicas o locales | B11: 0 | C11: Suelen cobrarse DESPUÉS de justificar el gasto
A12: TOTAL ORIGEN DE FONDOS | B12: =IFERROR(IF(COUNT(B6:B11)=0,"",SUM(B6:B11)),"") -> 71600
A13: USOS
A14: Necesidad total de caja al arranque | B14: =IFERROR(IF('Inversión Inicial'!$B$29="","",'Inversión Inicial'!$B$29),"") -> 71487.205 | C14: Inversión más el IVA que hay que adelantar
A15: Diferencia (origen - usos) | B15: =IFERROR(B12-B14,"") -> 112.795 | C15: En rojo (negativa) el plan NO está financiado. Muy por encima de cero tampoco es gratis: se pagan intereses por un dinero que no se usa
A16: Diferencia sobre los usos (%) | B16: =IFERROR(B15/B14,"") -> 0.0015778348 | C16: Ámbar por encima del margen que fijes: es deuda que pagas sin necesitarla
A17: Exceso de financiación admisible (%) | B17: 0.05 | C17: Un pequeño colchón sobre la necesidad es sano; un 20 % de más son intereses tirados
A18: Préstamo que ajustaría el origen a la necesidad | B18: =IFERROR(MAX(0,B14-B12+B7),"") -> 51487.205 | C18: Cópialo en «Préstamo bancario solicitado» de la hoja de Supuestos y la diferencia se pone a cero
A19: CONDICIONES DEL PRÉSTAMO
A20: Importe del principal | B20: =IFERROR(IF('0. Supuestos'!$B$31=0,"",'0. Supuestos'!$B$31),"") -> 51600
A21: Tipo de interés nominal anual | B21: =IFERROR(IF('0. Supuestos'!$B$32="","",'0. Supuestos'!$B$32),"") -> 0.065
A22: Plazo total (años) | B22: =IFERROR(IF('0. Supuestos'!$B$33="","",'0. Supuestos'!$B$33),"") -> 6
A23: Carencia de principal aplicada (años) | B23: =IFERROR(IF(OR('0. Supuestos'!$B$34="",'0. Supuestos'!$B$33=""),"",IF('0. Supuestos'!$B$34>='0. Supuestos'!$B$33,0,'0. Supuestos'!$B$34)),"") -> 1 | C23: Una carencia igual o mayor que el plazo no existe: la hoja la anula en origen
A24: Cuota anual durante la amortización | B24: =IFERROR(IF(B22-B23<=0,"",IF(B21=0,B20/(B22-B23),B20*B21/(1-(1+B21)^-(B22-B23)))),"") -> 12416.742 | C24: Sistema francés, anualidad algebraica. Con el tipo al 0 % es el principal entre los años de amortización: sin esa rama el cuadro se apagaba entero
A25: CUADRO DE AMORTIZACIÓN
A26: Año | B26: Capital pendiente | C26: Intereses | D26: Amortización de principal | E26: Cuota total | F26: Capital al cierre | G26: Flujo disponible para la deuda (después de impuestos; del año 4 en adelante, el del año 3 mantenido) | H26: DSCR del año
A27: 1 | B27: =IFERROR(IF(B20="","",B20),"") -> 51600 | C27: =IFERROR(IF(OR(1>B22,B27=""),"",B27*B21),"") -> 3354 | D27: =IFERROR(IF(OR(1>B22,B27=""),"",IF(1<=B23,0,MIN(B27,B24-C27))),"") -> 0 | E27: =IFERROR(IF(C27="","",C27+D27),"") -> 3354 | F27: =IFERROR(IF(D27="","",B27-D27),"") -> 51600 | G27: =IFERROR(IF(E27="","",'PyG 3 Años'!$B$41-'PyG 3 Años'!$B$46+'PyG 3 Años'!$B$36+'PyG 3 Años'!$B$37),"") -> 19493.106 | H27: =IFERROR(IF(OR(E27="",E27=0),"",G27/E27),"") -> 5.811898
A28: 2 | B28: =IFERROR(IF(OR(2>B22,F27=""),"",F27),"") -> 51600 | C28: =IFERROR(IF(OR(2>B22,B28=""),"",B28*B21),"") -> 3354 | D28: =IFERROR(IF(OR(2>B22,B28=""),"",IF(2<=B23,0,MIN(B28,B24-C28))),"") -> 9062.7421 | E28: =IFERROR(IF(C28="","",C28+D28),"") -> 12416.742 | F28: =IFERROR(IF(D28="","",B28-D28),"") -> 42537.258 | G28: =IFERROR(IF(E28="","",'PyG 3 Años'!$C$41-'PyG 3 Años'!$C$46+'PyG 3 Años'!$C$36+'PyG 3 Años'!$C$37),"") -> 22895.361 | H28: =IFERROR(IF(OR(E28="",E28=0),"",G28/E28),"") -> 1.8439105
A29: 3 | B29: =IFERROR(IF(OR(3>B22,F28=""),"",F28),"") -> 42537.258 | C29: =IFERROR(IF(OR(3>B22,B29=""),"",B29*B21),"") -> 2764.9218 | D29: =IFERROR(IF(OR(3>B22,B29=""),"",IF(3<=B23,0,MIN(B29,B24-C29))),"") -> 9651.8204 | E29: =IFERROR(IF(C29="","",C29+D29),"") -> 12416.742 | F29: =IFERROR(IF(D29="","",B29-D29),"") -> 32885.437 | G29: =IFERROR(IF(E29="","",'PyG 3 Años'!$D$41-'PyG 3 Años'!$D$46+'PyG 3 Años'!$D$36+'PyG 3 Años'!$D$37),"") -> 21341.244 | H29: =IFERROR(IF(OR(E29="",E29=0),"",G29/E29),"") -> 1.7187475
A30: 4 | B30: =IFERROR(IF(OR(4>B22,F29=""),"",F29),"") -> 32885.437 | C30: =IFERROR(IF(OR(4>B22,B30=""),"",B30*B21),"") -> 2137.5534 | D30: =IFERROR(IF(OR(4>B22,B30=""),"",IF(4<=B23,0,MIN(B30,B24-C30))),"") -> 10279.189 | E30: =IFERROR(IF(C30="","",C30+D30),"") -> 12416.742 | F30: =IFERROR(IF(D30="","",B30-D30),"") -> 22606.249 | G30: =IFERROR(IF(E30="","",'PyG 3 Años'!$D$41-'PyG 3 Años'!$D$46+'PyG 3 Años'!$D$36+'PyG 3 Años'!$D$37),"") -> 21341.244 | H30: =IFERROR(IF(OR(E30="",E30=0),"",G30/E30),"") -> 1.7187475
A31: 5 | B31: =IFERROR(IF(OR(5>B22,F30=""),"",F30),"") -> 22606.249 | C31: =IFERROR(IF(OR(5>B22,B31=""),"",B31*B21),"") -> 1469.4062 | D31: =IFERROR(IF(OR(5>B22,B31=""),"",IF(5<=B23,0,MIN(B31,B24-C31))),"") -> 10947.336 | E31: =IFERROR(IF(C31="","",C31+D31),"") -> 12416.742 | F31: =IFERROR(IF(D31="","",B31-D31),"") -> 11658.913 | G31: =IFERROR(IF(E31="","",'PyG 3 Años'!$D$41-'PyG 3 Años'!$D$46+'PyG 3 Años'!$D$36+'PyG 3 Años'!$D$37),"") -> 21341.244 | H31: =IFERROR(IF(OR(E31="",E31=0),"",G31/E31),"") -> 1.7187475
A32: 6 | B32: =IFERROR(IF(OR(6>B22,F31=""),"",F31),"") -> 11658.913 | C32: =IFERROR(IF(OR(6>B22,B32=""),"",B32*B21),"") -> 757.82933 | D32: =IFERROR(IF(OR(6>B22,B32=""),"",IF(6<=B23,0,MIN(B32,B24-C32))),"") -> 11658.913 | E32: =IFERROR(IF(C32="","",C32+D32),"") -> 12416.742 | F32: =IFERROR(IF(D32="","",B32-D32),"") -> 0 | G32: =IFERROR(IF(E32="","",'PyG 3 Años'!$D$41-'PyG 3 Años'!$D$46+'PyG 3 Años'!$D$36+'PyG 3 Años'!$D$37),"") -> 21341.244 | H32: =IFERROR(IF(OR(E32="",E32=0),"",G32/E32),"") -> 1.7187475
A33: 7 | B33: =IFERROR(IF(OR(7>B22,F32=""),"",F32),"") | C33: =IFERROR(IF(OR(7>B22,B33=""),"",B33*B21),"") | D33: =IFERROR(IF(OR(7>B22,B33=""),"",IF(7<=B23,0,MIN(B33,B24-C33))),"") | E33: =IFERROR(IF(C33="","",C33+D33),"") | F33: =IFERROR(IF(D33="","",B33-D33),"") | G33: =IFERROR(IF(E33="","",'PyG 3 Años'!$D$41-'PyG 3 Años'!$D$46+'PyG 3 Años'!$D$36+'PyG 3 Años'!$D$37),"") | H33: =IFERROR(IF(OR(E33="",E33=0),"",G33/E33),"")
A34: 8 | B34: =IFERROR(IF(OR(8>B22,F33=""),"",F33),"") | C34: =IFERROR(IF(OR(8>B22,B34=""),"",B34*B21),"") | D34: =IFERROR(IF(OR(8>B22,B34=""),"",IF(8<=B23,0,MIN(B34,B24-C34))),"") | E34: =IFERROR(IF(C34="","",C34+D34),"") | F34: =IFERROR(IF(D34="","",B34-D34),"") | G34: =IFERROR(IF(E34="","",'PyG 3 Años'!$D$41-'PyG 3 Años'!$D$46+'PyG 3 Años'!$D$36+'PyG 3 Años'!$D$37),"") | H34: =IFERROR(IF(OR(E34="",E34=0),"",G34/E34),"")
A35: 9 | B35: =IFERROR(IF(OR(9>B22,F34=""),"",F34),"") | C35: =IFERROR(IF(OR(9>B22,B35=""),"",B35*B21),"") | D35: =IFERROR(IF(OR(9>B22,B35=""),"",IF(9<=B23,0,MIN(B35,B24-C35))),"") | E35: =IFERROR(IF(C35="","",C35+D35),"") | F35: =IFERROR(IF(D35="","",B35-D35),"") | G35: =IFERROR(IF(E35="","",'PyG 3 Años'!$D$41-'PyG 3 Años'!$D$46+'PyG 3 Años'!$D$36+'PyG 3 Años'!$D$37),"") | H35: =IFERROR(IF(OR(E35="",E35=0),"",G35/E35),"")
A36: 10 | B36: =IFERROR(IF(OR(10>B22,F35=""),"",F35),"") | C36: =IFERROR(IF(OR(10>B22,B36=""),"",B36*B21),"") | D36: =IFERROR(IF(OR(10>B22,B36=""),"",IF(10<=B23,0,MIN(B36,B24-C36))),"") | E36: =IFERROR(IF(C36="","",C36+D36),"") | F36: =IFERROR(IF(D36="","",B36-D36),"") | G36: =IFERROR(IF(E36="","",'PyG 3 Años'!$D$41-'PyG 3 Años'!$D$46+'PyG 3 Años'!$D$36+'PyG 3 Años'!$D$37),"") | H36: =IFERROR(IF(OR(E36="",E36=0),"",G36/E36),"")
A37: 11 | B37: =IFERROR(IF(OR(11>B22,F36=""),"",F36),"") | C37: =IFERROR(IF(OR(11>B22,B37=""),"",B37*B21),"") | D37: =IFERROR(IF(OR(11>B22,B37=""),"",IF(11<=B23,0,MIN(B37,B24-C37))),"") | E37: =IFERROR(IF(C37="","",C37+D37),"") | F37: =IFERROR(IF(D37="","",B37-D37),"") | G37: =IFERROR(IF(E37="","",'PyG 3 Años'!$D$41-'PyG 3 Años'!$D$46+'PyG 3 Años'!$D$36+'PyG 3 Años'!$D$37),"") | H37: =IFERROR(IF(OR(E37="",E37=0),"",G37/E37),"")
A38: 12 | B38: =IFERROR(IF(OR(12>B22,F37=""),"",F37),"") | C38: =IFERROR(IF(OR(12>B22,B38=""),"",B38*B21),"") | D38: =IFERROR(IF(OR(12>B22,B38=""),"",IF(12<=B23,0,MIN(B38,B24-C38))),"") | E38: =IFERROR(IF(C38="","",C38+D38),"") | F38: =IFERROR(IF(D38="","",B38-D38),"") | G38: =IFERROR(IF(E38="","",'PyG 3 Años'!$D$41-'PyG 3 Años'!$D$46+'PyG 3 Años'!$D$36+'PyG 3 Años'!$D$37),"") | H38: =IFERROR(IF(OR(E38="",E38=0),"",G38/E38),"")
A39: 13 | B39: =IFERROR(IF(OR(13>B22,F38=""),"",F38),"") | C39: =IFERROR(IF(OR(13>B22,B39=""),"",B39*B21),"") | D39: =IFERROR(IF(OR(13>B22,B39=""),"",IF(13<=B23,0,MIN(B39,B24-C39))),"") | E39: =IFERROR(IF(C39="","",C39+D39),"") | F39: =IFERROR(IF(D39="","",B39-D39),"") | G39: =IFERROR(IF(E39="","",'PyG 3 Años'!$D$41-'PyG 3 Años'!$D$46+'PyG 3 Años'!$D$36+'PyG 3 Años'!$D$37),"") | H39: =IFERROR(IF(OR(E39="",E39=0),"",G39/E39),"")
A40: 14 | B40: =IFERROR(IF(OR(14>B22,F39=""),"",F39),"") | C40: =IFERROR(IF(OR(14>B22,B40=""),"",B40*B21),"") | D40: =IFERROR(IF(OR(14>B22,B40=""),"",IF(14<=B23,0,MIN(B40,B24-C40))),"") | E40: =IFERROR(IF(C40="","",C40+D40),"") | F40: =IFERROR(IF(D40="","",B40-D40),"") | G40: =IFERROR(IF(E40="","",'PyG 3 Años'!$D$41-'PyG 3 Años'!$D$46+'PyG 3 Años'!$D$36+'PyG 3 Años'!$D$37),"") | H40: =IFERROR(IF(OR(E40="",E40=0),"",G40/E40),"")
A41: 15 | B41: =IFERROR(IF(OR(15>B22,F40=""),"",F40),"") | C41: =IFERROR(IF(OR(15>B22,B41=""),"",B41*B21),"") | D41: =IFERROR(IF(OR(15>B22,B41=""),"",IF(15<=B23,0,MIN(B41,B24-C41))),"") | E41: =IFERROR(IF(C41="","",C41+D41),"") | F41: =IFERROR(IF(D41="","",B41-D41),"") | G41: =IFERROR(IF(E41="","",'PyG 3 Años'!$D$41-'PyG 3 Años'!$D$46+'PyG 3 Años'!$D$36+'PyG 3 Años'!$D$37),"") | H41: =IFERROR(IF(OR(E41="",E41=0),"",G41/E41),"")
A42: Tolerancia de cierre del cuadro (€) | B42: 0.01 | C42: Margen por redondeo. Por encima, el cuadro no cierra y hay capital sin devolver
A43: Capital pendiente al vencimiento | B43: =IFERROR(IF(B20="","",ROUND(B20-SUM(D27:D41),2)),"") -> 0 | C43: Tiene que ser cero: el principal devuelto en el cuadro tiene que ser el prestado. Si sale positivo, el plazo no llega
A44: Intereses del año 1 | B44: =IFERROR(IF(B20="","",IF(C27="",0,C27)),"") -> 3354
A45: Devolución de principal del año 1 | B45: =IFERROR(IF(B20="","",IF(D27="",0,D27)),"") -> 0
A46: Intereses del año 2 | B46: =IFERROR(IF(B20="","",IF(C28="",0,C28)),"") -> 3354
A47: Devolución de principal del año 2 | B47: =IFERROR(IF(B20="","",IF(D28="",0,D28)),"") -> 9062.7421
A48: Intereses del año 3 | B48: =IFERROR(IF(B20="","",IF(C29="",0,C29)),"") -> 2764.9218
A49: Devolución de principal del año 3 | B49: =IFERROR(IF(B20="","",IF(D29="",0,D29)),"") -> 9651.8204
A50: COBERTURA DEL SERVICIO DE LA DEUDA (DSCR)
A51: DSCR del año 1 | B51: =IFERROR(('PyG 3 Años'!$B$41-'PyG 3 Años'!$B$46+'PyG 3 Años'!$B$36+B44)/(B44+B45),"") -> 5.811898 | C51: Año de CARENCIA si la hay: con sólo intereses en el denominador el ratio se dispara y no mide el negocio
A52: DSCR del año 2 | B52: =IFERROR(('PyG 3 Años'!$C$41-'PyG 3 Años'!$C$46+'PyG 3 Años'!$C$36+B46)/(B46+B47),"") -> 1.8439105
A53: DSCR del año 3 | B53: =IFERROR(('PyG 3 Años'!$D$41-'PyG 3 Años'!$D$46+'PyG 3 Años'!$D$36+B48)/(B48+B49),"") -> 1.7187475
A54: DSCR mínimo de todo el cuadro | B54: =IFERROR(IF(COUNT(H27:H41)=0,"",MIN(H27:H41)),"") -> 1.7187475 | C54: El peor año de los que dura el préstamo, no el mejor de los tres que proyecta el P&L. Es el número que decide una operación. Ojo al alcance: los años 1 a 3 salen del P&L y del año 4 en adelante el cuadro MANTIENE el flujo del año 3, así que el mínimo de esos años es una proyección sostenida, no un año calculado. El flujo va después de impuestos
A56: El DSCR se calcula ANTES de la deuda y DESPUÉS de impuestos: al resultado antes de impuestos se le resta el Impuesto de Sociedades y se le devuelven la amortización contable y los intereses; el resultado se divide entre lo que hay que pagar ese año. Por debajo del mínimo de la hoja de Supuestos, el negocio no genera para pagar el préstamo. En el cuadro, el flujo de caja disponible de los años 4 en adelante se mantiene en el del año 3: el P&L sólo proyecta tres, y aquí no se inventa un crecimiento que no está calculado.
