Workbook

Sheet 0. Assumptions
A1: ASSUMPTIONS — the RATES and DRIVERS of the model are typed here
A2: Change the GREEN cells: the rest of the workbook recalculates on its own. Expense items are typed on their own tab (also in green) and are not repeated here. Amounts are in your currency.
A3: BUSINESS ACTIVITY
A4: Covers per day (year-1 average) | B4: 95 | C4: Average covers served per day over the year, bar and table service combined. Divide it by the seats on this sheet to get the implied seat turns per day (calculated below) and compare them with the seat-turn ceiling on the "Break-Even" tab. Start conservative: a new bar rarely fills its seats from the first month
A5: Average check (excl. sales tax) | B5: 27 | C5: Average check per guest EXCLUDING sales tax: what you ring up before tax is added. The "Menu price incl. sales tax (calculated)" row below shows what the guest sees on the menu once your local rate is applied. Compare both with the average check range in the benchmarks table on "Instructions"
A6: Operating days per year | B6: 360 | C6: One figure feeds the P&L, the break-even and the scenarios, so all three tabs always agree. It assumes the bar opens seven days a week, minus a few closed holidays: enter the days you will really be open. See "3-Year P&L" for how it drives annual sales
A7: Volume growth in year 2 | B7: 0.15 | C7: Growth in daily covers in year 2. Kept deliberately modest: a neighborhood bar takes time to build a base of regulars, so the plan does not lean on the after-work crowd consolidating in year 1
A8: Volume growth in year 3 | B8: 0.1 | C8: Growth in daily covers in year 3. Smaller than in year 2 on purpose: a bar with a fixed number of seats grows into its capacity and growth slows as it fills up
A9: Menu price incl. sales tax (calculated) | B9: =IFERROR(IF($B$5="","",$B$5*(1+SUMPRODUCT('3-Year P&L'!$E$10:$E$11,'3-Year P&L'!$G$10:$G$11))),"") -> 29.16 | C9: =IFERROR("Average check excl. sales tax plus the weighted sales tax of your sales lines ("&TEXT(SUMPRODUCT('3-Year P&L'!$E$10:$E$11,'3-Year P&L'!$G$10:$G$11)*100,"0")&"%), rounded. In the US, menu prices usually exclude sales tax and it is added at the register; in the UK, menu prices include VAT.","") -> Average check excl. sales tax plus the weighted sales tax of your sales lines (8%), rounded. In the US, menu prices usually exclude sales tax and it is added at the register; in the UK, menu prices include VAT.
A10: SALES MIX AND COST OF GOODS SOLD
A11: FOOD share of total sales | B11: 0.35 | C11: Share of FOOD in total sales. It is an INPUT: change it here and the P&L, the cash flow and the sales tax collected recalculate on their own
A12: BEVERAGE share of total sales | B12: =IFERROR(IF(COUNT(B11)=0,"",1-B11),"") -> 0.65 | C12: Calculated as the remainder: food + beverage = 100%
A13: Cost of goods sold on FOOD sales | B13: 0.3 | C13: Food cost on FOOD sales (small plates): ingredients as a share of what the kitchen sells. Stay inside the small-plates range in the benchmarks table on "Instructions"
A14: Cost of goods sold on BEVERAGE sales | B14: 0.22 | C14: Pour cost on BEVERAGE sales: beer, wine, spirits and cocktail ingredients as a share of what the bar sells. It is a weighted blend of the beer and wine pour cost and the cocktail pour cost in the benchmarks on "Instructions", and it includes garnish and spillage
A15: Disposables and packaging as % of sales | B15: 0.01 | C15: Disposable take-out containers, napkins and bar paper, as a share of sales
A16: Delivery share of total sales | B16: 0 | C16: Zero by default: the opening checklist treats delivery as an option for later, only if margins allow it, not for day one. Raise it to the real share of the channel once you turn it on
A17: Delivery platform fee | B17: 0.25 | C17: Percentage a delivery marketplace (DoorDash, Uber Eats) keeps from each order. Confirm your real rate in the platform contract, and add it only if you switch delivery on
A18: Card processing fee | B18: 0.035 | C18: Card and mobile wallet / contactless processing fees on total sales. A neighborhood bar collects most of its drinks by card, so use your processor's effective rate rather than the headline one
A19: LABOR
A20: Employer payroll taxes | B20: 0.1 | C20: FICA (Social Security 6.2% + Medicare 1.45%) + federal and state unemployment taxes (FUTA / SUTA) + workers' comp. About 10% in total: adjust it to your state and your insurance carrier
A21: Monthly pay periods per year (keep 12) | B21: 12 | C21: Annual gross pay = monthly gross pay × this number. Keep 12 in the US: it counts the monthly salaries the model pays in a year, not how often you run payroll (weekly or biweekly payroll pays the same annual amount)
A22: Federal minimum wage, annual full-time | B22: 15080 | C22: US federal minimum wage: 7.25 per hour × 2,080 hours = 15,080 per year for a full-time job. Your state or city may set a higher floor: enter it in the state / local minimum wage cell below. Check the current rates at dol.gov
A23: RENT AND FIXED COSTS
A24: Monthly rent | B24: 6500 | C24: Monthly rent for a space with a bar counter and a patio. It must stay under the rent ceiling in the benchmarks table on "Instructions" and in the traffic light of the "3-Year P&L". Compare it with real quotes in your area, and negotiate the lease terms with your attorney
A25: Security deposit (months of rent) | B25: 2 | C25: Months of rent held as a security deposit. It is set in your commercial lease, so check the terms before you sign
A26: Monthly utilities (electricity, water, gas) | B26: 2000 | C26: Electricity, water and gas for a kitchen with a griddle, fryer and oven, plus the draft beer cooler and the back-bar refrigeration. Ask the landlord or the last tenant for the utility history ahead of signing
A27: Insurance (per year) | B27: 12000 | C27: Annual premium for general liability + liquor liability (dram shop) + property insurance, entered as one figure. Landlords and lenders ask for proof of coverage ahead of opening
A28: Miscellaneous and contingency as % of sales | B28: 0.01 | C28: Cushion for unbudgeted running costs. It is a VARIABLE cost: it rises and falls with sales, so it does not belong among the fixed costs
A29: FINANCING
A30: Owner's equity contributed | B30: 120000 | C30: Cash you and your partners put in. Lenders usually expect an owner equity injection (often around 10% for SBA start-ups; many want 20-30%). Check the equity share of your plan against what your lender asks for
A31: Loan requested | B31: 369000 | C31: Principal you request from your lender, for example an SBA 7(a) loan through a bank. The "Financing" tab checks that sources and uses match the cash need calculated on "Startup Costs", and has a cell that calculates the exact amount that balances them
A32: Nominal annual interest rate (not APR) | B32: 0.1 | C32: Nominal annual rate, not APR; get offers from two lenders, including an SBA-guaranteed loan, before you fix it
A33: Loan term (years) | B33: 10 | C33: Total years, interest-only period included
A34: Interest-only period (years) | B34: 0 | C34: Years you pay interest only, before principal repayment begins. A year of interest only can ease the tightest cash period (build-out and the first weeks of trading); ask your lender whether it offers it
A35: Working capital (months of fixed costs) | B35: 3 | C35: The minimum this workbook requires (see "Instructions"): a cushion of less than 3 months will not cover a slow season
A36: TAXES
A37: Effective income tax rate (years 1-2) | B37: 0.25 | C37: Example: 21% federal rate for a C corporation plus state tax, rounded to 25%. If you operate as a sole proprietorship, LLC taxed as a pass-through or S corporation, the business itself pays 0% here and you pay tax on the profit personally: set this to 0 and budget for your personal tax separately. The model applies this rate to the first two years with positive taxable income
A38: Effective income tax rate (from year 3) | B38: 0.25 | C38: From the third year with positive taxable income. Same example rate (21% federal C corporation + state). Confirm the rate that applies to you with your accountant and change it here
A39: Sales tax rate on sales | B39: 0.08 | C39: Example rate: state + local sales tax combined. It varies widely by state and city: look up yours. UK: 20% VAT on hot food and dine-in
A40: Sales tax rate on alcohol to go | B40: 0.08 | C40: Same example rate as above. Some states add separate liquor taxes: include them here if they apply to you. Alcohol served on site has its own rate in the sales tax breakdown block, further down. Utilities, equipment and services are handled in the cell below
A41: Recoverable input tax on purchases and capex | B41: 0 | C41: In the US, the sales tax you pay on purchases is a cost, not a credit: leave this at 0%. UK: 20% if you are VAT-registered
A42: Net operating losses carried forward | B42: 0 | C42: Net operating losses from earlier years still to be offset at the start. Federal rules let you offset up to 80% of taxable income in a year; the model offsets 100% as a simplification
A43: DEPRECIATION
A44: Useful life of build-out and fixtures (years) | B44: 10 | C44: Build-out, installations, ventilation and decor of a bar with a commercial kitchen, including the draft beer system. Straight-line depreciation for the books; tax depreciation (MACRS, Section 179) can differ, so ask your CPA
A45: Useful life of machinery, furniture and equipment (years) | B45: 7 | C45: Griddle, fryer, oven, refrigeration, the bar build and furniture. Straight-line depreciation over the useful life you enter; tax depreciation (MACRS, Section 179) can differ, so confirm it with your CPA
A47: GROWTH AND COST INFLATION
A48: Annual increase in fixed costs | B48: 0 | C48: SET TO ZERO: all three columns are in year-1 prices (real terms). Raise it if you want to project in nominal terms
A49: RAMP-UP AND CAPACITY
A50: Implied seat turns per day (calculated) | B50: =IFERROR($B$4/$B$51,"") -> 1.5833333 | C50: =IFERROR("That is "&TEXT(INT(ROUND(B50,1)),"0")&"."&TEXT(ROUND(MOD(ROUND(B50,1),1)*10,0),"0")&" seat turns per day on the "&TEXT($B$51,"0")&" seats in the cell below. Compare it with the ceiling on seat turns typed in ""Break-Even"" and with the turns your opening hours and your room really allow before you rely on either figure.","") -> That is 1.6 seat turns per day on the 60 seats in the cell below. Compare it with the ceiling on seat turns typed in "Break-Even" and with the turns your opening hours and your room really allow before you rely on either figure.
A51: Seating capacity (seats at tables + bar) | B51: 60 | C51: TOTAL capacity of the space: dining room seats and bar stools; add patio seats only if they are open most of the year. Count it on your floor plan rather than copying the example: counting a year-round patio raises capacity and lowers the implied seat turns. Daily covers ÷ seats gives the implied seat turns in the row below
A52: Month-1 activity as a % of steady-state activity | B52: 0.55 | C52: A new business does not sell on day one what it sells six months later. The daily volume above is the year-1 AVERAGE: the ramp only spreads year 1's sales across the months (slower start, stronger finish) and keeps the annual total. At 100% there is no ramp
A53: Months to reach steady state | B53: 6 | C53: The ramp rises in a straight line from the percentage above to 100% over this number of months
A54: Months of rent BEFORE opening (build-out and permits) | B54: 2 | C54: You pay for the space from the day you sign. These months are a startup cost: they do NOT overlap the P&L, which starts on opening day. If your liquor license is likely to take longer than the build-out (often 3-12 months from signing), enter the months until it is issued, or negotiate a license contingency and rent abatement in the lease.
A55: Contingency on the BUILD-OUT lines of the space block (%) | B55: 0.1 | C55: Cushion on the build-out and fit-out line. A lender will not finance a renovation without it
A57: RECEIPTS, PAYMENTS AND SALES TAX BREAKDOWN
A58: Average collection days | B58: 1 | C58: At 1 day, card settlements reach your bank the next business day. Raise it if you work with reservation or delivery platforms, which usually pay out between the next day and 30 days later
A59: Average days to pay suppliers | B59: 14 | C59: What your suppliers finance for you. It is the first thing you lose if you fall behind on a payment
A60: Month of extra pay period 1 (only if pay periods > 12) | B60: 7 | C60: Month of the year (1-12) when the first extra pay period is paid out. Only used if pay periods > 12
A61: Month of extra pay period 2 (only if pay periods > 12) | B61: 12 | C61: Month of the year (1-12) when the second extra pay period is paid out. Only used if pay periods > 12
A62: ALCOHOLIC beverages as a share of total beverage sales | B62: 0.9 | C62: Share of beverage sales that is alcohol. The beverage line of this plan is cocktails, beer and wine, so a neighborhood bar sells mostly alcohol; the rest (soft drinks, water, coffee, non-alcoholic drinks) can be taxed differently. It works together with the sales tax rows for alcohol below
A63: Sales tax rate on alcohol served on site | B63: 0.08 | C63: Same example rate as the rest of on-site sales (8%: state + local). Some states add a tax on drinks served on premises; e.g. Texas: 8.25% mixed beverage sales tax (paid by the customer) + 6.7% gross receipts tax (paid by the bar): put the first here and add 6.7% × your alcohol share (about 6 points at 90%) to your beverage cost %. The workbook applies this rate only to the ALCOHOLIC part of beverage sales
A64: CONTROL THRESHOLDS AND FLOORS
A65: DSCR limit (minimum acceptable) | B65: 1.15 | C65: Below 1.0 the business does not generate enough to repay the loan. Lenders often write a minimum DSCR into the loan covenants: ask yours. Kit default: 1.15×
A66: DSCR target (green) | B66: 1.25 | C66: What lenders commonly look for before approving a loan comfortably. Kit default: 1.25× (editable estimate)
A67: Minimum cushion above break-even | B67: 0.15 | C67: How far planned sales must sit above cash break-even (fixed costs and the loan payment). The drop you can absorb is somewhat smaller: with a 15% cushion, about 13% of plan
A68: State / local minimum wage, annual full-time | C68: Your STATE or LOCAL minimum wage can be higher than the federal one: enter it here as an annual full-time figure (hourly rate × 2,080 hours). The higher of the two applies. Leave it empty or at 0 and the traffic light compares only against the federal minimum

Sheet Startup Costs
A1: BAR BUSINESS PLAN: NEIGHBORHOOD BAR WITH SMALL PLATES
A2: Estimated Startup Costs — US kit example (2026)
A3: US kit example (2026) — replace with your own quotes.
A5: Item | B5: Amount | C5: % of startup costs | D5: Notes | E5: Taxable / recoverable tax?
A6: STARTUP COSTS | B6: =IFERROR(IF(COUNT(B7:B27)=0,"",SUM(B7:B27)),"") -> 361700 | C6: =IFERROR(B6/$B$30,"") -> 0.73977598
A7: LLC formation + legal | B7: 2500 | C7: =IFERROR(B7/$B$30,"") -> 0.0051131876 | D7: Articles of organization (state filing fee), registered agent and attorney time for the operating agreement. Fees vary by state | E7: No
A8: Liquor license + local permits (non-quota state example) | B8: 15000 | C8: =IFERROR(B8/$B$30,"") -> 0.030679125 | D8: Beer & wine licenses start around $3,000; full liquor runs $12,000-$400,000. In quota states you buy an existing license at market price, which costs far more; this row is an example for a state WITHOUT a quota. A license bought from another owner is an intangible asset: ask your CPA. Apply right after signing the lease: it often takes 3-12 months. Most states also charge an annual or biennial renewal fee: add it to your fixed costs | E8: No
A9: Architect, MEP drawings + permit fees | B9: 15000 | C9: =IFERROR(B9/$B$30,"") -> 0.030679125 | D9: Architect and MEP drawings plus permit fees, required with a commercial kitchen | E9: Yes
A10: Build-out (second-generation space) | B10: 70000 | C10: =IFERROR(B10/$B$30,"") -> 0.14316925 | D10: Flooring, paint, an accessible restroom (ADA) and the work to adapt a second-generation space | E10: Yes
A11: Electrical + HVAC | B11: 22000 | C11: =IFERROR(B11/$B$30,"") -> 0.044996051 | D11: Electrical service sized for the kitchen and the back bar, plus heating and air conditioning | E11: Yes
A12: Plumbing, grease interceptor + Type I hood | B12: 28000 | C12: =IFERROR(B12/$B$30,"") -> 0.057267701 | D12: Type I hood, exhaust, grease interceptor and plumbing | E12: Yes
A13: Kitchen equipment (griddle, fryer, oven) | B13: 20000 | C13: =IFERROR(B13/$B$30,"") -> 0.040905501 | D13: Commercial griddle, fryer, convection oven and broiler for the small-plates menu | E13: Yes
A14: Refrigeration (walk-in + back-bar coolers) | B14: 18000 | C14: =IFERROR(B14/$B$30,"") -> 0.03681495 | D14: Walk-in cooler plus under-bar and back-bar refrigerators for beer, wine and mixers | E14: Yes
A15: Bar build (bar top + underbar stations) | B15: 35000 | C15: =IFERROR(B15/$B$30,"") -> 0.071584626 | D15: Bar top and underbar stations (ice well, sinks, speed rails), plus a display case for small plates and the draft taps | E15: Yes
A16: Draft beer system + installation | B16: 14000 | C16: =IFERROR(B16/$B$30,"") -> 0.02863385 | D16: Taps, draft lines, keg cooler, kegs and CO2, plus installation | E16: Yes
A17: Furniture (tables, high-tops + bar stools) | B17: 15000 | C17: =IFERROR(B17/$B$30,"") -> 0.030679125 | D17: High-tops, tables and bar stools for the dining room and bar | E17: Yes
A18: Patio (furniture + awning) | B18: 6000 | C18: =IFERROR(B18/$B$30,"") -> 0.01227165 | D18: Tables, chairs and an awning for the patio, if your permit allows it | E18: Yes
... A24: POS + handhelds + software | B24: 5000 | C24: =IFERROR(B24/$B$30,"") -> 0.010226375 | D24: Countertop POS at the bar, wireless handheld POS and management software | E24: Yes
A25: Security deposit | B25: =IFERROR(IF('0. Assumptions'!$B$24="","",'0. Assumptions'!$B$24*'0. Assumptions'!$B$25),"") -> 13000 | C25: =IFERROR(B25/$B$30,"") -> 0.026588575 | D25: =IFERROR(""&TEXT('0. Assumptions'!$B$25,"0")&IF('0. Assumptions'!$B$25=1," month"," months")&" of rent, from ""0. Assumptions"". Refundable when the lease ends: it is not depreciated and carries no tax","") -> 2 months of rent, from "0. Assumptions". Refundable when the lease ends: it is not depreciated and carries no tax | E25: No
A26: Rent paid before opening | B26: =IFERROR(IF('0. Assumptions'!$B$24="","",'0. Assumptions'!$B$24*'0. Assumptions'!$B$54),"") -> 13000 | C26: =IFERROR(B26/$B$30,"") -> 0.026588575 | D26: =IFERROR("Rent "&IF('0. Assumptions'!$B$54=1,"for the month","for the "&TEXT('0. Assumptions'!$B$54,"0")&" months")&" of build-out and permits before opening. It does not overlap the P&L, which starts on opening day: its twelve months are twelve trading months","") -> Rent for the 2 months of build-out and permits before opening. It does not overlap the P&L, which starts on opening day: its twelve months are twelve trading months | E26: Yes
A27: Build-out and setup contingency | B27: =IFERROR(IF(COUNT(B9,B10,B11,B12,B16,B20,B21)=0,"",ROUND((B9+B10+B11+B12+B16+B20+B21)*'0. Assumptions'!$B$55,0)),"") -> 17200 | C27: =IFERROR(B27/$B$30,"") -> 0.03517873 | D27: =IFERROR("At "&TEXT('0. Assumptions'!$B$55,"0%")&" of the BUILD-OUT items of this block (architect and MEP drawings, build-out, electrical and HVAC, plumbing, grease interceptor and hood, draft beer system, decor and lighting, signage), not of the whole block: the other items are left "&"out. No lender funds a build-out without a cushion: the percentage is in ""0. Assumptions""","") -> At 10% of the BUILD-OUT items of this block (architect and MEP drawings, build-out, electrical and HVAC, plumbing, grease interceptor and hood, draft beer system, decor and lighting, signage), not of the whole block: the other items are left out. No lender funds a build-out without a cushion: the percentage is in "0. Assumptions" | E27: Yes
A28: WORKING CAPITAL | B28: =IFERROR(IF(B29="","",B29),"") -> 127231.8 | C28: =IFERROR(B28/$B$30,"") -> 0.26022402
A29: Operating cushion until break-even | B29: =IFERROR(IF('0. Assumptions'!$B$35*('3-Year P&L'!$B$37-'3-Year P&L'!$B$35)=0,"",'0. Assumptions'!$B$35*('3-Year P&L'!$B$37-'3-Year P&L'!$B$35)/12),"") -> 127231.8 | C29: =IFERROR(B29/$B$30,"") -> 0.26022402 | D29: =IFERROR("Covers "&TEXT('0. Assumptions'!$B$35,"0")&IF('0. Assumptions'!$B$35=1," month"," months")&" of year-1 CASH fixed costs (the P&L fixed costs minus depreciation, which is not paid out), the minimum the Instructions of this workbook ask for","") -> Covers 3 months of year-1 CASH fixed costs (the P&L fixed costs minus depreciation, which is not paid out), the minimum the Instructions of this workbook ask for | E29: No
A30: TOTAL STARTUP COSTS (sum of the blocks) | B30: =IFERROR(B6+B28,"") -> 488931.8 | D30: =IFERROR("The percentages in column C are read on this figure, which includes the working capital ("&TEXT(C28,"0%")&" of the total). To compare the breakdown with another plan, use the CAPEX row below.","") -> The percentages in column C are read on this figure, which includes the working capital (26% of the total). To compare the breakdown with another plan, use the CAPEX row below.
A31: CAPEX (startup costs excluding working capital) | B31: =IFERROR(B30-B28,"") -> 361700 | D31: What you buy: build-out, equipment, launch and formation costs. The cash cushion is not an investment: it is working capital
A32: Recoverable input tax on capex | B32: =IFERROR(IF(B30="","",SUMIF($E$7:$E$27,"Yes",$B$7:$B$27)*'0. Assumptions'!$B$41),"") -> 0 | D32: =IFERROR("At "&TEXT('0. Assumptions'!$B$41,"0%")&" on the items marked ""Yes"" in the tax column. US: the sales tax you pay on equipment is part of its cost and is not recovered, so this rate is 0. UK (VAT-registered): 20%, reclaimed on your VAT return, but you pay it first, so the loan has to cover it","") -> At 0% on the items marked "Yes" in the tax column. US: the sales tax you pay on equipment is part of its cost and is not recovered, so this rate is 0. UK (VAT-registered): 20%, reclaimed on your VAT return, but you pay it first, so the loan has to cover it
A33: TOTAL CASH NEEDED AT LAUNCH | B33: =IFERROR(B30+B32,"") -> 488931.8 | D33: This is the figure the Financing tab has to cover
A34: DEPRECIATION BASES (not added to startup costs)
A35: Build-out, fixtures and setup | B35: =IFERROR(IF(B9="","",B9+B10+B11+B12+B16+B20+B21+B27),"") -> 189200 | D35: =IFERROR("Depreciated over "&TEXT('0. Assumptions'!$B$44,"0")&" years","") -> Depreciated over 10 years
A36: Machinery, furniture and equipment | B36: =IFERROR(IF(B13="","",B13+B14+B15+B17+B18+B19+B24),"") -> 107000 | D36: =IFERROR("Depreciated over "&TEXT('0. Assumptions'!$B$45,"0")&" years","") -> Depreciated over 7 years
A37: Annual depreciation of fixed assets | B37: =IFERROR(B35/MAX(1,'0. Assumptions'!$B$44)+B36/MAX(1,'0. Assumptions'!$B$45),"") -> 34205.714 | D37: =IFERROR("Not depreciated, because they are not fixed assets: LLC formation and legal, liquor license and local permits (a license bought from another owner is an intangible asset: ask your CPA), launch marketing, opening inventory, security "&"deposit, pre-opening rent and the working capital reserve. They add up to "&TEXT(B30-B35-B36,"#,##0")&" of the "&TEXT(B30,"#,##0")&" total investment.","") -> Not depreciated, because they are not fixed assets: LLC formation and legal, liquor license and local permits (a license bought from another owner is an intangible asset: ask your CPA), launch marketing, opening inventory, security deposit, pre-opening rent and the working capital reserve. They add up to 192732 of the 488932 total investment.

Sheet 3-Year P&L
A1: PRO FORMA P&L — 3 YEARS
A2: Base case — neighborhood bar with small plates, 60 seats
A4: Item | B4: Year 1 | C4: Year 2 | D4: Year 3 | E4: % of sales (year 1) | F4: Notes | G4: Sales tax rate on the line (%)
A5: REVENUE
A6: Covers per day (average) | B6: =IFERROR(IF('0. Assumptions'!$B$4="","",'0. Assumptions'!$B$4),"") -> 95 | C6: =IFERROR(B6*(1+'0. Assumptions'!$B$7),"") -> 109.25 | D6: =IFERROR(C6*(1+'0. Assumptions'!$B$8),"") -> 120.175 | F6: Growth for years 2 and 3 is set in "0. Assumptions"
A7: Average check (excl. sales tax) | B7: =IFERROR(IF('0. Assumptions'!$B$5="","",'0. Assumptions'!$B$5),"") -> 27 | C7: =IFERROR(IF(B7="","",B7),"") -> 27 | D7: =IFERROR(IF(C7="","",C7),"") -> 27 | F7: Held constant at year-1 prices: a price increase is a separate decision
A8: Operating days per year | B8: =IFERROR(IF('0. Assumptions'!$B$6="","",'0. Assumptions'!$B$6),"") -> 360 | C8: =IFERROR(IF(B8="","",B8),"") -> 360 | D8: =IFERROR(IF(C8="","",C8),"") -> 360
A9: TOTAL REVENUE (excl. sales tax) | B9: =IFERROR(IF(B6*B7*B8=0,"",B6*B7*B8),"") -> 923400 | C9: =IFERROR(IF(C6*C7*C8=0,"",C6*C7*C8),"") -> 1061910 | D9: =IFERROR(IF(D6*D7*D8=0,"",D6*D7*D8),"") -> 1168101 | E9: =IFERROR(IF(B9="","",1),"") -> 1
A10: Food sales (small plates) | B10: =IFERROR(IF(B9="","",B9*$E$10),"") -> 323190 | C10: =IFERROR(IF(C9="","",C9*$E$10),"") -> 371668.5 | D10: =IFERROR(IF(D9="","",D9*$E$10),"") -> 408835.35 | E10: =IFERROR(IF('0. Assumptions'!$B$11="","",'0. Assumptions'!$B$11),"") -> 0.35 | F10: Small plates sold at the bar and at tables, plus events, catering and take-out | G10: =IFERROR(IF(B9="","",'0. Assumptions'!$B$39),"") -> 0.08
A11: Beverage sales (cocktails, beer, wine + non-alcoholic) | B11: =IFERROR(IF(B9="","",B9*$E$11),"") -> 600210 | C11: =IFERROR(IF(C9="","",C9*$E$11),"") -> 690241.5 | D11: =IFERROR(IF(D9="","",D9*$E$11),"") -> 759265.65 | E11: =IFERROR(IF('0. Assumptions'!$B$12="","",'0. Assumptions'!$B$12),"") -> 0.65 | F11: Draft beer, wine and cocktails and spirits (a higher cost per drink because of preparation: see the pour cost range in the benchmarks on "Instructions"), plus non-alcoholic drinks | G11: =IFERROR(IF(B9="","",('0. Assumptions'!$B$62*((1-'0. Assumptions'!$B$16)*'0. Assumptions'!$B$63+'0. Assumptions'!$B$16*'0. Assumptions'!$B$40)+(1-'0. Assumptions'!$B$62)*'0. Assumptions'!$B$39)),"") -> 0.08
A12: VARIABLE COSTS
A13: Cost of goods sold — food | B13: =IFERROR(IF(B9="","",B9*'0. Assumptions'!$B$11*'0. Assumptions'!$B$13),"") -> 96957 | C13: =IFERROR(IF(C9="","",C9*'0. Assumptions'!$B$11*'0. Assumptions'!$B$13),"") -> 111500.55 | D13: =IFERROR(IF(D9="","",D9*'0. Assumptions'!$B$11*'0. Assumptions'!$B$13),"") -> 122650.6 | E13: =IFERROR(B13/$B$9,"") -> 0.105 | F13: =IFERROR("At "&TEXT('0. Assumptions'!$B$13,"0%")&" of FOOD sales, not of total sales: beverages have their own line","") -> At 30% of FOOD sales, not of total sales: beverages have their own line | G13: =IFERROR(IF(B9="","",'0. Assumptions'!$B$41),"") -> 0
A14: Cost of goods sold — beverage | B14: =IFERROR(IF(B9="","",B9*'0. Assumptions'!$B$12*'0. Assumptions'!$B$14),"") -> 132046.2 | C14: =IFERROR(IF(C9="","",C9*'0. Assumptions'!$B$12*'0. Assumptions'!$B$14),"") -> 151853.13 | D14: =IFERROR(IF(D9="","",D9*'0. Assumptions'!$B$12*'0. Assumptions'!$B$14),"") -> 167038.44 | E14: =IFERROR(B14/$B$9,"") -> 0.143 | F14: =IFERROR("At "&TEXT('0. Assumptions'!$B$14,"0%")&" of BEVERAGE sales","") -> At 22% of BEVERAGE sales | G14: =IFERROR(IF(B9="","",'0. Assumptions'!$B$41),"") -> 0
A15: Disposables and packaging | B15: =IFERROR(IF(B9="","",B9*'0. Assumptions'!$B$15),"") -> 9234 | C15: =IFERROR(IF(C9="","",C9*'0. Assumptions'!$B$15),"") -> 10619.1 | D15: =IFERROR(IF(D9="","",D9*'0. Assumptions'!$B$15),"") -> 11681.01 | E15: =IFERROR(B15/$B$9,"") -> 0.01 | G15: =IFERROR(IF(B9="","",'0. Assumptions'!$B$41),"") -> 0
A16: Delivery platform fees | B16: =IFERROR(IF(B9="","",B9*'0. Assumptions'!$B$16*'0. Assumptions'!$B$17),"") -> 0 | C16: =IFERROR(IF(C9="","",C9*'0. Assumptions'!$B$16*'0. Assumptions'!$B$17),"") -> 0 | D16: =IFERROR(IF(D9="","",D9*'0. Assumptions'!$B$16*'0. Assumptions'!$B$17),"") -> 0 | E16: =IFERROR(B16/$B$9,"") -> 0 | F16: Applied to the sales of THAT CHANNEL. With 0% delivery in Assumptions, this line is zero | G16: =IFERROR(IF(B9="","",'0. Assumptions'!$B$41),"") -> 0
A17: Card processing fees | B17: =IFERROR(IF(B9="","",B9*'0. Assumptions'!$B$18),"") -> 32319 | C17: =IFERROR(IF(C9="","",C9*'0. Assumptions'!$B$18),"") -> 37166.85 | D17: =IFERROR(IF(D9="","",D9*'0. Assumptions'!$B$18),"") -> 40883.535 | E17: =IFERROR(B17/$B$9,"") -> 0.035 | F17: Card processing fees are not subject to sales tax: no tax is recovered or deducted for them | G17: 0
A18: Miscellaneous and contingency | B18: =IFERROR(IF(B9="","",B9*'0. Assumptions'!$B$28),"") -> 9234 | C18: =IFERROR(IF(C9="","",C9*'0. Assumptions'!$B$28),"") -> 10619.1 | D18: =IFERROR(IF(D9="","",D9*'0. Assumptions'!$B$28),"") -> 11681.01 | E18: =IFERROR(B18/$B$9,"") -> 0.01 | F18: =IFERROR("At "&TEXT('0. Assumptions'!$B$28,"0%")&" of sales. It is a VARIABLE cost: it moves with revenue, so it cannot sit in fixed costs","") -> At 1% of sales. It is a VARIABLE cost: it moves with revenue, so it cannot sit in fixed costs | G18: =IFERROR(IF(B9="","",'0. Assumptions'!$B$41),"") -> 0
A19: TOTAL VARIABLE COSTS | B19: =IFERROR(IF(B9="","",SUM(B13:B18)),"") -> 279790.2 | C19: =IFERROR(IF(C9="","",SUM(C13:C18)),"") -> 321758.73 | D19: =IFERROR(IF(D9="","",SUM(D13:D18)),"") -> 353934.6 | E19: =IFERROR(B19/$B$9,"") -> 0.303
A20: GROSS MARGIN | B20: =IFERROR(IF(B9="","",B9-B19),"") -> 643609.8 | C20: =IFERROR(IF(C9="","",C9-C19),"") -> 740151.27 | D20: =IFERROR(IF(D9="","",D9-D19),"") -> 814166.4 | E20: =IFERROR(B20/$B$9,"") -> 0.697
A21: FIXED COSTS
A22: Rent | B22: =IFERROR(IF(B9="","",'0. Assumptions'!$B$24*12),"") -> 78000 | C22: =IFERROR(IF(C9="","",B22*(1+'0. Assumptions'!$B$48)),"") -> 78000 | D22: =IFERROR(IF(D9="","",C22*(1+'0. Assumptions'!$B$48)),"") -> 78000 | E22: =IFERROR(B22/$B$9,"") -> 0.084470435 | F22: The monthly amount is on the "0. Assumptions" tab; here it is multiplied by twelve. Rent for the build-out months, which comes before opening, is on the Startup Costs tab and is NOT counted twice | G22: =IFERROR(IF(B9="","",'0. Assumptions'!$B$41),"") -> 0
A23: Labor (wages + employer payroll taxes) | B23: =IFERROR(IF(B9="","",Staffing!$G$12),"") -> 308827.2 | C23: =IFERROR(IF(C9="","",Staffing!$B$16),"") -> 314827.2 | D23: =IFERROR(IF(D9="","",Staffing!$B$17),"") -> 320827.2 | E23: =IFERROR(B23/$B$9,"") -> 0.33444574 | F23: Comes from the Staffing tab: it is the SAME number, not a separate estimate. Years 2 and 3 add the new hires declared on that tab, not a percentage of volume | G23: 0
A24: Utilities (electricity, water, gas) | B24: =IFERROR(IF(B9="","",'0. Assumptions'!$B$26*12),"") -> 24000 | C24: =IFERROR(IF(C9="","",B24*(1+'0. Assumptions'!$B$48)),"") -> 24000 | D24: =IFERROR(IF(D9="","",C24*(1+'0. Assumptions'!$B$48)),"") -> 24000 | E24: =IFERROR(B24/$B$9,"") -> 0.025990903 | F24: Enter the monthly bills excl. sales tax. The workbook applies a single tax treatment to this whole line, the one in the column next to it; if one utility is taxed differently in your area, give it its own line | G24: =IFERROR(IF(B9="","",'0. Assumptions'!$B$41),"") -> 0
A25: Insurance (general + liquor liability + property) | B25: =IFERROR(IF(B9="","",'0. Assumptions'!$B$27),"") -> 12000 | C25: =IFERROR(IF(C9="","",B25*(1+'0. Assumptions'!$B$48)),"") -> 12000 | D25: =IFERROR(IF(D9="","",C25*(1+'0. Assumptions'!$B$48)),"") -> 12000 | E25: =IFERROR(B25/$B$9,"") -> 0.012995452 | F25: Insurance premiums are not subject to sales tax: there is no recoverable tax on them | G25: 0
A26: Accounting + bookkeeping | B26: 6000 | C26: =IFERROR(IF(C9="","",B26*(1+'0. Assumptions'!$B$48)),"") -> 6000 | D26: =IFERROR(IF(D9="","",C26*(1+'0. Assumptions'!$B$48)),"") -> 6000 | E26: =IFERROR(B26/$B$9,"") -> 0.0064977258 | G26: =IFERROR(IF(B9="","",'0. Assumptions'!$B$41),"") -> 0
A27: Equipment maintenance | B27: 8000 | C27: =IFERROR(IF(C9="","",B27*(1+'0. Assumptions'!$B$48)),"") -> 8000 | D27: =IFERROR(IF(D9="","",C27*(1+'0. Assumptions'!$B$48)),"") -> 8000 | E27: =IFERROR(B27/$B$9,"") -> 0.0086636344 | G27: =IFERROR(IF(B9="","",'0. Assumptions'!$B$41),"") -> 0
A28: Marketing and advertising | B28: 15000 | C28: =IFERROR(IF(C9="","",B28*(1+'0. Assumptions'!$B$48)),"") -> 15000 | D28: =IFERROR(IF(D9="","",C28*(1+'0. Assumptions'!$B$48)),"") -> 15000 | E28: =IFERROR(B28/$B$9,"") -> 0.016244314 | G28: =IFERROR(IF(B9="","",'0. Assumptions'!$B$41),"") -> 0
A29: Software (POS, reservations, inventory) | B29: 4800 | C29: =IFERROR(IF(C9="","",B29*(1+'0. Assumptions'!$B$48)),"") -> 4800 | D29: =IFERROR(IF(D9="","",C29*(1+'0. Assumptions'!$B$48)),"") -> 4800 | E29: =IFERROR(B29/$B$9,"") -> 0.0051981806 | G29: =IFERROR(IF(B9="","",'0. Assumptions'!$B$41),"") -> 0
A30: Cleaning supplies + linens | B30: 7200 | C30: =IFERROR(IF(C9="","",B30*(1+'0. Assumptions'!$B$48)),"") -> 7200 | D30: =IFERROR(IF(D9="","",C30*(1+'0. Assumptions'!$B$48)),"") -> 7200 | E30: =IFERROR(B30/$B$9,"") -> 0.007797271 | G30: =IFERROR(IF(B9="","",'0. Assumptions'!$B$41),"") -> 0
A31: Waste + grease hauling (trash, recycling, used oil) | B31: 3000 | C31: =IFERROR(IF(C9="","",B31*(1+'0. Assumptions'!$B$48)),"") -> 3000 | D31: =IFERROR(IF(D9="","",C31*(1+'0. Assumptions'!$B$48)),"") -> 3000 | E31: =IFERROR(B31/$B$9,"") -> 0.0032488629 | F31: Licensed waste / grease hauler; the opening checklist asks for it ahead of opening. With a griddle and fryer running, a bar with a kitchen produces more used oil than a coffee shop, so get a quote for your area | G31: =IFERROR(IF(B9="","",'0. Assumptions'!$B$41),"") -> 0
A32: Pest control | B32: 1200 | C32: =IFERROR(IF(C9="","",B32*(1+'0. Assumptions'!$B$48)),"") -> 1200 | D32: =IFERROR(IF(D9="","",C32*(1+'0. Assumptions'!$B$48)),"") -> 1200 | E32: =IFERROR(B32/$B$9,"") -> 0.0012995452 | F32: Licensed pest control company. It is part of the HACCP-based food safety plan, alongside the allergen and food safety training that the opening checklist asks for in its staff phase | G32: =IFERROR(IF(B9="","",'0. Assumptions'!$B$41),"") -> 0
A33: Music licensing (ASCAP/BMI/SESAC) | B33: 3000 | C33: =IFERROR(IF(C9="","",B33*(1+'0. Assumptions'!$B$48)),"") -> 3000 | D33: =IFERROR(IF(D9="","",C33*(1+'0. Assumptions'!$B$48)),"") -> 3000 | E33: =IFERROR(B33/$B$9,"") -> 0.0032488629 | F33: Public-performance licenses from ASCAP, BMI and SESAC. They are separate from your local permits: budget for them if you play music in the bar or hire a DJ | G33: =IFERROR(IF(B9="","",'0. Assumptions'!$B$41),"") -> 0
A34: Safety + responsible-service training | B34: 1000 | C34: =IFERROR(IF(C9="","",B34*(1+'0. Assumptions'!$B$48)),"") -> 1000 | D34: =IFERROR(IF(D9="","",C34*(1+'0. Assumptions'!$B$48)),"") -> 1000 | E34: =IFERROR(B34/$B$9,"") -> 0.0010829543 | F34: Staff training in responsible beverage service (TIPS / ServSafe Alcohol) and in workplace safety. Check what your state or city requires for people who pour alcohol; it also supports your dram shop liability coverage | G34: =IFERROR(IF(B9="","",'0. Assumptions'!$B$41),"") -> 0
A35: Depreciation of fixed assets | B35: =IFERROR(IF(B9="","",'Startup Costs'!$B$37),"") -> 34205.714 | C35: =IFERROR(IF(C9="","",B35),"") -> 34205.714 | D35: =IFERROR(IF(D9="","",B35),"") -> 34205.714 | E35: =IFERROR(B35/$B$9,"") -> 0.037043225 | F35: Comes from the depreciation bases on the Startup Costs tab: real fixed assets only. It does NOT rise with inflation: it is a charge on the HISTORICAL cost of the assets | G35: 0
A36: Interest expense (loan interest) | B36: =IFERROR(IF(B9="","",Financing!$B$44),"") -> 36900 | C36: =IFERROR(IF(C9="","",Financing!$B$46),"") -> 34584.695 | D36: =IFERROR(IF(D9="","",Financing!$B$48),"") -> 32037.859 | E36: =IFERROR(B36/$B$9,"") -> 0.039961014 | F36: Only INTEREST is an expense. Principal repaid appears on the cash flow tab | G36: 0
A37: TOTAL FIXED COSTS | B37: =IFERROR(IF(B9="","",SUM(B22:B36)),"") -> 543132.91 | C37: =IFERROR(IF(C9="","",SUM(C22:C36)),"") -> 546817.61 | D37: =IFERROR(IF(D9="","",SUM(D22:D36)),"") -> 550270.77 | E37: =IFERROR(B37/$B$9,"") -> 0.58818812
A38: Recoverable input tax on variable costs | B38: =IFERROR(IF(B9="","",SUMPRODUCT(B13:B18,G13:G18)),"") -> 0 | C38: =IFERROR(IF(C9="","",SUMPRODUCT(C13:C18,G13:G18)),"") -> 0 | D38: =IFERROR(IF(D9="","",SUMPRODUCT(D13:D18,G13:G18)),"") -> 0 | F38: Each line at ITS OWN rate, read from the column next to it. It is what the cash flow tab overpays to suppliers and later deducts (zero wherever no tax is recoverable)
A39: Recoverable input tax on fixed costs | B39: =IFERROR(IF(B9="","",SUMPRODUCT(B22:B36,G22:G36)),"") -> 0 | C39: =IFERROR(IF(C9="","",SUMPRODUCT(C22:C36,G22:G36)),"") -> 0 | D39: =IFERROR(IF(D9="","",SUMPRODUCT(D22:D36,G22:G36)),"") -> 0
A40: PRE-TAX INCOME (EBT) | B40: =IFERROR(IF(B9="","",B20-B37),"") -> 100476.89 | C40: =IFERROR(IF(C9="","",C20-C37),"") -> 193333.66 | D40: =IFERROR(IF(D9="","",D20-D37),"") -> 263895.62 | E40: =IFERROR(B40/$B$9,"") -> 0.10881188
A41: Net operating losses carried forward (opening) | B41: =IFERROR(IF(B9="","",'0. Assumptions'!$B$42),"") -> 0 | C41: =IFERROR(IF(C9="","",B46),"") -> 0 | D41: =IFERROR(IF(D9="","",C46),"") -> 0 | F41: Federal rules let a year's losses offset the profits of later years (the federal limit is 80% of taxable income; this model offsets 100% as a simplification)
A42: Taxable income (after loss offset) | B42: =IFERROR(IF(B9="","",MAX(0,B40-B41)),"") -> 100476.89 | C42: =IFERROR(IF(C9="","",MAX(0,C40-C41)),"") -> 193333.66 | D42: =IFERROR(IF(D9="","",MAX(0,D40-D41)),"") -> 263895.62
A43: Years with positive taxable income (cumulative) | B43: =IFERROR(IF(B9="","",IF(B42>0,1,0)),"") -> 1 | C43: =IFERROR(IF(C9="","",B43+IF(C42>0,1,0)),"") -> 2 | D43: =IFERROR(IF(D9="","",C43+IF(D42>0,1,0)),"") -> 3
A44: Effective income tax rate applied | B44: =IFERROR(IF(B9="","",IF(B42<=0,"",IF(B43<=2,'0. Assumptions'!$B$37,'0. Assumptions'!$B$38))),"") -> 0.25 | C44: =IFERROR(IF(C9="","",IF(C42<=0,"",IF(C43<=2,'0. Assumptions'!$B$37,'0. Assumptions'!$B$38))),"") -> 0.25 | D44: =IFERROR(IF(D9="","",IF(D42<=0,"",IF(D43<=2,'0. Assumptions'!$B$37,'0. Assumptions'!$B$38))),"") -> 0.25 | F44: The "years 1-2" rate applies to the first two years with positive taxable income, not to the first two calendar years of the business. The model approximates this by counting the first two profitable years
A45: Income tax | B45: =IFERROR(IF(B9="","",IF(B44="",0,B42*B44)),"") -> 25119.221 | C45: =IFERROR(IF(C9="","",IF(C44="",0,C42*C44)),"") -> 48333.415 | D45: =IFERROR(IF(D9="","",IF(D44="",0,D42*D44)),"") -> 65973.906
A46: Net operating losses carried forward (closing) | B46: =IFERROR(IF(B9="","",MAX(0,B41-B40)),"") -> 0 | C46: =IFERROR(IF(C9="","",MAX(0,C41-C40)),"") -> 0 | D46: =IFERROR(IF(D9="","",MAX(0,D41-D40)),"") -> 0
A47: NET INCOME | B47: =IFERROR(IF(B9="","",B40-B45),"") -> 75357.664 | C47: =IFERROR(IF(C9="","",C40-C45),"") -> 145000.25 | D47: =IFERROR(IF(D9="","",D40-D45),"") -> 197921.72 | E47: =IFERROR(B47/$B$9,"") -> 0.081608907
A48: KEY RATIOS
A49: Ratio | B49: Year 1 | C49: Year 2 | D49: Year 3 | E49: Threshold | F49: Comment
A50: Gross margin / Sales | B50: =IFERROR(IF(B9="","",B20/B9),"") -> 0.697 | C50: =IFERROR(IF(C9="","",C20/C9),"") -> 0.697 | D50: =IFERROR(IF(D9="","",D20/D9),"") -> 0.697 | E50: 0.68 | F50: Floor set by this workbook (see "Instructions"): gross margin at or above 68% (kit benchmark, editable estimate)
A51: Cost of goods sold (food + beverage) | B51: =IFERROR(IF(B9="","",B13+B14),"") -> 229003.2 | C51: =IFERROR(IF(C9="","",C13+C14),"") -> 263353.68 | D51: =IFERROR(IF(D9="","",D13+D14),"") -> 289689.05
A52: Cost of goods sold / Sales | B52: =IFERROR(IF(B9="","",B51/B9),"") -> 0.248 | C52: =IFERROR(IF(C9="","",C51/C9),"") -> 0.248 | D52: =IFERROR(IF(D9="","",D51/D9),"") -> 0.248 | E52: 0.28 | F52: Ceiling set by this workbook: cost of goods sold at or below 28% of sales (kit benchmark, editable estimate), a blend of the food cost and pour cost ranges in the benchmarks on "Instructions"
A53: Labor cost / Sales | B53: =IFERROR(IF(B9="","",B23/B9),"") -> 0.33444574 | C53: =IFERROR(IF(C9="","",C23/C9),"") -> 0.29647258 | D53: =IFERROR(IF(D9="","",D23/D9),"") -> 0.27465707 | E53: 0.35 | F53: Ceiling set by this workbook (see "Instructions"): labor at or below 35% of sales (kit benchmark, editable estimate). It leaves room to pay a qualified kitchen lead full time. Tips are not modeled
A54: Rent / Sales | B54: =IFERROR(IF(B9="","",B22/B9),"") -> 0.084470435 | C54: =IFERROR(IF(C9="","",C22/C9),"") -> 0.073452552 | D54: =IFERROR(IF(D9="","",D22/D9),"") -> 0.066775048 | E54: 0.1 | F54: Ceiling set by this workbook (see "Instructions"): rent at or below 10% of sales (kit benchmark, editable estimate)
A55: Net income / Sales | B55: =IFERROR(IF(B9="","",B47/B9),"") -> 0.081608907 | C55: =IFERROR(IF(C9="","",C47/C9),"") -> 0.13654664 | D55: =IFERROR(IF(D9="","",D47/D9),"") -> 0.16943887 | E55: 0.05 | F55: Target set by this workbook (see "Instructions"): net income at or above 5% of sales (kit benchmark, editable estimate), after depreciation, interest and income tax
A56: Break-even reached | B56: =IFERROR(IF(B9="","",IF(B9>='Break-Even'!$B$16,"Yes","No")),"") -> Yes | C56: =IFERROR(IF(C9="","",IF(C9>='Break-Even'!$C$16,"Yes","No")),"") -> Yes | D56: =IFERROR(IF(D9="","",IF(D9>='Break-Even'!$D$16,"Yes","No")),"") -> Yes | F56: Compares each year's sales with that same year's threshold, which the Break-Even tab calculates with that year's fixed costs
A58: All figures are EXCL. SALES TAX. Years 2 and 3 are in year-1 prices unless you raise cost inflation in the "0. Assumptions" tab. The "Sales tax rate on the line (%)" column shows, on SALES lines, the rate collected on each one and, on COST lines, the rate paid on that item. The cash flow tab reads it: insurance and card fees carry no sales tax, and wages, depreciation and interest carry none either.

Sheet Break-Even
A1: BREAK-EVEN ANALYSIS
A2: Monthly and daily break-even — neighborhood bar with small plates
A4: Variable | B4: Year 1 | C4: Year 2 | D4: Year 3 | E4: Notes
A5: BASE DATA BY YEAR
A6: Annual fixed costs | B6: =IFERROR(IF('3-Year P&L'!$B$9="","",'3-Year P&L'!$B$37),"") -> 543132.91 | C6: =IFERROR(IF('3-Year P&L'!$C$9="","",'3-Year P&L'!$C$37),"") -> 546817.61 | D6: =IFERROR(IF('3-Year P&L'!$D$9="","",'3-Year P&L'!$D$37),"") -> 550270.77 | E6: The SAME fixed costs as the P&L. Each year has its own, which is why the threshold cannot be a single one for all three years
A7: Monthly fixed costs | B7: =IFERROR(IF('3-Year P&L'!$B$9="","",B6/12),"") -> 45261.076 | C7: =IFERROR(IF('3-Year P&L'!$C$9="","",C6/12),"") -> 45568.134 | D7: =IFERROR(IF('3-Year P&L'!$D$9="","",D6/12),"") -> 45855.898
A8: Average check (excl. sales tax) | B8: =IFERROR(IF('3-Year P&L'!$B$9="","",'3-Year P&L'!$B$7),"") -> 27 | C8: =IFERROR(IF('3-Year P&L'!$C$9="","",'3-Year P&L'!$C$7),"") -> 27 | D8: =IFERROR(IF('3-Year P&L'!$D$9="","",'3-Year P&L'!$D$7),"") -> 27
A9: Variable cost per cover | B9: =IFERROR(IF('3-Year P&L'!$B$9="","",'3-Year P&L'!$B$19/('3-Year P&L'!$B$6*'3-Year P&L'!$B$8)),"") -> 8.181 | C9: =IFERROR(IF('3-Year P&L'!$C$9="","",'3-Year P&L'!$C$19/('3-Year P&L'!$C$6*'3-Year P&L'!$C$8)),"") -> 8.181 | D9: =IFERROR(IF('3-Year P&L'!$D$9="","",'3-Year P&L'!$D$19/('3-Year P&L'!$D$6*'3-Year P&L'!$D$8)),"") -> 8.181 | E9: Comes from the P&L total variable costs, not from a separate estimate. It includes miscellaneous and contingency, which is a percentage of sales
A10: Contribution margin per cover | B10: =IFERROR(IF('3-Year P&L'!$B$9="","",B8-B9),"") -> 18.819 | C10: =IFERROR(IF('3-Year P&L'!$C$9="","",C8-C9),"") -> 18.819 | D10: =IFERROR(IF('3-Year P&L'!$D$9="","",D8-D9),"") -> 18.819 | E10: Average check minus unit variable cost
A11: Operating days per year | B11: =IFERROR(IF('3-Year P&L'!$B$9="","",'3-Year P&L'!$B$8),"") -> 360 | C11: =IFERROR(IF('3-Year P&L'!$C$9="","",'3-Year P&L'!$C$8),"") -> 360 | D11: =IFERROR(IF('3-Year P&L'!$D$9="","",'3-Year P&L'!$D$8),"") -> 360 | E11: The same calendar as the P&L and the scenarios
A12: Principal repaid in the year | B12: =IFERROR(IF('3-Year P&L'!$B$9="","",Financing!$B$45),"") -> 23153.051 | C12: =IFERROR(IF('3-Year P&L'!$C$9="","",Financing!$B$47),"") -> 25468.356 | D12: =IFERROR(IF('3-Year P&L'!$D$9="","",Financing!$B$49),"") -> 28015.191 | E12: Principal is NOT a P&L expense, but it leaves the cash account. Without it, the published break-even threshold would sit below the real one
A13: ACCOUNTING BREAK-EVEN (includes depreciation)
A14: Covers needed per year | B14: =IFERROR(IF('3-Year P&L'!$B$9="","",IF(B10<=0,"",B6/B10)),"") -> 28860.881 | C14: =IFERROR(IF('3-Year P&L'!$C$9="","",IF(C10<=0,"",C6/C10)),"") -> 29056.677 | D14: =IFERROR(IF('3-Year P&L'!$D$9="","",IF(D10<=0,"",D6/D10)),"") -> 29240.171
A15: Covers needed per day | B15: =IFERROR(IF('3-Year P&L'!$B$9="","",B14/B11),"") -> 80.169113 | C15: =IFERROR(IF('3-Year P&L'!$C$9="","",C14/C11),"") -> 80.712992 | D15: =IFERROR(IF('3-Year P&L'!$D$9="","",D14/D11),"") -> 81.222697
A16: Revenue needed per year | B16: =IFERROR(IF('3-Year P&L'!$B$9="","",B14*B8),"") -> 779243.78 | C16: =IFERROR(IF('3-Year P&L'!$C$9="","",C14*C8),"") -> 784530.29 | D16: =IFERROR(IF('3-Year P&L'!$D$9="","",D14*D8),"") -> 789484.61
A17: CASH BREAK-EVEN (loan payments in, depreciation out)
A18: Cash fixed costs + principal repaid for the year | B18: =IFERROR(IF('3-Year P&L'!$B$9="","",B6-'3-Year P&L'!$B$35+B12),"") -> 532080.25 | C18: =IFERROR(IF('3-Year P&L'!$C$9="","",C6-'3-Year P&L'!$C$35+C12),"") -> 538080.25 | D18: =IFERROR(IF('3-Year P&L'!$D$9="","",D6-'3-Year P&L'!$D$35+D12),"") -> 544080.25 | E18: The P&L fixed costs without depreciation (which is not paid in cash) and WITH principal repaid (which is). This is the threshold that decides whether cash holds up
A19: Covers needed per year (cash) | B19: =IFERROR(IF('3-Year P&L'!$B$9="","",IF(B10<=0,"",B18/B10)),"") -> 28273.567 | C19: =IFERROR(IF('3-Year P&L'!$C$9="","",IF(C10<=0,"",C18/C10)),"") -> 28592.393 | D19: =IFERROR(IF('3-Year P&L'!$D$9="","",IF(D10<=0,"",D18/D10)),"") -> 28911.22
A20: Covers needed per day (cash) | B20: =IFERROR(IF('3-Year P&L'!$B$9="","",B19/B11),"") -> 78.537685 | C20: =IFERROR(IF('3-Year P&L'!$C$9="","",C19/C11),"") -> 79.423315 | D20: =IFERROR(IF('3-Year P&L'!$D$9="","",D19/D11),"") -> 80.308945
A21: Revenue needed per year (cash) | B21: =IFERROR(IF('3-Year P&L'!$B$9="","",B19*B8),"") -> 763386.3 | C21: =IFERROR(IF('3-Year P&L'!$C$9="","",C19*C8),"") -> 771994.62 | D21: =IFERROR(IF('3-Year P&L'!$D$9="","",D19*D8),"") -> 780602.94
A22: COMPARISON WITH THE PLAN
A23: Covers per day forecast in the plan | B23: =IFERROR(IF('3-Year P&L'!$B$9="","",'3-Year P&L'!$B$6),"") -> 95 | C23: =IFERROR(IF('3-Year P&L'!$C$9="","",'3-Year P&L'!$C$6),"") -> 109.25 | D23: =IFERROR(IF('3-Year P&L'!$D$9="","",'3-Year P&L'!$D$6),"") -> 120.175
A24: Cushion above CASH break-even (%) | B24: =IFERROR(IF('3-Year P&L'!$B$9="","",B23/B20-1),"") -> 0.20961039 | C24: =IFERROR(IF('3-Year P&L'!$C$9="","",C23/C20-1),"") -> 0.37554067 | D24: =IFERROR(IF('3-Year P&L'!$D$9="","",D23/D20-1),"") -> 0.49640866 | E24: How far planned sales sit above cash break-even. The drop you can absorb before you cannot pay the fixed costs and the loan payment is somewhat smaller: with a 25% cushion, 20%. The required minimum is set in the "0. Assumptions" tab
A25: Maximum seat turns per day the space allows | B25: 3 | E25: Full table services per seat per day that your opening hours allow. It is the physical ceiling of the space, not a target
A26: Seat turns per day that the cash break-even requires | B26: =IFERROR(IF('3-Year P&L'!$B$9="","",B20/'0. Assumptions'!$B$51),"") -> 1.3089614 | C26: =IFERROR(IF('3-Year P&L'!$C$9="","",C20/'0. Assumptions'!$B$51),"") -> 1.3237219 | D26: =IFERROR(IF('3-Year P&L'!$D$9="","",D20/'0. Assumptions'!$B$51),"") -> 1.3384824 | E26: Break-even covers spread across the seats declared on the "0. Assumptions" tab. If it is above the ceiling in the row above, the break-even is out of reach for the space
A27: INTERPRETATION
A28: =IFERROR("With the average check excl. sales tax above, you need "&TEXT(ROUNDUP(B15,0),"0")&" covers a day over your "&TEXT(B11,"0")&" opening days to avoid losing money (accounting break-even, depreciation included), and "&TEXT(ROUNDUP(B20,0),"0")&" for cash to hold (cash break-even: depreciation out, because it is not paid, and the year's loan payment in"&IF(B12=0,"; no principal is repaid this year (interest-only period or no loan)","")&"). The ""Revenue needed per year"" rows show the same figures in your currency.","") -> With the average check excl. sales tax above, you need 81 covers a day over your 360 opening days to avoid losing money (accounting break-even, depreciation included), and 79 for cash to hold (cash break-even: depreciation out, because it is not paid, and the year's loan payment in). The "Revenue needed per year" rows show the same figures in your currency.
A30: BREAK-EVEN SENSITIVITY
A31: Covers per day needed to cover costs for each average check (columns) and each variable cost per cover (rows). Green cells are below the covers per day the plan forecasts.
A33: Covers per day needed: average check excl. sales tax (columns) × variable cost per cover (rows) | B33: =IFERROR($B$8-2,"") -> 25 | C33: =IFERROR(IF($B$8="","",$B$8),"") -> 27 | D33: =IFERROR($B$8+2,"") -> 29 | E33: =IFERROR($B$8+4,"") -> 31
A34: =IFERROR($B$9*0.85,"") -> 6.95385 | B34: =IFERROR(IF($B$33-$A34<=0,"",$B$6/($B$33-$A34)/$B$11),"") -> 83.60246 | C34: =IFERROR(IF($C$33-$A34<=0,"",$B$6/($C$33-$A34)/$B$11),"") -> 75.261461 | D34: =IFERROR(IF($D$33-$A34<=0,"",$B$6/($D$33-$A34)/$B$11),"") -> 68.433833 | E34: =IFERROR(IF($E$33-$A34<=0,"",$B$6/($E$33-$A34)/$B$11),"") -> 62.741958
A35: =IFERROR($B$9*0.925,"") -> 7.567425 | B35: =IFERROR(IF($B$33-$A35<=0,"",$B$6/($B$33-$A35)/$B$11),"") -> 86.545019 | C35: =IFERROR(IF($C$33-$A35<=0,"",$B$6/($C$33-$A35)/$B$11),"") -> 77.637809 | D35: =IFERROR(IF($D$33-$A35<=0,"",$B$6/($D$33-$A35)/$B$11),"") -> 70.392967 | E35: =IFERROR(IF($E$33-$A35<=0,"",$B$6/($E$33-$A35)/$B$11),"") -> 64.384838
A36: =IFERROR($B$9*1.0,"") -> 8.181 | B36: =IFERROR(IF($B$33-$A36<=0,"",$B$6/($B$33-$A36)/$B$11),"") -> 89.702274 | C36: =IFERROR(IF($C$33-$A36<=0,"",$B$6/($C$33-$A36)/$B$11),"") -> 80.169113 | D36: =IFERROR(IF($D$33-$A36<=0,"",$B$6/($D$33-$A36)/$B$11),"") -> 72.46758 | E36: =IFERROR(IF($E$33-$A36<=0,"",$B$6/($E$33-$A36)/$B$11),"") -> 66.116067
A37: =IFERROR($B$9*1.075,"") -> 8.794575 | B37: =IFERROR(IF($B$33-$A37<=0,"",$B$6/($B$33-$A37)/$B$11),"") -> 93.09861 | C37: =IFERROR(IF($C$33-$A37<=0,"",$B$6/($C$33-$A37)/$B$11),"") -> 82.871042 | D37: =IFERROR(IF($D$33-$A37<=0,"",$B$6/($D$33-$A37)/$B$11),"") -> 74.668191 | E37: =IFERROR(IF($E$33-$A37<=0,"",$B$6/($E$33-$A37)/$B$11),"") -> 67.942971
A38: =IFERROR($B$9*1.15,"") -> 9.40815 | B38: =IFERROR(IF($B$33-$A38<=0,"",$B$6/($B$33-$A38)/$B$11),"") -> 96.762253 | C38: =IFERROR(IF($C$33-$A38<=0,"",$B$6/($C$33-$A38)/$B$11),"") -> 85.761449 | D38: =IFERROR(IF($D$33-$A38<=0,"",$B$6/($D$33-$A38)/$B$11),"") -> 77.00664 | E38: =IFERROR(IF($E$33-$A38<=0,"",$B$6/($E$33-$A38)/$B$11),"") -> 69.873704

Sheet Scenarios
A1: SCENARIO ANALYSIS
A2: Pessimistic / Base / Optimistic — Year 1
A4: Metric | B4: Pessimistic | C4: Base | D4: Optimistic | E4: Notes
A5: Covers per day | B5: 71 | C5: =IFERROR(IF('3-Year P&L'!$B$6="","",'3-Year P&L'!$B$6),"") -> 95 | D5: 119
A6: Average check (excl. sales tax) | B6: 25 | C6: =IFERROR(IF('3-Year P&L'!$B$7="","",'3-Year P&L'!$B$7),"") -> 27 | D6: 29
A7: Operating days per year | B7: 340 | C7: =IFERROR(IF('3-Year P&L'!$B$8="","",'3-Year P&L'!$B$8),"") -> 360 | D7: 360
A8: ANNUAL REVENUE (excl. sales tax) | B8: =IFERROR(IF(B5*B6*B7=0,"",B5*B6*B7),"") -> 603500 | C8: =IFERROR(IF(C5*C6*C7=0,"",C5*C6*C7),"") -> 923400 | D8: =IFERROR(IF(D5*D6*D7=0,"",D5*D6*D7),"") -> 1242360
A9: Cost of goods sold — food | B9: =IFERROR(IF(B8="","",B8*'0. Assumptions'!$B$11*'0. Assumptions'!$B$13),"") -> 63367.5 | C9: =IFERROR(IF(C8="","",C8*'0. Assumptions'!$B$11*'0. Assumptions'!$B$13),"") -> 96957 | D9: =IFERROR(IF(D8="","",D8*'0. Assumptions'!$B$11*'0. Assumptions'!$B$13),"") -> 130447.8
A10: Cost of goods sold — beverage | B10: =IFERROR(IF(B8="","",B8*'0. Assumptions'!$B$12*'0. Assumptions'!$B$14),"") -> 86300.5 | C10: =IFERROR(IF(C8="","",C8*'0. Assumptions'!$B$12*'0. Assumptions'!$B$14),"") -> 132046.2 | D10: =IFERROR(IF(D8="","",D8*'0. Assumptions'!$B$12*'0. Assumptions'!$B$14),"") -> 177657.48
A11: Disposables and packaging | B11: =IFERROR(IF(B8="","",B8*'0. Assumptions'!$B$15),"") -> 6035 | C11: =IFERROR(IF(C8="","",C8*'0. Assumptions'!$B$15),"") -> 9234 | D11: =IFERROR(IF(D8="","",D8*'0. Assumptions'!$B$15),"") -> 12423.6
A12: Delivery platform fees | B12: =IFERROR(IF(B8="","",B8*'0. Assumptions'!$B$16*'0. Assumptions'!$B$17),"") -> 0 | C12: =IFERROR(IF(C8="","",C8*'0. Assumptions'!$B$16*'0. Assumptions'!$B$17),"") -> 0 | D12: =IFERROR(IF(D8="","",D8*'0. Assumptions'!$B$16*'0. Assumptions'!$B$17),"") -> 0
A13: Card processing fees | B13: =IFERROR(IF(B8="","",B8*'0. Assumptions'!$B$18),"") -> 21122.5 | C13: =IFERROR(IF(C8="","",C8*'0. Assumptions'!$B$18),"") -> 32319 | D13: =IFERROR(IF(D8="","",D8*'0. Assumptions'!$B$18),"") -> 43482.6
A14: Miscellaneous and contingency | B14: =IFERROR(IF(B8="","",B8*'0. Assumptions'!$B$28),"") -> 6035 | C14: =IFERROR(IF(C8="","",C8*'0. Assumptions'!$B$28),"") -> 9234 | D14: =IFERROR(IF(D8="","",D8*'0. Assumptions'!$B$28),"") -> 12423.6
A15: TOTAL VARIABLE COSTS | B15: =IFERROR(IF(B8="","",SUM(B9:B14)),"") -> 182860.5 | C15: =IFERROR(IF(C8="","",SUM(C9:C14)),"") -> 279790.2 | D15: =IFERROR(IF(D8="","",SUM(D9:D14)),"") -> 376435.08
A16: GROSS MARGIN | B16: =IFERROR(IF(B8="","",B8-B15),"") -> 420639.5 | C16: =IFERROR(IF(C8="","",C8-C15),"") -> 643609.8 | D16: =IFERROR(IF(D8="","",D8-D15),"") -> 865924.92
A17: FIXED COSTS (the P&L's) | B17: =IFERROR(IF(B8="","",'3-Year P&L'!$B$37),"") -> 543132.91 | C17: =IFERROR(IF(C8="","",'3-Year P&L'!$B$37),"") -> 543132.91 | D17: =IFERROR(IF(D8="","",'3-Year P&L'!$B$37),"") -> 543132.91 | E17: Fixed costs do not change with the scenario: that is why they are fixed
A18: PRE-TAX INCOME (EBT) | B18: =IFERROR(IF(B8="","",B16-B17),"") -> -122493.41 | C18: =IFERROR(IF(C8="","",C16-C17),"") -> 100476.89 | D18: =IFERROR(IF(D8="","",D16-D17),"") -> 322792.01
A19: Income tax | B19: =IFERROR(IF(B8="","",MAX(0,B18-'0. Assumptions'!$B$42)*'0. Assumptions'!$B$37),"") -> 0 | C19: =IFERROR(IF(C8="","",MAX(0,C18-'0. Assumptions'!$B$42)*'0. Assumptions'!$B$37),"") -> 25119.221 | D19: =IFERROR(IF(D8="","",MAX(0,D18-'0. Assumptions'!$B$42)*'0. Assumptions'!$B$37),"") -> 80698.001 | E19: At the "years 1-2" effective income tax rate, offsetting prior net operating losses
A20: NET INCOME | B20: =IFERROR(IF(B8="","",B18-B19),"") -> -122493.41 | C20: =IFERROR(IF(C8="","",C18-C19),"") -> 75357.664 | D20: =IFERROR(IF(D8="","",D18-D19),"") -> 242094
A21: Covers per day to break even | B21: =IFERROR(IF(B8="","",IF(B6-B15/(B5*B7)<=0,"",B17/(B6-B15/(B5*B7))/B7)),"") -> 91.675739 | C21: =IFERROR(IF(C8="","",IF(C6-C15/(C5*C7)<=0,"",C17/(C6-C15/(C5*C7))/C7)),"") -> 80.169113 | D21: =IFERROR(IF(D8="","",IF(D6-D15/(D5*D7)<=0,"",D17/(D6-D15/(D5*D7))/D7)),"") -> 74.640209
A22: WHAT EACH SCENARIO DEMANDS
A23: Labor cost / Sales | B23: =IFERROR(IF(B8="","",'3-Year P&L'!$B$23/B8),"") -> 0.51172693 | C23: =IFERROR(IF(C8="","",'3-Year P&L'!$B$23/C8),"") -> 0.33444574 | D23: =IFERROR(IF(D8="","",'3-Year P&L'!$B$23/D8),"") -> 0.24858109 | E23: The SAME staffing in all three scenarios. If labor cost blows up in the pessimistic case, adjust it in the Staffing tab, not here
A24: Covers per year per full-time equivalent | B24: =IFERROR(IF(B8="","",B5*B7/Staffing!$C$12),"") -> 3448.5714 | C24: =IFERROR(IF(C8="","",C5*C7/Staffing!$C$12),"") -> 4885.7143 | D24: =IFERROR(IF(D8="","",D5*D7/Staffing!$C$12),"") -> 6120 | E24: Covers each full-time employee in the "Staffing" tab would have to serve. In the optimistic scenario it tells you whether you need to hire
A25: Year-1 closing cash balance (estimate, same method in all three scenarios) | B25: =IFERROR(IF(B8="","",'Startup Costs'!$B$29+B20+'3-Year P&L'!$B$35-Financing!$B$45),"") -> 15791.049 | C25: =IFERROR(IF(C8="","",'Startup Costs'!$B$29+C20+'3-Year P&L'!$B$35-Financing!$B$45),"") -> 213642.13 | D25: =IFERROR(IF(D8="","",'Startup Costs'!$B$29+D20+'3-Year P&L'!$B$35-Financing!$B$45),"") -> 380378.47 | E25: ESTIMATED balance: working capital plus the year's result, adding back depreciation (which is not paid) and subtracting loan principal. It does not include the timing gap between receipts and payments or the sales tax settlement, so the three columns can be compared with each other. In red, the scenario runs out of cash
A26: Actual month-12 balance from the 12-Month Cash Flow tab (Base case only) | C26: =IFERROR(IF(C8="","",'12-Month Cash Flow'!$M$22),"") -> 270545.64 | E26: The ACTUAL base-case balance, with its timing of receipts and payments and its sales tax settlement. It exists only for the Base scenario, the only one with its own monthly cash flow: that is why it is not in the row above, where it would be compared against two estimates
A28: The "Base" column reads its three inputs from the "0. Assumptions" tab, so it reproduces EXACTLY year 1 of the P&L. The other two scenarios use the same cost rates: the only things that change are covers, average check and days. FIXED COSTS are the same in all three: miscellaneous and contingency, which is a percentage of sales, sits at the top with the variable costs and each scenario carries its own.

Sheet Staffing
A1: STAFFING STRUCTURE AND COSTS
A2: =IFERROR("Payroll — "&TEXT('0. Assumptions'!$B$21,"0")&" pay periods + employer taxes "&TEXT('0. Assumptions'!$B$20*100,"0")&"%","") -> Payroll — 12 pay periods + employer taxes 10%
A4: Position | B4: People | C4: FTE | D4: Gross pay per month (total for the position) | E4: Employer payroll taxes (total for the position) | F4: Cost per month (total for the position) | G4: Cost per year | H4: Hours per week per person | I4: Hours per year for the position | J4: Notes
A5: Owner / general manager | B5: 1 | C5: 1 | D5: 5000 | E5: =IFERROR(IF(D5="","",D5*'0. Assumptions'!$B$20),"") -> 500 | F5: =IFERROR(IF(D5="","",D5+E5),"") -> 5500 | G5: =IFERROR(IF(D5="","",F5*MAX(12,'0. Assumptions'!$B$21)),"") -> 66000 | H5: =IFERROR(IF(D5="","",C5*$B$19),"") -> 40 | I5: =IFERROR(IF(D5="","",H5*B5*$B$20),"") -> 2000 | J5: Handles purchasing, cash, vendors and social media, and covers the bar or the floor during the busy evening shift
A6: Kitchen lead | B6: 1 | C6: 1 | D6: 4200 | E6: =IFERROR(IF(D6="","",D6*'0. Assumptions'!$B$20),"") -> 420 | F6: =IFERROR(IF(D6="","",D6+E6),"") -> 4620 | G6: =IFERROR(IF(D6="","",F6*MAX(12,'0. Assumptions'!$B$21)),"") -> 55440 | H6: =IFERROR(IF(D6="","",C6*$B$19),"") -> 40 | I6: =IFERROR(IF(D6="","",H6*B6*$B$20),"") -> 2000 | J6: Designs the small-plates menu, runs the line and tracks food cost every week, a WEEKLY task in the first 90 days on the checklist. The one skilled role clearly above the wage floor
A7: Bartenders (peak shifts) | B7: 3 | C7: 0.7 | D7: 6188 | E7: =IFERROR(IF(D7="","",D7*'0. Assumptions'!$B$20),"") -> 618.8 | F7: =IFERROR(IF(D7="","",D7+E7),"") -> 6806.8 | G7: =IFERROR(IF(D7="","",F7*MAX(12,'0. Assumptions'!$B$21)),"") -> 81681.6 | H7: =IFERROR(IF(D7="","",C7*$B$19),"") -> 28 | I7: =IFERROR(IF(D7="","",H7*B7*$B$20),"") -> 4200 | J7: Pour draft beer, wine and cocktails. The after-work and evening rush is where a neighborhood bar earns most of its sales
A8: Servers (floor & patio) | B8: 2 | C8: 0.5 | D8: 2600 | E8: =IFERROR(IF(D8="","",D8*'0. Assumptions'!$B$20),"") -> 260 | F8: =IFERROR(IF(D8="","",D8+E8),"") -> 2860 | G8: =IFERROR(IF(D8="","",F8*MAX(12,'0. Assumptions'!$B$21)),"") -> 34320 | H8: =IFERROR(IF(D8="","",C8*$B$19),"") -> 20 | I8: =IFERROR(IF(D8="","",H8*B8*$B$20),"") -> 2000 | J8: Cover table and patio service in the evening shift, on part-time hours matched to the weekday traffic described in "Instructions"
A9: Line / prep cook | B9: 1 | C9: 0.8 | D9: 2496 | E9: =IFERROR(IF(D9="","",D9*'0. Assumptions'!$B$20),"") -> 249.6 | F9: =IFERROR(IF(D9="","",D9+E9),"") -> 2745.6 | G9: =IFERROR(IF(D9="","",F9*MAX(12,'0. Assumptions'!$B$21)),"") -> 32947.2 | H9: =IFERROR(IF(D9="","",C9*$B$19),"") -> 32 | I9: =IFERROR(IF(D9="","",H9*B9*$B$20),"") -> 1600 | J9: Prep, cleaning and support on the griddle and fryer during the busy shift, on part-time hours
A10: Barback / weekend extra | B10: 2 | C10: 0.4 | D10: 2080 | E10: =IFERROR(IF(D10="","",D10*'0. Assumptions'!$B$20),"") -> 208 | F10: =IFERROR(IF(D10="","",D10+E10),"") -> 2288 | G10: =IFERROR(IF(D10="","",F10*MAX(12,'0. Assumptions'!$B$21)),"") -> 27456 | H10: =IFERROR(IF(D10="","",C10*$B$19),"") -> 16 | I10: =IFERROR(IF(D10="","",H10*B10*$B$20),"") -> 1600 | J10: Extra hands for the Friday and Saturday peaks: restocking ice, glassware and kegs and clearing the bar, on a few hours a week, matched to the weekend peaks described in "Instructions"
A11: Relief cover (vacations + days off) | B11: 1 | C11: 0.3 | D11: 832 | E11: =IFERROR(IF(D11="","",D11*'0. Assumptions'!$B$20),"") -> 83.2 | F11: =IFERROR(IF(D11="","",D11+E11),"") -> 915.2 | G11: =IFERROR(IF(D11="","",F11*MAX(12,'0. Assumptions'!$B$21)),"") -> 10982.4 | H11: =IFERROR(IF(D11="","",C11*$B$19),"") -> 12 | I11: =IFERROR(IF(D11="","",H11*B11*$B$20),"") -> 600 | J11: Covers vacation, paid time off and the weekly day off for the team
A12: TOTAL STAFF | B12: =IFERROR(IF(COUNT(D5:D11)=0,"",SUM(B5:B11)),"") -> 11 | C12: =IFERROR(IF(COUNT(D5:D11)=0,"",SUMPRODUCT(B5:B11,C5:C11)),"") -> 7 | D12: =IFERROR(IF(COUNT(D5:D11)=0,"",SUM(D5:D11)),"") -> 23396 | E12: =IFERROR(IF(COUNT(D5:D11)=0,"",SUM(E5:E11)),"") -> 2339.6 | F12: =IFERROR(IF(COUNT(D5:D11)=0,"",SUM(F5:F11)),"") -> 25735.6 | G12: =IFERROR(IF(COUNT(D5:D11)=0,"",SUM(G5:G11)),"") -> 308827.2 | I12: =IFERROR(IF(COUNT(D5:D11)=0,"",SUM(I5:I11)),"") -> 14000
A13: STAFF GROWTH (stepped cost)
A14: Annual cost of year-2 hires | B14: 6000 | J14: FULL ANNUAL cost (gross pay + employer payroll taxes, over all pay periods) of whoever you hire that year. The P&L adds it to the previous year's cost: staffing grows by people, not by a percentage
A15: Annual cost of year-3 hires | B15: 6000 | J15: FULL ANNUAL cost (gross pay + employer payroll taxes, over all pay periods) of whoever you hire that year. The P&L adds it to the previous year's cost: staffing grows by people, not by a percentage
A16: Labor cost, year 2 | B16: =IFERROR(IF(G12="","",G12*(1+'0. Assumptions'!$B$48)+B14),"") -> 314827.2
A17: Labor cost, year 3 | B17: =IFERROR(IF(B16="","",B16*(1+'0. Assumptions'!$B$48)+B15),"") -> 320827.2
A18: COVERAGE OF SERVICE HOURS
A19: Full-time week (hours per week) | B19: 40 | J19: 40 hours a week is the FLSA overtime threshold for non-exempt employees; some states add daily overtime rules. Change it if your own full-time week is different
A20: Weeks worked per year per person | B20: 50 | J20: 50 weeks: 52 minus about two weeks of vacation, holidays and average absences. There is no federal vacation requirement in the US: adjust it to your own policy
A21: Service hours per day to cover | B21: 9 | J21: Hours the bar is open to the public each day, from opening to closing. It is an estimate for a neighborhood bar open from afternoon to late night: count the hours against your real schedule
A22: People needed at the same time in each shift | B22: 3.5 | J22: Average number of people working at the same time across the bar and the floor. Rushes need more people and the end of each shift needs fewer
A23: Production hours per day BEFORE opening | B23: 3 | J23: Prep time ahead of opening: small-plates mise en place, batched syrups and juices, garnish and ice, with the griddle, fryer and oven running. It is work time that does not overlap with serving guests
A24: People on the production shift | B24: 2 | J24: Kitchen lead and line / prep cook. Closing, cleaning and the management of purchasing and cash fall OUTSIDE this schedule: they are the margin between the hours hired and the hours needed
A25: Service hours to cover per year | B25: =IFERROR(IF(OR(B21="",B22="",'0. Assumptions'!$B$6=""),"",B21*B22*'0. Assumptions'!$B$6+B23*B24*'0. Assumptions'!$B$6),"") -> 13500
A26: Hours hired per year | B26: =IFERROR(IF(I12="","",I12),"") -> 14000
A27: Coverage (hired / needed) | B27: =IFERROR(B26/B25,"") -> 1.037037 | J27: Below 100% the staff cannot cover the hours the plan declares: either hire more or cut the hours
A29: The gross pay, employer payroll taxes, monthly cost and annual cost columns are TOTALS for the row: for a position with two people they include both. The payroll tax rate and the number of pay periods are in the "0. Assumptions" tab. Tips are not modeled: bartenders, barbacks and servers are budgeted at a base wage of at least $15/h. Federal rules allow a $2.13/h cash wage with a tip credit of up to $5.12 where the state permits it; CA, OR, WA, AK, MN, MT and NV do not (DOL)
A30: The pay floor is the HIGHER of the federal minimum wage and your state / local minimum wage, both in the "0. Assumptions" tab; part-time positions get it in proportion. There is no single national table above the federal floor: the state / local cell is delivered empty so you can enter the rate for your state and city.

Sheet Instructions
A1: HOW TO USE THIS WORKBOOK — Bar Financial Projections
A3: HOW TO USE THIS WORKBOOK
A4: This financial plan is a MODEL: you type only in the GREEN cells and everything else recalculates on its own.
A5: 1. "0. Assumptions" is the control sheet: covers per day, average check excl. sales tax, operating days, food and beverage mix, cost of goods sold, rent, financing and taxes.
A6: 2. Startup cost items, fixed costs and staffing are typed in their own tab, also in green. No number is typed twice.
A7: 3. On "Break-Even" you only type the seat-turn ceiling your space allows; everything else derives from the rest. The other three tabs also have green cells you can change: the pessimistic and optimistic scenarios on "Scenarios", the seasonality and the launch ramp-up on "12-Month Cash Flow", and the other financing sources on "Financing" (rows 8-11 count as sources but are not amortized: Your bank or SBA 7(a) loan goes in "Loan requested" on "0. Assumptions"). Everything else is calculated.
A8: 4. All figures are EXCL. SALES TAX. To turn a menu price into a price excl. sales tax, divide it by 1 + your sales tax rate (with an 8% rate, divide by 1.08); if an item is taxed at a different rate (alcohol to go, for instance), use that rate. The rate of each sales line is in the "Sales tax rate on the line (%)" column of the P&L, and from it come the receipts, the sales tax collected and the equivalent menu price incl. sales tax. With the default 0% recoverable input tax, the sales tax you pay on purchases and startup costs is treated as a cost; in the UK, enter 20% if you are VAT-registered.
A9: 5. If you change the staffing, the P&L reads it on its own: labor cost comes from the "Staffing" tab, not from a separate estimate.
A10: 6. The "12-Month Cash Flow" tab answers the question that decides a bank deal: in which month the cash runs out. The minimum balance of the year can never be in red.
A11: 7. The "Financing" tab matches what you need with what you put in and builds the amortization schedule of the loan. If the difference shows in red, the plan is not financed; far above zero is not free either, because you pay interest on money you do not use.
A12: 8. The Word document in this pack uses the same example figures as this workbook. If you change a number here, update the Word document to match: where the two differ, this spreadsheet is the one that recalculates.
A14: RATIOS AUDITED BY THIS WORKBOOK
A15: Thresholds live in the "Threshold" column of the KEY RATIOS block of the P&L: change them there and the traffic light changes with them.
A17: Ratio | B17: Year 1 value | C17: Threshold | D17: Status
A18: Cost of goods sold / Sales | B18: =IFERROR(IF('3-Year P&L'!$B$52="","",'3-Year P&L'!$B$52),"") -> 0.248 | C18: =IFERROR(IF('3-Year P&L'!$E$52="","",'3-Year P&L'!$E$52),"") -> 0.28 | D18: =IFERROR(IF(OR(B18="",C18=""),"",IF(B18<=C18,"OK","REVIEW")),"") -> OK
A19: Labor cost / Sales | B19: =IFERROR(IF('3-Year P&L'!$B$53="","",'3-Year P&L'!$B$53),"") -> 0.33444574 | C19: =IFERROR(IF('3-Year P&L'!$E$53="","",'3-Year P&L'!$E$53),"") -> 0.35 | D19: =IFERROR(IF(OR(B19="",C19=""),"",IF(B19<=C19,"OK","REVIEW")),"") -> OK
A20: Rent / Sales | B20: =IFERROR(IF('3-Year P&L'!$B$54="","",'3-Year P&L'!$B$54),"") -> 0.084470435 | C20: =IFERROR(IF('3-Year P&L'!$E$54="","",'3-Year P&L'!$E$54),"") -> 0.1 | D20: =IFERROR(IF(OR(B20="",C20=""),"",IF(B20<=C20,"OK","REVIEW")),"") -> OK
A21: Net income / Sales | B21: =IFERROR(IF('3-Year P&L'!$B$55="","",'3-Year P&L'!$B$55),"") -> 0.081608907 | C21: =IFERROR(IF('3-Year P&L'!$E$55="","",'3-Year P&L'!$E$55),"") -> 0.05 | D21: =IFERROR(IF(OR(B21="",C21=""),"",IF(B21>=C21,"OK","REVIEW")),"") -> OK
A22: Gross margin / Sales | B22: =IFERROR(IF('3-Year P&L'!$B$50="","",'3-Year P&L'!$B$50),"") -> 0.697 | C22: =IFERROR(IF('3-Year P&L'!$E$50="","",'3-Year P&L'!$E$50),"") -> 0.68 | D22: =IFERROR(IF(OR(B22="",C22=""),"",IF(B22>=C22,"OK","REVIEW")),"") -> OK
A24: THIS PLAN'S KEY FIGURES
A25: Total startup costs (sum of the blocks) | B25: =IFERROR(IF('Startup Costs'!$B$30="","",'Startup Costs'!$B$30),"") -> 488931.8
A26: Total cash needed at launch | B26: =IFERROR(IF('Startup Costs'!$B$33="","",'Startup Costs'!$B$33),"") -> 488931.8
A27: Working capital funded | B27: =IFERROR(IF('Startup Costs'!$B$29="","",'Startup Costs'!$B$29),"") -> 127231.8
A28: Forecast year-1 revenue | B28: =IFERROR(IF('3-Year P&L'!$B$9="","",'3-Year P&L'!$B$9),"") -> 923400
A29: Year-1 net income | B29: =IFERROR(IF('3-Year P&L'!$B$47="","",'3-Year P&L'!$B$47),"") -> 75357.664
A30: Covers per day for the ACCOUNTING break-even (depreciation included) | B30: =IFERROR(IF('Break-Even'!$B$15="","",'Break-Even'!$B$15),"") -> 80.169113
A31: Project payback (years), before debt | B31: =IFERROR(IF('12-Month Cash Flow'!$B$31="","",'12-Month Cash Flow'!$B$31),"") -> 2.5
A33: WHY THIS MODEL IS BUILT THIS WAY
A34: Item | B34: Common shortcut | C34: This workbook | D34: Why
A35: Labor cost in the P&L | B35: A figure typed by hand into the P&L | C35: The total of the "Staffing" tab | D35: A typed figure drifts away from what the payroll tab actually adds up to. Here both are the same number, and it recalculates every time you change a salary.
A36: Staffing | B36: A headcount with a lump-sum labor cost | C36: Positions with hours, part-time shifts and a wage for each role | D36: Sized by hours, with the schedule visible on the "Staffing" tab: the hours the bar is open to guests plus the prep time ahead of opening, with the people needed at once, on every day the bar opens. Hired hours cover those needed hours and leave a small margin for closing, cleaning and administration. No wage falls below the minimum wage floor, and part-time roles respect it in proportion.
A37: Covers per day in year 1 | B37: A typed number with no link to the seats | C37: Covers per day, with the implied seat turns shown next to the seating capacity | D37: Volume is set from the seats and a realistic number of seat turns, then checked against the ceiling on "Break-Even", so the plan never assumes more covers than the space can serve.
A38: Average check | B38: A figure that does not say whether it includes sales tax | C38: Average check EXCL. sales tax, with the menu price incl. sales tax calculated from it | D38: The workbook states what the number is: the menu price with tax comes from your local rate on "0. Assumptions", so the P&L never counts sales tax as revenue.
A39: Year-1 revenue | B39: A total typed by hand | C39: Covers × average check × days open | D39: Revenue is built from its drivers, so changing the volume, the price or the calendar moves the P&L, the break-even and the scenarios together.
A40: Rent | B40: A flat monthly amount buried in the costs | C40: One monthly rent on "0. Assumptions", checked as a share of sales | D40: The traffic light on the "3-Year P&L" compares rent with its ceiling, so you see whether the lease is viable when you negotiate it.
A41: Opening calendar | B41: Different calendars on different tabs | C41: One figure for days open, a single input on "0. Assumptions" | D41: When tabs use different calendars, their results do not agree with each other. One input feeds the P&L, the break-even and the scenarios.
A42: Working capital | B42: A typed amount with a number of months in its label | C42: A number of months of fixed cash costs, by formula | D42: A typed amount can fall short of even one month of fixed costs without anyone noticing. Here it recalculates every time you change a fixed cost.
A43: Depreciation | B43: One flat rate applied to the whole investment | C43: Straight-line, only on build-out and equipment, each over its own useful life, by formula | D43: Working capital, the security deposit, opening inventory and launch marketing are not fixed assets and are not depreciated. Tax depreciation (MACRS, Section 179) can differ: ask your CPA.
A44: Build-out contingency | B44: A typed amount | C44: A percentage of the build-out lines, editable on "0. Assumptions" | D44: A percentage buried in a row label goes stale as soon as any line changes. Here it is an input and recalculates.
A45: Income tax | B45: A flat rate every year, with no offset for losses | C45: One effective rate for years 1-2 and another from year 3, offsetting net operating losses carried forward | D45: It uses an effective income tax rate (federal plus state; a pass-through business pays none at the entity level) and carries net operating losses forward, the way a lender would model it. Federal rules cap the offset at 80% of taxable income while the model offsets in full, so treat it as a simplification and ask your CPA which structure applies to you.
... A50: Salaries and covered hours | B50: No check | C50: A traffic light per salary and a counter of hired hours against needed hours | D50: The "Staffing" tab flags red if a salary falls below the minimum wage floor in proportion to its hours, and amber if the team does not cover the schedule the project declares.
A52: US INDUSTRY BENCHMARKS (sourced) AND KIT ESTIMATES
A53: Benchmark | B53: Value | C53: Source | D53: Note
A54: Food cost (small plates) | B54: 25-35% of food sales | C54: Kit estimate | D54: Short kitchen with trim put to use: ingredients stay low on a small-plates menu
A55: Pour cost, whole bar | B55: 18-24% (median just above 20%) | C55: BevSpot (bevspot.com) | D55: The beverage cost in this example (the "Cost of goods sold on BEVERAGE sales" row of "0. Assumptions") includes garnish and spillage
A56: Beer pour cost (median) | B56: 24% | C56: BevSpot (bevspot.com) | D56: Draft beer lowers the cost compared with bottles if you keep the lines clean and control waste
A57: Labor cost / sales | B57: ≤ 35% | C57: Kit estimate | D57: Includes barbacks and weekend extras; tips are not included
A58: Rent / sales | B58: ≤ 10% | C58: Kit estimate | D58: The threshold used by the traffic light of the "3-Year P&L"
A59: Average check per guest | B59: $20-$35 excl. sales tax | C59: Kit estimate | D59: Small plates + drinks; the menu price incl. sales tax for THIS plan is calculated on "0. Assumptions"
A60: Spirits pour cost (median) | B60: 15% | C60: BevSpot (bevspot.com) | D60: Cocktails with a standardized recipe and a jigger
A61: Wine pour cost (median) | B61: 28% | C61: BevSpot (bevspot.com) | D61: Wine by the glass: control the open bottle
A62: Seat turns per day | B62: 1.5-3 | C62: Kit estimate | D62: It is the default ceiling on "Break-Even": adjust it to your hours and your seating capacity
A63: Startup costs, bar in a leased space | B63: $110,000-$550,000 (survey average $425,500) | C63: RestaurantOwner.com survey, via Poster (joinposter.com) | D63: Compare it with the capex on "Startup Costs"
A64: Liquor license | B64: Beer & wine from about $3,000; full liquor $12,000-$400,000 | C64: Poster (joinposter.com) | D64: In quota states you buy an existing license at market price; this workbook budgets a state without a quota
... A69: Minimum wage floor | B69: Federal $7.25/h + your state | C69: U.S. Department of Labor (dol.gov) | D69: Enter your state's floor on "0. Assumptions"; check your state and city rates at dol.gov
A71: To edit a cell that is not green: Review → Unprotect Sheet (there is no password).
A72: More templates and kits in the catalog at aichef.pro/en/digital-products
A73: Designed by John Guerrero — chef and restaurant consultant since 2010, in the kitchen since age 17 · johnguerrero.es
A74: Version 2.2 · October 2026 · aichef.pro/en/digital-products/bar-business-plan · info@aichef.pro
A75: Planning tool, not financial, tax or legal advice. Requirements vary by state, county and city — check with your accountant and local authorities.

Sheet 12-Month Cash Flow
A1: CASH FLOW FORECAST — YEAR 1
A2: The P&L tells you whether the business makes money; this tab tells you whether you have cash left to get to the end of the month. It is the first one a lender looks at.
A4: Item | B4: Month 1 | C4: Month 2 | D4: Month 3 | E4: Month 4 | F4: Month 5 | G4: Month 6 | H4: Month 7 | I4: Month 8 | J4: Month 9 | K4: Month 10 | L4: Month 11 | M4: Month 12 | N4: Year
A5: Monthly seasonality (adds up to 100%) | B5: 0.064 | C5: 0.068 | D5: 0.078 | E5: 0.08 | F5: 0.086 | G5: 0.093 | H5: 0.098 | I5: 0.093 | J5: 0.083 | K5: 0.08 | L5: 0.077 | M5: 0.1 | N5: =IFERROR(IF('3-Year P&L'!$B$9="","",SUM(B5:M5)),"") -> 1 | O5: Profile for your area: adjust it to your own slow and busy months (weather, tourism, events). It must add up to 100%
A6: Launch ramp-up (% of steady-state activity) | B6: =IFERROR(IF('3-Year P&L'!$B$9="","",MIN(1,'0. Assumptions'!$B$52+(1-'0. Assumptions'!$B$52)*0/MAX(1,'0. Assumptions'!$B$53-1))),"") -> 0.55 | C6: =IFERROR(IF('3-Year P&L'!$B$9="","",MIN(1,'0. Assumptions'!$B$52+(1-'0. Assumptions'!$B$52)*1/MAX(1,'0. Assumptions'!$B$53-1))),"") -> 0.64 | D6: =IFERROR(IF('3-Year P&L'!$B$9="","",MIN(1,'0. Assumptions'!$B$52+(1-'0. Assumptions'!$B$52)*2/MAX(1,'0. Assumptions'!$B$53-1))),"") -> 0.73 | E6: =IFERROR(IF('3-Year P&L'!$B$9="","",MIN(1,'0. Assumptions'!$B$52+(1-'0. Assumptions'!$B$52)*3/MAX(1,'0. Assumptions'!$B$53-1))),"") -> 0.82 | F6: =IFERROR(IF('3-Year P&L'!$B$9="","",MIN(1,'0. Assumptions'!$B$52+(1-'0. Assumptions'!$B$52)*4/MAX(1,'0. Assumptions'!$B$53-1))),"") -> 0.91 | G6: =IFERROR(IF('3-Year P&L'!$B$9="","",MIN(1,'0. Assumptions'!$B$52+(1-'0. Assumptions'!$B$52)*5/MAX(1,'0. Assumptions'!$B$53-1))),"") -> 1 | H6: =IFERROR(IF('3-Year P&L'!$B$9="","",MIN(1,'0. Assumptions'!$B$52+(1-'0. Assumptions'!$B$52)*6/MAX(1,'0. Assumptions'!$B$53-1))),"") -> 1 | I6: =IFERROR(IF('3-Year P&L'!$B$9="","",MIN(1,'0. Assumptions'!$B$52+(1-'0. Assumptions'!$B$52)*7/MAX(1,'0. Assumptions'!$B$53-1))),"") -> 1 | J6: =IFERROR(IF('3-Year P&L'!$B$9="","",MIN(1,'0. Assumptions'!$B$52+(1-'0. Assumptions'!$B$52)*8/MAX(1,'0. Assumptions'!$B$53-1))),"") -> 1 | K6: =IFERROR(IF('3-Year P&L'!$B$9="","",MIN(1,'0. Assumptions'!$B$52+(1-'0. Assumptions'!$B$52)*9/MAX(1,'0. Assumptions'!$B$53-1))),"") -> 1 | L6: =IFERROR(IF('3-Year P&L'!$B$9="","",MIN(1,'0. Assumptions'!$B$52+(1-'0. Assumptions'!$B$52)*10/MAX(1,'0. Assumptions'!$B$53-1))),"") -> 1 | M6: =IFERROR(IF('3-Year P&L'!$B$9="","",MIN(1,'0. Assumptions'!$B$52+(1-'0. Assumptions'!$B$52)*11/MAX(1,'0. Assumptions'!$B$53-1))),"") -> 1 | O6: Rises in a straight line from the month-1 percentage to 100% over the number of months you set in Assumptions. With month 1 at 100%, the ramp disappears
A7: Split of activity by month (calculated) | B7: =IFERROR(IF('3-Year P&L'!$B$9="","",B5*B6/SUMPRODUCT($B$5:$M$5,$B$6:$M$6)),"") -> 0.038958739 | C7: =IFERROR(IF('3-Year P&L'!$B$9="","",C5*C6/SUMPRODUCT($B$5:$M$5,$B$6:$M$6)),"") -> 0.048167168 | D7: =IFERROR(IF('3-Year P&L'!$B$9="","",D5*D6/SUMPRODUCT($B$5:$M$5,$B$6:$M$6)),"") -> 0.063020188 | E7: =IFERROR(IF('3-Year P&L'!$B$9="","",E5*E6/SUMPRODUCT($B$5:$M$5,$B$6:$M$6)),"") -> 0.072604923 | F7: =IFERROR(IF('3-Year P&L'!$B$9="","",F5*F6/SUMPRODUCT($B$5:$M$5,$B$6:$M$6)),"") -> 0.086616788 | G7: =IFERROR(IF('3-Year P&L'!$B$9="","",G5*G6/SUMPRODUCT($B$5:$M$5,$B$6:$M$6)),"") -> 0.10293076 | H7: =IFERROR(IF('3-Year P&L'!$B$9="","",H5*H6/SUMPRODUCT($B$5:$M$5,$B$6:$M$6)),"") -> 0.10846467 | I7: =IFERROR(IF('3-Year P&L'!$B$9="","",I5*I6/SUMPRODUCT($B$5:$M$5,$B$6:$M$6)),"") -> 0.10293076 | ... M7: =IFERROR(IF('3-Year P&L'!$B$9="","",M5*M6/SUMPRODUCT($B$5:$M$5,$B$6:$M$6)),"") -> 0.11067824 | N7: =IFERROR(IF('3-Year P&L'!$B$9="","",SUM(B7:M7)),"") -> 1 | O7: Seasonality × ramp-up, normalized to 100%: the YEAR brings in what the P&L says, but split the way a business that has just opened would split it
A8: CASH IN
A9: Sales collected (incl. sales tax collected) | B9: =IFERROR(IF('3-Year P&L'!$B$9="","",('3-Year P&L'!$B$9+'3-Year P&L'!$B$9*SUMPRODUCT('3-Year P&L'!$E$10:$E$11,'3-Year P&L'!$G$10:$G$11))*B7*(1-MIN(30,'0. Assumptions'!$B$58)/30)),"") -> 37557.378 | C9: =IFERROR(IF('3-Year P&L'!$B$9="","",('3-Year P&L'!$B$9+'3-Year P&L'!$B$9*SUMPRODUCT('3-Year P&L'!$E$10:$E$11,'3-Year P&L'!$G$10:$G$11))*(C7*(1-MIN(30,'0. Assumptions'!$B$58)/30)+B7*MIN(30,'0. Assumptions'!$B$58)/30)),"") -> 47729.658 | D9: =IFERROR(IF('3-Year P&L'!$B$9="","",('3-Year P&L'!$B$9+'3-Year P&L'!$B$9*SUMPRODUCT('3-Year P&L'!$E$10:$E$11,'3-Year P&L'!$G$10:$G$11))*(D7*(1-MIN(30,'0. Assumptions'!$B$58)/30)+C7*MIN(30,'0. Assumptions'!$B$58)/30)),"") -> 62354.519 | E9: =IFERROR(IF('3-Year P&L'!$B$9="","",('3-Year P&L'!$B$9+'3-Year P&L'!$B$9*SUMPRODUCT('3-Year P&L'!$E$10:$E$11,'3-Year P&L'!$G$10:$G$11))*(E7*(1-MIN(30,'0. Assumptions'!$B$58)/30)+D7*MIN(30,'0. Assumptions'!$B$58)/30)),"") -> 72088.237 | F9: =IFERROR(IF('3-Year P&L'!$B$9="","",('3-Year P&L'!$B$9+'3-Year P&L'!$B$9*SUMPRODUCT('3-Year P&L'!$E$10:$E$11,'3-Year P&L'!$G$10:$G$11))*(F7*(1-MIN(30,'0. Assumptions'!$B$58)/30)+E7*MIN(30,'0. Assumptions'!$B$58)/30)),"") -> 85914.709 | G9: =IFERROR(IF('3-Year P&L'!$B$9="","",('3-Year P&L'!$B$9+'3-Year P&L'!$B$9*SUMPRODUCT('3-Year P&L'!$E$10:$E$11,'3-Year P&L'!$G$10:$G$11))*(G7*(1-MIN(30,'0. Assumptions'!$B$58)/30)+F7*MIN(30,'0. Assumptions'!$B$58)/30)),"") -> 102107.65 | H9: =IFERROR(IF('3-Year P&L'!$B$9="","",('3-Year P&L'!$B$9+'3-Year P&L'!$B$9*SUMPRODUCT('3-Year P&L'!$E$10:$E$11,'3-Year P&L'!$G$10:$G$11))*(H7*(1-MIN(30,'0. Assumptions'!$B$58)/30)+G7*MIN(30,'0. Assumptions'!$B$58)/30)),"") -> 107984.82 | I9: =IFERROR(IF('3-Year P&L'!$B$9="","",('3-Year P&L'!$B$9+'3-Year P&L'!$B$9*SUMPRODUCT('3-Year P&L'!$E$10:$E$11,'3-Year P&L'!$G$10:$G$11))*(I7*(1-MIN(30,'0. Assumptions'!$B$58)/30)+H7*MIN(30,'0. Assumptions'!$B$58)/30)),"") -> 102833.93 | J9: =IFERROR(IF('3-Year P&L'!$B$9="","",('3-Year P&L'!$B$9+'3-Year P&L'!$B$9*SUMPRODUCT('3-Year P&L'!$E$10:$E$11,'3-Year P&L'!$G$10:$G$11))*(J7*(1-MIN(30,'0. Assumptions'!$B$58)/30)+I7*MIN(30,'0. Assumptions'!$B$58)/30)),"") -> 91980.255 | ... M9: =IFERROR(IF('3-Year P&L'!$B$9="","",('3-Year P&L'!$B$9+'3-Year P&L'!$B$9*SUMPRODUCT('3-Year P&L'!$E$10:$E$11,'3-Year P&L'!$G$10:$G$11))*(M7*(1-MIN(30,'0. Assumptions'!$B$58)/30)+L7*MIN(30,'0. Assumptions'!$B$58)/30)),"") -> 109530.09 | N9: =IFERROR(IF('3-Year P&L'!$B$9="","",SUM(B9:M9)),"") -> 993592.79 | O9: The month's sales plus the sales tax collected, adjusted by the average collection days from the Assumptions tab
A10: CASH OUT
A11: Purchases and variable costs (incl. sales tax) | B11: =IFERROR(IF('3-Year P&L'!$B$9="","",-('3-Year P&L'!$B$13*(1+'3-Year P&L'!$G$13)+'3-Year P&L'!$B$14*(1+'3-Year P&L'!$G$14)+'3-Year P&L'!$B$15*(1+'3-Year P&L'!$G$15)+'3-Year P&L'!$B$16*(1+'3-Year P&L'!$G$16)+'3-Year P&L'!$B$17*(1+'3-Year P&L'!$G$17)+'3-Year P&L'!$B$18*(1+'3-Year P&L'!$G$18))*B7*(1-MIN(30,'0. Assumptions'!$B$59)/30)),"") -> -5813.4792 | C11: =IFERROR(IF('3-Year P&L'!$B$9="","",-('3-Year P&L'!$B$13*(1+'3-Year P&L'!$G$13)+'3-Year P&L'!$B$14*(1+'3-Year P&L'!$G$14)+'3-Year P&L'!$B$15*(1+'3-Year P&L'!$G$15)+'3-Year P&L'!$B$16*(1+'3-Year P&L'!$G$16)+'3-Year P&L'!$B$17*(1+'3-Year P&L'!$G$17)+'3-Year P&L'!$B$18*(1+'3-Year P&L'!$G$18))*(C7*(1-MIN(30,'0. Assumptions'!$B$59)/30)+B7*MIN(30,'0. Assumptions'!$B$59)/30)),"") -> -12274.368 | D11: =IFERROR(IF('3-Year P&L'!$B$9="","",-('3-Year P&L'!$B$13*(1+'3-Year P&L'!$G$13)+'3-Year P&L'!$B$14*(1+'3-Year P&L'!$G$14)+'3-Year P&L'!$B$15*(1+'3-Year P&L'!$G$15)+'3-Year P&L'!$B$16*(1+'3-Year P&L'!$G$16)+'3-Year P&L'!$B$17*(1+'3-Year P&L'!$G$17)+'3-Year P&L'!$B$18*(1+'3-Year P&L'!$G$18))*(D7*(1-MIN(30,'0. Assumptions'!$B$59)/30)+C7*MIN(30,'0. Assumptions'!$B$59)/30)),"") -> -15693.091 | E11: =IFERROR(IF('3-Year P&L'!$B$9="","",-('3-Year P&L'!$B$13*(1+'3-Year P&L'!$G$13)+'3-Year P&L'!$B$14*(1+'3-Year P&L'!$G$14)+'3-Year P&L'!$B$15*(1+'3-Year P&L'!$G$15)+'3-Year P&L'!$B$16*(1+'3-Year P&L'!$G$16)+'3-Year P&L'!$B$17*(1+'3-Year P&L'!$G$17)+'3-Year P&L'!$B$18*(1+'3-Year P&L'!$G$18))*(E7*(1-MIN(30,'0. Assumptions'!$B$59)/30)+D7*MIN(30,'0. Assumptions'!$B$59)/30)),"") -> -19062.679 | F11: =IFERROR(IF('3-Year P&L'!$B$9="","",-('3-Year P&L'!$B$13*(1+'3-Year P&L'!$G$13)+'3-Year P&L'!$B$14*(1+'3-Year P&L'!$G$14)+'3-Year P&L'!$B$15*(1+'3-Year P&L'!$G$15)+'3-Year P&L'!$B$16*(1+'3-Year P&L'!$G$16)+'3-Year P&L'!$B$17*(1+'3-Year P&L'!$G$17)+'3-Year P&L'!$B$18*(1+'3-Year P&L'!$G$18))*(F7*(1-MIN(30,'0. Assumptions'!$B$59)/30)+E7*MIN(30,'0. Assumptions'!$B$59)/30)),"") -> -22405.017 | G11: =IFERROR(IF('3-Year P&L'!$B$9="","",-('3-Year P&L'!$B$13*(1+'3-Year P&L'!$G$13)+'3-Year P&L'!$B$14*(1+'3-Year P&L'!$G$14)+'3-Year P&L'!$B$15*(1+'3-Year P&L'!$G$15)+'3-Year P&L'!$B$16*(1+'3-Year P&L'!$G$16)+'3-Year P&L'!$B$17*(1+'3-Year P&L'!$G$17)+'3-Year P&L'!$B$18*(1+'3-Year P&L'!$G$18))*(G7*(1-MIN(30,'0. Assumptions'!$B$59)/30)+F7*MIN(30,'0. Assumptions'!$B$59)/30)),"") -> -26668.923 | H11: =IFERROR(IF('3-Year P&L'!$B$9="","",-('3-Year P&L'!$B$13*(1+'3-Year P&L'!$G$13)+'3-Year P&L'!$B$14*(1+'3-Year P&L'!$G$14)+'3-Year P&L'!$B$15*(1+'3-Year P&L'!$G$15)+'3-Year P&L'!$B$16*(1+'3-Year P&L'!$G$16)+'3-Year P&L'!$B$17*(1+'3-Year P&L'!$G$17)+'3-Year P&L'!$B$18*(1+'3-Year P&L'!$G$18))*(H7*(1-MIN(30,'0. Assumptions'!$B$59)/30)+G7*MIN(30,'0. Assumptions'!$B$59)/30)),"") -> -29624.796 | I11: =IFERROR(IF('3-Year P&L'!$B$9="","",-('3-Year P&L'!$B$13*(1+'3-Year P&L'!$G$13)+'3-Year P&L'!$B$14*(1+'3-Year P&L'!$G$14)+'3-Year P&L'!$B$15*(1+'3-Year P&L'!$G$15)+'3-Year P&L'!$B$16*(1+'3-Year P&L'!$G$16)+'3-Year P&L'!$B$17*(1+'3-Year P&L'!$G$17)+'3-Year P&L'!$B$18*(1+'3-Year P&L'!$G$18))*(I7*(1-MIN(30,'0. Assumptions'!$B$59)/30)+H7*MIN(30,'0. Assumptions'!$B$59)/30)),"") -> -29521.574 | J11: =IFERROR(IF('3-Year P&L'!$B$9="","",-('3-Year P&L'!$B$13*(1+'3-Year P&L'!$G$13)+'3-Year P&L'!$B$14*(1+'3-Year P&L'!$G$14)+'3-Year P&L'!$B$15*(1+'3-Year P&L'!$G$15)+'3-Year P&L'!$B$16*(1+'3-Year P&L'!$G$16)+'3-Year P&L'!$B$17*(1+'3-Year P&L'!$G$17)+'3-Year P&L'!$B$18*(1+'3-Year P&L'!$G$18))*(J7*(1-MIN(30,'0. Assumptions'!$B$59)/30)+I7*MIN(30,'0. Assumptions'!$B$59)/30)),"") -> -27147.461 | ... M11: =IFERROR(IF('3-Year P&L'!$B$9="","",-('3-Year P&L'!$B$13*(1+'3-Year P&L'!$G$13)+'3-Year P&L'!$B$14*(1+'3-Year P&L'!$G$14)+'3-Year P&L'!$B$15*(1+'3-Year P&L'!$G$15)+'3-Year P&L'!$B$16*(1+'3-Year P&L'!$G$16)+'3-Year P&L'!$B$17*(1+'3-Year P&L'!$G$17)+'3-Year P&L'!$B$18*(1+'3-Year P&L'!$G$18))*(M7*(1-MIN(30,'0. Assumptions'!$B$59)/30)+L7*MIN(30,'0. Assumptions'!$B$59)/30)),"") -> -27642.928 | N11: =IFERROR(IF('3-Year P&L'!$B$9="","",SUM(B11:M11)),"") -> -265339.08 | O11: =IFERROR("Food and beverage purchases, consumables, fees and contingencies, each at ITS tax rate (column G of the P&L; 0 in the US, where the sales tax you pay is part of the cost) and with the supplier payment days from ""0. Assumptions""."&IF('0. Assumptions'!$B$59=0,""," With "&TEXT('0. Assumptions'!$B$59,"0")&" payment days, the last purchases of the year are paid next year: the ""Year"" column of this row holds "&TEXT(MAX(0,12-ROUNDUP('0. Assumptions'!$B$59/30,0)),"0")&" months of purchases, not the year's cost."),"") -> Food and beverage purchases, consumables, fees and contingencies, each at ITS tax rate (column G of the P&L; 0 in the US, where the sales tax you pay is part of the cost) and with the supplier payment days from "0. Assumptions". With 14 payment days, the last purchases of the year are paid next year: the "Year" column of this row holds 11 months of purchases, not the year's cost.
A12: Operating fixed costs (incl. sales tax) | B12: =IFERROR(IF('3-Year P&L'!$B$9="","",-('3-Year P&L'!$B$37-'3-Year P&L'!$B$23-'3-Year P&L'!$B$35-'3-Year P&L'!$B$36+'3-Year P&L'!$B$39)/12),"") -> -13600 | C12: =IFERROR(IF('3-Year P&L'!$B$9="","",-('3-Year P&L'!$B$37-'3-Year P&L'!$B$23-'3-Year P&L'!$B$35-'3-Year P&L'!$B$36+'3-Year P&L'!$B$39)/12),"") -> -13600 | D12: =IFERROR(IF('3-Year P&L'!$B$9="","",-('3-Year P&L'!$B$37-'3-Year P&L'!$B$23-'3-Year P&L'!$B$35-'3-Year P&L'!$B$36+'3-Year P&L'!$B$39)/12),"") -> -13600 | E12: =IFERROR(IF('3-Year P&L'!$B$9="","",-('3-Year P&L'!$B$37-'3-Year P&L'!$B$23-'3-Year P&L'!$B$35-'3-Year P&L'!$B$36+'3-Year P&L'!$B$39)/12),"") -> -13600 | F12: =IFERROR(IF('3-Year P&L'!$B$9="","",-('3-Year P&L'!$B$37-'3-Year P&L'!$B$23-'3-Year P&L'!$B$35-'3-Year P&L'!$B$36+'3-Year P&L'!$B$39)/12),"") -> -13600 | G12: =IFERROR(IF('3-Year P&L'!$B$9="","",-('3-Year P&L'!$B$37-'3-Year P&L'!$B$23-'3-Year P&L'!$B$35-'3-Year P&L'!$B$36+'3-Year P&L'!$B$39)/12),"") -> -13600 | H12: =IFERROR(IF('3-Year P&L'!$B$9="","",-('3-Year P&L'!$B$37-'3-Year P&L'!$B$23-'3-Year P&L'!$B$35-'3-Year P&L'!$B$36+'3-Year P&L'!$B$39)/12),"") -> -13600 | I12: =IFERROR(IF('3-Year P&L'!$B$9="","",-('3-Year P&L'!$B$37-'3-Year P&L'!$B$23-'3-Year P&L'!$B$35-'3-Year P&L'!$B$36+'3-Year P&L'!$B$39)/12),"") -> -13600 | ... M12: =IFERROR(IF('3-Year P&L'!$B$9="","",-('3-Year P&L'!$B$37-'3-Year P&L'!$B$23-'3-Year P&L'!$B$35-'3-Year P&L'!$B$36+'3-Year P&L'!$B$39)/12),"") -> -13600 | N12: =IFERROR(IF('3-Year P&L'!$B$9="","",SUM(B12:M12)),"") -> -163200 | O12: The fixed costs that leave cash, each with its own tax rate: insurance carries none
A13: Payroll and employer payroll taxes | B13: =IFERROR(IF('3-Year P&L'!$B$9="","",-'3-Year P&L'!$B$23/MAX(12,'0. Assumptions'!$B$21)*(1+IF(1='0. Assumptions'!$B$60,(MAX(12,'0. Assumptions'!$B$21)-12)/2,0)+IF(1='0. Assumptions'!$B$61,(MAX(12,'0. Assumptions'!$B$21)-12)/2,0))),"") -> -25735.6 | C13: =IFERROR(IF('3-Year P&L'!$B$9="","",-'3-Year P&L'!$B$23/MAX(12,'0. Assumptions'!$B$21)*(1+IF(2='0. Assumptions'!$B$60,(MAX(12,'0. Assumptions'!$B$21)-12)/2,0)+IF(2='0. Assumptions'!$B$61,(MAX(12,'0. Assumptions'!$B$21)-12)/2,0))),"") -> -25735.6 | D13: =IFERROR(IF('3-Year P&L'!$B$9="","",-'3-Year P&L'!$B$23/MAX(12,'0. Assumptions'!$B$21)*(1+IF(3='0. Assumptions'!$B$60,(MAX(12,'0. Assumptions'!$B$21)-12)/2,0)+IF(3='0. Assumptions'!$B$61,(MAX(12,'0. Assumptions'!$B$21)-12)/2,0))),"") -> -25735.6 | E13: =IFERROR(IF('3-Year P&L'!$B$9="","",-'3-Year P&L'!$B$23/MAX(12,'0. Assumptions'!$B$21)*(1+IF(4='0. Assumptions'!$B$60,(MAX(12,'0. Assumptions'!$B$21)-12)/2,0)+IF(4='0. Assumptions'!$B$61,(MAX(12,'0. Assumptions'!$B$21)-12)/2,0))),"") -> -25735.6 | F13: =IFERROR(IF('3-Year P&L'!$B$9="","",-'3-Year P&L'!$B$23/MAX(12,'0. Assumptions'!$B$21)*(1+IF(5='0. Assumptions'!$B$60,(MAX(12,'0. Assumptions'!$B$21)-12)/2,0)+IF(5='0. Assumptions'!$B$61,(MAX(12,'0. Assumptions'!$B$21)-12)/2,0))),"") -> -25735.6 | G13: =IFERROR(IF('3-Year P&L'!$B$9="","",-'3-Year P&L'!$B$23/MAX(12,'0. Assumptions'!$B$21)*(1+IF(6='0. Assumptions'!$B$60,(MAX(12,'0. Assumptions'!$B$21)-12)/2,0)+IF(6='0. Assumptions'!$B$61,(MAX(12,'0. Assumptions'!$B$21)-12)/2,0))),"") -> -25735.6 | H13: =IFERROR(IF('3-Year P&L'!$B$9="","",-'3-Year P&L'!$B$23/MAX(12,'0. Assumptions'!$B$21)*(1+IF(7='0. Assumptions'!$B$60,(MAX(12,'0. Assumptions'!$B$21)-12)/2,0)+IF(7='0. Assumptions'!$B$61,(MAX(12,'0. Assumptions'!$B$21)-12)/2,0))),"") -> -25735.6 | I13: =IFERROR(IF('3-Year P&L'!$B$9="","",-'3-Year P&L'!$B$23/MAX(12,'0. Assumptions'!$B$21)*(1+IF(8='0. Assumptions'!$B$60,(MAX(12,'0. Assumptions'!$B$21)-12)/2,0)+IF(8='0. Assumptions'!$B$61,(MAX(12,'0. Assumptions'!$B$21)-12)/2,0))),"") -> -25735.6 | J13: =IFERROR(IF('3-Year P&L'!$B$9="","",-'3-Year P&L'!$B$23/MAX(12,'0. Assumptions'!$B$21)*(1+IF(9='0. Assumptions'!$B$60,(MAX(12,'0. Assumptions'!$B$21)-12)/2,0)+IF(9='0. Assumptions'!$B$61,(MAX(12,'0. Assumptions'!$B$21)-12)/2,0))),"") -> -25735.6 | K13: =IFERROR(IF('3-Year P&L'!$B$9="","",-'3-Year P&L'!$B$23/MAX(12,'0. Assumptions'!$B$21)*(1+IF(10='0. Assumptions'!$B$60,(MAX(12,'0. Assumptions'!$B$21)-12)/2,0)+IF(10='0. Assumptions'!$B$61,(MAX(12,'0. Assumptions'!$B$21)-12)/2,0))),"") -> -25735.6 | L13: =IFERROR(IF('3-Year P&L'!$B$9="","",-'3-Year P&L'!$B$23/MAX(12,'0. Assumptions'!$B$21)*(1+IF(11='0. Assumptions'!$B$60,(MAX(12,'0. Assumptions'!$B$21)-12)/2,0)+IF(11='0. Assumptions'!$B$61,(MAX(12,'0. Assumptions'!$B$21)-12)/2,0))),"") -> -25735.6 | M13: =IFERROR(IF('3-Year P&L'!$B$9="","",-'3-Year P&L'!$B$23/MAX(12,'0. Assumptions'!$B$21)*(1+IF(12='0. Assumptions'!$B$60,(MAX(12,'0. Assumptions'!$B$21)-12)/2,0)+IF(12='0. Assumptions'!$B$61,(MAX(12,'0. Assumptions'!$B$21)-12)/2,0))),"") -> -25735.6 | N13: =IFERROR(IF('3-Year P&L'!$B$9="","",SUM(B13:M13)),"") -> -308827.2 | O13: Twelve monthly installments plus extra pay periods in the months you set in Assumptions (only if pay periods > 12). The total for the year is the same as the P&L's
A14: Loan interest | B14: =IFERROR(IF('3-Year P&L'!$B$9="","",-Financing!$B$44/12),"") -> -3075 | C14: =IFERROR(IF('3-Year P&L'!$B$9="","",-Financing!$B$44/12),"") -> -3075 | D14: =IFERROR(IF('3-Year P&L'!$B$9="","",-Financing!$B$44/12),"") -> -3075 | E14: =IFERROR(IF('3-Year P&L'!$B$9="","",-Financing!$B$44/12),"") -> -3075 | F14: =IFERROR(IF('3-Year P&L'!$B$9="","",-Financing!$B$44/12),"") -> -3075 | G14: =IFERROR(IF('3-Year P&L'!$B$9="","",-Financing!$B$44/12),"") -> -3075 | H14: =IFERROR(IF('3-Year P&L'!$B$9="","",-Financing!$B$44/12),"") -> -3075 | I14: =IFERROR(IF('3-Year P&L'!$B$9="","",-Financing!$B$44/12),"") -> -3075 | ... M14: =IFERROR(IF('3-Year P&L'!$B$9="","",-Financing!$B$44/12),"") -> -3075 | N14: =IFERROR(IF('3-Year P&L'!$B$9="","",SUM(B14:M14)),"") -> -36900
A15: Loan principal repaid | B15: =IFERROR(IF('3-Year P&L'!$B$9="","",-Financing!$B$45/12),"") -> -1929.4209 | C15: =IFERROR(IF('3-Year P&L'!$B$9="","",-Financing!$B$45/12),"") -> -1929.4209 | D15: =IFERROR(IF('3-Year P&L'!$B$9="","",-Financing!$B$45/12),"") -> -1929.4209 | E15: =IFERROR(IF('3-Year P&L'!$B$9="","",-Financing!$B$45/12),"") -> -1929.4209 | F15: =IFERROR(IF('3-Year P&L'!$B$9="","",-Financing!$B$45/12),"") -> -1929.4209 | G15: =IFERROR(IF('3-Year P&L'!$B$9="","",-Financing!$B$45/12),"") -> -1929.4209 | H15: =IFERROR(IF('3-Year P&L'!$B$9="","",-Financing!$B$45/12),"") -> -1929.4209 | I15: =IFERROR(IF('3-Year P&L'!$B$9="","",-Financing!$B$45/12),"") -> -1929.4209 | ... M15: =IFERROR(IF('3-Year P&L'!$B$9="","",-Financing!$B$45/12),"") -> -1929.4209 | N15: =IFERROR(IF('3-Year P&L'!$B$9="","",SUM(B15:M15)),"") -> -23153.051
A16: Sales tax collected (memo) | B16: =IFERROR(IF('3-Year P&L'!$B$9="","",'3-Year P&L'!$B$9*B7*SUMPRODUCT('3-Year P&L'!$E$10:$E$11,'3-Year P&L'!$G$10:$G$11)),"") -> 2877.96 | C16: =IFERROR(IF('3-Year P&L'!$B$9="","",'3-Year P&L'!$B$9*C7*SUMPRODUCT('3-Year P&L'!$E$10:$E$11,'3-Year P&L'!$G$10:$G$11)),"") -> 3558.2051 | D16: =IFERROR(IF('3-Year P&L'!$B$9="","",'3-Year P&L'!$B$9*D7*SUMPRODUCT('3-Year P&L'!$E$10:$E$11,'3-Year P&L'!$G$10:$G$11)),"") -> 4655.4273 | E16: =IFERROR(IF('3-Year P&L'!$B$9="","",'3-Year P&L'!$B$9*E7*SUMPRODUCT('3-Year P&L'!$E$10:$E$11,'3-Year P&L'!$G$10:$G$11)),"") -> 5363.4709 | F16: =IFERROR(IF('3-Year P&L'!$B$9="","",'3-Year P&L'!$B$9*F7*SUMPRODUCT('3-Year P&L'!$E$10:$E$11,'3-Year P&L'!$G$10:$G$11)),"") -> 6398.5553 | G16: =IFERROR(IF('3-Year P&L'!$B$9="","",'3-Year P&L'!$B$9*G7*SUMPRODUCT('3-Year P&L'!$E$10:$E$11,'3-Year P&L'!$G$10:$G$11)),"") -> 7603.7011 | H16: =IFERROR(IF('3-Year P&L'!$B$9="","",'3-Year P&L'!$B$9*H7*SUMPRODUCT('3-Year P&L'!$E$10:$E$11,'3-Year P&L'!$G$10:$G$11)),"") -> 8012.5022 | I16: =IFERROR(IF('3-Year P&L'!$B$9="","",'3-Year P&L'!$B$9*I7*SUMPRODUCT('3-Year P&L'!$E$10:$E$11,'3-Year P&L'!$G$10:$G$11)),"") -> 7603.7011 | ... M16: =IFERROR(IF('3-Year P&L'!$B$9="","",'3-Year P&L'!$B$9*M7*SUMPRODUCT('3-Year P&L'!$E$10:$E$11,'3-Year P&L'!$G$10:$G$11)),"") -> 8176.0227 | N16: =IFERROR(IF('3-Year P&L'!$B$9="","",SUM(B16:M16)),"") -> 73872 | O16: Each sales line at ITS OWN rate, read from the sales tax column of the P&L (alcohol to go has its own rate cell in the Assumptions tab)
A17: Recoverable input tax (memo) | B17: =IFERROR(IF('3-Year P&L'!$B$9="","",'3-Year P&L'!$B$38*B7+'3-Year P&L'!$B$39/12),"") -> 0 | C17: =IFERROR(IF('3-Year P&L'!$B$9="","",'3-Year P&L'!$B$38*C7+'3-Year P&L'!$B$39/12),"") -> 0 | D17: =IFERROR(IF('3-Year P&L'!$B$9="","",'3-Year P&L'!$B$38*D7+'3-Year P&L'!$B$39/12),"") -> 0 | E17: =IFERROR(IF('3-Year P&L'!$B$9="","",'3-Year P&L'!$B$38*E7+'3-Year P&L'!$B$39/12),"") -> 0 | F17: =IFERROR(IF('3-Year P&L'!$B$9="","",'3-Year P&L'!$B$38*F7+'3-Year P&L'!$B$39/12),"") -> 0 | G17: =IFERROR(IF('3-Year P&L'!$B$9="","",'3-Year P&L'!$B$38*G7+'3-Year P&L'!$B$39/12),"") -> 0 | H17: =IFERROR(IF('3-Year P&L'!$B$9="","",'3-Year P&L'!$B$38*H7+'3-Year P&L'!$B$39/12),"") -> 0 | I17: =IFERROR(IF('3-Year P&L'!$B$9="","",'3-Year P&L'!$B$38*I7+'3-Year P&L'!$B$39/12),"") -> 0 | ... M17: =IFERROR(IF('3-Year P&L'!$B$9="","",'3-Year P&L'!$B$38*M7+'3-Year P&L'!$B$39/12),"") -> 0 | N17: =IFERROR(IF('3-Year P&L'!$B$9="","",SUM(B17:M17)),"") -> 0 | O17: Each item at its own rate, read from the tax column of the P&L: insurance and card processing fees carry none
A18: Carried forward (capex input tax included) | E18: =IFERROR(IF('3-Year P&L'!$B$9="","",'Startup Costs'!$B$32),"") -> 0 | H18: =IFERROR(IF('3-Year P&L'!$B$9="","",MAX(0,-E19)),"") -> 0 | K18: =IFERROR(IF('3-Year P&L'!$B$9="","",MAX(0,-H19)),"") -> 0 | O18: Sales tax paid on STARTUP COSTS enters here: it is offset against the tax collected in later quarters until used up. With 0% recoverable input tax (the US default) this line stays at zero
A19: Quarterly sales tax return | E19: =IFERROR(IF('3-Year P&L'!$B$9="","",SUM(B16:D16)-SUM(B17:D17)-E18),"") -> 11091.592 | H19: =IFERROR(IF('3-Year P&L'!$B$9="","",SUM(E16:G16)-SUM(E17:G17)-H18),"") -> 19365.727 | K19: =IFERROR(IF('3-Year P&L'!$B$9="","",SUM(H16:J16)-SUM(H17:J17)-K18),"") -> 22402.302 | O19: Sales tax collected minus recoverable input tax for the quarter, minus what was carried forward. If negative, nothing is paid: it is offset in the next quarter. With 0% recoverable input tax (the US default) it equals the sales tax collected in the quarter
A20: Sales tax remitted (quarterly filer) | E20: =IFERROR(IF('3-Year P&L'!$B$9="","",IF(E19<=0,"",-E19)),"") -> -11091.592 | H20: =IFERROR(IF('3-Year P&L'!$B$9="","",IF(H19<=0,"",-H19)),"") -> -19365.727 | K20: =IFERROR(IF('3-Year P&L'!$B$9="","",IF(K19<=0,"",-K19)),"") -> -22402.302 | N20: =IFERROR(IF('3-Year P&L'!$B$9="","",SUM(B20:M20)),"") -> -52859.622 | O20: Cash only leaves when the quarter's result is positive. Months without a settlement are left blank, not zero. The cell turns RED when the payment takes more cash than is left that month. The model settles quarterly, in the month after each plan quarter (Months 4, 7 and 10, and the fourth quarter in Month 13: April, July, October and January when Month 1 is January): if your state requires monthly filing, expect smaller payments every month instead
A21: MONTHLY NET CASH FLOW | B21: =IFERROR(IF('3-Year P&L'!$B$9="","",SUM(B9:B15)+IF(B20="",0,B20)),"") -> -12596.122 | C21: =IFERROR(IF('3-Year P&L'!$B$9="","",SUM(C9:C15)+IF(C20="",0,C20)),"") -> -8884.7313 | D21: =IFERROR(IF('3-Year P&L'!$B$9="","",SUM(D9:D15)+IF(D20="",0,D20)),"") -> 2321.4071 | E21: =IFERROR(IF('3-Year P&L'!$B$9="","",SUM(E9:E15)+IF(E20="",0,E20)),"") -> -2406.055 | F21: =IFERROR(IF('3-Year P&L'!$B$9="","",SUM(F9:F15)+IF(F20="",0,F20)),"") -> 19169.672 | G21: =IFERROR(IF('3-Year P&L'!$B$9="","",SUM(G9:G15)+IF(G20="",0,G20)),"") -> 31098.705 | H21: =IFERROR(IF('3-Year P&L'!$B$9="","",SUM(H9:H15)+IF(H20="",0,H20)),"") -> 14654.275 | I21: =IFERROR(IF('3-Year P&L'!$B$9="","",SUM(I9:I15)+IF(I20="",0,I20)),"") -> 28972.33 | ... M21: =IFERROR(IF('3-Year P&L'!$B$9="","",SUM(M9:M15)+IF(M20="",0,M20)),"") -> 37547.139 | N21: =IFERROR(IF('3-Year P&L'!$B$9="","",SUM(B21:M21)),"") -> 143313.84
A22: CUMULATIVE CASH BALANCE | B22: =IFERROR(IF('3-Year P&L'!$B$9="","",'Startup Costs'!$B$29+B21),"") -> 114635.68 | C22: =IFERROR(IF('3-Year P&L'!$B$9="","",B22+C21),"") -> 105750.95 | D22: =IFERROR(IF('3-Year P&L'!$B$9="","",C22+D21),"") -> 108072.35 | E22: =IFERROR(IF('3-Year P&L'!$B$9="","",D22+E21),"") -> 105666.3 | F22: =IFERROR(IF('3-Year P&L'!$B$9="","",E22+F21),"") -> 124835.97 | G22: =IFERROR(IF('3-Year P&L'!$B$9="","",F22+G21),"") -> 155934.68 | H22: =IFERROR(IF('3-Year P&L'!$B$9="","",G22+H21),"") -> 170588.95 | I22: =IFERROR(IF('3-Year P&L'!$B$9="","",H22+I21),"") -> 199561.28 | J22: =IFERROR(IF('3-Year P&L'!$B$9="","",I22+J21),"") -> 220054.05 | ... M22: =IFERROR(IF('3-Year P&L'!$B$9="","",L22+M21),"") -> 270545.64
A23: Minimum balance of the year | B23: =IFERROR(IF('3-Year P&L'!$B$9="","",IF(COUNT(B22:M22)=0,"",MIN(B22:M22))),"") -> 105666.3 | D23: If negative, raise working capital or the loan: you run out of cash
A24: Month when cash bottoms out | B24: =IFERROR(IF('3-Year P&L'!$B$9="","",IF(COUNT(B22:M22)=0,"",MATCH(MIN(B22:M22),B22:M22,0))),"") -> 4 | D24: It answers the question that decides a bank deal: in which month the cash runs out
A25: RETURN ON INVESTMENT
A26: Free cash flow before debt, year 1 | B26: =IFERROR(IF('3-Year P&L'!$B$9="","",'3-Year P&L'!$B$47+'3-Year P&L'!$B$35+Financing!$B$44),"") -> 146463.38 | D26: Net income plus depreciation (which is not paid) plus that year's interest: principal is not subtracted because this flow is BEFORE debt. The SAME basis as years 2 and 3, so the payback compares like with like
A27: Free cash flow before debt, year 2 | B27: =IFERROR(IF('3-Year P&L'!$B$9="","",'3-Year P&L'!$C$47+'3-Year P&L'!$C$35+Financing!$B$46),"") -> 213790.65 | D27: Net income plus depreciation (which is not paid) plus that year's interest: principal is not subtracted because this flow is BEFORE debt. Without a monthly table, it is an estimate
A28: Free cash flow before debt, year 3 | B28: =IFERROR(IF('3-Year P&L'!$B$9="","",'3-Year P&L'!$D$47+'3-Year P&L'!$D$35+Financing!$B$48),"") -> 264165.29 | D28: Net income plus depreciation (which is not paid) plus that year's interest: principal is not subtracted because this flow is BEFORE debt. Without a monthly table, it is an estimate
A29: For reference: ACTUAL year-1 cash flow (monthly table, before debt) | B29: =IFERROR(IF('3-Year P&L'!$B$9="","",N21+Financing!$B$44+Financing!$B$45),"") -> 203366.89 | D29: The sum of the twelve monthly net cash flows above, adding back the interest and principal paid that year. It is NOT the one the payback uses: it includes sales tax not yet settled and supplier credit, two things that have to be paid back and that years 2 and 3 do not have
A30: Investment to recover (net of recoverable input tax) | B30: =IFERROR(IF('3-Year P&L'!$B$9="","",'Startup Costs'!$B$33-'Startup Costs'!$B$32),"") -> 488931.8 | D30: CAPEX plus working capital: the total cash needed MINUS the recoverable input tax on startup costs, which is not lost (it is recovered through the quarterly return, and this tab offsets it quarter by quarter; it is zero in the US default). Working capital is recovered when you close, but until then it is tied up
A31: Project payback (years), before debt | B31: =IFERROR(IF('3-Year P&L'!$B$9="","",IF(B26>=B30,ROUND(B30/B26,1),IF(B26+B27>=B30,ROUND(1+(B30-B26)/B27,1),IF(B26+B27+B28>=B30,ROUND(2+(B30-B26-B27)/B28,1),"Over 3 years")))),"") -> 2.5 | D31: Measures how long the business takes to repay the investment with what it generates BEFORE paying the lender, on the SAME cash flow basis in all three years. Whether you can afford the loan payment is shown by the DSCR in the Financing tab
A32: Payback on CAPEX, excluding working capital (years) | B32: =IFERROR(IF('3-Year P&L'!$B$9="","",IF(B26>='Startup Costs'!$B$31,ROUND('Startup Costs'!$B$31/B26,1),IF(B26+B27>='Startup Costs'!$B$31,ROUND(1+('Startup Costs'!$B$31-B26)/B27,1),IF(B26+B27+B28>='Startup Costs'!$B$31,ROUND(2+('Startup Costs'!$B$31-B26-B27)/B28,1),"Over 3 years")))),"") -> 2 | D32: The same calculation on what you BUY (build-out, equipment, launch and formation costs), without working capital: that money is not spent, it is tied up and comes back when the business closes. For reference only: the payback that matters is the one above
A34: Fourth-quarter sales tax is settled in Month 13 (January of the following year when Month 1 is January), so it does not appear in this table. The model pays year-1 income tax in July of year 2 (a simplification: estimated tax payments are usually quarterly). The loan payment is spread in twelve equal parts following the ANNUAL schedule in the Financing tab, and payroll in twelve monthly installments (plus extra pay periods in their month, only if pay periods > 12).

Sheet Financing
A1: FINANCING PLAN
A2: What you need, where it comes from and what it costs to repay. It is the sheet your lender asks for along with the P&L.
A4: Item | B4: Amount | C4: Notes
A5: SOURCES OF FUNDS
A6: Owner's equity (your own money) | B6: =IFERROR(IF('0. Assumptions'!$B$30="","",'0. Assumptions'!$B$30),"") -> 120000
A7: Loan requested — bank or SBA 7(a) (amortized below) | B7: =IFERROR(IF('0. Assumptions'!$B$31="","",'0. Assumptions'!$B$31),"") -> 369000
A8: Other loan (not in the schedule or the DSCR — enter your loan in row 7) | B8: 0 | C8: A source of funds only: NOT amortized, so it is not in the schedule, the P&L interest or the DSCR. Enter your bank or SBA 7(a) loan in row 7 ("Loan requested" in "0. Assumptions"); use this row only for a second loan
A9: SBA Microloan (not in the schedule or the DSCR — enter your loan in row 7) | B9: 0 | C9: SBA Microloans go up to $50,000 through nonprofit intermediaries. Like row 8, a source of funds only: not in the schedule or the DSCR. If it is your only loan, enter it in row 7 instead
A10: Investors / partners (equity: dilutes, not repaid) | B10: 0 | C10: Equity: it dilutes your ownership and is not repaid
A11: Local grants (usually paid after you spend) | B11: 0 | C11: Usually paid AFTER you document the spending
A12: TOTAL SOURCES OF FUNDS | B12: =IFERROR(IF(COUNT(B6:B11)=0,"",SUM(B6:B11)),"") -> 489000
A13: USES OF FUNDS
A14: Total cash needed at launch | B14: =IFERROR(IF('Startup Costs'!$B$33="","",'Startup Costs'!$B$33),"") -> 488931.8 | C14: Startup costs plus any recoverable tax you have to advance (zero by default in the US)
A15: Difference (sources - uses) | B15: =IFERROR(B12-B14,"") -> 68.2 | C15: In red (negative), the plan is NOT funded. Far above zero is not free either: you pay interest on money you do not use
A16: Difference as a % of uses | B16: =IFERROR(B15/B14,"") -> 0.00013948776 | C16: Amber above the margin you set: it is debt you pay for without needing it
A17: Acceptable over-funding (%) | B17: 0.05 | C17: A small cushion over the need is healthy; 20% extra is interest thrown away
A18: Loan that would match sources to needs | B18: =IFERROR(MAX(0,B14-B12+B7),"") -> 368931.8 | C18: Copy it into "Loan requested" in the "0. Assumptions" tab and the difference goes to zero. Rows 8-11 lower this figure, but only the row-7 loan is amortized and counted in the DSCR
A19: LOAN TERMS
A20: Principal amount | B20: =IFERROR(IF('0. Assumptions'!$B$31=0,"",'0. Assumptions'!$B$31),"") -> 369000
A21: Nominal annual interest rate (not APR) | B21: =IFERROR(IF('0. Assumptions'!$B$32="","",'0. Assumptions'!$B$32),"") -> 0.1
A22: Total term (years) | B22: =IFERROR(IF('0. Assumptions'!$B$33="","",'0. Assumptions'!$B$33),"") -> 10
A23: Interest-only period applied (years) | B23: =IFERROR(IF(OR('0. Assumptions'!$B$34="",'0. Assumptions'!$B$33=""),"",IF('0. Assumptions'!$B$34>='0. Assumptions'!$B$33,0,'0. Assumptions'!$B$34)),"") -> 0 | C23: An interest-only period equal to or longer than the term does not exist: the sheet cancels it at the source
A24: Annual payment during repayment | B24: =IFERROR(IF(B22-B23<=0,"",IF(B21=0,B20/(B22-B23),B20*B21/(1-(1+B21)^-(B22-B23)))),"") -> 60053.051 | C24: Standard amortizing loan with a level annual payment. At a 0% rate it is the principal divided by the repayment years: without that branch the schedule would shut down entirely
A25: AMORTIZATION SCHEDULE
A26: Year | B26: Opening balance | C26: Interest | D26: Principal repaid | E26: Total payment | F26: Closing balance | G26: Cash flow available for debt service (after tax; from year 4 on, year 3 held flat) | H26: DSCR for the year
A27: 1 | B27: =IFERROR(IF(B20="","",B20),"") -> 369000 | C27: =IFERROR(IF(OR(1>B22,B27=""),"",B27*B21),"") -> 36900 | D27: =IFERROR(IF(OR(1>B22,B27=""),"",IF(1<=B23,0,MIN(B27,B24-C27))),"") -> 23153.051 | E27: =IFERROR(IF(C27="","",C27+D27),"") -> 60053.051 | F27: =IFERROR(IF(D27="","",B27-D27),"") -> 345846.95 | G27: =IFERROR(IF(E27="","",'3-Year P&L'!$B$40-'3-Year P&L'!$B$45+'3-Year P&L'!$B$35+'3-Year P&L'!$B$36),"") -> 146463.38 | H27: =IFERROR(IF(OR(E27="",E27=0),"",G27/E27),"") -> 2.4388999
A28: 2 | B28: =IFERROR(IF(OR(2>B22,F27=""),"",F27),"") -> 345846.95 | C28: =IFERROR(IF(OR(2>B22,B28=""),"",B28*B21),"") -> 34584.695 | D28: =IFERROR(IF(OR(2>B22,B28=""),"",IF(2<=B23,0,MIN(B28,B24-C28))),"") -> 25468.356 | E28: =IFERROR(IF(C28="","",C28+D28),"") -> 60053.051 | F28: =IFERROR(IF(D28="","",B28-D28),"") -> 320378.59 | G28: =IFERROR(IF(E28="","",'3-Year P&L'!$C$40-'3-Year P&L'!$C$45+'3-Year P&L'!$C$35+'3-Year P&L'!$C$36),"") -> 213790.65 | H28: =IFERROR(IF(OR(E28="",E28=0),"",G28/E28),"") -> 3.5600299
A29: 3 | B29: =IFERROR(IF(OR(3>B22,F28=""),"",F28),"") -> 320378.59 | C29: =IFERROR(IF(OR(3>B22,B29=""),"",B29*B21),"") -> 32037.859 | D29: =IFERROR(IF(OR(3>B22,B29=""),"",IF(3<=B23,0,MIN(B29,B24-C29))),"") -> 28015.191 | E29: =IFERROR(IF(C29="","",C29+D29),"") -> 60053.051 | F29: =IFERROR(IF(D29="","",B29-D29),"") -> 292363.4 | G29: =IFERROR(IF(E29="","",'3-Year P&L'!$D$40-'3-Year P&L'!$D$45+'3-Year P&L'!$D$35+'3-Year P&L'!$D$36),"") -> 264165.29 | H29: =IFERROR(IF(OR(E29="",E29=0),"",G29/E29),"") -> 4.3988655
A30: 4 | B30: =IFERROR(IF(OR(4>B22,F29=""),"",F29),"") -> 292363.4 | C30: =IFERROR(IF(OR(4>B22,B30=""),"",B30*B21),"") -> 29236.34 | D30: =IFERROR(IF(OR(4>B22,B30=""),"",IF(4<=B23,0,MIN(B30,B24-C30))),"") -> 30816.71 | E30: =IFERROR(IF(C30="","",C30+D30),"") -> 60053.051 | F30: =IFERROR(IF(D30="","",B30-D30),"") -> 261546.69 | G30: =IFERROR(IF(E30="","",'3-Year P&L'!$D$40-'3-Year P&L'!$D$45+'3-Year P&L'!$D$35+'3-Year P&L'!$D$36),"") -> 264165.29 | H30: =IFERROR(IF(OR(E30="",E30=0),"",G30/E30),"") -> 4.3988655
A31: 5 | B31: =IFERROR(IF(OR(5>B22,F30=""),"",F30),"") -> 261546.69 | C31: =IFERROR(IF(OR(5>B22,B31=""),"",B31*B21),"") -> 26154.669 | D31: =IFERROR(IF(OR(5>B22,B31=""),"",IF(5<=B23,0,MIN(B31,B24-C31))),"") -> 33898.382 | E31: =IFERROR(IF(C31="","",C31+D31),"") -> 60053.051 | F31: =IFERROR(IF(D31="","",B31-D31),"") -> 227648.31 | G31: =IFERROR(IF(E31="","",'3-Year P&L'!$D$40-'3-Year P&L'!$D$45+'3-Year P&L'!$D$35+'3-Year P&L'!$D$36),"") -> 264165.29 | H31: =IFERROR(IF(OR(E31="",E31=0),"",G31/E31),"") -> 4.3988655
A32: 6 | B32: =IFERROR(IF(OR(6>B22,F31=""),"",F31),"") -> 227648.31 | C32: =IFERROR(IF(OR(6>B22,B32=""),"",B32*B21),"") -> 22764.831 | D32: =IFERROR(IF(OR(6>B22,B32=""),"",IF(6<=B23,0,MIN(B32,B24-C32))),"") -> 37288.22 | E32: =IFERROR(IF(C32="","",C32+D32),"") -> 60053.051 | F32: =IFERROR(IF(D32="","",B32-D32),"") -> 190360.09 | G32: =IFERROR(IF(E32="","",'3-Year P&L'!$D$40-'3-Year P&L'!$D$45+'3-Year P&L'!$D$35+'3-Year P&L'!$D$36),"") -> 264165.29 | H32: =IFERROR(IF(OR(E32="",E32=0),"",G32/E32),"") -> 4.3988655
A33: 7 | B33: =IFERROR(IF(OR(7>B22,F32=""),"",F32),"") -> 190360.09 | C33: =IFERROR(IF(OR(7>B22,B33=""),"",B33*B21),"") -> 19036.009 | D33: =IFERROR(IF(OR(7>B22,B33=""),"",IF(7<=B23,0,MIN(B33,B24-C33))),"") -> 41017.042 | E33: =IFERROR(IF(C33="","",C33+D33),"") -> 60053.051 | F33: =IFERROR(IF(D33="","",B33-D33),"") -> 149343.05 | G33: =IFERROR(IF(E33="","",'3-Year P&L'!$D$40-'3-Year P&L'!$D$45+'3-Year P&L'!$D$35+'3-Year P&L'!$D$36),"") -> 264165.29 | H33: =IFERROR(IF(OR(E33="",E33=0),"",G33/E33),"") -> 4.3988655
A34: 8 | B34: =IFERROR(IF(OR(8>B22,F33=""),"",F33),"") -> 149343.05 | C34: =IFERROR(IF(OR(8>B22,B34=""),"",B34*B21),"") -> 14934.305 | D34: =IFERROR(IF(OR(8>B22,B34=""),"",IF(8<=B23,0,MIN(B34,B24-C34))),"") -> 45118.746 | E34: =IFERROR(IF(C34="","",C34+D34),"") -> 60053.051 | F34: =IFERROR(IF(D34="","",B34-D34),"") -> 104224.3 | G34: =IFERROR(IF(E34="","",'3-Year P&L'!$D$40-'3-Year P&L'!$D$45+'3-Year P&L'!$D$35+'3-Year P&L'!$D$36),"") -> 264165.29 | H34: =IFERROR(IF(OR(E34="",E34=0),"",G34/E34),"") -> 4.3988655
A35: 9 | B35: =IFERROR(IF(OR(9>B22,F34=""),"",F34),"") -> 104224.3 | C35: =IFERROR(IF(OR(9>B22,B35=""),"",B35*B21),"") -> 10422.43 | D35: =IFERROR(IF(OR(9>B22,B35=""),"",IF(9<=B23,0,MIN(B35,B24-C35))),"") -> 49630.62 | E35: =IFERROR(IF(C35="","",C35+D35),"") -> 60053.051 | F35: =IFERROR(IF(D35="","",B35-D35),"") -> 54593.682 | G35: =IFERROR(IF(E35="","",'3-Year P&L'!$D$40-'3-Year P&L'!$D$45+'3-Year P&L'!$D$35+'3-Year P&L'!$D$36),"") -> 264165.29 | H35: =IFERROR(IF(OR(E35="",E35=0),"",G35/E35),"") -> 4.3988655
A36: 10 | B36: =IFERROR(IF(OR(10>B22,F35=""),"",F35),"") -> 54593.682 | C36: =IFERROR(IF(OR(10>B22,B36=""),"",B36*B21),"") -> 5459.3682 | D36: =IFERROR(IF(OR(10>B22,B36=""),"",IF(10<=B23,0,MIN(B36,B24-C36))),"") -> 54593.682 | E36: =IFERROR(IF(C36="","",C36+D36),"") -> 60053.051 | F36: =IFERROR(IF(D36="","",B36-D36),"") -> 6.0390448e-10 | G36: =IFERROR(IF(E36="","",'3-Year P&L'!$D$40-'3-Year P&L'!$D$45+'3-Year P&L'!$D$35+'3-Year P&L'!$D$36),"") -> 264165.29 | H36: =IFERROR(IF(OR(E36="",E36=0),"",G36/E36),"") -> 4.3988655
A37: 11 | B37: =IFERROR(IF(OR(11>B22,F36=""),"",F36),"") | C37: =IFERROR(IF(OR(11>B22,B37=""),"",B37*B21),"") | D37: =IFERROR(IF(OR(11>B22,B37=""),"",IF(11<=B23,0,MIN(B37,B24-C37))),"") | E37: =IFERROR(IF(C37="","",C37+D37),"") | F37: =IFERROR(IF(D37="","",B37-D37),"") | G37: =IFERROR(IF(E37="","",'3-Year P&L'!$D$40-'3-Year P&L'!$D$45+'3-Year P&L'!$D$35+'3-Year P&L'!$D$36),"") | H37: =IFERROR(IF(OR(E37="",E37=0),"",G37/E37),"")
A38: 12 | B38: =IFERROR(IF(OR(12>B22,F37=""),"",F37),"") | C38: =IFERROR(IF(OR(12>B22,B38=""),"",B38*B21),"") | D38: =IFERROR(IF(OR(12>B22,B38=""),"",IF(12<=B23,0,MIN(B38,B24-C38))),"") | E38: =IFERROR(IF(C38="","",C38+D38),"") | F38: =IFERROR(IF(D38="","",B38-D38),"") | G38: =IFERROR(IF(E38="","",'3-Year P&L'!$D$40-'3-Year P&L'!$D$45+'3-Year P&L'!$D$35+'3-Year P&L'!$D$36),"") | H38: =IFERROR(IF(OR(E38="",E38=0),"",G38/E38),"")
A39: 13 | B39: =IFERROR(IF(OR(13>B22,F38=""),"",F38),"") | C39: =IFERROR(IF(OR(13>B22,B39=""),"",B39*B21),"") | D39: =IFERROR(IF(OR(13>B22,B39=""),"",IF(13<=B23,0,MIN(B39,B24-C39))),"") | E39: =IFERROR(IF(C39="","",C39+D39),"") | F39: =IFERROR(IF(D39="","",B39-D39),"") | G39: =IFERROR(IF(E39="","",'3-Year P&L'!$D$40-'3-Year P&L'!$D$45+'3-Year P&L'!$D$35+'3-Year P&L'!$D$36),"") | H39: =IFERROR(IF(OR(E39="",E39=0),"",G39/E39),"")
A40: 14 | B40: =IFERROR(IF(OR(14>B22,F39=""),"",F39),"") | C40: =IFERROR(IF(OR(14>B22,B40=""),"",B40*B21),"") | D40: =IFERROR(IF(OR(14>B22,B40=""),"",IF(14<=B23,0,MIN(B40,B24-C40))),"") | E40: =IFERROR(IF(C40="","",C40+D40),"") | F40: =IFERROR(IF(D40="","",B40-D40),"") | G40: =IFERROR(IF(E40="","",'3-Year P&L'!$D$40-'3-Year P&L'!$D$45+'3-Year P&L'!$D$35+'3-Year P&L'!$D$36),"") | H40: =IFERROR(IF(OR(E40="",E40=0),"",G40/E40),"")
A41: 15 | B41: =IFERROR(IF(OR(15>B22,F40=""),"",F40),"") | C41: =IFERROR(IF(OR(15>B22,B41=""),"",B41*B21),"") | D41: =IFERROR(IF(OR(15>B22,B41=""),"",IF(15<=B23,0,MIN(B41,B24-C41))),"") | E41: =IFERROR(IF(C41="","",C41+D41),"") | F41: =IFERROR(IF(D41="","",B41-D41),"") | G41: =IFERROR(IF(E41="","",'3-Year P&L'!$D$40-'3-Year P&L'!$D$45+'3-Year P&L'!$D$35+'3-Year P&L'!$D$36),"") | H41: =IFERROR(IF(OR(E41="",E41=0),"",G41/E41),"")
A42: Schedule closing tolerance | B42: 0.01 | C42: Rounding margin. Above it, the schedule does not close and there is principal left unpaid
A43: Balance outstanding at maturity | B43: =IFERROR(IF(B20="","",ROUND(B20-SUM(D27:D41),2)),"") -> 0 | C43: Must be zero: the principal repaid in the schedule has to equal the amount borrowed. If it is positive, the term falls short
A44: Year-1 interest | B44: =IFERROR(IF(B20="","",IF(C27="",0,C27)),"") -> 36900
A45: Year-1 principal repaid | B45: =IFERROR(IF(B20="","",IF(D27="",0,D27)),"") -> 23153.051
A46: Year-2 interest | B46: =IFERROR(IF(B20="","",IF(C28="",0,C28)),"") -> 34584.695
A47: Year-2 principal repaid | B47: =IFERROR(IF(B20="","",IF(D28="",0,D28)),"") -> 25468.356
A48: Year-3 interest | B48: =IFERROR(IF(B20="","",IF(C29="",0,C29)),"") -> 32037.859
A49: Year-3 principal repaid | B49: =IFERROR(IF(B20="","",IF(D29="",0,D29)),"") -> 28015.191
A50: DEBT SERVICE COVERAGE RATIO (DSCR)
A51: Year-1 DSCR | B51: =IFERROR(('3-Year P&L'!$B$40-'3-Year P&L'!$B$45+'3-Year P&L'!$B$35+B44)/(B44+B45),"") -> 2.4388999 | C51: An INTEREST-ONLY year, if there is one: with only interest in the denominator the ratio shoots up and does not measure the business
A52: Year-2 DSCR | B52: =IFERROR(('3-Year P&L'!$C$40-'3-Year P&L'!$C$45+'3-Year P&L'!$C$35+B46)/(B46+B47),"") -> 3.5600299
A53: Year-3 DSCR | B53: =IFERROR(('3-Year P&L'!$D$40-'3-Year P&L'!$D$45+'3-Year P&L'!$D$35+B48)/(B48+B49),"") -> 4.3988655
A54: Minimum DSCR across the whole schedule | B54: =IFERROR(IF(COUNT(H27:H41)=0,"",MIN(H27:H41)),"") -> 2.4388999 | C54: The worst year of the life of the loan, not the best of the three the P&L projects. It is the number that decides a loan. Mind the scope: years 1 to 3 come from the P&L, and from year 4 on the schedule HOLDS year 3's cash flow, so the minimum over those years is a sustained projection, not a calculated year. The cash flow is after tax
A56: DSCR is calculated BEFORE debt and AFTER tax: income tax is subtracted from pre-tax income, depreciation and interest are added back, and the result is divided by what has to be paid that year. Below the minimum in the "0. Assumptions" tab, the business does not generate enough to repay the loan. In the schedule, the available cash flow from year 4 on is held at year 3's: the P&L projects only three years, and no growth is invented here that has not been calculated.
