Workbook

Sheet Instrucciones
A1: Plan Financiero a 3 Años
A2: AI Chef Pro · aichef.pro — Cómo Montar una Churrería-Chocolatería
A3: Para qué sirve: saber si el negocio gana dinero en un año normal, cuánto tienes que poner el día que abres (con el fondo de maniobra), si aguanta el valle del primer año, si aguanta el banco y qué canal paga los fijos.
A5: Instrucciones de Uso
A6: Celdas verdes = campos editables
A7: Las celdas en crema son resultados que el libro calcula; las blancas con fórmula, también. No escribas encima.
A9: 1. Hoja «0. Supuestos». Arriba, las cifras que copias a mano de los libros 2, 3, 4, 5 y 8 (cada celda verde dice de qué celda exacta). Debajo, el calendario, la rampa de arranque, el fondo de maniobra, la financiación, los GASTOS FIJOS de cada mes (nacen aquí) y los escenarios. Al pie, el CUADRE: anota lo que publica hoy cada celda de origen y, si lo que usas se separa, la fila se pone en rojo.
A10: 2. Hoja «Inversión Inicial». El CAPEX del libro 2 más el fondo de maniobra, que se calcula aquí con los meses de colchón: es la inversión total que le enseñas al banco.
A11: 3. Hoja «PyG 3 Años». La cuenta de resultados: el año 1 con la rampa de arranque, el año 2 de crucero y el año 3. La primera pregunta es si el año 2 gana dinero, en euros.
A12: 4. Hoja «Punto de Equilibrio». Cuántas raciones al día pagan los fijos y qué meses del año no llegan.
A13: 5. Hoja «Escenarios». Tres escenarios de raciones, el verano con los fijos dentro (las tres salidas del libro 5: cerrar, carta de verano y ferias) y el local con sala frente a sólo despacho.
A14: 6. Hojas «Personal» y «Canales y Punto Muerto». Lo que pesa la plantilla y qué canal (sala, para llevar, ferias) paga los fijos.
... A53: Versión 1.0 · octubre 2026 · aichef.pro/guia-churreria-chocolateria · info@aichef.pro

Sheet 0. Supuestos
A1: Supuestos del Plan Financiero
A2: AI Chef Pro · aichef.pro — Cómo Montar una Churrería-Chocolatería
A3: Todo lo que el resto de hojas da por sabido vive aquí. Ninguna fórmula de este libro lleva dentro un tipo, un porcentaje, un número de meses ni un umbral.
A5: Supuesto | B5: Valor | C5: Unidad | D5: De dónde sale | E5: Nota
A6: Lo que Copias del Libro 2 (CAPEX y Renta)
A7: CAPEX de apertura SIN fondo de maniobra (base imponible) | B7: 86415.65 | C7: € | D7: cópialo del libro 2: calculadora-capex-churreria.xlsx!Resumen!L5 | E7: El total de los once bloques del libro 2, SIN fondo de maniobra: el fondo se calcula aquí y sólo aquí. Si copias un total que ya lo lleve, lo contarías dos veces.
A8: Renta mensual del local (sin IVA) | B8: 910 | C8: €/mes | D8: cópialo del libro 2: calculadora-capex-churreria.xlsx!Parámetros!L5 | E8: Nace en el libro 2 (con el traspaso y la fianza). Aquí entra en los fijos.
A9: Partidas del CAPEX que no se amortizan (fianza, stock inicial y marketing de apertura) | B9: 4668.3 | C9: € | D9: cópialo del libro 2: calculadora-capex-churreria.xlsx!Resumen!L6 | E9: Son los bloques 9, 10 y 11 de tu CAPEX: la fianza se recupera, el stock se vende y el marketing es gasto del primer año. Nace en el libro 2: si tu CAPEX cambia, cópiala de nuevo.
A10: Lo que Copias del Libro 3 (Carta y Escandallo)
A11: Coste de materia por ración en sala (invierno, aceite absorbido incluido) | B11: 0.27314864 | C11: €/ración | D11: cópialo del libro 3: carta-de-apertura-y-escandallo-churro.xlsx!Mix y Ticket Canal y Temporada!L9 | E11: Materia prima más el aceite que se queda en la masa. Sale del escandallo.
A12: Coste de materia por ración para llevar (invierno, aceite absorbido incluido) | B12: 0.30546293 | C12: €/ración | D12: cópialo del libro 3: carta-de-apertura-y-escandallo-churro.xlsx!Mix y Ticket Canal y Temporada!L8 | E12: Con el envase de llevar dentro. Sale del escandallo.
A13: Ticket sin IVA por ración en sala (invierno) | B13: 2.1480519 | C13: €/ración | D13: cópialo del libro 3: carta-de-apertura-y-escandallo-churro.xlsx!Mix y Ticket Canal y Temporada!L10 | E13: Base imponible media de una ración de la carta en sala.
A14: Ticket sin IVA por ración para llevar (invierno) | B14: 2.1924242 | C14: €/ración | D14: cópialo del libro 3: carta-de-apertura-y-escandallo-churro.xlsx!Mix y Ticket Canal y Temporada!L11 | E14: Base imponible media para llevar, con el vaso cobrado aparte.
A15: Raciones que se consumen en sala (el resto, para llevar) | B15: 0.7 | C15: % | D15: cópialo del libro 3: carta-de-apertura-y-escandallo-churro.xlsx!Mix y Ticket Canal y Temporada!L12 | E15: Se copia tal cual, con el formato de porcentaje (0,70 es el 70 %). Con él se mezclan el ticket y la materia de los dos canales.
A16: Lo que Copias del Libro 4 (Aceite de Fritura)
A17: Renovación del aceite por ración (el aceite que se tira al cambiar la cuba) | B17: 0.028398374 | C17: €/ración | D17: cópialo del libro 4: aceite-de-fritura-coste-y-cambio.xlsx!Consumo y Reposición!L5 | E17: Distinto del aceite absorbido, que ya va en la materia: es el descarte al cambiar el aceite.
A18: Lo que Copias del Libro 5 (Temporada, Verano y Ferias)
A19: Raciones de un año normal | B19: 107400 | C19: raciones | D19: cópialo del libro 5: temporada-franjas-y-ferias.xlsx!Peso sobre el Año!L5 | E19: Días tipo y días punta por su demanda base. Es un año normal: la rampa del primer año la pone este libro.
A20: Coeficiente de enero | B20: 1.25 | C20: coeficiente | D20: cópialo del libro 5: temporada-franjas-y-ferias.xlsx!Peso sobre el Año!L6 | E20: Reparte las raciones del año: los doce suman 12.
A21: Coeficiente de febrero | B21: 1.15 | C21: coeficiente | D21: cópialo del libro 5: temporada-franjas-y-ferias.xlsx!Peso sobre el Año!L7
A22: Coeficiente de marzo | B22: 1.1 | C22: coeficiente | D22: cópialo del libro 5: temporada-franjas-y-ferias.xlsx!Peso sobre el Año!L8
A23: Coeficiente de abril | B23: 0.95 | C23: coeficiente | D23: cópialo del libro 5: temporada-franjas-y-ferias.xlsx!Peso sobre el Año!L9
A24: Coeficiente de mayo | B24: 0.85 | C24: coeficiente | D24: cópialo del libro 5: temporada-franjas-y-ferias.xlsx!Peso sobre el Año!L10
A25: Coeficiente de junio | B25: 0.7 | C25: coeficiente | D25: cópialo del libro 5: temporada-franjas-y-ferias.xlsx!Peso sobre el Año!L11
A26: Coeficiente de julio | B26: 0.55 | C26: coeficiente | D26: cópialo del libro 5: temporada-franjas-y-ferias.xlsx!Peso sobre el Año!L12
A27: Coeficiente de agosto | B27: 0.5 | C27: coeficiente | D27: cópialo del libro 5: temporada-franjas-y-ferias.xlsx!Peso sobre el Año!L13
A28: Coeficiente de septiembre | B28: 0.8 | C28: coeficiente | D28: cópialo del libro 5: temporada-franjas-y-ferias.xlsx!Peso sobre el Año!L14
A29: Coeficiente de octubre | B29: 1.1 | C29: coeficiente | D29: cópialo del libro 5: temporada-franjas-y-ferias.xlsx!Peso sobre el Año!L15
A30: Coeficiente de noviembre | B30: 1.3 | C30: coeficiente | D30: cópialo del libro 5: temporada-franjas-y-ferias.xlsx!Peso sobre el Año!L16
A31: Coeficiente de diciembre | B31: 1.75 | C31: coeficiente | D31: cópialo del libro 5: temporada-franjas-y-ferias.xlsx!Peso sobre el Año!L17
A32: Resultado anual de ferias (las de fuera de julio y agosto) | B32: 0 | C32: € | D32: cópialo del libro 5: temporada-franjas-y-ferias.xlsx!Calendario de Ferias!L5 | E32: Una línea de canal. El punto muerto de cada evento vive en el libro 5; las ferias de julio y agosto van en la salida del verano.
A33: Contribución de julio y agosto de la salida que eliges | B33: 17368.709 | C33: € | D33: cópialo del libro 5: temporada-franjas-y-ferias.xlsx!El Verano (Tres Salidas)!L5 | E33: Ventas sin IVA menos materia de julio y agosto de la salida que eliges. Lo que pagas igual en las tres salidas lo resta este libro.
A34: Contribución de julio y agosto si cierras | B34: 0 | C34: € | D34: cópialo del libro 5: temporada-franjas-y-ferias.xlsx!El Verano (Tres Salidas)!L6 | E34: Cerrar deja cero por definición, salvo que cambies las banderas de la salida en el libro 5. Aquí se enseña con los fijos dentro, en «Escenarios».
A35: Contribución de julio y agosto con carta de verano | B35: 17368.709 | C35: € | D35: cópialo del libro 5: temporada-franjas-y-ferias.xlsx!El Verano (Tres Salidas)!L7 | E35: Ventas menos materia de julio y agosto con la carta de verano. Con ella y las dos de al lado, «Escenarios» enseña el verano con fijos de las tres salidas.
A36: Contribución de julio y agosto con ferias | B36: 2106.4537 | C36: € | D36: cópialo del libro 5: temporada-franjas-y-ferias.xlsx!El Verano (Tres Salidas)!L8 | E36: Lo que dejan las ferias de julio y agosto, ya con su materia, tasas, desplazamiento, montaje y personal.
A37: Ventas sin IVA del local en julio y agosto de la salida que eliges | B37: 20737.72 | C37: € | D37: cópialo del libro 5: temporada-franjas-y-ferias.xlsx!El Verano (Tres Salidas)!L9 | E37: Las ventas del local de julio y agosto con el ticket de la salida que eliges (carta de verano, cero si cierras o sales de ferias). Valoran el verano de las ventas del año.
A38: Lo que Copias del Libro 8 (Plantilla)
A39: Coste anual de la plantilla (Seguridad Social, refuerzos y sustituciones incluidos) | B39: 119350.2 | C39: €/año | D39: cópialo del libro 8: turnos-plantilla-y-madrugada.xlsx!Coste de Plantilla!L5 | E39: Con el suelo del SMI y el plus de nocturnidad ya aplicados en el libro 8. El titular va dentro como un puesto más; su cuota de autónomos, en los gastos fijos.
A41: Calendario, Arranque y Crecimiento
A42: Días del año | B42: 365 | C42: días | D42: calendario | E42: Un año normal.
A43: Días al año con el local cerrado | B43: 5 | C43: días | D43: supuesto declarado de El Molinete | E43: Cinco días al año con la persiana bajada, todos a la vez, para la limpieza a fondo y la puesta a punto de la línea. Los mismos que pones en «Parámetros» del libro 5.
A44: Meses del año (los cuenta la hoja: son los coeficientes) | B44: =COUNT('0. Supuestos'!$B$20:$B$31) -> 12 | C44: meses | D44: calculado | E44: Cuenta los doce coeficientes de arriba. Sirve para pasar de año a mes sin escribir un 12 dentro de ninguna fórmula.
A45: Mes de apertura (número del mes) | B45: 9 | C45: mes | D45: supuesto declarado de El Molinete | E45: Abre el 1 de septiembre: un mes de rodaje antes del pico de octubre a marzo y el valle de verano al final del año 1 (§3.6). El año 1 de este libro son los doce meses que empiezan aquí.
A46: Primer mes del verano (número del mes) | B46: 7 | C46: mes | D46: supuesto declarado de El Molinete | E46: El valle: julio. Son los meses de la contribución del verano (X16) y los mismos que pones en el libro 5.
A47: Segundo mes del verano (número del mes) | B47: 8 | C47: mes | D47: supuesto declarado de El Molinete | E47: Agosto.
A48: Ventas del primer mes sobre las de un mes normal (rampa) | B48: 0.55 | D48: heredado de la Guía de la Chocolatería (supuesto declarado) | E48: El primer mes vendes el 55 % de lo que venderás cuando el barrio te conozca.
A49: Meses hasta vender como un mes normal | B49: 6 | C49: meses | D49: heredado de la Guía de la Chocolatería (supuesto declarado) | E49: La rampa sube en línea recta desde el primer mes hasta este.
A50: Crecimiento de las raciones en el año 3 sobre el año 2 | B50: 0 | D50: supuesto declarado de este libro (sin crecimiento) | E50: A cero: el año 3 repite el año de crucero y sólo cambian los intereses. Si subes precios o ganas clientela, ponlo aquí; si lo hace tu competencia, en negativo.
A52: Fondo de Maniobra, Amortización e Inversión
A53: Meses de colchón (fondo de maniobra) | B53: 6 | C53: meses | D53: heredado de la Guía de la Chocolatería (supuesto declarado) | E53: Meses de gastos fijos de caja que hay que tener el día que abres. El fondo de maniobra se calcula SÓLO en el libro 6.
A54: Años de amortización del inmovilizado | B54: 10 | C54: años | D54: heredado de la Guía de la Chocolatería (supuesto declarado) | E54: Vida útil contable del inmovilizado.
A55: Año de crucero (el que da los intereses del fondo) | B55: 2 | C55: año | D55: heredado de la Guía de la Chocolatería (supuesto declarado) | E55: El año 1 va en rampa y con carencia: la foto de un año normal es el 2.
A57: Financiación
A58: Parte de la inversión total que pides al banco | B58: 0.6 | D58: heredado de la Guía de la Chocolatería (supuesto declarado) | E58: La estructura heredada de la hermana: 40 % de fondos propios y 60 % de préstamo.
A59: Parte que pones tú (recursos propios) | B59: =1-'0. Supuestos'!$B$58 -> 0.4 | D59: heredado de la Guía de la Chocolatería (supuesto declarado) | E59: Lo que no pides al banco. Se calcula: un solo dato para la estructura.
A60: Tipo de interés nominal anual | B60: 0.062 | D60: heredado de la Guía de la Chocolatería (supuesto declarado) | E60: Pide la oferta por escrito: con la TAE delante, no sólo el nominal.
A61: Plazo del préstamo (meses) | B61: 84 | C61: meses | D61: heredado de la Guía de la Chocolatería (supuesto declarado) | E61: El cuadro de «Financiación» tiene 84 filas: más plazo no cabe.
A62: Carencia de principal (meses en que sólo pagas intereses) | B62: 6 | C62: meses | D62: heredado de la Guía de la Chocolatería (supuesto declarado) | E62: Es lo que hace que la cuota no se coma la caja en la rampa del primer año. Es lo primero que hay que negociar.
A63: Préstamo bancario que pides (punto fijo) | B63: 99300 | C63: € | D63: calculado | E63: El 60 % de la inversión total, redondeado. Como la inversión lleva el fondo y el fondo lleva los intereses, la hoja «Financiación» te dice si esta cifra sigue siendo la que pide la estructura; si no, copia la suya aquí.
A64: Redondeo del préstamo (múltiplo de) | B64: 100 | C64: € | D64: calculado (redondeado a centenas) | E64: Los bancos conceden cifras redondas.
A65: Tolerancia del cierre del cuadro y del punto fijo | B65: 0.01 | C65: € | D65: heredado de la Guía de la Chocolatería (tolerancia de cierre del cuadro) | E65: Por debajo de esta diferencia, dos importes se dan por iguales.
A67: Gastos Fijos Mensuales (Nacen Sólo Aquí, sin IVA)
A68: Suministros: gas de la freidora | B68: 170 | C68: €/mes | D68: supuesto declarado de El Molinete | E68: Una freidora de gas de 25 L encendida dos turnos al día. Pide la simulación a la comercializadora con la potencia del proyecto.
A69: Suministros: electricidad | B69: 320 | C69: €/mes | D69: supuesto declarado de El Molinete | E69: Chocolateras, cafetera, extracción, frío y luz, con la potencia contratada.
A70: Suministros: agua | B70: 45 | C70: €/mes | D70: supuesto declarado de El Molinete | E70: Supuesto, sin fuente pública; pon el tuyo.
A71: Limpieza de conductos y campana | B71: 60 | C71: €/mes | D71: supuesto declarado de El Molinete + CUN-23 | E71: Dos limpiezas al año prorrateadas. En el ejemplo de Madrid la ordenanza pide al menos una al año.
A72: Mantenimiento de equipos y revisión del gas | B72: 90 | C72: €/mes | D72: supuesto declarado de El Molinete + CHN-48 | E72: Incluye la parte de la inspección periódica de la instalación receptora de gas, cada cinco años.
A73: Seguros (multirriesgo y responsabilidad civil) | B73: 75 | C73: €/mes | D73: supuesto declarado de El Molinete | E73: El seguro de responsabilidad civil va sin cifra con fuente, como en la hermana.
A74: Asesoría laboral, fiscal y contable | B74: 190 | C74: €/mes | D74: supuesto declarado de El Molinete | E74: Cuatro nóminas y la contabilidad.
A75: TPV, facturación y comisiones del datáfono | B75: 110 | C75: €/mes | D75: supuesto declarado de El Molinete + CHN-75 | E75: Con Verifactu en el horizonte: 2027, no 2026.
A76: Gestor de aceite usado | B76: 0 | C76: €/mes | D76: supuesto declarado de El Molinete + CUS-44h | E76: La recogida no cuesta: el gestor de ejemplo recoge gratis o con valoración. Lo que cuesta es no guardar los justificantes (CUN-27).
A77: Telefonía e internet | B77: 50 | C77: €/mes | D77: supuesto declarado de El Molinete | E77: Supuesto, sin fuente pública; pon el tuyo.
A78: Limpieza, papel y consumibles | B78: 160 | C78: €/mes | D78: supuesto declarado de El Molinete | E78: Supuesto, sin fuente pública; pon el tuyo.
A79: Publicidad y redes | B79: 120 | C79: €/mes | D79: supuesto declarado de El Molinete | E79: Supuesto, sin fuente pública; pon el tuyo.
... A82: Otros gastos de estructura | B82: 100 | C82: €/mes | D82: supuesto declarado de El Molinete | E82: Supuesto, sin fuente pública; pon el tuyo.
A83: TOTAL GASTOS FIJOS DEL MES (sin renta ni plantilla) | B83: =SUM(B68:B82) -> 1870 | C83: €/mes | D83: calculado | E83: La renta llega del libro 2 y la plantilla del libro 8: no están aquí.
A85: Escenarios
A86: Escenario pesimista: raciones sobre el año normal | B86: -0.15 | D86: supuesto declarado de este libro | E86: Un año entero yendo mal (un invierno templado, una obra en la calle), no un mal día.
A87: Escenario optimista: raciones sobre el año normal | B87: 0.1 | D87: supuesto declarado de este libro | E87: Más clientela con la misma plantilla.
A88: Ahorro de fijos al año si montas sólo despacho (sin sala) | B88: 0 | C88: €/año | D88: supuesto declarado de este libro | E88: A cero, «Escenarios» enseña lo que pierdes si el mismo local vende sólo para llevar. Sin sala te ahorras parte de la plantilla, de la renta y de la limpieza: pon aquí ese ahorro.
A90: Tolerancia de las Filas de CUADRE
A91: Tolerancia de las filas de CUADRE | B91: 0.02 | D91: heredado de la Guía de la Chocolatería (tolerancia de las filas de CUADRE) | E91: Por encima de esta desviación, la fila de CUADRE avisa de que lo que has copiado no es lo que publica el libro de origen.
A93: Cuadre de lo que Has Copiado
A94: Cuadre | B94: Lo que publica hoy la celda de origen (anótalo) | C94: Desviación | D94: Veredicto | E94: Si no cuadra
A95: CUADRE · CAPEX de apertura SIN fondo de maniobra (base imponible) (X10) | B95: 86415.65 | C95: =IFERROR(IF(B95=0,ABS('0. Supuestos'!$B$7-B95),ABS('0. Supuestos'!$B$7-B95)/ABS(B95)),"") -> 0 | D95: =IF(NOT(ISNUMBER(C95)),"",IF(C95<='0. Supuestos'!$B$91,"CUADRA","REVISA: no es lo que publica el libro 2")) -> CUADRA | E95: Vuelve a copiar la cifra de su celda de origen (libro 2, calculadora-capex-churreria.xlsx!Resumen!L5) en la fila 7, o anota aquí lo que publica hoy.
A96: CUADRE · Coste de materia por ración en sala (invierno, aceite absorbido incluido) (X11) | B96: 0.27314864 | C96: =IFERROR(IF(B96=0,ABS('0. Supuestos'!$B$11-B96),ABS('0. Supuestos'!$B$11-B96)/ABS(B96)),"") -> 0 | D96: =IF(NOT(ISNUMBER(C96)),"",IF(C96<='0. Supuestos'!$B$91,"CUADRA","REVISA: no es lo que publica el libro 3")) -> CUADRA | E96: Vuelve a copiar la cifra de su celda de origen (libro 3, carta-de-apertura-y-escandallo-churro.xlsx!Mix y Ticket Canal y Temporada!L9) en la fila 11, o anota aquí lo que publica hoy.
A97: CUADRE · Coste de materia por ración para llevar (invierno, aceite absorbido incluido) (X11) | B97: 0.30546293 | C97: =IFERROR(IF(B97=0,ABS('0. Supuestos'!$B$12-B97),ABS('0. Supuestos'!$B$12-B97)/ABS(B97)),"") -> 0 | D97: =IF(NOT(ISNUMBER(C97)),"",IF(C97<='0. Supuestos'!$B$91,"CUADRA","REVISA: no es lo que publica el libro 3")) -> CUADRA | E97: Vuelve a copiar la cifra de su celda de origen (libro 3, carta-de-apertura-y-escandallo-churro.xlsx!Mix y Ticket Canal y Temporada!L8) en la fila 12, o anota aquí lo que publica hoy.
A98: CUADRE · Ticket sin IVA por ración en sala (invierno) (X11) | B98: 2.1480519 | C98: =IFERROR(IF(B98=0,ABS('0. Supuestos'!$B$13-B98),ABS('0. Supuestos'!$B$13-B98)/ABS(B98)),"") -> 0 | D98: =IF(NOT(ISNUMBER(C98)),"",IF(C98<='0. Supuestos'!$B$91,"CUADRA","REVISA: no es lo que publica el libro 3")) -> CUADRA | E98: Vuelve a copiar la cifra de su celda de origen (libro 3, carta-de-apertura-y-escandallo-churro.xlsx!Mix y Ticket Canal y Temporada!L10) en la fila 13, o anota aquí lo que publica hoy.
A99: CUADRE · Ticket sin IVA por ración para llevar (invierno) (X11) | B99: 2.1924242 | C99: =IFERROR(IF(B99=0,ABS('0. Supuestos'!$B$14-B99),ABS('0. Supuestos'!$B$14-B99)/ABS(B99)),"") -> 0 | D99: =IF(NOT(ISNUMBER(C99)),"",IF(C99<='0. Supuestos'!$B$91,"CUADRA","REVISA: no es lo que publica el libro 3")) -> CUADRA | E99: Vuelve a copiar la cifra de su celda de origen (libro 3, carta-de-apertura-y-escandallo-churro.xlsx!Mix y Ticket Canal y Temporada!L11) en la fila 14, o anota aquí lo que publica hoy.
A100: CUADRE · Raciones que se consumen en sala (el resto, para llevar) (X11) | B100: 0.7 | C100: =IFERROR(IF(B100=0,ABS('0. Supuestos'!$B$15-B100),ABS('0. Supuestos'!$B$15-B100)/ABS(B100)),"") -> 0 | D100: =IF(NOT(ISNUMBER(C100)),"",IF(C100<='0. Supuestos'!$B$91,"CUADRA","REVISA: no es lo que publica el libro 3")) -> CUADRA | E100: Vuelve a copiar la cifra de su celda de origen (libro 3, carta-de-apertura-y-escandallo-churro.xlsx!Mix y Ticket Canal y Temporada!L12) en la fila 15, o anota aquí lo que publica hoy.
A101: CUADRE · Renovación del aceite por ración (el aceite que se tira al cambiar la cuba) (X12) | B101: 0.028398374 | C101: =IFERROR(IF(B101=0,ABS('0. Supuestos'!$B$17-B101),ABS('0. Supuestos'!$B$17-B101)/ABS(B101)),"") -> 0 | D101: =IF(NOT(ISNUMBER(C101)),"",IF(C101<='0. Supuestos'!$B$91,"CUADRA","REVISA: no es lo que publica el libro 4")) -> CUADRA | E101: Vuelve a copiar la cifra de su celda de origen (libro 4, aceite-de-fritura-coste-y-cambio.xlsx!Consumo y Reposición!L5) en la fila 17, o anota aquí lo que publica hoy.
A102: CUADRE · Raciones de un año normal (X13) | B102: 107400 | C102: =IFERROR(IF(B102=0,ABS('0. Supuestos'!$B$19-B102),ABS('0. Supuestos'!$B$19-B102)/ABS(B102)),"") -> 0 | D102: =IF(NOT(ISNUMBER(C102)),"",IF(C102<='0. Supuestos'!$B$91,"CUADRA","REVISA: no es lo que publica el libro 5")) -> CUADRA | E102: Vuelve a copiar la cifra de su celda de origen (libro 5, temporada-franjas-y-ferias.xlsx!Peso sobre el Año!L5) en la fila 19, o anota aquí lo que publica hoy.
A103: CUADRE · Coeficiente de enero (X13) | B103: 1.25 | C103: =IFERROR(IF(B103=0,ABS('0. Supuestos'!$B$20-B103),ABS('0. Supuestos'!$B$20-B103)/ABS(B103)),"") -> 0 | D103: =IF(NOT(ISNUMBER(C103)),"",IF(C103<='0. Supuestos'!$B$91,"CUADRA","REVISA: no es lo que publica el libro 5")) -> CUADRA | E103: Vuelve a copiar la cifra de su celda de origen (libro 5, temporada-franjas-y-ferias.xlsx!Peso sobre el Año!L6) en la fila 20, o anota aquí lo que publica hoy.
A104: CUADRE · Coeficiente de febrero (X13) | B104: 1.15 | C104: =IFERROR(IF(B104=0,ABS('0. Supuestos'!$B$21-B104),ABS('0. Supuestos'!$B$21-B104)/ABS(B104)),"") -> 0 | D104: =IF(NOT(ISNUMBER(C104)),"",IF(C104<='0. Supuestos'!$B$91,"CUADRA","REVISA: no es lo que publica el libro 5")) -> CUADRA | E104: Vuelve a copiar la cifra de su celda de origen (libro 5, temporada-franjas-y-ferias.xlsx!Peso sobre el Año!L7) en la fila 21, o anota aquí lo que publica hoy.
A105: CUADRE · Coeficiente de marzo (X13) | B105: 1.1 | C105: =IFERROR(IF(B105=0,ABS('0. Supuestos'!$B$22-B105),ABS('0. Supuestos'!$B$22-B105)/ABS(B105)),"") -> 0 | D105: =IF(NOT(ISNUMBER(C105)),"",IF(C105<='0. Supuestos'!$B$91,"CUADRA","REVISA: no es lo que publica el libro 5")) -> CUADRA | E105: Vuelve a copiar la cifra de su celda de origen (libro 5, temporada-franjas-y-ferias.xlsx!Peso sobre el Año!L8) en la fila 22, o anota aquí lo que publica hoy.
A106: CUADRE · Coeficiente de abril (X13) | B106: 0.95 | C106: =IFERROR(IF(B106=0,ABS('0. Supuestos'!$B$23-B106),ABS('0. Supuestos'!$B$23-B106)/ABS(B106)),"") -> 0 | D106: =IF(NOT(ISNUMBER(C106)),"",IF(C106<='0. Supuestos'!$B$91,"CUADRA","REVISA: no es lo que publica el libro 5")) -> CUADRA | E106: Vuelve a copiar la cifra de su celda de origen (libro 5, temporada-franjas-y-ferias.xlsx!Peso sobre el Año!L9) en la fila 23, o anota aquí lo que publica hoy.
A107: CUADRE · Coeficiente de mayo (X13) | B107: 0.85 | C107: =IFERROR(IF(B107=0,ABS('0. Supuestos'!$B$24-B107),ABS('0. Supuestos'!$B$24-B107)/ABS(B107)),"") -> 0 | D107: =IF(NOT(ISNUMBER(C107)),"",IF(C107<='0. Supuestos'!$B$91,"CUADRA","REVISA: no es lo que publica el libro 5")) -> CUADRA | E107: Vuelve a copiar la cifra de su celda de origen (libro 5, temporada-franjas-y-ferias.xlsx!Peso sobre el Año!L10) en la fila 24, o anota aquí lo que publica hoy.
A108: CUADRE · Coeficiente de junio (X13) | B108: 0.7 | C108: =IFERROR(IF(B108=0,ABS('0. Supuestos'!$B$25-B108),ABS('0. Supuestos'!$B$25-B108)/ABS(B108)),"") -> 0 | D108: =IF(NOT(ISNUMBER(C108)),"",IF(C108<='0. Supuestos'!$B$91,"CUADRA","REVISA: no es lo que publica el libro 5")) -> CUADRA | E108: Vuelve a copiar la cifra de su celda de origen (libro 5, temporada-franjas-y-ferias.xlsx!Peso sobre el Año!L11) en la fila 25, o anota aquí lo que publica hoy.
A109: CUADRE · Coeficiente de julio (X13) | B109: 0.55 | C109: =IFERROR(IF(B109=0,ABS('0. Supuestos'!$B$26-B109),ABS('0. Supuestos'!$B$26-B109)/ABS(B109)),"") -> 0 | D109: =IF(NOT(ISNUMBER(C109)),"",IF(C109<='0. Supuestos'!$B$91,"CUADRA","REVISA: no es lo que publica el libro 5")) -> CUADRA | E109: Vuelve a copiar la cifra de su celda de origen (libro 5, temporada-franjas-y-ferias.xlsx!Peso sobre el Año!L12) en la fila 26, o anota aquí lo que publica hoy.
A110: CUADRE · Coeficiente de agosto (X13) | B110: 0.5 | C110: =IFERROR(IF(B110=0,ABS('0. Supuestos'!$B$27-B110),ABS('0. Supuestos'!$B$27-B110)/ABS(B110)),"") -> 0 | D110: =IF(NOT(ISNUMBER(C110)),"",IF(C110<='0. Supuestos'!$B$91,"CUADRA","REVISA: no es lo que publica el libro 5")) -> CUADRA | E110: Vuelve a copiar la cifra de su celda de origen (libro 5, temporada-franjas-y-ferias.xlsx!Peso sobre el Año!L13) en la fila 27, o anota aquí lo que publica hoy.
...

Sheet Inversión Inicial
A1: Inversión Inicial: CAPEX y Fondo de Maniobra
A2: AI Chef Pro · aichef.pro — Cómo Montar una Churrería-Chocolatería
A3: El CAPEX llega del libro 2 SIN fondo de maniobra; el fondo se calcula aquí, con los fijos de caja de un mes y los meses de colchón. Inversión total = CAPEX + fondo. Todo sin IVA.
A5: CAPEX (del Libro 2, sin Fondo de Maniobra)
A6: CAPEX de apertura (copiado del libro 2) | B6: ='0. Supuestos'!$B$7 -> 86415.65 | C6: Los once bloques del libro 2: obra, extracción, fritura, chocolate, barra, control, TPV, licencias, fianza, stock y marketing.
A7: De él, lo que no se amortiza (fianza, stock y marketing) | B7: ='0. Supuestos'!$B$9 -> 4668.3 | C7: Se pone en «0. Supuestos».
A8: CAPEX que se amortiza | B8: =B6-B7 -> 81747.35
A9: Años de amortización | B9: ='0. Supuestos'!$B$54 -> 10
A10: Amortización anual | B10: =IFERROR(B8/B9,"") -> 8174.735 | C10: Es un coste del P&L pero no sale de la caja.
A12: Fondo de Maniobra (Se Calcula Aquí y Sólo Aquí)
A13: Plantilla de un mes | B13: =IFERROR('0. Supuestos'!$B$39/'0. Supuestos'!$B$44,"") -> 9945.8501 | C13: El coste anual del libro 8 entre los meses del año.
A14: Renta del mes | B14: ='0. Supuestos'!$B$8 -> 910
A15: Gastos fijos del mes | B15: ='0. Supuestos'!$B$83 -> 1870
A16: Intereses de un mes del año de crucero | B16: =IFERROR(INDEX('Financiación'!$B$117:$B$123,'0. Supuestos'!$B$55)/'0. Supuestos'!$B$44,"") -> 449.56323 | C16: Los del año de crucero de «Financiación», no los de la carencia: con los del año 1 el fondo saldría distinto según cuándo lo mires.
A17: Fijos de caja de un mes | B17: =SUM(B13:B16) -> 13175.413 | C17: La amortización no está: no es caja.
A18: Meses de colchón | B18: ='0. Supuestos'!$B$53 -> 6
A19: FONDO DE MANIOBRA | B19: =B17*B18 -> 79052.48 | C19: Lo que tiene que haber en la cuenta el día que abres para pagar los fijos mientras el negocio arranca y en el valle del verano.
A21: Inversión Total
A22: CAPEX sin fondo | B22: =B6 -> 86415.65
A23: Fondo de maniobra | B23: =B19 -> 79052.48
A24: INVERSIÓN TOTAL (CAPEX + fondo) | B24: =B22+B23 -> 165468.13 | C24: Es la cifra que le enseñas al banco.
A25: De ella, préstamo bancario | B25: ='0. Supuestos'!$B$63 -> 99300
A26: De ella, lo que pones tú | B26: =B24-B25 -> 66168.13
A28: El IVA que adelantas al comprar el equipo y pagar la obra NO está aquí: lo calcula el libro 2 en su hoja «IVA y Tesorería» y Hacienda te lo devuelve después. Cuéntalo con tu banco aparte, porque el día que abres sí sale de la cuenta.

Sheet PyG 3 Años
A1: Cuenta de Resultados a 3 Años
A2: AI Chef Pro · aichef.pro — Cómo Montar una Churrería-Chocolatería
A3: Año 1 con la rampa de arranque (suma la hoja de Tesorería), año 2 de crucero (un año normal) y año 3. Formato de contribución: lo que deja cada ración menos los fijos. Sin IVA y antes de impuestos.
A5: Concepto | B5: Año 1 (con rampa) | C5: Año 2 (crucero) | D5: Año 3 | E5: Notas
A6: Raciones y Contribución
A7: Raciones del año | B7: ='Tesorería 12 meses'!$N$11 -> 93666.225 | C7: ='0. Supuestos'!$B$19 -> 107400 | D7: =C7*(1+'0. Supuestos'!$B$50) -> 107400 | E7: Año 2: las del libro 5. Año 1: con la rampa. Año 3: con el crecimiento de «0. Supuestos».
A8: De ellas, raciones de la carta de invierno (fuera de julio y agosto) | B8: =SUMIF('Tesorería 12 meses'!$B$9:$M$9,0,'Tesorería 12 meses'!$B$11:$M$11) -> 84268.725 | C8: =IFERROR('0. Supuestos'!$B$19*(SUM('0. Supuestos'!$B$20:$B$31)-INDEX('0. Supuestos'!$B$20:$B$31,'0. Supuestos'!$B$46)-INDEX('0. Supuestos'!$B$20:$B$31,'0. Supuestos'!$B$47))/'0. Supuestos'!$B$44,"") -> 98002.5 | D8: =C8*(1+'0. Supuestos'!$B$50) -> 98002.5
A9: Ventas sin IVA de la carta de invierno | B9: ='Tesorería 12 meses'!$N$13 -> 182135.36 | C9: =C8*'Canales y Punto Muerto'!$D$8 -> 211819.04 | D9: =D8*'Canales y Punto Muerto'!$D$8 -> 211819.04 | E9: Raciones por el ticket medio de la mezcla sala / para llevar (hoja «Canales»).
A10: Materia de la carta de invierno (aceite absorbido incluido) | B10: ='Tesorería 12 meses'!$N$15 -> 23834.813 | C10: =C8*'Canales y Punto Muerto'!$E$8 -> 27719.314 | D10: =D8*'Canales y Punto Muerto'!$E$8 -> 27719.314 | E10: El margen sale del escandallo del libro 3, nunca de un porcentaje del sector.
A11: Contribución de la carta de invierno | B11: =B9-B10 -> 158300.55 | C11: =C9-C10 -> 184099.73 | D11: =D9-D10 -> 184099.73
A12: Contribución de julio y agosto (la salida que eliges en el libro 5) | B12: ='Tesorería 12 meses'!$N$17 -> 17368.709 | C12: ='0. Supuestos'!$B$33 -> 17368.709 | D12: =C12*(1+'0. Supuestos'!$B$50) -> 17368.709 | E12: Si cierras en verano, es cero: los fijos de esos dos meses se pagan igual (hoja «Escenarios»).
A13: Renovación del aceite (se resta) | B13: ='Tesorería 12 meses'!$N$18 -> 2659.9685 | C13: =C7*'0. Supuestos'!$B$17 -> 3049.9854 | D13: =D7*'0. Supuestos'!$B$17 -> 3049.9854 | E13: El aceite que se tira al cambiar la cuba (libro 4). El absorbido ya va en la materia.
A14: Ferias (resultado del año, libro 5) | B14: ='Tesorería 12 meses'!$N$19 -> 0 | C14: ='0. Supuestos'!$B$32 -> 0 | D14: ='0. Supuestos'!$B$32 -> 0
A15: CONTRIBUCIÓN DEL AÑO | B15: =B11+B12-B13+B14 -> 173009.29 | C15: =C11+C12-C13+C14 -> 198418.45 | D15: =D11+D12-D13+D14 -> 198418.45
A16: Costes Fijos
A17: Plantilla (libro 8) | B17: ='0. Supuestos'!$B$39 -> 119350.2 | C17: ='0. Supuestos'!$B$39 -> 119350.2 | D17: ='0. Supuestos'!$B$39 -> 119350.2 | E17: La misma los tres años: se contrata desde el primer día.
A18: Renta del local (libro 2) | B18: ='0. Supuestos'!$B$8*'0. Supuestos'!$B$44 -> 10920 | C18: ='0. Supuestos'!$B$8*'0. Supuestos'!$B$44 -> 10920 | D18: ='0. Supuestos'!$B$8*'0. Supuestos'!$B$44 -> 10920
A19: Gastos fijos (suministros, seguros, asesoría, TPV, cuota de autónomos...) | B19: ='0. Supuestos'!$B$83*'0. Supuestos'!$B$44 -> 22440 | C19: ='0. Supuestos'!$B$83*'0. Supuestos'!$B$44 -> 22440 | D19: ='0. Supuestos'!$B$83*'0. Supuestos'!$B$44 -> 22440 | E19: Los de «0. Supuestos», que nacen en este libro.
A20: Amortización del inmovilizado | B20: ='Inversión Inicial'!$B$10 -> 8174.735 | C20: ='Inversión Inicial'!$B$10 -> 8174.735 | D20: ='Inversión Inicial'!$B$10 -> 8174.735 | E20: No sale de la caja.
A21: Intereses del préstamo | B21: ='Financiación'!$B$117 -> 6075.6785 | C21: ='Financiación'!$B$118 -> 5394.7588 | D21: ='Financiación'!$B$119 -> 4552.342 | E21: Los de cada año del cuadro de «Financiación».
A22: TOTAL COSTES FIJOS | B22: =SUM(B17:B21) -> 166960.61 | C22: =SUM(C17:C21) -> 166279.69 | D22: =SUM(D17:D21) -> 165437.28
A23: RESULTADO ANTES DE IMPUESTOS | B23: =B15-B22 -> 6048.671 | C23: =C15-C22 -> 32138.755 | D23: =D15-D22 -> 32981.171 | E23: En euros. Sin Impuesto de Sociedades ni IRPF: dependen de tu forma jurídica.
A24: ¿Gana dinero? | B24: =IF(NOT(ISNUMBER(B23)),"",IF(B23>=0,"Gana dinero","Pierde dinero")) -> Gana dinero | C24: =IF(NOT(ISNUMBER(C23)),"",IF(C23>=0,"Gana dinero","Pierde dinero")) -> Gana dinero | D24: =IF(NOT(ISNUMBER(D23)),"",IF(D23>=0,"Gana dinero","Pierde dinero")) -> Gana dinero
A26: Ventas y Lecturas por Ración
A27: Ventas sin IVA de julio y agosto (la salida que eliges en el libro 5) | B27: ='Tesorería 12 meses'!$N$14 -> 20737.72 | C27: ='0. Supuestos'!$B$37 -> 20737.72 | D27: =C27*(1+'0. Supuestos'!$B$50) -> 20737.72 | E27: Con el ticket de la salida elegida (libro 5, X16 ter): cero si cierras o sales de ferias, cuyas ventas están en su contribución. El resultado cuenta con la contribución, no con estas ventas.
A28: VENTAS SIN IVA DEL AÑO (con el verano de la salida elegida) | B28: =B9+B27 -> 202873.08 | C28: =C9+C27 -> 232556.76 | D28: =D9+D27 -> 232556.76
A29: Resultado sobre ventas | B29: =IFERROR(B23/B28,"") -> 0.02981505 | C29: =IFERROR(C23/C28,"") -> 0.13819747 | D29: =IFERROR(D23/D28,"") -> 0.14181988 | E29: Información, no veredicto: el veredicto es el resultado en euros.
A30: Contribución por ración | B30: =IFERROR(B15/B7,"") -> 1.8470829 | C30: =IFERROR(C15/C7,"") -> 1.8474716 | D30: =IFERROR(D15/D7,"") -> 1.8474716
A31: Resultado por ración | B31: =IFERROR(B23/B7,"") -> 0.064576863 | C31: =IFERROR(C23/C7,"") -> 0.29924353 | D31: =IFERROR(D23/D7,"") -> 0.30708726
A32: Caja que genera el negocio antes de la deuda (resultado + amortización + intereses) | B32: =B23+B20+B21 -> 20299.085 | C32: =C23+C20+C21 -> 45708.248 | D32: =D23+D20+D21 -> 45708.248 | E32: Con ella se paga la cuota del préstamo (hoja «Financiación»).
A34: El año 2 es el de crucero: un año entero sin la rampa del arranque. Es el que se cita en el resumen del plan de negocio y el que decide si el negocio funciona. El año 1 suele salir peor por la rampa y por la carencia; el año 3 repite el 2 salvo que pongas crecimiento.

Sheet Punto de Equilibrio
A1: Punto de Equilibrio en Raciones al Día
A2: AI Chef Pro · aichef.pro — Cómo Montar una Churrería-Chocolatería
A3: Cuántas raciones al día pagan los fijos del año de crucero, con la contribución media por ración de tu carta, y qué meses no llegan.
A5: Año de Crucero
A6: Fijos del año (con amortización e intereses) | B6: ='PyG 3 Años'!$C$22 -> 166279.69
A7: Contribución del año | B7: ='PyG 3 Años'!$C$15 -> 198418.45
A8: Raciones del año | B8: ='PyG 3 Años'!$C$7 -> 107400
A9: Contribución media por ración | B9: =IFERROR(B7/B8,"") -> 1.8474716 | C9: Mezcla la carta de invierno, el verano, las ferias y el aceite.
A10: Días de apertura al año | B10: =('0. Supuestos'!$B$42-'0. Supuestos'!$B$43) -> 360
A11: Raciones al año que pagan los fijos | B11: =IFERROR(B6/B9,"") -> 90003.925
A12: PUNTO DE EQUILIBRIO: raciones al día | B12: =IFERROR(B11/B10,"") -> 250.0109
A13: Raciones al día que prevés vender (media del año) | B13: =IFERROR(B8/B10,"") -> 298.33333
A14: Margen de seguridad (raciones al día por encima del equilibrio) | B14: =B13-B12 -> 48.322431
A15: Lo que te sobra (o falta) al año, en euros | B15: =B7-B6 -> 32138.755 | C15: Es el resultado antes de impuestos del año de crucero.
A16: Veredicto | B16: =IF(NOT(ISNUMBER(B15)),"",IF(B15>=0,"Por encima del punto de equilibrio","Por debajo del punto de equilibrio")) -> Por encima del punto de equilibrio
A17: Contribución que necesitas cada mes para pagar los fijos | B17: =IFERROR(B6/'0. Supuestos'!$B$44,"") -> 13856.641
A18: Ventas sin IVA al mes en el punto de equilibrio (estimación) | B18: =IFERROR(B11/'0. Supuestos'!$B$44*'PyG 3 Años'!$C$28/'PyG 3 Años'!$C$7,"") -> 16240.705 | C18: Con las ventas del año de «PyG 3 Años», que estiman julio y agosto con el ticket de invierno.
A19: Punto de equilibrio de caja: raciones al día (sin la amortización) | B19: =IFERROR((B6-'PyG 3 Años'!$C$20)/B9/B10,"") -> 237.71973 | C19: Lo que necesitas para no perder caja, aunque contablemente pierdas dinero.
A21: Mes a Mes del Año de Crucero
A22: Mes | B22: Número del mes | C22: Coeficiente | D22: Raciones del mes | E22: Raciones al día | F22: Contribución del mes | G22: Fijos del mes | H22: Resultado del mes | I22: ¿Paga sus fijos?
A23: Enero | B23: 1 | C23: ='0. Supuestos'!$B$20 -> 1.25 | D23: =IFERROR('0. Supuestos'!$B$19*C23/'0. Supuestos'!$B$44,"") -> 11187.5 | E23: =IFERROR(D23/($B$10/'0. Supuestos'!$B$44),"") -> 372.91667 | F23: =IFERROR(IF(OR(B23='0. Supuestos'!$B$46,B23='0. Supuestos'!$B$47),IF(INDEX('0. Supuestos'!$B$20:$B$31,'0. Supuestos'!$B$46)+INDEX('0. Supuestos'!$B$20:$B$31,'0. Supuestos'!$B$47)>0,'0. Supuestos'!$B$33*C23/(INDEX('0. Supuestos'!$B$20:$B$31,'0. Supuestos'!$B$46)+INDEX('0. Supuestos'!$B$20:$B$31,'0. Supuestos'!$B$47)),0),D23*('Canales y Punto Muerto'!$D$8-'Canales y Punto Muerto'!$E$8))-D23*'0. Supuestos'!$B$17+'0. Supuestos'!$B$32/'0. Supuestos'!$B$44,"") -> 20698.244 | G23: =IFERROR($B$6/'0. Supuestos'!$B$44,"") -> 13856.641 | H23: =F23-G23 -> 6841.6024 | I23: =IF(NOT(ISNUMBER(H23)),"",IF(H23>=0,"Sí","No")) -> Sí
A24: Febrero | B24: 2 | C24: ='0. Supuestos'!$B$21 -> 1.15 | D24: =IFERROR('0. Supuestos'!$B$19*C24/'0. Supuestos'!$B$44,"") -> 10292.5 | E24: =IFERROR(D24/($B$10/'0. Supuestos'!$B$44),"") -> 343.08333 | F24: =IFERROR(IF(OR(B24='0. Supuestos'!$B$46,B24='0. Supuestos'!$B$47),IF(INDEX('0. Supuestos'!$B$20:$B$31,'0. Supuestos'!$B$46)+INDEX('0. Supuestos'!$B$20:$B$31,'0. Supuestos'!$B$47)>0,'0. Supuestos'!$B$33*C24/(INDEX('0. Supuestos'!$B$20:$B$31,'0. Supuestos'!$B$46)+INDEX('0. Supuestos'!$B$20:$B$31,'0. Supuestos'!$B$47)),0),D24*('Canales y Punto Muerto'!$D$8-'Canales y Punto Muerto'!$E$8))-D24*'0. Supuestos'!$B$17+'0. Supuestos'!$B$32/'0. Supuestos'!$B$44,"") -> 19042.384 | G24: =IFERROR($B$6/'0. Supuestos'!$B$44,"") -> 13856.641 | H24: =F24-G24 -> 5185.7429 | I24: =IF(NOT(ISNUMBER(H24)),"",IF(H24>=0,"Sí","No")) -> Sí
A25: Marzo | B25: 3 | C25: ='0. Supuestos'!$B$22 -> 1.1 | D25: =IFERROR('0. Supuestos'!$B$19*C25/'0. Supuestos'!$B$44,"") -> 9845 | E25: =IFERROR(D25/($B$10/'0. Supuestos'!$B$44),"") -> 328.16667 | F25: =IFERROR(IF(OR(B25='0. Supuestos'!$B$46,B25='0. Supuestos'!$B$47),IF(INDEX('0. Supuestos'!$B$20:$B$31,'0. Supuestos'!$B$46)+INDEX('0. Supuestos'!$B$20:$B$31,'0. Supuestos'!$B$47)>0,'0. Supuestos'!$B$33*C25/(INDEX('0. Supuestos'!$B$20:$B$31,'0. Supuestos'!$B$46)+INDEX('0. Supuestos'!$B$20:$B$31,'0. Supuestos'!$B$47)),0),D25*('Canales y Punto Muerto'!$D$8-'Canales y Punto Muerto'!$E$8))-D25*'0. Supuestos'!$B$17+'0. Supuestos'!$B$32/'0. Supuestos'!$B$44,"") -> 18214.454 | G25: =IFERROR($B$6/'0. Supuestos'!$B$44,"") -> 13856.641 | H25: =F25-G25 -> 4357.8132 | I25: =IF(NOT(ISNUMBER(H25)),"",IF(H25>=0,"Sí","No")) -> Sí
A26: Abril | B26: 4 | C26: ='0. Supuestos'!$B$23 -> 0.95 | D26: =IFERROR('0. Supuestos'!$B$19*C26/'0. Supuestos'!$B$44,"") -> 8502.5 | E26: =IFERROR(D26/($B$10/'0. Supuestos'!$B$44),"") -> 283.41667 | F26: =IFERROR(IF(OR(B26='0. Supuestos'!$B$46,B26='0. Supuestos'!$B$47),IF(INDEX('0. Supuestos'!$B$20:$B$31,'0. Supuestos'!$B$46)+INDEX('0. Supuestos'!$B$20:$B$31,'0. Supuestos'!$B$47)>0,'0. Supuestos'!$B$33*C26/(INDEX('0. Supuestos'!$B$20:$B$31,'0. Supuestos'!$B$46)+INDEX('0. Supuestos'!$B$20:$B$31,'0. Supuestos'!$B$47)),0),D26*('Canales y Punto Muerto'!$D$8-'Canales y Punto Muerto'!$E$8))-D26*'0. Supuestos'!$B$17+'0. Supuestos'!$B$32/'0. Supuestos'!$B$44,"") -> 15730.665 | G26: =IFERROR($B$6/'0. Supuestos'!$B$44,"") -> 13856.641 | H26: =F26-G26 -> 1874.0239 | I26: =IF(NOT(ISNUMBER(H26)),"",IF(H26>=0,"Sí","No")) -> Sí
A27: Mayo | B27: 5 | C27: ='0. Supuestos'!$B$24 -> 0.85 | D27: =IFERROR('0. Supuestos'!$B$19*C27/'0. Supuestos'!$B$44,"") -> 7607.5 | E27: =IFERROR(D27/($B$10/'0. Supuestos'!$B$44),"") -> 253.58333 | F27: =IFERROR(IF(OR(B27='0. Supuestos'!$B$46,B27='0. Supuestos'!$B$47),IF(INDEX('0. Supuestos'!$B$20:$B$31,'0. Supuestos'!$B$46)+INDEX('0. Supuestos'!$B$20:$B$31,'0. Supuestos'!$B$47)>0,'0. Supuestos'!$B$33*C27/(INDEX('0. Supuestos'!$B$20:$B$31,'0. Supuestos'!$B$46)+INDEX('0. Supuestos'!$B$20:$B$31,'0. Supuestos'!$B$47)),0),D27*('Canales y Punto Muerto'!$D$8-'Canales y Punto Muerto'!$E$8))-D27*'0. Supuestos'!$B$17+'0. Supuestos'!$B$32/'0. Supuestos'!$B$44,"") -> 14074.806 | G27: =IFERROR($B$6/'0. Supuestos'!$B$44,"") -> 13856.641 | H27: =F27-G27 -> 218.16443 | I27: =IF(NOT(ISNUMBER(H27)),"",IF(H27>=0,"Sí","No")) -> Sí
A28: Junio | B28: 6 | C28: ='0. Supuestos'!$B$25 -> 0.7 | D28: =IFERROR('0. Supuestos'!$B$19*C28/'0. Supuestos'!$B$44,"") -> 6265 | E28: =IFERROR(D28/($B$10/'0. Supuestos'!$B$44),"") -> 208.83333 | F28: =IFERROR(IF(OR(B28='0. Supuestos'!$B$46,B28='0. Supuestos'!$B$47),IF(INDEX('0. Supuestos'!$B$20:$B$31,'0. Supuestos'!$B$46)+INDEX('0. Supuestos'!$B$20:$B$31,'0. Supuestos'!$B$47)>0,'0. Supuestos'!$B$33*C28/(INDEX('0. Supuestos'!$B$20:$B$31,'0. Supuestos'!$B$46)+INDEX('0. Supuestos'!$B$20:$B$31,'0. Supuestos'!$B$47)),0),D28*('Canales y Punto Muerto'!$D$8-'Canales y Punto Muerto'!$E$8))-D28*'0. Supuestos'!$B$17+'0. Supuestos'!$B$32/'0. Supuestos'!$B$44,"") -> 11591.016 | G28: =IFERROR($B$6/'0. Supuestos'!$B$44,"") -> 13856.641 | H28: =F28-G28 -> -2265.6248 | I28: =IF(NOT(ISNUMBER(H28)),"",IF(H28>=0,"Sí","No")) -> No
A29: Julio | B29: 7 | C29: ='0. Supuestos'!$B$26 -> 0.55 | D29: =IFERROR('0. Supuestos'!$B$19*C29/'0. Supuestos'!$B$44,"") -> 4922.5 | E29: =IFERROR(D29/($B$10/'0. Supuestos'!$B$44),"") -> 164.08333 | F29: =IFERROR(IF(OR(B29='0. Supuestos'!$B$46,B29='0. Supuestos'!$B$47),IF(INDEX('0. Supuestos'!$B$20:$B$31,'0. Supuestos'!$B$46)+INDEX('0. Supuestos'!$B$20:$B$31,'0. Supuestos'!$B$47)>0,'0. Supuestos'!$B$33*C29/(INDEX('0. Supuestos'!$B$20:$B$31,'0. Supuestos'!$B$46)+INDEX('0. Supuestos'!$B$20:$B$31,'0. Supuestos'!$B$47)),0),D29*('Canales y Punto Muerto'!$D$8-'Canales y Punto Muerto'!$E$8))-D29*'0. Supuestos'!$B$17+'0. Supuestos'!$B$32/'0. Supuestos'!$B$44,"") -> 8958.1042 | G29: =IFERROR($B$6/'0. Supuestos'!$B$44,"") -> 13856.641 | H29: =F29-G29 -> -4898.537 | I29: =IF(NOT(ISNUMBER(H29)),"",IF(H29>=0,"Sí","No")) -> No
A30: Agosto | B30: 8 | C30: ='0. Supuestos'!$B$27 -> 0.5 | D30: =IFERROR('0. Supuestos'!$B$19*C30/'0. Supuestos'!$B$44,"") -> 4475 | E30: =IFERROR(D30/($B$10/'0. Supuestos'!$B$44),"") -> 149.16667 | F30: =IFERROR(IF(OR(B30='0. Supuestos'!$B$46,B30='0. Supuestos'!$B$47),IF(INDEX('0. Supuestos'!$B$20:$B$31,'0. Supuestos'!$B$46)+INDEX('0. Supuestos'!$B$20:$B$31,'0. Supuestos'!$B$47)>0,'0. Supuestos'!$B$33*C30/(INDEX('0. Supuestos'!$B$20:$B$31,'0. Supuestos'!$B$46)+INDEX('0. Supuestos'!$B$20:$B$31,'0. Supuestos'!$B$47)),0),D30*('Canales y Punto Muerto'!$D$8-'Canales y Punto Muerto'!$E$8))-D30*'0. Supuestos'!$B$17+'0. Supuestos'!$B$32/'0. Supuestos'!$B$44,"") -> 8143.7311 | G30: =IFERROR($B$6/'0. Supuestos'!$B$44,"") -> 13856.641 | H30: =F30-G30 -> -5712.9101 | I30: =IF(NOT(ISNUMBER(H30)),"",IF(H30>=0,"Sí","No")) -> No
A31: Septiembre | B31: 9 | C31: ='0. Supuestos'!$B$28 -> 0.8 | D31: =IFERROR('0. Supuestos'!$B$19*C31/'0. Supuestos'!$B$44,"") -> 7160 | E31: =IFERROR(D31/($B$10/'0. Supuestos'!$B$44),"") -> 238.66667 | F31: =IFERROR(IF(OR(B31='0. Supuestos'!$B$46,B31='0. Supuestos'!$B$47),IF(INDEX('0. Supuestos'!$B$20:$B$31,'0. Supuestos'!$B$46)+INDEX('0. Supuestos'!$B$20:$B$31,'0. Supuestos'!$B$47)>0,'0. Supuestos'!$B$33*C31/(INDEX('0. Supuestos'!$B$20:$B$31,'0. Supuestos'!$B$46)+INDEX('0. Supuestos'!$B$20:$B$31,'0. Supuestos'!$B$47)),0),D31*('Canales y Punto Muerto'!$D$8-'Canales y Punto Muerto'!$E$8))-D31*'0. Supuestos'!$B$17+'0. Supuestos'!$B$32/'0. Supuestos'!$B$44,"") -> 13246.876 | G31: =IFERROR($B$6/'0. Supuestos'!$B$44,"") -> 13856.641 | H31: =F31-G31 -> -609.76532 | I31: =IF(NOT(ISNUMBER(H31)),"",IF(H31>=0,"Sí","No")) -> No
A32: Octubre | B32: 10 | C32: ='0. Supuestos'!$B$29 -> 1.1 | D32: =IFERROR('0. Supuestos'!$B$19*C32/'0. Supuestos'!$B$44,"") -> 9845 | E32: =IFERROR(D32/($B$10/'0. Supuestos'!$B$44),"") -> 328.16667 | F32: =IFERROR(IF(OR(B32='0. Supuestos'!$B$46,B32='0. Supuestos'!$B$47),IF(INDEX('0. Supuestos'!$B$20:$B$31,'0. Supuestos'!$B$46)+INDEX('0. Supuestos'!$B$20:$B$31,'0. Supuestos'!$B$47)>0,'0. Supuestos'!$B$33*C32/(INDEX('0. Supuestos'!$B$20:$B$31,'0. Supuestos'!$B$46)+INDEX('0. Supuestos'!$B$20:$B$31,'0. Supuestos'!$B$47)),0),D32*('Canales y Punto Muerto'!$D$8-'Canales y Punto Muerto'!$E$8))-D32*'0. Supuestos'!$B$17+'0. Supuestos'!$B$32/'0. Supuestos'!$B$44,"") -> 18214.454 | G32: =IFERROR($B$6/'0. Supuestos'!$B$44,"") -> 13856.641 | H32: =F32-G32 -> 4357.8132 | I32: =IF(NOT(ISNUMBER(H32)),"",IF(H32>=0,"Sí","No")) -> Sí
A33: Noviembre | B33: 11 | C33: ='0. Supuestos'!$B$30 -> 1.3 | D33: =IFERROR('0. Supuestos'!$B$19*C33/'0. Supuestos'!$B$44,"") -> 11635 | E33: =IFERROR(D33/($B$10/'0. Supuestos'!$B$44),"") -> 387.83333 | F33: =IFERROR(IF(OR(B33='0. Supuestos'!$B$46,B33='0. Supuestos'!$B$47),IF(INDEX('0. Supuestos'!$B$20:$B$31,'0. Supuestos'!$B$46)+INDEX('0. Supuestos'!$B$20:$B$31,'0. Supuestos'!$B$47)>0,'0. Supuestos'!$B$33*C33/(INDEX('0. Supuestos'!$B$20:$B$31,'0. Supuestos'!$B$46)+INDEX('0. Supuestos'!$B$20:$B$31,'0. Supuestos'!$B$47)),0),D33*('Canales y Punto Muerto'!$D$8-'Canales y Punto Muerto'!$E$8))-D33*'0. Supuestos'!$B$17+'0. Supuestos'!$B$32/'0. Supuestos'!$B$44,"") -> 21526.173 | G33: =IFERROR($B$6/'0. Supuestos'!$B$44,"") -> 13856.641 | H33: =F33-G33 -> 7669.5321 | I33: =IF(NOT(ISNUMBER(H33)),"",IF(H33>=0,"Sí","No")) -> Sí
A34: Diciembre | B34: 12 | C34: ='0. Supuestos'!$B$31 -> 1.75 | D34: =IFERROR('0. Supuestos'!$B$19*C34/'0. Supuestos'!$B$44,"") -> 15662.5 | E34: =IFERROR(D34/($B$10/'0. Supuestos'!$B$44),"") -> 522.08333 | F34: =IFERROR(IF(OR(B34='0. Supuestos'!$B$46,B34='0. Supuestos'!$B$47),IF(INDEX('0. Supuestos'!$B$20:$B$31,'0. Supuestos'!$B$46)+INDEX('0. Supuestos'!$B$20:$B$31,'0. Supuestos'!$B$47)>0,'0. Supuestos'!$B$33*C34/(INDEX('0. Supuestos'!$B$20:$B$31,'0. Supuestos'!$B$46)+INDEX('0. Supuestos'!$B$20:$B$31,'0. Supuestos'!$B$47)),0),D34*('Canales y Punto Muerto'!$D$8-'Canales y Punto Muerto'!$E$8))-D34*'0. Supuestos'!$B$17+'0. Supuestos'!$B$32/'0. Supuestos'!$B$44,"") -> 28977.541 | G34: =IFERROR($B$6/'0. Supuestos'!$B$44,"") -> 13856.641 | H34: =F34-G34 -> 15120.9 | I34: =IF(NOT(ISNUMBER(H34)),"",IF(H34>=0,"Sí","No")) -> Sí
A35: TOTAL DEL AÑO | D35: =SUM(D23:D34) -> 107400 | F35: =SUM(F23:F34) -> 198418.45 | G35: =SUM(G23:G34) -> 166279.69 | H35: =SUM(H23:H34) -> 32138.755
A36: Meses que no pagan sus fijos | B36: =COUNTIF(H23:H34,"<0") -> 4
A38: Los meses que no pagan sus fijos los pagan los meses buenos: por eso el fondo de maniobra tiene que llegar vivo al primer verano. El punto de equilibrio en raciones al día usa la contribución media de todo el año; en un mes concreto, mira su fila.

Sheet Escenarios
A1: Escenarios: Raciones, Verano y Formato
A2: AI Chef Pro · aichef.pro — Cómo Montar una Churrería-Chocolatería
A3: Tres escenarios de raciones sobre el año de crucero, el verano con sus fijos dentro y el mismo local con sala o sólo despacho. Todo en euros.
A5: Métrica | B5: Pesimista | C5: Base (año de crucero) | D5: Optimista | E5: Notas
A6: Raciones sobre el año normal | B6: ='0. Supuestos'!$B$86 -> -0.15 | C6: 0 | D6: ='0. Supuestos'!$B$87 -> 0.1 | E6: Se cambian en «0. Supuestos». La base no se mueve: es el año de crucero.
A7: Raciones del año | B7: ='PyG 3 Años'!$C$7*(1+B6) -> 91290 | C7: ='PyG 3 Años'!$C$7*(1+C6) -> 107400 | D7: ='PyG 3 Años'!$C$7*(1+D6) -> 118140
A8: Contribución que depende de las raciones | B8: =('PyG 3 Años'!$C$15-'PyG 3 Años'!$C$14)*(1+B6) -> 168655.68 | C8: =('PyG 3 Años'!$C$15-'PyG 3 Años'!$C$14)*(1+C6) -> 198418.45 | D8: =('PyG 3 Años'!$C$15-'PyG 3 Años'!$C$14)*(1+D6) -> 218260.29 | E8: Carta, verano y aceite se mueven con las raciones; las ferias, no.
A10: CONTRIBUCIÓN DEL AÑO | B10: =B8+B24 -> 170762.14 | C10: =C8+C24 -> 226131.73 | D10: =D8+D24 -> 192653.47
A11: Fijos del año (los mismos en los tres) | B11: ='PyG 3 Años'!$C$22 -> 166279.69 | C11: ='PyG 3 Años'!$C$22 -> 166279.69 | D11: ='PyG 3 Años'!$C$22 -> 166279.69 | E11: Si en el pesimista no aguantas, el ajuste es la plantilla o la renta, no las raciones.
A12: RESULTADO ANTES DE IMPUESTOS | B12: =B10-B11 -> 4482.4409 | C12: =C10-C11 -> 59852.037 | D12: =D10-D11 -> 26373.771
A13: ¿Gana dinero? | B13: =IF(NOT(ISNUMBER(B12)),"",IF(B12>=0,"Gana dinero","Pierde dinero")) -> Gana dinero | C13: =IF(NOT(ISNUMBER(C12)),"",IF(C12>=0,"Gana dinero","Pierde dinero")) -> Gana dinero | D13: =IF(NOT(ISNUMBER(D12)),"",IF(D12>=0,"Gana dinero","Pierde dinero")) -> Gana dinero
A14: Raciones al día que pagan los fijos | B14: =IFERROR(IF(B10<=0,"",B11/(B10/B7)/'Punto de Equilibrio'!$B$10),"") -> 246.92687 | C14: =IFERROR(IF(C10<=0,"",C11/(C10/C7)/'Punto de Equilibrio'!$B$10),"") -> 219.37114 | D14: =IFERROR(IF(D10<=0,"",D11/(D10/D7)/'Punto de Equilibrio'!$B$10),"") -> 283.24148
A15: Raciones al día que vendes | B15: =IFERROR(B7/'Punto de Equilibrio'!$B$10,"") -> 253.58333 | C15: =IFERROR(C7/'Punto de Equilibrio'!$B$10,"") -> 298.33333 | D15: =IFERROR(D7/'Punto de Equilibrio'!$B$10,"") -> 328.16667
A16: Margen de seguridad (raciones al día) | B16: =IFERROR(B15-B14,"") -> 6.6564658 | C16: =IFERROR(C15-C14,"") -> 78.962194 | D16: =IFERROR(D15-D14,"") -> 44.925184
A18: El Verano con los Fijos Dentro (Julio y Agosto)
A19: Salida del verano | B19: Contribución de julio y agosto | C19: Fijos de esos dos meses | D19: Resultado con fijos | E19: Notas
A20: Meses del verano | B20: =COUNT('0. Supuestos'!$B$46:$B$47) -> 2
A21: Fijos de esos meses (los mismos en las tres salidas) | B21: =IFERROR('PyG 3 Años'!$C$22*B20/'0. Supuestos'!$B$44,"") -> 27713.282 | E21: Plantilla, renta, gastos fijos, amortización e intereses de dos meses del año de crucero. Se pagan abras o cierres.
A22: Cerrar en julio y agosto | B22: ='0. Supuestos'!$B$34 -> 0 | C22: =$B$21 -> 27713.282 | D22: =B22-C22 -> -27713.282 | E22: Contribución cero por definición: no vendes, pero pagas los fijos.
A23: Abrir con la carta de verano | B23: ='0. Supuestos'!$B$35 -> 17368.709 | C23: =$B$21 -> 27713.282 | D23: =B23-C23 -> -10344.573 | E23: Ventas menos materia de julio y agosto, del libro 5.
A24: Salir de ferias en julio y agosto | B24: ='0. Supuestos'!$B$36 -> 2106.4537 | C24: =$B$21 -> 27713.282 | D24: =B24-C24 -> -25606.829 | E24: Lo que dejan las ferias de esos dos meses, del libro 5.
A25: La salida que eliges en el libro 5 (su contribución, X16) | B25: ='0. Supuestos'!$B$33 -> 17368.709 | C25: =$B$21 -> 27713.282 | D25: =B25-C25 -> -10344.573 | E25: En El Molinete, la carta de verano. Es una de las tres de arriba.
A26: Lo que te deja la salida elegida frente a cerrar | B26: =D25-D22 -> 17368.709
A27: Un verano con resultado negativo es lo normal en una churrería: lo que decide es cuánto menos negativo es abrir que cerrar. Las tres salidas se enseñan aquí con la misma regla: su contribución (la copias del libro 5) menos los «Fijos de esos meses». El libro 5, en «El Verano (Tres Salidas)», compara las tres sin fijos y elige la que más deja.
A29: Local con Sala o Sólo Despacho para Llevar
A30: Métrica | B30: Local con sala (el caso) | C30: Sólo despacho para llevar | E30: Notas
A31: Parte de las raciones que conservas | B31: ='Canales y Punto Muerto'!$B$6+'Canales y Punto Muerto'!$B$7 -> 1 | C31: ='Canales y Punto Muerto'!$B$7 -> 0.3 | E31: Sin sala, el mismo local vende sólo la parte que ya se llevaban.
A32: Raciones del año | B32: ='PyG 3 Años'!$C$7 -> 107400 | C32: ='PyG 3 Años'!$C$7*'Canales y Punto Muerto'!$B$7 -> 32220
A33: Contribución de la carta de invierno | B33: ='Canales y Punto Muerto'!$G$8 -> 184099.73 | C33: ='Canales y Punto Muerto'!$G$7 -> 55478.078
A34: Contribución de julio y agosto | B34: ='PyG 3 Años'!$C$12 -> 17368.709 | C34: ='PyG 3 Años'!$C$12*'Canales y Punto Muerto'!$B$7 -> 5210.6127 | E34: En el despacho, la parte para llevar del verano.
A35: Renovación del aceite (se resta) | B35: ='PyG 3 Años'!$C$13 -> 3049.9854 | C35: ='PyG 3 Años'!$C$13*'Canales y Punto Muerto'!$B$7 -> 914.99561
A36: Ferias | B36: ='PyG 3 Años'!$C$14 -> 0 | C36: ='PyG 3 Años'!$C$14 -> 0 | E36: Las ferias no dependen de tener sala.
A37: CONTRIBUCIÓN DEL AÑO | B37: =B33+B34-B35+B36 -> 198418.45 | C37: =C33+C34-C35+C36 -> 59773.695
A38: Fijos del año | B38: ='PyG 3 Años'!$C$22 -> 166279.69 | C38: ='PyG 3 Años'!$C$22-'0. Supuestos'!$B$88 -> 166279.69 | E38: El despacho resta el ahorro que pongas en «0. Supuestos» (a cero, los mismos fijos).
A39: RESULTADO ANTES DE IMPUESTOS | B39: =B37-B38 -> 32138.755 | C39: =C37-C38 -> -106506
A40: ¿Gana dinero? | B40: =IF(NOT(ISNUMBER(B39)),"",IF(B39>=0,"Gana dinero","Pierde dinero")) -> Gana dinero | C40: =IF(NOT(ISNUMBER(C39)),"",IF(C39>=0,"Gana dinero","Pierde dinero")) -> Pierde dinero
A41: Ahorro de fijos al año que necesitaría el despacho para no perder dinero | C41: =MAX(0,C38-C37) -> 106506 | E41: Si un despacho más pequeño (menos renta, menos plantilla) no consigue ahorrarte esto, la sala es la que paga el negocio.
A43: El despacho de esta hoja es el MISMO local vendiendo sólo para llevar. Un despacho de verdad es otro local, con otra renta y otro CAPEX (libro 2, «Variante del Formato»): para estudiarlo, haz una copia de este libro con sus cifras.

Sheet Personal
A1: Personal: Lo que Pesa la Plantilla
A2: AI Chef Pro · aichef.pro — Cómo Montar una Churrería-Chocolatería
A3: El coste de la plantilla llega del libro 8, que es donde viven el convenio, el suelo del SMI y las dos figuras de nocturnidad. Aquí sólo se mide lo que pesa en el negocio.
A5: Año de Crucero
A6: Coste anual de la plantilla (libro 8) | B6: ='0. Supuestos'!$B$39 -> 119350.2 | C6: Con la Seguridad Social de empresa, el refuerzo de Navidad y Reyes y las sustituciones de vacaciones. Coste por puesto = el mayor entre su salario y el SMI.
A7: Cuota de autónomos del titular (de los gastos fijos) | B7: ='0. Supuestos'!$B$81*'0. Supuestos'!$B$44 -> 3840 | C7: El titular está en la plantilla como un puesto más: aquí sólo va su cuota.
A8: COSTE TOTAL DE LAS PERSONAS | B8: =B6+B7 -> 123190.2
A9: Al mes | B9: =IFERROR(B8/'0. Supuestos'!$B$44,"") -> 10265.85
A10: Por ración vendida | B10: =IFERROR(B8/'PyG 3 Años'!$C$7,"") -> 1.1470224
A11: Sobre las ventas del año (estimación) | B11: =IFERROR(B8/'PyG 3 Años'!$C$28,"") -> 0.52972101 | C11: Información, no veredicto.
A12: Sobre la contribución del año | B12: =IFERROR(B8/'PyG 3 Años'!$C$15,"") -> 0.62086062 | C12: Qué parte de lo que deja la carta se va en personas.
A13: Raciones al día que hacen falta sólo para pagar a las personas | B13: =IFERROR(B8/'Punto de Equilibrio'!$B$9/'Punto de Equilibrio'!$B$10,"") -> 185.22342
A15: Lo que Este Libro No Hace
A16: No reproduce el cuadrante semanal por empleado ni las nóminas: el libro 8 calcula las horas por franja, las dos figuras de nocturnidad (el trabajador nocturno del Estatuto y el plus del convenio) y el coste anual por puesto. Para el cuadrante semana a semana, el Kit de Gestión de Personal de aichef.pro.

Sheet Tesorería 12 meses
A1: Tesorería del Primer Año, Mes a Mes
A2: AI Chef Pro · aichef.pro — Cómo Montar una Churrería-Chocolatería
A3: Los doce meses que empiezan el mes de apertura, con la rampa de arranque. Flujos sin IVA. El valle es el saldo más bajo: si baja de cero, el fondo de maniobra no aguanta.
A5: Mes de explotación | B5: 1 | C5: 2 | D5: 3 | E5: 4 | F5: 5 | G5: 6 | H5: 7 | I5: 8 | J5: 9 | K5: 10 | L5: 11 | M5: 12 | N5: Año 1
A6: Mes del calendario (número) | B6: =MOD('0. Supuestos'!$B$45+B5-1-1,'0. Supuestos'!$B$44)+1 -> 9 | C6: =MOD('0. Supuestos'!$B$45+C5-1-1,'0. Supuestos'!$B$44)+1 -> 10 | D6: =MOD('0. Supuestos'!$B$45+D5-1-1,'0. Supuestos'!$B$44)+1 -> 11 | E6: =MOD('0. Supuestos'!$B$45+E5-1-1,'0. Supuestos'!$B$44)+1 -> 12 | F6: =MOD('0. Supuestos'!$B$45+F5-1-1,'0. Supuestos'!$B$44)+1 -> 1 | G6: =MOD('0. Supuestos'!$B$45+G5-1-1,'0. Supuestos'!$B$44)+1 -> 2 | H6: =MOD('0. Supuestos'!$B$45+H5-1-1,'0. Supuestos'!$B$44)+1 -> 3 | I6: =MOD('0. Supuestos'!$B$45+I5-1-1,'0. Supuestos'!$B$44)+1 -> 4 | ... M6: =MOD('0. Supuestos'!$B$45+M5-1-1,'0. Supuestos'!$B$44)+1 -> 8
A7: Mes | B7: =INDEX('Tesorería 12 meses'!$B$42:$B$53,B6) -> Septiembre | C7: =INDEX('Tesorería 12 meses'!$B$42:$B$53,C6) -> Octubre | D7: =INDEX('Tesorería 12 meses'!$B$42:$B$53,D6) -> Noviembre | E7: =INDEX('Tesorería 12 meses'!$B$42:$B$53,E6) -> Diciembre | F7: =INDEX('Tesorería 12 meses'!$B$42:$B$53,F6) -> Enero | G7: =INDEX('Tesorería 12 meses'!$B$42:$B$53,G6) -> Febrero | H7: =INDEX('Tesorería 12 meses'!$B$42:$B$53,H6) -> Marzo | I7: =INDEX('Tesorería 12 meses'!$B$42:$B$53,I6) -> Abril | ... M7: =INDEX('Tesorería 12 meses'!$B$42:$B$53,M6) -> Agosto
A8: Coeficiente del mes | B8: =INDEX('Tesorería 12 meses'!$C$42:$C$53,B6) -> 0.8 | C8: =INDEX('Tesorería 12 meses'!$C$42:$C$53,C6) -> 1.1 | D8: =INDEX('Tesorería 12 meses'!$C$42:$C$53,D6) -> 1.3 | E8: =INDEX('Tesorería 12 meses'!$C$42:$C$53,E6) -> 1.75 | F8: =INDEX('Tesorería 12 meses'!$C$42:$C$53,F6) -> 1.25 | G8: =INDEX('Tesorería 12 meses'!$C$42:$C$53,G6) -> 1.15 | H8: =INDEX('Tesorería 12 meses'!$C$42:$C$53,H6) -> 1.1 | I8: =INDEX('Tesorería 12 meses'!$C$42:$C$53,I6) -> 0.95 | ... M8: =INDEX('Tesorería 12 meses'!$C$42:$C$53,M6) -> 0.5
A9: ¿Julio o agosto? (1 sí, 0 no) | B9: =IF(OR(B6='0. Supuestos'!$B$46,B6='0. Supuestos'!$B$47),1,0) -> 0 | C9: =IF(OR(C6='0. Supuestos'!$B$46,C6='0. Supuestos'!$B$47),1,0) -> 0 | D9: =IF(OR(D6='0. Supuestos'!$B$46,D6='0. Supuestos'!$B$47),1,0) -> 0 | E9: =IF(OR(E6='0. Supuestos'!$B$46,E6='0. Supuestos'!$B$47),1,0) -> 0 | F9: =IF(OR(F6='0. Supuestos'!$B$46,F6='0. Supuestos'!$B$47),1,0) -> 0 | G9: =IF(OR(G6='0. Supuestos'!$B$46,G6='0. Supuestos'!$B$47),1,0) -> 0 | H9: =IF(OR(H6='0. Supuestos'!$B$46,H6='0. Supuestos'!$B$47),1,0) -> 0 | I9: =IF(OR(I6='0. Supuestos'!$B$46,I6='0. Supuestos'!$B$47),1,0) -> 0 | ... M9: =IF(OR(M6='0. Supuestos'!$B$46,M6='0. Supuestos'!$B$47),1,0) -> 1
A10: Rampa de arranque | B10: =IFERROR(MIN(1,'0. Supuestos'!$B$48+(1-'0. Supuestos'!$B$48)*(B5-1)/('0. Supuestos'!$B$49-1)),1) -> 0.55 | C10: =IFERROR(MIN(1,'0. Supuestos'!$B$48+(1-'0. Supuestos'!$B$48)*(C5-1)/('0. Supuestos'!$B$49-1)),1) -> 0.64 | D10: =IFERROR(MIN(1,'0. Supuestos'!$B$48+(1-'0. Supuestos'!$B$48)*(D5-1)/('0. Supuestos'!$B$49-1)),1) -> 0.73 | E10: =IFERROR(MIN(1,'0. Supuestos'!$B$48+(1-'0. Supuestos'!$B$48)*(E5-1)/('0. Supuestos'!$B$49-1)),1) -> 0.82 | F10: =IFERROR(MIN(1,'0. Supuestos'!$B$48+(1-'0. Supuestos'!$B$48)*(F5-1)/('0. Supuestos'!$B$49-1)),1) -> 0.91 | G10: =IFERROR(MIN(1,'0. Supuestos'!$B$48+(1-'0. Supuestos'!$B$48)*(G5-1)/('0. Supuestos'!$B$49-1)),1) -> 1 | H10: =IFERROR(MIN(1,'0. Supuestos'!$B$48+(1-'0. Supuestos'!$B$48)*(H5-1)/('0. Supuestos'!$B$49-1)),1) -> 1 | I10: =IFERROR(MIN(1,'0. Supuestos'!$B$48+(1-'0. Supuestos'!$B$48)*(I5-1)/('0. Supuestos'!$B$49-1)),1) -> 1 | ... M10: =IFERROR(MIN(1,'0. Supuestos'!$B$48+(1-'0. Supuestos'!$B$48)*(M5-1)/('0. Supuestos'!$B$49-1)),1) -> 1
A11: Raciones del mes | B11: =IFERROR('0. Supuestos'!$B$19*B8/'0. Supuestos'!$B$44*B10,"") -> 3938 | C11: =IFERROR('0. Supuestos'!$B$19*C8/'0. Supuestos'!$B$44*C10,"") -> 6300.8 | D11: =IFERROR('0. Supuestos'!$B$19*D8/'0. Supuestos'!$B$44*D10,"") -> 8493.55 | E11: =IFERROR('0. Supuestos'!$B$19*E8/'0. Supuestos'!$B$44*E10,"") -> 12843.25 | F11: =IFERROR('0. Supuestos'!$B$19*F8/'0. Supuestos'!$B$44*F10,"") -> 10180.625 | G11: =IFERROR('0. Supuestos'!$B$19*G8/'0. Supuestos'!$B$44*G10,"") -> 10292.5 | H11: =IFERROR('0. Supuestos'!$B$19*H8/'0. Supuestos'!$B$44*H10,"") -> 9845 | I11: =IFERROR('0. Supuestos'!$B$19*I8/'0. Supuestos'!$B$44*I10,"") -> 8502.5 | ... M11: =IFERROR('0. Supuestos'!$B$19*M8/'0. Supuestos'!$B$44*M10,"") -> 4475 | N11: =SUM(B11:M11) -> 93666.225
A12: Lo que Entra: Contribución
A13: Ventas sin IVA de la carta de invierno | B13: =IF(B9=1,0,B11*'Canales y Punto Muerto'!$D$8) -> 8511.45 | C13: =IF(C9=1,0,C11*'Canales y Punto Muerto'!$D$8) -> 13618.32 | D13: =IF(D9=1,0,D11*'Canales y Punto Muerto'!$D$8) -> 18357.65 | E13: =IF(E9=1,0,E11*'Canales y Punto Muerto'!$D$8) -> 27758.934 | F13: =IF(F9=1,0,F11*'Canales y Punto Muerto'!$D$8) -> 22004.033 | G13: =IF(G9=1,0,G11*'Canales y Punto Muerto'!$D$8) -> 22245.835 | H13: =IF(H9=1,0,H11*'Canales y Punto Muerto'!$D$8) -> 21278.625 | I13: =IF(I9=1,0,I11*'Canales y Punto Muerto'!$D$8) -> 18376.994 | ... M13: =IF(M9=1,0,M11*'Canales y Punto Muerto'!$D$8) -> 0 | N13: =SUM(B13:M13) -> 182135.36
A14: Ventas sin IVA de julio y agosto (salida elegida, libro 5) | B14: =IFERROR(IF(B9=1,IF(INDEX('0. Supuestos'!$B$20:$B$31,'0. Supuestos'!$B$46)+INDEX('0. Supuestos'!$B$20:$B$31,'0. Supuestos'!$B$47)>0,'0. Supuestos'!$B$37*B8/(INDEX('0. Supuestos'!$B$20:$B$31,'0. Supuestos'!$B$46)+INDEX('0. Supuestos'!$B$20:$B$31,'0. Supuestos'!$B$47))*B10,0),0),"") -> 0 | C14: =IFERROR(IF(C9=1,IF(INDEX('0. Supuestos'!$B$20:$B$31,'0. Supuestos'!$B$46)+INDEX('0. Supuestos'!$B$20:$B$31,'0. Supuestos'!$B$47)>0,'0. Supuestos'!$B$37*C8/(INDEX('0. Supuestos'!$B$20:$B$31,'0. Supuestos'!$B$46)+INDEX('0. Supuestos'!$B$20:$B$31,'0. Supuestos'!$B$47))*C10,0),0),"") -> 0 | D14: =IFERROR(IF(D9=1,IF(INDEX('0. Supuestos'!$B$20:$B$31,'0. Supuestos'!$B$46)+INDEX('0. Supuestos'!$B$20:$B$31,'0. Supuestos'!$B$47)>0,'0. Supuestos'!$B$37*D8/(INDEX('0. Supuestos'!$B$20:$B$31,'0. Supuestos'!$B$46)+INDEX('0. Supuestos'!$B$20:$B$31,'0. Supuestos'!$B$47))*D10,0),0),"") -> 0 | E14: =IFERROR(IF(E9=1,IF(INDEX('0. Supuestos'!$B$20:$B$31,'0. Supuestos'!$B$46)+INDEX('0. Supuestos'!$B$20:$B$31,'0. Supuestos'!$B$47)>0,'0. Supuestos'!$B$37*E8/(INDEX('0. Supuestos'!$B$20:$B$31,'0. Supuestos'!$B$46)+INDEX('0. Supuestos'!$B$20:$B$31,'0. Supuestos'!$B$47))*E10,0),0),"") -> 0 | F14: =IFERROR(IF(F9=1,IF(INDEX('0. Supuestos'!$B$20:$B$31,'0. Supuestos'!$B$46)+INDEX('0. Supuestos'!$B$20:$B$31,'0. Supuestos'!$B$47)>0,'0. Supuestos'!$B$37*F8/(INDEX('0. Supuestos'!$B$20:$B$31,'0. Supuestos'!$B$46)+INDEX('0. Supuestos'!$B$20:$B$31,'0. Supuestos'!$B$47))*F10,0),0),"") -> 0 | G14: =IFERROR(IF(G9=1,IF(INDEX('0. Supuestos'!$B$20:$B$31,'0. Supuestos'!$B$46)+INDEX('0. Supuestos'!$B$20:$B$31,'0. Supuestos'!$B$47)>0,'0. Supuestos'!$B$37*G8/(INDEX('0. Supuestos'!$B$20:$B$31,'0. Supuestos'!$B$46)+INDEX('0. Supuestos'!$B$20:$B$31,'0. Supuestos'!$B$47))*G10,0),0),"") -> 0 | H14: =IFERROR(IF(H9=1,IF(INDEX('0. Supuestos'!$B$20:$B$31,'0. Supuestos'!$B$46)+INDEX('0. Supuestos'!$B$20:$B$31,'0. Supuestos'!$B$47)>0,'0. Supuestos'!$B$37*H8/(INDEX('0. Supuestos'!$B$20:$B$31,'0. Supuestos'!$B$46)+INDEX('0. Supuestos'!$B$20:$B$31,'0. Supuestos'!$B$47))*H10,0),0),"") -> 0 | I14: =IFERROR(IF(I9=1,IF(INDEX('0. Supuestos'!$B$20:$B$31,'0. Supuestos'!$B$46)+INDEX('0. Supuestos'!$B$20:$B$31,'0. Supuestos'!$B$47)>0,'0. Supuestos'!$B$37*I8/(INDEX('0. Supuestos'!$B$20:$B$31,'0. Supuestos'!$B$46)+INDEX('0. Supuestos'!$B$20:$B$31,'0. Supuestos'!$B$47))*I10,0),0),"") -> 0 | ... M14: =IFERROR(IF(M9=1,IF(INDEX('0. Supuestos'!$B$20:$B$31,'0. Supuestos'!$B$46)+INDEX('0. Supuestos'!$B$20:$B$31,'0. Supuestos'!$B$47)>0,'0. Supuestos'!$B$37*M8/(INDEX('0. Supuestos'!$B$20:$B$31,'0. Supuestos'!$B$46)+INDEX('0. Supuestos'!$B$20:$B$31,'0. Supuestos'!$B$47))*M10,0),0),"") -> 9875.1045 | N14: =SUM(B14:M14) -> 20737.72
A15: Materia de la carta de invierno | B15: =IF(B9=1,0,B11*'Canales y Punto Muerto'!$E$8) -> 1113.8354 | C15: =IF(C9=1,0,C11*'Canales y Punto Muerto'!$E$8) -> 1782.1367 | D15: =IF(D9=1,0,D11*'Canales y Punto Muerto'!$E$8) -> 2402.3405 | E15: =IF(E9=1,0,E11*'Canales y Punto Muerto'!$E$8) -> 3632.6224 | F15: =IF(F9=1,0,F11*'Canales y Punto Muerto'!$E$8) -> 2879.5178 | G15: =IF(G9=1,0,G11*'Canales y Punto Muerto'!$E$8) -> 2911.1608 | H15: =IF(H9=1,0,H11*'Canales y Punto Muerto'!$E$8) -> 2784.5886 | I15: =IF(I9=1,0,I11*'Canales y Punto Muerto'!$E$8) -> 2404.872 | ... M15: =IF(M9=1,0,M11*'Canales y Punto Muerto'!$E$8) -> 0 | N15: =SUM(B15:M15) -> 23834.813
A16: Contribución de la carta de invierno | B16: =B13-B15 -> 7397.6146 | C16: =C13-C15 -> 11836.183 | D16: =D13-D15 -> 15955.31 | E16: =E13-E15 -> 24126.311 | F16: =F13-F15 -> 19124.515 | G16: =G13-G15 -> 19334.674 | H16: =H13-H15 -> 18494.036 | I16: =I13-I15 -> 15972.122 | ... M16: =M13-M15 -> 0 | N16: =SUM(B16:M16) -> 158300.55
A17: Contribución de julio y agosto (salida elegida, libro 5) | B17: =IFERROR(IF(B9=1,IF(INDEX('0. Supuestos'!$B$20:$B$31,'0. Supuestos'!$B$46)+INDEX('0. Supuestos'!$B$20:$B$31,'0. Supuestos'!$B$47)>0,'0. Supuestos'!$B$33*B8/(INDEX('0. Supuestos'!$B$20:$B$31,'0. Supuestos'!$B$46)+INDEX('0. Supuestos'!$B$20:$B$31,'0. Supuestos'!$B$47))*B10,0),0),"") -> 0 | C17: =IFERROR(IF(C9=1,IF(INDEX('0. Supuestos'!$B$20:$B$31,'0. Supuestos'!$B$46)+INDEX('0. Supuestos'!$B$20:$B$31,'0. Supuestos'!$B$47)>0,'0. Supuestos'!$B$33*C8/(INDEX('0. Supuestos'!$B$20:$B$31,'0. Supuestos'!$B$46)+INDEX('0. Supuestos'!$B$20:$B$31,'0. Supuestos'!$B$47))*C10,0),0),"") -> 0 | D17: =IFERROR(IF(D9=1,IF(INDEX('0. Supuestos'!$B$20:$B$31,'0. Supuestos'!$B$46)+INDEX('0. Supuestos'!$B$20:$B$31,'0. Supuestos'!$B$47)>0,'0. Supuestos'!$B$33*D8/(INDEX('0. Supuestos'!$B$20:$B$31,'0. Supuestos'!$B$46)+INDEX('0. Supuestos'!$B$20:$B$31,'0. Supuestos'!$B$47))*D10,0),0),"") -> 0 | E17: =IFERROR(IF(E9=1,IF(INDEX('0. Supuestos'!$B$20:$B$31,'0. Supuestos'!$B$46)+INDEX('0. Supuestos'!$B$20:$B$31,'0. Supuestos'!$B$47)>0,'0. Supuestos'!$B$33*E8/(INDEX('0. Supuestos'!$B$20:$B$31,'0. Supuestos'!$B$46)+INDEX('0. Supuestos'!$B$20:$B$31,'0. Supuestos'!$B$47))*E10,0),0),"") -> 0 | F17: =IFERROR(IF(F9=1,IF(INDEX('0. Supuestos'!$B$20:$B$31,'0. Supuestos'!$B$46)+INDEX('0. Supuestos'!$B$20:$B$31,'0. Supuestos'!$B$47)>0,'0. Supuestos'!$B$33*F8/(INDEX('0. Supuestos'!$B$20:$B$31,'0. Supuestos'!$B$46)+INDEX('0. Supuestos'!$B$20:$B$31,'0. Supuestos'!$B$47))*F10,0),0),"") -> 0 | G17: =IFERROR(IF(G9=1,IF(INDEX('0. Supuestos'!$B$20:$B$31,'0. Supuestos'!$B$46)+INDEX('0. Supuestos'!$B$20:$B$31,'0. Supuestos'!$B$47)>0,'0. Supuestos'!$B$33*G8/(INDEX('0. Supuestos'!$B$20:$B$31,'0. Supuestos'!$B$46)+INDEX('0. Supuestos'!$B$20:$B$31,'0. Supuestos'!$B$47))*G10,0),0),"") -> 0 | H17: =IFERROR(IF(H9=1,IF(INDEX('0. Supuestos'!$B$20:$B$31,'0. Supuestos'!$B$46)+INDEX('0. Supuestos'!$B$20:$B$31,'0. Supuestos'!$B$47)>0,'0. Supuestos'!$B$33*H8/(INDEX('0. Supuestos'!$B$20:$B$31,'0. Supuestos'!$B$46)+INDEX('0. Supuestos'!$B$20:$B$31,'0. Supuestos'!$B$47))*H10,0),0),"") -> 0 | I17: =IFERROR(IF(I9=1,IF(INDEX('0. Supuestos'!$B$20:$B$31,'0. Supuestos'!$B$46)+INDEX('0. Supuestos'!$B$20:$B$31,'0. Supuestos'!$B$47)>0,'0. Supuestos'!$B$33*I8/(INDEX('0. Supuestos'!$B$20:$B$31,'0. Supuestos'!$B$46)+INDEX('0. Supuestos'!$B$20:$B$31,'0. Supuestos'!$B$47))*I10,0),0),"") -> 0 | ... M17: =IFERROR(IF(M9=1,IF(INDEX('0. Supuestos'!$B$20:$B$31,'0. Supuestos'!$B$46)+INDEX('0. Supuestos'!$B$20:$B$31,'0. Supuestos'!$B$47)>0,'0. Supuestos'!$B$33*M8/(INDEX('0. Supuestos'!$B$20:$B$31,'0. Supuestos'!$B$46)+INDEX('0. Supuestos'!$B$20:$B$31,'0. Supuestos'!$B$47))*M10,0),0),"") -> 8270.8138 | N17: =SUM(B17:M17) -> 17368.709
A18: Renovación del aceite | B18: =B11*'0. Supuestos'!$B$17 -> 111.8328 | C18: =C11*'0. Supuestos'!$B$17 -> 178.93247 | D18: =D11*'0. Supuestos'!$B$17 -> 241.20301 | E18: =E11*'0. Supuestos'!$B$17 -> 364.72742 | F18: =F11*'0. Supuestos'!$B$17 -> 289.1132 | G18: =G11*'0. Supuestos'!$B$17 -> 292.29026 | H18: =H11*'0. Supuestos'!$B$17 -> 279.58199 | I18: =I11*'0. Supuestos'!$B$17 -> 241.45717 | ... M18: =M11*'0. Supuestos'!$B$17 -> 127.08272 | N18: =SUM(B18:M18) -> 2659.9685
A19: Ferias (resultado del año repartido) | B19: =IFERROR('0. Supuestos'!$B$32/'0. Supuestos'!$B$44,"") -> 0 | C19: =IFERROR('0. Supuestos'!$B$32/'0. Supuestos'!$B$44,"") -> 0 | D19: =IFERROR('0. Supuestos'!$B$32/'0. Supuestos'!$B$44,"") -> 0 | E19: =IFERROR('0. Supuestos'!$B$32/'0. Supuestos'!$B$44,"") -> 0 | F19: =IFERROR('0. Supuestos'!$B$32/'0. Supuestos'!$B$44,"") -> 0 | G19: =IFERROR('0. Supuestos'!$B$32/'0. Supuestos'!$B$44,"") -> 0 | H19: =IFERROR('0. Supuestos'!$B$32/'0. Supuestos'!$B$44,"") -> 0 | I19: =IFERROR('0. Supuestos'!$B$32/'0. Supuestos'!$B$44,"") -> 0 | ... M19: =IFERROR('0. Supuestos'!$B$32/'0. Supuestos'!$B$44,"") -> 0 | N19: =SUM(B19:M19) -> 0
A20: CONTRIBUCIÓN DEL MES | B20: =B16+B17-B18+B19 -> 7285.7818 | C20: =C16+C17-C18+C19 -> 11657.251 | D20: =D16+D17-D18+D19 -> 15714.107 | E20: =E16+E17-E18+E19 -> 23761.584 | F20: =F16+F17-F18+F19 -> 18835.402 | G20: =G16+G17-G18+G19 -> 19042.384 | H20: =H16+H17-H18+H19 -> 18214.454 | I20: =I16+I17-I18+I19 -> 15730.665 | ... M20: =M16+M17-M18+M19 -> 8143.7311 | N20: =SUM(B20:M20) -> 173009.29
A21: Lo que Sale: Fijos y Deuda
A22: Plantilla | B22: =IFERROR('0. Supuestos'!$B$39/'0. Supuestos'!$B$44,"") -> 9945.8501 | C22: =IFERROR('0. Supuestos'!$B$39/'0. Supuestos'!$B$44,"") -> 9945.8501 | D22: =IFERROR('0. Supuestos'!$B$39/'0. Supuestos'!$B$44,"") -> 9945.8501 | E22: =IFERROR('0. Supuestos'!$B$39/'0. Supuestos'!$B$44,"") -> 9945.8501 | F22: =IFERROR('0. Supuestos'!$B$39/'0. Supuestos'!$B$44,"") -> 9945.8501 | G22: =IFERROR('0. Supuestos'!$B$39/'0. Supuestos'!$B$44,"") -> 9945.8501 | H22: =IFERROR('0. Supuestos'!$B$39/'0. Supuestos'!$B$44,"") -> 9945.8501 | I22: =IFERROR('0. Supuestos'!$B$39/'0. Supuestos'!$B$44,"") -> 9945.8501 | ... M22: =IFERROR('0. Supuestos'!$B$39/'0. Supuestos'!$B$44,"") -> 9945.8501 | N22: =SUM(B22:M22) -> 119350.2
A23: Renta | B23: ='0. Supuestos'!$B$8 -> 910 | C23: ='0. Supuestos'!$B$8 -> 910 | D23: ='0. Supuestos'!$B$8 -> 910 | E23: ='0. Supuestos'!$B$8 -> 910 | F23: ='0. Supuestos'!$B$8 -> 910 | G23: ='0. Supuestos'!$B$8 -> 910 | H23: ='0. Supuestos'!$B$8 -> 910 | I23: ='0. Supuestos'!$B$8 -> 910 | ... M23: ='0. Supuestos'!$B$8 -> 910 | N23: =SUM(B23:M23) -> 10920
A24: Gastos fijos | B24: ='0. Supuestos'!$B$83 -> 1870 | C24: ='0. Supuestos'!$B$83 -> 1870 | D24: ='0. Supuestos'!$B$83 -> 1870 | E24: ='0. Supuestos'!$B$83 -> 1870 | F24: ='0. Supuestos'!$B$83 -> 1870 | G24: ='0. Supuestos'!$B$83 -> 1870 | H24: ='0. Supuestos'!$B$83 -> 1870 | I24: ='0. Supuestos'!$B$83 -> 1870 | ... M24: ='0. Supuestos'!$B$83 -> 1870 | N24: =SUM(B24:M24) -> 22440
A25: Intereses del préstamo | B25: =INDEX('Financiación'!$C$28:$C$111,B5) -> 513.05 | C25: =INDEX('Financiación'!$C$28:$C$111,C5) -> 513.05 | D25: =INDEX('Financiación'!$C$28:$C$111,D5) -> 513.05 | E25: =INDEX('Financiación'!$C$28:$C$111,E5) -> 513.05 | F25: =INDEX('Financiación'!$C$28:$C$111,F5) -> 513.05 | G25: =INDEX('Financiación'!$C$28:$C$111,G5) -> 513.05 | H25: =INDEX('Financiación'!$C$28:$C$111,H5) -> 513.05 | I25: =INDEX('Financiación'!$C$28:$C$111,I5) -> 507.69228 | ... M25: =INDEX('Financiación'!$C$28:$C$111,M5) -> 485.98317 | N25: =SUM(B25:M25) -> 6075.6785
A26: Devolución de principal | B26: =INDEX('Financiación'!$D$28:$D$111,B5) -> 0 | C26: =INDEX('Financiación'!$D$28:$D$111,C5) -> 0 | D26: =INDEX('Financiación'!$D$28:$D$111,D5) -> 0 | E26: =INDEX('Financiación'!$D$28:$D$111,E5) -> 0 | F26: =INDEX('Financiación'!$D$28:$D$111,F5) -> 0 | G26: =INDEX('Financiación'!$D$28:$D$111,G5) -> 0 | H26: =INDEX('Financiación'!$D$28:$D$111,H5) -> 1036.9773 | I26: =INDEX('Financiación'!$D$28:$D$111,I5) -> 1042.3351 | ... M26: =INDEX('Financiación'!$D$28:$D$111,M5) -> 1064.0442 | N26: =SUM(B26:M26) -> 6302.7856
A27: TOTAL PAGOS FIJOS | B27: =SUM(B22:B26) -> 13238.9 | C27: =SUM(C22:C26) -> 13238.9 | D27: =SUM(D22:D26) -> 13238.9 | E27: =SUM(E22:E26) -> 13238.9 | F27: =SUM(F22:F26) -> 13238.9 | G27: =SUM(G22:G26) -> 13238.9 | H27: =SUM(H22:H26) -> 14275.877 | I27: =SUM(I22:I26) -> 14275.877 | ... M27: =SUM(M22:M26) -> 14275.877 | N27: =SUM(B27:M27) -> 165088.67
A28: FLUJO DEL MES | B28: =B20-B27 -> -5953.1183 | C28: =C20-C27 -> -1581.6493 | D28: =D20-D27 -> 2475.2065 | E28: =E20-E27 -> 10522.684 | F28: =F20-F27 -> 5596.5016 | G28: =G20-G27 -> 5803.484 | H28: =H20-H27 -> 3938.5769 | I28: =I20-I27 -> 1454.7877 | ... M28: =M20-M27 -> -6132.1463 | N28: =SUM(B28:M28) -> 7920.6204
A29: SALDO DE CAJA AL CIERRE DEL MES | B29: =$B$32+B28 -> 73099.362 | C29: =B29+C28 -> 71517.712 | D29: =C29+D28 -> 73992.919 | E29: =D29+E28 -> 84515.602 | F29: =E29+F28 -> 90112.104 | G29: =F29+G28 -> 95915.588 | H29: =G29+H28 -> 99854.165 | I29: =H29+I28 -> 101308.95 | J29: =I29+J28 -> 101107.88 | ... M29: =L29+M28 -> 86973.1
A31: El Valle y el Fondo de Maniobra
A32: Saldo el día que abres (lo que pones tú + préstamo - CAPEX) | B32: ='Financiación'!$B$6+'Financiación'!$B$7-'0. Supuestos'!$B$7 -> 79052.48
A33: De él, fondo de maniobra (hoja «Inversión Inicial») | B33: ='Inversión Inicial'!$B$19 -> 79052.48
A34: Saldo más bajo del año (el valle) | B34: =MIN(B29:M29) -> 71517.712
A35: Mes del valle | B35: =IFERROR(INDEX(B7:M7,MATCH(B34,B29:M29,0)),"") -> Octubre
A36: ¿Aguanta el fondo el valle? | B36: =IF(NOT(ISNUMBER(B34)),"",IF(B34>=0,"Aguanta: el saldo no baja de cero","No aguanta: el saldo se pone en negativo")) -> Aguanta: el saldo no baja de cero
A37: Caja que se come el arranque hasta el valle | B37: =B32-B34 -> 7534.7676
A38: En negativo, el valle dice cuántos euros te faltan en el peor mes: sube los meses de colchón, negocia más carencia o abre en otro mes. Ningún cobro se aplaza: en una churrería se cobra al momento. El IVA de la explotación se liquida cada trimestre y no está aquí.
A40: Calendario (lo Usan las Filas de Arriba)
A41: Número del mes | B41: Mes | C41: Coeficiente (de «0. Supuestos»)
A42: 1 | B42: Enero | C42: ='0. Supuestos'!$B$20 -> 1.25
A43: 2 | B43: Febrero | C43: ='0. Supuestos'!$B$21 -> 1.15
A44: 3 | B44: Marzo | C44: ='0. Supuestos'!$B$22 -> 1.1
A45: 4 | B45: Abril | C45: ='0. Supuestos'!$B$23 -> 0.95
A46: 5 | B46: Mayo | C46: ='0. Supuestos'!$B$24 -> 0.85
A47: 6 | B47: Junio | C47: ='0. Supuestos'!$B$25 -> 0.7
A48: 7 | B48: Julio | C48: ='0. Supuestos'!$B$26 -> 0.55
A49: 8 | B49: Agosto | C49: ='0. Supuestos'!$B$27 -> 0.5
A50: 9 | B50: Septiembre | C50: ='0. Supuestos'!$B$28 -> 0.8
A51: 10 | B51: Octubre | C51: ='0. Supuestos'!$B$29 -> 1.1
A52: 11 | B52: Noviembre | C52: ='0. Supuestos'!$B$30 -> 1.3
A53: 12 | B53: Diciembre | C53: ='0. Supuestos'!$B$31 -> 1.75

Sheet Financiación
A1: Financiación: De Dónde Sale y Cuánto Cuesta Devolverlo
A2: AI Chef Pro · aichef.pro — Cómo Montar una Churrería-Chocolatería
A3: El cuadro de amortización es MENSUAL (84 filas) porque la carencia son seis meses. La cuota es la anualidad del sistema francés escrita a mano: la función PMT está prohibida en esta familia. La lectura de si aguanta el banco va en euros.
A5: Origen de los Fondos
A6: Lo que pones tú (recursos propios) | B6: =B11-B7 -> 66168.13 | H6: La inversión total menos el préstamo. Un banco quiere verte arriesgar lo tuyo.
A7: Préstamo bancario | B7: ='0. Supuestos'!$B$63 -> 99300
A8: TOTAL ORIGEN DE LOS FONDOS | B8: =B6+B7 -> 165468.13
A9: Parte que pones tú, en % | B9: =IFERROR(B6/B8,"") -> 0.39988444
A10: Usos
A11: Inversión total (CAPEX + fondo de maniobra) | B11: ='Inversión Inicial'!$B$24 -> 165468.13
A12: Lo que pondrías tú con la estructura de «0. Supuestos» | B12: =B11*'0. Supuestos'!$B$59 -> 66187.252
A13: Diferencia (lo que pones tú de verdad menos lo de la estructura) | B13: =B6-B12 -> -19.122041 | H13: Sale de redondear el préstamo: unos cientos de euros arriba o abajo.
A14: El Préstamo como Punto Fijo
A15: Préstamo que pide la estructura (redondeado) | B15: =IFERROR(ROUND('0. Supuestos'!$B$58*B11/'0. Supuestos'!$B$64,0)*'0. Supuestos'!$B$64,"") -> 99300 | H15: El porcentaje de préstamo por la inversión total, redondeado. La inversión lleva el fondo, y el fondo los intereses de este mismo préstamo: por eso el préstamo es una celda verde y aquí se comprueba.
A16: Comprobación del punto fijo | B16: =IF(NOT(ISNUMBER(B15)),"",IF(ABS(B15-B7)<='0. Supuestos'!$B$65,"Cerrado: el préstamo es el que pide la estructura","REVISA: copia la cifra de la fila 15 en el préstamo de «0. Supuestos»")) -> Cerrado: el préstamo es el que pide la estructura | H16: Si cambias el CAPEX, los fijos o los meses de colchón, el préstamo que pide la estructura cambia: copia la cifra nueva y esta fila vuelve a decir «Cerrado». A la segunda vez se queda quieta.
A17: Condiciones del Préstamo
A18: Importe del principal | B18: =IF('0. Supuestos'!$B$63=0,"",'0. Supuestos'!$B$63) -> 99300
A19: Tipo de interés nominal anual | B19: ='0. Supuestos'!$B$60 -> 0.062
A20: Tipo mensual | B20: =IFERROR(B19/'0. Supuestos'!$B$44,"") -> 0.0051666667
A21: Plazo total (meses) | B21: ='0. Supuestos'!$B$61 -> 84
A22: Carencia de principal aplicada (meses) | B22: =IF('0. Supuestos'!$B$62>='0. Supuestos'!$B$61,'0. Supuestos'!$B$61-1,'0. Supuestos'!$B$62) -> 6 | H22: Una carencia igual o mayor que el plazo no existe: la hoja la recorta.
A23: Meses de amortización | B23: =B21-B22 -> 78
A24: Cuota mensual durante la amortización | B24: =IFERROR(IF(B23<=0,"",IF(B20=0,B18/B23,B18*B20/(1-(1+B20)^(-B23)))),"") -> 1550.0273
A25: Sistema francés: capital por tipo mensual dividido entre uno menos (uno más el tipo) elevado a menos el número de cuotas. Con el tipo a cero es el principal entre los meses de amortización.
A27: Mes | B27: Capital pendiente | C27: Intereses | D27: Devolución de principal | E27: Cuota total | F27: Capital al cierre | H27: Notas
A28: 1 | B28: =IF($B$18="","",$B$18) -> 99300 | C28: =IF(OR(A28>$B$21,B28=""),"",B28*$B$20) -> 513.05 | D28: =IF(OR(A28>$B$21,B28=""),"",IF(A28<=$B$22,0,MIN(B28,$B$24-C28))) -> 0 | E28: =IF(C28="","",C28+D28) -> 513.05 | F28: =IF(D28="","",B28-D28) -> 99300 | H28: Durante la carencia la devolución de principal vale cero y sólo se pagan intereses.
A29: 2 | B29: =IF(OR(A29>$B$21,F28=""),"",F28) -> 99300 | C29: =IF(OR(A29>$B$21,B29=""),"",B29*$B$20) -> 513.05 | D29: =IF(OR(A29>$B$21,B29=""),"",IF(A29<=$B$22,0,MIN(B29,$B$24-C29))) -> 0 | E29: =IF(C29="","",C29+D29) -> 513.05 | F29: =IF(D29="","",B29-D29) -> 99300
A30: 3 | B30: =IF(OR(A30>$B$21,F29=""),"",F29) -> 99300 | C30: =IF(OR(A30>$B$21,B30=""),"",B30*$B$20) -> 513.05 | D30: =IF(OR(A30>$B$21,B30=""),"",IF(A30<=$B$22,0,MIN(B30,$B$24-C30))) -> 0 | E30: =IF(C30="","",C30+D30) -> 513.05 | F30: =IF(D30="","",B30-D30) -> 99300
A31: 4 | B31: =IF(OR(A31>$B$21,F30=""),"",F30) -> 99300 | C31: =IF(OR(A31>$B$21,B31=""),"",B31*$B$20) -> 513.05 | D31: =IF(OR(A31>$B$21,B31=""),"",IF(A31<=$B$22,0,MIN(B31,$B$24-C31))) -> 0 | E31: =IF(C31="","",C31+D31) -> 513.05 | F31: =IF(D31="","",B31-D31) -> 99300
A32: 5 | B32: =IF(OR(A32>$B$21,F31=""),"",F31) -> 99300 | C32: =IF(OR(A32>$B$21,B32=""),"",B32*$B$20) -> 513.05 | D32: =IF(OR(A32>$B$21,B32=""),"",IF(A32<=$B$22,0,MIN(B32,$B$24-C32))) -> 0 | E32: =IF(C32="","",C32+D32) -> 513.05 | F32: =IF(D32="","",B32-D32) -> 99300
A33: 6 | B33: =IF(OR(A33>$B$21,F32=""),"",F32) -> 99300 | C33: =IF(OR(A33>$B$21,B33=""),"",B33*$B$20) -> 513.05 | D33: =IF(OR(A33>$B$21,B33=""),"",IF(A33<=$B$22,0,MIN(B33,$B$24-C33))) -> 0 | E33: =IF(C33="","",C33+D33) -> 513.05 | F33: =IF(D33="","",B33-D33) -> 99300
A34: 7 | B34: =IF(OR(A34>$B$21,F33=""),"",F33) -> 99300 | C34: =IF(OR(A34>$B$21,B34=""),"",B34*$B$20) -> 513.05 | D34: =IF(OR(A34>$B$21,B34=""),"",IF(A34<=$B$22,0,MIN(B34,$B$24-C34))) -> 1036.9773 | E34: =IF(C34="","",C34+D34) -> 1550.0273 | F34: =IF(D34="","",B34-D34) -> 98263.023
A35: 8 | B35: =IF(OR(A35>$B$21,F34=""),"",F34) -> 98263.023 | C35: =IF(OR(A35>$B$21,B35=""),"",B35*$B$20) -> 507.69228 | D35: =IF(OR(A35>$B$21,B35=""),"",IF(A35<=$B$22,0,MIN(B35,$B$24-C35))) -> 1042.3351 | E35: =IF(C35="","",C35+D35) -> 1550.0273 | F35: =IF(D35="","",B35-D35) -> 97220.688
A36: 9 | B36: =IF(OR(A36>$B$21,F35=""),"",F35) -> 97220.688 | C36: =IF(OR(A36>$B$21,B36=""),"",B36*$B$20) -> 502.30689 | D36: =IF(OR(A36>$B$21,B36=""),"",IF(A36<=$B$22,0,MIN(B36,$B$24-C36))) -> 1047.7205 | E36: =IF(C36="","",C36+D36) -> 1550.0273 | F36: =IF(D36="","",B36-D36) -> 96172.967
A37: 10 | B37: =IF(OR(A37>$B$21,F36=""),"",F36) -> 96172.967 | C37: =IF(OR(A37>$B$21,B37=""),"",B37*$B$20) -> 496.89366 | D37: =IF(OR(A37>$B$21,B37=""),"",IF(A37<=$B$22,0,MIN(B37,$B$24-C37))) -> 1053.1337 | E37: =IF(C37="","",C37+D37) -> 1550.0273 | F37: =IF(D37="","",B37-D37) -> 95119.833
A38: 11 | B38: =IF(OR(A38>$B$21,F37=""),"",F37) -> 95119.833 | C38: =IF(OR(A38>$B$21,B38=""),"",B38*$B$20) -> 491.45247 | D38: =IF(OR(A38>$B$21,B38=""),"",IF(A38<=$B$22,0,MIN(B38,$B$24-C38))) -> 1058.5749 | E38: =IF(C38="","",C38+D38) -> 1550.0273 | F38: =IF(D38="","",B38-D38) -> 94061.259
A39: 12 | B39: =IF(OR(A39>$B$21,F38=""),"",F38) -> 94061.259 | C39: =IF(OR(A39>$B$21,B39=""),"",B39*$B$20) -> 485.98317 | D39: =IF(OR(A39>$B$21,B39=""),"",IF(A39<=$B$22,0,MIN(B39,$B$24-C39))) -> 1064.0442 | E39: =IF(C39="","",C39+D39) -> 1550.0273 | F39: =IF(D39="","",B39-D39) -> 92997.214
A40: 13 | B40: =IF(OR(A40>$B$21,F39=""),"",F39) -> 92997.214 | C40: =IF(OR(A40>$B$21,B40=""),"",B40*$B$20) -> 480.48561 | D40: =IF(OR(A40>$B$21,B40=""),"",IF(A40<=$B$22,0,MIN(B40,$B$24-C40))) -> 1069.5417 | E40: =IF(C40="","",C40+D40) -> 1550.0273 | F40: =IF(D40="","",B40-D40) -> 91927.673
... A111: 84 | B111: =IF(OR(A111>$B$21,F110=""),"",F110) -> 1542.06 | C111: =IF(OR(A111>$B$21,B111=""),"",B111*$B$20) -> 7.9673102 | D111: =IF(OR(A111>$B$21,B111=""),"",IF(A111<=$B$22,0,MIN(B111,$B$24-C111))) -> 1542.06 | E111: =IF(C111="","",C111+D111) -> 1550.0273 | F111: =IF(D111="","",B111-D111) -> 2.3403572e-09
A112: Capital pendiente al vencimiento | B112: =IF($B$18="","",ROUND($B$18-SUM(D28:D111),2)) -> 0
A113: ¿Cierra el cuadro de amortización? | B113: =IF(B112="","",IF(ABS(B112)<='0. Supuestos'!$B$65,"Sí","No: revisa el plazo")) -> Sí
A115: Resumen por Año: ¿Genera el Negocio la Cuota?
A116: Año | B116: Intereses | C116: Devolución de principal | D116: Servicio de la deuda (cuota) | E116: Caja que deja el negocio antes de la deuda | F116: Lo que sobra (o falta) tras pagar al banco | G116: DSCR | H116: Notas
A117: 1 | B117: =SUM(C28:C39) -> 6075.6785 | C117: =SUM(D28:D39) -> 6302.7856 | D117: =B117+C117 -> 12378.464 | E117: ='PyG 3 Años'!B23+'PyG 3 Años'!B20+'PyG 3 Años'!B21 -> 20299.085 | F117: =E117-D117 -> 7920.6204 | G117: =IFERROR(IF(D117=0,"",E117/D117),"") -> 1.639871 | H117: La caja que deja el negocio es el resultado antes de impuestos más la amortización (que no se paga) y más los intereses (que son parte de la cuota). Del año 4 en adelante se repite el año 3: este libro no proyecta más lejos.
A118: 2 | B118: =SUM(C40:C51) -> 5394.7588 | C118: =SUM(D40:D51) -> 13205.569 | D118: =B118+C118 -> 18600.328 | E118: ='PyG 3 Años'!C23+'PyG 3 Años'!C20+'PyG 3 Años'!C21 -> 45708.248 | F118: =E118-D118 -> 27107.92 | G118: =IFERROR(IF(D118=0,"",E118/D118),"") -> 2.4573893
A119: 3 | B119: =SUM(C52:C63) -> 4552.342 | C119: =SUM(D52:D63) -> 14047.986 | D119: =B119+C119 -> 18600.328 | E119: ='PyG 3 Años'!D23+'PyG 3 Años'!D20+'PyG 3 Años'!D21 -> 45708.248 | F119: =E119-D119 -> 27107.92 | G119: =IFERROR(IF(D119=0,"",E119/D119),"") -> 2.4573893
A120: 4 | B120: =SUM(C64:C75) -> 3656.1854 | C120: =SUM(D64:D75) -> 14944.143 | D120: =B120+C120 -> 18600.328 | E120: ='PyG 3 Años'!D23+'PyG 3 Años'!D20+'PyG 3 Años'!D21 -> 45708.248 | F120: =E120-D120 -> 27107.92 | G120: =IFERROR(IF(D120=0,"",E120/D120),"") -> 2.4573893
A121: 5 | B121: =SUM(C76:C87) -> 2702.8607 | C121: =SUM(D76:D87) -> 15897.467 | D121: =B121+C121 -> 18600.328 | E121: ='PyG 3 Años'!D23+'PyG 3 Años'!D20+'PyG 3 Años'!D21 -> 45708.248 | F121: =E121-D121 -> 27107.92 | G121: =IFERROR(IF(D121=0,"",E121/D121),"") -> 2.4573893
A122: 6 | B122: =SUM(C88:C99) -> 1688.721 | C122: =SUM(D88:D99) -> 16911.607 | D122: =B122+C122 -> 18600.328 | E122: ='PyG 3 Años'!D23+'PyG 3 Años'!D20+'PyG 3 Años'!D21 -> 45708.248 | F122: =E122-D122 -> 27107.92 | G122: =IFERROR(IF(D122=0,"",E122/D122),"") -> 2.4573893
A123: 7 | B123: =SUM(C100:C111) -> 609.88681 | C123: =SUM(D100:D111) -> 17990.441 | D123: =B123+C123 -> 18600.328 | E123: ='PyG 3 Años'!D23+'PyG 3 Años'!D20+'PyG 3 Años'!D21 -> 45708.248 | F123: =E123-D123 -> 27107.92 | G123: =IFERROR(IF(D123=0,"",E123/D123),"") -> 2.4573893
A124: Lo que sobra en el peor año del préstamo | B124: =MIN(F117:F123) -> 7920.6204
A125: ¿Aguanta el banco? | B125: =IF(NOT(ISNUMBER(B124)),"",IF(B124>=0,"Aguanta: en el peor año te sobra dinero después de pagar la cuota","No aguanta: hay un año en que el negocio no genera la cuota")) -> Aguanta: en el peor año te sobra dinero después de pagar la cuota
A126: Año del peor margen | B126: =IFERROR(MATCH(B124,F117:F123,0),"") -> 1
A127: DSCR más bajo (información para el banco) | B127: =IF(COUNT(G117:G123)=0,"",MIN(G117:G123)) -> 1.639871 | H127: Caja antes de la deuda entre la cuota. Te lo van a pedir, pero la lectura que decide es la de los euros: un ratio alto sobre una cuota pequeña puede seguir dejando pocos euros.
A129: El año de la carencia sale holgado porque casi no devuelves principal. Mira el año 2 y el año 3, con la cuota completa.

Sheet Canales y Punto Muerto
A1: Canales y Punto Muerto: Sala, para Llevar y Ferias
A2: AI Chef Pro · aichef.pro — Cómo Montar una Churrería-Chocolatería
A3: Lo que deja cada canal en el año de crucero y si alguno paga los fijos él solo. Las raciones de la carta de invierno son las de los meses fuera de julio y agosto; el verano entra con su contribución (libro 5).
A5: Canal | B5: Parte de las raciones | C5: Raciones de la carta de invierno (año de crucero) | D5: Ticket sin IVA por ración | E5: Materia por ración (aceite absorbido incluido) | F5: Contribución por ración | G5: Contribución del año | H5: Peso sobre la contribución
A6: Sala (barra, mesas y terraza) | B6: ='0. Supuestos'!$B$15 -> 0.7 | C6: ='PyG 3 Años'!$C$8*B6 -> 68601.75 | D6: ='0. Supuestos'!$B$13 -> 2.1480519 | E6: ='0. Supuestos'!$B$11 -> 0.27314864 | F6: =D6-E6 -> 1.8749033 | G6: =C6*F6 -> 128621.65 | H6: =IFERROR(G6/$G$12,"") -> 0.64823432
A7: Para llevar (despacho a calle) | B7: =1-B6 -> 0.3 | C7: ='PyG 3 Años'!$C$8*B7 -> 29400.75 | D7: ='0. Supuestos'!$B$14 -> 2.1924242 | E7: ='0. Supuestos'!$B$12 -> 0.30546293 | F7: =D7-E7 -> 1.8869613 | G7: =C7*F7 -> 55478.078 | H7: =IFERROR(G7/$G$12,"") -> 0.27960141
A8: Carta de invierno: los dos canales juntos (la mezcla) | B8: =B6+B7 -> 1 | C8: =C6+C7 -> 98002.5 | D8: =B6*D6+B7*D7 -> 2.1613636 | E8: =B6*E6+B7*E7 -> 0.28284293 | F8: =D8-E8 -> 1.8785207 | G8: =G6+G7 -> 184099.73 | H8: =IFERROR(G8/$G$12,"") -> 0.92783572
A9: Julio y agosto: la salida que eliges en el libro 5 | G9: ='0. Supuestos'!$B$33 -> 17368.709 | H9: =IFERROR(G9/$G$12,"") -> 0.087535756
A10: Ferias (resultado del año, libro 5) | G10: ='0. Supuestos'!$B$32 -> 0 | H10: =IFERROR(G10/$G$12,"") -> 0
A11: Renovación del aceite (todas las raciones del año, en negativo) | G11: =-'0. Supuestos'!$B$19*'0. Supuestos'!$B$17 -> -3049.9854 | H11: =IFERROR(G11/$G$12,"") -> -0.015371481
A12: CONTRIBUCIÓN DEL AÑO DE CRUCERO | G12: =SUM(G8:G11) -> 198418.45
A14: ¿Qué Canal Paga los Fijos?
A15: Fijos del año de crucero (los del P&L) | B15: ='PyG 3 Años'!$C$22 -> 166279.69
A16: Si sólo tuvieras... | B16: Contribución del año | C16: Menos los fijos del año | D16: Lectura en euros | E16: Raciones al día de equilibrio si todas fueran de este canal
A17: La sala | B17: =G6 -> 128621.65 | C17: =B17-$B$15 -> -37658.047 | D17: =IF(NOT(ISNUMBER(C17)),"",IF(C17>=0,"Paga los fijos","No llega a los fijos")) -> No llega a los fijos | E17: =IFERROR(IF(F6-'0. Supuestos'!$B$17<=0,"",$B$15/(F6-'0. Supuestos'!$B$17)/'Punto de Equilibrio'!$B$10),"") -> 250.14179
A18: El para llevar | B18: =G7 -> 55478.078 | C18: =B18-$B$15 -> -110801.62 | D18: =IF(NOT(ISNUMBER(C18)),"",IF(C18>=0,"Paga los fijos","No llega a los fijos")) -> No llega a los fijos | E18: =IFERROR(IF(F7-'0. Supuestos'!$B$17<=0,"",$B$15/(F7-'0. Supuestos'!$B$17)/'Punto de Equilibrio'!$B$10),"") -> 248.51891
A19: Sala y para llevar (la carta de invierno entera) | B19: =G8 -> 184099.73 | C19: =B19-$B$15 -> 17820.031 | D19: =IF(NOT(ISNUMBER(C19)),"",IF(C19>=0,"Paga los fijos","No llega a los fijos")) -> Paga los fijos | E19: =IFERROR(IF(F8-'0. Supuestos'!$B$17<=0,"",$B$15/(F8-'0. Supuestos'!$B$17)/'Punto de Equilibrio'!$B$10),"") -> 249.6527
A20: Todo el negocio (con el verano, las ferias y el aceite) | B20: =G12 -> 198418.45 | C20: =B20-$B$15 -> 32138.755 | D20: =IF(NOT(ISNUMBER(C20)),"",IF(C20>=0,"Paga los fijos","No llega a los fijos")) -> Paga los fijos | E20: ='Punto de Equilibrio'!$B$12 -> 250.0109
A21: El canal que más deja | B21: =IF(G6>=G7,A6,A7) -> Sala (barra, mesas y terraza)
A23: Las ferias tienen su propio punto muerto, evento a evento, en el libro 5 (hoja «Punto Muerto por Evento»): aquí entra sólo su resultado del año. Las raciones al día de equilibrio de un canal suponen que todas tus raciones fueran de ese canal, con la renovación del aceite descontada.
