Workbook

Sheet Pescado
A1: CALCULADORA DEL PESCADO — COSTE POR KILO ÚTIL, POR LONCHA, POR CORTE Y POR ROLL
A2: Escribe solo en las celdas VERDES: todo lo demás se calcula. Importes sin IVA. Todos los valores por defecto son una estimación del kit, editable: cámbialos por los de tu proveedor y, sobre todo, por lo que midas en tus propios pescados.
A3: AVISO FIJO. Anisakis (RD 1021/2022, art. 8): el pescado que se sirve crudo o casi crudo se congela a −20 °C o menos durante al menos 24 horas, o a −35 °C o menos durante al menos 15 horas, en la totalidad del producto; la acuicultura queda exenta solo con documento escrito del proveedor, y hay que informar al cliente en la carta o en un cartel (art. 8.2). Los minutos de limpieza (25) no tienen fuente: mídelos.
A5: A. TRES PESCADOS Y UNO LIBRE | B5: Salmón entero de acuicultura | C5: Lomo de salmón comprado limpio | D5: Atún aleta amarilla en saku ultracongelado | E5: Otro pescado (escribe el tuyo) | F5: Notas
A6: Precio de compra (€/kg, sin IVA) | B6: 9.5 | C6: 21.8 | D6: 26 | E6: 18 | F6: Salmón noruego entero de acuicultura: unos 11,95 €/kg en minorista y 6-7,5 € en origen; lomo o filete congelado, de 20,7 a 21,8 €/kg (Makro); el atún aleta amarilla en saku ultracongelado no tiene precio publicado en España. El kit pone 9,50 · 21,80 · 26,00 €/kg. Estimación del kit, editable.
A7: Rendimiento: lomo limpio sobre el peso comprado | B7: 0.55 | C7: 0.92 | D7: 0.9 | E7: 0.8 | F7: Parte del pescado entero que queda como lomo limpio para sushi: de 50 a 60 % en el salmón entero. Mídelo con 3 salmones (hoja «Instrucciones»). En el atún en saku es la parte que se aprovecha al cortar. Estimación del kit, editable.
A8: Recorte que reaprovechas (% del peso comprado) | B8: 0.15 | C8: 0.03 | D8: 0.05 | E8: 0.05 | F8: Recorte que reaprovechas (tartar, maki, poke), en % del peso comprado. Lo que tiras no cuenta aquí. Estimación del kit, editable.
A10: B. DATOS COMUNES | B10: Valor | C10: Notas
A11: Merma de vitrina (% del pescado cortado que no se vende) | B11: 0.05 | C11: Lo que se queda en la vitrina o en el pase y se tira al cierre. Estimación del kit, editable.
A12: Gramos de neta por loncha de nigiri (g) | B12: 15 | C12: Criterio del plan: pesa 10 lonchas y usa la media. Estimación del kit, editable.
A13: Gramos por corte de sashimi (g) | B13: 15 | C13: Pesa 10 cortes y usa la media. Estimación del kit, editable.
A14: Gramos de pescado por roll (g) | B14: 40 | C14: Un uramaki o un maki de 8 piezas con pescado dentro. Estimación del kit, editable.
A15: Minutos de limpieza de un pescado entero (min) | B15: 25 | C15: Sin fuente: mídelo. Cronometra la limpieza de 3 piezas y usa la media. Estimación del kit, editable.
A16: Coste por hora del itamae (€/h) | B16: 22 | C16: 2.200 € brutos × 14 pagas + 33 % de cargas ÷ 1.840 h ≈ 22 €/h. Estimación del kit, editable.
A17: Peso de una pieza entera (kg) | B17: 5 | C17: Salmón entero de acuicultura de unos 5 kg. Estimación del kit, editable.
A18: ¿Congelación anti-anisakis o documento? (desplegable) | B18: Congelo yo: −20 °C ≥ 24 h o −35 °C ≥ 15 h
A19: Gramos por kilo (constante) | B19: 1000 | C19: Constante: un kilo son 1.000 gramos. No se edita.
A20: Minutos por hora (constante) | B20: 60 | C20: Constante: una hora son 60 minutos. No se edita.
A22: C. COSTE POR KG ÚTIL Y POR PIEZA | B22: =B5 -> Salmón entero de acuicultura | C22: =C5 -> Lomo de salmón comprado limpio | D22: =D5 -> Atún aleta amarilla en saku ultracongelado | E22: =E5 -> Otro pescado (escribe el tuyo) | F22: Notas
A23: Parte aprovechada (rendimiento + recorte) | B23: =B$7+B$8 -> 0.7 | C23: =C$7+C$8 -> 0.95 | D23: =D$7+D$8 -> 0.95 | E23: =E$7+E$8 -> 0.85 | F23: Lomo + recorte que reaprovechas.
A24: COSTE POR KG ÚTIL (€) | B24: =B$6/B$23/(1-$B$11) -> 14.285714 | C24: =C$6/C$23/(1-$B$11) -> 24.155125 | D24: =D$6/D$23/(1-$B$11) -> 28.808864 | E24: =E$6/E$23/(1-$B$11) -> 22.291022 | F24: Precio ÷ (rendimiento + recorte) ÷ (1 − merma de vitrina).
A25: Coste de una loncha de nigiri (€) | B25: =B$24*$B$12/$B$19 -> 0.21428571 | C25: =C$24*$B$12/$B$19 -> 0.36232687 | D25: =D$24*$B$12/$B$19 -> 0.43213296 | E25: =E$24*$B$12/$B$19 -> 0.33436533 | F25: Coste por kg útil × gramos ÷ 1.000.
A26: Coste de un corte de sashimi (€) | B26: =B$24*$B$13/$B$19 -> 0.21428571 | C26: =C$24*$B$13/$B$19 -> 0.36232687 | D26: =D$24*$B$13/$B$19 -> 0.43213296 | E26: =E$24*$B$13/$B$19 -> 0.33436533 | F26: Coste por kg útil × gramos ÷ 1.000.
A27: Coste del pescado de un roll (€) | B27: =B$24*$B$14/$B$19 -> 0.57142857 | C27: =C$24*$B$14/$B$19 -> 0.96620499 | D27: =D$24*$B$14/$B$19 -> 1.1523546 | E27: =E$24*$B$14/$B$19 -> 0.89164087 | F27: Coste por kg útil × gramos ÷ 1.000.
A29: D. ¿ENTERO O LOMO LIMPIO? | B29: Valor | C29: Notas
A30: Coste de limpiar una pieza entera (€) | B30: =$B$15/$B$20*$B$16 -> 9.1666667 | C30: Minutos de limpieza ÷ 60 × coste por hora del itamae.
A31: Kilos útiles de una pieza entera (kg) | B31: =$B$17*$B$7 -> 2.75 | C31: Peso de la pieza × rendimiento del salmón entero.
A32: MANO DE OBRA DE LIMPIEZA POR KG ÚTIL (€) | B32: =$B$30/$B$31 -> 3.3333333 | C32: Coste de limpiar una pieza ÷ kilos útiles.
A33: Coste por kg útil del entero con la limpieza incluida (€) | B33: =$B$24+$B$32 -> 17.619048 | C33: Coste por kg útil + mano de obra por kg útil.
A34: EL ENTERO TE COMPENSA MIENTRAS LIMPIARLO CUESTE MENOS DE (€ por kg útil) | B34: =$C$24-$B$24 -> 9.8694104 | C34: Coste por kg útil del lomo comprado − coste por kg útil del entero.
A35: Veredicto con tu mano de obra | B35: =IF($B$32<$B$34,"El entero compensa","Compra el lomo limpio") -> El entero compensa | C35: El entero compensa si limpiarlo cuesta menos que esa diferencia.
A36: Recordatorio de tu caso de congelación | B36: =INDEX($B$39:$B$41,MATCH($B$18,$A$39:$A$41,0)) -> RD 1021/2022, art. 8: −20 °C o menos durante al menos 24 h, o −35 °C o menos durante al menos 15 h, en la totalidad del producto. Registra temperatura y horas de cada lote.
A38: LISTA DEL DESPLEGABLE DE CONGELACIÓN | B38: Recordatorio
A39: Congelo yo: −20 °C ≥ 24 h o −35 °C ≥ 15 h | B39: RD 1021/2022, art. 8: −20 °C o menos durante al menos 24 h, o −35 °C o menos durante al menos 15 h, en la totalidad del producto. Registra temperatura y horas de cada lote.
A40: Llega congelado con documento del proveedor | B40: Guarda el documento del proveedor de cada lote: tiene que acreditar que el pescado se ha congelado a esas temperaturas y horas.
A41: Acuicultura con documento escrito | B41: La acuicultura queda exenta solo con el documento escrito del proveedor. Archívalo con el albarán y pídelo de nuevo si cambia de origen.

Sheet Arroz
A1: CALCULADORA DEL ARROZ — CUÁNTO SHARI SALE DE UN KILO, CUÁNTO CUESTA Y CUÁNTO COMPRAR AL DÍA
A2: Escribe solo en las celdas VERDES: todo lo demás se calcula. Importes sin IVA. Todos los valores por defecto son una estimación del kit, editable: pesa tus bolas de shari y cambia los gramos por los tuyos.
A3: AVISO FIJO. El pH de cada tanda se registra en el Kit de Tareas Sushi Bar (hoja 03). El shari a temperatura ambiente, sólo si tu APPCC lo justifica con el pH de cada tanda y un tiempo máximo y lo demuestras a sanidad (RD 1086/2020, art. 30.5); si no, refrigerado.
A5: A. EL ARROZ Y EL SHARI | B5: Valor | C5: Notas
A6: Arroz crudo para sushi (€/kg, sin IVA) | B6: 1.85 | C6: Entre 1,81 €/kg (METRO Chef, 5 kg) y 1,85 €/kg (DACSA, 5 kg); otra marca, a 2,50 €/kg en saco de 20 kg. Estimación del kit, editable.
A7: Factor de arroz crudo a cocido (×) | B7: 2.2 | C7: Un kilo de arroz crudo da 2,2 kg de arroz cocido. Estimación del kit, editable.
A8: Sushi-zu (aliño de vinagre) por kg de arroz cocido (ml) | B8: 100 | C8: Vinagre de arroz, azúcar y sal: unos 100 ml por kilo de arroz cocido. Estimación del kit, editable.
A9: Sushi-zu (€/l, sin IVA) | B9: 4.4 | C9: Vinagre, azúcar y sal. Estimación del kit, editable.
A10: Gramos de shari por nigiri (g) | B10: 20 | C10: Shari es el arroz ya aliñado. Pesa 10 bolas y usa la media. Estimación del kit, editable.
A11: Gramos de shari por hosomaki (g) | B11: 70 | C11: Un rollo fino de 6 piezas. Estimación del kit, editable.
A12: Gramos de shari por uramaki (g) | B12: 120 | C12: Un rollo de 8 piezas. Estimación del kit, editable.
A13: Gramos de shari por temaki (g) | B13: 60 | C13: Un cono. Estimación del kit, editable.
A14: Gramos de shari por poke (g) | B14: 150 | C14: Un bol. Estimación del kit, editable.
A15: Nori (€ por hoja, sin IVA) | B15: 0.26 | C15: Nori Gold, 100 hojas por 25,95 € = 0,26 €/hoja. Estimación del kit, editable.
A16: Hojas de nori por nigiri | B16: 0.05 | C16: La tira que ata el nigiri. Estimación del kit, editable.
A17: Hojas de nori por hosomaki | B17: 0.5 | C17: Media hoja por rollo. Estimación del kit, editable.
... A25: Mililitros por litro (constante) | B25: 1000 | C25: Constante: un litro son 1.000 ml. No se edita.
A27: RESULTADOS | B27: Valor | C27: Notas
A28: KG DE SHARI POR KG DE ARROZ CRUDO (kg) | B28: =$B$7*(1+$B$8/$B$25) -> 2.42 | C28: Factor crudo a cocido × (1 + sushi-zu en litros por kg cocido).
A29: COSTE POR KG DE SHARI (€) | B29: =($B$6+$B$7*$B$8/$B$25*$B$9)/$B$28 -> 1.1644628 | C29: (Arroz + sushi-zu de un kilo de arroz crudo) ÷ kg de shari.
A30: Coste por kg de shari con la merma del cierre (€) | B30: =$B$29/(1-$B$21) -> 1.2257503 | C30: Coste por kg de shari ÷ (1 − shari que se tira). Alimenta el escandallo.
A31: NIGIRIS POR KILO DE ARROZ CRUDO (piezas) | B31: =$B$24*$B$28/$B$10 -> 121 | C31: 1.000 × kg de shari por kg crudo ÷ gramos por nigiri.
A32: Coste del shari de un nigiri (€) | B32: =$B$10*$B$30/$B$24 -> 0.024515007 | C32: Gramos × coste por kg de shari con merma ÷ 1.000.
A33: Coste del shari de un hosomaki (€) | B33: =$B$11*$B$30/$B$24 -> 0.085802523 | C33: Gramos × coste por kg de shari con merma ÷ 1.000.
A34: Coste del shari de un uramaki (€) | B34: =$B$12*$B$30/$B$24 -> 0.14709004 | C34: Gramos × coste por kg de shari con merma ÷ 1.000.
A35: Coste del shari de un temaki (€) | B35: =$B$13*$B$30/$B$24 -> 0.07354502 | C35: Gramos × coste por kg de shari con merma ÷ 1.000.
A36: Coste del shari de un poke (€) | B36: =$B$14*$B$30/$B$24 -> 0.18386255 | C36: Gramos × coste por kg de shari con merma ÷ 1.000.
A37: Coste del nori de un nigiri (€) | B37: =$B$16*$B$15 -> 0.013 | C37: Hojas × precio de la hoja.
A38: Coste del nori de un hosomaki (€) | B38: =$B$17*$B$15 -> 0.13 | C38: Hojas × precio de la hoja.
A39: Coste del nori de un uramaki (€) | B39: =$B$18*$B$15 -> 0.13 | C39: Hojas × precio de la hoja.
A40: Coste del nori de un temaki (€) | B40: =$B$19*$B$15 -> 0.13 | C40: Hojas × precio de la hoja.
A41: Coste del nori de un poke (€) | B41: =$B$20*$B$15 -> 0.026 | C41: Hojas × precio de la hoja.
A42: Shari que vendes al día (kg) | B42: =$B$22*$B$23/$B$24 -> 11.85 | C42: Comensales × gramos por comensal ÷ 1.000.
A43: KG DE ARROZ CRUDO AL DÍA | B43: =$B$42/$B$28 -> 4.8966942 | C43: Shari que vendes ÷ kg de shari por kg de arroz crudo.
A44: Kg de arroz crudo al día contando lo que se tira | B44: =$B$43/(1-$B$21) -> 5.154415 | C44: Arroz crudo al día ÷ (1 − shari que se tira).

Sheet Escandallo
A1: ESCANDALLO DEL SUSHI BAR — 14 PRODUCTOS, POR PIEZA Y POR CANAL
A2: Escribe solo en las celdas VERDES (nombres, pescado, gramos, nori, precios de carta y unidades). Importes sin IVA salvo el precio de carta. Todos los valores por defecto son una estimación del kit, editable: pon los tuyos. El coste del pescado viene de la hoja «Pescado», el del shari y el nori de la hoja «Arroz».
A4: DATOS GENERALES | B4: Valor | D4: Notas
A5: IVA de la comida (%) | B5: 0.1 | D5: Comida preparada, en sala, para llevar y a domicilio: 10 % (Ley 37/1992, art. 91).
A6: Food cost objetivo (% sobre el precio sin IVA) | B6: 0.3 | D6: Objetivo de la carta del sushi bar. Estimación del kit, editable.
A7: Margen de vigilancia sobre el objetivo (puntos) | B7: 0.05 | D7: Hasta este margen por encima del objetivo, el semáforo dice «Vigila el coste».
A8: Caja para llevar por pedido (€, sin IVA) | B8: 0.4 | D8: Bandeja, cierre, bolsa, salsas y palillos de un pedido para llevar. Estimación del kit, editable.
A9: Caja de plataforma por pedido (€, sin IVA) | B9: 0.9 | D9: Envase de reparto más sellado. Estimación del kit, editable.
A10: Recargo de precio en la plataforma (%) | B10: 0.15 | D10: Lo que subes el precio en la plataforma para compensar. Estimación del kit, editable.
A11: Comisión de la plataforma de reparto (%) | B11: 0.3 | D11: Sobre el precio sin IVA del pedido. Revisa tu contrato. Estimación del kit, editable.
A12: Coste por kg de shari con merma (€, de la hoja Arroz) | B12: ='Arroz'!$B$30 -> 1.2257503
A13: Nori (€ por hoja, de la hoja Arroz) | B13: ='Arroz'!$B$15 -> 0.26
A15: PRODUCTO | B15: Pescado (0 a 4) | C15: Gramos de neta | D15: Gramos de shari | E15: Hojas de nori | F15: Otros ingredientes (€) | G15: PVP con IVA de sala (€) | H15: Unidades a la semana | I15: COSTE (€) | J15: PVP sin IVA (€) | K15: FOOD COST (%) | L15: Semáforo | M15: PVP con IVA sugerido (€) | N15: Margen en sala (€) | O15: Margen para llevar (€) | P15: Margen en plataforma (€) | Q15: Puesto por margen
A16: Nigiri de salmón (2 piezas) | B16: 1 | C16: 30 | D16: 40 | E16: 0.1 | F16: 0.03 | G16: 5.2 | H16: 110 | I16: =C16/'Pescado'!$B$19*CHOOSE(B16+1,0,'Pescado'!$B$24,'Pescado'!$C$24,'Pescado'!$D$24,'Pescado'!$E$24)+D16/'Pescado'!$B$19*$B$12+E16*$B$13+F16 -> 0.53360144 | J16: =G16/(1+$B$5) -> 4.7272727 | K16: =I16/J16 -> 0.11287723 | L16: =IF(K16<=$B$6,"En objetivo",IF(K16<=$B$6+$B$7,"Vigila el coste","Por encima del objetivo")) -> En objetivo | M16: =I16/$B$6*(1+$B$5) -> 1.9565386 | N16: =J16-I16 -> 4.1936713 | O16: =N16-$B$8 -> 3.7936713 | P16: =J16*(1+$B$10)*(1-$B$11)-I16-$B$9 -> 2.3718531 | Q16: =1+COUNTIF($N$16:$N$29,">"&N16) -> 12
A17: Nigiri de atún (2 piezas) | B17: 3 | C17: 30 | D17: 40 | E17: 0.1 | F17: 0.03 | G17: 6 | H17: 70 | I17: =C17/'Pescado'!$B$19*CHOOSE(B17+1,0,'Pescado'!$B$24,'Pescado'!$C$24,'Pescado'!$D$24,'Pescado'!$E$24)+D17/'Pescado'!$B$19*$B$12+E17*$B$13+F17 -> 0.96929594 | J17: =G17/(1+$B$5) -> 5.4545455 | K17: =I17/J17 -> 0.17770426 | L17: =IF(K17<=$B$6,"En objetivo",IF(K17<=$B$6+$B$7,"Vigila el coste","Por encima del objetivo")) -> En objetivo | M17: =I17/$B$6*(1+$B$5) -> 3.5540851 | N17: =J17-I17 -> 4.4852495 | O17: =N17-$B$8 -> 4.0852495 | P17: =J17*(1+$B$10)*(1-$B$11)-I17-$B$9 -> 2.5216131 | Q17: =1+COUNTIF($N$16:$N$29,">"&N17) -> 10
A18: Sashimi de salmón (5 cortes) | B18: 1 | C18: 75 | D18: 0 | E18: 0 | F18: 0.04 | G18: 7.5 | H18: 50 | I18: =C18/'Pescado'!$B$19*CHOOSE(B18+1,0,'Pescado'!$B$24,'Pescado'!$C$24,'Pescado'!$D$24,'Pescado'!$E$24)+D18/'Pescado'!$B$19*$B$12+E18*$B$13+F18 -> 1.1114286 | J18: =G18/(1+$B$5) -> 6.8181818 | K18: =I18/J18 -> 0.16300952 | L18: =IF(K18<=$B$6,"En objetivo",IF(K18<=$B$6+$B$7,"Vigila el coste","Por encima del objetivo")) -> En objetivo | M18: =I18/$B$6*(1+$B$5) -> 4.0752381 | N18: =J18-I18 -> 5.7067532 | O18: =N18-$B$8 -> 5.3067532 | P18: =J18*(1+$B$10)*(1-$B$11)-I18-$B$9 -> 3.4772078 | Q18: =1+COUNTIF($N$16:$N$29,">"&N18) -> 7
A19: Hosomaki de salmón (6 piezas) | B19: 1 | C19: 25 | D19: 70 | E19: 0.5 | F19: 0.05 | G19: 5.5 | H19: 20 | I19: =C19/'Pescado'!$B$19*CHOOSE(B19+1,0,'Pescado'!$B$24,'Pescado'!$C$24,'Pescado'!$D$24,'Pescado'!$E$24)+D19/'Pescado'!$B$19*$B$12+E19*$B$13+F19 -> 0.62294538 | J19: =G19/(1+$B$5) -> 5 | K19: =I19/J19 -> 0.12458908 | L19: =IF(K19<=$B$6,"En objetivo",IF(K19<=$B$6+$B$7,"Vigila el coste","Por encima del objetivo")) -> En objetivo | M19: =I19/$B$6*(1+$B$5) -> 2.2841331 | N19: =J19-I19 -> 4.3770546 | O19: =N19-$B$8 -> 3.9770546 | P19: =J19*(1+$B$10)*(1-$B$11)-I19-$B$9 -> 2.5020546 | Q19: =1+COUNTIF($N$16:$N$29,">"&N19) -> 11
A20: Uramaki California (8 piezas) | B20: 0 | C20: 0 | D20: 120 | E20: 0.5 | F20: 0.52 | G20: 9.6 | H20: 35 | I20: =C20/'Pescado'!$B$19*CHOOSE(B20+1,0,'Pescado'!$B$24,'Pescado'!$C$24,'Pescado'!$D$24,'Pescado'!$E$24)+D20/'Pescado'!$B$19*$B$12+E20*$B$13+F20 -> 0.79709004 | J20: =G20/(1+$B$5) -> 8.7272727 | K20: =I20/J20 -> 0.091333234 | L20: =IF(K20<=$B$6,"En objetivo",IF(K20<=$B$6+$B$7,"Vigila el coste","Por encima del objetivo")) -> En objetivo | M20: =I20/$B$6*(1+$B$5) -> 2.9226635 | N20: =J20-I20 -> 7.9301827 | O20: =N20-$B$8 -> 7.5301827 | P20: =J20*(1+$B$10)*(1-$B$11)-I20-$B$9 -> 5.3283645 | Q20: =1+COUNTIF($N$16:$N$29,">"&N20) -> 6
A21: Uramaki de salmón y aguacate (8 piezas) | B21: 1 | C21: 40 | D21: 120 | E21: 0.5 | F21: 0.45 | G21: 11.5 | H21: 35 | I21: =C21/'Pescado'!$B$19*CHOOSE(B21+1,0,'Pescado'!$B$24,'Pescado'!$C$24,'Pescado'!$D$24,'Pescado'!$E$24)+D21/'Pescado'!$B$19*$B$12+E21*$B$13+F21 -> 1.2985186 | J21: =G21/(1+$B$5) -> 10.454545 | K21: =I21/J21 -> 0.12420613 | L21: =IF(K21<=$B$6,"En objetivo",IF(K21<=$B$6+$B$7,"Vigila el coste","Por encima del objetivo")) -> En objetivo | M21: =I21/$B$6*(1+$B$5) -> 4.7612349 | N21: =J21-I21 -> 9.1560268 | O21: =N21-$B$8 -> 8.7560268 | P21: =J21*(1+$B$10)*(1-$B$11)-I21-$B$9 -> 6.2173905 | Q21: =1+COUNTIF($N$16:$N$29,">"&N21) -> 4
A22: Uramaki de langostino en tempura (8 piezas) | B22: 0 | C22: 0 | D22: 120 | E22: 0.5 | F22: 1.37 | G22: 11.5 | H22: 40 | I22: =C22/'Pescado'!$B$19*CHOOSE(B22+1,0,'Pescado'!$B$24,'Pescado'!$C$24,'Pescado'!$D$24,'Pescado'!$E$24)+D22/'Pescado'!$B$19*$B$12+E22*$B$13+F22 -> 1.64709 | J22: =G22/(1+$B$5) -> 10.454545 | K22: =I22/J22 -> 0.15754774 | L22: =IF(K22<=$B$6,"En objetivo",IF(K22<=$B$6+$B$7,"Vigila el coste","Por encima del objetivo")) -> En objetivo | M22: =I22/$B$6*(1+$B$5) -> 6.0393301 | N22: =J22-I22 -> 8.8074554 | O22: =N22-$B$8 -> 8.4074554 | P22: =J22*(1+$B$10)*(1-$B$11)-I22-$B$9 -> 5.8688191 | Q22: =1+COUNTIF($N$16:$N$29,">"&N22) -> 5
A23: Temaki de salmón | B23: 1 | C23: 40 | D23: 60 | E23: 0.5 | F23: 0.4 | G23: 6.9 | H23: 30 | I23: =C23/'Pescado'!$B$19*CHOOSE(B23+1,0,'Pescado'!$B$24,'Pescado'!$C$24,'Pescado'!$D$24,'Pescado'!$E$24)+D23/'Pescado'!$B$19*$B$12+E23*$B$13+F23 -> 1.1749736 | J23: =G23/(1+$B$5) -> 6.2727273 | K23: =I23/J23 -> 0.18731463 | L23: =IF(K23<=$B$6,"En objetivo",IF(K23<=$B$6+$B$7,"Vigila el coste","Por encima del objetivo")) -> En objetivo | M23: =I23/$B$6*(1+$B$5) -> 4.3082365 | N23: =J23-I23 -> 5.0977537 | O23: =N23-$B$8 -> 4.6977537 | P23: =J23*(1+$B$10)*(1-$B$11)-I23-$B$9 -> 2.9745719 | Q23: =1+COUNTIF($N$16:$N$29,">"&N23) -> 9
A24: Poke de salmón | B24: 1 | C24: 100 | D24: 150 | E24: 0.1 | F24: 0.76 | G24: 12.9 | H24: 45 | I24: =C24/'Pescado'!$B$19*CHOOSE(B24+1,0,'Pescado'!$B$24,'Pescado'!$C$24,'Pescado'!$D$24,'Pescado'!$E$24)+D24/'Pescado'!$B$19*$B$12+E24*$B$13+F24 -> 2.398434 | J24: =G24/(1+$B$5) -> 11.727273 | K24: =I24/J24 -> 0.20451763 | L24: =IF(K24<=$B$6,"En objetivo",IF(K24<=$B$6+$B$7,"Vigila el coste","Por encima del objetivo")) -> En objetivo | M24: =I24/$B$6*(1+$B$5) -> 8.7942579 | N24: =J24-I24 -> 9.3288387 | O24: =N24-$B$8 -> 8.9288387 | P24: =J24*(1+$B$10)*(1-$B$11)-I24-$B$9 -> 6.1420206 | Q24: =1+COUNTIF($N$16:$N$29,">"&N24) -> 3
A25: Combinado de 12 piezas | B25: 1 | C25: 100 | D25: 190 | E25: 0.5 | F25: 0.45 | G25: 14.9 | H25: 25 | I25: =C25/'Pescado'!$B$19*CHOOSE(B25+1,0,'Pescado'!$B$24,'Pescado'!$C$24,'Pescado'!$D$24,'Pescado'!$E$24)+D25/'Pescado'!$B$19*$B$12+E25*$B$13+F25 -> 2.241464 | J25: =G25/(1+$B$5) -> 13.545455 | K25: =I25/J25 -> 0.16547721 | L25: =IF(K25<=$B$6,"En objetivo",IF(K25<=$B$6+$B$7,"Vigila el coste","Por encima del objetivo")) -> En objetivo | M25: =I25/$B$6*(1+$B$5) -> 8.2187013 | N25: =J25-I25 -> 11.303991 | O25: =N25-$B$8 -> 10.903991 | P25: =J25*(1+$B$10)*(1-$B$11)-I25-$B$9 -> 7.7626269 | Q25: =1+COUNTIF($N$16:$N$29,">"&N25) -> 2
A26: Combinado de 24 piezas | B26: 1 | C26: 220 | D26: 380 | E26: 1 | F26: 0.33 | G26: 29 | H26: 15 | I26: =C26/'Pescado'!$B$19*CHOOSE(B26+1,0,'Pescado'!$B$24,'Pescado'!$C$24,'Pescado'!$D$24,'Pescado'!$E$24)+D26/'Pescado'!$B$19*$B$12+E26*$B$13+F26 -> 4.1986423 | J26: =G26/(1+$B$5) -> 26.363636 | K26: =I26/J26 -> 0.15925884 | L26: =IF(K26<=$B$6,"En objetivo",IF(K26<=$B$6+$B$7,"Vigila el coste","Por encima del objetivo")) -> En objetivo | M26: =I26/$B$6*(1+$B$5) -> 15.395022 | N26: =J26-I26 -> 22.164994 | O26: =N26-$B$8 -> 21.764994 | P26: =J26*(1+$B$10)*(1-$B$11)-I26-$B$9 -> 16.124085 | Q26: =1+COUNTIF($N$16:$N$29,">"&N26) -> 1
A27: Gyozas (6 piezas) | B27: 0 | C27: 0 | D27: 0 | E27: 0 | F27: 1.1 | G27: 7 | H27: 60 | I27: =C27/'Pescado'!$B$19*CHOOSE(B27+1,0,'Pescado'!$B$24,'Pescado'!$C$24,'Pescado'!$D$24,'Pescado'!$E$24)+D27/'Pescado'!$B$19*$B$12+E27*$B$13+F27 -> 1.1 | J27: =G27/(1+$B$5) -> 6.3636364 | K27: =I27/J27 -> 0.17285714 | L27: =IF(K27<=$B$6,"En objetivo",IF(K27<=$B$6+$B$7,"Vigila el coste","Por encima del objetivo")) -> En objetivo | M27: =I27/$B$6*(1+$B$5) -> 4.0333333 | N27: =J27-I27 -> 5.2636364 | O27: =N27-$B$8 -> 4.8636364 | P27: =J27*(1+$B$10)*(1-$B$11)-I27-$B$9 -> 3.1227273 | Q27: =1+COUNTIF($N$16:$N$29,">"&N27) -> 8
... A29: Mochi (2 piezas) | B29: 0 | C29: 0 | D29: 0 | E29: 0 | F29: 1.25 | G29: 5.5 | H29: 45 | I29: =C29/'Pescado'!$B$19*CHOOSE(B29+1,0,'Pescado'!$B$24,'Pescado'!$C$24,'Pescado'!$D$24,'Pescado'!$E$24)+D29/'Pescado'!$B$19*$B$12+E29*$B$13+F29 -> 1.25 | J29: =G29/(1+$B$5) -> 5 | K29: =I29/J29 -> 0.25 | L29: =IF(K29<=$B$6,"En objetivo",IF(K29<=$B$6+$B$7,"Vigila el coste","Por encima del objetivo")) -> En objetivo | M29: =I29/$B$6*(1+$B$5) -> 4.5833333 | N29: =J29-I29 -> 3.75 | O29: =N29-$B$8 -> 3.35 | P29: =J29*(1+$B$10)*(1-$B$11)-I29-$B$9 -> 1.875 | Q29: =1+COUNTIF($N$16:$N$29,">"&N29) -> 13
A31: FOOD COST PONDERADO DE LA SEMANA (suma de costes × unidades ÷ suma de PVP sin IVA × unidades) | B31: Valor
A32: Ventas de la semana sin IVA (€) | B32: =SUMPRODUCT($J$16:$J$29,$H$16:$H$29) -> 4734.5455
A33: Coste de la comida vendida en la semana (€) | B33: =SUMPRODUCT($I$16:$I$29,$H$16:$H$29) -> 760.25209
A34: FOOD COST PONDERADO (%) | B34: =IF($B$32=0,0,$B$33/$B$32) -> 0.16057552
A35: Semáforo del food cost ponderado | B35: =IF($B$34<=$B$6,"En objetivo",IF($B$34<=$B$6+$B$7,"Vigila el coste","Por encima del objetivo")) -> En objetivo
A37: Pescado: 0 = ninguno · 1 = Salmón entero de acuicultura · 2 = Lomo de salmón comprado limpio · 3 = Atún aleta amarilla en saku ultracongelado · 4 = Otro pescado (escribe el tuyo). El food cost de la tabla es el del plato servido en sala, sin contar las bebidas. En el pedido para llevar se descuenta la caja; en la plataforma, además, se sube el precio con el recargo y se descuenta la comisión sobre ese precio. El margen se ordena por el de sala. AVISO FIJO: la tempura y las gyozas viajan mal; en la plataforma, ofrécelas solo con envase ventilado o déjalas fuera de la carta de reparto. Este coste es TEÓRICO: el plan de negocio trabaja con un 29 %, el lado prudente; la diferencia entre la receta y la caja está explicada en la hoja «Instrucciones».

Sheet Instrucciones
A1: INSTRUCCIONES DE USO — Calculadora del pescado, el arroz y el escandallo
A2: Tres herramientas en un libro: la hoja «Pescado» te dice cuánto cuesta el kilo útil de salmón entero, de lomo comprado limpio y de atún, cuánto vale cada loncha, corte y roll y si te compensa comprar el pescado entero; la hoja «Arroz» calcula el shari que sale de un kilo de arroz crudo, su coste, cuántos nigiris das por kilo y cuánto arroz compras al día; la hoja «Escandallo» calcula el coste, el food cost, el margen y el precio de carta de 14 productos, con el margen en sala, para llevar y en plataforma, y el food cost ponderado de tu semana. Solo se escribe en las celdas VERDES; lo demás se calcula.
A3: Todos los valores por defecto son estimación del kit, editable: son ejemplos coherentes con el caso del plan de negocio, no precios de nadie. Cámbialos por los de tu proveedor y por lo que midas en tu barra antes de decidir precios.
A4: HOJA «PESCADO»
A6: 1. Mide tu rendimiento. Pesa 3 salmones enteros, límpialos y pesa el lomo que sale de cada uno; divide entre el peso del pescado entero y escribe la media en «Rendimiento». Pesa también el recorte que reaprovechas (tartar, maki, poke) y escríbelo en «Recorte que reaprovechas». Pesa 10 lonchas de nigiri y 10 cortes de sashimi y usa la media en los gramos.
A7: 2. El coste por kilo útil es el precio ÷ (rendimiento + recorte) ÷ (1 − merma de vitrina). Es el número que alimenta el escandallo: con los valores del kit sale a 14,29 €/kg en el salmón entero, 24,16 en el lomo comprado y 28,81 en el atún en saku.
A8: 3. La limpieza también cuesta. El kit supone 25 minutos por pieza entera, un dato sin fuente: cronométralo. El coste por hora del itamae (el jefe de barra: compra, limpia y corta el pescado) se estima en 22 €/h: 2.200 € brutos × 14 pagas + 33 % de cargas ÷ 1.840 h ≈ 22 €/h. La hoja te dice hasta qué coste de limpieza por kilo útil te compensa comprar el pescado entero.
A9: 4. Anisakis (RD 1021/2022, art. 8). El pescado que se sirve crudo o casi crudo se congela a −20 °C o menos durante al menos 24 horas, o a −35 °C o menos durante al menos 15 horas, en la totalidad del producto. La acuicultura queda exenta solo con documento escrito del proveedor. Hay que informar al cliente en la carta o en un cartel (art. 8.2). El desplegable de la hoja es solo un recordatorio: no cambia ningún cálculo.
A10: HOJA «ARROZ»
A12: 1. Pesa 10 bolas de shari (el arroz ya aliñado con sushi-zu) y usa la media en los gramos por nigiri; haz lo mismo con un hosomaki, un uramaki, un temaki y un poke.
A13: 2. Los resultados clave son los kilos de shari por kilo de arroz crudo (2,42 con los valores del kit), el coste por kilo de shari y los nigiris que das por cada kilo de arroz crudo. Con eso sabes cuánto arroz tienes que comprar al día para tus comensales.
A14: 3. Seguridad del shari. A temperatura ambiente solo puede mantenerse si tu APPCC lo justifica y lo demuestras a sanidad (RD 1086/2020, art. 30.5); si no, se mantiene refrigerado. El pH de 4,6 o menos es el límite crítico del APPCC del Kit de Tareas Sushi Bar, no una cifra legal. El pH de cada tanda se registra en el Kit de Tareas Sushi Bar (hoja 03).
... A32: Versión 1.0 · noviembre 2026 · aichef.pro/plan-negocio-sushi-bar · info@aichef.pro
