Workbook

Sheet 0. Supuestos
A1: SUPUESTOS — aquí se teclean las TASAS y los DRIVERS del modelo
A2: Cambia las celdas VERDES: el resto del libro se recalcula solo. Las partidas de gasto se teclean en su hoja (también en verde) y no se repiten aquí.
A3: ACTIVIDAD
A4: Comensales/día (media del año 1) | B4: 79 | C4: Comensales equivalentes al día, media del año: unos 45 en sala (barra y mesas) y unos 34 de para llevar y domicilio, que son los pedidos (unos 8,5 para recoger y 13 de plataforma al día) contando cada pedido como 1,6 comensales. Un sábado, unos 114 con los pedidos; un martes, unos 52. Contrástalo con el paso de gente de tu calle un viernes por la noche y un martes a mediodía
A5: Ticket medio SIN IVA (€) | B5: 20 | C5: SIN IVA, por comensal: en sala, el menú del día de mediodía (14,90 € con IVA, un 30 % de la sala) y la cena o el fin de semana (28,60 € con IVA) dejan unos 22,26 € sin IVA; el pedido para llevar (de media 27,00 € con IVA: un combinado y algún extra) sale a 15,34 € por comensal equivalente y el de plataforma, con la carta un 15 % más cara y un pedido algo mayor, a 18,47 €. La media de los tres canales da 20,08 €; el caso se queda en 20,00 €. El precio con IVA está en la fila «PVP equivalente con IVA» de abajo
A6: Días de apertura al año | B6: 300 | C6: 365 días menos los 52 lunes de cierre, 10 días de cierre en agosto y 3 festivos sueltos (Navidad, Año Nuevo y Reyes). Es el MISMO dato para la cuenta de resultados, el punto de equilibrio, los escenarios y las horas de personal
A7: Crecimiento de volumen del año 2 | B7: 0.06 | C7: Clientela que repite y más pedidos para llevar el segundo año. Se aplica a los comensales con el mismo ticket; el personal NO sube con este porcentaje: sale de la hoja Personal
A8: Crecimiento de volumen del año 3 | B8: 0.04 | C8: Sobre el año 2. Conservador: el techo lo ponen la barra, las 36 plazas los viernes y los sábados por la noche y lo que puede cortar un solo itamae
A9: PVP equivalente con IVA (calculado) | B9: =IFERROR(IF($B$5="","",$B$5*(1+SUMPRODUCT('PyG 3 Años'!$E$10:$E$11,'PyG 3 Años'!$G$10:$G$11))),"") -> 22.0231 | C9: =IFERROR("Ticket sin IVA más el IVA medio ponderado de tus líneas de venta: "&TEXT(SUMPRODUCT('PyG 3 Años'!$E$10:$E$11,'PyG 3 Años'!$G$10:$G$11)*100,"0")&" %. En sala todo va al 10 % (art. 91.Uno.2.2.º de la Ley 37/1992, alcohol incluido); la bebida que sale para llevar o a domicilio (columna H de su línea en el P&L) mueve la media. Aquí va redondeado. Compáralo con el rango del sector, que va con IVA.","") -> Ticket sin IVA más el IVA medio ponderado de tus líneas de venta: 10 %. En sala todo va al 10 % (art. 91.Uno.2.2.º de la Ley 37/1992, alcohol incluido); la bebida que sale para llevar o a domicilio (columna H de su línea en el P&L) mueve la media. Aquí va redondeado. Compáralo con el rango del sector, que va con IVA.
A10: MIX Y COSTE DE MERCANCÍA
A11: Ventas de COMIDA sobre el total | B11: 0.85 | C11: Peso de la COMIDA sobre el total de ventas. Es un INPUT: cámbialo aquí y el P&L, la tesorería y el IVA repercutido se recalculan solos
A12: Ventas de BEBIDA sobre el total | B12: =IFERROR(IF(COUNT(B11)=0,"",1-B11),"") -> 0.15 | C12: Se calcula como el resto: comida + bebida = 100 %
A13: Coste de mercancía sobre las ventas de COMIDA | B13: 0.29 | C13: Materia prima de la comida sobre sus ventas: un 29 %, el lado prudente. El escandallo teórico de la calculadora del pack sale en un 16 % de media ponderada (el nigiri de salmón, en un 11 %; el combinado de 24 piezas, en un 16 %), pero la cuenta real es lo que compras frente a lo que vendes: se pierden la merma del pescado que no se vende en la vitrina y del recorte que no se reaprovecha, la neta y el shari que pesan más que en el escandallo, el shari, el nori y las salsas que se tiran al cierre, las comidas del personal, las invitaciones y los errores de pedido y el menú del día, que deja poco margen; y el pescado es un precio estimado por el kit. Un japonés con pescado de calidad trabaja con un 30-35 %. Mide tu consumo el primer trimestre y cambia esta celda: cada punto vale unos 4.000 € al año
A14: Coste de mercancía sobre las ventas de BEBIDA | B14: 0.28 | C14: Cerveza japonesa al 32 %, sake y vino al 30 %, refrescos y agua al 28 % y té al 10 % de su precio de venta, en una mezcla de 45/20/25/10. Pide el precio del sake y de la cerveza japonesa por escrito: dependen de un importador
A15: Consumibles sobre ventas | B15: 0.03 | C15: Cajas de sushi, tarrinas de soja, palillos, bolsas, servilletas y toallitas (unos 0,90-1,20 € por pedido que sale del local) y los envases para que el cliente se lleve lo que no consuma (Ley 1/2025, art. 8). El envase de plástico de un solo uso se cobra aparte en el tique (Ley 7/2022, art. 55)
A16: Ventas por delivery sobre el total | B16: 0.24 | C16: Ventas por PLATAFORMA con su reparto (Glovo, Just Eat, Uber Eats) sobre el total. Lo que se recoge en el local NO paga comisión y no va aquí: empújalo. El combinado viaja bien; la tempura y las gyozas llegan peor: no subas de aquí sin probarlo
A17: Comisión de la plataforma de delivery | B17: 0.3 | C17: Comisión de la plataforma con su reparto sobre lo que vende ese canal: el plan básico de Uber Eats ronda el 30 % más IVA, Glovo va del 15 al 35 % según la zona y Just Eat, del 13 al 35 %. Compruébala en tu contrato. Si repartes tú, pon 0 y suma el repartidor, con contrato laboral, a la hoja Personal
A18: Comisión de los medios de pago | B18: 0.008 | C18: Tarjeta y bizum sobre el total facturado
A19: PERSONAL
A20: Seguridad Social a cargo de la empresa | B20: 0.33 | C20: Contingencias comunes + AT/EP + desempleo + FOGASA + FP; ajusta a tu convenio y bonificaciones
A21: Número de pagas anuales | B21: 14 | C21: Salario bruto anual = bruto mensual × pagas
A22: SMI anual de referencia (€) | B22: 17094 | C22: SMI 2026: 17.094 € al año (1.221 €/mes en 14 pagas), suelo legal por jornada completa. Comprueba el importe vigente si presentas el plan en otro ejercicio
A23: LOCAL Y FIJOS
A24: Alquiler mensual del local (€) | B24: 1600 | C24: Local de 95 m² que ya fue de restauración, con salida de humos a cubierta posible: barra de sushi a la vista con 8 taburetes, sala de 28 plazas, cocina eléctrica, cuarto frío y una zona de empaquetado de pedidos junto a la puerta, en un barrio con vida de noche de una ciudad de 150.000 a 500.000 habitantes, sin traspaso: unos 17 € el m². El peso sobre las ventas lo calcula el propio libro en la fila «Alquiler / Ventas» del P&L
A25: Fianza del alquiler (meses) | B25: 2 | C25: Dos meses de renta, lo habitual en un contrato de local de negocio: compruébalo con tu abogado
A26: Suministros mensuales de luz, agua y gas (€) | B26: 1100 | C26: Luz (la cocina es eléctrica: arroceras, inducción, freidora y plancha; el frío del pescado y el congelador de −20 °C, la extracción y la climatización) y agua. Pide el histórico del local
A27: Seguros (€/año) | B27: 1800 | C27: Responsabilidad civil de al menos 300.000 € y multirriesgo con incendio y avería del frío, que es el pescado de la cámara y del congelador. Dile a la aseguradora que sirves pescado crudo y que trabajas con freidora: cambia la prima y las condiciones
A28: Varios e imprevistos sobre ventas | B28: 0.02 | C28: Colchón de gasto corriente no presupuestado (pequeñas reparaciones, utillaje que se rompe, pruebas de carta)
A29: FINANCIACIÓN
A30: Recursos propios aportados (€) | B30: 55000 | C30: Aportación de los socios. Un banco pide entre el 25 y el 30 % de la necesidad de caja con dinero propio
A31: Préstamo bancario solicitado (€) | B31: 131000 | C31: Principal solicitado. La hoja de Financiación compara lo que aportas con la necesidad de caja de la hoja de inversión y te dice si sobra o falta: ajústalo con ese dato
A32: Tipo de interés nominal anual | B32: 0.06 | C32: Tipo nominal anual. Pide oferta a dos entidades y a una línea ICO antes de fijarlo; el frío y el equipo de cocina se pueden pagar con leasing o renting: compáralo
A33: Plazo del préstamo (años) | B33: 7 | C33: Años totales, carencia incluida
A34: Carencia de principal (años) | B34: 1 | C34: El primer año sólo intereses: la obra de la barra, el conducto de extracción y la cocina antes de facturar. Desde el segundo año se devuelve el principal: mira la holgura de caja de ese año en el Punto de Equilibrio
A35: Fondo de maniobra (meses de costes fijos) | B35: 3 | C35: Tres meses de costes fijos: el colchón para la rampa del arranque, que con el Mes 1 en enero va de enero a abril, y para agosto, el mes más flojo del año
A36: FISCAL
A37: Impuesto de Sociedades, nueva creación | B37: 0.15 | C37: Art. 29.1 LIS: el PRIMER ejercicio con base imponible positiva y el SIGUIENTE. El libro lo aproxima contando los dos primeros ejercicios con base positiva: coincide con la ley salvo que entre ellos haya un ejercicio en pérdidas
A38: Impuesto de Sociedades, tipo general | B38: 0.25 | C38: A partir del tercer ejercicio con base positiva. Es el tipo general del art. 29.1 LIS: si tu cifra de negocios queda por debajo de 1 M € (microempresa) o de 10 M € (reducida dimensión), desde 2025 hay tipos más bajos que se implantan de forma gradual; confirma el de tu ejercicio con tu asesor y cámbialo aquí
A39: IVA repercutido de restauración | B39: 0.1 | C39: Tipo reducido de hostelería
A40: IVA repercutido/soportado general | B40: 0.21 | C40: Tipo general. En este libro lo usan dos cosas: el IVA que soportas al comprar el alcohol (el proveedor lo factura al 21 %) y el que repercutes por la bebida que sale para llevar o a domicilio (es una entrega de bienes). El alcohol servido en sala va al reducido, como fija la línea de bebida del P&L. Suministros, equipamiento y servicios tienen su tipo en la celda de abajo. En las compras, el libro manda al general la parte de la bebida que declara la celda «Bebida que compras al 21 %» de esta hoja: la cerveza, el sake, el vino y los refrescos con azúcares o edulcorantes añadidos, cuya factura va al 21 % (art. 91.Uno.1.1.º de la Ley 37/1992)
A41: IVA soportado en compras e inversión | B41: 0.21 | C41: Recuperable vía modelo 303, pero hay que adelantarlo
A42: Bases negativas de ejercicios anteriores (€) | B42: 0 | C42: Pérdidas pendientes de compensar al empezar (art. 26 LIS)
A43: AMORTIZACIÓN
A44: Vida útil de obra e instalaciones (años) | B44: 10 | C44: Obra y barra de sushi, conducto de extracción hasta cubierta, instalación eléctrica, fontanería, climatización, rótulo y fachada. Coeficientes de la tabla del art. 12.1 de la Ley del Impuesto sobre Sociedades: confírmalo con tu asesor
A45: Vida útil de maquinaria y mobiliario (años) | B45: 10 | C45: Vitrina de sushi, arroceras, congelador, cocina caliente, campana extractora, frío, lavavajillas, utillaje, mobiliario y TPV: un 10 % anual, dentro del coeficiente máximo de la tabla del art. 12.1 de la Ley del Impuesto sobre Sociedades para la maquinaria (12 %) y para el mobiliario (10 %). Confírmalo con tu asesor
A47: CRECIMIENTO Y ACTUALIZACIÓN DE COSTES
A48: Subida anual de los costes fijos | B48: 0 | C48: A CERO: las tres columnas están en euros del año 1 (términos reales). Súbela si quieres proyectar en euros corrientes
A49: ARRANQUE Y AFORO
A50: Rotaciones al día implícitas (calculado) | B50: =IFERROR($B$4/$B$51,"") -> 2.1944444 | C50: =IFERROR("Son "&TEXT(INT(ROUND(B50,1)),"0")&","&TEXT(ROUND(MOD(ROUND(B50,1),1)*10,0),"0")&" servicios por plaza y día sobre las "&TEXT($B$51,"0")&" plazas de la celda de arriba. Incluye los pedidos para llevar y a domicilio (1 pedido = 1,6 comensales), que no ocupan mesa: la rotación real de tu sala ronda 1,25 por plaza y día.","") -> Son 2,2 servicios por plaza y día sobre las 36 plazas de la celda de arriba. Incluye los pedidos para llevar y a domicilio (1 pedido = 1,6 comensales), que no ocupan mesa: la rotación real de tu sala ronda 1,25 por plaza y día.
A51: Aforo del local (plazas sentadas, con la barra) | B51: 36 | C51: Plazas interiores: 8 taburetes en la barra de sushi y 28 en mesa. Quien se lleva el pedido o lo recibe en casa no ocupa mesa: por eso la rotación de la fila de arriba es más alta que la real de tu sala
A52: Actividad del mes 1 sobre la de crucero | B52: 0.75 | C52: Un sushi bar que abre trae curiosos el primer mes, pero la clientela fija y la nota en las plataformas tardan un trimestre: el Mes 1 (enero) factura un 75 % de lo que facturará a los cuatro meses. Con 100 % se elimina la rampa
A53: Meses hasta alcanzar el régimen de crucero | B53: 4 | C53: Cuatro meses hasta el ritmo de crucero: de enero a abril
A54: Meses de alquiler ANTES de abrir (obra y licencias) | B54: 2 | C54: Dos meses de renta antes de abrir: la obra de la barra, el conducto de extracción y la licencia. Si el banco te da el préstamo al empezar la obra, súmale los intereses de esos meses, que este libro no cuenta, y ten en cuenta que la carencia corre desde la firma
A55: Imprevistos sobre las partidas de OBRA del bloque de local (%) | B55: 0.1 | C55: Colchón sobre la obra y las instalaciones del local, que es donde aparecen las sorpresas (el conducto hasta cubierta, la potencia eléctrica de la cocina, el separador de grasas). Un banco no financia una reforma sin él
A57: COBROS, PAGOS Y DESGLOSE DEL IVA
A58: Días medios de cobro | B58: 2 | C58: Media ponderada: la sala y lo que se recoge en el local cobran al momento y la plataforma liquida cada semana o cada quince días lo que vende por ella (un 24 % de las ventas). Con liquidación semanal salen unos 2 días
A59: Días medios de pago a proveedor | B59: 30 | C59: Plazo de pago a los proveedores de pescado, arroz, algas y bebida: lo que te financian. Negócialo por escrito: si el proveedor de pescado te pide pago semanal, baja esta cifra
A60: Mes de la paga extra de verano | B60: 7 | C60: Mes de la TESORERÍA en el que sale la paga extra de verano: julio es el Mes 7, porque el Mes 1 del plan es enero
A61: Mes de la paga extra de Navidad | B61: 12 | C61: Mes de la TESORERÍA en el que sale la paga extra de Navidad: diciembre es el Mes 12, porque el Mes 1 del plan es enero
A62: Bebida que compras al 21 % (cerveza, sake, vino y refrescos con azúcares o edulcorantes añadidos) sobre el total de bebida | B62: 0.75 | C62: Sólo mueve el IVA que SOPORTAS al comprar la bebida: la cerveza, el sake, el vino y los refrescos con azúcares o edulcorantes añadidos te los facturan al 21 %; el agua, el té y lo que no lleve azúcares ni edulcorantes añadidos, al 10 %. Con un 75 % sale un 18,3 %. El IVA que REPERCUTES lo fija la línea de bebida del P&L (columna H)
A63: IVA de la bebida ALCOHÓLICA servida en sala | B63: 0.1 | C63: SIN EFECTO en este libro: el IVA que repercute la bebida lo fija su línea del P&L. En sala, todo al 10 % (art. 91.Uno.2.2.º de la Ley 37/1992); para llevar o a domicilio, la cerveza, el sake, el vino y los refrescos con azúcares o edulcorantes añadidos, al 21 %, en la columna H de esa línea
A64: UMBRALES Y SUELOS DE CONTROL
A65: DSCR mínimo aceptable | B65: 1 | C65: Por debajo de 1 el negocio no genera para pagar el préstamo. Ponlo en el covenant que te exija tu banco
A66: DSCR objetivo (verde) | B66: 1.25 | C66: Lo que suele pedir una entidad para dar el préstamo sin garantías adicionales
A67: Holgura mínima sobre el punto de equilibrio | B67: 0.15 | C67: Cuánto deben superar las ventas previstas a las del equilibrio de caja (costes fijos y cuota del préstamo). La caída que aguantas es algo menor: con un 15 % de holgura, un 13 % de lo previsto
A68: Suelo salarial anual del convenio provincial (€) | B68: 0 | C68: Los sushi bares van al convenio PROVINCIAL de hostelería: el art. 4 del VI Acuerdo Laboral de ámbito Estatal para el sector de Hostelería no nombra el sushi bar, pero incluye los restaurantes y el reparto de comidas preparadas. Copia aquí el salario base del grupo más bajo de la tabla de TU provincia. Con 0 el semáforo compara sólo contra el SMI

Sheet Inversión Inicial
A1: PLAN DE NEGOCIO: SUSHI BAR
A2: Inversión inicial estimada — sushi bar con barra a la vista, mesas, para llevar y a domicilio
A3: Ajusta las cifras a tu proyecto: son las de un caso tipo en una ciudad media, sin traspaso. Pon tus presupuestos reales en las celdas de importe.
A5: Concepto | B5: Importe | C5: % s/inversión | D5: Notas | E5: ¿Lleva IVA?
A6: INVERSIÓN | B6: =IFERROR(IF(COUNT(B7:B27)=0,"",SUM(B7:B27)),"") -> 109750 | C6: =IFERROR(B6/$B$30,"") -> 0.67060541
A7: Proyecto técnico de actividad y de extracción, y dirección de obra | B7: 3500 | C7: =IFERROR(B7/$B$30,"") -> 0.021386049 | D7: Proyecto de la actividad y del conducto de extracción, memoria para la licencia o la declaración responsable y certificado final de obra | E7: Sí
A8: Obra del local con barra de sushi a la vista, rótulo y fachada | B8: 28000 | C8: =IFERROR(B8/$B$30,"") -> 0.1710884 | D8: Barra de sushi de obra a la vista, cocina alicatada, cuarto frío, suelo antideslizante, aseos (uno adaptado), falsos techos y aislamiento acústico, más el rótulo y la fachada. Estimación del kit: pide dos presupuestos | E8: Sí
A9: Conducto de extracción exclusivo hasta cubierta | B9: 5000 | C9: =IFERROR(B9/$B$30,"") -> 0.030551499 | D9: Conducto exclusivo hasta la cubierta para la freidora de tempura y la plancha de las gyozas: Madrid pide superar en 1 m lo que haya en 15 m (Ordenanza 4/2021). Ningún fabricante da precio por metro: pide oferta con tu proyecto | E9: Sí
A10: Instalación eléctrica, cuadro y boletín | B10: 4500 | C10: =IFERROR(B10/$B$30,"") -> 0.027496349 | D10: La cocina es eléctrica (arroceras, inducción, freidora y plancha), más el frío, la extracción y la climatización. Pregunta la potencia disponible ANTES de firmar: una acometida nueva tarda | E10: Sí
A11: Fontanería, separador de grasas y climatización | B11: 7500 | C11: =IFERROR(B11/$B$30,"") -> 0.045827249 | D11: Agua fría y caliente en la cocina y en la barra, desagües con separador de grasas y climatización de la sala | E11: Sí
A12: Vitrina refrigerada de sushi para la barra | B12: 2500 | C12: =IFERROR(B12/$B$30,"") -> 0.01527575 | D12: La vitrina de la neta (el pescado cortado que va sobre el arroz) a la vista del cliente. Una de 6 cubetas GN 1/3 ronda los 999 € sin IVA y la de barra de gama alta pasa de 4.500 €: el caso cuenta una media | E12: Sí
A13: Arroceras industriales, mantenedor de arroz y hangiri | B13: 1500 | C13: =IFERROR(B13/$B$30,"") -> 0.0091654497 | D13: Dos arroceras (la de 8 litros ronda los 484 € sin IVA), un mantenedor y el hangiri, la tina de madera donde se aliña el shari. Estimación del kit | E13: Sí
A14: Armario congelador de -20 °C con registrador y arcón | B14: 2000 | C14: =IFERROR(B14/$B$30,"") -> 0.0122206 | D14: El congelador del anisakis tiene que llevar el pescado a -20 °C o menos en la totalidad del producto durante al menos 24 horas, o a -35 °C o menos 15 horas (RD 1021/2022, art. 8.1), y registrar la temperatura; un congelador que sólo marca -18 °C no sirve para eso. El arcón, para el resto del congelado. Estimación del kit: pide la ficha técnica | E14: Sí
A15: Cocina caliente: inducción, freidora de tempura y plancha | B15: 3500 | C15: =IFERROR(B15/$B$30,"") -> 0.021386049 | D15: Placas de inducción para el miso y los caldos, freidora para la tempura y plancha para las gyozas. Estimación del kit | E15: Sí
A16: Campana extractora con motor y filtros | B16: 1500 | C16: =IFERROR(B16/$B$30,"") -> 0.0091654497 | D16: Campana extractora con motor y filtros de grasa sobre la freidora, la plancha y la inducción (una de 1,5 a 2 m va de unos 543 a 813 € sin IVA) | E16: Sí
A17: Frío: armario de pescado, armarios de cocina, mesa refrigerada y nevera de bebida y sake | B17: 7500 | C17: =IFERROR(B17/$B$30,"") -> 0.045827249 | D17: Armario de pescado a 0-2 °C (el pescado fresco va entre 0 y 4 °C: RD 1021/2022, art. 4.1), armarios refrigerados de cocina, mesa refrigerada de trabajo para la barra y nevera de bebida y sake | E17: Sí
A18: Lavavajillas de capota, fregaderos, lavamanos, mesas inox y estanterías | B18: 5500 | C18: =IFERROR(B18/$B$30,"") -> 0.033606649 | D18: Lavavajillas, fregaderos, lavamanos de accionamiento no manual, mesas de acero inoxidable y estanterías | E18: Sí
... A24: Stock inicial: pescado, arroz, algas, salsas, cajas de pedidos y bebida | B24: 3500 | C24: =IFERROR(B24/$B$30,"") -> 0.021386049 | D24: Pescado, arroz para sushi, nori, salsas, el primer pedido de cajas para llevar y a domicilio y la bebida, el sake incluido (pídelo con su plazo: depende de un importador) | E24: Sí
A25: Fianza del alquiler | B25: =IFERROR(IF('0. Supuestos'!$B$24="","",'0. Supuestos'!$B$24*'0. Supuestos'!$B$25),"") -> 3200 | C25: =IFERROR(B25/$B$30,"") -> 0.019552959 | D25: =IFERROR(""&TEXT('0. Supuestos'!$B$25,"0")&" meses de renta, al tipo de la hoja de Supuestos. Es un activo recuperable al cerrar: ni se amortiza ni lleva IVA","") -> 2 meses de renta, al tipo de la hoja de Supuestos. Es un activo recuperable al cerrar: ni se amortiza ni lleva IVA | E25: No
A26: Alquiler de los meses previos a la apertura | B26: =IFERROR(IF('0. Supuestos'!$B$24="","",'0. Supuestos'!$B$24*'0. Supuestos'!$B$54),"") -> 3200 | C26: =IFERROR(B26/$B$30,"") -> 0.019552959 | D26: =IFERROR("Renta "&IF('0. Supuestos'!$B$54=1,"del mes","de los "&TEXT('0. Supuestos'!$B$54,"0")&" meses")&" de obra y licencias. NO se solapa con el P&L, que arranca el día de la apertura: los doce meses del P&L son los doce de explotación","") -> Renta de los 2 meses de obra y licencias. NO se solapa con el P&L, que arranca el día de la apertura: los doce meses del P&L son los doce de explotación | E26: Sí
A27: Imprevistos de obra y acondicionamiento | B27: =IFERROR(IF(COUNT(B7,B8,B9,B10,B11)=0,"",ROUND((B7+B8+B9+B10+B11)*'0. Supuestos'!$B$55,0)),"") -> 4850 | C27: =IFERROR(B27/$B$30,"") -> 0.029634954 | D27: =IFERROR("Al "&TEXT('0. Supuestos'!$B$55,"0%")&" de las partidas de OBRA Y ACONDICIONAMIENTO de este bloque (Proyecto técnico de actividad y de extracción, y dirección de obra, Obra del local con barra de sushi a la vista, rótulo y fachada, Conducto de extracción exclusivo hasta "&"cubierta, Instalación eléctrica, cuadro y boletín y Fontanería, separador de grasas y climatización), no del bloque entero: el resto de partidas del bloque quedan fuera. Un banco no financia una reforma sin colchón: el porcentaje está en "&"la hoja de Supuestos","") -> Al 10% de las partidas de OBRA Y ACONDICIONAMIENTO de este bloque (Proyecto técnico de actividad y de extracción, y dirección de obra, Obra del local con barra de sushi a la vista, rótulo y fachada, Conducto de extracción exclusivo hasta cubierta, Instalación eléctrica, cuadro y boletín y Fontanería, separador de grasas y climatización), no del bloque entero: el resto de partidas del bloque quedan fuera. Un banco no financia una reforma sin colchón: el porcentaje está en la hoja de Supuestos | E27: Sí
A28: FONDO DE MANIOBRA | B28: =IFERROR(IF(B29="","",B29),"") -> 53908.09 | C28: =IFERROR(B28/$B$30,"") -> 0.32939459
A29: Colchón operativo hasta alcanzar el equilibrio | B29: =IFERROR(IF('0. Supuestos'!$B$35*('PyG 3 Años'!$B$37-'PyG 3 Años'!$B$35)=0,"",'0. Supuestos'!$B$35*('PyG 3 Años'!$B$37-'PyG 3 Años'!$B$35)/12),"") -> 53908.09 | C29: =IFERROR(B29/$B$30,"") -> 0.32939459 | D29: =IFERROR("Cubre "&TEXT('0. Supuestos'!$B$35,"0")&IF('0. Supuestos'!$B$35=1," mes"," meses")&" de costes fijos DE CAJA del año 1 (los del P&L menos la amortización, que no se paga), que es el mínimo que exigen las Instrucciones de este libro","") -> Cubre 3 meses de costes fijos DE CAJA del año 1 (los del P&L menos la amortización, que no se paga), que es el mínimo que exigen las Instrucciones de este libro | E29: No
A30: INVERSIÓN TOTAL (suma de los bloques) | B30: =IFERROR(B6+B28,"") -> 163658.09 | D30: =IFERROR("Los porcentajes de la columna C se leen sobre esta cifra, que incluye el fondo de maniobra ("&TEXT(C28,"0%")&" del total). Para comparar el desglose con otro plan, usa la fila de CAPEX de abajo.","") -> Los porcentajes de la columna C se leen sobre esta cifra, que incluye el fondo de maniobra (33% del total). Para comparar el desglose con otro plan, usa la fila de CAPEX de abajo.
A31: CAPEX (inversión sin el fondo de maniobra) | B31: =IFERROR(B30-B28,"") -> 109750 | D31: Es lo que se compra: obra, equipamiento, lanzamiento y gastos de constitución. El colchón de caja no es inversión, es circulante
A32: IVA soportado sobre la inversión (recuperable) | B32: =IFERROR(IF(B30="","",SUMIF($E$7:$E$27,"Sí",$B$7:$B$27)*'0. Supuestos'!$B$41),"") -> 21745.5 | D32: =IFERROR("Al "&TEXT('0. Supuestos'!$B$41,"0%")&" sobre las partidas marcadas con «Sí» en la columna de IVA. Las tasas y licencias no están sujetas y los seguros están exentos (art. 20.Uno.16 LIVA). Las tasas y aranceles registrales no llevan IVA; los honorarios de notaría y gestoría sí "&"(21 %, deducible). Se recupera con el modelo 303, pero hay que adelantarlo","") -> Al 21% sobre las partidas marcadas con «Sí» en la columna de IVA. Las tasas y licencias no están sujetas y los seguros están exentos (art. 20.Uno.16 LIVA). Las tasas y aranceles registrales no llevan IVA; los honorarios de notaría y gestoría sí (21 %, deducible). Se recupera con el modelo 303, pero hay que adelantarlo
A33: NECESIDAD TOTAL DE CAJA AL ARRANQUE | B33: =IFERROR(B30+B32,"") -> 185403.59 | D33: Es la cifra que tiene que cubrir la hoja de Financiación
A34: BASES DE AMORTIZACIÓN (no suman a la inversión)
A35: Obra, instalaciones y acondicionamiento | B35: =IFERROR(IF(B7="","",B7+B8+B9+B10+B11+B27),"") -> 53350 | D35: =IFERROR("Se amortiza en "&TEXT('0. Supuestos'!$B$44,"0")&" años","") -> Se amortiza en 10 años
A36: Maquinaria, mobiliario y equipos | B36: =IFERROR(IF(B12="","",B12+B13+B14+B15+B16+B17+B18+B19+B20+B21),"") -> 39000 | D36: =IFERROR("Se amortiza en "&TEXT('0. Supuestos'!$B$45,"0")&" años","") -> Se amortiza en 10 años
A37: Amortización anual del inmovilizado | B37: =IFERROR(B35/MAX(1,'0. Supuestos'!$B$44)+B36/MAX(1,'0. Supuestos'!$B$45),"") -> 9235 | D37: =IFERROR("No se amortizan, por no ser inmovilizado, Constitución de la SL, licencia, tasas, registro sanitario y APPCC, Marca, web, fotos y lanzamiento, Stock inicial: pescado, arroz, algas, salsas, cajas de pedidos y bebida, Fianza del alquiler, "&"Alquiler de los meses previos a la apertura ni Colchón operativo hasta alcanzar el equilibrio. Suman "&TEXT(B30-B35-B36,"0")&" € de los "&TEXT(B30,"0")&" € de inversión.","") -> No se amortizan, por no ser inmovilizado, Constitución de la SL, licencia, tasas, registro sanitario y APPCC, Marca, web, fotos y lanzamiento, Stock inicial: pescado, arroz, algas, salsas, cajas de pedidos y bebida, Fianza del alquiler, Alquiler de los meses previos a la apertura ni Colchón operativo hasta alcanzar el equilibrio. Suman 71308 € de los 163658 € de inversión.

Sheet PyG 3 Años
A1: CUENTA DE RESULTADOS PREVISIONAL — 3 AÑOS
A2: Escenario realista — sushi bar con barra a la vista, mesas, para llevar y a domicilio
A4: Concepto | B4: Año 1 | C4: Año 2 | D4: Año 3 | E4: % s/ventas (año 1) | F4: Notas | G4: Tipo de IVA de la línea (%) | H4: Bebida para llevar o a domicilio al 21 % (%)
A5: INGRESOS
A6: Comensales/día (media) | B6: =IFERROR(IF('0. Supuestos'!$B$4="","",'0. Supuestos'!$B$4),"") -> 79 | C6: =IFERROR(B6*(1+'0. Supuestos'!$B$7),"") -> 83.74 | D6: =IFERROR(C6*(1+'0. Supuestos'!$B$8),"") -> 87.0896 | F6: El crecimiento de los años 2 y 3 está en la hoja de Supuestos
A7: Ticket medio sin IVA | B7: =IFERROR(IF('0. Supuestos'!$B$5="","",'0. Supuestos'!$B$5),"") -> 20 | C7: =IFERROR(IF(B7="","",B7),"") -> 20 | D7: =IFERROR(IF(C7="","",C7),"") -> 20 | F7: Constante en euros del año 1: una subida de precios es una decisión aparte
A8: Días de apertura al año | B8: =IFERROR(IF('0. Supuestos'!$B$6="","",'0. Supuestos'!$B$6),"") -> 300 | C8: =IFERROR(IF(B8="","",B8),"") -> 300 | D8: =IFERROR(IF(C8="","",C8),"") -> 300
A9: INGRESOS TOTALES (sin IVA) | B9: =IFERROR(IF(B6*B7*B8=0,"",B6*B7*B8),"") -> 474000 | C9: =IFERROR(IF(C6*C7*C8=0,"",C6*C7*C8),"") -> 502440 | D9: =IFERROR(IF(D6*D7*D8=0,"",D6*D7*D8),"") -> 522537.6 | E9: =IFERROR(IF(B9="","",1),"") -> 1
A10: Ventas de sushi y cocina (sala, para llevar y a domicilio) | B10: =IFERROR(IF(B9="","",B9*$E$10),"") -> 402900 | C10: =IFERROR(IF(C9="","",C9*$E$10),"") -> 427074 | D10: =IFERROR(IF(D9="","",D9*$E$10),"") -> 444156.96 | E10: =IFERROR(IF('0. Supuestos'!$B$11="","",'0. Supuestos'!$B$11),"") -> 0.85 | F10: Sushi, sashimi y poke, gyozas, tempura, sopa de miso y postres: en sala unos 63 % de las ventas, para llevar unos 13 % y por plataforma unos 24 %. Todo al 10 % de IVA, se coma en la barra o salga del local (art. 91.Uno.1.1.º y 2.2.º de la Ley 37/1992) | G10: =IFERROR(IF(B9="","",'0. Supuestos'!$B$39),"") -> 0.1
A11: Ventas de bebida (cerveza, sake, vino, refrescos, agua y té) | B11: =IFERROR(IF(B9="","",B9*$E$11),"") -> 71100 | C11: =IFERROR(IF(C9="","",C9*$E$11),"") -> 75366 | D11: =IFERROR(IF(D9="","",D9*$E$11),"") -> 78380.64 | E11: =IFERROR(IF('0. Supuestos'!$B$12="","",'0. Supuestos'!$B$12),"") -> 0.15 | F11: Bebida de sala y la que sale con los pedidos · La columna H es la parte de la bebida que sale del local y va al 21 %: la cerveza, el sake, el vino y los refrescos con azúcares o edulcorantes añadidos (art. 91.Uno.1.1.º a y b de la Ley 37/1992); el agua, el té y lo que no lleve azúcares ni edulcorantes añadidos, y toda la bebida en sala, al 10 %. Un 7 % = un 1,05 % de las ventas | G11: =IFERROR(IF(B9="","",H11*0.21+(1-H11)*'0. Supuestos'!$B$39),"") -> 0.1077 | H11: 0.07
A12: COSTES VARIABLES
A13: Coste de mercancía — comida | B13: =IFERROR(IF(B9="","",B9*'0. Supuestos'!$B$11*'0. Supuestos'!$B$13),"") -> 116841 | C13: =IFERROR(IF(C9="","",C9*'0. Supuestos'!$B$11*'0. Supuestos'!$B$13),"") -> 123851.46 | D13: =IFERROR(IF(D9="","",D9*'0. Supuestos'!$B$11*'0. Supuestos'!$B$13),"") -> 128805.52 | E13: =IFERROR(B13/$B$9,"") -> 0.2465 | F13: =IFERROR("Al "&TEXT('0. Supuestos'!$B$13,"0%")&" de las ventas de COMIDA, no del total: la bebida tiene su propia línea · Pescado, marisco, algas, salsas y surimi al 10 %; arroz, verdura, aguacate, huevo y queso al 4 % (art. 91.Dos.1.1.º de la Ley 37/1992). Ajústalo a tus facturas","") -> Al 29% de las ventas de COMIDA, no del total: la bebida tiene su propia línea · Pescado, marisco, algas, salsas y surimi al 10 %; arroz, verdura, aguacate, huevo y queso al 4 % (art. 91.Dos.1.1.º de la Ley 37/1992). Ajústalo a tus facturas | G13: 0.087
A14: Coste de mercancía — bebida | B14: =IFERROR(IF(B9="","",B9*'0. Supuestos'!$B$12*'0. Supuestos'!$B$14),"") -> 19908 | C14: =IFERROR(IF(C9="","",C9*'0. Supuestos'!$B$12*'0. Supuestos'!$B$14),"") -> 21102.48 | D14: =IFERROR(IF(D9="","",D9*'0. Supuestos'!$B$12*'0. Supuestos'!$B$14),"") -> 21946.579 | E14: =IFERROR(B14/$B$9,"") -> 0.042 | F14: =IFERROR("Al "&TEXT('0. Supuestos'!$B$14,"0%")&" de las ventas de BEBIDA","") -> Al 28% de las ventas de BEBIDA | G14: =IFERROR(IF(B9="","",('0. Supuestos'!$B$62*'0. Supuestos'!$B$40+(1-'0. Supuestos'!$B$62)*'0. Supuestos'!$B$39)),"") -> 0.1825
A15: Consumibles y envases | B15: =IFERROR(IF(B9="","",B9*'0. Supuestos'!$B$15),"") -> 14220 | C15: =IFERROR(IF(C9="","",C9*'0. Supuestos'!$B$15),"") -> 15073.2 | D15: =IFERROR(IF(D9="","",D9*'0. Supuestos'!$B$15),"") -> 15676.128 | E15: =IFERROR(B15/$B$9,"") -> 0.03 | G15: =IFERROR(IF(B9="","",'0. Supuestos'!$B$41),"") -> 0.21
A16: Comisiones de delivery | B16: =IFERROR(IF(B9="","",B9*'0. Supuestos'!$B$16*'0. Supuestos'!$B$17),"") -> 34128 | C16: =IFERROR(IF(C9="","",C9*'0. Supuestos'!$B$16*'0. Supuestos'!$B$17),"") -> 36175.68 | D16: =IFERROR(IF(D9="","",D9*'0. Supuestos'!$B$16*'0. Supuestos'!$B$17),"") -> 37622.707 | E16: =IFERROR(B16/$B$9,"") -> 0.072 | F16: Sobre las ventas DEL CANAL. Con 0 % de delivery en Supuestos, esta línea vale cero | G16: =IFERROR(IF(B9="","",'0. Supuestos'!$B$41),"") -> 0.21
A17: Comisiones de los medios de pago | B17: =IFERROR(IF(B9="","",B9*'0. Supuestos'!$B$18),"") -> 3792 | C17: =IFERROR(IF(C9="","",C9*'0. Supuestos'!$B$18),"") -> 4019.52 | D17: =IFERROR(IF(D9="","",D9*'0. Supuestos'!$B$18),"") -> 4180.3008 | E17: =IFERROR(B17/$B$9,"") -> 0.008 | F17: Las comisiones de los medios de pago están EXENTAS de IVA (art. 20.Uno.18 LIVA): no se deduce nada por ellas | G17: 0
A18: Varios e imprevistos | B18: =IFERROR(IF(B9="","",B9*'0. Supuestos'!$B$28),"") -> 9480 | C18: =IFERROR(IF(C9="","",C9*'0. Supuestos'!$B$28),"") -> 10048.8 | D18: =IFERROR(IF(D9="","",D9*'0. Supuestos'!$B$28),"") -> 10450.752 | E18: =IFERROR(B18/$B$9,"") -> 0.02 | F18: =IFERROR("Al "&TEXT('0. Supuestos'!$B$28,"0%")&" de las ventas. Es un coste VARIABLE: sube y baja con la facturación, así que no puede vivir en los costes fijos","") -> Al 2% de las ventas. Es un coste VARIABLE: sube y baja con la facturación, así que no puede vivir en los costes fijos | G18: =IFERROR(IF(B9="","",'0. Supuestos'!$B$41),"") -> 0.21
A19: TOTAL COSTES VARIABLES | B19: =IFERROR(IF(B9="","",SUM(B13:B18)),"") -> 198369 | C19: =IFERROR(IF(C9="","",SUM(C13:C18)),"") -> 210271.14 | D19: =IFERROR(IF(D9="","",SUM(D13:D18)),"") -> 218681.99 | E19: =IFERROR(B19/$B$9,"") -> 0.4185
A20: MARGEN BRUTO | B20: =IFERROR(IF(B9="","",B9-B19),"") -> 275631 | C20: =IFERROR(IF(C9="","",C9-C19),"") -> 292168.86 | D20: =IFERROR(IF(D9="","",D9-D19),"") -> 303855.61 | E20: =IFERROR(B20/$B$9,"") -> 0.5815
A21: COSTES FIJOS
A22: Alquiler del local | B22: =IFERROR(IF(B9="","",'0. Supuestos'!$B$24*12),"") -> 19200 | C22: =IFERROR(IF(C9="","",B22*(1+'0. Supuestos'!$B$48)),"") -> 19200 | D22: =IFERROR(IF(D9="","",C22*(1+'0. Supuestos'!$B$48)),"") -> 19200 | E22: =IFERROR(B22/$B$9,"") -> 0.040506329 | F22: El importe mensual está en la hoja de Supuestos; aquí se multiplica por doce. Los dos meses de renta previos a la apertura están en la hoja de Inversión y NO se cuentan dos veces | G22: =IFERROR(IF(B9="","",'0. Supuestos'!$B$41),"") -> 0.21
A23: Personal (nóminas + Seguridad Social) | B23: =IFERROR(IF(B9="","",'Personal'!$G$12),"") -> 159722.36 | C23: =IFERROR(IF(C9="","",'Personal'!$B$16),"") -> 165722.36 | D23: =IFERROR(IF(D9="","",'Personal'!$B$17),"") -> 171722.36 | E23: =IFERROR(B23/$B$9,"") -> 0.336967 | F23: Sale de la hoja de Personal: es el MISMO número, no una estimación aparte. Los años 2 y 3 suman las INCORPORACIONES declaradas en esa hoja, no un porcentaje de volumen | G23: 0
A24: Suministros (luz, agua, gas) | B24: =IFERROR(IF(B9="","",'0. Supuestos'!$B$26*12),"") -> 13200 | C24: =IFERROR(IF(C9="","",B24*(1+'0. Supuestos'!$B$48)),"") -> 13200 | D24: =IFERROR(IF(D9="","",C24*(1+'0. Supuestos'!$B$48)),"") -> 13200 | E24: =IFERROR(B24/$B$9,"") -> 0.027848101 | F24: Luz y gas van al 21 %; la factura del agua, al 10 %. El libro aplica a toda esta partida el tipo de la columna de al lado (21 %): si el agua pesa mucho en tu local, sepárala en su línea | G24: =IFERROR(IF(B9="","",'0. Supuestos'!$B$41),"") -> 0.21
A25: Seguros (RC + multirriesgo) | B25: =IFERROR(IF(B9="","",'0. Supuestos'!$B$27),"") -> 1800 | C25: =IFERROR(IF(C9="","",B25*(1+'0. Supuestos'!$B$48)),"") -> 1800 | D25: =IFERROR(IF(D9="","",C25*(1+'0. Supuestos'!$B$48)),"") -> 1800 | E25: =IFERROR(B25/$B$9,"") -> 0.0037974684 | F25: Las operaciones de seguro están EXENTAS de IVA (art. 20.Uno.16 LIVA): la prima no lleva IVA deducible | G25: 0
A26: Gestoría laboral, fiscal y contable | B26: 2400 | C26: =IFERROR(IF(C9="","",B26*(1+'0. Supuestos'!$B$48)),"") -> 2400 | D26: =IFERROR(IF(D9="","",C26*(1+'0. Supuestos'!$B$48)),"") -> 2400 | E26: =IFERROR(B26/$B$9,"") -> 0.0050632911 | F26: Contabilidad, impuestos de la SL, nóminas y contratos de la plantilla | G26: =IFERROR(IF(B9="","",'0. Supuestos'!$B$41),"") -> 0.21
A27: Mantenimiento del frío, el congelador, la campana extractora y el pH-metro | B27: 1800 | C27: =IFERROR(IF(C9="","",B27*(1+'0. Supuestos'!$B$48)),"") -> 1800 | D27: =IFERROR(IF(D9="","",C27*(1+'0. Supuestos'!$B$48)),"") -> 1800 | E27: =IFERROR(B27/$B$9,"") -> 0.0037974684 | F27: El frigorista para la cámara, los armarios y el congelador, que tiene que llegar a −20 °C en el centro del pescado (anisakis); la limpieza de la campana extractora y del conducto al menos una vez al año (Madrid lo exige en su Ordenanza 4/2021, art. 23; mira la de tu ayuntamiento) y las soluciones de calibración del pH-metro | G27: =IFERROR(IF(B9="","",'0. Supuestos'!$B$41),"") -> 0.21
A28: Marketing y publicidad | B28: 4000 | C28: =IFERROR(IF(C9="","",B28*(1+'0. Supuestos'!$B$48)),"") -> 4000 | D28: =IFERROR(IF(D9="","",C28*(1+'0. Supuestos'!$B$48)),"") -> 4000 | E28: =IFERROR(B28/$B$9,"") -> 0.0084388186 | F28: Ficha de Google Business, redes sociales, fotos, las promociones de las plataformas y las fechas fuertes (San Valentín, Nochebuena y Nochevieja); la campaña de apertura va en la inversión | G28: =IFERROR(IF(B9="","",'0. Supuestos'!$B$41),"") -> 0.21
A29: Software, TPV, teléfono e internet | B29: 1800 | C29: =IFERROR(IF(C9="","",B29*(1+'0. Supuestos'!$B$48)),"") -> 1800 | D29: =IFERROR(IF(D9="","",C29*(1+'0. Supuestos'!$B$48)),"") -> 1800 | E29: =IFERROR(B29/$B$9,"") -> 0.0037974684 | F29: Cuota del TPV con Veri*factu, las tablets de las plataformas, teléfono e internet | G29: =IFERROR(IF(B9="","",'0. Supuestos'!$B$41),"") -> 0.21
A30: Limpieza, lavandería, EPI y análisis de autocontrol | B30: 1500 | C30: =IFERROR(IF(C9="","",B30*(1+'0. Supuestos'!$B$48)),"") -> 1500 | D30: =IFERROR(IF(D9="","",C30*(1+'0. Supuestos'!$B$48)),"") -> 1500 | E30: =IFERROR(B30/$B$9,"") -> 0.003164557 | F30: Productos de limpieza, lavado de uniformes y paños, guantes y los análisis de autocontrol que fije tu APPCC | G30: =IFERROR(IF(B9="","",'0. Supuestos'!$B$41),"") -> 0.21
A31: Gestión de residuos y del aceite usado de la freidora | B31: 600 | C31: =IFERROR(IF(C9="","",B31*(1+'0. Supuestos'!$B$48)),"") -> 600 | D31: =IFERROR(IF(D9="","",C31*(1+'0. Supuestos'!$B$48)),"") -> 600 | E31: =IFERROR(B31/$B$9,"") -> 0.0012658228 | F31: La tasa de basuras, el cartón de las cajas y el aceite usado de la freidora de tempura con gestor autorizado. Pon las de tu ayuntamiento | G31: =IFERROR(IF(B9="","",'0. Supuestos'!$B$41),"") -> 0.21
A32: Desinsectación, desratización y desinfección (DDD) | B32: 450 | C32: =IFERROR(IF(C9="","",B32*(1+'0. Supuestos'!$B$48)),"") -> 450 | D32: =IFERROR(IF(D9="","",C32*(1+'0. Supuestos'!$B$48)),"") -> 450 | E32: =IFERROR(B32/$B$9,"") -> 0.00094936709 | F32: Contrato con una empresa inscrita en el ROESB: forma parte de los prerrequisitos del APPCC | G32: =IFERROR(IF(B9="","",'0. Supuestos'!$B$41),"") -> 0.21
A33: Derechos de autor por música ambiental (SGAE y AGEDI-AIE) | B33: 500 | C33: =IFERROR(IF(C9="","",B33*(1+'0. Supuestos'!$B$48)),"") -> 500 | D33: =IFERROR(IF(D9="","",C33*(1+'0. Supuestos'!$B$48)),"") -> 500 | E33: =IFERROR(B33/$B$9,"") -> 0.0010548523 | F33: SGAE y AGEDI-AIE son dos licencias distintas; el importe depende de los metros y del aforo de tu sala | G33: =IFERROR(IF(B9="","",'0. Supuestos'!$B$41),"") -> 0.21
A34: Prevención de riesgos laborales, vigilancia de la salud y formación | B34: 800 | C34: =IFERROR(IF(C9="","",B34*(1+'0. Supuestos'!$B$48)),"") -> 800 | D34: =IFERROR(IF(D9="","",C34*(1+'0. Supuestos'!$B$48)),"") -> 800 | E34: =IFERROR(B34/$B$9,"") -> 0.0016877637 | F34: El plan de prevención es obligatorio (Ley 31/1995): cortes con los cuchillos de la barra, quemaduras de la freidora y la plancha, el frío del congelador y las cargas; los reconocimientos médicos de la plantilla y la formación en higiene del pescado crudo y en alérgenos | G34: =IFERROR(IF(B9="","",'0. Supuestos'!$B$41),"") -> 0.21
A35: Amortización del inmovilizado | B35: =IFERROR(IF(B9="","",'Inversión Inicial'!$B$37),"") -> 9235 | C35: =IFERROR(IF(C9="","",B35),"") -> 9235 | D35: =IFERROR(IF(D9="","",B35),"") -> 9235 | E35: =IFERROR(B35/$B$9,"") -> 0.019483122 | F35: Sale de las bases de amortización de la hoja de Inversión: sólo inmovilizado real. NO sube con el IPC: es una cuota sobre el coste HISTÓRICO del inmovilizado | G35: 0
A36: Gastos financieros (intereses del préstamo) | B36: =IFERROR(IF(B9="","",'Financiación'!$B$44),"") -> 7860 | C36: =IFERROR(IF(C9="","",'Financiación'!$B$46),"") -> 7860 | D36: =IFERROR(IF(D9="","",'Financiación'!$B$48),"") -> 6733.1697 | E36: =IFERROR(B36/$B$9,"") -> 0.016582278 | F36: Sólo los INTERESES son gasto. La devolución del principal va en la hoja de Tesorería | G36: 0
A37: TOTAL COSTES FIJOS | B37: =IFERROR(IF(B9="","",SUM(B22:B36)),"") -> 224867.36 | C37: =IFERROR(IF(C9="","",SUM(C22:C36)),"") -> 230867.36 | D37: =IFERROR(IF(D9="","",SUM(D22:D36)),"") -> 235740.53 | E37: =IFERROR(B37/$B$9,"") -> 0.47440371
A38: IVA soportado de los costes variables | B38: =IFERROR(IF(B9="","",SUMPRODUCT(B13:B18,G13:G18)),"") -> 25942.257 | C38: =IFERROR(IF(C9="","",SUMPRODUCT(C13:C18,G13:G18)),"") -> 27498.792 | D38: =IFERROR(IF(D9="","",SUMPRODUCT(D13:D18,G13:G18)),"") -> 28598.744 | F38: Cada línea a SU tipo, leído de la columna de al lado. Es lo que la hoja de Tesorería paga de más a los proveedores y luego se deduce
A39: IVA soportado de los costes fijos | B39: =IFERROR(IF(B9="","",SUMPRODUCT(B22:B36,G22:G36)),"") -> 9712.5 | C39: =IFERROR(IF(C9="","",SUMPRODUCT(C22:C36,G22:G36)),"") -> 9712.5 | D39: =IFERROR(IF(D9="","",SUMPRODUCT(D22:D36,G22:G36)),"") -> 9712.5
A40: RESULTADO ANTES DE IMPUESTOS | B40: =IFERROR(IF(B9="","",B20-B37),"") -> 50763.64 | C40: =IFERROR(IF(C9="","",C20-C37),"") -> 61301.5 | D40: =IFERROR(IF(D9="","",D20-D37),"") -> 68115.085 | E40: =IFERROR(B40/$B$9,"") -> 0.10709629
A41: Bases negativas pendientes al inicio | B41: =IFERROR(IF(B9="","",'0. Supuestos'!$B$42),"") -> 0 | C41: =IFERROR(IF(C9="","",B46),"") -> 0 | D41: =IFERROR(IF(D9="","",C46),"") -> 0 | F41: Art. 26 LIS: las pérdidas de un ejercicio se compensan con los beneficios de los siguientes
A42: Base imponible (después de compensar) | B42: =IFERROR(IF(B9="","",MAX(0,B40-B41)),"") -> 50763.64 | C42: =IFERROR(IF(C9="","",MAX(0,C40-C41)),"") -> 61301.5 | D42: =IFERROR(IF(D9="","",MAX(0,D40-D41)),"") -> 68115.085
A43: Ejercicios con base positiva (acumulado) | B43: =IFERROR(IF(B9="","",IF(B42>0,1,0)),"") -> 1 | C43: =IFERROR(IF(C9="","",B43+IF(C42>0,1,0)),"") -> 2 | D43: =IFERROR(IF(D9="","",C43+IF(D42>0,1,0)),"") -> 3
A44: Tipo de Impuesto de Sociedades aplicado | B44: =IFERROR(IF(B9="","",IF(B42<=0,"",IF(B43<=2,'0. Supuestos'!$B$37,'0. Supuestos'!$B$38))),"") -> 0.15 | C44: =IFERROR(IF(C9="","",IF(C42<=0,"",IF(C43<=2,'0. Supuestos'!$B$37,'0. Supuestos'!$B$38))),"") -> 0.15 | D44: =IFERROR(IF(D9="","",IF(D42<=0,"",IF(D43<=2,'0. Supuestos'!$B$37,'0. Supuestos'!$B$38))),"") -> 0.25 | F44: Art. 29.1 LIS: el 15 % de entidad de nueva creación se aplica al PRIMER ejercicio con base positiva y al SIGUIENTE, no al primer año de vida. El libro lo aproxima contando los dos primeros ejercicios con base positiva
A45: Impuesto de Sociedades | B45: =IFERROR(IF(B9="","",IF(B44="",0,B42*B44)),"") -> 7614.546 | C45: =IFERROR(IF(C9="","",IF(C44="",0,C42*C44)),"") -> 9195.225 | D45: =IFERROR(IF(D9="","",IF(D44="",0,D42*D44)),"") -> 17028.771
A46: Bases negativas pendientes al cierre | B46: =IFERROR(IF(B9="","",MAX(0,B41-B40)),"") -> 0 | C46: =IFERROR(IF(C9="","",MAX(0,C41-C40)),"") -> 0 | D46: =IFERROR(IF(D9="","",MAX(0,D41-D40)),"") -> 0
A47: RESULTADO NETO | B47: =IFERROR(IF(B9="","",B40-B45),"") -> 43149.094 | C47: =IFERROR(IF(C9="","",C40-C45),"") -> 52106.275 | D47: =IFERROR(IF(D9="","",D40-D45),"") -> 51086.313 | E47: =IFERROR(B47/$B$9,"") -> 0.091031844
A48: RATIOS CLAVE
A49: Ratio | B49: Año 1 | C49: Año 2 | D49: Año 3 | E49: Umbral | F49: Comentario
A50: Margen bruto / Ventas | B50: =IFERROR(IF(B9="","",B20/B9),"") -> 0.5815 | C50: =IFERROR(IF(C9="","",C20/C9),"") -> 0.5815 | D50: =IFERROR(IF(D9="","",D20/D9),"") -> 0.5815 | E50: 0.52 | F50: Suelo del margen tras TODOS los costes variables (mercancía, envases, plataforma, medios de pago y varios). Con casi un cuarto de las ventas por plataforma, un sushi bar deja menos que una sala sola. Estimación del kit
A51: Coste de mercancía (comida + bebida) | B51: =IFERROR(IF(B9="","",B13+B14),"") -> 136749 | C51: =IFERROR(IF(C9="","",C13+C14),"") -> 144953.94 | D51: =IFERROR(IF(D9="","",D13+D14),"") -> 150752.1
A52: Coste de mercancía / Ventas | B52: =IFERROR(IF(B9="","",B51/B9),"") -> 0.2885 | C52: =IFERROR(IF(C9="","",C51/C9),"") -> 0.2885 | D52: =IFERROR(IF(D9="","",D51/D9),"") -> 0.2885 | E52: 0.31 | F52: Techo de la materia prima sobre ventas: el salmón paga la carta y el atún, el langostino y la merma de la vitrina la encarecen. Estimación del kit
A53: Coste de personal / Ventas | B53: =IFERROR(IF(B9="","",B23/B9),"") -> 0.336967 | C53: =IFERROR(IF(C9="","",C23/C9),"") -> 0.32983512 | D53: =IFERROR(IF(D9="","",D23/D9),"") -> 0.32863159 | E53: 0.38 | F53: Techo del personal sobre ventas con itamae, sushiman y una sala de dos servicios. Estimación del kit
A54: Alquiler / Ventas | B54: =IFERROR(IF(B9="","",B22/B9),"") -> 0.040506329 | C54: =IFERROR(IF(C9="","",C22/C9),"") -> 0.038213518 | D54: =IFERROR(IF(D9="","",D22/D9),"") -> 0.036743767 | E54: 0.1 | F54: Techo del alquiler sobre ventas para un local con salida de humos a cubierta: estimación del kit
A55: Resultado neto / Ventas | B55: =IFERROR(IF(B9="","",B47/B9),"") -> 0.091031844 | C55: =IFERROR(IF(C9="","",C47/C9),"") -> 0.10370646 | D55: =IFERROR(IF(D9="","",D47/D9),"") -> 0.097765813 | E55: 0.05 | F55: Suelo de resultado neto a régimen para que el plan se sostenga. Un sushi bar bien llevado deja en torno a un 8-10 %. Estimación del kit
A56: Punto de equilibrio alcanzado | B56: =IFERROR(IF(B9="","",IF(B9>='Punto Equilibrio'!$B$16,"Sí","No")),"") -> Sí | C56: =IFERROR(IF(C9="","",IF(C9>='Punto Equilibrio'!$C$16,"Sí","No")),"") -> Sí | D56: =IFERROR(IF(D9="","",IF(D9>='Punto Equilibrio'!$D$16,"Sí","No")),"") -> Sí | F56: Compara las ventas de CADA año con el umbral de ese mismo año, que calcula la hoja de Punto de Equilibrio con los costes fijos del año
A58: Todas las cifras van SIN IVA. Las columnas de los años 2 y 3 están en euros del año 1 salvo que subas la actualización de costes en la hoja de Supuestos. La columna «Tipo de IVA de la línea» dice, en las líneas de VENTA, a qué tipo se repercute cada una, y en las de COSTE a qué tipo se compra la partida. La lee la hoja de Tesorería: los seguros y las comisiones de los medios de pago están exentos, y las nóminas, la amortización y los intereses no llevan IVA.

Sheet Punto Equilibrio
A1: ANÁLISIS DE PUNTO DE EQUILIBRIO
A2: Punto de equilibrio mensual y diario — sushi bar con barra a la vista, mesas, para llevar y a domicilio
A4: Variable | B4: Año 1 | C4: Año 2 | D4: Año 3 | E4: Notas
A5: DATOS BASE POR AÑO
A6: Costes fijos anuales | B6: =IFERROR(IF('PyG 3 Años'!$B$9="","",'PyG 3 Años'!$B$37),"") -> 224867.36 | C6: =IFERROR(IF('PyG 3 Años'!$C$9="","",'PyG 3 Años'!$C$37),"") -> 230867.36 | D6: =IFERROR(IF('PyG 3 Años'!$D$9="","",'PyG 3 Años'!$D$37),"") -> 235740.53 | E6: Los MISMOS costes fijos del P&L. Cada año tiene los suyos: por eso el umbral no puede ser uno solo para los tres
A7: Costes fijos mensuales | B7: =IFERROR(IF('PyG 3 Años'!$B$9="","",B6/12),"") -> 18738.947 | C7: =IFERROR(IF('PyG 3 Años'!$C$9="","",C6/12),"") -> 19238.947 | D7: =IFERROR(IF('PyG 3 Años'!$D$9="","",D6/12),"") -> 19645.044
A8: Ticket medio sin IVA | B8: =IFERROR(IF('PyG 3 Años'!$B$9="","",'PyG 3 Años'!$B$7),"") -> 20 | C8: =IFERROR(IF('PyG 3 Años'!$C$9="","",'PyG 3 Años'!$C$7),"") -> 20 | D8: =IFERROR(IF('PyG 3 Años'!$D$9="","",'PyG 3 Años'!$D$7),"") -> 20
A9: Coste variable por comensal | B9: =IFERROR(IF('PyG 3 Años'!$B$9="","",'PyG 3 Años'!$B$19/('PyG 3 Años'!$B$6*'PyG 3 Años'!$B$8)),"") -> 8.37 | C9: =IFERROR(IF('PyG 3 Años'!$C$9="","",'PyG 3 Años'!$C$19/('PyG 3 Años'!$C$6*'PyG 3 Años'!$C$8)),"") -> 8.37 | D9: =IFERROR(IF('PyG 3 Años'!$D$9="","",'PyG 3 Años'!$D$19/('PyG 3 Años'!$D$6*'PyG 3 Años'!$D$8)),"") -> 8.37 | E9: Sale del total de costes variables del P&L, no de una estimación aparte. Incluye los varios e imprevistos, que son un porcentaje de las ventas
A10: Margen de contribución por comensal | B10: =IFERROR(IF('PyG 3 Años'!$B$9="","",B8-B9),"") -> 11.63 | C10: =IFERROR(IF('PyG 3 Años'!$C$9="","",C8-C9),"") -> 11.63 | D10: =IFERROR(IF('PyG 3 Años'!$D$9="","",D8-D9),"") -> 11.63 | E10: Ticket menos coste variable unitario
A11: Días de apertura al año | B11: =IFERROR(IF('PyG 3 Años'!$B$9="","",'PyG 3 Años'!$B$8),"") -> 300 | C11: =IFERROR(IF('PyG 3 Años'!$C$9="","",'PyG 3 Años'!$C$8),"") -> 300 | D11: =IFERROR(IF('PyG 3 Años'!$D$9="","",'PyG 3 Años'!$D$8),"") -> 300 | E11: El mismo calendario que el P&L y que los escenarios
A12: Devolución de principal del año (cuota) | B12: =IFERROR(IF('PyG 3 Años'!$B$9="","",'Financiación'!$B$45),"") -> 0 | C12: =IFERROR(IF('PyG 3 Años'!$C$9="","",'Financiación'!$B$47),"") -> 18780.504 | D12: =IFERROR(IF('PyG 3 Años'!$D$9="","",'Financiación'!$B$49),"") -> 19907.335 | E12: El principal NO es gasto del P&L, pero sale de la caja. Sin él, el umbral de equilibrio se publica por debajo del real
A13: PUNTO DE EQUILIBRIO CONTABLE (incluye amortización)
A14: Comensales necesarios al año | B14: =IFERROR(IF('PyG 3 Años'!$B$9="","",IF(B10<=0,"",B6/B10)),"") -> 19335.113 | C14: =IFERROR(IF('PyG 3 Años'!$C$9="","",IF(C10<=0,"",C6/C10)),"") -> 19851.02 | D14: =IFERROR(IF('PyG 3 Años'!$D$9="","",IF(D10<=0,"",D6/D10)),"") -> 20270.037
A15: Comensales necesarios al día | B15: =IFERROR(IF('PyG 3 Años'!$B$9="","",B14/B11),"") -> 64.450375 | C15: =IFERROR(IF('PyG 3 Años'!$C$9="","",C14/C11),"") -> 66.170066 | D15: =IFERROR(IF('PyG 3 Años'!$D$9="","",D14/D11),"") -> 67.56679
A16: Ingresos necesarios al año | B16: =IFERROR(IF('PyG 3 Años'!$B$9="","",B14*B8),"") -> 386702.25 | C16: =IFERROR(IF('PyG 3 Años'!$C$9="","",C14*C8),"") -> 397020.4 | D16: =IFERROR(IF('PyG 3 Años'!$D$9="","",D14*D8),"") -> 405400.74
A17: PUNTO DE EQUILIBRIO DE CAJA (incluye la cuota del préstamo)
A18: Costes fijos de caja + principal del año | B18: =IFERROR(IF('PyG 3 Años'!$B$9="","",B6-'PyG 3 Años'!$B$35+B12),"") -> 215632.36 | C18: =IFERROR(IF('PyG 3 Años'!$C$9="","",C6-'PyG 3 Años'!$C$35+C12),"") -> 240412.86 | D18: =IFERROR(IF('PyG 3 Años'!$D$9="","",D6-'PyG 3 Años'!$D$35+D12),"") -> 246412.86 | E18: Los fijos del P&L sin la amortización (que no se paga) y CON la devolución de principal (que sí). Es el umbral que decide si la caja aguanta
A19: Comensales necesarios al año (caja) | B19: =IFERROR(IF('PyG 3 Años'!$B$9="","",IF(B10<=0,"",B18/B10)),"") -> 18541.046 | C19: =IFERROR(IF('PyG 3 Años'!$C$9="","",IF(C10<=0,"",C18/C10)),"") -> 20671.785 | D19: =IFERROR(IF('PyG 3 Años'!$D$9="","",IF(D10<=0,"",D18/D10)),"") -> 21187.693
A20: Comensales necesarios al día (caja) | B20: =IFERROR(IF('PyG 3 Años'!$B$9="","",B19/B11),"") -> 61.803485 | C20: =IFERROR(IF('PyG 3 Años'!$C$9="","",C19/C11),"") -> 68.905951 | D20: =IFERROR(IF('PyG 3 Años'!$D$9="","",D19/D11),"") -> 70.625642
A21: Ingresos necesarios al año (caja) | B21: =IFERROR(IF('PyG 3 Años'!$B$9="","",B19*B8),"") -> 370820.91 | C21: =IFERROR(IF('PyG 3 Años'!$C$9="","",C19*C8),"") -> 413435.71 | D21: =IFERROR(IF('PyG 3 Años'!$D$9="","",D19*D8),"") -> 423753.85
A22: CONTRASTE CON EL PLAN
A23: Comensales/día previstos en el plan | B23: =IFERROR(IF('PyG 3 Años'!$B$9="","",'PyG 3 Años'!$B$6),"") -> 79 | C23: =IFERROR(IF('PyG 3 Años'!$C$9="","",'PyG 3 Años'!$C$6),"") -> 83.74 | D23: =IFERROR(IF('PyG 3 Años'!$D$9="","",'PyG 3 Años'!$D$6),"") -> 87.0896
A24: Holgura sobre el equilibrio de CAJA (%) | B24: =IFERROR(IF('PyG 3 Años'!$B$9="","",B23/B20-1),"") -> 0.27824506 | C24: =IFERROR(IF('PyG 3 Años'!$C$9="","",C23/C20-1),"") -> 0.21527964 | D24: =IFERROR(IF('PyG 3 Años'!$D$9="","",D23/D20-1),"") -> 0.23311587 | E24: Cuánto superan tus ventas previstas a las del equilibrio de caja. La caída que aguantas antes de no poder pagar los costes fijos y la cuota es algo menor: con un 25 % de holgura, un 20 %. El mínimo exigible está en la hoja de Supuestos
A25: Rotaciones al día que da el local como máximo | B25: 3 | E25: Servicios completos por plaza y día que puedes hacer con comidas, cenas y un segundo turno de cena el viernes y el sábado (estancias de 45-60 minutos). Es el techo físico del local, no un objetivo
A26: Rotaciones al día que exige el equilibrio de caja | B26: =IFERROR(IF('PyG 3 Años'!$B$9="","",B20/'0. Supuestos'!$B$51),"") -> 1.7167635 | C26: =IFERROR(IF('PyG 3 Años'!$C$9="","",C20/'0. Supuestos'!$B$51),"") -> 1.9140542 | D26: =IFERROR(IF('PyG 3 Años'!$D$9="","",D20/'0. Supuestos'!$B$51),"") -> 1.9618234 | E26: Comensales de equilibrio entre las plazas que declara la hoja de Supuestos. Por encima del techo de arriba, el punto de equilibrio está fuera del alcance del local
A27: INTERPRETACIÓN
A28: =IFERROR("Con el ticket medio sin IVA de la fila de arriba necesitas "&TEXT(ROUNDUP(B15,0),"0")&" comensales al día durante los "&TEXT(B11,"0")&" días que abres para no perder dinero (equilibrio contable, con la amortización dentro), y "&TEXT(ROUNDUP(B20,0),"0")&" para que la caja aguante (equilibrio de caja: sin la amortización, que no se paga, y con la cuota del préstamo del año"&IF(B12=0,"; este año sólo intereses, porque el préstamo está en carencia","")&"). En las filas «Ingresos necesarios al año» tienes esas mismas cifras en euros.","") -> Con el ticket medio sin IVA de la fila de arriba necesitas 65 comensales al día durante los 300 días que abres para no perder dinero (equilibrio contable, con la amortización dentro), y 62 para que la caja aguante (equilibrio de caja: sin la amortización, que no se paga, y con la cuota del préstamo del año; este año sólo intereses, porque el préstamo está en carencia). En las filas «Ingresos necesarios al año» tienes esas mismas cifras en euros.
A30: SENSIBILIDAD DEL PUNTO DE EQUILIBRIO
A31: Comensales/día necesarios para cubrir costes según el ticket medio (columnas) y el coste variable por comensal (filas). En verde, los que están por debajo de los comensales que prevé el plan.
A33: Comensales/día necesarios: ticket medio sin IVA (columnas) × coste variable por comensal (filas) | B33: =IFERROR($B$8-2,"") -> 18 | C33: =IFERROR(IF($B$8="","",$B$8),"") -> 20 | D33: =IFERROR($B$8+2,"") -> 22 | E33: =IFERROR($B$8+4,"") -> 24
A34: =IFERROR($B$9*0.85,"") -> 7.1145 | B34: =IFERROR(IF($B$33-$A34<=0,"",$B$6/($B$33-$A34)/$B$11),"") -> 68.858377 | C34: =IFERROR(IF($C$33-$A34<=0,"",$B$6/($C$33-$A34)/$B$11),"") -> 58.170647 | D34: =IFERROR(IF($D$33-$A34<=0,"",$B$6/($D$33-$A34)/$B$11),"") -> 50.3549 | E34: =IFERROR(IF($E$33-$A34<=0,"",$B$6/($E$33-$A34)/$B$11),"") -> 44.390623
A35: =IFERROR($B$9*0.925,"") -> 7.74225 | B35: =IFERROR(IF($B$33-$A35<=0,"",$B$6/($B$33-$A35)/$B$11),"") -> 73.072347 | C35: =IFERROR(IF($C$33-$A35<=0,"",$B$6/($C$33-$A35)/$B$11),"") -> 61.149711 | D35: =IFERROR(IF($D$33-$A35<=0,"",$B$6/($D$33-$A35)/$B$11),"") -> 52.57196 | E35: =IFERROR(IF($E$33-$A35<=0,"",$B$6/($E$33-$A35)/$B$11),"") -> 46.10465
A36: =IFERROR($B$9*1.0,"") -> 8.37 | B36: =IFERROR(IF($B$33-$A36<=0,"",$B$6/($B$33-$A36)/$B$11),"") -> 77.835708 | C36: =IFERROR(IF($C$33-$A36<=0,"",$B$6/($C$33-$A36)/$B$11),"") -> 64.450375 | D36: =IFERROR(IF($D$33-$A36<=0,"",$B$6/($D$33-$A36)/$B$11),"") -> 54.99324 | E36: =IFERROR(IF($E$33-$A36<=0,"",$B$6/($E$33-$A36)/$B$11),"") -> 47.956357
A37: =IFERROR($B$9*1.075,"") -> 8.99775 | B37: =IFERROR(IF($B$33-$A37<=0,"",$B$6/($B$33-$A37)/$B$11),"") -> 83.263392 | C37: =IFERROR(IF($C$33-$A37<=0,"",$B$6/($C$33-$A37)/$B$11),"") -> 68.127689 | D37: =IFERROR(IF($D$33-$A37<=0,"",$B$6/($D$33-$A37)/$B$11),"") -> 57.64832 | E37: =IFERROR(IF($E$33-$A37<=0,"",$B$6/($E$33-$A37)/$B$11),"") -> 49.96303
A38: =IFERROR($B$9*1.15,"") -> 9.6255 | B38: =IFERROR(IF($B$33-$A38<=0,"",$B$6/($B$33-$A38)/$B$11),"") -> 89.50479 | C38: =IFERROR(IF($C$33-$A38<=0,"",$B$6/($C$33-$A38)/$B$11),"") -> 72.250023 | D38: =IFERROR(IF($D$33-$A38<=0,"",$B$6/($D$33-$A38)/$B$11),"") -> 60.57278 | E38: =IFERROR(IF($E$33-$A38<=0,"",$B$6/($E$33-$A38)/$B$11),"") -> 52.14497

Sheet Escenarios
A1: ANÁLISIS DE ESCENARIOS
A2: Pesimista / Realista / Optimista — Año 1
A4: Métrica | B4: Pesimista | C4: Realista | D4: Optimista | E4: Notas
A5: Comensales/día | B5: 68 | C5: =IFERROR(IF('PyG 3 Años'!$B$6="","",'PyG 3 Años'!$B$6),"") -> 79 | D5: 90
A6: Ticket medio sin IVA | B6: 19 | C6: =IFERROR(IF('PyG 3 Años'!$B$7="","",'PyG 3 Años'!$B$7),"") -> 20 | D6: 21
A7: Días de apertura al año | B7: 295 | C7: =IFERROR(IF('PyG 3 Años'!$B$8="","",'PyG 3 Años'!$B$8),"") -> 300 | D7: 305
A8: INGRESOS ANUALES (sin IVA) | B8: =IFERROR(IF(B5*B6*B7=0,"",B5*B6*B7),"") -> 381140 | C8: =IFERROR(IF(C5*C6*C7=0,"",C5*C6*C7),"") -> 474000 | D8: =IFERROR(IF(D5*D6*D7=0,"",D5*D6*D7),"") -> 576450
A9: Coste de mercancía — comida | B9: =IFERROR(IF(B8="","",B8*'0. Supuestos'!$B$11*'0. Supuestos'!$B$13),"") -> 93951.01 | C9: =IFERROR(IF(C8="","",C8*'0. Supuestos'!$B$11*'0. Supuestos'!$B$13),"") -> 116841 | D9: =IFERROR(IF(D8="","",D8*'0. Supuestos'!$B$11*'0. Supuestos'!$B$13),"") -> 142094.92
A10: Coste de mercancía — bebida | B10: =IFERROR(IF(B8="","",B8*'0. Supuestos'!$B$12*'0. Supuestos'!$B$14),"") -> 16007.88 | C10: =IFERROR(IF(C8="","",C8*'0. Supuestos'!$B$12*'0. Supuestos'!$B$14),"") -> 19908 | D10: =IFERROR(IF(D8="","",D8*'0. Supuestos'!$B$12*'0. Supuestos'!$B$14),"") -> 24210.9
A11: Consumibles y envases | B11: =IFERROR(IF(B8="","",B8*'0. Supuestos'!$B$15),"") -> 11434.2 | C11: =IFERROR(IF(C8="","",C8*'0. Supuestos'!$B$15),"") -> 14220 | D11: =IFERROR(IF(D8="","",D8*'0. Supuestos'!$B$15),"") -> 17293.5
A12: Comisiones de delivery | B12: =IFERROR(IF(B8="","",B8*'0. Supuestos'!$B$16*'0. Supuestos'!$B$17),"") -> 27442.08 | C12: =IFERROR(IF(C8="","",C8*'0. Supuestos'!$B$16*'0. Supuestos'!$B$17),"") -> 34128 | D12: =IFERROR(IF(D8="","",D8*'0. Supuestos'!$B$16*'0. Supuestos'!$B$17),"") -> 41504.4
A13: Comisiones de los medios de pago | B13: =IFERROR(IF(B8="","",B8*'0. Supuestos'!$B$18),"") -> 3049.12 | C13: =IFERROR(IF(C8="","",C8*'0. Supuestos'!$B$18),"") -> 3792 | D13: =IFERROR(IF(D8="","",D8*'0. Supuestos'!$B$18),"") -> 4611.6
A14: Varios e imprevistos | B14: =IFERROR(IF(B8="","",B8*'0. Supuestos'!$B$28),"") -> 7622.8 | C14: =IFERROR(IF(C8="","",C8*'0. Supuestos'!$B$28),"") -> 9480 | D14: =IFERROR(IF(D8="","",D8*'0. Supuestos'!$B$28),"") -> 11529
A15: TOTAL COSTES VARIABLES | B15: =IFERROR(IF(B8="","",SUM(B9:B14)),"") -> 159507.09 | C15: =IFERROR(IF(C8="","",SUM(C9:C14)),"") -> 198369 | D15: =IFERROR(IF(D8="","",SUM(D9:D14)),"") -> 241244.32
A16: MARGEN BRUTO | B16: =IFERROR(IF(B8="","",B8-B15),"") -> 221632.91 | C16: =IFERROR(IF(C8="","",C8-C15),"") -> 275631 | D16: =IFERROR(IF(D8="","",D8-D15),"") -> 335205.68
A17: COSTES FIJOS (los del P&L) | B17: =IFERROR(IF(B8="","",'PyG 3 Años'!$B$37),"") -> 224867.36 | C17: =IFERROR(IF(C8="","",'PyG 3 Años'!$B$37),"") -> 224867.36 | D17: =IFERROR(IF(D8="","",'PyG 3 Años'!$B$37),"") -> 224867.36 | E17: Los costes fijos no cambian con el escenario: por eso son fijos
A18: RESULTADO ANTES DE IMPUESTOS | B18: =IFERROR(IF(B8="","",B16-B17),"") -> -3234.45 | C18: =IFERROR(IF(C8="","",C16-C17),"") -> 50763.64 | D18: =IFERROR(IF(D8="","",D16-D17),"") -> 110338.32
A19: Impuesto de Sociedades | B19: =IFERROR(IF(B8="","",MAX(0,B18-'0. Supuestos'!$B$42)*'0. Supuestos'!$B$37),"") -> 0 | C19: =IFERROR(IF(C8="","",MAX(0,C18-'0. Supuestos'!$B$42)*'0. Supuestos'!$B$37),"") -> 7614.546 | D19: =IFERROR(IF(D8="","",MAX(0,D18-'0. Supuestos'!$B$42)*'0. Supuestos'!$B$37),"") -> 16550.747 | E19: Al tipo de entidad de nueva creación, compensando las bases negativas anteriores
A20: RESULTADO NETO | B20: =IFERROR(IF(B8="","",B18-B19),"") -> -3234.45 | C20: =IFERROR(IF(C8="","",C18-C19),"") -> 43149.094 | D20: =IFERROR(IF(D8="","",D18-D19),"") -> 93787.568
A21: Comensales/día para el equilibrio | B21: =IFERROR(IF(B8="","",IF(B6-B15/(B5*B7)<=0,"",B17/(B6-B15/(B5*B7))/B7)),"") -> 68.992373 | C21: =IFERROR(IF(C8="","",IF(C6-C15/(C5*C7)<=0,"",C17/(C6-C15/(C5*C7))/C7)),"") -> 64.450375 | D21: =IFERROR(IF(D8="","",IF(D6-D15/(D5*D7)<=0,"",D17/(D6-D15/(D5*D7))/D7)),"") -> 60.375059
A22: LO QUE CADA ESCENARIO EXIGE
A23: Coste de personal / Ventas | B23: =IFERROR(IF(B8="","",'PyG 3 Años'!$B$23/B8),"") -> 0.41906481 | C23: =IFERROR(IF(C8="","",'PyG 3 Años'!$B$23/C8),"") -> 0.336967 | D23: =IFERROR(IF(D8="","",'PyG 3 Años'!$B$23/D8),"") -> 0.2770793 | E23: La MISMA plantilla en los tres escenarios. Si en el pesimista se dispara, el ajuste hay que hacerlo en la hoja de Personal, no aquí
A24: Comensales al año por jornada equivalente | B24: =IFERROR(IF(B8="","",B5*B7/'Personal'!$C$12),"") -> 3749.5327 | C24: =IFERROR(IF(C8="","",C5*C7/'Personal'!$C$12),"") -> 4429.9065 | D24: =IFERROR(IF(D8="","",D5*D7/'Personal'!$C$12),"") -> 5130.8411 | E24: Comensales que tendría que sacar cada jornada completa del cuadro de Personal. En el optimista dice si hace falta contratar
A25: Saldo de caja al cierre del año 1 (estimado, el mismo método en los tres escenarios) | B25: =IFERROR(IF(B8="","",'Inversión Inicial'!$B$29+B20+'PyG 3 Años'!$B$35-'Financiación'!$B$45),"") -> 59908.64 | C25: =IFERROR(IF(C8="","",'Inversión Inicial'!$B$29+C20+'PyG 3 Años'!$B$35-'Financiación'!$B$45),"") -> 106292.18 | D25: =IFERROR(IF(D8="","",'Inversión Inicial'!$B$29+D20+'PyG 3 Años'!$B$35-'Financiación'!$B$45),"") -> 156930.66 | E25: Saldo ESTIMADO: fondo de maniobra más el resultado del año, devolviendo la amortización (que no se paga) y restando el principal del préstamo. No incluye el desfase de cobros y pagos ni la liquidación del IVA, así que las tres columnas se pueden comparar entre sí. En rojo, el escenario se queda sin caja
A26: Saldo real del mes 12 de la hoja de Tesorería (sólo realista) | C26: =IFERROR(IF(C8="","",'Tesorería 12 meses'!$M$22),"") -> 144399.19 | E26: El saldo REAL del caso base, con su desfase de cobros y pagos y su liquidación de IVA. Sólo existe para el escenario realista, que es el único con tesorería mensual propia: por eso no está en la fila de arriba, donde se compararía contra dos estimaciones
A28: La columna «Realista» lee sus tres datos de la hoja de Supuestos, así que reproduce EXACTAMENTE el año 1 del P&L. Los otros dos escenarios usan las mismas tasas de coste: lo único que cambia son los comensales, el ticket y los días. Los COSTES FIJOS sí son los mismos en los tres: los varios e imprevistos, que son un porcentaje de las ventas, van arriba con los variables y cada escenario carga los suyos.

Sheet Personal
A1: ESTRUCTURA DE PERSONAL Y COSTES
A2: =IFERROR("Convenio Hostelería — "&TEXT('0. Supuestos'!$B$21,"0")&" pagas + SS "&TEXT('0. Supuestos'!$B$20*100,"0")&" %","") -> Convenio Hostelería — 14 pagas + SS 33 %
A4: Puesto | B4: Personas | C4: Jornada | D4: Bruto mes (€, total del puesto) | E4: Seg. Social a cargo de la empresa (€) | F4: Coste mes (€, total del puesto) | G4: Coste año (€) | H4: Horas/semana por persona | I4: Horas/año del puesto | J4: Notas
A5: Titular — itamae y gerente: compra y corte del pescado, carta y gestión | B5: 1 | C5: 1 | D5: 2200 | E5: =IFERROR(IF(D5="","",D5*'0. Supuestos'!$B$20),"") -> 726 | F5: =IFERROR(IF(D5="","",D5+E5),"") -> 2926 | G5: =IFERROR(IF(D5="","",F5*MAX(12,'0. Supuestos'!$B$21)),"") -> 40964 | H5: =IFERROR(IF(D5="","",C5*$B$19),"") -> 40 | I5: =IFERROR(IF(D5="","",H5*B5*$B$20),"") -> 1840 | J5: El itamae (jefe de barra): compra, limpia y corta el pescado, lleva la barra en el servicio fuerte, firma la carta y el APPCC del anisakis y gestiona. Como administrador de la SL cotiza en el régimen de autónomos: el libro le imputa el 33 % de Seguridad Social sobre 14 pagas como si fuera nómina, que es el lado prudente. Confirma con tu gestoría la cuota real y si te aplica la reducida de inicio
A6: Sushiman o sushiwoman: shari, rolls y combinados | B6: 1 | C6: 1 | D6: 1650 | E6: =IFERROR(IF(D6="","",D6*'0. Supuestos'!$B$20),"") -> 544.5 | F6: =IFERROR(IF(D6="","",D6+E6),"") -> 2194.5 | G6: =IFERROR(IF(D6="","",F6*MAX(12,'0. Supuestos'!$B$21)),"") -> 30723 | H6: =IFERROR(IF(D6="","",C6*$B$19),"") -> 40 | I6: =IFERROR(IF(D6="","",H6*B6*$B$20),"") -> 1840 | J6: El shari de cada tanda, los rolls, los combinados de las plataformas y la barra cuando el itamae no está. Es inversión, no gasto: si sólo el titular sabe cortar y montar, una baja cierra la barra
A7: Cocinero/a de cocina caliente y arroz | B7: 1 | C7: 1 | D7: 1400 | E7: =IFERROR(IF(D7="","",D7*'0. Supuestos'!$B$20),"") -> 462 | F7: =IFERROR(IF(D7="","",D7+E7),"") -> 1862 | G7: =IFERROR(IF(D7="","",F7*MAX(12,'0. Supuestos'!$B$21)),"") -> 26068 | H7: =IFERROR(IF(D7="","",C7*$B$19),"") -> 40 | I7: =IFERROR(IF(D7="","",H7*B7*$B$20),"") -> 1840 | J7: Las arroceras, las gyozas, la tempura, la sopa de miso y el office
A8: Encargado/a de sala y pedidos | B8: 1 | C8: 1 | D8: 1500 | E8: =IFERROR(IF(D8="","",D8*'0. Supuestos'!$B$20),"") -> 495 | F8: =IFERROR(IF(D8="","",D8+E8),"") -> 1995 | G8: =IFERROR(IF(D8="","",F8*MAX(12,'0. Supuestos'!$B$21)),"") -> 27930 | H8: =IFERROR(IF(D8="","",C8*$B$19),"") -> 40 | I8: =IFERROR(IF(D8="","",H8*B8*$B$20),"") -> 1840 | J8: Todo el año: sala, caja, los pedidos para llevar, las tablets de las plataformas y la información de alérgenos
A9: Camarero/a de cenas y fines de semana | B9: 1 | C9: 0.75 | D9: 1013 | E9: =IFERROR(IF(D9="","",D9*'0. Supuestos'!$B$20),"") -> 334.29 | F9: =IFERROR(IF(D9="","",D9+E9),"") -> 1347.29 | G9: =IFERROR(IF(D9="","",F9*MAX(12,'0. Supuestos'!$B$21)),"") -> 18862.06 | H9: =IFERROR(IF(D9="","",C9*$B$19),"") -> 30 | I9: =IFERROR(IF(D9="","",H9*B9*$B$20),"") -> 1380 | J9: 30 horas a la semana: las cenas y el fin de semana, cuando la sala se llena
A10: Refuerzo de viernes a domingo: sala y empaquetado de pedidos | B10: 1 | C10: 0.5 | D10: 675 | E10: =IFERROR(IF(D10="","",D10*'0. Supuestos'!$B$20),"") -> 222.75 | F10: =IFERROR(IF(D10="","",D10+E10),"") -> 897.75 | G10: =IFERROR(IF(D10="","",F10*MAX(12,'0. Supuestos'!$B$21)),"") -> 12568.5 | H10: =IFERROR(IF(D10="","",C10*$B$19),"") -> 20 | I10: =IFERROR(IF(D10="","",H10*B10*$B$20),"") -> 920 | J10: Sala y empaquetado de los pedidos de las noches fuertes. Este plan NO tiene reparto propio: si lo pones, el repartidor va con contrato laboral del convenio de hostelería, nunca como autónomo
A11: Suplencias de vacaciones y descansos | B11: 1 | C11: 0.1 | D11: 140 | E11: =IFERROR(IF(D11="","",D11*'0. Supuestos'!$B$20),"") -> 46.2 | F11: =IFERROR(IF(D11="","",D11+E11),"") -> 186.2 | G11: =IFERROR(IF(D11="","",F11*MAX(12,'0. Supuestos'!$B$21)),"") -> 2606.8 | H11: =IFERROR(IF(D11="","",C11*$B$19),"") -> 4 | I11: =IFERROR(IF(D11="","",H11*B11*$B$20),"") -> 184 | J11: Cobertura de los 30 días de vacaciones (art. 38 ET) y del descanso semanal del equipo de todo el año
A12: TOTAL PLANTILLA | B12: =IFERROR(IF(COUNT(D5:D11)=0,"",SUM(B5:B11)),"") -> 7 | C12: =IFERROR(IF(COUNT(D5:D11)=0,"",SUM(C5:C11)),"") -> 5.35 | D12: =IFERROR(IF(COUNT(D5:D11)=0,"",SUM(D5:D11)),"") -> 8578 | E12: =IFERROR(IF(COUNT(D5:D11)=0,"",SUM(E5:E11)),"") -> 2830.74 | F12: =IFERROR(IF(COUNT(D5:D11)=0,"",SUM(F5:F11)),"") -> 11408.74 | G12: =IFERROR(IF(COUNT(D5:D11)=0,"",SUM(G5:G11)),"") -> 159722.36 | I12: =IFERROR(IF(COUNT(D5:D11)=0,"",SUM(I5:I11)),"") -> 9844
A13: CRECIMIENTO DE LA PLANTILLA (coste escalonado)
A14: Coste anual de las incorporaciones del año 2 (€) | B14: 6000 | J14: Coste ANUAL completo (bruto + Seguridad Social × pagas) de lo que se contrate ese año. El P&L lo suma al coste del año anterior: la plantilla no crece con un porcentaje, crece con personas
A15: Coste anual de las incorporaciones del año 3 (€) | B15: 6000 | J15: Coste ANUAL completo (bruto + Seguridad Social × pagas) de lo que se contrate ese año. El P&L lo suma al coste del año anterior: la plantilla no crece con un porcentaje, crece con personas
A16: Coste de personal del año 2 | B16: =IFERROR(IF(G12="","",G12*(1+'0. Supuestos'!$B$48)+B14),"") -> 165722.36
A17: Coste de personal del año 3 | B17: =IFERROR(IF(B16="","",B16*(1+'0. Supuestos'!$B$48)+B15),"") -> 171722.36
A18: COBERTURA POR HORAS DE SERVICIO
A19: Jornada completa del convenio (horas/semana) | B19: 40 | J19: Art. 34.1 del Estatuto de los Trabajadores; tu convenio provincial puede fijar menos
A20: Semanas trabajadas al año por persona | B20: 46 | J20: 46 semanas: 52 menos las vacaciones (30 días naturales, art. 38 ET), los festivos y las ausencias medias
A21: Horas de servicio al día que hay que cubrir | B21: 6.5 | J21: Horas con el local abierto al público, sumando las comidas (13:00-16:00) y las cenas (20:00-23:30). La tarde de cierre entre los dos servicios no se cuenta
A22: Personas necesarias a la vez en cada franja | B22: 3.5 | J22: Presencia media a la vez entre la barra, la cocina caliente, la sala y los pedidos. El viernes y el sábado por la noche hacen falta seis (dos en la barra, uno en caliente, dos en sala y uno empaquetando): entran el refuerzo y el camarero de cenas (el cuadrante anual no lo ve: ponlo en el turno)
A23: Horas de producción al día ANTES de abrir | B23: 3 | J23: El shari del día, el corte y la limpieza del pescado, las salsas y la mise en place antes de abrir
A24: Personas en el turno de producción | B24: 2 | J24: El itamae con el sushiman o el cocinero. El cierre, la limpieza y las compras quedan fuera de este cuadrante: son el margen entre las horas contratadas y las necesarias
A25: Horas de servicio a cubrir al año | B25: =IFERROR(IF(OR(B21="",B22="",'0. Supuestos'!$B$6=""),"",B21*B22*'0. Supuestos'!$B$6+B23*B24*'0. Supuestos'!$B$6),"") -> 8625
A26: Horas contratadas al año | B26: =IFERROR(IF(I12="","",I12),"") -> 9844
A27: Cobertura (contratadas / necesarias) | B27: =IFERROR(B26/B25,"") -> 1.1413333 | J27: Por debajo del 100 % la plantilla no llega a cubrir el horario que declara el plan: o se contrata más o se recorta el horario
A29: Las columnas «Bruto mes», «Seg. Social», «Coste mes» y «Coste año» son TOTALES de la fila: en un puesto con dos personas incluyen a las dos. «Jornada» es el porcentaje sobre la jornada completa del convenio y sirve para comparar el salario con el suelo legal en proporción. El tipo de Seguridad Social y el número de pagas están en la hoja «0. Supuestos».
A30: El suelo salarial es el MAYOR entre el SMI y el salario de convenio, los dos en la hoja «0. Supuestos»; las jornadas parciales lo llevan en proporción. El convenio aplicable es el PROVINCIAL de hostelería: no existe una tabla salarial estatal única, así que la celda del convenio se entrega vacía para que copies la de tu provincia.

Sheet Instrucciones
A1: INSTRUCCIONES DE USO — Plan financiero Sushi Bar
A3: CÓMO SE USA ESTE LIBRO
A4: Este plan financiero es un MODELO: sólo se teclea en las celdas VERDES y el resto se recalcula solo.
A5: 1. «0. Supuestos» es la hoja de mando: comensales, ticket sin IVA, días de apertura, mezcla de comida y bebida, coste de mercancía, alquiler, financiación e impuestos.
A6: 2. Las partidas de la inversión, los costes fijos y la plantilla se teclean en su propia hoja, también en verde. Ningún número se escribe dos veces.
A7: 3. En «Punto Equilibrio» sólo se teclea el techo de rotaciones que da tu local; todo lo demás se deriva de lo anterior. En las otras tres hojas también hay celdas verdes que puedes tocar: el escenario pesimista y el optimista en «Escenarios», la estacionalidad y la rampa de arranque en «Tesorería 12 meses», y las cuatro fuentes alternativas de financiación en «Financiación». Todo lo demás se calcula.
A8: 4. Todas las cifras van SIN IVA. Para pasar un PVP a precio sin IVA, divide por el tipo que le corresponda: entre 1,10 en sala (comida y bebida, alcohol incluido: art. 91.Uno.2.2.º de la Ley 37/1992 del IVA) y, cuando se venden para llevar, los alimentos —el sushi y el poke incluidos—, que son productos alimenticios al tipo reducido por el art. 91.Uno.1.1.º; y entre 1,21 el tipo general, que en hostelería sólo alcanza a lo que sale del local como entrega de bienes excluida del reducido: el alcohol y los refrescos o los zumos con azúcares o edulcorantes añadidos para llevar o a domicilio (la comida para llevar sigue al 10 %); el libro lo aplica a la parte de la bebida que declara la columna H de su línea en el P&L. El tipo de cada línea de venta está en la columna «Tipo de IVA de la línea» del P&L y de ahí salen los cobros, el IVA repercutido y el PVP equivalente. El IVA de la inversión se adelanta y se recupera con el modelo 303.
A9: 5. Si cambias la plantilla, el P&L la lee sola: el coste de personal sale de la hoja «Personal», no de una estimación aparte.
A10: 6. La hoja «Tesorería 12 meses» responde la pregunta que decide una operación bancaria: en qué mes se agota la caja. Su Mes 1 es ENERO, en el orden del calendario: la rampa del arranque va de enero a abril y agosto, con el cierre de vacaciones, es el mes más flojo; por eso el fondo de maniobra cuenta. Si abres en otro mes, gira la fila de estacionalidad. El saldo mínimo del año nunca puede salir en rojo.
A11: 7. La hoja «Financiación» cuadra lo que hace falta con lo que se aporta y monta el cuadro de amortización del préstamo. Si la diferencia sale en rojo, el plan no está financiado.
A12: 8. El plan de negocio en Word de este pack cita las cifras de este Excel: si cambias una celda verde, el Excel manda. La calculadora del pescado, el arroz y el escandallo del pack va aparte: mide el rendimiento del salmón, el shari que sale de cada kilo de arroz y ESCANDALLA cada pieza en cada canal. No copies el food cost de un nigiri en la hoja de Supuestos: la celda «Coste de mercancía sobre las ventas de COMIDA» es la media ponderada de TODA la carta más la merma de pescado, el shari tirado y las comidas del personal, y por eso sale más alta que el escandallo teórico. Con los escandallos de tu carta, comprueba que esa media cuadra.
A14: RATIOS QUE AUDITA EL LIBRO
A15: Los umbrales viven en la columna «Umbral» del bloque RATIOS CLAVE del P&L: cámbialos ahí y el semáforo cambia con ellos.
A17: Ratio | B17: Valor del año 1 | C17: Umbral | D17: Estado
A18: Coste de mercancía / Ventas | B18: =IFERROR(IF('PyG 3 Años'!$B$52="","",'PyG 3 Años'!$B$52),"") -> 0.2885 | C18: =IFERROR(IF('PyG 3 Años'!$E$52="","",'PyG 3 Años'!$E$52),"") -> 0.31 | D18: =IFERROR(IF(OR(B18="",C18=""),"",IF(B18<=C18,"CUMPLE","REVISAR")),"") -> CUMPLE
A19: Coste de personal / Ventas | B19: =IFERROR(IF('PyG 3 Años'!$B$53="","",'PyG 3 Años'!$B$53),"") -> 0.336967 | C19: =IFERROR(IF('PyG 3 Años'!$E$53="","",'PyG 3 Años'!$E$53),"") -> 0.38 | D19: =IFERROR(IF(OR(B19="",C19=""),"",IF(B19<=C19,"CUMPLE","REVISAR")),"") -> CUMPLE
A20: Alquiler / Ventas | B20: =IFERROR(IF('PyG 3 Años'!$B$54="","",'PyG 3 Años'!$B$54),"") -> 0.040506329 | C20: =IFERROR(IF('PyG 3 Años'!$E$54="","",'PyG 3 Años'!$E$54),"") -> 0.1 | D20: =IFERROR(IF(OR(B20="",C20=""),"",IF(B20<=C20,"CUMPLE","REVISAR")),"") -> CUMPLE
A21: Resultado neto / Ventas | B21: =IFERROR(IF('PyG 3 Años'!$B$55="","",'PyG 3 Años'!$B$55),"") -> 0.091031844 | C21: =IFERROR(IF('PyG 3 Años'!$E$55="","",'PyG 3 Años'!$E$55),"") -> 0.05 | D21: =IFERROR(IF(OR(B21="",C21=""),"",IF(B21>=C21,"CUMPLE","REVISAR")),"") -> CUMPLE
A22: Margen bruto / Ventas | B22: =IFERROR(IF('PyG 3 Años'!$B$50="","",'PyG 3 Años'!$B$50),"") -> 0.5815 | C22: =IFERROR(IF('PyG 3 Años'!$E$50="","",'PyG 3 Años'!$E$50),"") -> 0.52 | D22: =IFERROR(IF(OR(B22="",C22=""),"",IF(B22>=C22,"CUMPLE","REVISAR")),"") -> CUMPLE
A24: CIFRAS DE ESTE PLAN
A25: Inversión total (suma de los bloques) | B25: =IFERROR(IF('Inversión Inicial'!$B$30="","",'Inversión Inicial'!$B$30),"") -> 163658.09
A26: Necesidad total de caja al arranque | B26: =IFERROR(IF('Inversión Inicial'!$B$33="","",'Inversión Inicial'!$B$33),"") -> 185403.59
A27: Fondo de maniobra dotado | B27: =IFERROR(IF('Inversión Inicial'!$B$29="","",'Inversión Inicial'!$B$29),"") -> 53908.09
A28: Facturación prevista del año 1 | B28: =IFERROR(IF('PyG 3 Años'!$B$9="","",'PyG 3 Años'!$B$9),"") -> 474000
A29: Resultado neto del año 1 | B29: =IFERROR(IF('PyG 3 Años'!$B$47="","",'PyG 3 Años'!$B$47),"") -> 43149.094
A30: Comensales/día para el punto de equilibrio CONTABLE (con la amortización dentro) | B30: =IFERROR(IF('Punto Equilibrio'!$B$15="","",'Punto Equilibrio'!$B$15),"") -> 64.450375
A31: Payback del proyecto (años), antes de la deuda | B31: =IFERROR(IF('Tesorería 12 meses'!$B$31="","",'Tesorería 12 meses'!$B$31),"") -> 2.5
A33: DATOS DE REFERENCIA DEL SECTOR
A34: Referencia | B34: Valor | C34: Fuente | D34: Nota
A35: Mes 1 del plan | B35: Enero | C35: Decisión del plan | D35: En el orden del calendario: la rampa cae sobre enero-abril y agosto, con el cierre de vacaciones, es el mes más flojo. Si abres en otro mes, gira la fila de estacionalidad de la Tesorería
A36: Sushi en el reparto a domicilio | B36: El maki, segundo plato más pedido | C36: Gastrómetro de Just Eat 2025, publicado en prensa en diciembre de 2025 | D36: Sólo lo supera la hamburguesa. Por eso el caso cuenta un 24 % de las ventas por plataforma
A37: Nigiri y combinado en carta | B37: 2,50-2,60 € la pieza de nigiri · 24,90-30,60 € el combinado de 24 piezas | C37: Cartas de cadenas y restaurantes de sushi leídas en octubre de 2026 | D37: El caso: nigiri de salmón a 2,60 € la pieza (5,20 € las dos), combinado de 24 piezas a 29,00 € y menú del día de mediodía a 14,90 €, todo con IVA
A38: Coste del nigiri de salmón | B38: Un 11 % de su precio sin IVA | C38: Estimación del kit con los gramajes de la calculadora del pack (editables) | D38: 15 g de neta de salmón entero de acuicultura a 9,50 €/kg con un 55 % de lomo y un 15 % de recorte reaprovechado, y 20 g de shari. El 29 % del plan es el consumo real de TODA la carta, con la merma
A39: Rendimiento del salmón entero | B39: Un 50-60 % de lomo limpio | C39: Guías de gestión de restaurantes (fuente secundaria) | D39: Mide el tuyo con 3 salmones y llévalo a la hoja «Pescado» de la calculadora del pack
A40: Arroz para sushi | B40: 1,81-1,85 € el kg sin IVA | C40: Catálogo de Makro, sacos de 5 kg, octubre de 2026 | D40: Un kilo de arroz crudo da unos 2,4 kg de shari, unos 120 nigiris con 20 g (calculadora del pack). El arroz es barato: el coste está en el pescado y en la mano del itamae
A41: Comisión de la plataforma con su reparto | B41: 13-35 % más IVA | C41: Guías del sector, 2025-2026: compruébalo en tu contrato | D41: El plan básico de Uber Eats ronda el 30 %. Lo que se recoge en el local no paga comisión
A42: IVA del sushi | B42: 10 % en la venta · 4 % el arroz en la compra | C42: Ley 37/1992, art. 91.Uno.1.1.º, 91.Uno.2.2.º y 91.Dos.1.1.º | D42: La comida, al 10 % en sala, para llevar y a domicilio. La cerveza, el sake, el vino y los refrescos con azúcares o edulcorantes añadidos que salen del local, al 21 %. El arroz, la verdura, el huevo y el queso se compran al 4 %
A43: Pescado para consumir crudo (anisakis) | B43: −20 °C 24 h o −35 °C 15 h en la totalidad del producto | C43: Real Decreto 1021/2022, art. 8 | D43: O que llegue tratado de una etapa anterior con su documento, o de acuicultura libre de anisakis acreditada por escrito. Y hay que informar al cliente en la carta o en un cartel (art. 8.2)
A44: Shari a temperatura ambiente | B44: Sólo con una temperatura justificada ante sanidad | C44: Real Decreto 1086/2020, art. 30.5 | D44: La comida preparada se refrigera, se mantiene a 63 °C o más o se sirve cuanto antes (RD 1086/2020, art. 30.2). El shari a temperatura ambiente sólo si tu APPCC lo justifica con evidencia científica y lo demuestras a sanidad: pH de cada tanda y tiempo máximo. Si no, refrigerado
A45: Salario mínimo interprofesional 2026 | B45: 1.221 € al mes en 14 pagas | C45: Real Decreto 126/2026 | D45: A prorrata en jornada parcial
A46: Convenio colectivo aplicable | B46: Provincial de hostelería | C46: VI Acuerdo Laboral de ámbito Estatal para el sector de Hostelería, art. 4 | D46: No nombra el sushi bar: entra como restaurante. Copia tu tabla salarial en la celda de Supuestos
A48: Para editar una celda que no esté en verde: Revisar → Desproteger hoja (no tiene contraseña).
A49: Más plantillas y kits del catálogo en aichef.pro/productos-digitales
A50: Diseñado por John Guerrero — chef y consultor gastronómico desde 2010, en cocina desde los 17 años · johnguerrero.es
A51: Versión 1.0 · noviembre 2026 · aichef.pro/plan-negocio-sushi-bar · info@aichef.pro

Sheet Tesorería 12 meses
A1: PREVISIÓN DE TESORERÍA — AÑO 1
A2: El P&L dice si el negocio gana dinero; esta hoja dice si le queda caja para llegar a fin de mes. Es la primera que mira un banco.
A4: Concepto | B4: Mes 1 (€) | C4: Mes 2 (€) | D4: Mes 3 (€) | E4: Mes 4 (€) | F4: Mes 5 (€) | G4: Mes 6 (€) | H4: Mes 7 (€) | I4: Mes 8 (€) | J4: Mes 9 (€) | K4: Mes 10 (€) | L4: Mes 11 (€) | M4: Mes 12 (€) | N4: Año (€)
A5: Estacionalidad del mes (suma 100 %) | B5: 0.082 | C5: 0.086 | D5: 0.086 | E5: 0.084 | F5: 0.086 | G5: 0.084 | H5: 0.08 | I5: 0.066 | J5: 0.082 | K5: 0.086 | L5: 0.086 | M5: 0.092 | N5: =IFERROR(IF('PyG 3 Años'!$B$9="","",SUM(B5:M5)),"") -> 1 | O5: Mes 1 = ENERO, en el orden del calendario: diciembre es el pico (bandejas de Nochebuena y Nochevieja), febrero sube con San Valentín y agosto es el mes más flojo (cierre de 10 días y ciudad vacía). En la costa, agosto sube. Si abres en otro mes, gira la fila. Tiene que sumar 100 %
A6: Rampa de arranque (% de la actividad de crucero) | B6: =IFERROR(IF('PyG 3 Años'!$B$9="","",MIN(1,'0. Supuestos'!$B$52+(1-'0. Supuestos'!$B$52)*0/MAX(1,'0. Supuestos'!$B$53-1))),"") -> 0.75 | C6: =IFERROR(IF('PyG 3 Años'!$B$9="","",MIN(1,'0. Supuestos'!$B$52+(1-'0. Supuestos'!$B$52)*1/MAX(1,'0. Supuestos'!$B$53-1))),"") -> 0.83333333 | D6: =IFERROR(IF('PyG 3 Años'!$B$9="","",MIN(1,'0. Supuestos'!$B$52+(1-'0. Supuestos'!$B$52)*2/MAX(1,'0. Supuestos'!$B$53-1))),"") -> 0.91666667 | E6: =IFERROR(IF('PyG 3 Años'!$B$9="","",MIN(1,'0. Supuestos'!$B$52+(1-'0. Supuestos'!$B$52)*3/MAX(1,'0. Supuestos'!$B$53-1))),"") -> 1 | F6: =IFERROR(IF('PyG 3 Años'!$B$9="","",MIN(1,'0. Supuestos'!$B$52+(1-'0. Supuestos'!$B$52)*4/MAX(1,'0. Supuestos'!$B$53-1))),"") -> 1 | G6: =IFERROR(IF('PyG 3 Años'!$B$9="","",MIN(1,'0. Supuestos'!$B$52+(1-'0. Supuestos'!$B$52)*5/MAX(1,'0. Supuestos'!$B$53-1))),"") -> 1 | H6: =IFERROR(IF('PyG 3 Años'!$B$9="","",MIN(1,'0. Supuestos'!$B$52+(1-'0. Supuestos'!$B$52)*6/MAX(1,'0. Supuestos'!$B$53-1))),"") -> 1 | I6: =IFERROR(IF('PyG 3 Años'!$B$9="","",MIN(1,'0. Supuestos'!$B$52+(1-'0. Supuestos'!$B$52)*7/MAX(1,'0. Supuestos'!$B$53-1))),"") -> 1 | J6: =IFERROR(IF('PyG 3 Años'!$B$9="","",MIN(1,'0. Supuestos'!$B$52+(1-'0. Supuestos'!$B$52)*8/MAX(1,'0. Supuestos'!$B$53-1))),"") -> 1 | K6: =IFERROR(IF('PyG 3 Años'!$B$9="","",MIN(1,'0. Supuestos'!$B$52+(1-'0. Supuestos'!$B$52)*9/MAX(1,'0. Supuestos'!$B$53-1))),"") -> 1 | L6: =IFERROR(IF('PyG 3 Años'!$B$9="","",MIN(1,'0. Supuestos'!$B$52+(1-'0. Supuestos'!$B$52)*10/MAX(1,'0. Supuestos'!$B$53-1))),"") -> 1 | M6: =IFERROR(IF('PyG 3 Años'!$B$9="","",MIN(1,'0. Supuestos'!$B$52+(1-'0. Supuestos'!$B$52)*11/MAX(1,'0. Supuestos'!$B$53-1))),"") -> 1 | O6: Sube en línea recta desde el porcentaje del mes 1 hasta el 100 % en los meses que digas en Supuestos. Con el mes 1 al 100 % la rampa desaparece
A7: Reparto de la actividad por mes (calculado) | B7: =IFERROR(IF('PyG 3 Años'!$B$9="","",B5*B6/SUMPRODUCT($B$5:$M$5,$B$6:$M$6)),"") -> 0.064196242 | C7: =IFERROR(IF('PyG 3 Años'!$B$9="","",C5*C6/SUMPRODUCT($B$5:$M$5,$B$6:$M$6)),"") -> 0.074808629 | D7: =IFERROR(IF('PyG 3 Años'!$B$9="","",D5*D6/SUMPRODUCT($B$5:$M$5,$B$6:$M$6)),"") -> 0.082289492 | E7: =IFERROR(IF('PyG 3 Años'!$B$9="","",E5*E6/SUMPRODUCT($B$5:$M$5,$B$6:$M$6)),"") -> 0.087682672 | F7: =IFERROR(IF('PyG 3 Años'!$B$9="","",F5*F6/SUMPRODUCT($B$5:$M$5,$B$6:$M$6)),"") -> 0.089770355 | G7: =IFERROR(IF('PyG 3 Años'!$B$9="","",G5*G6/SUMPRODUCT($B$5:$M$5,$B$6:$M$6)),"") -> 0.087682672 | H7: =IFERROR(IF('PyG 3 Años'!$B$9="","",H5*H6/SUMPRODUCT($B$5:$M$5,$B$6:$M$6)),"") -> 0.083507307 | I7: =IFERROR(IF('PyG 3 Años'!$B$9="","",I5*I6/SUMPRODUCT($B$5:$M$5,$B$6:$M$6)),"") -> 0.068893528 | ... M7: =IFERROR(IF('PyG 3 Años'!$B$9="","",M5*M6/SUMPRODUCT($B$5:$M$5,$B$6:$M$6)),"") -> 0.096033403 | N7: =IFERROR(IF('PyG 3 Años'!$B$9="","",SUM(B7:M7)),"") -> 1 | O7: Estacionalidad × rampa, normalizado a 100 %: el AÑO factura lo que dice el P&L, pero repartido como lo reparte un local que acaba de abrir
A8: COBROS
A9: Ventas cobradas (con IVA repercutido) | B9: =IFERROR(IF('PyG 3 Años'!$B$9="","",('PyG 3 Años'!$B$9+'PyG 3 Años'!$B$9*SUMPRODUCT('PyG 3 Años'!$E$10:$E$11,'PyG 3 Años'!$G$10:$G$11))*B7*(1-MIN(30,'0. Supuestos'!$B$58)/30)),"") -> 31273.262 | C9: =IFERROR(IF('PyG 3 Años'!$B$9="","",('PyG 3 Años'!$B$9+'PyG 3 Años'!$B$9*SUMPRODUCT('PyG 3 Años'!$E$10:$E$11,'PyG 3 Años'!$G$10:$G$11))*(C7*(1-MIN(30,'0. Supuestos'!$B$58)/30)+B7*MIN(30,'0. Supuestos'!$B$58)/30)),"") -> 38676.901 | D9: =IFERROR(IF('PyG 3 Años'!$B$9="","",('PyG 3 Años'!$B$9+'PyG 3 Años'!$B$9*SUMPRODUCT('PyG 3 Años'!$E$10:$E$11,'PyG 3 Años'!$G$10:$G$11))*(D7*(1-MIN(30,'0. Supuestos'!$B$58)/30)+C7*MIN(30,'0. Supuestos'!$B$58)/30)),"") -> 42690.484 | E9: =IFERROR(IF('PyG 3 Años'!$B$9="","",('PyG 3 Años'!$B$9+'PyG 3 Años'!$B$9*SUMPRODUCT('PyG 3 Años'!$E$10:$E$11,'PyG 3 Años'!$G$10:$G$11))*(E7*(1-MIN(30,'0. Supuestos'!$B$58)/30)+D7*MIN(30,'0. Supuestos'!$B$58)/30)),"") -> 45578.085 | F9: =IFERROR(IF('PyG 3 Años'!$B$9="","",('PyG 3 Años'!$B$9+'PyG 3 Años'!$B$9*SUMPRODUCT('PyG 3 Años'!$E$10:$E$11,'PyG 3 Años'!$G$10:$G$11))*(F7*(1-MIN(30,'0. Supuestos'!$B$58)/30)+E7*MIN(30,'0. Supuestos'!$B$58)/30)),"") -> 46782.766 | G9: =IFERROR(IF('PyG 3 Años'!$B$9="","",('PyG 3 Años'!$B$9+'PyG 3 Años'!$B$9*SUMPRODUCT('PyG 3 Años'!$E$10:$E$11,'PyG 3 Años'!$G$10:$G$11))*(G7*(1-MIN(30,'0. Supuestos'!$B$58)/30)+F7*MIN(30,'0. Supuestos'!$B$58)/30)),"") -> 45838.393 | H9: =IFERROR(IF('PyG 3 Años'!$B$9="","",('PyG 3 Años'!$B$9+'PyG 3 Años'!$B$9*SUMPRODUCT('PyG 3 Años'!$E$10:$E$11,'PyG 3 Años'!$G$10:$G$11))*(H7*(1-MIN(30,'0. Supuestos'!$B$58)/30)+G7*MIN(30,'0. Supuestos'!$B$58)/30)),"") -> 43731.716 | I9: =IFERROR(IF('PyG 3 Años'!$B$9="","",('PyG 3 Años'!$B$9+'PyG 3 Años'!$B$9*SUMPRODUCT('PyG 3 Años'!$E$10:$E$11,'PyG 3 Años'!$G$10:$G$11))*(I7*(1-MIN(30,'0. Supuestos'!$B$58)/30)+H7*MIN(30,'0. Supuestos'!$B$58)/30)),"") -> 36467.311 | J9: =IFERROR(IF('PyG 3 Años'!$B$9="","",('PyG 3 Años'!$B$9+'PyG 3 Años'!$B$9*SUMPRODUCT('PyG 3 Años'!$E$10:$E$11,'PyG 3 Años'!$G$10:$G$11))*(J7*(1-MIN(30,'0. Supuestos'!$B$58)/30)+I7*MIN(30,'0. Supuestos'!$B$58)/30)),"") -> 44094.936 | ... M9: =IFERROR(IF('PyG 3 Años'!$B$9="","",('PyG 3 Años'!$B$9+'PyG 3 Años'!$B$9*SUMPRODUCT('PyG 3 Años'!$E$10:$E$11,'PyG 3 Años'!$G$10:$G$11))*(M7*(1-MIN(30,'0. Supuestos'!$B$58)/30)+L7*MIN(30,'0. Supuestos'!$B$58)/30)),"") -> 49906.46 | N9: =IFERROR(IF('PyG 3 Años'!$B$9="","",SUM(B9:M9)),"") -> 518605.84 | O9: Ventas del mes con el IVA repercutido, corregidas por los días medios de cobro de la hoja de Supuestos
A10: PAGOS
A11: Compras y costes variables (IVA incluido) | B11: =IFERROR(IF('PyG 3 Años'!$B$9="","",-('PyG 3 Años'!$B$13*(1+'PyG 3 Años'!$G$13)+'PyG 3 Años'!$B$14*(1+'PyG 3 Años'!$G$14)+'PyG 3 Años'!$B$15*(1+'PyG 3 Años'!$G$15)+'PyG 3 Años'!$B$16*(1+'PyG 3 Años'!$G$16)+'PyG 3 Años'!$B$17*(1+'PyG 3 Años'!$G$17)+'PyG 3 Años'!$B$18*(1+'PyG 3 Años'!$G$18))*B7*(1-MIN(30,'0. Supuestos'!$B$59)/30)),"") -> 0 | C11: =IFERROR(IF('PyG 3 Años'!$B$9="","",-('PyG 3 Años'!$B$13*(1+'PyG 3 Años'!$G$13)+'PyG 3 Años'!$B$14*(1+'PyG 3 Años'!$G$14)+'PyG 3 Años'!$B$15*(1+'PyG 3 Años'!$G$15)+'PyG 3 Años'!$B$16*(1+'PyG 3 Años'!$G$16)+'PyG 3 Años'!$B$17*(1+'PyG 3 Años'!$G$17)+'PyG 3 Años'!$B$18*(1+'PyG 3 Años'!$G$18))*(C7*(1-MIN(30,'0. Supuestos'!$B$59)/30)+B7*MIN(30,'0. Supuestos'!$B$59)/30)),"") -> -14399.94 | D11: =IFERROR(IF('PyG 3 Años'!$B$9="","",-('PyG 3 Años'!$B$13*(1+'PyG 3 Años'!$G$13)+'PyG 3 Años'!$B$14*(1+'PyG 3 Años'!$G$14)+'PyG 3 Años'!$B$15*(1+'PyG 3 Años'!$G$15)+'PyG 3 Años'!$B$16*(1+'PyG 3 Años'!$G$16)+'PyG 3 Años'!$B$17*(1+'PyG 3 Años'!$G$17)+'PyG 3 Años'!$B$18*(1+'PyG 3 Años'!$G$18))*(D7*(1-MIN(30,'0. Supuestos'!$B$59)/30)+C7*MIN(30,'0. Supuestos'!$B$59)/30)),"") -> -16780.418 | E11: =IFERROR(IF('PyG 3 Años'!$B$9="","",-('PyG 3 Años'!$B$13*(1+'PyG 3 Años'!$G$13)+'PyG 3 Años'!$B$14*(1+'PyG 3 Años'!$G$14)+'PyG 3 Años'!$B$15*(1+'PyG 3 Años'!$G$15)+'PyG 3 Años'!$B$16*(1+'PyG 3 Años'!$G$16)+'PyG 3 Años'!$B$17*(1+'PyG 3 Años'!$G$17)+'PyG 3 Años'!$B$18*(1+'PyG 3 Años'!$G$18))*(E7*(1-MIN(30,'0. Supuestos'!$B$59)/30)+D7*MIN(30,'0. Supuestos'!$B$59)/30)),"") -> -18458.459 | F11: =IFERROR(IF('PyG 3 Años'!$B$9="","",-('PyG 3 Años'!$B$13*(1+'PyG 3 Años'!$G$13)+'PyG 3 Años'!$B$14*(1+'PyG 3 Años'!$G$14)+'PyG 3 Años'!$B$15*(1+'PyG 3 Años'!$G$15)+'PyG 3 Años'!$B$16*(1+'PyG 3 Años'!$G$16)+'PyG 3 Años'!$B$17*(1+'PyG 3 Años'!$G$17)+'PyG 3 Años'!$B$18*(1+'PyG 3 Años'!$G$18))*(F7*(1-MIN(30,'0. Supuestos'!$B$59)/30)+E7*MIN(30,'0. Supuestos'!$B$59)/30)),"") -> -19668.21 | G11: =IFERROR(IF('PyG 3 Años'!$B$9="","",-('PyG 3 Años'!$B$13*(1+'PyG 3 Años'!$G$13)+'PyG 3 Años'!$B$14*(1+'PyG 3 Años'!$G$14)+'PyG 3 Años'!$B$15*(1+'PyG 3 Años'!$G$15)+'PyG 3 Años'!$B$16*(1+'PyG 3 Años'!$G$16)+'PyG 3 Años'!$B$17*(1+'PyG 3 Años'!$G$17)+'PyG 3 Años'!$B$18*(1+'PyG 3 Años'!$G$18))*(G7*(1-MIN(30,'0. Supuestos'!$B$59)/30)+F7*MIN(30,'0. Supuestos'!$B$59)/30)),"") -> -20136.501 | H11: =IFERROR(IF('PyG 3 Años'!$B$9="","",-('PyG 3 Años'!$B$13*(1+'PyG 3 Años'!$G$13)+'PyG 3 Años'!$B$14*(1+'PyG 3 Años'!$G$14)+'PyG 3 Años'!$B$15*(1+'PyG 3 Años'!$G$15)+'PyG 3 Años'!$B$16*(1+'PyG 3 Años'!$G$16)+'PyG 3 Años'!$B$17*(1+'PyG 3 Años'!$G$17)+'PyG 3 Años'!$B$18*(1+'PyG 3 Años'!$G$18))*(H7*(1-MIN(30,'0. Supuestos'!$B$59)/30)+G7*MIN(30,'0. Supuestos'!$B$59)/30)),"") -> -19668.21 | I11: =IFERROR(IF('PyG 3 Años'!$B$9="","",-('PyG 3 Años'!$B$13*(1+'PyG 3 Años'!$G$13)+'PyG 3 Años'!$B$14*(1+'PyG 3 Años'!$G$14)+'PyG 3 Años'!$B$15*(1+'PyG 3 Años'!$G$15)+'PyG 3 Años'!$B$16*(1+'PyG 3 Años'!$G$16)+'PyG 3 Años'!$B$17*(1+'PyG 3 Años'!$G$17)+'PyG 3 Años'!$B$18*(1+'PyG 3 Años'!$G$18))*(I7*(1-MIN(30,'0. Supuestos'!$B$59)/30)+H7*MIN(30,'0. Supuestos'!$B$59)/30)),"") -> -18731.629 | J11: =IFERROR(IF('PyG 3 Años'!$B$9="","",-('PyG 3 Años'!$B$13*(1+'PyG 3 Años'!$G$13)+'PyG 3 Años'!$B$14*(1+'PyG 3 Años'!$G$14)+'PyG 3 Años'!$B$15*(1+'PyG 3 Años'!$G$15)+'PyG 3 Años'!$B$16*(1+'PyG 3 Años'!$G$16)+'PyG 3 Años'!$B$17*(1+'PyG 3 Años'!$G$17)+'PyG 3 Años'!$B$18*(1+'PyG 3 Años'!$G$18))*(J7*(1-MIN(30,'0. Supuestos'!$B$59)/30)+I7*MIN(30,'0. Supuestos'!$B$59)/30)),"") -> -15453.594 | ... M11: =IFERROR(IF('PyG 3 Años'!$B$9="","",-('PyG 3 Años'!$B$13*(1+'PyG 3 Años'!$G$13)+'PyG 3 Años'!$B$14*(1+'PyG 3 Años'!$G$14)+'PyG 3 Años'!$B$15*(1+'PyG 3 Años'!$G$15)+'PyG 3 Años'!$B$16*(1+'PyG 3 Años'!$G$16)+'PyG 3 Años'!$B$17*(1+'PyG 3 Años'!$G$17)+'PyG 3 Años'!$B$18*(1+'PyG 3 Años'!$G$18))*(M7*(1-MIN(30,'0. Supuestos'!$B$59)/30)+L7*MIN(30,'0. Supuestos'!$B$59)/30)),"") -> -20136.501 | N11: =IFERROR(IF('PyG 3 Años'!$B$9="","",SUM(B11:M11)),"") -> -202769.88 | O11: =IFERROR("Materia prima, consumibles, comisiones e imprevistos, cada uno con SU tipo de IVA (la columna del P&L) y con los días de pago a proveedor de Supuestos."&IF('0. Supuestos'!$B$59=0,""," Con "&TEXT('0. Supuestos'!$B$59,"0")&" días de pago, las primeras compras se pagan ya en el año siguiente: la columna «Año» de esta fila recoge "&TEXT(MAX(0,12-ROUNDUP('0. Supuestos'!$B$59/30,0)),"0")&" mensualidades de compra, no el coste del ejercicio."),"") -> Materia prima, consumibles, comisiones e imprevistos, cada uno con SU tipo de IVA (la columna del P&L) y con los días de pago a proveedor de Supuestos. Con 30 días de pago, las primeras compras se pagan ya en el año siguiente: la columna «Año» de esta fila recoge 11 mensualidades de compra, no el coste del ejercicio.
A12: Costes fijos de explotación (IVA incluido) | B12: =IFERROR(IF('PyG 3 Años'!$B$9="","",-('PyG 3 Años'!$B$37-'PyG 3 Años'!$B$23-'PyG 3 Años'!$B$35-'PyG 3 Años'!$B$36+'PyG 3 Años'!$B$39)/12),"") -> -4813.5417 | C12: =IFERROR(IF('PyG 3 Años'!$B$9="","",-('PyG 3 Años'!$B$37-'PyG 3 Años'!$B$23-'PyG 3 Años'!$B$35-'PyG 3 Años'!$B$36+'PyG 3 Años'!$B$39)/12),"") -> -4813.5417 | D12: =IFERROR(IF('PyG 3 Años'!$B$9="","",-('PyG 3 Años'!$B$37-'PyG 3 Años'!$B$23-'PyG 3 Años'!$B$35-'PyG 3 Años'!$B$36+'PyG 3 Años'!$B$39)/12),"") -> -4813.5417 | E12: =IFERROR(IF('PyG 3 Años'!$B$9="","",-('PyG 3 Años'!$B$37-'PyG 3 Años'!$B$23-'PyG 3 Años'!$B$35-'PyG 3 Años'!$B$36+'PyG 3 Años'!$B$39)/12),"") -> -4813.5417 | F12: =IFERROR(IF('PyG 3 Años'!$B$9="","",-('PyG 3 Años'!$B$37-'PyG 3 Años'!$B$23-'PyG 3 Años'!$B$35-'PyG 3 Años'!$B$36+'PyG 3 Años'!$B$39)/12),"") -> -4813.5417 | G12: =IFERROR(IF('PyG 3 Años'!$B$9="","",-('PyG 3 Años'!$B$37-'PyG 3 Años'!$B$23-'PyG 3 Años'!$B$35-'PyG 3 Años'!$B$36+'PyG 3 Años'!$B$39)/12),"") -> -4813.5417 | H12: =IFERROR(IF('PyG 3 Años'!$B$9="","",-('PyG 3 Años'!$B$37-'PyG 3 Años'!$B$23-'PyG 3 Años'!$B$35-'PyG 3 Años'!$B$36+'PyG 3 Años'!$B$39)/12),"") -> -4813.5417 | I12: =IFERROR(IF('PyG 3 Años'!$B$9="","",-('PyG 3 Años'!$B$37-'PyG 3 Años'!$B$23-'PyG 3 Años'!$B$35-'PyG 3 Años'!$B$36+'PyG 3 Años'!$B$39)/12),"") -> -4813.5417 | ... M12: =IFERROR(IF('PyG 3 Años'!$B$9="","",-('PyG 3 Años'!$B$37-'PyG 3 Años'!$B$23-'PyG 3 Años'!$B$35-'PyG 3 Años'!$B$36+'PyG 3 Años'!$B$39)/12),"") -> -4813.5417 | N12: =IFERROR(IF('PyG 3 Años'!$B$9="","",SUM(B12:M12)),"") -> -57762.5 | O12: Los fijos que salen de caja, cada uno con su tipo de IVA: los seguros están exentos y no llevan
A13: Nóminas y Seguridad Social | B13: =IFERROR(IF('PyG 3 Años'!$B$9="","",-'PyG 3 Años'!$B$23/MAX(12,'0. Supuestos'!$B$21)*(1+IF(1='0. Supuestos'!$B$60,(MAX(12,'0. Supuestos'!$B$21)-12)/2,0)+IF(1='0. Supuestos'!$B$61,(MAX(12,'0. Supuestos'!$B$21)-12)/2,0))),"") -> -11408.74 | C13: =IFERROR(IF('PyG 3 Años'!$B$9="","",-'PyG 3 Años'!$B$23/MAX(12,'0. Supuestos'!$B$21)*(1+IF(2='0. Supuestos'!$B$60,(MAX(12,'0. Supuestos'!$B$21)-12)/2,0)+IF(2='0. Supuestos'!$B$61,(MAX(12,'0. Supuestos'!$B$21)-12)/2,0))),"") -> -11408.74 | D13: =IFERROR(IF('PyG 3 Años'!$B$9="","",-'PyG 3 Años'!$B$23/MAX(12,'0. Supuestos'!$B$21)*(1+IF(3='0. Supuestos'!$B$60,(MAX(12,'0. Supuestos'!$B$21)-12)/2,0)+IF(3='0. Supuestos'!$B$61,(MAX(12,'0. Supuestos'!$B$21)-12)/2,0))),"") -> -11408.74 | E13: =IFERROR(IF('PyG 3 Años'!$B$9="","",-'PyG 3 Años'!$B$23/MAX(12,'0. Supuestos'!$B$21)*(1+IF(4='0. Supuestos'!$B$60,(MAX(12,'0. Supuestos'!$B$21)-12)/2,0)+IF(4='0. Supuestos'!$B$61,(MAX(12,'0. Supuestos'!$B$21)-12)/2,0))),"") -> -11408.74 | F13: =IFERROR(IF('PyG 3 Años'!$B$9="","",-'PyG 3 Años'!$B$23/MAX(12,'0. Supuestos'!$B$21)*(1+IF(5='0. Supuestos'!$B$60,(MAX(12,'0. Supuestos'!$B$21)-12)/2,0)+IF(5='0. Supuestos'!$B$61,(MAX(12,'0. Supuestos'!$B$21)-12)/2,0))),"") -> -11408.74 | G13: =IFERROR(IF('PyG 3 Años'!$B$9="","",-'PyG 3 Años'!$B$23/MAX(12,'0. Supuestos'!$B$21)*(1+IF(6='0. Supuestos'!$B$60,(MAX(12,'0. Supuestos'!$B$21)-12)/2,0)+IF(6='0. Supuestos'!$B$61,(MAX(12,'0. Supuestos'!$B$21)-12)/2,0))),"") -> -11408.74 | H13: =IFERROR(IF('PyG 3 Años'!$B$9="","",-'PyG 3 Años'!$B$23/MAX(12,'0. Supuestos'!$B$21)*(1+IF(7='0. Supuestos'!$B$60,(MAX(12,'0. Supuestos'!$B$21)-12)/2,0)+IF(7='0. Supuestos'!$B$61,(MAX(12,'0. Supuestos'!$B$21)-12)/2,0))),"") -> -22817.48 | I13: =IFERROR(IF('PyG 3 Años'!$B$9="","",-'PyG 3 Años'!$B$23/MAX(12,'0. Supuestos'!$B$21)*(1+IF(8='0. Supuestos'!$B$60,(MAX(12,'0. Supuestos'!$B$21)-12)/2,0)+IF(8='0. Supuestos'!$B$61,(MAX(12,'0. Supuestos'!$B$21)-12)/2,0))),"") -> -11408.74 | J13: =IFERROR(IF('PyG 3 Años'!$B$9="","",-'PyG 3 Años'!$B$23/MAX(12,'0. Supuestos'!$B$21)*(1+IF(9='0. Supuestos'!$B$60,(MAX(12,'0. Supuestos'!$B$21)-12)/2,0)+IF(9='0. Supuestos'!$B$61,(MAX(12,'0. Supuestos'!$B$21)-12)/2,0))),"") -> -11408.74 | K13: =IFERROR(IF('PyG 3 Años'!$B$9="","",-'PyG 3 Años'!$B$23/MAX(12,'0. Supuestos'!$B$21)*(1+IF(10='0. Supuestos'!$B$60,(MAX(12,'0. Supuestos'!$B$21)-12)/2,0)+IF(10='0. Supuestos'!$B$61,(MAX(12,'0. Supuestos'!$B$21)-12)/2,0))),"") -> -11408.74 | L13: =IFERROR(IF('PyG 3 Años'!$B$9="","",-'PyG 3 Años'!$B$23/MAX(12,'0. Supuestos'!$B$21)*(1+IF(11='0. Supuestos'!$B$60,(MAX(12,'0. Supuestos'!$B$21)-12)/2,0)+IF(11='0. Supuestos'!$B$61,(MAX(12,'0. Supuestos'!$B$21)-12)/2,0))),"") -> -11408.74 | M13: =IFERROR(IF('PyG 3 Años'!$B$9="","",-'PyG 3 Años'!$B$23/MAX(12,'0. Supuestos'!$B$21)*(1+IF(12='0. Supuestos'!$B$60,(MAX(12,'0. Supuestos'!$B$21)-12)/2,0)+IF(12='0. Supuestos'!$B$61,(MAX(12,'0. Supuestos'!$B$21)-12)/2,0))),"") -> -22817.48 | N13: =IFERROR(IF('PyG 3 Años'!$B$9="","",SUM(B13:M13)),"") -> -159722.36 | O13: Doce mensualidades más las pagas extra en los meses que digas en Supuestos. La suma del año es la misma que la del P&L
A14: Intereses del préstamo | B14: =IFERROR(IF('PyG 3 Años'!$B$9="","",-'Financiación'!$B$44/12),"") -> -655 | C14: =IFERROR(IF('PyG 3 Años'!$B$9="","",-'Financiación'!$B$44/12),"") -> -655 | D14: =IFERROR(IF('PyG 3 Años'!$B$9="","",-'Financiación'!$B$44/12),"") -> -655 | E14: =IFERROR(IF('PyG 3 Años'!$B$9="","",-'Financiación'!$B$44/12),"") -> -655 | F14: =IFERROR(IF('PyG 3 Años'!$B$9="","",-'Financiación'!$B$44/12),"") -> -655 | G14: =IFERROR(IF('PyG 3 Años'!$B$9="","",-'Financiación'!$B$44/12),"") -> -655 | H14: =IFERROR(IF('PyG 3 Años'!$B$9="","",-'Financiación'!$B$44/12),"") -> -655 | I14: =IFERROR(IF('PyG 3 Años'!$B$9="","",-'Financiación'!$B$44/12),"") -> -655 | ... M14: =IFERROR(IF('PyG 3 Años'!$B$9="","",-'Financiación'!$B$44/12),"") -> -655 | N14: =IFERROR(IF('PyG 3 Años'!$B$9="","",SUM(B14:M14)),"") -> -7860
A15: Devolución de principal del préstamo | B15: =IFERROR(IF('PyG 3 Años'!$B$9="","",-'Financiación'!$B$45/12),"") -> 0 | C15: =IFERROR(IF('PyG 3 Años'!$B$9="","",-'Financiación'!$B$45/12),"") -> 0 | D15: =IFERROR(IF('PyG 3 Años'!$B$9="","",-'Financiación'!$B$45/12),"") -> 0 | E15: =IFERROR(IF('PyG 3 Años'!$B$9="","",-'Financiación'!$B$45/12),"") -> 0 | F15: =IFERROR(IF('PyG 3 Años'!$B$9="","",-'Financiación'!$B$45/12),"") -> 0 | G15: =IFERROR(IF('PyG 3 Años'!$B$9="","",-'Financiación'!$B$45/12),"") -> 0 | H15: =IFERROR(IF('PyG 3 Años'!$B$9="","",-'Financiación'!$B$45/12),"") -> 0 | I15: =IFERROR(IF('PyG 3 Años'!$B$9="","",-'Financiación'!$B$45/12),"") -> 0 | ... M15: =IFERROR(IF('PyG 3 Años'!$B$9="","",-'Financiación'!$B$45/12),"") -> 0 | N15: =IFERROR(IF('PyG 3 Años'!$B$9="","",SUM(B15:M15)),"") -> 0
A16: IVA repercutido del mes (memoria) | B16: =IFERROR(IF('PyG 3 Años'!$B$9="","",'PyG 3 Años'!$B$9*B7*SUMPRODUCT('PyG 3 Años'!$E$10:$E$11,'PyG 3 Años'!$G$10:$G$11)),"") -> 3078.0474 | C16: =IFERROR(IF('PyG 3 Años'!$B$9="","",'PyG 3 Años'!$B$9*C7*SUMPRODUCT('PyG 3 Años'!$E$10:$E$11,'PyG 3 Años'!$G$10:$G$11)),"") -> 3586.8845 | D16: =IFERROR(IF('PyG 3 Años'!$B$9="","",'PyG 3 Años'!$B$9*D7*SUMPRODUCT('PyG 3 Años'!$E$10:$E$11,'PyG 3 Años'!$G$10:$G$11)),"") -> 3945.5729 | E16: =IFERROR(IF('PyG 3 Años'!$B$9="","",'PyG 3 Años'!$B$9*E7*SUMPRODUCT('PyG 3 Años'!$E$10:$E$11,'PyG 3 Años'!$G$10:$G$11)),"") -> 4204.1623 | F16: =IFERROR(IF('PyG 3 Años'!$B$9="","",'PyG 3 Años'!$B$9*F7*SUMPRODUCT('PyG 3 Años'!$E$10:$E$11,'PyG 3 Años'!$G$10:$G$11)),"") -> 4304.2614 | G16: =IFERROR(IF('PyG 3 Años'!$B$9="","",'PyG 3 Años'!$B$9*G7*SUMPRODUCT('PyG 3 Años'!$E$10:$E$11,'PyG 3 Años'!$G$10:$G$11)),"") -> 4204.1623 | H16: =IFERROR(IF('PyG 3 Años'!$B$9="","",'PyG 3 Años'!$B$9*H7*SUMPRODUCT('PyG 3 Años'!$E$10:$E$11,'PyG 3 Años'!$G$10:$G$11)),"") -> 4003.9641 | I16: =IFERROR(IF('PyG 3 Años'!$B$9="","",'PyG 3 Años'!$B$9*I7*SUMPRODUCT('PyG 3 Años'!$E$10:$E$11,'PyG 3 Años'!$G$10:$G$11)),"") -> 3303.2704 | ... M16: =IFERROR(IF('PyG 3 Años'!$B$9="","",'PyG 3 Años'!$B$9*M7*SUMPRODUCT('PyG 3 Años'!$E$10:$E$11,'PyG 3 Años'!$G$10:$G$11)),"") -> 4604.5587 | N16: =IFERROR(IF('PyG 3 Años'!$B$9="","",SUM(B16:M16)),"") -> 47947.47 | O16: Cada línea de venta a SU tipo, leído de la columna de IVA del P&L: en sala, alcohol incluido, el reducido (art. 91.Uno.2.2.º de la Ley 37/1992 del IVA); la parte de la bebida que sale para llevar o a domicilio y declara la columna H de su línea (cerveza, sake, vino y refrescos con azúcares o edulcorantes añadidos), al general (art. 91.Uno.1.1.º a y b); la comida, también la que sale para llevar o a domicilio, al reducido (art. 91.Uno.1.1.º y 2.2.º)
A17: IVA soportado del mes (memoria) | B17: =IFERROR(IF('PyG 3 Años'!$B$9="","",'PyG 3 Años'!$B$38*B7+'PyG 3 Años'!$B$39/12),"") -> 2474.7704 | C17: =IFERROR(IF('PyG 3 Años'!$B$9="","",'PyG 3 Años'!$B$38*C7+'PyG 3 Años'!$B$39/12),"") -> 2750.0797 | D17: =IFERROR(IF('PyG 3 Años'!$B$9="","",'PyG 3 Años'!$B$38*D7+'PyG 3 Años'!$B$39/12),"") -> 2944.1501 | E17: =IFERROR(IF('PyG 3 Años'!$B$9="","",'PyG 3 Años'!$B$38*E7+'PyG 3 Años'!$B$39/12),"") -> 3084.0614 | F17: =IFERROR(IF('PyG 3 Años'!$B$9="","",'PyG 3 Años'!$B$38*F7+'PyG 3 Años'!$B$39/12),"") -> 3138.2206 | G17: =IFERROR(IF('PyG 3 Años'!$B$9="","",'PyG 3 Años'!$B$38*G7+'PyG 3 Años'!$B$39/12),"") -> 3084.0614 | H17: =IFERROR(IF('PyG 3 Años'!$B$9="","",'PyG 3 Años'!$B$38*H7+'PyG 3 Años'!$B$39/12),"") -> 2975.743 | I17: =IFERROR(IF('PyG 3 Años'!$B$9="","",'PyG 3 Años'!$B$38*I7+'PyG 3 Años'!$B$39/12),"") -> 2596.6286 | ... M17: =IFERROR(IF('PyG 3 Años'!$B$9="","",'PyG 3 Años'!$B$38*M7+'PyG 3 Años'!$B$39/12),"") -> 3300.6982 | N17: =IFERROR(IF('PyG 3 Años'!$B$9="","",SUM(B17:M17)),"") -> 35654.757 | O17: Cada partida a su tipo, leído de la columna de IVA del P&L: los seguros y las comisiones de los medios de pago están exentos
A18: IVA a compensar arrastrado (inversión incluida) | E18: =IFERROR(IF('PyG 3 Años'!$B$9="","",'Inversión Inicial'!$B$32),"") -> 21745.5 | H18: =IFERROR(IF('PyG 3 Años'!$B$9="","",MAX(0,-E19)),"") -> 19303.995 | K18: =IFERROR(IF('PyG 3 Años'!$B$9="","",MAX(0,-H19)),"") -> 15897.753 | O18: El IVA soportado de la INVERSIÓN entra aquí: se compensa contra el repercutido de los trimestres siguientes hasta agotarlo (modelo 303)
A19: Resultado de la liquidación trimestral | E19: =IFERROR(IF('PyG 3 Años'!$B$9="","",SUM(B16:D16)-SUM(B17:D17)-E18),"") -> -19303.995 | H19: =IFERROR(IF('PyG 3 Años'!$B$9="","",SUM(E16:G16)-SUM(E17:G17)-H18),"") -> -15897.753 | K19: =IFERROR(IF('PyG 3 Años'!$B$9="","",SUM(H16:J16)-SUM(H17:J17)-K18),"") -> -13088.729 | O19: Repercutido menos soportado del trimestre menos lo que venía arrastrado. En negativo NO se paga: se compensa en el trimestre siguiente
A20: Pago del IVA (modelo 303) | E20: =IFERROR(IF('PyG 3 Años'!$B$9="","",IF(E19<=0,"",-E19)),"") | H20: =IFERROR(IF('PyG 3 Años'!$B$9="","",IF(H19<=0,"",-H19)),"") | K20: =IFERROR(IF('PyG 3 Años'!$B$9="","",IF(K19<=0,"",-K19)),"") | N20: =IFERROR(IF('PyG 3 Años'!$B$9="","",SUM(B20:M20)),"") -> 0 | O20: Sólo sale caja cuando el resultado del trimestre es positivo. Los meses sin liquidación van en blanco, no a cero. La celda se pinta en ROJO cuando el pago del 303 se lleva más caja de la que queda ese mes
A21: FLUJO DEL MES | B21: =IFERROR(IF('PyG 3 Años'!$B$9="","",SUM(B9:B15)+IF(B20="",0,B20)),"") -> 14395.98 | C21: =IFERROR(IF('PyG 3 Años'!$B$9="","",SUM(C9:C15)+IF(C20="",0,C20)),"") -> 7399.6793 | D21: =IFERROR(IF('PyG 3 Años'!$B$9="","",SUM(D9:D15)+IF(D20="",0,D20)),"") -> 9032.785 | E21: =IFERROR(IF('PyG 3 Años'!$B$9="","",SUM(E9:E15)+IF(E20="",0,E20)),"") -> 10242.344 | F21: =IFERROR(IF('PyG 3 Años'!$B$9="","",SUM(F9:F15)+IF(F20="",0,F20)),"") -> 10237.273 | G21: =IFERROR(IF('PyG 3 Años'!$B$9="","",SUM(G9:G15)+IF(G20="",0,G20)),"") -> 8824.6102 | H21: =IFERROR(IF('PyG 3 Años'!$B$9="","",SUM(H9:H15)+IF(H20="",0,H20)),"") -> -4222.5164 | I21: =IFERROR(IF('PyG 3 Años'!$B$9="","",SUM(I9:I15)+IF(I20="",0,I20)),"") -> 858.40041 | ... M21: =IFERROR(IF('PyG 3 Años'!$B$9="","",SUM(M9:M15)+IF(M20="",0,M20)),"") -> 1483.9367 | N21: =IFERROR(IF('PyG 3 Años'!$B$9="","",SUM(B21:M21)),"") -> 90491.1
A22: SALDO ACUMULADO DE CAJA | B22: =IFERROR(IF('PyG 3 Años'!$B$9="","",'Inversión Inicial'!$B$29+B21),"") -> 68304.07 | C22: =IFERROR(IF('PyG 3 Años'!$B$9="","",B22+C21),"") -> 75703.749 | D22: =IFERROR(IF('PyG 3 Años'!$B$9="","",C22+D21),"") -> 84736.534 | E22: =IFERROR(IF('PyG 3 Años'!$B$9="","",D22+E21),"") -> 94978.879 | F22: =IFERROR(IF('PyG 3 Años'!$B$9="","",E22+F21),"") -> 105216.15 | G22: =IFERROR(IF('PyG 3 Años'!$B$9="","",F22+G21),"") -> 114040.76 | H22: =IFERROR(IF('PyG 3 Años'!$B$9="","",G22+H21),"") -> 109818.25 | I22: =IFERROR(IF('PyG 3 Años'!$B$9="","",H22+I21),"") -> 110676.65 | J22: =IFERROR(IF('PyG 3 Años'!$B$9="","",I22+J21),"") -> 122440.71 | ... M22: =IFERROR(IF('PyG 3 Años'!$B$9="","",L22+M21),"") -> 144399.19
A23: Saldo mínimo del año | B23: =IFERROR(IF('PyG 3 Años'!$B$9="","",IF(COUNT(B22:M22)=0,"",MIN(B22:M22))),"") -> 68304.07 | D23: Si es negativo, sube el fondo de maniobra o el préstamo: te quedas sin caja
A24: Mes en el que la caja toca fondo | B24: =IFERROR(IF('PyG 3 Años'!$B$9="","",IF(COUNT(B22:M22)=0,"",MATCH(MIN(B22:M22),B22:M22,0))),"") -> 1 | D24: Es la respuesta a la pregunta que decide una operación bancaria: en qué mes se agota la caja
A25: RETORNO DE LA INVERSIÓN
A26: Flujo de caja libre antes de la deuda, año 1 | B26: =IFERROR(IF('PyG 3 Años'!$B$9="","",'PyG 3 Años'!$B$47+'PyG 3 Años'!$B$35+'Financiación'!$B$44),"") -> 60244.094 | D26: Resultado neto más amortización (que no se paga) más los intereses de ese año: el principal no se resta porque este flujo es ANTES de la deuda. La MISMA base que los años 2 y 3, para que el payback compare peras con peras
A27: Flujo de caja libre antes de la deuda, año 2 | B27: =IFERROR(IF('PyG 3 Años'!$B$9="","",'PyG 3 Años'!$C$47+'PyG 3 Años'!$C$35+'Financiación'!$B$46),"") -> 69201.275 | D27: Resultado neto más amortización (que no se paga) más los intereses de ese año: el principal no se resta porque este flujo es ANTES de la deuda. Sin tabla mensual, es una estimación
A28: Flujo de caja libre antes de la deuda, año 3 | B28: =IFERROR(IF('PyG 3 Años'!$B$9="","",'PyG 3 Años'!$D$47+'PyG 3 Años'!$D$35+'Financiación'!$B$48),"") -> 67054.483 | D28: Resultado neto más amortización (que no se paga) más los intereses de ese año: el principal no se resta porque este flujo es ANTES de la deuda. Sin tabla mensual, es una estimación
A29: Informativo: flujo REAL de caja del año 1 (tabla mensual, antes de la deuda) | B29: =IFERROR(IF('PyG 3 Años'!$B$9="","",N21+'Financiación'!$B$44+'Financiación'!$B$45),"") -> 98351.1 | D29: La suma de los doce FLUJO DEL MES de arriba, devolviéndole los intereses y el principal que se pagaron ese año. NO es la que usa el payback: lleva dentro el IVA que todavía no se ha liquidado y el crédito del proveedor, dos cosas que hay que devolver y que los años 2 y 3 no tienen
A30: Inversión a recuperar (sin el IVA, que se recupera por el 303) | B30: =IFERROR(IF('PyG 3 Años'!$B$9="","",'Inversión Inicial'!$B$33-'Inversión Inicial'!$B$32),"") -> 163658.09 | D30: CAPEX más fondo de maniobra: la necesidad total de caja MENOS el IVA soportado de la inversión, que no se pierde (se recupera con el modelo 303 y esta misma hoja lo compensa trimestre a trimestre). El fondo de maniobra sí se recupera al cerrar, pero hasta entonces está inmovilizado
A31: Payback del proyecto (años), antes de la deuda | B31: =IFERROR(IF('PyG 3 Años'!$B$9="","",IF(B26>=B30,ROUND(B30/B26,1),IF(B26+B27>=B30,ROUND(1+(B30-B26)/B27,1),IF(B26+B27+B28>=B30,ROUND(2+(B30-B26-B27)/B28,1),"Más de 3 años")))),"") -> 2.5 | D31: Mide cuánto tarda el negocio en devolver la inversión con lo que genera ANTES de pagar al banco, con la MISMA base de flujo en los tres años; si puedes pagar la cuota lo dice el DSCR de la hoja de Financiación. El plan de negocio en Word cita esta cifra; si cambias una celda verde, manda este libro
A32: Payback sobre el CAPEX, sin fondo de maniobra (años) | B32: =IFERROR(IF('PyG 3 Años'!$B$9="","",IF(B26>='Inversión Inicial'!$B$31,ROUND('Inversión Inicial'!$B$31/B26,1),IF(B26+B27>='Inversión Inicial'!$B$31,ROUND(1+('Inversión Inicial'!$B$31-B26)/B27,1),IF(B26+B27+B28>='Inversión Inicial'!$B$31,ROUND(2+('Inversión Inicial'!$B$31-B26-B27)/B28,1),"Más de 3 años")))),"") -> 1.7 | D32: El mismo cálculo sobre lo que se COMPRA (obra, equipamiento, lanzamiento y constitución), sin el fondo de maniobra: ese dinero no se gasta, se inmoviliza y vuelve al cerrar el negocio. Informativo: el payback que se publica es el de arriba
A34: El IVA del cuarto trimestre se liquida en enero del año siguiente, así que no aparece en este cuadro. El Impuesto de Sociedades del año 1 se paga en julio del año 2. La cuota del préstamo se reparte en doce partes iguales siguiendo el cuadro ANUAL de la hoja de Financiación, y las nóminas en doce mensualidades más las dos pagas extra en su mes.

Sheet Financiación
A1: PLAN DE FINANCIACIÓN
A2: Qué hace falta, de dónde sale y cuánto cuesta devolverlo. Es la hoja que el banco pide junto con el P&L.
A4: Concepto | B4: Importe | C4: Notas
A5: ORIGEN DE FONDOS
A6: Recursos propios de los socios | B6: =IFERROR(IF('0. Supuestos'!$B$30="","",'0. Supuestos'!$B$30),"") -> 55000
A7: Préstamo bancario | B7: =IFERROR(IF('0. Supuestos'!$B$31="","",'0. Supuestos'!$B$31),"") -> 131000
A8: Línea ICO (avalada por el ICO, la concede tu banco) | B8: 0 | C8: Consulta las líneas del ejercicio en curso en ico.es
A9: Préstamo participativo ENISA | B9: 0 | C9: Para sociedades; sin garantías personales
A10: Business angels o socios inversores | B10: 0 | C10: Entra en el capital: diluye, no se devuelve
A11: Subvenciones autonómicas o locales | B11: 0 | C11: Suelen cobrarse DESPUÉS de justificar el gasto
A12: TOTAL ORIGEN DE FONDOS | B12: =IFERROR(IF(COUNT(B6:B11)=0,"",SUM(B6:B11)),"") -> 186000
A13: USOS
A14: Necesidad total de caja al arranque | B14: =IFERROR(IF('Inversión Inicial'!$B$33="","",'Inversión Inicial'!$B$33),"") -> 185403.59 | C14: Inversión más el IVA que hay que adelantar
A15: Diferencia (origen - usos) | B15: =IFERROR(B12-B14,"") -> 596.41 | C15: En rojo (negativa) el plan NO está financiado. Muy por encima de cero tampoco es gratis: se pagan intereses por un dinero que no se usa
A16: Diferencia sobre los usos (%) | B16: =IFERROR(B15/B14,"") -> 0.0032168201 | C16: Ámbar por encima del margen que fijes: es deuda que pagas sin necesitarla
A17: Exceso de financiación admisible (%) | B17: 0.05 | C17: Un pequeño colchón sobre la necesidad es sano; un 20 % de más son intereses tirados
A18: Préstamo que ajustaría el origen a la necesidad | B18: =IFERROR(MAX(0,B14-B12+B7),"") -> 130403.59 | C18: Cópialo en «Préstamo bancario solicitado» de la hoja de Supuestos y la diferencia se pone a cero
A19: CONDICIONES DEL PRÉSTAMO
A20: Importe del principal | B20: =IFERROR(IF('0. Supuestos'!$B$31=0,"",'0. Supuestos'!$B$31),"") -> 131000
A21: Tipo de interés nominal anual | B21: =IFERROR(IF('0. Supuestos'!$B$32="","",'0. Supuestos'!$B$32),"") -> 0.06
A22: Plazo total (años) | B22: =IFERROR(IF('0. Supuestos'!$B$33="","",'0. Supuestos'!$B$33),"") -> 7
A23: Carencia de principal aplicada (años) | B23: =IFERROR(IF(OR('0. Supuestos'!$B$34="",'0. Supuestos'!$B$33=""),"",IF('0. Supuestos'!$B$34>='0. Supuestos'!$B$33,0,'0. Supuestos'!$B$34)),"") -> 1 | C23: Una carencia igual o mayor que el plazo no existe: la hoja la anula en origen
A24: Cuota anual durante la amortización | B24: =IFERROR(IF(B22-B23<=0,"",IF(B21=0,B20/(B22-B23),B20*B21/(1-(1+B21)^-(B22-B23)))),"") -> 26640.504 | C24: Sistema francés, anualidad algebraica. Con el tipo al 0 % es el principal entre los años de amortización: sin esa rama el cuadro se apagaba entero
A25: CUADRO DE AMORTIZACIÓN
A26: Año | B26: Capital pendiente | C26: Intereses | D26: Amortización de principal | E26: Cuota total | F26: Capital al cierre | G26: Flujo disponible para la deuda (después de impuestos; del año 4 en adelante, el del año 3 mantenido) | H26: DSCR del año
A27: 1 | B27: =IFERROR(IF(B20="","",B20),"") -> 131000 | C27: =IFERROR(IF(OR(1>B22,B27=""),"",B27*B21),"") -> 7860 | D27: =IFERROR(IF(OR(1>B22,B27=""),"",IF(1<=B23,0,MIN(B27,B24-C27))),"") -> 0 | E27: =IFERROR(IF(C27="","",C27+D27),"") -> 7860 | F27: =IFERROR(IF(D27="","",B27-D27),"") -> 131000 | G27: =IFERROR(IF(E27="","",'PyG 3 Años'!$B$40-'PyG 3 Años'!$B$45+'PyG 3 Años'!$B$35+'PyG 3 Años'!$B$36),"") -> 60244.094 | H27: =IFERROR(IF(OR(E27="",E27=0),"",G27/E27),"") -> 7.664643
A28: 2 | B28: =IFERROR(IF(OR(2>B22,F27=""),"",F27),"") -> 131000 | C28: =IFERROR(IF(OR(2>B22,B28=""),"",B28*B21),"") -> 7860 | D28: =IFERROR(IF(OR(2>B22,B28=""),"",IF(2<=B23,0,MIN(B28,B24-C28))),"") -> 18780.504 | E28: =IFERROR(IF(C28="","",C28+D28),"") -> 26640.504 | F28: =IFERROR(IF(D28="","",B28-D28),"") -> 112219.5 | G28: =IFERROR(IF(E28="","",'PyG 3 Años'!$C$40-'PyG 3 Años'!$C$45+'PyG 3 Años'!$C$35+'PyG 3 Años'!$C$36),"") -> 69201.275 | H28: =IFERROR(IF(OR(E28="",E28=0),"",G28/E28),"") -> 2.5975963
A29: 3 | B29: =IFERROR(IF(OR(3>B22,F28=""),"",F28),"") -> 112219.5 | C29: =IFERROR(IF(OR(3>B22,B29=""),"",B29*B21),"") -> 6733.1697 | D29: =IFERROR(IF(OR(3>B22,B29=""),"",IF(3<=B23,0,MIN(B29,B24-C29))),"") -> 19907.335 | E29: =IFERROR(IF(C29="","",C29+D29),"") -> 26640.504 | F29: =IFERROR(IF(D29="","",B29-D29),"") -> 92312.161 | G29: =IFERROR(IF(E29="","",'PyG 3 Años'!$D$40-'PyG 3 Años'!$D$45+'PyG 3 Años'!$D$35+'PyG 3 Años'!$D$36),"") -> 67054.483 | H29: =IFERROR(IF(OR(E29="",E29=0),"",G29/E29),"") -> 2.5170125
A30: 4 | B30: =IFERROR(IF(OR(4>B22,F29=""),"",F29),"") -> 92312.161 | C30: =IFERROR(IF(OR(4>B22,B30=""),"",B30*B21),"") -> 5538.7297 | D30: =IFERROR(IF(OR(4>B22,B30=""),"",IF(4<=B23,0,MIN(B30,B24-C30))),"") -> 21101.775 | E30: =IFERROR(IF(C30="","",C30+D30),"") -> 26640.504 | F30: =IFERROR(IF(D30="","",B30-D30),"") -> 71210.386 | G30: =IFERROR(IF(E30="","",'PyG 3 Años'!$D$40-'PyG 3 Años'!$D$45+'PyG 3 Años'!$D$35+'PyG 3 Años'!$D$36),"") -> 67054.483 | H30: =IFERROR(IF(OR(E30="",E30=0),"",G30/E30),"") -> 2.5170125
A31: 5 | B31: =IFERROR(IF(OR(5>B22,F30=""),"",F30),"") -> 71210.386 | C31: =IFERROR(IF(OR(5>B22,B31=""),"",B31*B21),"") -> 4272.6232 | D31: =IFERROR(IF(OR(5>B22,B31=""),"",IF(5<=B23,0,MIN(B31,B24-C31))),"") -> 22367.881 | E31: =IFERROR(IF(C31="","",C31+D31),"") -> 26640.504 | F31: =IFERROR(IF(D31="","",B31-D31),"") -> 48842.505 | G31: =IFERROR(IF(E31="","",'PyG 3 Años'!$D$40-'PyG 3 Años'!$D$45+'PyG 3 Años'!$D$35+'PyG 3 Años'!$D$36),"") -> 67054.483 | H31: =IFERROR(IF(OR(E31="",E31=0),"",G31/E31),"") -> 2.5170125
A32: 6 | B32: =IFERROR(IF(OR(6>B22,F31=""),"",F31),"") -> 48842.505 | C32: =IFERROR(IF(OR(6>B22,B32=""),"",B32*B21),"") -> 2930.5503 | D32: =IFERROR(IF(OR(6>B22,B32=""),"",IF(6<=B23,0,MIN(B32,B24-C32))),"") -> 23709.954 | E32: =IFERROR(IF(C32="","",C32+D32),"") -> 26640.504 | F32: =IFERROR(IF(D32="","",B32-D32),"") -> 25132.551 | G32: =IFERROR(IF(E32="","",'PyG 3 Años'!$D$40-'PyG 3 Años'!$D$45+'PyG 3 Años'!$D$35+'PyG 3 Años'!$D$36),"") -> 67054.483 | H32: =IFERROR(IF(OR(E32="",E32=0),"",G32/E32),"") -> 2.5170125
A33: 7 | B33: =IFERROR(IF(OR(7>B22,F32=""),"",F32),"") -> 25132.551 | C33: =IFERROR(IF(OR(7>B22,B33=""),"",B33*B21),"") -> 1507.9531 | D33: =IFERROR(IF(OR(7>B22,B33=""),"",IF(7<=B23,0,MIN(B33,B24-C33))),"") -> 25132.551 | E33: =IFERROR(IF(C33="","",C33+D33),"") -> 26640.504 | F33: =IFERROR(IF(D33="","",B33-D33),"") -> 1.3096724e-10 | G33: =IFERROR(IF(E33="","",'PyG 3 Años'!$D$40-'PyG 3 Años'!$D$45+'PyG 3 Años'!$D$35+'PyG 3 Años'!$D$36),"") -> 67054.483 | H33: =IFERROR(IF(OR(E33="",E33=0),"",G33/E33),"") -> 2.5170125
A34: 8 | B34: =IFERROR(IF(OR(8>B22,F33=""),"",F33),"") | C34: =IFERROR(IF(OR(8>B22,B34=""),"",B34*B21),"") | D34: =IFERROR(IF(OR(8>B22,B34=""),"",IF(8<=B23,0,MIN(B34,B24-C34))),"") | E34: =IFERROR(IF(C34="","",C34+D34),"") | F34: =IFERROR(IF(D34="","",B34-D34),"") | G34: =IFERROR(IF(E34="","",'PyG 3 Años'!$D$40-'PyG 3 Años'!$D$45+'PyG 3 Años'!$D$35+'PyG 3 Años'!$D$36),"") | H34: =IFERROR(IF(OR(E34="",E34=0),"",G34/E34),"")
A35: 9 | B35: =IFERROR(IF(OR(9>B22,F34=""),"",F34),"") | C35: =IFERROR(IF(OR(9>B22,B35=""),"",B35*B21),"") | D35: =IFERROR(IF(OR(9>B22,B35=""),"",IF(9<=B23,0,MIN(B35,B24-C35))),"") | E35: =IFERROR(IF(C35="","",C35+D35),"") | F35: =IFERROR(IF(D35="","",B35-D35),"") | G35: =IFERROR(IF(E35="","",'PyG 3 Años'!$D$40-'PyG 3 Años'!$D$45+'PyG 3 Años'!$D$35+'PyG 3 Años'!$D$36),"") | H35: =IFERROR(IF(OR(E35="",E35=0),"",G35/E35),"")
A36: 10 | B36: =IFERROR(IF(OR(10>B22,F35=""),"",F35),"") | C36: =IFERROR(IF(OR(10>B22,B36=""),"",B36*B21),"") | D36: =IFERROR(IF(OR(10>B22,B36=""),"",IF(10<=B23,0,MIN(B36,B24-C36))),"") | E36: =IFERROR(IF(C36="","",C36+D36),"") | F36: =IFERROR(IF(D36="","",B36-D36),"") | G36: =IFERROR(IF(E36="","",'PyG 3 Años'!$D$40-'PyG 3 Años'!$D$45+'PyG 3 Años'!$D$35+'PyG 3 Años'!$D$36),"") | H36: =IFERROR(IF(OR(E36="",E36=0),"",G36/E36),"")
A37: 11 | B37: =IFERROR(IF(OR(11>B22,F36=""),"",F36),"") | C37: =IFERROR(IF(OR(11>B22,B37=""),"",B37*B21),"") | D37: =IFERROR(IF(OR(11>B22,B37=""),"",IF(11<=B23,0,MIN(B37,B24-C37))),"") | E37: =IFERROR(IF(C37="","",C37+D37),"") | F37: =IFERROR(IF(D37="","",B37-D37),"") | G37: =IFERROR(IF(E37="","",'PyG 3 Años'!$D$40-'PyG 3 Años'!$D$45+'PyG 3 Años'!$D$35+'PyG 3 Años'!$D$36),"") | H37: =IFERROR(IF(OR(E37="",E37=0),"",G37/E37),"")
A38: 12 | B38: =IFERROR(IF(OR(12>B22,F37=""),"",F37),"") | C38: =IFERROR(IF(OR(12>B22,B38=""),"",B38*B21),"") | D38: =IFERROR(IF(OR(12>B22,B38=""),"",IF(12<=B23,0,MIN(B38,B24-C38))),"") | E38: =IFERROR(IF(C38="","",C38+D38),"") | F38: =IFERROR(IF(D38="","",B38-D38),"") | G38: =IFERROR(IF(E38="","",'PyG 3 Años'!$D$40-'PyG 3 Años'!$D$45+'PyG 3 Años'!$D$35+'PyG 3 Años'!$D$36),"") | H38: =IFERROR(IF(OR(E38="",E38=0),"",G38/E38),"")
A39: 13 | B39: =IFERROR(IF(OR(13>B22,F38=""),"",F38),"") | C39: =IFERROR(IF(OR(13>B22,B39=""),"",B39*B21),"") | D39: =IFERROR(IF(OR(13>B22,B39=""),"",IF(13<=B23,0,MIN(B39,B24-C39))),"") | E39: =IFERROR(IF(C39="","",C39+D39),"") | F39: =IFERROR(IF(D39="","",B39-D39),"") | G39: =IFERROR(IF(E39="","",'PyG 3 Años'!$D$40-'PyG 3 Años'!$D$45+'PyG 3 Años'!$D$35+'PyG 3 Años'!$D$36),"") | H39: =IFERROR(IF(OR(E39="",E39=0),"",G39/E39),"")
A40: 14 | B40: =IFERROR(IF(OR(14>B22,F39=""),"",F39),"") | C40: =IFERROR(IF(OR(14>B22,B40=""),"",B40*B21),"") | D40: =IFERROR(IF(OR(14>B22,B40=""),"",IF(14<=B23,0,MIN(B40,B24-C40))),"") | E40: =IFERROR(IF(C40="","",C40+D40),"") | F40: =IFERROR(IF(D40="","",B40-D40),"") | G40: =IFERROR(IF(E40="","",'PyG 3 Años'!$D$40-'PyG 3 Años'!$D$45+'PyG 3 Años'!$D$35+'PyG 3 Años'!$D$36),"") | H40: =IFERROR(IF(OR(E40="",E40=0),"",G40/E40),"")
A41: 15 | B41: =IFERROR(IF(OR(15>B22,F40=""),"",F40),"") | C41: =IFERROR(IF(OR(15>B22,B41=""),"",B41*B21),"") | D41: =IFERROR(IF(OR(15>B22,B41=""),"",IF(15<=B23,0,MIN(B41,B24-C41))),"") | E41: =IFERROR(IF(C41="","",C41+D41),"") | F41: =IFERROR(IF(D41="","",B41-D41),"") | G41: =IFERROR(IF(E41="","",'PyG 3 Años'!$D$40-'PyG 3 Años'!$D$45+'PyG 3 Años'!$D$35+'PyG 3 Años'!$D$36),"") | H41: =IFERROR(IF(OR(E41="",E41=0),"",G41/E41),"")
A42: Tolerancia de cierre del cuadro (€) | B42: 0.01 | C42: Margen por redondeo. Por encima, el cuadro no cierra y hay capital sin devolver
A43: Capital pendiente al vencimiento | B43: =IFERROR(IF(B20="","",ROUND(B20-SUM(D27:D41),2)),"") -> 0 | C43: Tiene que ser cero: el principal devuelto en el cuadro tiene que ser el prestado. Si sale positivo, el plazo no llega
A44: Intereses del año 1 | B44: =IFERROR(IF(B20="","",IF(C27="",0,C27)),"") -> 7860
A45: Devolución de principal del año 1 | B45: =IFERROR(IF(B20="","",IF(D27="",0,D27)),"") -> 0
A46: Intereses del año 2 | B46: =IFERROR(IF(B20="","",IF(C28="",0,C28)),"") -> 7860
A47: Devolución de principal del año 2 | B47: =IFERROR(IF(B20="","",IF(D28="",0,D28)),"") -> 18780.504
A48: Intereses del año 3 | B48: =IFERROR(IF(B20="","",IF(C29="",0,C29)),"") -> 6733.1697
A49: Devolución de principal del año 3 | B49: =IFERROR(IF(B20="","",IF(D29="",0,D29)),"") -> 19907.335
A50: COBERTURA DEL SERVICIO DE LA DEUDA (DSCR)
A51: DSCR del año 1 | B51: =IFERROR(('PyG 3 Años'!$B$40-'PyG 3 Años'!$B$45+'PyG 3 Años'!$B$35+B44)/(B44+B45),"") -> 7.664643 | C51: Año de CARENCIA si la hay: con sólo intereses en el denominador el ratio se dispara y no mide el negocio
A52: DSCR del año 2 | B52: =IFERROR(('PyG 3 Años'!$C$40-'PyG 3 Años'!$C$45+'PyG 3 Años'!$C$35+B46)/(B46+B47),"") -> 2.5975963
A53: DSCR del año 3 | B53: =IFERROR(('PyG 3 Años'!$D$40-'PyG 3 Años'!$D$45+'PyG 3 Años'!$D$35+B48)/(B48+B49),"") -> 2.5170125
A54: DSCR mínimo de todo el cuadro | B54: =IFERROR(IF(COUNT(H27:H41)=0,"",MIN(H27:H41)),"") -> 2.5170125 | C54: El peor año de los que dura el préstamo, no el mejor de los tres que proyecta el P&L. Es el número que decide una operación. Ojo al alcance: los años 1 a 3 salen del P&L y del año 4 en adelante el cuadro MANTIENE el flujo del año 3, así que el mínimo de esos años es una proyección sostenida, no un año calculado. El flujo va después de impuestos
A56: El DSCR se calcula ANTES de la deuda y DESPUÉS de impuestos: al resultado antes de impuestos se le resta el Impuesto de Sociedades y se le devuelven la amortización contable y los intereses; el resultado se divide entre lo que hay que pagar ese año. Por debajo del mínimo de la hoja de Supuestos, el negocio no genera para pagar el préstamo. En el cuadro, el flujo de caja disponible de los años 4 en adelante se mantiene en el del año 3: el P&L sólo proyecta tres, y aquí no se inventa un crecimiento que no está calculado.
