Workbook

Sheet 0. Assumptions
A1: ASSUMPTIONS — the RATES and DRIVERS of the model are typed here
A2: Change the GREEN cells: the rest of the workbook recalculates on its own. Expense items are typed on their own tab (also in green) and are not repeated here. Amounts are in your currency.
A3: BUSINESS ACTIVITY
A4: Covers per day (year-1 average) | B4: 125 | C4: Guests served per day, averaged over the year and counting every service. The seat turns this implies are calculated in the "Implied seat turns per day (calculated)" cell on this same tab; compare them with the maximum your space allows on the "3. Break-Even" tab
A5: Average check (excl. sales tax) | B5: 28 | C5: EXCL. sales tax. The "Menu price incl. sales tax (calculated)" cell below converts it into the price on your menu: compare that figure with the average-check range in the industry benchmarks table on the "Instructions" tab
A6: Operating days per year | B6: 310 | C6: One closing day a week plus holidays and vacations. The SAME figure drives the P&L, the break-even and the scenarios
A7: Volume growth in year 2 | B7: 0.1 | C7: Second year, with a regular clientele already in place
A8: Volume growth in year 3 | B8: 0.06 | C8: Third year, close to the seat-turn ceiling of the space
A9: Menu price incl. sales tax (calculated) | B9: =IFERROR(IF($B$5="","",$B$5*(1+SUMPRODUCT('2. 3-Year P&L'!$E$11:$E$12,'2. 3-Year P&L'!$G$11:$G$12))),"") -> 30.24 | C9: =IFERROR("Average check excl. sales tax plus the weighted sales tax of your sales lines ("&TEXT(SUMPRODUCT('2. 3-Year P&L'!$E$11:$E$12,'2. 3-Year P&L'!$G$11:$G$12)*100,"0")&"%), rounded. In the US, menu prices usually exclude sales tax and it is added at the register; in the UK, menu prices include VAT.","") -> Average check excl. sales tax plus the weighted sales tax of your sales lines (8%), rounded. In the US, menu prices usually exclude sales tax and it is added at the register; in the UK, menu prices include VAT.
A10: SALES MIX AND COST OF GOODS SOLD
A11: FOOD share of total sales | B11: 0.7 | C11: Share of FOOD in total sales. It is an INPUT: change it here and the P&L, the cash flow and the sales tax collected recalculate on their own
A12: BEVERAGE share of total sales | B12: =IFERROR(IF(COUNT(B11)=0,"",1-B11),"") -> 0.3 | C12: Calculated as the remainder: food + beverage = 100%
A13: Cost of goods sold on FOOD sales | B13: 0.29 | C13: Food cost target for a casual restaurant with a bar: the industry benchmarks table on the "Instructions" tab shows 25-35% of food sales. Applied to FOOD sales ONLY
A14: Cost of goods sold on BEVERAGE sales | B14: 0.24 | C14: Beverage cost as a percentage of beverage sales, not of total sales
A15: Disposables and packaging as % of sales | B15: 0.015 | C15: Napkins, paper goods, cleaning supplies and to-go packaging
A16: Delivery share of total sales | B16: 0 | C16: ZERO by default: if you do not deliver, you do not carry an invented cost. Raise it to the REAL weight of the channel and the commission applies only to that share
A17: Delivery platform fee | B17: 0.25 | C17: Typical DoorDash / Uber Eats commission on orders served through that channel; confirm it in your contract before projecting
A18: Card processing fee | B18: 0.035 | C18: Card and mobile wallet fees on total sales; get quotes from two POS or payment providers. The example is a blended rate (a percentage plus a per-transaction fee): check your processor's statement and enter your effective rate (kit estimate)
A19: LABOR
A20: Employer payroll taxes | B20: 0.1 | C20: FICA (Social Security 6.2% + Medicare 1.45%) + federal and state unemployment taxes (FUTA / SUTA) + workers' comp. About 10% in total: adjust it to your state and your insurance carrier
A21: Monthly pay periods per year (keep 12) | B21: 12 | C21: Annual gross pay = monthly gross pay × this number. Keep 12 in the US: it counts the monthly salaries the model pays in a year, not how often you run payroll (weekly or biweekly payroll pays the same annual amount)
A22: Federal minimum wage, annual full-time | B22: 15080 | C22: US federal minimum wage: 7.25 per hour × 2,080 hours = 15,080 per year for a full-time job. Your state or city may set a higher floor: enter it in the state / local minimum wage cell below. Check the current rates at dol.gov
A23: RENT AND FIXED COSTS
A24: Monthly rent | B24: 7000 | C24: Total monthly occupancy cost for a space of about 2,800 sq ft in an urban area: base rent plus estimated NNN / CAM charges (property tax, building insurance and common-area maintenance), kept under the 10% of sales ceiling that this workbook flags. Replace it with your lease: if it quotes base rent only, add those charges here
A25: Security deposit (months of rent) | B25: 2 | C25: Months of rent held as a security deposit. It is set in your commercial lease, so check the terms before you sign
A26: Monthly utilities (electricity, water, gas) | B26: 2500 | C26: Electricity, water and gas for a kitchen with ovens, walk-in cooler and hood: ask for the space's utility history before you sign
A27: Insurance (per year) | B27: 9000 | C27: General liability + property coverage for the space + liquor liability if you serve alcohol. Workers' compensation is part of the employer payroll taxes rate, not of this line
A28: Miscellaneous and contingency as % of sales | B28: 0.02 | C28: Cushion for operating expenses that are not budgeted
A29: FINANCING
A30: Owner's equity contributed | B30: 130000 | C30: Owners' contribution. With too little, lenders pass: they usually expect an owner equity injection (often around 10% for SBA start-ups; many want 20-30%) measured against the cash need calculated on the "1. Startup Costs" tab
A31: Loan requested | B31: 399000 | C31: Principal requested: if your loan is an SBA 7(a), this is the cell. The "7. Financing" tab checks that sources and uses match the cash need, and has a cell that calculates the exact amount that balances them
A32: Nominal annual interest rate (not APR) | B32: 0.1 | C32: Nominal annual rate, not APR; get offers from two lenders, including an SBA-guaranteed loan, before you fix it
A33: Loan term (years) | B33: 10 | C33: Total years, interest-only period included
A34: Interest-only period (years) | B34: 0 | C34: Years in which you pay only interest, usually the first year, when cash is tightest. Zero by default in this workbook
A35: Working capital (months of fixed costs) | B35: 3 | C35: The minimum this workbook requires: 3 months of fixed costs as working capital before you open
A36: TAXES
A37: Effective income tax rate (years 1-2) | B37: 0.25 | C37: Example: 21% federal rate for a C corporation plus state tax, rounded to 25%. If you operate as a sole proprietorship, LLC taxed as a pass-through or S corporation, the business itself pays 0% here and you pay tax on the profit personally: set this to 0 and budget for your personal tax separately. The model applies this rate to the first two years with positive taxable income
A38: Effective income tax rate (from year 3) | B38: 0.25 | C38: From the third year with positive taxable income. Same example rate (21% federal C corporation + state). Confirm the rate that applies to you with your accountant and change it here
A39: Sales tax rate on sales | B39: 0.08 | C39: Example rate: state + local sales tax combined. It varies widely by state and city: look up yours. UK: 20% VAT on hot food and dine-in
A40: Sales tax rate on alcohol to go | B40: 0.08 | C40: Same example rate as above. Some states add separate liquor taxes: include them here if they apply to you. Alcohol served on site has its own rate in the sales tax breakdown block, further down. Utilities, equipment and services are handled in the cell below
A41: Recoverable input tax on purchases and capex | B41: 0 | C41: In the US, the sales tax you pay on purchases is a cost, not a credit: leave this at 0%. UK: 20% if you are VAT-registered
A42: Net operating losses carried forward | B42: 0 | C42: Net operating losses from earlier years still to be offset at the start. Federal rules let you offset up to 80% of taxable income in a year; the model offsets 100% as a simplification
A43: DEPRECIATION
A44: Useful life of build-out and fixtures (years) | B44: 10 | C44: Build-out, fixtures and decor of a restaurant. Book depreciation in this model is straight-line; MACRS and Section 179 are tax treatments handled outside the model, so confirm them with your accountant
A45: Useful life of machinery, furniture and equipment (years) | B45: 7 | C45: Kitchen and bar equipment, furniture and fixtures. Book depreciation in this model is straight-line; MACRS and Section 179 are tax treatments handled outside the model, so confirm them with your accountant
A47: GROWTH AND COST INFLATION
A48: Annual increase in fixed costs | B48: 0 | C48: SET TO ZERO: all three columns are in year-1 prices (real terms). Raise it if you want to project in nominal terms
A49: RAMP-UP AND CAPACITY
A50: Implied seat turns per day (calculated) | B50: =IFERROR($B$4/$B$51,"") -> 1.8382353 | C50: =IFERROR("That is "&TEXT(INT(ROUND(B50,1)),"0")&"."&TEXT(ROUND(MOD(ROUND(B50,1),1)*10,0),"0")&" seat turns per day on the "&TEXT($B$51,"0")&" seats in the cell below. Compare this daily average with your real meal periods and with the table turns you can sustain at peak before you rely on it.","") -> That is 1.8 seat turns per day on the 68 seats in the cell below. Compare this daily average with your real meal periods and with the table turns you can sustain at peak before you rely on it.
A51: Seating capacity (seats at tables + bar) | B51: 68 | C51: This feeds the implied seat turns: covers per day ÷ seats. Count the seats on your floor plan, do not copy the example
A52: Month-1 activity as a % of steady-state activity | B52: 0.55 | C52: A new business does not sell on day one what it sells six months later. The daily volume above is the year-1 AVERAGE: the ramp only spreads year 1's sales across the months (slower start, stronger finish) and keeps the annual total. At 100% there is no ramp
A53: Months to reach steady state | B53: 6 | C53: The ramp rises in a straight line from the percentage above to 100% over this number of months
A54: Months of rent BEFORE opening (build-out and permits) | B54: 1 | C54: You pay for the space from the day you sign. These months are a startup cost: they do NOT overlap the P&L, which starts on opening day
A55: Contingency on the BUILD-OUT lines of the space block (%) | B55: 0.1 | C55: Cushion on the build-out and fit-out line. A lender will not finance a renovation without it
A57: RECEIPTS, PAYMENTS AND SALES TAX BREAKDOWN
A58: Average collection days | B58: 1 | C58: At 1 day, card settlements reach your bank the next business day. Raise it if you work with reservation or delivery platforms, which usually pay out between the next day and 30 days later
A59: Average days to pay suppliers | B59: 14 | C59: What your suppliers finance for you. It is the first thing you lose if you fall behind on a payment
A60: Month of extra pay period 1 (only if pay periods > 12) | B60: 7 | C60: Month of the year (1-12) when the first extra pay period is paid out. Only used if pay periods > 12
A61: Month of extra pay period 2 (only if pay periods > 12) | B61: 12 | C61: Month of the year (1-12) when the second extra pay period is paid out. Only used if pay periods > 12
A62: ALCOHOLIC beverages as a share of total beverage sales | B62: 0.7 | C62: Share of alcohol within the beverage line (70% in the example: beer, wine and cocktails). It is used the same way on sales and on purchases, and it is an approximation, since alcohol usually weighs a bit more in cost than in sales. It only matters if alcohol is taxed at a different rate than the rest
A63: Sales tax rate on alcohol served on site | B63: 0.08 | C63: Same example rate as the rest of on-site sales (8%: state + local). Some states and cities add a liquor-by-the-drink or mixed beverage tax on top of sales tax: if yours does, type the COMBINED rate here. The workbook applies this rate only to the ALCOHOLIC part of beverage sales
A64: CONTROL THRESHOLDS AND FLOORS
A65: DSCR limit (minimum acceptable) | B65: 1.15 | C65: Below 1.0 the business does not generate enough to repay the loan. Lenders often write a minimum DSCR into the loan covenants: ask yours. Kit default: 1.15×
A66: DSCR target (green) | B66: 1.25 | C66: What lenders commonly look for before approving a loan comfortably. Kit default: 1.25× (editable estimate)
A67: Minimum cushion above break-even | B67: 0.15 | C67: How far you can fall below plan before you start losing money
A68: State / local minimum wage, annual full-time | C68: Your STATE or LOCAL minimum wage can be higher than the federal one: enter it here as an annual full-time figure (hourly rate × 2,080 hours). The higher of the two applies. Leave it empty or at 0 and the traffic light compares only against the federal minimum

Sheet 1. Startup Costs
A1: AI Chef Pro
A2: Startup Costs — Restaurant & Bar
A3: Restaurant Business Plan: Casual Restaurant & Bar — US example (2026)
A5: Item | B5: Amount | C5: % of startup costs | D5: Notes | E5: Taxable / recoverable tax?
A6: SPACE AND BUILD-OUT | B6: =IFERROR(IF(COUNT(B7:B13)=0,"",SUM(B7:B13)),"") -> 153800 | C6: =IFERROR(B6/$B$48,"") -> 0.29090441
A7: Broker and lease review | B7: 3000 | C7: =IFERROR(B7/$B$48,"") -> 0.0056743384 | D7: Tenant-rep broker fee and attorney review of the lease | E7: Yes
A8: Build-out (second-generation restaurant space) | B8: 90000 | C8: =IFERROR(B8/$B$48,"") -> 0.17023015 | D8: Kitchen rough-ins, hood connection, utilities, flooring and paint. A second-generation space (a former restaurant) usually costs less to convert than a raw shell | E8: Yes
A9: Architect, MEP drawings and permits (building + health plan review) | B9: 18000 | C9: =IFERROR(B9/$B$48,"") -> 0.03404603 | D9: Architect / engineer fees and city permit fees | E9: Yes
A10: Interior design | B10: 10000 | C10: =IFERROR(B10/$B$48,"") -> 0.018914461 | D10: Interior design for the dining room, lighting and signage | E10: Yes
A11: Security deposit | B11: =IFERROR(IF('0. Assumptions'!$B$24="","",'0. Assumptions'!$B$24*'0. Assumptions'!$B$25),"") -> 14000 | C11: =IFERROR(B11/$B$48,"") -> 0.026480246 | D11: =IFERROR(""&TEXT('0. Assumptions'!$B$25,"0")&IF('0. Assumptions'!$B$25=1," month"," months")&" of rent, from ""0. Assumptions"". Refundable when the lease ends: it is not depreciated and carries no tax","") -> 2 months of rent, from "0. Assumptions". Refundable when the lease ends: it is not depreciated and carries no tax | E11: No
A12: Rent paid before opening | B12: =IFERROR(IF('0. Assumptions'!$B$24="","",'0. Assumptions'!$B$24*'0. Assumptions'!$B$54),"") -> 7000 | C12: =IFERROR(B12/$B$48,"") -> 0.013240123 | D12: =IFERROR("Rent "&IF('0. Assumptions'!$B$54=1,"for the month","for the "&TEXT('0. Assumptions'!$B$54,"0")&" months")&" of build-out and permits before opening. It does not overlap the P&L, which starts on opening day: its twelve months are twelve trading months","") -> Rent for the month of build-out and permits before opening. It does not overlap the P&L, which starts on opening day: its twelve months are twelve trading months | E12: Yes
A13: Build-out and setup contingency | B13: =IFERROR(IF(COUNT(B8,B9,B10)=0,"",ROUND((B8+B9+B10)*'0. Assumptions'!$B$55,0)),"") -> 11800 | C13: =IFERROR(B13/$B$48,"") -> 0.022319064 | D13: =IFERROR("At "&TEXT('0. Assumptions'!$B$55,"0%")&" of the BUILD-OUT items of this block (build-out, architect and permit drawings, interior design), not of the whole block: the other items are left out. No lender funds a build-out without a cushion: the percentage is in ""0. Assumptions""","") -> At 10% of the BUILD-OUT items of this block (build-out, architect and permit drawings, interior design), not of the whole block: the other items are left out. No lender funds a build-out without a cushion: the percentage is in "0. Assumptions" | E13: Yes
A14: KITCHEN EQUIPMENT | B14: =IFERROR(IF(COUNT(B15:B24)=0,"",SUM(B15:B24)),"") -> 102000 | C14: =IFERROR(B14/$B$48,"") -> 0.1929275
A15: Cooking line (range + griddle) | B15: 14000 | C15: =IFERROR(B15/$B$48,"") -> 0.026480246 | D15: 4-burner range + griddle | E15: Yes
A16: Convection oven | B16: 9000 | C16: =IFERROR(B16/$B$48,"") -> 0.017023015 | D16: Holds 10 full-size sheet pans | E16: Yes
A17: Fryers | B17: 4000 | C17: =IFERROR(B17/$B$48,"") -> 0.0075657845 | D17: 2 vats, about 2 gallons each | E17: Yes
A18: Refrigerated prep tables | B18: 6000 | C18: =IFERROR(B18/$B$48,"") -> 0.011348677 | D18: 3 doors, about 14 cu ft | E18: Yes
A19: Walk-in cooler | B19: 16000 | C19: =IFERROR(B19/$B$48,"") -> 0.030263138 | D19: Refrigerator and freezer sections | E19: Yes
A20: Type I hood + UL 300 fire suppression | B20: 25000 | C20: =IFERROR(B20/$B$48,"") -> 0.047286153 | D20: Installation included; the suppression system is inspected under NFPA 96 | E20: Yes
A21: Commercial dishwasher | B21: 8000 | C21: =IFERROR(B21/$B$48,"") -> 0.015131569 | D21: Standard 20-inch rack | E21: Yes
A22: Smallwares and kitchen utensils | B22: 8000 | C22: =IFERROR(B22/$B$48,"") -> 0.015131569 | D22: Sauté pans, stockpots, hotel pans, knives and cutting boards | E22: Yes
A23: Sinks + grease interceptor | B23: 9000 | C23: =IFERROR(B23/$B$48,"") -> 0.017023015 | E23: Yes
A24: NSF shelving | B24: 3000 | C24: =IFERROR(B24/$B$48,"") -> 0.0056743384 | D24: 3 units, 4 shelves each | E24: Yes
A25: DINING ROOM AND BAR EQUIPMENT | B25: =IFERROR(IF(COUNT(B26:B35)=0,"",SUM(B26:B35)),"") -> 81400 | C25: =IFERROR(B25/$B$48,"") -> 0.15396371
A26: Bar (build and install) | B26: 25000 | C26: =IFERROR(B26/$B$48,"") -> 0.047286153 | D26: About 16 linear feet | E26: Yes
A27: Dining tables and chairs (15 tables × 4 chairs) | B27: 15000 | C27: =IFERROR(B27/$B$48,"") -> 0.028371692 | D27: About 1,000 per table, with its 4 chairs | E27: Yes
A28: Bar stools (8 units) | B28: 2400 | C28: =IFERROR(B28/$B$48,"") -> 0.0045394707 | D28: About 300 per stool | E28: Yes
A29: Espresso machine | B29: 8000 | C29: =IFERROR(B29/$B$48,"") -> 0.015131569 | D29: 2 groups | E29: Yes
A30: Coffee grinder | B30: 1500 | C30: =IFERROR(B30/$B$48,"") -> 0.0028371692 | E30: Yes
A31: Beer taps (2 lines) | B31: 6000 | C31: =IFERROR(B31/$B$48,"") -> 0.011348677 | D31: Installation + opening kegs | E31: Yes
A32: Wine fridge | B32: 2500 | C32: =IFERROR(B32/$B$48,"") -> 0.0047286153 | D32: Holds about 24 bottles | E32: Yes
A33: Glassware, plates and flatware | B33: 8000 | C33: =IFERROR(B33/$B$48,"") -> 0.015131569 | D33: Full service for 50 guests | E33: Yes
A34: POS + reservations | B34: 5000 | C34: =IFERROR(B34/$B$48,"") -> 0.0094572306 | D34: Terminals + annual software license | E34: Yes
A35: Patio furniture | B35: 8000 | C35: =IFERROR(B35/$B$48,"") -> 0.015131569 | D35: Tables, chairs, awning and heaters for the patio seats described in the plan. Set it to 0 if your space has no patio or the sidewalk café permit is not approved | E35: Yes
A36: MARKETING AND LAUNCH | B36: =IFERROR(IF(COUNT(B37:B39)=0,"",SUM(B37:B39)),"") -> 16000 | C36: =IFERROR(B36/$B$48,"") -> 0.030263138
A37: Brand and menu design | B37: 5000 | C37: =IFERROR(B37/$B$48,"") -> 0.0094572306 | D37: Logo, menu design, signage | E37: Yes
A38: Website + Google Business Profile | B38: 3000 | C38: =IFERROR(B38/$B$48,"") -> 0.0056743384 | D38: Basic website + Google Business Profile listing | E38: Yes
A39: Grand opening campaign | B39: 8000 | C39: =IFERROR(B39/$B$48,"") -> 0.015131569 | D39: First 3 months, social media included | E39: Yes
A40: LEGAL AND FORMATION COSTS | B40: =IFERROR(IF(COUNT(B41:B42)=0,"",SUM(B41:B42)),"") -> 17500 | C40: =IFERROR(B40/$B$48,"") -> 0.033100307
A41: LLC formation and legal | B41: 2500 | C41: =IFERROR(B41/$B$48,"") -> 0.0047286153 | D41: Articles of organization, registered agent and operating agreement | E41: No
A42: Liquor license + permits (non-quota state example) | B42: 15000 | C42: =IFERROR(B42/$B$48,"") -> 0.028371692 | E42: No
A43: OPENING INVENTORY | B43: =IFERROR(IF(COUNT(B44:B45)=0,"",SUM(B44:B45)),"") -> 18000 | C43: =IFERROR(B43/$B$48,"") -> 0.03404603
A44: Opening food inventory | B44: 8000 | C44: =IFERROR(B44/$B$48,"") -> 0.015131569 | D44: Ingredients to start service: dry, fresh and frozen. NOT depreciated: it is working capital | E44: Yes
A45: Opening bar inventory | B45: 10000 | C45: =IFERROR(B45/$B$48,"") -> 0.018914461 | D45: Wine, beer, spirits and soft drinks from the opening menu. Ask your distributors about consignment or payment terms before you budget it | E45: Yes
A46: WORKING CAPITAL | B46: =IFERROR(IF(B47="","",B47),"") -> 139996 | C46: =IFERROR(B46/$B$48,"") -> 0.26479489
A47: Operating cushion until break-even | B47: =IFERROR(IF('0. Assumptions'!$B$35*('2. 3-Year P&L'!$B$40-'2. 3-Year P&L'!$B$38)=0,"",'0. Assumptions'!$B$35*('2. 3-Year P&L'!$B$40-'2. 3-Year P&L'!$B$38)/12),"") -> 139996 | C47: =IFERROR(B47/$B$48,"") -> 0.26479489 | D47: =IFERROR("Covers "&TEXT('0. Assumptions'!$B$35,"0")&IF('0. Assumptions'!$B$35=1," month"," months")&" of year-1 CASH fixed costs (the P&L fixed costs minus depreciation, which is not paid out), the minimum the Instructions of this workbook ask for","") -> Covers 3 months of year-1 CASH fixed costs (the P&L fixed costs minus depreciation, which is not paid out), the minimum the Instructions of this workbook ask for | E47: No
A48: TOTAL STARTUP COSTS (sum of the blocks) | B48: =IFERROR(B6+B14+B25+B36+B40+B43+B46,"") -> 528696 | D48: =IFERROR("The percentages in column C are read on this figure, which includes the working capital ("&TEXT(C46,"0%")&" of the total). To compare the breakdown with another plan, use the CAPEX row below.","") -> The percentages in column C are read on this figure, which includes the working capital (26% of the total). To compare the breakdown with another plan, use the CAPEX row below.
A49: CAPEX (startup costs excluding working capital) | B49: =IFERROR(B48-B46,"") -> 388700 | D49: What you buy: build-out, equipment, launch and formation costs. The cash cushion is not an investment: it is working capital
A50: Recoverable input tax on capex | B50: =IFERROR(IF(B48="","",SUMIF($E$7:$E$45,"Yes",$B$7:$B$45)*'0. Assumptions'!$B$41),"") -> 0 | D50: =IFERROR("At "&TEXT('0. Assumptions'!$B$41,"0%")&" on the items marked ""Yes"" in the tax column. US: the sales tax you pay on equipment is part of its cost and is not recovered, so this rate is 0. UK (VAT-registered): 20%, reclaimed on your VAT return, but you pay it first, so the loan has to cover it","") -> At 0% on the items marked "Yes" in the tax column. US: the sales tax you pay on equipment is part of its cost and is not recovered, so this rate is 0. UK (VAT-registered): 20%, reclaimed on your VAT return, but you pay it first, so the loan has to cover it
A51: TOTAL CASH NEEDED AT LAUNCH | B51: =IFERROR(B48+B50,"") -> 528696 | D51: This is the figure the Financing tab has to cover
A52: DEPRECIATION BASES (not added to startup costs)
A53: Build-out, fixtures and setup | B53: =IFERROR(IF(B8="","",B8+B9+B10+B13+B20+B26),"") -> 179800 | D53: =IFERROR("Depreciated over "&TEXT('0. Assumptions'!$B$44,"0")&" years","") -> Depreciated over 10 years
A54: Machinery, furniture and equipment | B54: =IFERROR(IF(B15="","",B15+B16+B17+B18+B19+B21+B22+B23+B24+B27+B28+B29+B30+B31+B32+B33+B34+B35),"") -> 133400 | D54: =IFERROR("Depreciated over "&TEXT('0. Assumptions'!$B$45,"0")&" years","") -> Depreciated over 7 years
A55: Annual depreciation of fixed assets | B55: =IFERROR(B53/MAX(1,'0. Assumptions'!$B$44)+B54/MAX(1,'0. Assumptions'!$B$45),"") -> 37037.143 | D55: =IFERROR("Not depreciated, because they are not fixed assets: broker and lease review fees, security deposit, pre-opening rent, brand design, website and Google Business Profile, grand opening campaign, entity formation and legal, liquor license and "&"permits, opening food and bar inventory and the working capital reserve. They add up to "&TEXT(B48-B53-B54,"#,##0")&" of the "&TEXT(B48,"#,##0")&" total investment.","") -> Not depreciated, because they are not fixed assets: broker and lease review fees, security deposit, pre-opening rent, brand design, website and Google Business Profile, grand opening campaign, entity formation and legal, liquor license and permits, opening food and bar inventory and the working capital reserve. They add up to 215496 of the 528696 total investment.
A57: NOTE: all amounts are US kit-example estimates (2026); replace them with your own quotes.
A58: AI Chef Pro · aichef.pro/en/digital-products/restaurant-business-plan

Sheet 2. 3-Year P&L
A1: AI Chef Pro
A2: 3-Year Projected P&L
A3: Restaurant Business Plan: Casual Restaurant & Bar — US example (2026)
A5: Item | B5: Year 1 | C5: Year 2 | D5: Year 3 | E5: % of sales (year 1) | F5: Notes | G5: Sales tax rate on the line (%)
A6: REVENUE
A7: Covers per day (average) | B7: =IFERROR(IF('0. Assumptions'!$B$4="","",'0. Assumptions'!$B$4),"") -> 125 | C7: =IFERROR(B7*(1+'0. Assumptions'!$B$7),"") -> 137.5 | D7: =IFERROR(C7*(1+'0. Assumptions'!$B$8),"") -> 145.75 | F7: Growth for years 2 and 3 is set in "0. Assumptions"
A8: Average check (excl. sales tax) | B8: =IFERROR(IF('0. Assumptions'!$B$5="","",'0. Assumptions'!$B$5),"") -> 28 | C8: =IFERROR(IF(B8="","",B8),"") -> 28 | D8: =IFERROR(IF(C8="","",C8),"") -> 28 | F8: Held constant at year-1 prices: a price increase is a separate decision
A9: Operating days per year | B9: =IFERROR(IF('0. Assumptions'!$B$6="","",'0. Assumptions'!$B$6),"") -> 310 | C9: =IFERROR(IF(B9="","",B9),"") -> 310 | D9: =IFERROR(IF(C9="","",C9),"") -> 310
A10: TOTAL REVENUE (excl. sales tax) | B10: =IFERROR(IF(B7*B8*B9=0,"",B7*B8*B9),"") -> 1085000 | C10: =IFERROR(IF(C7*C8*C9=0,"",C7*C8*C9),"") -> 1193500 | D10: =IFERROR(IF(D7*D8*D9=0,"",D7*D8*D9),"") -> 1265110 | E10: =IFERROR(IF(B10="","",1),"") -> 1
A11: Food sales (kitchen and bar) | B11: =IFERROR(IF(B10="","",B10*$E$11),"") -> 759500 | C11: =IFERROR(IF(C10="","",C10*$E$11),"") -> 835450 | D11: =IFERROR(IF(D10="","",D10*$E$11),"") -> 885577 | E11: =IFERROR(IF('0. Assumptions'!$B$11="","",'0. Assumptions'!$B$11),"") -> 0.7 | F11: Lunch specials, regular menu and shared plates | G11: =IFERROR(IF(B10="","",'0. Assumptions'!$B$39),"") -> 0.08
A12: Beverage sales (draft beer, wine, coffee and cocktails) | B12: =IFERROR(IF(B10="","",B10*$E$12),"") -> 325500 | C12: =IFERROR(IF(C10="","",C10*$E$12),"") -> 358050 | D12: =IFERROR(IF(D10="","",D10*$E$12),"") -> 379533 | E12: =IFERROR(IF('0. Assumptions'!$B$12="","",'0. Assumptions'!$B$12),"") -> 0.3 | F12: Calculated as the remainder: food + beverage = 100% | G12: =IFERROR(IF(B10="","",('0. Assumptions'!$B$62*((1-'0. Assumptions'!$B$16)*'0. Assumptions'!$B$63+'0. Assumptions'!$B$16*'0. Assumptions'!$B$40)+(1-'0. Assumptions'!$B$62)*'0. Assumptions'!$B$39)),"") -> 0.08
A13: VARIABLE COSTS
A14: Cost of goods sold — food | B14: =IFERROR(IF(B10="","",B10*'0. Assumptions'!$B$11*'0. Assumptions'!$B$13),"") -> 220255 | C14: =IFERROR(IF(C10="","",C10*'0. Assumptions'!$B$11*'0. Assumptions'!$B$13),"") -> 242280.5 | D14: =IFERROR(IF(D10="","",D10*'0. Assumptions'!$B$11*'0. Assumptions'!$B$13),"") -> 256817.33 | E14: =IFERROR(B14/$B$10,"") -> 0.203 | F14: =IFERROR("At "&TEXT('0. Assumptions'!$B$13,"0%")&" of FOOD sales, not of total sales: beverages have their own line","") -> At 29% of FOOD sales, not of total sales: beverages have their own line | G14: =IFERROR(IF(B10="","",'0. Assumptions'!$B$41),"") -> 0
A15: Cost of goods sold — beverage | B15: =IFERROR(IF(B10="","",B10*'0. Assumptions'!$B$12*'0. Assumptions'!$B$14),"") -> 78120 | C15: =IFERROR(IF(C10="","",C10*'0. Assumptions'!$B$12*'0. Assumptions'!$B$14),"") -> 85932 | D15: =IFERROR(IF(D10="","",D10*'0. Assumptions'!$B$12*'0. Assumptions'!$B$14),"") -> 91087.92 | E15: =IFERROR(B15/$B$10,"") -> 0.072 | F15: =IFERROR("At "&TEXT('0. Assumptions'!$B$14,"0%")&" of BEVERAGE sales","") -> At 24% of BEVERAGE sales | G15: =IFERROR(IF(B10="","",'0. Assumptions'!$B$41),"") -> 0
A16: Disposables and packaging | B16: =IFERROR(IF(B10="","",B10*'0. Assumptions'!$B$15),"") -> 16275 | C16: =IFERROR(IF(C10="","",C10*'0. Assumptions'!$B$15),"") -> 17902.5 | D16: =IFERROR(IF(D10="","",D10*'0. Assumptions'!$B$15),"") -> 18976.65 | E16: =IFERROR(B16/$B$10,"") -> 0.015 | G16: =IFERROR(IF(B10="","",'0. Assumptions'!$B$41),"") -> 0
A17: Delivery platform fees | B17: =IFERROR(IF(B10="","",B10*'0. Assumptions'!$B$16*'0. Assumptions'!$B$17),"") -> 0 | C17: =IFERROR(IF(C10="","",C10*'0. Assumptions'!$B$16*'0. Assumptions'!$B$17),"") -> 0 | D17: =IFERROR(IF(D10="","",D10*'0. Assumptions'!$B$16*'0. Assumptions'!$B$17),"") -> 0 | E17: =IFERROR(B17/$B$10,"") -> 0 | F17: Applied to the sales of THAT CHANNEL. With 0% delivery in Assumptions, this line is zero | G17: =IFERROR(IF(B10="","",'0. Assumptions'!$B$41),"") -> 0
A18: Card processing fees | B18: =IFERROR(IF(B10="","",B10*'0. Assumptions'!$B$18),"") -> 37975 | C18: =IFERROR(IF(C10="","",C10*'0. Assumptions'!$B$18),"") -> 41772.5 | D18: =IFERROR(IF(D10="","",D10*'0. Assumptions'!$B$18),"") -> 44278.85 | E18: =IFERROR(B18/$B$10,"") -> 0.035 | F18: Card processing fees are not subject to sales tax: no tax is recovered or deducted for them | G18: 0
A19: Miscellaneous and contingency | B19: =IFERROR(IF(B10="","",B10*'0. Assumptions'!$B$28),"") -> 21700 | C19: =IFERROR(IF(C10="","",C10*'0. Assumptions'!$B$28),"") -> 23870 | D19: =IFERROR(IF(D10="","",D10*'0. Assumptions'!$B$28),"") -> 25302.2 | E19: =IFERROR(B19/$B$10,"") -> 0.02 | F19: =IFERROR("At "&TEXT('0. Assumptions'!$B$28,"0%")&" of sales. It is a VARIABLE cost: it moves with revenue, so it cannot sit in fixed costs","") -> At 2% of sales. It is a VARIABLE cost: it moves with revenue, so it cannot sit in fixed costs | G19: =IFERROR(IF(B10="","",'0. Assumptions'!$B$41),"") -> 0
A20: TOTAL VARIABLE COSTS | B20: =IFERROR(IF(B10="","",SUM(B14:B19)),"") -> 374325 | C20: =IFERROR(IF(C10="","",SUM(C14:C19)),"") -> 411757.5 | D20: =IFERROR(IF(D10="","",SUM(D14:D19)),"") -> 436462.95 | E20: =IFERROR(B20/$B$10,"") -> 0.345
A21: GROSS MARGIN | B21: =IFERROR(IF(B10="","",B10-B20),"") -> 710675 | C21: =IFERROR(IF(C10="","",C10-C20),"") -> 781742.5 | D21: =IFERROR(IF(D10="","",D10-D20),"") -> 828647.05 | E21: =IFERROR(B21/$B$10,"") -> 0.655
A22: FIXED COSTS
A23: Rent | B23: =IFERROR(IF(B10="","",'0. Assumptions'!$B$24*12),"") -> 84000 | C23: =IFERROR(IF(C10="","",B23*(1+'0. Assumptions'!$B$48)),"") -> 84000 | D23: =IFERROR(IF(D10="","",C23*(1+'0. Assumptions'!$B$48)),"") -> 84000 | E23: =IFERROR(B23/$B$10,"") -> 0.077419355 | F23: The monthly amount is on the "0. Assumptions" tab; here it is multiplied by twelve. Rent for the build-out months, which comes before opening, is on the Startup Costs tab and is NOT counted twice | G23: =IFERROR(IF(B10="","",'0. Assumptions'!$B$41),"") -> 0
A24: Labor (wages + employer payroll taxes) | B24: =IFERROR(IF(B10="","",'5. Staffing'!$G$13),"") -> 334884 | C24: =IFERROR(IF(C10="","",'5. Staffing'!$B$17),"") -> 342884 | D24: =IFERROR(IF(D10="","",'5. Staffing'!$B$18),"") -> 350884 | E24: =IFERROR(B24/$B$10,"") -> 0.30864885 | F24: Comes from the Staffing tab: it is the SAME number, not a separate estimate. Years 2 and 3 add the new hires declared on that tab, not a percentage of volume | G24: 0
A25: Utilities (electricity, water, gas) | B25: =IFERROR(IF(B10="","",'0. Assumptions'!$B$26*12),"") -> 30000 | C25: =IFERROR(IF(C10="","",B25*(1+'0. Assumptions'!$B$48)),"") -> 30000 | D25: =IFERROR(IF(D10="","",C25*(1+'0. Assumptions'!$B$48)),"") -> 30000 | E25: =IFERROR(B25/$B$10,"") -> 0.02764977 | F25: Enter the monthly bills excl. sales tax. The workbook applies a single tax treatment to this whole line, the one in the column next to it; if one utility is taxed differently in your area, give it its own line | G25: =IFERROR(IF(B10="","",'0. Assumptions'!$B$41),"") -> 0
A26: Insurance (general liability + property / auto) | B26: =IFERROR(IF(B10="","",'0. Assumptions'!$B$27),"") -> 9000 | C26: =IFERROR(IF(C10="","",B26*(1+'0. Assumptions'!$B$48)),"") -> 9000 | D26: =IFERROR(IF(D10="","",C26*(1+'0. Assumptions'!$B$48)),"") -> 9000 | E26: =IFERROR(B26/$B$10,"") -> 0.0082949309 | F26: Insurance premiums are not subject to sales tax: there is no recoverable tax on them | G26: 0
A27: Accounting / bookkeeping | B27: 6000 | C27: =IFERROR(IF(C10="","",B27*(1+'0. Assumptions'!$B$48)),"") -> 6000 | D27: =IFERROR(IF(D10="","",C27*(1+'0. Assumptions'!$B$48)),"") -> 6000 | E27: =IFERROR(B27/$B$10,"") -> 0.0055299539 | G27: =IFERROR(IF(B10="","",'0. Assumptions'!$B$41),"") -> 0
A28: Marketing and advertising | B28: 18000 | C28: =IFERROR(IF(C10="","",B28*(1+'0. Assumptions'!$B$48)),"") -> 18000 | D28: =IFERROR(IF(D10="","",C28*(1+'0. Assumptions'!$B$48)),"") -> 18000 | E28: =IFERROR(B28/$B$10,"") -> 0.016589862 | G28: =IFERROR(IF(B10="","",'0. Assumptions'!$B$41),"") -> 0
A29: Maintenance and repairs | B29: 9000 | C29: =IFERROR(IF(C10="","",B29*(1+'0. Assumptions'!$B$48)),"") -> 9000 | D29: =IFERROR(IF(D10="","",C29*(1+'0. Assumptions'!$B$48)),"") -> 9000 | E29: =IFERROR(B29/$B$10,"") -> 0.0082949309 | G29: =IFERROR(IF(B10="","",'0. Assumptions'!$B$41),"") -> 0
A30: Software (POS, reservations, social media) | B30: 4800 | C30: =IFERROR(IF(C10="","",B30*(1+'0. Assumptions'!$B$48)),"") -> 4800 | D30: =IFERROR(IF(D10="","",C30*(1+'0. Assumptions'!$B$48)),"") -> 4800 | E30: =IFERROR(B30/$B$10,"") -> 0.0044239631 | G30: =IFERROR(IF(B10="","",'0. Assumptions'!$B$41),"") -> 0
A31: Cleaning, laundry and linens | B31: 9600 | C31: =IFERROR(IF(C10="","",B31*(1+'0. Assumptions'!$B$48)),"") -> 9600 | D31: =IFERROR(IF(D10="","",C31*(1+'0. Assumptions'!$B$48)),"") -> 9600 | E31: =IFERROR(B31/$B$10,"") -> 0.0088479263 | F31: Table linens, kitchen towels and uniforms. Get a quote in your area: this is an indicative, editable amount | G31: =IFERROR(IF(B10="","",'0. Assumptions'!$B$41),"") -> 0
A32: Waste and grease hauling | B32: 3600 | C32: =IFERROR(IF(C10="","",B32*(1+'0. Assumptions'!$B$48)),"") -> 3600 | D32: =IFERROR(IF(D10="","",C32*(1+'0. Assumptions'!$B$48)),"") -> 3600 | E32: =IFERROR(B32/$B$10,"") -> 0.0033179724 | F32: Licensed hauler. Inspectors check it, and used cooking oil cannot go down the drain | G32: =IFERROR(IF(B10="","",'0. Assumptions'!$B$41),"") -> 0
A33: Pest control | B33: 1200 | C33: =IFERROR(IF(C10="","",B33*(1+'0. Assumptions'!$B$48)),"") -> 1200 | D33: =IFERROR(IF(D10="","",C33*(1+'0. Assumptions'!$B$48)),"") -> 1200 | E33: =IFERROR(B33/$B$10,"") -> 0.0011059908 | F33: Licensed pest control company; part of your HACCP-based food safety plan | G33: =IFERROR(IF(B10="","",'0. Assumptions'!$B$41),"") -> 0
A34: Music licensing (ASCAP, BMI, SESAC) | B34: 1200 | C34: =IFERROR(IF(C10="","",B34*(1+'0. Assumptions'!$B$48)),"") -> 1200 | D34: =IFERROR(IF(D10="","",C34*(1+'0. Assumptions'!$B$48)),"") -> 1200 | E34: =IFERROR(B34/$B$10,"") -> 0.0011059908 | F34: ASCAP, BMI and SESAC are separate licensing organizations; the fee depends on the size and capacity of your space | G34: =IFERROR(IF(B10="","",'0. Assumptions'!$B$41),"") -> 0
A35: Training and certifications | B35: 1000 | C35: =IFERROR(IF(C10="","",B35*(1+'0. Assumptions'!$B$48)),"") -> 1000 | D35: =IFERROR(IF(D10="","",C35*(1+'0. Assumptions'!$B$48)),"") -> 1000 | E35: =IFERROR(B35/$B$10,"") -> 0.00092165899 | F35: Food handler cards, Certified Food Protection Manager certification (for example ServSafe) and basic workplace safety training for the team. Requirements vary by state and county | G35: =IFERROR(IF(B10="","",'0. Assumptions'!$B$41),"") -> 0
A36: Online reservation fees | B36: 3000 | C36: =IFERROR(IF(C10="","",B36*(1+'0. Assumptions'!$B$48)),"") -> 3000 | D36: =IFERROR(IF(D10="","",C36*(1+'0. Assumptions'!$B$48)),"") -> 3000 | E36: =IFERROR(B36/$B$10,"") -> 0.002764977 | F36: Reservation platforms such as OpenTable or Resy may charge per seated guest or per booking: read the fine print before you sign | G36: =IFERROR(IF(B10="","",'0. Assumptions'!$B$41),"") -> 0
A37: Smallwares and glassware replacement | B37: 4800 | C37: =IFERROR(IF(C10="","",B37*(1+'0. Assumptions'!$B$48)),"") -> 4800 | D37: =IFERROR(IF(D10="","",C37*(1+'0. Assumptions'!$B$48)),"") -> 4800 | E37: =IFERROR(B37/$B$10,"") -> 0.0044239631 | F37: Breakage during the year. A casual restaurant with a bar breaks more than you would think to budget | G37: =IFERROR(IF(B10="","",'0. Assumptions'!$B$41),"") -> 0
A38: Depreciation of fixed assets | B38: =IFERROR(IF(B10="","",'1. Startup Costs'!$B$55),"") -> 37037.143 | C38: =IFERROR(IF(C10="","",B38),"") -> 37037.143 | D38: =IFERROR(IF(D10="","",B38),"") -> 37037.143 | E38: =IFERROR(B38/$B$10,"") -> 0.034135616 | F38: Comes from the depreciation bases on the Startup Costs tab: real fixed assets only. It does NOT rise with inflation: it is a charge on the HISTORICAL cost of the assets | G38: 0
A39: Interest expense (loan interest) | B39: =IFERROR(IF(B10="","",'7. Financing'!$B$44),"") -> 39900 | C39: =IFERROR(IF(C10="","",'7. Financing'!$B$46),"") -> 37396.459 | D39: =IFERROR(IF(D10="","",'7. Financing'!$B$48),"") -> 34642.563 | E39: =IFERROR(B39/$B$10,"") -> 0.036774194 | F39: Only INTEREST is an expense. Principal repaid appears on the cash flow tab | G39: 0
A40: TOTAL FIXED COSTS | B40: =IFERROR(IF(B10="","",SUM(B23:B39)),"") -> 597021.14 | C40: =IFERROR(IF(C10="","",SUM(C23:C39)),"") -> 602517.6 | D40: =IFERROR(IF(D10="","",SUM(D23:D39)),"") -> 607763.71 | E40: =IFERROR(B40/$B$10,"") -> 0.5502499
A41: Recoverable input tax on variable costs | B41: =IFERROR(IF(B10="","",SUMPRODUCT(B14:B19,G14:G19)),"") -> 0 | C41: =IFERROR(IF(C10="","",SUMPRODUCT(C14:C19,G14:G19)),"") -> 0 | D41: =IFERROR(IF(D10="","",SUMPRODUCT(D14:D19,G14:G19)),"") -> 0 | F41: Each line at ITS OWN rate, read from the column next to it. It is what the cash flow tab overpays to suppliers and later deducts (zero wherever no tax is recoverable)
A42: Recoverable input tax on fixed costs | B42: =IFERROR(IF(B10="","",SUMPRODUCT(B23:B39,G23:G39)),"") -> 0 | C42: =IFERROR(IF(C10="","",SUMPRODUCT(C23:C39,G23:G39)),"") -> 0 | D42: =IFERROR(IF(D10="","",SUMPRODUCT(D23:D39,G23:G39)),"") -> 0
A43: PRE-TAX INCOME (EBT) | B43: =IFERROR(IF(B10="","",B21-B40),"") -> 113653.86 | C43: =IFERROR(IF(C10="","",C21-C40),"") -> 179224.9 | D43: =IFERROR(IF(D10="","",D21-D40),"") -> 220883.34 | E43: =IFERROR(B43/$B$10,"") -> 0.1047501
A44: Net operating losses carried forward (opening) | B44: =IFERROR(IF(B10="","",'0. Assumptions'!$B$42),"") -> 0 | C44: =IFERROR(IF(C10="","",B49),"") -> 0 | D44: =IFERROR(IF(D10="","",C49),"") -> 0 | F44: Federal rules let a year's losses offset the profits of later years (the federal limit is 80% of taxable income; this model offsets 100% as a simplification)
A45: Taxable income (after loss offset) | B45: =IFERROR(IF(B10="","",MAX(0,B43-B44)),"") -> 113653.86 | C45: =IFERROR(IF(C10="","",MAX(0,C43-C44)),"") -> 179224.9 | D45: =IFERROR(IF(D10="","",MAX(0,D43-D44)),"") -> 220883.34
A46: Years with positive taxable income (cumulative) | B46: =IFERROR(IF(B10="","",IF(B45>0,1,0)),"") -> 1 | C46: =IFERROR(IF(C10="","",B46+IF(C45>0,1,0)),"") -> 2 | D46: =IFERROR(IF(D10="","",C46+IF(D45>0,1,0)),"") -> 3
A47: Effective income tax rate applied | B47: =IFERROR(IF(B10="","",IF(B45<=0,"",IF(B46<=2,'0. Assumptions'!$B$37,'0. Assumptions'!$B$38))),"") -> 0.25 | C47: =IFERROR(IF(C10="","",IF(C45<=0,"",IF(C46<=2,'0. Assumptions'!$B$37,'0. Assumptions'!$B$38))),"") -> 0.25 | D47: =IFERROR(IF(D10="","",IF(D45<=0,"",IF(D46<=2,'0. Assumptions'!$B$37,'0. Assumptions'!$B$38))),"") -> 0.25 | F47: The "years 1-2" rate applies to the first two years with positive taxable income, not to the first two calendar years of the business. The model approximates this by counting the first two profitable years
A48: Income tax | B48: =IFERROR(IF(B10="","",IF(B47="",0,B45*B47)),"") -> 28413.464 | C48: =IFERROR(IF(C10="","",IF(C47="",0,C45*C47)),"") -> 44806.225 | D48: =IFERROR(IF(D10="","",IF(D47="",0,D45*D47)),"") -> 55220.836
A49: Net operating losses carried forward (closing) | B49: =IFERROR(IF(B10="","",MAX(0,B44-B43)),"") -> 0 | C49: =IFERROR(IF(C10="","",MAX(0,C44-C43)),"") -> 0 | D49: =IFERROR(IF(D10="","",MAX(0,D44-D43)),"") -> 0
A50: NET INCOME | B50: =IFERROR(IF(B10="","",B43-B48),"") -> 85240.393 | C50: =IFERROR(IF(C10="","",C43-C48),"") -> 134418.67 | D50: =IFERROR(IF(D10="","",D43-D48),"") -> 165662.51 | E50: =IFERROR(B50/$B$10,"") -> 0.078562574
A51: KEY RATIOS
A52: Ratio | B52: Year 1 | C52: Year 2 | D52: Year 3 | E52: Threshold | F52: Comment
A53: Gross margin / Sales | B53: =IFERROR(IF(B10="","",B21/B10),"") -> 0.655 | C53: =IFERROR(IF(C10="","",C21/C10),"") -> 0.655 | D53: =IFERROR(IF(D10="","",D21/D10),"") -> 0.655 | E53: 0.65 | F53: Kit benchmark (editable estimate): gross margin of at least 65%. Below it, review your menu prices and recipe costing
A54: Cost of goods sold (food + beverage) | B54: =IFERROR(IF(B10="","",B14+B15),"") -> 298375 | C54: =IFERROR(IF(C10="","",C14+C15),"") -> 328212.5 | D54: =IFERROR(IF(D10="","",D14+D15),"") -> 347905.25
A55: Cost of goods sold / Sales | B55: =IFERROR(IF(B10="","",B54/B10),"") -> 0.275 | C55: =IFERROR(IF(C10="","",C54/C10),"") -> 0.275 | D55: =IFERROR(IF(D10="","",D54/D10),"") -> 0.275 | E55: 0.32 | F55: Kit benchmark (editable estimate): cost of goods sold up to 32% of sales, inside the food-cost range of the industry benchmarks table
A56: Labor cost / Sales | B56: =IFERROR(IF(B10="","",B24/B10),"") -> 0.30864885 | C56: =IFERROR(IF(C10="","",C24/C10),"") -> 0.28729284 | D56: =IFERROR(IF(D10="","",D24/D10),"") -> 0.27735454 | E56: 0.35 | F56: Kit benchmark (editable estimate): labor up to 35% of sales. The industry benchmarks table shows 25-33% for full-service restaurants; this is the ceiling the traffic light applies
A57: Rent / Sales | B57: =IFERROR(IF(B10="","",B23/B10),"") -> 0.077419355 | C57: =IFERROR(IF(C10="","",C23/C10),"") -> 0.070381232 | D57: =IFERROR(IF(D10="","",D23/D10),"") -> 0.066397388 | E57: 0.1 | F57: Kit benchmark (editable estimate): rent up to 10% of sales
A58: Net income / Sales | B58: =IFERROR(IF(B10="","",B50/B10),"") -> 0.078562574 | C58: =IFERROR(IF(C10="","",C50/C10),"") -> 0.11262562 | D58: =IFERROR(IF(D10="","",D50/D10),"") -> 0.13094712 | E58: 0.05 | F58: Kit benchmark (editable estimate): net margin of at least 5% of sales
A59: Break-even reached | B59: =IFERROR(IF(B10="","",IF(B10>='3. Break-Even'!$B$17,"Yes","No")),"") -> Yes | C59: =IFERROR(IF(C10="","",IF(C10>='3. Break-Even'!$C$17,"Yes","No")),"") -> Yes | D59: =IFERROR(IF(D10="","",IF(D10>='3. Break-Even'!$D$17,"Yes","No")),"") -> Yes | F59: Compares each year's sales with that same year's threshold, which the Break-Even tab calculates with that year's fixed costs
A61: All figures are EXCL. SALES TAX. Years 2 and 3 are in year-1 prices unless you raise cost inflation in the "0. Assumptions" tab. The "Sales tax rate on the line (%)" column shows, on SALES lines, the rate collected on each one and, on COST lines, the rate paid on that item. The cash flow tab reads it: insurance and card fees carry no sales tax, and wages, depreciation and interest carry none either.
A62: AI Chef Pro · aichef.pro/en/digital-products/restaurant-business-plan

Sheet 3. Break-Even
A1: AI Chef Pro
A2: Break-Even Analysis — Restaurant & Bar
A3: Restaurant Business Plan: Casual Restaurant & Bar — US example (2026)
A5: Variable | B5: Year 1 | C5: Year 2 | D5: Year 3 | E5: Notes
A6: BASE DATA BY YEAR
A7: Annual fixed costs | B7: =IFERROR(IF('2. 3-Year P&L'!$B$10="","",'2. 3-Year P&L'!$B$40),"") -> 597021.14 | C7: =IFERROR(IF('2. 3-Year P&L'!$C$10="","",'2. 3-Year P&L'!$C$40),"") -> 602517.6 | D7: =IFERROR(IF('2. 3-Year P&L'!$D$10="","",'2. 3-Year P&L'!$D$40),"") -> 607763.71 | E7: The SAME fixed costs as the P&L. Each year has its own, which is why the threshold cannot be a single one for all three years
A8: Monthly fixed costs | B8: =IFERROR(IF('2. 3-Year P&L'!$B$10="","",B7/12),"") -> 49751.762 | C8: =IFERROR(IF('2. 3-Year P&L'!$C$10="","",C7/12),"") -> 50209.8 | D8: =IFERROR(IF('2. 3-Year P&L'!$D$10="","",D7/12),"") -> 50646.976
A9: Average check (excl. sales tax) | B9: =IFERROR(IF('2. 3-Year P&L'!$B$10="","",'2. 3-Year P&L'!$B$8),"") -> 28 | C9: =IFERROR(IF('2. 3-Year P&L'!$C$10="","",'2. 3-Year P&L'!$C$8),"") -> 28 | D9: =IFERROR(IF('2. 3-Year P&L'!$D$10="","",'2. 3-Year P&L'!$D$8),"") -> 28
A10: Variable cost per cover | B10: =IFERROR(IF('2. 3-Year P&L'!$B$10="","",'2. 3-Year P&L'!$B$20/('2. 3-Year P&L'!$B$7*'2. 3-Year P&L'!$B$9)),"") -> 9.66 | C10: =IFERROR(IF('2. 3-Year P&L'!$C$10="","",'2. 3-Year P&L'!$C$20/('2. 3-Year P&L'!$C$7*'2. 3-Year P&L'!$C$9)),"") -> 9.66 | D10: =IFERROR(IF('2. 3-Year P&L'!$D$10="","",'2. 3-Year P&L'!$D$20/('2. 3-Year P&L'!$D$7*'2. 3-Year P&L'!$D$9)),"") -> 9.66 | E10: Comes from the P&L total variable costs, not from a separate estimate. It includes miscellaneous and contingency, which is a percentage of sales
A11: Contribution margin per cover | B11: =IFERROR(IF('2. 3-Year P&L'!$B$10="","",B9-B10),"") -> 18.34 | C11: =IFERROR(IF('2. 3-Year P&L'!$C$10="","",C9-C10),"") -> 18.34 | D11: =IFERROR(IF('2. 3-Year P&L'!$D$10="","",D9-D10),"") -> 18.34 | E11: Average check minus unit variable cost
A12: Operating days per year | B12: =IFERROR(IF('2. 3-Year P&L'!$B$10="","",'2. 3-Year P&L'!$B$9),"") -> 310 | C12: =IFERROR(IF('2. 3-Year P&L'!$C$10="","",'2. 3-Year P&L'!$C$9),"") -> 310 | D12: =IFERROR(IF('2. 3-Year P&L'!$D$10="","",'2. 3-Year P&L'!$D$9),"") -> 310 | E12: The same calendar as the P&L and the scenarios
A13: Principal repaid in the year | B13: =IFERROR(IF('2. 3-Year P&L'!$B$10="","",'7. Financing'!$B$45),"") -> 25035.413 | C13: =IFERROR(IF('2. 3-Year P&L'!$C$10="","",'7. Financing'!$B$47),"") -> 27538.954 | D13: =IFERROR(IF('2. 3-Year P&L'!$D$10="","",'7. Financing'!$B$49),"") -> 30292.849 | E13: Principal is NOT a P&L expense, but it leaves the cash account. Without it, the published break-even threshold would sit below the real one
A14: ACCOUNTING BREAK-EVEN (includes depreciation)
A15: Covers needed per year | B15: =IFERROR(IF('2. 3-Year P&L'!$B$10="","",IF(B11<=0,"",B7/B11)),"") -> 32552.952 | C15: =IFERROR(IF('2. 3-Year P&L'!$C$10="","",IF(C11<=0,"",C7/C11)),"") -> 32852.65 | D15: =IFERROR(IF('2. 3-Year P&L'!$D$10="","",IF(D11<=0,"",D7/D11)),"") -> 33138.697
A16: Covers needed per day | B16: =IFERROR(IF('2. 3-Year P&L'!$B$10="","",B15/B12),"") -> 105.00952 | C16: =IFERROR(IF('2. 3-Year P&L'!$C$10="","",C15/C12),"") -> 105.97629 | D16: =IFERROR(IF('2. 3-Year P&L'!$D$10="","",D15/D12),"") -> 106.89902
A17: Revenue needed per year | B17: =IFERROR(IF('2. 3-Year P&L'!$B$10="","",B15*B9),"") -> 911482.66 | C17: =IFERROR(IF('2. 3-Year P&L'!$C$10="","",C15*C9),"") -> 919874.2 | D17: =IFERROR(IF('2. 3-Year P&L'!$D$10="","",D15*D9),"") -> 927883.52
A18: CASH BREAK-EVEN (loan payments in, depreciation out)
A19: Cash fixed costs + principal repaid for the year | B19: =IFERROR(IF('2. 3-Year P&L'!$B$10="","",B7-'2. 3-Year P&L'!$B$38+B13),"") -> 585019.41 | C19: =IFERROR(IF('2. 3-Year P&L'!$C$10="","",C7-'2. 3-Year P&L'!$C$38+C13),"") -> 593019.41 | D19: =IFERROR(IF('2. 3-Year P&L'!$D$10="","",D7-'2. 3-Year P&L'!$D$38+D13),"") -> 601019.41 | E19: The P&L fixed costs without depreciation (which is not paid in cash) and WITH principal repaid (which is). This is the threshold that decides whether cash holds up
A20: Covers needed per year (cash) | B20: =IFERROR(IF('2. 3-Year P&L'!$B$10="","",IF(B11<=0,"",B19/B11)),"") -> 31898.55 | C20: =IFERROR(IF('2. 3-Year P&L'!$C$10="","",IF(C11<=0,"",C19/C11)),"") -> 32334.755 | D20: =IFERROR(IF('2. 3-Year P&L'!$D$10="","",IF(D11<=0,"",D19/D11)),"") -> 32770.96
A21: Covers needed per day (cash) | B21: =IFERROR(IF('2. 3-Year P&L'!$B$10="","",B20/B12),"") -> 102.89855 | C21: =IFERROR(IF('2. 3-Year P&L'!$C$10="","",C20/C12),"") -> 104.30566 | D21: =IFERROR(IF('2. 3-Year P&L'!$D$10="","",D20/D12),"") -> 105.71278
A22: Revenue needed per year (cash) | B22: =IFERROR(IF('2. 3-Year P&L'!$B$10="","",B20*B9),"") -> 893159.41 | C22: =IFERROR(IF('2. 3-Year P&L'!$C$10="","",C20*C9),"") -> 905373.15 | D22: =IFERROR(IF('2. 3-Year P&L'!$D$10="","",D20*D9),"") -> 917586.89
A23: COMPARISON WITH THE PLAN
A24: Covers per day forecast in the plan | B24: =IFERROR(IF('2. 3-Year P&L'!$B$10="","",'2. 3-Year P&L'!$B$7),"") -> 125 | C24: =IFERROR(IF('2. 3-Year P&L'!$C$10="","",'2. 3-Year P&L'!$C$7),"") -> 137.5 | D24: =IFERROR(IF('2. 3-Year P&L'!$D$10="","",'2. 3-Year P&L'!$D$7),"") -> 145.75
A25: Cushion above CASH break-even (%) | B25: =IFERROR(IF('2. 3-Year P&L'!$B$10="","",B24/B21-1),"") -> 0.21478875 | C25: =IFERROR(IF('2. 3-Year P&L'!$C$10="","",C24/C21-1),"") -> 0.31824099 | D25: =IFERROR(IF('2. 3-Year P&L'!$D$10="","",D24/D21-1),"") -> 0.37873592 | E25: How far you can fall before you cannot pay the fixed costs and the loan payment. The required minimum is set in the "0. Assumptions" tab
A26: Maximum seat turns per day the space allows | B26: 3 | E26: Full table services per seat per day that your opening hours allow. It is the physical ceiling of the space, not a target
A27: Seat turns per day that the cash break-even requires | B27: =IFERROR(IF('2. 3-Year P&L'!$B$10="","",B21/'0. Assumptions'!$B$51),"") -> 1.513214 | C27: =IFERROR(IF('2. 3-Year P&L'!$C$10="","",C21/'0. Assumptions'!$B$51),"") -> 1.5339068 | D27: =IFERROR(IF('2. 3-Year P&L'!$D$10="","",D21/'0. Assumptions'!$B$51),"") -> 1.5545996 | E27: Break-even covers spread across the seats declared on the "0. Assumptions" tab. If it is above the ceiling in the row above, the break-even is out of reach for the space
A28: INTERPRETATION
A29: =IFERROR("With the average check excl. sales tax above, you need "&TEXT(ROUNDUP(B16,0),"0")&" covers a day over your "&TEXT(B12,"0")&" opening days to avoid losing money (accounting break-even, depreciation included), and "&TEXT(ROUNDUP(B21,0),"0")&" for cash to hold (cash break-even: depreciation out, because it is not paid, and the year's loan payment in"&IF(B13=0,"; no principal is repaid this year (interest-only period or no loan)","")&"). The ""Revenue needed per year"" rows show the same figures in your currency.","") -> With the average check excl. sales tax above, you need 106 covers a day over your 310 opening days to avoid losing money (accounting break-even, depreciation included), and 103 for cash to hold (cash break-even: depreciation out, because it is not paid, and the year's loan payment in). The "Revenue needed per year" rows show the same figures in your currency.
A31: BREAK-EVEN SENSITIVITY
A32: Covers per day needed to cover costs for each average check (columns) and each variable cost per cover (rows). Green cells are below the covers per day the plan forecasts.
A34: Covers per day needed: average check excl. sales tax (columns) × variable cost per cover (rows) | B34: =IFERROR($B$9-2,"") -> 26 | C34: =IFERROR(IF($B$9="","",$B$9),"") -> 28 | D34: =IFERROR($B$9+2,"") -> 30 | E34: =IFERROR($B$9+4,"") -> 32
A35: =IFERROR($B$10*0.85,"") -> 8.211 | B35: =IFERROR(IF($B$34-$A35<=0,"",$B$7/($B$34-$A35)/$B$12),"") -> 108.26211 | C35: =IFERROR(IF($C$34-$A35<=0,"",$B$7/($C$34-$A35)/$B$12),"") -> 97.320464 | D35: =IFERROR(IF($D$34-$A35<=0,"",$B$7/($D$34-$A35)/$B$12),"") -> 88.387473 | E35: =IFERROR(IF($E$34-$A35<=0,"",$B$7/($E$34-$A35)/$B$12),"") -> 80.95652
A36: =IFERROR($B$10*0.925,"") -> 8.9355 | B36: =IFERROR(IF($B$34-$A36<=0,"",$B$7/($B$34-$A36)/$B$12),"") -> 112.85855 | C36: =IFERROR(IF($C$34-$A36<=0,"",$B$7/($C$34-$A36)/$B$12),"") -> 101.01889 | D36: =IFERROR(IF($D$34-$A36<=0,"",$B$7/($D$34-$A36)/$B$12),"") -> 91.427504 | E36: =IFERROR(IF($E$34-$A36<=0,"",$B$7/($E$34-$A36)/$B$12),"") -> 83.499519
A37: =IFERROR($B$10*1.0,"") -> 9.66 | B37: =IFERROR(IF($B$34-$A37<=0,"",$B$7/($B$34-$A37)/$B$12),"") -> 117.86259 | C37: =IFERROR(IF($C$34-$A37<=0,"",$B$7/($C$34-$A37)/$B$12),"") -> 105.00952 | D37: =IFERROR(IF($D$34-$A37<=0,"",$B$7/($D$34-$A37)/$B$12),"") -> 94.684103 | E37: =IFERROR(IF($E$34-$A37<=0,"",$B$7/($E$34-$A37)/$B$12),"") -> 86.20746
A38: =IFERROR($B$10*1.075,"") -> 10.3845 | B38: =IFERROR(IF($B$34-$A38<=0,"",$B$7/($B$34-$A38)/$B$12),"") -> 123.33096 | C38: =IFERROR(IF($C$34-$A38<=0,"",$B$7/($C$34-$A38)/$B$12),"") -> 109.32841 | D38: =IFERROR(IF($D$34-$A38<=0,"",$B$7/($D$34-$A38)/$B$12),"") -> 98.181268 | E38: =IFERROR(IF($E$34-$A38<=0,"",$B$7/($E$34-$A38)/$B$12),"") -> 89.096928
A39: =IFERROR($B$10*1.15,"") -> 11.109 | B39: =IFERROR(IF($B$34-$A39<=0,"",$B$7/($B$34-$A39)/$B$12),"") -> 129.33145 | C39: =IFERROR(IF($C$34-$A39<=0,"",$B$7/($C$34-$A39)/$B$12),"") -> 114.0178 | D39: =IFERROR(IF($D$34-$A39<=0,"",$B$7/($D$34-$A39)/$B$12),"") -> 101.94668 | E39: =IFERROR(IF($E$34-$A39<=0,"",$B$7/($E$34-$A39)/$B$12),"") -> 92.18681
A41: AI Chef Pro · aichef.pro/en/digital-products/restaurant-business-plan

Sheet 4. Scenarios
A1: AI Chef Pro
A2: Scenario Analysis — Year 1
A3: Restaurant Business Plan: Casual Restaurant & Bar — US example (2026)
A5: Metric | B5: Pessimistic | C5: Base | D5: Optimistic | E5: Notes
A6: Covers per day | B6: 91 | C6: =IFERROR(IF('2. 3-Year P&L'!$B$7="","",'2. 3-Year P&L'!$B$7),"") -> 125 | D6: 148
A7: Average check (excl. sales tax) | B7: 24.46 | C7: =IFERROR(IF('2. 3-Year P&L'!$B$8="","",'2. 3-Year P&L'!$B$8),"") -> 28 | D7: 28.46
A8: Operating days per year | B8: 300 | C8: =IFERROR(IF('2. 3-Year P&L'!$B$9="","",'2. 3-Year P&L'!$B$9),"") -> 310 | D8: 320
A9: ANNUAL REVENUE (excl. sales tax) | B9: =IFERROR(IF(B6*B7*B8=0,"",B6*B7*B8),"") -> 667758 | C9: =IFERROR(IF(C6*C7*C8=0,"",C6*C7*C8),"") -> 1085000 | D9: =IFERROR(IF(D6*D7*D8=0,"",D6*D7*D8),"") -> 1347865.6
A10: Cost of goods sold — food | B10: =IFERROR(IF(B9="","",B9*'0. Assumptions'!$B$11*'0. Assumptions'!$B$13),"") -> 135554.87 | C10: =IFERROR(IF(C9="","",C9*'0. Assumptions'!$B$11*'0. Assumptions'!$B$13),"") -> 220255 | D10: =IFERROR(IF(D9="","",D9*'0. Assumptions'!$B$11*'0. Assumptions'!$B$13),"") -> 273616.72
A11: Cost of goods sold — beverage | B11: =IFERROR(IF(B9="","",B9*'0. Assumptions'!$B$12*'0. Assumptions'!$B$14),"") -> 48078.576 | C11: =IFERROR(IF(C9="","",C9*'0. Assumptions'!$B$12*'0. Assumptions'!$B$14),"") -> 78120 | D11: =IFERROR(IF(D9="","",D9*'0. Assumptions'!$B$12*'0. Assumptions'!$B$14),"") -> 97046.323
A12: Disposables and packaging | B12: =IFERROR(IF(B9="","",B9*'0. Assumptions'!$B$15),"") -> 10016.37 | C12: =IFERROR(IF(C9="","",C9*'0. Assumptions'!$B$15),"") -> 16275 | D12: =IFERROR(IF(D9="","",D9*'0. Assumptions'!$B$15),"") -> 20217.984
A13: Delivery platform fees | B13: =IFERROR(IF(B9="","",B9*'0. Assumptions'!$B$16*'0. Assumptions'!$B$17),"") -> 0 | C13: =IFERROR(IF(C9="","",C9*'0. Assumptions'!$B$16*'0. Assumptions'!$B$17),"") -> 0 | D13: =IFERROR(IF(D9="","",D9*'0. Assumptions'!$B$16*'0. Assumptions'!$B$17),"") -> 0
A14: Card processing fees | B14: =IFERROR(IF(B9="","",B9*'0. Assumptions'!$B$18),"") -> 23371.53 | C14: =IFERROR(IF(C9="","",C9*'0. Assumptions'!$B$18),"") -> 37975 | D14: =IFERROR(IF(D9="","",D9*'0. Assumptions'!$B$18),"") -> 47175.296
A15: Miscellaneous and contingency | B15: =IFERROR(IF(B9="","",B9*'0. Assumptions'!$B$28),"") -> 13355.16 | C15: =IFERROR(IF(C9="","",C9*'0. Assumptions'!$B$28),"") -> 21700 | D15: =IFERROR(IF(D9="","",D9*'0. Assumptions'!$B$28),"") -> 26957.312
A16: TOTAL VARIABLE COSTS | B16: =IFERROR(IF(B9="","",SUM(B10:B15)),"") -> 230376.51 | C16: =IFERROR(IF(C9="","",SUM(C10:C15)),"") -> 374325 | D16: =IFERROR(IF(D9="","",SUM(D10:D15)),"") -> 465013.63
A17: GROSS MARGIN | B17: =IFERROR(IF(B9="","",B9-B16),"") -> 437381.49 | C17: =IFERROR(IF(C9="","",C9-C16),"") -> 710675 | D17: =IFERROR(IF(D9="","",D9-D16),"") -> 882851.97
A18: FIXED COSTS (the P&L's) | B18: =IFERROR(IF(B9="","",'2. 3-Year P&L'!$B$40),"") -> 597021.14 | C18: =IFERROR(IF(C9="","",'2. 3-Year P&L'!$B$40),"") -> 597021.14 | D18: =IFERROR(IF(D9="","",'2. 3-Year P&L'!$B$40),"") -> 597021.14 | E18: Fixed costs do not change with the scenario: that is why they are fixed
A19: PRE-TAX INCOME (EBT) | B19: =IFERROR(IF(B9="","",B17-B18),"") -> -159639.65 | C19: =IFERROR(IF(C9="","",C17-C18),"") -> 113653.86 | D19: =IFERROR(IF(D9="","",D17-D18),"") -> 285830.83
A20: Income tax | B20: =IFERROR(IF(B9="","",MAX(0,B19-'0. Assumptions'!$B$42)*'0. Assumptions'!$B$37),"") -> 0 | C20: =IFERROR(IF(C9="","",MAX(0,C19-'0. Assumptions'!$B$42)*'0. Assumptions'!$B$37),"") -> 28413.464 | D20: =IFERROR(IF(D9="","",MAX(0,D19-'0. Assumptions'!$B$42)*'0. Assumptions'!$B$37),"") -> 71457.706 | E20: At the "years 1-2" effective income tax rate, offsetting prior net operating losses
A21: NET INCOME | B21: =IFERROR(IF(B9="","",B19-B20),"") -> -159639.65 | C21: =IFERROR(IF(C9="","",C19-C20),"") -> 85240.393 | D21: =IFERROR(IF(D9="","",D19-D20),"") -> 214373.12
A22: Covers per day to break even | B22: =IFERROR(IF(B9="","",IF(B7-B16/(B6*B8)<=0,"",B18/(B7-B16/(B6*B8))/B8)),"") -> 124.21404 | C22: =IFERROR(IF(C9="","",IF(C7-C16/(C6*C8)<=0,"",C18/(C7-C16/(C6*C8))/C8)),"") -> 105.00952 | D22: =IFERROR(IF(D9="","",IF(D7-D16/(D6*D8)<=0,"",D18/(D7-D16/(D6*D8))/D8)),"") -> 100.08374
A23: WHAT EACH SCENARIO DEMANDS
A24: Labor cost / Sales | B24: =IFERROR(IF(B9="","",'2. 3-Year P&L'!$B$24/B9),"") -> 0.50150504 | C24: =IFERROR(IF(C9="","",'2. 3-Year P&L'!$B$24/C9),"") -> 0.30864885 | D24: =IFERROR(IF(D9="","",'2. 3-Year P&L'!$B$24/D9),"") -> 0.24845504 | E24: The SAME staffing in all three scenarios. If labor cost blows up in the pessimistic case, adjust it in the Staffing tab, not here
A25: Covers per year per full-time equivalent | B25: =IFERROR(IF(B9="","",B6*B8/'5. Staffing'!$C$13),"") -> 3433.9623 | C25: =IFERROR(IF(C9="","",C6*C8/'5. Staffing'!$C$13),"") -> 4874.2138 | D25: =IFERROR(IF(D9="","",D6*D8/'5. Staffing'!$C$13),"") -> 5957.2327 | E25: Covers each full-time employee in the "5. Staffing" tab would have to serve. In the optimistic scenario it tells you whether you need to hire
A26: Year-1 closing cash balance (estimate, same method in all three scenarios) | B26: =IFERROR(IF(B9="","",'1. Startup Costs'!$B$47+B21+'2. 3-Year P&L'!$B$38-'7. Financing'!$B$45),"") -> -7641.9226 | C26: =IFERROR(IF(C9="","",'1. Startup Costs'!$B$47+C21+'2. 3-Year P&L'!$B$38-'7. Financing'!$B$45),"") -> 237238.12 | D26: =IFERROR(IF(D9="","",'1. Startup Costs'!$B$47+D21+'2. 3-Year P&L'!$B$38-'7. Financing'!$B$45),"") -> 366370.85 | E26: ESTIMATED balance: working capital plus the year's result, adding back depreciation (which is not paid) and subtracting loan principal. It does not include the timing gap between receipts and payments or the sales tax settlement, so the three columns can be compared with each other. In red, the scenario runs out of cash
A27: Actual month-12 balance from the 12-Month Cash Flow tab (Base case only) | C27: =IFERROR(IF(C9="","",'6. 12-Month Cash Flow'!$M$22),"") -> 308868.22 | E27: The ACTUAL base-case balance, with its timing of receipts and payments and its sales tax settlement. It exists only for the Base scenario, the only one with its own monthly cash flow: that is why it is not in the row above, where it would be compared against two estimates
A29: The "Base" column reads its three inputs from the "0. Assumptions" tab, so it reproduces EXACTLY year 1 of the P&L. The other two scenarios use the same cost rates: the only things that change are covers, average check and days. FIXED COSTS are the same in all three: miscellaneous and contingency, which is a percentage of sales, sits at the top with the variable costs and each scenario carries its own.
A30: NOTE: The pessimistic scenario reflects a slow start with lower traffic. The optimistic one assumes strong seat turns and a higher average check. Fixed costs are constant in all 3 scenarios.
A31: AI Chef Pro · aichef.pro/en/digital-products/restaurant-business-plan

Sheet 5. Staffing
A1: AI Chef Pro
A2: Staffing Plan & Labor Cost
A3: Restaurant Business Plan: Casual Restaurant & Bar — US example (2026)
A5: Position | B5: People | C5: FTE | D5: Gross pay per month (total for the position) | E5: Employer payroll taxes (total for the position) | F5: Cost per month (total for the position) | G5: Cost per year | H5: Hours per week per person | I5: Hours per year for the position | J5: Notes
A6: General manager / owner | B6: 1 | C6: 1 | D6: 4500 | E6: =IFERROR(IF(D6="","",D6*'0. Assumptions'!$B$20),"") -> 450 | F6: =IFERROR(IF(D6="","",D6+E6),"") -> 4950 | G6: =IFERROR(IF(D6="","",F6*MAX(12,'0. Assumptions'!$B$21)),"") -> 59400 | H6: =IFERROR(IF(D6="","",C6*$B$20),"") -> 40 | I6: =IFERROR(IF(D6="","",H6*B6*$B$21),"") -> 2000 | J6: Works the floor: purchasing, cash-out, suppliers and social media
A7: Head chef | B7: 1 | C7: 1 | D7: 4200 | E7: =IFERROR(IF(D7="","",D7*'0. Assumptions'!$B$20),"") -> 420 | F7: =IFERROR(IF(D7="","",D7+E7),"") -> 4620 | G7: =IFERROR(IF(D7="","",F7*MAX(12,'0. Assumptions'!$B$21)),"") -> 55440 | H7: =IFERROR(IF(D7="","",C7*$B$20),"") -> 40 | I7: =IFERROR(IF(D7="","",H7*B7*$B$21),"") -> 2000 | J7: Recipe costing, ordering and the hot line
A8: Line cooks | B8: 2 | C8: 1 | D8: 6400 | E8: =IFERROR(IF(D8="","",D8*'0. Assumptions'!$B$20),"") -> 640 | F8: =IFERROR(IF(D8="","",D8+E8),"") -> 7040 | G8: =IFERROR(IF(D8="","",F8*MAX(12,'0. Assumptions'!$B$21)),"") -> 84480 | H8: =IFERROR(IF(D8="","",C8*$B$20),"") -> 40 | I8: =IFERROR(IF(D8="","",H8*B8*$B$21),"") -> 4000 | J8: Mise en place, cold station and kitchen cleaning. Paid above the federal minimum wage on a full-time basis
A9: Servers / bartenders | B9: 2 | C9: 1 | D9: 5200 | E9: =IFERROR(IF(D9="","",D9*'0. Assumptions'!$B$20),"") -> 520 | F9: =IFERROR(IF(D9="","",D9+E9),"") -> 5720 | G9: =IFERROR(IF(D9="","",F9*MAX(12,'0. Assumptions'!$B$21)),"") -> 68640 | H9: =IFERROR(IF(D9="","",C9*$B$20),"") -> 40 | I9: =IFERROR(IF(D9="","",H9*B9*$B$21),"") -> 4000 | J9: Full time, covering both the lunch and the dinner service. Tips are not modeled (no tip credit): the base wage is set at 15 per hour or more. Federal law allows a cash wage of 2.13 per hour plus a tip credit where your state permits it; CA, OR, WA, AK, MN, MT and NV do not allow a tip credit (DOL)
A10: Part-time servers | B10: 2 | C10: 0.5 | D10: 2600 | E10: =IFERROR(IF(D10="","",D10*'0. Assumptions'!$B$20),"") -> 260 | F10: =IFERROR(IF(D10="","",D10+E10),"") -> 2860 | G10: =IFERROR(IF(D10="","",F10*MAX(12,'0. Assumptions'!$B$21)),"") -> 34320 | H10: =IFERROR(IF(D10="","",C10*$B$20),"") -> 20 | I10: =IFERROR(IF(D10="","",H10*B10*$B$21),"") -> 2000 | J10: Reinforcement for the two busy services. Same base wage and no tip credit as above; part-time pay is compared with the pay floor in proportion to FTE
A11: Dishwasher / weekend extra | B11: 1 | C11: 0.75 | D11: 1950 | E11: =IFERROR(IF(D11="","",D11*'0. Assumptions'!$B$20),"") -> 195 | F11: =IFERROR(IF(D11="","",D11+E11),"") -> 2145 | G11: =IFERROR(IF(D11="","",F11*MAX(12,'0. Assumptions'!$B$21)),"") -> 25740 | H11: =IFERROR(IF(D11="","",C11*$B$20),"") -> 30 | I11: =IFERROR(IF(D11="","",H11*B11*$B$21),"") -> 1500 | J11: Friday, Saturday and Sunday: dishwasher and extra hands for the busiest days
A12: Vacation and day-off relief | B12: 1 | C12: 0.2 | D12: 520 | E12: =IFERROR(IF(D12="","",D12*'0. Assumptions'!$B$20),"") -> 52 | F12: =IFERROR(IF(D12="","",D12+E12),"") -> 572 | G12: =IFERROR(IF(D12="","",F12*MAX(12,'0. Assumptions'!$B$21)),"") -> 6864 | H12: =IFERROR(IF(D12="","",C12*$B$20),"") -> 8 | I12: =IFERROR(IF(D12="","",H12*B12*$B$21),"") -> 400 | J12: Covers vacation, paid time off and the weekly day off for the six positions above. The US sets no federal vacation requirement, so this follows your own policy
A13: TOTAL STAFF | B13: =IFERROR(IF(COUNT(D6:D12)=0,"",SUM(B6:B12)),"") -> 10 | C13: =IFERROR(IF(COUNT(D6:D12)=0,"",SUMPRODUCT(B6:B12,C6:C12)),"") -> 7.95 | D13: =IFERROR(IF(COUNT(D6:D12)=0,"",SUM(D6:D12)),"") -> 25370 | E13: =IFERROR(IF(COUNT(D6:D12)=0,"",SUM(E6:E12)),"") -> 2537 | F13: =IFERROR(IF(COUNT(D6:D12)=0,"",SUM(F6:F12)),"") -> 27907 | G13: =IFERROR(IF(COUNT(D6:D12)=0,"",SUM(G6:G12)),"") -> 334884 | I13: =IFERROR(IF(COUNT(D6:D12)=0,"",SUM(I6:I12)),"") -> 15900
A14: STAFF GROWTH (stepped cost)
A15: Annual cost of year-2 hires | B15: 8000 | J15: FULL ANNUAL cost (gross pay + employer payroll taxes, over all pay periods) of whoever you hire that year. The P&L adds it to the previous year's cost: staffing grows by people, not by a percentage
A16: Annual cost of year-3 hires | B16: 8000 | J16: FULL ANNUAL cost (gross pay + employer payroll taxes, over all pay periods) of whoever you hire that year. The P&L adds it to the previous year's cost: staffing grows by people, not by a percentage
A17: Labor cost, year 2 | B17: =IFERROR(IF(G13="","",G13*(1+'0. Assumptions'!$B$48)+B15),"") -> 342884
A18: Labor cost, year 3 | B18: =IFERROR(IF(B17="","",B17*(1+'0. Assumptions'!$B$48)+B16),"") -> 350884
A19: COVERAGE OF SERVICE HOURS
A20: Full-time week (hours per week) | B20: 40 | J20: 40 hours a week is the FLSA overtime threshold for non-exempt employees; some states add daily overtime rules. Change it if your own full-time week is different
A21: Weeks worked per year per person | B21: 50 | J21: 50 weeks: 52 minus about two weeks of vacation, holidays and average absences. There is no federal vacation requirement in the US: adjust it to your own policy
A22: Service hours per day to cover | B22: 12 | J22: From opening to closing, bar included. Count them on your real schedule
A23: People needed at the same time in each shift | B23: 4 | J23: Average number of people present at the same time across kitchen, bar and floor. The two busy services need more and mid-afternoon needs fewer
A24: Service hours to cover per year | B24: =IFERROR(IF(OR(B22="",B23="",'0. Assumptions'!$B$6=""),"",B22*B23*'0. Assumptions'!$B$6),"") -> 14880
A25: Hours hired per year | B25: =IFERROR(IF(I13="","",I13),"") -> 15900
A26: Coverage (hired / needed) | B26: =IFERROR(B25/B24,"") -> 1.0685484 | J26: Below 100% the staff cannot cover the hours the plan declares: either hire more or cut the hours
A28: The gross pay, employer payroll taxes, monthly cost and annual cost columns are TOTALS for the row: for a position with two people they include both. FTE is the share of a full-time week for each person, and it is used to compare pay with the legal minimum in proportion; the TOTAL row multiplies it by the people in each position, so it gives the full-time equivalents of the whole team. The payroll tax rate and the number of pay periods are in the "0. Assumptions" tab.
A29: The pay floor is the HIGHER of the federal minimum wage and your state / local minimum wage, both in the "0. Assumptions" tab; part-time positions get it in proportion. There is no single national table above the federal floor: the state / local cell is delivered empty so you can enter the rate for your state and city.
A30: AI Chef Pro · aichef.pro/en/digital-products/restaurant-business-plan

Sheet Instructions
A1: INSTRUCTIONS FOR USE — Restaurant Financial Projections (Casual Restaurant & Bar)
A3: HOW TO USE THIS WORKBOOK
A4: This financial plan is a MODEL: you type only in the GREEN cells and everything else recalculates on its own.
A5: 1. "0. Assumptions" is the control sheet: covers per day, average check excl. sales tax, operating days, food and beverage mix, cost of goods sold, rent, financing and taxes.
A6: 2. Startup cost items, fixed costs and staffing are typed in their own tab, also in green. No number is typed twice.
A7: 3. On "3. Break-Even" you only type the seat-turn ceiling your space allows; everything else derives from the rest. The other tabs also have green cells you can change: the pessimistic and optimistic scenarios on "4. Scenarios", the seasonality and the launch ramp-up on "6. 12-Month Cash Flow", and the other funding sources on "7. Financing" (rows 8-11 count as sources but are not amortized: your bank or SBA 7(a) loan goes in "Loan requested" on "0. Assumptions"). Everything else is calculated.
A8: 4. All figures are EXCL. SALES TAX. To turn a menu price into a price excl. sales tax, divide it by 1 + your sales tax rate (with an 8% rate, divide by 1.08); if an item is taxed at a different rate (alcohol to go, for instance), use that rate. The rate of each sales line is in the "Sales tax rate on the line (%)" column of the P&L, and from it come the receipts, the sales tax collected and the equivalent menu price incl. sales tax. With the default 0% recoverable input tax, the sales tax you pay on purchases and startup costs is treated as a cost; in the UK, enter 20% if you are VAT-registered.
A9: 5. If you change the staffing, the P&L reads it on its own: labor cost comes from the "Staffing" tab, not from a separate estimate.
A10: 6. The "6. 12-Month Cash Flow" tab answers the question that decides a loan: in which month the cash runs out. The minimum balance of the year can never be in red.
A11: 7. The "7. Financing" tab matches what you need with what you put in and builds the amortization schedule of the loan. If the difference is red, the plan is not funded.
A13: RATIOS AUDITED BY THIS WORKBOOK
A14: Thresholds live in the "Threshold" column of the KEY RATIOS block of the P&L: change them there and the traffic light changes with them.
A16: Ratio | B16: Year 1 value | C16: Threshold | D16: Status
A17: Cost of goods sold / Sales | B17: =IFERROR(IF('2. 3-Year P&L'!$B$55="","",'2. 3-Year P&L'!$B$55),"") -> 0.275 | C17: =IFERROR(IF('2. 3-Year P&L'!$E$55="","",'2. 3-Year P&L'!$E$55),"") -> 0.32 | D17: =IFERROR(IF(OR(B17="",C17=""),"",IF(B17<=C17,"OK","REVIEW")),"") -> OK
A18: Labor cost / Sales | B18: =IFERROR(IF('2. 3-Year P&L'!$B$56="","",'2. 3-Year P&L'!$B$56),"") -> 0.30864885 | C18: =IFERROR(IF('2. 3-Year P&L'!$E$56="","",'2. 3-Year P&L'!$E$56),"") -> 0.35 | D18: =IFERROR(IF(OR(B18="",C18=""),"",IF(B18<=C18,"OK","REVIEW")),"") -> OK
A19: Rent / Sales | B19: =IFERROR(IF('2. 3-Year P&L'!$B$57="","",'2. 3-Year P&L'!$B$57),"") -> 0.077419355 | C19: =IFERROR(IF('2. 3-Year P&L'!$E$57="","",'2. 3-Year P&L'!$E$57),"") -> 0.1 | D19: =IFERROR(IF(OR(B19="",C19=""),"",IF(B19<=C19,"OK","REVIEW")),"") -> OK
A20: Net income / Sales | B20: =IFERROR(IF('2. 3-Year P&L'!$B$58="","",'2. 3-Year P&L'!$B$58),"") -> 0.078562574 | C20: =IFERROR(IF('2. 3-Year P&L'!$E$58="","",'2. 3-Year P&L'!$E$58),"") -> 0.05 | D20: =IFERROR(IF(OR(B20="",C20=""),"",IF(B20>=C20,"OK","REVIEW")),"") -> OK
A21: Gross margin / Sales | B21: =IFERROR(IF('2. 3-Year P&L'!$B$53="","",'2. 3-Year P&L'!$B$53),"") -> 0.655 | C21: =IFERROR(IF('2. 3-Year P&L'!$E$53="","",'2. 3-Year P&L'!$E$53),"") -> 0.65 | D21: =IFERROR(IF(OR(B21="",C21=""),"",IF(B21>=C21,"OK","REVIEW")),"") -> OK
A23: THIS PLAN'S KEY FIGURES
A24: Total startup costs (sum of the blocks) | B24: =IFERROR(IF('1. Startup Costs'!$B$48="","",'1. Startup Costs'!$B$48),"") -> 528696
A25: Total cash needed at launch | B25: =IFERROR(IF('1. Startup Costs'!$B$51="","",'1. Startup Costs'!$B$51),"") -> 528696
A26: Working capital funded | B26: =IFERROR(IF('1. Startup Costs'!$B$47="","",'1. Startup Costs'!$B$47),"") -> 139996
A27: Forecast year-1 revenue | B27: =IFERROR(IF('2. 3-Year P&L'!$B$10="","",'2. 3-Year P&L'!$B$10),"") -> 1085000
A28: Year-1 net income | B28: =IFERROR(IF('2. 3-Year P&L'!$B$50="","",'2. 3-Year P&L'!$B$50),"") -> 85240.393
A29: Covers per day for the ACCOUNTING break-even (depreciation included) | B29: =IFERROR(IF('3. Break-Even'!$B$16="","",'3. Break-Even'!$B$16),"") -> 105.00952
A30: Project payback (years), before debt | B30: =IFERROR(IF('6. 12-Month Cash Flow'!$B$31="","",'6. 12-Month Cash Flow'!$B$31),"") -> 2.7
A32: WHY THIS MODEL IS BUILT THIS WAY
A33: Item | B33: Common shortcut | C33: This workbook | D33: Why
A34: Labor cost in the P&L | B34: A typed-in number, disconnected from the staffing tab | C34: The total of the "5. Staffing" tab, by formula | D34: When the P&L and the staffing tab disagree, nobody knows which one to trust. Here both say the same thing, and if you change a salary the result changes on its own.
A35: Staffing | B35: A handful of positions sized by guesswork | C35: Positions, including part-time lines and relief coverage, sized to the service hours you declare | D35: Labor is sized to the hours of service this workbook declares, so the payroll comes from the schedule and is then tested against the labor-cost ceiling in the industry benchmarks table.
A36: Covers per day, year 1 | B36: Backed out of a revenue target | C36: Typed in as an input and tested against the seat count | D36: Covers per day is a driver, not a plug. Compare the seat turns it implies on the "0. Assumptions" tab with the ceiling your space allows on the "3. Break-Even" tab.
A37: Average check | B37: A single number, without saying whether it includes sales tax | C37: Entered EXCL. sales tax | D37: Revenue is booked excl. sales tax, as it appears in your P&L. The workbook calculates the equivalent menu price incl. sales tax so you can compare it with your real menu and with the benchmark range.
A38: Rent | B38: A monthly figure with no link to sales | C38: A monthly rent on the "0. Assumptions" tab, tested as a percentage of sales | D38: The "2. 3-Year P&L" shows rent against the 10% of sales ceiling, so you see right away whether the location is viable.
A39: Utilities | B39: A low flat estimate that ignores the equipment | C39: A monthly figure sized to a kitchen with ovens, coolers and a hood | D39: A kitchen with ovens, walk-in coolers and a Type I hood does not run on a token share of sales: ask for the space's utility history and enter a realistic bill.
A40: Working capital | B40: A round number with a "3 months" label | C40: 3 months of cash fixed costs, by formula | D40: A typed figure can cover far fewer months than its label says. A formula recalculates by itself whenever you change any expense.
A41: Depreciation | B41: A flat annual number with an implied base nobody can trace | C41: Real depreciable base divided by useful life, by formula | D41: The fixed assets listed in this workbook add up to more than a rule of thumb suggests, and working capital is never depreciated.
A42: Loan payment in the P&L | B42: The full payment, principal included | C42: Interest only; principal repaid goes to the cash flow | D42: Putting the full payment above the line turns the P&L into a cash flow, and a lender spots it immediately.
A43: Income tax | B43: A flat rate that ignores the losses of the first year | C43: An effective income tax rate (years 1-2 and from year 3), with net operating losses carried forward | D43: Early losses offset later profits, so the model carries them forward. Federal rules cap the offset at 80% of taxable income and the model offsets 100%, a declared simplification. If your business is a pass-through entity, set the rate to 0% and remember that you pay the tax on your personal return.
A44: Delivery platform fees | B44: A percentage of ALL revenue, with no switch | C44: Share of sales through the channel × platform commission, at 0 by default | D44: If you do not deliver, you do not carry an invented cost.
A45: Beverage cost | B45: A food-cost percentage applied to the total PLUS a separate beverage percentage | C45: Each product family carries its own cost rate | D45: Applying both rates to the same sales charges the beverage cost twice. Here food and beverage each pay their own cost, once.
A47: INDUSTRY BENCHMARKS
A48: Benchmark | B48: Value | C48: Source | D48: Note
A49: Average check, casual restaurant (menu price) | B49: 25-40 | C49: Kit estimate | D49: The menu-price equivalent of this plan is calculated on the "0. Assumptions" tab
A50: Rent for a casual restaurant of about 2,800 sq ft in an urban area | B50: About 7,000 per month | C50: Kit estimate
A51: Food cost target | B51: 25-35% | C51: Kit estimate
A52: Labor cost / Sales | B52: 25-33% | C52: Kit estimate | D52: The "2. 3-Year P&L" flags labor above 35% of sales (kit benchmark, editable estimate)
A53: Net margin | B53: 5% or more | C53: Kit estimate
A54: Break-even | B54: Reachable within 12 months | C54: Kit estimate
A55: Average opening investment | B55: 175,000-400,000 (survey median 375,500) | C55: DoorDash for Merchants (merchants.doordash.com) | D55: This is the industry reference range. The investment in THIS plan is calculated on the "1. Startup Costs" tab: if it lands above the range, it is because it includes working capital, opening inventory and a build-out contingency, which reference ranges do not always count
A56: Liquor license (state + local) | B56: From 50 to 300,000+ | C56: Webstaurant Store (webstaurantstore.com) | D56: This workbook budgets a non-quota state example; in quota states you buy an existing license
A57: Prime cost (food + labor) | B57: 60-65% of sales | C57: Restaurant365 (restaurant365.com)
A58: Applicable state / local minimum wage | B58: State and local minimum wage | C58: DOL (dol.gov/agencies/whd/minimum-wage) | D58: There is no single national table above the federal floor: look up the rate for your state and city and enter it on the "0. Assumptions" tab
A60: To edit a cell that is not green: Review → Unprotect Sheet (there is no password).
A61: More templates and kits in the catalog at aichef.pro/en/digital-products
A62: Designed by John Guerrero — chef and restaurant consultant since 2010, in the kitchen since age 17 · johnguerrero.es
A63: Version 2.2 · October 2026 · aichef.pro/en/digital-products/restaurant-business-plan · info@aichef.pro
A64: Planning tool, not financial, tax or legal advice. Requirements vary by state, county and city — check with your accountant and local authorities.

Sheet 6. 12-Month Cash Flow
A1: CASH FLOW FORECAST — YEAR 1
A2: The P&L tells you whether the business makes money; this tab tells you whether you have cash left to get to the end of the month. It is the first one a lender looks at.
A4: Item | B4: Month 1 | C4: Month 2 | D4: Month 3 | E4: Month 4 | F4: Month 5 | G4: Month 6 | H4: Month 7 | I4: Month 8 | J4: Month 9 | K4: Month 10 | L4: Month 11 | M4: Month 12 | N4: Year
A5: Monthly seasonality (adds up to 100%) | B5: 0.07 | C5: 0.072 | D5: 0.082 | E5: 0.085 | F5: 0.09 | G5: 0.088 | H5: 0.085 | I5: 0.062 | J5: 0.085 | K5: 0.088 | L5: 0.087 | M5: 0.106 | N5: =IFERROR(IF('2. 3-Year P&L'!$B$10="","",SUM(B5:M5)),"") -> 1 | O5: Profile for your area: adjust it to your own slow and busy months (weather, tourism, events). It must add up to 100%
A6: Launch ramp-up (% of steady-state activity) | B6: =IFERROR(IF('2. 3-Year P&L'!$B$10="","",MIN(1,'0. Assumptions'!$B$52+(1-'0. Assumptions'!$B$52)*0/MAX(1,'0. Assumptions'!$B$53-1))),"") -> 0.55 | C6: =IFERROR(IF('2. 3-Year P&L'!$B$10="","",MIN(1,'0. Assumptions'!$B$52+(1-'0. Assumptions'!$B$52)*1/MAX(1,'0. Assumptions'!$B$53-1))),"") -> 0.64 | D6: =IFERROR(IF('2. 3-Year P&L'!$B$10="","",MIN(1,'0. Assumptions'!$B$52+(1-'0. Assumptions'!$B$52)*2/MAX(1,'0. Assumptions'!$B$53-1))),"") -> 0.73 | E6: =IFERROR(IF('2. 3-Year P&L'!$B$10="","",MIN(1,'0. Assumptions'!$B$52+(1-'0. Assumptions'!$B$52)*3/MAX(1,'0. Assumptions'!$B$53-1))),"") -> 0.82 | F6: =IFERROR(IF('2. 3-Year P&L'!$B$10="","",MIN(1,'0. Assumptions'!$B$52+(1-'0. Assumptions'!$B$52)*4/MAX(1,'0. Assumptions'!$B$53-1))),"") -> 0.91 | G6: =IFERROR(IF('2. 3-Year P&L'!$B$10="","",MIN(1,'0. Assumptions'!$B$52+(1-'0. Assumptions'!$B$52)*5/MAX(1,'0. Assumptions'!$B$53-1))),"") -> 1 | H6: =IFERROR(IF('2. 3-Year P&L'!$B$10="","",MIN(1,'0. Assumptions'!$B$52+(1-'0. Assumptions'!$B$52)*6/MAX(1,'0. Assumptions'!$B$53-1))),"") -> 1 | I6: =IFERROR(IF('2. 3-Year P&L'!$B$10="","",MIN(1,'0. Assumptions'!$B$52+(1-'0. Assumptions'!$B$52)*7/MAX(1,'0. Assumptions'!$B$53-1))),"") -> 1 | J6: =IFERROR(IF('2. 3-Year P&L'!$B$10="","",MIN(1,'0. Assumptions'!$B$52+(1-'0. Assumptions'!$B$52)*8/MAX(1,'0. Assumptions'!$B$53-1))),"") -> 1 | K6: =IFERROR(IF('2. 3-Year P&L'!$B$10="","",MIN(1,'0. Assumptions'!$B$52+(1-'0. Assumptions'!$B$52)*9/MAX(1,'0. Assumptions'!$B$53-1))),"") -> 1 | L6: =IFERROR(IF('2. 3-Year P&L'!$B$10="","",MIN(1,'0. Assumptions'!$B$52+(1-'0. Assumptions'!$B$52)*10/MAX(1,'0. Assumptions'!$B$53-1))),"") -> 1 | M6: =IFERROR(IF('2. 3-Year P&L'!$B$10="","",MIN(1,'0. Assumptions'!$B$52+(1-'0. Assumptions'!$B$52)*11/MAX(1,'0. Assumptions'!$B$53-1))),"") -> 1 | O6: Rises in a straight line from the month-1 percentage to 100% over the number of months you set in Assumptions. With month 1 at 100%, the ramp disappears
A7: Split of activity by month (calculated) | B7: =IFERROR(IF('2. 3-Year P&L'!$B$10="","",B5*B6/SUMPRODUCT($B$5:$M$5,$B$6:$M$6)),"") -> 0.042918933 | C7: =IFERROR(IF('2. 3-Year P&L'!$B$10="","",C5*C6/SUMPRODUCT($B$5:$M$5,$B$6:$M$6)),"") -> 0.051368947 | D7: =IFERROR(IF('2. 3-Year P&L'!$B$10="","",D5*D6/SUMPRODUCT($B$5:$M$5,$B$6:$M$6)),"") -> 0.066730581 | E7: =IFERROR(IF('2. 3-Year P&L'!$B$10="","",E5*E6/SUMPRODUCT($B$5:$M$5,$B$6:$M$6)),"") -> 0.077699991 | F7: =IFERROR(IF('2. 3-Year P&L'!$B$10="","",F5*F6/SUMPRODUCT($B$5:$M$5,$B$6:$M$6)),"") -> 0.091300276 | G7: =IFERROR(IF('2. 3-Year P&L'!$B$10="","",G5*G6/SUMPRODUCT($B$5:$M$5,$B$6:$M$6)),"") -> 0.098100419 | H7: =IFERROR(IF('2. 3-Year P&L'!$B$10="","",H5*H6/SUMPRODUCT($B$5:$M$5,$B$6:$M$6)),"") -> 0.094756087 | I7: =IFERROR(IF('2. 3-Year P&L'!$B$10="","",I5*I6/SUMPRODUCT($B$5:$M$5,$B$6:$M$6)),"") -> 0.069116204 | ... M7: =IFERROR(IF('2. 3-Year P&L'!$B$10="","",M5*M6/SUMPRODUCT($B$5:$M$5,$B$6:$M$6)),"") -> 0.11816641 | N7: =IFERROR(IF('2. 3-Year P&L'!$B$10="","",SUM(B7:M7)),"") -> 1 | O7: Seasonality × ramp-up, normalized to 100%: the YEAR brings in what the P&L says, but split the way a business that has just opened would split it
A8: CASH IN
A9: Sales collected (incl. sales tax collected) | B9: =IFERROR(IF('2. 3-Year P&L'!$B$10="","",('2. 3-Year P&L'!$B$10+'2. 3-Year P&L'!$B$10*SUMPRODUCT('2. 3-Year P&L'!$E$11:$E$12,'2. 3-Year P&L'!$G$11:$G$12))*B7*(1-MIN(30,'0. Assumptions'!$B$58)/30)),"") -> 48615.993 | C9: =IFERROR(IF('2. 3-Year P&L'!$B$10="","",('2. 3-Year P&L'!$B$10+'2. 3-Year P&L'!$B$10*SUMPRODUCT('2. 3-Year P&L'!$E$11:$E$12,'2. 3-Year P&L'!$G$11:$G$12))*(C7*(1-MIN(30,'0. Assumptions'!$B$58)/30)+B7*MIN(30,'0. Assumptions'!$B$58)/30)),"") -> 59864.074 | D9: =IFERROR(IF('2. 3-Year P&L'!$B$10="","",('2. 3-Year P&L'!$B$10+'2. 3-Year P&L'!$B$10*SUMPRODUCT('2. 3-Year P&L'!$E$11:$E$12,'2. 3-Year P&L'!$G$11:$G$12))*(D7*(1-MIN(30,'0. Assumptions'!$B$58)/30)+C7*MIN(30,'0. Assumptions'!$B$58)/30)),"") -> 77594.869 | E9: =IFERROR(IF('2. 3-Year P&L'!$B$10="","",('2. 3-Year P&L'!$B$10+'2. 3-Year P&L'!$B$10*SUMPRODUCT('2. 3-Year P&L'!$E$11:$E$12,'2. 3-Year P&L'!$G$11:$G$12))*(E7*(1-MIN(30,'0. Assumptions'!$B$58)/30)+D7*MIN(30,'0. Assumptions'!$B$58)/30)),"") -> 90620.384 | F9: =IFERROR(IF('2. 3-Year P&L'!$B$10="","",('2. 3-Year P&L'!$B$10+'2. 3-Year P&L'!$B$10*SUMPRODUCT('2. 3-Year P&L'!$E$11:$E$12,'2. 3-Year P&L'!$G$11:$G$12))*(F7*(1-MIN(30,'0. Assumptions'!$B$58)/30)+E7*MIN(30,'0. Assumptions'!$B$58)/30)),"") -> 106454.44 | G9: =IFERROR(IF('2. 3-Year P&L'!$B$10="","",('2. 3-Year P&L'!$B$10+'2. 3-Year P&L'!$B$10*SUMPRODUCT('2. 3-Year P&L'!$E$11:$E$12,'2. 3-Year P&L'!$G$11:$G$12))*(G7*(1-MIN(30,'0. Assumptions'!$B$58)/30)+F7*MIN(30,'0. Assumptions'!$B$58)/30)),"") -> 114688.46 | H9: =IFERROR(IF('2. 3-Year P&L'!$B$10="","",('2. 3-Year P&L'!$B$10+'2. 3-Year P&L'!$B$10*SUMPRODUCT('2. 3-Year P&L'!$E$11:$E$12,'2. 3-Year P&L'!$G$11:$G$12))*(H7*(1-MIN(30,'0. Assumptions'!$B$58)/30)+G7*MIN(30,'0. Assumptions'!$B$58)/30)),"") -> 111165.81 | I9: =IFERROR(IF('2. 3-Year P&L'!$B$10="","",('2. 3-Year P&L'!$B$10+'2. 3-Year P&L'!$B$10*SUMPRODUCT('2. 3-Year P&L'!$E$11:$E$12,'2. 3-Year P&L'!$G$11:$G$12))*(I7*(1-MIN(30,'0. Assumptions'!$B$58)/30)+H7*MIN(30,'0. Assumptions'!$B$58)/30)),"") -> 81991.862 | J9: =IFERROR(IF('2. 3-Year P&L'!$B$10="","",('2. 3-Year P&L'!$B$10+'2. 3-Year P&L'!$B$10*SUMPRODUCT('2. 3-Year P&L'!$E$11:$E$12,'2. 3-Year P&L'!$G$11:$G$12))*(J7*(1-MIN(30,'0. Assumptions'!$B$58)/30)+I7*MIN(30,'0. Assumptions'!$B$58)/30)),"") -> 110033.69 | ... M9: =IFERROR(IF('2. 3-Year P&L'!$B$10="","",('2. 3-Year P&L'!$B$10+'2. 3-Year P&L'!$B$10*SUMPRODUCT('2. 3-Year P&L'!$E$11:$E$12,'2. 3-Year P&L'!$G$11:$G$12))*(M7*(1-MIN(30,'0. Assumptions'!$B$58)/30)+L7*MIN(30,'0. Assumptions'!$B$58)/30)),"") -> 137640.08 | N9: =IFERROR(IF('2. 3-Year P&L'!$B$10="","",SUM(B9:M9)),"") -> 1167184.4 | O9: The month's sales plus the sales tax collected, adjusted by the average collection days from the Assumptions tab
A10: CASH OUT
A11: Purchases and variable costs (incl. sales tax) | B11: =IFERROR(IF('2. 3-Year P&L'!$B$10="","",-('2. 3-Year P&L'!$B$14*(1+'2. 3-Year P&L'!$G$14)+'2. 3-Year P&L'!$B$15*(1+'2. 3-Year P&L'!$G$15)+'2. 3-Year P&L'!$B$16*(1+'2. 3-Year P&L'!$G$16)+'2. 3-Year P&L'!$B$17*(1+'2. 3-Year P&L'!$G$17)+'2. 3-Year P&L'!$B$18*(1+'2. 3-Year P&L'!$G$18)+'2. 3-Year P&L'!$B$19*(1+'2. 3-Year P&L'!$G$19))*B7*(1-MIN(30,'0. Assumptions'!$B$59)/30)),"") -> -8568.3359 | C11: =IFERROR(IF('2. 3-Year P&L'!$B$10="","",-('2. 3-Year P&L'!$B$14*(1+'2. 3-Year P&L'!$G$14)+'2. 3-Year P&L'!$B$15*(1+'2. 3-Year P&L'!$G$15)+'2. 3-Year P&L'!$B$16*(1+'2. 3-Year P&L'!$G$16)+'2. 3-Year P&L'!$B$17*(1+'2. 3-Year P&L'!$G$17)+'2. 3-Year P&L'!$B$18*(1+'2. 3-Year P&L'!$G$18)+'2. 3-Year P&L'!$B$19*(1+'2. 3-Year P&L'!$G$19))*(C7*(1-MIN(30,'0. Assumptions'!$B$59)/30)+B7*MIN(30,'0. Assumptions'!$B$59)/30)),"") -> -17752.59 | D11: =IFERROR(IF('2. 3-Year P&L'!$B$10="","",-('2. 3-Year P&L'!$B$14*(1+'2. 3-Year P&L'!$G$14)+'2. 3-Year P&L'!$B$15*(1+'2. 3-Year P&L'!$G$15)+'2. 3-Year P&L'!$B$16*(1+'2. 3-Year P&L'!$G$16)+'2. 3-Year P&L'!$B$17*(1+'2. 3-Year P&L'!$G$17)+'2. 3-Year P&L'!$B$18*(1+'2. 3-Year P&L'!$G$18)+'2. 3-Year P&L'!$B$19*(1+'2. 3-Year P&L'!$G$19))*(D7*(1-MIN(30,'0. Assumptions'!$B$59)/30)+C7*MIN(30,'0. Assumptions'!$B$59)/30)),"") -> -22295.478 | E11: =IFERROR(IF('2. 3-Year P&L'!$B$10="","",-('2. 3-Year P&L'!$B$14*(1+'2. 3-Year P&L'!$G$14)+'2. 3-Year P&L'!$B$15*(1+'2. 3-Year P&L'!$G$15)+'2. 3-Year P&L'!$B$16*(1+'2. 3-Year P&L'!$G$16)+'2. 3-Year P&L'!$B$17*(1+'2. 3-Year P&L'!$G$17)+'2. 3-Year P&L'!$B$18*(1+'2. 3-Year P&L'!$G$18)+'2. 3-Year P&L'!$B$19*(1+'2. 3-Year P&L'!$G$19))*(E7*(1-MIN(30,'0. Assumptions'!$B$59)/30)+D7*MIN(30,'0. Assumptions'!$B$59)/30)),"") -> -27168.858 | F11: =IFERROR(IF('2. 3-Year P&L'!$B$10="","",-('2. 3-Year P&L'!$B$14*(1+'2. 3-Year P&L'!$G$14)+'2. 3-Year P&L'!$B$15*(1+'2. 3-Year P&L'!$G$15)+'2. 3-Year P&L'!$B$16*(1+'2. 3-Year P&L'!$G$16)+'2. 3-Year P&L'!$B$17*(1+'2. 3-Year P&L'!$G$17)+'2. 3-Year P&L'!$B$18*(1+'2. 3-Year P&L'!$G$18)+'2. 3-Year P&L'!$B$19*(1+'2. 3-Year P&L'!$G$19))*(F7*(1-MIN(30,'0. Assumptions'!$B$59)/30)+E7*MIN(30,'0. Assumptions'!$B$59)/30)),"") -> -31800.21 | G11: =IFERROR(IF('2. 3-Year P&L'!$B$10="","",-('2. 3-Year P&L'!$B$14*(1+'2. 3-Year P&L'!$G$14)+'2. 3-Year P&L'!$B$15*(1+'2. 3-Year P&L'!$G$15)+'2. 3-Year P&L'!$B$16*(1+'2. 3-Year P&L'!$G$16)+'2. 3-Year P&L'!$B$17*(1+'2. 3-Year P&L'!$G$17)+'2. 3-Year P&L'!$B$18*(1+'2. 3-Year P&L'!$G$18)+'2. 3-Year P&L'!$B$19*(1+'2. 3-Year P&L'!$G$19))*(G7*(1-MIN(30,'0. Assumptions'!$B$59)/30)+F7*MIN(30,'0. Assumptions'!$B$59)/30)),"") -> -35533.556 | H11: =IFERROR(IF('2. 3-Year P&L'!$B$10="","",-('2. 3-Year P&L'!$B$14*(1+'2. 3-Year P&L'!$G$14)+'2. 3-Year P&L'!$B$15*(1+'2. 3-Year P&L'!$G$15)+'2. 3-Year P&L'!$B$16*(1+'2. 3-Year P&L'!$G$16)+'2. 3-Year P&L'!$B$17*(1+'2. 3-Year P&L'!$G$17)+'2. 3-Year P&L'!$B$18*(1+'2. 3-Year P&L'!$G$18)+'2. 3-Year P&L'!$B$19*(1+'2. 3-Year P&L'!$G$19))*(H7*(1-MIN(30,'0. Assumptions'!$B$59)/30)+G7*MIN(30,'0. Assumptions'!$B$59)/30)),"") -> -36053.777 | I11: =IFERROR(IF('2. 3-Year P&L'!$B$10="","",-('2. 3-Year P&L'!$B$14*(1+'2. 3-Year P&L'!$G$14)+'2. 3-Year P&L'!$B$15*(1+'2. 3-Year P&L'!$G$15)+'2. 3-Year P&L'!$B$16*(1+'2. 3-Year P&L'!$G$16)+'2. 3-Year P&L'!$B$17*(1+'2. 3-Year P&L'!$G$17)+'2. 3-Year P&L'!$B$18*(1+'2. 3-Year P&L'!$G$18)+'2. 3-Year P&L'!$B$19*(1+'2. 3-Year P&L'!$G$19))*(I7*(1-MIN(30,'0. Assumptions'!$B$59)/30)+H7*MIN(30,'0. Assumptions'!$B$59)/30)),"") -> -30350.826 | J11: =IFERROR(IF('2. 3-Year P&L'!$B$10="","",-('2. 3-Year P&L'!$B$14*(1+'2. 3-Year P&L'!$G$14)+'2. 3-Year P&L'!$B$15*(1+'2. 3-Year P&L'!$G$15)+'2. 3-Year P&L'!$B$16*(1+'2. 3-Year P&L'!$G$16)+'2. 3-Year P&L'!$B$17*(1+'2. 3-Year P&L'!$G$17)+'2. 3-Year P&L'!$B$18*(1+'2. 3-Year P&L'!$G$18)+'2. 3-Year P&L'!$B$19*(1+'2. 3-Year P&L'!$G$19))*(J7*(1-MIN(30,'0. Assumptions'!$B$59)/30)+I7*MIN(30,'0. Assumptions'!$B$59)/30)),"") -> -30990.669 | ... M11: =IFERROR(IF('2. 3-Year P&L'!$B$10="","",-('2. 3-Year P&L'!$B$14*(1+'2. 3-Year P&L'!$G$14)+'2. 3-Year P&L'!$B$15*(1+'2. 3-Year P&L'!$G$15)+'2. 3-Year P&L'!$B$16*(1+'2. 3-Year P&L'!$G$16)+'2. 3-Year P&L'!$B$17*(1+'2. 3-Year P&L'!$G$17)+'2. 3-Year P&L'!$B$18*(1+'2. 3-Year P&L'!$G$18)+'2. 3-Year P&L'!$B$19*(1+'2. 3-Year P&L'!$G$19))*(M7*(1-MIN(30,'0. Assumptions'!$B$59)/30)+L7*MIN(30,'0. Assumptions'!$B$59)/30)),"") -> -40532.68 | N11: =IFERROR(IF('2. 3-Year P&L'!$B$10="","",SUM(B11:M11)),"") -> -353683.1 | O11: =IFERROR("Food and beverage purchases, consumables, fees and contingencies, each at ITS tax rate (column G of the P&L; 0 in the US, where the sales tax you pay is part of the cost) and with the supplier payment days from ""0. Assumptions""."&IF('0. Assumptions'!$B$59=0,""," With "&TEXT('0. Assumptions'!$B$59,"0")&" payment days, the last purchases of the year are paid next year: the ""Year"" column of this row holds "&TEXT(MAX(0,12-ROUNDUP('0. Assumptions'!$B$59/30,0)),"0")&" months of purchases, not the year's cost."),"") -> Food and beverage purchases, consumables, fees and contingencies, each at ITS tax rate (column G of the P&L; 0 in the US, where the sales tax you pay is part of the cost) and with the supplier payment days from "0. Assumptions". With 14 payment days, the last purchases of the year are paid next year: the "Year" column of this row holds 11 months of purchases, not the year's cost.
A12: Operating fixed costs (incl. sales tax) | B12: =IFERROR(IF('2. 3-Year P&L'!$B$10="","",-('2. 3-Year P&L'!$B$40-'2. 3-Year P&L'!$B$24-'2. 3-Year P&L'!$B$38-'2. 3-Year P&L'!$B$39+'2. 3-Year P&L'!$B$42)/12),"") -> -15433.333 | C12: =IFERROR(IF('2. 3-Year P&L'!$B$10="","",-('2. 3-Year P&L'!$B$40-'2. 3-Year P&L'!$B$24-'2. 3-Year P&L'!$B$38-'2. 3-Year P&L'!$B$39+'2. 3-Year P&L'!$B$42)/12),"") -> -15433.333 | D12: =IFERROR(IF('2. 3-Year P&L'!$B$10="","",-('2. 3-Year P&L'!$B$40-'2. 3-Year P&L'!$B$24-'2. 3-Year P&L'!$B$38-'2. 3-Year P&L'!$B$39+'2. 3-Year P&L'!$B$42)/12),"") -> -15433.333 | E12: =IFERROR(IF('2. 3-Year P&L'!$B$10="","",-('2. 3-Year P&L'!$B$40-'2. 3-Year P&L'!$B$24-'2. 3-Year P&L'!$B$38-'2. 3-Year P&L'!$B$39+'2. 3-Year P&L'!$B$42)/12),"") -> -15433.333 | F12: =IFERROR(IF('2. 3-Year P&L'!$B$10="","",-('2. 3-Year P&L'!$B$40-'2. 3-Year P&L'!$B$24-'2. 3-Year P&L'!$B$38-'2. 3-Year P&L'!$B$39+'2. 3-Year P&L'!$B$42)/12),"") -> -15433.333 | G12: =IFERROR(IF('2. 3-Year P&L'!$B$10="","",-('2. 3-Year P&L'!$B$40-'2. 3-Year P&L'!$B$24-'2. 3-Year P&L'!$B$38-'2. 3-Year P&L'!$B$39+'2. 3-Year P&L'!$B$42)/12),"") -> -15433.333 | H12: =IFERROR(IF('2. 3-Year P&L'!$B$10="","",-('2. 3-Year P&L'!$B$40-'2. 3-Year P&L'!$B$24-'2. 3-Year P&L'!$B$38-'2. 3-Year P&L'!$B$39+'2. 3-Year P&L'!$B$42)/12),"") -> -15433.333 | I12: =IFERROR(IF('2. 3-Year P&L'!$B$10="","",-('2. 3-Year P&L'!$B$40-'2. 3-Year P&L'!$B$24-'2. 3-Year P&L'!$B$38-'2. 3-Year P&L'!$B$39+'2. 3-Year P&L'!$B$42)/12),"") -> -15433.333 | ... M12: =IFERROR(IF('2. 3-Year P&L'!$B$10="","",-('2. 3-Year P&L'!$B$40-'2. 3-Year P&L'!$B$24-'2. 3-Year P&L'!$B$38-'2. 3-Year P&L'!$B$39+'2. 3-Year P&L'!$B$42)/12),"") -> -15433.333 | N12: =IFERROR(IF('2. 3-Year P&L'!$B$10="","",SUM(B12:M12)),"") -> -185200 | O12: The fixed costs that leave cash, each with its own tax rate: insurance carries none
A13: Payroll and employer payroll taxes | B13: =IFERROR(IF('2. 3-Year P&L'!$B$10="","",-'2. 3-Year P&L'!$B$24/MAX(12,'0. Assumptions'!$B$21)*(1+IF(1='0. Assumptions'!$B$60,(MAX(12,'0. Assumptions'!$B$21)-12)/2,0)+IF(1='0. Assumptions'!$B$61,(MAX(12,'0. Assumptions'!$B$21)-12)/2,0))),"") -> -27907 | C13: =IFERROR(IF('2. 3-Year P&L'!$B$10="","",-'2. 3-Year P&L'!$B$24/MAX(12,'0. Assumptions'!$B$21)*(1+IF(2='0. Assumptions'!$B$60,(MAX(12,'0. Assumptions'!$B$21)-12)/2,0)+IF(2='0. Assumptions'!$B$61,(MAX(12,'0. Assumptions'!$B$21)-12)/2,0))),"") -> -27907 | D13: =IFERROR(IF('2. 3-Year P&L'!$B$10="","",-'2. 3-Year P&L'!$B$24/MAX(12,'0. Assumptions'!$B$21)*(1+IF(3='0. Assumptions'!$B$60,(MAX(12,'0. Assumptions'!$B$21)-12)/2,0)+IF(3='0. Assumptions'!$B$61,(MAX(12,'0. Assumptions'!$B$21)-12)/2,0))),"") -> -27907 | E13: =IFERROR(IF('2. 3-Year P&L'!$B$10="","",-'2. 3-Year P&L'!$B$24/MAX(12,'0. Assumptions'!$B$21)*(1+IF(4='0. Assumptions'!$B$60,(MAX(12,'0. Assumptions'!$B$21)-12)/2,0)+IF(4='0. Assumptions'!$B$61,(MAX(12,'0. Assumptions'!$B$21)-12)/2,0))),"") -> -27907 | F13: =IFERROR(IF('2. 3-Year P&L'!$B$10="","",-'2. 3-Year P&L'!$B$24/MAX(12,'0. Assumptions'!$B$21)*(1+IF(5='0. Assumptions'!$B$60,(MAX(12,'0. Assumptions'!$B$21)-12)/2,0)+IF(5='0. Assumptions'!$B$61,(MAX(12,'0. Assumptions'!$B$21)-12)/2,0))),"") -> -27907 | G13: =IFERROR(IF('2. 3-Year P&L'!$B$10="","",-'2. 3-Year P&L'!$B$24/MAX(12,'0. Assumptions'!$B$21)*(1+IF(6='0. Assumptions'!$B$60,(MAX(12,'0. Assumptions'!$B$21)-12)/2,0)+IF(6='0. Assumptions'!$B$61,(MAX(12,'0. Assumptions'!$B$21)-12)/2,0))),"") -> -27907 | H13: =IFERROR(IF('2. 3-Year P&L'!$B$10="","",-'2. 3-Year P&L'!$B$24/MAX(12,'0. Assumptions'!$B$21)*(1+IF(7='0. Assumptions'!$B$60,(MAX(12,'0. Assumptions'!$B$21)-12)/2,0)+IF(7='0. Assumptions'!$B$61,(MAX(12,'0. Assumptions'!$B$21)-12)/2,0))),"") -> -27907 | I13: =IFERROR(IF('2. 3-Year P&L'!$B$10="","",-'2. 3-Year P&L'!$B$24/MAX(12,'0. Assumptions'!$B$21)*(1+IF(8='0. Assumptions'!$B$60,(MAX(12,'0. Assumptions'!$B$21)-12)/2,0)+IF(8='0. Assumptions'!$B$61,(MAX(12,'0. Assumptions'!$B$21)-12)/2,0))),"") -> -27907 | J13: =IFERROR(IF('2. 3-Year P&L'!$B$10="","",-'2. 3-Year P&L'!$B$24/MAX(12,'0. Assumptions'!$B$21)*(1+IF(9='0. Assumptions'!$B$60,(MAX(12,'0. Assumptions'!$B$21)-12)/2,0)+IF(9='0. Assumptions'!$B$61,(MAX(12,'0. Assumptions'!$B$21)-12)/2,0))),"") -> -27907 | K13: =IFERROR(IF('2. 3-Year P&L'!$B$10="","",-'2. 3-Year P&L'!$B$24/MAX(12,'0. Assumptions'!$B$21)*(1+IF(10='0. Assumptions'!$B$60,(MAX(12,'0. Assumptions'!$B$21)-12)/2,0)+IF(10='0. Assumptions'!$B$61,(MAX(12,'0. Assumptions'!$B$21)-12)/2,0))),"") -> -27907 | L13: =IFERROR(IF('2. 3-Year P&L'!$B$10="","",-'2. 3-Year P&L'!$B$24/MAX(12,'0. Assumptions'!$B$21)*(1+IF(11='0. Assumptions'!$B$60,(MAX(12,'0. Assumptions'!$B$21)-12)/2,0)+IF(11='0. Assumptions'!$B$61,(MAX(12,'0. Assumptions'!$B$21)-12)/2,0))),"") -> -27907 | M13: =IFERROR(IF('2. 3-Year P&L'!$B$10="","",-'2. 3-Year P&L'!$B$24/MAX(12,'0. Assumptions'!$B$21)*(1+IF(12='0. Assumptions'!$B$60,(MAX(12,'0. Assumptions'!$B$21)-12)/2,0)+IF(12='0. Assumptions'!$B$61,(MAX(12,'0. Assumptions'!$B$21)-12)/2,0))),"") -> -27907 | N13: =IFERROR(IF('2. 3-Year P&L'!$B$10="","",SUM(B13:M13)),"") -> -334884 | O13: Twelve monthly installments plus extra pay periods in the months you set in Assumptions (only if pay periods > 12). The total for the year is the same as the P&L's
A14: Loan interest | B14: =IFERROR(IF('2. 3-Year P&L'!$B$10="","",-'7. Financing'!$B$44/12),"") -> -3325 | C14: =IFERROR(IF('2. 3-Year P&L'!$B$10="","",-'7. Financing'!$B$44/12),"") -> -3325 | D14: =IFERROR(IF('2. 3-Year P&L'!$B$10="","",-'7. Financing'!$B$44/12),"") -> -3325 | E14: =IFERROR(IF('2. 3-Year P&L'!$B$10="","",-'7. Financing'!$B$44/12),"") -> -3325 | F14: =IFERROR(IF('2. 3-Year P&L'!$B$10="","",-'7. Financing'!$B$44/12),"") -> -3325 | G14: =IFERROR(IF('2. 3-Year P&L'!$B$10="","",-'7. Financing'!$B$44/12),"") -> -3325 | H14: =IFERROR(IF('2. 3-Year P&L'!$B$10="","",-'7. Financing'!$B$44/12),"") -> -3325 | I14: =IFERROR(IF('2. 3-Year P&L'!$B$10="","",-'7. Financing'!$B$44/12),"") -> -3325 | ... M14: =IFERROR(IF('2. 3-Year P&L'!$B$10="","",-'7. Financing'!$B$44/12),"") -> -3325 | N14: =IFERROR(IF('2. 3-Year P&L'!$B$10="","",SUM(B14:M14)),"") -> -39900
A15: Loan principal repaid | B15: =IFERROR(IF('2. 3-Year P&L'!$B$10="","",-'7. Financing'!$B$45/12),"") -> -2086.2844 | C15: =IFERROR(IF('2. 3-Year P&L'!$B$10="","",-'7. Financing'!$B$45/12),"") -> -2086.2844 | D15: =IFERROR(IF('2. 3-Year P&L'!$B$10="","",-'7. Financing'!$B$45/12),"") -> -2086.2844 | E15: =IFERROR(IF('2. 3-Year P&L'!$B$10="","",-'7. Financing'!$B$45/12),"") -> -2086.2844 | F15: =IFERROR(IF('2. 3-Year P&L'!$B$10="","",-'7. Financing'!$B$45/12),"") -> -2086.2844 | G15: =IFERROR(IF('2. 3-Year P&L'!$B$10="","",-'7. Financing'!$B$45/12),"") -> -2086.2844 | H15: =IFERROR(IF('2. 3-Year P&L'!$B$10="","",-'7. Financing'!$B$45/12),"") -> -2086.2844 | I15: =IFERROR(IF('2. 3-Year P&L'!$B$10="","",-'7. Financing'!$B$45/12),"") -> -2086.2844 | ... M15: =IFERROR(IF('2. 3-Year P&L'!$B$10="","",-'7. Financing'!$B$45/12),"") -> -2086.2844 | N15: =IFERROR(IF('2. 3-Year P&L'!$B$10="","",SUM(B15:M15)),"") -> -25035.413
A16: Sales tax collected (memo) | B16: =IFERROR(IF('2. 3-Year P&L'!$B$10="","",'2. 3-Year P&L'!$B$10*B7*SUMPRODUCT('2. 3-Year P&L'!$E$11:$E$12,'2. 3-Year P&L'!$G$11:$G$12)),"") -> 3725.3634 | C16: =IFERROR(IF('2. 3-Year P&L'!$B$10="","",'2. 3-Year P&L'!$B$10*C7*SUMPRODUCT('2. 3-Year P&L'!$E$11:$E$12,'2. 3-Year P&L'!$G$11:$G$12)),"") -> 4458.8246 | D16: =IFERROR(IF('2. 3-Year P&L'!$B$10="","",'2. 3-Year P&L'!$B$10*D7*SUMPRODUCT('2. 3-Year P&L'!$E$11:$E$12,'2. 3-Year P&L'!$G$11:$G$12)),"") -> 5792.2144 | E16: =IFERROR(IF('2. 3-Year P&L'!$B$10="","",'2. 3-Year P&L'!$B$10*E7*SUMPRODUCT('2. 3-Year P&L'!$E$11:$E$12,'2. 3-Year P&L'!$G$11:$G$12)),"") -> 6744.3592 | F16: =IFERROR(IF('2. 3-Year P&L'!$B$10="","",'2. 3-Year P&L'!$B$10*F7*SUMPRODUCT('2. 3-Year P&L'!$E$11:$E$12,'2. 3-Year P&L'!$G$11:$G$12)),"") -> 7924.864 | G16: =IFERROR(IF('2. 3-Year P&L'!$B$10="","",'2. 3-Year P&L'!$B$10*G7*SUMPRODUCT('2. 3-Year P&L'!$E$11:$E$12,'2. 3-Year P&L'!$G$11:$G$12)),"") -> 8515.1164 | H16: =IFERROR(IF('2. 3-Year P&L'!$B$10="","",'2. 3-Year P&L'!$B$10*H7*SUMPRODUCT('2. 3-Year P&L'!$E$11:$E$12,'2. 3-Year P&L'!$G$11:$G$12)),"") -> 8224.8283 | I16: =IFERROR(IF('2. 3-Year P&L'!$B$10="","",'2. 3-Year P&L'!$B$10*I7*SUMPRODUCT('2. 3-Year P&L'!$E$11:$E$12,'2. 3-Year P&L'!$G$11:$G$12)),"") -> 5999.2865 | ... M16: =IFERROR(IF('2. 3-Year P&L'!$B$10="","",'2. 3-Year P&L'!$B$10*M7*SUMPRODUCT('2. 3-Year P&L'!$E$11:$E$12,'2. 3-Year P&L'!$G$11:$G$12)),"") -> 10256.845 | N16: =IFERROR(IF('2. 3-Year P&L'!$B$10="","",SUM(B16:M16)),"") -> 86800 | O16: Each sales line at ITS OWN rate, read from the sales tax column of the P&L (alcohol to go has its own rate cell in the Assumptions tab)
A17: Recoverable input tax (memo) | B17: =IFERROR(IF('2. 3-Year P&L'!$B$10="","",'2. 3-Year P&L'!$B$41*B7+'2. 3-Year P&L'!$B$42/12),"") -> 0 | C17: =IFERROR(IF('2. 3-Year P&L'!$B$10="","",'2. 3-Year P&L'!$B$41*C7+'2. 3-Year P&L'!$B$42/12),"") -> 0 | D17: =IFERROR(IF('2. 3-Year P&L'!$B$10="","",'2. 3-Year P&L'!$B$41*D7+'2. 3-Year P&L'!$B$42/12),"") -> 0 | E17: =IFERROR(IF('2. 3-Year P&L'!$B$10="","",'2. 3-Year P&L'!$B$41*E7+'2. 3-Year P&L'!$B$42/12),"") -> 0 | F17: =IFERROR(IF('2. 3-Year P&L'!$B$10="","",'2. 3-Year P&L'!$B$41*F7+'2. 3-Year P&L'!$B$42/12),"") -> 0 | G17: =IFERROR(IF('2. 3-Year P&L'!$B$10="","",'2. 3-Year P&L'!$B$41*G7+'2. 3-Year P&L'!$B$42/12),"") -> 0 | H17: =IFERROR(IF('2. 3-Year P&L'!$B$10="","",'2. 3-Year P&L'!$B$41*H7+'2. 3-Year P&L'!$B$42/12),"") -> 0 | I17: =IFERROR(IF('2. 3-Year P&L'!$B$10="","",'2. 3-Year P&L'!$B$41*I7+'2. 3-Year P&L'!$B$42/12),"") -> 0 | ... M17: =IFERROR(IF('2. 3-Year P&L'!$B$10="","",'2. 3-Year P&L'!$B$41*M7+'2. 3-Year P&L'!$B$42/12),"") -> 0 | N17: =IFERROR(IF('2. 3-Year P&L'!$B$10="","",SUM(B17:M17)),"") -> 0 | O17: Each item at its own rate, read from the tax column of the P&L: insurance and card processing fees carry none
A18: Carried forward (capex input tax included) | E18: =IFERROR(IF('2. 3-Year P&L'!$B$10="","",'1. Startup Costs'!$B$50),"") -> 0 | H18: =IFERROR(IF('2. 3-Year P&L'!$B$10="","",MAX(0,-E19)),"") -> 0 | K18: =IFERROR(IF('2. 3-Year P&L'!$B$10="","",MAX(0,-H19)),"") -> 0 | O18: Sales tax paid on STARTUP COSTS enters here: it is offset against the tax collected in later quarters until used up. With 0% recoverable input tax (the US default) this line stays at zero
A19: Quarterly sales tax return | E19: =IFERROR(IF('2. 3-Year P&L'!$B$10="","",SUM(B16:D16)-SUM(B17:D17)-E18),"") -> 13976.402 | H19: =IFERROR(IF('2. 3-Year P&L'!$B$10="","",SUM(E16:G16)-SUM(E17:G17)-H18),"") -> 23184.34 | K19: =IFERROR(IF('2. 3-Year P&L'!$B$10="","",SUM(H16:J16)-SUM(H17:J17)-K18),"") -> 22448.943 | O19: Sales tax collected minus recoverable input tax for the quarter, minus what was carried forward. If negative, nothing is paid: it is offset in the next quarter. With 0% recoverable input tax (the US default) it equals the sales tax collected in the quarter
A20: Sales tax remitted (quarterly filer) | E20: =IFERROR(IF('2. 3-Year P&L'!$B$10="","",IF(E19<=0,"",-E19)),"") -> -13976.402 | H20: =IFERROR(IF('2. 3-Year P&L'!$B$10="","",IF(H19<=0,"",-H19)),"") -> -23184.34 | K20: =IFERROR(IF('2. 3-Year P&L'!$B$10="","",IF(K19<=0,"",-K19)),"") -> -22448.943 | N20: =IFERROR(IF('2. 3-Year P&L'!$B$10="","",SUM(B20:M20)),"") -> -59609.685 | O20: Cash only leaves when the quarter's result is positive. Months without a settlement are left blank, not zero. The cell turns RED when the payment takes more cash than is left that month. The model settles quarterly, in the month after each plan quarter (Months 4, 7 and 10, and the fourth quarter in Month 13: April, July, October and January when Month 1 is January): if your state requires monthly filing, expect smaller payments every month instead
A21: MONTHLY NET CASH FLOW | B21: =IFERROR(IF('2. 3-Year P&L'!$B$10="","",SUM(B9:B15)+IF(B20="",0,B20)),"") -> -8703.961 | C21: =IFERROR(IF('2. 3-Year P&L'!$B$10="","",SUM(C9:C15)+IF(C20="",0,C20)),"") -> -6640.1338 | D21: =IFERROR(IF('2. 3-Year P&L'!$B$10="","",SUM(D9:D15)+IF(D20="",0,D20)),"") -> 6547.7736 | E21: =IFERROR(IF('2. 3-Year P&L'!$B$10="","",SUM(E9:E15)+IF(E20="",0,E20)),"") -> 723.50658 | F21: =IFERROR(IF('2. 3-Year P&L'!$B$10="","",SUM(F9:F15)+IF(F20="",0,F20)),"") -> 25902.609 | G21: =IFERROR(IF('2. 3-Year P&L'!$B$10="","",SUM(G9:G15)+IF(G20="",0,G20)),"") -> 30403.283 | H21: =IFERROR(IF('2. 3-Year P&L'!$B$10="","",SUM(H9:H15)+IF(H20="",0,H20)),"") -> 3176.0778 | I21: =IFERROR(IF('2. 3-Year P&L'!$B$10="","",SUM(I9:I15)+IF(I20="",0,I20)),"") -> 2889.4184 | ... M21: =IFERROR(IF('2. 3-Year P&L'!$B$10="","",SUM(M9:M15)+IF(M20="",0,M20)),"") -> 48355.786 | N21: =IFERROR(IF('2. 3-Year P&L'!$B$10="","",SUM(B21:M21)),"") -> 168872.22
A22: CUMULATIVE CASH BALANCE | B22: =IFERROR(IF('2. 3-Year P&L'!$B$10="","",'1. Startup Costs'!$B$47+B21),"") -> 131292.04 | C22: =IFERROR(IF('2. 3-Year P&L'!$B$10="","",B22+C21),"") -> 124651.91 | D22: =IFERROR(IF('2. 3-Year P&L'!$B$10="","",C22+D21),"") -> 131199.68 | E22: =IFERROR(IF('2. 3-Year P&L'!$B$10="","",D22+E21),"") -> 131923.19 | F22: =IFERROR(IF('2. 3-Year P&L'!$B$10="","",E22+F21),"") -> 157825.79 | G22: =IFERROR(IF('2. 3-Year P&L'!$B$10="","",F22+G21),"") -> 188229.08 | H22: =IFERROR(IF('2. 3-Year P&L'!$B$10="","",G22+H21),"") -> 191405.16 | I22: =IFERROR(IF('2. 3-Year P&L'!$B$10="","",H22+I21),"") -> 194294.57 | J22: =IFERROR(IF('2. 3-Year P&L'!$B$10="","",I22+J21),"") -> 224585.98 | ... M22: =IFERROR(IF('2. 3-Year P&L'!$B$10="","",L22+M21),"") -> 308868.22
A23: Minimum balance of the year | B23: =IFERROR(IF('2. 3-Year P&L'!$B$10="","",IF(COUNT(B22:M22)=0,"",MIN(B22:M22))),"") -> 124651.91 | D23: If negative, raise working capital or the loan: you run out of cash
A24: Month when cash bottoms out | B24: =IFERROR(IF('2. 3-Year P&L'!$B$10="","",IF(COUNT(B22:M22)=0,"",MATCH(MIN(B22:M22),B22:M22,0))),"") -> 2 | D24: It answers the question that decides a bank deal: in which month the cash runs out
A25: RETURN ON INVESTMENT
A26: Free cash flow before debt, year 1 | B26: =IFERROR(IF('2. 3-Year P&L'!$B$10="","",'2. 3-Year P&L'!$B$50+'2. 3-Year P&L'!$B$38+'7. Financing'!$B$44),"") -> 162177.54 | D26: Net income plus depreciation (which is not paid) plus that year's interest: principal is not subtracted because this flow is BEFORE debt. The SAME basis as years 2 and 3, so the payback compares like with like
A27: Free cash flow before debt, year 2 | B27: =IFERROR(IF('2. 3-Year P&L'!$B$10="","",'2. 3-Year P&L'!$C$50+'2. 3-Year P&L'!$C$38+'7. Financing'!$B$46),"") -> 208852.28 | D27: Net income plus depreciation (which is not paid) plus that year's interest: principal is not subtracted because this flow is BEFORE debt. Without a monthly table, it is an estimate
A28: Free cash flow before debt, year 3 | B28: =IFERROR(IF('2. 3-Year P&L'!$B$10="","",'2. 3-Year P&L'!$D$50+'2. 3-Year P&L'!$D$38+'7. Financing'!$B$48),"") -> 237342.21 | D28: Net income plus depreciation (which is not paid) plus that year's interest: principal is not subtracted because this flow is BEFORE debt. Without a monthly table, it is an estimate
A29: For reference: ACTUAL year-1 cash flow (monthly table, before debt) | B29: =IFERROR(IF('2. 3-Year P&L'!$B$10="","",N21+'7. Financing'!$B$44+'7. Financing'!$B$45),"") -> 233807.63 | D29: The sum of the twelve monthly net cash flows above, adding back the interest and principal paid that year. It is NOT the one the payback uses: it includes sales tax not yet settled and supplier credit, two things that have to be paid back and that years 2 and 3 do not have
A30: Investment to recover (net of recoverable input tax) | B30: =IFERROR(IF('2. 3-Year P&L'!$B$10="","",'1. Startup Costs'!$B$51-'1. Startup Costs'!$B$50),"") -> 528696 | D30: CAPEX plus working capital: the total cash needed MINUS the recoverable input tax on startup costs, which is not lost (it is recovered through the quarterly return, and this tab offsets it quarter by quarter; it is zero in the US default). Working capital is recovered when you close, but until then it is tied up
A31: Project payback (years), before debt | B31: =IFERROR(IF('2. 3-Year P&L'!$B$10="","",IF(B26>=B30,ROUND(B30/B26,1),IF(B26+B27>=B30,ROUND(1+(B30-B26)/B27,1),IF(B26+B27+B28>=B30,ROUND(2+(B30-B26-B27)/B28,1),"Over 3 years")))),"") -> 2.7 | D31: Measures how long the business takes to repay the investment with what it generates BEFORE paying the lender, on the SAME cash flow basis in all three years. Whether you can afford the loan payment is shown by the DSCR in the Financing tab
A32: Payback on CAPEX, excluding working capital (years) | B32: =IFERROR(IF('2. 3-Year P&L'!$B$10="","",IF(B26>='1. Startup Costs'!$B$49,ROUND('1. Startup Costs'!$B$49/B26,1),IF(B26+B27>='1. Startup Costs'!$B$49,ROUND(1+('1. Startup Costs'!$B$49-B26)/B27,1),IF(B26+B27+B28>='1. Startup Costs'!$B$49,ROUND(2+('1. Startup Costs'!$B$49-B26-B27)/B28,1),"Over 3 years")))),"") -> 2.1 | D32: The same calculation on what you BUY (build-out, equipment, launch and formation costs), without working capital: that money is not spent, it is tied up and comes back when the business closes. For reference only: the payback that matters is the one above
A34: Fourth-quarter sales tax is settled in January of the following year, so it does not appear in this table. The model pays year-1 income tax in July of year 2 (a simplification: estimated tax payments are usually quarterly). The loan payment is spread in twelve equal parts following the ANNUAL schedule in the Financing tab, and payroll in twelve monthly installments (plus extra pay periods in their month, only if pay periods > 12).

Sheet 7. Financing
A1: FINANCING PLAN
A2: What you need, where it comes from and what it costs to repay. It is the sheet your lender asks for along with the P&L.
A4: Item | B4: Amount | C4: Notes
A5: SOURCES OF FUNDS
A6: Owner's equity (your own money) | B6: =IFERROR(IF('0. Assumptions'!$B$30="","",'0. Assumptions'!$B$30),"") -> 130000
A7: Loan requested — bank or SBA 7(a) (amortized below) | B7: =IFERROR(IF('0. Assumptions'!$B$31="","",'0. Assumptions'!$B$31),"") -> 399000
A8: Other loan (not in the schedule or the DSCR — enter your loan in row 7) | B8: 0 | C8: A source of funds only: NOT amortized, so it is not in the schedule, the P&L interest or the DSCR. Enter your bank or SBA 7(a) loan in row 7 ("Loan requested" in "0. Assumptions"); use this row only for a second loan
A9: SBA Microloan (not in the schedule or the DSCR — enter your loan in row 7) | B9: 0 | C9: SBA Microloans go up to 50,000 through nonprofit intermediaries. Like row 8, a source of funds only: not in the schedule or the DSCR. If it is your only loan, enter it in row 7 instead
A10: Investors / partners (equity: dilutes, not repaid) | B10: 0 | C10: Equity: it dilutes your ownership and is not repaid
A11: Local grants (usually paid after you spend) | B11: 0 | C11: Usually paid AFTER you document the spending
A12: TOTAL SOURCES OF FUNDS | B12: =IFERROR(IF(COUNT(B6:B11)=0,"",SUM(B6:B11)),"") -> 529000
A13: USES OF FUNDS
A14: Total cash needed at launch | B14: =IFERROR(IF('1. Startup Costs'!$B$51="","",'1. Startup Costs'!$B$51),"") -> 528696 | C14: Startup costs plus any recoverable tax you have to advance (zero by default in the US)
A15: Difference (sources - uses) | B15: =IFERROR(B12-B14,"") -> 304 | C15: In red (negative), the plan is NOT funded. Far above zero is not free either: you pay interest on money you do not use
A16: Difference as a % of uses | B16: =IFERROR(B15/B14,"") -> 0.00057499962 | C16: Amber above the margin you set: it is debt you pay for without needing it
A17: Acceptable over-funding (%) | B17: 0.05 | C17: A small cushion over the need is healthy; 20% extra is interest thrown away
A18: Loan that would match sources to needs | B18: =IFERROR(MAX(0,B14-B12+B7),"") -> 398696 | C18: Copy it into "Loan requested" in the "0. Assumptions" tab and the difference goes to zero. Rows 8-11 lower this figure, but only the row-7 loan is amortized and counted in the DSCR
A19: LOAN TERMS
A20: Principal amount | B20: =IFERROR(IF('0. Assumptions'!$B$31=0,"",'0. Assumptions'!$B$31),"") -> 399000
A21: Nominal annual interest rate (not APR) | B21: =IFERROR(IF('0. Assumptions'!$B$32="","",'0. Assumptions'!$B$32),"") -> 0.1
A22: Total term (years) | B22: =IFERROR(IF('0. Assumptions'!$B$33="","",'0. Assumptions'!$B$33),"") -> 10
A23: Interest-only period applied (years) | B23: =IFERROR(IF(OR('0. Assumptions'!$B$34="",'0. Assumptions'!$B$33=""),"",IF('0. Assumptions'!$B$34>='0. Assumptions'!$B$33,0,'0. Assumptions'!$B$34)),"") -> 0 | C23: An interest-only period equal to or longer than the term does not exist: the sheet cancels it at the source
A24: Annual payment during repayment | B24: =IFERROR(IF(B22-B23<=0,"",IF(B21=0,B20/(B22-B23),B20*B21/(1-(1+B21)^-(B22-B23)))),"") -> 64935.413 | C24: Standard amortizing loan with a level annual payment. At a 0% rate it is the principal divided by the repayment years: without that branch the schedule would shut down entirely
A25: AMORTIZATION SCHEDULE
A26: Year | B26: Opening balance | C26: Interest | D26: Principal repaid | E26: Total payment | F26: Closing balance | G26: Cash flow available for debt service (after tax; from year 4 on, year 3 held flat) | H26: DSCR for the year
A27: 1 | B27: =IFERROR(IF(B20="","",B20),"") -> 399000 | C27: =IFERROR(IF(OR(1>B22,B27=""),"",B27*B21),"") -> 39900 | D27: =IFERROR(IF(OR(1>B22,B27=""),"",IF(1<=B23,0,MIN(B27,B24-C27))),"") -> 25035.413 | E27: =IFERROR(IF(C27="","",C27+D27),"") -> 64935.413 | F27: =IFERROR(IF(D27="","",B27-D27),"") -> 373964.59 | G27: =IFERROR(IF(E27="","",'2. 3-Year P&L'!$B$43-'2. 3-Year P&L'!$B$48+'2. 3-Year P&L'!$B$38+'2. 3-Year P&L'!$B$39),"") -> 162177.54 | H27: =IFERROR(IF(OR(E27="",E27=0),"",G27/E27),"") -> 2.4975207
A28: 2 | B28: =IFERROR(IF(OR(2>B22,F27=""),"",F27),"") -> 373964.59 | C28: =IFERROR(IF(OR(2>B22,B28=""),"",B28*B21),"") -> 37396.459 | D28: =IFERROR(IF(OR(2>B22,B28=""),"",IF(2<=B23,0,MIN(B28,B24-C28))),"") -> 27538.954 | E28: =IFERROR(IF(C28="","",C28+D28),"") -> 64935.413 | F28: =IFERROR(IF(D28="","",B28-D28),"") -> 346425.63 | G28: =IFERROR(IF(E28="","",'2. 3-Year P&L'!$C$43-'2. 3-Year P&L'!$C$48+'2. 3-Year P&L'!$C$38+'2. 3-Year P&L'!$C$39),"") -> 208852.28 | H28: =IFERROR(IF(OR(E28="",E28=0),"",G28/E28),"") -> 3.2163078
A29: 3 | B29: =IFERROR(IF(OR(3>B22,F28=""),"",F28),"") -> 346425.63 | C29: =IFERROR(IF(OR(3>B22,B29=""),"",B29*B21),"") -> 34642.563 | D29: =IFERROR(IF(OR(3>B22,B29=""),"",IF(3<=B23,0,MIN(B29,B24-C29))),"") -> 30292.849 | E29: =IFERROR(IF(C29="","",C29+D29),"") -> 64935.413 | F29: =IFERROR(IF(D29="","",B29-D29),"") -> 316132.78 | G29: =IFERROR(IF(E29="","",'2. 3-Year P&L'!$D$43-'2. 3-Year P&L'!$D$48+'2. 3-Year P&L'!$D$38+'2. 3-Year P&L'!$D$39),"") -> 237342.21 | H29: =IFERROR(IF(OR(E29="",E29=0),"",G29/E29),"") -> 3.6550505
A30: 4 | B30: =IFERROR(IF(OR(4>B22,F29=""),"",F29),"") -> 316132.78 | C30: =IFERROR(IF(OR(4>B22,B30=""),"",B30*B21),"") -> 31613.278 | D30: =IFERROR(IF(OR(4>B22,B30=""),"",IF(4<=B23,0,MIN(B30,B24-C30))),"") -> 33322.134 | E30: =IFERROR(IF(C30="","",C30+D30),"") -> 64935.413 | F30: =IFERROR(IF(D30="","",B30-D30),"") -> 282810.65 | G30: =IFERROR(IF(E30="","",'2. 3-Year P&L'!$D$43-'2. 3-Year P&L'!$D$48+'2. 3-Year P&L'!$D$38+'2. 3-Year P&L'!$D$39),"") -> 237342.21 | H30: =IFERROR(IF(OR(E30="",E30=0),"",G30/E30),"") -> 3.6550505
A31: 5 | B31: =IFERROR(IF(OR(5>B22,F30=""),"",F30),"") -> 282810.65 | C31: =IFERROR(IF(OR(5>B22,B31=""),"",B31*B21),"") -> 28281.065 | D31: =IFERROR(IF(OR(5>B22,B31=""),"",IF(5<=B23,0,MIN(B31,B24-C31))),"") -> 36654.348 | E31: =IFERROR(IF(C31="","",C31+D31),"") -> 64935.413 | F31: =IFERROR(IF(D31="","",B31-D31),"") -> 246156.3 | G31: =IFERROR(IF(E31="","",'2. 3-Year P&L'!$D$43-'2. 3-Year P&L'!$D$48+'2. 3-Year P&L'!$D$38+'2. 3-Year P&L'!$D$39),"") -> 237342.21 | H31: =IFERROR(IF(OR(E31="",E31=0),"",G31/E31),"") -> 3.6550505
A32: 6 | B32: =IFERROR(IF(OR(6>B22,F31=""),"",F31),"") -> 246156.3 | C32: =IFERROR(IF(OR(6>B22,B32=""),"",B32*B21),"") -> 24615.63 | D32: =IFERROR(IF(OR(6>B22,B32=""),"",IF(6<=B23,0,MIN(B32,B24-C32))),"") -> 40319.782 | E32: =IFERROR(IF(C32="","",C32+D32),"") -> 64935.413 | F32: =IFERROR(IF(D32="","",B32-D32),"") -> 205836.52 | G32: =IFERROR(IF(E32="","",'2. 3-Year P&L'!$D$43-'2. 3-Year P&L'!$D$48+'2. 3-Year P&L'!$D$38+'2. 3-Year P&L'!$D$39),"") -> 237342.21 | H32: =IFERROR(IF(OR(E32="",E32=0),"",G32/E32),"") -> 3.6550505
A33: 7 | B33: =IFERROR(IF(OR(7>B22,F32=""),"",F32),"") -> 205836.52 | C33: =IFERROR(IF(OR(7>B22,B33=""),"",B33*B21),"") -> 20583.652 | D33: =IFERROR(IF(OR(7>B22,B33=""),"",IF(7<=B23,0,MIN(B33,B24-C33))),"") -> 44351.761 | E33: =IFERROR(IF(C33="","",C33+D33),"") -> 64935.413 | F33: =IFERROR(IF(D33="","",B33-D33),"") -> 161484.76 | G33: =IFERROR(IF(E33="","",'2. 3-Year P&L'!$D$43-'2. 3-Year P&L'!$D$48+'2. 3-Year P&L'!$D$38+'2. 3-Year P&L'!$D$39),"") -> 237342.21 | H33: =IFERROR(IF(OR(E33="",E33=0),"",G33/E33),"") -> 3.6550505
A34: 8 | B34: =IFERROR(IF(OR(8>B22,F33=""),"",F33),"") -> 161484.76 | C34: =IFERROR(IF(OR(8>B22,B34=""),"",B34*B21),"") -> 16148.476 | D34: =IFERROR(IF(OR(8>B22,B34=""),"",IF(8<=B23,0,MIN(B34,B24-C34))),"") -> 48786.937 | E34: =IFERROR(IF(C34="","",C34+D34),"") -> 64935.413 | F34: =IFERROR(IF(D34="","",B34-D34),"") -> 112697.82 | G34: =IFERROR(IF(E34="","",'2. 3-Year P&L'!$D$43-'2. 3-Year P&L'!$D$48+'2. 3-Year P&L'!$D$38+'2. 3-Year P&L'!$D$39),"") -> 237342.21 | H34: =IFERROR(IF(OR(E34="",E34=0),"",G34/E34),"") -> 3.6550505
A35: 9 | B35: =IFERROR(IF(OR(9>B22,F34=""),"",F34),"") -> 112697.82 | C35: =IFERROR(IF(OR(9>B22,B35=""),"",B35*B21),"") -> 11269.782 | D35: =IFERROR(IF(OR(9>B22,B35=""),"",IF(9<=B23,0,MIN(B35,B24-C35))),"") -> 53665.63 | E35: =IFERROR(IF(C35="","",C35+D35),"") -> 64935.413 | F35: =IFERROR(IF(D35="","",B35-D35),"") -> 59032.193 | G35: =IFERROR(IF(E35="","",'2. 3-Year P&L'!$D$43-'2. 3-Year P&L'!$D$48+'2. 3-Year P&L'!$D$38+'2. 3-Year P&L'!$D$39),"") -> 237342.21 | H35: =IFERROR(IF(OR(E35="",E35=0),"",G35/E35),"") -> 3.6550505
A36: 10 | B36: =IFERROR(IF(OR(10>B22,F35=""),"",F35),"") -> 59032.193 | C36: =IFERROR(IF(OR(10>B22,B36=""),"",B36*B21),"") -> 5903.2193 | D36: =IFERROR(IF(OR(10>B22,B36=""),"",IF(10<=B23,0,MIN(B36,B24-C36))),"") -> 59032.193 | E36: =IFERROR(IF(C36="","",C36+D36),"") -> 64935.413 | F36: =IFERROR(IF(D36="","",B36-D36),"") -> 6.5483619e-10 | G36: =IFERROR(IF(E36="","",'2. 3-Year P&L'!$D$43-'2. 3-Year P&L'!$D$48+'2. 3-Year P&L'!$D$38+'2. 3-Year P&L'!$D$39),"") -> 237342.21 | H36: =IFERROR(IF(OR(E36="",E36=0),"",G36/E36),"") -> 3.6550505
A37: 11 | B37: =IFERROR(IF(OR(11>B22,F36=""),"",F36),"") | C37: =IFERROR(IF(OR(11>B22,B37=""),"",B37*B21),"") | D37: =IFERROR(IF(OR(11>B22,B37=""),"",IF(11<=B23,0,MIN(B37,B24-C37))),"") | E37: =IFERROR(IF(C37="","",C37+D37),"") | F37: =IFERROR(IF(D37="","",B37-D37),"") | G37: =IFERROR(IF(E37="","",'2. 3-Year P&L'!$D$43-'2. 3-Year P&L'!$D$48+'2. 3-Year P&L'!$D$38+'2. 3-Year P&L'!$D$39),"") | H37: =IFERROR(IF(OR(E37="",E37=0),"",G37/E37),"")
A38: 12 | B38: =IFERROR(IF(OR(12>B22,F37=""),"",F37),"") | C38: =IFERROR(IF(OR(12>B22,B38=""),"",B38*B21),"") | D38: =IFERROR(IF(OR(12>B22,B38=""),"",IF(12<=B23,0,MIN(B38,B24-C38))),"") | E38: =IFERROR(IF(C38="","",C38+D38),"") | F38: =IFERROR(IF(D38="","",B38-D38),"") | G38: =IFERROR(IF(E38="","",'2. 3-Year P&L'!$D$43-'2. 3-Year P&L'!$D$48+'2. 3-Year P&L'!$D$38+'2. 3-Year P&L'!$D$39),"") | H38: =IFERROR(IF(OR(E38="",E38=0),"",G38/E38),"")
A39: 13 | B39: =IFERROR(IF(OR(13>B22,F38=""),"",F38),"") | C39: =IFERROR(IF(OR(13>B22,B39=""),"",B39*B21),"") | D39: =IFERROR(IF(OR(13>B22,B39=""),"",IF(13<=B23,0,MIN(B39,B24-C39))),"") | E39: =IFERROR(IF(C39="","",C39+D39),"") | F39: =IFERROR(IF(D39="","",B39-D39),"") | G39: =IFERROR(IF(E39="","",'2. 3-Year P&L'!$D$43-'2. 3-Year P&L'!$D$48+'2. 3-Year P&L'!$D$38+'2. 3-Year P&L'!$D$39),"") | H39: =IFERROR(IF(OR(E39="",E39=0),"",G39/E39),"")
A40: 14 | B40: =IFERROR(IF(OR(14>B22,F39=""),"",F39),"") | C40: =IFERROR(IF(OR(14>B22,B40=""),"",B40*B21),"") | D40: =IFERROR(IF(OR(14>B22,B40=""),"",IF(14<=B23,0,MIN(B40,B24-C40))),"") | E40: =IFERROR(IF(C40="","",C40+D40),"") | F40: =IFERROR(IF(D40="","",B40-D40),"") | G40: =IFERROR(IF(E40="","",'2. 3-Year P&L'!$D$43-'2. 3-Year P&L'!$D$48+'2. 3-Year P&L'!$D$38+'2. 3-Year P&L'!$D$39),"") | H40: =IFERROR(IF(OR(E40="",E40=0),"",G40/E40),"")
A41: 15 | B41: =IFERROR(IF(OR(15>B22,F40=""),"",F40),"") | C41: =IFERROR(IF(OR(15>B22,B41=""),"",B41*B21),"") | D41: =IFERROR(IF(OR(15>B22,B41=""),"",IF(15<=B23,0,MIN(B41,B24-C41))),"") | E41: =IFERROR(IF(C41="","",C41+D41),"") | F41: =IFERROR(IF(D41="","",B41-D41),"") | G41: =IFERROR(IF(E41="","",'2. 3-Year P&L'!$D$43-'2. 3-Year P&L'!$D$48+'2. 3-Year P&L'!$D$38+'2. 3-Year P&L'!$D$39),"") | H41: =IFERROR(IF(OR(E41="",E41=0),"",G41/E41),"")
A42: Schedule closing tolerance | B42: 0.01 | C42: Rounding margin. Above it, the schedule does not close and there is principal left unpaid
A43: Balance outstanding at maturity | B43: =IFERROR(IF(B20="","",ROUND(B20-SUM(D27:D41),2)),"") -> 0 | C43: Must be zero: the principal repaid in the schedule has to equal the amount borrowed. If it is positive, the term falls short
A44: Year-1 interest | B44: =IFERROR(IF(B20="","",IF(C27="",0,C27)),"") -> 39900
A45: Year-1 principal repaid | B45: =IFERROR(IF(B20="","",IF(D27="",0,D27)),"") -> 25035.413
A46: Year-2 interest | B46: =IFERROR(IF(B20="","",IF(C28="",0,C28)),"") -> 37396.459
A47: Year-2 principal repaid | B47: =IFERROR(IF(B20="","",IF(D28="",0,D28)),"") -> 27538.954
A48: Year-3 interest | B48: =IFERROR(IF(B20="","",IF(C29="",0,C29)),"") -> 34642.563
A49: Year-3 principal repaid | B49: =IFERROR(IF(B20="","",IF(D29="",0,D29)),"") -> 30292.849
A50: DEBT SERVICE COVERAGE RATIO (DSCR)
A51: Year-1 DSCR | B51: =IFERROR(('2. 3-Year P&L'!$B$43-'2. 3-Year P&L'!$B$48+'2. 3-Year P&L'!$B$38+B44)/(B44+B45),"") -> 2.4975207 | C51: An INTEREST-ONLY year, if there is one: with only interest in the denominator the ratio shoots up and does not measure the business
A52: Year-2 DSCR | B52: =IFERROR(('2. 3-Year P&L'!$C$43-'2. 3-Year P&L'!$C$48+'2. 3-Year P&L'!$C$38+B46)/(B46+B47),"") -> 3.2163078
A53: Year-3 DSCR | B53: =IFERROR(('2. 3-Year P&L'!$D$43-'2. 3-Year P&L'!$D$48+'2. 3-Year P&L'!$D$38+B48)/(B48+B49),"") -> 3.6550505
A54: Minimum DSCR across the whole schedule | B54: =IFERROR(IF(COUNT(H27:H41)=0,"",MIN(H27:H41)),"") -> 2.4975207 | C54: The worst year of the life of the loan, not the best of the three the P&L projects. It is the number that decides a loan. Mind the scope: years 1 to 3 come from the P&L, and from year 4 on the schedule HOLDS year 3's cash flow, so the minimum over those years is a sustained projection, not a calculated year. The cash flow is after tax
A56: DSCR is calculated BEFORE debt and AFTER tax: income tax is subtracted from pre-tax income, depreciation and interest are added back, and the result is divided by what has to be paid that year. Below the minimum in the "0. Assumptions" tab, the business does not generate enough to repay the loan. In the schedule, the available cash flow from year 4 on is held at year 3's: the P&L projects only three years, and no growth is invented here that has not been calculated.
