Workbook

Sheet Instrucciones
A1: Campañas y Valle del Año
A2: AI Chef Pro · aichef.pro — Cómo Montar una Chocolatería
A3: Para qué sirve: saber si aguantas Navidad antes de que llegue, y de qué vives en julio y en agosto.
A5: Instrucciones de uso
A6: 1. Hoja «Parámetros». Lo primero son las ventas del año y las piezas de OBRADOR que salen un día normal, que no son lo mismo que las ventas: una caja de 35 bombones es UNA venta y treinta y seis bombones de obrador. Después, el coste por hora del refuerzo, que se calcula con el bruto de tu convenio, las pagas y la Seguridad Social.
A7: 2. Hoja «Calendario de Campañas». Las doce filas son las del BONUS-02-calendario-anual-tareas.xlsx del Kit de Tareas Chocolatería: las fechas, las acciones clave y los productos destacados están copiados de ahí y no se tocan. Lo que rellenas tú son las unidades del producto estrella un día normal y un día de pico, su PVP y los días que dura la campaña. De ahí salen los euros.
A8: 3. Hoja «Peso sobre el Año». Doce coeficientes que reparten las ventas del año, más el peso de cada campaña. Los coeficientes son supuestos y su forma la dicta el calendario del kit: diciembre arriba, agosto abajo y siete meses «Alta». Sustitúyelos por los tuyos en cuanto tengas un año de TPV.
A9: 4. Hoja «Capacidad vs Demanda del Pico». Arriba va la capacidad diaria del obrador, que se COPIA a mano de la hoja «Cuello de Botella» del libro 1: no hay ninguna fórmula entre ficheros, y por eso hay una fila de CUADRE que avisa si las dos cifras se separan. Debajo, mes a mes, si aguantas.
A10: 5. Hoja «Refuerzo y Tesorería». Personas de refuerzo, horas, antelación de compra de moldes y de packaging, y el dinero que eso deja parado. El resultado incremental de cada campaña es lo que de verdad te deja, ya descontado el refuerzo y el coste de tener el dinero quieto.
A11: 6. Hoja «El Valle de Agosto». Un mes «Baja» de doce. Lo que para es el obrador, no la caja: la tienda abre para el turista. La hoja calcula la caída del margen al cambiar el mix -menos ganache fresca, más tableta y producto estable- y pone los gastos fijos contra una facturación menor pero NO nula.
A13: Celdas verdes = campos editables
A15: Lo que conviene saber antes de empezar
... A30: Versión 1.0 · septiembre 2026 · aichef.pro/guia-chocolateria-obrador · info@aichef.pro

Sheet Parámetros
A1: Parámetros
A2: AI Chef Pro · aichef.pro — Cómo Montar una Chocolatería
A3: Ninguna fórmula de este libro lleva un número dentro: ni los días de la semana, ni los del año, ni el tipo de interés. Todo está aquí y todo se puede cambiar.
A5: Volumen, precio y margen
A6: Parámetro | B6: Valor | C6: Unidad | D6: De dónde sale | E6: Nota
A7: Ventas anuales sin IVA en velocidad de crucero | B7: 199087.94 | C7: EUR/año | D7: supuesto | E7: Sale de la carta y del tráfico supuesto de La Almendra: clientes al día por piezas por ticket por PVP medio ponderado. NO es un dato del sector -no existe ticket medio publicado de chocolatería- y se sustituye por el de tu plan financiero.
A8: Clientes al día en velocidad de crucero | B8: 67 | C8: clientes/día | D8: supuesto | E8: Mídelo con tu TPV en dos semanas y cámbialo.
A9: Piezas de VENTA al día en velocidad de crucero | B9: 93.8 | C9: ventas/día | D9: supuesto | E9: Clientes al día por piezas por ticket. Una caja cuenta como UNA.
A10: Días de apertura al año | B10: 304 | C10: días | D10: supuesto | E10: 6 dias por semana x 52 semanas = 312, menos 8 dias de cierre por festivos = 304. En agosto la TIENDA NO CIERRA: lo que para es el obrador (D36, y el literal del kit dice «la tienda abre para el turista aunque el obrador pare»). Una bomboneria de menos de 300 m2 tiene libertad horaria por el art. 5.2 de la Ley 1/2004, no por el 5.1 (`CHN-77`).
A11: Ticket medio sin IVA | B11: =IFERROR('Parámetros'!$B$7/('Parámetros'!$B$8*'Parámetros'!$B$10),"") -> 9.7745454 | C11: EUR/ticket | D11: calculado | E11: Ventas del año entre clientes al día por días de apertura. No se teclea: si lo tecleas y encima pones las ventas, se pueden contradecir.
A12: Bombones al día que salen del obrador en velocidad de crucero | B12: 472 | C12: piezas/día | D12: supuesto | E12: NO es lo mismo que las ventas: una caja de 35 bombones es UNA venta y treinta y seis bombones de obrador. Es la MISMA magnitud que el libro 1 publica como «Bombones al día objetivo» (471,81), y por eso se mide en bombones y no en tickets: comparar la capacidad con los tickets es lo que hace creer que Navidad cabe.
A13: Horas de obrador al día en jornada normal | B13: 8 | C13: horas | D13: supuesto | E13: Horas de reloj que el obrador está en marcha un día cualquiera, no horas de apertura de la tienda.
A14: Margen bruto medio con el mix de todo el año | B14: 0.7478 | C14: sobre ventas | D14: supuesto | E14: En el ejemplo sale de la carta de La Almendra (libro 4, hoja «Mix y Ticket Medio»), y aquí es una celda verde: este libro no tiene la carta dentro y no puede recalcularlo.
A15: Margen bruto medio con el mix de julio y agosto | B15: 0.7422 | C15: sobre ventas | D15: supuesto | E15: Menos ganache fresca y más tableta y producto estable -literal del kit-. El margen NO sube por vender tableta: la tableta lleva más chocolate por pieza y menos manos, y en este ejemplo el mix de verano deja algo MENOS de margen. Comprueba el tuyo antes de darlo por bueno.
A16: IVA del chocolate | B16: 0.1 | C16: sobre base | D16: CHN-71 | E16: El chocolate va al 10 % POR EXCLUSIÓN: la lista del 4 % es cerrada y no lo nombra, y tampoco está entre las dos exclusiones del 10 %. Se usa aquí para pasar la facturación de campaña, que se escribe CON IVA porque es precio de mostrador, a base imponible.
A18: Coste del refuerzo (convenio de Madrid, marcado EJEMPLO)
A19: Bruto mensual del grupo de convenio del refuerzo | B19: 1192.42 | C19: EUR/mes | D19: CHN-65b | E19: Grupo 5, «Personal de apoyo», del convenio de la Comunidad de Madrid (código 28001025011981, denominación oficial en REGCON «CONFITERIAS PASTELERIAS Y REPOSTERIA (COMERCIO E INDUSTRIA)»). Es un EJEMPLO: sustitúyelo por el de TU convenio. Y ojo: está PROBADO que no existe un convenio estatal del chocolate.
A20: Pagas del convenio al año | B20: 15 | C20: pagas | D20: CHN-65b | E20: El convenio de Madrid paga 15, no 14: cambia el coste mes a mes.
A21: Seguridad Social a cargo de la empresa | B21: 0.33 | C21: sobre bruto | D21: motor.PARAMETROS | E21: Contingencias comunes, desempleo, FOGASA y formación. Un refuerzo de campaña cuesta un tercio más de lo que pone su nómina.
A22: Horas anuales de contrato a jornada completa | B22: 1780 | C22: horas/año | D22: supuesto | E22: 40 horas por 52 semanas son 2.080, menos vacaciones y festivos.
A23: Coste por hora PAGADA del refuerzo | B23: =IFERROR('Parámetros'!$B$19*'Parámetros'!$B$20*(1+'Parámetros'!$B$21)/'Parámetros'!$B$22,"") -> 13.364483 | C23: EUR/hora | D23: calculado | E23: Bruto mensual por pagas por (1 más Seguridad Social), entre las horas anuales de contrato. NO es el «coste de la hora de obrador» del libro 4, que se calcula sobre horas PRODUCTIVAS y sobre otros grupos: las dos son correctas y miden denominadores distintos.
A25: Dinero, umbrales y calendario
A26: Tipo de interés anual del circulante | B26: 0.062 | C26: anual | D26: supuesto | E26: Coste del dinero parado en moldes y packaging de temporada. Si financias la compra con póliza, pon el tipo de tu póliza; si la pagas de tu caja, pon lo que te costaría pedirla.
A27: Gastos fijos mensuales | B27: 10212.17 | C27: EUR/mes | D27: supuesto | E27: Los del año de crucero, con personal, autónomos, alquiler, suministros, amortización y financieros dentro. Es la cifra contra la que se mide agosto, y por eso es una celda verde: el que manda es tu plan financiero.
A28: Umbral para marcar una campaña como grande | B28: 0.08 | C28: de las ventas del año | D28: supuesto | E28: Criterio de la casa, no del sector. Por encima de este peso, la campaña deja de ser una fecha y pasa a ser una decisión de compra, de personal y de tesorería.
A29: Tolerancia de las filas de CUADRE | B29: 0.02 | C29: desviación | D29: supuesto | E29: Por encima de esta desviación, la fila de CUADRE avisa de que lo que has traído de otro libro ya no es lo que aquel publica.
A30: Días por semana | B30: 7 | C30: días | D30: calendario | E30: Vive aquí porque las antelaciones de compra se cuentan en SEMANAS y el coste financiero en días: ninguna fórmula del libro lleva un número dentro.
A31: Días del año para el coste financiero | B31: 365 | C31: días | D31: convención | E31: Base de cálculo del interés del circulante. Tu banco puede usar 360: cámbialo aquí y todo el libro se recalcula.
A33: Versión 1.0 · septiembre 2026 · aichef.pro/guia-chocolateria-obrador · info@aichef.pro

Sheet Calendario de Campañas
A1: Calendario de Campañas
A2: AI Chef Pro · aichef.pro — Cómo Montar una Chocolatería
A3: Las FECHAS, las acciones clave y los productos destacados son del BONUS-02-calendario-anual-tareas.xlsx del Kit de Tareas Chocolatería, copiados fila a fila y SIN reescribir. Esta hoja pone los EUROS.
A6: Mes | B6: Temporada que declara el kit | C6: Campaña | D6: ¿Campaña propia? | E6: Producto estrella | F6: Bombones de obrador por unidad | G6: Unidades al día fuera de campaña | H6: Unidades al día en el pico | I6: PVP de campaña con IVA (EUR) | J6: Días de campaña | K6: Factor del pico | L6: Unidades incrementales de la campaña | M6: Facturación de la campaña con IVA (EUR) | N6: Facturación de la campaña sin IVA (EUR) | O6: Facturación INCREMENTAL sin IVA (EUR) | P6: Días de adelanto que admite | Q6: Acciones clave que publica el kit | R6: Productos destacados que publica el kit | S6: Nota
A7: Enero | B7: Media | C7: Reyes | D7: No | E7: TF4 - Turron de chocolate con almendra, 250 g | F7: 1 | G7: 0 | H7: 40 | I7: 18.5 | J7: 5 | K7: =IFERROR(H7/G7,"") | L7: =IFERROR((H7-G7)*J7,"") -> 200 | M7: =IFERROR(H7*J7*I7,"") -> 3700 | N7: =IFERROR(M7/(1+'Parámetros'!$B$16),"") -> 3363.6364 | O7: =IFERROR(L7*I7/(1+'Parámetros'!$B$16),"") -> 3363.6364 | P7: 20 | Q7: Reyes (6): liquidar turron y figuras de Navidad · rebajas post-Navidad · lanzar la coleccion de invierno · planificar San Valentin | R7: Trufas, bombones especiados, chocolate caliente | S7: Fecha menor: cierra la produccion de Navidad y liquida el stock. Lo que se produce para Reyes ya esta hecho en diciembre.
A8: Febrero | B8: Alta | C8: San Valentin | D8: Sí | E8: CJ1 - Caja surtida de 12 bombones | F8: 13 | G8: 8 | H8: 55 | I8: 20 | J8: 6 | K8: =IFERROR(H8/G8,"") -> 6.875 | L8: =IFERROR((H8-G8)*J8,"") -> 282 | M8: =IFERROR(H8*J8*I8,"") -> 6600 | N8: =IFERROR(M8/(1+'Parámetros'!$B$16),"") -> 6000 | O8: =IFERROR(L8*I8/(1+'Parámetros'!$B$16),"") -> 5127.2727 | P8: 8 | Q8: San Valentin (14): corazones y edicion limitada · fecha limite de encargos el dia 10 · entregas expres los dias 13 y 14 | R8: Corazones, bombones premium, tabletas personalizadas | S8: El pico de regalo. `CHS-34` mide que las ventas de chocolates y dulces pueden DUPLICAR el promedio anual en San Valentin, y que hay companias que hacen en ese solo evento hasta el 10 % de su venta anual: ese 10 % es de una compania concreta, no una regla del sector. La fecha limite de encargos la publica el propio kit: el dia 10.
A9: Marzo | B9: Alta | C9: Dia del Padre | D9: No | E9: CJ1 - Caja surtida de 12 bombones | F9: 13 | G9: 8 | H9: 26 | I9: 20 | J9: 4 | K9: =IFERROR(H9/G9,"") -> 3.25 | L9: =IFERROR((H9-G9)*J9,"") -> 72 | M9: =IFERROR(H9*J9*I9,"") -> 2080 | N9: =IFERROR(M9/(1+'Parámetros'!$B$16),"") -> 1890.9091 | O9: =IFERROR(L9*I9/(1+'Parámetros'!$B$16),"") -> 1309.0909 | P9: 8 | Q9: Dia del Padre (19) · preparacion de Pascua (fecha movil) · talleres infantiles de Semana Santa | R9: Figuras, huevos, monas de chocolate | S9: Fecha menor, y el mes en el que ya hay que estar produciendo Pascua. Los talleres infantiles de Semana Santa son la primera vez del ano en que la sala factura por hora en vez de por bombon.
A10: Abril | B10: Alta | C10: Pascua | D10: Sí | E10: TF1 - Huevo de Pascua de chocolate con leche, 250 g | F10: 1 | G10: 2 | H10: 30 | I10: 18.5 | J10: 10 | K10: =IFERROR(H10/G10,"") -> 15 | L10: =IFERROR((H10-G10)*J10,"") -> 280 | M10: =IFERROR(H10*J10*I10,"") -> 5550 | N10: =IFERROR(M10/(1+'Parámetros'!$B$16),"") -> 5045.4545 | O10: =IFERROR(L10*I10/(1+'Parámetros'!$B$16),"") -> 4709.0909 | P10: 20 | Q10: Semana Santa y Pascua: monas y huevos · arrancan las COMUNIONES (abril-junio): detalles de mesa, figuras y cajas personalizadas | R10: Huevos, conejos, bombones florales | S10: Campana de FIGURA Y MOLDE: la compra de moldes va MUY por delante, y es tesoreria inmovilizada que el libro 6 cuantifica. Fecha movil: si la Pascua cae pronto, marzo se come parte de abril.
A11: Mayo | B11: Alta | C11: COMUNIONES (pico) y Dia de la Madre | D11: Sí | E11: CJ4 - Estuche corporativo personalizado de 24 bombones | F11: 25 | G11: 1 | H11: 14 | I11: 34 | J11: 14 | K11: =IFERROR(H11/G11,"") -> 14 | L11: =IFERROR((H11-G11)*J11,"") -> 182 | M11: =IFERROR(H11*J11*I11,"") -> 6664 | N11: =IFERROR(M11/(1+'Parámetros'!$B$16),"") -> 6058.1818 | O11: =IFERROR(L11*I11/(1+'Parámetros'!$B$16),"") -> 5625.4545 | P11: 8 | Q11: Dia de la Madre (1.er domingo) · pico de COMUNIONES · edicion regalo premium | R11: Bombones premium, cestas regalo, tabletas grabadas | S11: El pico de las comuniones, y el mes con mas dias de campana del primer semestre. El packaging personalizado va con MAS antelacion que los moldes: es lo contrario de Pascua.
A12: Junio | B12: Media | C12: COMUNIONES (ultimas) | D12: Sí | E12: CJ2 - Caja surtida de 20 bombones | F12: 21 | G12: 1 | H12: 9 | I12: 28 | J12: 8 | K12: =IFERROR(H12/G12,"") -> 9 | L12: =IFERROR((H12-G12)*J12,"") -> 64 | M12: =IFERROR(H12*J12*I12,"") -> 2016 | N12: =IFERROR(M12/(1+'Parámetros'!$B$16),"") -> 1832.7273 | O12: =IFERROR(L12*I12/(1+'Parámetros'!$B$16),"") -> 1629.0909 | P12: 8 | Q12: Ultimas comuniones · inicio del verano: adaptar catalogo (menos ganache fresca, mas tableta y producto estable) | R12: Tabletas con fruta, bombones en camara | S12: El mes de apertura de La Almendra (1 de junio): «Media», con seis meses de rodaje por delante hasta Navidad. Y el mes en el que el catalogo EMPIEZA a cambiar, literal del kit: «menos ganache fresca, mas tableta y producto estable». Aqui arranca tambien la parada de ENVIOS, que es de canal online, no de mostrador.
A13: Julio | B13: Media | C13: Temporada turistica | D13: No | E13: TF5 - Almendras marcona banadas en chocolate, bolsa de 150 g | F13: 1 | G13: 6 | H13: 18 | I13: 7.4 | J13: 26 | K13: =IFERROR(H13/G13,"") -> 3 | L13: =IFERROR((H13-G13)*J13,"") -> 312 | M13: =IFERROR(H13*J13*I13,"") -> 3463.2 | N13: =IFERROR(M13/(1+'Parámetros'!$B$16),"") -> 3148.3636 | O13: =IFERROR(L13*I13/(1+'Parámetros'!$B$16),"") -> 2098.9091 | P13: 20 | Q13: Temporada turistica: packs souvenir y colaboraciones locales · vigilar a diario la temperatura de tienda y vitrina | R13: Tabletas souvenir, bombones regionales | S13: El turista no compra ganache: compra souvenir que viaja. Por eso julio ya usa el MIX DE VERANO, y por eso el kit manda vigilar A DIARIO la temperatura de tienda y vitrina.
A14: Agosto | B14: Baja | C14: Valle del obrador | D14: No | E14: TB1 - Tableta de chocolate negro de origen 70 %, 100 g | F14: 1 | G14: 5 | H14: 9 | I14: 6.9 | J14: 26 | K14: =IFERROR(H14/G14,"") -> 1.8 | L14: =IFERROR((H14-G14)*J14,"") -> 104 | M14: =IFERROR(H14*J14*I14,"") -> 1614.6 | N14: =IFERROR(M14/(1+'Parámetros'!$B$16),"") -> 1467.8182 | O14: =IFERROR(L14*I14/(1+'Parámetros'!$B$16),"") -> 652.36364 | P14: 20 | Q14: Asuncion (15): festivo nacional, la tienda abre para el turista aunque el obrador pare · mantenimiento profundo · vacaciones escalonadas · cerrar el pedido de coberturas de Navidad | R14: Produccion reducida, planificacion Q4 | S14: EL UNICO MES «BAJA» DE LOS DOCE. Lo que para es el OBRADOR, no la caja: el literal del kit es «la tienda abre para el turista aunque el obrador pare». Y es el mes en el que se CIERRA EL PEDIDO DE COBERTURAS DE NAVIDAD, que es la decision de tesoreria mas grande del ano.
A15: Septiembre | B15: Media | C15: Apertura de agenda corporativa | D15: No | E15: CJ4 - Estuche corporativo personalizado de 24 bombones | F15: 25 | G15: 1 | H15: 4 | I15: 34 | J15: 20 | K15: =IFERROR(H15/G15,"") -> 4 | L15: =IFERROR((H15-G15)*J15,"") -> 60 | M15: =IFERROR(H15*J15*I15,"") -> 2720 | N15: =IFERROR(M15/(1+'Parámetros'!$B$16),"") -> 2472.7273 | O15: =IFERROR(L15*I15/(1+'Parámetros'!$B$16),"") -> 1854.5455 | P15: 8 | Q15: Vuelta a la rutina · coleccion de otono · ferias gastronomicas · abrir la agenda de pedidos corporativos de Navidad | R15: Bombones de frutos secos, praline, especiados | S15: El mes que decide diciembre: aqui se abre la agenda corporativa, y el plazo minimo de un pedido de empresa es de 14 dias desde la aprobacion de la muestra (`CHS-55`). Vender un estuche corporativo el 15 de diciembre no es una venta: es una promesa que no se puede cumplir.
A16: Octubre | B16: Alta | C16: Halloween | D16: Sí | E16: BC5 - Trufa de chocolate negro al cacao | F16: 1 | G16: 1 | H16: 12 | I16: 18.5 | J16: 6 | K16: =IFERROR(H16/G16,"") -> 12 | L16: =IFERROR((H16-G16)*J16,"") -> 66 | M16: =IFERROR(H16*J16*I16,"") -> 1332 | N16: =IFERROR(M16/(1+'Parámetros'!$B$16),"") -> 1210.9091 | O16: =IFERROR(L16*I16/(1+'Parámetros'!$B$16),"") -> 1110 | P16: 20 | Q16: Halloween (31): figuras y bombones de temporada · produccion navidena a pleno · publicar el catalogo de Navidad | R16: Figuras Halloween, bombones calabaza, tabletas oscuras | S16: Arranque de la temporada alta. Lo importante de octubre NO es Halloween: es que la produccion de Navidad ya va a pleno y se PAGA aqui, para cobrarse en diciembre. Ese desfase es lo que el libro 7 pone en la tesoreria mes a mes.
A17: Noviembre | B17: Alta | C17: Todos los Santos y Black Friday | D17: Sí | E17: TF3 - Hueso de santo banado en chocolate | F17: 1 | G17: 0 | H17: 90 | I17: 1.6 | J17: 5 | K17: =IFERROR(H17/G17,"") | L17: =IFERROR((H17-G17)*J17,"") -> 450 | M17: =IFERROR(H17*J17*I17,"") -> 720 | N17: =IFERROR(M17/(1+'Parámetros'!$B$16),"") -> 654.54545 | O17: =IFERROR(L17*I17/(1+'Parámetros'!$B$16),"") -> 654.54545 | P17: 3 | Q17: Todos los Santos (1): panellets y huesos de santo banados · Black Friday (ultimo viernes) · preventa de Navidad · turrones y cestas | R17: Panellets y huesos de santo banados, turrones, cestas corporativas, figuras navidenas | S17: Dos campanas en un mes y ninguna se parece: Todos los Santos es produccion de obrador a pieza pequena (los huesos de santo, TF3, la unica referencia con huevo), y Black Friday es canal ONLINE con descuento. Ojo con el descuento: subir en noviembre para «rebajar» en diciembre NO cumple la regla de los 30 dias del art. 20 de la Ley 7/1996 en la redaccion del RDL 24/2021 (`CHN-76`) - que NO es el art. 20 del TRLGDCU.
A18: Diciembre | B18: Alta | C18: Navidad | D18: Sí | E18: CJ3 - Caja surtida de 35 bombones | F18: 36 | G18: 2 | H18: 22 | I18: 45 | J18: 22 | K18: =IFERROR(H18/G18,"") -> 11 | L18: =IFERROR((H18-G18)*J18,"") -> 440 | M18: =IFERROR(H18*J18*I18,"") -> 21780 | N18: =IFERROR(M18/(1+'Parámetros'!$B$16),"") -> 19800 | O18: =IFERROR(L18*I18/(1+'Parámetros'!$B$16),"") -> 18000 | P18: 8 | Q18: NAVIDAD, maxima produccion · puente de la Constitucion y la Inmaculada (6-8): fin de semana largo de maxima venta en tienda · fecha limite de encargos y horarios especiales del 24 y el 31 | R18: Turrones, figuras, bombones navidenos, cestas | S18: LA CAMPANA MAYOR, y la que decide el ano. Su pedido corporativo se cierra en octubre y su limite de produccion lo calcula el libro 7 HACIA ATRAS desde la capacidad del libro 1 (cruce 7 <- 1 de `CRUCES`). La fecha limite de encargos y los horarios del 24 y el 31 los publica el propio kit.
A19: TOTAL del año | J19: =SUM(J7:J18) -> 152 | L19: =SUM(L7:L18) -> 2512 | M19: =SUM(M7:M18) -> 58239.8 | N19: =SUM(N7:N18) -> 52945.273 | O19: =SUM(O7:O18) -> 46134
A21: La campaña de COMUNIONES (abril, mayo y junio) es la única que reparte su carga en tres meses en vez de concentrarla en una semana, y es campaña PROPIA, no la cola de Pascua: lo que la distingue es que se encarga con seis semanas de antelación un detalle de mesa personalizado, con señal. El obrador trabaja contra pedido firme: merma cero y tesorería a favor.
A23: Versión 1.0 · septiembre 2026 · aichef.pro/guia-chocolateria-obrador · info@aichef.pro

Sheet Peso sobre el Año
A1: Peso Sobre el Año
A2: AI Chef Pro · aichef.pro — Cómo Montar una Chocolatería
A3: Doce coeficientes que reparten las ventas del año. Son SUPUESTOS -no existe reparto mensual publicado de chocolatería- y su forma la dicta el calendario del kit: diciembre arriba, agosto abajo.
A6: Mes | B6: Temporada que declara el kit | C6: Coeficiente de estacionalidad | D6: Días de apertura del mes | E6: Ventas del mes sin IVA (EUR) | F6: Peso sobre el año | G6: Ventas por día de apertura (EUR) | H6: Veces un día medio | I6: Nota
A7: Enero | B7: Media | C7: 0.92 | D7: 26 | E7: =IFERROR('Parámetros'!$B$7*C7/12,"") -> 15263.409 | F7: =IFERROR(E7/'Parámetros'!$B$7,"") -> 0.076666667 | G7: =IFERROR(E7/D7,"") -> 587.05418 | H7: =IFERROR(G7*'Parámetros'!$B$10/'Parámetros'!$B$7,"") -> 0.89641026
A8: Febrero | B8: Alta | C8: 1.12 | D8: 24 | E8: =IFERROR('Parámetros'!$B$7*C8/12,"") -> 18581.541 | F8: =IFERROR(E8/'Parámetros'!$B$7,"") -> 0.093333333 | G8: =IFERROR(E8/D8,"") -> 774.23088 | H8: =IFERROR(G8*'Parámetros'!$B$10/'Parámetros'!$B$7,"") -> 1.1822222
A9: Marzo | B9: Alta | C9: 1.02 | D9: 26 | E9: =IFERROR('Parámetros'!$B$7*C9/12,"") -> 16922.475 | F9: =IFERROR(E9/'Parámetros'!$B$7,"") -> 0.085 | G9: =IFERROR(E9/D9,"") -> 650.86442 | H9: =IFERROR(G9*'Parámetros'!$B$10/'Parámetros'!$B$7,"") -> 0.99384615
A10: Abril | B10: Alta | C10: 1.08 | D10: 25 | E10: =IFERROR('Parámetros'!$B$7*C10/12,"") -> 17917.915 | F10: =IFERROR(E10/'Parámetros'!$B$7,"") -> 0.09 | G10: =IFERROR(E10/D10,"") -> 716.71658 | H10: =IFERROR(G10*'Parámetros'!$B$10/'Parámetros'!$B$7,"") -> 1.0944
A11: Mayo | B11: Alta | C11: 1.1 | D11: 26 | E11: =IFERROR('Parámetros'!$B$7*C11/12,"") -> 18249.728 | F11: =IFERROR(E11/'Parámetros'!$B$7,"") -> 0.091666667 | G11: =IFERROR(E11/D11,"") -> 701.91261 | H11: =IFERROR(G11*'Parámetros'!$B$10/'Parámetros'!$B$7,"") -> 1.0717949
A12: Junio | B12: Media | C12: 0.92 | D12: 25 | E12: =IFERROR('Parámetros'!$B$7*C12/12,"") -> 15263.409 | F12: =IFERROR(E12/'Parámetros'!$B$7,"") -> 0.076666667 | G12: =IFERROR(E12/D12,"") -> 610.53635 | H12: =IFERROR(G12*'Parámetros'!$B$10/'Parámetros'!$B$7,"") -> 0.93226667
A13: Julio | B13: Media | C13: 0.82 | D13: 27 | E13: =IFERROR('Parámetros'!$B$7*C13/12,"") -> 13604.343 | F13: =IFERROR(E13/'Parámetros'!$B$7,"") -> 0.068333333 | G13: =IFERROR(E13/D13,"") -> 503.86454 | H13: =IFERROR(G13*'Parámetros'!$B$10/'Parámetros'!$B$7,"") -> 0.76938272
A14: Agosto | B14: Baja | C14: 0.6 | D14: 26 | E14: =IFERROR('Parámetros'!$B$7*C14/12,"") -> 9954.397 | F14: =IFERROR(E14/'Parámetros'!$B$7,"") -> 0.05 | G14: =IFERROR(E14/D14,"") -> 382.86142 | H14: =IFERROR(G14*'Parámetros'!$B$10/'Parámetros'!$B$7,"") -> 0.58461538 | I14: El único mes «Baja» de los doce. Agosto NO vale cero: la tienda abre para el turista y lo que para es el obrador.
A15: Septiembre | B15: Media | C15: 0.86 | D15: 25 | E15: =IFERROR('Parámetros'!$B$7*C15/12,"") -> 14267.969 | F15: =IFERROR(E15/'Parámetros'!$B$7,"") -> 0.071666667 | G15: =IFERROR(E15/D15,"") -> 570.71876 | H15: =IFERROR(G15*'Parámetros'!$B$10/'Parámetros'!$B$7,"") -> 0.87146667
A16: Octubre | B16: Alta | C16: 1.02 | D16: 26 | E16: =IFERROR('Parámetros'!$B$7*C16/12,"") -> 16922.475 | F16: =IFERROR(E16/'Parámetros'!$B$7,"") -> 0.085 | G16: =IFERROR(E16/D16,"") -> 650.86442 | H16: =IFERROR(G16*'Parámetros'!$B$10/'Parámetros'!$B$7,"") -> 0.99384615
A17: Noviembre | B17: Alta | C17: 1.1 | D17: 25 | E17: =IFERROR('Parámetros'!$B$7*C17/12,"") -> 18249.728 | F17: =IFERROR(E17/'Parámetros'!$B$7,"") -> 0.091666667 | G17: =IFERROR(E17/D17,"") -> 729.98911 | H17: =IFERROR(G17*'Parámetros'!$B$10/'Parámetros'!$B$7,"") -> 1.1146667
A18: Diciembre | B18: Alta | C18: 1.44 | D18: 23 | E18: =IFERROR('Parámetros'!$B$7*C18/12,"") -> 23890.553 | F18: =IFERROR(E18/'Parámetros'!$B$7,"") -> 0.12 | G18: =IFERROR(E18/D18,"") -> 1038.7197 | H18: =IFERROR(G18*'Parámetros'!$B$10/'Parámetros'!$B$7,"") -> 1.586087
A19: TOTAL del año | C19: =SUM(C7:C18) -> 12 | D19: =SUM(D7:D18) -> 304 | E19: =SUM(E7:E18) -> 199087.94 | F19: =SUM(F7:F18) -> 1
A21: Lo que pesa cada campaña sobre el año
A22: Campaña | B22: Mes | C22: Facturación de la campaña sin IVA (EUR) | D22: Peso sobre las ventas del año | E22: Facturación INCREMENTAL sin IVA (EUR) | F22: Peso incremental sobre el año | G22: ¿Campaña grande? | H22: Nota
A23: Reyes | B23: Enero | C23: ='Calendario de Campañas'!N7 -> 3363.6364 | D23: =IFERROR(C23/'Parámetros'!$B$7,"") -> 0.016895229 | E23: ='Calendario de Campañas'!O7 -> 3363.6364 | F23: =IFERROR(E23/'Parámetros'!$B$7,"") -> 0.016895229 | G23: =IF(NOT(ISNUMBER(D23)),"",IF(D23>='Parámetros'!$B$28,"Sí","No")) -> No
A24: San Valentin | B24: Febrero | C24: ='Calendario de Campañas'!N8 -> 6000 | D24: =IFERROR(C24/'Parámetros'!$B$7,"") -> 0.030137436 | E24: ='Calendario de Campañas'!O8 -> 5127.2727 | F24: =IFERROR(E24/'Parámetros'!$B$7,"") -> 0.025753809 | G24: =IF(NOT(ISNUMBER(D24)),"",IF(D24>='Parámetros'!$B$28,"Sí","No")) -> No
A25: Dia del Padre | B25: Marzo | C25: ='Calendario de Campañas'!N9 -> 1890.9091 | D25: =IFERROR(C25/'Parámetros'!$B$7,"") -> 0.0094978585 | E25: ='Calendario de Campañas'!O9 -> 1309.0909 | F25: =IFERROR(E25/'Parámetros'!$B$7,"") -> 0.0065754405 | G25: =IF(NOT(ISNUMBER(D25)),"",IF(D25>='Parámetros'!$B$28,"Sí","No")) -> No
A26: Pascua | B26: Abril | C26: ='Calendario de Campañas'!N10 -> 5045.4545 | D26: =IFERROR(C26/'Parámetros'!$B$7,"") -> 0.025342844 | E26: ='Calendario de Campañas'!O10 -> 4709.0909 | F26: =IFERROR(E26/'Parámetros'!$B$7,"") -> 0.023653321 | G26: =IF(NOT(ISNUMBER(D26)),"",IF(D26>='Parámetros'!$B$28,"Sí","No")) -> No
A27: COMUNIONES (pico) y Dia de la Madre | B27: Mayo | C27: ='Calendario de Campañas'!N11 -> 6058.1818 | D27: =IFERROR(C27/'Parámetros'!$B$7,"") -> 0.030429678 | E27: ='Calendario de Campañas'!O11 -> 5625.4545 | F27: =IFERROR(E27/'Parámetros'!$B$7,"") -> 0.028256129 | G27: =IF(NOT(ISNUMBER(D27)),"",IF(D27>='Parámetros'!$B$28,"Sí","No")) -> No
A28: COMUNIONES (ultimas) | B28: Junio | C28: ='Calendario de Campañas'!N12 -> 1832.7273 | D28: =IFERROR(C28/'Parámetros'!$B$7,"") -> 0.0092056167 | E28: ='Calendario de Campañas'!O12 -> 1629.0909 | F28: =IFERROR(E28/'Parámetros'!$B$7,"") -> 0.0081827704 | G28: =IF(NOT(ISNUMBER(D28)),"",IF(D28>='Parámetros'!$B$28,"Sí","No")) -> No
A29: Temporada turistica | B29: Julio | C29: ='Calendario de Campañas'!N13 -> 3148.3636 | D29: =IFERROR(C29/'Parámetros'!$B$7,"") -> 0.015813934 | E29: ='Calendario de Campañas'!O13 -> 2098.9091 | F29: =IFERROR(E29/'Parámetros'!$B$7,"") -> 0.010542623 | G29: =IF(NOT(ISNUMBER(D29)),"",IF(D29>='Parámetros'!$B$28,"Sí","No")) -> No
A30: Valle del obrador | B30: Agosto | C30: ='Calendario de Campañas'!N14 -> 1467.8182 | D30: =IFERROR(C30/'Parámetros'!$B$7,"") -> 0.0073727127 | E30: ='Calendario de Campañas'!O14 -> 652.36364 | F30: =IFERROR(E30/'Parámetros'!$B$7,"") -> 0.0032767612 | G30: =IF(NOT(ISNUMBER(D30)),"",IF(D30>='Parámetros'!$B$28,"Sí","No")) -> No
A31: Apertura de agenda corporativa | B31: Septiembre | C31: ='Calendario de Campañas'!N15 -> 2472.7273 | D31: =IFERROR(C31/'Parámetros'!$B$7,"") -> 0.012420277 | E31: ='Calendario de Campañas'!O15 -> 1854.5455 | F31: =IFERROR(E31/'Parámetros'!$B$7,"") -> 0.0093152074 | G31: =IF(NOT(ISNUMBER(D31)),"",IF(D31>='Parámetros'!$B$28,"Sí","No")) -> No
A32: Halloween | B32: Octubre | C32: ='Calendario de Campañas'!N16 -> 1210.9091 | D32: =IFERROR(C32/'Parámetros'!$B$7,"") -> 0.0060822825 | E32: ='Calendario de Campañas'!O16 -> 1110 | F32: =IFERROR(E32/'Parámetros'!$B$7,"") -> 0.0055754256 | G32: =IF(NOT(ISNUMBER(D32)),"",IF(D32>='Parámetros'!$B$28,"Sí","No")) -> No
A33: Todos los Santos y Black Friday | B33: Noviembre | C33: ='Calendario de Campañas'!N17 -> 654.54545 | D33: =IFERROR(C33/'Parámetros'!$B$7,"") -> 0.0032877203 | E33: ='Calendario de Campañas'!O17 -> 654.54545 | F33: =IFERROR(E33/'Parámetros'!$B$7,"") -> 0.0032877203 | G33: =IF(NOT(ISNUMBER(D33)),"",IF(D33>='Parámetros'!$B$28,"Sí","No")) -> No
A34: Navidad | B34: Diciembre | C34: ='Calendario de Campañas'!N18 -> 19800 | D34: =IFERROR(C34/'Parámetros'!$B$7,"") -> 0.099453538 | E34: ='Calendario de Campañas'!O18 -> 18000 | F34: =IFERROR(E34/'Parámetros'!$B$7,"") -> 0.090412307 | G34: =IF(NOT(ISNUMBER(D34)),"",IF(D34>='Parámetros'!$B$28,"Sí","No")) -> Sí
A35: TOTAL de las doce campañas | C35: =SUM(C23:C34) -> 52945.273 | D35: =SUM(D23:D34) -> 0.26593913 | E35: =SUM(E23:E34) -> 46134 | F35: =SUM(F23:F34) -> 0.23172674
A37: Contraste publicado: hasta el 10 % de la venta anual en un solo evento | B37: 0.1 | C37: Es el caso EXTREMO de una compañía concreta, no una regla del sector: la fuente dice que las ventas de chocolates y dulces pueden llegar a duplicar el promedio anual en San Valentín y que hay compañías que hacen en ese solo evento hasta el 10 % de su venta anual. Sirve para saber si tu reparto es plausible, no para copiarlo.
A39: La suma de las doce campañas NO tiene que dar el 100 % del año: una campaña es lo que se vende del producto estrella en sus días, y el resto del año se vende carta. Lo que sí tiene que cuadrar es que las unidades de campaña quepan dentro de las unidades del año, y eso lo comprueba la hoja «El Valle de Agosto».
A41: Versión 1.0 · septiembre 2026 · aichef.pro/guia-chocolateria-obrador · info@aichef.pro

Sheet Capacidad vs Demanda del Pico
A1: Capacidad vs Demanda del Pico
A2: AI Chef Pro · aichef.pro — Cómo Montar una Chocolatería
A3: Todo se mide en BOMBONES DE OBRADOR: una caja de 35 bombones es una venta y treinta y seis piezas de obrador. Medir el pico en tickets es lo que hace creer que Navidad cabe.
A5: Capacidad diaria del obrador: trae aquí la cifra de capacidad-obrador-y-clima.xlsx!Cuello de Botella!B7
A6: Capacidad del obrador en jornada normal (bombones de obrador/día) | B6: 512 | C6: piezas/día | D6: libro 1 | E6: COPIA a mano el resultado de la hoja «Cuello de Botella» del libro «capacidad-obrador-y-clima.xlsx» de este mismo pack: la casilla de piezas al día que permite el equipo que limita. NO hay ninguna fórmula entre ficheros -si la hubiera, se rompería al mover o renombrar el otro libro-. El valor por defecto son los 512 bombones al día que ese libro publica hoy en «Bombones al día que permite el conjunto», con el puesto de envasado y montaje de cajas como equipo que limita. Si cambias de atemperadora, de moldes o de puesto de envasado, vuelve a copiarlo.
A7: Cifra que publica hoy esa hoja del libro 1 | B7: 512 | C7: piezas/día | E7: Anota aquí lo que ves en el libro 1 la última vez que lo abriste. Si arriba tecleas otra cosa -porque has comprado otra máquina, o porque te lo dijo el instalador-, la fila de CUADRE te avisa en vez de dejar las dos cifras separadas en silencio.
A8: Desviación entre las dos | B8: =IFERROR(ABS(B6-B7)/B7,"") -> 0
A9: CUADRE: la capacidad que usas frente a la que publica el libro 1 | B9: =IF(NOT(ISNUMBER(B8)),"",IF(B8<='Parámetros'!$B$29,"CUADRA","REVISA: la capacidad que estás usando no es la que calcula el libro 1")) -> CUADRA
A11: Mes | B11: Campaña | C11: Bombones de obrador de base al día | D11: Unidades extra del producto estrella al día | E11: Bombones de obrador extra al día | F11: DEMANDA de bombones de obrador al día | G11: Capacidad al día | H11: Déficit diario | I11: ¿Aguanta el obrador? | J11: Horas de obrador que harían falta | K11: Excedente de un día normal | L11: Piezas adelantables antes de la campaña | M11: Déficit de la campaña tras adelantar | N11: Bombones de obrador extra en toda la campaña | O11: Nota
A12: Enero | B12: Reyes | C12: =IFERROR('Parámetros'!$B$12*'Peso sobre el Año'!C7,"") -> 434.24 | D12: =IFERROR('Calendario de Campañas'!H7-'Calendario de Campañas'!G7,"") -> 40 | E12: =IFERROR(D12*'Calendario de Campañas'!F7,"") -> 40 | F12: =IFERROR(C12+E12,"") -> 474.24 | G12: =B6 -> 512 | H12: =IF(OR(NOT(ISNUMBER(F12)),NOT(ISNUMBER(G12))),"",MAX(0,F12-G12)) -> 0 | I12: =IF(NOT(ISNUMBER(H12)),"",IF(H12<=0,"Sí","No")) -> Sí | J12: =IFERROR(F12*'Parámetros'!$B$13/G12,"") -> 7.41 | K12: =IF(OR(NOT(ISNUMBER(G12)),NOT(ISNUMBER(C12))),"",MAX(0,G12-C12)) -> 77.76 | L12: =IFERROR(K12*'Calendario de Campañas'!P7,"") -> 1555.2 | M12: =IF(OR(NOT(ISNUMBER(H12)),NOT(ISNUMBER(L12))),"",MAX(0,H12*'Calendario de Campañas'!J7-L12)) -> 0 | N12: =IFERROR(E12*'Calendario de Campañas'!J7,"") -> 200 | O12: Las tres palancas, y van en este orden: adelantar producción de lo que aguanta, alargar la jornada de máquina y, sólo después, contratar refuerzo. La columna de piezas adelantables usa los días de adelanto que admite el producto estrella de cada campaña, que los manda la vida útil, no las ganas.
A13: Febrero | B13: San Valentin | C13: =IFERROR('Parámetros'!$B$12*'Peso sobre el Año'!C8,"") -> 528.64 | D13: =IFERROR('Calendario de Campañas'!H8-'Calendario de Campañas'!G8,"") -> 47 | E13: =IFERROR(D13*'Calendario de Campañas'!F8,"") -> 611 | F13: =IFERROR(C13+E13,"") -> 1139.64 | G13: =B6 -> 512 | H13: =IF(OR(NOT(ISNUMBER(F13)),NOT(ISNUMBER(G13))),"",MAX(0,F13-G13)) -> 627.64 | I13: =IF(NOT(ISNUMBER(H13)),"",IF(H13<=0,"Sí","No")) -> No | J13: =IFERROR(F13*'Parámetros'!$B$13/G13,"") -> 17.806875 | K13: =IF(OR(NOT(ISNUMBER(G13)),NOT(ISNUMBER(C13))),"",MAX(0,G13-C13)) -> 0 | L13: =IFERROR(K13*'Calendario de Campañas'!P8,"") -> 0 | M13: =IF(OR(NOT(ISNUMBER(H13)),NOT(ISNUMBER(L13))),"",MAX(0,H13*'Calendario de Campañas'!J8-L13)) -> 3765.84 | N13: =IFERROR(E13*'Calendario de Campañas'!J8,"") -> 3666
A14: Marzo | B14: Dia del Padre | C14: =IFERROR('Parámetros'!$B$12*'Peso sobre el Año'!C9,"") -> 481.44 | D14: =IFERROR('Calendario de Campañas'!H9-'Calendario de Campañas'!G9,"") -> 18 | E14: =IFERROR(D14*'Calendario de Campañas'!F9,"") -> 234 | F14: =IFERROR(C14+E14,"") -> 715.44 | G14: =B6 -> 512 | H14: =IF(OR(NOT(ISNUMBER(F14)),NOT(ISNUMBER(G14))),"",MAX(0,F14-G14)) -> 203.44 | I14: =IF(NOT(ISNUMBER(H14)),"",IF(H14<=0,"Sí","No")) -> No | J14: =IFERROR(F14*'Parámetros'!$B$13/G14,"") -> 11.17875 | K14: =IF(OR(NOT(ISNUMBER(G14)),NOT(ISNUMBER(C14))),"",MAX(0,G14-C14)) -> 30.56 | L14: =IFERROR(K14*'Calendario de Campañas'!P9,"") -> 244.48 | M14: =IF(OR(NOT(ISNUMBER(H14)),NOT(ISNUMBER(L14))),"",MAX(0,H14*'Calendario de Campañas'!J9-L14)) -> 569.28 | N14: =IFERROR(E14*'Calendario de Campañas'!J9,"") -> 936
A15: Abril | B15: Pascua | C15: =IFERROR('Parámetros'!$B$12*'Peso sobre el Año'!C10,"") -> 509.76 | D15: =IFERROR('Calendario de Campañas'!H10-'Calendario de Campañas'!G10,"") -> 28 | E15: =IFERROR(D15*'Calendario de Campañas'!F10,"") -> 28 | F15: =IFERROR(C15+E15,"") -> 537.76 | G15: =B6 -> 512 | H15: =IF(OR(NOT(ISNUMBER(F15)),NOT(ISNUMBER(G15))),"",MAX(0,F15-G15)) -> 25.76 | I15: =IF(NOT(ISNUMBER(H15)),"",IF(H15<=0,"Sí","No")) -> No | J15: =IFERROR(F15*'Parámetros'!$B$13/G15,"") -> 8.4025 | K15: =IF(OR(NOT(ISNUMBER(G15)),NOT(ISNUMBER(C15))),"",MAX(0,G15-C15)) -> 2.24 | L15: =IFERROR(K15*'Calendario de Campañas'!P10,"") -> 44.8 | M15: =IF(OR(NOT(ISNUMBER(H15)),NOT(ISNUMBER(L15))),"",MAX(0,H15*'Calendario de Campañas'!J10-L15)) -> 212.8 | N15: =IFERROR(E15*'Calendario de Campañas'!J10,"") -> 280
A16: Mayo | B16: COMUNIONES (pico) y Dia de la Madre | C16: =IFERROR('Parámetros'!$B$12*'Peso sobre el Año'!C11,"") -> 519.2 | D16: =IFERROR('Calendario de Campañas'!H11-'Calendario de Campañas'!G11,"") -> 13 | E16: =IFERROR(D16*'Calendario de Campañas'!F11,"") -> 325 | F16: =IFERROR(C16+E16,"") -> 844.2 | G16: =B6 -> 512 | H16: =IF(OR(NOT(ISNUMBER(F16)),NOT(ISNUMBER(G16))),"",MAX(0,F16-G16)) -> 332.2 | I16: =IF(NOT(ISNUMBER(H16)),"",IF(H16<=0,"Sí","No")) -> No | J16: =IFERROR(F16*'Parámetros'!$B$13/G16,"") -> 13.190625 | K16: =IF(OR(NOT(ISNUMBER(G16)),NOT(ISNUMBER(C16))),"",MAX(0,G16-C16)) -> 0 | L16: =IFERROR(K16*'Calendario de Campañas'!P11,"") -> 0 | M16: =IF(OR(NOT(ISNUMBER(H16)),NOT(ISNUMBER(L16))),"",MAX(0,H16*'Calendario de Campañas'!J11-L16)) -> 4650.8 | N16: =IFERROR(E16*'Calendario de Campañas'!J11,"") -> 4550
A17: Junio | B17: COMUNIONES (ultimas) | C17: =IFERROR('Parámetros'!$B$12*'Peso sobre el Año'!C12,"") -> 434.24 | D17: =IFERROR('Calendario de Campañas'!H12-'Calendario de Campañas'!G12,"") -> 8 | E17: =IFERROR(D17*'Calendario de Campañas'!F12,"") -> 168 | F17: =IFERROR(C17+E17,"") -> 602.24 | G17: =B6 -> 512 | H17: =IF(OR(NOT(ISNUMBER(F17)),NOT(ISNUMBER(G17))),"",MAX(0,F17-G17)) -> 90.24 | I17: =IF(NOT(ISNUMBER(H17)),"",IF(H17<=0,"Sí","No")) -> No | J17: =IFERROR(F17*'Parámetros'!$B$13/G17,"") -> 9.41 | K17: =IF(OR(NOT(ISNUMBER(G17)),NOT(ISNUMBER(C17))),"",MAX(0,G17-C17)) -> 77.76 | L17: =IFERROR(K17*'Calendario de Campañas'!P12,"") -> 622.08 | M17: =IF(OR(NOT(ISNUMBER(H17)),NOT(ISNUMBER(L17))),"",MAX(0,H17*'Calendario de Campañas'!J12-L17)) -> 99.84 | N17: =IFERROR(E17*'Calendario de Campañas'!J12,"") -> 1344
A18: Julio | B18: Temporada turistica | C18: =IFERROR('Parámetros'!$B$12*'Peso sobre el Año'!C13,"") -> 387.04 | D18: =IFERROR('Calendario de Campañas'!H13-'Calendario de Campañas'!G13,"") -> 12 | E18: =IFERROR(D18*'Calendario de Campañas'!F13,"") -> 12 | F18: =IFERROR(C18+E18,"") -> 399.04 | G18: =B6 -> 512 | H18: =IF(OR(NOT(ISNUMBER(F18)),NOT(ISNUMBER(G18))),"",MAX(0,F18-G18)) -> 0 | I18: =IF(NOT(ISNUMBER(H18)),"",IF(H18<=0,"Sí","No")) -> Sí | J18: =IFERROR(F18*'Parámetros'!$B$13/G18,"") -> 6.235 | K18: =IF(OR(NOT(ISNUMBER(G18)),NOT(ISNUMBER(C18))),"",MAX(0,G18-C18)) -> 124.96 | L18: =IFERROR(K18*'Calendario de Campañas'!P13,"") -> 2499.2 | M18: =IF(OR(NOT(ISNUMBER(H18)),NOT(ISNUMBER(L18))),"",MAX(0,H18*'Calendario de Campañas'!J13-L18)) -> 0 | N18: =IFERROR(E18*'Calendario de Campañas'!J13,"") -> 312
A19: Agosto | B19: Valle del obrador | C19: =IFERROR('Parámetros'!$B$12*'Peso sobre el Año'!C14,"") -> 283.2 | D19: =IFERROR('Calendario de Campañas'!H14-'Calendario de Campañas'!G14,"") -> 4 | E19: =IFERROR(D19*'Calendario de Campañas'!F14,"") -> 4 | F19: =IFERROR(C19+E19,"") -> 287.2 | G19: =B6 -> 512 | H19: =IF(OR(NOT(ISNUMBER(F19)),NOT(ISNUMBER(G19))),"",MAX(0,F19-G19)) -> 0 | I19: =IF(NOT(ISNUMBER(H19)),"",IF(H19<=0,"Sí","No")) -> Sí | J19: =IFERROR(F19*'Parámetros'!$B$13/G19,"") -> 4.4875 | K19: =IF(OR(NOT(ISNUMBER(G19)),NOT(ISNUMBER(C19))),"",MAX(0,G19-C19)) -> 228.8 | L19: =IFERROR(K19*'Calendario de Campañas'!P14,"") -> 4576 | M19: =IF(OR(NOT(ISNUMBER(H19)),NOT(ISNUMBER(L19))),"",MAX(0,H19*'Calendario de Campañas'!J14-L19)) -> 0 | N19: =IFERROR(E19*'Calendario de Campañas'!J14,"") -> 104
A20: Septiembre | B20: Apertura de agenda corporativa | C20: =IFERROR('Parámetros'!$B$12*'Peso sobre el Año'!C15,"") -> 405.92 | D20: =IFERROR('Calendario de Campañas'!H15-'Calendario de Campañas'!G15,"") -> 3 | E20: =IFERROR(D20*'Calendario de Campañas'!F15,"") -> 75 | F20: =IFERROR(C20+E20,"") -> 480.92 | G20: =B6 -> 512 | H20: =IF(OR(NOT(ISNUMBER(F20)),NOT(ISNUMBER(G20))),"",MAX(0,F20-G20)) -> 0 | I20: =IF(NOT(ISNUMBER(H20)),"",IF(H20<=0,"Sí","No")) -> Sí | J20: =IFERROR(F20*'Parámetros'!$B$13/G20,"") -> 7.514375 | K20: =IF(OR(NOT(ISNUMBER(G20)),NOT(ISNUMBER(C20))),"",MAX(0,G20-C20)) -> 106.08 | L20: =IFERROR(K20*'Calendario de Campañas'!P15,"") -> 848.64 | M20: =IF(OR(NOT(ISNUMBER(H20)),NOT(ISNUMBER(L20))),"",MAX(0,H20*'Calendario de Campañas'!J15-L20)) -> 0 | N20: =IFERROR(E20*'Calendario de Campañas'!J15,"") -> 1500
A21: Octubre | B21: Halloween | C21: =IFERROR('Parámetros'!$B$12*'Peso sobre el Año'!C16,"") -> 481.44 | D21: =IFERROR('Calendario de Campañas'!H16-'Calendario de Campañas'!G16,"") -> 11 | E21: =IFERROR(D21*'Calendario de Campañas'!F16,"") -> 11 | F21: =IFERROR(C21+E21,"") -> 492.44 | G21: =B6 -> 512 | H21: =IF(OR(NOT(ISNUMBER(F21)),NOT(ISNUMBER(G21))),"",MAX(0,F21-G21)) -> 0 | I21: =IF(NOT(ISNUMBER(H21)),"",IF(H21<=0,"Sí","No")) -> Sí | J21: =IFERROR(F21*'Parámetros'!$B$13/G21,"") -> 7.694375 | K21: =IF(OR(NOT(ISNUMBER(G21)),NOT(ISNUMBER(C21))),"",MAX(0,G21-C21)) -> 30.56 | L21: =IFERROR(K21*'Calendario de Campañas'!P16,"") -> 611.2 | M21: =IF(OR(NOT(ISNUMBER(H21)),NOT(ISNUMBER(L21))),"",MAX(0,H21*'Calendario de Campañas'!J16-L21)) -> 0 | N21: =IFERROR(E21*'Calendario de Campañas'!J16,"") -> 66
A22: Noviembre | B22: Todos los Santos y Black Friday | C22: =IFERROR('Parámetros'!$B$12*'Peso sobre el Año'!C17,"") -> 519.2 | D22: =IFERROR('Calendario de Campañas'!H17-'Calendario de Campañas'!G17,"") -> 90 | E22: =IFERROR(D22*'Calendario de Campañas'!F17,"") -> 90 | F22: =IFERROR(C22+E22,"") -> 609.2 | G22: =B6 -> 512 | H22: =IF(OR(NOT(ISNUMBER(F22)),NOT(ISNUMBER(G22))),"",MAX(0,F22-G22)) -> 97.2 | I22: =IF(NOT(ISNUMBER(H22)),"",IF(H22<=0,"Sí","No")) -> No | J22: =IFERROR(F22*'Parámetros'!$B$13/G22,"") -> 9.51875 | K22: =IF(OR(NOT(ISNUMBER(G22)),NOT(ISNUMBER(C22))),"",MAX(0,G22-C22)) -> 0 | L22: =IFERROR(K22*'Calendario de Campañas'!P17,"") -> 0 | M22: =IF(OR(NOT(ISNUMBER(H22)),NOT(ISNUMBER(L22))),"",MAX(0,H22*'Calendario de Campañas'!J17-L22)) -> 486 | N22: =IFERROR(E22*'Calendario de Campañas'!J17,"") -> 450
A23: Diciembre | B23: Navidad | C23: =IFERROR('Parámetros'!$B$12*'Peso sobre el Año'!C18,"") -> 679.68 | D23: =IFERROR('Calendario de Campañas'!H18-'Calendario de Campañas'!G18,"") -> 20 | E23: =IFERROR(D23*'Calendario de Campañas'!F18,"") -> 720 | F23: =IFERROR(C23+E23,"") -> 1399.68 | G23: =B6 -> 512 | H23: =IF(OR(NOT(ISNUMBER(F23)),NOT(ISNUMBER(G23))),"",MAX(0,F23-G23)) -> 887.68 | I23: =IF(NOT(ISNUMBER(H23)),"",IF(H23<=0,"Sí","No")) -> No | J23: =IFERROR(F23*'Parámetros'!$B$13/G23,"") -> 21.87 | K23: =IF(OR(NOT(ISNUMBER(G23)),NOT(ISNUMBER(C23))),"",MAX(0,G23-C23)) -> 0 | L23: =IFERROR(K23*'Calendario de Campañas'!P18,"") -> 0 | M23: =IF(OR(NOT(ISNUMBER(H23)),NOT(ISNUMBER(L23))),"",MAX(0,H23*'Calendario de Campañas'!J18-L23)) -> 19528.96 | N23: =IFERROR(E23*'Calendario de Campañas'!J18,"") -> 15840
A24: TOTAL del año | N24: =SUM(N12:N23) -> 29248
A26: Campañas que NO aguanta el obrador | B26: =COUNTIF(I12:I23,"No") -> 7
A27: Campañas con déficit incluso después de adelantar | B27: =COUNTIF(M12:M23,">0") -> 7
A29: Un «No» aquí no significa que no puedas hacer la campaña: significa que ese día, con ese equipo y esa plantilla, no cabe. Mira la columna de al lado -piezas adelantables- antes de contratar a nadie: adelantar tableta y figura es gratis y contratar no lo es.
A31: Versión 1.0 · septiembre 2026 · aichef.pro/guia-chocolateria-obrador · info@aichef.pro

Sheet Refuerzo y Tesorería
A1: Refuerzo y Tesorería
A2: AI Chef Pro · aichef.pro — Cómo Montar una Chocolatería
A3: Una campaña no cuesta sólo las horas del refuerzo: cuesta también el dinero que dejas parado en moldes y en packaging semanas antes de vender nada.
A6: Mes | B6: Campaña | C6: Personas de refuerzo | D6: Horas por persona | E6: Coste del refuerzo (EUR) | F6: Antelación de los moldes (semanas) | G6: Inversión en moldes de temporada (EUR) | H6: Antelación del packaging (semanas) | I6: Inversión en packaging de temporada (EUR) | J6: Tesorería inmovilizada (EUR) | K6: Días con el dinero parado | L6: Coste financiero del inmovilizado (EUR) | M6: Margen bruto de la facturación incremental (EUR) | N6: RESULTADO INCREMENTAL (EUR) | O6: Veredicto | P6: Nota
A7: Enero | B7: Reyes | C7: 0 | D7: 0 | E7: =IFERROR(C7*D7*'Parámetros'!$B$23,"") -> 0 | F7: 0 | G7: 0 | H7: 0 | I7: 120 | J7: =IFERROR(G7+I7,"") -> 120 | K7: =IF(OR(NOT(ISNUMBER(F7)),NOT(ISNUMBER(H7))),"",MAX(F7,H7)*'Parámetros'!$B$30) -> 0 | L7: =IFERROR(J7*'Parámetros'!$B$26*K7/'Parámetros'!$B$31,"") -> 0 | M7: =IFERROR('Calendario de Campañas'!O7*'Parámetros'!$B$14,"") -> 2515.3273 | N7: =IFERROR(M7-E7-L7,"") -> 2515.3273 | O7: =IF(NOT(ISNUMBER(N7)),"",IF(N7>=0,"La campaña deja dinero","La campaña cuesta más de lo que deja")) -> La campaña deja dinero | P7: Cero personas de refuerzo y cero euros es un cero REAL: esa campaña se cubre con la plantilla que ya tienes.
A8: Febrero | B8: San Valentin | C8: 1 | D8: 30 | E8: =IFERROR(C8*D8*'Parámetros'!$B$23,"") -> 400.93448 | F8: 8 | G8: 280 | H8: 6 | I8: 420 | J8: =IFERROR(G8+I8,"") -> 700 | K8: =IF(OR(NOT(ISNUMBER(F8)),NOT(ISNUMBER(H8))),"",MAX(F8,H8)*'Parámetros'!$B$30) -> 56 | L8: =IFERROR(J8*'Parámetros'!$B$26*K8/'Parámetros'!$B$31,"") -> 6.6586301 | M8: =IFERROR('Calendario de Campañas'!O8*'Parámetros'!$B$14,"") -> 3834.1745 | N8: =IFERROR(M8-E8-L8,"") -> 3426.5814 | O8: =IF(NOT(ISNUMBER(N8)),"",IF(N8>=0,"La campaña deja dinero","La campaña cuesta más de lo que deja")) -> La campaña deja dinero | P8: Con refuerzo contratado: recuerda que el coste de empresa es un tercio más que el bruto de la nómina.
A9: Marzo | B9: Dia del Padre | C9: 0 | D9: 0 | E9: =IFERROR(C9*D9*'Parámetros'!$B$23,"") -> 0 | F9: 6 | G9: 0 | H9: 4 | I9: 180 | J9: =IFERROR(G9+I9,"") -> 180 | K9: =IF(OR(NOT(ISNUMBER(F9)),NOT(ISNUMBER(H9))),"",MAX(F9,H9)*'Parámetros'!$B$30) -> 42 | L9: =IFERROR(J9*'Parámetros'!$B$26*K9/'Parámetros'!$B$31,"") -> 1.2841644 | M9: =IFERROR('Calendario de Campañas'!O9*'Parámetros'!$B$14,"") -> 978.93818 | N9: =IFERROR(M9-E9-L9,"") -> 977.65402 | O9: =IF(NOT(ISNUMBER(N9)),"",IF(N9>=0,"La campaña deja dinero","La campaña cuesta más de lo que deja")) -> La campaña deja dinero | P9: Cero personas de refuerzo y cero euros es un cero REAL: esa campaña se cubre con la plantilla que ya tienes.
A10: Abril | B10: Pascua | C10: 1 | D10: 40 | E10: =IFERROR(C10*D10*'Parámetros'!$B$23,"") -> 534.5793 | F10: 10 | G10: 520 | H10: 6 | I10: 380 | J10: =IFERROR(G10+I10,"") -> 900 | K10: =IF(OR(NOT(ISNUMBER(F10)),NOT(ISNUMBER(H10))),"",MAX(F10,H10)*'Parámetros'!$B$30) -> 70 | L10: =IFERROR(J10*'Parámetros'!$B$26*K10/'Parámetros'!$B$31,"") -> 10.70137 | M10: =IFERROR('Calendario de Campañas'!O10*'Parámetros'!$B$14,"") -> 3521.4582 | N10: =IFERROR(M10-E10-L10,"") -> 2976.1775 | O10: =IF(NOT(ISNUMBER(N10)),"",IF(N10>=0,"La campaña deja dinero","La campaña cuesta más de lo que deja")) -> La campaña deja dinero | P10: Con refuerzo contratado: recuerda que el coste de empresa es un tercio más que el bruto de la nómina.
A11: Mayo | B11: COMUNIONES (pico) y Dia de la Madre | C11: 1 | D11: 50 | E11: =IFERROR(C11*D11*'Parámetros'!$B$23,"") -> 668.22413 | F11: 8 | G11: 240 | H11: 10 | I11: 560 | J11: =IFERROR(G11+I11,"") -> 800 | K11: =IF(OR(NOT(ISNUMBER(F11)),NOT(ISNUMBER(H11))),"",MAX(F11,H11)*'Parámetros'!$B$30) -> 70 | L11: =IFERROR(J11*'Parámetros'!$B$26*K11/'Parámetros'!$B$31,"") -> 9.5123288 | M11: =IFERROR('Calendario de Campañas'!O11*'Parámetros'!$B$14,"") -> 4206.7149 | N11: =IFERROR(M11-E11-L11,"") -> 3528.9785 | O11: =IF(NOT(ISNUMBER(N11)),"",IF(N11>=0,"La campaña deja dinero","La campaña cuesta más de lo que deja")) -> La campaña deja dinero | P11: Con refuerzo contratado: recuerda que el coste de empresa es un tercio más que el bruto de la nómina.
A12: Junio | B12: COMUNIONES (ultimas) | C12: 0 | D12: 0 | E12: =IFERROR(C12*D12*'Parámetros'!$B$23,"") -> 0 | F12: 6 | G12: 0 | H12: 8 | I12: 260 | J12: =IFERROR(G12+I12,"") -> 260 | K12: =IF(OR(NOT(ISNUMBER(F12)),NOT(ISNUMBER(H12))),"",MAX(F12,H12)*'Parámetros'!$B$30) -> 56 | L12: =IFERROR(J12*'Parámetros'!$B$26*K12/'Parámetros'!$B$31,"") -> 2.4732055 | M12: =IFERROR('Calendario de Campañas'!O12*'Parámetros'!$B$14,"") -> 1218.2342 | N12: =IFERROR(M12-E12-L12,"") -> 1215.761 | O12: =IF(NOT(ISNUMBER(N12)),"",IF(N12>=0,"La campaña deja dinero","La campaña cuesta más de lo que deja")) -> La campaña deja dinero | P12: Cero personas de refuerzo y cero euros es un cero REAL: esa campaña se cubre con la plantilla que ya tienes.
A13: Julio | B13: Temporada turistica | C13: 0 | D13: 0 | E13: =IFERROR(C13*D13*'Parámetros'!$B$23,"") -> 0 | F13: 0 | G13: 0 | H13: 4 | I13: 220 | J13: =IFERROR(G13+I13,"") -> 220 | K13: =IF(OR(NOT(ISNUMBER(F13)),NOT(ISNUMBER(H13))),"",MAX(F13,H13)*'Parámetros'!$B$30) -> 28 | L13: =IFERROR(J13*'Parámetros'!$B$26*K13/'Parámetros'!$B$31,"") -> 1.0463562 | M13: =IFERROR('Calendario de Campañas'!O13*'Parámetros'!$B$14,"") -> 1569.5642 | N13: =IFERROR(M13-E13-L13,"") -> 1568.5179 | O13: =IF(NOT(ISNUMBER(N13)),"",IF(N13>=0,"La campaña deja dinero","La campaña cuesta más de lo que deja")) -> La campaña deja dinero | P13: Cero personas de refuerzo y cero euros es un cero REAL: esa campaña se cubre con la plantilla que ya tienes.
A14: Agosto | B14: Valle del obrador | C14: 0 | D14: 0 | E14: =IFERROR(C14*D14*'Parámetros'!$B$23,"") -> 0 | F14: 0 | G14: 0 | H14: 0 | I14: 0 | J14: =IFERROR(G14+I14,"") -> 0 | K14: =IF(OR(NOT(ISNUMBER(F14)),NOT(ISNUMBER(H14))),"",MAX(F14,H14)*'Parámetros'!$B$30) -> 0 | L14: =IFERROR(J14*'Parámetros'!$B$26*K14/'Parámetros'!$B$31,"") -> 0 | M14: =IFERROR('Calendario de Campañas'!O14*'Parámetros'!$B$14,"") -> 487.83753 | N14: =IFERROR(M14-E14-L14,"") -> 487.83753 | O14: =IF(NOT(ISNUMBER(N14)),"",IF(N14>=0,"La campaña deja dinero","La campaña cuesta más de lo que deja")) -> La campaña deja dinero | P14: Cero personas de refuerzo y cero euros es un cero REAL: esa campaña se cubre con la plantilla que ya tienes.
A15: Septiembre | B15: Apertura de agenda corporativa | C15: 0 | D15: 0 | E15: =IFERROR(C15*D15*'Parámetros'!$B$23,"") -> 0 | F15: 0 | G15: 0 | H15: 12 | I15: 340 | J15: =IFERROR(G15+I15,"") -> 340 | K15: =IF(OR(NOT(ISNUMBER(F15)),NOT(ISNUMBER(H15))),"",MAX(F15,H15)*'Parámetros'!$B$30) -> 84 | L15: =IFERROR(J15*'Parámetros'!$B$26*K15/'Parámetros'!$B$31,"") -> 4.8512877 | M15: =IFERROR('Calendario de Campañas'!O15*'Parámetros'!$B$14,"") -> 1386.8291 | N15: =IFERROR(M15-E15-L15,"") -> 1381.9778 | O15: =IF(NOT(ISNUMBER(N15)),"",IF(N15>=0,"La campaña deja dinero","La campaña cuesta más de lo que deja")) -> La campaña deja dinero | P15: Cero personas de refuerzo y cero euros es un cero REAL: esa campaña se cubre con la plantilla que ya tienes.
A16: Octubre | B16: Halloween | C16: 0 | D16: 0 | E16: =IFERROR(C16*D16*'Parámetros'!$B$23,"") -> 0 | F16: 8 | G16: 180 | H16: 6 | I16: 200 | J16: =IFERROR(G16+I16,"") -> 380 | K16: =IF(OR(NOT(ISNUMBER(F16)),NOT(ISNUMBER(H16))),"",MAX(F16,H16)*'Parámetros'!$B$30) -> 56 | L16: =IFERROR(J16*'Parámetros'!$B$26*K16/'Parámetros'!$B$31,"") -> 3.6146849 | M16: =IFERROR('Calendario de Campañas'!O16*'Parámetros'!$B$14,"") -> 830.058 | N16: =IFERROR(M16-E16-L16,"") -> 826.44332 | O16: =IF(NOT(ISNUMBER(N16)),"",IF(N16>=0,"La campaña deja dinero","La campaña cuesta más de lo que deja")) -> La campaña deja dinero | P16: Cero personas de refuerzo y cero euros es un cero REAL: esa campaña se cubre con la plantilla que ya tienes.
A17: Noviembre | B17: Todos los Santos y Black Friday | C17: 1 | D17: 25 | E17: =IFERROR(C17*D17*'Parámetros'!$B$23,"") -> 334.11206 | F17: 4 | G17: 140 | H17: 8 | I17: 380 | J17: =IFERROR(G17+I17,"") -> 520 | K17: =IF(OR(NOT(ISNUMBER(F17)),NOT(ISNUMBER(H17))),"",MAX(F17,H17)*'Parámetros'!$B$30) -> 56 | L17: =IFERROR(J17*'Parámetros'!$B$26*K17/'Parámetros'!$B$31,"") -> 4.946411 | M17: =IFERROR('Calendario de Campañas'!O17*'Parámetros'!$B$14,"") -> 489.46909 | N17: =IFERROR(M17-E17-L17,"") -> 150.41062 | O17: =IF(NOT(ISNUMBER(N17)),"",IF(N17>=0,"La campaña deja dinero","La campaña cuesta más de lo que deja")) -> La campaña deja dinero | P17: Con refuerzo contratado: recuerda que el coste de empresa es un tercio más que el bruto de la nómina.
A18: Diciembre | B18: Navidad | C18: 2 | D18: 70 | E18: =IFERROR(C18*D18*'Parámetros'!$B$23,"") -> 1871.0276 | F18: 12 | G18: 450 | H18: 14 | I18: 980 | J18: =IFERROR(G18+I18,"") -> 1430 | K18: =IF(OR(NOT(ISNUMBER(F18)),NOT(ISNUMBER(H18))),"",MAX(F18,H18)*'Parámetros'!$B$30) -> 98 | L18: =IFERROR(J18*'Parámetros'!$B$26*K18/'Parámetros'!$B$31,"") -> 23.804603 | M18: =IFERROR('Calendario de Campañas'!O18*'Parámetros'!$B$14,"") -> 13460.4 | N18: =IFERROR(M18-E18-L18,"") -> 11565.568 | O18: =IF(NOT(ISNUMBER(N18)),"",IF(N18>=0,"La campaña deja dinero","La campaña cuesta más de lo que deja")) -> La campaña deja dinero | P18: Las inversiones en moldes y en packaging son CIFRAS DE CAMPAÑA y supuestos declarados, no un número de moldes por un precio: un molde de policarbonato vale entre 24,20 y 42,83 EUR y elegir un punto de ese rango para multiplicarlo es inventarse un presupuesto.
A19: TOTAL del año | E19: =SUM(E7:E18) -> 3808.8775 | G19: =SUM(G7:G18) -> 1810 | I19: =SUM(I7:I18) -> 4040 | J19: =SUM(J7:J18) -> 5850 | L19: =SUM(L7:L18) -> 68.893041 | M19: =SUM(M7:M18) -> 34499.005 | N19: =SUM(N7:N18) -> 30621.235
A21: El resultado incremental es lo que la campaña te deja POR ENCIMA de lo que habrías vendido igual: por eso se calcula sobre la facturación incremental y no sobre la total. Una campaña que sale negativa no es siempre una campaña que retirar -Navidad trae clientes que vuelven en enero-, pero sí es una campaña que hay que rehacer: menos referencias, menos moldes nuevos o más precio.
A23: Versión 1.0 · septiembre 2026 · aichef.pro/guia-chocolateria-obrador · info@aichef.pro

Sheet El Valle de Agosto
A1: El Valle de Agosto
A2: AI Chef Pro · aichef.pro — Cómo Montar una Chocolatería
A3: Un mes «Baja» de doce, y lo que para es el OBRADOR, no la caja: literal del kit, «la tienda abre para el turista aunque el obrador pare».
A5: Concepto | B5: Valor | C5: Unidad | D5: De dónde sale | E5: Nota
A6: Mes del valle según el calendario del kit | B6: Agosto | C6: mes | D6: BONUS-02!Calendario | E6: Es AGOSTO, y es uno de los doce. Junio y julio son «Media»: en junio empieza a cambiar el catálogo y en julio entra el turista.
A7: Meses en temporada «Baja» de los doce | B7: 1 | C7: meses | D7: BONUS-02!Calendario | E7: Siete «Alta», cuatro «Media» y UNO «Baja». Hablar de un valle de tres meses contradice el calendario que la propia casa publica.
A8: ¿Paras el obrador en agosto? | B8: Sí | C8: sí/no | D8: decisión tuya | E8: En el ejemplo, sí: mantenimiento profundo, vacaciones escalonadas y cierre del pedido de coberturas de Navidad, que son los tres motivos que nombra el propio kit.
A9: ¿Paras los envíos? | B9: Sí | C9: sí/no | D9: decisión tuya | E9: Es una decisión de CANAL ONLINE, no de mostrador: el chocolate no viaja en verano sin cadena de frío.
A10: Meses con los envíos parados | B10: de junio a septiembre | C10: meses | D10: supuesto sobre dato de canal online | E10: De junio a septiembre. El mostrador sigue vivo los cuatro meses, y en julio y agosto con turista.
A11: Ventas de agosto sin IVA | B11: ='Peso sobre el Año'!E14 -> 9954.397 | C11: EUR | D11: calculado | E11: Sale del coeficiente de estacionalidad de agosto. NO es cero: la tienda abre.
A12: Ventas de un mes medio sin IVA | B12: =IFERROR('Parámetros'!$B$7/12,"") -> 16590.662 | C12: EUR | D12: calculado | E12: Las ventas del año entre doce.
A13: Agosto frente a un mes medio | B13: =IFERROR(B11/B12,"") -> 0.6 | C13: veces | D13: calculado | E13: Cuánto factura agosto por cada euro de un mes normal.
A14: Margen bruto con el mix de todo el año | B14: ='Parámetros'!$B$14 -> 0.7478 | C14: sobre ventas | D14: Parámetros | E14: El de la carta completa.
A15: Margen bruto con el mix de julio y agosto | B15: ='Parámetros'!$B$15 -> 0.7422 | C15: sobre ventas | D15: Parámetros | E15: Menos ganache fresca, más tableta y producto estable: literal del kit para junio.
A16: Caída del margen al cambiar el mix | B16: =IFERROR(B15-B14,"") -> -0.0056 | C16: puntos | D16: calculado | E16: Sale en NEGATIVO si el mix de verano deja menos margen, que es lo que pasa en este ejemplo: la tableta lleva más chocolate por pieza y menos manos. Vender producto estable en agosto es una decisión de CADUCIDAD, no de margen, y conviene saberlo antes de tomarla.
A17: Margen bruto de agosto en euros | B17: =IFERROR(B11*B15,"") -> 7388.1535 | C17: EUR | D17: calculado | E17: Ventas de agosto por el margen del mix de verano.
A18: Margen bruto de un mes medio en euros | B18: =IFERROR(B12*B14,"") -> 12406.497 | C18: EUR | D18: calculado | E18: Ventas de un mes medio por el margen del año.
A19: Gastos fijos del mes | B19: ='Parámetros'!$B$27 -> 10212.17 | C19: EUR | D19: Parámetros | E19: Siguen corriendo enteros: el alquiler, el préstamo, los seguros y los tres equipos de frío, que en agosto trabajan más que nunca.
A20: RESULTADO DE AGOSTO | B20: =IFERROR(B17-B19,"") -> -2824.0165 | C20: EUR | D20: calculado | E20: Margen bruto de agosto menos los gastos fijos del mes. Es la cifra que hay que mirar en mayo, no en agosto.
A21: Resultado de un mes medio | B21: =IFERROR(B18-B19,"") -> 2194.3268 | C21: EUR | D21: calculado | E21: Para comparar.
A22: Lo que te cuesta agosto frente a un mes medio | B22: =IFERROR(B20-B21,"") -> -5018.3433 | C22: EUR | D22: calculado | E22: Ésta es la cifra que hay que tener provisionada, y es la razón por la que el ejemplo abre el 1 de junio: así el valle cae dentro del arranque, cuando todavía sale barato.
A23: Veredicto de agosto | B23: =IF(NOT(ISNUMBER(B20)),"",IF(B20>=0,"Agosto se paga solo","Agosto da pérdida: provisiónala, no cierres la tienda")) -> Agosto da pérdida: provisiónala, no cierres la tienda | D23: calculado | E23: Un agosto en negativo NO es un motivo para cerrar: es un motivo para provisionarlo. Cerrar la tienda en el mes en el que el turista pasa por delante sería cambiar una pérdida pequeña por una grande.
A25: Comprobación interna: las unidades de campaña frente a las del año
A26: Bombones de obrador extra que suman las doce campañas | B26: ='Capacidad vs Demanda del Pico'!N24 -> 29248 | C26: piezas/año | D26: Capacidad vs Demanda | E26: Son las bombones de obrador que las campañas añaden a lo que se produce un día normal.
A27: Bombones de obrador al año en velocidad de crucero | B27: =IFERROR('Parámetros'!$B$12*'Parámetros'!$B$10,"") -> 143488 | C27: piezas/año | D27: Parámetros | E27: Bombones de obrador al día por días de apertura.
A28: Las campañas sobre la producción del año | B28: =IFERROR(B26/B27,"") -> 0.20383586 | C28: sobre el año | D28: calculado | E28: Cuánto añaden las campañas a un año de producción.
A29: CUADRE INTERNO (no es un cruce entre libros): ¿caben las campañas dentro del año? | B29: =IF(NOT(ISNUMBER(B28)),"",IF(B28<=1,"CUADRA: las campañas caben dentro del año","REVISA: las campañas suman más producción que todo un año")) -> CUADRA: las campañas caben dentro del año | D29: calculado | E29: Si las campañas añaden más producción que la de un año entero, o el calendario está inflado o las unidades de pico están mal medidas. No es un cruce con otro fichero: es una comprobación de este libro consigo mismo.
A31: Lo que el kit dice, literal, de los tres meses de verano: junio, «adaptar catálogo (menos ganache fresca, más tableta y producto estable)»; julio, «temporada turística: packs souvenir y colaboraciones locales»; agosto, «la tienda abre para el turista aunque el obrador pare». Tres meses, tres cosas distintas, y sólo uno de ellos es «Baja».
A33: Y la línea que sí funciona en agosto son los TALLERES: no dependen del precio del cacao, no necesitan obrador y ocupan la sala en el mes en el que la sala está vacía. Su economía -euros por hora de sala dando taller frente a euros por hora de la misma sala vendiendo- la calcula el plan financiero del pack, no este libro.
A37: Listas de validación (no las borres: las usan los desplegables)
A38: Sí o no
A39: Sí
A40: No
A43: Versión 1.0 · septiembre 2026 · aichef.pro/guia-chocolateria-obrador · info@aichef.pro
