Workbook

Sheet Instrucciones
A1: Plan financiero a 3 años
A2: AI Chef Pro · aichef.pro — Cómo Montar una Chocolatería
A3: Para qué sirve: saber si el negocio se sostiene, qué canal lo sostiene y si el taller da dinero o te ocupa el obrador en el peor momento.
A5: Instrucciones de uso
A6: 1. Hoja «0. Supuestos»: es el cuadro de mandos. Aquí se teclean las TASAS y los DRIVERS —clientes al día, piezas por ticket, días de apertura, tipos de IVA, food cost, condiciones del préstamo, umbrales de control— y el resto del libro se recalcula solo. Las partidas de gasto se teclean en su hoja, no aquí.
A7: 2. Hoja «Inversión Inicial»: NO vuelve a pedirte las nueve partidas del CAPEX. Te pide UNA cifra —el CAPEX SIN el fondo de maniobra, que publica el libro «calculadora-capex-chocolateria»— y dota aquí el fondo de maniobra con TUS meses de colchón y TUS gastos fijos. El fondo se calcula una sola vez en todo el pack, y es esta hoja la que lo calcula.
A8: 3. Hoja «PyG 3 Años»: la cuenta de resultados. El AÑO 2 es el año de crucero; el año 1 lleva la rampa de arranque y el año 3 crece sobre el crucero. La amortización y los intereses van DENTRO de los costes fijos, y la cuota de autónomos del titular también. Abajo, el escenario de formato: bombonería frente a bombonería con taza y churros, lado a lado.
A9: 4. Hoja «Punto de Equilibrio»: cuántos clientes al día hay que hacer para no perder dinero, en dos versiones. La CONTABLE incluye la amortización; la de CAJA le quita la amortización (que no se paga) y le suma la devolución de principal (que sí). La segunda es la que decide si llegas a fin de mes.
A10: 5. Hoja «Escenarios»: el mismo modelo con tres juegos de clientes, ticket medio y días de apertura. La columna «Realista» LEE el año de crucero del P&L, así que no puede desviarse de él.
A11: 6. Hoja «Personal»: tres personas y dos jornadas y media, con el bruto del convenio en celda verde y la Seguridad Social a cargo de la empresa DENTRO. Del bruto al coste empresa hay un tercio más: es el salto que más sorprende. Al lado, los salarios de MERCADO, que son orientativos y no son un convenio.
A12: 7. Hoja «Tesorería 12 meses»: el P&L dice si el negocio gana dinero; esta hoja dice si le queda caja para llegar a fin de mes. Trae la estacionalidad con el valle de agosto dentro, la rampa de arranque, el desfase de cobros y pagos, la liquidación trimestral del IVA y la FECHA LÍMITE de cierre de pedidos de Navidad, calculada hacia atrás desde la capacidad de tu obrador.
A13: 8. Hoja «Financiación»: de dónde sale el dinero y cuánto cuesta devolverlo. El cuadro de amortización es MENSUAL, con 84 filas, porque la carencia de este caso son seis meses y un cuadro anual no sabe expresar medio año. Abajo, el DSCR año a año: es el número que decide la operación bancaria.
... A31: Qué hace este libro y qué hace otro (para no teclear dos veces)
A32: Producto o libro | B32: Qué aporta | C32: Qué NO hace este libro
A33: kit-tareas-chocolateria (12 €) | B33: La operación del obrador que ya tienes: partidas de producción, curvas de templado, calendario anual de campañas y fichas de tarea por perfil. | C33: Este libro NO planifica producción ni templa nada. Toma su resultado en euros y lo proyecta a tres años. Los tres perfiles de la hoja de Personal son los de ese kit, con sus nombres.
A34: El libro «sensibilidad-al-precio-del-cacao» de esta misma guía | B34: El precio de la cobertura, en las dos bases de IVA, y qué pasa con cada referencia si el cacao sube un 40 %. | C34: Aquí el coste de la materia entra como UN porcentaje sobre las ventas. El precio de la cobertura en base imponible se trae de allí por celda verde, con su fila de cuadre.
A35: El libro «calculadora-capex-chocolateria» de esta misma guía | B35: El CAPEX partida a partida, con su columna de IVA por línea, la variante del formato y la comparación entre traspaso y obra nueva. | C35: Aquí entra UNA cifra: el CAPEX SIN el fondo de maniobra. El fondo lo dota esta hoja y vuelve allí ya calculado.
A36: El libro «capacidad-obrador-y-clima» de esta misma guía | B36: Cuántos bombones al día aguanta el equipo que vas a comprar y cuál es el que limita. | C36: Aquí esa capacidad sólo sirve para una cosa, y es importante: calcular hacia atrás la fecha límite de cierre de pedidos de Navidad.
A37: plan-negocio-bar-restaurante y los demás planes de negocio (35 €) | B37: El dossier completo que se le entrega al banco, con memoria escrita. | C37: Este libro es el motor de números de una GUÍA de apertura. Si vas a pedir financiación de verdad, el dossier del banco es aquel producto.
A39: Cada cuánto se usa este libro
A40: Cadencia: «0. Supuestos» e «Inversión Inicial», MIENTRAS BUSCAS LOCAL y pides presupuestos, tantas veces como haga falta. El P&L, el punto de equilibrio y los escenarios, UNA VEZ ANTES DE FIRMAR y otra antes de sentarte con el banco. «Tesorería 12 meses», CADA MES durante el primer año, sustituyendo la previsión por lo que pasó de verdad. «Canales y Punto Muerto» y «Talleres y Regalo Corporativo», cada vez que te plantees abrir o cerrar un canal, y en septiembre, cuando se cierra la agenda corporativa de Navidad.
A42: Para editar la estructura o una celda que no esté en verde: Revisar > Desproteger hoja (no tiene contraseña).
A44: Diseñado por John Guerrero — chef y consultor gastronómico desde 2010, en cocina desde los 17 años.
A45: Versión 1.0 · septiembre 2026 · aichef.pro/guia-chocolateria-obrador · info@aichef.pro

Sheet 0. Supuestos
A1: Supuestos: Las Tasas y los Drivers del Modelo
A2: AI Chef Pro · aichef.pro — Cómo Montar una Chocolatería
A3: Cambia las celdas VERDES y el resto del libro se recalcula solo. Las partidas de gasto se teclean en su hoja, no aquí. Cada supuesto lleva al lado de dónde sale y qué pasa si lo mueves.
A5: ACTIVIDAD
A6: Clientes al día en velocidad de crucero | B6: 67 | C6: SUPUESTO, y de los gordos: no existe dato público de tráfico de una bombonería española, así que este número no es un benchmark. Cuéntalos tú en la puerta de tres bombonerías parecidas a la que quieres abrir, un sábado y un martes, y trae el tuyo. Es la ÚNICA palanca que hay que tocar para mover el resultado: los costes no se maquillan.
A7: Piezas por ticket | B7: 1.4 | C7: SUPUESTO. En bombonería es BAJO -1,4- porque la unidad de venta real es la CAJA, no la pieza: quien entra a por un regalo se lleva una caja de 20 euros, no ocho bombones sueltos. De aquí sale el ticket medio, que NO se teclea: se calcula.
A8: PVP medio ponderado de la carta, CON IVA (€/pieza) | B8: 7.68 | C8: Sale de las 28 referencias del libro «carta-de-apertura-y-escandallo-chocolate», ponderadas por su mix de ventas. Si cambias la carta allí, trae aquí el nuevo PVP medio: es COPIA declarada, no un vínculo entre ficheros.
A9: Ticket medio CON IVA (€) | B9: =IFERROR($B$7*$B$8,"") -> 10.752 | C9: Piezas por ticket x PVP medio ponderado. Es lo que ve el cliente en el datáfono.
A10: Ticket medio SIN IVA (€) | B10: =IFERROR($B$9/(1+$B$20),"") -> 9.7745455 | C10: Es el que entra en el P&L: la cuenta de resultados va siempre sin IVA. Se divide por el IVA MEDIO de la carta, no por un tipo suelto, para que el día que entre una referencia a otro tipo el libro siga cuadrando.
A11: Días de apertura al año | B11: 304 | C11: SUPUESTO: 6 días por semana x 52 semanas = 312, menos 8 días de cierre por festivos. En AGOSTO NO SE CIERRA: lo que para es el obrador, no la tienda, y el literal del kit lo dice («la tienda abre para el turista aunque el obrador pare»). Una bombonería de menos de 300 m² tiene libertad horaria por el art. 5.2 de la Ley de Horarios Comerciales, no por el 5.1.
A12: Actividad del año 1 sobre la de crucero (%) | B12: =IFERROR(SUMPRODUCT('Tesorería 12 meses'!B6:M6,'Tesorería 12 meses'!B7:M7),"") -> 0.88450094 | C12: NO se teclea: sale de la estacionalidad y de la rampa de la hoja de Tesorería. Un local que abre no factura desde el primer día lo que factura a los seis meses, y proyectar el año 1 a velocidad de crucero es el error que más planes de negocio tumba. Aquí además la apertura es el 1 de junio, así que la rampa cae justo sobre el valle de agosto.
A13: Crecimiento de volumen del año 3 (%) | B13: 0.04 | C13: SUPUESTO. El año 2 ya es el de crucero: el año 3 sólo crece lo que dé la clientela fija y la agenda corporativa que repite, no un salto de negocio. Un 4 % es prudente; si pones más, tendrás que decir de dónde sale.
A14: IVA Y TIPOS
A15: IVA del chocolate y la bombonería (%) | B15: 0.1 | C15: El 10 % sale POR EXCLUSIÓN, no porque un precepto nombre al chocolate: la lista del 4 % del art. 91.Dos.1.1.o es cerrada y tiene siete letras, el chocolate no está en ninguna, y tampoco está entre las dos exclusiones del 10 % (bebidas alcohólicas y refrescantes).
A16: IVA del chocolate a la taza SERVIDO en sala (%) | B16: 0.1 | C16: La taza servida en sala es una prestación de servicio de hostelería, no la entrega de un bien: va al 10 % por el art. 91.Uno.2.2.o. La tableta para taza que te llevas a casa es una entrega de bien, y va por la línea de arriba.
A17: IVA de los talleres y catas (%) | B17: Pregúntaselo a tu asesor | C17: VA SIN CIFRA A PROPÓSITO, y no es un olvido. Lo que SÍ está cerrado: un taller de bombonería NO está exento de IVA, porque el art. 20.Uno.10.o excluye de la exención las clases «para cuya realización sea necesario darse de alta en las tarifas de actividades empresariales o artísticas del IAE». Lo que NO está cerrado es el TIPO: el art. 91 no nombra los talleres. Esta guía no publica una cifra que no pueda sostener; escribe tú la que te diga tu asesor.
A18: IVA general (%) | B18: 0.21 | C18: Tipo general del art. 90.Uno de la Ley 37/1992. Es el que soportas en obra, maquinaria, moldes, packaging y servicios. Sin la columna de IVA por línea el CAPEX sale hasta un 21 % desviado, que es el error más caro de todo el proceso.
A19: IVA medio de las compras de materia prima (%) | B19: 0.1 | C19: SUPUESTO de trabajo: la cobertura y los frutos secos van al 10 % y el packaging al 21 %. Sólo afecta a la TESORERÍA (lo que adelantas al proveedor), nunca al resultado. Pídele a tu distribuidor una factura de ejemplo y afínalo.
A20: IVA medio ponderado de la carta (%) | B20: =IFERROR($B$15,"") -> 0.1 | C20: Hoy toda la carta va al 10 %, así que el IVA medio es ése. Esta celda existe para que el día que entres una referencia a otro tipo -una bebida, por ejemplo- no haya que tocar el libro entero: cambias aquí y el ticket sin IVA, la tesorería y el modelo 303 te siguen.
A21: COSTE DE VENTAS
A22: Food cost de escandallo de la carta (%) | B22: 0.252157 | C22: Coste de MATERIA sobre PVP, los dos en BASE IMPONIBLE, ponderado por los euros que vende cada referencia. Sale del libro «carta-de-apertura-y-escandallo-chocolate». Ojo con la base: el precio de la cobertura que publica la fuente lleva el IVA dentro, y un escandallo hecho con esa base sale un 9 % alto.
A23: Peso del packaging sobre el coste de la pieza (%) | B23: 0.12 | C23: SUPUESTO. En bombonería pesa más que en pastelería: la caja ES el producto en las campañas de regalo, y el 23 % de diferencia de precio por bombón entre la caja de 12 y la de 35 se juega ahí.
A24: Coste de ventas sobre las ventas (food cost del P&L, %) | B24: =IFERROR($B$22*(1+$B$23),"") -> 0.28241584 | C24: SE DERIVA: escandallo + packaging. Es el que proyecta el P&L, y es MAYOR que el de una pieza suelta a propósito. Si además revendes producto de terceros o tienes merma de producto fresco por encima de la que ya lleva el escandallo, súbelo tú.
A25: Food cost OBJETIVO de la casa (regla única, %) | B25: 0.3 | C25: SUPUESTO declarado: no existe dato público de food cost de bombonería. Es la regla única de la casa, y el margen bruto objetivo de la línea de abajo se DERIVA de él: guardar los dos por separado es un error de método, porque antes o después dicen cosas distintas.
A26: Margen bruto objetivo (%) | B26: =IFERROR(1-$B$25,"") -> 0.7 | C26: Se DERIVA del food cost objetivo. Margen bruto y food cost son la misma regla dicha dos veces.
A27: Brecha entre el food cost del P&L y el objetivo (puntos) | B27: =IFERROR($B$24-$B$25,"") -> -0.01758416 | C27: En NEGATIVO estás por debajo del objetivo, y esa diferencia es tu colchón. En positivo, tu carta no llega a la regla de la casa: o suben los precios, o baja el coste de la cobertura, o cambia el mix.
A28: PERSONAL
A29: Seguridad Social a cargo de la empresa (%) | B29: 0.33 | C29: Cotización empresarial aproximada sobre el salario bruto (contingencias comunes, desempleo, FOGASA y formación). Ajústala a tu convenio y a tus contratos.
A30: Número de pagas del convenio | B30: 15 | C30: El convenio de referencia paga 15, no 14, y eso cambia el coste mes a mes y el reparto de la tesorería. Busca el tuyo: NO existe convenio estatal del chocolate, está comprobado en el registro oficial.
A31: SMI vigente (€/año, 14 pagas) | B31: 17094 | C31: 1.221 €/mes × 14 pagas = 17.094 €/año — Real Decreto 126/2026, de 18 de febrero (BOE-A-2026-3815), con efectos desde el 1-ene-2026. El convenio provincial de hostelería prevalece si fija un mínimo superior.
A32: Jornada completa (horas/semana) | B32: 40 | C32: SUPUESTO: la jornada anual del convenio de referencia no se ha verificado. Comprueba la del tuyo antes de dimensionar turnos.
A33: LOCAL Y GASTOS FIJOS
A34: Alquiler mensual del local (€) | B34: 1300 | C34: SUPUESTO para una ciudad media. La renta observada en los ocho traspasos verificados va de 910 €/mes (74 m² en Madrid-Vallecas) a 2.200 €/mes (180 m² en Barcelona); aquí se toma la parte baja porque ninguna de esas dos ciudades es una ciudad media.
A35: Fianza del alquiler (meses de renta) | B35: 2 | C35: SUPUESTO. La fianza no es un gasto: es un depósito que se recupera. Está dentro del CAPEX del libro 2 porque hay que tenerla el día de la firma, y por eso no se amortiza.
A36: Suministros mensuales de luz, agua y climatización (€) | B36: 780 | C36: SUPUESTO. Un obrador de chocolate NO tiene hornos, pero tiene TRES equipos de frío y una climatización con deshumidificación funcionando 24 horas, y en agosto a pleno. No se estima: se le pide la simulación a la comercializadora con la potencia del proyecto eléctrico.
A37: Cuota de autónomos del titular (€/mes) | B37: 320 | C37: SUPUESTO, y va como renglón propio de los fijos. El titular de este caso es el Encargado, y su retribución YA está en la nómina de la hoja de Personal: ponerle además una «retribución del propietario» sería contarlo dos veces. Lo que va aparte es la cuota.
A38: Subida anual de los costes fijos (%) | B38: 0 | C38: A CERO: las tres columnas del P&L están en euros del año 1 (términos reales). Súbela si quieres proyectar en euros corrientes, pero entonces sube también el ticket medio o estarás proyectando una pérdida de margen que no has decidido.
A39: FINANCIACIÓN
A40: Recursos propios aportados (€) | B40: 78105.23 | C40: SUPUESTO sembrado para que el plan quede financiado: es la necesidad total de caja menos el préstamo. Míralo dos veces, porque es mucho dinero: si no lo tienes, o baja la inversión (mira la hoja «Traspaso vs Obra Nueva» del libro de CAPEX) o sube el préstamo, y entonces vigila el DSCR de la hoja de Financiación.
A41: Préstamo bancario solicitado (€) | B41: 90300 | C41: SUPUESTO: el 60 % de la inversión total, redondeado a centenas, que es la estructura 40/60 del caso. Las condiciones las pone tu banco y dependen de la garantía. Pide oferta a dos entidades y a una línea ICO antes de fijarlo.
A42: Tipo de interés nominal anual (%) | B42: 0.062 | C42: SUPUESTO.
A43: Plazo total del préstamo (meses) | B43: 84 | C43: SUPUESTO: 7 años, carencia incluida. El cuadro de amortización de la hoja de Financiación tiene 84 filas; si alargas el plazo por encima de 84 meses, tendrás que añadirlas.
A44: Carencia de principal (meses) | B44: 6 | C44: SUPUESTO, y es lo PRIMERO que hay que negociar: la carencia es lo que hace que el préstamo no se coma la caja justo en la rampa de arranque. Durante la carencia sólo se pagan intereses.
A45: Fondo de maniobra (meses de gastos fijos) | B45: 6 | C45: SUPUESTO, y ESTE ES EL ÚNICO SITIO DEL PACK DONDE SE DECIDE. Meses de gastos fijos que hay que tener en caja el día que abres. El libro de CAPEX no te lo vuelve a preguntar: recibe el fondo ya calculado desde aquí. Si se pidiera en los dos, el fondo se calcularía dos veces y los dos libros publicarían dos inversiones totales distintas.
A46: FISCAL
A47: Impuesto de Sociedades, entidad de nueva creación (%) | B47: 0.15 | C47: Art. 29.1 de la Ley del Impuesto sobre Sociedades: se aplica al PRIMER ejercicio con base imponible positiva y al siguiente, no a los dos primeros años naturales. Si eres autónomo y no sociedad, esta línea no te aplica: tributas en IRPF.
A48: Impuesto de Sociedades, tipo general (%) | B48: 0.25 | C48: A partir del tercer ejercicio con base positiva.
A49: Bases negativas de ejercicios anteriores (€) | B49: 0 | C49: Pérdidas pendientes de compensar al empezar. En una apertura son cero: se rellena si arrancas dentro de una sociedad que ya existía.
A50: AMORTIZACIÓN
A51: Años de amortización del inmovilizado | B51: 10 | C51: SUPUESTO, y en la práctica obra y maquinaria tienen coeficientes distintos. Sin amortización la rentabilidad publicada es mentira: la atemperadora se gasta.
A52: ARRANQUE
A53: Actividad del mes 1 sobre la de crucero (%) | B53: 0.55 | C53: SUPUESTO. Con el 100 % eliminas la rampa y el año 1 se proyecta como si abrieras a pleno rendimiento, que es justo lo que no pasa.
A54: Meses hasta alcanzar el régimen de crucero | B54: 6 | C54: SUPUESTO. La rampa sube en línea recta desde el porcentaje de arriba hasta el 100 % en este número de meses.
A55: Mes de apertura (1-12) | B55: 6 | C55: SUPUESTO: el 1 de junio. Junio es «Media» en el calendario de campañas del kit, deja SEIS meses de rodaje antes de Navidad y mete el valle de agosto dentro del arranque, que es cuando sale barato. Abrir dentro de una campaña «Alta» es el error que avisa el cronograma del libro de licencias.
A56: Días de apertura a la semana | B56: 6 | C56: SUPUESTO. Lo usa el cálculo de la fecha límite de Navidad para pasar de días de PRODUCCIÓN a días de calendario: si produces seis días de cada siete, cada día de obrador son 1,17 días naturales.
A57: COBROS Y PAGOS
A58: Días medios de cobro | B58: =IFERROR(SUMPRODUCT('Canales y Punto Muerto'!B6:B10,'Canales y Punto Muerto'!G6:G10),"") -> 7.65 | C58: NO se teclea: sale de la hoja «Canales y Punto Muerto», ponderando los días de cobro de cada canal por su peso en las ventas. El mostrador y el taller cobran al contado; el corporativo, a 30 días, y el B2B a 45: ahí financias tú.
A59: Días medios de pago a proveedor | B59: 30 | C59: SUPUESTO. Es lo que te financian tus proveedores, y lo primero que se pierde si te retrasas en un pago. Ojo en septiembre y octubre: es cuando se paga la cobertura de Navidad.
A60: Mes de la primera paga extra (1-12) | B60: 7 | C60: SUPUESTO. Con 15 pagas hay TRES meses en los que la nómina sale doble; escribe aquí en cuáles cae en tu convenio.
A61: Mes de la segunda paga extra (1-12) | B61: 12 | C61: SUPUESTO. Diciembre es el mes de más caja y de más nómina a la vez.
A62: Mes de la tercera paga extra (1-12) | B62: 3 | C62: SUPUESTO. Si tu convenio paga 14, pon aquí un número fuera de 1-12 (por ejemplo 0) y baja a 14 las pagas de arriba.
A63: UMBRALES Y SUELOS DE CONTROL
A64: DSCR mínimo aceptable | B64: 1 | C64: Por debajo de 1 el negocio no genera lo suficiente para pagar el préstamo. Pon el que te exija tu banco en el contrato.
A65: DSCR objetivo (verde) | B65: 1.25 | C65: Lo que suele pedir una entidad para dar el préstamo sin garantías adicionales.
A66: Holgura mínima sobre el punto de equilibrio (%) | B66: 0.15 | C66: Cuánto puedes caer sobre lo previsto antes de entrar en pérdidas. Con un negocio tan estacional como éste, la holgura no es un lujo: es lo que te deja llegar a octubre.
A67: Margen neto de referencia, suelo (%) | B67: 0.08 | C67: SUPUESTO DE CONTROL, no un dato del sector: NO existe rentabilidad publicada de bombonería artesana en España. Está aquí para que contrastes tu proyección, no para que la persigas.
A68: Margen neto de referencia, techo (%) | B68: 0.12 | C68: SUPUESTO DE CONTROL. Si tu proyección sale por encima, desconfía antes de enseñarla: casi siempre falta un coste.
A69: Techo de coste de personal sobre ventas (%) | B69: 0.35 | C69: SUPUESTO de control. En un obrador con tienda el personal es la primera partida; por encima de este techo, o subes precios o redimensionas turnos.
A70: Techo de alquiler sobre ventas (%) | B70: 0.1 | C70: SUPUESTO de control. Un alquiler por encima del 10 % de las ventas se come el margen de todo lo demás, y no se renegocia una vez firmado.
A71: Paso de la sensibilidad del coste variable (€) | B71: 0.2 | C71: Cuánto sube y baja el coste variable por ticket en la tabla de sensibilidad del punto de equilibrio. Con el cacao como está, la columna de la derecha no es un ejercicio teórico.
A72: Tolerancia de los cuadres entre libros (%) | B72: 0.02 | C72: Cuánto puede alejarse una cifra traída de otro libro antes de que su fila de CUADRE se ponga en rojo. Un 2 % tolera el redondeo; una máquina distinta, no.

Sheet Inversión Inicial
A1: Inversión Inicial: La Cifra que Viene y la que se Dota Aquí
A2: AI Chef Pro · aichef.pro — Cómo Montar una Chocolatería
A3: Esta hoja NO te vuelve a pedir las nueve partidas del CAPEX: eso lo hace el libro «calculadora-capex-chocolateria». Aquí entra UNA cifra suya -el CAPEX SIN el fondo de maniobra- y se DOTA el fondo de maniobra con tus meses de colchón y tus gastos fijos. El fondo se calcula una sola vez en todo el pack, y es aquí.
A5: LO QUE VIENE DEL LIBRO DE CAPEX (cruce 7 <- 2)
A6: CAPEX SIN el fondo de maniobra: trae aquí la cifra de calculadora-capex-chocolateria.xlsx!Resumen!B7 («CAPEX SIN el fondo de maniobra») | B6: 89219.35 | D6: CÓPIALA A MANO. No hay ninguna fórmula entre ficheros: un enlace se rompe en cuanto alguien mueve una carpeta, y entonces el libro miente sin avisar. Y OJO CON CUÁL COPIAS: NO es «el CAPEX total». El total de aquel libro lleva DENTRO el bloque «fondo de maniobra», y este libro vuelve a dotarlo tres filas más abajo: traer el total contaría el fondo dos veces y publicaría dos inversiones totales distintas para la misma bombonería. VALOR POR DEFECTO DECLARADO: el del caso «La Almendra».
A7: Cifra que publica hoy esa celda del libro de CAPEX | B7: 89219.35 | D7: Anota aquí lo que ves en el libro 2 la última vez que lo abriste. Si arriba tecleas otra cosa -porque has cerrado un presupuesto mejor, o porque el instalador te ha subido la climatización-, la fila de CUADRE te avisa en vez de dejar las dos cifras separadas en silencio.
A8: Desviación entre las dos | B8: =IFERROR(ABS(B6-B7)/B7,"") -> 0
A9: CUADRE DEL CAPEX: lo que usas frente a lo que publica el libro 2 | B9: =IFERROR(IF(NOT(ISNUMBER(B8)),"",IF(B8<='0. Supuestos'!$B$72,"CUADRA","REVISA: el CAPEX que estás usando no es el que publica el libro 2")),"") -> CUADRA | D9: Es la red de seguridad de todo el pack: dos libros que dicen cosas distintas sobre la misma inversión es el defecto que más caro sale y el que menos se nota.
A10: IVA soportado sobre la inversión, traído del libro 2 | B10: 17912.86 | D10: Copia de calculadora-capex-chocolateria.xlsx!CAPEX por Bloque!M40 («IVA soportado total»). Se recupera por el modelo 303, pero hay que ADELANTARLO: la hoja de Tesorería lo arrastra trimestre a trimestre, y esa espera es la partida que más sorprende al que abre.
A11: Inmovilizado amortizable, traído del libro 2 | B11: 83614.99 | D11: El CAPEX menos la FIANZA (que es un depósito y se recupera) y menos el primer pedido de packaging y moldes de consumo (que son existencias, no inmovilizado). De aquí sale la amortización anual que entra en los costes fijos.
A13: EL FONDO DE MANIOBRA SE DOTA AQUÍ (y viaja al libro 2 ya calculado: cruce 2 <- 7)
A14: Gastos fijos mensuales del año de crucero (€) | B14: =IFERROR('PyG 3 Años'!C31/12,"") -> 10212.169 | D14: El total de costes fijos del AÑO 2 del P&L dividido entre doce. Es la foto de un mes normal: por eso lleva dentro la amortización y los intereses del AÑO DE CRUCERO, no los del año 1, que es el de la carencia. Ésta es una de las dos celdas que cita el resto del pack.
A15: Meses de colchón (de «0. Supuestos») | B15: =IFERROR('0. Supuestos'!$B$45,"") -> 6 | D15: Se decide en «0. Supuestos», y sólo allí. El libro de CAPEX no lo pregunta.
A16: FONDO DE MANIOBRA (€) | B16: =IFERROR(B14*B15,"") -> 61273.016 | D16: Meses de colchón x gastos fijos mensuales. ES LA CIFRA QUE VIAJA AL LIBRO 2: cópiala allí en su celda verde del cruce, y su fila de CUADRE te dirá si las dos siguen diciendo lo mismo. No es inversión que se compra: es caja, y es lo que te deja llegar a octubre del primer año.
A18: LA INVERSIÓN, EN DOS LÍNEAS
A19: CAPEX (lo que se compra, sin el fondo de maniobra) | B19: =IFERROR(B6,"") -> 89219.35 | C19: =IFERROR(B19/B21,"") -> 0.59284967 | D19: Obra, climatización, equipo de templado, frío, mobiliario, packaging y moldes, TPV y rótulo, fianza y licencias.
A20: Del cual NO forma parte: el fondo de maniobra (es caja) | B20: =IFERROR(B16,"") -> 61273.016 | C20: =IFERROR(B20/B21,"") -> 0.40715033
A21: INVERSIÓN TOTAL (lo que se compra más la caja del arranque) | B21: =IFERROR(B19+B20,"") -> 150492.37 | D21: Esta cifra y la que publica el libro de CAPEX tienen que ser IDÉNTICAS, y lo son por construcción: aquel libro publica el CAPEX ya depurado de fondo y éste le devuelve el fondo ya calculado.
A22: IVA soportado sobre la inversión (recuperable, pero hay que ADELANTARLO) | B22: =IFERROR(B10,"") -> 17912.86
A23: NECESIDAD TOTAL DE CAJA AL ARRANQUE | B23: =IFERROR(B21+B22,"") -> 168405.23 | D23: Es la cifra que tiene que cubrir la hoja de Financiación. Si el origen de fondos no llega aquí, el plan no está financiado, y da igual lo bonito que sea el P&L.
A25: BASES DE AMORTIZACIÓN (no suman a la inversión)
A26: Inmovilizado amortizable | B26: =IFERROR(B11,"") -> 83614.99 | D26: El que has traído del libro 2. Ni la fianza ni el fondo de maniobra se amortizan: la primera se recupera y el segundo es caja.
A27: Amortización anual del inmovilizado | B27: =IFERROR(B26/MAX(1,'0. Supuestos'!$B$51),"") -> 8361.499 | D27: Es la línea que entra en los costes fijos del P&L. Sin ella la rentabilidad publicada es mentira: la atemperadora se gasta, y la cámara de chocolate también.
A29: Todas las cifras van en BASE SIN IVA. El IVA de la inversión se trae aparte, arriba, para que puedas ver cuánto dinero tienes que adelantar y cuánto vas a recuperar. Y una advertencia que vale dinero: la renta que pagues ANTES de abrir no está aquí. Si la vas a pagar, súmala en el libro de CAPEX a la línea de fianza y dilo en su nota, para que los dos libros sigan diciendo lo mismo.

Sheet PyG 3 Años
A1: Cuenta de Resultados a 3 Años
A2: AI Chef Pro · aichef.pro — Cómo Montar una Chocolatería
A3: El AÑO 2 es el año de crucero: es el que citan la guía y el business plan. El año 1 lleva la rampa de arranque -y el valle de agosto dentro- y el año 3 crece sobre el crucero. Amortización, intereses y la cuota de autónomos del titular van DENTRO de los costes fijos.
A5: Concepto | B5: Año 1 (arranque) | C5: Año 2 (crucero) | D5: Año 3 | E5: % s/ventas (año 2) | F5: Tipo de IVA de la línea | G5: Notas
A6: INGRESOS
A7: Clientes al día | B7: =IFERROR('0. Supuestos'!$B$6,"") -> 67 | C7: =IFERROR('0. Supuestos'!$B$6,"") -> 67 | D7: =IFERROR(C7*(1+'0. Supuestos'!$B$13),"") -> 69.68 | G7: Los años 1 y 2 comparten el tráfico de crucero; lo que separa al año 1 es la rampa de la fila de abajo, no menos clientes al día en el mes 12.
A8: Ticket medio sin IVA (€) | B8: =IFERROR('0. Supuestos'!$B$10,"") -> 9.7745455 | C8: =IFERROR('0. Supuestos'!$B$10,"") -> 9.7745455 | D8: =IFERROR('0. Supuestos'!$B$10,"") -> 9.7745455 | G8: Constante en euros del año 1: una subida de precios es una decisión aparte, y se toma en la carta, no aquí.
A9: Días de apertura al año | B9: =IFERROR('0. Supuestos'!$B$11,"") -> 304 | C9: =IFERROR('0. Supuestos'!$B$11,"") -> 304 | D9: =IFERROR('0. Supuestos'!$B$11,"") -> 304
A10: Actividad sobre la velocidad de crucero (%) | B10: =IFERROR('0. Supuestos'!$B$12,"") -> 0.88450094 | C10: 1 | D10: 1 | G10: El año 1 lo calcula «0. Supuestos» desde la rampa y la estacionalidad de la hoja de Tesorería. Los años 2 y 3 están al 100 % porque el año 2 es, por definición, el de crucero: si crees que vas a tardar más en llegar, bájalos.
A11: INGRESOS TOTALES (sin IVA) | B11: =IFERROR(IF(B7*B8*B9*B10=0,"",B7*B8*B9*B10),"") -> 176093.47 | C11: =IFERROR(IF(C7*C8*C9*C10=0,"",C7*C8*C9*C10),"") -> 199087.94 | D11: =IFERROR(IF(D7*D8*D9*D10=0,"",D7*D8*D9*D10),"") -> 207051.46 | E11: =IFERROR(C11/$C$11,"") -> 1 | F11: =IFERROR('0. Supuestos'!$B$20,"") -> 0.1 | G11: Clientes x ticket medio sin IVA x días x actividad. El reparto por canal está en la hoja «Canales y Punto Muerto»: aquí es UNA cifra, porque lo que cambia por canal es el MARGEN, no el precio.
A12: COSTES VARIABLES
A13: Coste de ventas (cobertura, rellenos, packaging y merma) | B13: =IFERROR(IF(B11="","",B11*'0. Supuestos'!$B$24),"") -> 49731.586 | C13: =IFERROR(IF(C11="","",C11*'0. Supuestos'!$B$24),"") -> 56225.588 | D13: =IFERROR(IF(D11="","",D11*'0. Supuestos'!$B$24),"") -> 58474.612 | E13: =IFERROR(C13/$C$11,"") -> 0.28241584 | F13: =IFERROR('0. Supuestos'!$B$19,"") -> 0.1 | G13: Al food cost DERIVADO de «0. Supuestos»: el de escandallo de la carta más el packaging. La materia prima que manda aquí es la cobertura, y su precio vive en el libro «sensibilidad-al-precio-del-cacao» EN BASE IMPONIBLE: si copias el precio con IVA, este renglón sale un 9 % alto.
A14: TOTAL COSTES VARIABLES | B14: =IFERROR(IF(B11="","",B13),"") -> 49731.586 | C14: =IFERROR(IF(C11="","",C13),"") -> 56225.588 | D14: =IFERROR(IF(D11="","",D13),"") -> 58474.612 | E14: =IFERROR(C14/$C$11,"") -> 0.28241584
A15: MARGEN BRUTO | B15: =IFERROR(IF(B11="","",B11-B14),"") -> 126361.89 | C15: =IFERROR(IF(C11="","",C11-C14),"") -> 142862.35 | D15: =IFERROR(IF(D11="","",D11-D14),"") -> 148576.85 | E15: =IFERROR(C15/$C$11,"") -> 0.71758416
A16: COSTES FIJOS
A17: Personal (nóminas y Seguridad Social) | B17: =IFERROR(IF(B11="","",'Personal'!$I$9),"") -> 68418.725 | C17: =IFERROR(IF(C11="","",'Personal'!$I$9),"") -> 68418.725 | D17: =IFERROR(IF(D11="","",'Personal'!$I$9),"") -> 68418.725 | E17: =IFERROR(C17/$C$11,"") -> 0.34366082 | F17: 0 | G17: Sale de la hoja de Personal: es el MISMO número, no una estimación aparte, y dentro va la retribución del titular, que es el Encargado. Las nóminas no llevan IVA. El refuerzo de campañas NO está aquí: se dimensiona en el libro «campanas-y-valle-del-ano».
A18: Cuota de autónomos del titular | B18: =IFERROR(IF(B11="","",'0. Supuestos'!$B$37*12),"") -> 3840 | C18: =IFERROR(IF(C11="","",B18*(1+'0. Supuestos'!$B$38)),"") -> 3840 | D18: =IFERROR(IF(D11="","",C18*(1+'0. Supuestos'!$B$38)),"") -> 3840 | E18: =IFERROR(C18/$C$11,"") -> 0.019287959 | F18: 0 | G18: RENGLÓN PROPIO, y es lo ÚNICO que va aparte del titular: su sueldo ya está en la nómina de arriba, porque el titular de este caso es el Encargado. Ponerle además una «retribución del propietario» sería contarlo dos veces.
A19: Alquiler del local | B19: =IFERROR(IF(B11="","",'0. Supuestos'!$B$34*12),"") -> 15600 | C19: =IFERROR(IF(C11="","",B19*(1+'0. Supuestos'!$B$38)),"") -> 15600 | D19: =IFERROR(IF(D11="","",C19*(1+'0. Supuestos'!$B$38)),"") -> 15600 | E19: =IFERROR(C19/$C$11,"") -> 0.078357332 | F19: =IFERROR('0. Supuestos'!$B$18,"") -> 0.21 | G19: El importe mensual está en «0. Supuestos»; aquí se multiplica por doce. El arrendamiento de local de negocio lleva IVA al tipo general.
A20: Suministros (luz, agua y climatización) | B20: =IFERROR(IF(B11="","",'0. Supuestos'!$B$36*12),"") -> 9360 | C20: =IFERROR(IF(C11="","",B20*(1+'0. Supuestos'!$B$38)),"") -> 9360 | D20: =IFERROR(IF(D11="","",C20*(1+'0. Supuestos'!$B$38)),"") -> 9360 | E20: =IFERROR(C20/$C$11,"") -> 0.047014399 | F20: =IFERROR('0. Supuestos'!$B$18,"") -> 0.21 | G20: Luz va al 21 % y el agua al 10 %. El libro aplica a toda la partida el tipo de la columna de al lado: si el agua te pesa, sepárala en su propia línea. Y ojo en agosto: la climatización con deshumidificación no para aunque pare el obrador.
A21: Seguros | B21: 1320 | C21: =IFERROR(IF(C11="","",B21*(1+'0. Supuestos'!$B$38)),"") -> 1320 | D21: =IFERROR(IF(D11="","",C21*(1+'0. Supuestos'!$B$38)),"") -> 1320 | E21: =IFERROR(C21/$C$11,"") -> 0.0066302358 | F21: 0 | G21: Responsabilidad civil y continente. `CHN-70` (seguro de RC) está en los EXCLUIDOS de la verificación legal: NO está verificado como obligatorio y depende de tu comunidad autónoma, así que aquí va como supuesto y sin cifra de norma detrás. Las operaciones de seguro están exentas de IVA, y por eso su tipo va a cero. Importe ANUAL: el mensual del caso, por doce.
A22: Gestoría y asesoría | B22: 2400 | C22: =IFERROR(IF(C11="","",B22*(1+'0. Supuestos'!$B$38)),"") -> 2400 | D22: =IFERROR(IF(D11="","",C22*(1+'0. Supuestos'!$B$38)),"") -> 2400 | E22: =IFERROR(C22/$C$11,"") -> 0.012054974 | F22: 0.21 | G22: Supuesto. Importe ANUAL: el mensual del caso, por doce.
A23: Software, TPV y pasarela de cobro | B23: 720 | C23: =IFERROR(IF(C11="","",B23*(1+'0. Supuestos'!$B$38)),"") -> 720 | D23: =IFERROR(IF(D11="","",C23*(1+'0. Supuestos'!$B$38)),"") -> 720 | E23: =IFERROR(C23/$C$11,"") -> 0.0036164923 | F23: 0.21 | G23: Supuesto. Con Verifactu en el horizonte (1 de enero de 2027 para sociedades y 1 de julio de 2027 para autónomos, no 2026) esta cuota deja de ser opcional. Importe ANUAL: el mensual del caso, por doce.
A24: Telefonía e internet | B24: 660 | C24: =IFERROR(IF(C11="","",B24*(1+'0. Supuestos'!$B$38)),"") -> 660 | D24: =IFERROR(IF(D11="","",C24*(1+'0. Supuestos'!$B$38)),"") -> 660 | E24: =IFERROR(C24/$C$11,"") -> 0.0033151179 | F24: 0.21 | G24: Supuesto. Importe ANUAL: el mensual del caso, por doce.
A25: Limpieza y consumibles | B25: 1680 | C25: =IFERROR(IF(C11="","",B25*(1+'0. Supuestos'!$B$38)),"") -> 1680 | D25: =IFERROR(IF(D11="","",C25*(1+'0. Supuestos'!$B$38)),"") -> 1680 | E25: =IFERROR(C25/$C$11,"") -> 0.0084384819 | F25: 0.21 | G25: Supuesto. Incluye guantes y utillaje dedicado: el equipo que has usado con un alérgeno no se reutiliza para otro alimento sin limpiarlo. Importe ANUAL: el mensual del caso, por doce.
A26: Mantenimiento de equipos | B26: 1560 | C26: =IFERROR(IF(C11="","",B26*(1+'0. Supuestos'!$B$38)),"") -> 1560 | D26: =IFERROR(IF(D11="","",C26*(1+'0. Supuestos'!$B$38)),"") -> 1560 | E26: =IFERROR(C26/$C$11,"") -> 0.0078357332 | F26: 0.21 | G26: Supuesto. Si montas la variante de taza y churros con freidora de gas, súmale la inspección periódica obligatoria cada cinco años, que se te repercute. Importe ANUAL: el mensual del caso, por doce.
A27: Publicidad y redes | B27: 2160 | C27: =IFERROR(IF(C11="","",B27*(1+'0. Supuestos'!$B$38)),"") -> 2160 | D27: =IFERROR(IF(D11="","",C27*(1+'0. Supuestos'!$B$38)),"") -> 2160 | E27: =IFERROR(C27/$C$11,"") -> 0.010849477 | F27: 0.21 | G27: Supuesto. Importe ANUAL: el mensual del caso, por doce.
A28: Otros gastos de estructura | B28: 1560 | C28: =IFERROR(IF(C11="","",B28*(1+'0. Supuestos'!$B$38)),"") -> 1560 | D28: =IFERROR(IF(D11="","",C28*(1+'0. Supuestos'!$B$38)),"") -> 1560 | E28: =IFERROR(C28/$C$11,"") -> 0.0078357332 | F28: 0.21 | G28: Supuesto. Importe ANUAL: el mensual del caso, por doce.
A29: Amortización del inmovilizado | B29: =IFERROR(IF(B11="","",'Inversión Inicial'!$B$27),"") -> 8361.499 | C29: =IFERROR(IF(C11="","",'Inversión Inicial'!$B$27),"") -> 8361.499 | D29: =IFERROR(IF(D11="","",'Inversión Inicial'!$B$27),"") -> 8361.499 | E29: =IFERROR(C29/$C$11,"") -> 0.041999023 | F29: 0 | G29: Sale de la base de amortización de la hoja de Inversión. No sube con el IPC: es un reparto contable de una inversión ya hecha.
A30: Gastos financieros del préstamo | B30: =IFERROR(IF(B11="","",'Financiación'!$B$116),"") -> 5525.0128 | C30: =IFERROR(IF(C11="","",'Financiación'!$B$117),"") -> 4905.8078 | D30: =IFERROR(IF(D11="","",'Financiación'!$B$118),"") -> 4139.7431 | E30: =IFERROR(C30/$C$11,"") -> 0.024641411 | F30: 0 | G30: Sólo los INTERESES son gasto. La devolución del principal sale de la caja pero no del resultado: va en la hoja de Tesorería. Los que usa el fondo de maniobra son los del AÑO 2, no los del año 1, que es el de la carencia.
A31: TOTAL COSTES FIJOS | B31: =IFERROR(IF(B11="","",SUM(B17:B30)),"") -> 123165.24 | C31: =IFERROR(IF(C11="","",SUM(C17:C30)),"") -> 122546.03 | D31: =IFERROR(IF(D11="","",SUM(D17:D30)),"") -> 121779.97 | E31: =IFERROR(C31/$C$11,"") -> 0.61553719 | G31: De esta celda, columna del año 2 y dividida entre doce, sale el fondo de maniobra de todo el pack.
A32: IVA soportado de los costes variables | B32: =IFERROR(IF(B11="","",B13*$F$13),"") -> 4973.1586 | C32: =IFERROR(IF(C11="","",C13*$F$13),"") -> 5622.5588 | D32: =IFERROR(IF(D11="","",D13*$F$13),"") -> 5847.4612
A33: IVA soportado de los costes fijos | B33: =IFERROR(IF(B11="","",SUMPRODUCT(B17:B30,$F$17:$F$30)),"") -> 7497 | C33: =IFERROR(IF(C11="","",SUMPRODUCT(C17:C30,$F$17:$F$30)),"") -> 7497 | D33: =IFERROR(IF(D11="","",SUMPRODUCT(D17:D30,$F$17:$F$30)),"") -> 7497 | G33: Cada línea a SU tipo, leído de la columna de al lado. Es lo que la hoja de Tesorería paga de más a los proveedores y luego recupera en el modelo 303.
A34: RESULTADO ANTES DE IMPUESTOS | B34: =IFERROR(IF(B11="","",B15-B31),"") -> 3196.6497 | C34: =IFERROR(IF(C11="","",C15-C31),"") -> 20316.322 | D34: =IFERROR(IF(D11="","",D15-D31),"") -> 26796.881 | E34: =IFERROR(C34/$C$11,"") -> 0.10204697
A35: Bases negativas pendientes al inicio | B35: =IFERROR(IF(B11="","",'0. Supuestos'!$B$49),"") -> 0 | C35: =IFERROR(IF(C11="","",B40),"") -> 0 | D35: =IFERROR(IF(D11="","",C40),"") -> 0 | G35: Art. 26 de la Ley del Impuesto sobre Sociedades: las pérdidas de un ejercicio se compensan con los beneficios de los siguientes.
A36: Base imponible (después de compensar) | B36: =IFERROR(IF(B11="","",MAX(0,B34-B35)),"") -> 3196.6497 | C36: =IFERROR(IF(C11="","",MAX(0,C34-C35)),"") -> 20316.322 | D36: =IFERROR(IF(D11="","",MAX(0,D34-D35)),"") -> 26796.881
A37: Ejercicios con base positiva (acumulado) | B37: =IFERROR(IF(B11="","",IF(B36>0,1,0)),"") -> 1 | C37: =IFERROR(IF(C11="","",B37+IF(C36>0,1,0)),"") -> 2 | D37: =IFERROR(IF(D11="","",C37+IF(D36>0,1,0)),"") -> 3
A38: Tipo de Impuesto de Sociedades aplicado | B38: =IFERROR(IF(B11="","",IF(B36<=0,"",IF(B37<=2,'0. Supuestos'!$B$47,'0. Supuestos'!$B$48))),"") -> 0.15 | C38: =IFERROR(IF(C11="","",IF(C36<=0,"",IF(C37<=2,'0. Supuestos'!$B$47,'0. Supuestos'!$B$48))),"") -> 0.15 | D38: =IFERROR(IF(D11="","",IF(D36<=0,"",IF(D37<=2,'0. Supuestos'!$B$47,'0. Supuestos'!$B$48))),"") -> 0.25 | G38: El 15 % de entidad de nueva creación se aplica al PRIMER ejercicio con base positiva y al siguiente, no a los dos primeros años naturales. Si tributas en IRPF, esta línea no te aplica.
A39: Impuesto de Sociedades | B39: =IFERROR(IF(B11="","",IF(B38="",0,B36*B38)),"") -> 479.49746 | C39: =IFERROR(IF(C11="","",IF(C38="",0,C36*C38)),"") -> 3047.4483 | D39: =IFERROR(IF(D11="","",IF(D38="",0,D36*D38)),"") -> 6699.2203
A40: Bases negativas pendientes al cierre | B40: =IFERROR(IF(B11="","",MAX(0,B35-B34)),"") -> 0 | C40: =IFERROR(IF(C11="","",MAX(0,C35-C34)),"") -> 0 | D40: =IFERROR(IF(D11="","",MAX(0,D35-D34)),"") -> 0
A41: RESULTADO NETO | B41: =IFERROR(IF(B11="","",B34-B39),"") -> 2717.1522 | C41: =IFERROR(IF(C11="","",C34-C39),"") -> 17268.874 | D41: =IFERROR(IF(D11="","",D34-D39),"") -> 20097.661 | E41: =IFERROR(C41/$C$11,"") -> 0.086739929
A42: RATIOS CLAVE
A43: Ratio | B43: Año 1 | C43: Año 2 | D43: Año 3 | E43: Umbral | G43: Comentario
A44: Margen bruto / ventas | B44: =IFERROR(IF(B11="","",B15/B11),"") -> 0.71758416 | C44: =IFERROR(IF(C11="","",C15/C11),"") -> 0.71758416 | D44: =IFERROR(IF(D11="","",D15/D11),"") -> 0.71758416 | E44: =IFERROR('0. Supuestos'!$B$26,"") -> 0.7 | G44: El suelo es la regla única de margen del propio libro. Por debajo, o suben los precios o baja el coste de la cobertura.
A45: Coste de ventas / ventas | B45: =IFERROR(IF(B11="","",B13/B11),"") -> 0.28241584 | C45: =IFERROR(IF(C11="","",C13/C11),"") -> 0.28241584 | D45: =IFERROR(IF(D11="","",D13/D11),"") -> 0.28241584 | E45: =IFERROR('0. Supuestos'!$B$25,"") -> 0.3 | G45: Es el food cost proyectado. Cuando midas el tuyo de verdad, con tres meses de compras y de ventas, cámbialo en «0. Supuestos» y mira qué le pasa a este cuadro.
A46: Coste de personal / ventas | B46: =IFERROR(IF(B11="","",B17/B11),"") -> 0.38853641 | C46: =IFERROR(IF(C11="","",C17/C11),"") -> 0.34366082 | D46: =IFERROR(IF(D11="","",D17/D11),"") -> 0.33044309 | E46: =IFERROR('0. Supuestos'!$B$69,"") -> 0.35 | G46: En un obrador con tienda el personal es la primera partida. Por encima del techo, o subes precios o redimensionas turnos.
A47: Alquiler / ventas | B47: =IFERROR(IF(B11="","",B19/B11),"") -> 0.088589315 | C47: =IFERROR(IF(C11="","",C19/C11),"") -> 0.078357332 | D47: =IFERROR(IF(D11="","",D19/D11),"") -> 0.075343589 | E47: =IFERROR('0. Supuestos'!$B$70,"") -> 0.1 | G47: Un alquiler por encima del techo se come el margen de todo lo demás, y no se renegocia una vez firmado.
A48: Resultado neto / ventas | B48: =IFERROR(IF(B11="","",B41/B11),"") -> 0.01543017 | C48: =IFERROR(IF(C11="","",C41/C11),"") -> 0.086739929 | D48: =IFERROR(IF(D11="","",D41/D11),"") -> 0.097066019 | E48: =IFERROR('0. Supuestos'!$B$67,"") -> 0.08 | G48: El suelo es un SUPUESTO de control, no un dato del sector: no existe rentabilidad publicada de bombonería artesana española.
A49: Margen neto dentro de la banda de referencia | B49: =IFERROR(IF(B48="","",IF(AND(B48>='0. Supuestos'!$B$67,B48<='0. Supuestos'!$B$68),"Sí","No: revísalo")),"") -> No: revísalo | C49: =IFERROR(IF(C48="","",IF(AND(C48>='0. Supuestos'!$B$67,C48<='0. Supuestos'!$B$68),"Sí","No: revísalo")),"") -> Sí | D49: =IFERROR(IF(D48="","",IF(AND(D48>='0. Supuestos'!$B$67,D48<='0. Supuestos'!$B$68),"Sí","No: revísalo")),"") -> Sí | G49: Si sale por ENCIMA del techo, desconfía antes de enseñarlo: casi siempre falta un coste. Si sale por debajo del suelo, el negocio no está mal planteado por fuerza, pero tiene poco donde caerse.
A50: Punto de equilibrio alcanzado | B50: =IFERROR(IF(B11="","",IF(B11>='Punto de Equilibrio'!$B$17,"Sí","No")),"") -> Sí | C50: =IFERROR(IF(C11="","",IF(C11>='Punto de Equilibrio'!$C$17,"Sí","No")),"") -> Sí | D50: =IFERROR(IF(D11="","",IF(D11>='Punto de Equilibrio'!$D$17,"Sí","No")),"") -> Sí | G50: Compara las ventas de CADA año con el umbral contable de ese mismo año, que calcula la hoja «Punto de Equilibrio». El umbral de caja, que es el que de verdad te deja dormir, está allí.
A52: ESCENARIO DE FORMATO: BOMBONERÍA FRENTE A BOMBONERÍA CON TAZA Y CHURROS (año de crucero)
A53: Concepto (año 2) | B53: Bombonería | C53: Bombonería + taza y churros | G53: Notas
A54: Clientes al día que añade el servicio de taza y churros | C54: 35 | G54: SUPUESTO. Es OTRO negocio, con otro horario y otro público: no son los mismos clientes comprando más, son clientes nuevos a otra hora.
A55: PVP con IVA de la ración con chocolate, mínimo publicado (€) | C55: 3.5 | G55: Dato de mercado: el chocolate convierte una ración de churros de 2,50 € en 3,50-4 €, entre un 40 y un 60 % más de ticket. Se publica el RANGO, y el libro usa el mínimo.
A56: PVP con IVA de la ración con chocolate, máximo publicado (€) | C56: 4 | G56: El techo del mismo rango. Si tu carta está por encima, dilo aquí y mira cómo se mueve la columna de la derecha.
A57: PVP con IVA que usa el escenario (el mínimo: criterio conservador) | C57: =IFERROR(C55,"") -> 3.5 | G57: Se usa el mínimo del rango a propósito: un escenario que se defiende con el techo del rango no es un escenario, es un deseo.
A58: Margen bruto de la línea de taza y churros (%) | C58: 0.5 | G58: SE PUBLICAN LAS DOS CIFRAS QUE HAY, no la más bonita: el margen bruto del churro se cita entre el 85 y el 90 %, y un maestro churrero lo rebaja a «un poco más del 50 %». El libro usa el 50 % porque es el que aguanta una discusión con el banco.
A59: Coste de personal adicional al año (€) | C59: 12462.96 | G59: SUPUESTO: media jornada más del grupo de convenio del Dependiente, con la Seguridad Social a cargo de la empresa dentro. La taza se sirve, y servir es mano de obra: sin esta línea el escenario sale redondo y es mentira.
A60: Otros costes fijos adicionales al año (€) | C60: 1200 | G60: SUPUESTO: mantenimiento de freidora y extracción, y la inspección periódica de la instalación de gas cada cinco años, repercutida. Y una que no es un euro pero cuesta tiempo: la bombonería se libra de la licencia previa de actividad hasta 750 m² y la chocolatería de taza NO, porque su grupo de IAE no está en el Anexo de esa ley.
A61: Ventas del año sin IVA (€) | B61: =IFERROR(C11,"") -> 199087.94 | C61: =IFERROR(B61+C54*C57/(1+'0. Supuestos'!$B$16)*C9,"") -> 232942.49 | G61: La taza servida en sala va al 10 % por ser prestación de servicio de hostelería, no entrega de un bien: por eso el PVP se pasa a base imponible con ESE tipo.
A62: Costes variables (€) | B62: =IFERROR(C14,"") -> 56225.588 | C62: =IFERROR(B62+(C61-B61)*(1-C58),"") -> 73152.861
A63: Margen bruto (€) | B63: =IFERROR(B61-B62,"") -> 142862.35 | C63: =IFERROR(C61-C62,"") -> 159789.63
A64: Costes fijos (€) | B64: =IFERROR(C31,"") -> 122546.03 | C64: =IFERROR(B64+C59+C60,"") -> 136208.99
A65: Resultado antes de impuestos (€) | B65: =IFERROR(B63-B64,"") -> 20316.322 | C65: =IFERROR(C63-C64,"") -> 23580.635
A66: Resultado neto (€) | B66: =IFERROR(B65-MAX(0,B65)*'0. Supuestos'!$B$47,"") -> 17268.874 | C66: =IFERROR(C65-MAX(0,C65)*'0. Supuestos'!$B$47,"") -> 20043.54
A67: Margen neto (%) | B67: =IFERROR(B66/B61,"") -> 0.086739929 | C67: =IFERROR(C66/C61,"") -> 0.086045014
A68: VEREDICTO DEL FORMATO | B68: =IFERROR(IF(OR(B67="",C67=""),"",IF(C67>B67,"La taza y los churros suman: aporta más margen del que se come en fijos","La taza y los churros restan: con estos supuestos te ocupan sala y personal para nada")),"") -> La taza y los churros restan: con estos supuestos te ocupan sala y personal para nada | G68: Son DOS NEGOCIOS, y la norma los separa sola: el Anexo de la Ley 12/2012 incluye el epígrafe 644.5 de bombones y caramelos y no contiene ningún grupo de la agrupación 67, donde está la chocolatería de taza. Antes de mirar el margen, mira eso: la bombonería se libra de la licencia previa de actividad hasta 750 m² y la taza no.
A70: DE DÓNDE SALE EL COSTE DE VENTAS: EL PRECIO DE LA COBERTURA (cruce 7 <- 3)
A71: Precio de la cobertura negra EN BASE IMPONIBLE: trae aquí la cifra de sensibilidad-al-precio-del-cacao.xlsx!Coste de Cobertura!G7 («precio de la cobertura negra EN BASE IMPONIBLE») | B71: 22.7455 | C71: €/kg | G71: CÓPIALA A MANO, y cópiala BIEN: es la celda más crítica de todo el pack. La fuente publica 25,02 €/kg CON EL IVA DENTRO, y un escandallo se calcula con precios SIN IVA porque el soportado es deducible. Con la base equivocada el food cost sale un 9 % alto y este P&L entero está mal. Por eso lo que se copia es la celda de BASE IMPONIBLE, nunca la de la fuente.
A72: Cifra que publica hoy esa celda del libro 3 | B72: 22.7455 | G72: Anota aquí lo que ves en el libro «sensibilidad-al-precio-del-cacao» la última vez que lo abriste. Si arriba tecleas otra cosa -porque te han pasado tarifa nueva-, la fila de CUADRE te avisa.
A73: Desviación entre las dos | B73: =IFERROR(ABS(B71-B72)/B72,"") -> 0
A74: CUADRE DE LA COBERTURA: el precio que usas frente al del libro 3 | B74: =IFERROR(IF(NOT(ISNUMBER(B73)),"",IF(B73<='0. Supuestos'!$B$72,"CUADRA","REVISA: el precio de cobertura que usas no es el del libro 3")),"") -> CUADRA
A75: Kilos de cobertura negra que se van al año | B75: 462.1 | C75: kg/año | G75: También del libro 3, que los calcula referencia a referencia. Es la cobertura MÁS USADA de la carta, no toda la que compras.
A76: Coste anual de esa cobertura (€) | B76: =IFERROR(B71*B75,"") -> 10510.696
A77: Peso sobre el coste de ventas del año de crucero (%) | B77: =IFERROR(IF(C13="","",B76/C13),"") -> 0.18693794
A78: Subida del precio del cacao que quieres simular (%) | B78: 0.4 | G78: El 40 % no es un número de miedo: es uno de los escenarios que trabaja el libro «sensibilidad-al-precio-del-cacao», y allí está referencia a referencia. Aquí sólo se mira lo que le hace a la cuenta de resultados entera.
A79: Lo que te costaría esa subida al año (€) | B79: =IFERROR(B76*B78,"") -> 4204.2782
A80: Margen neto del año de crucero DESPUÉS de esa subida (%) | B80: =IFERROR(IF(C11="","",(C41-B79)/C11),"") -> 0.065622235 | G80: Es la pregunta que hay que saber responder antes de firmar un alquiler: si el cacao sube lo que ya ha subido otras veces, ¿el negocio sigue en pie? Si esta celda se pone en rojo, tu plan depende del precio del cacao más de lo que crees, y la respuesta no es esperar: es gramaje, mix o precio.
A82: Todas las cifras van SIN IVA. Las columnas de los años 2 y 3 están en euros del año 1 mientras la «Subida anual de los costes fijos» de «0. Supuestos» valga cero. Y una advertencia que vale dinero: si tu proyección del año 1 sale en positivo, míralo dos veces. Casi ninguna apertura gana dinero el primer año, y lo que decide si sobrevives no es este cuadro sino la hoja de Tesorería.

Sheet Punto de Equilibrio
A1: Punto de Equilibrio: Cuántos Clientes al Día
A2: AI Chef Pro · aichef.pro — Cómo Montar una Chocolatería
A3: Dos umbrales, y no dicen lo mismo. El CONTABLE incluye la amortización; el de CAJA le quita la amortización (que no se paga) y le suma la devolución de principal (que sí). El segundo es el que decide si llegas a fin de mes.
A5: Variable | B5: Año 1 | C5: Año 2 | D5: Año 3 | E5: Notas
A6: DATOS BASE POR AÑO
A7: Costes fijos anuales | B7: =IFERROR(IF('PyG 3 Años'!B11="","",'PyG 3 Años'!B31),"") -> 123165.24 | C7: =IFERROR(IF('PyG 3 Años'!C11="","",'PyG 3 Años'!C31),"") -> 122546.03 | D7: =IFERROR(IF('PyG 3 Años'!D11="","",'PyG 3 Años'!D31),"") -> 121779.97 | E7: Los MISMOS costes fijos del P&L. Cada año tiene los suyos: por eso el umbral no puede ser uno solo para los tres.
A8: Costes fijos mensuales | B8: =IFERROR(IF('PyG 3 Años'!B11="","",B7/12),"") -> 10263.77 | C8: =IFERROR(IF('PyG 3 Años'!C11="","",C7/12),"") -> 10212.169 | D8: =IFERROR(IF('PyG 3 Años'!D11="","",D7/12),"") -> 10148.331
A9: Ticket medio sin IVA (€) | B9: =IFERROR(IF('PyG 3 Años'!B11="","",'PyG 3 Años'!B8),"") -> 9.7745455 | C9: =IFERROR(IF('PyG 3 Años'!C11="","",'PyG 3 Años'!C8),"") -> 9.7745455 | D9: =IFERROR(IF('PyG 3 Años'!D11="","",'PyG 3 Años'!D8),"") -> 9.7745455
A10: Coste variable por ticket (€) | B10: =IFERROR(IF('PyG 3 Años'!B11="","",'PyG 3 Años'!B14/('PyG 3 Años'!B7*'PyG 3 Años'!B9*'PyG 3 Años'!B10)),"") -> 2.7604865 | C10: =IFERROR(IF('PyG 3 Años'!C11="","",'PyG 3 Años'!C14/('PyG 3 Años'!C7*'PyG 3 Años'!C9*'PyG 3 Años'!C10)),"") -> 2.7604865 | D10: =IFERROR(IF('PyG 3 Años'!D11="","",'PyG 3 Años'!D14/('PyG 3 Años'!D7*'PyG 3 Años'!D9*'PyG 3 Años'!D10)),"") -> 2.7604865 | E10: Sale del total de costes variables del P&L dividido por los clientes de ese año, no de una estimación aparte.
A11: Margen de contribución por ticket (€) | B11: =IFERROR(IF('PyG 3 Años'!B11="","",B9-B10),"") -> 7.014059 | C11: =IFERROR(IF('PyG 3 Años'!C11="","",C9-C10),"") -> 7.014059 | D11: =IFERROR(IF('PyG 3 Años'!D11="","",D9-D10),"") -> 7.014059 | E11: Ticket menos coste variable unitario. Es lo que deja cada cliente para pagar los fijos. En bombonería es alto y los fijos también: las dos cosas van juntas.
A12: Días de apertura al año | B12: =IFERROR(IF('PyG 3 Años'!B11="","",'PyG 3 Años'!B9),"") -> 304 | C12: =IFERROR(IF('PyG 3 Años'!C11="","",'PyG 3 Años'!C9),"") -> 304 | D12: =IFERROR(IF('PyG 3 Años'!D11="","",'PyG 3 Años'!D9),"") -> 304
A13: Devolución de principal del año (sale de caja) | B13: =IFERROR(IF('PyG 3 Años'!B11="","",'Financiación'!$C$116),"") -> 5731.5362 | C13: =IFERROR(IF('PyG 3 Años'!C11="","",'Financiación'!$C$117),"") -> 12008.69 | D13: =IFERROR(IF('PyG 3 Años'!D11="","",'Financiación'!$C$118),"") -> 12774.755 | E13: El principal NO es gasto del P&L, pero sale de la caja. Sin él, el umbral de equilibrio se publica por debajo de lo que de verdad hay que facturar.
A14: PUNTO DE EQUILIBRIO CONTABLE (incluye la amortización)
A15: Clientes necesarios al año | B15: =IFERROR(IF('PyG 3 Años'!B11="","",IF(B11<=0,"",B7/B11)),"") -> 17559.766 | C15: =IFERROR(IF('PyG 3 Años'!C11="","",IF(C11<=0,"",C7/C11)),"") -> 17471.486 | D15: =IFERROR(IF('PyG 3 Años'!D11="","",IF(D11<=0,"",D7/D11)),"") -> 17362.267
A16: Clientes necesarios al día | B16: =IFERROR(IF('PyG 3 Años'!B11="","",B15/B12),"") -> 57.762389 | C16: =IFERROR(IF('PyG 3 Años'!C11="","",C15/C12),"") -> 57.471992 | D16: =IFERROR(IF('PyG 3 Años'!D11="","",D15/D12),"") -> 57.112721
A17: Ingresos necesarios al año (sin IVA) | B17: =IFERROR(IF('PyG 3 Años'!B11="","",B15*B9),"") -> 171638.73 | C17: =IFERROR(IF('PyG 3 Años'!C11="","",C15*C9),"") -> 170775.83 | D17: =IFERROR(IF('PyG 3 Años'!D11="","",D15*D9),"") -> 169708.27
A18: Ingresos necesarios al mes (sin IVA) | B18: =IFERROR(IF('PyG 3 Años'!B11="","",B17/12),"") -> 14303.228 | C18: =IFERROR(IF('PyG 3 Años'!C11="","",C17/12),"") -> 14231.319 | D18: =IFERROR(IF('PyG 3 Años'!D11="","",D17/12),"") -> 14142.356
A19: PUNTO DE EQUILIBRIO DE CAJA (incluye la cuota del préstamo)
A20: Costes fijos de caja más el principal del año | B20: =IFERROR(IF('PyG 3 Años'!B11="","",B7-'PyG 3 Años'!B29+B13),"") -> 120535.27 | C20: =IFERROR(IF('PyG 3 Años'!C11="","",C7-'PyG 3 Años'!C29+C13),"") -> 126193.22 | D20: =IFERROR(IF('PyG 3 Años'!D11="","",D7-'PyG 3 Años'!D29+D13),"") -> 126193.22 | E20: Los fijos del P&L sin la amortización (que no se paga) y CON la devolución de principal (que sí). Es el umbral que decide si sobrevives, no el contable.
A21: Clientes necesarios al año (caja) | B21: =IFERROR(IF('PyG 3 Años'!B11="","",IF(B11<=0,"",B20/B11)),"") -> 17184.81 | C21: =IFERROR(IF('PyG 3 Años'!C11="","",IF(C11<=0,"",C20/C11)),"") -> 17991.469 | D21: =IFERROR(IF('PyG 3 Años'!D11="","",IF(D11<=0,"",D20/D11)),"") -> 17991.469
A22: Clientes necesarios al día (caja) | B22: =IFERROR(IF('PyG 3 Años'!B11="","",B21/B12),"") -> 56.528981 | C22: =IFERROR(IF('PyG 3 Años'!C11="","",C21/C12),"") -> 59.182463 | D22: =IFERROR(IF('PyG 3 Años'!D11="","",D21/D12),"") -> 59.182463
A23: Ingresos necesarios al año (caja, sin IVA) | B23: =IFERROR(IF('PyG 3 Años'!B11="","",B21*B9),"") -> 167973.71 | C23: =IFERROR(IF('PyG 3 Años'!C11="","",C21*C9),"") -> 175858.43 | D23: =IFERROR(IF('PyG 3 Años'!D11="","",D21*D9),"") -> 175858.43
A24: CONTRASTE CON EL PLAN
A25: Clientes al día previstos en el plan | B25: =IFERROR(IF('PyG 3 Años'!B11="","",'PyG 3 Años'!B7*'PyG 3 Años'!B10),"") -> 59.261563 | C25: =IFERROR(IF('PyG 3 Años'!C11="","",'PyG 3 Años'!C7*'PyG 3 Años'!C10),"") -> 67 | D25: =IFERROR(IF('PyG 3 Años'!D11="","",'PyG 3 Años'!D7*'PyG 3 Años'!D10),"") -> 69.68
A26: Holgura sobre el equilibrio de CAJA (%) | B26: =IFERROR(IF('PyG 3 Años'!B11="","",IF(B22<=0,"",B25/B22-1)),"") -> 0.048339481 | C26: =IFERROR(IF('PyG 3 Años'!C11="","",IF(C22<=0,"",C25/C22-1)),"") -> 0.13209213 | D26: =IFERROR(IF('PyG 3 Años'!D11="","",IF(D22<=0,"",D25/D22-1)),"") -> 0.17737581 | E26: Cuánto puedes caer sobre lo previsto antes de no poder pagar los fijos y la cuota. El mínimo exigible está en «0. Supuestos».
A27: Lectura de la holgura | B27: =IFERROR(IF('PyG 3 Años'!B11="","",IF(B26<0,"Por debajo del equilibrio",IF(B26<'0. Supuestos'!$B$66,"Ajustada","Suficiente"))),"") -> Ajustada | C27: =IFERROR(IF('PyG 3 Años'!C11="","",IF(C26<0,"Por debajo del equilibrio",IF(C26<'0. Supuestos'!$B$66,"Ajustada","Suficiente"))),"") -> Ajustada | D27: =IFERROR(IF('PyG 3 Años'!D11="","",IF(D26<0,"Por debajo del equilibrio",IF(D26<'0. Supuestos'!$B$66,"Ajustada","Suficiente"))),"") -> Suficiente
A28: Lectura rápida: si los clientes al día previstos están por debajo de los clientes al día de CAJA, el negocio no genera para pagar los fijos y la cuota, y da igual lo que diga el resultado contable. Si están justo por encima, no tienes margen para un mes malo -y aquí los meses malos están en el calendario, no en la mala suerte-: negocia carencia, baja inversión o revisa el ticket medio antes de firmar nada.
A30: EL PUNTO MUERTO, POR FORMATO (año de crucero)
A31: Concepto | B31: Bombonería | C31: Bombonería + taza y churros | E31: Notas
A32: Costes fijos mensuales (€) | B32: =IFERROR('PyG 3 Años'!B64/12,"") -> 10212.169 | C32: =IFERROR('PyG 3 Años'!C64/12,"") -> 11350.749
A33: Margen de contribución sobre ventas (%) | B33: =IFERROR('PyG 3 Años'!B63/'PyG 3 Años'!B61,"") -> 0.71758416 | C33: =IFERROR('PyG 3 Años'!C63/'PyG 3 Años'!C61,"") -> 0.68596171
A34: PUNTO MUERTO MENSUAL (€ sin IVA) | B34: =IFERROR(IF(B33<=0,"",B32/B33),"") -> 14231.319 | C34: =IFERROR(IF(C33<=0,"",C32/C33),"") -> 16547.205 | E34: El formato con taza y churros factura más, pero también arrastra más fijos y un margen bruto mucho peor en esa línea. Lo que decide no es cuál factura más: es cuál necesita menos para no perder dinero.
A35: Punto muerto por día de apertura (€) | B35: =IFERROR(B34*12/'0. Supuestos'!$B$11,"") -> 561.7626 | C35: =IFERROR(C34*12/'0. Supuestos'!$B$11,"") -> 653.17916
A36: Los dos formatos comparten obrador, alquiler y titular; lo que cambia es la sala, el personal de servicio y la licencia. Si el punto muerto de la derecha sale MÁS ALTO, la taza y los churros te están obligando a facturar más para estar igual: puede seguir mereciendo la pena por tráfico y por horario, pero eso ya es una decisión tuya y no un resultado del libro.
A38: SENSIBILIDAD DEL PUNTO DE EQUILIBRIO (año de crucero)
A39: Clientes al día necesarios: ticket medio (columnas) x coste variable por ticket (filas) | B39: =IFERROR($C$9-1,"") -> 8.7745455 | C39: =IFERROR($C$9,"") -> 9.7745455 | D39: =IFERROR($C$9+1,"") -> 10.774545 | E39: =IFERROR($C$9+2,"") -> 11.774545
A40: =IFERROR($C$10-2*'0. Supuestos'!$B$71,"") -> 2.3604865 | B40: =IFERROR(IF(B$39-$A40<=0,"",$C$7/(B$39-$A40)/$C$12),"") -> 62.848182 | C40: =IFERROR(IF(C$39-$A40<=0,"",$C$7/(C$39-$A40)/$C$12),"") -> 54.371289 | D40: =IFERROR(IF(D$39-$A40<=0,"",$C$7/(D$39-$A40)/$C$12),"") -> 47.909332 | E40: =IFERROR(IF(E$39-$A40<=0,"",$C$7/(E$39-$A40)/$C$12),"") -> 42.820206
A41: =IFERROR($C$10-1*'0. Supuestos'!$B$71,"") -> 2.5604865 | B41: =IFERROR(IF(B$39-$A41<=0,"",$C$7/(B$39-$A41)/$C$12),"") -> 64.870956 | C41: =IFERROR(IF(C$39-$A41<=0,"",$C$7/(C$39-$A41)/$C$12),"") -> 55.878659 | D41: =IFERROR(IF(D$39-$A41<=0,"",$C$7/(D$39-$A41)/$C$12),"") -> 49.075852 | E41: =IFERROR(IF(E$39-$A41<=0,"",$C$7/(E$39-$A41)/$C$12),"") -> 43.74966
A42: =IFERROR($C$10,"") -> 2.7604865 | B42: =IFERROR(IF(B$39-$A42<=0,"",$C$7/(B$39-$A42)/$C$12),"") -> 67.028266 | C42: =IFERROR(IF(C$39-$A42<=0,"",$C$7/(C$39-$A42)/$C$12),"") -> 57.471992 | D42: =IFERROR(IF(D$39-$A42<=0,"",$C$7/(D$39-$A42)/$C$12),"") -> 50.300596 | E42: =IFERROR(IF(E$39-$A42<=0,"",$C$7/(E$39-$A42)/$C$12),"") -> 44.720358
A43: =IFERROR($C$10+1*'0. Supuestos'!$B$71,"") -> 2.9604865 | B43: =IFERROR(IF(B$39-$A43<=0,"",$C$7/(B$39-$A43)/$C$12),"") -> 69.333996 | C43: =IFERROR(IF(C$39-$A43<=0,"",$C$7/(C$39-$A43)/$C$12),"") -> 59.158858 | D43: =IFERROR(IF(D$39-$A43<=0,"",$C$7/(D$39-$A43)/$C$12),"") -> 51.588035 | E43: =IFERROR(IF(E$39-$A43<=0,"",$C$7/(E$39-$A43)/$C$12),"") -> 45.735109
A44: =IFERROR($C$10+2*'0. Supuestos'!$B$71,"") -> 3.1604865 | B44: =IFERROR(IF(B$39-$A44<=0,"",$C$7/(B$39-$A44)/$C$12),"") -> 71.80401 | C44: =IFERROR(IF(C$39-$A44<=0,"",$C$7/(C$39-$A44)/$C$12),"") -> 60.94774 | D44: =IFERROR(IF(D$39-$A44<=0,"",$C$7/(D$39-$A44)/$C$12),"") -> 52.943108 | E44: =IFERROR(IF(E$39-$A44<=0,"",$C$7/(E$39-$A44)/$C$12),"") -> 46.79698
A46: La celda del centro es tu escenario. Muévete una columna a la izquierda y estarás viendo qué pasa si tienes que bajar el ticket medio un euro; una fila hacia abajo, qué pasa si el cacao te sube el coste variable. Los dos movimientos han pasado en los últimos tres años, y el segundo tiene su propio libro en esta guía.

Sheet Escenarios
A1: Escenarios: Pesimista, Realista y Optimista
A2: AI Chef Pro · aichef.pro — Cómo Montar una Chocolatería
A3: La columna «Realista» LEE el año de crucero del P&L, así que no puede desviarse de él. Las otras dos son verdes: son tus apuestas, y la de la izquierda es la que hay que poder sobrevivir.
A5: Métrica | B5: Pesimista | C5: Realista | D5: Optimista | E5: Notas
A6: Clientes al día | B6: 48 | C6: =IFERROR('PyG 3 Años'!C7,"") -> 67 | D6: 85 | E6: SUPUESTOS los dos extremos. El pesimista no es «un mal día»: es el año entero yendo mal, con una Navidad floja dentro.
A7: Ticket medio sin IVA (€) | B7: 8.2 | C7: =IFERROR('PyG 3 Años'!C8,"") -> 9.7745455 | D7: 11.5 | E7: SUPUESTOS. En bombonería el ticket lo mueve el MIX, no el precio: si la gente compra cajas de 12 en vez de cajas de 35, el ticket cae sin que hayas bajado un solo precio.
A8: Días de apertura al año | B8: 290 | C8: =IFERROR('PyG 3 Años'!C9,"") -> 304 | D8: 310 | E8: SUPUESTOS. Ojo con creer que abrir más días arregla un año malo: lo que arregla un año malo es Navidad.
A9: INGRESOS ANUALES (sin IVA) | B9: =IFERROR(IF(B6*B7*B8=0,"",B6*B7*B8),"") -> 114144 | C9: =IFERROR(IF(C6*C7*C8=0,"",C6*C7*C8),"") -> 199087.94 | D9: =IFERROR(IF(D6*D7*D8=0,"",D6*D7*D8),"") -> 303025
A10: Coste de ventas (food cost del P&L) | B10: =IFERROR(IF(B9="","",B9*'0. Supuestos'!$B$24),"") -> 32236.074 | C10: =IFERROR(IF(C9="","",C9*'0. Supuestos'!$B$24),"") -> 56225.588 | D10: =IFERROR(IF(D9="","",D9*'0. Supuestos'!$B$24),"") -> 85579.06
A11: TOTAL COSTES VARIABLES | B11: =IFERROR(IF(B9="","",B10),"") -> 32236.074 | C11: =IFERROR(IF(C9="","",C10),"") -> 56225.588 | D11: =IFERROR(IF(D9="","",D10),"") -> 85579.06
A12: MARGEN BRUTO | B12: =IFERROR(IF(B9="","",B9-B11),"") -> 81907.926 | C12: =IFERROR(IF(C9="","",C9-C11),"") -> 142862.35 | D12: =IFERROR(IF(D9="","",D9-D11),"") -> 217445.94
A13: COSTES FIJOS (los del año de crucero del P&L) | B13: =IFERROR(IF(B9="","",'PyG 3 Años'!$C$31),"") -> 122546.03 | C13: =IFERROR(IF(C9="","",'PyG 3 Años'!$C$31),"") -> 122546.03 | D13: =IFERROR(IF(D9="","",'PyG 3 Años'!$C$31),"") -> 122546.03 | E13: Los costes fijos no cambian con el escenario: por eso son fijos. Si en el pesimista se disparan sobre las ventas, el ajuste hay que hacerlo en la hoja de Personal, no aquí.
A14: RESULTADO ANTES DE IMPUESTOS | B14: =IFERROR(IF(B9="","",B12-B13),"") -> -40638.105 | C14: =IFERROR(IF(C9="","",C12-C13),"") -> 20316.322 | D14: =IFERROR(IF(D9="","",D12-D13),"") -> 94899.909
A15: Impuesto de Sociedades | B15: =IFERROR(IF(B9="","",MAX(0,B14-'0. Supuestos'!$B$49)*'0. Supuestos'!$B$47),"") -> 0 | C15: =IFERROR(IF(C9="","",MAX(0,C14-'0. Supuestos'!$B$49)*'0. Supuestos'!$B$47),"") -> 3047.4483 | D15: =IFERROR(IF(D9="","",MAX(0,D14-'0. Supuestos'!$B$49)*'0. Supuestos'!$B$47),"") -> 14234.986 | E15: Al tipo de entidad de nueva creación, compensando las bases negativas anteriores. Con resultado negativo no hay cuota.
A16: RESULTADO NETO | B16: =IFERROR(IF(B9="","",B14-B15),"") -> -40638.105 | C16: =IFERROR(IF(C9="","",C14-C15),"") -> 17268.874 | D16: =IFERROR(IF(D9="","",D14-D15),"") -> 80664.922
A17: Margen neto (%) | B17: =IFERROR(IF(B9="","",B16/B9),"") -> -0.35602489 | C17: =IFERROR(IF(C9="","",C16/C9),"") -> 0.086739929 | D17: =IFERROR(IF(D9="","",D16/D9),"") -> 0.2661989 | E17: Contrástalo con la banda de referencia de «0. Supuestos», que es un supuesto de control y no un dato del sector. El optimista que se va muy por encima suele estar olvidándose de un coste, no descubriendo un negocio mejor.
A18: Clientes al día para el equilibrio | B18: =IFERROR(IF(B9="","",IF(B7-B11/(B6*B8)<=0,"",B13/(B7-B11/(B6*B8))/B8)),"") -> 71.8149 | C18: =IFERROR(IF(C9="","",IF(C7-C11/(C6*C8)<=0,"",C13/(C7-C11/(C6*C8))/C8)),"") -> 57.471992 | D18: =IFERROR(IF(D9="","",IF(D7-D11/(D6*D8)<=0,"",D13/(D7-D11/(D6*D8))/D8)),"") -> 47.903459
A19: LO QUE CADA ESCENARIO EXIGE
A20: Coste de personal / ventas | B20: =IFERROR(IF(B9="","",'PyG 3 Años'!$C$17/B9),"") -> 0.5994071 | C20: =IFERROR(IF(C9="","",'PyG 3 Años'!$C$17/C9),"") -> 0.34366082 | D20: =IFERROR(IF(D9="","",'PyG 3 Años'!$C$17/D9),"") -> 0.22578574 | E20: La MISMA plantilla en los tres escenarios: tres personas y dos jornadas y media. En el pesimista es donde se ve si esa plantilla se sostiene.
A21: Ventas al año por jornada equivalente (€) | B21: =IFERROR(IF(B9="","",B9/'Personal'!$C$9),"") -> 45657.6 | C21: =IFERROR(IF(C9="","",C9/'Personal'!$C$9),"") -> 79635.177 | D21: =IFERROR(IF(D9="","",D9/'Personal'!$C$9),"") -> 121210 | E21: Cuánto tendría que facturar cada jornada completa del cuadro de Personal. En el optimista dice si hace falta contratar antes de llegar ahí -y en bombonería contratar en noviembre ya es tarde-.
A22: Saldo de caja estimado al cierre del año 1 (mismo método en los tres) | B22: =IFERROR(IF(B9="","",'Inversión Inicial'!$B$16+B16+'PyG 3 Años'!$C$29-'Financiación'!$C$116),"") -> 23264.874 | C22: =IFERROR(IF(C9="","",'Inversión Inicial'!$B$16+C16+'PyG 3 Años'!$C$29-'Financiación'!$C$116),"") -> 81171.852 | D22: =IFERROR(IF(D9="","",'Inversión Inicial'!$B$16+D16+'PyG 3 Años'!$C$29-'Financiación'!$C$116),"") -> 144567.9 | E22: Fondo de maniobra más el resultado del año, devolviendo la amortización (que no se paga) y restando el principal (que sí). Es una ESTIMACIÓN: el saldo de verdad, con su desfase de cobros y su liquidación de IVA, está en la hoja de Tesorería.
A23: Saldo real del mes 12 de la hoja de Tesorería (sólo el realista) | C23: =IFERROR(IF(C9="","",'Tesorería 12 meses'!M23),"") -> 72959.294 | E23: Sólo existe para el caso base: la tesorería mes a mes está construida sobre el año 1 del P&L, no sobre los escenarios.
A25: La columna «Realista» lee sus tres datos del año de crucero del P&L, así que reproduce EXACTAMENTE ese año. Si quieres mover el caso base, muévelo en «0. Supuestos» y esta columna te sigue.

Sheet Personal
A1: Personal: Tres Personas y Dos Jornadas y Media
A2: AI Chef Pro · aichef.pro — Cómo Montar una Chocolatería
A3: Los tres perfiles son los del kit de tareas de chocolatería, con sus nombres: Encargado, Chocolatero y Dependiente. El bruto sale del convenio, en celda verde, y la Seguridad Social a cargo de la empresa va DENTRO: del bruto al coste empresa hay un tercio más.
A5: Persona y perfil | B5: Personas | C5: Jornada | D5: Grupo de convenio | E5: Bruto mes del grupo (€) | F5: Bruto mes del puesto (€) | G5: Seguridad Social a cargo de la empresa (€) | H5: Coste mes (€) | I5: Coste año (€) | J5: Horas/semana | K5: Área | L5: Notas
A6: P1 · Encargado | B6: 1 | C6: 1 | D6: Grupo 2 | E6: =IFERROR(INDEX($E$13:$E$17,MATCH(D6,$A$13:$A$17,0)),"") -> 1427.89 | F6: =IFERROR(E6*C6*B6,"") -> 1427.89 | G6: =IFERROR(F6*'0. Supuestos'!$B$29,"") -> 471.2037 | H6: =IFERROR(F6+G6,"") -> 1899.0937 | I6: =IFERROR(H6*MAX(12,'0. Supuestos'!$B$30),"") -> 28486.406 | J6: 40 | K6: OBRADOR | L6: Turno de Partido (08:00-13:00 y 17:00-20:00).
A7: P2 · Chocolatero | B7: 1 | C7: 1 | D7: Grupo 3 | E7: =IFERROR(INDEX($E$13:$E$17,MATCH(D7,$A$13:$A$17,0)),"") -> 1376.91 | F7: =IFERROR(E7*C7*B7,"") -> 1376.91 | G7: =IFERROR(F7*'0. Supuestos'!$B$29,"") -> 454.3803 | H7: =IFERROR(F7+G7,"") -> 1831.2903 | I7: =IFERROR(H7*MAX(12,'0. Supuestos'!$B$30),"") -> 27469.355 | J7: 40 | K7: OBRADOR | L7: Turno de Mañana (07:00-15:00).
A8: P3 · Dependiente | B8: 1 | C8: 0.5 | D8: Grupo 4 | E8: =IFERROR(INDEX($E$13:$E$17,MATCH(D8,$A$13:$A$17,0)),"") -> 1249.42 | F8: =IFERROR(E8*C8*B8,"") -> 624.71 | G8: =IFERROR(F8*'0. Supuestos'!$B$29,"") -> 206.1543 | H8: =IFERROR(F8+G8,"") -> 830.8643 | I8: =IFERROR(H8*MAX(12,'0. Supuestos'!$B$30),"") -> 12462.965 | J8: 20 | K8: TIENDA | L8: Turno de Tarde (16:30-20:30).
A9: TOTAL PLANTILLA | B9: =IFERROR(IF(COUNT(E6:E8)=0,"",SUM(B6:B8)),"") -> 3 | C9: =IFERROR(IF(COUNT(E6:E8)=0,"",SUM(C6:C8)),"") -> 2.5 | F9: =IFERROR(IF(COUNT(E6:E8)=0,"",SUM(F6:F8)),"") -> 3429.51 | G9: =IFERROR(IF(COUNT(E6:E8)=0,"",SUM(G6:G8)),"") -> 1131.7383 | H9: =IFERROR(IF(COUNT(E6:E8)=0,"",SUM(H6:H8)),"") -> 4561.2483 | I9: =IFERROR(IF(COUNT(E6:E8)=0,"",SUM(I6:I8)),"") -> 68418.725 | J9: =IFERROR(IF(COUNT(E6:E8)=0,"",SUM(J6:J8)),"") -> 100 | L9: Este «Coste año» es el que lee el P&L. No hay una segunda estimación de personal en ninguna parte del libro. Y dentro va la retribución del titular, que en este caso es el Encargado: lo único que va aparte, en los fijos, es su cuota de autónomos.
A11: EL CONVENIO DE REFERENCIA (sustitúyelo por el tuyo)
A12: Grupo | B12: Denominación del grupo | E12: Bruto mes (€) | F12: Bruto año (€) | G12: Áreas funcionales | I12: Puestos que cita
A13: Grupo 1 | B13: Técnicos y titulados superiores | E13: 1733.88 | F13: =IFERROR(E13*MAX(12,'0. Supuestos'!$B$30),"") -> 26008.2 | G13: ADMINISTRACION | I13: -
A14: Grupo 2 | B14: Dirección, jefes y encargados | E14: 1427.89 | F14: =IFERROR(E14*MAX(12,'0. Supuestos'!$B$30),"") -> 21418.35 | G14: OBRADOR / TIENDA / ADMINISTRACION | I14: maestro de obrador, encargado
A15: Grupo 3 | B15: Personal especialista | E15: 1376.91 | F15: =IFERROR(E15*MAX(12,'0. Supuestos'!$B$30),"") -> 20653.65 | G15: OBRADOR / TIENDA | I15: especialista de producción, encargado de sección
A16: Grupo 4 | B16: Personal cualificado | E16: 1249.42 | F16: =IFERROR(E16*MAX(12,'0. Supuestos'!$B$30),"") -> 18741.3 | G16: OBRADOR / TIENDA | I16: personal cualificado de producción y de envasado, dependiente
A17: Grupo 5 | B17: Personal de apoyo y ayuda en servicios auxiliares | E17: 1192.42 | F17: =IFERROR(E17*MAX(12,'0. Supuestos'!$B$30),"") -> 17886.3 | G17: OBRADOR / TIENDA | I17: ayudante de producción, ayudante de comercio, peón, limpiador, almacenero
A19: CONTRASTE CON EL SMI
A20: Bruto anual del grupo más bajo (€) | B20: =IFERROR(IF(COUNT(F13:F17)=0,"",MIN(F13:F17)),"") -> 17886.3
A21: SMI anual de referencia (€) | B21: =IFERROR('0. Supuestos'!$B$31,"") -> 17094
A22: ¿Algún grupo queda por debajo del SMI? | B22: =IFERROR(IF(B20="","",IF(B20<B21,"Sí: revísalo con tu asesor","No: aquí manda el convenio")),"") -> No: aquí manda el convenio | L22: El SMI es una referencia ANUAL en cómputo global, no un mínimo por concepto. En este sector manda el convenio: el grupo más bajo de la tabla de ejemplo ya lo supera. Las dos cosas caducan el 31-12-2026.
A24: SALARIOS DE MERCADO (orientativos, y NUNCA un convenio)
A25: Etiqueta de la fuente salarial | B25: Mín. (€/h) | C25: Máx. (€/h) | D25: Equivale a | E25: Coste año a jornada completa (€) | L25: Notas
A26: «Chocolatero / bombonero especializado» | B26: 13 | C26: 16 | D26: Chocolatero | E26: =IFERROR(B26*$B$42*(1+'0. Supuestos'!$B$29),"") -> 30776.2 | L26: Fiabilidad media, y NUNCA se presentan como tabla de convenio. Las etiquetas entrecomilladas son las de la FUENTE salarial, no los perfiles de esta casa: los perfiles son los tres del kit, y la columna «Equivale a» está para eso. Sirven para saber si lo que vas a ofrecer está dentro de mercado; lo que te OBLIGA es tu convenio.
A27: «Oficial de primera» | B27: 11 | C27: 13 | D27: Chocolatero | E27: =IFERROR(B27*$B$42*(1+'0. Supuestos'!$B$29),"") -> 26041.4
A28: «Auxiliar / ayudante» | B28: 8 | C28: 9.5 | D28: Dependiente | E28: =IFERROR(B28*$B$42*(1+'0. Supuestos'!$B$29),"") -> 18939.2
A29: «Encargado / maestro» | B29: 15 | C29: 20 | D29: Encargado | E29: =IFERROR(B29*$B$42*(1+'0. Supuestos'!$B$29),"") -> 35511
A31: LOS CUATRO CONVENIOS DE ÁMBITO PROVINCIAL O SUPERIOR QUE SÍ NOMBRAN CHOCOLATES O BOMBONES
A32: Código | B32: Ámbito | E32: Denominación | L32: Notas
A33: 45000145011981 | B33: Toledo | E33: - | L33: ESTÁ PROBADO que NO existe convenio ESTATAL del chocolate: el registro oficial devuelve «no se ha encontrado ningún acuerdo» para chocolate, bombones, confitería y pastelería, y el control con «turrones» devuelve 29 trámites, así que la consulta funciona. Estos cuatro existen y nombran el producto, pero su ámbito FUNCIONAL es una pregunta para un laboralista, no una respuesta de esta guía.
A34: 80000725012008 | B34: Comunitat Valenciana | E34: CHOCOLATES, TORREFACTORES DE CAFES Y SUCEDANEOS (01/01/2023-31/12/2026)
A35: 01000425011981 | B35: Alava | E35: caducado
A36: 22001125012010 | B36: Huesca | E36: -
A38: HORAS, DIMENSIONADO Y COSTE HORA
A39: Horas contratadas a la semana | B39: =IFERROR(J9,"") -> 100
A40: Jornadas completas equivalentes | B40: =IFERROR(C9,"") -> 2.5
A41: Personas con más horas de las que da su jornada | B41: =IFERROR(SUMPRODUCT((J6:J8>C6:C8*'0. Supuestos'!$B$32)*1),"") -> 0 | L41: Tiene que valer cero. Si se pone en rojo, alguien está contratado a media jornada y trabajando más horas de las que cobra: eso no es un ahorro, es una inspección.
A42: Horas anuales de contrato | B42: 1780 | L42: SUPUESTO: 40 h x 52 semanas = 2.080, menos 30 días naturales de vacaciones y los festivos del calendario laboral.
A43: Parte de la jornada a pie de mesa (%) | B43: 0.85 | L43: SUPUESTO. El resto es recepción de mercancía, limpieza, formación y reuniones. Si lo pones al 100 % estarás repartiendo el coste de personal entre horas que no existen.
A44: COSTE DE UNA HORA DE OBRADOR (€) | B44: =IFERROR(SUMPRODUCT((K6:K8="OBRADOR")*I6:I8)/SUMPRODUCT((K6:K8="OBRADOR")*C6:C8*B6:B8)/$B$42/$B$43,"") -> 18.491659 | L44: Coste empresa de las personas del ÁREA OBRADOR dividido entre sus horas PRODUCTIVAS. No es el bruto ni el bruto con Seguridad Social: es lo que de verdad cuesta un minuto de templado, y es el número que usan el escandallo del libro 4 y la hoja de talleres para saber lo que cuesta un docente.
A46: El refuerzo de las campañas NO está en este cuadro: la estacionalidad manda horas extra en Navidad, en San Valentín y en comuniones, y eso se dimensiona y se cuesta en el libro «campanas-y-valle-del-ano». Aquí está la plantilla ESTABLE, que es la que entra en los costes fijos del P&L. Y una nota de método: los tres nombres de perfil son los de las hojas del kit de tareas -Encargado, Chocolatero y Dependiente-, no «maestro chocolatero» ni «bombonero», que son etiquetas de fuentes salariales y no puestos de esta casa.

Sheet Tesorería 12 meses
A1: Tesorería de los 12 Primeros Meses
A2: AI Chef Pro · aichef.pro — Cómo Montar una Chocolatería
A3: El P&L dice si el negocio gana dinero; esta hoja dice si le queda caja para llegar a fin de mes. Es la primera que mira un banco, y la que más aperturas ha salvado. Abajo, la fecha límite de cierre de pedidos de Navidad, calculada hacia atrás desde la capacidad de tu obrador.
A5: Concepto | B5: Mes 1 | C5: Mes 2 | D5: Mes 3 | E5: Mes 4 | F5: Mes 5 | G5: Mes 6 | H5: Mes 7 | I5: Mes 8 | J5: Mes 9 | K5: Mes 10 | L5: Mes 11 | M5: Mes 12 | N5: Año (€) | O5: Notas
A6: Estacionalidad del mes (tiene que sumar 100 %) | B6: 0.076667 | C6: 0.093333 | D6: 0.085 | E6: 0.09 | F6: 0.091667 | G6: 0.076667 | H6: 0.068333 | I6: 0.05 | J6: 0.071667 | K6: 0.085 | L6: 0.091667 | M6: 0.12 | N6: =IFERROR(SUM(B6:M6),"") -> 1.000001 | O6: DICIEMBRE manda, y AGOSTO es el suelo: son los doce coeficientes del calendario de campañas del kit traducidos a euros, con media 1,000 exacta. Agosto NO vale cero -la tienda abre para el turista aunque el obrador pare-, y por eso el valle se nota en el margen y no en la persiana. SON SUPUESTOS: no existe reparto mensual publicado de las ventas de una chocolatería, y la guía te enseña a medir el tuyo con el TPV.
A7: Rampa de arranque (% de la actividad de crucero) | B7: =IFERROR(MIN(1,'0. Supuestos'!$B$53+(1-'0. Supuestos'!$B$53)*0/MAX(1,'0. Supuestos'!$B$54-1)),"") -> 0.55 | C7: =IFERROR(MIN(1,'0. Supuestos'!$B$53+(1-'0. Supuestos'!$B$53)*1/MAX(1,'0. Supuestos'!$B$54-1)),"") -> 0.64 | D7: =IFERROR(MIN(1,'0. Supuestos'!$B$53+(1-'0. Supuestos'!$B$53)*2/MAX(1,'0. Supuestos'!$B$54-1)),"") -> 0.73 | E7: =IFERROR(MIN(1,'0. Supuestos'!$B$53+(1-'0. Supuestos'!$B$53)*3/MAX(1,'0. Supuestos'!$B$54-1)),"") -> 0.82 | F7: =IFERROR(MIN(1,'0. Supuestos'!$B$53+(1-'0. Supuestos'!$B$53)*4/MAX(1,'0. Supuestos'!$B$54-1)),"") -> 0.91 | G7: =IFERROR(MIN(1,'0. Supuestos'!$B$53+(1-'0. Supuestos'!$B$53)*5/MAX(1,'0. Supuestos'!$B$54-1)),"") -> 1 | H7: =IFERROR(MIN(1,'0. Supuestos'!$B$53+(1-'0. Supuestos'!$B$53)*6/MAX(1,'0. Supuestos'!$B$54-1)),"") -> 1 | I7: =IFERROR(MIN(1,'0. Supuestos'!$B$53+(1-'0. Supuestos'!$B$53)*7/MAX(1,'0. Supuestos'!$B$54-1)),"") -> 1 | J7: =IFERROR(MIN(1,'0. Supuestos'!$B$53+(1-'0. Supuestos'!$B$53)*8/MAX(1,'0. Supuestos'!$B$54-1)),"") -> 1 | K7: =IFERROR(MIN(1,'0. Supuestos'!$B$53+(1-'0. Supuestos'!$B$53)*9/MAX(1,'0. Supuestos'!$B$54-1)),"") -> 1 | L7: =IFERROR(MIN(1,'0. Supuestos'!$B$53+(1-'0. Supuestos'!$B$53)*10/MAX(1,'0. Supuestos'!$B$54-1)),"") -> 1 | M7: =IFERROR(MIN(1,'0. Supuestos'!$B$53+(1-'0. Supuestos'!$B$53)*11/MAX(1,'0. Supuestos'!$B$54-1)),"") -> 1 | O7: Sube en línea recta desde el porcentaje del mes 1 hasta el 100 % en los meses que digas en «0. Supuestos». Con el 100 % en el mes 1 la rampa desaparece, y entonces estás proyectando una apertura que no existe. Ojo al calendario: este caso abre el 1 de junio, así que el mes 3 de la rampa es agosto.
A8: Reparto de la actividad por mes (calculado) | B8: =IFERROR(B6*B7/SUMPRODUCT($B$6:$M$6,$B$7:$M$7),"") -> 0.047673041 | C8: =IFERROR(C6*C7/SUMPRODUCT($B$6:$M$6,$B$7:$M$7),"") -> 0.067533133 | D8: =IFERROR(D6*D7/SUMPRODUCT($B$6:$M$6,$B$7:$M$7),"") -> 0.070152554 | E8: =IFERROR(E6*E7/SUMPRODUCT($B$6:$M$6,$B$7:$M$7),"") -> 0.083436881 | F8: =IFERROR(F6*F7/SUMPRODUCT($B$6:$M$6,$B$7:$M$7),"") -> 0.094309645 | G8: =IFERROR(G6*G7/SUMPRODUCT($B$6:$M$6,$B$7:$M$7),"") -> 0.086678257 | H8: =IFERROR(H6*H7/SUMPRODUCT($B$6:$M$6,$B$7:$M$7),"") -> 0.077255995 | I8: =IFERROR(I6*I7/SUMPRODUCT($B$6:$M$6,$B$7:$M$7),"") -> 0.056529052 | ... M8: =IFERROR(M6*M7/SUMPRODUCT($B$6:$M$6,$B$7:$M$7),"") -> 0.13566973 | N8: =IFERROR(SUM(B8:M8),"") -> 1 | O8: Estacionalidad x rampa, normalizado al 100 %: el AÑO factura lo que dice el P&L, pero repartido como lo reparte la realidad.
A9: COBROS
A10: Ventas cobradas (con el IVA repercutido dentro) | B10: =IFERROR(IF('PyG 3 Años'!$B$11="","",'PyG 3 Años'!$B$11*(1+'0. Supuestos'!$B$20)*(B8*(1-'0. Supuestos'!$B$58/30))),"") -> 6879.6299 | C10: =IFERROR(IF('PyG 3 Años'!$B$11="","",'PyG 3 Años'!$B$11*(1+'0. Supuestos'!$B$20)*(C8*(1-'0. Supuestos'!$B$58/30)+B8*('0. Supuestos'!$B$58/30))),"") -> 12100.385 | D10: =IFERROR(IF('PyG 3 Años'!$B$11="","",'PyG 3 Años'!$B$11*(1+'0. Supuestos'!$B$20)*(D8*(1-'0. Supuestos'!$B$58/30)+C8*('0. Supuestos'!$B$58/30))),"") -> 13459.363 | E10: =IFERROR(IF('PyG 3 Años'!$B$11="","",'PyG 3 Años'!$B$11*(1+'0. Supuestos'!$B$20)*(E8*(1-'0. Supuestos'!$B$58/30)+D8*('0. Supuestos'!$B$58/30))),"") -> 15505.79 | F10: =IFERROR(IF('PyG 3 Años'!$B$11="","",'PyG 3 Años'!$B$11*(1+'0. Supuestos'!$B$20)*(F8*(1-'0. Supuestos'!$B$58/30)+E8*('0. Supuestos'!$B$58/30))),"") -> 17730.992 | G10: =IFERROR(IF('PyG 3 Años'!$B$11="","",'PyG 3 Años'!$B$11*(1+'0. Supuestos'!$B$20)*(G8*(1-'0. Supuestos'!$B$58/30)+F8*('0. Supuestos'!$B$58/30))),"") -> 17166.769 | H10: =IFERROR(IF('PyG 3 Años'!$B$11="","",'PyG 3 Años'!$B$11*(1+'0. Supuestos'!$B$20)*(H8*(1-'0. Supuestos'!$B$58/30)+G8*('0. Supuestos'!$B$58/30))),"") -> 15430.109 | I10: =IFERROR(IF('PyG 3 Años'!$B$11="","",'PyG 3 Años'!$B$11*(1+'0. Supuestos'!$B$20)*(I8*(1-'0. Supuestos'!$B$58/30)+H8*('0. Supuestos'!$B$58/30))),"") -> 11973.628 | J10: =IFERROR(IF('PyG 3 Años'!$B$11="","",'PyG 3 Años'!$B$11*(1+'0. Supuestos'!$B$20)*(J8*(1-'0. Supuestos'!$B$58/30)+I8*('0. Supuestos'!$B$58/30))),"") -> 14484.863 | ... M10: =IFERROR(IF('PyG 3 Años'!$B$11="","",'PyG 3 Años'!$B$11*(1+'0. Supuestos'!$B$20)*(M8*(1-'0. Supuestos'!$B$58/30)+L8*('0. Supuestos'!$B$58/30))),"") -> 24697.376 | N10: =IFERROR(IF('PyG 3 Años'!$B$11="","",SUM(B10:M10)),"") -> 187001.52 | O10: Ventas del mes con el IVA repercutido, corregidas por los días medios de cobro que calcula la hoja de canales. El mostrador y el taller cobran al contado; el corporativo a 30 días y el B2B a 45, y ahí financias tú.
A11: PAGOS
A12: Compras y coste de ventas (IVA incluido) | B12: =IFERROR(IF('PyG 3 Años'!$B$11="","",-'PyG 3 Años'!$B$13*(1+'PyG 3 Años'!$F$13)*(B8*(1-'0. Supuestos'!$B$59/30))+0),"") -> 0 | C12: =IFERROR(IF('PyG 3 Años'!$B$11="","",-'PyG 3 Años'!$B$13*(1+'PyG 3 Años'!$F$13)*(C8*(1-'0. Supuestos'!$B$59/30)+B8*('0. Supuestos'!$B$59/30))+0),"") -> -2607.9415 | D12: =IFERROR(IF('PyG 3 Años'!$B$11="","",-'PyG 3 Años'!$B$13*(1+'PyG 3 Años'!$F$13)*(D8*(1-'0. Supuestos'!$B$59/30)+C8*('0. Supuestos'!$B$59/30))+0),"") -> -3694.3828 | E12: =IFERROR(IF('PyG 3 Años'!$B$11="","",-'PyG 3 Años'!$B$13*(1+'PyG 3 Años'!$F$13)*(E8*(1-'0. Supuestos'!$B$59/30)+D8*('0. Supuestos'!$B$59/30))+0),"") -> -3837.6775 | F12: =IFERROR(IF('PyG 3 Años'!$B$11="","",-'PyG 3 Años'!$B$13*(1+'PyG 3 Años'!$F$13)*(F8*(1-'0. Supuestos'!$B$59/30)+E8*('0. Supuestos'!$B$59/30))+0),"") -> -4564.3933 | G12: =IFERROR(IF('PyG 3 Años'!$B$11="","",-'PyG 3 Años'!$B$13*(1+'PyG 3 Años'!$F$13)*(G8*(1-'0. Supuestos'!$B$59/30)+F8*('0. Supuestos'!$B$59/30))+0),"") -> -5159.185 | H12: =IFERROR(IF('PyG 3 Años'!$B$11="","",-'PyG 3 Años'!$B$13*(1+'PyG 3 Años'!$F$13)*(H8*(1-'0. Supuestos'!$B$59/30)+G8*('0. Supuestos'!$B$59/30))+0),"") -> -4741.7119 | I12: =IFERROR(IF('PyG 3 Años'!$B$11="","",-'PyG 3 Años'!$B$13*(1+'PyG 3 Años'!$F$13)*(I8*(1-'0. Supuestos'!$B$59/30)+H8*('0. Supuestos'!$B$59/30))+0),"") -> -4226.2694 | J12: =IFERROR(IF('PyG 3 Años'!$B$11="","",-'PyG 3 Años'!$B$13*(1+'PyG 3 Años'!$F$13)*(J8*(1-'0. Supuestos'!$B$59/30)+I8*('0. Supuestos'!$B$59/30))+0),"") -> -3092.4074 | ... M12: =IFERROR(IF('PyG 3 Años'!$B$11="","",-'PyG 3 Años'!$B$13*(1+'PyG 3 Años'!$F$13)*(M8*(1-'0. Supuestos'!$B$59/30)+L8*('0. Supuestos'!$B$59/30))+0),"") -> -5669.4341 | N12: =IFERROR(IF('PyG 3 Años'!$B$11="","",SUM(B12:M12)),"") -> -47282.967 | O12: Con los días medios de pago a proveedor de «0. Supuestos». A 30 días el mes 1 no paga nada: el proveedor te está financiando el arranque, y por eso perder ese crédito por un retraso sale tan caro. Ojo a la compra de cobertura de Navidad, que se paga en octubre y se cobra en diciembre.
A13: Costes fijos de explotación (IVA incluido) | B13: =IFERROR(IF('PyG 3 Años'!$B$11="","",-(('PyG 3 Años'!$B$31-'PyG 3 Años'!$B$17-'PyG 3 Años'!$B$29-'PyG 3 Años'!$B$30)+'PyG 3 Años'!$B$33)/12),"") -> -4029.75 | C13: =IFERROR(IF('PyG 3 Años'!$B$11="","",-(('PyG 3 Años'!$B$31-'PyG 3 Años'!$B$17-'PyG 3 Años'!$B$29-'PyG 3 Años'!$B$30)+'PyG 3 Años'!$B$33)/12),"") -> -4029.75 | D13: =IFERROR(IF('PyG 3 Años'!$B$11="","",-(('PyG 3 Años'!$B$31-'PyG 3 Años'!$B$17-'PyG 3 Años'!$B$29-'PyG 3 Años'!$B$30)+'PyG 3 Años'!$B$33)/12),"") -> -4029.75 | E13: =IFERROR(IF('PyG 3 Años'!$B$11="","",-(('PyG 3 Años'!$B$31-'PyG 3 Años'!$B$17-'PyG 3 Años'!$B$29-'PyG 3 Años'!$B$30)+'PyG 3 Años'!$B$33)/12),"") -> -4029.75 | F13: =IFERROR(IF('PyG 3 Años'!$B$11="","",-(('PyG 3 Años'!$B$31-'PyG 3 Años'!$B$17-'PyG 3 Años'!$B$29-'PyG 3 Años'!$B$30)+'PyG 3 Años'!$B$33)/12),"") -> -4029.75 | G13: =IFERROR(IF('PyG 3 Años'!$B$11="","",-(('PyG 3 Años'!$B$31-'PyG 3 Años'!$B$17-'PyG 3 Años'!$B$29-'PyG 3 Años'!$B$30)+'PyG 3 Años'!$B$33)/12),"") -> -4029.75 | H13: =IFERROR(IF('PyG 3 Años'!$B$11="","",-(('PyG 3 Años'!$B$31-'PyG 3 Años'!$B$17-'PyG 3 Años'!$B$29-'PyG 3 Años'!$B$30)+'PyG 3 Años'!$B$33)/12),"") -> -4029.75 | I13: =IFERROR(IF('PyG 3 Años'!$B$11="","",-(('PyG 3 Años'!$B$31-'PyG 3 Años'!$B$17-'PyG 3 Años'!$B$29-'PyG 3 Años'!$B$30)+'PyG 3 Años'!$B$33)/12),"") -> -4029.75 | ... M13: =IFERROR(IF('PyG 3 Años'!$B$11="","",-(('PyG 3 Años'!$B$31-'PyG 3 Años'!$B$17-'PyG 3 Años'!$B$29-'PyG 3 Años'!$B$30)+'PyG 3 Años'!$B$33)/12),"") -> -4029.75 | N13: =IFERROR(IF('PyG 3 Años'!$B$11="","",SUM(B13:M13)),"") -> -48357 | O13: Los fijos que salen de caja, cada uno con su tipo de IVA: sin las nóminas (van abajo), sin la amortización (no se paga) y sin los intereses (van aparte). La cuota de autónomos del titular SÍ está aquí: se paga todos los meses, también en agosto.
A14: Nóminas y Seguridad Social | B14: =IFERROR(IF('PyG 3 Años'!$B$11="","",-'PyG 3 Años'!$B$17/MAX(12,'0. Supuestos'!$B$30)*(1+IF(1='0. Supuestos'!$B$60,1,0)+IF(1='0. Supuestos'!$B$61,1,0)+IF(1='0. Supuestos'!$B$62,1,0))),"") -> -4561.2483 | C14: =IFERROR(IF('PyG 3 Años'!$B$11="","",-'PyG 3 Años'!$B$17/MAX(12,'0. Supuestos'!$B$30)*(1+IF(2='0. Supuestos'!$B$60,1,0)+IF(2='0. Supuestos'!$B$61,1,0)+IF(2='0. Supuestos'!$B$62,1,0))),"") -> -4561.2483 | D14: =IFERROR(IF('PyG 3 Años'!$B$11="","",-'PyG 3 Años'!$B$17/MAX(12,'0. Supuestos'!$B$30)*(1+IF(3='0. Supuestos'!$B$60,1,0)+IF(3='0. Supuestos'!$B$61,1,0)+IF(3='0. Supuestos'!$B$62,1,0))),"") -> -9122.4966 | E14: =IFERROR(IF('PyG 3 Años'!$B$11="","",-'PyG 3 Años'!$B$17/MAX(12,'0. Supuestos'!$B$30)*(1+IF(4='0. Supuestos'!$B$60,1,0)+IF(4='0. Supuestos'!$B$61,1,0)+IF(4='0. Supuestos'!$B$62,1,0))),"") -> -4561.2483 | F14: =IFERROR(IF('PyG 3 Años'!$B$11="","",-'PyG 3 Años'!$B$17/MAX(12,'0. Supuestos'!$B$30)*(1+IF(5='0. Supuestos'!$B$60,1,0)+IF(5='0. Supuestos'!$B$61,1,0)+IF(5='0. Supuestos'!$B$62,1,0))),"") -> -4561.2483 | G14: =IFERROR(IF('PyG 3 Años'!$B$11="","",-'PyG 3 Años'!$B$17/MAX(12,'0. Supuestos'!$B$30)*(1+IF(6='0. Supuestos'!$B$60,1,0)+IF(6='0. Supuestos'!$B$61,1,0)+IF(6='0. Supuestos'!$B$62,1,0))),"") -> -4561.2483 | H14: =IFERROR(IF('PyG 3 Años'!$B$11="","",-'PyG 3 Años'!$B$17/MAX(12,'0. Supuestos'!$B$30)*(1+IF(7='0. Supuestos'!$B$60,1,0)+IF(7='0. Supuestos'!$B$61,1,0)+IF(7='0. Supuestos'!$B$62,1,0))),"") -> -9122.4966 | I14: =IFERROR(IF('PyG 3 Años'!$B$11="","",-'PyG 3 Años'!$B$17/MAX(12,'0. Supuestos'!$B$30)*(1+IF(8='0. Supuestos'!$B$60,1,0)+IF(8='0. Supuestos'!$B$61,1,0)+IF(8='0. Supuestos'!$B$62,1,0))),"") -> -4561.2483 | J14: =IFERROR(IF('PyG 3 Años'!$B$11="","",-'PyG 3 Años'!$B$17/MAX(12,'0. Supuestos'!$B$30)*(1+IF(9='0. Supuestos'!$B$60,1,0)+IF(9='0. Supuestos'!$B$61,1,0)+IF(9='0. Supuestos'!$B$62,1,0))),"") -> -4561.2483 | K14: =IFERROR(IF('PyG 3 Años'!$B$11="","",-'PyG 3 Años'!$B$17/MAX(12,'0. Supuestos'!$B$30)*(1+IF(10='0. Supuestos'!$B$60,1,0)+IF(10='0. Supuestos'!$B$61,1,0)+IF(10='0. Supuestos'!$B$62,1,0))),"") -> -4561.2483 | L14: =IFERROR(IF('PyG 3 Años'!$B$11="","",-'PyG 3 Años'!$B$17/MAX(12,'0. Supuestos'!$B$30)*(1+IF(11='0. Supuestos'!$B$60,1,0)+IF(11='0. Supuestos'!$B$61,1,0)+IF(11='0. Supuestos'!$B$62,1,0))),"") -> -4561.2483 | M14: =IFERROR(IF('PyG 3 Años'!$B$11="","",-'PyG 3 Años'!$B$17/MAX(12,'0. Supuestos'!$B$30)*(1+IF(12='0. Supuestos'!$B$60,1,0)+IF(12='0. Supuestos'!$B$61,1,0)+IF(12='0. Supuestos'!$B$62,1,0))),"") -> -9122.4966 | N14: =IFERROR(IF('PyG 3 Años'!$B$11="","",SUM(B14:M14)),"") -> -68418.724 | O14: Doce mensualidades más las pagas extra en los meses que digas. Con 15 pagas hay tres meses que salen dobles, y siempre pillan a contrapié: uno de ellos suele caer en el mes flojo.
A15: Intereses del préstamo | B15: =IFERROR(IF('PyG 3 Años'!$B$11="","",-IF('Financiación'!C26="",0,'Financiación'!C26)),"") -> -466.55 | C15: =IFERROR(IF('PyG 3 Años'!$B$11="","",-IF('Financiación'!C27="",0,'Financiación'!C27)),"") -> -466.55 | D15: =IFERROR(IF('PyG 3 Años'!$B$11="","",-IF('Financiación'!C28="",0,'Financiación'!C28)),"") -> -466.55 | E15: =IFERROR(IF('PyG 3 Años'!$B$11="","",-IF('Financiación'!C29="",0,'Financiación'!C29)),"") -> -466.55 | F15: =IFERROR(IF('PyG 3 Años'!$B$11="","",-IF('Financiación'!C30="",0,'Financiación'!C30)),"") -> -466.55 | G15: =IFERROR(IF('PyG 3 Años'!$B$11="","",-IF('Financiación'!C31="",0,'Financiación'!C31)),"") -> -466.55 | H15: =IFERROR(IF('PyG 3 Años'!$B$11="","",-IF('Financiación'!C32="",0,'Financiación'!C32)),"") -> -466.55 | I15: =IFERROR(IF('PyG 3 Años'!$B$11="","",-IF('Financiación'!C33="",0,'Financiación'!C33)),"") -> -461.67788 | J15: =IFERROR(IF('PyG 3 Años'!$B$11="","",-IF('Financiación'!C34="",0,'Financiación'!C34)),"") -> -456.78058 | K15: =IFERROR(IF('PyG 3 Años'!$B$11="","",-IF('Financiación'!C35="",0,'Financiación'!C35)),"") -> -451.85798 | L15: =IFERROR(IF('PyG 3 Años'!$B$11="","",-IF('Financiación'!C36="",0,'Financiación'!C36)),"") -> -446.90995 | M15: =IFERROR(IF('PyG 3 Años'!$B$11="","",-IF('Financiación'!C37="",0,'Financiación'!C37)),"") -> -441.93636 | N15: =IFERROR(IF('PyG 3 Años'!$B$11="","",SUM(B15:M15)),"") -> -5525.0128
A16: Devolución de principal del préstamo | B16: =IFERROR(IF('PyG 3 Años'!$B$11="","",-IF('Financiación'!D26="",0,'Financiación'!D26)),"") -> 0 | C16: =IFERROR(IF('PyG 3 Años'!$B$11="","",-IF('Financiación'!D27="",0,'Financiación'!D27)),"") -> 0 | D16: =IFERROR(IF('PyG 3 Años'!$B$11="","",-IF('Financiación'!D28="",0,'Financiación'!D28)),"") -> 0 | E16: =IFERROR(IF('PyG 3 Años'!$B$11="","",-IF('Financiación'!D29="",0,'Financiación'!D29)),"") -> 0 | F16: =IFERROR(IF('PyG 3 Años'!$B$11="","",-IF('Financiación'!D30="",0,'Financiación'!D30)),"") -> 0 | G16: =IFERROR(IF('PyG 3 Años'!$B$11="","",-IF('Financiación'!D31="",0,'Financiación'!D31)),"") -> 0 | H16: =IFERROR(IF('PyG 3 Años'!$B$11="","",-IF('Financiación'!D32="",0,'Financiación'!D32)),"") -> -942.99149 | I16: =IFERROR(IF('PyG 3 Años'!$B$11="","",-IF('Financiación'!D33="",0,'Financiación'!D33)),"") -> -947.86361 | J16: =IFERROR(IF('PyG 3 Años'!$B$11="","",-IF('Financiación'!D34="",0,'Financiación'!D34)),"") -> -952.76091 | K16: =IFERROR(IF('PyG 3 Años'!$B$11="","",-IF('Financiación'!D35="",0,'Financiación'!D35)),"") -> -957.6835 | L16: =IFERROR(IF('PyG 3 Años'!$B$11="","",-IF('Financiación'!D36="",0,'Financiación'!D36)),"") -> -962.63153 | M16: =IFERROR(IF('PyG 3 Años'!$B$11="","",-IF('Financiación'!D37="",0,'Financiación'!D37)),"") -> -967.60513 | N16: =IFERROR(IF('PyG 3 Años'!$B$11="","",SUM(B16:M16)),"") -> -5731.5362 | O16: Sale del cuadro MENSUAL de la hoja de Financiación. Durante la carencia esta fila vale cero, y ése es justo el efecto que se negocia con el banco.
A17: IVA repercutido del mes (memoria) | B17: =IFERROR(IF('PyG 3 Años'!$B$11="","",'PyG 3 Años'!$B$11*B8*'0. Supuestos'!$B$20),"") -> 839.49114 | C17: =IFERROR(IF('PyG 3 Años'!$B$11="","",'PyG 3 Años'!$B$11*C8*'0. Supuestos'!$B$20),"") -> 1189.2144 | D17: =IFERROR(IF('PyG 3 Años'!$B$11="","",'PyG 3 Años'!$B$11*D8*'0. Supuestos'!$B$20),"") -> 1235.3407 | E17: =IFERROR(IF('PyG 3 Años'!$B$11="","",'PyG 3 Años'!$B$11*E8*'0. Supuestos'!$B$20),"") -> 1469.269 | F17: =IFERROR(IF('PyG 3 Años'!$B$11="","",'PyG 3 Años'!$B$11*F8*'0. Supuestos'!$B$20),"") -> 1660.7313 | G17: =IFERROR(IF('PyG 3 Años'!$B$11="","",'PyG 3 Años'!$B$11*G8*'0. Supuestos'!$B$20),"") -> 1526.3475 | H17: =IFERROR(IF('PyG 3 Años'!$B$11="","",'PyG 3 Años'!$B$11*H8*'0. Supuestos'!$B$20),"") -> 1360.4276 | I17: =IFERROR(IF('PyG 3 Años'!$B$11="","",'PyG 3 Años'!$B$11*I8*'0. Supuestos'!$B$20),"") -> 995.43971 | ... M17: =IFERROR(IF('PyG 3 Años'!$B$11="","",'PyG 3 Años'!$B$11*M8*'0. Supuestos'!$B$20),"") -> 2389.0553 | N17: =IFERROR(IF('PyG 3 Años'!$B$11="","",SUM(B17:M17)),"") -> 17609.347
A18: IVA soportado del mes (memoria) | B18: =IFERROR(IF('PyG 3 Años'!$B$11="","",'PyG 3 Años'!$B$32*B8+'PyG 3 Años'!$B$33/12),"") -> 861.83559 | C18: =IFERROR(IF('PyG 3 Años'!$B$11="","",'PyG 3 Años'!$B$32*C8+'PyG 3 Años'!$B$33/12),"") -> 960.60298 | D18: =IFERROR(IF('PyG 3 Años'!$B$11="","",'PyG 3 Años'!$B$32*D8+'PyG 3 Años'!$B$33/12),"") -> 973.62978 | E18: =IFERROR(IF('PyG 3 Años'!$B$11="","",'PyG 3 Años'!$B$32*E8+'PyG 3 Años'!$B$33/12),"") -> 1039.6948 | F18: =IFERROR(IF('PyG 3 Años'!$B$11="","",'PyG 3 Años'!$B$32*F8+'PyG 3 Años'!$B$33/12),"") -> 1093.7668 | G18: =IFERROR(IF('PyG 3 Años'!$B$11="","",'PyG 3 Años'!$B$32*G8+'PyG 3 Años'!$B$33/12),"") -> 1055.8147 | H18: =IFERROR(IF('PyG 3 Años'!$B$11="","",'PyG 3 Años'!$B$32*H8+'PyG 3 Años'!$B$33/12),"") -> 1008.9563 | I18: =IFERROR(IF('PyG 3 Años'!$B$11="","",'PyG 3 Años'!$B$32*I8+'PyG 3 Años'!$B$33/12),"") -> 905.87794 | ... M18: =IFERROR(IF('PyG 3 Años'!$B$11="","",'PyG 3 Años'!$B$32*M8+'PyG 3 Años'!$B$33/12),"") -> 1299.4571 | N18: =IFERROR(IF('PyG 3 Años'!$B$11="","",SUM(B18:M18)),"") -> 12470.159
A19: IVA a compensar arrastrado (inversión incluida) | E19: =IFERROR(IF('PyG 3 Años'!$B$11="","",'Inversión Inicial'!$B$22),"") -> 17912.86 | H19: =IFERROR(IF('PyG 3 Años'!$B$11="","",MAX(0,-E20)),"") -> 17444.882 | K19: =IFERROR(IF('PyG 3 Años'!$B$11="","",MAX(0,-H20)),"") -> 15977.811 | O19: El IVA soportado de la INVERSIÓN entra aquí y se compensa contra el repercutido de los trimestres siguientes. Con una inversión grande tardas medio año en recuperarlo, y ese medio año lo financias tú.
A20: Resultado de la liquidación trimestral | E20: =IFERROR(IF('PyG 3 Años'!$B$11="","",SUM(B17:D17)-SUM(B18:D18)-E19),"") -> -17444.882 | H20: =IFERROR(IF('PyG 3 Años'!$B$11="","",SUM(E17:G17)-SUM(E18:G18)-H19),"") -> -15977.811 | K20: =IFERROR(IF('PyG 3 Años'!$B$11="","",SUM(H17:J17)-SUM(H18:J18)-K19),"") -> -15137.676
A21: Pago del IVA (modelo 303) | E21: =IFERROR(IF('PyG 3 Años'!$B$11="","",IF(E20<=0,"",-E20)),"") | H21: =IFERROR(IF('PyG 3 Años'!$B$11="","",IF(H20<=0,"",-H20)),"") | K21: =IFERROR(IF('PyG 3 Años'!$B$11="","",IF(K20<=0,"",-K20)),"") | N21: =IFERROR(IF('PyG 3 Años'!$B$11="","",IF(E21="",0,E21)+IF(H21="",0,H21)+IF(K21="",0,K21)),"") -> 0 | O21: Sólo sale caja cuando el resultado del trimestre es positivo. Los meses sin liquidación van en BLANCO, no a cero: un cero significaría «liquidé y no pagué nada», que es otra cosa. El cuarto trimestre se liquida en enero del año siguiente y por eso no aparece.
A22: FLUJO DEL MES | B22: =IFERROR(IF('PyG 3 Años'!$B$11="","",SUM(B10:B16)+IF(B21="",0,B21)),"") -> -2177.9184 | C22: =IFERROR(IF('PyG 3 Años'!$B$11="","",SUM(C10:C16)+IF(C21="",0,C21)),"") -> 434.89474 | D22: =IFERROR(IF('PyG 3 Años'!$B$11="","",SUM(D10:D16)+IF(D21="",0,D21)),"") -> -3853.8162 | E22: =IFERROR(IF('PyG 3 Años'!$B$11="","",SUM(E10:E16)+IF(E21="",0,E21)),"") -> 2610.5643 | F22: =IFERROR(IF('PyG 3 Años'!$B$11="","",SUM(F10:F16)+IF(F21="",0,F21)),"") -> 4109.0509 | G22: =IFERROR(IF('PyG 3 Años'!$B$11="","",SUM(G10:G16)+IF(G21="",0,G21)),"") -> 2950.0359 | H22: =IFERROR(IF('PyG 3 Años'!$B$11="","",SUM(H10:H16)+IF(H21="",0,H21)),"") -> -3873.3907 | I22: =IFERROR(IF('PyG 3 Años'!$B$11="","",SUM(I10:I16)+IF(I21="",0,I21)),"") -> -2253.1813 | ... M22: =IFERROR(IF('PyG 3 Años'!$B$11="","",SUM(M10:M16)+IF(M21="",0,M21)),"") -> 4466.1533 | N22: =IFERROR(IF('PyG 3 Años'!$B$11="","",SUM(B22:M22)),"") -> 11686.279
A23: SALDO ACUMULADO DE CAJA | B23: =IFERROR(IF('PyG 3 Años'!$B$11="","",'Inversión Inicial'!$B$16+B22),"") -> 59095.097 | C23: =IFERROR(IF('PyG 3 Años'!$B$11="","",B23+C22),"") -> 59529.992 | D23: =IFERROR(IF('PyG 3 Años'!$B$11="","",C23+D22),"") -> 55676.176 | E23: =IFERROR(IF('PyG 3 Años'!$B$11="","",D23+E22),"") -> 58286.74 | F23: =IFERROR(IF('PyG 3 Años'!$B$11="","",E23+F22),"") -> 62395.791 | G23: =IFERROR(IF('PyG 3 Años'!$B$11="","",F23+G22),"") -> 65345.827 | H23: =IFERROR(IF('PyG 3 Años'!$B$11="","",G23+H22),"") -> 61472.436 | I23: =IFERROR(IF('PyG 3 Años'!$B$11="","",H23+I22),"") -> 59219.255 | J23: =IFERROR(IF('PyG 3 Años'!$B$11="","",I23+J22),"") -> 60611.171 | ... M23: =IFERROR(IF('PyG 3 Años'!$B$11="","",L23+M22),"") -> 72959.294
A24: Saldo mínimo del año (€) | B24: =IFERROR(IF('PyG 3 Años'!$B$11="","",IF(COUNT(B23:M23)=0,"",MIN(B23:M23))),"") -> 55676.176 | O24: Si es negativo te quedas sin caja: sube el fondo de maniobra, sube el préstamo o negocia más carencia. No lo dejes para verlo pasar.
A25: Mes en el que la caja toca fondo | B25: =IFERROR(IF('PyG 3 Años'!$B$11="","",IF(COUNT(B23:M23)=0,"",MATCH(MIN(B23:M23),B23:M23,0))),"") -> 3 | O25: Es la respuesta a la pregunta que decide una operación bancaria: en qué mes se agota la caja. Abriendo el 1 de junio, ese mes cae casi siempre en el valle.
A27: RETORNO DE LA INVERSIÓN
A28: Flujo de caja libre antes de la deuda, año 1 | B28: =IFERROR(IF('PyG 3 Años'!$B$11="","",'PyG 3 Años'!B41+'PyG 3 Años'!B29+'Financiación'!$B$116),"") -> 16603.664 | O28: Resultado neto más amortización (que no se paga) más los intereses de ese año: el principal no se resta porque este flujo se compara con la inversión, no con la deuda.
A29: Flujo de caja libre antes de la deuda, año 2 | B29: =IFERROR(IF('PyG 3 Años'!$B$11="","",'PyG 3 Años'!C41+'PyG 3 Años'!C29+'Financiación'!$B$117),"") -> 30536.181
A30: Flujo de caja libre antes de la deuda, año 3 | B30: =IFERROR(IF('PyG 3 Años'!$B$11="","",'PyG 3 Años'!D41+'PyG 3 Años'!D29+'Financiación'!$B$118),"") -> 32598.903
A31: Inversión a recuperar (sin el IVA, que se recupera por el 303) | B31: =IFERROR(IF('PyG 3 Años'!$B$11="","",'Inversión Inicial'!$B$23-'Inversión Inicial'!$B$22),"") -> 150492.37
A32: Payback del proyecto (años), antes de la deuda | B32: =IFERROR(IF('PyG 3 Años'!$B$11="","",IF(B28>=B31,ROUND(B31/B28,1),IF(B28+B29>=B31,ROUND(1+(B31-B28)/B29,1),IF(B28+B29+B30>=B31,ROUND(2+(B31-B28-B29)/B30,1),"Más de 3 años")))),"") -> Más de 3 años | O32: Cuánto tarda el negocio en devolver la inversión con lo que genera ANTES de pagar al banco. Si sale «Más de 3 años», este libro no proyecta lo suficiente para decírtelo: es una señal, no un fallo.
A34: LA FECHA LÍMITE DE CIERRE DE PEDIDOS DE NAVIDAD (cruce 7 <- 1, calculada HACIA ATRÁS desde tu capacidad)
A35: Capacidad del obrador en jornada normal (bombones/día): trae aquí la cifra de capacidad-obrador-y-clima.xlsx!Cuello de Botella!B7 («Bombones al día que permite el conjunto») | B35: 512 | O35: CÓPIALA A MANO del libro «capacidad-obrador-y-clima»: la casilla de bombones al día que permite el equipo que limita. No hay ninguna fórmula entre ficheros. VALOR POR DEFECTO DECLARADO: los 512 bombones al día del caso, con el puesto de envasado y montaje de cajas como cuello de botella. Si cambias de atemperadora, de moldes o de puesto de envasado, vuelve a copiarlo.
A36: Cifra que publica hoy esa hoja del libro 1 | B36: 512 | O36: Anota aquí lo que ves en el libro 1 la última vez que lo abriste. Si arriba tecleas otra cosa -porque te lo dijo el instalador, o porque cuentas con horas extra-, la fila de CUADRE te avisa en vez de dejar las dos cifras separadas en silencio.
A37: Desviación entre las dos | B37: =IFERROR(ABS(B35-B36)/B36,"") -> 0
A38: CUADRE DE LA CAPACIDAD: la que usas frente a la del libro 1 | B38: =IFERROR(IF(NOT(ISNUMBER(B37)),"",IF(B37<='0. Supuestos'!$B$72,"CUADRA","REVISA: la capacidad que estás usando no es la que calcula el libro 1")),"") -> CUADRA
A39: Bombones de obrador al día en velocidad de crucero | B39: 472 | O39: Lo que sale del obrador un día normal, contado en BOMBONES DE OBRADOR: una caja de 35 es una venta y treinta y seis piezas. Sale del mismo libro 1; medir el pico en tickets es lo que hace creer que Navidad cabe.
A40: Excedente diario para adelantar producción (bombones/día) | B40: =IFERROR(B35-B39,"") -> 40 | O40: Lo que te sobra cada día para ir haciendo Navidad por delante. Si sale cero o negativo, no hay fecha límite que valga: no puedes adelantar nada y la campaña se resuelve con horas extra, con refuerzo o diciendo que no. Eso se dimensiona en el libro «campanas-y-valle-del-ano».
A41: Bombones de la campaña de Navidad que quieres tener hechos POR ADELANTADO | B41: 2400 | O41: SUPUESTO, y OJO CON LO QUE ES: NO es lo que vas a vender en diciembre, que es muchísimo más. Es lo que quieres tener FABRICADO Y GUARDADO antes de que empiece la punta, y por eso sólo caben las referencias que aguantan -tabletas, turrones, figuras y bombones estabilizados-, nunca la ganache fresca. Todo lo que no quepa aquí se resuelve con horas extra y refuerzo, y eso se dimensiona y se cuesta en el libro «campanas-y-valle-del-ano».
A42: Días de obrador que hacen falta para fabricarlos | B42: =IFERROR(IF(B40<=0,"",B41/B40),"") -> 60
A43: Días de calendario que hay que empezar antes | B43: =IFERROR(IF(B42="","",ROUND(B42*7/'0. Supuestos'!$B$56,0)),"") -> 70 | O43: De días de PRODUCCIÓN a días de calendario: si abres seis días de cada siete, cada día de obrador son 1,17 días naturales. Sin NETWORKDAYS, que esta familia tiene prohibida: aritmética de días y de índices de mes, que se entiende y se audita.
A44: Fecha en la que tiene que estar todo hecho | B44: 46741 | O44: SUPUESTO: el 20 de diciembre, que es cuando se lleva el grueso de los encargos. Ponla del año que estés planificando.
A45: FECHA LÍMITE DE CIERRE DE PEDIDOS DE NAVIDAD | B45: =IFERROR(IF(B43="","",B44-B43),"") -> 46671 | O45: A partir de aquí, cada pedido nuevo de Navidad te obliga a comprar horas o a decir que no. NO es una fecha comercial: la fija tu obrador, y por eso se calcula hacia atrás desde la capacidad y no desde el calendario de marketing.
A46: Mes en el que cae esa fecha (índice 1-12) | B46: =IFERROR(IF(B45="","",MONTH(B45)),"") -> 10
A47: LECTURA | B47: =IFERROR(IF(B43="","No hay excedente diario: no puedes adelantar nada y la campaña se resuelve con refuerzo",IF(B46<=10,"Cierras en octubre o antes: la agenda corporativa y la de encargos tienen que estar montadas en septiembre","Cierras dentro de noviembre o diciembre: vas justo, y una avería te deja sin campaña")),"") -> Cierras en octubre o antes: la agenda corporativa y la de encargos tienen que estar montadas en septiembre
A48: Esta fecha es la que convierte la capacidad del obrador en una decisión comercial: hasta ella coges encargos, después empiezas a comprar horas. Y explica por qué el pedido de regalo corporativo se cierra en octubre: entre que el cliente aprueba la muestra y tú fabricas pasan catorce días como mínimo, y esos catorce días caen ENCIMA de los que acabas de calcular.
A50: Escribe los ingresos y los gastos SIN IVA en el resto del libro: la capa de IVA de esta hoja lo añade, porque la tesorería es caja. El Impuesto de Sociedades no está en este cuadro: se paga en julio del año siguiente, fuera de los doce meses.

Sheet Financiación
A1: Financiación: De Dónde Sale y Cuánto Cuesta Devolverlo
A2: AI Chef Pro · aichef.pro — Cómo Montar una Chocolatería
A3: El cuadro de amortización es MENSUAL, con 84 filas, porque la carencia de este caso son seis meses y un cuadro anual no sabe expresar medio año. La cuota es una anualidad algebraica del sistema francés: PMT está prohibida en esta familia.
A5: ORIGEN DE FONDOS
A6: Recursos propios aportados | B6: =IFERROR('0. Supuestos'!$B$40,"") -> 78105.23 | H6: Aportación de los socios o del promotor. Un banco quiere ver un 25-30 % de fondos propios sobre la necesidad total antes de sentarse a hablar. Aquí es el 40 %, que es la estructura declarada del caso.
A7: Préstamo bancario | B7: =IFERROR('0. Supuestos'!$B$41,"") -> 90300
A8: Otras fuentes (ICO, ENISA, subvenciones, socios) | B8: 0 | H8: A cero por defecto. Las subvenciones suelen cobrarse DESPUÉS de justificar el gasto: no cuentes con ellas para pagar la obra.
A9: TOTAL ORIGEN DE FONDOS | B9: =IFERROR(IF(COUNT(B6:B8)=0,"",SUM(B6:B8)),"") -> 168405.23
A10: USOS
A11: Necesidad total de caja al arranque | B11: =IFERROR('Inversión Inicial'!$B$23,"") -> 168405.23 | H11: Inversión total -CAPEX más fondo de maniobra- y el IVA que hay que adelantar.
A12: Diferencia (origen menos usos) | B12: =IFERROR(B9-B11,"") -> 0.0043470032 | H12: En negativo el plan NO está financiado. Muy por encima de cero tampoco es gratis: son intereses que pagas sin necesitarlos.
A13: Diferencia sobre los usos (%) | B13: =IFERROR(B12/B11,"") -> 2.5812757e-08
A14: Préstamo que ajustaría el origen a la necesidad | B14: =IFERROR(MAX(0,B11-B9+B7),"") -> 90299.996 | H14: Cópialo en «Préstamo bancario solicitado» de «0. Supuestos» y la diferencia de arriba se pone a cero. Después mira el DSCR: pedir más siempre se puede, devolverlo no.
A15: CONDICIONES DEL PRÉSTAMO
A16: Importe del principal | B16: =IFERROR(IF('0. Supuestos'!$B$41=0,"",'0. Supuestos'!$B$41),"") -> 90300
A17: Tipo de interés nominal anual | B17: =IFERROR('0. Supuestos'!$B$42,"") -> 0.062
A18: Tipo mensual | B18: =IFERROR(B17/12,"") -> 0.0051666667
A19: Plazo total (meses) | B19: =IFERROR('0. Supuestos'!$B$43,"") -> 84
A20: Carencia de principal aplicada (meses) | B20: =IFERROR(IF('0. Supuestos'!$B$44>='0. Supuestos'!$B$43,'0. Supuestos'!$B$43-1,'0. Supuestos'!$B$44),"") -> 6 | H20: Una carencia igual o mayor que el plazo no existe: la hoja la anula en origen.
A21: Meses de amortización | B21: =IFERROR(B19-B20,"") -> 78
A22: Cuota mensual durante la amortización | B22: =IFERROR(IF(B21<=0,"",IF(B18=0,B16/B21,B16*B18/(1-(1+B18)^(-B21)))),"") -> 1409.5415
A23: Sistema francés, escrito como anualidad algebraica: capital x tipo mensual dividido por uno menos (uno más el tipo) elevado a menos el número de cuotas. Con el tipo al 0 % es el principal entre los meses de amortización. No se usa la función PMT: esta familia la tiene prohibida porque no todos los motores de hoja de cálculo la evalúan igual.
A25: Mes | B25: Capital pendiente (€) | C25: Intereses (€) | D25: Amortización de principal (€) | E25: Cuota total (€) | F25: Capital al cierre (€) | H25: Notas
A26: 1 | B26: =IFERROR(IF($B$16="","",$B$16),"") -> 90300 | C26: =IFERROR(IF(OR(A26>$B$19,B26=""),"",B26*$B$18),"") -> 466.55 | D26: =IFERROR(IF(OR(A26>$B$19,B26=""),"",IF(A26<=$B$20,0,MIN(B26,$B$22-C26))),"") -> 0 | E26: =IFERROR(IF(C26="","",C26+D26),"") -> 466.55 | F26: =IFERROR(IF(D26="","",B26-D26),"") -> 90300 | H26: Durante la carencia la columna de amortización vale cero y sólo se pagan intereses. Es lo que hace que el préstamo no se coma la caja en la rampa de arranque, y es lo primero que hay que negociar.
A27: 2 | B27: =IFERROR(IF(OR(A27>$B$19,F26=""),"",F26),"") -> 90300 | C27: =IFERROR(IF(OR(A27>$B$19,B27=""),"",B27*$B$18),"") -> 466.55 | D27: =IFERROR(IF(OR(A27>$B$19,B27=""),"",IF(A27<=$B$20,0,MIN(B27,$B$22-C27))),"") -> 0 | E27: =IFERROR(IF(C27="","",C27+D27),"") -> 466.55 | F27: =IFERROR(IF(D27="","",B27-D27),"") -> 90300
A28: 3 | B28: =IFERROR(IF(OR(A28>$B$19,F27=""),"",F27),"") -> 90300 | C28: =IFERROR(IF(OR(A28>$B$19,B28=""),"",B28*$B$18),"") -> 466.55 | D28: =IFERROR(IF(OR(A28>$B$19,B28=""),"",IF(A28<=$B$20,0,MIN(B28,$B$22-C28))),"") -> 0 | E28: =IFERROR(IF(C28="","",C28+D28),"") -> 466.55 | F28: =IFERROR(IF(D28="","",B28-D28),"") -> 90300
A29: 4 | B29: =IFERROR(IF(OR(A29>$B$19,F28=""),"",F28),"") -> 90300 | C29: =IFERROR(IF(OR(A29>$B$19,B29=""),"",B29*$B$18),"") -> 466.55 | D29: =IFERROR(IF(OR(A29>$B$19,B29=""),"",IF(A29<=$B$20,0,MIN(B29,$B$22-C29))),"") -> 0 | E29: =IFERROR(IF(C29="","",C29+D29),"") -> 466.55 | F29: =IFERROR(IF(D29="","",B29-D29),"") -> 90300
A30: 5 | B30: =IFERROR(IF(OR(A30>$B$19,F29=""),"",F29),"") -> 90300 | C30: =IFERROR(IF(OR(A30>$B$19,B30=""),"",B30*$B$18),"") -> 466.55 | D30: =IFERROR(IF(OR(A30>$B$19,B30=""),"",IF(A30<=$B$20,0,MIN(B30,$B$22-C30))),"") -> 0 | E30: =IFERROR(IF(C30="","",C30+D30),"") -> 466.55 | F30: =IFERROR(IF(D30="","",B30-D30),"") -> 90300
A31: 6 | B31: =IFERROR(IF(OR(A31>$B$19,F30=""),"",F30),"") -> 90300 | C31: =IFERROR(IF(OR(A31>$B$19,B31=""),"",B31*$B$18),"") -> 466.55 | D31: =IFERROR(IF(OR(A31>$B$19,B31=""),"",IF(A31<=$B$20,0,MIN(B31,$B$22-C31))),"") -> 0 | E31: =IFERROR(IF(C31="","",C31+D31),"") -> 466.55 | F31: =IFERROR(IF(D31="","",B31-D31),"") -> 90300
A32: 7 | B32: =IFERROR(IF(OR(A32>$B$19,F31=""),"",F31),"") -> 90300 | C32: =IFERROR(IF(OR(A32>$B$19,B32=""),"",B32*$B$18),"") -> 466.55 | D32: =IFERROR(IF(OR(A32>$B$19,B32=""),"",IF(A32<=$B$20,0,MIN(B32,$B$22-C32))),"") -> 942.99149 | E32: =IFERROR(IF(C32="","",C32+D32),"") -> 1409.5415 | F32: =IFERROR(IF(D32="","",B32-D32),"") -> 89357.009
A33: 8 | B33: =IFERROR(IF(OR(A33>$B$19,F32=""),"",F32),"") -> 89357.009 | C33: =IFERROR(IF(OR(A33>$B$19,B33=""),"",B33*$B$18),"") -> 461.67788 | D33: =IFERROR(IF(OR(A33>$B$19,B33=""),"",IF(A33<=$B$20,0,MIN(B33,$B$22-C33))),"") -> 947.86361 | E33: =IFERROR(IF(C33="","",C33+D33),"") -> 1409.5415 | F33: =IFERROR(IF(D33="","",B33-D33),"") -> 88409.145
A34: 9 | B34: =IFERROR(IF(OR(A34>$B$19,F33=""),"",F33),"") -> 88409.145 | C34: =IFERROR(IF(OR(A34>$B$19,B34=""),"",B34*$B$18),"") -> 456.78058 | D34: =IFERROR(IF(OR(A34>$B$19,B34=""),"",IF(A34<=$B$20,0,MIN(B34,$B$22-C34))),"") -> 952.76091 | E34: =IFERROR(IF(C34="","",C34+D34),"") -> 1409.5415 | F34: =IFERROR(IF(D34="","",B34-D34),"") -> 87456.384
A35: 10 | B35: =IFERROR(IF(OR(A35>$B$19,F34=""),"",F34),"") -> 87456.384 | C35: =IFERROR(IF(OR(A35>$B$19,B35=""),"",B35*$B$18),"") -> 451.85798 | D35: =IFERROR(IF(OR(A35>$B$19,B35=""),"",IF(A35<=$B$20,0,MIN(B35,$B$22-C35))),"") -> 957.6835 | E35: =IFERROR(IF(C35="","",C35+D35),"") -> 1409.5415 | F35: =IFERROR(IF(D35="","",B35-D35),"") -> 86498.7
A36: 11 | B36: =IFERROR(IF(OR(A36>$B$19,F35=""),"",F35),"") -> 86498.7 | C36: =IFERROR(IF(OR(A36>$B$19,B36=""),"",B36*$B$18),"") -> 446.90995 | D36: =IFERROR(IF(OR(A36>$B$19,B36=""),"",IF(A36<=$B$20,0,MIN(B36,$B$22-C36))),"") -> 962.63153 | E36: =IFERROR(IF(C36="","",C36+D36),"") -> 1409.5415 | F36: =IFERROR(IF(D36="","",B36-D36),"") -> 85536.069
A37: 12 | B37: =IFERROR(IF(OR(A37>$B$19,F36=""),"",F36),"") -> 85536.069 | C37: =IFERROR(IF(OR(A37>$B$19,B37=""),"",B37*$B$18),"") -> 441.93636 | D37: =IFERROR(IF(OR(A37>$B$19,B37=""),"",IF(A37<=$B$20,0,MIN(B37,$B$22-C37))),"") -> 967.60513 | E37: =IFERROR(IF(C37="","",C37+D37),"") -> 1409.5415 | F37: =IFERROR(IF(D37="","",B37-D37),"") -> 84568.464
A38: 13 | B38: =IFERROR(IF(OR(A38>$B$19,F37=""),"",F37),"") -> 84568.464 | C38: =IFERROR(IF(OR(A38>$B$19,B38=""),"",B38*$B$18),"") -> 436.93706 | D38: =IFERROR(IF(OR(A38>$B$19,B38=""),"",IF(A38<=$B$20,0,MIN(B38,$B$22-C38))),"") -> 972.60442 | E38: =IFERROR(IF(C38="","",C38+D38),"") -> 1409.5415 | F38: =IFERROR(IF(D38="","",B38-D38),"") -> 83595.859
... A109: 84 | B109: =IFERROR(IF(OR(A109>$B$19,F108=""),"",F108),"") -> 1402.2963 | C109: =IFERROR(IF(OR(A109>$B$19,B109=""),"",B109*$B$18),"") -> 7.2451975 | D109: =IFERROR(IF(OR(A109>$B$19,B109=""),"",IF(A109<=$B$20,0,MIN(B109,$B$22-C109))),"") -> 1402.2963 | E109: =IFERROR(IF(C109="","",C109+D109),"") -> 1409.5415 | F109: =IFERROR(IF(D109="","",B109-D109),"") -> 2.0309017e-09
A110: Tolerancia de cierre del cuadro (€) | B110: 0.01
A111: Capital pendiente al vencimiento | B111: =IFERROR(IF($B$16="","",ROUND($B$16-SUM(D26:D109),2)),"") -> 0
A112: ¿Cierra el cuadro de amortización? | B112: =IFERROR(IF(B111="","",IF(ABS(B111)<=B110,"Sí","No: revisa el plazo")),"") -> Sí | H112: Tiene que decir «Sí»: el principal devuelto en el cuadro tiene que ser el prestado. Si dice que no, el plazo no da para amortizarlo con esa cuota y queda capital sin devolver al vencimiento.
A114: RESUMEN POR AÑO Y COBERTURA DEL SERVICIO DE LA DEUDA (DSCR)
A115: Año | B115: Intereses (€) | C115: Principal devuelto (€) | D115: Cuota total (€) | E115: Flujo disponible para la deuda (€) | F115: DSCR | H115: Notas
A116: 1 | B116: =IFERROR(SUM(C26:C37),"") -> 5525.0128 | C116: =IFERROR(SUM(D26:D37),"") -> 5731.5362 | D116: =IFERROR(B116+C116,"") -> 11256.549 | E116: =IFERROR('PyG 3 Años'!B34-'PyG 3 Años'!B39+'PyG 3 Años'!B29+B116,"") -> 16603.664 | F116: =IFERROR(IF(OR(D116="",D116=0),"",E116/D116),"") -> 1.4750226 | H116: El flujo disponible se calcula ANTES de la deuda y DESPUÉS de impuestos: al resultado antes de impuestos se le resta la cuota del Impuesto de Sociedades y se le suma la amortización, que no se paga. Del año 4 en adelante se mantiene el flujo del año 3: este libro no proyecta más lejos, y decirlo es más honesto que inventarse un crecimiento.
A117: 2 | B117: =IFERROR(SUM(C38:C49),"") -> 4905.8078 | C117: =IFERROR(SUM(D38:D49),"") -> 12008.69 | D117: =IFERROR(B117+C117,"") -> 16914.498 | E117: =IFERROR('PyG 3 Años'!C34-'PyG 3 Años'!C39+'PyG 3 Años'!C29+B117,"") -> 30536.181 | F117: =IFERROR(IF(OR(D117="",D117=0),"",E117/D117),"") -> 1.8053259
A118: 3 | B118: =IFERROR(SUM(C50:C61),"") -> 4139.7431 | C118: =IFERROR(SUM(D50:D61),"") -> 12774.755 | D118: =IFERROR(B118+C118,"") -> 16914.498 | E118: =IFERROR('PyG 3 Años'!D34-'PyG 3 Años'!D39+'PyG 3 Años'!D29+B118,"") -> 32598.903 | F118: =IFERROR(IF(OR(D118="",D118=0),"",E118/D118),"") -> 1.9272758
A119: 4 | B119: =IFERROR(SUM(C62:C73),"") -> 3324.8091 | C119: =IFERROR(SUM(D62:D73),"") -> 13589.689 | D119: =IFERROR(B119+C119,"") -> 16914.498 | E119: =IFERROR('PyG 3 Años'!D34-'PyG 3 Años'!D39+'PyG 3 Años'!D29+B119,"") -> 31783.969 | F119: =IFERROR(IF(OR(D119="",D119=0),"",E119/D119),"") -> 1.8790962
A120: 5 | B120: =IFERROR(SUM(C74:C85),"") -> 2457.8885 | C120: =IFERROR(SUM(D74:D85),"") -> 14456.609 | D120: =IFERROR(B120+C120,"") -> 16914.498 | E120: =IFERROR('PyG 3 Años'!D34-'PyG 3 Años'!D39+'PyG 3 Años'!D29+B120,"") -> 30917.048 | F120: =IFERROR(IF(OR(D120="",D120=0),"",E120/D120),"") -> 1.8278431
A121: 6 | B121: =IFERROR(SUM(C86:C97),"") -> 1535.6648 | C121: =IFERROR(SUM(D86:D97),"") -> 15378.833 | D121: =IFERROR(B121+C121,"") -> 16914.498 | E121: =IFERROR('PyG 3 Años'!D34-'PyG 3 Años'!D39+'PyG 3 Años'!D29+B121,"") -> 29994.825 | F121: =IFERROR(IF(OR(D121="",D121=0),"",E121/D121),"") -> 1.7733204
A122: 7 | B122: =IFERROR(SUM(C98:C109),"") -> 554.61006 | C122: =IFERROR(SUM(D98:D109),"") -> 16359.888 | D122: =IFERROR(B122+C122,"") -> 16914.498 | E122: =IFERROR('PyG 3 Años'!D34-'PyG 3 Años'!D39+'PyG 3 Años'!D29+B122,"") -> 29013.77 | F122: =IFERROR(IF(OR(D122="",D122=0),"",E122/D122),"") -> 1.7153196
A123: DSCR mínimo de todo el cuadro | B123: =IFERROR(IF(COUNT(F116:F122)=0,"",MIN(F116:F122)),"") -> 1.4750226 | H123: Es el PEOR año de los que dura el préstamo, no el mejor de los tres que proyecta el P&L. Es el número que decide la operación.
A124: Lectura del DSCR | B124: =IFERROR(IF(B123="","",IF(B123<'0. Supuestos'!$B$64,"Por debajo del mínimo",IF(B123<'0. Supuestos'!$B$65,"Entre el mínimo y el objetivo","En objetivo"))),"") -> En objetivo
A126: El año de carencia infla el DSCR: con sólo intereses en el denominador el ratio se dispara y no está midiendo el negocio, está midiendo que todavía no devuelves nada. Mira el año 2 y el año 3, que es cuando la cuota está completa.

Sheet Canales y Punto Muerto
A1: Canales y Punto Muerto: Qué Canal Sostiene el Negocio
A2: AI Chef Pro · aichef.pro — Cómo Montar una Chocolatería
A3: Cinco canales, cada uno con su margen, su coste de servir, su comisión, su coste de envío y sus días de cobro. La suma no es lo interesante: lo interesante es qué pasa con el punto muerto cuando quitas uno, y cuáles de los cinco te sacan de la nota del epígrafe 644.5 del IAE.
A5: Canal | B5: % de las ventas | C5: Margen bruto (%) | D5: Coste de servir (%) | E5: Comisión de plataforma (%) | F5: Envío refrigerado (€/pedido) | G5: Días de cobro | H5: Margen de contribución (%) | I5: Ventas del año de crucero (€) | J5: Margen de contribución (€) | K5: ¿Te saca de la nota del 644.5? | L5: Notas
A6: Mostrador | B6: 0.62 | C6: 0.7 | D6: 0 | E6: 0 | F6: 0 | G6: 0 | H6: =IFERROR(C6-D6-E6,"") -> 0.7 | I6: =IFERROR(IF('PyG 3 Años'!$C$11="","",'PyG 3 Años'!$C$11*B6),"") -> 123434.52 | J6: =IFERROR(IF(H6="","",I6*H6),"") -> 86404.167 | K6: No | L6: Cobro al contado y dentro de la nota del 644.5 sin discusión: vendes en las propias dependencias. Es el canal que paga el alquiler.
A7: Online con envío refrigerado | B7: 0.12 | C7: 0.58 | D7: 0.04 | E7: 0 | F7: 8.5 | G7: 0 | H7: =IFERROR(C7-D7-E7,"") -> 0.54 | I7: =IFERROR(IF('PyG 3 Años'!$C$11="","",'PyG 3 Años'!$C$11*B7),"") -> 23890.553 | J7: =IFERROR(IF(H7="","",I7*H7),"") -> 12900.899 | K7: No lo sé | L7: LO QUE SI ESTA VERIFICADO: vender online al consumidor SIGUE SIENDO comercio al por menor a efectos del IAE, porque la Regla 4.a.2.D) lo define por el destino y comprende el realizado sin establecimiento (`CHN-95`); y vender por internet NO cambia tu registro sanitario (`CHN-90`). LO QUE NO ESTA VERIFICADO es si la condición de la nota del 644.5 sobre la FABRICACION se rompe al comercializar fuera de las dependencias: eso es lo que hay que preguntar al asesor. Lo que si cambia: te conviertes en ENVASADOR (`CHN-59`) y respondes de la temperatura en el camión (`CHN-88`), mas la información obligatoria ANTES de pagar (`CHN-57`). Coste de envío refrigerado de 8,50 euros: SUPUESTO, y es el número que decide si el canal existe. PARADO de junio a septiembre (`VALLE`).
A8: B2B a hostelería | B8: 0.11 | C8: 0.48 | D8: 0.03 | E8: 0 | F8: 0 | G8: 45 | H8: =IFERROR(C8-D8-E8,"") -> 0.45 | I8: =IFERROR(IF('PyG 3 Años'!$C$11="","",'PyG 3 Años'!$C$11*B8),"") -> 21899.674 | J8: =IFERROR(IF(H8="","",I8*H8),"") -> 9854.8531 | K8: No lo sé | L8: Peor margen y cobro a 45 días: financias tu. Y es el canal que puede meterte en el art. 3 del RD 1021/2022 si dejas de ser marginal, localizado o restringido - los TRES requisitos son ACUMULATIVOS, y basta con servir a UN SOLO cliente inscrito en el RGSEAA para perder «restringido» (`CHN-41`). «Marginal» tiene DOS vías independientes: hasta el 25 % del volumen anual O hasta 500 kg/semana. Y los 500 kg NO incluyen el mostrador: el art. 3 solo habla del suministro a otros minoristas de distinta titularidad.
A9: Regalo corporativo | B9: 0.09 | C9: 0.55 | D9: 0.03 | E9: 0 | F9: 0 | G9: 30 | H9: =IFERROR(C9-D9-E9,"") -> 0.52 | I9: =IFERROR(IF('PyG 3 Años'!$C$11="","",'PyG 3 Años'!$C$11*B9),"") -> 17917.915 | J9: =IFERROR(IF(H9="","",I9*H9),"") -> 9317.3157 | K9: No lo sé | L9: PLAZO MÍNIMO VERIFICADO: 14 días desde la aprobación de la muestra, con mínimos de fabricación de 10 a 25 cajas (`CHS-55`). Es lo que decide si aceptas un pedido de empresa el 15 de diciembre. Y es el canal que obliga a la SEGUNDA TABLA del libro 9: el art. 5.3.b) del EUDR exige registrar a quien suministras, y conservarlo cinco años (`CHN-24`, D48). El pedido mínimo (250 euros) y los 30 días de cobro son supuestos.
A10: Talleres y catas | B10: 0.06 | C10: 0.82 | D10: 0.05 | E10: 0 | F10: 0 | G10: 0 | H10: =IFERROR(C10-D10-E10,"") -> 0.77 | I10: =IFERROR(IF('PyG 3 Años'!$C$11="","",'PyG 3 Años'!$C$11*B10),"") -> 11945.277 | J10: =IFERROR(IF(H10="","",I10*H10),"") -> 9197.8629 | K10: No | L10: 25-45 euros/persona, mínimo habitual de 6 personas y 90-150 minutos (`CHS-30`). El aforo de 12 y las 3 horas de docente (preparación y recogida incluidas) son SUPUESTOS. LA ÚNICA LÍNEA QUE FUNCIONA EN AGOSTO y que no depende del precio del cacao: por eso su hoja calcula euros/hora de sala dando taller frente a euros/hora de la misma sala vendiendo. IVA: NO esta exento (el art. 20.Uno.10.o excluye las clases para cuya realización haya que darse de alta en las tarifas empresariales del IAE, `CHN-71b`), pero el TIPO NO SE CIERRA y la guía NO publica ninguna cifra de tipo (D42e). Y ojo con la columna del 644.5: el taller NO comercializa bombones fuera de tus dependencias, así que no rompe la nota del epígrafe. Lo que si abre es otra pregunta, y es la del propio `CHN-71b`: si la Hacienda entiende que hay que darse de alta por esta actividad, eso es un alta distinta, no un problema de la nota del 644.5. Los TRES canales que la rompen son el online, el B2B y el corporativo.
A11: TOTAL | B11: =IFERROR(IF(COUNT(B6:B10)=0,"",SUM(B6:B10)),"") -> 1 | H11: =IFERROR(J11/I11,"") -> 0.6413 | I11: =IFERROR(IF(COUNT(I6:I10)=0,"",SUM(I6:I10)),"") -> 199087.94 | J11: =IFERROR(IF(COUNT(J6:J10)=0,"",SUM(J6:J10)),"") -> 127675.1 | L11: La columna «% de las ventas» tiene que sumar 100 %. Si no suma, todo lo de abajo está mal.
A13: EL PUNTO MUERTO, CANAL A CANAL
A14: Costes fijos del año de crucero (€) | B14: =IFERROR('PyG 3 Años'!$C$31,"") -> 122546.03
A15: Costes fijos mensuales (€) | B15: =IFERROR(B14/12,"") -> 10212.169
A16: Margen de contribución medio ponderado (%) | B16: =IFERROR(H11,"") -> 0.6413
A17: Margen bruto objetivo de la regla única (%) | B17: =IFERROR('0. Supuestos'!$B$26,"") -> 0.7
A18: Lo que se llevan servir, cobrar y las comisiones (%) | B18: =IFERROR(B17-B16,"") -> 0.0587 | L18: La diferencia entre el margen bruto objetivo de la carta y el margen de contribución real. No es un error de ninguno de los dos: es lo que cuesta poner el bombón en manos del cliente por cada vía.
A19: Punto muerto mensual CON todos los canales (€) | B19: =IFERROR(IF(B16<=0,"",B15/B16),"") -> 15924.169
A20: Punto muerto mensual SIN el canal B2B (€) | B20: =IFERROR(IF(OR(I11-I8<=0,(J11-J8)/(I11-I8)<=0),"",B15/((J11-J8)/(I11-I8))),"") -> 15357.943
A21: Diferencia (€/mes) | B21: =IFERROR(IF(OR(B20="",B19=""),"",B20-B19),"") -> -566.22555 | L21: Si sale NEGATIVA, quitar el B2B te BAJA el punto muerto: ese canal estaba tirando del margen medio hacia abajo, y lo que aporta es volumen, no rentabilidad. Ojo, eso no dice que haya que cerrarlo: dice qué tienes que exigirle. Y en chocolate el B2B tiene un coste extra que no está en esta fila: es el que te puede meter en el art. 3 del RD 1021/2022.
A22: Canal que sostiene el negocio | B22: =IFERROR(IF(COUNT(J6:J10)=0,"",INDEX($A$6:$A$10,MATCH(MAX($J$6:$J$10),$J$6:$J$10,0))),"") -> Mostrador
A23: Aporte de ese canal al margen de contribución (%) | B23: =IFERROR(IF(J11="","",MAX($J$6:$J$10)/J11),"") -> 0.67675035 | L23: Es el canal que paga el alquiler. Todo lo que pongas en marcha en los otros cuatro se financia con éste, así que lo primero que hay que proteger es su margen.
A25: LA NOTA DEL EPÍGRAFE 644.5: QUÉ CANALES TE SACAN DE ELLA
A26: Canales que hay que consultar con tu asesor | B26: =IFERROR(COUNTIF(K6:K10,"No lo sé"),"") -> 3 | L26: La nota del epígrafe 644.5 faculta para «la fabricación de bombones y caramelos en el propio establecimiento, siempre que su comercialización se realice en las propias dependencias de venta». El mostrador y el taller no la rompen; el online, el B2B y el corporativo comercializan FUERA de tus dependencias, y ésa es la pregunta. Esta hoja NO emite un epígrafe de IAE por canal, y no es un olvido: ninguna fuente lo da.
A27: La pregunta, redactada para el asesor | B27: Mi epígrafe es el 644.5, cuya nota permite fabricar bombones «siempre que su comercialización se realice en las propias dependencias de venta». Voy a vender además por este canal: [CANAL]. Con la Regla 4.a.1 del RDLeg 1175/1990 delante -una cuota faculta exclusivamente para su actividad-, ¿ese canal me obliga a dar otra alta, y cual? Y si la respuesta es el epígrafe industrial 421.1, ¿que consecuencias tiene que el Anexo de la Ley 12/2012 liste el 644.5 y no el 421.1?
A29: EL AVISO DEL ART. 3: CUÁNDO EL B2B TE CAMBIA DE RÉGIMEN
A30: Peso del canal B2B sobre las ventas, en euros (referencia; NO es el test del art. 3) | B30: =IFERROR(B8,"") -> 0.11
A31: La vía a) del art. 3.2 se mide en VOLUMEN (kg), no en euros, y sólo cuenta a los minoristas de distinta titularidad -no toda hostelería ni el regalo corporativo-. Se resuelve en «checklist-legal-licencias-y-cacao.xlsx», hoja «Suministro a Otros Minoristas».
A32: La vía a) del art. 3.2 se resuelve en checklist-legal-licencias-y-cacao.xlsx!Suministro a Otros Minoristas!B26
A33: El art. 3 del RD 1021/2022 sólo se activa si suministras a establecimientos minoristas de DISTINTA titularidad. Si entras, hay que presentar declaración responsable y llevar registro de destinatarios, cantidades y fechas. Este aviso mira sólo el porcentaje EN EUROS del B2B, como referencia de negocio; el árbol legal completo -con el test en volumen- está en el libro «checklist-legal-licencias-y-cacao».
A34: Días medios de cobro ponderados | B34: =IFERROR('0. Supuestos'!$B$58,"") -> 7.65 | L34: Es el número que usa la hoja de Tesorería para desfasar los cobros. Sube solo en cuanto crecen el B2B y el corporativo, y ése es su coste oculto: no es sólo que dejen menos margen, es que lo dejan más tarde -y el corporativo lo deja en enero, no en diciembre-.
A36: EL ENVÍO REFRIGERADO: EL NÚMERO QUE DECIDE SI EL CANAL ONLINE EXISTE
A37: Pedido medio del canal online (€ sin IVA) | B37: 35 | L37: SUPUESTO, y es el pedido MÍNIMO del caso. Si tu pedido medio baja de aquí, el envío se come el canal: no es que gane menos, es que trabajas para el transportista.
A38: Coste del envío sobre el pedido medio (%) | B38: =IFERROR(IF(B37<=0,"",F7/B37),"") -> 0.24285714
A39: Margen de contribución del online DESPUÉS del envío (%) | B39: =IFERROR(IF(B38="","",H7-B38),"") -> 0.29714286
A40: VEREDICTO DEL CANAL ONLINE | B40: =IFERROR(IF(B39="","",IF(B39<=0,"El envío se come el canal: sube el pedido mínimo o cierra el online",IF(B39<B16,"Aguanta, pero deja menos que el mostrador: úsalo para llegar donde no llegas, no para sustituirlo","Aguanta bien"))),"") -> Aguanta, pero deja menos que el mostrador: úsalo para llegar donde no llegas, no para sustituirlo | L40: Y hay una cosa que no se ve en el margen: los envíos de este caso PARAN de junio a septiembre. El chocolate no viaja en verano sin cadena de frío, y eso no es un problema de coste, es de calendario.
A42: Los porcentajes de esta hoja son SUPUESTOS: no existe reparto publicado por canal de una bombonería española. Son una hipótesis de trabajo coherente con el caso -mostrador mayoritario, online pequeño y parado en verano, B2B y corporativo con cobro aplazado y taller pequeño pero con el mejor margen-, y lo primero que hay que sustituir por tus propios datos del TPV en cuanto tengas tres meses.
A44: Listas de validación (no las borres: las usan los desplegables)
A45: Respuesta del 644.5
A46: Sí
A47: No
A48: No lo sé

Sheet Talleres y Regalo Corporativo
A1: Talleres y Regalo Corporativo: Las Dos Líneas que No Dependen del Cacao
A2: AI Chef Pro · aichef.pro — Cómo Montar una Chocolatería
A3: El taller es la única línea que funciona en agosto y a la que no le afecta el precio de la cobertura. Y el regalo corporativo es el que llena diciembre, pero cobra en enero. Esta hoja dice cuántos asistentes necesita un taller para cubrirse y qué deja una hora de sala dando taller frente a la misma hora vendiendo.
A5: EL TALLER: CUÁNTOS ASISTENTES HACEN FALTA PARA QUE SE PAGUE SOLO
A6: Precio por persona, mínimo del rango publicado | B6: 25 | C6: €/persona | D6: Dato de mercado: los talleres y catas de bombonería se mueven entre 25 y 45 € por persona, con un mínimo habitual de 6 personas y una duración de 90 a 150 minutos. Se publica el RANGO, y el libro trabaja con el mínimo.
A7: Precio por persona, máximo del rango publicado | B7: 45 | C7: €/persona | D7: El techo del mismo rango. Cobrar el techo exige otra cosa: cata guiada, orígenes, material para llevarse a casa.
A8: Precio por persona que vas a cobrar | B8: 25 | C8: €/persona | D8: Sembrado con el MÍNIMO a propósito: si el taller se paga solo al precio más bajo del rango, se paga solo. Súbelo cuando tengas la sala llena dos sábados seguidos.
A9: Aforo del taller | B9: 12 | C9: personas | D9: SUPUESTO: doce personas es lo que cabe alrededor de una mesa de mármol sin que nadie tenga que mirar por encima de otro. Tu aforo lo manda tu sala, no este número.
A10: Mínimo de personas para hacerlo | B10: 6 | C10: personas | D10: El mínimo habitual del mercado. Por debajo de este número, el taller se pospone: no es tacañería, es que el docente cuesta lo mismo con tres que con doce.
A11: Duración mínima publicada | B11: 90 | C11: minutos | D11: Rango publicado de mercado.
A12: Duración máxima publicada | B12: 150 | C12: minutos | D12: Rango publicado de mercado.
A13: Horas de docente por taller | B13: 3 | C13: horas | D13: SUPUESTO: la sesión más la preparación y la recogida. El error clásico es contar sólo los 90 minutos de cara al público: montar y desmontar un taller de templado se lleva casi otro tanto.
A14: Coste de una hora de obrador (€) | B14: =IFERROR('Personal'!$B$44,"") -> 18.491659 | C14: €/hora | D14: Sale de la hoja de Personal: coste empresa del área de obrador entre sus horas productivas. El docente no es gratis aunque seas tú: tu hora dando taller es una hora que no estás templando.
A15: Coste del docente por taller (€) | B15: =IFERROR(B13*B14,"") -> 55.474977 | C15: €/taller
A16: Coste de materia y material por asistente (€) | B16: 3.5 | C16: €/persona | D16: SUPUESTO: cobertura para templar, moldes de un uso, caja para llevarse lo que ha hecho y delantal. Es lo que convierte un taller en un recuerdo, y por eso no se recorta.
A17: Coste de servir el canal de talleres (%) | B17: =IFERROR('Canales y Punto Muerto'!D10,"") -> 0.05 | D17: Sale de la hoja de canales: reservas, pasarela de cobro y las horas de tienda que se van en atender la inscripción.
A18: Ingreso neto por asistente (€) | B18: =IFERROR(B8*(1-B17),"") -> 23.75 | C18: €/persona
A19: ASISTENTES NECESARIOS PARA CUBRIR EL PUNTO MUERTO DEL TALLER | B19: =IFERROR(IF(B18<=0,"",B15/B18),"") -> 2.3357885 | C19: personas | D19: Sólo contra el coste del DOCENTE, que es el criterio más conservador y el que se puede defender: es el coste que existe aunque no venga nadie. Es el número que decide si abres el calendario de talleres.
A20: Asistentes necesarios contando también la materia y el material | B20: =IFERROR(IF(B18-B16<=0,"",B15/(B18-B16)),"") -> 2.739505 | C20: personas | D20: El mismo cálculo con el material dentro. La diferencia entre los dos números es lo que te puedes permitir regalar en una primera edición para llenar la sala.
A21: LECTURA FRENTE AL MÍNIMO DE PERSONAS | B21: =IFERROR(IF(B20="","",IF(B20<=B10,"El mínimo habitual de mercado ya cubre el taller: el resto es margen","Con el mínimo de mercado NO se cubre: sube el precio o baja el coste de docente")),"") -> El mínimo habitual de mercado ya cubre el taller: el resto es margen
A23: LA PREGUNTA DE VERDAD: €/HORA DE SALA DANDO TALLER FRENTE A €/HORA VENDIENDO
A24: Horas que la sala está ocupada por el taller | B24: =IFERROR(B13,"") -> 3 | C24: horas | D24: Las mismas del docente: mientras montas, das y recoges, esa sala no vende. Si tu taller es fuera del horario de tienda, pon aquí las horas que de verdad solapan.
A25: Ingreso del taller a aforo completo (€) | B25: =IFERROR(B9*B8,"") -> 300 | C25: €/taller
A26: Margen por hora de sala DANDO TALLER (€/hora) | B26: =IFERROR(IF(B24<=0,"",(B25-B16*B9-B15)/B24),"") -> 67.508341 | C26: €/hora
A27: Ventas de mostrador del año de crucero (€) | B27: =IFERROR('Canales y Punto Muerto'!I6,"") -> 123434.52 | C27: €/año
A28: Horas de tienda abierta al año | B28: 3040 | C28: horas/año | D28: SUPUESTO: los días de apertura del año por diez horas de persiana levantada. Cámbialo por tu horario real, que es lo que hace que esta comparación signifique algo.
A29: Margen por hora de sala VENDIENDO (€/hora) | B29: =IFERROR(IF(B28<=0,"",B27*'Canales y Punto Muerto'!H6/B28),"") -> 28.422423 | C29: €/hora | D29: Margen de contribución del mostrador repartido entre las horas que la tienda está abierta. Es la comparación honesta: margen contra margen, hora contra hora.
A30: Diferencia a favor del taller (€/hora) | B30: =IFERROR(IF(OR(B26="",B29=""),"",B26-B29),"") -> 39.085918 | C30: €/hora
A31: VEREDICTO DE LA HORA DE SALA | B31: =IFERROR(IF(B30="","",IF(B30>0,"La hora de taller deja más que la hora vendiendo: el calendario de talleres se defiende solo","La hora de taller deja MENOS que vender: hazlos fuera del horario de tienda o en agosto, cuando esa hora no vende")),"") -> La hora de taller deja más que la hora vendiendo: el calendario de talleres se defiende solo
A33: CUÁNTOS TALLERES HACEN EL 6 % DE VENTAS QUE DICE LA HOJA DE CANALES
A34: Talleres al mes | B34: 4 | C34: talleres/mes | D34: SUPUESTO: uno por semana, normalmente en sábado. En agosto es la única línea que sigue funcionando.
A35: Asistentes medios por taller | B35: 8 | C35: personas | D35: SUPUESTO: dos tercios del aforo. Llenar los doce todas las semanas es una previsión, no un supuesto.
A36: Ingresos de talleres al año (€) | B36: =IFERROR(B34*12*B35*B8,"") -> 9600 | C36: €/año
A37: Ventas del canal «talleres» según la hoja de canales (€) | B37: =IFERROR('Canales y Punto Muerto'!I10,"") -> 11945.277 | C37: €/año
A38: Diferencia entre las dos (€) | B38: =IFERROR(IF(OR(B36="",B37=""),"",B36-B37),"") -> -2345.2765 | C38: €/año
A39: LECTURA | B39: =IFERROR(IF(B38="","",IF(ABS(B38)<B37,"Cuadra: el calendario de talleres sostiene el peso que le da la hoja de canales","No cuadra: o haces más talleres, o llenas más, o baja el peso del canal en la hoja de canales")),"") -> Cuadra: el calendario de talleres sostiene el peso que le da la hoja de canales | D39: Es un CUADRE interno de este libro, no un cruce con otro fichero: sirve para que el 6 % de ventas que le da la hoja de canales al taller no sea un número puesto a ojo, sino algo que cabe en un calendario de verdad.
A41: EL IVA DEL TALLER
A42: Tipo de IVA que vas a aplicar al taller | B42: =IFERROR('0. Supuestos'!$B$17,"") -> Pregúntaselo a tu asesor | D42: Viene de «0. Supuestos», y VA SIN CIFRA a propósito.
A43: Lo que SÍ está cerrado: un taller de bombonería NO está exento de IVA. El art. 20.Uno.10.º de la Ley del IVA excluye de la exención de la enseñanza las clases «para cuya realización sea necesario darse de alta en las tarifas de actividades empresariales o artísticas del IAE», que es exactamente tu caso. Lo que NO está cerrado es el TIPO: el art. 91 no nombra los talleres, y esta guía no publica una cifra que no pueda sostener. Y ojo, que son dos preguntas distintas: el taller no rompe la nota del epígrafe 644.5 -no comercializas bombones fuera de tus dependencias-, pero sí abre la pregunta de si hay que darse de alta por esta actividad, que es un alta distinta.
A45: EL REGALO CORPORATIVO: LLENA DICIEMBRE Y COBRA EN ENERO
A46: Pedido mínimo que aceptas (€ sin IVA) | B46: 250 | C46: €/pedido | D46: SUPUESTO. Por debajo de un mínimo, un pedido de empresa cuesta más en muestras, llamadas y personalización de lo que deja.
A47: Días de cobro del canal corporativo | B47: 30 | C47: días | D47: SUPUESTO: 30 días. Lo que significa de verdad es que la caja de diciembre entra en enero, justo después de haber pagado la cobertura en octubre y las extras en diciembre.
A48: Plazo mínimo desde que aprueban la muestra | B48: 14 | C48: días | D48: DATO DE MERCADO VERIFICADO: catorce días desde la aprobación de la muestra, con mínimos de fabricación de 10 a 25 cajas. Es lo que decide si aceptas un pedido de empresa el 15 de diciembre: la respuesta casi siempre es que no.
A49: Mínimo de fabricación, suelo del rango | B49: 10 | C49: cajas | D49: Rango publicado de mercado.
A50: Mínimo de fabricación, techo del rango | B50: 25 | C50: cajas | D50: Rango publicado de mercado.
A51: Pedidos corporativos al año | B51: 40 | C51: pedidos/año | D51: SUPUESTO. La mayoría se concentran en noviembre y diciembre, y por eso la agenda se cierra en octubre.
A52: Facturación del canal corporativo (€/año) | B52: =IFERROR(B51*B46,"") -> 10000 | C52: €/año
A53: Margen de contribución que deja (€/año) | B53: =IFERROR(B52*'Canales y Punto Muerto'!H9,"") -> 5200 | C53: €/año
A54: Caja inmovilizada por el aplazamiento (€) | B54: =IFERROR(B52*B47/365,"") -> 821.91781 | C54: € | D54: Lo que tienes prestado a tus clientes de empresa en todo momento. No es un gasto, pero es dinero que no está en tu cuenta, y en diciembre es justo cuando hace falta.
A55: Lo que cuesta financiar esa caja (€/año) | B55: =IFERROR(B54*'0. Supuestos'!$B$42,"") -> 50.958904 | C55: €/año | D55: Al mismo tipo que tu préstamo. Es pequeño comparado con el margen del canal, y aun así conviene verlo escrito: financiar a un cliente no es gratis.
A56: FECHA LÍMITE PARA ACEPTAR UN PEDIDO CORPORATIVO | B56: =IFERROR(IF('Tesorería 12 meses'!$B$45="","",'Tesorería 12 meses'!$B$45-B48),"") -> 46657 | D56: La fecha límite de cierre de pedidos de Navidad que calcula la hoja de Tesorería, MENOS los catorce días que van desde que el cliente aprueba la muestra hasta que puedes servir. Los dos plazos se suman, y por eso la agenda corporativa se cierra antes que la de particulares.
A57: LECTURA DEL CANAL CORPORATIVO | B57: =IFERROR(IF(B56="","",IF(MONTH(B56)<=10,"Tienes que cerrar la agenda corporativa en octubre o antes: septiembre es el mes de llamar","Llegas a noviembre, pero vas justo: una muestra rechazada te deja sin el pedido")),"") -> Tienes que cerrar la agenda corporativa en octubre o antes: septiembre es el mes de llamar
A59: Las dos líneas de esta hoja tienen algo en común y conviene decirlo: NO dependen del precio del cacao. El taller vende tiempo y experiencia, y el corporativo vende un encargo cerrado con precio pactado. Por eso son las dos que sostienen un año en el que la cobertura suba un 40 %, y por eso el taller es lo único que funciona en agosto, cuando el obrador está parado y la tienda vive del turista. Lo que no son es un plan B: son dos canales con su propio coste de personal y su propio calendario.
