Workbook

Sheet Calculator
A1: WEDDING VENUE PRICING & QUOTE CALCULATOR
A2: Type only in the GREEN cells: everything else is calculated. Amounts exclude sales tax unless the row says otherwise. The default values are Kit estimates: replace them with your own venue's.
A4: EVENT DETAILS | B4: Value | C4: Notes
A5: Client | B5: Couple | C5: Couple or Corporate: they change the payment schedule and the cancellation tiers (table at the end). A corporate client gets the quote "plus sales tax"; a couple, with sales tax included.
A6: Event type | B6: Wedding | C6: Wedding, corporate event (meeting, dinner, holiday party), private celebration (shower, milestone birthday, rehearsal dinner) or micro wedding / elopement. It sets the venue rate, the caterer's food & beverage per guest and the direct cost from the tables at the end.
A7: Event date | B7: 46669 | C7: Type the full date (mm/dd/yyyy). It sets the season and the type of day from the month and weekday tables.
A8: Expected guests | B8: 130 | C8: Whole number of guests. The quote uses the higher of this number and the season minimum.
A9: Ceremonies on site (no.) | B9: 1 | C9: At the price in the extra services table.
A10: Additional hours of venue use (no.) | B10: 2 | C10: Hours beyond the base rental window in your agreement.
A11: Premium decor & lighting packages (no.) | B11: 1 | C11: Decor, furniture and lighting beyond the standard setup.
A12: Rehearsals the day before (no.) | B12: 0 | C12: 0 if the couple does not book a rehearsal at the venue.
A13: Venue staff hours on the event (coordinator and attendants) | B13: 16 | C13: Kit estimate: type your team's real hours (servers, bartenders and kitchen staff belong to the caterer).
A14: Hourly wage of venue staff | B14: 18 | C14: Kit estimate. At least your state or local minimum wage.
A15: Employer payroll taxes (% of wages) | B15: 0.1 | C15: FICA 7.65% plus federal and state unemployment taxes, about 10% (Kit estimate): check with your payroll provider.
A16: Direct cost of extra services (% of their price) | B16: 0.4 | C16: Kit estimate: what it costs you to deliver the ceremony, the decor package, the extra hours and the rehearsal.
A17: Rounding of the venue rental fee (multiple, in dollars) | B17: 50 | C17: The venue rental fee is rounded to the nearest multiple of this amount.
A18: Caterer commission (% of the caterer's food & beverage sales) | B18: 0.1 | C18: An editable ASSUMPTION, not a market figure: negotiate it with your caterer. For reference only: the caterer pays it to the venue, not the client.
... A20: Sales tax on the caterer's food & beverage (reference only) | B20: 0.08 | C20: The caterer bills the menu and the bar with its own sales tax, service charge and gratuity; they are not venue revenue.
A22: CALCULATION | B22: Value | C22: Notes
A23: Season of the date (from the month table) | B23: =INDEX('Calculator'!$B$82:$B$93,MONTH($B$7)) -> Peak | C23: Looks up the month of the date in the table at the end.
A24: Type of day (from the weekday table) | B24: =INDEX('Calculator'!$B$96:$B$102,WEEKDAY($B$7)) -> Saturday | C24: Looks up the weekday of the date in the table at the end.
A25: Season adjustment (premium + / discount −) | B25: =INDEX('Calculator'!$B$72:$B$74,MATCH($B$23,'Calculator'!$A$72:$A$74,0)) -> 0.15 | C25: From the season table.
A26: Day adjustment (premium + / discount −) | B26: =INDEX('Calculator'!$B$77:$B$79,MATCH($B$24,'Calculator'!$A$77:$A$79,0)) -> 0 | C26: From the day table.
A27: Venue rate for the event type (Saturday, shoulder season) | B27: =INDEX('Calculator'!$B$66:$B$69,MATCH($B$6,'Calculator'!$A$66:$A$69,0)) -> 8000 | C27: From the event type table.
A28: VENUE RENTAL FEE EXCL. SALES TAX | B28: =ROUND($B$27*(1+$B$25)*(1+$B$26)/$B$17,0)*$B$17 -> 9200 | C28: Rate × (1 + season adjustment) × (1 + day adjustment), rounded to the chosen multiple.
A29: Season minimum (guests) | B29: =INDEX('Calculator'!$C$72:$C$74,MATCH($B$23,'Calculator'!$A$72:$A$74,0)) -> 100 | C29: From the season table.
A30: Guaranteed guest count | B30: =MAX($B$8,$B$29) -> 130 | C30: The higher of the expected guests and the season minimum.
A31: Minimum check | B31: =IF($B$8<$B$29,"Below the minimum: the quote uses the season minimum","Meets the minimum") -> Meets the minimum
A32: Ceremonies | B32: =$B$9*'Calculator'!$B$105 -> 750 | C32: No. × price from the extra services table.
A33: Additional hours | B33: =$B$10*'Calculator'!$B$106 -> 1000
A34: Premium decor & lighting | B34: =$B$11*'Calculator'!$B$107 -> 800
A35: Rehearsals | B35: =$B$12*'Calculator'!$B$108 -> 0
A36: Extra services excl. sales tax | B36: =$B$32+$B$33+$B$34+$B$35 -> 2550
A37: Taxable amount (venue rental + services) | B37: =$B$28+$B$36 -> 11750
A38: Sales tax on venue charges | B38: =$B$37*$B$19 -> 940
A39: VENUE TOTAL (incl. sales tax) | B39: =$B$37+$B$38 -> 12690 | C39: It does not include food or the bar: the exclusive caterer bills them separately.
A40: Amount you quote (Couple: incl. sales tax · Corporate: plus sales tax) | B40: =IF($B$5="Couple",$B$39,$B$37) -> 12690 | C40: A corporate client gets the quote excl. sales tax ("plus sales tax"; if it is tax-exempt, ask for its exemption certificate); a couple, with sales tax included.
A41: Venue rental & services per guaranteed guest (excl. sales tax) | B41: =$B$37/$B$30 -> 90.384615 | C41: To compare with other venues.
A42: Payment 1: retainer | B42: =$B$39*INDEX('Calculator'!$B$111:$C$111,MATCH($B$5,'Calculator'!$B$110:$C$110,0)) -> 3172.5 | C42: At signing.
A43: Payment 2: second installment | B43: =$B$39*INDEX('Calculator'!$B$112:$C$112,MATCH($B$5,'Calculator'!$B$110:$C$110,0)) -> 4441.5
A44: Second installment due by | B44: =$B$7-INDEX('Calculator'!$B$114:$C$114,MATCH($B$5,'Calculator'!$B$110:$C$110,0)) -> 46489 | C44: Event date minus the days in the table.
A45: Payment 3: final balance | B45: =$B$39*INDEX('Calculator'!$B$113:$C$113,MATCH($B$5,'Calculator'!$B$110:$C$110,0)) -> 5076
A46: Final balance due by | B46: =$B$7-INDEX('Calculator'!$B$115:$C$115,MATCH($B$5,'Calculator'!$B$110:$C$110,0)) -> 46639 | C46: Event date minus the days in the table.
A47: Caterer's food & beverage excl. sales tax (estimate, guaranteed guests) | B47: =INDEX('Calculator'!$C$66:$C$69,MATCH($B$6,'Calculator'!$A$66:$A$69,0))*$B$30 -> 14300 | C47: FOR REFERENCE. Food & beverage per guest from the event type table × guaranteed guests. It is not venue revenue.
A48: ESTIMATED CATERER COMMISSION (for reference) | B48: =$B$47*$B$18 -> 1430 | C48: The exclusive caterer pays it to the venue, not the client. It is an assumption: negotiate it.
A49: Caterer's food & beverage incl. sales tax (reference, billed by the caterer) | B49: =$B$47*(1+$B$20) -> 15444 | C49: So the client sees the full cost; the caterer's service charge and gratuity come on top.
A50: Full reference budget for the client (venue incl. sales tax + food & beverage) | B50: =$B$39+$B$49 -> 28134 | C50: What the client pays the venue plus what it pays the caterer.
A51: Direct event cost: cleaning, restrooms, generator fuel, parking and security | B51: =INDEX('Calculator'!$D$66:$D$69,MATCH($B$6,'Calculator'!$A$66:$A$69,0)) -> 1000 | C51: From the event type table (Kit estimate).
A52: Venue staff cost (wages + payroll taxes) | B52: =$B$13*$B$14*(1+$B$15) -> 316.8
A53: Direct cost of the extra services | B53: =$B$36*$B$16 -> 1020
A54: Total direct cost of the event | B54: =$B$51+$B$52+$B$53 -> 2336.8
A55: Venue revenue from the event (excl. sales tax, commission included) | B55: =$B$37+$B$48 -> 13180 | C55: Venue rental + services + estimated commission.
A56: Event contribution for the venue ($) | B56: =$B$55-$B$54 -> 10843.2 | C56: Before rent, salaried staff, utilities, insurance and the overhead in the financial plan.
A57: Event contribution margin (calculated) | B57: =IF($B$55=0,0,$B$56/$B$55) -> 0.82270106 | C57: It comes from the costs; it is never typed in.
A58: Event contribution without the commission ($) | B58: =$B$37-$B$54 -> 9413.2 | C58: What the event would leave if the caterer paid no commission.
A59: Amount kept if the client cancels: tier 1 | B59: =$B$39*INDEX('Calculator'!$B$116:$C$116,MATCH($B$5,'Calculator'!$B$110:$C$110,0)) -> 1269 | C59: Furthest from the event (see the tier table). If the venue cancels: it refunds everything it collected.
A60: Amount kept if the client cancels: tier 2 | B60: =$B$39*INDEX('Calculator'!$B$117:$C$117,MATCH($B$5,'Calculator'!$B$110:$C$110,0)) -> 3172.5
A61: Amount kept if the client cancels: tier 3 | B61: =$B$39*INDEX('Calculator'!$B$118:$C$118,MATCH($B$5,'Calculator'!$B$110:$C$110,0)) -> 6345
A62: Amount kept if the client cancels: tier 4 | B62: =$B$39*INDEX('Calculator'!$B$119:$C$119,MATCH($B$5,'Calculator'!$B$110:$C$110,0)) -> 9517.5
A63: Amount kept if the client cancels: tier 5 | B63: =$B$39*INDEX('Calculator'!$B$120:$C$120,MATCH($B$5,'Calculator'!$B$110:$C$110,0)) -> 12690 | C63: Last tier, up to the event day. The agreement credits back what you recover by rebooking the date and the costs you save by not holding the event.
A65: EVENT TYPE → VENUE RATE, CATERER'S FOOD & BEVERAGE AND DIRECT COST (excl. sales tax) | B65: Venue rate (Saturday, shoulder season) | C65: Caterer's food & beverage per guest | D65: Direct event cost
A66: Wedding | B66: 8000 | C66: 110 | D66: 1000 | E66: Kit estimates (published barn venue rate cards range roughly $3,500-$10,000 for a peak Saturday: get local quotes). Direct cost: cleaning, restrooms, generator fuel, parking attendants and security.
A67: Corporate event | B67: 3500 | C67: 50 | D67: 500
A68: Private celebration | B68: 4000 | C68: 55 | D68: 500
A69: Micro wedding / elopement | B69: 2000 | C69: 80 | D69: 300
A71: SEASON → RATE ADJUSTMENT AND GUEST MINIMUM | B71: Adjustment (+ premium / − discount) | C71: Guest minimum
A72: Peak | B72: 0.15 | C72: 100 | D72: Kit example. Peak season carries a premium and off-peak a discount; the event type rates are for a Saturday in shoulder season.
A73: Shoulder | B73: 0 | C73: 75
A74: Off-peak | B74: -0.2 | C74: 50
A76: TYPE OF DAY → RATE ADJUSTMENT | B76: Adjustment (+ premium / − discount)
A77: Saturday | B77: 0 | C77: Kit example: venue rate cards usually discount Fridays, Sundays and weekdays. The season and day adjustments multiply.
A78: Friday or Sunday | B78: -0.15
A79: Weekday | B79: -0.3
A81: MONTH → SEASON | B81: Season
A82: January | B82: Off-peak | C82: Fall is the busiest wedding season in the US, with October, September and June as the peaks (Kit pattern). Adjust the months to your area.
A83: February | B83: Off-peak
A84: March | B84: Off-peak
A85: April | B85: Shoulder
A86: May | B86: Peak
A87: June | B87: Peak
A88: July | B88: Shoulder
A89: August | B89: Shoulder
A90: September | B90: Peak
A91: October | B91: Peak
A92: November | B92: Shoulder
A93: December | B93: Off-peak
A95: WEEKDAY → TYPE OF DAY | B95: Type of day
... A104: VENUE EXTRA SERVICES (price excl. sales tax) | B104: Price
A105: Ceremony on site (per ceremony) | B105: 750 | C105: Kit example prices: type your own.
A106: Additional hour of venue use (per hour) | B106: 500
A107: Premium decor & lighting package (per event) | B107: 800
A108: Rehearsal the day before (per rehearsal) | B108: 400
A110: POLICY BY CLIENT | B110: Couple | C110: Corporate
A111: Payment 1: retainer to book the date (% of the total) | B111: 0.25 | C111: 0.3 | D111: At signing. The retainer is applied to the price; what you keep if the client cancels is set only by the cancellation schedule below.
A112: Payment 2: second installment (% of the total) | B112: 0.35 | C112: 0.3 | D112: Due on the date in the next row.
A113: Payment 3: final balance before the event (% of the total) | B113: 0.4 | C113: 0.4 | D113: The rest, before the event. Issue a receipt for every payment, the retainer included.
A114: Second installment: days before the event | B114: 180 | C114: 60 | D114: Couples, about six months before; corporate clients, two months. If they book later, both are due together.
A115: Final balance: days before the event | B115: 30 | C115: 15 | D115: Couples, 30 days before; corporate clients, 15.
A116: Cancellation tier 1: what you keep (% of the total) | B116: 0.1 | C116: 0.05 | D116: Furthest from the event. Never more than the retainer you collected.
A117: Cancellation tier 2: what you keep (% of the total) | B117: 0.25 | C117: 0.15 | D117: Rises as the event gets closer.
...

Sheet Examples
A1: 3 EXAMPLE QUOTES — with the same formulas as the "Calculator" tab
A2: Kit estimates to show the calculation, not market prices: change the inputs in "Calculator" to quote your own events. The tables (rates, seasons, days, extras, payments and cancellation) are at the end of that tab and also drive these examples.
A4: EVENT DETAILS | B4: Saturday wedding in peak season | C4: Friday wedding in shoulder season | D4: Weekday corporate event
A5: Client | B5: Couple | C5: Couple | D5: Corporate
A6: Event type | B6: Wedding | C6: Wedding | D6: Corporate event
A7: Event date | B7: 46669 | C7: 46584 | D7: 46498
A8: Expected guests | B8: 130 | C8: 100 | D8: 50
A9: Ceremonies on site (no.) | B9: 1 | C9: 1 | D9: 0
A10: Additional hours of venue use (no.) | B10: 2 | C10: 0 | D10: 1
A11: Premium decor & lighting packages (no.) | B11: 1 | C11: 0 | D11: 0
A12: Rehearsals the day before (no.) | B12: 0 | C12: 1 | D12: 0
A13: Venue staff hours on the event (coordinator and attendants) | B13: 16 | C13: 14 | D13: 10
A14: Hourly wage of venue staff | B14: 18 | C14: 18 | D14: 18
A15: Employer payroll taxes (% of wages) | B15: 0.1 | C15: 0.1 | D15: 0.1
A16: Direct cost of extra services (% of their price) | B16: 0.4 | C16: 0.4 | D16: 0.4
A17: Rounding of the venue rental fee (multiple, in dollars) | B17: 50 | C17: 50 | D17: 50
A18: Caterer commission (% of the caterer's food & beverage sales) | B18: 0.1 | C18: 0.1 | D18: 0.1
... A20: Sales tax on the caterer's food & beverage (reference only) | B20: 0.08 | C20: 0.08 | D20: 0.08
A22: RESULT | B22: Saturday wedding in peak season | C22: Friday wedding in shoulder season | D22: Weekday corporate event
A23: Season of the date (from the month table) | B23: =INDEX('Calculator'!$B$82:$B$93,MONTH($B$7)) -> Peak | C23: =INDEX('Calculator'!$B$82:$B$93,MONTH($C$7)) -> Shoulder | D23: =INDEX('Calculator'!$B$82:$B$93,MONTH($D$7)) -> Shoulder
A24: Type of day (from the weekday table) | B24: =INDEX('Calculator'!$B$96:$B$102,WEEKDAY($B$7)) -> Saturday | C24: =INDEX('Calculator'!$B$96:$B$102,WEEKDAY($C$7)) -> Friday or Sunday | D24: =INDEX('Calculator'!$B$96:$B$102,WEEKDAY($D$7)) -> Weekday
A25: Season adjustment (premium + / discount −) | B25: =INDEX('Calculator'!$B$72:$B$74,MATCH($B$23,'Calculator'!$A$72:$A$74,0)) -> 0.15 | C25: =INDEX('Calculator'!$B$72:$B$74,MATCH($C$23,'Calculator'!$A$72:$A$74,0)) -> 0 | D25: =INDEX('Calculator'!$B$72:$B$74,MATCH($D$23,'Calculator'!$A$72:$A$74,0)) -> 0
A26: Day adjustment (premium + / discount −) | B26: =INDEX('Calculator'!$B$77:$B$79,MATCH($B$24,'Calculator'!$A$77:$A$79,0)) -> 0 | C26: =INDEX('Calculator'!$B$77:$B$79,MATCH($C$24,'Calculator'!$A$77:$A$79,0)) -> -0.15 | D26: =INDEX('Calculator'!$B$77:$B$79,MATCH($D$24,'Calculator'!$A$77:$A$79,0)) -> -0.3
A27: Venue rate for the event type (Saturday, shoulder season) | B27: =INDEX('Calculator'!$B$66:$B$69,MATCH($B$6,'Calculator'!$A$66:$A$69,0)) -> 8000 | C27: =INDEX('Calculator'!$B$66:$B$69,MATCH($C$6,'Calculator'!$A$66:$A$69,0)) -> 8000 | D27: =INDEX('Calculator'!$B$66:$B$69,MATCH($D$6,'Calculator'!$A$66:$A$69,0)) -> 3500
A28: VENUE RENTAL FEE EXCL. SALES TAX | B28: =ROUND($B$27*(1+$B$25)*(1+$B$26)/$B$17,0)*$B$17 -> 9200 | C28: =ROUND($C$27*(1+$C$25)*(1+$C$26)/$C$17,0)*$C$17 -> 6800 | D28: =ROUND($D$27*(1+$D$25)*(1+$D$26)/$D$17,0)*$D$17 -> 2450
A29: Season minimum (guests) | B29: =INDEX('Calculator'!$C$72:$C$74,MATCH($B$23,'Calculator'!$A$72:$A$74,0)) -> 100 | C29: =INDEX('Calculator'!$C$72:$C$74,MATCH($C$23,'Calculator'!$A$72:$A$74,0)) -> 75 | D29: =INDEX('Calculator'!$C$72:$C$74,MATCH($D$23,'Calculator'!$A$72:$A$74,0)) -> 75
A30: Guaranteed guest count | B30: =MAX($B$8,$B$29) -> 130 | C30: =MAX($C$8,$C$29) -> 100 | D30: =MAX($D$8,$D$29) -> 75
A31: Minimum check | B31: =IF($B$8<$B$29,"Below the minimum: the quote uses the season minimum","Meets the minimum") -> Meets the minimum | C31: =IF($C$8<$C$29,"Below the minimum: the quote uses the season minimum","Meets the minimum") -> Meets the minimum | D31: =IF($D$8<$D$29,"Below the minimum: the quote uses the season minimum","Meets the minimum") -> Below the minimum: the quote uses the season minimum
A32: Ceremonies | B32: =$B$9*'Calculator'!$B$105 -> 750 | C32: =$C$9*'Calculator'!$B$105 -> 750 | D32: =$D$9*'Calculator'!$B$105 -> 0
A33: Additional hours | B33: =$B$10*'Calculator'!$B$106 -> 1000 | C33: =$C$10*'Calculator'!$B$106 -> 0 | D33: =$D$10*'Calculator'!$B$106 -> 500
A34: Premium decor & lighting | B34: =$B$11*'Calculator'!$B$107 -> 800 | C34: =$C$11*'Calculator'!$B$107 -> 0 | D34: =$D$11*'Calculator'!$B$107 -> 0
A35: Rehearsals | B35: =$B$12*'Calculator'!$B$108 -> 0 | C35: =$C$12*'Calculator'!$B$108 -> 400 | D35: =$D$12*'Calculator'!$B$108 -> 0
A36: Extra services excl. sales tax | B36: =$B$32+$B$33+$B$34+$B$35 -> 2550 | C36: =$C$32+$C$33+$C$34+$C$35 -> 1150 | D36: =$D$32+$D$33+$D$34+$D$35 -> 500
A37: Taxable amount (venue rental + services) | B37: =$B$28+$B$36 -> 11750 | C37: =$C$28+$C$36 -> 7950 | D37: =$D$28+$D$36 -> 2950
A38: Sales tax on venue charges | B38: =$B$37*$B$19 -> 940 | C38: =$C$37*$C$19 -> 636 | D38: =$D$37*$D$19 -> 236
A39: VENUE TOTAL (incl. sales tax) | B39: =$B$37+$B$38 -> 12690 | C39: =$C$37+$C$38 -> 8586 | D39: =$D$37+$D$38 -> 3186
A40: Amount you quote (Couple: incl. sales tax · Corporate: plus sales tax) | B40: =IF($B$5="Couple",$B$39,$B$37) -> 12690 | C40: =IF($C$5="Couple",$C$39,$C$37) -> 8586 | D40: =IF($D$5="Couple",$D$39,$D$37) -> 2950
A41: Venue rental & services per guaranteed guest (excl. sales tax) | B41: =$B$37/$B$30 -> 90.384615 | C41: =$C$37/$C$30 -> 79.5 | D41: =$D$37/$D$30 -> 39.333333
A42: Payment 1: retainer | B42: =$B$39*INDEX('Calculator'!$B$111:$C$111,MATCH($B$5,'Calculator'!$B$110:$C$110,0)) -> 3172.5 | C42: =$C$39*INDEX('Calculator'!$B$111:$C$111,MATCH($C$5,'Calculator'!$B$110:$C$110,0)) -> 2146.5 | D42: =$D$39*INDEX('Calculator'!$B$111:$C$111,MATCH($D$5,'Calculator'!$B$110:$C$110,0)) -> 955.8
A43: Payment 2: second installment | B43: =$B$39*INDEX('Calculator'!$B$112:$C$112,MATCH($B$5,'Calculator'!$B$110:$C$110,0)) -> 4441.5 | C43: =$C$39*INDEX('Calculator'!$B$112:$C$112,MATCH($C$5,'Calculator'!$B$110:$C$110,0)) -> 3005.1 | D43: =$D$39*INDEX('Calculator'!$B$112:$C$112,MATCH($D$5,'Calculator'!$B$110:$C$110,0)) -> 955.8
A44: Second installment due by | B44: =$B$7-INDEX('Calculator'!$B$114:$C$114,MATCH($B$5,'Calculator'!$B$110:$C$110,0)) -> 46489 | C44: =$C$7-INDEX('Calculator'!$B$114:$C$114,MATCH($C$5,'Calculator'!$B$110:$C$110,0)) -> 46404 | D44: =$D$7-INDEX('Calculator'!$B$114:$C$114,MATCH($D$5,'Calculator'!$B$110:$C$110,0)) -> 46438
A45: Payment 3: final balance | B45: =$B$39*INDEX('Calculator'!$B$113:$C$113,MATCH($B$5,'Calculator'!$B$110:$C$110,0)) -> 5076 | C45: =$C$39*INDEX('Calculator'!$B$113:$C$113,MATCH($C$5,'Calculator'!$B$110:$C$110,0)) -> 3434.4 | D45: =$D$39*INDEX('Calculator'!$B$113:$C$113,MATCH($D$5,'Calculator'!$B$110:$C$110,0)) -> 1274.4
A46: Final balance due by | B46: =$B$7-INDEX('Calculator'!$B$115:$C$115,MATCH($B$5,'Calculator'!$B$110:$C$110,0)) -> 46639 | C46: =$C$7-INDEX('Calculator'!$B$115:$C$115,MATCH($C$5,'Calculator'!$B$110:$C$110,0)) -> 46554 | D46: =$D$7-INDEX('Calculator'!$B$115:$C$115,MATCH($D$5,'Calculator'!$B$110:$C$110,0)) -> 46483
A47: Caterer's food & beverage excl. sales tax (estimate, guaranteed guests) | B47: =INDEX('Calculator'!$C$66:$C$69,MATCH($B$6,'Calculator'!$A$66:$A$69,0))*$B$30 -> 14300 | C47: =INDEX('Calculator'!$C$66:$C$69,MATCH($C$6,'Calculator'!$A$66:$A$69,0))*$C$30 -> 11000 | D47: =INDEX('Calculator'!$C$66:$C$69,MATCH($D$6,'Calculator'!$A$66:$A$69,0))*$D$30 -> 3750
A48: ESTIMATED CATERER COMMISSION (for reference) | B48: =$B$47*$B$18 -> 1430 | C48: =$C$47*$C$18 -> 1100 | D48: =$D$47*$D$18 -> 375
A49: Caterer's food & beverage incl. sales tax (reference, billed by the caterer) | B49: =$B$47*(1+$B$20) -> 15444 | C49: =$C$47*(1+$C$20) -> 11880 | D49: =$D$47*(1+$D$20) -> 4050
A50: Full reference budget for the client (venue incl. sales tax + food & beverage) | B50: =$B$39+$B$49 -> 28134 | C50: =$C$39+$C$49 -> 20466 | D50: =$D$39+$D$49 -> 7236
A51: Direct event cost: cleaning, restrooms, generator fuel, parking and security | B51: =INDEX('Calculator'!$D$66:$D$69,MATCH($B$6,'Calculator'!$A$66:$A$69,0)) -> 1000 | C51: =INDEX('Calculator'!$D$66:$D$69,MATCH($C$6,'Calculator'!$A$66:$A$69,0)) -> 1000 | D51: =INDEX('Calculator'!$D$66:$D$69,MATCH($D$6,'Calculator'!$A$66:$A$69,0)) -> 500
A52: Venue staff cost (wages + payroll taxes) | B52: =$B$13*$B$14*(1+$B$15) -> 316.8 | C52: =$C$13*$C$14*(1+$C$15) -> 277.2 | D52: =$D$13*$D$14*(1+$D$15) -> 198
A53: Direct cost of the extra services | B53: =$B$36*$B$16 -> 1020 | C53: =$C$36*$C$16 -> 460 | D53: =$D$36*$D$16 -> 200
A54: Total direct cost of the event | B54: =$B$51+$B$52+$B$53 -> 2336.8 | C54: =$C$51+$C$52+$C$53 -> 1737.2 | D54: =$D$51+$D$52+$D$53 -> 898
A55: Venue revenue from the event (excl. sales tax, commission included) | B55: =$B$37+$B$48 -> 13180 | C55: =$C$37+$C$48 -> 9050 | D55: =$D$37+$D$48 -> 3325
A56: Event contribution for the venue ($) | B56: =$B$55-$B$54 -> 10843.2 | C56: =$C$55-$C$54 -> 7312.8 | D56: =$D$55-$D$54 -> 2427
A57: Event contribution margin (calculated) | B57: =IF($B$55=0,0,$B$56/$B$55) -> 0.82270106 | C57: =IF($C$55=0,0,$C$56/$C$55) -> 0.8080442 | D57: =IF($D$55=0,0,$D$56/$D$55) -> 0.72992481
A58: Event contribution without the commission ($) | B58: =$B$37-$B$54 -> 9413.2 | C58: =$C$37-$C$54 -> 6212.8 | D58: =$D$37-$D$54 -> 2052
A59: Amount kept if the client cancels: tier 1 | B59: =$B$39*INDEX('Calculator'!$B$116:$C$116,MATCH($B$5,'Calculator'!$B$110:$C$110,0)) -> 1269 | C59: =$C$39*INDEX('Calculator'!$B$116:$C$116,MATCH($C$5,'Calculator'!$B$110:$C$110,0)) -> 858.6 | D59: =$D$39*INDEX('Calculator'!$B$116:$C$116,MATCH($D$5,'Calculator'!$B$110:$C$110,0)) -> 159.3
A60: Amount kept if the client cancels: tier 2 | B60: =$B$39*INDEX('Calculator'!$B$117:$C$117,MATCH($B$5,'Calculator'!$B$110:$C$110,0)) -> 3172.5 | C60: =$C$39*INDEX('Calculator'!$B$117:$C$117,MATCH($C$5,'Calculator'!$B$110:$C$110,0)) -> 2146.5 | D60: =$D$39*INDEX('Calculator'!$B$117:$C$117,MATCH($D$5,'Calculator'!$B$110:$C$110,0)) -> 477.9
A61: Amount kept if the client cancels: tier 3 | B61: =$B$39*INDEX('Calculator'!$B$118:$C$118,MATCH($B$5,'Calculator'!$B$110:$C$110,0)) -> 6345 | C61: =$C$39*INDEX('Calculator'!$B$118:$C$118,MATCH($C$5,'Calculator'!$B$110:$C$110,0)) -> 4293 | D61: =$D$39*INDEX('Calculator'!$B$118:$C$118,MATCH($D$5,'Calculator'!$B$110:$C$110,0)) -> 1115.1
A62: Amount kept if the client cancels: tier 4 | B62: =$B$39*INDEX('Calculator'!$B$119:$C$119,MATCH($B$5,'Calculator'!$B$110:$C$110,0)) -> 9517.5 | C62: =$C$39*INDEX('Calculator'!$B$119:$C$119,MATCH($C$5,'Calculator'!$B$110:$C$110,0)) -> 6439.5 | D62: =$D$39*INDEX('Calculator'!$B$119:$C$119,MATCH($D$5,'Calculator'!$B$110:$C$110,0)) -> 1911.6
A63: Amount kept if the client cancels: tier 5 | B63: =$B$39*INDEX('Calculator'!$B$120:$C$120,MATCH($B$5,'Calculator'!$B$110:$C$110,0)) -> 12690 | C63: =$C$39*INDEX('Calculator'!$B$120:$C$120,MATCH($C$5,'Calculator'!$B$110:$C$110,0)) -> 8586 | D63: =$D$39*INDEX('Calculator'!$B$120:$C$120,MATCH($D$5,'Calculator'!$B$110:$C$110,0)) -> 3186
A65: WHAT EACH EXAMPLE SHOWS
A66: Saturday wedding in peak season | B66: Couple, 130 guests, a Saturday in October: peak season (+15%) and the reference day (Saturday, no adjustment). Ceremony on site, two additional hours and the premium decor package. The couple sees the price with sales tax included. The commission is what the exclusive caterer would pay the venue at 10% (an assumption): the couple does not pay it. Three payments: retainer, second installment six months before and final balance 30 days before.
A67: Friday wedding in shoulder season | B67: Couple, 100 guests, a Friday in July: shoulder season (no adjustment) and Friday (−15%). Ceremony on site and a rehearsal the day before. Same payment schedule and cancellation tiers as the first example: only the venue rate changes.
A68: Weekday corporate event | B68: Corporate client, 50 guests, a Wednesday in April: shoulder season and a weekday (−30%). The 50 guests are below the season minimum (75): the quote uses 75 and the commission is estimated on them. Quoted "plus sales tax" and paid on another schedule (30% to book, 30% two months before and 40% 15 days before) with other cancellation tiers.

Sheet Instructions
A1: HOW TO USE — Wedding Venue Pricing & Quote Calculator
A2: It turns your rate card into a full quote for a specific event: the season and type of day of the date, the guest minimum, extra services, sales tax, total, payment schedule, the estimated caterer commission, the event contribution and what you keep if the client cancels. Type only in the GREEN cells; the margin is calculated.
A3: 1. Choose the client (Couple or Corporate), the event type, the full date and the expected guests.
A4: 2. The date sets the season (month table) and the type of day (weekday table). Each one carries a premium or a discount in its own visible table; both multiply the event type rate.
A5: 3. Each season has a guest minimum: the quote uses the higher of the expected guests and the minimum, and the commission is estimated on that guaranteed guest count.
A6: 4. Type how many extra services the event takes (ceremony on site, additional hours, premium decor package, rehearsal the day before). Their prices are in the "Venue extra services" table and are Kit examples: type your own.
A7: 5. Type the venue staff hours, the hourly wage, the payroll tax rate and the direct cost of the extras. The direct event cost (cleaning, restrooms, generator fuel, parking and security) is in the event type table.
A8: SALES TAX, COMMISSION AND THE CATERER'S MENU
A10: The venue bills its rental fee and services at the sales tax rate you type (8% in the example). Whether a venue rental fee is taxable depends on the state (taxable in some, exempt in others, sometimes only when it is billed with catering): ask your state's department of revenue. The exclusive caterer bills food and the bar with its own sales tax, service charge and gratuity; they are not venue revenue, and the calculator shows them only as a reference for the client.
A11: The caterer commission is what the exclusive caterer pays the venue for the exclusivity. Here it is an editable assumption (10% of the caterer's food & beverage sales, net of sales tax, service charge and gratuities): it is not a market figure, negotiate it. The caterer pays it, not the client; the plan treats it as a fee between businesses (0% sales tax in the example): confirm it with your CPA.
A12: The event contribution does not deduct rent, salaried staff, utilities, insurance or overhead. Those are in the financial plan.
A13: PAYMENTS AND CANCELLATION
... A26: Planning tool, not financial, tax or legal advice. Requirements vary by state, county and city — check with your accountant and local authorities.
