Workbook

Sheet Instrucciones
B2: 📋 Escandallo Estándar — Plato a la Carta
B3: Kit de Escandallos Pro — AI Chef Pro
B4: www.aichef.pro
B6: Cómo usar esta plantilla
B8: ▸ Ve a la pestaña 'Escandallo' para empezar.
B9: ▸ El ejemplo cargado es un solomillo con Pedro Ximénez: bórralo o escribe encima.
B10: ▸ Las celdas VERDES son las editables; el resto son fórmulas.
B12: Columnas de la hoja de escandallo
B14: ▸ Ingrediente: el producto tal como lo compras.
B15: ▸ Categoría: familia del ingrediente (desplegable). Es la que precarga la merma en las filas vacías.
B16: ▸ Ud. Compra: la unidad en la que COMPRAS (kg, L, docena, manojo…).
B17: ▸ Precio/Ud (€): lo que pagas por esa unidad de compra.
... B65: Versión 2.1 · septiembre 2026 · aichef.pro/kit-escandallos · info@aichef.pro

Sheet Escandallo
A1: Escandallo — Solomillo con PX y Espárragos
A2: Introduce tus ingredientes y cantidades. Las celdas verdes son editables.
L3: 📷 Foto del Plato
A4: Ingrediente | B4: Categoría | C4: Ud. Compra | D4: Precio/Ud (€) | E4: Cantidad | F4: Ud. Uso | G4: Factor | H4: Merma (%) | I4: Cant. Bruta | J4: Coste (€)
A5: Solomillo de ternera | B5: Carne roja | C5: kg | D5: 28.5 | E5: 0.2 | F5: kg | G5: =IF(C5&F5="","",IFERROR(VLOOKUP(C5&"→"&F5,Conversiones!$A$5:$B$67,2,FALSE),"?")) -> 1 | H5: 0.2354 | I5: =IFERROR(IF(E5="","",E5/(1-H5)),"revisa merma") -> 0.26157468 | J5: =IF(G5="?","revisa unidades",IFERROR(I5*D5/G5,"")) -> 7.4548784
A6: Patata agria | B6: Verdura raíz | C6: kg | D6: 1.8 | E6: 0.15 | F6: kg | G6: =IF(C6&F6="","",IFERROR(VLOOKUP(C6&"→"&F6,Conversiones!$A$5:$B$67,2,FALSE),"?")) -> 1 | H6: 0.12 | I6: =IFERROR(IF(E6="","",E6/(1-H6)),"revisa merma") -> 0.17045455 | J6: =IF(G6="?","revisa unidades",IFERROR(I6*D6/G6,"")) -> 0.30681818
A7: Espárrago verde | B7: Verdura hoja | C7: kg | D7: 6.5 | E7: 0.08 | F7: kg | G7: =IF(C7&F7="","",IFERROR(VLOOKUP(C7&"→"&F7,Conversiones!$A$5:$B$67,2,FALSE),"?")) -> 1 | H7: 0.25 | I7: =IFERROR(IF(E7="","",E7/(1-H7)),"revisa merma") -> 0.10666667 | J7: =IF(G7="?","revisa unidades",IFERROR(I7*D7/G7,"")) -> 0.69333333
A8: Mantequilla | B8: Lácteos | C8: kg | D8: 9 | E8: 0.03 | F8: kg | G8: =IF(C8&F8="","",IFERROR(VLOOKUP(C8&"→"&F8,Conversiones!$A$5:$B$67,2,FALSE),"?")) -> 1 | H8: 0.03 | I8: =IFERROR(IF(E8="","",E8/(1-H8)),"revisa merma") -> 0.030927835 | J8: =IF(G8="?","revisa unidades",IFERROR(I8*D8/G8,"")) -> 0.27835052 | L8: Foto del plato terminado: Revisar → Desproteger hoja, luego Insertar → Imagen
A9: Vino Pedro Ximénez | B9: Bebidas/licores | C9: L | D9: 8.5 | E9: 0.05 | F9: L | G9: =IF(C9&F9="","",IFERROR(VLOOKUP(C9&"→"&F9,Conversiones!$A$5:$B$67,2,FALSE),"?")) -> 1 | H9: 0.02 | I9: =IFERROR(IF(E9="","",E9/(1-H9)),"revisa merma") -> 0.051020408 | J9: =IF(G9="?","revisa unidades",IFERROR(I9*D9/G9,"")) -> 0.43367347
A10: Fondo oscuro de ternera | B10: Salsas/condimentos | C10: L | D10: 12 | E10: 0.08 | F10: L | G10: =IF(C10&F10="","",IFERROR(VLOOKUP(C10&"→"&F10,Conversiones!$A$5:$B$67,2,FALSE),"?")) -> 1 | H10: 0.07 | I10: =IFERROR(IF(E10="","",E10/(1-H10)),"revisa merma") -> 0.086021505 | J10: =IF(G10="?","revisa unidades",IFERROR(I10*D10/G10,"")) -> 1.0322581
A11: Aceite de oliva virgen extra | B11: Aceites/grasas | C11: L | D11: 7.5 | E11: 0.03 | F11: L | G11: =IF(C11&F11="","",IFERROR(VLOOKUP(C11&"→"&F11,Conversiones!$A$5:$B$67,2,FALSE),"?")) -> 1 | H11: 0.03 | I11: =IFERROR(IF(E11="","",E11/(1-H11)),"revisa merma") -> 0.030927835 | J11: =IF(G11="?","revisa unidades",IFERROR(I11*D11/G11,"")) -> 0.23195876
A12: Flor de sal | B12: Secos/granos | C12: kg | D12: 15 | E12: 0.003 | F12: kg | G12: =IF(C12&F12="","",IFERROR(VLOOKUP(C12&"→"&F12,Conversiones!$A$5:$B$67,2,FALSE),"?")) -> 1 | H12: 0.02 | I12: =IFERROR(IF(E12="","",E12/(1-H12)),"revisa merma") -> 0.0030612245 | J12: =IF(G12="?","revisa unidades",IFERROR(I12*D12/G12,"")) -> 0.045918367
A13: Pimienta negra | B13: Especias/hierbas | C13: kg | D13: 25 | E13: 0.002 | F13: kg | G13: =IF(C13&F13="","",IFERROR(VLOOKUP(C13&"→"&F13,Conversiones!$A$5:$B$67,2,FALSE),"?")) -> 1 | H13: 0.2 | I13: =IFERROR(IF(E13="","",E13/(1-H13)),"revisa merma") -> 0.0025 | J13: =IF(G13="?","revisa unidades",IFERROR(I13*D13/G13,"")) -> 0.0625
A14: Microgreens (bandeja 50 g) | B14: Verdura hoja | C14: kg | D14: 70 | E14: 0.003 | F14: kg | G14: =IF(C14&F14="","",IFERROR(VLOOKUP(C14&"→"&F14,Conversiones!$A$5:$B$67,2,FALSE),"?")) -> 1 | H14: 0 | I14: =IFERROR(IF(E14="","",E14/(1-H14)),"revisa merma") -> 0.003 | J14: =IF(G14="?","revisa unidades",IFERROR(I14*D14/G14,"")) -> 0.21
G15: =IF(C15&F15="","",IFERROR(VLOOKUP(C15&"→"&F15,Conversiones!$A$5:$B$67,2,FALSE),"?")) | H15: =IFERROR(VLOOKUP(B15,Mermas!$A$5:$C$25,2,FALSE),"") | I15: =IFERROR(IF(E15="","",E15/(1-H15)),"revisa merma") | J15: =IF(G15="?","revisa unidades",IFERROR(I15*D15/G15,""))
G16: =IF(C16&F16="","",IFERROR(VLOOKUP(C16&"→"&F16,Conversiones!$A$5:$B$67,2,FALSE),"?")) | H16: =IFERROR(VLOOKUP(B16,Mermas!$A$5:$C$25,2,FALSE),"") | I16: =IFERROR(IF(E16="","",E16/(1-H16)),"revisa merma") | J16: =IF(G16="?","revisa unidades",IFERROR(I16*D16/G16,""))
G17: =IF(C17&F17="","",IFERROR(VLOOKUP(C17&"→"&F17,Conversiones!$A$5:$B$67,2,FALSE),"?")) | H17: =IFERROR(VLOOKUP(B17,Mermas!$A$5:$C$25,2,FALSE),"") | I17: =IFERROR(IF(E17="","",E17/(1-H17)),"revisa merma") | J17: =IF(G17="?","revisa unidades",IFERROR(I17*D17/G17,""))
G18: =IF(C18&F18="","",IFERROR(VLOOKUP(C18&"→"&F18,Conversiones!$A$5:$B$67,2,FALSE),"?")) | H18: =IFERROR(VLOOKUP(B18,Mermas!$A$5:$C$25,2,FALSE),"") | I18: =IFERROR(IF(E18="","",E18/(1-H18)),"revisa merma") | J18: =IF(G18="?","revisa unidades",IFERROR(I18*D18/G18,""))
G19: =IF(C19&F19="","",IFERROR(VLOOKUP(C19&"→"&F19,Conversiones!$A$5:$B$67,2,FALSE),"?")) | H19: =IFERROR(VLOOKUP(B19,Mermas!$A$5:$C$25,2,FALSE),"") | I19: =IFERROR(IF(E19="","",E19/(1-H19)),"revisa merma") | J19: =IF(G19="?","revisa unidades",IFERROR(I19*D19/G19,""))
G20: =IF(C20&F20="","",IFERROR(VLOOKUP(C20&"→"&F20,Conversiones!$A$5:$B$67,2,FALSE),"?")) | H20: =IFERROR(VLOOKUP(B20,Mermas!$A$5:$C$25,2,FALSE),"") | I20: =IFERROR(IF(E20="","",E20/(1-H20)),"revisa merma") | J20: =IF(G20="?","revisa unidades",IFERROR(I20*D20/G20,""))
G21: =IF(C21&F21="","",IFERROR(VLOOKUP(C21&"→"&F21,Conversiones!$A$5:$B$67,2,FALSE),"?")) | H21: =IFERROR(VLOOKUP(B21,Mermas!$A$5:$C$25,2,FALSE),"") | I21: =IFERROR(IF(E21="","",E21/(1-H21)),"revisa merma") | J21: =IF(G21="?","revisa unidades",IFERROR(I21*D21/G21,""))
G22: =IF(C22&F22="","",IFERROR(VLOOKUP(C22&"→"&F22,Conversiones!$A$5:$B$67,2,FALSE),"?")) | H22: =IFERROR(VLOOKUP(B22,Mermas!$A$5:$C$25,2,FALSE),"") | I22: =IFERROR(IF(E22="","",E22/(1-H22)),"revisa merma") | J22: =IF(G22="?","revisa unidades",IFERROR(I22*D22/G22,""))
G23: =IF(C23&F23="","",IFERROR(VLOOKUP(C23&"→"&F23,Conversiones!$A$5:$B$67,2,FALSE),"?")) | H23: =IFERROR(VLOOKUP(B23,Mermas!$A$5:$C$25,2,FALSE),"") | I23: =IFERROR(IF(E23="","",E23/(1-H23)),"revisa merma") | J23: =IF(G23="?","revisa unidades",IFERROR(I23*D23/G23,""))
G24: =IF(C24&F24="","",IFERROR(VLOOKUP(C24&"→"&F24,Conversiones!$A$5:$B$67,2,FALSE),"?")) | H24: =IFERROR(VLOOKUP(B24,Mermas!$A$5:$C$25,2,FALSE),"") | I24: =IFERROR(IF(E24="","",E24/(1-H24)),"revisa merma") | J24: =IF(G24="?","revisa unidades",IFERROR(I24*D24/G24,""))
A26: COSTE TOTAL INGREDIENTES | J26: =SUM(J5:J24) -> 10.749689
A27: Coste elaboración (%) | I27: 0.1 | J27: =J26*I27 -> 1.0749689
A28: COSTE TOTAL DEL PLATO | J28: =J26+J27 -> 11.824658
A29: Nº de raciones | I29: 1
A30: COSTE POR RACIÓN | J30: =IFERROR(J28/I29,"") -> 11.824658
A32: Food Cost objetivo (%) | I32: 0.3
A33: PVP SUGERIDO (sin IVA) | J33: =IFERROR(J30/I32,"") -> 39.415527
A34: Tipo de IVA (%) | I34: 0.1
A35: PVP CON IVA | J35: =IFERROR(J33*(1+I34),"") -> 43.357079
A36: Margen bruto (€) | J36: =IFERROR(J33-J30,"") -> 27.590869
A37: Margen bruto (%) | J37: =IFERROR((J33-J30)/J33,"") -> 0.7
A39: PVP actual en carta (sin IVA)
A40: FOOD COST REAL (%) | J40: =IFERROR(J30/I39,"")

Sheet Conversiones
A1: Tabla de conversión Ud. Compra → Ud. Uso
A2: La usa la columna «Factor» de cada escandallo. Puedes añadir parejas al final, hasta la fila 67: la clave se escribe «compra→uso».
A4: Conversión (compra→uso) | B4: Factor | C4: Qué significa
A5: kg→kg | B5: 1 | C5: misma unidad
A6: kg→g | B6: 1000 | C6: 1 kg = 1.000 g
A7: g→g | B7: 1 | C7: misma unidad
A8: g→kg | B8: 0.001 | C8: 1 g = 0,001 kg
A9: L→L | B9: 1 | C9: misma unidad
A10: L→ml | B10: 1000 | C10: 1 L = 1.000 ml
A11: L→cl | B11: 100 | C11: 1 L = 100 cl
A12: ml→ml | B12: 1 | C12: misma unidad
A13: ml→L | B13: 0.001 | C13: 1 ml = 0,001 L
A14: ml→cl | B14: 0.1 | C14: 1 ml = 0,1 cl
A15: cl→cl | B15: 1 | C15: misma unidad
A16: cl→ml | B16: 10 | C16: 1 cl = 10 ml
... A37: sobre→g | B37: 10 | C37: sobre ≈ 10 g

Sheet Mermas
A1: Mermas de referencia por categoría
A2: La «típica» es la que se precarga en las filas vacías del escandallo al elegir categoría. Ajústala a tu proveedor.
A3: Mide tu merma real con la plantilla 12 (Test de Rendimiento) y llévala a «Merma (%)» de la ficha.
A4: Categoría | B4: Merma típica | C4: Mínima | D4: Máxima
A5: Carne roja | B5: 0.2 | C5: 0.15 | D5: 0.25
A6: Aves | B6: 0.25 | C6: 0.2 | D6: 0.3
A7: Pescado | B7: 0.35 | C7: 0.3 | D7: 0.45
A8: Marisco | B8: 0.45 | C8: 0.35 | D8: 0.55
A9: Verdura hoja | B9: 0.25 | C9: 0.2 | D9: 0.35
A10: Verdura raíz | B10: 0.12 | C10: 0.08 | D10: 0.18
A11: Verdura fruto | B11: 0.1 | C11: 0.06 | D11: 0.15
A12: Fruta | B12: 0.15 | C12: 0.1 | D12: 0.25
A13: Lácteos | B13: 0.03 | C13: 0.01 | D13: 0.05
A14: Secos/granos | B14: 0.02 | C14: 0.01 | D14: 0.04
A15: Congelados | B15: 0.07 | C15: 0.03 | D15: 0.1
A16: Pan/bollería | B16: 0.05 | C16: 0.02 | D16: 0.1
... A25: Pasta/arroz | B25: 0.02 | C25: 0.01 | D25: 0.04
