Workbook

Sheet Instrucciones
B2: 📋 Escandallo — Menú Degustación
B3: Kit de Escandallos Pro — AI Chef Pro
B4: www.aichef.pro
B6: Cómo usar esta plantilla
B8: ▸ Cada pestaña numerada es un pase del menú: hay NUEVE ('1. Aperitivo'…'9. Pase'), los cinco primeros con ejemplo y los cuatro últimos vacíos.
B9: ▸ La pestaña 'Resumen' suma sólo los pases que tengan ingredientes: los que dejes vacíos no ensucian el total.
B10: ▸ El Food Cost objetivo se edita UNA sola vez, en el Resumen; cada pase lo lee de allí, así que no hay dos precios para lo mismo.
B11: ▸ Las celdas VERDES son las editables; el resto son fórmulas.
B13: Columnas de la hoja de escandallo
B15: ▸ Ingrediente: el producto tal como lo compras.
B16: ▸ Categoría: familia del ingrediente (desplegable). Es la que precarga la merma en las filas vacías.
B17: ▸ Ud. Compra: la unidad en la que COMPRAS (kg, L, docena, manojo…).
... B65: Versión 2.1 · septiembre 2026 · aichef.pro/kit-escandallos · info@aichef.pro

Sheet 1. Aperitivo
A1: Aperitivo — Tartar de Atún con Aguacate
A2: Introduce tus ingredientes y cantidades. Las celdas verdes son editables.
L3: 📷 Foto del Plato
A4: Ingrediente | B4: Categoría | C4: Ud. Compra | D4: Precio/Ud (€) | E4: Cantidad | F4: Ud. Uso | G4: Factor | H4: Merma (%) | I4: Cant. Bruta | J4: Coste (€)
A5: Atún rojo (lomo) | B5: Pescado | C5: kg | D5: 42 | E5: 0.08 | F5: kg | G5: =IF(C5&F5="","",IFERROR(VLOOKUP(C5&"→"&F5,Conversiones!$A$5:$B$67,2,FALSE),"?")) -> 1 | H5: 0.35 | I5: =IFERROR(IF(E5="","",E5/(1-H5)),"revisa merma") -> 0.12307692 | J5: =IF(G5="?","revisa unidades",IFERROR(I5*D5/G5,"")) -> 5.1692308
A6: Aguacate Hass | B6: Fruta | C6: ud | D6: 1.5 | E6: 0.5 | F6: ud | G6: =IF(C6&F6="","",IFERROR(VLOOKUP(C6&"→"&F6,Conversiones!$A$5:$B$67,2,FALSE),"?")) -> 1 | H6: 0.3 | I6: =IFERROR(IF(E6="","",E6/(1-H6)),"revisa merma") -> 0.71428571 | J6: =IF(G6="?","revisa unidades",IFERROR(I6*D6/G6,"")) -> 1.0714286
A7: Sésamo tostado | B7: Secos/granos | C7: kg | D7: 12 | E7: 0.005 | F7: kg | G7: =IF(C7&F7="","",IFERROR(VLOOKUP(C7&"→"&F7,Conversiones!$A$5:$B$67,2,FALSE),"?")) -> 1 | H7: 0.02 | I7: =IFERROR(IF(E7="","",E7/(1-H7)),"revisa merma") -> 0.0051020408 | J7: =IF(G7="?","revisa unidades",IFERROR(I7*D7/G7,"")) -> 0.06122449
A8: Salsa de soja | B8: Salsas/condimentos | C8: L | D8: 6 | E8: 0.015 | F8: L | G8: =IF(C8&F8="","",IFERROR(VLOOKUP(C8&"→"&F8,Conversiones!$A$5:$B$67,2,FALSE),"?")) -> 1 | H8: 0.02 | I8: =IFERROR(IF(E8="","",E8/(1-H8)),"revisa merma") -> 0.015306122 | J8: =IF(G8="?","revisa unidades",IFERROR(I8*D8/G8,"")) -> 0.091836735 | L8: Foto del plato terminado: Revisar → Desproteger hoja, luego Insertar → Imagen
A9: Aceite de sésamo | B9: Aceites/grasas | C9: L | D9: 14 | E9: 0.01 | F9: L | G9: =IF(C9&F9="","",IFERROR(VLOOKUP(C9&"→"&F9,Conversiones!$A$5:$B$67,2,FALSE),"?")) -> 1 | H9: 0.03 | I9: =IFERROR(IF(E9="","",E9/(1-H9)),"revisa merma") -> 0.010309278 | J9: =IF(G9="?","revisa unidades",IFERROR(I9*D9/G9,"")) -> 0.1443299
G10: =IF(C10&F10="","",IFERROR(VLOOKUP(C10&"→"&F10,Conversiones!$A$5:$B$67,2,FALSE),"?")) | H10: =IFERROR(VLOOKUP(B10,Mermas!$A$5:$C$25,2,FALSE),"") | I10: =IFERROR(IF(E10="","",E10/(1-H10)),"revisa merma") | J10: =IF(G10="?","revisa unidades",IFERROR(I10*D10/G10,""))
G11: =IF(C11&F11="","",IFERROR(VLOOKUP(C11&"→"&F11,Conversiones!$A$5:$B$67,2,FALSE),"?")) | H11: =IFERROR(VLOOKUP(B11,Mermas!$A$5:$C$25,2,FALSE),"") | I11: =IFERROR(IF(E11="","",E11/(1-H11)),"revisa merma") | J11: =IF(G11="?","revisa unidades",IFERROR(I11*D11/G11,""))
G12: =IF(C12&F12="","",IFERROR(VLOOKUP(C12&"→"&F12,Conversiones!$A$5:$B$67,2,FALSE),"?")) | H12: =IFERROR(VLOOKUP(B12,Mermas!$A$5:$C$25,2,FALSE),"") | I12: =IFERROR(IF(E12="","",E12/(1-H12)),"revisa merma") | J12: =IF(G12="?","revisa unidades",IFERROR(I12*D12/G12,""))
G13: =IF(C13&F13="","",IFERROR(VLOOKUP(C13&"→"&F13,Conversiones!$A$5:$B$67,2,FALSE),"?")) | H13: =IFERROR(VLOOKUP(B13,Mermas!$A$5:$C$25,2,FALSE),"") | I13: =IFERROR(IF(E13="","",E13/(1-H13)),"revisa merma") | J13: =IF(G13="?","revisa unidades",IFERROR(I13*D13/G13,""))
G14: =IF(C14&F14="","",IFERROR(VLOOKUP(C14&"→"&F14,Conversiones!$A$5:$B$67,2,FALSE),"?")) | H14: =IFERROR(VLOOKUP(B14,Mermas!$A$5:$C$25,2,FALSE),"") | I14: =IFERROR(IF(E14="","",E14/(1-H14)),"revisa merma") | J14: =IF(G14="?","revisa unidades",IFERROR(I14*D14/G14,""))
G15: =IF(C15&F15="","",IFERROR(VLOOKUP(C15&"→"&F15,Conversiones!$A$5:$B$67,2,FALSE),"?")) | H15: =IFERROR(VLOOKUP(B15,Mermas!$A$5:$C$25,2,FALSE),"") | I15: =IFERROR(IF(E15="","",E15/(1-H15)),"revisa merma") | J15: =IF(G15="?","revisa unidades",IFERROR(I15*D15/G15,""))
G16: =IF(C16&F16="","",IFERROR(VLOOKUP(C16&"→"&F16,Conversiones!$A$5:$B$67,2,FALSE),"?")) | H16: =IFERROR(VLOOKUP(B16,Mermas!$A$5:$C$25,2,FALSE),"") | I16: =IFERROR(IF(E16="","",E16/(1-H16)),"revisa merma") | J16: =IF(G16="?","revisa unidades",IFERROR(I16*D16/G16,""))
G17: =IF(C17&F17="","",IFERROR(VLOOKUP(C17&"→"&F17,Conversiones!$A$5:$B$67,2,FALSE),"?")) | H17: =IFERROR(VLOOKUP(B17,Mermas!$A$5:$C$25,2,FALSE),"") | I17: =IFERROR(IF(E17="","",E17/(1-H17)),"revisa merma") | J17: =IF(G17="?","revisa unidades",IFERROR(I17*D17/G17,""))
G18: =IF(C18&F18="","",IFERROR(VLOOKUP(C18&"→"&F18,Conversiones!$A$5:$B$67,2,FALSE),"?")) | H18: =IFERROR(VLOOKUP(B18,Mermas!$A$5:$C$25,2,FALSE),"") | I18: =IFERROR(IF(E18="","",E18/(1-H18)),"revisa merma") | J18: =IF(G18="?","revisa unidades",IFERROR(I18*D18/G18,""))
G19: =IF(C19&F19="","",IFERROR(VLOOKUP(C19&"→"&F19,Conversiones!$A$5:$B$67,2,FALSE),"?")) | H19: =IFERROR(VLOOKUP(B19,Mermas!$A$5:$C$25,2,FALSE),"") | I19: =IFERROR(IF(E19="","",E19/(1-H19)),"revisa merma") | J19: =IF(G19="?","revisa unidades",IFERROR(I19*D19/G19,""))
A21: COSTE TOTAL INGREDIENTES | J21: =SUM(J5:J19) -> 6.5380505
A22: Coste elaboración (%) | I22: 0.1 | J22: =J21*I22 -> 0.65380505
A23: COSTE TOTAL DEL PLATO | J23: =J21+J22 -> 7.1918555
A24: Nº de raciones | I24: 1
A25: COSTE POR RACIÓN | J25: =IFERROR(J23/I24,"") -> 7.1918555
A27: Food Cost objetivo (%) — se edita en el Resumen | I27: =Resumen!$C$16 -> 0.25
A28: PVP SUGERIDO (sin IVA) | J28: =IFERROR(J25/I27,"") -> 28.767422
A29: Tipo de IVA (%) | I29: 0.1
A30: PVP CON IVA | J30: =IFERROR(J28*(1+I29),"") -> 31.644164
A31: Margen bruto (€) | J31: =IFERROR(J28-J25,"") -> 21.575567
A32: Margen bruto (%) | J32: =IFERROR((J28-J25)/J28,"") -> 0.75
A34: PVP actual en carta (sin IVA)
A35: FOOD COST REAL (%) | J35: =IFERROR(J25/I34,"")

Sheet 2. Entrante
A1: Entrante — Vieira con Coliflor y Trufa
A2: Introduce tus ingredientes y cantidades. Las celdas verdes son editables.
L3: 📷 Foto del Plato
A4: Ingrediente | B4: Categoría | C4: Ud. Compra | D4: Precio/Ud (€) | E4: Cantidad | F4: Ud. Uso | G4: Factor | H4: Merma (%) | I4: Cant. Bruta | J4: Coste (€)
A5: Vieira fresca (grande) | B5: Marisco | C5: kg | D5: 48 | E5: 0.06 | F5: kg | G5: =IF(C5&F5="","",IFERROR(VLOOKUP(C5&"→"&F5,Conversiones!$A$5:$B$67,2,FALSE),"?")) -> 1 | H5: 0.45 | I5: =IFERROR(IF(E5="","",E5/(1-H5)),"revisa merma") -> 0.10909091 | J5: =IF(G5="?","revisa unidades",IFERROR(I5*D5/G5,"")) -> 5.2363636
A6: Coliflor | B6: Verdura hoja | C6: kg | D6: 2.5 | E6: 0.1 | F6: kg | G6: =IF(C6&F6="","",IFERROR(VLOOKUP(C6&"→"&F6,Conversiones!$A$5:$B$67,2,FALSE),"?")) -> 1 | H6: 0.3 | I6: =IFERROR(IF(E6="","",E6/(1-H6)),"revisa merma") -> 0.14285714 | J6: =IF(G6="?","revisa unidades",IFERROR(I6*D6/G6,"")) -> 0.35714286
A7: Trufa negra | B7: Setas/hongos | C7: kg | D7: 800 | E7: 0.005 | F7: kg | G7: =IF(C7&F7="","",IFERROR(VLOOKUP(C7&"→"&F7,Conversiones!$A$5:$B$67,2,FALSE),"?")) -> 1 | H7: 0.1 | I7: =IFERROR(IF(E7="","",E7/(1-H7)),"revisa merma") -> 0.0055555556 | J7: =IF(G7="?","revisa unidades",IFERROR(I7*D7/G7,"")) -> 4.4444444
A8: Nata 35% MG | B8: Lácteos | C8: L | D8: 3.8 | E8: 0.05 | F8: L | G8: =IF(C8&F8="","",IFERROR(VLOOKUP(C8&"→"&F8,Conversiones!$A$5:$B$67,2,FALSE),"?")) -> 1 | H8: 0.03 | I8: =IFERROR(IF(E8="","",E8/(1-H8)),"revisa merma") -> 0.051546392 | J8: =IF(G8="?","revisa unidades",IFERROR(I8*D8/G8,"")) -> 0.19587629 | L8: Foto del plato terminado: Revisar → Desproteger hoja, luego Insertar → Imagen
A9: Mantequilla | B9: Lácteos | C9: kg | D9: 9 | E9: 0.02 | F9: kg | G9: =IF(C9&F9="","",IFERROR(VLOOKUP(C9&"→"&F9,Conversiones!$A$5:$B$67,2,FALSE),"?")) -> 1 | H9: 0.03 | I9: =IFERROR(IF(E9="","",E9/(1-H9)),"revisa merma") -> 0.020618557 | J9: =IF(G9="?","revisa unidades",IFERROR(I9*D9/G9,"")) -> 0.18556701
G10: =IF(C10&F10="","",IFERROR(VLOOKUP(C10&"→"&F10,Conversiones!$A$5:$B$67,2,FALSE),"?")) | H10: =IFERROR(VLOOKUP(B10,Mermas!$A$5:$C$25,2,FALSE),"") | I10: =IFERROR(IF(E10="","",E10/(1-H10)),"revisa merma") | J10: =IF(G10="?","revisa unidades",IFERROR(I10*D10/G10,""))
G11: =IF(C11&F11="","",IFERROR(VLOOKUP(C11&"→"&F11,Conversiones!$A$5:$B$67,2,FALSE),"?")) | H11: =IFERROR(VLOOKUP(B11,Mermas!$A$5:$C$25,2,FALSE),"") | I11: =IFERROR(IF(E11="","",E11/(1-H11)),"revisa merma") | J11: =IF(G11="?","revisa unidades",IFERROR(I11*D11/G11,""))
G12: =IF(C12&F12="","",IFERROR(VLOOKUP(C12&"→"&F12,Conversiones!$A$5:$B$67,2,FALSE),"?")) | H12: =IFERROR(VLOOKUP(B12,Mermas!$A$5:$C$25,2,FALSE),"") | I12: =IFERROR(IF(E12="","",E12/(1-H12)),"revisa merma") | J12: =IF(G12="?","revisa unidades",IFERROR(I12*D12/G12,""))
G13: =IF(C13&F13="","",IFERROR(VLOOKUP(C13&"→"&F13,Conversiones!$A$5:$B$67,2,FALSE),"?")) | H13: =IFERROR(VLOOKUP(B13,Mermas!$A$5:$C$25,2,FALSE),"") | I13: =IFERROR(IF(E13="","",E13/(1-H13)),"revisa merma") | J13: =IF(G13="?","revisa unidades",IFERROR(I13*D13/G13,""))
G14: =IF(C14&F14="","",IFERROR(VLOOKUP(C14&"→"&F14,Conversiones!$A$5:$B$67,2,FALSE),"?")) | H14: =IFERROR(VLOOKUP(B14,Mermas!$A$5:$C$25,2,FALSE),"") | I14: =IFERROR(IF(E14="","",E14/(1-H14)),"revisa merma") | J14: =IF(G14="?","revisa unidades",IFERROR(I14*D14/G14,""))
G15: =IF(C15&F15="","",IFERROR(VLOOKUP(C15&"→"&F15,Conversiones!$A$5:$B$67,2,FALSE),"?")) | H15: =IFERROR(VLOOKUP(B15,Mermas!$A$5:$C$25,2,FALSE),"") | I15: =IFERROR(IF(E15="","",E15/(1-H15)),"revisa merma") | J15: =IF(G15="?","revisa unidades",IFERROR(I15*D15/G15,""))
G16: =IF(C16&F16="","",IFERROR(VLOOKUP(C16&"→"&F16,Conversiones!$A$5:$B$67,2,FALSE),"?")) | H16: =IFERROR(VLOOKUP(B16,Mermas!$A$5:$C$25,2,FALSE),"") | I16: =IFERROR(IF(E16="","",E16/(1-H16)),"revisa merma") | J16: =IF(G16="?","revisa unidades",IFERROR(I16*D16/G16,""))
G17: =IF(C17&F17="","",IFERROR(VLOOKUP(C17&"→"&F17,Conversiones!$A$5:$B$67,2,FALSE),"?")) | H17: =IFERROR(VLOOKUP(B17,Mermas!$A$5:$C$25,2,FALSE),"") | I17: =IFERROR(IF(E17="","",E17/(1-H17)),"revisa merma") | J17: =IF(G17="?","revisa unidades",IFERROR(I17*D17/G17,""))
G18: =IF(C18&F18="","",IFERROR(VLOOKUP(C18&"→"&F18,Conversiones!$A$5:$B$67,2,FALSE),"?")) | H18: =IFERROR(VLOOKUP(B18,Mermas!$A$5:$C$25,2,FALSE),"") | I18: =IFERROR(IF(E18="","",E18/(1-H18)),"revisa merma") | J18: =IF(G18="?","revisa unidades",IFERROR(I18*D18/G18,""))
G19: =IF(C19&F19="","",IFERROR(VLOOKUP(C19&"→"&F19,Conversiones!$A$5:$B$67,2,FALSE),"?")) | H19: =IFERROR(VLOOKUP(B19,Mermas!$A$5:$C$25,2,FALSE),"") | I19: =IFERROR(IF(E19="","",E19/(1-H19)),"revisa merma") | J19: =IF(G19="?","revisa unidades",IFERROR(I19*D19/G19,""))
A21: COSTE TOTAL INGREDIENTES | J21: =SUM(J5:J19) -> 10.419394
A22: Coste elaboración (%) | I22: 0.1 | J22: =J21*I22 -> 1.0419394
A23: COSTE TOTAL DEL PLATO | J23: =J21+J22 -> 11.461334
A24: Nº de raciones | I24: 1
A25: COSTE POR RACIÓN | J25: =IFERROR(J23/I24,"") -> 11.461334
A27: Food Cost objetivo (%) — se edita en el Resumen | I27: =Resumen!$C$16 -> 0.25
A28: PVP SUGERIDO (sin IVA) | J28: =IFERROR(J25/I27,"") -> 45.845335
A29: Tipo de IVA (%) | I29: 0.1
A30: PVP CON IVA | J30: =IFERROR(J28*(1+I29),"") -> 50.429868
A31: Margen bruto (€) | J31: =IFERROR(J28-J25,"") -> 34.384001
A32: Margen bruto (%) | J32: =IFERROR((J28-J25)/J28,"") -> 0.75
A34: PVP actual en carta (sin IVA)
A35: FOOD COST REAL (%) | J35: =IFERROR(J25/I34,"")

Sheet 3. Pescado
A1: Pescado — Lubina con Beurre Blanc
A2: Introduce tus ingredientes y cantidades. Las celdas verdes son editables.
L3: 📷 Foto del Plato
A4: Ingrediente | B4: Categoría | C4: Ud. Compra | D4: Precio/Ud (€) | E4: Cantidad | F4: Ud. Uso | G4: Factor | H4: Merma (%) | I4: Cant. Bruta | J4: Coste (€)
A5: Lubina salvaje | B5: Pescado | C5: kg | D5: 32 | E5: 0.16 | F5: kg | G5: =IF(C5&F5="","",IFERROR(VLOOKUP(C5&"→"&F5,Conversiones!$A$5:$B$67,2,FALSE),"?")) -> 1 | H5: 0.4 | I5: =IFERROR(IF(E5="","",E5/(1-H5)),"revisa merma") -> 0.26666667 | J5: =IF(G5="?","revisa unidades",IFERROR(I5*D5/G5,"")) -> 8.5333333
A6: Chalota | B6: Verdura raíz | C6: kg | D6: 4.5 | E6: 0.03 | F6: kg | G6: =IF(C6&F6="","",IFERROR(VLOOKUP(C6&"→"&F6,Conversiones!$A$5:$B$67,2,FALSE),"?")) -> 1 | H6: 0.15 | I6: =IFERROR(IF(E6="","",E6/(1-H6)),"revisa merma") -> 0.035294118 | J6: =IF(G6="?","revisa unidades",IFERROR(I6*D6/G6,"")) -> 0.15882353
A7: Vino blanco seco | B7: Bebidas/licores | C7: L | D7: 5 | E7: 0.04 | F7: L | G7: =IF(C7&F7="","",IFERROR(VLOOKUP(C7&"→"&F7,Conversiones!$A$5:$B$67,2,FALSE),"?")) -> 1 | H7: 0.02 | I7: =IFERROR(IF(E7="","",E7/(1-H7)),"revisa merma") -> 0.040816327 | J7: =IF(G7="?","revisa unidades",IFERROR(I7*D7/G7,"")) -> 0.20408163
A8: Mantequilla | B8: Lácteos | C8: kg | D8: 9 | E8: 0.04 | F8: kg | G8: =IF(C8&F8="","",IFERROR(VLOOKUP(C8&"→"&F8,Conversiones!$A$5:$B$67,2,FALSE),"?")) -> 1 | H8: 0.03 | I8: =IFERROR(IF(E8="","",E8/(1-H8)),"revisa merma") -> 0.041237113 | J8: =IF(G8="?","revisa unidades",IFERROR(I8*D8/G8,"")) -> 0.37113402 | L8: Foto del plato terminado: Revisar → Desproteger hoja, luego Insertar → Imagen
A9: Hinojo fresco | B9: Verdura raíz | C9: kg | D9: 5 | E9: 0.06 | F9: kg | G9: =IF(C9&F9="","",IFERROR(VLOOKUP(C9&"→"&F9,Conversiones!$A$5:$B$67,2,FALSE),"?")) -> 1 | H9: 0.25 | I9: =IFERROR(IF(E9="","",E9/(1-H9)),"revisa merma") -> 0.08 | J9: =IF(G9="?","revisa unidades",IFERROR(I9*D9/G9,"")) -> 0.4
G10: =IF(C10&F10="","",IFERROR(VLOOKUP(C10&"→"&F10,Conversiones!$A$5:$B$67,2,FALSE),"?")) | H10: =IFERROR(VLOOKUP(B10,Mermas!$A$5:$C$25,2,FALSE),"") | I10: =IFERROR(IF(E10="","",E10/(1-H10)),"revisa merma") | J10: =IF(G10="?","revisa unidades",IFERROR(I10*D10/G10,""))
G11: =IF(C11&F11="","",IFERROR(VLOOKUP(C11&"→"&F11,Conversiones!$A$5:$B$67,2,FALSE),"?")) | H11: =IFERROR(VLOOKUP(B11,Mermas!$A$5:$C$25,2,FALSE),"") | I11: =IFERROR(IF(E11="","",E11/(1-H11)),"revisa merma") | J11: =IF(G11="?","revisa unidades",IFERROR(I11*D11/G11,""))
G12: =IF(C12&F12="","",IFERROR(VLOOKUP(C12&"→"&F12,Conversiones!$A$5:$B$67,2,FALSE),"?")) | H12: =IFERROR(VLOOKUP(B12,Mermas!$A$5:$C$25,2,FALSE),"") | I12: =IFERROR(IF(E12="","",E12/(1-H12)),"revisa merma") | J12: =IF(G12="?","revisa unidades",IFERROR(I12*D12/G12,""))
G13: =IF(C13&F13="","",IFERROR(VLOOKUP(C13&"→"&F13,Conversiones!$A$5:$B$67,2,FALSE),"?")) | H13: =IFERROR(VLOOKUP(B13,Mermas!$A$5:$C$25,2,FALSE),"") | I13: =IFERROR(IF(E13="","",E13/(1-H13)),"revisa merma") | J13: =IF(G13="?","revisa unidades",IFERROR(I13*D13/G13,""))
G14: =IF(C14&F14="","",IFERROR(VLOOKUP(C14&"→"&F14,Conversiones!$A$5:$B$67,2,FALSE),"?")) | H14: =IFERROR(VLOOKUP(B14,Mermas!$A$5:$C$25,2,FALSE),"") | I14: =IFERROR(IF(E14="","",E14/(1-H14)),"revisa merma") | J14: =IF(G14="?","revisa unidades",IFERROR(I14*D14/G14,""))
G15: =IF(C15&F15="","",IFERROR(VLOOKUP(C15&"→"&F15,Conversiones!$A$5:$B$67,2,FALSE),"?")) | H15: =IFERROR(VLOOKUP(B15,Mermas!$A$5:$C$25,2,FALSE),"") | I15: =IFERROR(IF(E15="","",E15/(1-H15)),"revisa merma") | J15: =IF(G15="?","revisa unidades",IFERROR(I15*D15/G15,""))
G16: =IF(C16&F16="","",IFERROR(VLOOKUP(C16&"→"&F16,Conversiones!$A$5:$B$67,2,FALSE),"?")) | H16: =IFERROR(VLOOKUP(B16,Mermas!$A$5:$C$25,2,FALSE),"") | I16: =IFERROR(IF(E16="","",E16/(1-H16)),"revisa merma") | J16: =IF(G16="?","revisa unidades",IFERROR(I16*D16/G16,""))
G17: =IF(C17&F17="","",IFERROR(VLOOKUP(C17&"→"&F17,Conversiones!$A$5:$B$67,2,FALSE),"?")) | H17: =IFERROR(VLOOKUP(B17,Mermas!$A$5:$C$25,2,FALSE),"") | I17: =IFERROR(IF(E17="","",E17/(1-H17)),"revisa merma") | J17: =IF(G17="?","revisa unidades",IFERROR(I17*D17/G17,""))
G18: =IF(C18&F18="","",IFERROR(VLOOKUP(C18&"→"&F18,Conversiones!$A$5:$B$67,2,FALSE),"?")) | H18: =IFERROR(VLOOKUP(B18,Mermas!$A$5:$C$25,2,FALSE),"") | I18: =IFERROR(IF(E18="","",E18/(1-H18)),"revisa merma") | J18: =IF(G18="?","revisa unidades",IFERROR(I18*D18/G18,""))
G19: =IF(C19&F19="","",IFERROR(VLOOKUP(C19&"→"&F19,Conversiones!$A$5:$B$67,2,FALSE),"?")) | H19: =IFERROR(VLOOKUP(B19,Mermas!$A$5:$C$25,2,FALSE),"") | I19: =IFERROR(IF(E19="","",E19/(1-H19)),"revisa merma") | J19: =IF(G19="?","revisa unidades",IFERROR(I19*D19/G19,""))
A21: COSTE TOTAL INGREDIENTES | J21: =SUM(J5:J19) -> 9.6673725
A22: Coste elaboración (%) | I22: 0.1 | J22: =J21*I22 -> 0.96673725
A23: COSTE TOTAL DEL PLATO | J23: =J21+J22 -> 10.63411
A24: Nº de raciones | I24: 1
A25: COSTE POR RACIÓN | J25: =IFERROR(J23/I24,"") -> 10.63411
A27: Food Cost objetivo (%) — se edita en el Resumen | I27: =Resumen!$C$16 -> 0.25
A28: PVP SUGERIDO (sin IVA) | J28: =IFERROR(J25/I27,"") -> 42.536439
A29: Tipo de IVA (%) | I29: 0.1
A30: PVP CON IVA | J30: =IFERROR(J28*(1+I29),"") -> 46.790083
A31: Margen bruto (€) | J31: =IFERROR(J28-J25,"") -> 31.902329
A32: Margen bruto (%) | J32: =IFERROR((J28-J25)/J28,"") -> 0.75
A34: PVP actual en carta (sin IVA)
A35: FOOD COST REAL (%) | J35: =IFERROR(J25/I34,"")

Sheet 4. Carne
A1: Carne — Carrillera Ibérica al Vino Tinto
A2: Introduce tus ingredientes y cantidades. Las celdas verdes son editables.
L3: 📷 Foto del Plato
A4: Ingrediente | B4: Categoría | C4: Ud. Compra | D4: Precio/Ud (€) | E4: Cantidad | F4: Ud. Uso | G4: Factor | H4: Merma (%) | I4: Cant. Bruta | J4: Coste (€)
A5: Carrillera ibérica | B5: Carne roja | C5: kg | D5: 18 | E5: 0.2 | F5: kg | G5: =IF(C5&F5="","",IFERROR(VLOOKUP(C5&"→"&F5,Conversiones!$A$5:$B$67,2,FALSE),"?")) -> 1 | H5: 0.15 | I5: =IFERROR(IF(E5="","",E5/(1-H5)),"revisa merma") -> 0.23529412 | J5: =IF(G5="?","revisa unidades",IFERROR(I5*D5/G5,"")) -> 4.2352941
A6: Vino tinto reserva | B6: Bebidas/licores | C6: L | D6: 6 | E6: 0.1 | F6: L | G6: =IF(C6&F6="","",IFERROR(VLOOKUP(C6&"→"&F6,Conversiones!$A$5:$B$67,2,FALSE),"?")) -> 1 | H6: 0.02 | I6: =IFERROR(IF(E6="","",E6/(1-H6)),"revisa merma") -> 0.10204082 | J6: =IF(G6="?","revisa unidades",IFERROR(I6*D6/G6,"")) -> 0.6122449
A7: Zanahoria | B7: Verdura raíz | C7: kg | D7: 1.2 | E7: 0.05 | F7: kg | G7: =IF(C7&F7="","",IFERROR(VLOOKUP(C7&"→"&F7,Conversiones!$A$5:$B$67,2,FALSE),"?")) -> 1 | H7: 0.12 | I7: =IFERROR(IF(E7="","",E7/(1-H7)),"revisa merma") -> 0.056818182 | J7: =IF(G7="?","revisa unidades",IFERROR(I7*D7/G7,"")) -> 0.068181818
A8: Puré de boniato | B8: Verdura raíz | C8: kg | D8: 2.5 | E8: 0.1 | F8: kg | G8: =IF(C8&F8="","",IFERROR(VLOOKUP(C8&"→"&F8,Conversiones!$A$5:$B$67,2,FALSE),"?")) -> 1 | H8: 0.15 | I8: =IFERROR(IF(E8="","",E8/(1-H8)),"revisa merma") -> 0.11764706 | J8: =IF(G8="?","revisa unidades",IFERROR(I8*D8/G8,"")) -> 0.29411765 | L8: Foto del plato terminado: Revisar → Desproteger hoja, luego Insertar → Imagen
A9: Romero fresco (1 rama ≈ 1/12 manojo) | B9: Especias/hierbas | C9: manojo | D9: 1 | E9: 0.083 | F9: manojo | G9: =IF(C9&F9="","",IFERROR(VLOOKUP(C9&"→"&F9,Conversiones!$A$5:$B$67,2,FALSE),"?")) -> 1 | H9: 0.2 | I9: =IFERROR(IF(E9="","",E9/(1-H9)),"revisa merma") -> 0.10375 | J9: =IF(G9="?","revisa unidades",IFERROR(I9*D9/G9,"")) -> 0.10375
G10: =IF(C10&F10="","",IFERROR(VLOOKUP(C10&"→"&F10,Conversiones!$A$5:$B$67,2,FALSE),"?")) | H10: =IFERROR(VLOOKUP(B10,Mermas!$A$5:$C$25,2,FALSE),"") | I10: =IFERROR(IF(E10="","",E10/(1-H10)),"revisa merma") | J10: =IF(G10="?","revisa unidades",IFERROR(I10*D10/G10,""))
G11: =IF(C11&F11="","",IFERROR(VLOOKUP(C11&"→"&F11,Conversiones!$A$5:$B$67,2,FALSE),"?")) | H11: =IFERROR(VLOOKUP(B11,Mermas!$A$5:$C$25,2,FALSE),"") | I11: =IFERROR(IF(E11="","",E11/(1-H11)),"revisa merma") | J11: =IF(G11="?","revisa unidades",IFERROR(I11*D11/G11,""))
G12: =IF(C12&F12="","",IFERROR(VLOOKUP(C12&"→"&F12,Conversiones!$A$5:$B$67,2,FALSE),"?")) | H12: =IFERROR(VLOOKUP(B12,Mermas!$A$5:$C$25,2,FALSE),"") | I12: =IFERROR(IF(E12="","",E12/(1-H12)),"revisa merma") | J12: =IF(G12="?","revisa unidades",IFERROR(I12*D12/G12,""))
G13: =IF(C13&F13="","",IFERROR(VLOOKUP(C13&"→"&F13,Conversiones!$A$5:$B$67,2,FALSE),"?")) | H13: =IFERROR(VLOOKUP(B13,Mermas!$A$5:$C$25,2,FALSE),"") | I13: =IFERROR(IF(E13="","",E13/(1-H13)),"revisa merma") | J13: =IF(G13="?","revisa unidades",IFERROR(I13*D13/G13,""))
G14: =IF(C14&F14="","",IFERROR(VLOOKUP(C14&"→"&F14,Conversiones!$A$5:$B$67,2,FALSE),"?")) | H14: =IFERROR(VLOOKUP(B14,Mermas!$A$5:$C$25,2,FALSE),"") | I14: =IFERROR(IF(E14="","",E14/(1-H14)),"revisa merma") | J14: =IF(G14="?","revisa unidades",IFERROR(I14*D14/G14,""))
G15: =IF(C15&F15="","",IFERROR(VLOOKUP(C15&"→"&F15,Conversiones!$A$5:$B$67,2,FALSE),"?")) | H15: =IFERROR(VLOOKUP(B15,Mermas!$A$5:$C$25,2,FALSE),"") | I15: =IFERROR(IF(E15="","",E15/(1-H15)),"revisa merma") | J15: =IF(G15="?","revisa unidades",IFERROR(I15*D15/G15,""))
G16: =IF(C16&F16="","",IFERROR(VLOOKUP(C16&"→"&F16,Conversiones!$A$5:$B$67,2,FALSE),"?")) | H16: =IFERROR(VLOOKUP(B16,Mermas!$A$5:$C$25,2,FALSE),"") | I16: =IFERROR(IF(E16="","",E16/(1-H16)),"revisa merma") | J16: =IF(G16="?","revisa unidades",IFERROR(I16*D16/G16,""))
G17: =IF(C17&F17="","",IFERROR(VLOOKUP(C17&"→"&F17,Conversiones!$A$5:$B$67,2,FALSE),"?")) | H17: =IFERROR(VLOOKUP(B17,Mermas!$A$5:$C$25,2,FALSE),"") | I17: =IFERROR(IF(E17="","",E17/(1-H17)),"revisa merma") | J17: =IF(G17="?","revisa unidades",IFERROR(I17*D17/G17,""))
G18: =IF(C18&F18="","",IFERROR(VLOOKUP(C18&"→"&F18,Conversiones!$A$5:$B$67,2,FALSE),"?")) | H18: =IFERROR(VLOOKUP(B18,Mermas!$A$5:$C$25,2,FALSE),"") | I18: =IFERROR(IF(E18="","",E18/(1-H18)),"revisa merma") | J18: =IF(G18="?","revisa unidades",IFERROR(I18*D18/G18,""))
G19: =IF(C19&F19="","",IFERROR(VLOOKUP(C19&"→"&F19,Conversiones!$A$5:$B$67,2,FALSE),"?")) | H19: =IFERROR(VLOOKUP(B19,Mermas!$A$5:$C$25,2,FALSE),"") | I19: =IFERROR(IF(E19="","",E19/(1-H19)),"revisa merma") | J19: =IF(G19="?","revisa unidades",IFERROR(I19*D19/G19,""))
A21: COSTE TOTAL INGREDIENTES | J21: =SUM(J5:J19) -> 5.3135885
A22: Coste elaboración (%) | I22: 0.1 | J22: =J21*I22 -> 0.53135885
A23: COSTE TOTAL DEL PLATO | J23: =J21+J22 -> 5.8449473
A24: Nº de raciones | I24: 1
A25: COSTE POR RACIÓN | J25: =IFERROR(J23/I24,"") -> 5.8449473
A27: Food Cost objetivo (%) — se edita en el Resumen | I27: =Resumen!$C$16 -> 0.25
A28: PVP SUGERIDO (sin IVA) | J28: =IFERROR(J25/I27,"") -> 23.379789
A29: Tipo de IVA (%) | I29: 0.1
A30: PVP CON IVA | J30: =IFERROR(J28*(1+I29),"") -> 25.717768
A31: Margen bruto (€) | J31: =IFERROR(J28-J25,"") -> 17.534842
A32: Margen bruto (%) | J32: =IFERROR((J28-J25)/J28,"") -> 0.75
A34: PVP actual en carta (sin IVA)
A35: FOOD COST REAL (%) | J35: =IFERROR(J25/I34,"")

Sheet 5. Postre
A1: Postre — Esfera de Chocolate con Fruta de la Pasión
A2: Introduce tus ingredientes y cantidades. Las celdas verdes son editables.
L3: 📷 Foto del Plato
A4: Ingrediente | B4: Categoría | C4: Ud. Compra | D4: Precio/Ud (€) | E4: Cantidad | F4: Ud. Uso | G4: Factor | H4: Merma (%) | I4: Cant. Bruta | J4: Coste (€)
A5: Chocolate negro 70% | B5: Chocolate/cacao | C5: kg | D5: 18 | E5: 0.06 | F5: kg | G5: =IF(C5&F5="","",IFERROR(VLOOKUP(C5&"→"&F5,Conversiones!$A$5:$B$67,2,FALSE),"?")) -> 1 | H5: 0.05 | I5: =IFERROR(IF(E5="","",E5/(1-H5)),"revisa merma") -> 0.063157895 | J5: =IF(G5="?","revisa unidades",IFERROR(I5*D5/G5,"")) -> 1.1368421
A6: Fruta de la pasión | B6: Fruta | C6: kg | D6: 14 | E6: 0.04 | F6: kg | G6: =IF(C6&F6="","",IFERROR(VLOOKUP(C6&"→"&F6,Conversiones!$A$5:$B$67,2,FALSE),"?")) -> 1 | H6: 0.5 | I6: =IFERROR(IF(E6="","",E6/(1-H6)),"revisa merma") -> 0.08 | J6: =IF(G6="?","revisa unidades",IFERROR(I6*D6/G6,"")) -> 1.12
A7: Nata 35% MG | B7: Lácteos | C7: L | D7: 3.8 | E7: 0.06 | F7: L | G7: =IF(C7&F7="","",IFERROR(VLOOKUP(C7&"→"&F7,Conversiones!$A$5:$B$67,2,FALSE),"?")) -> 1 | H7: 0.03 | I7: =IFERROR(IF(E7="","",E7/(1-H7)),"revisa merma") -> 0.06185567 | J7: =IF(G7="?","revisa unidades",IFERROR(I7*D7/G7,"")) -> 0.23505155
A8: Azúcar | B8: Secos/granos | C8: kg | D8: 1.2 | E8: 0.025 | F8: kg | G8: =IF(C8&F8="","",IFERROR(VLOOKUP(C8&"→"&F8,Conversiones!$A$5:$B$67,2,FALSE),"?")) -> 1 | H8: 0.02 | I8: =IFERROR(IF(E8="","",E8/(1-H8)),"revisa merma") -> 0.025510204 | J8: =IF(G8="?","revisa unidades",IFERROR(I8*D8/G8,"")) -> 0.030612245 | L8: Foto del plato terminado: Revisar → Desproteger hoja, luego Insertar → Imagen
A9: Manteca de cacao | B9: Chocolate/cacao | C9: kg | D9: 22 | E9: 0.015 | F9: kg | G9: =IF(C9&F9="","",IFERROR(VLOOKUP(C9&"→"&F9,Conversiones!$A$5:$B$67,2,FALSE),"?")) -> 1 | H9: 0.05 | I9: =IFERROR(IF(E9="","",E9/(1-H9)),"revisa merma") -> 0.015789474 | J9: =IF(G9="?","revisa unidades",IFERROR(I9*D9/G9,"")) -> 0.34736842
G10: =IF(C10&F10="","",IFERROR(VLOOKUP(C10&"→"&F10,Conversiones!$A$5:$B$67,2,FALSE),"?")) | H10: =IFERROR(VLOOKUP(B10,Mermas!$A$5:$C$25,2,FALSE),"") | I10: =IFERROR(IF(E10="","",E10/(1-H10)),"revisa merma") | J10: =IF(G10="?","revisa unidades",IFERROR(I10*D10/G10,""))
G11: =IF(C11&F11="","",IFERROR(VLOOKUP(C11&"→"&F11,Conversiones!$A$5:$B$67,2,FALSE),"?")) | H11: =IFERROR(VLOOKUP(B11,Mermas!$A$5:$C$25,2,FALSE),"") | I11: =IFERROR(IF(E11="","",E11/(1-H11)),"revisa merma") | J11: =IF(G11="?","revisa unidades",IFERROR(I11*D11/G11,""))
G12: =IF(C12&F12="","",IFERROR(VLOOKUP(C12&"→"&F12,Conversiones!$A$5:$B$67,2,FALSE),"?")) | H12: =IFERROR(VLOOKUP(B12,Mermas!$A$5:$C$25,2,FALSE),"") | I12: =IFERROR(IF(E12="","",E12/(1-H12)),"revisa merma") | J12: =IF(G12="?","revisa unidades",IFERROR(I12*D12/G12,""))
G13: =IF(C13&F13="","",IFERROR(VLOOKUP(C13&"→"&F13,Conversiones!$A$5:$B$67,2,FALSE),"?")) | H13: =IFERROR(VLOOKUP(B13,Mermas!$A$5:$C$25,2,FALSE),"") | I13: =IFERROR(IF(E13="","",E13/(1-H13)),"revisa merma") | J13: =IF(G13="?","revisa unidades",IFERROR(I13*D13/G13,""))
G14: =IF(C14&F14="","",IFERROR(VLOOKUP(C14&"→"&F14,Conversiones!$A$5:$B$67,2,FALSE),"?")) | H14: =IFERROR(VLOOKUP(B14,Mermas!$A$5:$C$25,2,FALSE),"") | I14: =IFERROR(IF(E14="","",E14/(1-H14)),"revisa merma") | J14: =IF(G14="?","revisa unidades",IFERROR(I14*D14/G14,""))
G15: =IF(C15&F15="","",IFERROR(VLOOKUP(C15&"→"&F15,Conversiones!$A$5:$B$67,2,FALSE),"?")) | H15: =IFERROR(VLOOKUP(B15,Mermas!$A$5:$C$25,2,FALSE),"") | I15: =IFERROR(IF(E15="","",E15/(1-H15)),"revisa merma") | J15: =IF(G15="?","revisa unidades",IFERROR(I15*D15/G15,""))
G16: =IF(C16&F16="","",IFERROR(VLOOKUP(C16&"→"&F16,Conversiones!$A$5:$B$67,2,FALSE),"?")) | H16: =IFERROR(VLOOKUP(B16,Mermas!$A$5:$C$25,2,FALSE),"") | I16: =IFERROR(IF(E16="","",E16/(1-H16)),"revisa merma") | J16: =IF(G16="?","revisa unidades",IFERROR(I16*D16/G16,""))
G17: =IF(C17&F17="","",IFERROR(VLOOKUP(C17&"→"&F17,Conversiones!$A$5:$B$67,2,FALSE),"?")) | H17: =IFERROR(VLOOKUP(B17,Mermas!$A$5:$C$25,2,FALSE),"") | I17: =IFERROR(IF(E17="","",E17/(1-H17)),"revisa merma") | J17: =IF(G17="?","revisa unidades",IFERROR(I17*D17/G17,""))
G18: =IF(C18&F18="","",IFERROR(VLOOKUP(C18&"→"&F18,Conversiones!$A$5:$B$67,2,FALSE),"?")) | H18: =IFERROR(VLOOKUP(B18,Mermas!$A$5:$C$25,2,FALSE),"") | I18: =IFERROR(IF(E18="","",E18/(1-H18)),"revisa merma") | J18: =IF(G18="?","revisa unidades",IFERROR(I18*D18/G18,""))
G19: =IF(C19&F19="","",IFERROR(VLOOKUP(C19&"→"&F19,Conversiones!$A$5:$B$67,2,FALSE),"?")) | H19: =IFERROR(VLOOKUP(B19,Mermas!$A$5:$C$25,2,FALSE),"") | I19: =IFERROR(IF(E19="","",E19/(1-H19)),"revisa merma") | J19: =IF(G19="?","revisa unidades",IFERROR(I19*D19/G19,""))
A21: COSTE TOTAL INGREDIENTES | J21: =SUM(J5:J19) -> 2.8698743
A22: Coste elaboración (%) | I22: 0.1 | J22: =J21*I22 -> 0.28698743
A23: COSTE TOTAL DEL PLATO | J23: =J21+J22 -> 3.1568617
A24: Nº de raciones | I24: 1
A25: COSTE POR RACIÓN | J25: =IFERROR(J23/I24,"") -> 3.1568617
A27: Food Cost objetivo (%) — se edita en el Resumen | I27: =Resumen!$C$16 -> 0.25
A28: PVP SUGERIDO (sin IVA) | J28: =IFERROR(J25/I27,"") -> 12.627447
A29: Tipo de IVA (%) | I29: 0.1
A30: PVP CON IVA | J30: =IFERROR(J28*(1+I29),"") -> 13.890192
A31: Margen bruto (€) | J31: =IFERROR(J28-J25,"") -> 9.4705852
A32: Margen bruto (%) | J32: =IFERROR((J28-J25)/J28,"") -> 0.75
A34: PVP actual en carta (sin IVA)
A35: FOOD COST REAL (%) | J35: =IFERROR(J25/I34,"")

Sheet 6. Pase
A1: 6. Pase — escribe aquí el nombre del pase
A2: Pase libre: rellena los ingredientes y el Resumen lo suma solo. Si lo dejas vacío, no cuenta.
L3: 📷 Foto del Plato
A4: Ingrediente | B4: Categoría | C4: Ud. Compra | D4: Precio/Ud (€) | E4: Cantidad | F4: Ud. Uso | G4: Factor | H4: Merma (%) | I4: Cant. Bruta | J4: Coste (€)
G5: =IF(C5&F5="","",IFERROR(VLOOKUP(C5&"→"&F5,Conversiones!$A$5:$B$67,2,FALSE),"?")) | H5: =IFERROR(VLOOKUP(B5,Mermas!$A$5:$C$25,2,FALSE),"") | I5: =IFERROR(IF(E5="","",E5/(1-H5)),"revisa merma") | J5: =IF(G5="?","revisa unidades",IFERROR(I5*D5/G5,""))
G6: =IF(C6&F6="","",IFERROR(VLOOKUP(C6&"→"&F6,Conversiones!$A$5:$B$67,2,FALSE),"?")) | H6: =IFERROR(VLOOKUP(B6,Mermas!$A$5:$C$25,2,FALSE),"") | I6: =IFERROR(IF(E6="","",E6/(1-H6)),"revisa merma") | J6: =IF(G6="?","revisa unidades",IFERROR(I6*D6/G6,""))
G7: =IF(C7&F7="","",IFERROR(VLOOKUP(C7&"→"&F7,Conversiones!$A$5:$B$67,2,FALSE),"?")) | H7: =IFERROR(VLOOKUP(B7,Mermas!$A$5:$C$25,2,FALSE),"") | I7: =IFERROR(IF(E7="","",E7/(1-H7)),"revisa merma") | J7: =IF(G7="?","revisa unidades",IFERROR(I7*D7/G7,""))
G8: =IF(C8&F8="","",IFERROR(VLOOKUP(C8&"→"&F8,Conversiones!$A$5:$B$67,2,FALSE),"?")) | H8: =IFERROR(VLOOKUP(B8,Mermas!$A$5:$C$25,2,FALSE),"") | I8: =IFERROR(IF(E8="","",E8/(1-H8)),"revisa merma") | J8: =IF(G8="?","revisa unidades",IFERROR(I8*D8/G8,"")) | L8: Foto del plato terminado: Revisar → Desproteger hoja, luego Insertar → Imagen
G9: =IF(C9&F9="","",IFERROR(VLOOKUP(C9&"→"&F9,Conversiones!$A$5:$B$67,2,FALSE),"?")) | H9: =IFERROR(VLOOKUP(B9,Mermas!$A$5:$C$25,2,FALSE),"") | I9: =IFERROR(IF(E9="","",E9/(1-H9)),"revisa merma") | J9: =IF(G9="?","revisa unidades",IFERROR(I9*D9/G9,""))
G10: =IF(C10&F10="","",IFERROR(VLOOKUP(C10&"→"&F10,Conversiones!$A$5:$B$67,2,FALSE),"?")) | H10: =IFERROR(VLOOKUP(B10,Mermas!$A$5:$C$25,2,FALSE),"") | I10: =IFERROR(IF(E10="","",E10/(1-H10)),"revisa merma") | J10: =IF(G10="?","revisa unidades",IFERROR(I10*D10/G10,""))
G11: =IF(C11&F11="","",IFERROR(VLOOKUP(C11&"→"&F11,Conversiones!$A$5:$B$67,2,FALSE),"?")) | H11: =IFERROR(VLOOKUP(B11,Mermas!$A$5:$C$25,2,FALSE),"") | I11: =IFERROR(IF(E11="","",E11/(1-H11)),"revisa merma") | J11: =IF(G11="?","revisa unidades",IFERROR(I11*D11/G11,""))
G12: =IF(C12&F12="","",IFERROR(VLOOKUP(C12&"→"&F12,Conversiones!$A$5:$B$67,2,FALSE),"?")) | H12: =IFERROR(VLOOKUP(B12,Mermas!$A$5:$C$25,2,FALSE),"") | I12: =IFERROR(IF(E12="","",E12/(1-H12)),"revisa merma") | J12: =IF(G12="?","revisa unidades",IFERROR(I12*D12/G12,""))
G13: =IF(C13&F13="","",IFERROR(VLOOKUP(C13&"→"&F13,Conversiones!$A$5:$B$67,2,FALSE),"?")) | H13: =IFERROR(VLOOKUP(B13,Mermas!$A$5:$C$25,2,FALSE),"") | I13: =IFERROR(IF(E13="","",E13/(1-H13)),"revisa merma") | J13: =IF(G13="?","revisa unidades",IFERROR(I13*D13/G13,""))
G14: =IF(C14&F14="","",IFERROR(VLOOKUP(C14&"→"&F14,Conversiones!$A$5:$B$67,2,FALSE),"?")) | H14: =IFERROR(VLOOKUP(B14,Mermas!$A$5:$C$25,2,FALSE),"") | I14: =IFERROR(IF(E14="","",E14/(1-H14)),"revisa merma") | J14: =IF(G14="?","revisa unidades",IFERROR(I14*D14/G14,""))
G15: =IF(C15&F15="","",IFERROR(VLOOKUP(C15&"→"&F15,Conversiones!$A$5:$B$67,2,FALSE),"?")) | H15: =IFERROR(VLOOKUP(B15,Mermas!$A$5:$C$25,2,FALSE),"") | I15: =IFERROR(IF(E15="","",E15/(1-H15)),"revisa merma") | J15: =IF(G15="?","revisa unidades",IFERROR(I15*D15/G15,""))
G16: =IF(C16&F16="","",IFERROR(VLOOKUP(C16&"→"&F16,Conversiones!$A$5:$B$67,2,FALSE),"?")) | H16: =IFERROR(VLOOKUP(B16,Mermas!$A$5:$C$25,2,FALSE),"") | I16: =IFERROR(IF(E16="","",E16/(1-H16)),"revisa merma") | J16: =IF(G16="?","revisa unidades",IFERROR(I16*D16/G16,""))
G17: =IF(C17&F17="","",IFERROR(VLOOKUP(C17&"→"&F17,Conversiones!$A$5:$B$67,2,FALSE),"?")) | H17: =IFERROR(VLOOKUP(B17,Mermas!$A$5:$C$25,2,FALSE),"") | I17: =IFERROR(IF(E17="","",E17/(1-H17)),"revisa merma") | J17: =IF(G17="?","revisa unidades",IFERROR(I17*D17/G17,""))
G18: =IF(C18&F18="","",IFERROR(VLOOKUP(C18&"→"&F18,Conversiones!$A$5:$B$67,2,FALSE),"?")) | H18: =IFERROR(VLOOKUP(B18,Mermas!$A$5:$C$25,2,FALSE),"") | I18: =IFERROR(IF(E18="","",E18/(1-H18)),"revisa merma") | J18: =IF(G18="?","revisa unidades",IFERROR(I18*D18/G18,""))
G19: =IF(C19&F19="","",IFERROR(VLOOKUP(C19&"→"&F19,Conversiones!$A$5:$B$67,2,FALSE),"?")) | H19: =IFERROR(VLOOKUP(B19,Mermas!$A$5:$C$25,2,FALSE),"") | I19: =IFERROR(IF(E19="","",E19/(1-H19)),"revisa merma") | J19: =IF(G19="?","revisa unidades",IFERROR(I19*D19/G19,""))
A21: COSTE TOTAL INGREDIENTES | J21: =SUM(J5:J19) -> 0
A22: Coste elaboración (%) | I22: 0.1 | J22: =J21*I22 -> 0
A23: COSTE TOTAL DEL PLATO | J23: =J21+J22 -> 0
A24: Nº de raciones | I24: 1
A25: COSTE POR RACIÓN | J25: =IFERROR(J23/I24,"") -> 0
A27: Food Cost objetivo (%) — se edita en el Resumen | I27: =Resumen!$C$16 -> 0.25
A28: PVP SUGERIDO (sin IVA) | J28: =IFERROR(J25/I27,"") -> 0
A29: Tipo de IVA (%) | I29: 0.1
A30: PVP CON IVA | J30: =IFERROR(J28*(1+I29),"") -> 0
A31: Margen bruto (€) | J31: =IFERROR(J28-J25,"") -> 0
A32: Margen bruto (%) | J32: =IFERROR((J28-J25)/J28,"")
A34: PVP actual en carta (sin IVA)
A35: FOOD COST REAL (%) | J35: =IFERROR(J25/I34,"")

Sheet 7. Pase
A1: 7. Pase — escribe aquí el nombre del pase
A2: Pase libre: rellena los ingredientes y el Resumen lo suma solo. Si lo dejas vacío, no cuenta.
L3: 📷 Foto del Plato
A4: Ingrediente | B4: Categoría | C4: Ud. Compra | D4: Precio/Ud (€) | E4: Cantidad | F4: Ud. Uso | G4: Factor | H4: Merma (%) | I4: Cant. Bruta | J4: Coste (€)
G5: =IF(C5&F5="","",IFERROR(VLOOKUP(C5&"→"&F5,Conversiones!$A$5:$B$67,2,FALSE),"?")) | H5: =IFERROR(VLOOKUP(B5,Mermas!$A$5:$C$25,2,FALSE),"") | I5: =IFERROR(IF(E5="","",E5/(1-H5)),"revisa merma") | J5: =IF(G5="?","revisa unidades",IFERROR(I5*D5/G5,""))
G6: =IF(C6&F6="","",IFERROR(VLOOKUP(C6&"→"&F6,Conversiones!$A$5:$B$67,2,FALSE),"?")) | H6: =IFERROR(VLOOKUP(B6,Mermas!$A$5:$C$25,2,FALSE),"") | I6: =IFERROR(IF(E6="","",E6/(1-H6)),"revisa merma") | J6: =IF(G6="?","revisa unidades",IFERROR(I6*D6/G6,""))
G7: =IF(C7&F7="","",IFERROR(VLOOKUP(C7&"→"&F7,Conversiones!$A$5:$B$67,2,FALSE),"?")) | H7: =IFERROR(VLOOKUP(B7,Mermas!$A$5:$C$25,2,FALSE),"") | I7: =IFERROR(IF(E7="","",E7/(1-H7)),"revisa merma") | J7: =IF(G7="?","revisa unidades",IFERROR(I7*D7/G7,""))
G8: =IF(C8&F8="","",IFERROR(VLOOKUP(C8&"→"&F8,Conversiones!$A$5:$B$67,2,FALSE),"?")) | H8: =IFERROR(VLOOKUP(B8,Mermas!$A$5:$C$25,2,FALSE),"") | I8: =IFERROR(IF(E8="","",E8/(1-H8)),"revisa merma") | J8: =IF(G8="?","revisa unidades",IFERROR(I8*D8/G8,"")) | L8: Foto del plato terminado: Revisar → Desproteger hoja, luego Insertar → Imagen
G9: =IF(C9&F9="","",IFERROR(VLOOKUP(C9&"→"&F9,Conversiones!$A$5:$B$67,2,FALSE),"?")) | H9: =IFERROR(VLOOKUP(B9,Mermas!$A$5:$C$25,2,FALSE),"") | I9: =IFERROR(IF(E9="","",E9/(1-H9)),"revisa merma") | J9: =IF(G9="?","revisa unidades",IFERROR(I9*D9/G9,""))
G10: =IF(C10&F10="","",IFERROR(VLOOKUP(C10&"→"&F10,Conversiones!$A$5:$B$67,2,FALSE),"?")) | H10: =IFERROR(VLOOKUP(B10,Mermas!$A$5:$C$25,2,FALSE),"") | I10: =IFERROR(IF(E10="","",E10/(1-H10)),"revisa merma") | J10: =IF(G10="?","revisa unidades",IFERROR(I10*D10/G10,""))
G11: =IF(C11&F11="","",IFERROR(VLOOKUP(C11&"→"&F11,Conversiones!$A$5:$B$67,2,FALSE),"?")) | H11: =IFERROR(VLOOKUP(B11,Mermas!$A$5:$C$25,2,FALSE),"") | I11: =IFERROR(IF(E11="","",E11/(1-H11)),"revisa merma") | J11: =IF(G11="?","revisa unidades",IFERROR(I11*D11/G11,""))
G12: =IF(C12&F12="","",IFERROR(VLOOKUP(C12&"→"&F12,Conversiones!$A$5:$B$67,2,FALSE),"?")) | H12: =IFERROR(VLOOKUP(B12,Mermas!$A$5:$C$25,2,FALSE),"") | I12: =IFERROR(IF(E12="","",E12/(1-H12)),"revisa merma") | J12: =IF(G12="?","revisa unidades",IFERROR(I12*D12/G12,""))
G13: =IF(C13&F13="","",IFERROR(VLOOKUP(C13&"→"&F13,Conversiones!$A$5:$B$67,2,FALSE),"?")) | H13: =IFERROR(VLOOKUP(B13,Mermas!$A$5:$C$25,2,FALSE),"") | I13: =IFERROR(IF(E13="","",E13/(1-H13)),"revisa merma") | J13: =IF(G13="?","revisa unidades",IFERROR(I13*D13/G13,""))
G14: =IF(C14&F14="","",IFERROR(VLOOKUP(C14&"→"&F14,Conversiones!$A$5:$B$67,2,FALSE),"?")) | H14: =IFERROR(VLOOKUP(B14,Mermas!$A$5:$C$25,2,FALSE),"") | I14: =IFERROR(IF(E14="","",E14/(1-H14)),"revisa merma") | J14: =IF(G14="?","revisa unidades",IFERROR(I14*D14/G14,""))
G15: =IF(C15&F15="","",IFERROR(VLOOKUP(C15&"→"&F15,Conversiones!$A$5:$B$67,2,FALSE),"?")) | H15: =IFERROR(VLOOKUP(B15,Mermas!$A$5:$C$25,2,FALSE),"") | I15: =IFERROR(IF(E15="","",E15/(1-H15)),"revisa merma") | J15: =IF(G15="?","revisa unidades",IFERROR(I15*D15/G15,""))
G16: =IF(C16&F16="","",IFERROR(VLOOKUP(C16&"→"&F16,Conversiones!$A$5:$B$67,2,FALSE),"?")) | H16: =IFERROR(VLOOKUP(B16,Mermas!$A$5:$C$25,2,FALSE),"") | I16: =IFERROR(IF(E16="","",E16/(1-H16)),"revisa merma") | J16: =IF(G16="?","revisa unidades",IFERROR(I16*D16/G16,""))
G17: =IF(C17&F17="","",IFERROR(VLOOKUP(C17&"→"&F17,Conversiones!$A$5:$B$67,2,FALSE),"?")) | H17: =IFERROR(VLOOKUP(B17,Mermas!$A$5:$C$25,2,FALSE),"") | I17: =IFERROR(IF(E17="","",E17/(1-H17)),"revisa merma") | J17: =IF(G17="?","revisa unidades",IFERROR(I17*D17/G17,""))
G18: =IF(C18&F18="","",IFERROR(VLOOKUP(C18&"→"&F18,Conversiones!$A$5:$B$67,2,FALSE),"?")) | H18: =IFERROR(VLOOKUP(B18,Mermas!$A$5:$C$25,2,FALSE),"") | I18: =IFERROR(IF(E18="","",E18/(1-H18)),"revisa merma") | J18: =IF(G18="?","revisa unidades",IFERROR(I18*D18/G18,""))
G19: =IF(C19&F19="","",IFERROR(VLOOKUP(C19&"→"&F19,Conversiones!$A$5:$B$67,2,FALSE),"?")) | H19: =IFERROR(VLOOKUP(B19,Mermas!$A$5:$C$25,2,FALSE),"") | I19: =IFERROR(IF(E19="","",E19/(1-H19)),"revisa merma") | J19: =IF(G19="?","revisa unidades",IFERROR(I19*D19/G19,""))
A21: COSTE TOTAL INGREDIENTES | J21: =SUM(J5:J19) -> 0
A22: Coste elaboración (%) | I22: 0.1 | J22: =J21*I22 -> 0
A23: COSTE TOTAL DEL PLATO | J23: =J21+J22 -> 0
A24: Nº de raciones | I24: 1
A25: COSTE POR RACIÓN | J25: =IFERROR(J23/I24,"") -> 0
A27: Food Cost objetivo (%) — se edita en el Resumen | I27: =Resumen!$C$16 -> 0.25
A28: PVP SUGERIDO (sin IVA) | J28: =IFERROR(J25/I27,"") -> 0
A29: Tipo de IVA (%) | I29: 0.1
A30: PVP CON IVA | J30: =IFERROR(J28*(1+I29),"") -> 0
A31: Margen bruto (€) | J31: =IFERROR(J28-J25,"") -> 0
A32: Margen bruto (%) | J32: =IFERROR((J28-J25)/J28,"")
A34: PVP actual en carta (sin IVA)
A35: FOOD COST REAL (%) | J35: =IFERROR(J25/I34,"")

Sheet 8. Pase
A1: 8. Pase — escribe aquí el nombre del pase
A2: Pase libre: rellena los ingredientes y el Resumen lo suma solo. Si lo dejas vacío, no cuenta.
L3: 📷 Foto del Plato
A4: Ingrediente | B4: Categoría | C4: Ud. Compra | D4: Precio/Ud (€) | E4: Cantidad | F4: Ud. Uso | G4: Factor | H4: Merma (%) | I4: Cant. Bruta | J4: Coste (€)
G5: =IF(C5&F5="","",IFERROR(VLOOKUP(C5&"→"&F5,Conversiones!$A$5:$B$67,2,FALSE),"?")) | H5: =IFERROR(VLOOKUP(B5,Mermas!$A$5:$C$25,2,FALSE),"") | I5: =IFERROR(IF(E5="","",E5/(1-H5)),"revisa merma") | J5: =IF(G5="?","revisa unidades",IFERROR(I5*D5/G5,""))
G6: =IF(C6&F6="","",IFERROR(VLOOKUP(C6&"→"&F6,Conversiones!$A$5:$B$67,2,FALSE),"?")) | H6: =IFERROR(VLOOKUP(B6,Mermas!$A$5:$C$25,2,FALSE),"") | I6: =IFERROR(IF(E6="","",E6/(1-H6)),"revisa merma") | J6: =IF(G6="?","revisa unidades",IFERROR(I6*D6/G6,""))
G7: =IF(C7&F7="","",IFERROR(VLOOKUP(C7&"→"&F7,Conversiones!$A$5:$B$67,2,FALSE),"?")) | H7: =IFERROR(VLOOKUP(B7,Mermas!$A$5:$C$25,2,FALSE),"") | I7: =IFERROR(IF(E7="","",E7/(1-H7)),"revisa merma") | J7: =IF(G7="?","revisa unidades",IFERROR(I7*D7/G7,""))
G8: =IF(C8&F8="","",IFERROR(VLOOKUP(C8&"→"&F8,Conversiones!$A$5:$B$67,2,FALSE),"?")) | H8: =IFERROR(VLOOKUP(B8,Mermas!$A$5:$C$25,2,FALSE),"") | I8: =IFERROR(IF(E8="","",E8/(1-H8)),"revisa merma") | J8: =IF(G8="?","revisa unidades",IFERROR(I8*D8/G8,"")) | L8: Foto del plato terminado: Revisar → Desproteger hoja, luego Insertar → Imagen
G9: =IF(C9&F9="","",IFERROR(VLOOKUP(C9&"→"&F9,Conversiones!$A$5:$B$67,2,FALSE),"?")) | H9: =IFERROR(VLOOKUP(B9,Mermas!$A$5:$C$25,2,FALSE),"") | I9: =IFERROR(IF(E9="","",E9/(1-H9)),"revisa merma") | J9: =IF(G9="?","revisa unidades",IFERROR(I9*D9/G9,""))
G10: =IF(C10&F10="","",IFERROR(VLOOKUP(C10&"→"&F10,Conversiones!$A$5:$B$67,2,FALSE),"?")) | H10: =IFERROR(VLOOKUP(B10,Mermas!$A$5:$C$25,2,FALSE),"") | I10: =IFERROR(IF(E10="","",E10/(1-H10)),"revisa merma") | J10: =IF(G10="?","revisa unidades",IFERROR(I10*D10/G10,""))
G11: =IF(C11&F11="","",IFERROR(VLOOKUP(C11&"→"&F11,Conversiones!$A$5:$B$67,2,FALSE),"?")) | H11: =IFERROR(VLOOKUP(B11,Mermas!$A$5:$C$25,2,FALSE),"") | I11: =IFERROR(IF(E11="","",E11/(1-H11)),"revisa merma") | J11: =IF(G11="?","revisa unidades",IFERROR(I11*D11/G11,""))
G12: =IF(C12&F12="","",IFERROR(VLOOKUP(C12&"→"&F12,Conversiones!$A$5:$B$67,2,FALSE),"?")) | H12: =IFERROR(VLOOKUP(B12,Mermas!$A$5:$C$25,2,FALSE),"") | I12: =IFERROR(IF(E12="","",E12/(1-H12)),"revisa merma") | J12: =IF(G12="?","revisa unidades",IFERROR(I12*D12/G12,""))
G13: =IF(C13&F13="","",IFERROR(VLOOKUP(C13&"→"&F13,Conversiones!$A$5:$B$67,2,FALSE),"?")) | H13: =IFERROR(VLOOKUP(B13,Mermas!$A$5:$C$25,2,FALSE),"") | I13: =IFERROR(IF(E13="","",E13/(1-H13)),"revisa merma") | J13: =IF(G13="?","revisa unidades",IFERROR(I13*D13/G13,""))
G14: =IF(C14&F14="","",IFERROR(VLOOKUP(C14&"→"&F14,Conversiones!$A$5:$B$67,2,FALSE),"?")) | H14: =IFERROR(VLOOKUP(B14,Mermas!$A$5:$C$25,2,FALSE),"") | I14: =IFERROR(IF(E14="","",E14/(1-H14)),"revisa merma") | J14: =IF(G14="?","revisa unidades",IFERROR(I14*D14/G14,""))
G15: =IF(C15&F15="","",IFERROR(VLOOKUP(C15&"→"&F15,Conversiones!$A$5:$B$67,2,FALSE),"?")) | H15: =IFERROR(VLOOKUP(B15,Mermas!$A$5:$C$25,2,FALSE),"") | I15: =IFERROR(IF(E15="","",E15/(1-H15)),"revisa merma") | J15: =IF(G15="?","revisa unidades",IFERROR(I15*D15/G15,""))
G16: =IF(C16&F16="","",IFERROR(VLOOKUP(C16&"→"&F16,Conversiones!$A$5:$B$67,2,FALSE),"?")) | H16: =IFERROR(VLOOKUP(B16,Mermas!$A$5:$C$25,2,FALSE),"") | I16: =IFERROR(IF(E16="","",E16/(1-H16)),"revisa merma") | J16: =IF(G16="?","revisa unidades",IFERROR(I16*D16/G16,""))
G17: =IF(C17&F17="","",IFERROR(VLOOKUP(C17&"→"&F17,Conversiones!$A$5:$B$67,2,FALSE),"?")) | H17: =IFERROR(VLOOKUP(B17,Mermas!$A$5:$C$25,2,FALSE),"") | I17: =IFERROR(IF(E17="","",E17/(1-H17)),"revisa merma") | J17: =IF(G17="?","revisa unidades",IFERROR(I17*D17/G17,""))
G18: =IF(C18&F18="","",IFERROR(VLOOKUP(C18&"→"&F18,Conversiones!$A$5:$B$67,2,FALSE),"?")) | H18: =IFERROR(VLOOKUP(B18,Mermas!$A$5:$C$25,2,FALSE),"") | I18: =IFERROR(IF(E18="","",E18/(1-H18)),"revisa merma") | J18: =IF(G18="?","revisa unidades",IFERROR(I18*D18/G18,""))
G19: =IF(C19&F19="","",IFERROR(VLOOKUP(C19&"→"&F19,Conversiones!$A$5:$B$67,2,FALSE),"?")) | H19: =IFERROR(VLOOKUP(B19,Mermas!$A$5:$C$25,2,FALSE),"") | I19: =IFERROR(IF(E19="","",E19/(1-H19)),"revisa merma") | J19: =IF(G19="?","revisa unidades",IFERROR(I19*D19/G19,""))
A21: COSTE TOTAL INGREDIENTES | J21: =SUM(J5:J19) -> 0
A22: Coste elaboración (%) | I22: 0.1 | J22: =J21*I22 -> 0
A23: COSTE TOTAL DEL PLATO | J23: =J21+J22 -> 0
A24: Nº de raciones | I24: 1
A25: COSTE POR RACIÓN | J25: =IFERROR(J23/I24,"") -> 0
A27: Food Cost objetivo (%) — se edita en el Resumen | I27: =Resumen!$C$16 -> 0.25
A28: PVP SUGERIDO (sin IVA) | J28: =IFERROR(J25/I27,"") -> 0
A29: Tipo de IVA (%) | I29: 0.1
A30: PVP CON IVA | J30: =IFERROR(J28*(1+I29),"") -> 0
A31: Margen bruto (€) | J31: =IFERROR(J28-J25,"") -> 0
A32: Margen bruto (%) | J32: =IFERROR((J28-J25)/J28,"")
A34: PVP actual en carta (sin IVA)
A35: FOOD COST REAL (%) | J35: =IFERROR(J25/I34,"")

Sheet 9. Pase
A1: 9. Pase — escribe aquí el nombre del pase
A2: Pase libre: rellena los ingredientes y el Resumen lo suma solo. Si lo dejas vacío, no cuenta.
L3: 📷 Foto del Plato
A4: Ingrediente | B4: Categoría | C4: Ud. Compra | D4: Precio/Ud (€) | E4: Cantidad | F4: Ud. Uso | G4: Factor | H4: Merma (%) | I4: Cant. Bruta | J4: Coste (€)
G5: =IF(C5&F5="","",IFERROR(VLOOKUP(C5&"→"&F5,Conversiones!$A$5:$B$67,2,FALSE),"?")) | H5: =IFERROR(VLOOKUP(B5,Mermas!$A$5:$C$25,2,FALSE),"") | I5: =IFERROR(IF(E5="","",E5/(1-H5)),"revisa merma") | J5: =IF(G5="?","revisa unidades",IFERROR(I5*D5/G5,""))
G6: =IF(C6&F6="","",IFERROR(VLOOKUP(C6&"→"&F6,Conversiones!$A$5:$B$67,2,FALSE),"?")) | H6: =IFERROR(VLOOKUP(B6,Mermas!$A$5:$C$25,2,FALSE),"") | I6: =IFERROR(IF(E6="","",E6/(1-H6)),"revisa merma") | J6: =IF(G6="?","revisa unidades",IFERROR(I6*D6/G6,""))
G7: =IF(C7&F7="","",IFERROR(VLOOKUP(C7&"→"&F7,Conversiones!$A$5:$B$67,2,FALSE),"?")) | H7: =IFERROR(VLOOKUP(B7,Mermas!$A$5:$C$25,2,FALSE),"") | I7: =IFERROR(IF(E7="","",E7/(1-H7)),"revisa merma") | J7: =IF(G7="?","revisa unidades",IFERROR(I7*D7/G7,""))
G8: =IF(C8&F8="","",IFERROR(VLOOKUP(C8&"→"&F8,Conversiones!$A$5:$B$67,2,FALSE),"?")) | H8: =IFERROR(VLOOKUP(B8,Mermas!$A$5:$C$25,2,FALSE),"") | I8: =IFERROR(IF(E8="","",E8/(1-H8)),"revisa merma") | J8: =IF(G8="?","revisa unidades",IFERROR(I8*D8/G8,"")) | L8: Foto del plato terminado: Revisar → Desproteger hoja, luego Insertar → Imagen
G9: =IF(C9&F9="","",IFERROR(VLOOKUP(C9&"→"&F9,Conversiones!$A$5:$B$67,2,FALSE),"?")) | H9: =IFERROR(VLOOKUP(B9,Mermas!$A$5:$C$25,2,FALSE),"") | I9: =IFERROR(IF(E9="","",E9/(1-H9)),"revisa merma") | J9: =IF(G9="?","revisa unidades",IFERROR(I9*D9/G9,""))
G10: =IF(C10&F10="","",IFERROR(VLOOKUP(C10&"→"&F10,Conversiones!$A$5:$B$67,2,FALSE),"?")) | H10: =IFERROR(VLOOKUP(B10,Mermas!$A$5:$C$25,2,FALSE),"") | I10: =IFERROR(IF(E10="","",E10/(1-H10)),"revisa merma") | J10: =IF(G10="?","revisa unidades",IFERROR(I10*D10/G10,""))
G11: =IF(C11&F11="","",IFERROR(VLOOKUP(C11&"→"&F11,Conversiones!$A$5:$B$67,2,FALSE),"?")) | H11: =IFERROR(VLOOKUP(B11,Mermas!$A$5:$C$25,2,FALSE),"") | I11: =IFERROR(IF(E11="","",E11/(1-H11)),"revisa merma") | J11: =IF(G11="?","revisa unidades",IFERROR(I11*D11/G11,""))
G12: =IF(C12&F12="","",IFERROR(VLOOKUP(C12&"→"&F12,Conversiones!$A$5:$B$67,2,FALSE),"?")) | H12: =IFERROR(VLOOKUP(B12,Mermas!$A$5:$C$25,2,FALSE),"") | I12: =IFERROR(IF(E12="","",E12/(1-H12)),"revisa merma") | J12: =IF(G12="?","revisa unidades",IFERROR(I12*D12/G12,""))
G13: =IF(C13&F13="","",IFERROR(VLOOKUP(C13&"→"&F13,Conversiones!$A$5:$B$67,2,FALSE),"?")) | H13: =IFERROR(VLOOKUP(B13,Mermas!$A$5:$C$25,2,FALSE),"") | I13: =IFERROR(IF(E13="","",E13/(1-H13)),"revisa merma") | J13: =IF(G13="?","revisa unidades",IFERROR(I13*D13/G13,""))
G14: =IF(C14&F14="","",IFERROR(VLOOKUP(C14&"→"&F14,Conversiones!$A$5:$B$67,2,FALSE),"?")) | H14: =IFERROR(VLOOKUP(B14,Mermas!$A$5:$C$25,2,FALSE),"") | I14: =IFERROR(IF(E14="","",E14/(1-H14)),"revisa merma") | J14: =IF(G14="?","revisa unidades",IFERROR(I14*D14/G14,""))
G15: =IF(C15&F15="","",IFERROR(VLOOKUP(C15&"→"&F15,Conversiones!$A$5:$B$67,2,FALSE),"?")) | H15: =IFERROR(VLOOKUP(B15,Mermas!$A$5:$C$25,2,FALSE),"") | I15: =IFERROR(IF(E15="","",E15/(1-H15)),"revisa merma") | J15: =IF(G15="?","revisa unidades",IFERROR(I15*D15/G15,""))
G16: =IF(C16&F16="","",IFERROR(VLOOKUP(C16&"→"&F16,Conversiones!$A$5:$B$67,2,FALSE),"?")) | H16: =IFERROR(VLOOKUP(B16,Mermas!$A$5:$C$25,2,FALSE),"") | I16: =IFERROR(IF(E16="","",E16/(1-H16)),"revisa merma") | J16: =IF(G16="?","revisa unidades",IFERROR(I16*D16/G16,""))
G17: =IF(C17&F17="","",IFERROR(VLOOKUP(C17&"→"&F17,Conversiones!$A$5:$B$67,2,FALSE),"?")) | H17: =IFERROR(VLOOKUP(B17,Mermas!$A$5:$C$25,2,FALSE),"") | I17: =IFERROR(IF(E17="","",E17/(1-H17)),"revisa merma") | J17: =IF(G17="?","revisa unidades",IFERROR(I17*D17/G17,""))
G18: =IF(C18&F18="","",IFERROR(VLOOKUP(C18&"→"&F18,Conversiones!$A$5:$B$67,2,FALSE),"?")) | H18: =IFERROR(VLOOKUP(B18,Mermas!$A$5:$C$25,2,FALSE),"") | I18: =IFERROR(IF(E18="","",E18/(1-H18)),"revisa merma") | J18: =IF(G18="?","revisa unidades",IFERROR(I18*D18/G18,""))
G19: =IF(C19&F19="","",IFERROR(VLOOKUP(C19&"→"&F19,Conversiones!$A$5:$B$67,2,FALSE),"?")) | H19: =IFERROR(VLOOKUP(B19,Mermas!$A$5:$C$25,2,FALSE),"") | I19: =IFERROR(IF(E19="","",E19/(1-H19)),"revisa merma") | J19: =IF(G19="?","revisa unidades",IFERROR(I19*D19/G19,""))
A21: COSTE TOTAL INGREDIENTES | J21: =SUM(J5:J19) -> 0
A22: Coste elaboración (%) | I22: 0.1 | J22: =J21*I22 -> 0
A23: COSTE TOTAL DEL PLATO | J23: =J21+J22 -> 0
A24: Nº de raciones | I24: 1
A25: COSTE POR RACIÓN | J25: =IFERROR(J23/I24,"") -> 0
A27: Food Cost objetivo (%) — se edita en el Resumen | I27: =Resumen!$C$16 -> 0.25
A28: PVP SUGERIDO (sin IVA) | J28: =IFERROR(J25/I27,"") -> 0
A29: Tipo de IVA (%) | I29: 0.1
A30: PVP CON IVA | J30: =IFERROR(J28*(1+I29),"") -> 0
A31: Margen bruto (€) | J31: =IFERROR(J28-J25,"") -> 0
A32: Margen bruto (%) | J32: =IFERROR((J28-J25)/J28,"")
A34: PVP actual en carta (sin IVA)
A35: FOOD COST REAL (%) | J35: =IFERROR(J25/I34,"")

Sheet Resumen
B2: Resumen — Menú Degustación
B4: Pase | C4: Coste (€)
B5: 1. Aperitivo | C5: =IF('1. Aperitivo'!$J$21=0,"",'1. Aperitivo'!$J$25) -> 7.1918555
B6: 2. Entrante | C6: =IF('2. Entrante'!$J$21=0,"",'2. Entrante'!$J$25) -> 11.461334
B7: 3. Pescado | C7: =IF('3. Pescado'!$J$21=0,"",'3. Pescado'!$J$25) -> 10.63411
B8: 4. Carne | C8: =IF('4. Carne'!$J$21=0,"",'4. Carne'!$J$25) -> 5.8449473
B9: 5. Postre | C9: =IF('5. Postre'!$J$21=0,"",'5. Postre'!$J$25) -> 3.1568617
B10: 6. Pase | C10: =IF('6. Pase'!$J$21=0,"",'6. Pase'!$J$25)
B11: 7. Pase | C11: =IF('7. Pase'!$J$21=0,"",'7. Pase'!$J$25)
B12: 8. Pase | C12: =IF('8. Pase'!$J$21=0,"",'8. Pase'!$J$25)
B13: 9. Pase | C13: =IF('9. Pase'!$J$21=0,"",'9. Pase'!$J$25)
B14: COSTE TOTAL MENÚ | C14: =SUM(C5:C13) -> 38.289108
B16: Food Cost objetivo (%) — el único food cost del libro: los pases lo leen de aquí | C16: 0.25
B17: PVP SUGERIDO (sin IVA) | C17: =IFERROR(C14/C16,"") -> 153.15643
B18: Tipo de IVA (%) | C18: 0.1
B19: PVP CON IVA | C19: =IFERROR(C17*(1+C18),"") -> 168.47208
B21: Los pases sin ingredientes no suman: el menú puede tener de 5 a 9 pases sin tocar una sola fórmula.

Sheet Conversiones
A1: Tabla de conversión Ud. Compra → Ud. Uso
A2: La usa la columna «Factor» de cada escandallo. Puedes añadir parejas al final, hasta la fila 67: la clave se escribe «compra→uso».
A4: Conversión (compra→uso) | B4: Factor | C4: Qué significa
A5: kg→kg | B5: 1 | C5: misma unidad
A6: kg→g | B6: 1000 | C6: 1 kg = 1.000 g
A7: g→g | B7: 1 | C7: misma unidad
A8: g→kg | B8: 0.001 | C8: 1 g = 0,001 kg
A9: L→L | B9: 1 | C9: misma unidad
A10: L→ml | B10: 1000 | C10: 1 L = 1.000 ml
A11: L→cl | B11: 100 | C11: 1 L = 100 cl
A12: ml→ml | B12: 1 | C12: misma unidad
A13: ml→L | B13: 0.001 | C13: 1 ml = 0,001 L
A14: ml→cl | B14: 0.1 | C14: 1 ml = 0,1 cl
A15: cl→cl | B15: 1 | C15: misma unidad
A16: cl→ml | B16: 10 | C16: 1 cl = 10 ml
... A37: sobre→g | B37: 10 | C37: sobre ≈ 10 g

Sheet Mermas
A1: Mermas de referencia por categoría
A2: La «típica» es la que se precarga en las filas vacías del escandallo al elegir categoría. Ajústala a tu proveedor.
A3: Mide tu merma real con la plantilla 12 (Test de Rendimiento) y llévala a «Merma (%)» de la ficha.
A4: Categoría | B4: Merma típica | C4: Mínima | D4: Máxima
A5: Carne roja | B5: 0.2 | C5: 0.15 | D5: 0.25
A6: Aves | B6: 0.25 | C6: 0.2 | D6: 0.3
A7: Pescado | B7: 0.35 | C7: 0.3 | D7: 0.45
A8: Marisco | B8: 0.45 | C8: 0.35 | D8: 0.55
A9: Verdura hoja | B9: 0.25 | C9: 0.2 | D9: 0.35
A10: Verdura raíz | B10: 0.12 | C10: 0.08 | D10: 0.18
A11: Verdura fruto | B11: 0.1 | C11: 0.06 | D11: 0.15
A12: Fruta | B12: 0.15 | C12: 0.1 | D12: 0.25
A13: Lácteos | B13: 0.03 | C13: 0.01 | D13: 0.05
A14: Secos/granos | B14: 0.02 | C14: 0.01 | D14: 0.04
A15: Congelados | B15: 0.07 | C15: 0.03 | D15: 0.1
A16: Pan/bollería | B16: 0.05 | C16: 0.02 | D16: 0.1
... A25: Pasta/arroz | B25: 0.02 | C25: 0.01 | D25: 0.04
