Workbook

Sheet Instrucciones
B2: 📋 Escandallo — Pastelería y Repostería
B3: Kit de Escandallos Pro — AI Chef Pro
B4: www.aichef.pro
B6: Cómo usar esta plantilla
B8: ▸ Una pestaña por elaboración: tarta de chocolate (12 raciones), croissants (20 unidades) y macarons (30 unidades).
B9: ▸ El escandallo es de la TANDA COMPLETA. «Rendimiento (uds por tanda)» reparte el coste: «COSTE POR UNIDAD» y «PVP POR UNIDAD» son los que van a la vitrina, no el total de la tanda.
B10: ▸ Mermas propias de obrador ya cargadas: 12 % en el chocolate de cobertura (pérdida de temperado) y 8 % en las harinas (evaporación de horneado).
B11: ▸ El colorante se escandalla por bote: 2 g de un bote de 50 g = 0,04 botes, no 0,1 «unidades».
B12: ▸ Food cost objetivo de referencia en pastelería: 20-30 %.
B13: ▸ Las celdas VERDES son las editables; el resto son fórmulas.
B15: Columnas de la hoja de escandallo
B17: ▸ Ingrediente: el producto tal como lo compras.
... B67: Versión 2.1 · septiembre 2026 · aichef.pro/kit-escandallos · info@aichef.pro

Sheet Tarta Chocolate
A1: Tarta de Chocolate 70% — 12 raciones
A2: El escandallo es de la TANDA COMPLETA: el «Rendimiento» reparte el coste entre las unidades que salen. Las celdas verdes son las editables.
L3: 📷 Foto de la Elaboración
A4: Ingrediente | B4: Categoría | C4: Ud. Compra | D4: Precio/Ud (€) | E4: Cantidad | F4: Ud. Uso | G4: Factor | H4: Merma (%) | I4: Cant. Bruta | J4: Coste (€)
A5: Chocolate negro 70% | B5: Chocolate/cacao | C5: kg | D5: 18 | E5: 0.4 | F5: kg | G5: =IF(C5&F5="","",IFERROR(VLOOKUP(C5&"→"&F5,Conversiones!$A$5:$B$67,2,FALSE),"?")) -> 1 | H5: 0.12 | I5: =IFERROR(IF(E5="","",E5/(1-H5)),"revisa merma") -> 0.45454545 | J5: =IF(G5="?","revisa unidades",IFERROR(I5*D5/G5,"")) -> 8.1818182
A6: Mantequilla | B6: Lácteos | C6: kg | D6: 9 | E6: 0.25 | F6: kg | G6: =IF(C6&F6="","",IFERROR(VLOOKUP(C6&"→"&F6,Conversiones!$A$5:$B$67,2,FALSE),"?")) -> 1 | H6: 0.03 | I6: =IFERROR(IF(E6="","",E6/(1-H6)),"revisa merma") -> 0.25773196 | J6: =IF(G6="?","revisa unidades",IFERROR(I6*D6/G6,"")) -> 2.3195876
A7: Huevos (unidades) | B7: Huevos | C7: docena | D7: 3.6 | E7: 6 | F7: ud | G7: =IF(C7&F7="","",IFERROR(VLOOKUP(C7&"→"&F7,Conversiones!$A$5:$B$67,2,FALSE),"?")) -> 12 | H7: 0 | I7: =IFERROR(IF(E7="","",E7/(1-H7)),"revisa merma") -> 6 | J7: =IF(G7="?","revisa unidades",IFERROR(I7*D7/G7,"")) -> 1.8
A8: Azúcar | B8: Secos/granos | C8: kg | D8: 1.2 | E8: 0.2 | F8: kg | G8: =IF(C8&F8="","",IFERROR(VLOOKUP(C8&"→"&F8,Conversiones!$A$5:$B$67,2,FALSE),"?")) -> 1 | H8: 0.02 | I8: =IFERROR(IF(E8="","",E8/(1-H8)),"revisa merma") -> 0.20408163 | J8: =IF(G8="?","revisa unidades",IFERROR(I8*D8/G8,"")) -> 0.24489796 | L8: Foto de la elaboración terminada: Revisar → Desproteger hoja, luego Insertar → Imagen
A9: Harina floja | B9: Secos/granos | C9: kg | D9: 0.9 | E9: 0.12 | F9: kg | G9: =IF(C9&F9="","",IFERROR(VLOOKUP(C9&"→"&F9,Conversiones!$A$5:$B$67,2,FALSE),"?")) -> 1 | H9: 0.08 | I9: =IFERROR(IF(E9="","",E9/(1-H9)),"revisa merma") -> 0.13043478 | J9: =IF(G9="?","revisa unidades",IFERROR(I9*D9/G9,"")) -> 0.1173913
A10: Nata 35% MG | B10: Lácteos | C10: L | D10: 3.8 | E10: 0.2 | F10: L | G10: =IF(C10&F10="","",IFERROR(VLOOKUP(C10&"→"&F10,Conversiones!$A$5:$B$67,2,FALSE),"?")) -> 1 | H10: 0.03 | I10: =IFERROR(IF(E10="","",E10/(1-H10)),"revisa merma") -> 0.20618557 | J10: =IF(G10="?","revisa unidades",IFERROR(I10*D10/G10,"")) -> 0.78350515
A11: Cacao en polvo | B11: Chocolate/cacao | C11: kg | D11: 12 | E11: 0.03 | F11: kg | G11: =IF(C11&F11="","",IFERROR(VLOOKUP(C11&"→"&F11,Conversiones!$A$5:$B$67,2,FALSE),"?")) -> 1 | H11: 0.05 | I11: =IFERROR(IF(E11="","",E11/(1-H11)),"revisa merma") -> 0.031578947 | J11: =IF(G11="?","revisa unidades",IFERROR(I11*D11/G11,"")) -> 0.37894737
A12: Sal | B12: Secos/granos | C12: kg | D12: 0.6 | E12: 0.003 | F12: kg | G12: =IF(C12&F12="","",IFERROR(VLOOKUP(C12&"→"&F12,Conversiones!$A$5:$B$67,2,FALSE),"?")) -> 1 | H12: 0.02 | I12: =IFERROR(IF(E12="","",E12/(1-H12)),"revisa merma") -> 0.0030612245 | J12: =IF(G12="?","revisa unidades",IFERROR(I12*D12/G12,"")) -> 0.0018367347
G13: =IF(C13&F13="","",IFERROR(VLOOKUP(C13&"→"&F13,Conversiones!$A$5:$B$67,2,FALSE),"?")) | H13: =IFERROR(VLOOKUP(B13,Mermas!$A$5:$C$25,2,FALSE),"") | I13: =IFERROR(IF(E13="","",E13/(1-H13)),"revisa merma") | J13: =IF(G13="?","revisa unidades",IFERROR(I13*D13/G13,""))
G14: =IF(C14&F14="","",IFERROR(VLOOKUP(C14&"→"&F14,Conversiones!$A$5:$B$67,2,FALSE),"?")) | H14: =IFERROR(VLOOKUP(B14,Mermas!$A$5:$C$25,2,FALSE),"") | I14: =IFERROR(IF(E14="","",E14/(1-H14)),"revisa merma") | J14: =IF(G14="?","revisa unidades",IFERROR(I14*D14/G14,""))
G15: =IF(C15&F15="","",IFERROR(VLOOKUP(C15&"→"&F15,Conversiones!$A$5:$B$67,2,FALSE),"?")) | H15: =IFERROR(VLOOKUP(B15,Mermas!$A$5:$C$25,2,FALSE),"") | I15: =IFERROR(IF(E15="","",E15/(1-H15)),"revisa merma") | J15: =IF(G15="?","revisa unidades",IFERROR(I15*D15/G15,""))
G16: =IF(C16&F16="","",IFERROR(VLOOKUP(C16&"→"&F16,Conversiones!$A$5:$B$67,2,FALSE),"?")) | H16: =IFERROR(VLOOKUP(B16,Mermas!$A$5:$C$25,2,FALSE),"") | I16: =IFERROR(IF(E16="","",E16/(1-H16)),"revisa merma") | J16: =IF(G16="?","revisa unidades",IFERROR(I16*D16/G16,""))
G17: =IF(C17&F17="","",IFERROR(VLOOKUP(C17&"→"&F17,Conversiones!$A$5:$B$67,2,FALSE),"?")) | H17: =IFERROR(VLOOKUP(B17,Mermas!$A$5:$C$25,2,FALSE),"") | I17: =IFERROR(IF(E17="","",E17/(1-H17)),"revisa merma") | J17: =IF(G17="?","revisa unidades",IFERROR(I17*D17/G17,""))
G18: =IF(C18&F18="","",IFERROR(VLOOKUP(C18&"→"&F18,Conversiones!$A$5:$B$67,2,FALSE),"?")) | H18: =IFERROR(VLOOKUP(B18,Mermas!$A$5:$C$25,2,FALSE),"") | I18: =IFERROR(IF(E18="","",E18/(1-H18)),"revisa merma") | J18: =IF(G18="?","revisa unidades",IFERROR(I18*D18/G18,""))
G19: =IF(C19&F19="","",IFERROR(VLOOKUP(C19&"→"&F19,Conversiones!$A$5:$B$67,2,FALSE),"?")) | H19: =IFERROR(VLOOKUP(B19,Mermas!$A$5:$C$25,2,FALSE),"") | I19: =IFERROR(IF(E19="","",E19/(1-H19)),"revisa merma") | J19: =IF(G19="?","revisa unidades",IFERROR(I19*D19/G19,""))
G20: =IF(C20&F20="","",IFERROR(VLOOKUP(C20&"→"&F20,Conversiones!$A$5:$B$67,2,FALSE),"?")) | H20: =IFERROR(VLOOKUP(B20,Mermas!$A$5:$C$25,2,FALSE),"") | I20: =IFERROR(IF(E20="","",E20/(1-H20)),"revisa merma") | J20: =IF(G20="?","revisa unidades",IFERROR(I20*D20/G20,""))
G21: =IF(C21&F21="","",IFERROR(VLOOKUP(C21&"→"&F21,Conversiones!$A$5:$B$67,2,FALSE),"?")) | H21: =IFERROR(VLOOKUP(B21,Mermas!$A$5:$C$25,2,FALSE),"") | I21: =IFERROR(IF(E21="","",E21/(1-H21)),"revisa merma") | J21: =IF(G21="?","revisa unidades",IFERROR(I21*D21/G21,""))
G22: =IF(C22&F22="","",IFERROR(VLOOKUP(C22&"→"&F22,Conversiones!$A$5:$B$67,2,FALSE),"?")) | H22: =IFERROR(VLOOKUP(B22,Mermas!$A$5:$C$25,2,FALSE),"") | I22: =IFERROR(IF(E22="","",E22/(1-H22)),"revisa merma") | J22: =IF(G22="?","revisa unidades",IFERROR(I22*D22/G22,""))
A24: COSTE TOTAL INGREDIENTES | J24: =SUM(J5:J22) -> 13.827984
A25: Coste elaboración (%) | I25: 0.1 | J25: =J24*I25 -> 1.3827984
A26: COSTE TOTAL DE LA TANDA | J26: =J24+J25 -> 15.210783
A27: Rendimiento (uds por tanda) | I27: 12
A28: COSTE POR UNIDAD | J28: =IFERROR(J26/I27,"") -> 1.2675652
A30: Food Cost objetivo (%) | I30: 0.25
A31: PVP POR UNIDAD (sin IVA) | J31: =IFERROR(J28/I30,"") -> 5.0702609
A32: Tipo de IVA (%) | I32: 0.1
A33: PVP POR UNIDAD (con IVA) | J33: =IFERROR(J31*(1+I32),"") -> 5.577287
A34: Margen bruto (€) | J34: =IFERROR(J31-J28,"") -> 3.8026957
A35: Margen bruto (%) | J35: =IFERROR((J31-J28)/J31,"") -> 0.75
A37: PVP actual en carta (sin IVA)
A38: FOOD COST REAL (%) | J38: =IFERROR(J28/I37,"")

Sheet Croissants
A1: Croissants de Mantequilla — 20 unidades
A2: El escandallo es de la TANDA COMPLETA: el «Rendimiento» reparte el coste entre las unidades que salen. Las celdas verdes son las editables.
L3: 📷 Foto de la Elaboración
A4: Ingrediente | B4: Categoría | C4: Ud. Compra | D4: Precio/Ud (€) | E4: Cantidad | F4: Ud. Uso | G4: Factor | H4: Merma (%) | I4: Cant. Bruta | J4: Coste (€)
A5: Harina de fuerza | B5: Secos/granos | C5: kg | D5: 1.1 | E5: 0.5 | F5: kg | G5: =IF(C5&F5="","",IFERROR(VLOOKUP(C5&"→"&F5,Conversiones!$A$5:$B$67,2,FALSE),"?")) -> 1 | H5: 0.08 | I5: =IFERROR(IF(E5="","",E5/(1-H5)),"revisa merma") -> 0.54347826 | J5: =IF(G5="?","revisa unidades",IFERROR(I5*D5/G5,"")) -> 0.59782609
A6: Mantequilla seca (82% MG) | B6: Lácteos | C6: kg | D6: 12 | E6: 0.28 | F6: kg | G6: =IF(C6&F6="","",IFERROR(VLOOKUP(C6&"→"&F6,Conversiones!$A$5:$B$67,2,FALSE),"?")) -> 1 | H6: 0.03 | I6: =IFERROR(IF(E6="","",E6/(1-H6)),"revisa merma") -> 0.28865979 | J6: =IF(G6="?","revisa unidades",IFERROR(I6*D6/G6,"")) -> 3.4639175
A7: Leche entera | B7: Lácteos | C7: L | D7: 1.1 | E7: 0.15 | F7: L | G7: =IF(C7&F7="","",IFERROR(VLOOKUP(C7&"→"&F7,Conversiones!$A$5:$B$67,2,FALSE),"?")) -> 1 | H7: 0.03 | I7: =IFERROR(IF(E7="","",E7/(1-H7)),"revisa merma") -> 0.15463918 | J7: =IF(G7="?","revisa unidades",IFERROR(I7*D7/G7,"")) -> 0.17010309
A8: Azúcar | B8: Secos/granos | C8: kg | D8: 1.2 | E8: 0.06 | F8: kg | G8: =IF(C8&F8="","",IFERROR(VLOOKUP(C8&"→"&F8,Conversiones!$A$5:$B$67,2,FALSE),"?")) -> 1 | H8: 0.02 | I8: =IFERROR(IF(E8="","",E8/(1-H8)),"revisa merma") -> 0.06122449 | J8: =IF(G8="?","revisa unidades",IFERROR(I8*D8/G8,"")) -> 0.073469388 | L8: Foto de la elaboración terminada: Revisar → Desproteger hoja, luego Insertar → Imagen
A9: Levadura fresca | B9: Secos/granos | C9: kg | D9: 5 | E9: 0.02 | F9: kg | G9: =IF(C9&F9="","",IFERROR(VLOOKUP(C9&"→"&F9,Conversiones!$A$5:$B$67,2,FALSE),"?")) -> 1 | H9: 0.05 | I9: =IFERROR(IF(E9="","",E9/(1-H9)),"revisa merma") -> 0.021052632 | J9: =IF(G9="?","revisa unidades",IFERROR(I9*D9/G9,"")) -> 0.10526316
A10: Sal | B10: Secos/granos | C10: kg | D10: 0.6 | E10: 0.01 | F10: kg | G10: =IF(C10&F10="","",IFERROR(VLOOKUP(C10&"→"&F10,Conversiones!$A$5:$B$67,2,FALSE),"?")) -> 1 | H10: 0.02 | I10: =IFERROR(IF(E10="","",E10/(1-H10)),"revisa merma") -> 0.010204082 | J10: =IF(G10="?","revisa unidades",IFERROR(I10*D10/G10,"")) -> 0.006122449
A11: Huevo (para pintar) | B11: Huevos | C11: docena | D11: 3.6 | E11: 1 | F11: ud | G11: =IF(C11&F11="","",IFERROR(VLOOKUP(C11&"→"&F11,Conversiones!$A$5:$B$67,2,FALSE),"?")) -> 12 | H11: 0 | I11: =IFERROR(IF(E11="","",E11/(1-H11)),"revisa merma") -> 1 | J11: =IF(G11="?","revisa unidades",IFERROR(I11*D11/G11,"")) -> 0.3
G12: =IF(C12&F12="","",IFERROR(VLOOKUP(C12&"→"&F12,Conversiones!$A$5:$B$67,2,FALSE),"?")) | H12: =IFERROR(VLOOKUP(B12,Mermas!$A$5:$C$25,2,FALSE),"") | I12: =IFERROR(IF(E12="","",E12/(1-H12)),"revisa merma") | J12: =IF(G12="?","revisa unidades",IFERROR(I12*D12/G12,""))
G13: =IF(C13&F13="","",IFERROR(VLOOKUP(C13&"→"&F13,Conversiones!$A$5:$B$67,2,FALSE),"?")) | H13: =IFERROR(VLOOKUP(B13,Mermas!$A$5:$C$25,2,FALSE),"") | I13: =IFERROR(IF(E13="","",E13/(1-H13)),"revisa merma") | J13: =IF(G13="?","revisa unidades",IFERROR(I13*D13/G13,""))
G14: =IF(C14&F14="","",IFERROR(VLOOKUP(C14&"→"&F14,Conversiones!$A$5:$B$67,2,FALSE),"?")) | H14: =IFERROR(VLOOKUP(B14,Mermas!$A$5:$C$25,2,FALSE),"") | I14: =IFERROR(IF(E14="","",E14/(1-H14)),"revisa merma") | J14: =IF(G14="?","revisa unidades",IFERROR(I14*D14/G14,""))
G15: =IF(C15&F15="","",IFERROR(VLOOKUP(C15&"→"&F15,Conversiones!$A$5:$B$67,2,FALSE),"?")) | H15: =IFERROR(VLOOKUP(B15,Mermas!$A$5:$C$25,2,FALSE),"") | I15: =IFERROR(IF(E15="","",E15/(1-H15)),"revisa merma") | J15: =IF(G15="?","revisa unidades",IFERROR(I15*D15/G15,""))
G16: =IF(C16&F16="","",IFERROR(VLOOKUP(C16&"→"&F16,Conversiones!$A$5:$B$67,2,FALSE),"?")) | H16: =IFERROR(VLOOKUP(B16,Mermas!$A$5:$C$25,2,FALSE),"") | I16: =IFERROR(IF(E16="","",E16/(1-H16)),"revisa merma") | J16: =IF(G16="?","revisa unidades",IFERROR(I16*D16/G16,""))
G17: =IF(C17&F17="","",IFERROR(VLOOKUP(C17&"→"&F17,Conversiones!$A$5:$B$67,2,FALSE),"?")) | H17: =IFERROR(VLOOKUP(B17,Mermas!$A$5:$C$25,2,FALSE),"") | I17: =IFERROR(IF(E17="","",E17/(1-H17)),"revisa merma") | J17: =IF(G17="?","revisa unidades",IFERROR(I17*D17/G17,""))
G18: =IF(C18&F18="","",IFERROR(VLOOKUP(C18&"→"&F18,Conversiones!$A$5:$B$67,2,FALSE),"?")) | H18: =IFERROR(VLOOKUP(B18,Mermas!$A$5:$C$25,2,FALSE),"") | I18: =IFERROR(IF(E18="","",E18/(1-H18)),"revisa merma") | J18: =IF(G18="?","revisa unidades",IFERROR(I18*D18/G18,""))
G19: =IF(C19&F19="","",IFERROR(VLOOKUP(C19&"→"&F19,Conversiones!$A$5:$B$67,2,FALSE),"?")) | H19: =IFERROR(VLOOKUP(B19,Mermas!$A$5:$C$25,2,FALSE),"") | I19: =IFERROR(IF(E19="","",E19/(1-H19)),"revisa merma") | J19: =IF(G19="?","revisa unidades",IFERROR(I19*D19/G19,""))
G20: =IF(C20&F20="","",IFERROR(VLOOKUP(C20&"→"&F20,Conversiones!$A$5:$B$67,2,FALSE),"?")) | H20: =IFERROR(VLOOKUP(B20,Mermas!$A$5:$C$25,2,FALSE),"") | I20: =IFERROR(IF(E20="","",E20/(1-H20)),"revisa merma") | J20: =IF(G20="?","revisa unidades",IFERROR(I20*D20/G20,""))
G21: =IF(C21&F21="","",IFERROR(VLOOKUP(C21&"→"&F21,Conversiones!$A$5:$B$67,2,FALSE),"?")) | H21: =IFERROR(VLOOKUP(B21,Mermas!$A$5:$C$25,2,FALSE),"") | I21: =IFERROR(IF(E21="","",E21/(1-H21)),"revisa merma") | J21: =IF(G21="?","revisa unidades",IFERROR(I21*D21/G21,""))
A23: COSTE TOTAL INGREDIENTES | J23: =SUM(J5:J21) -> 4.7167017
A24: Coste elaboración (%) | I24: 0.1 | J24: =J23*I24 -> 0.47167017
A25: COSTE TOTAL DE LA TANDA | J25: =J23+J24 -> 5.1883719
A26: Rendimiento (uds por tanda) | I26: 20
A27: COSTE POR UNIDAD | J27: =IFERROR(J25/I26,"") -> 0.25941859
A29: Food Cost objetivo (%) | I29: 0.25
A30: PVP POR UNIDAD (sin IVA) | J30: =IFERROR(J27/I29,"") -> 1.0376744
A31: Tipo de IVA (%) | I31: 0.1
A32: PVP POR UNIDAD (con IVA) | J32: =IFERROR(J30*(1+I31),"") -> 1.1414418
A33: Margen bruto (€) | J33: =IFERROR(J30-J27,"") -> 0.77825578
A34: Margen bruto (%) | J34: =IFERROR((J30-J27)/J30,"") -> 0.75
A36: PVP actual en carta (sin IVA)
A37: FOOD COST REAL (%) | J37: =IFERROR(J27/I36,"")

Sheet Macarons
A1: Macarons de Frambuesa — 30 unidades
A2: El escandallo es de la TANDA COMPLETA: el «Rendimiento» reparte el coste entre las unidades que salen. Las celdas verdes son las editables.
L3: 📷 Foto de la Elaboración
A4: Ingrediente | B4: Categoría | C4: Ud. Compra | D4: Precio/Ud (€) | E4: Cantidad | F4: Ud. Uso | G4: Factor | H4: Merma (%) | I4: Cant. Bruta | J4: Coste (€)
A5: Harina de almendra | B5: Secos/granos | C5: kg | D5: 14 | E5: 0.15 | F5: kg | G5: =IF(C5&F5="","",IFERROR(VLOOKUP(C5&"→"&F5,Conversiones!$A$5:$B$67,2,FALSE),"?")) -> 1 | H5: 0.02 | I5: =IFERROR(IF(E5="","",E5/(1-H5)),"revisa merma") -> 0.15306122 | J5: =IF(G5="?","revisa unidades",IFERROR(I5*D5/G5,"")) -> 2.1428571
A6: Azúcar glas | B6: Secos/granos | C6: kg | D6: 2.5 | E6: 0.15 | F6: kg | G6: =IF(C6&F6="","",IFERROR(VLOOKUP(C6&"→"&F6,Conversiones!$A$5:$B$67,2,FALSE),"?")) -> 1 | H6: 0.02 | I6: =IFERROR(IF(E6="","",E6/(1-H6)),"revisa merma") -> 0.15306122 | J6: =IF(G6="?","revisa unidades",IFERROR(I6*D6/G6,"")) -> 0.38265306
A7: Claras de huevo | B7: Huevos | C7: kg | D7: 6 | E7: 0.11 | F7: kg | G7: =IF(C7&F7="","",IFERROR(VLOOKUP(C7&"→"&F7,Conversiones!$A$5:$B$67,2,FALSE),"?")) -> 1 | H7: 0.05 | I7: =IFERROR(IF(E7="","",E7/(1-H7)),"revisa merma") -> 0.11578947 | J7: =IF(G7="?","revisa unidades",IFERROR(I7*D7/G7,"")) -> 0.69473684
A8: Azúcar | B8: Secos/granos | C8: kg | D8: 1.2 | E8: 0.15 | F8: kg | G8: =IF(C8&F8="","",IFERROR(VLOOKUP(C8&"→"&F8,Conversiones!$A$5:$B$67,2,FALSE),"?")) -> 1 | H8: 0.02 | I8: =IFERROR(IF(E8="","",E8/(1-H8)),"revisa merma") -> 0.15306122 | J8: =IF(G8="?","revisa unidades",IFERROR(I8*D8/G8,"")) -> 0.18367347 | L8: Foto de la elaboración terminada: Revisar → Desproteger hoja, luego Insertar → Imagen
A9: Frambuesa congelada | B9: Congelados | C9: kg | D9: 9 | E9: 0.1 | F9: kg | G9: =IF(C9&F9="","",IFERROR(VLOOKUP(C9&"→"&F9,Conversiones!$A$5:$B$67,2,FALSE),"?")) -> 1 | H9: 0.07 | I9: =IFERROR(IF(E9="","",E9/(1-H9)),"revisa merma") -> 0.10752688 | J9: =IF(G9="?","revisa unidades",IFERROR(I9*D9/G9,"")) -> 0.96774194
A10: Chocolate blanco | B10: Chocolate/cacao | C10: kg | D10: 15 | E10: 0.08 | F10: kg | G10: =IF(C10&F10="","",IFERROR(VLOOKUP(C10&"→"&F10,Conversiones!$A$5:$B$67,2,FALSE),"?")) -> 1 | H10: 0.12 | I10: =IFERROR(IF(E10="","",E10/(1-H10)),"revisa merma") -> 0.090909091 | J10: =IF(G10="?","revisa unidades",IFERROR(I10*D10/G10,"")) -> 1.3636364
A11: Colorante rojo (bote 50 g · 2 g/tanda) | B11: Secos/granos | C11: ud | D11: 4 | E11: 0.04 | F11: ud | G11: =IF(C11&F11="","",IFERROR(VLOOKUP(C11&"→"&F11,Conversiones!$A$5:$B$67,2,FALSE),"?")) -> 1 | H11: 0 | I11: =IFERROR(IF(E11="","",E11/(1-H11)),"revisa merma") -> 0.04 | J11: =IF(G11="?","revisa unidades",IFERROR(I11*D11/G11,"")) -> 0.16
G12: =IF(C12&F12="","",IFERROR(VLOOKUP(C12&"→"&F12,Conversiones!$A$5:$B$67,2,FALSE),"?")) | H12: =IFERROR(VLOOKUP(B12,Mermas!$A$5:$C$25,2,FALSE),"") | I12: =IFERROR(IF(E12="","",E12/(1-H12)),"revisa merma") | J12: =IF(G12="?","revisa unidades",IFERROR(I12*D12/G12,""))
G13: =IF(C13&F13="","",IFERROR(VLOOKUP(C13&"→"&F13,Conversiones!$A$5:$B$67,2,FALSE),"?")) | H13: =IFERROR(VLOOKUP(B13,Mermas!$A$5:$C$25,2,FALSE),"") | I13: =IFERROR(IF(E13="","",E13/(1-H13)),"revisa merma") | J13: =IF(G13="?","revisa unidades",IFERROR(I13*D13/G13,""))
G14: =IF(C14&F14="","",IFERROR(VLOOKUP(C14&"→"&F14,Conversiones!$A$5:$B$67,2,FALSE),"?")) | H14: =IFERROR(VLOOKUP(B14,Mermas!$A$5:$C$25,2,FALSE),"") | I14: =IFERROR(IF(E14="","",E14/(1-H14)),"revisa merma") | J14: =IF(G14="?","revisa unidades",IFERROR(I14*D14/G14,""))
G15: =IF(C15&F15="","",IFERROR(VLOOKUP(C15&"→"&F15,Conversiones!$A$5:$B$67,2,FALSE),"?")) | H15: =IFERROR(VLOOKUP(B15,Mermas!$A$5:$C$25,2,FALSE),"") | I15: =IFERROR(IF(E15="","",E15/(1-H15)),"revisa merma") | J15: =IF(G15="?","revisa unidades",IFERROR(I15*D15/G15,""))
G16: =IF(C16&F16="","",IFERROR(VLOOKUP(C16&"→"&F16,Conversiones!$A$5:$B$67,2,FALSE),"?")) | H16: =IFERROR(VLOOKUP(B16,Mermas!$A$5:$C$25,2,FALSE),"") | I16: =IFERROR(IF(E16="","",E16/(1-H16)),"revisa merma") | J16: =IF(G16="?","revisa unidades",IFERROR(I16*D16/G16,""))
G17: =IF(C17&F17="","",IFERROR(VLOOKUP(C17&"→"&F17,Conversiones!$A$5:$B$67,2,FALSE),"?")) | H17: =IFERROR(VLOOKUP(B17,Mermas!$A$5:$C$25,2,FALSE),"") | I17: =IFERROR(IF(E17="","",E17/(1-H17)),"revisa merma") | J17: =IF(G17="?","revisa unidades",IFERROR(I17*D17/G17,""))
G18: =IF(C18&F18="","",IFERROR(VLOOKUP(C18&"→"&F18,Conversiones!$A$5:$B$67,2,FALSE),"?")) | H18: =IFERROR(VLOOKUP(B18,Mermas!$A$5:$C$25,2,FALSE),"") | I18: =IFERROR(IF(E18="","",E18/(1-H18)),"revisa merma") | J18: =IF(G18="?","revisa unidades",IFERROR(I18*D18/G18,""))
G19: =IF(C19&F19="","",IFERROR(VLOOKUP(C19&"→"&F19,Conversiones!$A$5:$B$67,2,FALSE),"?")) | H19: =IFERROR(VLOOKUP(B19,Mermas!$A$5:$C$25,2,FALSE),"") | I19: =IFERROR(IF(E19="","",E19/(1-H19)),"revisa merma") | J19: =IF(G19="?","revisa unidades",IFERROR(I19*D19/G19,""))
G20: =IF(C20&F20="","",IFERROR(VLOOKUP(C20&"→"&F20,Conversiones!$A$5:$B$67,2,FALSE),"?")) | H20: =IFERROR(VLOOKUP(B20,Mermas!$A$5:$C$25,2,FALSE),"") | I20: =IFERROR(IF(E20="","",E20/(1-H20)),"revisa merma") | J20: =IF(G20="?","revisa unidades",IFERROR(I20*D20/G20,""))
G21: =IF(C21&F21="","",IFERROR(VLOOKUP(C21&"→"&F21,Conversiones!$A$5:$B$67,2,FALSE),"?")) | H21: =IFERROR(VLOOKUP(B21,Mermas!$A$5:$C$25,2,FALSE),"") | I21: =IFERROR(IF(E21="","",E21/(1-H21)),"revisa merma") | J21: =IF(G21="?","revisa unidades",IFERROR(I21*D21/G21,""))
A23: COSTE TOTAL INGREDIENTES | J23: =SUM(J5:J21) -> 5.8952988
A24: Coste elaboración (%) | I24: 0.1 | J24: =J23*I24 -> 0.58952988
A25: COSTE TOTAL DE LA TANDA | J25: =J23+J24 -> 6.4848287
A26: Rendimiento (uds por tanda) | I26: 30
A27: COSTE POR UNIDAD | J27: =IFERROR(J25/I26,"") -> 0.21616096
A29: Food Cost objetivo (%) | I29: 0.25
A30: PVP POR UNIDAD (sin IVA) | J30: =IFERROR(J27/I29,"") -> 0.86464383
A31: Tipo de IVA (%) | I31: 0.1
A32: PVP POR UNIDAD (con IVA) | J32: =IFERROR(J30*(1+I31),"") -> 0.95110821
A33: Margen bruto (€) | J33: =IFERROR(J30-J27,"") -> 0.64848287
A34: Margen bruto (%) | J34: =IFERROR((J30-J27)/J30,"") -> 0.75
A36: PVP actual en carta (sin IVA)
A37: FOOD COST REAL (%) | J37: =IFERROR(J27/I36,"")

Sheet Conversiones
A1: Tabla de conversión Ud. Compra → Ud. Uso
A2: La usa la columna «Factor» de cada escandallo. Puedes añadir parejas al final, hasta la fila 67: la clave se escribe «compra→uso».
A4: Conversión (compra→uso) | B4: Factor | C4: Qué significa
A5: kg→kg | B5: 1 | C5: misma unidad
A6: kg→g | B6: 1000 | C6: 1 kg = 1.000 g
A7: g→g | B7: 1 | C7: misma unidad
A8: g→kg | B8: 0.001 | C8: 1 g = 0,001 kg
A9: L→L | B9: 1 | C9: misma unidad
A10: L→ml | B10: 1000 | C10: 1 L = 1.000 ml
A11: L→cl | B11: 100 | C11: 1 L = 100 cl
A12: ml→ml | B12: 1 | C12: misma unidad
A13: ml→L | B13: 0.001 | C13: 1 ml = 0,001 L
A14: ml→cl | B14: 0.1 | C14: 1 ml = 0,1 cl
A15: cl→cl | B15: 1 | C15: misma unidad
A16: cl→ml | B16: 10 | C16: 1 cl = 10 ml
... A37: sobre→g | B37: 10 | C37: sobre ≈ 10 g

Sheet Mermas
A1: Mermas de referencia por categoría
A2: La «típica» es la que se precarga en las filas vacías del escandallo al elegir categoría. Ajústala a tu proveedor.
A3: Mide tu merma real con la plantilla 12 (Test de Rendimiento) y llévala a «Merma (%)» de la ficha.
A4: Categoría | B4: Merma típica | C4: Mínima | D4: Máxima
A5: Carne roja | B5: 0.2 | C5: 0.15 | D5: 0.25
A6: Aves | B6: 0.25 | C6: 0.2 | D6: 0.3
A7: Pescado | B7: 0.35 | C7: 0.3 | D7: 0.45
A8: Marisco | B8: 0.45 | C8: 0.35 | D8: 0.55
A9: Verdura hoja | B9: 0.25 | C9: 0.2 | D9: 0.35
A10: Verdura raíz | B10: 0.12 | C10: 0.08 | D10: 0.18
A11: Verdura fruto | B11: 0.1 | C11: 0.06 | D11: 0.15
A12: Fruta | B12: 0.15 | C12: 0.1 | D12: 0.25
A13: Lácteos | B13: 0.03 | C13: 0.01 | D13: 0.05
A14: Secos/granos | B14: 0.02 | C14: 0.01 | D14: 0.04
A15: Congelados | B15: 0.07 | C15: 0.03 | D15: 0.1
A16: Pan/bollería | B16: 0.05 | C16: 0.02 | D16: 0.1
... A25: Pasta/arroz | B25: 0.02 | C25: 0.01 | D25: 0.04
