Workbook

Sheet Instrucciones
B2: 📋 Escandallo — Catering por Persona
B3: Kit de Escandallos Pro — AI Chef Pro
B4: www.aichef.pro
B6: Cómo usar esta plantilla
B8: ▸ La pestaña «Cocktail (por persona)» se escandalla POR COMENSAL. El número de comensales se escribe UNA sola vez, en «Presupuesto»!C5: si lo metes también en el escandallo, facturas el evento por partida doble.
B9: ▸ «Presupuesto» es la hoja INTERNA: enseña tus costes y tu margen. El bloque de PVP de la hoja de escandallo es orientativo y sólo cubre la materia prima; el precio al cliente sale del Presupuesto.
B10: ▸ El personal ya no es una constante escondida: camareros = REDONDEAR.MÁS(comensales ÷ comensales por camarero) × horas × €/hora, más el jefe de sala. Todos los parámetros son celdas verdes.
B11: ▸ «Checklist Evento»: marca con ✓ en el desplegable de la última columna; el contador del final lleva la cuenta sobre el total.
B12: ▸ «Presupuesto Cliente» es la ÚNICA hoja que se le enseña al cliente: concepto, comensales y precio con IVA. Sin costes ni margen.
B13: ▸ Food cost objetivo de referencia en catering: 30-40 %.
B14: ▸ Las celdas VERDES son las editables; el resto son fórmulas.
B16: Columnas de la hoja de escandallo
... B68: Versión 2.1 · septiembre 2026 · aichef.pro/kit-escandallos · info@aichef.pro

Sheet Cocktail (por persona)
A1: Catering Cocktail — Coste por Persona
A2: AVISO: todas las cantidades son POR COMENSAL. El número de comensales se escribe UNA sola vez, en «Presupuesto»!C5 — no lo multipliques aquí o facturarás el evento dos veces.
L3: 📷 Foto del Montaje
A4: Ingrediente | B4: Categoría | C4: Ud. Compra | D4: Precio/Ud (€) | E4: Cantidad | F4: Ud. Uso | G4: Factor | H4: Merma (%) | I4: Cant. Bruta | J4: Coste (€)
A5: Jamón ibérico (loncheado) | B5: Carne roja | C5: kg | D5: 65 | E5: 0.04 | F5: kg | G5: =IF(C5&F5="","",IFERROR(VLOOKUP(C5&"→"&F5,Conversiones!$A$5:$B$67,2,FALSE),"?")) -> 1 | H5: 0.05 | I5: =IFERROR(IF(E5="","",E5/(1-H5)),"revisa merma") -> 0.042105263 | J5: =IF(G5="?","revisa unidades",IFERROR(I5*D5/G5,"")) -> 2.7368421
A6: Queso manchego curado | B6: Lácteos | C6: kg | D6: 16 | E6: 0.04 | F6: kg | G6: =IF(C6&F6="","",IFERROR(VLOOKUP(C6&"→"&F6,Conversiones!$A$5:$B$67,2,FALSE),"?")) -> 1 | H6: 0.1 | I6: =IFERROR(IF(E6="","",E6/(1-H6)),"revisa merma") -> 0.044444444 | J6: =IF(G6="?","revisa unidades",IFERROR(I6*D6/G6,"")) -> 0.71111111
A7: Salmón ahumado | B7: Pescado | C7: kg | D7: 35 | E7: 0.03 | F7: kg | G7: =IF(C7&F7="","",IFERROR(VLOOKUP(C7&"→"&F7,Conversiones!$A$5:$B$67,2,FALSE),"?")) -> 1 | H7: 0.1 | I7: =IFERROR(IF(E7="","",E7/(1-H7)),"revisa merma") -> 0.033333333 | J7: =IF(G7="?","revisa unidades",IFERROR(I7*D7/G7,"")) -> 1.1666667
A8: Langostino cocido | B8: Marisco | C8: kg | D8: 18 | E8: 0.05 | F8: kg | G8: =IF(C8&F8="","",IFERROR(VLOOKUP(C8&"→"&F8,Conversiones!$A$5:$B$67,2,FALSE),"?")) -> 1 | H8: 0.45 | I8: =IFERROR(IF(E8="","",E8/(1-H8)),"revisa merma") -> 0.090909091 | J8: =IF(G8="?","revisa unidades",IFERROR(I8*D8/G8,"")) -> 1.6363636 | L8: Foto del montaje terminado: Revisar → Desproteger hoja, luego Insertar → Imagen
A9: Croquetas (ud) | B9: Congelados | C9: ud | D9: 0.35 | E9: 3 | F9: ud | G9: =IF(C9&F9="","",IFERROR(VLOOKUP(C9&"→"&F9,Conversiones!$A$5:$B$67,2,FALSE),"?")) -> 1 | H9: 0.05 | I9: =IFERROR(IF(E9="","",E9/(1-H9)),"revisa merma") -> 3.1578947 | J9: =IF(G9="?","revisa unidades",IFERROR(I9*D9/G9,"")) -> 1.1052632
A10: Mini quiche (ud) | B10: Congelados | C10: ud | D10: 0.45 | E10: 2 | F10: ud | G10: =IF(C10&F10="","",IFERROR(VLOOKUP(C10&"→"&F10,Conversiones!$A$5:$B$67,2,FALSE),"?")) -> 1 | H10: 0.05 | I10: =IFERROR(IF(E10="","",E10/(1-H10)),"revisa merma") -> 2.1052632 | J10: =IF(G10="?","revisa unidades",IFERROR(I10*D10/G10,"")) -> 0.94736842
A11: Pan mini (ud) | B11: Pan/bollería | C11: ud | D11: 0.15 | E11: 3 | F11: ud | G11: =IF(C11&F11="","",IFERROR(VLOOKUP(C11&"→"&F11,Conversiones!$A$5:$B$67,2,FALSE),"?")) -> 1 | H11: 0.1 | I11: =IFERROR(IF(E11="","",E11/(1-H11)),"revisa merma") -> 3.3333333 | J11: =IF(G11="?","revisa unidades",IFERROR(I11*D11/G11,"")) -> 0.5
A12: Fruta variada | B12: Fruta | C12: kg | D12: 3.5 | E12: 0.06 | F12: kg | G12: =IF(C12&F12="","",IFERROR(VLOOKUP(C12&"→"&F12,Conversiones!$A$5:$B$67,2,FALSE),"?")) -> 1 | H12: 0.15 | I12: =IFERROR(IF(E12="","",E12/(1-H12)),"revisa merma") -> 0.070588235 | J12: =IF(G12="?","revisa unidades",IFERROR(I12*D12/G12,"")) -> 0.24705882
A13: Bebida (vino + agua) | B13: Bebidas/licores | C13: L | D13: 3 | E13: 0.35 | F13: L | G13: =IF(C13&F13="","",IFERROR(VLOOKUP(C13&"→"&F13,Conversiones!$A$5:$B$67,2,FALSE),"?")) -> 1 | H13: 0.05 | I13: =IFERROR(IF(E13="","",E13/(1-H13)),"revisa merma") -> 0.36842105 | J13: =IF(G13="?","revisa unidades",IFERROR(I13*D13/G13,"")) -> 1.1052632
A14: Café | B14: Bebidas/licores | C14: ud | D14: 0.2 | E14: 1 | F14: ud | G14: =IF(C14&F14="","",IFERROR(VLOOKUP(C14&"→"&F14,Conversiones!$A$5:$B$67,2,FALSE),"?")) -> 1 | H14: 0 | I14: =IFERROR(IF(E14="","",E14/(1-H14)),"revisa merma") -> 1 | J14: =IF(G14="?","revisa unidades",IFERROR(I14*D14/G14,"")) -> 0.2
G15: =IF(C15&F15="","",IFERROR(VLOOKUP(C15&"→"&F15,Conversiones!$A$5:$B$67,2,FALSE),"?")) | H15: =IFERROR(VLOOKUP(B15,Mermas!$A$5:$C$25,2,FALSE),"") | I15: =IFERROR(IF(E15="","",E15/(1-H15)),"revisa merma") | J15: =IF(G15="?","revisa unidades",IFERROR(I15*D15/G15,""))
G16: =IF(C16&F16="","",IFERROR(VLOOKUP(C16&"→"&F16,Conversiones!$A$5:$B$67,2,FALSE),"?")) | H16: =IFERROR(VLOOKUP(B16,Mermas!$A$5:$C$25,2,FALSE),"") | I16: =IFERROR(IF(E16="","",E16/(1-H16)),"revisa merma") | J16: =IF(G16="?","revisa unidades",IFERROR(I16*D16/G16,""))
G17: =IF(C17&F17="","",IFERROR(VLOOKUP(C17&"→"&F17,Conversiones!$A$5:$B$67,2,FALSE),"?")) | H17: =IFERROR(VLOOKUP(B17,Mermas!$A$5:$C$25,2,FALSE),"") | I17: =IFERROR(IF(E17="","",E17/(1-H17)),"revisa merma") | J17: =IF(G17="?","revisa unidades",IFERROR(I17*D17/G17,""))
G18: =IF(C18&F18="","",IFERROR(VLOOKUP(C18&"→"&F18,Conversiones!$A$5:$B$67,2,FALSE),"?")) | H18: =IFERROR(VLOOKUP(B18,Mermas!$A$5:$C$25,2,FALSE),"") | I18: =IFERROR(IF(E18="","",E18/(1-H18)),"revisa merma") | J18: =IF(G18="?","revisa unidades",IFERROR(I18*D18/G18,""))
G19: =IF(C19&F19="","",IFERROR(VLOOKUP(C19&"→"&F19,Conversiones!$A$5:$B$67,2,FALSE),"?")) | H19: =IFERROR(VLOOKUP(B19,Mermas!$A$5:$C$25,2,FALSE),"") | I19: =IFERROR(IF(E19="","",E19/(1-H19)),"revisa merma") | J19: =IF(G19="?","revisa unidades",IFERROR(I19*D19/G19,""))
G20: =IF(C20&F20="","",IFERROR(VLOOKUP(C20&"→"&F20,Conversiones!$A$5:$B$67,2,FALSE),"?")) | H20: =IFERROR(VLOOKUP(B20,Mermas!$A$5:$C$25,2,FALSE),"") | I20: =IFERROR(IF(E20="","",E20/(1-H20)),"revisa merma") | J20: =IF(G20="?","revisa unidades",IFERROR(I20*D20/G20,""))
G21: =IF(C21&F21="","",IFERROR(VLOOKUP(C21&"→"&F21,Conversiones!$A$5:$B$67,2,FALSE),"?")) | H21: =IFERROR(VLOOKUP(B21,Mermas!$A$5:$C$25,2,FALSE),"") | I21: =IFERROR(IF(E21="","",E21/(1-H21)),"revisa merma") | J21: =IF(G21="?","revisa unidades",IFERROR(I21*D21/G21,""))
G22: =IF(C22&F22="","",IFERROR(VLOOKUP(C22&"→"&F22,Conversiones!$A$5:$B$67,2,FALSE),"?")) | H22: =IFERROR(VLOOKUP(B22,Mermas!$A$5:$C$25,2,FALSE),"") | I22: =IFERROR(IF(E22="","",E22/(1-H22)),"revisa merma") | J22: =IF(G22="?","revisa unidades",IFERROR(I22*D22/G22,""))
G23: =IF(C23&F23="","",IFERROR(VLOOKUP(C23&"→"&F23,Conversiones!$A$5:$B$67,2,FALSE),"?")) | H23: =IFERROR(VLOOKUP(B23,Mermas!$A$5:$C$25,2,FALSE),"") | I23: =IFERROR(IF(E23="","",E23/(1-H23)),"revisa merma") | J23: =IF(G23="?","revisa unidades",IFERROR(I23*D23/G23,""))
G24: =IF(C24&F24="","",IFERROR(VLOOKUP(C24&"→"&F24,Conversiones!$A$5:$B$67,2,FALSE),"?")) | H24: =IFERROR(VLOOKUP(B24,Mermas!$A$5:$C$25,2,FALSE),"") | I24: =IFERROR(IF(E24="","",E24/(1-H24)),"revisa merma") | J24: =IF(G24="?","revisa unidades",IFERROR(I24*D24/G24,""))
A26: COSTE TOTAL INGREDIENTES | J26: =SUM(J5:J24) -> 10.355937
A27: Coste elaboración (%) | I27: 0.1 | J27: =J26*I27 -> 1.0355937
A28: COSTE TOTAL POR PERSONA | J28: =J26+J27 -> 11.391531
A29: Nº de raciones | I29: 1
A30: COSTE POR RACIÓN | J30: =IFERROR(J28/I29,"") -> 11.391531
A32: Food Cost objetivo (%) | I32: 0.35
A33: PVP SUGERIDO (sin IVA) | J33: =IFERROR(J30/I32,"") -> 32.547231
A34: Tipo de IVA (%) | I34: 0.1
A35: PVP CON IVA | J35: =IFERROR(J33*(1+I34),"") -> 35.801954
A36: Margen bruto (€) | J36: =IFERROR(J33-J30,"") -> 21.1557
A37: Margen bruto (%) | J37: =IFERROR((J33-J30)/J33,"") -> 0.65
A39: PVP actual en carta (sin IVA)
A40: FOOD COST REAL (%) | J40: =IFERROR(J30/I39,"")
A42: PVP orientativo: cubre sólo la materia prima. El precio que se le da al cliente sale de la hoja «Presupuesto», que suma personal, menaje, transporte y montaje.

Sheet Presupuesto
B2: Presupuesto de Catering — hoja INTERNA
B3: Enseña tus costes y tu margen: NO se le manda al cliente. Para eso está «Presupuesto Cliente».
B4: Concepto | C4: Importe (€)
B5: Número de comensales | C5: 50
B6: Coste de alimentación por comensal (€) — enlazado al escandallo «Cocktail (por persona)» | C6: ='Cocktail (por persona)'!$J$30 -> 11.391531
B7: Coste total de alimentación (€) | C7: =IFERROR(C5*C6,"") -> 569.57654
B8: Personal de servicio
B9: Comensales por camarero | C9: 22
B10: Nº de camareros (calculado) | C10: =IFERROR(ROUNDUP(C5/C9,0),"") -> 3
B11: Horas por camarero | C11: 5
B12: Coste por hora de camarero (€) | C12: 16
B13: Horas de jefe de sala | C13: 6
B14: Coste por hora de jefe de sala (€) | C14: 22
B15: COSTE DE PERSONAL (€) | C15: =IFERROR(C10*C11*C12+C13*C14,"") -> 372
B16: Menaje, transporte y montaje
B17: Menaje y desechables por comensal (€) | C17: 1.2
B18: Coste de menaje (€) | C18: =IFERROR(C5*C17,"") -> 60
B19: Transporte y logística (€) | C19: 150
B20: Montaje y desmontaje (€) | C20: 200
B21: COSTE TOTAL DEL EVENTO (€) | C21: =IFERROR(C7+C15+C18+C19+C20,"") -> 1351.5765
B22: Coste por comensal (€) | C22: =IFERROR(C21/C5,"") -> 27.031531
B23: Precio de venta
B24: Food Cost objetivo de la COMIDA (%) | C24: 0.35
B25: Margen sobre servicios (%) | C25: 0.2
B26: PVP de la alimentación (€) | C26: =IFERROR(C7/C24,"") -> 1627.3615
B27: PVP de los servicios (personal, menaje, transporte, montaje) (€) | C27: =IFERROR((C15+C18+C19+C20)*(1+C25),"") -> 938.4
B28: Mínimo de facturación por evento (€) | C28: 600
B29: PVP DEL EVENTO (sin IVA) | C29: =IFERROR(MAX(C26+C27,C28),"") -> 2565.7615
B30: PVP POR PERSONA (sin IVA) | C30: =IFERROR(C29/C5,"") -> 51.315231
B31: Tipo de IVA (%) | C31: 0.1
B32: PVP POR PERSONA (con IVA) | C32: =IFERROR(C30*(1+C31),"") -> 56.446754
B33: PRESUPUESTO TOTAL (con IVA) | C33: =IFERROR(C29*(1+C31),"") -> 2822.3377
B34: Margen bruto del evento (€) | C34: =IFERROR(C29-C21,"") -> 1214.185
B35: Food cost de la comida sobre lo facturado (%) | C35: =IFERROR(C7/C29,"") -> 0.22199122
B37: El food cost objetivo se aplica SÓLO a la comida (C7 ÷ C24). El personal, el menaje, el transporte y el montaje no llevan food cost: van a coste más el margen de servicios de C25. Aplicar el 35 % al coste total multiplicaba el presupuesto por 2,9 y perdías el evento. C35 te enseña qué food cost de comida te queda sobre el total facturado. Ojo con los eventos pequeños: el transporte, el montaje y el jefe de sala son fijos, así que con 10 comensales el precio por persona se dispara por encima de los 100 €. No es un error de la hoja: es lo que cuesta de verdad mover un catering para diez. Ajusta esas tres celdas verdes a la realidad de tu evento pequeño.

Sheet Checklist Evento
A1: Checklist de Evento — Catering
A2: Marca con ✓ en la columna «✓ Completada» (es un desplegable: ✓ / — / N/A). El contador del final cuenta sólo los ✓. Las cuatro filas en blanco del final son para tus propias tareas y también cuentan.
A4: # | B4: Tarea | C4: Bloque | D4: Responsable | E4: Cuándo | F4: ✓ Completada
A5: 1 | B5: Confirmar por escrito el nº definitivo de comensales | C5: Timings | D5: Comercial | E5: D-7
A6: 2 | B6: Cerrar menú definitivo y recoger alérgenos e intolerancias | C6: Timings | D6: Jefe de cocina | E6: D-7
A7: 3 | B7: Cursar pedido a proveedores con fecha y hora de entrega | C7: Timings | D7: Compras | E7: D-5
A8: 4 | B8: Confirmar hora de acceso al espacio y muelle de carga | C8: Timings | D8: Producción | E8: D-3
A9: 5 | B9: Producir las elaboraciones que aguantan 24 h | C9: Timings | D9: Jefe de cocina | E9: D-1
A10: 6 | B10: Cargar el vehículo siguiendo la hoja de ruta | C10: Timings | D10: Producción | E10: D · mañana
A11: 7 | B11: Montaje en el espacio (buffet, barras, office) | C11: Timings | D11: Jefe de sala | E11: D · H-3 h
A12: 8 | B12: Briefing con el equipo de sala y reparto de rangos | C12: Timings | D12: Jefe de sala | E12: D · H-1 h
A13: 9 | B13: Servicio | C13: Timings | D13: Todo el equipo | E13: D · hora H
A14: 10 | B14: Desmontaje, recuento de material y salida | C14: Timings | D14: Jefe de sala | E14: D · H+1 h
A15: 11 | B15: Nº de camareros según el Presupuesto (1 por cada 22 pax) | C15: Personal | D15: Jefe de sala | E15: D-3
A16: 12 | B16: Jefe de sala asignado, con el teléfono del cliente | C16: Personal | D16: Comercial | E16: D-3
... A36: 32 | B36: Registro sanitario y carnés de manipulador al día | C36: Permisos | D36: Administración | E36: D-7
A42: Tareas completadas: | D42: =COUNTIF(F5:F40,"✓") -> 0 | E42: de | F42: =COUNTIF(B5:B40,"?*") -> 32
A44: Responsable del evento:
A45: Fecha del evento:

Sheet Presupuesto Cliente
A2: Propuesta de Catering
B3: Cliente:
B4: Evento y fecha:
B5: Lugar:
B7: Concepto | C7: Comensales | D7: Precio por persona (IVA incl.) | E7: Total (€)
B8: Servicio de catering cocktail — menú acordado | C8: =IFERROR('Presupuesto'!C5,"") -> 50 | D8: =IFERROR('Presupuesto'!C32,"") -> 56.446754 | E8: =IF(B8="","",IFERROR(C8*D8,0)) -> 2822.3377
E9: =IF(B9="","",IFERROR(C9*D9,0))
E10: =IF(B10="","",IFERROR(C10*D10,0))
E11: =IF(B11="","",IFERROR(C11*D11,0))
B13: TOTAL (IVA incluido) | E13: =IFERROR(SUM(E8:E11),"") -> 2822.3377
A15: Presupuesto válido 30 días desde su emisión. Precios con IVA incluido. El número definitivo de comensales se confirma 7 días antes del evento; a partir de esa fecha se factura el número confirmado.
B17: — Kit de Escandallos Pro · AI Chef Pro · aichef.pro

Sheet Conversiones
A1: Tabla de conversión Ud. Compra → Ud. Uso
A2: La usa la columna «Factor» de cada escandallo. Puedes añadir parejas al final, hasta la fila 67: la clave se escribe «compra→uso».
A4: Conversión (compra→uso) | B4: Factor | C4: Qué significa
A5: kg→kg | B5: 1 | C5: misma unidad
A6: kg→g | B6: 1000 | C6: 1 kg = 1.000 g
A7: g→g | B7: 1 | C7: misma unidad
A8: g→kg | B8: 0.001 | C8: 1 g = 0,001 kg
A9: L→L | B9: 1 | C9: misma unidad
A10: L→ml | B10: 1000 | C10: 1 L = 1.000 ml
A11: L→cl | B11: 100 | C11: 1 L = 100 cl
A12: ml→ml | B12: 1 | C12: misma unidad
A13: ml→L | B13: 0.001 | C13: 1 ml = 0,001 L
A14: ml→cl | B14: 0.1 | C14: 1 ml = 0,1 cl
A15: cl→cl | B15: 1 | C15: misma unidad
A16: cl→ml | B16: 10 | C16: 1 cl = 10 ml
... A37: sobre→g | B37: 10 | C37: sobre ≈ 10 g

Sheet Mermas
A1: Mermas de referencia por categoría
A2: La «típica» es la que se precarga en las filas vacías del escandallo al elegir categoría. Ajústala a tu proveedor.
A3: Mide tu merma real con la plantilla 12 (Test de Rendimiento) y llévala a «Merma (%)» de la ficha.
A4: Categoría | B4: Merma típica | C4: Mínima | D4: Máxima
A5: Carne roja | B5: 0.2 | C5: 0.15 | D5: 0.25
A6: Aves | B6: 0.25 | C6: 0.2 | D6: 0.3
A7: Pescado | B7: 0.35 | C7: 0.3 | D7: 0.45
A8: Marisco | B8: 0.45 | C8: 0.35 | D8: 0.55
A9: Verdura hoja | B9: 0.25 | C9: 0.2 | D9: 0.35
A10: Verdura raíz | B10: 0.12 | C10: 0.08 | D10: 0.18
A11: Verdura fruto | B11: 0.1 | C11: 0.06 | D11: 0.15
A12: Fruta | B12: 0.15 | C12: 0.1 | D12: 0.25
A13: Lácteos | B13: 0.03 | C13: 0.01 | D13: 0.05
A14: Secos/granos | B14: 0.02 | C14: 0.01 | D14: 0.04
A15: Congelados | B15: 0.07 | C15: 0.03 | D15: 0.1
A16: Pan/bollería | B16: 0.05 | C16: 0.02 | D16: 0.1
... A25: Pasta/arroz | B25: 0.02 | C25: 0.01 | D25: 0.04
