Workbook

Sheet Instrucciones
B2: 📋 Escandallo — Cafetería y Brunch
B3: Kit de Escandallos Pro — AI Chef Pro
B4: www.aichef.pro
B6: Cómo usar esta plantilla
B8: ▸ 4 recetas típicas de brunch y cafetería: tostada de aguacate, açaí bowl, eggs benedict y carrot cake.
B9: ▸ La carrot cake se escandalla por tanda: 12 raciones en «Nº de raciones» y el coste por porción sale solo.
B10: ▸ Food cost objetivo de referencia en cafetería: 25-30 %.
B11: ▸ Las celdas VERDES son las editables; el resto son fórmulas.
B13: Columnas de la hoja de escandallo
B15: ▸ Ingrediente: el producto tal como lo compras.
B16: ▸ Categoría: familia del ingrediente (desplegable). Es la que precarga la merma en las filas vacías.
B17: ▸ Ud. Compra: la unidad en la que COMPRAS (kg, L, docena, manojo…).
... B65: Versión 2.1 · septiembre 2026 · aichef.pro/kit-escandallos · info@aichef.pro

Sheet Tostada Aguacate
A1: Tostada de Aguacate con Huevo Poché
A2: Introduce tus ingredientes y cantidades. Las celdas verdes son editables.
L3: 📷 Foto del Plato
A4: Ingrediente | B4: Categoría | C4: Ud. Compra | D4: Precio/Ud (€) | E4: Cantidad | F4: Ud. Uso | G4: Factor | H4: Merma (%) | I4: Cant. Bruta | J4: Coste (€)
A5: Pan de masa madre (rebanada gruesa) | B5: Pan/bollería | C5: ud | D5: 0.6 | E5: 1 | F5: ud | G5: =IF(C5&F5="","",IFERROR(VLOOKUP(C5&"→"&F5,Conversiones!$A$5:$B$67,2,FALSE),"?")) -> 1 | H5: 0 | I5: =IFERROR(IF(E5="","",E5/(1-H5)),"revisa merma") -> 1 | J5: =IF(G5="?","revisa unidades",IFERROR(I5*D5/G5,"")) -> 0.6
A6: Aguacate Hass (½ pieza) | B6: Fruta | C6: ud | D6: 1.5 | E6: 0.4 | F6: ud | G6: =IF(C6&F6="","",IFERROR(VLOOKUP(C6&"→"&F6,Conversiones!$A$5:$B$67,2,FALSE),"?")) -> 1 | H6: 0.28 | I6: =IFERROR(IF(E6="","",E6/(1-H6)),"revisa merma") -> 0.55555556 | J6: =IF(G6="?","revisa unidades",IFERROR(I6*D6/G6,"")) -> 0.83333333
A7: Huevo campero | B7: Huevos | C7: docena | D7: 4.2 | E7: 1 | F7: ud | G7: =IF(C7&F7="","",IFERROR(VLOOKUP(C7&"→"&F7,Conversiones!$A$5:$B$67,2,FALSE),"?")) -> 12 | H7: 0 | I7: =IFERROR(IF(E7="","",E7/(1-H7)),"revisa merma") -> 1 | J7: =IF(G7="?","revisa unidades",IFERROR(I7*D7/G7,"")) -> 0.35
A8: Tomate cherry | B8: Verdura fruto | C8: kg | D8: 4 | E8: 0.04 | F8: kg | G8: =IF(C8&F8="","",IFERROR(VLOOKUP(C8&"→"&F8,Conversiones!$A$5:$B$67,2,FALSE),"?")) -> 1 | H8: 0.05 | I8: =IFERROR(IF(E8="","",E8/(1-H8)),"revisa merma") -> 0.042105263 | J8: =IF(G8="?","revisa unidades",IFERROR(I8*D8/G8,"")) -> 0.16842105 | L8: Foto del plato terminado: Revisar → Desproteger hoja, luego Insertar → Imagen
A9: Semillas mix | B9: Secos/granos | C9: kg | D9: 10 | E9: 0.01 | F9: kg | G9: =IF(C9&F9="","",IFERROR(VLOOKUP(C9&"→"&F9,Conversiones!$A$5:$B$67,2,FALSE),"?")) -> 1 | H9: 0.02 | I9: =IFERROR(IF(E9="","",E9/(1-H9)),"revisa merma") -> 0.010204082 | J9: =IF(G9="?","revisa unidades",IFERROR(I9*D9/G9,"")) -> 0.10204082
A10: AOVE | B10: Aceites/grasas | C10: L | D10: 7.5 | E10: 0.01 | F10: L | G10: =IF(C10&F10="","",IFERROR(VLOOKUP(C10&"→"&F10,Conversiones!$A$5:$B$67,2,FALSE),"?")) -> 1 | H10: 0.03 | I10: =IFERROR(IF(E10="","",E10/(1-H10)),"revisa merma") -> 0.010309278 | J10: =IF(G10="?","revisa unidades",IFERROR(I10*D10/G10,"")) -> 0.077319588
A11: Sal en escamas | B11: Secos/granos | C11: kg | D11: 15 | E11: 0.002 | F11: kg | G11: =IF(C11&F11="","",IFERROR(VLOOKUP(C11&"→"&F11,Conversiones!$A$5:$B$67,2,FALSE),"?")) -> 1 | H11: 0.02 | I11: =IFERROR(IF(E11="","",E11/(1-H11)),"revisa merma") -> 0.0020408163 | J11: =IF(G11="?","revisa unidades",IFERROR(I11*D11/G11,"")) -> 0.030612245
G12: =IF(C12&F12="","",IFERROR(VLOOKUP(C12&"→"&F12,Conversiones!$A$5:$B$67,2,FALSE),"?")) | H12: =IFERROR(VLOOKUP(B12,Mermas!$A$5:$C$25,2,FALSE),"") | I12: =IFERROR(IF(E12="","",E12/(1-H12)),"revisa merma") | J12: =IF(G12="?","revisa unidades",IFERROR(I12*D12/G12,""))
G13: =IF(C13&F13="","",IFERROR(VLOOKUP(C13&"→"&F13,Conversiones!$A$5:$B$67,2,FALSE),"?")) | H13: =IFERROR(VLOOKUP(B13,Mermas!$A$5:$C$25,2,FALSE),"") | I13: =IFERROR(IF(E13="","",E13/(1-H13)),"revisa merma") | J13: =IF(G13="?","revisa unidades",IFERROR(I13*D13/G13,""))
G14: =IF(C14&F14="","",IFERROR(VLOOKUP(C14&"→"&F14,Conversiones!$A$5:$B$67,2,FALSE),"?")) | H14: =IFERROR(VLOOKUP(B14,Mermas!$A$5:$C$25,2,FALSE),"") | I14: =IFERROR(IF(E14="","",E14/(1-H14)),"revisa merma") | J14: =IF(G14="?","revisa unidades",IFERROR(I14*D14/G14,""))
G15: =IF(C15&F15="","",IFERROR(VLOOKUP(C15&"→"&F15,Conversiones!$A$5:$B$67,2,FALSE),"?")) | H15: =IFERROR(VLOOKUP(B15,Mermas!$A$5:$C$25,2,FALSE),"") | I15: =IFERROR(IF(E15="","",E15/(1-H15)),"revisa merma") | J15: =IF(G15="?","revisa unidades",IFERROR(I15*D15/G15,""))
G16: =IF(C16&F16="","",IFERROR(VLOOKUP(C16&"→"&F16,Conversiones!$A$5:$B$67,2,FALSE),"?")) | H16: =IFERROR(VLOOKUP(B16,Mermas!$A$5:$C$25,2,FALSE),"") | I16: =IFERROR(IF(E16="","",E16/(1-H16)),"revisa merma") | J16: =IF(G16="?","revisa unidades",IFERROR(I16*D16/G16,""))
G17: =IF(C17&F17="","",IFERROR(VLOOKUP(C17&"→"&F17,Conversiones!$A$5:$B$67,2,FALSE),"?")) | H17: =IFERROR(VLOOKUP(B17,Mermas!$A$5:$C$25,2,FALSE),"") | I17: =IFERROR(IF(E17="","",E17/(1-H17)),"revisa merma") | J17: =IF(G17="?","revisa unidades",IFERROR(I17*D17/G17,""))
G18: =IF(C18&F18="","",IFERROR(VLOOKUP(C18&"→"&F18,Conversiones!$A$5:$B$67,2,FALSE),"?")) | H18: =IFERROR(VLOOKUP(B18,Mermas!$A$5:$C$25,2,FALSE),"") | I18: =IFERROR(IF(E18="","",E18/(1-H18)),"revisa merma") | J18: =IF(G18="?","revisa unidades",IFERROR(I18*D18/G18,""))
G19: =IF(C19&F19="","",IFERROR(VLOOKUP(C19&"→"&F19,Conversiones!$A$5:$B$67,2,FALSE),"?")) | H19: =IFERROR(VLOOKUP(B19,Mermas!$A$5:$C$25,2,FALSE),"") | I19: =IFERROR(IF(E19="","",E19/(1-H19)),"revisa merma") | J19: =IF(G19="?","revisa unidades",IFERROR(I19*D19/G19,""))
G20: =IF(C20&F20="","",IFERROR(VLOOKUP(C20&"→"&F20,Conversiones!$A$5:$B$67,2,FALSE),"?")) | H20: =IFERROR(VLOOKUP(B20,Mermas!$A$5:$C$25,2,FALSE),"") | I20: =IFERROR(IF(E20="","",E20/(1-H20)),"revisa merma") | J20: =IF(G20="?","revisa unidades",IFERROR(I20*D20/G20,""))
G21: =IF(C21&F21="","",IFERROR(VLOOKUP(C21&"→"&F21,Conversiones!$A$5:$B$67,2,FALSE),"?")) | H21: =IFERROR(VLOOKUP(B21,Mermas!$A$5:$C$25,2,FALSE),"") | I21: =IFERROR(IF(E21="","",E21/(1-H21)),"revisa merma") | J21: =IF(G21="?","revisa unidades",IFERROR(I21*D21/G21,""))
A23: COSTE TOTAL INGREDIENTES | J23: =SUM(J5:J21) -> 2.161727
A24: Coste elaboración (%) | I24: 0.1 | J24: =J23*I24 -> 0.2161727
A25: COSTE TOTAL DEL PLATO | J25: =J23+J24 -> 2.3778997
A26: Nº de raciones | I26: 1
A27: COSTE POR RACIÓN | J27: =IFERROR(J25/I26,"") -> 2.3778997
A29: Food Cost objetivo (%) | I29: 0.28
A30: PVP SUGERIDO (sin IVA) | J30: =IFERROR(J27/I29,"") -> 8.4924991
A31: Tipo de IVA (%) | I31: 0.1
A32: PVP CON IVA | J32: =IFERROR(J30*(1+I31),"") -> 9.341749
A33: Margen bruto (€) | J33: =IFERROR(J30-J27,"") -> 6.1145993
A34: Margen bruto (%) | J34: =IFERROR((J30-J27)/J30,"") -> 0.72
A36: PVP actual en carta (sin IVA)
A37: FOOD COST REAL (%) | J37: =IFERROR(J27/I36,"")

Sheet Açaí Bowl
A1: Açaí Bowl con Granola y Fruta
A2: Introduce tus ingredientes y cantidades. Las celdas verdes son editables.
L3: 📷 Foto del Plato
A4: Ingrediente | B4: Categoría | C4: Ud. Compra | D4: Precio/Ud (€) | E4: Cantidad | F4: Ud. Uso | G4: Factor | H4: Merma (%) | I4: Cant. Bruta | J4: Coste (€)
A5: Açaí congelado | B5: Congelados | C5: kg | D5: 22 | E5: 0.1 | F5: kg | G5: =IF(C5&F5="","",IFERROR(VLOOKUP(C5&"→"&F5,Conversiones!$A$5:$B$67,2,FALSE),"?")) -> 1 | H5: 0.07 | I5: =IFERROR(IF(E5="","",E5/(1-H5)),"revisa merma") -> 0.10752688 | J5: =IF(G5="?","revisa unidades",IFERROR(I5*D5/G5,"")) -> 2.3655914
A6: Plátano | B6: Fruta | C6: kg | D6: 1.5 | E6: 0.12 | F6: kg | G6: =IF(C6&F6="","",IFERROR(VLOOKUP(C6&"→"&F6,Conversiones!$A$5:$B$67,2,FALSE),"?")) -> 1 | H6: 0.25 | I6: =IFERROR(IF(E6="","",E6/(1-H6)),"revisa merma") -> 0.16 | J6: =IF(G6="?","revisa unidades",IFERROR(I6*D6/G6,"")) -> 0.24
A7: Leche de avena | B7: Bebidas/licores | C7: L | D7: 2.5 | E7: 0.08 | F7: L | G7: =IF(C7&F7="","",IFERROR(VLOOKUP(C7&"→"&F7,Conversiones!$A$5:$B$67,2,FALSE),"?")) -> 1 | H7: 0.03 | I7: =IFERROR(IF(E7="","",E7/(1-H7)),"revisa merma") -> 0.082474227 | J7: =IF(G7="?","revisa unidades",IFERROR(I7*D7/G7,"")) -> 0.20618557
A8: Granola artesanal | B8: Secos/granos | C8: kg | D8: 8 | E8: 0.04 | F8: kg | G8: =IF(C8&F8="","",IFERROR(VLOOKUP(C8&"→"&F8,Conversiones!$A$5:$B$67,2,FALSE),"?")) -> 1 | H8: 0.02 | I8: =IFERROR(IF(E8="","",E8/(1-H8)),"revisa merma") -> 0.040816327 | J8: =IF(G8="?","revisa unidades",IFERROR(I8*D8/G8,"")) -> 0.32653061 | L8: Foto del plato terminado: Revisar → Desproteger hoja, luego Insertar → Imagen
A9: Arándanos | B9: Fruta | C9: kg | D9: 12 | E9: 0.03 | F9: kg | G9: =IF(C9&F9="","",IFERROR(VLOOKUP(C9&"→"&F9,Conversiones!$A$5:$B$67,2,FALSE),"?")) -> 1 | H9: 0.05 | I9: =IFERROR(IF(E9="","",E9/(1-H9)),"revisa merma") -> 0.031578947 | J9: =IF(G9="?","revisa unidades",IFERROR(I9*D9/G9,"")) -> 0.37894737
A10: Coco rallado | B10: Secos/granos | C10: kg | D10: 7 | E10: 0.01 | F10: kg | G10: =IF(C10&F10="","",IFERROR(VLOOKUP(C10&"→"&F10,Conversiones!$A$5:$B$67,2,FALSE),"?")) -> 1 | H10: 0.02 | I10: =IFERROR(IF(E10="","",E10/(1-H10)),"revisa merma") -> 0.010204082 | J10: =IF(G10="?","revisa unidades",IFERROR(I10*D10/G10,"")) -> 0.071428571
A11: Miel | B11: Secos/granos | C11: kg | D11: 10 | E11: 0.015 | F11: kg | G11: =IF(C11&F11="","",IFERROR(VLOOKUP(C11&"→"&F11,Conversiones!$A$5:$B$67,2,FALSE),"?")) -> 1 | H11: 0.03 | I11: =IFERROR(IF(E11="","",E11/(1-H11)),"revisa merma") -> 0.015463918 | J11: =IF(G11="?","revisa unidades",IFERROR(I11*D11/G11,"")) -> 0.15463918
G12: =IF(C12&F12="","",IFERROR(VLOOKUP(C12&"→"&F12,Conversiones!$A$5:$B$67,2,FALSE),"?")) | H12: =IFERROR(VLOOKUP(B12,Mermas!$A$5:$C$25,2,FALSE),"") | I12: =IFERROR(IF(E12="","",E12/(1-H12)),"revisa merma") | J12: =IF(G12="?","revisa unidades",IFERROR(I12*D12/G12,""))
G13: =IF(C13&F13="","",IFERROR(VLOOKUP(C13&"→"&F13,Conversiones!$A$5:$B$67,2,FALSE),"?")) | H13: =IFERROR(VLOOKUP(B13,Mermas!$A$5:$C$25,2,FALSE),"") | I13: =IFERROR(IF(E13="","",E13/(1-H13)),"revisa merma") | J13: =IF(G13="?","revisa unidades",IFERROR(I13*D13/G13,""))
G14: =IF(C14&F14="","",IFERROR(VLOOKUP(C14&"→"&F14,Conversiones!$A$5:$B$67,2,FALSE),"?")) | H14: =IFERROR(VLOOKUP(B14,Mermas!$A$5:$C$25,2,FALSE),"") | I14: =IFERROR(IF(E14="","",E14/(1-H14)),"revisa merma") | J14: =IF(G14="?","revisa unidades",IFERROR(I14*D14/G14,""))
G15: =IF(C15&F15="","",IFERROR(VLOOKUP(C15&"→"&F15,Conversiones!$A$5:$B$67,2,FALSE),"?")) | H15: =IFERROR(VLOOKUP(B15,Mermas!$A$5:$C$25,2,FALSE),"") | I15: =IFERROR(IF(E15="","",E15/(1-H15)),"revisa merma") | J15: =IF(G15="?","revisa unidades",IFERROR(I15*D15/G15,""))
G16: =IF(C16&F16="","",IFERROR(VLOOKUP(C16&"→"&F16,Conversiones!$A$5:$B$67,2,FALSE),"?")) | H16: =IFERROR(VLOOKUP(B16,Mermas!$A$5:$C$25,2,FALSE),"") | I16: =IFERROR(IF(E16="","",E16/(1-H16)),"revisa merma") | J16: =IF(G16="?","revisa unidades",IFERROR(I16*D16/G16,""))
G17: =IF(C17&F17="","",IFERROR(VLOOKUP(C17&"→"&F17,Conversiones!$A$5:$B$67,2,FALSE),"?")) | H17: =IFERROR(VLOOKUP(B17,Mermas!$A$5:$C$25,2,FALSE),"") | I17: =IFERROR(IF(E17="","",E17/(1-H17)),"revisa merma") | J17: =IF(G17="?","revisa unidades",IFERROR(I17*D17/G17,""))
G18: =IF(C18&F18="","",IFERROR(VLOOKUP(C18&"→"&F18,Conversiones!$A$5:$B$67,2,FALSE),"?")) | H18: =IFERROR(VLOOKUP(B18,Mermas!$A$5:$C$25,2,FALSE),"") | I18: =IFERROR(IF(E18="","",E18/(1-H18)),"revisa merma") | J18: =IF(G18="?","revisa unidades",IFERROR(I18*D18/G18,""))
G19: =IF(C19&F19="","",IFERROR(VLOOKUP(C19&"→"&F19,Conversiones!$A$5:$B$67,2,FALSE),"?")) | H19: =IFERROR(VLOOKUP(B19,Mermas!$A$5:$C$25,2,FALSE),"") | I19: =IFERROR(IF(E19="","",E19/(1-H19)),"revisa merma") | J19: =IF(G19="?","revisa unidades",IFERROR(I19*D19/G19,""))
G20: =IF(C20&F20="","",IFERROR(VLOOKUP(C20&"→"&F20,Conversiones!$A$5:$B$67,2,FALSE),"?")) | H20: =IFERROR(VLOOKUP(B20,Mermas!$A$5:$C$25,2,FALSE),"") | I20: =IFERROR(IF(E20="","",E20/(1-H20)),"revisa merma") | J20: =IF(G20="?","revisa unidades",IFERROR(I20*D20/G20,""))
G21: =IF(C21&F21="","",IFERROR(VLOOKUP(C21&"→"&F21,Conversiones!$A$5:$B$67,2,FALSE),"?")) | H21: =IFERROR(VLOOKUP(B21,Mermas!$A$5:$C$25,2,FALSE),"") | I21: =IFERROR(IF(E21="","",E21/(1-H21)),"revisa merma") | J21: =IF(G21="?","revisa unidades",IFERROR(I21*D21/G21,""))
A23: COSTE TOTAL INGREDIENTES | J23: =SUM(J5:J21) -> 3.7433227
A24: Coste elaboración (%) | I24: 0.1 | J24: =J23*I24 -> 0.37433227
A25: COSTE TOTAL DEL PLATO | J25: =J23+J24 -> 4.117655
A26: Nº de raciones | I26: 1
A27: COSTE POR RACIÓN | J27: =IFERROR(J25/I26,"") -> 4.117655
A29: Food Cost objetivo (%) | I29: 0.28
A30: PVP SUGERIDO (sin IVA) | J30: =IFERROR(J27/I29,"") -> 14.705911
A31: Tipo de IVA (%) | I31: 0.1
A32: PVP CON IVA | J32: =IFERROR(J30*(1+I31),"") -> 16.176502
A33: Margen bruto (€) | J33: =IFERROR(J30-J27,"") -> 10.588256
A34: Margen bruto (%) | J34: =IFERROR((J30-J27)/J30,"") -> 0.72
A36: PVP actual en carta (sin IVA)
A37: FOOD COST REAL (%) | J37: =IFERROR(J27/I36,"")

Sheet Eggs Benedict
A1: Eggs Benedict con Salmón Ahumado
A2: Introduce tus ingredientes y cantidades. Las celdas verdes son editables.
L3: 📷 Foto del Plato
A4: Ingrediente | B4: Categoría | C4: Ud. Compra | D4: Precio/Ud (€) | E4: Cantidad | F4: Ud. Uso | G4: Factor | H4: Merma (%) | I4: Cant. Bruta | J4: Coste (€)
A5: English muffin | B5: Pan/bollería | C5: ud | D5: 0.4 | E5: 2 | F5: ud | G5: =IF(C5&F5="","",IFERROR(VLOOKUP(C5&"→"&F5,Conversiones!$A$5:$B$67,2,FALSE),"?")) -> 1 | H5: 0 | I5: =IFERROR(IF(E5="","",E5/(1-H5)),"revisa merma") -> 2 | J5: =IF(G5="?","revisa unidades",IFERROR(I5*D5/G5,"")) -> 0.8
A6: Huevo campero | B6: Huevos | C6: docena | D6: 4.2 | E6: 2 | F6: ud | G6: =IF(C6&F6="","",IFERROR(VLOOKUP(C6&"→"&F6,Conversiones!$A$5:$B$67,2,FALSE),"?")) -> 12 | H6: 0 | I6: =IFERROR(IF(E6="","",E6/(1-H6)),"revisa merma") -> 2 | J6: =IF(G6="?","revisa unidades",IFERROR(I6*D6/G6,"")) -> 0.7
A7: Salmón ahumado | B7: Pescado | C7: kg | D7: 35 | E7: 0.06 | F7: kg | G7: =IF(C7&F7="","",IFERROR(VLOOKUP(C7&"→"&F7,Conversiones!$A$5:$B$67,2,FALSE),"?")) -> 1 | H7: 0.05 | I7: =IFERROR(IF(E7="","",E7/(1-H7)),"revisa merma") -> 0.063157895 | J7: =IF(G7="?","revisa unidades",IFERROR(I7*D7/G7,"")) -> 2.2105263
A8: Mantequilla (hollandaise) | B8: Lácteos | C8: kg | D8: 9 | E8: 0.05 | F8: kg | G8: =IF(C8&F8="","",IFERROR(VLOOKUP(C8&"→"&F8,Conversiones!$A$5:$B$67,2,FALSE),"?")) -> 1 | H8: 0.03 | I8: =IFERROR(IF(E8="","",E8/(1-H8)),"revisa merma") -> 0.051546392 | J8: =IF(G8="?","revisa unidades",IFERROR(I8*D8/G8,"")) -> 0.46391753 | L8: Foto del plato terminado: Revisar → Desproteger hoja, luego Insertar → Imagen
A9: Limón | B9: Fruta | C9: kg | D9: 2.5 | E9: 0.01 | F9: kg | G9: =IF(C9&F9="","",IFERROR(VLOOKUP(C9&"→"&F9,Conversiones!$A$5:$B$67,2,FALSE),"?")) -> 1 | H9: 0.28 | I9: =IFERROR(IF(E9="","",E9/(1-H9)),"revisa merma") -> 0.013888889 | J9: =IF(G9="?","revisa unidades",IFERROR(I9*D9/G9,"")) -> 0.034722222
A10: Cebollino (1 rama ≈ 1/12 manojo) | B10: Especias/hierbas | C10: manojo | D10: 1.5 | E10: 0.083 | F10: manojo | G10: =IF(C10&F10="","",IFERROR(VLOOKUP(C10&"→"&F10,Conversiones!$A$5:$B$67,2,FALSE),"?")) -> 1 | H10: 0.2 | I10: =IFERROR(IF(E10="","",E10/(1-H10)),"revisa merma") -> 0.10375 | J10: =IF(G10="?","revisa unidades",IFERROR(I10*D10/G10,"")) -> 0.155625
G11: =IF(C11&F11="","",IFERROR(VLOOKUP(C11&"→"&F11,Conversiones!$A$5:$B$67,2,FALSE),"?")) | H11: =IFERROR(VLOOKUP(B11,Mermas!$A$5:$C$25,2,FALSE),"") | I11: =IFERROR(IF(E11="","",E11/(1-H11)),"revisa merma") | J11: =IF(G11="?","revisa unidades",IFERROR(I11*D11/G11,""))
G12: =IF(C12&F12="","",IFERROR(VLOOKUP(C12&"→"&F12,Conversiones!$A$5:$B$67,2,FALSE),"?")) | H12: =IFERROR(VLOOKUP(B12,Mermas!$A$5:$C$25,2,FALSE),"") | I12: =IFERROR(IF(E12="","",E12/(1-H12)),"revisa merma") | J12: =IF(G12="?","revisa unidades",IFERROR(I12*D12/G12,""))
G13: =IF(C13&F13="","",IFERROR(VLOOKUP(C13&"→"&F13,Conversiones!$A$5:$B$67,2,FALSE),"?")) | H13: =IFERROR(VLOOKUP(B13,Mermas!$A$5:$C$25,2,FALSE),"") | I13: =IFERROR(IF(E13="","",E13/(1-H13)),"revisa merma") | J13: =IF(G13="?","revisa unidades",IFERROR(I13*D13/G13,""))
G14: =IF(C14&F14="","",IFERROR(VLOOKUP(C14&"→"&F14,Conversiones!$A$5:$B$67,2,FALSE),"?")) | H14: =IFERROR(VLOOKUP(B14,Mermas!$A$5:$C$25,2,FALSE),"") | I14: =IFERROR(IF(E14="","",E14/(1-H14)),"revisa merma") | J14: =IF(G14="?","revisa unidades",IFERROR(I14*D14/G14,""))
G15: =IF(C15&F15="","",IFERROR(VLOOKUP(C15&"→"&F15,Conversiones!$A$5:$B$67,2,FALSE),"?")) | H15: =IFERROR(VLOOKUP(B15,Mermas!$A$5:$C$25,2,FALSE),"") | I15: =IFERROR(IF(E15="","",E15/(1-H15)),"revisa merma") | J15: =IF(G15="?","revisa unidades",IFERROR(I15*D15/G15,""))
G16: =IF(C16&F16="","",IFERROR(VLOOKUP(C16&"→"&F16,Conversiones!$A$5:$B$67,2,FALSE),"?")) | H16: =IFERROR(VLOOKUP(B16,Mermas!$A$5:$C$25,2,FALSE),"") | I16: =IFERROR(IF(E16="","",E16/(1-H16)),"revisa merma") | J16: =IF(G16="?","revisa unidades",IFERROR(I16*D16/G16,""))
G17: =IF(C17&F17="","",IFERROR(VLOOKUP(C17&"→"&F17,Conversiones!$A$5:$B$67,2,FALSE),"?")) | H17: =IFERROR(VLOOKUP(B17,Mermas!$A$5:$C$25,2,FALSE),"") | I17: =IFERROR(IF(E17="","",E17/(1-H17)),"revisa merma") | J17: =IF(G17="?","revisa unidades",IFERROR(I17*D17/G17,""))
G18: =IF(C18&F18="","",IFERROR(VLOOKUP(C18&"→"&F18,Conversiones!$A$5:$B$67,2,FALSE),"?")) | H18: =IFERROR(VLOOKUP(B18,Mermas!$A$5:$C$25,2,FALSE),"") | I18: =IFERROR(IF(E18="","",E18/(1-H18)),"revisa merma") | J18: =IF(G18="?","revisa unidades",IFERROR(I18*D18/G18,""))
G19: =IF(C19&F19="","",IFERROR(VLOOKUP(C19&"→"&F19,Conversiones!$A$5:$B$67,2,FALSE),"?")) | H19: =IFERROR(VLOOKUP(B19,Mermas!$A$5:$C$25,2,FALSE),"") | I19: =IFERROR(IF(E19="","",E19/(1-H19)),"revisa merma") | J19: =IF(G19="?","revisa unidades",IFERROR(I19*D19/G19,""))
G20: =IF(C20&F20="","",IFERROR(VLOOKUP(C20&"→"&F20,Conversiones!$A$5:$B$67,2,FALSE),"?")) | H20: =IFERROR(VLOOKUP(B20,Mermas!$A$5:$C$25,2,FALSE),"") | I20: =IFERROR(IF(E20="","",E20/(1-H20)),"revisa merma") | J20: =IF(G20="?","revisa unidades",IFERROR(I20*D20/G20,""))
A22: COSTE TOTAL INGREDIENTES | J22: =SUM(J5:J20) -> 4.3647911
A23: Coste elaboración (%) | I23: 0.1 | J23: =J22*I23 -> 0.43647911
A24: COSTE TOTAL DEL PLATO | J24: =J22+J23 -> 4.8012702
A25: Nº de raciones | I25: 1
A26: COSTE POR RACIÓN | J26: =IFERROR(J24/I25,"") -> 4.8012702
A28: Food Cost objetivo (%) | I28: 0.28
A29: PVP SUGERIDO (sin IVA) | J29: =IFERROR(J26/I28,"") -> 17.147393
A30: Tipo de IVA (%) | I30: 0.1
A31: PVP CON IVA | J31: =IFERROR(J29*(1+I30),"") -> 18.862133
A32: Margen bruto (€) | J32: =IFERROR(J29-J26,"") -> 12.346123
A33: Margen bruto (%) | J33: =IFERROR((J29-J26)/J29,"") -> 0.72
A35: PVP actual en carta (sin IVA)
A36: FOOD COST REAL (%) | J36: =IFERROR(J26/I35,"")

Sheet Carrot Cake
A1: Carrot Cake con Frosting de Queso — tanda de 12 raciones (molde de 20 cm, dos capas)
A2: Escandallo por TANDA. El «Nº de raciones» reparte el coste entre las porciones que salen.
L3: 📷 Foto del Plato
A4: Ingrediente | B4: Categoría | C4: Ud. Compra | D4: Precio/Ud (€) | E4: Cantidad | F4: Ud. Uso | G4: Factor | H4: Merma (%) | I4: Cant. Bruta | J4: Coste (€)
A5: Zanahoria | B5: Verdura raíz | C5: kg | D5: 1.4 | E5: 0.45 | F5: kg | G5: =IF(C5&F5="","",IFERROR(VLOOKUP(C5&"→"&F5,Conversiones!$A$5:$B$67,2,FALSE),"?")) -> 1 | H5: 0.2 | I5: =IFERROR(IF(E5="","",E5/(1-H5)),"revisa merma") -> 0.5625 | J5: =IF(G5="?","revisa unidades",IFERROR(I5*D5/G5,"")) -> 0.7875
A6: Harina floja | B6: Secos/granos | C6: kg | D6: 1.2 | E6: 0.3 | F6: kg | G6: =IF(C6&F6="","",IFERROR(VLOOKUP(C6&"→"&F6,Conversiones!$A$5:$B$67,2,FALSE),"?")) -> 1 | H6: 0.02 | I6: =IFERROR(IF(E6="","",E6/(1-H6)),"revisa merma") -> 0.30612245 | J6: =IF(G6="?","revisa unidades",IFERROR(I6*D6/G6,"")) -> 0.36734694
A7: Azúcar moreno | B7: Secos/granos | C7: kg | D7: 2.2 | E7: 0.28 | F7: kg | G7: =IF(C7&F7="","",IFERROR(VLOOKUP(C7&"→"&F7,Conversiones!$A$5:$B$67,2,FALSE),"?")) -> 1 | H7: 0.02 | I7: =IFERROR(IF(E7="","",E7/(1-H7)),"revisa merma") -> 0.28571429 | J7: =IF(G7="?","revisa unidades",IFERROR(I7*D7/G7,"")) -> 0.62857143
A8: Huevo campero | B8: Huevos | C8: docena | D8: 4.2 | E8: 6 | F8: ud | G8: =IF(C8&F8="","",IFERROR(VLOOKUP(C8&"→"&F8,Conversiones!$A$5:$B$67,2,FALSE),"?")) -> 12 | H8: 0 | I8: =IFERROR(IF(E8="","",E8/(1-H8)),"revisa merma") -> 6 | J8: =IF(G8="?","revisa unidades",IFERROR(I8*D8/G8,"")) -> 2.1 | L8: Foto del plato terminado: Revisar → Desproteger hoja, luego Insertar → Imagen
A9: Aceite de girasol | B9: Aceites/grasas | C9: L | D9: 2.4 | E9: 0.24 | F9: L | G9: =IF(C9&F9="","",IFERROR(VLOOKUP(C9&"→"&F9,Conversiones!$A$5:$B$67,2,FALSE),"?")) -> 1 | H9: 0 | I9: =IFERROR(IF(E9="","",E9/(1-H9)),"revisa merma") -> 0.24 | J9: =IF(G9="?","revisa unidades",IFERROR(I9*D9/G9,"")) -> 0.576
A10: Nueces peladas | B10: Secos/granos | C10: kg | D10: 16 | E10: 0.12 | F10: kg | G10: =IF(C10&F10="","",IFERROR(VLOOKUP(C10&"→"&F10,Conversiones!$A$5:$B$67,2,FALSE),"?")) -> 1 | H10: 0.05 | I10: =IFERROR(IF(E10="","",E10/(1-H10)),"revisa merma") -> 0.12631579 | J10: =IF(G10="?","revisa unidades",IFERROR(I10*D10/G10,"")) -> 2.0210526
A11: Canela molida | B11: Especias/hierbas | C11: kg | D11: 32 | E11: 0.008 | F11: kg | G11: =IF(C11&F11="","",IFERROR(VLOOKUP(C11&"→"&F11,Conversiones!$A$5:$B$67,2,FALSE),"?")) -> 1 | H11: 0.02 | I11: =IFERROR(IF(E11="","",E11/(1-H11)),"revisa merma") -> 0.0081632653 | J11: =IF(G11="?","revisa unidades",IFERROR(I11*D11/G11,"")) -> 0.26122449
A12: Queso crema (frosting) | B12: Lácteos | C12: kg | D12: 7.9 | E12: 0.45 | F12: kg | G12: =IF(C12&F12="","",IFERROR(VLOOKUP(C12&"→"&F12,Conversiones!$A$5:$B$67,2,FALSE),"?")) -> 1 | H12: 0.03 | I12: =IFERROR(IF(E12="","",E12/(1-H12)),"revisa merma") -> 0.46391753 | J12: =IF(G12="?","revisa unidades",IFERROR(I12*D12/G12,"")) -> 3.6649485
A13: Azúcar glas (frosting) | B13: Secos/granos | C13: kg | D13: 2.8 | E13: 0.2 | F13: kg | G13: =IF(C13&F13="","",IFERROR(VLOOKUP(C13&"→"&F13,Conversiones!$A$5:$B$67,2,FALSE),"?")) -> 1 | H13: 0.02 | I13: =IFERROR(IF(E13="","",E13/(1-H13)),"revisa merma") -> 0.20408163 | J13: =IF(G13="?","revisa unidades",IFERROR(I13*D13/G13,"")) -> 0.57142857
A14: Mantequilla (frosting) | B14: Lácteos | C14: kg | D14: 10.5 | E14: 0.12 | F14: kg | G14: =IF(C14&F14="","",IFERROR(VLOOKUP(C14&"→"&F14,Conversiones!$A$5:$B$67,2,FALSE),"?")) -> 1 | H14: 0.03 | I14: =IFERROR(IF(E14="","",E14/(1-H14)),"revisa merma") -> 0.12371134 | J14: =IF(G14="?","revisa unidades",IFERROR(I14*D14/G14,"")) -> 1.2989691
G15: =IF(C15&F15="","",IFERROR(VLOOKUP(C15&"→"&F15,Conversiones!$A$5:$B$67,2,FALSE),"?")) | H15: =IFERROR(VLOOKUP(B15,Mermas!$A$5:$C$25,2,FALSE),"") | I15: =IFERROR(IF(E15="","",E15/(1-H15)),"revisa merma") | J15: =IF(G15="?","revisa unidades",IFERROR(I15*D15/G15,""))
G16: =IF(C16&F16="","",IFERROR(VLOOKUP(C16&"→"&F16,Conversiones!$A$5:$B$67,2,FALSE),"?")) | H16: =IFERROR(VLOOKUP(B16,Mermas!$A$5:$C$25,2,FALSE),"") | I16: =IFERROR(IF(E16="","",E16/(1-H16)),"revisa merma") | J16: =IF(G16="?","revisa unidades",IFERROR(I16*D16/G16,""))
G17: =IF(C17&F17="","",IFERROR(VLOOKUP(C17&"→"&F17,Conversiones!$A$5:$B$67,2,FALSE),"?")) | H17: =IFERROR(VLOOKUP(B17,Mermas!$A$5:$C$25,2,FALSE),"") | I17: =IFERROR(IF(E17="","",E17/(1-H17)),"revisa merma") | J17: =IF(G17="?","revisa unidades",IFERROR(I17*D17/G17,""))
G18: =IF(C18&F18="","",IFERROR(VLOOKUP(C18&"→"&F18,Conversiones!$A$5:$B$67,2,FALSE),"?")) | H18: =IFERROR(VLOOKUP(B18,Mermas!$A$5:$C$25,2,FALSE),"") | I18: =IFERROR(IF(E18="","",E18/(1-H18)),"revisa merma") | J18: =IF(G18="?","revisa unidades",IFERROR(I18*D18/G18,""))
G19: =IF(C19&F19="","",IFERROR(VLOOKUP(C19&"→"&F19,Conversiones!$A$5:$B$67,2,FALSE),"?")) | H19: =IFERROR(VLOOKUP(B19,Mermas!$A$5:$C$25,2,FALSE),"") | I19: =IFERROR(IF(E19="","",E19/(1-H19)),"revisa merma") | J19: =IF(G19="?","revisa unidades",IFERROR(I19*D19/G19,""))
G20: =IF(C20&F20="","",IFERROR(VLOOKUP(C20&"→"&F20,Conversiones!$A$5:$B$67,2,FALSE),"?")) | H20: =IFERROR(VLOOKUP(B20,Mermas!$A$5:$C$25,2,FALSE),"") | I20: =IFERROR(IF(E20="","",E20/(1-H20)),"revisa merma") | J20: =IF(G20="?","revisa unidades",IFERROR(I20*D20/G20,""))
G21: =IF(C21&F21="","",IFERROR(VLOOKUP(C21&"→"&F21,Conversiones!$A$5:$B$67,2,FALSE),"?")) | H21: =IFERROR(VLOOKUP(B21,Mermas!$A$5:$C$25,2,FALSE),"") | I21: =IFERROR(IF(E21="","",E21/(1-H21)),"revisa merma") | J21: =IF(G21="?","revisa unidades",IFERROR(I21*D21/G21,""))
A23: COSTE TOTAL INGREDIENTES | J23: =SUM(J5:J21) -> 12.277042
A24: Coste elaboración (%) | I24: 0.1 | J24: =J23*I24 -> 1.2277042
A25: COSTE TOTAL DEL PLATO | J25: =J23+J24 -> 13.504746
A26: Nº de raciones | I26: 12
A27: COSTE POR RACIÓN | J27: =IFERROR(J25/I26,"") -> 1.1253955
A29: Food Cost objetivo (%) | I29: 0.25
A30: PVP SUGERIDO (sin IVA) | J30: =IFERROR(J27/I29,"") -> 4.5015819
A31: Tipo de IVA (%) | I31: 0.1
A32: PVP CON IVA | J32: =IFERROR(J30*(1+I31),"") -> 4.9517401
A33: Margen bruto (€) | J33: =IFERROR(J30-J27,"") -> 3.3761864
A34: Margen bruto (%) | J34: =IFERROR((J30-J27)/J30,"") -> 0.75
A36: PVP actual en carta (sin IVA)
A37: FOOD COST REAL (%) | J37: =IFERROR(J27/I36,"")

Sheet Conversiones
A1: Tabla de conversión Ud. Compra → Ud. Uso
A2: La usa la columna «Factor» de cada escandallo. Puedes añadir parejas al final, hasta la fila 67: la clave se escribe «compra→uso».
A4: Conversión (compra→uso) | B4: Factor | C4: Qué significa
A5: kg→kg | B5: 1 | C5: misma unidad
A6: kg→g | B6: 1000 | C6: 1 kg = 1.000 g
A7: g→g | B7: 1 | C7: misma unidad
A8: g→kg | B8: 0.001 | C8: 1 g = 0,001 kg
A9: L→L | B9: 1 | C9: misma unidad
A10: L→ml | B10: 1000 | C10: 1 L = 1.000 ml
A11: L→cl | B11: 100 | C11: 1 L = 100 cl
A12: ml→ml | B12: 1 | C12: misma unidad
A13: ml→L | B13: 0.001 | C13: 1 ml = 0,001 L
A14: ml→cl | B14: 0.1 | C14: 1 ml = 0,1 cl
A15: cl→cl | B15: 1 | C15: misma unidad
A16: cl→ml | B16: 10 | C16: 1 cl = 10 ml
... A37: sobre→g | B37: 10 | C37: sobre ≈ 10 g

Sheet Mermas
A1: Mermas de referencia por categoría
A2: La «típica» es la que se precarga en las filas vacías del escandallo al elegir categoría. Ajústala a tu proveedor.
A3: Mide tu merma real con la plantilla 12 (Test de Rendimiento) y llévala a «Merma (%)» de la ficha.
A4: Categoría | B4: Merma típica | C4: Mínima | D4: Máxima
A5: Carne roja | B5: 0.2 | C5: 0.15 | D5: 0.25
A6: Aves | B6: 0.25 | C6: 0.2 | D6: 0.3
A7: Pescado | B7: 0.35 | C7: 0.3 | D7: 0.45
A8: Marisco | B8: 0.45 | C8: 0.35 | D8: 0.55
A9: Verdura hoja | B9: 0.25 | C9: 0.2 | D9: 0.35
A10: Verdura raíz | B10: 0.12 | C10: 0.08 | D10: 0.18
A11: Verdura fruto | B11: 0.1 | C11: 0.06 | D11: 0.15
A12: Fruta | B12: 0.15 | C12: 0.1 | D12: 0.25
A13: Lácteos | B13: 0.03 | C13: 0.01 | D13: 0.05
A14: Secos/granos | B14: 0.02 | C14: 0.01 | D14: 0.04
A15: Congelados | B15: 0.07 | C15: 0.03 | D15: 0.1
A16: Pan/bollería | B16: 0.05 | C16: 0.02 | D16: 0.1
... A25: Pasta/arroz | B25: 0.02 | C25: 0.01 | D25: 0.04
