Workbook

Sheet 0. Assumptions
A1: ASSUMPTIONS — the RATES and DRIVERS of the model are typed here
A2: Change the GREEN cells: the rest of the workbook recalculates on its own. Expense items are typed on their own tab (also in green) and are not repeated here. Amounts are in your currency.
A3: BUSINESS ACTIVITY
A4: Transactions per day (average for year 1) | B4: 210 | C4: Transactions served per day on average over the year (bread, pastries and coffee at the counter, plus what the wholesale channel picks up). It is a driver, not a figure backed out of a revenue target, and it should sit between the pessimistic and optimistic scenarios published on the "Scenarios" tab. With fewer transactions, net income falls below the 5% floor this workbook sets, because fixed costs (labor, rent, insurance) do not grow with volume and each extra transaction goes almost entirely to the bottom line. WATCH OUT: the base case is demanding on both sides at once, volume and average check; if either one comes in lower in your area, net income drops below that floor. Compare it with your location before you trust it
A5: Average check (excl. sales tax) | B5: 10 | C5: EXCL. SALES TAX. It sits in the upper part of the range that the industry benchmarks table on the "Instructions" tab gives for a bakery average check (kit estimate), because it combines pastries and coffee with the bread, not just the loaf. Check it against your own menu: if your real average check is lower, lower it here and see what happens to net income
A6: Operating days per year | B6: 310 | C6: The SAME number feeds the "3-Year P&L", the "Break-Even" tab and the "Scenarios" tab, so all three always work on the same operating calendar
A7: Volume growth in year 2 | B7: 0.12 | C7: Second year, with the wholesale channel (cafés and restaurants) already established and no launch spending. Kept moderate on purpose
A8: Volume growth in year 3 | B8: 0.07 | C8: Third year, close to the production ceiling of the oven you installed
A9: Menu price incl. sales tax (calculated) | B9: =IFERROR(IF($B$5="","",$B$5*(1+SUMPRODUCT('3-Year P&L'!$E$10:$E$11,'3-Year P&L'!$G$10:$G$11))),"") -> 10.256 | C9: =IFERROR("Average check excl. sales tax plus the weighted sales tax of your sales lines ("&TEXT(SUMPRODUCT('3-Year P&L'!$E$10:$E$11,'3-Year P&L'!$G$10:$G$11)*100,"0")&"%), rounded: the tax-exempt share of the bakery line (column H of ""3-Year P&L"") lowers it. In the US, prices usually exclude sales tax and it is added at the register; in the UK, prices include VAT.","") -> Average check excl. sales tax plus the weighted sales tax of your sales lines (3%), rounded: the tax-exempt share of the bakery line (column H of "3-Year P&L") lowers it. In the US, prices usually exclude sales tax and it is added at the register; in the UK, prices include VAT.
A10: SALES MIX AND COST OF GOODS SOLD
A11: FOOD share of total sales | B11: 0.85 | C11: Share of FOOD in total sales. It is an INPUT: change it here and the P&L, the cash flow and the sales tax collected recalculate on their own
A12: BEVERAGE share of total sales | B12: =IFERROR(IF(COUNT(B11)=0,"",1-B11),"") -> 0.15 | C12: Calculated as the remainder: food + beverage = 100%
A13: Cost of goods sold on FOOD sales | B13: 0.3 | C13: Cost of goods sold on bread and pastries, weighted with the ranges in the industry benchmarks table on the "Instructions" tab. Bread (25-30%) weighs more in the mix than pastries (32-38%), so the blend sits close to the low end of the pastry range
A14: Cost of goods sold on BEVERAGE sales | B14: 0.22 | C14: Cost of coffee and beverages against their own sales: inside the 20-30% that the industry benchmarks table on the "Instructions" tab gives for coffee (kit estimate)
A15: Disposables and packaging as % of sales | B15: 0.03 | C15: Paper bags, pastry boxes and counter napkins
A16: Delivery share of total sales | B16: 0 | C16: ZERO by default: fresh-baked bread does not travel well and this plan does not deliver on day one. Raise it if you turn on a delivery channel for pastries or breakfast orders
A17: Delivery platform fee | B17: 0.25 | C17: Typical DoorDash / Uber Eats commission on orders served through that channel, if you ever turn it on
A18: Card processing fee | B18: 0.035 | C18: Card and mobile wallet fees on total sales in the shop (the example, 3.5%, is a kit estimate: enter your effective rate)
A19: LABOR
A20: Employer payroll taxes | B20: 0.1 | C20: FICA (Social Security 6.2% + Medicare 1.45%) + federal and state unemployment taxes (FUTA / SUTA) + workers' comp. About 10% in total: adjust it to your state and your insurance carrier
A21: Monthly pay periods per year (keep 12) | B21: 12 | C21: Annual gross pay = monthly gross pay × this number. Keep 12 in the US: it counts the monthly salaries the model pays in a year, not how often you run payroll (weekly or biweekly payroll pays the same annual amount)
A22: Federal minimum wage, annual full-time | B22: 15080 | C22: US federal minimum wage: 7.25 per hour × 2,080 hours = 15,080 per year for a full-time job. Your state or city may set a higher floor: enter it in the state / local minimum wage cell below. Check the current rates at dol.gov
A23: RENT AND FIXED COSTS
A24: Monthly rent | B24: 4200 | C24: Space for a bakery with a production area and a storefront (see Phase 2 of the checklist: plan for about 860 sq ft or more for production, storefront and storage; the example is about 1,800 sq ft). Include NNN / CAM charges (property tax, building insurance, common-area maintenance) in this cell, not just the base rent. The workbook calculates the weight on sales in the "Rent / Sales" row of the ratios block on the "3-Year P&L": in the base case it stays BELOW the 10% ceiling set in the industry benchmarks table on the "Instructions" tab
A25: Security deposit (months of rent) | B25: 2 | C25: Months of rent held as a security deposit. It is set in your commercial lease, so check the terms before you sign
A26: Monthly utilities (electricity, water, gas) | B26: 1500 | C26: Electricity, water and gas: ovens need a heavy electrical load, so ask your utility about three-phase service (see Phase 2 of the checklist). Ask for the space's utility history before you sign
A27: Insurance (per year) | B27: 4500 | C27: General liability (landlords and events often require 1 million per occurrence) plus property coverage or a business owner's policy (BOP) for a space with ovens (fire risk from the ovens, see Phase 2 of the checklist)
A28: Miscellaneous and contingency as % of sales | B28: 0.02 | C28: Cushion for operating expenses that are not budgeted
A29: FINANCING
A30: Owner's equity contributed | B30: 70000 | C30: Owners' contribution. With too little, lenders pass: they usually expect an owner equity injection (often around 10% for SBA start-ups; many want 20-30%) measured against the cash need calculated on the "Startup Costs" tab
A31: Loan requested | B31: 197000 | C31: Principal requested — bank or SBA 7(a): if your loan is an SBA 7(a), this is the cell. It is the only loan that the amortization schedule, the P&L interest and the DSCR use. The "Financing" tab checks that sources and uses match the cash need calculated on the "Startup Costs" tab, and has a cell that calculates the exact amount that balances them
A32: Nominal annual interest rate (not APR) | B32: 0.1 | C32: Nominal annual rate, not APR; get offers from two lenders, including an SBA-guaranteed loan, before you fix it
A33: Loan term (years) | B33: 10 | C33: Total years, interest-only period included
A34: Interest-only period (years) | B34: 0 | C34: Years in which you pay only interest. ZERO by default: repayment starts in year 1, so the year-1 DSCR already measures the full loan payment. If you negotiate an interest-only period, the principal repayment hits all at once when it ends: the "Break-Even" tab measures that cushion year by year
A35: Working capital (months of fixed costs) | B35: 3 | C35: The minimum this workbook requires (see "Instructions"): a cushion of less than 3 months will not cover a slow season
A36: TAXES
A37: Effective income tax rate (years 1-2) | B37: 0.25 | C37: Example: 21% federal rate for a C corporation plus state tax, rounded to 25%. If you operate as a sole proprietorship, LLC taxed as a pass-through or S corporation, the business itself pays 0% here and you pay tax on the profit personally: set this to 0 and budget for your personal tax separately. The model applies this rate to the first two years with positive taxable income
A38: Effective income tax rate (from year 3) | B38: 0.25 | C38: From the third year with positive taxable income. Same example rate (21% federal C corporation + state). Confirm the rate that applies to you with your accountant and change it here
A39: Sales tax rate on sales | B39: 0.08 | C39: Example rate: state + local sales tax combined. It varies widely by state and city: look up yours. UK: 20% VAT on hot food and dine-in
A40: Sales tax rate on alcohol to go | B40: 0.08 | C40: Sales tax rate on alcohol sold to go or delivered. In this workbook it applies only to the ALCOHOLIC part of beverage sales that leaves through the delivery channel, and this bakery sells no alcohol by default, so it does not affect the result. Some states add a separate liquor tax: check yours
A41: Recoverable input tax on purchases and capex | B41: 0 | C41: In the US, the sales tax you pay on purchases is a cost, not a credit: leave this at 0%. UK: 20% if you are VAT-registered
A42: Net operating losses carried forward | B42: 0 | C42: Net operating losses from earlier years still to be offset at the start. Federal rules let you offset up to 80% of taxable income in a year; the model offsets 100% as a simplification
A43: DEPRECIATION
A44: Useful life of build-out and fixtures (years) | B44: 10 | C44: Build-out, electrical service and ventilation of a bakery production area. Book depreciation in this model is straight-line; MACRS and Section 179 are tax treatments handled outside the model, so confirm them with your accountant
A45: Useful life of machinery, furniture and equipment (years) | B45: 7 | C45: Oven, mixer, divider, coolers and display case. Book depreciation in this model is straight-line; MACRS and Section 179 are tax treatments handled outside the model, so confirm them with your accountant
A47: GROWTH AND COST INFLATION
A48: Annual increase in fixed costs | B48: 0 | C48: SET TO ZERO: all three columns are in year-1 prices (real terms). Raise it if you want to project in nominal terms
A49: RAMP-UP AND CAPACITY
A51: Seating capacity (seats at tables + bar) | B51: 15 | C51: Most transactions are counter sales (to go), not table service: this number covers only the café corner with seats, not the line at the bread counter. It helps you size the seating area of the space; the volume of the business is projected from counter transactions, not from seat turns
A52: Month-1 activity as a % of steady-state activity | B52: 0.55 | C52: A new business does not sell on day one what it sells six months later. The daily volume above is the year-1 AVERAGE: the ramp only spreads year 1's sales across the months (slower start, stronger finish) and keeps the annual total. At 100% there is no ramp
A53: Months to reach steady state | B53: 6 | C53: The ramp rises in a straight line from the percentage above to 100% over this number of months
A54: Months of rent BEFORE opening (build-out and permits) | B54: 1 | C54: You pay for the space from the day you sign. These months are a startup cost: they do NOT overlap the P&L, which starts on opening day
A55: Contingency on the BUILD-OUT lines of the space block (%) | B55: 0.1 | C55: Cushion on the build-out and fit-out line. A lender will not finance a renovation without it
A57: RECEIPTS, PAYMENTS AND SALES TAX BREAKDOWN
A58: Average collection days | B58: 1 | C58: Weighted average: the counter is paid on the spot (0 days) and wholesale accounts (cafés and restaurants) usually pay on terms, often 30 days. With the weight this plan gives to wholesale, it comes to about a day on average: raise it if your deliveries to other businesses weigh more
A59: Average days to pay suppliers | B59: 14 | C59: What your suppliers finance for you. It is the first thing you lose if you fall behind on a payment
A60: Month of extra pay period 1 (only if pay periods > 12) | B60: 7 | C60: Month of the year (1-12) when the first extra pay period is paid out. Only used if pay periods > 12
A61: Month of extra pay period 2 (only if pay periods > 12) | B61: 12 | C61: Month of the year (1-12) when the second extra pay period is paid out. Only used if pay periods > 12
A62: ALCOHOLIC beverages as a share of total beverage sales | B62: 0 | C62: ZERO: the beverage line of this plan is coffee and tea, with no alcohol (unlike a coffee shop with brunch, which may pour a celebratory mimosa). If you add sparkling wine for celebration breakfasts, raise this cell; you will also need your state liquor license
A63: Sales tax rate on alcohol served at the counter | B63: 0.08 | C63: Rate for alcohol served at the counter: the same as the rest of on-site sales in this example (8%: state + local). Alcohol rates vary by state and some states add a separate liquor tax: check yours. The workbook applies the alcohol rates only to the ALCOHOLIC part of beverage sales, and this plan sells none by default
A64: CONTROL THRESHOLDS AND FLOORS
A65: DSCR limit (minimum acceptable) | B65: 1.15 | C65: Below 1.0 the business does not generate enough to repay the loan. Lenders often write a minimum DSCR into the loan covenants: ask yours. Kit default: 1.15×
A66: DSCR target (green) | B66: 1.25 | C66: What lenders commonly look for before approving a loan comfortably. Kit default: 1.25× (editable estimate)
A67: Minimum cushion above break-even | B67: 0.15 | C67: How far planned sales must sit above cash break-even (fixed costs and the loan payment). The drop you can absorb is somewhat smaller: with a 15% cushion, about 13% of plan
A68: State / local minimum wage, annual full-time | C68: Your STATE or LOCAL minimum wage can be higher than the federal one: enter it here as an annual full-time figure (hourly rate × 2,080 hours). The higher of the two applies. Leave it empty or at 0 and the traffic light compares only against the federal minimum

Sheet Startup Costs
A1: BUSINESS PLAN: BAKERY
A2: Startup Costs — US example (2026)
A3: Adjust the figures to your project.
A5: Item | B5: Amount | C5: % of startup costs | D5: Notes | E5: Taxable / recoverable tax?
A6: STARTUP COSTS | B6: =IFERROR(IF(COUNT(B7:B28)=0,"",SUM(B7:B28)),"") -> 182500 | C6: =IFERROR(B6/$B$31,"") -> 0.68426637
A7: LLC formation and legal | B7: 1500 | C7: =IFERROR(B7/$B$31,"") -> 0.0056241072 | D7: Single-member LLC: filing fee and attorney review (fees vary by state) | E7: No
A8: Licenses and health plan review | B8: 2500 | C8: =IFERROR(B8/$B$31,"") -> 0.009373512 | D8: A bakery with ovens needs a certificate of occupancy and a health department plan review | E8: No
A9: Architect and permit drawings | B9: 6000 | C9: =IFERROR(B9/$B$31,"") -> 0.022496429 | D9: Required: oven ventilation and electrical load drawings | E9: Yes
A10: Build-out | B10: 35000 | C10: =IFERROR(B10/$B$31,"") -> 0.13122917 | D10: Technical flooring, washable wall finishes, production area | E10: Yes
A11: Electrical service upgrade for the ovens | B11: 10000 | C11: =IFERROR(B11/$B$31,"") -> 0.037494048 | D11: Three-phase service, check with your utility | E11: Yes
A12: Oven ventilation and exhaust | B12: 10000 | C12: =IFERROR(B12/$B$31,"") -> 0.037494048 | D12: Required: hood, exhaust fan and filters; ask the city whether a ventilation permit applies | E12: Yes
A13: Deck / rack oven | B13: 25000 | C13: =IFERROR(B13/$B$31,"") -> 0.09373512 | D13: Deck oven (artisan) or rack oven (volume) | E13: Yes
A14: Spiral mixer (55-110 lb) | B14: 9000 | C14: =IFERROR(B14/$B$31,"") -> 0.033744643 | D14: Capacity based on daily production | E14: Yes
A15: Divider-rounder | B15: 7000 | C15: =IFERROR(B15/$B$31,"") -> 0.026245833 | D15: For batch production of uniform pieces | E15: Yes
A16: Proofer / retarder | B16: 10000 | C16: =IFERROR(B16/$B$31,"") -> 0.037494048 | D16: Programmable slow fermentation: key to quality | E16: Yes
A17: Walk-in cooler and freezer | B17: 9000 | C17: =IFERROR(B17/$B$31,"") -> 0.033744643 | D17: Storage for raw ingredients and frozen dough | E17: Yes
A18: Stainless tables and shelving | B18: 5000 | C18: =IFERROR(B18/$B$31,"") -> 0.018747024 | D18: Production work surface | E18: Yes
... A25: Opening ingredients inventory (flour, yeast, etc.) | B25: 3000 | C25: =IFERROR(B25/$B$31,"") -> 0.011248214 | D25: Bread flour, rye, sourdough starter, yeast | E25: Yes
A26: Security deposit | B26: =IFERROR(IF('0. Assumptions'!$B$24="","",'0. Assumptions'!$B$24*'0. Assumptions'!$B$25),"") -> 8400 | C26: =IFERROR(B26/$B$31,"") -> 0.031495 | D26: =IFERROR(""&TEXT('0. Assumptions'!$B$25,"0")&IF('0. Assumptions'!$B$25=1," month"," months")&" of rent, from ""0. Assumptions"". Refundable when the lease ends: it is not depreciated and carries no tax","") -> 2 months of rent, from "0. Assumptions". Refundable when the lease ends: it is not depreciated and carries no tax | E26: No
A27: Rent paid before opening | B27: =IFERROR(IF('0. Assumptions'!$B$24="","",'0. Assumptions'!$B$24*'0. Assumptions'!$B$54),"") -> 4200 | C27: =IFERROR(B27/$B$31,"") -> 0.0157475 | D27: =IFERROR("Rent "&IF('0. Assumptions'!$B$54=1,"for the month","for the "&TEXT('0. Assumptions'!$B$54,"0")&" months")&" of build-out and permits before opening. It does not overlap the P&L, which starts on opening day: its twelve months are twelve trading months","") -> Rent for the month of build-out and permits before opening. It does not overlap the P&L, which starts on opening day: its twelve months are twelve trading months | E27: Yes
A28: Build-out and setup contingency | B28: =IFERROR(IF(COUNT(B9,B10,B11,B12,B23)=0,"",ROUND((B9+B10+B11+B12+B23)*'0. Assumptions'!$B$55,0)),"") -> 6400 | C28: =IFERROR(B28/$B$31,"") -> 0.023996191 | D28: =IFERROR("At "&TEXT('0. Assumptions'!$B$55,"0%")&" of the BUILD-OUT items of this block (architect and building permits, construction, electrical service upgrade for the ovens, oven ventilation and exhaust, signage), not of the whole block: the other items are left out. No lender funds a "&"build-out without a cushion: the percentage is in ""0. Assumptions""","") -> At 10% of the BUILD-OUT items of this block (architect and building permits, construction, electrical service upgrade for the ovens, oven ventilation and exhaust, signage), not of the whole block: the other items are left out. No lender funds a build-out without a cushion: the percentage is in "0. Assumptions" | E28: Yes
A29: WORKING CAPITAL | B29: =IFERROR(IF(B30="","",B30),"") -> 84209 | C29: =IFERROR(B29/$B$31,"") -> 0.31573363
A30: Operating cushion until break-even | B30: =IFERROR(IF('0. Assumptions'!$B$35*('3-Year P&L'!$B$38-'3-Year P&L'!$B$36)=0,"",'0. Assumptions'!$B$35*('3-Year P&L'!$B$38-'3-Year P&L'!$B$36)/12),"") -> 84209 | C30: =IFERROR(B30/$B$31,"") -> 0.31573363 | D30: =IFERROR("Covers "&TEXT('0. Assumptions'!$B$35,"0")&IF('0. Assumptions'!$B$35=1," month"," months")&" of year-1 CASH fixed costs (the P&L fixed costs minus depreciation, which is not paid out), the minimum the Instructions of this workbook ask for","") -> Covers 3 months of year-1 CASH fixed costs (the P&L fixed costs minus depreciation, which is not paid out), the minimum the Instructions of this workbook ask for | E30: No
A31: TOTAL STARTUP COSTS (sum of the blocks) | B31: =IFERROR(B6+B29,"") -> 266709 | D31: =IFERROR("The percentages in column C are read on this figure, which includes the working capital ("&TEXT(C29,"0%")&" of the total). To compare the breakdown with another plan, use the CAPEX row below.","") -> The percentages in column C are read on this figure, which includes the working capital (32% of the total). To compare the breakdown with another plan, use the CAPEX row below.
A32: CAPEX (startup costs excluding working capital) | B32: =IFERROR(B31-B29,"") -> 182500 | D32: What you buy: build-out, equipment, launch and formation costs. The cash cushion is not an investment: it is working capital
A33: Recoverable input tax on capex | B33: =IFERROR(IF(B31="","",SUMIF($E$7:$E$28,"Yes",$B$7:$B$28)*'0. Assumptions'!$B$41),"") -> 0 | D33: =IFERROR("At "&TEXT('0. Assumptions'!$B$41,"0%")&" on the items marked ""Yes"" in the tax column. US: the sales tax you pay on equipment is part of its cost and is not recovered, so this rate is 0. UK (VAT-registered): 20%, reclaimed on your VAT return, but you pay it first, so the loan has to cover it","") -> At 0% on the items marked "Yes" in the tax column. US: the sales tax you pay on equipment is part of its cost and is not recovered, so this rate is 0. UK (VAT-registered): 20%, reclaimed on your VAT return, but you pay it first, so the loan has to cover it
A34: TOTAL CASH NEEDED AT LAUNCH | B34: =IFERROR(B31+B33,"") -> 266709 | D34: This is the figure the Financing tab has to cover
A35: DEPRECIATION BASES (not added to startup costs)
A36: Build-out, fixtures and setup | B36: =IFERROR(IF(B9="","",B9+B10+B11+B12+B23+B28),"") -> 70400 | D36: =IFERROR("Depreciated over "&TEXT('0. Assumptions'!$B$44,"0")&" years","") -> Depreciated over 10 years
A37: Machinery, furniture and equipment | B37: =IFERROR(IF(B13="","",B13+B14+B15+B16+B17+B18+B19+B20+B21+B22),"") -> 88500 | D37: =IFERROR("Depreciated over "&TEXT('0. Assumptions'!$B$45,"0")&" years","") -> Depreciated over 7 years
A38: Annual depreciation of fixed assets | B38: =IFERROR(B36/MAX(1,'0. Assumptions'!$B$44)+B37/MAX(1,'0. Assumptions'!$B$45),"") -> 19682.857 | D38: =IFERROR("Not depreciated, because they are not fixed assets: entity formation and legal, licenses and health plan review, launch marketing, opening inventory, security deposit, pre-opening rent and the working capital reserve. They add up to "&TEXT(B31-B36-B37,"#,##0")&" of the "&TEXT(B31,"#,##0")&" total investment.","") -> Not depreciated, because they are not fixed assets: entity formation and legal, licenses and health plan review, launch marketing, opening inventory, security deposit, pre-opening rent and the working capital reserve. They add up to 107809 of the 266709 total investment.

Sheet 3-Year P&L
A1: PROFIT AND LOSS STATEMENT — 3 YEARS
A2: Base scenario — Bakery with storefront, café corner and wholesale
A4: Item | B4: Year 1 | C4: Year 2 | D4: Year 3 | E4: % of sales (year 1) | F4: Notes | G4: Sales tax rate on the line (%) | H4: Tax-exempt share of the line (%)
A5: REVENUE
A6: Transactions per day (average) | B6: =IFERROR(IF('0. Assumptions'!$B$4="","",'0. Assumptions'!$B$4),"") -> 210 | C6: =IFERROR(B6*(1+'0. Assumptions'!$B$7),"") -> 235.2 | D6: =IFERROR(C6*(1+'0. Assumptions'!$B$8),"") -> 251.664 | F6: Growth for years 2 and 3 is set in "0. Assumptions"
A7: Average check (excl. sales tax) | B7: =IFERROR(IF('0. Assumptions'!$B$5="","",'0. Assumptions'!$B$5),"") -> 10 | C7: =IFERROR(IF(B7="","",B7),"") -> 10 | D7: =IFERROR(IF(C7="","",C7),"") -> 10 | F7: Held constant at year-1 prices: a price increase is a separate decision
A8: Operating days per year | B8: =IFERROR(IF('0. Assumptions'!$B$6="","",'0. Assumptions'!$B$6),"") -> 310 | C8: =IFERROR(IF(B8="","",B8),"") -> 310 | D8: =IFERROR(IF(C8="","",C8),"") -> 310
A9: TOTAL REVENUE (excl. sales tax) | B9: =IFERROR(IF(B6*B7*B8=0,"",B6*B7*B8),"") -> 651000 | C9: =IFERROR(IF(C6*C7*C8=0,"",C6*C7*C8),"") -> 729120 | D9: =IFERROR(IF(D6*D7*D8=0,"",D6*D7*D8),"") -> 780158.4 | E9: =IFERROR(IF(B9="","",1),"") -> 1
A10: Bakery sales: bread, pastries and wholesale to cafés | B10: =IFERROR(IF(B9="","",B9*$E$10),"") -> 553350 | C10: =IFERROR(IF(C9="","",C9*$E$10),"") -> 619752 | D10: =IFERROR(IF(D9="","",D9*$E$10),"") -> 663134.64 | E10: =IFERROR(IF('0. Assumptions'!$B$11="","",'0. Assumptions'!$B$11),"") -> 0.85 | F10: Artisan bread and pastries from the shop, plus the wholesale channel to cafés and restaurants (the bread you sell to another business is the same product line as the bread you sell at the counter; only the channel changes). NOTE: the model projects sales with ONE engine — transactions × average check × days — so a delivery to another business enters here as one more transaction, not as a big order. What the workbook does capture is its effect on cash, through the average collection days on "0. Assumptions". If wholesale weighs heavily in your project, model it separately · The percentage on the right ("Tax-exempt share of the line (%)") is the part of this line that carries no sales tax: bakery goods to go, plus wholesale sales to a café that resells them (with a resale certificate on file). The example is 0.80. Many states exempt bakery goods sold to go and tax what is eaten in the shop, but the rules vary by state: check yours. At 0 the workbook taxes the whole line. In the UK, cold bakery goods to go are zero-rated and on-site consumption carries 20% VAT. It only affects cash flow: the P&L is excl. sales tax | G10: =IFERROR(IF(B9="","",H10*0+(1-H10)*'0. Assumptions'!$B$39),"") -> 0.016 | H10: 0.8
A11: Coffee and beverage sales (no alcohol) | B11: =IFERROR(IF(B9="","",B9*$E$11),"") -> 97650 | C11: =IFERROR(IF(C9="","",C9*$E$11),"") -> 109368 | D11: =IFERROR(IF(D9="","",D9*$E$11),"") -> 117023.76 | E11: =IFERROR(IF('0. Assumptions'!$B$12="","",'0. Assumptions'!$B$12),"") -> 0.15 | F11: Whole-bean coffee, teas and infusions from the counter, to go with breakfast or an afternoon snack: specialty beans cost more than commodity coffee, and the benchmarks table on the "Instructions" tab puts beverage cost at 20-30% of its own sales (kit estimate) | G11: =IFERROR(IF(B9="","",('0. Assumptions'!$B$62*((1-'0. Assumptions'!$B$16)*'0. Assumptions'!$B$63+'0. Assumptions'!$B$16*'0. Assumptions'!$B$40)+(1-'0. Assumptions'!$B$62)*'0. Assumptions'!$B$39)),"") -> 0.08
A12: VARIABLE COSTS
A13: Cost of goods sold — food | B13: =IFERROR(IF(B9="","",B9*'0. Assumptions'!$B$11*'0. Assumptions'!$B$13),"") -> 166005 | C13: =IFERROR(IF(C9="","",C9*'0. Assumptions'!$B$11*'0. Assumptions'!$B$13),"") -> 185925.6 | D13: =IFERROR(IF(D9="","",D9*'0. Assumptions'!$B$11*'0. Assumptions'!$B$13),"") -> 198940.39 | E13: =IFERROR(B13/$B$9,"") -> 0.255 | F13: =IFERROR("At "&TEXT('0. Assumptions'!$B$13,"0%")&" of FOOD sales, not of total sales: beverages have their own line · In the US the sales tax you pay on ingredients is a cost, not a credit, so column G of this row is 0","") -> At 30% of FOOD sales, not of total sales: beverages have their own line · In the US the sales tax you pay on ingredients is a cost, not a credit, so column G of this row is 0 | G13: =IFERROR(IF(B9="","",'0. Assumptions'!$B$41),"") -> 0
A14: Cost of goods sold — beverage | B14: =IFERROR(IF(B9="","",B9*'0. Assumptions'!$B$12*'0. Assumptions'!$B$14),"") -> 21483 | C14: =IFERROR(IF(C9="","",C9*'0. Assumptions'!$B$12*'0. Assumptions'!$B$14),"") -> 24060.96 | D14: =IFERROR(IF(D9="","",D9*'0. Assumptions'!$B$12*'0. Assumptions'!$B$14),"") -> 25745.227 | E14: =IFERROR(B14/$B$9,"") -> 0.033 | F14: =IFERROR("At "&TEXT('0. Assumptions'!$B$14,"0%")&" of BEVERAGE sales","") -> At 22% of BEVERAGE sales | G14: =IFERROR(IF(B9="","",'0. Assumptions'!$B$41),"") -> 0
A15: Disposables and packaging | B15: =IFERROR(IF(B9="","",B9*'0. Assumptions'!$B$15),"") -> 19530 | C15: =IFERROR(IF(C9="","",C9*'0. Assumptions'!$B$15),"") -> 21873.6 | D15: =IFERROR(IF(D9="","",D9*'0. Assumptions'!$B$15),"") -> 23404.752 | E15: =IFERROR(B15/$B$9,"") -> 0.03 | G15: =IFERROR(IF(B9="","",'0. Assumptions'!$B$41),"") -> 0
A16: Delivery platform fees | B16: =IFERROR(IF(B9="","",B9*'0. Assumptions'!$B$16*'0. Assumptions'!$B$17),"") -> 0 | C16: =IFERROR(IF(C9="","",C9*'0. Assumptions'!$B$16*'0. Assumptions'!$B$17),"") -> 0 | D16: =IFERROR(IF(D9="","",D9*'0. Assumptions'!$B$16*'0. Assumptions'!$B$17),"") -> 0 | E16: =IFERROR(B16/$B$9,"") -> 0 | F16: Applied to the sales of THAT CHANNEL. With 0% delivery in Assumptions, this line is zero | G16: =IFERROR(IF(B9="","",'0. Assumptions'!$B$41),"") -> 0
A17: Card processing fees | B17: =IFERROR(IF(B9="","",B9*'0. Assumptions'!$B$18),"") -> 22785 | C17: =IFERROR(IF(C9="","",C9*'0. Assumptions'!$B$18),"") -> 25519.2 | D17: =IFERROR(IF(D9="","",D9*'0. Assumptions'!$B$18),"") -> 27305.544 | E17: =IFERROR(B17/$B$9,"") -> 0.035 | F17: Card processing fees are not subject to sales tax: no tax is recovered or deducted for them | G17: 0
A18: Miscellaneous and contingency | B18: =IFERROR(IF(B9="","",B9*'0. Assumptions'!$B$28),"") -> 13020 | C18: =IFERROR(IF(C9="","",C9*'0. Assumptions'!$B$28),"") -> 14582.4 | D18: =IFERROR(IF(D9="","",D9*'0. Assumptions'!$B$28),"") -> 15603.168 | E18: =IFERROR(B18/$B$9,"") -> 0.02 | F18: =IFERROR("At "&TEXT('0. Assumptions'!$B$28,"0%")&" of sales. It is a VARIABLE cost: it moves with revenue, so it cannot sit in fixed costs","") -> At 2% of sales. It is a VARIABLE cost: it moves with revenue, so it cannot sit in fixed costs | G18: =IFERROR(IF(B9="","",'0. Assumptions'!$B$41),"") -> 0
A19: TOTAL VARIABLE COSTS | B19: =IFERROR(IF(B9="","",SUM(B13:B18)),"") -> 242823 | C19: =IFERROR(IF(C9="","",SUM(C13:C18)),"") -> 271961.76 | D19: =IFERROR(IF(D9="","",SUM(D13:D18)),"") -> 290999.08 | E19: =IFERROR(B19/$B$9,"") -> 0.373
A20: GROSS MARGIN | B20: =IFERROR(IF(B9="","",B9-B19),"") -> 408177 | C20: =IFERROR(IF(C9="","",C9-C19),"") -> 457158.24 | D20: =IFERROR(IF(D9="","",D9-D19),"") -> 489159.32 | E20: =IFERROR(B20/$B$9,"") -> 0.627
A21: FIXED COSTS
A22: Rent | B22: =IFERROR(IF(B9="","",'0. Assumptions'!$B$24*12),"") -> 50400 | C22: =IFERROR(IF(C9="","",B22*(1+'0. Assumptions'!$B$48)),"") -> 50400 | D22: =IFERROR(IF(D9="","",C22*(1+'0. Assumptions'!$B$48)),"") -> 50400 | E22: =IFERROR(B22/$B$9,"") -> 0.077419355 | F22: The monthly amount is on the "0. Assumptions" tab; here it is multiplied by twelve. Rent for the build-out months, which comes before opening, is on the Startup Costs tab and is NOT counted twice | G22: =IFERROR(IF(B9="","",'0. Assumptions'!$B$41),"") -> 0
A23: Labor (wages + employer payroll taxes) | B23: =IFERROR(IF(B9="","",Staffing!$G$11),"") -> 220836 | C23: =IFERROR(IF(C9="","",Staffing!$B$15),"") -> 226836 | D23: =IFERROR(IF(D9="","",Staffing!$B$16),"") -> 232836 | E23: =IFERROR(B23/$B$9,"") -> 0.33922581 | F23: Comes from the Staffing tab: it is the SAME number, not a separate estimate. Years 2 and 3 add the new hires declared on that tab, not a percentage of volume | G23: 0
A24: Utilities (electricity, water, gas) | B24: =IFERROR(IF(B9="","",'0. Assumptions'!$B$26*12),"") -> 18000 | C24: =IFERROR(IF(C9="","",B24*(1+'0. Assumptions'!$B$48)),"") -> 18000 | D24: =IFERROR(IF(D9="","",C24*(1+'0. Assumptions'!$B$48)),"") -> 18000 | E24: =IFERROR(B24/$B$9,"") -> 0.02764977 | F24: Enter the monthly bills excl. sales tax. The workbook applies a single tax treatment to this whole line, the one in the column next to it; if one utility is taxed differently in your area, give it its own line | G24: =IFERROR(IF(B9="","",'0. Assumptions'!$B$41),"") -> 0
A25: Insurance (general liability + property / auto) | B25: =IFERROR(IF(B9="","",'0. Assumptions'!$B$27),"") -> 4500 | C25: =IFERROR(IF(C9="","",B25*(1+'0. Assumptions'!$B$48)),"") -> 4500 | D25: =IFERROR(IF(D9="","",C25*(1+'0. Assumptions'!$B$48)),"") -> 4500 | E25: =IFERROR(B25/$B$9,"") -> 0.0069124424 | F25: Insurance premiums are not subject to sales tax: there is no recoverable tax on them | G25: 0
A26: Accountant | B26: 3600 | C26: =IFERROR(IF(C9="","",B26*(1+'0. Assumptions'!$B$48)),"") -> 3600 | D26: =IFERROR(IF(D9="","",C26*(1+'0. Assumptions'!$B$48)),"") -> 3600 | E26: =IFERROR(B26/$B$9,"") -> 0.0055299539 | G26: =IFERROR(IF(B9="","",'0. Assumptions'!$B$41),"") -> 0
A27: Oven and equipment maintenance | B27: 4000 | C27: =IFERROR(IF(C9="","",B27*(1+'0. Assumptions'!$B$48)),"") -> 4000 | D27: =IFERROR(IF(D9="","",C27*(1+'0. Assumptions'!$B$48)),"") -> 4000 | E27: =IFERROR(B27/$B$9,"") -> 0.0061443932 | G27: =IFERROR(IF(B9="","",'0. Assumptions'!$B$41),"") -> 0
A28: Marketing | B28: 7200 | C28: =IFERROR(IF(C9="","",B28*(1+'0. Assumptions'!$B$48)),"") -> 7200 | D28: =IFERROR(IF(D9="","",C28*(1+'0. Assumptions'!$B$48)),"") -> 7200 | E28: =IFERROR(B28/$B$9,"") -> 0.011059908 | G28: =IFERROR(IF(B9="","",'0. Assumptions'!$B$41),"") -> 0
A29: Software | B29: 1800 | C29: =IFERROR(IF(C9="","",B29*(1+'0. Assumptions'!$B$48)),"") -> 1800 | D29: =IFERROR(IF(D9="","",C29*(1+'0. Assumptions'!$B$48)),"") -> 1800 | E29: =IFERROR(B29/$B$9,"") -> 0.002764977 | G29: =IFERROR(IF(B9="","",'0. Assumptions'!$B$41),"") -> 0
A30: Cleaning | B30: 2400 | C30: =IFERROR(IF(C9="","",B30*(1+'0. Assumptions'!$B$48)),"") -> 2400 | D30: =IFERROR(IF(D9="","",C30*(1+'0. Assumptions'!$B$48)),"") -> 2400 | E30: =IFERROR(B30/$B$9,"") -> 0.0036866359 | G30: =IFERROR(IF(B9="","",'0. Assumptions'!$B$41),"") -> 0
A31: Miscellaneous | B31: 1200 | C31: =IFERROR(IF(C9="","",B31*(1+'0. Assumptions'!$B$48)),"") -> 1200 | D31: =IFERROR(IF(D9="","",C31*(1+'0. Assumptions'!$B$48)),"") -> 1200 | E31: =IFERROR(B31/$B$9,"") -> 0.001843318 | G31: =IFERROR(IF(B9="","",'0. Assumptions'!$B$41),"") -> 0
A32: Waste hauling (organic and cardboard) | B32: 1200 | C32: =IFERROR(IF(C9="","",B32*(1+'0. Assumptions'!$B$48)),"") -> 1200 | D32: =IFERROR(IF(D9="","",C32*(1+'0. Assumptions'!$B$48)),"") -> 1200 | E32: =IFERROR(B32/$B$9,"") -> 0.001843318 | F32: Licensed waste / grease hauler; the checklist asks for the contract before you open. This plan does not fry, so the volume is lower than a restaurant's: get a quote in your area | G32: =IFERROR(IF(B9="","",'0. Assumptions'!$B$41),"") -> 0
A33: Pest control | B33: 900 | C33: =IFERROR(IF(C9="","",B33*(1+'0. Assumptions'!$B$48)),"") -> 900 | D33: =IFERROR(IF(D9="","",C33*(1+'0. Assumptions'!$B$48)),"") -> 900 | E33: =IFERROR(B33/$B$9,"") -> 0.0013824885 | F33: Licensed pest control company; part of the HACCP-based food safety plan that the checklist already requires in the staff phase. Stored flour attracts pests more easily than a restaurant pantry does, so the budget is slightly higher | G33: =IFERROR(IF(B9="","",'0. Assumptions'!$B$41),"") -> 0
A34: Music licensing (ASCAP, BMI, SESAC) | B34: 600 | C34: =IFERROR(IF(C9="","",B34*(1+'0. Assumptions'!$B$48)),"") -> 600 | D34: =IFERROR(IF(D9="","",C34*(1+'0. Assumptions'!$B$48)),"") -> 600 | E34: =IFERROR(B34/$B$9,"") -> 0.00092165899 | F34: ASCAP, BMI and SESAC are separate licensing organizations; the fee depends on the size and capacity of your shop. Only needed if you play music | G34: =IFERROR(IF(B9="","",'0. Assumptions'!$B$41),"") -> 0
A35: Training and certifications | B35: 500 | C35: =IFERROR(IF(C9="","",B35*(1+'0. Assumptions'!$B$48)),"") -> 500 | D35: =IFERROR(IF(D9="","",C35*(1+'0. Assumptions'!$B$48)),"") -> 500 | E35: =IFERROR(B35/$B$9,"") -> 0.00076804916 | F35: Food handler cards, Certified Food Protection Manager certification (for example ServSafe) and workplace safety training for the team. A bakery has specific hazards (burns, heavy lifting, flour dust in the air). Requirements vary by state and county | G35: =IFERROR(IF(B9="","",'0. Assumptions'!$B$41),"") -> 0
A36: Depreciation of fixed assets | B36: =IFERROR(IF(B9="","",'Startup Costs'!$B$38),"") -> 19682.857 | C36: =IFERROR(IF(C9="","",B36),"") -> 19682.857 | D36: =IFERROR(IF(D9="","",B36),"") -> 19682.857 | E36: =IFERROR(B36/$B$9,"") -> 0.030234804 | F36: Comes from the depreciation bases on the Startup Costs tab: real fixed assets only. It does NOT rise with inflation: it is a charge on the HISTORICAL cost of the assets | G36: 0
A37: Interest expense (loan interest) | B37: =IFERROR(IF(B9="","",Financing!$B$44),"") -> 19700 | C37: =IFERROR(IF(C9="","",Financing!$B$46),"") -> 18463.916 | D37: =IFERROR(IF(D9="","",Financing!$B$48),"") -> 17104.223 | E37: =IFERROR(B37/$B$9,"") -> 0.030261137 | F37: Only INTEREST is an expense. Principal repaid appears on the cash flow tab | G37: 0
A38: TOTAL FIXED COSTS | B38: =IFERROR(IF(B9="","",SUM(B22:B37)),"") -> 356518.86 | C38: =IFERROR(IF(C9="","",SUM(C22:C37)),"") -> 361282.77 | D38: =IFERROR(IF(D9="","",SUM(D22:D37)),"") -> 365923.08 | E38: =IFERROR(B38/$B$9,"") -> 0.54764801
A39: Recoverable input tax on variable costs | B39: =IFERROR(IF(B9="","",SUMPRODUCT(B13:B18,G13:G18)),"") -> 0 | C39: =IFERROR(IF(C9="","",SUMPRODUCT(C13:C18,G13:G18)),"") -> 0 | D39: =IFERROR(IF(D9="","",SUMPRODUCT(D13:D18,G13:G18)),"") -> 0 | F39: Each line at ITS OWN rate, read from the column next to it. It is what the cash flow tab overpays to suppliers and later deducts (zero wherever no tax is recoverable)
A40: Recoverable input tax on fixed costs | B40: =IFERROR(IF(B9="","",SUMPRODUCT(B22:B37,G22:G37)),"") -> 0 | C40: =IFERROR(IF(C9="","",SUMPRODUCT(C22:C37,G22:G37)),"") -> 0 | D40: =IFERROR(IF(D9="","",SUMPRODUCT(D22:D37,G22:G37)),"") -> 0
A41: PRE-TAX INCOME (EBT) | B41: =IFERROR(IF(B9="","",B20-B38),"") -> 51658.143 | C41: =IFERROR(IF(C9="","",C20-C38),"") -> 95875.467 | D41: =IFERROR(IF(D9="","",D20-D38),"") -> 123236.24 | E41: =IFERROR(B41/$B$9,"") -> 0.079351986
A42: Net operating losses carried forward (opening) | B42: =IFERROR(IF(B9="","",'0. Assumptions'!$B$42),"") -> 0 | C42: =IFERROR(IF(C9="","",B47),"") -> 0 | D42: =IFERROR(IF(D9="","",C47),"") -> 0 | F42: Federal rules let a year's losses offset the profits of later years (the federal limit is 80% of taxable income; this model offsets 100% as a simplification)
A43: Taxable income (after loss offset) | B43: =IFERROR(IF(B9="","",MAX(0,B41-B42)),"") -> 51658.143 | C43: =IFERROR(IF(C9="","",MAX(0,C41-C42)),"") -> 95875.467 | D43: =IFERROR(IF(D9="","",MAX(0,D41-D42)),"") -> 123236.24
A44: Years with positive taxable income (cumulative) | B44: =IFERROR(IF(B9="","",IF(B43>0,1,0)),"") -> 1 | C44: =IFERROR(IF(C9="","",B44+IF(C43>0,1,0)),"") -> 2 | D44: =IFERROR(IF(D9="","",C44+IF(D43>0,1,0)),"") -> 3
A45: Effective income tax rate applied | B45: =IFERROR(IF(B9="","",IF(B43<=0,"",IF(B44<=2,'0. Assumptions'!$B$37,'0. Assumptions'!$B$38))),"") -> 0.25 | C45: =IFERROR(IF(C9="","",IF(C43<=0,"",IF(C44<=2,'0. Assumptions'!$B$37,'0. Assumptions'!$B$38))),"") -> 0.25 | D45: =IFERROR(IF(D9="","",IF(D43<=0,"",IF(D44<=2,'0. Assumptions'!$B$37,'0. Assumptions'!$B$38))),"") -> 0.25 | F45: The "years 1-2" rate applies to the first two years with positive taxable income, not to the first two calendar years of the business. The model approximates this by counting the first two profitable years
A46: Income tax | B46: =IFERROR(IF(B9="","",IF(B45="",0,B43*B45)),"") -> 12914.536 | C46: =IFERROR(IF(C9="","",IF(C45="",0,C43*C45)),"") -> 23968.867 | D46: =IFERROR(IF(D9="","",IF(D45="",0,D43*D45)),"") -> 30809.059
A47: Net operating losses carried forward (closing) | B47: =IFERROR(IF(B9="","",MAX(0,B42-B41)),"") -> 0 | C47: =IFERROR(IF(C9="","",MAX(0,C42-C41)),"") -> 0 | D47: =IFERROR(IF(D9="","",MAX(0,D42-D41)),"") -> 0
A48: NET INCOME | B48: =IFERROR(IF(B9="","",B41-B46),"") -> 38743.607 | C48: =IFERROR(IF(C9="","",C41-C46),"") -> 71906.6 | D48: =IFERROR(IF(D9="","",D41-D46),"") -> 92427.177 | E48: =IFERROR(B48/$B$9,"") -> 0.059513989
A49: KEY RATIOS
A50: Ratio | B50: Year 1 | C50: Year 2 | D50: Year 3 | E50: Threshold | F50: Comment
A51: Gross margin / Sales | B51: =IFERROR(IF(B9="","",B20/B9),"") -> 0.627 | C51: =IFERROR(IF(C9="","",C20/C9),"") -> 0.627 | D51: =IFERROR(IF(D9="","",D20/D9),"") -> 0.627 | E51: 0.6 | F51: Kit benchmark (editable estimate): the floor this workbook sets for a bakery, a gross margin of at least 60%. Artisan bread earns a better margin than industrial bread
A52: Cost of goods sold (food + beverage) | B52: =IFERROR(IF(B9="","",B13+B14),"") -> 187488 | C52: =IFERROR(IF(C9="","",C13+C14),"") -> 209986.56 | D52: =IFERROR(IF(D9="","",D13+D14),"") -> 224685.62
A53: Cost of goods sold / Sales | B53: =IFERROR(IF(B9="","",B52/B9),"") -> 0.288 | C53: =IFERROR(IF(C9="","",C52/C9),"") -> 0.288 | D53: =IFERROR(IF(D9="","",D52/D9),"") -> 0.288 | E53: 0.33 | F53: Kit benchmark (editable estimate): ceiling for the blended cost of goods sold, inside the 28-35% range for bakeries (Toast). Bread, pastries and coffee each have their own range in the industry benchmarks table on the "Instructions" tab
A54: Labor cost / Sales | B54: =IFERROR(IF(B9="","",B23/B9),"") -> 0.33922581 | C54: =IFERROR(IF(C9="","",C23/C9),"") -> 0.31110928 | D54: =IFERROR(IF(D9="","",D23/D9),"") -> 0.29844708 | E54: 0.38 | F54: Kit benchmark (editable estimate): 38% is inside the 24-40% labor range for bakeries (Toast), where artisan bread runs 34-40%. The reason it is higher than a coffee shop's is the early production shift and the double job (production plus selling). Using a lower ceiling would require a staff below the minimum a bakery that bakes every day can operate with
A55: Rent / Sales | B55: =IFERROR(IF(B9="","",B22/B9),"") -> 0.077419355 | C55: =IFERROR(IF(C9="","",C22/C9),"") -> 0.069124424 | D55: =IFERROR(IF(D9="","",D22/D9),"") -> 0.064602265 | E55: 0.1 | F55: Kit benchmark (editable estimate): rent up to 10% of sales
A56: Net income / Sales | B56: =IFERROR(IF(B9="","",B48/B9),"") -> 0.059513989 | C56: =IFERROR(IF(C9="","",C48/C9),"") -> 0.098621078 | D56: =IFERROR(IF(D9="","",D48/D9),"") -> 0.11847232 | E56: 0.05 | F56: Kit benchmark (editable estimate): 5% of sales, at the top of the 3-5% that is typical of the food sector (Toast); artisan and specialty bakeries can earn more. With EBITDA in the low part of the range in the industry benchmarks table, what is left after depreciation, interest and income tax is a net margin of about 5%
A57: Break-even reached | B57: =IFERROR(IF(B9="","",IF(B9>='Break-Even'!$B$16,"Yes","No")),"") -> Yes | C57: =IFERROR(IF(C9="","",IF(C9>='Break-Even'!$C$16,"Yes","No")),"") -> Yes | D57: =IFERROR(IF(D9="","",IF(D9>='Break-Even'!$D$16,"Yes","No")),"") -> Yes | F57: Compares each year's sales with that same year's threshold, which the Break-Even tab calculates with that year's fixed costs
A59: All figures are EXCL. SALES TAX. Years 2 and 3 are in year-1 prices unless you raise cost inflation in the "0. Assumptions" tab. The "Sales tax rate on the line (%)" column shows, on SALES lines, the rate collected on each one and, on COST lines, the rate paid on that item. The cash flow tab reads it: insurance and card fees carry no sales tax, and wages, depreciation and interest carry none either.

Sheet Break-Even
A1: BREAK-EVEN
A4: Variable | B4: Year 1 | C4: Year 2 | D4: Year 3 | E4: Notes
A5: BASE DATA BY YEAR
A6: Annual fixed costs | B6: =IFERROR(IF('3-Year P&L'!$B$9="","",'3-Year P&L'!$B$38),"") -> 356518.86 | C6: =IFERROR(IF('3-Year P&L'!$C$9="","",'3-Year P&L'!$C$38),"") -> 361282.77 | D6: =IFERROR(IF('3-Year P&L'!$D$9="","",'3-Year P&L'!$D$38),"") -> 365923.08 | E6: The SAME fixed costs as the P&L. Each year has its own, which is why the threshold cannot be a single one for all three years
A7: Monthly fixed costs | B7: =IFERROR(IF('3-Year P&L'!$B$9="","",B6/12),"") -> 29709.905 | C7: =IFERROR(IF('3-Year P&L'!$C$9="","",C6/12),"") -> 30106.898 | D7: =IFERROR(IF('3-Year P&L'!$D$9="","",D6/12),"") -> 30493.59
A8: Average check (excl. sales tax) | B8: =IFERROR(IF('3-Year P&L'!$B$9="","",'3-Year P&L'!$B$7),"") -> 10 | C8: =IFERROR(IF('3-Year P&L'!$C$9="","",'3-Year P&L'!$C$7),"") -> 10 | D8: =IFERROR(IF('3-Year P&L'!$D$9="","",'3-Year P&L'!$D$7),"") -> 10
A9: Variable cost per transaction | B9: =IFERROR(IF('3-Year P&L'!$B$9="","",'3-Year P&L'!$B$19/('3-Year P&L'!$B$6*'3-Year P&L'!$B$8)),"") -> 3.73 | C9: =IFERROR(IF('3-Year P&L'!$C$9="","",'3-Year P&L'!$C$19/('3-Year P&L'!$C$6*'3-Year P&L'!$C$8)),"") -> 3.73 | D9: =IFERROR(IF('3-Year P&L'!$D$9="","",'3-Year P&L'!$D$19/('3-Year P&L'!$D$6*'3-Year P&L'!$D$8)),"") -> 3.73 | E9: Comes from the P&L total variable costs, not from a separate estimate. It includes miscellaneous and contingency, which is a percentage of sales
A10: Contribution margin per transaction | B10: =IFERROR(IF('3-Year P&L'!$B$9="","",B8-B9),"") -> 6.27 | C10: =IFERROR(IF('3-Year P&L'!$C$9="","",C8-C9),"") -> 6.27 | D10: =IFERROR(IF('3-Year P&L'!$D$9="","",D8-D9),"") -> 6.27 | E10: Average check minus unit variable cost
A11: Operating days per year | B11: =IFERROR(IF('3-Year P&L'!$B$9="","",'3-Year P&L'!$B$8),"") -> 310 | C11: =IFERROR(IF('3-Year P&L'!$C$9="","",'3-Year P&L'!$C$8),"") -> 310 | D11: =IFERROR(IF('3-Year P&L'!$D$9="","",'3-Year P&L'!$D$8),"") -> 310 | E11: The same calendar as the P&L and the scenarios
A12: Principal repaid in the year | B12: =IFERROR(IF('3-Year P&L'!$B$9="","",Financing!$B$45),"") -> 12360.843 | C12: =IFERROR(IF('3-Year P&L'!$C$9="","",Financing!$B$47),"") -> 13596.927 | D12: =IFERROR(IF('3-Year P&L'!$D$9="","",Financing!$B$49),"") -> 14956.62 | E12: Principal is NOT a P&L expense, but it leaves the cash account. Without it, the published break-even threshold would sit below the real one
A13: ACCOUNTING BREAK-EVEN (includes depreciation)
A14: Transactions needed per year | B14: =IFERROR(IF('3-Year P&L'!$B$9="","",IF(B10<=0,"",B6/B10)),"") -> 56861.062 | C14: =IFERROR(IF('3-Year P&L'!$C$9="","",IF(C10<=0,"",C6/C10)),"") -> 57620.857 | D14: =IFERROR(IF('3-Year P&L'!$D$9="","",IF(D10<=0,"",D6/D10)),"") -> 58360.938
A15: Transactions needed per day | B15: =IFERROR(IF('3-Year P&L'!$B$9="","",B14/B11),"") -> 183.42278 | C15: =IFERROR(IF('3-Year P&L'!$C$9="","",C14/C11),"") -> 185.87373 | D15: =IFERROR(IF('3-Year P&L'!$D$9="","",D14/D11),"") -> 188.26109
A16: Revenue needed per year | B16: =IFERROR(IF('3-Year P&L'!$B$9="","",B14*B8),"") -> 568610.62 | C16: =IFERROR(IF('3-Year P&L'!$C$9="","",C14*C8),"") -> 576208.57 | D16: =IFERROR(IF('3-Year P&L'!$D$9="","",D14*D8),"") -> 583609.38
A17: CASH BREAK-EVEN (loan payments in, depreciation out)
A18: Cash fixed costs + principal repaid for the year | B18: =IFERROR(IF('3-Year P&L'!$B$9="","",B6-'3-Year P&L'!$B$36+B12),"") -> 349196.84 | C18: =IFERROR(IF('3-Year P&L'!$C$9="","",C6-'3-Year P&L'!$C$36+C12),"") -> 355196.84 | D18: =IFERROR(IF('3-Year P&L'!$D$9="","",D6-'3-Year P&L'!$D$36+D12),"") -> 361196.84 | E18: The P&L fixed costs without depreciation (which is not paid in cash) and WITH principal repaid (which is). This is the threshold that decides whether cash holds up
A19: Transactions needed per year (cash) | B19: =IFERROR(IF('3-Year P&L'!$B$9="","",IF(B10<=0,"",B18/B10)),"") -> 55693.276 | C19: =IFERROR(IF('3-Year P&L'!$C$9="","",IF(C10<=0,"",C18/C10)),"") -> 56650.214 | D19: =IFERROR(IF('3-Year P&L'!$D$9="","",IF(D10<=0,"",D18/D10)),"") -> 57607.152
A20: Transactions needed per day (cash) | B20: =IFERROR(IF('3-Year P&L'!$B$9="","",B19/B11),"") -> 179.65573 | C20: =IFERROR(IF('3-Year P&L'!$C$9="","",C19/C11),"") -> 182.74263 | D20: =IFERROR(IF('3-Year P&L'!$D$9="","",D19/D11),"") -> 185.82952
A21: Revenue needed per year (cash) | B21: =IFERROR(IF('3-Year P&L'!$B$9="","",B19*B8),"") -> 556932.76 | C21: =IFERROR(IF('3-Year P&L'!$C$9="","",C19*C8),"") -> 566502.14 | D21: =IFERROR(IF('3-Year P&L'!$D$9="","",D19*D8),"") -> 576071.52
A22: COMPARISON WITH THE PLAN
A23: Transactions per day forecast in the plan | B23: =IFERROR(IF('3-Year P&L'!$B$9="","",'3-Year P&L'!$B$6),"") -> 210 | C23: =IFERROR(IF('3-Year P&L'!$C$9="","",'3-Year P&L'!$C$6),"") -> 235.2 | D23: =IFERROR(IF('3-Year P&L'!$D$9="","",'3-Year P&L'!$D$6),"") -> 251.664
A24: Cushion above CASH break-even (%) | B24: =IFERROR(IF('3-Year P&L'!$B$9="","",B23/B20-1),"") -> 0.16890232 | C24: =IFERROR(IF('3-Year P&L'!$C$9="","",C23/C20-1),"") -> 0.28705603 | D24: =IFERROR(IF('3-Year P&L'!$D$9="","",D23/D20-1),"") -> 0.35427351 | E24: How far planned sales sit above cash break-even. The drop you can absorb before you cannot pay the fixed costs and the loan payment is somewhat smaller: with a 25% cushion, 20%. The required minimum is set in the "0. Assumptions" tab
A25: INTERPRETATION
A26: =IFERROR("With the average check excl. sales tax above, you need "&TEXT(ROUNDUP(B15,0),"0")&" transactions a day over your "&TEXT(B11,"0")&" opening days to avoid losing money (accounting break-even, depreciation included), and "&TEXT(ROUNDUP(B20,0),"0")&" for cash to hold (cash break-even: depreciation out, because it is not paid, and the year's loan payment in"&IF(B12=0,"; no principal is repaid this year (interest-only period or no loan)","")&"). The ""Revenue needed per year"" rows show the same figures in your currency.","") -> With the average check excl. sales tax above, you need 184 transactions a day over your 310 opening days to avoid losing money (accounting break-even, depreciation included), and 180 for cash to hold (cash break-even: depreciation out, because it is not paid, and the year's loan payment in). The "Revenue needed per year" rows show the same figures in your currency.
A28: BREAK-EVEN SENSITIVITY
A29: Transactions per day needed to cover costs, by average check (columns) and variable cost per transaction (rows). Green cells are below the transactions per day that the plan forecasts.
A31: Transactions per day needed: average check excl. sales tax (columns) × variable cost per transaction (rows) | B31: =IFERROR($B$8-2,"") -> 8 | C31: =IFERROR(IF($B$8="","",$B$8),"") -> 10 | D31: =IFERROR($B$8+2,"") -> 12 | E31: =IFERROR($B$8+4,"") -> 14
A32: =IFERROR($B$9*0.85,"") -> 3.1705 | B32: =IFERROR(IF($B$31-$A32<=0,"",$B$6/($B$31-$A32)/$B$11),"") -> 238.13248 | C32: =IFERROR(IF($C$31-$A32<=0,"",$B$6/($C$31-$A32)/$B$11),"") -> 168.39605 | D32: =IFERROR(IF($D$31-$A32<=0,"",$B$6/($D$31-$A32)/$B$11),"") -> 130.25209 | E32: =IFERROR(IF($E$31-$A32<=0,"",$B$6/($E$31-$A32)/$B$11),"") -> 106.19704
A33: =IFERROR($B$9*0.925,"") -> 3.45025 | B33: =IFERROR(IF($B$31-$A33<=0,"",$B$6/($B$31-$A33)/$B$11),"") -> 252.77451 | C33: =IFERROR(IF($C$31-$A33<=0,"",$B$6/($C$31-$A33)/$B$11),"") -> 175.58851 | D33: =IFERROR(IF($D$31-$A33<=0,"",$B$6/($D$31-$A33)/$B$11),"") -> 134.51397 | E33: =IFERROR(IF($E$31-$A33<=0,"",$B$6/($E$31-$A33)/$B$11),"") -> 109.01309
A34: =IFERROR($B$9*1.0,"") -> 3.73 | B34: =IFERROR(IF($B$31-$A34<=0,"",$B$6/($B$31-$A34)/$B$11),"") -> 269.33509 | C34: =IFERROR(IF($C$31-$A34<=0,"",$B$6/($C$31-$A34)/$B$11),"") -> 183.42278 | D34: =IFERROR(IF($D$31-$A34<=0,"",$B$6/($D$31-$A34)/$B$11),"") -> 139.06419 | E34: =IFERROR(IF($E$31-$A34<=0,"",$B$6/($E$31-$A34)/$B$11),"") -> 111.98255
A35: =IFERROR($B$9*1.075,"") -> 4.00975 | B35: =IFERROR(IF($B$31-$A35<=0,"",$B$6/($B$31-$A35)/$B$11),"") -> 288.21774 | C35: =IFERROR(IF($C$31-$A35<=0,"",$B$6/($C$31-$A35)/$B$11),"") -> 191.98879 | D35: =IFERROR(IF($D$31-$A35<=0,"",$B$6/($D$31-$A35)/$B$11),"") -> 143.93302 | E35: =IFERROR(IF($E$31-$A35<=0,"",$B$6/($E$31-$A35)/$B$11),"") -> 115.11832
A36: =IFERROR($B$9*1.15,"") -> 4.2895 | B36: =IFERROR(IF($B$31-$A36<=0,"",$B$6/($B$31-$A36)/$B$11),"") -> 309.94767 | C36: =IFERROR(IF($C$31-$A36<=0,"",$B$6/($C$31-$A36)/$B$11),"") -> 201.39407 | D36: =IFERROR(IF($D$31-$A36<=0,"",$B$6/($D$31-$A36)/$B$11),"") -> 149.15516 | E36: =IFERROR(IF($E$31-$A36<=0,"",$B$6/($E$31-$A36)/$B$11),"") -> 118.43477

Sheet Scenarios
A1: SCENARIOS
A4: Metric | B4: Pessimistic | C4: Base | D4: Optimistic | E4: Notes
A5: Transactions per day | B5: 140 | C5: =IFERROR(IF('3-Year P&L'!$B$6="","",'3-Year P&L'!$B$6),"") -> 210 | D5: 233
A6: Average check (excl. sales tax) | B6: 7.64 | C6: =IFERROR(IF('3-Year P&L'!$B$7="","",'3-Year P&L'!$B$7),"") -> 10 | D6: 10.91
A7: Operating days per year | B7: 300 | C7: =IFERROR(IF('3-Year P&L'!$B$8="","",'3-Year P&L'!$B$8),"") -> 310 | D7: 320
A8: ANNUAL REVENUE (excl. sales tax) | B8: =IFERROR(IF(B5*B6*B7=0,"",B5*B6*B7),"") -> 320880 | C8: =IFERROR(IF(C5*C6*C7=0,"",C5*C6*C7),"") -> 651000 | D8: =IFERROR(IF(D5*D6*D7=0,"",D5*D6*D7),"") -> 813449.6
A9: Cost of goods sold — food | B9: =IFERROR(IF(B8="","",B8*'0. Assumptions'!$B$11*'0. Assumptions'!$B$13),"") -> 81824.4 | C9: =IFERROR(IF(C8="","",C8*'0. Assumptions'!$B$11*'0. Assumptions'!$B$13),"") -> 166005 | D9: =IFERROR(IF(D8="","",D8*'0. Assumptions'!$B$11*'0. Assumptions'!$B$13),"") -> 207429.65
A10: Cost of goods sold — beverage | B10: =IFERROR(IF(B8="","",B8*'0. Assumptions'!$B$12*'0. Assumptions'!$B$14),"") -> 10589.04 | C10: =IFERROR(IF(C8="","",C8*'0. Assumptions'!$B$12*'0. Assumptions'!$B$14),"") -> 21483 | D10: =IFERROR(IF(D8="","",D8*'0. Assumptions'!$B$12*'0. Assumptions'!$B$14),"") -> 26843.837
A11: Disposables and packaging | B11: =IFERROR(IF(B8="","",B8*'0. Assumptions'!$B$15),"") -> 9626.4 | C11: =IFERROR(IF(C8="","",C8*'0. Assumptions'!$B$15),"") -> 19530 | D11: =IFERROR(IF(D8="","",D8*'0. Assumptions'!$B$15),"") -> 24403.488
A12: Delivery platform fees | B12: =IFERROR(IF(B8="","",B8*'0. Assumptions'!$B$16*'0. Assumptions'!$B$17),"") -> 0 | C12: =IFERROR(IF(C8="","",C8*'0. Assumptions'!$B$16*'0. Assumptions'!$B$17),"") -> 0 | D12: =IFERROR(IF(D8="","",D8*'0. Assumptions'!$B$16*'0. Assumptions'!$B$17),"") -> 0
A13: Card processing fees | B13: =IFERROR(IF(B8="","",B8*'0. Assumptions'!$B$18),"") -> 11230.8 | C13: =IFERROR(IF(C8="","",C8*'0. Assumptions'!$B$18),"") -> 22785 | D13: =IFERROR(IF(D8="","",D8*'0. Assumptions'!$B$18),"") -> 28470.736
A14: Miscellaneous and contingency | B14: =IFERROR(IF(B8="","",B8*'0. Assumptions'!$B$28),"") -> 6417.6 | C14: =IFERROR(IF(C8="","",C8*'0. Assumptions'!$B$28),"") -> 13020 | D14: =IFERROR(IF(D8="","",D8*'0. Assumptions'!$B$28),"") -> 16268.992
A15: TOTAL VARIABLE COSTS | B15: =IFERROR(IF(B8="","",SUM(B9:B14)),"") -> 119688.24 | C15: =IFERROR(IF(C8="","",SUM(C9:C14)),"") -> 242823 | D15: =IFERROR(IF(D8="","",SUM(D9:D14)),"") -> 303416.7
A16: GROSS MARGIN | B16: =IFERROR(IF(B8="","",B8-B15),"") -> 201191.76 | C16: =IFERROR(IF(C8="","",C8-C15),"") -> 408177 | D16: =IFERROR(IF(D8="","",D8-D15),"") -> 510032.9
A17: FIXED COSTS (the P&L's) | B17: =IFERROR(IF(B8="","",'3-Year P&L'!$B$38),"") -> 356518.86 | C17: =IFERROR(IF(C8="","",'3-Year P&L'!$B$38),"") -> 356518.86 | D17: =IFERROR(IF(D8="","",'3-Year P&L'!$B$38),"") -> 356518.86 | E17: Fixed costs do not change with the scenario: that is why they are fixed
A18: PRE-TAX INCOME (EBT) | B18: =IFERROR(IF(B8="","",B16-B17),"") -> -155327.1 | C18: =IFERROR(IF(C8="","",C16-C17),"") -> 51658.143 | D18: =IFERROR(IF(D8="","",D16-D17),"") -> 153514.04
A19: Income tax | B19: =IFERROR(IF(B8="","",MAX(0,B18-'0. Assumptions'!$B$42)*'0. Assumptions'!$B$37),"") -> 0 | C19: =IFERROR(IF(C8="","",MAX(0,C18-'0. Assumptions'!$B$42)*'0. Assumptions'!$B$37),"") -> 12914.536 | D19: =IFERROR(IF(D8="","",MAX(0,D18-'0. Assumptions'!$B$42)*'0. Assumptions'!$B$37),"") -> 38378.511 | E19: At the "years 1-2" effective income tax rate, offsetting prior net operating losses
A20: NET INCOME | B20: =IFERROR(IF(B8="","",B18-B19),"") -> -155327.1 | C20: =IFERROR(IF(C8="","",C18-C19),"") -> 38743.607 | D20: =IFERROR(IF(D8="","",D18-D19),"") -> 115135.53
A21: Transactions per day for break-even | B21: =IFERROR(IF(B8="","",IF(B6-B15/(B5*B7)<=0,"",B17/(B6-B15/(B5*B7))/B7)),"") -> 248.08491 | C21: =IFERROR(IF(C8="","",IF(C6-C15/(C5*C7)<=0,"",C17/(C6-C15/(C5*C7))/C7)),"") -> 183.42278 | D21: =IFERROR(IF(D8="","",IF(D6-D15/(D5*D7)<=0,"",D17/(D6-D15/(D5*D7))/D7)),"") -> 162.86968
A22: WHAT EACH SCENARIO DEMANDS
A23: Labor cost / Sales | B23: =IFERROR(IF(B8="","",'3-Year P&L'!$B$23/B8),"") -> 0.6882199 | C23: =IFERROR(IF(C8="","",'3-Year P&L'!$B$23/C8),"") -> 0.33922581 | D23: =IFERROR(IF(D8="","",'3-Year P&L'!$B$23/D8),"") -> 0.27148086 | E23: The SAME staffing in all three scenarios. If labor cost blows up in the pessimistic case, adjust it in the Staffing tab, not here
A24: Transactions per year per full-time equivalent | B24: =IFERROR(IF(B8="","",B5*B7/Staffing!$C$11),"") -> 7553.9568 | C24: =IFERROR(IF(C8="","",C5*C7/Staffing!$C$11),"") -> 11708.633 | D24: =IFERROR(IF(D8="","",D5*D7/Staffing!$C$11),"") -> 13410.072 | E24: Transactions that each full-time equivalent on the "Staffing" tab would have to handle. In the optimistic scenario it tells you whether you need to hire
A25: Year-1 closing cash balance (estimate, same method in all three scenarios) | B25: =IFERROR(IF(B8="","",'Startup Costs'!$B$30+B20+'3-Year P&L'!$B$36-Financing!$B$45),"") -> -63796.083 | C25: =IFERROR(IF(C8="","",'Startup Costs'!$B$30+C20+'3-Year P&L'!$B$36-Financing!$B$45),"") -> 130274.62 | D25: =IFERROR(IF(D8="","",'Startup Costs'!$B$30+D20+'3-Year P&L'!$B$36-Financing!$B$45),"") -> 206666.55 | E25: ESTIMATED balance: working capital plus the year's result, adding back depreciation (which is not paid) and subtracting loan principal. It does not include the timing gap between receipts and payments or the sales tax settlement, so the three columns can be compared with each other. In red, the scenario runs out of cash
A26: Actual month-12 balance from the 12-Month Cash Flow tab (Base case only) | C26: =IFERROR(IF(C8="","",'12-Month Cash Flow'!$M$22),"") -> 161114.45 | E26: The ACTUAL base-case balance, with its timing of receipts and payments and its sales tax settlement. It exists only for the Base scenario, the only one with its own monthly cash flow: that is why it is not in the row above, where it would be compared against two estimates
A28: The "Base" column reads its three inputs from the "0. Assumptions" tab, so it reproduces EXACTLY year 1 of the P&L. The other two scenarios use the same cost rates: the only things that change are transactions, average check and days. The FIXED COSTS are the same in all three: miscellaneous and contingency, which are a percentage of sales, sit at the top with the variable costs and each scenario carries its own.

Sheet Staffing
A1: STAFFING AND LABOR COSTS
A2: =IFERROR("Payroll — "&TEXT('0. Assumptions'!$B$21,"0")&" pay periods + employer taxes "&TEXT('0. Assumptions'!$B$20*100,"0")&"%","") -> Payroll — 12 pay periods + employer taxes 10%
A4: Position | B4: People | C4: FTE | D4: Gross pay per month (total for the position) | E4: Employer payroll taxes (total for the position) | F4: Cost per month (total for the position) | G4: Cost per year | H4: Hours per week per person | I4: Hours per year for the position | J4: Notes
A5: Head baker / Owner | B5: 1 | C5: 1 | D5: 4000 | E5: =IFERROR(IF(D5="","",D5*'0. Assumptions'!$B$20),"") -> 400 | F5: =IFERROR(IF(D5="","",D5+E5),"") -> 4400 | G5: =IFERROR(IF(D5="","",F5*MAX(12,'0. Assumptions'!$B$21)),"") -> 52800 | H5: =IFERROR(IF(D5="","",C5*$B$18),"") -> 40 | I5: =IFERROR(IF(D5="","",H5*B5*$B$19),"") -> 2000 | J5: Early production shift (4:00-5:00 AM start, see Phase 4 of the checklist): mixing, shaping and baking the first batch, plus management and purchasing. It is the most skilled position in the production area
A6: Baker | B6: 1 | C6: 1 | D6: 3300 | E6: =IFERROR(IF(D6="","",D6*'0. Assumptions'!$B$20),"") -> 330 | F6: =IFERROR(IF(D6="","",D6+E6),"") -> 3630 | G6: =IFERROR(IF(D6="","",F6*MAX(12,'0. Assumptions'!$B$21)),"") -> 43560 | H6: =IFERROR(IF(D6="","",C6*$B$18),"") -> 40 | I6: =IFERROR(IF(D6="","",H6*B6*$B$19),"") -> 2000 | J6: Second batch and morning pastries; covers the head baker on days off
A7: Bakery assistant | B7: 1 | C7: 1 | D7: 2800 | E7: =IFERROR(IF(D7="","",D7*'0. Assumptions'!$B$20),"") -> 280 | F7: =IFERROR(IF(D7="","",D7+E7),"") -> 3080 | G7: =IFERROR(IF(D7="","",F7*MAX(12,'0. Assumptions'!$B$21)),"") -> 36960 | H7: =IFERROR(IF(D7="","",C7*$B$18),"") -> 40 | I7: =IFERROR(IF(D7="","",H7*B7*$B$19),"") -> 2000 | J7: Weighing, cleaning, loading and unloading the ovens, and support with fermentation
A8: Counter staff / baristas | B8: 3 | C8: 0.67 | D8: 5200 | E8: =IFERROR(IF(D8="","",D8*'0. Assumptions'!$B$20),"") -> 520 | F8: =IFERROR(IF(D8="","",D8+E8),"") -> 5720 | G8: =IFERROR(IF(D8="","",F8*MAX(12,'0. Assumptions'!$B$21)),"") -> 68640 | H8: =IFERROR(IF(D8="","",C8*$B$18),"") -> 26.8 | I8: =IFERROR(IF(D8="","",H8*B8*$B$19),"") -> 4020 | J8: Customer service, register and restocking the display case during the whole opening day
A9: Weekend extra | B9: 1 | C9: 0.4 | D9: 1040 | E9: =IFERROR(IF(D9="","",D9*'0. Assumptions'!$B$20),"") -> 104 | F9: =IFERROR(IF(D9="","",D9+E9),"") -> 1144 | G9: =IFERROR(IF(D9="","",F9*MAX(12,'0. Assumptions'!$B$21)),"") -> 13728 | H9: =IFERROR(IF(D9="","",C9*$B$18),"") -> 16 | I9: =IFERROR(IF(D9="","",H9*B9*$B$19),"") -> 800 | J9: Reinforcement for the Saturday and Sunday morning peak, when pastry demand rises
A10: Vacation and day-off relief | B10: 1 | C10: 0.15 | D10: 390 | E10: =IFERROR(IF(D10="","",D10*'0. Assumptions'!$B$20),"") -> 39 | F10: =IFERROR(IF(D10="","",D10+E10),"") -> 429 | G10: =IFERROR(IF(D10="","",F10*MAX(12,'0. Assumptions'!$B$21)),"") -> 5148 | H10: =IFERROR(IF(D10="","",C10*$B$18),"") -> 6 | I10: =IFERROR(IF(D10="","",H10*B10*$B$19),"") -> 300 | J10: Covers paid time off and the weekly day off for the production team. The US sets no federal vacation requirement, so this follows your own policy
A11: TOTAL STAFF | B11: =IFERROR(IF(COUNT(D5:D10)=0,"",SUM(B5:B10)),"") -> 8 | C11: =IFERROR(IF(COUNT(D5:D10)=0,"",SUMPRODUCT(B5:B10,C5:C10)),"") -> 5.56 | D11: =IFERROR(IF(COUNT(D5:D10)=0,"",SUM(D5:D10)),"") -> 16730 | E11: =IFERROR(IF(COUNT(D5:D10)=0,"",SUM(E5:E10)),"") -> 1673 | F11: =IFERROR(IF(COUNT(D5:D10)=0,"",SUM(F5:F10)),"") -> 18403 | G11: =IFERROR(IF(COUNT(D5:D10)=0,"",SUM(G5:G10)),"") -> 220836 | I11: =IFERROR(IF(COUNT(D5:D10)=0,"",SUM(I5:I10)),"") -> 11120
A12: STAFF GROWTH (stepped cost)
A13: Annual cost of year-2 hires | B13: 6000 | J13: FULL ANNUAL cost (gross pay + employer payroll taxes, over all pay periods) of whoever you hire that year. The P&L adds it to the previous year's cost: staffing grows by people, not by a percentage
A14: Annual cost of year-3 hires | B14: 6000 | J14: FULL ANNUAL cost (gross pay + employer payroll taxes, over all pay periods) of whoever you hire that year. The P&L adds it to the previous year's cost: staffing grows by people, not by a percentage
A15: Labor cost, year 2 | B15: =IFERROR(IF(G11="","",G11*(1+'0. Assumptions'!$B$48)+B13),"") -> 226836
A16: Labor cost, year 3 | B16: =IFERROR(IF(B15="","",B15*(1+'0. Assumptions'!$B$48)+B14),"") -> 232836
A17: COVERAGE OF SERVICE HOURS
A18: Full-time week (hours per week) | B18: 40 | J18: 40 hours a week is the FLSA overtime threshold for non-exempt employees; some states add daily overtime rules. Change it if your own full-time week is different
A19: Weeks worked per year per person | B19: 50 | J19: 50 weeks: 52 minus about two weeks of vacation, holidays and average absences. There is no federal vacation requirement in the US: adjust it to your own policy
A20: Service hours per day to cover | B20: 12 | J20: From opening to closing of the SHOP. The production shift goes in the row below and does not overlap with the counter. Count them on your real schedule
A21: People needed at the same time in each shift | B21: 2 | J21: Average number of people at the counter at the same time through the day: two in this example, which covers the morning and afternoon peaks and the coffee corner
A22: Production hours per day BEFORE opening | B22: 4 | J22: Early production shift (4:00-5:00 AM start, see Phase 4 of the checklist): mixing, shaping and baking the first batch BEFORE the shop opens
A23: People on the production shift | B23: 2 | J23: The head baker and the baker. Change it if your production shift has a different number of people
A24: Service hours to cover per year | B24: =IFERROR(IF(OR(B20="",B21="",'0. Assumptions'!$B$6=""),"",B20*B21*'0. Assumptions'!$B$6+B22*B23*'0. Assumptions'!$B$6),"") -> 9920
A25: Hours hired per year | B25: =IFERROR(IF(I11="","",I11),"") -> 11120
A26: Coverage (hired / needed) | B26: =IFERROR(B25/B24,"") -> 1.1209677 | J26: Below 100% the staff cannot cover the hours the plan declares: either hire more or cut the hours
A28: The gross pay, employer payroll taxes, monthly cost and annual cost columns are TOTALS for the row: for a position with two people they include both. FTE is the share of a full-time week for each person, and it is used to compare pay with the legal minimum in proportion; the TOTAL row multiplies it by the people in each position, so it gives the full-time equivalents of the whole team. The payroll tax rate and the number of pay periods are in the "0. Assumptions" tab.
A29: The pay floor is the HIGHER of the federal minimum wage and your state / local minimum wage, both in the "0. Assumptions" tab; part-time positions get it in proportion. There is no single national table above the federal floor: the state / local cell is delivered empty so you can enter the rate for your state and city.

Sheet Instructions
A1: INSTRUCTIONS FOR USE — Bakery Financial Projections
A3: HOW TO USE THIS WORKBOOK
A4: This financial plan is a MODEL: you type only in the GREEN cells and everything else recalculates on its own.
A5: 1. "0. Assumptions" is the control sheet: transactions per day, average check excl. sales tax, operating days, food and beverage mix, cost of goods sold, rent, financing and taxes.
A6: 2. Startup cost items, fixed costs and staffing are typed in their own tab, also in green. No number is typed twice.
A7: 3. Only "Break-Even" is derived entirely from the rest. The other three tabs also have green cells you can edit: the pessimistic and optimistic scenarios in "Scenarios", seasonality and the launch ramp-up in "12-Month Cash Flow", and the other funding sources in "Financing" (rows 8-11 count as sources but are not amortized: Your bank or SBA 7(a) loan goes in "Loan requested" on "0. Assumptions"). Everything else is calculated.
A8: 4. All figures are EXCL. SALES TAX. To turn a menu price into a price excl. sales tax, divide it by 1 + your sales tax rate (with an 8% rate, divide by 1.08); if an item is taxed differently, use its own rate. The rate of each sales line is in the "Sales tax rate on the line (%)" column of the P&L, and from it come the receipts, the sales tax collected and the equivalent menu price incl. sales tax. On the bakery line, the tax-exempt share (bakery goods to go and wholesale for resale) carries no sales tax: check how your state treats it. With the default 0% recoverable input tax, the sales tax you pay on purchases and startup costs is treated as a cost; in the UK, enter 20% if you are VAT-registered.
A9: 5. If you change the staffing, the P&L reads it on its own: labor cost comes from the "Staffing" tab, not from a separate estimate.
A10: 6. The "12-Month Cash Flow" tab answers the question that decides a bank deal: in which month the cash runs out. The minimum balance of the year can never be in red.
A11: 7. The "Financing" tab matches what you need with what you put in and builds the amortization schedule of the loan. If the difference is red, the plan is not funded.
A12: 8. The Word business plan in this kit uses the same example figures as this workbook. The workbook is the one that recalculates on its own when you change a green cell: if you change one, update the matching figures in the Word document.
A14: RATIOS AUDITED BY THIS WORKBOOK
A15: Thresholds live in the "Threshold" column of the KEY RATIOS block of the P&L: change them there and the traffic light changes with them.
A17: Ratio | B17: Year 1 value | C17: Threshold | D17: Status
A18: Cost of goods sold / Sales | B18: =IFERROR(IF('3-Year P&L'!$B$53="","",'3-Year P&L'!$B$53),"") -> 0.288 | C18: =IFERROR(IF('3-Year P&L'!$E$53="","",'3-Year P&L'!$E$53),"") -> 0.33 | D18: =IFERROR(IF(OR(B18="",C18=""),"",IF(B18<=C18,"OK","REVIEW")),"") -> OK
A19: Labor cost / Sales | B19: =IFERROR(IF('3-Year P&L'!$B$54="","",'3-Year P&L'!$B$54),"") -> 0.33922581 | C19: =IFERROR(IF('3-Year P&L'!$E$54="","",'3-Year P&L'!$E$54),"") -> 0.38 | D19: =IFERROR(IF(OR(B19="",C19=""),"",IF(B19<=C19,"OK","REVIEW")),"") -> OK
A20: Rent / Sales | B20: =IFERROR(IF('3-Year P&L'!$B$55="","",'3-Year P&L'!$B$55),"") -> 0.077419355 | C20: =IFERROR(IF('3-Year P&L'!$E$55="","",'3-Year P&L'!$E$55),"") -> 0.1 | D20: =IFERROR(IF(OR(B20="",C20=""),"",IF(B20<=C20,"OK","REVIEW")),"") -> OK
A21: Net income / Sales | B21: =IFERROR(IF('3-Year P&L'!$B$56="","",'3-Year P&L'!$B$56),"") -> 0.059513989 | C21: =IFERROR(IF('3-Year P&L'!$E$56="","",'3-Year P&L'!$E$56),"") -> 0.05 | D21: =IFERROR(IF(OR(B21="",C21=""),"",IF(B21>=C21,"OK","REVIEW")),"") -> OK
A22: Gross margin / Sales | B22: =IFERROR(IF('3-Year P&L'!$B$51="","",'3-Year P&L'!$B$51),"") -> 0.627 | C22: =IFERROR(IF('3-Year P&L'!$E$51="","",'3-Year P&L'!$E$51),"") -> 0.6 | D22: =IFERROR(IF(OR(B22="",C22=""),"",IF(B22>=C22,"OK","REVIEW")),"") -> OK
A24: THIS PLAN'S KEY FIGURES
A25: Total startup costs (sum of the blocks) | B25: =IFERROR(IF('Startup Costs'!$B$31="","",'Startup Costs'!$B$31),"") -> 266709
A26: Total cash needed at launch | B26: =IFERROR(IF('Startup Costs'!$B$34="","",'Startup Costs'!$B$34),"") -> 266709
A27: Working capital funded | B27: =IFERROR(IF('Startup Costs'!$B$30="","",'Startup Costs'!$B$30),"") -> 84209
A28: Forecast year-1 revenue | B28: =IFERROR(IF('3-Year P&L'!$B$9="","",'3-Year P&L'!$B$9),"") -> 651000
A29: Year-1 net income | B29: =IFERROR(IF('3-Year P&L'!$B$48="","",'3-Year P&L'!$B$48),"") -> 38743.607
A30: Transactions per day for the ACCOUNTING break-even (depreciation included) | B30: =IFERROR(IF('Break-Even'!$B$15="","",'Break-Even'!$B$15),"") -> 183.42278
A31: Project payback (years), before debt | B31: =IFERROR(IF('12-Month Cash Flow'!$B$31="","",'12-Month Cash Flow'!$B$31),"") -> 2.6
A33: WHY THIS MODEL IS BUILT THIS WAY
A34: Item | B34: Common shortcut | C34: This workbook | D34: Why
A35: Labor cost in the P&L | B35: A typed-in number, disconnected from the staffing tab | C35: The total of the "Staffing" tab, by formula | D35: When the P&L and the staffing tab disagree, nobody knows which one to trust. Here both say the same thing, and if you change a salary the result changes on its own.
A36: Staffing | B36: A handful of full-time positions sized by guesswork | C36: Positions, including part-time lines, sized to the production shift and the shop hours you declare | D36: Sized to the hours that really have to be covered (the early production shift, the shop's opening hours and a line for vacation and day-off relief) and tested against the labor-cost ceiling in the P&L. No payroll line falls below the minimum wage in proportion to its FTE
A37: Transactions per day | B37: Backed out of a revenue target | C37: Typed in as an input and tested against the pessimistic and optimistic scenarios | D37: Transactions per day is a driver, not a plug. With fewer transactions, net income falls below the floor this workbook sets, because fixed costs do not grow with volume, so each extra transaction goes almost entirely to the bottom line. Compare it with the "Scenarios" tab.
A38: Average check | B38: A single number, without saying whether it includes sales tax | C38: Entered excl. sales tax; the "0. Assumptions" tab calculates the equivalent menu price incl. sales tax | D38: Revenue is booked excl. sales tax, as a business is projected. The example sits in the upper part of the range in the benchmarks table because the check combines bread, pastries and coffee, not just the loaf.
A39: Rent | B39: A monthly figure with no link to sales | C39: A monthly rent on the "0. Assumptions" tab, tested as a percentage of sales | D39: A bakery needs more square footage than a shop alone: production area, storefront and storage add up to the minimum the checklist suggests. The "3-Year P&L" shows rent against its ceiling as a percentage of sales, so you see right away whether the location is viable.
A40: Utilities | B40: A monthly figure typed in without checking what the ovens consume | C40: A monthly figure sized for ovens and refrigeration, on the "0. Assumptions" tab | D40: The electricity consumption of a bakery is not that of a shop: ovens need a heavy electrical load. Ask for the utility history of the space before you sign the lease.
A41: Opening calendar | B41: Two different calendars in the same workbook: a monthly day count on one tab and an annual count on another | C41: A single operating-days input on the "0. Assumptions" tab | D41: The daily break-even, the P&L and the scenarios all use the same number of days, so the daily break-even matches the days you actually plan to open.
A42: Working capital | B42: A round number with a "3 months" label | C42: 3 months of cash fixed costs, by formula | D42: A typed figure can cover far fewer months than its label says. A formula recalculates by itself whenever you change any expense: if you raise the rent or the staff, the cushion rises with them.
A43: Depreciation | B43: One flat period over the WHOLE investment, working capital and opening inventory included | C43: Only on the build-out and the equipment, each with its own useful life | D43: Only fixed assets are depreciated: the cash cushion and the opening inventory are not assets that wear out. Depreciation here is straight-line book depreciation; MACRS and Section 179 are tax treatments handled outside the model, so confirm them with your accountant.
A44: Build-out contingency | B44: A fixed amount with a percentage written inside the label | C44: A formula on the build-out lines, with the percentage on the "0. Assumptions" tab | D44: A percentage hidden in a label stops being true as soon as one line changes. Here the cushion is calculated only on what can really overrun in a renovation (drawings, build-out, electrical service, ventilation and signage), not on equipment bought at a closed price, and the percentage is an input: change it and the amount recalculates on its own instead of being redone by hand every time a quote changes.
A45: Income tax | B45: A flat rate that ignores the losses of the first year | C45: An effective income tax rate (years 1-2 and from year 3), with net operating losses carried forward | D45: Early losses offset later profits, so the model carries them forward. Federal rules cap the offset at 80% of taxable income and the model offsets 100%, a declared simplification. If your business is a pass-through entity, set the rate to 0% and remember that you pay the tax on your personal return.
... A51: Health permit | B51: Assumed a single registration for every bakery, without nuance | C51: Health department permit for the retail shop, with a flag for the wholesale channel | D51: A bakery that sells only to the public is licensed locally. Selling to other businesses can add requirements: a state agriculture department license and, if wholesale becomes your main channel, FDA food facility registration (retail food establishments, whose sales go mostly to consumers, are exempt). If wholesale grows, check with your accountant and your state agency.
A53: INDUSTRY BENCHMARKS
A54: Benchmark | B54: Value | C54: Source | D54: Note
A55: Food cost: artisan bread | B55: 25-30% | C55: Kit estimate | D55: Flour + yeast + water = low unit cost. Bakeries overall run 28-35% according to Toast
A56: Food cost: pastries | B56: 32-38% | C56: Kit estimate | D56: Butter and chocolate raise the cost
A57: Beverage cost: coffee | B57: 20-30% | C57: Kit estimate | D57: Whole-bean coffee, high margin
A58: Labor cost / Sales | B58: 24-40% (artisan bread 34-40%) | C58: Toast (pos.toasttab.com) | D58: Early production shift and a double job (production plus selling): the kit applies the top of this range as the ceiling in the "3-Year P&L"
A59: Rent / Sales | B59: Up to 10% | C59: Kit estimate | D59: A bakery needs more square footage than a shop alone, so rent weighs more than in a coffee shop
A60: Average check: bakery | B60: 7-12 | C60: Kit estimate | D60: Bread + pastries + coffee. The average check excl. sales tax of THIS plan is on the "0. Assumptions" tab
A61: Daily bread production (lb) | B61: 175-440 lb | C61: Kit estimate | D61: Depends on the oven and the equipment installed
A62: Bread waste (unsold) | B62: 5-10% | C62: Kit estimate | D62: Day-old bread loses its value: whatever does not sell is lost, so measure it every week (Phase 6 of the checklist)
A63: Target gross margin | B63: 60% or more | C63: Kit estimate | D63: Artisan bread earns a better margin than industrial bread
A64: Production start time | B64: 4:00-5:00 AM | C64: Kit estimate | D64: The early shift is critical to have bread on the shelf by 7:30 am
A65: EBITDA target (year 2) | B65: 10-20% | C65: Kit estimate | D65: Year 1 can be negative, which is normal for a new bakery. Net margins in the food sector are typically 3-5%, and artisan bakeries can earn more (Toast)
... A67: Applicable state / local minimum wage | B67: 7.25 per hour federal (15,080 per year full-time); state and local rates are often higher | C67: DOL (dol.gov/agencies/whd/minimum-wage) | D67: There is no single national table above the federal floor: look up the rate for your state and city and enter it on the "0. Assumptions" tab
A69: To edit a cell that is not green: Review → Unprotect Sheet (there is no password).
A70: More templates and kits in the catalog at aichef.pro/en/digital-products
A71: Designed by John Guerrero — chef and restaurant consultant since 2010, in the kitchen since age 17 · johnguerrero.es
A72: Version 2.2 · October 2026 · aichef.pro/en/digital-products/bakery-business-plan · info@aichef.pro
A73: Planning tool, not financial, tax or legal advice. Requirements vary by state, county and city — check with your accountant and local authorities.

Sheet 12-Month Cash Flow
A1: CASH FLOW FORECAST — YEAR 1
A2: The P&L tells you whether the business makes money; this tab tells you whether you have cash left to get to the end of the month. It is the first one a lender looks at.
A4: Item | B4: Month 1 | C4: Month 2 | D4: Month 3 | E4: Month 4 | F4: Month 5 | G4: Month 6 | H4: Month 7 | I4: Month 8 | J4: Month 9 | K4: Month 10 | L4: Month 11 | M4: Month 12 | N4: Year
A5: Monthly seasonality (adds up to 100%) | B5: 0.083 | C5: 0.078 | D5: 0.083 | E5: 0.085 | F5: 0.083 | G5: 0.08 | H5: 0.075 | I5: 0.06 | J5: 0.083 | K5: 0.085 | L5: 0.083 | M5: 0.122 | N5: =IFERROR(IF('3-Year P&L'!$B$9="","",SUM(B5:M5)),"") -> 1 | O5: Profile for your area: adjust it to your own slow and busy months (weather, tourism, events). It must add up to 100%
A6: Launch ramp-up (% of steady-state activity) | B6: =IFERROR(IF('3-Year P&L'!$B$9="","",MIN(1,'0. Assumptions'!$B$52+(1-'0. Assumptions'!$B$52)*0/MAX(1,'0. Assumptions'!$B$53-1))),"") -> 0.55 | C6: =IFERROR(IF('3-Year P&L'!$B$9="","",MIN(1,'0. Assumptions'!$B$52+(1-'0. Assumptions'!$B$52)*1/MAX(1,'0. Assumptions'!$B$53-1))),"") -> 0.64 | D6: =IFERROR(IF('3-Year P&L'!$B$9="","",MIN(1,'0. Assumptions'!$B$52+(1-'0. Assumptions'!$B$52)*2/MAX(1,'0. Assumptions'!$B$53-1))),"") -> 0.73 | E6: =IFERROR(IF('3-Year P&L'!$B$9="","",MIN(1,'0. Assumptions'!$B$52+(1-'0. Assumptions'!$B$52)*3/MAX(1,'0. Assumptions'!$B$53-1))),"") -> 0.82 | F6: =IFERROR(IF('3-Year P&L'!$B$9="","",MIN(1,'0. Assumptions'!$B$52+(1-'0. Assumptions'!$B$52)*4/MAX(1,'0. Assumptions'!$B$53-1))),"") -> 0.91 | G6: =IFERROR(IF('3-Year P&L'!$B$9="","",MIN(1,'0. Assumptions'!$B$52+(1-'0. Assumptions'!$B$52)*5/MAX(1,'0. Assumptions'!$B$53-1))),"") -> 1 | H6: =IFERROR(IF('3-Year P&L'!$B$9="","",MIN(1,'0. Assumptions'!$B$52+(1-'0. Assumptions'!$B$52)*6/MAX(1,'0. Assumptions'!$B$53-1))),"") -> 1 | I6: =IFERROR(IF('3-Year P&L'!$B$9="","",MIN(1,'0. Assumptions'!$B$52+(1-'0. Assumptions'!$B$52)*7/MAX(1,'0. Assumptions'!$B$53-1))),"") -> 1 | J6: =IFERROR(IF('3-Year P&L'!$B$9="","",MIN(1,'0. Assumptions'!$B$52+(1-'0. Assumptions'!$B$52)*8/MAX(1,'0. Assumptions'!$B$53-1))),"") -> 1 | K6: =IFERROR(IF('3-Year P&L'!$B$9="","",MIN(1,'0. Assumptions'!$B$52+(1-'0. Assumptions'!$B$52)*9/MAX(1,'0. Assumptions'!$B$53-1))),"") -> 1 | L6: =IFERROR(IF('3-Year P&L'!$B$9="","",MIN(1,'0. Assumptions'!$B$52+(1-'0. Assumptions'!$B$52)*10/MAX(1,'0. Assumptions'!$B$53-1))),"") -> 1 | M6: =IFERROR(IF('3-Year P&L'!$B$9="","",MIN(1,'0. Assumptions'!$B$52+(1-'0. Assumptions'!$B$52)*11/MAX(1,'0. Assumptions'!$B$53-1))),"") -> 1 | O6: Rises in a straight line from the month-1 percentage to 100% over the number of months you set in Assumptions. With month 1 at 100%, the ramp disappears
A7: Split of activity by month (calculated) | B7: =IFERROR(IF('3-Year P&L'!$B$9="","",B5*B6/SUMPRODUCT($B$5:$M$5,$B$6:$M$6)),"") -> 0.051327314 | C7: =IFERROR(IF('3-Year P&L'!$B$9="","",C5*C6/SUMPRODUCT($B$5:$M$5,$B$6:$M$6)),"") -> 0.056128358 | D7: =IFERROR(IF('3-Year P&L'!$B$9="","",D5*D6/SUMPRODUCT($B$5:$M$5,$B$6:$M$6)),"") -> 0.068125344 | E7: =IFERROR(IF('3-Year P&L'!$B$9="","",E5*E6/SUMPRODUCT($B$5:$M$5,$B$6:$M$6)),"") -> 0.07836832 | F7: =IFERROR(IF('3-Year P&L'!$B$9="","",F5*F6/SUMPRODUCT($B$5:$M$5,$B$6:$M$6)),"") -> 0.084923374 | G7: =IFERROR(IF('3-Year P&L'!$B$9="","",G5*G6/SUMPRODUCT($B$5:$M$5,$B$6:$M$6)),"") -> 0.089949291 | H7: =IFERROR(IF('3-Year P&L'!$B$9="","",H5*H6/SUMPRODUCT($B$5:$M$5,$B$6:$M$6)),"") -> 0.08432746 | I7: =IFERROR(IF('3-Year P&L'!$B$9="","",I5*I6/SUMPRODUCT($B$5:$M$5,$B$6:$M$6)),"") -> 0.067461968 | ... M7: =IFERROR(IF('3-Year P&L'!$B$9="","",M5*M6/SUMPRODUCT($B$5:$M$5,$B$6:$M$6)),"") -> 0.13717267 | N7: =IFERROR(IF('3-Year P&L'!$B$9="","",SUM(B7:M7)),"") -> 1 | O7: Seasonality × ramp-up, normalized to 100%: the YEAR brings in what the P&L says, but split the way a business that has just opened would split it
A8: CASH IN
A9: Sales collected (incl. sales tax collected) | B9: =IFERROR(IF('3-Year P&L'!$B$9="","",('3-Year P&L'!$B$9+'3-Year P&L'!$B$9*SUMPRODUCT('3-Year P&L'!$E$10:$E$11,'3-Year P&L'!$G$10:$G$11))*B7*(1-MIN(30,'0. Assumptions'!$B$58)/30)),"") -> 33127.166 | C9: =IFERROR(IF('3-Year P&L'!$B$9="","",('3-Year P&L'!$B$9+'3-Year P&L'!$B$9*SUMPRODUCT('3-Year P&L'!$E$10:$E$11,'3-Year P&L'!$G$10:$G$11))*(C7*(1-MIN(30,'0. Assumptions'!$B$58)/30)+B7*MIN(30,'0. Assumptions'!$B$58)/30)),"") -> 37368.124 | D9: =IFERROR(IF('3-Year P&L'!$B$9="","",('3-Year P&L'!$B$9+'3-Year P&L'!$B$9*SUMPRODUCT('3-Year P&L'!$E$10:$E$11,'3-Year P&L'!$G$10:$G$11))*(D7*(1-MIN(30,'0. Assumptions'!$B$58)/30)+C7*MIN(30,'0. Assumptions'!$B$58)/30)),"") -> 45217.95 | E9: =IFERROR(IF('3-Year P&L'!$B$9="","",('3-Year P&L'!$B$9+'3-Year P&L'!$B$9*SUMPRODUCT('3-Year P&L'!$E$10:$E$11,'3-Year P&L'!$G$10:$G$11))*(E7*(1-MIN(30,'0. Assumptions'!$B$58)/30)+D7*MIN(30,'0. Assumptions'!$B$58)/30)),"") -> 52095.869 | F9: =IFERROR(IF('3-Year P&L'!$B$9="","",('3-Year P&L'!$B$9+'3-Year P&L'!$B$9*SUMPRODUCT('3-Year P&L'!$E$10:$E$11,'3-Year P&L'!$G$10:$G$11))*(F7*(1-MIN(30,'0. Assumptions'!$B$58)/30)+E7*MIN(30,'0. Assumptions'!$B$58)/30)),"") -> 56554.53 | G9: =IFERROR(IF('3-Year P&L'!$B$9="","",('3-Year P&L'!$B$9+'3-Year P&L'!$B$9*SUMPRODUCT('3-Year P&L'!$E$10:$E$11,'3-Year P&L'!$G$10:$G$11))*(G7*(1-MIN(30,'0. Assumptions'!$B$58)/30)+F7*MIN(30,'0. Assumptions'!$B$58)/30)),"") -> 59944.193 | H9: =IFERROR(IF('3-Year P&L'!$B$9="","",('3-Year P&L'!$B$9+'3-Year P&L'!$B$9*SUMPRODUCT('3-Year P&L'!$E$10:$E$11,'3-Year P&L'!$G$10:$G$11))*(H7*(1-MIN(30,'0. Assumptions'!$B$58)/30)+G7*MIN(30,'0. Assumptions'!$B$58)/30)),"") -> 56427.661 | I9: =IFERROR(IF('3-Year P&L'!$B$9="","",('3-Year P&L'!$B$9+'3-Year P&L'!$B$9*SUMPRODUCT('3-Year P&L'!$E$10:$E$11,'3-Year P&L'!$G$10:$G$11))*(I7*(1-MIN(30,'0. Assumptions'!$B$58)/30)+H7*MIN(30,'0. Assumptions'!$B$58)/30)),"") -> 45417.386 | J9: =IFERROR(IF('3-Year P&L'!$B$9="","",('3-Year P&L'!$B$9+'3-Year P&L'!$B$9*SUMPRODUCT('3-Year P&L'!$E$10:$E$11,'3-Year P&L'!$G$10:$G$11))*(J7*(1-MIN(30,'0. Assumptions'!$B$58)/30)+I7*MIN(30,'0. Assumptions'!$B$58)/30)),"") -> 61732.612 | ... M9: =IFERROR(IF('3-Year P&L'!$B$9="","",('3-Year P&L'!$B$9+'3-Year P&L'!$B$9*SUMPRODUCT('3-Year P&L'!$E$10:$E$11,'3-Year P&L'!$G$10:$G$11))*(M7*(1-MIN(30,'0. Assumptions'!$B$58)/30)+L7*MIN(30,'0. Assumptions'!$B$58)/30)),"") -> 90609.562 | N9: =IFERROR(IF('3-Year P&L'!$B$9="","",SUM(B9:M9)),"") -> 664612.75 | O9: The month's sales plus the sales tax collected, adjusted by the average collection days from the Assumptions tab
A10: CASH OUT
A11: Purchases and variable costs (incl. sales tax) | B11: =IFERROR(IF('3-Year P&L'!$B$9="","",-('3-Year P&L'!$B$13*(1+'3-Year P&L'!$G$13)+'3-Year P&L'!$B$14*(1+'3-Year P&L'!$G$14)+'3-Year P&L'!$B$15*(1+'3-Year P&L'!$G$15)+'3-Year P&L'!$B$16*(1+'3-Year P&L'!$G$16)+'3-Year P&L'!$B$17*(1+'3-Year P&L'!$G$17)+'3-Year P&L'!$B$18*(1+'3-Year P&L'!$G$18))*B7*(1-MIN(30,'0. Assumptions'!$B$59)/30)),"") -> -6647.1746 | C11: =IFERROR(IF('3-Year P&L'!$B$9="","",-('3-Year P&L'!$B$13*(1+'3-Year P&L'!$G$13)+'3-Year P&L'!$B$14*(1+'3-Year P&L'!$G$14)+'3-Year P&L'!$B$15*(1+'3-Year P&L'!$G$15)+'3-Year P&L'!$B$16*(1+'3-Year P&L'!$G$16)+'3-Year P&L'!$B$17*(1+'3-Year P&L'!$G$17)+'3-Year P&L'!$B$18*(1+'3-Year P&L'!$G$18))*(C7*(1-MIN(30,'0. Assumptions'!$B$59)/30)+B7*MIN(30,'0. Assumptions'!$B$59)/30)),"") -> -13085.214 | D11: =IFERROR(IF('3-Year P&L'!$B$9="","",-('3-Year P&L'!$B$13*(1+'3-Year P&L'!$G$13)+'3-Year P&L'!$B$14*(1+'3-Year P&L'!$G$14)+'3-Year P&L'!$B$15*(1+'3-Year P&L'!$G$15)+'3-Year P&L'!$B$16*(1+'3-Year P&L'!$G$16)+'3-Year P&L'!$B$17*(1+'3-Year P&L'!$G$17)+'3-Year P&L'!$B$18*(1+'3-Year P&L'!$G$18))*(D7*(1-MIN(30,'0. Assumptions'!$B$59)/30)+C7*MIN(30,'0. Assumptions'!$B$59)/30)),"") -> -15182.933 | E11: =IFERROR(IF('3-Year P&L'!$B$9="","",-('3-Year P&L'!$B$13*(1+'3-Year P&L'!$G$13)+'3-Year P&L'!$B$14*(1+'3-Year P&L'!$G$14)+'3-Year P&L'!$B$15*(1+'3-Year P&L'!$G$15)+'3-Year P&L'!$B$16*(1+'3-Year P&L'!$G$16)+'3-Year P&L'!$B$17*(1+'3-Year P&L'!$G$17)+'3-Year P&L'!$B$18*(1+'3-Year P&L'!$G$18))*(E7*(1-MIN(30,'0. Assumptions'!$B$59)/30)+D7*MIN(30,'0. Assumptions'!$B$59)/30)),"") -> -17868.923 | F11: =IFERROR(IF('3-Year P&L'!$B$9="","",-('3-Year P&L'!$B$13*(1+'3-Year P&L'!$G$13)+'3-Year P&L'!$B$14*(1+'3-Year P&L'!$G$14)+'3-Year P&L'!$B$15*(1+'3-Year P&L'!$G$15)+'3-Year P&L'!$B$16*(1+'3-Year P&L'!$G$16)+'3-Year P&L'!$B$17*(1+'3-Year P&L'!$G$17)+'3-Year P&L'!$B$18*(1+'3-Year P&L'!$G$18))*(F7*(1-MIN(30,'0. Assumptions'!$B$59)/30)+E7*MIN(30,'0. Assumptions'!$B$59)/30)),"") -> -19878.547 | G11: =IFERROR(IF('3-Year P&L'!$B$9="","",-('3-Year P&L'!$B$13*(1+'3-Year P&L'!$G$13)+'3-Year P&L'!$B$14*(1+'3-Year P&L'!$G$14)+'3-Year P&L'!$B$15*(1+'3-Year P&L'!$G$15)+'3-Year P&L'!$B$16*(1+'3-Year P&L'!$G$16)+'3-Year P&L'!$B$17*(1+'3-Year P&L'!$G$17)+'3-Year P&L'!$B$18*(1+'3-Year P&L'!$G$18))*(G7*(1-MIN(30,'0. Assumptions'!$B$59)/30)+F7*MIN(30,'0. Assumptions'!$B$59)/30)),"") -> -21272.233 | H11: =IFERROR(IF('3-Year P&L'!$B$9="","",-('3-Year P&L'!$B$13*(1+'3-Year P&L'!$G$13)+'3-Year P&L'!$B$14*(1+'3-Year P&L'!$G$14)+'3-Year P&L'!$B$15*(1+'3-Year P&L'!$G$15)+'3-Year P&L'!$B$16*(1+'3-Year P&L'!$G$16)+'3-Year P&L'!$B$17*(1+'3-Year P&L'!$G$17)+'3-Year P&L'!$B$18*(1+'3-Year P&L'!$G$18))*(H7*(1-MIN(30,'0. Assumptions'!$B$59)/30)+G7*MIN(30,'0. Assumptions'!$B$59)/30)),"") -> -21113.698 | I11: =IFERROR(IF('3-Year P&L'!$B$9="","",-('3-Year P&L'!$B$13*(1+'3-Year P&L'!$G$13)+'3-Year P&L'!$B$14*(1+'3-Year P&L'!$G$14)+'3-Year P&L'!$B$15*(1+'3-Year P&L'!$G$15)+'3-Year P&L'!$B$16*(1+'3-Year P&L'!$G$16)+'3-Year P&L'!$B$17*(1+'3-Year P&L'!$G$17)+'3-Year P&L'!$B$18*(1+'3-Year P&L'!$G$18))*(I7*(1-MIN(30,'0. Assumptions'!$B$59)/30)+H7*MIN(30,'0. Assumptions'!$B$59)/30)),"") -> -18292.471 | J11: =IFERROR(IF('3-Year P&L'!$B$9="","",-('3-Year P&L'!$B$13*(1+'3-Year P&L'!$G$13)+'3-Year P&L'!$B$14*(1+'3-Year P&L'!$G$14)+'3-Year P&L'!$B$15*(1+'3-Year P&L'!$G$15)+'3-Year P&L'!$B$16*(1+'3-Year P&L'!$G$16)+'3-Year P&L'!$B$17*(1+'3-Year P&L'!$G$17)+'3-Year P&L'!$B$18*(1+'3-Year P&L'!$G$18))*(J7*(1-MIN(30,'0. Assumptions'!$B$59)/30)+I7*MIN(30,'0. Assumptions'!$B$59)/30)),"") -> -19730.387 | ... M11: =IFERROR(IF('3-Year P&L'!$B$9="","",-('3-Year P&L'!$B$13*(1+'3-Year P&L'!$G$13)+'3-Year P&L'!$B$14*(1+'3-Year P&L'!$G$14)+'3-Year P&L'!$B$15*(1+'3-Year P&L'!$G$15)+'3-Year P&L'!$B$16*(1+'3-Year P&L'!$G$16)+'3-Year P&L'!$B$17*(1+'3-Year P&L'!$G$17)+'3-Year P&L'!$B$18*(1+'3-Year P&L'!$G$18))*(M7*(1-MIN(30,'0. Assumptions'!$B$59)/30)+L7*MIN(30,'0. Assumptions'!$B$59)/30)),"") -> -28339.679 | N11: =IFERROR(IF('3-Year P&L'!$B$9="","",SUM(B11:M11)),"") -> -227278.95 | O11: =IFERROR("Food and beverage purchases, consumables, fees and contingencies, each at ITS tax rate (column G of the P&L; 0 in the US, where the sales tax you pay is part of the cost) and with the supplier payment days from ""0. Assumptions""."&IF('0. Assumptions'!$B$59=0,""," With "&TEXT('0. Assumptions'!$B$59,"0")&" payment days, the last purchases of the year are paid next year: the ""Year"" column of this row holds "&TEXT(MAX(0,12-ROUNDUP('0. Assumptions'!$B$59/30,0)),"0")&" months of purchases, not the year's cost."),"") -> Food and beverage purchases, consumables, fees and contingencies, each at ITS tax rate (column G of the P&L; 0 in the US, where the sales tax you pay is part of the cost) and with the supplier payment days from "0. Assumptions". With 14 payment days, the last purchases of the year are paid next year: the "Year" column of this row holds 11 months of purchases, not the year's cost.
A12: Operating fixed costs (incl. sales tax) | B12: =IFERROR(IF('3-Year P&L'!$B$9="","",-('3-Year P&L'!$B$38-'3-Year P&L'!$B$23-'3-Year P&L'!$B$36-'3-Year P&L'!$B$37+'3-Year P&L'!$B$40)/12),"") -> -8025 | C12: =IFERROR(IF('3-Year P&L'!$B$9="","",-('3-Year P&L'!$B$38-'3-Year P&L'!$B$23-'3-Year P&L'!$B$36-'3-Year P&L'!$B$37+'3-Year P&L'!$B$40)/12),"") -> -8025 | D12: =IFERROR(IF('3-Year P&L'!$B$9="","",-('3-Year P&L'!$B$38-'3-Year P&L'!$B$23-'3-Year P&L'!$B$36-'3-Year P&L'!$B$37+'3-Year P&L'!$B$40)/12),"") -> -8025 | E12: =IFERROR(IF('3-Year P&L'!$B$9="","",-('3-Year P&L'!$B$38-'3-Year P&L'!$B$23-'3-Year P&L'!$B$36-'3-Year P&L'!$B$37+'3-Year P&L'!$B$40)/12),"") -> -8025 | F12: =IFERROR(IF('3-Year P&L'!$B$9="","",-('3-Year P&L'!$B$38-'3-Year P&L'!$B$23-'3-Year P&L'!$B$36-'3-Year P&L'!$B$37+'3-Year P&L'!$B$40)/12),"") -> -8025 | G12: =IFERROR(IF('3-Year P&L'!$B$9="","",-('3-Year P&L'!$B$38-'3-Year P&L'!$B$23-'3-Year P&L'!$B$36-'3-Year P&L'!$B$37+'3-Year P&L'!$B$40)/12),"") -> -8025 | H12: =IFERROR(IF('3-Year P&L'!$B$9="","",-('3-Year P&L'!$B$38-'3-Year P&L'!$B$23-'3-Year P&L'!$B$36-'3-Year P&L'!$B$37+'3-Year P&L'!$B$40)/12),"") -> -8025 | I12: =IFERROR(IF('3-Year P&L'!$B$9="","",-('3-Year P&L'!$B$38-'3-Year P&L'!$B$23-'3-Year P&L'!$B$36-'3-Year P&L'!$B$37+'3-Year P&L'!$B$40)/12),"") -> -8025 | ... M12: =IFERROR(IF('3-Year P&L'!$B$9="","",-('3-Year P&L'!$B$38-'3-Year P&L'!$B$23-'3-Year P&L'!$B$36-'3-Year P&L'!$B$37+'3-Year P&L'!$B$40)/12),"") -> -8025 | N12: =IFERROR(IF('3-Year P&L'!$B$9="","",SUM(B12:M12)),"") -> -96300 | O12: The fixed costs that leave cash, each with its own tax rate: insurance carries none
A13: Payroll and employer payroll taxes | B13: =IFERROR(IF('3-Year P&L'!$B$9="","",-'3-Year P&L'!$B$23/MAX(12,'0. Assumptions'!$B$21)*(1+IF(1='0. Assumptions'!$B$60,(MAX(12,'0. Assumptions'!$B$21)-12)/2,0)+IF(1='0. Assumptions'!$B$61,(MAX(12,'0. Assumptions'!$B$21)-12)/2,0))),"") -> -18403 | C13: =IFERROR(IF('3-Year P&L'!$B$9="","",-'3-Year P&L'!$B$23/MAX(12,'0. Assumptions'!$B$21)*(1+IF(2='0. Assumptions'!$B$60,(MAX(12,'0. Assumptions'!$B$21)-12)/2,0)+IF(2='0. Assumptions'!$B$61,(MAX(12,'0. Assumptions'!$B$21)-12)/2,0))),"") -> -18403 | D13: =IFERROR(IF('3-Year P&L'!$B$9="","",-'3-Year P&L'!$B$23/MAX(12,'0. Assumptions'!$B$21)*(1+IF(3='0. Assumptions'!$B$60,(MAX(12,'0. Assumptions'!$B$21)-12)/2,0)+IF(3='0. Assumptions'!$B$61,(MAX(12,'0. Assumptions'!$B$21)-12)/2,0))),"") -> -18403 | E13: =IFERROR(IF('3-Year P&L'!$B$9="","",-'3-Year P&L'!$B$23/MAX(12,'0. Assumptions'!$B$21)*(1+IF(4='0. Assumptions'!$B$60,(MAX(12,'0. Assumptions'!$B$21)-12)/2,0)+IF(4='0. Assumptions'!$B$61,(MAX(12,'0. Assumptions'!$B$21)-12)/2,0))),"") -> -18403 | F13: =IFERROR(IF('3-Year P&L'!$B$9="","",-'3-Year P&L'!$B$23/MAX(12,'0. Assumptions'!$B$21)*(1+IF(5='0. Assumptions'!$B$60,(MAX(12,'0. Assumptions'!$B$21)-12)/2,0)+IF(5='0. Assumptions'!$B$61,(MAX(12,'0. Assumptions'!$B$21)-12)/2,0))),"") -> -18403 | G13: =IFERROR(IF('3-Year P&L'!$B$9="","",-'3-Year P&L'!$B$23/MAX(12,'0. Assumptions'!$B$21)*(1+IF(6='0. Assumptions'!$B$60,(MAX(12,'0. Assumptions'!$B$21)-12)/2,0)+IF(6='0. Assumptions'!$B$61,(MAX(12,'0. Assumptions'!$B$21)-12)/2,0))),"") -> -18403 | H13: =IFERROR(IF('3-Year P&L'!$B$9="","",-'3-Year P&L'!$B$23/MAX(12,'0. Assumptions'!$B$21)*(1+IF(7='0. Assumptions'!$B$60,(MAX(12,'0. Assumptions'!$B$21)-12)/2,0)+IF(7='0. Assumptions'!$B$61,(MAX(12,'0. Assumptions'!$B$21)-12)/2,0))),"") -> -18403 | I13: =IFERROR(IF('3-Year P&L'!$B$9="","",-'3-Year P&L'!$B$23/MAX(12,'0. Assumptions'!$B$21)*(1+IF(8='0. Assumptions'!$B$60,(MAX(12,'0. Assumptions'!$B$21)-12)/2,0)+IF(8='0. Assumptions'!$B$61,(MAX(12,'0. Assumptions'!$B$21)-12)/2,0))),"") -> -18403 | J13: =IFERROR(IF('3-Year P&L'!$B$9="","",-'3-Year P&L'!$B$23/MAX(12,'0. Assumptions'!$B$21)*(1+IF(9='0. Assumptions'!$B$60,(MAX(12,'0. Assumptions'!$B$21)-12)/2,0)+IF(9='0. Assumptions'!$B$61,(MAX(12,'0. Assumptions'!$B$21)-12)/2,0))),"") -> -18403 | K13: =IFERROR(IF('3-Year P&L'!$B$9="","",-'3-Year P&L'!$B$23/MAX(12,'0. Assumptions'!$B$21)*(1+IF(10='0. Assumptions'!$B$60,(MAX(12,'0. Assumptions'!$B$21)-12)/2,0)+IF(10='0. Assumptions'!$B$61,(MAX(12,'0. Assumptions'!$B$21)-12)/2,0))),"") -> -18403 | L13: =IFERROR(IF('3-Year P&L'!$B$9="","",-'3-Year P&L'!$B$23/MAX(12,'0. Assumptions'!$B$21)*(1+IF(11='0. Assumptions'!$B$60,(MAX(12,'0. Assumptions'!$B$21)-12)/2,0)+IF(11='0. Assumptions'!$B$61,(MAX(12,'0. Assumptions'!$B$21)-12)/2,0))),"") -> -18403 | M13: =IFERROR(IF('3-Year P&L'!$B$9="","",-'3-Year P&L'!$B$23/MAX(12,'0. Assumptions'!$B$21)*(1+IF(12='0. Assumptions'!$B$60,(MAX(12,'0. Assumptions'!$B$21)-12)/2,0)+IF(12='0. Assumptions'!$B$61,(MAX(12,'0. Assumptions'!$B$21)-12)/2,0))),"") -> -18403 | N13: =IFERROR(IF('3-Year P&L'!$B$9="","",SUM(B13:M13)),"") -> -220836 | O13: Twelve monthly installments plus extra pay periods in the months you set in Assumptions (only if pay periods > 12). The total for the year is the same as the P&L's
A14: Loan interest | B14: =IFERROR(IF('3-Year P&L'!$B$9="","",-Financing!$B$44/12),"") -> -1641.6667 | C14: =IFERROR(IF('3-Year P&L'!$B$9="","",-Financing!$B$44/12),"") -> -1641.6667 | D14: =IFERROR(IF('3-Year P&L'!$B$9="","",-Financing!$B$44/12),"") -> -1641.6667 | E14: =IFERROR(IF('3-Year P&L'!$B$9="","",-Financing!$B$44/12),"") -> -1641.6667 | F14: =IFERROR(IF('3-Year P&L'!$B$9="","",-Financing!$B$44/12),"") -> -1641.6667 | G14: =IFERROR(IF('3-Year P&L'!$B$9="","",-Financing!$B$44/12),"") -> -1641.6667 | H14: =IFERROR(IF('3-Year P&L'!$B$9="","",-Financing!$B$44/12),"") -> -1641.6667 | I14: =IFERROR(IF('3-Year P&L'!$B$9="","",-Financing!$B$44/12),"") -> -1641.6667 | ... M14: =IFERROR(IF('3-Year P&L'!$B$9="","",-Financing!$B$44/12),"") -> -1641.6667 | N14: =IFERROR(IF('3-Year P&L'!$B$9="","",SUM(B14:M14)),"") -> -19700
A15: Loan principal repaid | B15: =IFERROR(IF('3-Year P&L'!$B$9="","",-Financing!$B$45/12),"") -> -1030.0702 | C15: =IFERROR(IF('3-Year P&L'!$B$9="","",-Financing!$B$45/12),"") -> -1030.0702 | D15: =IFERROR(IF('3-Year P&L'!$B$9="","",-Financing!$B$45/12),"") -> -1030.0702 | E15: =IFERROR(IF('3-Year P&L'!$B$9="","",-Financing!$B$45/12),"") -> -1030.0702 | F15: =IFERROR(IF('3-Year P&L'!$B$9="","",-Financing!$B$45/12),"") -> -1030.0702 | G15: =IFERROR(IF('3-Year P&L'!$B$9="","",-Financing!$B$45/12),"") -> -1030.0702 | H15: =IFERROR(IF('3-Year P&L'!$B$9="","",-Financing!$B$45/12),"") -> -1030.0702 | I15: =IFERROR(IF('3-Year P&L'!$B$9="","",-Financing!$B$45/12),"") -> -1030.0702 | ... M15: =IFERROR(IF('3-Year P&L'!$B$9="","",-Financing!$B$45/12),"") -> -1030.0702 | N15: =IFERROR(IF('3-Year P&L'!$B$9="","",SUM(B15:M15)),"") -> -12360.843
A16: Sales tax collected (memo) | B16: =IFERROR(IF('3-Year P&L'!$B$9="","",'3-Year P&L'!$B$9*B7*SUMPRODUCT('3-Year P&L'!$E$10:$E$11,'3-Year P&L'!$G$10:$G$11)),"") -> 855.40049 | C16: =IFERROR(IF('3-Year P&L'!$B$9="","",'3-Year P&L'!$B$9*C7*SUMPRODUCT('3-Year P&L'!$E$10:$E$11,'3-Year P&L'!$G$10:$G$11)),"") -> 935.41276 | D16: =IFERROR(IF('3-Year P&L'!$B$9="","",'3-Year P&L'!$B$9*D7*SUMPRODUCT('3-Year P&L'!$E$10:$E$11,'3-Year P&L'!$G$10:$G$11)),"") -> 1135.3497 | E16: =IFERROR(IF('3-Year P&L'!$B$9="","",'3-Year P&L'!$B$9*E7*SUMPRODUCT('3-Year P&L'!$E$10:$E$11,'3-Year P&L'!$G$10:$G$11)),"") -> 1306.0551 | F16: =IFERROR(IF('3-Year P&L'!$B$9="","",'3-Year P&L'!$B$9*F7*SUMPRODUCT('3-Year P&L'!$E$10:$E$11,'3-Year P&L'!$G$10:$G$11)),"") -> 1415.299 | G16: =IFERROR(IF('3-Year P&L'!$B$9="","",'3-Year P&L'!$B$9*G7*SUMPRODUCT('3-Year P&L'!$E$10:$E$11,'3-Year P&L'!$G$10:$G$11)),"") -> 1499.0589 | H16: =IFERROR(IF('3-Year P&L'!$B$9="","",'3-Year P&L'!$B$9*H7*SUMPRODUCT('3-Year P&L'!$E$10:$E$11,'3-Year P&L'!$G$10:$G$11)),"") -> 1405.3677 | I16: =IFERROR(IF('3-Year P&L'!$B$9="","",'3-Year P&L'!$B$9*I7*SUMPRODUCT('3-Year P&L'!$E$10:$E$11,'3-Year P&L'!$G$10:$G$11)),"") -> 1124.2942 | ... M16: =IFERROR(IF('3-Year P&L'!$B$9="","",'3-Year P&L'!$B$9*M7*SUMPRODUCT('3-Year P&L'!$E$10:$E$11,'3-Year P&L'!$G$10:$G$11)),"") -> 2286.0648 | N16: =IFERROR(IF('3-Year P&L'!$B$9="","",SUM(B16:M16)),"") -> 16665.6 | O16: Each sales line under ITS OWN tax treatment, read from the sales tax column of the P&L: the tax-exempt share of the bakery line (goods to go and wholesale for resale) carries no sales tax and the rest takes the sales tax rate; alcohol to go would use its own rate cell on the "0. Assumptions" tab
A17: Recoverable input tax (memo) | B17: =IFERROR(IF('3-Year P&L'!$B$9="","",'3-Year P&L'!$B$39*B7+'3-Year P&L'!$B$40/12),"") -> 0 | C17: =IFERROR(IF('3-Year P&L'!$B$9="","",'3-Year P&L'!$B$39*C7+'3-Year P&L'!$B$40/12),"") -> 0 | D17: =IFERROR(IF('3-Year P&L'!$B$9="","",'3-Year P&L'!$B$39*D7+'3-Year P&L'!$B$40/12),"") -> 0 | E17: =IFERROR(IF('3-Year P&L'!$B$9="","",'3-Year P&L'!$B$39*E7+'3-Year P&L'!$B$40/12),"") -> 0 | F17: =IFERROR(IF('3-Year P&L'!$B$9="","",'3-Year P&L'!$B$39*F7+'3-Year P&L'!$B$40/12),"") -> 0 | G17: =IFERROR(IF('3-Year P&L'!$B$9="","",'3-Year P&L'!$B$39*G7+'3-Year P&L'!$B$40/12),"") -> 0 | H17: =IFERROR(IF('3-Year P&L'!$B$9="","",'3-Year P&L'!$B$39*H7+'3-Year P&L'!$B$40/12),"") -> 0 | I17: =IFERROR(IF('3-Year P&L'!$B$9="","",'3-Year P&L'!$B$39*I7+'3-Year P&L'!$B$40/12),"") -> 0 | ... M17: =IFERROR(IF('3-Year P&L'!$B$9="","",'3-Year P&L'!$B$39*M7+'3-Year P&L'!$B$40/12),"") -> 0 | N17: =IFERROR(IF('3-Year P&L'!$B$9="","",SUM(B17:M17)),"") -> 0 | O17: Each item at its own rate, read from the tax column of the P&L: insurance and card processing fees carry none
A18: Carried forward (capex input tax included) | E18: =IFERROR(IF('3-Year P&L'!$B$9="","",'Startup Costs'!$B$33),"") -> 0 | H18: =IFERROR(IF('3-Year P&L'!$B$9="","",MAX(0,-E19)),"") -> 0 | K18: =IFERROR(IF('3-Year P&L'!$B$9="","",MAX(0,-H19)),"") -> 0 | O18: Sales tax paid on STARTUP COSTS enters here: it is offset against the tax collected in later quarters until used up. With 0% recoverable input tax (the US default) this line stays at zero
A19: Quarterly sales tax return | E19: =IFERROR(IF('3-Year P&L'!$B$9="","",SUM(B16:D16)-SUM(B17:D17)-E18),"") -> 2926.163 | H19: =IFERROR(IF('3-Year P&L'!$B$9="","",SUM(E16:G16)-SUM(E17:G17)-H18),"") -> 4220.413 | K19: =IFERROR(IF('3-Year P&L'!$B$9="","",SUM(H16:J16)-SUM(H17:J17)-K18),"") -> 4084.9355 | O19: Sales tax collected minus recoverable input tax for the quarter, minus what was carried forward. If negative, nothing is paid: it is offset in the next quarter. With 0% recoverable input tax (the US default) it equals the sales tax collected in the quarter
A20: Sales tax remitted (quarterly filer) | E20: =IFERROR(IF('3-Year P&L'!$B$9="","",IF(E19<=0,"",-E19)),"") -> -2926.163 | H20: =IFERROR(IF('3-Year P&L'!$B$9="","",IF(H19<=0,"",-H19)),"") -> -4220.413 | K20: =IFERROR(IF('3-Year P&L'!$B$9="","",IF(K19<=0,"",-K19)),"") -> -4084.9355 | N20: =IFERROR(IF('3-Year P&L'!$B$9="","",SUM(B20:M20)),"") -> -11231.511 | O20: Cash only leaves when the quarter's result is positive. Months without a settlement are left blank, not zero. The cell turns RED when the payment takes more cash than is left that month. The model settles quarterly, in the month after each plan quarter (Months 4, 7 and 10, and the fourth quarter in Month 13: April, July, October and January when Month 1 is January): if your state requires monthly filing, expect smaller payments every month instead
A21: MONTHLY NET CASH FLOW | B21: =IFERROR(IF('3-Year P&L'!$B$9="","",SUM(B9:B15)+IF(B20="",0,B20)),"") -> -2619.7455 | C21: =IFERROR(IF('3-Year P&L'!$B$9="","",SUM(C9:C15)+IF(C20="",0,C20)),"") -> -4816.8275 | D21: =IFERROR(IF('3-Year P&L'!$B$9="","",SUM(D9:D15)+IF(D20="",0,D20)),"") -> 935.27968 | E21: =IFERROR(IF('3-Year P&L'!$B$9="","",SUM(E9:E15)+IF(E20="",0,E20)),"") -> 2201.0455 | F21: =IFERROR(IF('3-Year P&L'!$B$9="","",SUM(F9:F15)+IF(F20="",0,F20)),"") -> 7576.2459 | G21: =IFERROR(IF('3-Year P&L'!$B$9="","",SUM(G9:G15)+IF(G20="",0,G20)),"") -> 9572.2232 | H21: =IFERROR(IF('3-Year P&L'!$B$9="","",SUM(H9:H15)+IF(H20="",0,H20)),"") -> 1993.8132 | I21: =IFERROR(IF('3-Year P&L'!$B$9="","",SUM(I9:I15)+IF(I20="",0,I20)),"") -> -1974.8223 | ... M21: =IFERROR(IF('3-Year P&L'!$B$9="","",SUM(M9:M15)+IF(M20="",0,M20)),"") -> 33170.145 | N21: =IFERROR(IF('3-Year P&L'!$B$9="","",SUM(B21:M21)),"") -> 76905.447
A22: CUMULATIVE CASH BALANCE | B22: =IFERROR(IF('3-Year P&L'!$B$9="","",'Startup Costs'!$B$30+B21),"") -> 81589.254 | C22: =IFERROR(IF('3-Year P&L'!$B$9="","",B22+C21),"") -> 76772.427 | D22: =IFERROR(IF('3-Year P&L'!$B$9="","",C22+D21),"") -> 77707.707 | E22: =IFERROR(IF('3-Year P&L'!$B$9="","",D22+E21),"") -> 79908.752 | F22: =IFERROR(IF('3-Year P&L'!$B$9="","",E22+F21),"") -> 87484.998 | G22: =IFERROR(IF('3-Year P&L'!$B$9="","",F22+G21),"") -> 97057.221 | H22: =IFERROR(IF('3-Year P&L'!$B$9="","",G22+H21),"") -> 99051.034 | I22: =IFERROR(IF('3-Year P&L'!$B$9="","",H22+I21),"") -> 97076.212 | J22: =IFERROR(IF('3-Year P&L'!$B$9="","",I22+J21),"") -> 109978.7 | ... M22: =IFERROR(IF('3-Year P&L'!$B$9="","",L22+M21),"") -> 161114.45
A23: Minimum balance of the year | B23: =IFERROR(IF('3-Year P&L'!$B$9="","",IF(COUNT(B22:M22)=0,"",MIN(B22:M22))),"") -> 76772.427 | D23: If negative, raise working capital or the loan: you run out of cash
A24: Month when cash bottoms out | B24: =IFERROR(IF('3-Year P&L'!$B$9="","",IF(COUNT(B22:M22)=0,"",MATCH(MIN(B22:M22),B22:M22,0))),"") -> 2 | D24: It answers the question that decides a bank deal: in which month the cash runs out
A25: RETURN ON INVESTMENT
A26: Free cash flow before debt, year 1 | B26: =IFERROR(IF('3-Year P&L'!$B$9="","",'3-Year P&L'!$B$48+'3-Year P&L'!$B$36+Financing!$B$44),"") -> 78126.464 | D26: Net income plus depreciation (which is not paid) plus that year's interest: principal is not subtracted because this flow is BEFORE debt. The SAME basis as years 2 and 3, so the payback compares like with like
A27: Free cash flow before debt, year 2 | B27: =IFERROR(IF('3-Year P&L'!$B$9="","",'3-Year P&L'!$C$48+'3-Year P&L'!$C$36+Financing!$B$46),"") -> 110053.37 | D27: Net income plus depreciation (which is not paid) plus that year's interest: principal is not subtracted because this flow is BEFORE debt. Without a monthly table, it is an estimate
A28: Free cash flow before debt, year 3 | B28: =IFERROR(IF('3-Year P&L'!$B$9="","",'3-Year P&L'!$D$48+'3-Year P&L'!$D$36+Financing!$B$48),"") -> 129214.26 | D28: Net income plus depreciation (which is not paid) plus that year's interest: principal is not subtracted because this flow is BEFORE debt. Without a monthly table, it is an estimate
A29: For reference: ACTUAL year-1 cash flow (monthly table, before debt) | B29: =IFERROR(IF('3-Year P&L'!$B$9="","",N21+Financing!$B$44+Financing!$B$45),"") -> 108966.29 | D29: The sum of the twelve monthly net cash flows above, adding back the interest and principal paid that year. It is NOT the one the payback uses: it includes sales tax not yet settled and supplier credit, two things that have to be paid back and that years 2 and 3 do not have
A30: Investment to recover (net of recoverable input tax) | B30: =IFERROR(IF('3-Year P&L'!$B$9="","",'Startup Costs'!$B$34-'Startup Costs'!$B$33),"") -> 266709 | D30: CAPEX plus working capital: the total cash needed MINUS the recoverable input tax on startup costs, which is not lost (it is recovered through the quarterly return, and this tab offsets it quarter by quarter; it is zero in the US default). Working capital is recovered when you close, but until then it is tied up
A31: Project payback (years), before debt | B31: =IFERROR(IF('3-Year P&L'!$B$9="","",IF(B26>=B30,ROUND(B30/B26,1),IF(B26+B27>=B30,ROUND(1+(B30-B26)/B27,1),IF(B26+B27+B28>=B30,ROUND(2+(B30-B26-B27)/B28,1),"Over 3 years")))),"") -> 2.6 | D31: Measures how long the business takes to repay the investment with what it generates BEFORE paying the lender, on the SAME cash flow basis in all three years. Whether you can afford the loan payment is shown by the DSCR in the Financing tab
A32: Payback on CAPEX, excluding working capital (years) | B32: =IFERROR(IF('3-Year P&L'!$B$9="","",IF(B26>='Startup Costs'!$B$32,ROUND('Startup Costs'!$B$32/B26,1),IF(B26+B27>='Startup Costs'!$B$32,ROUND(1+('Startup Costs'!$B$32-B26)/B27,1),IF(B26+B27+B28>='Startup Costs'!$B$32,ROUND(2+('Startup Costs'!$B$32-B26-B27)/B28,1),"Over 3 years")))),"") -> 1.9 | D32: The same calculation on what you BUY (build-out, equipment, launch and formation costs), without working capital: that money is not spent, it is tied up and comes back when the business closes. For reference only: the payback that matters is the one above
A34: Fourth-quarter sales tax is settled in Month 13 (January of the following year when Month 1 is January), so it does not appear in this table. The model pays year-1 income tax in July of year 2 (a simplification: estimated tax payments are usually quarterly). The loan payment is spread in twelve equal parts following the ANNUAL schedule in the Financing tab, and payroll in twelve monthly installments (plus extra pay periods in their month, only if pay periods > 12).

Sheet Financing
A1: FINANCING PLAN
A2: What you need, where it comes from and what it costs to repay. It is the sheet your lender asks for along with the P&L.
A4: Item | B4: Amount | C4: Notes
A5: SOURCES OF FUNDS
A6: Owner's equity (your own money) | B6: =IFERROR(IF('0. Assumptions'!$B$30="","",'0. Assumptions'!$B$30),"") -> 70000
A7: Loan requested — bank or SBA 7(a) (amortized below) | B7: =IFERROR(IF('0. Assumptions'!$B$31="","",'0. Assumptions'!$B$31),"") -> 197000
A8: Other loan (not in the schedule or the DSCR — enter your loan in row 7) | B8: 0 | C8: A source of funds only: NOT amortized, so it is not in the schedule, the P&L interest or the DSCR. Enter your bank or SBA 7(a) loan in row 7 ("Loan requested" in "0. Assumptions"); use this row only for a second loan
A9: SBA Microloan (not in the schedule or the DSCR — enter your loan in row 7) | B9: 0 | C9: SBA Microloans go up to 50,000 through nonprofit intermediaries. Like row 8, a source of funds only: not in the schedule or the DSCR. If it is your only loan, enter it in row 7 instead
A10: Investors / partners (equity: dilutes, not repaid) | B10: 0 | C10: Equity: it dilutes your ownership and is not repaid
A11: Local grants (usually paid after you spend) | B11: 0 | C11: Usually paid AFTER you document the spending
A12: TOTAL SOURCES OF FUNDS | B12: =IFERROR(IF(COUNT(B6:B11)=0,"",SUM(B6:B11)),"") -> 267000
A13: USES OF FUNDS
A14: Total cash needed at launch | B14: =IFERROR(IF('Startup Costs'!$B$34="","",'Startup Costs'!$B$34),"") -> 266709 | C14: Startup costs plus any recoverable tax you have to advance (zero by default in the US)
A15: Difference (sources - uses) | B15: =IFERROR(B12-B14,"") -> 291 | C15: In red (negative), the plan is NOT funded. Far above zero is not free either: you pay interest on money you do not use
A16: Difference as a % of uses | B16: =IFERROR(B15/B14,"") -> 0.0010910768 | C16: Amber above the margin you set: it is debt you pay for without needing it
A17: Acceptable over-funding (%) | B17: 0.05 | C17: A small cushion over the need is healthy; 20% extra is interest thrown away
A18: Loan that would match sources to needs | B18: =IFERROR(MAX(0,B14-B12+B7),"") -> 196709 | C18: Copy it into "Loan requested" in the "0. Assumptions" tab and the difference goes to zero. Rows 8-11 lower this figure, but only the row-7 loan is amortized and counted in the DSCR
A19: LOAN TERMS
A20: Principal amount | B20: =IFERROR(IF('0. Assumptions'!$B$31=0,"",'0. Assumptions'!$B$31),"") -> 197000
A21: Nominal annual interest rate (not APR) | B21: =IFERROR(IF('0. Assumptions'!$B$32="","",'0. Assumptions'!$B$32),"") -> 0.1
A22: Total term (years) | B22: =IFERROR(IF('0. Assumptions'!$B$33="","",'0. Assumptions'!$B$33),"") -> 10
A23: Interest-only period applied (years) | B23: =IFERROR(IF(OR('0. Assumptions'!$B$34="",'0. Assumptions'!$B$33=""),"",IF('0. Assumptions'!$B$34>='0. Assumptions'!$B$33,0,'0. Assumptions'!$B$34)),"") -> 0 | C23: An interest-only period equal to or longer than the term does not exist: the sheet cancels it at the source
A24: Annual payment during repayment | B24: =IFERROR(IF(B22-B23<=0,"",IF(B21=0,B20/(B22-B23),B20*B21/(1-(1+B21)^-(B22-B23)))),"") -> 32060.843 | C24: Standard amortizing loan with a level annual payment. At a 0% rate it is the principal divided by the repayment years: without that branch the schedule would shut down entirely
A25: AMORTIZATION SCHEDULE
A26: Year | B26: Opening balance | C26: Interest | D26: Principal repaid | E26: Total payment | F26: Closing balance | G26: Cash flow available for debt service (after tax; from year 4 on, year 3 held flat) | H26: DSCR for the year
A27: 1 | B27: =IFERROR(IF(B20="","",B20),"") -> 197000 | C27: =IFERROR(IF(OR(1>B22,B27=""),"",B27*B21),"") -> 19700 | D27: =IFERROR(IF(OR(1>B22,B27=""),"",IF(1<=B23,0,MIN(B27,B24-C27))),"") -> 12360.843 | E27: =IFERROR(IF(C27="","",C27+D27),"") -> 32060.843 | F27: =IFERROR(IF(D27="","",B27-D27),"") -> 184639.16 | G27: =IFERROR(IF(E27="","",'3-Year P&L'!$B$41-'3-Year P&L'!$B$46+'3-Year P&L'!$B$36+'3-Year P&L'!$B$37),"") -> 78126.464 | H27: =IFERROR(IF(OR(E27="",E27=0),"",G27/E27),"") -> 2.4368188
A28: 2 | B28: =IFERROR(IF(OR(2>B22,F27=""),"",F27),"") -> 184639.16 | C28: =IFERROR(IF(OR(2>B22,B28=""),"",B28*B21),"") -> 18463.916 | D28: =IFERROR(IF(OR(2>B22,B28=""),"",IF(2<=B23,0,MIN(B28,B24-C28))),"") -> 13596.927 | E28: =IFERROR(IF(C28="","",C28+D28),"") -> 32060.843 | F28: =IFERROR(IF(D28="","",B28-D28),"") -> 171042.23 | G28: =IFERROR(IF(E28="","",'3-Year P&L'!$C$41-'3-Year P&L'!$C$46+'3-Year P&L'!$C$36+'3-Year P&L'!$C$37),"") -> 110053.37 | H28: =IFERROR(IF(OR(E28="",E28=0),"",G28/E28),"") -> 3.4326413
A29: 3 | B29: =IFERROR(IF(OR(3>B22,F28=""),"",F28),"") -> 171042.23 | C29: =IFERROR(IF(OR(3>B22,B29=""),"",B29*B21),"") -> 17104.223 | D29: =IFERROR(IF(OR(3>B22,B29=""),"",IF(3<=B23,0,MIN(B29,B24-C29))),"") -> 14956.62 | E29: =IFERROR(IF(C29="","",C29+D29),"") -> 32060.843 | F29: =IFERROR(IF(D29="","",B29-D29),"") -> 156085.61 | G29: =IFERROR(IF(E29="","",'3-Year P&L'!$D$41-'3-Year P&L'!$D$46+'3-Year P&L'!$D$36+'3-Year P&L'!$D$37),"") -> 129214.26 | H29: =IFERROR(IF(OR(E29="",E29=0),"",G29/E29),"") -> 4.0302826
A30: 4 | B30: =IFERROR(IF(OR(4>B22,F29=""),"",F29),"") -> 156085.61 | C30: =IFERROR(IF(OR(4>B22,B30=""),"",B30*B21),"") -> 15608.561 | D30: =IFERROR(IF(OR(4>B22,B30=""),"",IF(4<=B23,0,MIN(B30,B24-C30))),"") -> 16452.282 | E30: =IFERROR(IF(C30="","",C30+D30),"") -> 32060.843 | F30: =IFERROR(IF(D30="","",B30-D30),"") -> 139633.33 | G30: =IFERROR(IF(E30="","",'3-Year P&L'!$D$41-'3-Year P&L'!$D$46+'3-Year P&L'!$D$36+'3-Year P&L'!$D$37),"") -> 129214.26 | H30: =IFERROR(IF(OR(E30="",E30=0),"",G30/E30),"") -> 4.0302826
A31: 5 | B31: =IFERROR(IF(OR(5>B22,F30=""),"",F30),"") -> 139633.33 | C31: =IFERROR(IF(OR(5>B22,B31=""),"",B31*B21),"") -> 13963.333 | D31: =IFERROR(IF(OR(5>B22,B31=""),"",IF(5<=B23,0,MIN(B31,B24-C31))),"") -> 18097.51 | E31: =IFERROR(IF(C31="","",C31+D31),"") -> 32060.843 | F31: =IFERROR(IF(D31="","",B31-D31),"") -> 121535.82 | G31: =IFERROR(IF(E31="","",'3-Year P&L'!$D$41-'3-Year P&L'!$D$46+'3-Year P&L'!$D$36+'3-Year P&L'!$D$37),"") -> 129214.26 | H31: =IFERROR(IF(OR(E31="",E31=0),"",G31/E31),"") -> 4.0302826
A32: 6 | B32: =IFERROR(IF(OR(6>B22,F31=""),"",F31),"") -> 121535.82 | C32: =IFERROR(IF(OR(6>B22,B32=""),"",B32*B21),"") -> 12153.582 | D32: =IFERROR(IF(OR(6>B22,B32=""),"",IF(6<=B23,0,MIN(B32,B24-C32))),"") -> 19907.261 | E32: =IFERROR(IF(C32="","",C32+D32),"") -> 32060.843 | F32: =IFERROR(IF(D32="","",B32-D32),"") -> 101628.56 | G32: =IFERROR(IF(E32="","",'3-Year P&L'!$D$41-'3-Year P&L'!$D$46+'3-Year P&L'!$D$36+'3-Year P&L'!$D$37),"") -> 129214.26 | H32: =IFERROR(IF(OR(E32="",E32=0),"",G32/E32),"") -> 4.0302826
A33: 7 | B33: =IFERROR(IF(OR(7>B22,F32=""),"",F32),"") -> 101628.56 | C33: =IFERROR(IF(OR(7>B22,B33=""),"",B33*B21),"") -> 10162.856 | D33: =IFERROR(IF(OR(7>B22,B33=""),"",IF(7<=B23,0,MIN(B33,B24-C33))),"") -> 21897.987 | E33: =IFERROR(IF(C33="","",C33+D33),"") -> 32060.843 | F33: =IFERROR(IF(D33="","",B33-D33),"") -> 79730.571 | G33: =IFERROR(IF(E33="","",'3-Year P&L'!$D$41-'3-Year P&L'!$D$46+'3-Year P&L'!$D$36+'3-Year P&L'!$D$37),"") -> 129214.26 | H33: =IFERROR(IF(OR(E33="",E33=0),"",G33/E33),"") -> 4.0302826
A34: 8 | B34: =IFERROR(IF(OR(8>B22,F33=""),"",F33),"") -> 79730.571 | C34: =IFERROR(IF(OR(8>B22,B34=""),"",B34*B21),"") -> 7973.0571 | D34: =IFERROR(IF(OR(8>B22,B34=""),"",IF(8<=B23,0,MIN(B34,B24-C34))),"") -> 24087.786 | E34: =IFERROR(IF(C34="","",C34+D34),"") -> 32060.843 | F34: =IFERROR(IF(D34="","",B34-D34),"") -> 55642.785 | G34: =IFERROR(IF(E34="","",'3-Year P&L'!$D$41-'3-Year P&L'!$D$46+'3-Year P&L'!$D$36+'3-Year P&L'!$D$37),"") -> 129214.26 | H34: =IFERROR(IF(OR(E34="",E34=0),"",G34/E34),"") -> 4.0302826
A35: 9 | B35: =IFERROR(IF(OR(9>B22,F34=""),"",F34),"") -> 55642.785 | C35: =IFERROR(IF(OR(9>B22,B35=""),"",B35*B21),"") -> 5564.2785 | D35: =IFERROR(IF(OR(9>B22,B35=""),"",IF(9<=B23,0,MIN(B35,B24-C35))),"") -> 26496.564 | E35: =IFERROR(IF(C35="","",C35+D35),"") -> 32060.843 | F35: =IFERROR(IF(D35="","",B35-D35),"") -> 29146.221 | G35: =IFERROR(IF(E35="","",'3-Year P&L'!$D$41-'3-Year P&L'!$D$46+'3-Year P&L'!$D$36+'3-Year P&L'!$D$37),"") -> 129214.26 | H35: =IFERROR(IF(OR(E35="",E35=0),"",G35/E35),"") -> 4.0302826
A36: 10 | B36: =IFERROR(IF(OR(10>B22,F35=""),"",F35),"") -> 29146.221 | C36: =IFERROR(IF(OR(10>B22,B36=""),"",B36*B21),"") -> 2914.6221 | D36: =IFERROR(IF(OR(10>B22,B36=""),"",IF(10<=B23,0,MIN(B36,B24-C36))),"") -> 29146.221 | E36: =IFERROR(IF(C36="","",C36+D36),"") -> 32060.843 | F36: =IFERROR(IF(D36="","",B36-D36),"") -> 2.4374458e-10 | G36: =IFERROR(IF(E36="","",'3-Year P&L'!$D$41-'3-Year P&L'!$D$46+'3-Year P&L'!$D$36+'3-Year P&L'!$D$37),"") -> 129214.26 | H36: =IFERROR(IF(OR(E36="",E36=0),"",G36/E36),"") -> 4.0302826
A37: 11 | B37: =IFERROR(IF(OR(11>B22,F36=""),"",F36),"") | C37: =IFERROR(IF(OR(11>B22,B37=""),"",B37*B21),"") | D37: =IFERROR(IF(OR(11>B22,B37=""),"",IF(11<=B23,0,MIN(B37,B24-C37))),"") | E37: =IFERROR(IF(C37="","",C37+D37),"") | F37: =IFERROR(IF(D37="","",B37-D37),"") | G37: =IFERROR(IF(E37="","",'3-Year P&L'!$D$41-'3-Year P&L'!$D$46+'3-Year P&L'!$D$36+'3-Year P&L'!$D$37),"") | H37: =IFERROR(IF(OR(E37="",E37=0),"",G37/E37),"")
A38: 12 | B38: =IFERROR(IF(OR(12>B22,F37=""),"",F37),"") | C38: =IFERROR(IF(OR(12>B22,B38=""),"",B38*B21),"") | D38: =IFERROR(IF(OR(12>B22,B38=""),"",IF(12<=B23,0,MIN(B38,B24-C38))),"") | E38: =IFERROR(IF(C38="","",C38+D38),"") | F38: =IFERROR(IF(D38="","",B38-D38),"") | G38: =IFERROR(IF(E38="","",'3-Year P&L'!$D$41-'3-Year P&L'!$D$46+'3-Year P&L'!$D$36+'3-Year P&L'!$D$37),"") | H38: =IFERROR(IF(OR(E38="",E38=0),"",G38/E38),"")
A39: 13 | B39: =IFERROR(IF(OR(13>B22,F38=""),"",F38),"") | C39: =IFERROR(IF(OR(13>B22,B39=""),"",B39*B21),"") | D39: =IFERROR(IF(OR(13>B22,B39=""),"",IF(13<=B23,0,MIN(B39,B24-C39))),"") | E39: =IFERROR(IF(C39="","",C39+D39),"") | F39: =IFERROR(IF(D39="","",B39-D39),"") | G39: =IFERROR(IF(E39="","",'3-Year P&L'!$D$41-'3-Year P&L'!$D$46+'3-Year P&L'!$D$36+'3-Year P&L'!$D$37),"") | H39: =IFERROR(IF(OR(E39="",E39=0),"",G39/E39),"")
A40: 14 | B40: =IFERROR(IF(OR(14>B22,F39=""),"",F39),"") | C40: =IFERROR(IF(OR(14>B22,B40=""),"",B40*B21),"") | D40: =IFERROR(IF(OR(14>B22,B40=""),"",IF(14<=B23,0,MIN(B40,B24-C40))),"") | E40: =IFERROR(IF(C40="","",C40+D40),"") | F40: =IFERROR(IF(D40="","",B40-D40),"") | G40: =IFERROR(IF(E40="","",'3-Year P&L'!$D$41-'3-Year P&L'!$D$46+'3-Year P&L'!$D$36+'3-Year P&L'!$D$37),"") | H40: =IFERROR(IF(OR(E40="",E40=0),"",G40/E40),"")
A41: 15 | B41: =IFERROR(IF(OR(15>B22,F40=""),"",F40),"") | C41: =IFERROR(IF(OR(15>B22,B41=""),"",B41*B21),"") | D41: =IFERROR(IF(OR(15>B22,B41=""),"",IF(15<=B23,0,MIN(B41,B24-C41))),"") | E41: =IFERROR(IF(C41="","",C41+D41),"") | F41: =IFERROR(IF(D41="","",B41-D41),"") | G41: =IFERROR(IF(E41="","",'3-Year P&L'!$D$41-'3-Year P&L'!$D$46+'3-Year P&L'!$D$36+'3-Year P&L'!$D$37),"") | H41: =IFERROR(IF(OR(E41="",E41=0),"",G41/E41),"")
A42: Schedule closing tolerance | B42: 0.01 | C42: Rounding margin. Above it, the schedule does not close and there is principal left unpaid
A43: Balance outstanding at maturity | B43: =IFERROR(IF(B20="","",ROUND(B20-SUM(D27:D41),2)),"") -> 0 | C43: Must be zero: the principal repaid in the schedule has to equal the amount borrowed. If it is positive, the term falls short
A44: Year-1 interest | B44: =IFERROR(IF(B20="","",IF(C27="",0,C27)),"") -> 19700
A45: Year-1 principal repaid | B45: =IFERROR(IF(B20="","",IF(D27="",0,D27)),"") -> 12360.843
A46: Year-2 interest | B46: =IFERROR(IF(B20="","",IF(C28="",0,C28)),"") -> 18463.916
A47: Year-2 principal repaid | B47: =IFERROR(IF(B20="","",IF(D28="",0,D28)),"") -> 13596.927
A48: Year-3 interest | B48: =IFERROR(IF(B20="","",IF(C29="",0,C29)),"") -> 17104.223
A49: Year-3 principal repaid | B49: =IFERROR(IF(B20="","",IF(D29="",0,D29)),"") -> 14956.62
A50: DEBT SERVICE COVERAGE RATIO (DSCR)
A51: Year-1 DSCR | B51: =IFERROR(('3-Year P&L'!$B$41-'3-Year P&L'!$B$46+'3-Year P&L'!$B$36+B44)/(B44+B45),"") -> 2.4368188 | C51: An INTEREST-ONLY year, if there is one: with only interest in the denominator the ratio shoots up and does not measure the business
A52: Year-2 DSCR | B52: =IFERROR(('3-Year P&L'!$C$41-'3-Year P&L'!$C$46+'3-Year P&L'!$C$36+B46)/(B46+B47),"") -> 3.4326413
A53: Year-3 DSCR | B53: =IFERROR(('3-Year P&L'!$D$41-'3-Year P&L'!$D$46+'3-Year P&L'!$D$36+B48)/(B48+B49),"") -> 4.0302826
A54: Minimum DSCR across the whole schedule | B54: =IFERROR(IF(COUNT(H27:H41)=0,"",MIN(H27:H41)),"") -> 2.4368188 | C54: The worst year of the life of the loan, not the best of the three the P&L projects. It is the number that decides a loan. Mind the scope: years 1 to 3 come from the P&L, and from year 4 on the schedule HOLDS year 3's cash flow, so the minimum over those years is a sustained projection, not a calculated year. The cash flow is after tax
A56: DSCR is calculated BEFORE debt and AFTER tax: income tax is subtracted from pre-tax income, depreciation and interest are added back, and the result is divided by what has to be paid that year. Below the minimum in the "0. Assumptions" tab, the business does not generate enough to repay the loan. In the schedule, the available cash flow from year 4 on is held at year 3's: the P&L projects only three years, and no growth is invented here that has not been calculated.
