Workbook

Sheet 0. Assumptions
A1: ASSUMPTIONS — the RATES and DRIVERS of the model are typed here
A2: Change the GREEN cells: the rest of the workbook recalculates on its own. Expense items are typed on their own tab (also in green) and are not repeated here. Amounts are in US dollars (or your own currency).
A3: BUSINESS ACTIVITY
A4: Events per year (year-1 average) | B4: 170 | C4: Average number of events you serve per year, counting every corporate booking, wedding, private party and festival or farmers market day. It is the main volume driver of the whole workbook: the P&L, break-even and scenarios all read it, and years 2 and 3 grow in events. The example is a full-time owner-operator with an active corporate sales effort and two stations, not the average first year. Flashquotes shows about 15 bookings per operator per year on its own platform only, so do not read that as the events to expect. Compare this cell with the capacity row further down.
A5: Average price per guest (excl. sales tax, baristas included) | B5: 12.6 | C5: EXCL. sales tax, with the baristas, travel and extras included and the voluntary gratuity left out: the blended price per guest across everything you sell (hosted corporate and wedding bookings, private parties, festival days), not the price of any one package. Price per guest incl. sales tax = this value × (1 + your sales tax rate). Operators quote by booking and by hour, with a base fee plus an hourly rate (see the benchmarks table on the "Instructions" tab). The Pricing Calculator quotes per guest, per service hour and per drink: to bring a quote here, divide the revenue you bill in a year by the guests you serve in that year.
A6: Average guests per event | B6: 95 | C6: Average number of guests per event across your whole mix, from small private parties to weddings of well over a hundred guests. The typical Flashquotes booking is for 100 guests. At a festival or farmers market, every drink sold counts as one guest. Sales per event = guests × price per guest. One cell for the whole workbook: the P&L, break-even and scenarios all read it, so they always agree.
A7: Volume growth in year 2 | B7: 0.1 | C7: Growth in events in year 2 over year 1 (enter 0.10 for 10%). Kept conservative on purpose: repeat corporate clients build up slowly, wedding bookings are made months ahead, and two stations and a small team of baristas limit how fast you can grow.
A8: Volume growth in year 3 | B8: 0.06 | C8: Growth in events in year 3 over year 2, kept conservative for the same reason: corporate repeat business and planner referrals build up slowly, and two stations and your baristas limit how many events you can serve.
A9: Price per guest incl. sales tax (calculated) | B9: =IFERROR(IF($B$5="","",$B$5*(1+SUMPRODUCT('3-Year P&L'!$E$10:$E$11,'3-Year P&L'!$G$10:$G$11))),"") -> 13.608 | C9: =IFERROR("Price per guest excl. sales tax plus the weighted sales tax of your sales lines ("&TEXT(SUMPRODUCT('3-Year P&L'!$E$10:$E$11,'3-Year P&L'!$G$10:$G$11)*100,"0")&"%), rounded. In the US the quote adds sales tax on top, and many states tax the whole catering invoice (coffee service, baristas, add-ons and travel); in the UK, VAT is included in the price.","") -> Price per guest excl. sales tax plus the weighted sales tax of your sales lines (8%), rounded. In the US the quote adds sales tax on top, and many states tax the whole catering invoice (coffee service, baristas, add-ons and travel); in the UK, VAT is included in the price.
A10: SALES MIX AND COST OF GOODS SOLD
A11: COFFEE BAR PACKAGES share of sales (baristas, espresso drinks, batch & cold brew, milks, syrups, cups) | B11: 0.85 | C11: Share of sales that comes from coffee bar packages: the espresso bar with baristas, batch brew and cold brew, milks, syrups and compostable cups. It is an INPUT: change it here and the P&L, the cash flow and the sales tax collected recalculate on their own. The rest of your sales are add-ons.
A12: ADD-ONS share of sales (extra hours, branded cups & latte printing, pastries from a licensed bakery, travel fees) | B12: =IFERROR(IF(COUNT(B11)=0,"",1-B11),"") -> 0.15 | C12: Calculated as the remainder: coffee bar packages + add-ons = 100%. Add-ons are extra service hours, branded cups and latte printing, pastries from a licensed bakery and travel fees.
A13: Cost of goods on COFFEE BAR PACKAGE sales (beans, milks incl. oat milk, syrups, cold brew) | B13: 0.12 | C13: Cost of goods sold on coffee bar package sales: coffee (18 g, or 0.63 oz, per double), milk and oat milk, syrups and cold brew, with a 10% allowance for waste (purging, dialing in, leftover milk). Kit estimate built from an all-in cost of $0.75-1.50 per drink (grindkit.app). The cost of one drink from the calculator is not copied here: this cell is the average of your whole mix, and package revenue also pays for the baristas, so the share is lower than the 20-30% that GrindKit reports on drink revenue. It is the most sensitive lever in the plan: test it at the top of the range before you trust the result.
A14: Cost of goods on ADD-ON sales (pastries, branded cups, printing) | B14: 0.25 | C14: Cost of goods sold on add-ons: pastries bought from a licensed bakery, branded cups and printing ink. Extra hours and travel fees carry almost no cost of goods. Kit estimate.
A15: Compostable cups, lids, sleeves & napkins as % of sales | B15: 0.04 | C15: Compostable cups, lids, sleeves, wooden stirrers and napkins as a % of sales (about $0.30 per drink: Kit estimate). They are compostable because several cities require it (Seattle, as an example): check your local rules. The line scales with the number of drinks you serve. Fuel is NOT here: tow vehicle fuel has its own fixed line on the "3-Year P&L" tab, and generator fuel is in utilities.
A16: FESTIVALS & FARMERS MARKETS share of sales (guest-pay pop-ups) | B16: 0.05 | C16: Share of your sales that comes from festivals and farmers markets where each guest pays for their own drink, often with a minimum sales guarantee from the organizer. This is a side channel, not a delivery or marketplace channel. Set it to 0 if you only work hosted events. The organizer keeps a fee (next row).
A17: Organizer / vendor fee on those sales (booth fees converted to %) | B17: 0.15 | C17: Fee the organizer keeps on your festival and farmers market sales (Kit estimate). If you pay a flat booth fee instead, convert it into a percentage of what you expect to sell there. Not used while the festival share is 0%.
A18: Card processing fee | B18: 0.03 | C18: Card and ACH fees on total sales. Hosts pay their retainer and balance by card, festival guests almost always pay by card, and some companies pay by ACH or check, which lowers the cost. The example is a blended rate: a percentage plus a per-transaction fee, which weighs more on small orders. Check your processor's statement and enter your effective rate (Kit estimate).
A19: LABOR
A20: Employer payroll taxes | B20: 0.1 | C20: FICA (Social Security 6.2% + Medicare 1.45%) + federal and state unemployment taxes (FUTA / SUTA). Workers' comp is in the insurance line. The example uses a lean 10% with no benefits; ask your payroll provider for your rate.
A21: Monthly pay periods per year (keep 12) | B21: 12 | C21: Annual gross pay = monthly gross pay × this number. Keep 12 in the US: it counts the monthly salaries the model pays in a year, not how often you run payroll (weekly or biweekly payroll pays the same annual amount)
A22: Federal minimum wage, annual full-time | B22: 15080 | C22: US federal minimum wage: 7.25 per hour × 2,080 hours = 15,080 per year for a full-time job. Your state or city may set a higher floor: enter it in the state / local minimum wage cell below. Check the current rates at dol.gov
A23: COMMISSARY, CART STORAGE AND FIXED COSTS
A24: Commissary, cart storage & trailer parking, per month | B24: 700 | C24: Monthly cost of your commissary (a permitted shared kitchen), cart storage and trailer parking: one cell for everything you pay for the space. It covers filling potable water, dumping gray water, cold storage for the milk, dry storage and a place for the cart and the trailer. Carts typically pay $200-600 per month (cart-king.com) and shared kitchens charge roughly $15-45 per hour (The Food Corridor, 2023 Shared Kitchen Operator Survey). The deposit and the months before opening are calculated from it. Ask your health department in writing whether your county requires a commissary: many do, and some exempt self-contained units. Get quotes in your area before you sign.
A25: Commissary deposit (months) | B25: 1 | C25: Months of deposit on the commissary agreement. Many shared kitchens ask for one month up front: far less than the deposit on a commercial lease. Negotiate it in the written agreement.
A26: Monthly utilities (generator fuel, water and ice not covered by the commissary) | B26: 100 | C26: Generator fuel, water and ice that the commissary fee does not cover. The generator only runs at outdoor events, because most venues provide power, so this is a small fixed amount. Tow vehicle fuel is not here: it has its own fixed line on the "3-Year P&L" tab. It is the one cell for this cost, so you change it in one place and the rest of the workbook follows.
A27: Insurance (per year) | B27: 3800 | C27: General liability at $1M per occurrence and $2M aggregate with unlimited additional insureds, commercial auto that covers the trailer, workers' comp for your W-2 baristas and coverage for your equipment in transit. Venues ask for a certificate of insurance (COI) naming them as additional insured. There is no liquor liability line because this plan sells no alcohol. Insureon publishes averages for small businesses (see the benchmarks table on the "Instructions" tab); the example is a Kit estimate, so get quotes from an insurance agent. It is counted once, as an annual expense, not also in startup costs.
A28: Miscellaneous and contingency as % of sales | B28: 0.03 | C28: Extra milk, ice, cables and parking at the venue: the unbudgeted costs of each event. It is a VARIABLE cost: it rises and falls with the number of events, so it cannot sit among the fixed costs or it would move the break-even without anyone noticing. Tow vehicle fuel is not here: it has its own fixed line on the "3-Year P&L" tab.
A29: FINANCING
A30: Owner's equity contributed | B30: 30000 | C30: Your own money. Lenders usually expect an owner equity injection (often around 10% for SBA start-ups; many want 20-30%) on the total cash needed in this plan.
A31: Loan requested | B31: 71000 | C31: Principal requested: bank or SBA 7(a). The example loan is above the $50,000 ceiling of the SBA Microloan, so it fits an SBA 7(a) loan or a bank loan (or a Microloan with more of your own money). If your loan is an SBA 7(a), this is the cell. It is the only loan that the amortization schedule, the P&L interest and the DSCR use. The "Financing" tab checks that the sources of funds match the total cash needed on the "Startup Costs" tab (which includes working capital and the cart, portable bar, trailer and plan review contingency): copy the loan suggested there into this cell until the difference reaches zero. A lender will ask for your plan and projections.
A32: Nominal annual interest rate (not APR) | B32: 0.1 | C32: Nominal annual rate (not APR). The example (10%) is the kit's assumption for an SBA 7(a) loan. A smaller loan secured by a cart, a trailer and espresso equipment often prices above a storefront loan: ask two lenders for quotes, and ask about SBA-guaranteed loans, before you set it.
A33: Loan term (years) | B33: 7 | C33: Total years, interest-only period included. A cart, a portable bar, a trailer and espresso machines lose value faster than a storefront build-out, so the term is shorter. SBA 7(a) allows up to 10 years for equipment and working capital.
A34: Interest-only period (years) | B34: 0 | C34: ZERO by default: repayment starts in year 1, so the year-1 DSCR already measures the full loan payment. If you negotiate an interest-only first year, enter it here and read the year-1 DSCR with care.
A35: Working capital (months of fixed costs) | B35: 3 | C35: The minimum this workbook asks for (see "Instructions"): a cushion below 3 months does not cover a slow stretch, such as the summer dip in July and August or a corporate client who pays late.
A36: TAXES
A37: Effective income tax rate (years 1-2) | B37: 0.25 | C37: Example: 21% federal rate for a C corporation plus state tax, rounded to 25%. If you operate as a sole proprietorship, LLC taxed as a pass-through or S corporation, the business itself pays 0% here and you pay tax on the profit personally: set this to 0 and budget for your personal tax separately. The model applies this rate to the first two years with positive taxable income
A38: Effective income tax rate (from year 3) | B38: 0.25 | C38: From the third year with positive taxable income. Same example rate (21% federal C corporation + state). Confirm the rate that applies to you with your accountant and change it here
A39: Sales tax rate on sales | B39: 0.08 | C39: Example rate: state + local sales tax combined, applied to the whole invoice (coffee service, baristas, add-ons and travel). Hosted events are usually taxed as catering; at festivals and markets you collect it drink by drink and may need a permit where you sell. Rates and rules vary widely by state and city: look up yours. UK: 20% VAT applies to catering for events and functions (VAT Notice 709/1).
A40: Sales tax rate on alcohol sold (licensed only) | B40: 0.08 | C40: Same example rate as above. Some states add separate liquor taxes: include them here if they apply to you. Alcohol served on site has its own rate in the sales tax breakdown block, further down. Utilities, equipment and services are handled in the cell below
A41: Recoverable input tax on purchases and capex | B41: 0 | C41: In the US, the sales tax you pay on purchases is a cost, not a credit: leave this at 0%. UK: 20% if you are VAT-registered
A42: Net operating losses carried forward | B42: 0 | C42: Net operating losses from earlier years still to be offset at the start. Federal rules let you offset up to 80% of taxable income in a year; the model offsets 100% as a simplification
A43: DEPRECIATION
A44: Useful life of the espresso cart, portable bar, trailer and fit-outs (years) | B44: 7 | C44: The espresso cart, the portable espresso bar, the enclosed trailer with its wrap and fit-out, and the plan review: the assets that travel to the event are depreciated together. Straight-line book depreciation; tax methods such as MACRS or Section 179 are separate, so confirm with your accountant.
A45: Useful life of the espresso machines, grinders, brewing gear, POS and generator (years) | B45: 5 | C45: Espresso machines, grinders, generator and cords, batch brewer and cold brew system, smallwares, POS and software. Loading and unloading at every event wears them faster than a fixed bar, so a short life is prudent; burrs and gaskets are replaced sooner and go in maintenance. Straight-line book depreciation; MACRS or Section 179 are tax treatments: confirm with your accountant.
A47: GROWTH AND COST INFLATION
A48: Annual increase in fixed costs | B48: 0 | C48: SET TO ZERO: all three columns are in year-1 prices (real terms). Raise it if you want to project in nominal terms
A49: RAMP-UP AND CAPACITY
A51: Max events a year your stations and baristas can handle | B51: 350 | C51: INFORMATION ONLY: it does not enter any calculation in this workbook. It is your estimate of the most events a year your two stations and your baristas can handle. Weekdays have room because corporate events fill them; Saturdays in the wedding season are the bottleneck. Compare it with the events per year you plan and with the optimistic scenario: if the plan goes above it, you need a third station or more baristas. Volume itself is driven by the "Events per year" cell above.
A52: Month-1 activity as a % of steady-state activity | B52: 0.45 | C52: A new coffee catering company does not book in month one what it books in month eight: corporate clients want to try you first, and the median booking is made about 41 days ahead (Flashquotes), with weddings earlier. Events per year above is the year-1 AVERAGE: the ramp only spreads year 1's sales across the months (slower start, stronger finish) and keeps the annual total. At 100% there is no ramp. Festivals and farmers markets are an add-on channel, never a daily street route (that is the Food Truck Kit).
A53: Months to reach steady state | B53: 9 | C53: The ramp rises in a straight line from the percentage above to 100% over this number of months
A54: Months of commissary rent BEFORE opening | B54: 1 | C54: Getting the commissary agreement, the plan review and the cart inspection done takes weeks, and you test both stations and hold a corporate open house before your first booking, so you pay commissary rent before you earn anything. It belongs in startup costs, not in the P&L.
A55: Contingency on the cart, portable bar, trailer, wrap and plan review lines (%) | B55: 0.1 | C55: Calculated by formula on the espresso cart, portable bar, trailer, trailer wrap and plan review lines: if you change the cart price, the contingency recalculates on its own. The note on that row of the "Startup Costs" tab lists exactly which lines are included.
A57: RECEIPTS, PAYMENTS AND SALES TAX BREAKDOWN
A58: Average collection days | B58: 14 | C58: Average days between the event and the money in your bank. Hosts usually pay a retainer of 30-50% when they book the date (grindkit.app) and the balance 14 days before the event, while companies often pay at 15-30 days, so the example sits in between. Raise it if your clients pay later. The workbook does not model deposits: they improve your real cash flow.
A59: Average days to pay suppliers | B59: 7 | C59: What your suppliers finance for you. It is the first thing you lose if you fall behind on a payment
A60: Month of extra pay period 1 (only if pay periods > 12) | B60: 7 | C60: Month of the year (1-12) when the first extra pay period is paid out. Only used if pay periods > 12
A61: Month of extra pay period 2 (only if pay periods > 12) | B61: 12 | C61: Month of the year (1-12) when the second extra pay period is paid out. Only used if pay periods > 12
A62: ALCOHOL as a share of add-on sales (0%: no liquor license; espresso martinis go to a licensed mobile bar) | B62: 0 | C62: ZERO by default: a coffee cart sells no alcohol. Espresso martinis belong to a licensed mobile bar (see the Mobile Bar Business Plan Kit). Selling alcohol requires a liquor license (and, in some states, an event-by-event permit): check your state before adding it. If you ever add it, carry liquor liability coverage.
A63: Sales tax rate on alcohol served on site | B63: 0.08 | C63: Only used if you enter alcohol sales above, which is zero in this plan. Example rate: the same as the rest of the sales (state + local combined). Some states tax alcohol at a different rate or add liquor taxes: if you sell alcohol, enter the rate that applies.
A64: CONTROL THRESHOLDS AND FLOORS
A65: DSCR limit (minimum acceptable) | B65: 1.15 | C65: Below 1.0 the business does not generate enough to repay the loan. Lenders often write a minimum DSCR into the loan covenants: ask yours. Kit default: 1.15×
A66: DSCR target (green) | B66: 1.25 | C66: What lenders commonly look for before approving a loan comfortably. Kit default: 1.25× (editable estimate)
A67: Minimum cushion above break-even | B67: 0.15 | C67: Minimum cushion of the plan above break-even (plan ÷ break-even − 1). The drop you can absorb is 1 − break-even ÷ plan: a 15% cushion lets events fall by about 13% before costs stop being covered
A68: State / local minimum wage, annual full-time | C68: Enter the minimum wage of your state or city, annualized for a full-time job (hourly rate × 2,080 hours). The pay floor in the "Staffing" tab is the HIGHER of this cell and the federal minimum. With 0 or blank, the traffic light compares only against the federal floor. Check current rates at dol.gov.

Sheet Startup Costs
A1: BUSINESS PLAN: COFFEE CART & COFFEE CATERING COMPANY
A2: Estimated Startup Costs
A3: US kit example (2026) — replace with your own quotes.
A5: Item | B5: Amount | C5: % of startup costs | D5: Notes | E5: Taxable / recoverable tax?
A6: STARTUP COSTS | B6: =IFERROR(IF(COUNT(B7:B23)=0,"",SUM(B7:B23)),"") -> 71290 | C6: =IFERROR(B6/$B$26,"") -> 0.71083715
A7: Espresso cart (NSF, hand sink, fresh & gray water tanks, pump & filtration, undercounter fridge) | B7: 13400 | C7: =IFERROR(B7/$B$26,"") -> 0.13361226 | D7: Espresso cart with NSF certification, handwashing sink, potable and gray water tanks (your county sets the volume), pump and filter, and an under-counter refrigerator. Prices run from a few thousand dollars for a basic new cart to well above that for a custom build (see the benchmarks table on the "Instructions" tab). Ask your county for its plan review checklist BEFORE you buy the cart. | E7: Yes
A8: Portable espresso bar for the second station (with undercounter fridge) | B8: 5400 | C8: =IFERROR(B8/$B$26,"") -> 0.053843745 | D8: Portable espresso bar for the second station and for indoor rooms, with an under-counter refrigerator (Kit estimate). It travels in the trailer with the cart. | E8: Yes
A9: Espresso machines: 2-group volumetric (220V) + compact 2-group | B9: 15700 | C9: =IFERROR(B9/$B$26,"") -> 0.1565457 | D9: A 2-group volumetric machine at 220V / 3,400 W (about $8,500-9,000 in store prices; NEMA 6-20 plug, 15-17 A, dedicated circuit) plus a compact 2-group machine for the second station (about $7,200, 14 A). Store prices are a Kit estimate: ask for two quotes. A room without a 220V circuit needs a generator. | E9: Yes
A10: Espresso grinders ×4 (house + decaf at each station) | B10: 4800 | C10: =IFERROR(B10/$B$26,"") -> 0.047861107 | D10: Four espresso grinders (house blend and decaf at each station), $300-3,000 each (cart-king.com). Burrs wear out sooner than the grinder: they go in the maintenance line of the "3-Year P&L" tab. | E10: Yes
A11: Enclosed cargo trailer (6×12 ft, ramp door) | B11: 6500 | C11: =IFERROR(B11/$B$26,"") -> 0.064811916 | D11: An enclosed cargo trailer, 6×12 ft with a ramp door, that carries the cart, the portable bar and the gear. Your own vehicle tows it ($0 in the example). If you do not have a tow vehicle, a used one runs about $18,000 and is not in the budget. | E11: Yes
A12: Trailer wrap, hitch, tie-downs & cart loading ramps | B12: 1500 | C12: =IFERROR(B12/$B$26,"") -> 0.014956596 | D12: Trailer wrap, hitch, tie-downs on E-track and ramps to roll the cart in and out. Check your vehicle's towing capacity and that your insurance covers the wrap and the hitch. | E12: Yes
A13: LLC formation, contracts and legal | B13: 1500 | C13: =IFERROR(B13/$B$26,"") -> 0.014956596 | D13: State filing fees for the LLC (Secretary of State) plus an attorney's review of your standard contract (retainer, cancellation tiers, final guest count, service hours, outlet or generator, rain plan) or a filing service; a registered agent is also needed. Fees vary a lot by state. The "Taxable / recoverable tax?" column is set to No: it only matters if you enter a recoverable input tax rate (for example UK VAT). | E13: No
A14: First-year permits and certifications (health permit, food handler cards, CFPM, fire / generator) | B14: 1400 | C14: =IFERROR(B14/$B$26,"") -> 0.01395949 | D14: Varies a lot by city, county and state: get the amounts for yours before you close the budget. Expect the health permit for the mobile food unit, food handler cards, a Certified Food Protection Manager (CFPM) certificate, the business license, the sales tax permit and, where required, a fire marshal permit for the generator. | E14: No
A15: Mobile food unit plan review & cart inspection | B15: 1100 | C15: =IFERROR(B15/$B$26,"") -> 0.01096817 | D15: Plan review of the mobile food unit and inspection of the cart. As an example, Snohomish County, WA charges $1,100 for the plan review (snohd.org); add any electrical approval your state asks for. Rules and fees vary by county, so ask the health department for its fee schedule. If nobody charges for it, enter 0. | E15: Yes
A16: POS, card readers & booking software | B16: 1000 | C16: =IFERROR(B16/$B$26,"") -> 0.009971064 | D16: POS with card readers (also for festivals), plus booking software for quotes, proposals and e-signatures. | E16: Yes
A17: Batch brewer, airpots, cold brew system, smallwares & commissary storage racks | B17: 3300 | C17: =IFERROR(B17/$B$26,"") -> 0.032904511 | D17: Batch brewer, airpots, a cold brew system, milk pitchers, scales, tampers, knock boxes, sanitizer buckets and storage racks for the commissary: the tools that get depreciated. Daily disposables are NOT depreciated: they go in the compostable cups line of the P&L, at the % of sales set in the "0. Assumptions" tab. | E17: Yes
A18: Opening inventory (beans, milks, syrups, compostable cups) | B18: 1500 | C18: =IFERROR(B18/$B$26,"") -> 0.014956596 | D18: Coffee for your tastings and first events, milks, syrups and compostable cups. With 0% recoverable input tax (the US default), any sales tax you pay on this purchase is treated as a cost. | E18: Yes
... A20: Power: inverter generator (5,500 W), cords & power distribution | B20: 5000 | C20: =IFERROR(B20/$B$26,"") -> 0.04985532 | D20: A 5,500 W continuous inverter generator (quiet, for rooms without an outlet and for outdoor events), cords of the right gauge and a power strip with GFCI. Your fire marshal may ask for a minimum distance and a fire extinguisher: ask before you buy. | E20: Yes
A21: Commissary deposit | B21: =IFERROR(IF('0. Assumptions'!$B$24="","",'0. Assumptions'!$B$24*'0. Assumptions'!$B$25),"") -> 700 | C21: =IFERROR(B21/$B$26,"") -> 0.0069797448 | D21: =IFERROR(""&TEXT('0. Assumptions'!$B$25,"0")&IF('0. Assumptions'!$B$25=1," month"," months")&" of rent, from ""0. Assumptions"". Refundable when the commissary agreement ends: it is not depreciated and carries no tax","") -> 1 month of rent, from "0. Assumptions". Refundable when the commissary agreement ends: it is not depreciated and carries no tax | E21: No
A22: Commissary rent before opening | B22: =IFERROR(IF('0. Assumptions'!$B$24="","",'0. Assumptions'!$B$24*'0. Assumptions'!$B$54),"") -> 700 | C22: =IFERROR(B22/$B$26,"") -> 0.0069797448 | D22: =IFERROR("Rent "&IF('0. Assumptions'!$B$54=1,"for the month","for the "&TEXT('0. Assumptions'!$B$54,"0")&" months")&" of plan review, test events and pre-sales before opening. It does not overlap the P&L, which starts on opening day: its twelve months are twelve trading months","") -> Rent for the month of plan review, test events and pre-sales before opening. It does not overlap the P&L, which starts on opening day: its twelve months are twelve trading months | E22: Yes
A23: Cart, bar, trailer and plan review contingency | B23: =IFERROR(IF(COUNT(B7,B8,B11,B12,B15)=0,"",ROUND((B7+B8+B11+B12+B15)*'0. Assumptions'!$B$55,0)),"") -> 2790 | C23: =IFERROR(B23/$B$26,"") -> 0.027819268 | D23: =IFERROR("At "&TEXT('0. Assumptions'!$B$55,"0%")&" of the BUILD-OUT items of this block (espresso cart, portable espresso bar, enclosed cargo trailer, trailer wrap and hitch, and the mobile food unit plan review), not of the whole block: the other items are left out. No lender funds a build-out without a cushion: the percentage is in ""0. Assumptions""","") -> At 10% of the BUILD-OUT items of this block (espresso cart, portable espresso bar, enclosed cargo trailer, trailer wrap and hitch, and the mobile food unit plan review), not of the whole block: the other items are left out. No lender funds a build-out without a cushion: the percentage is in "0. Assumptions" | E23: Yes
A24: WORKING CAPITAL | B24: =IFERROR(IF(B25="","",B25),"") -> 29000.2 | C24: =IFERROR(B24/$B$26,"") -> 0.28916285
A25: Operating cushion until break-even | B25: =IFERROR(IF('0. Assumptions'!$B$35*('3-Year P&L'!$B$38-'3-Year P&L'!$B$36)=0,"",'0. Assumptions'!$B$35*('3-Year P&L'!$B$38-'3-Year P&L'!$B$36)/12),"") -> 29000.2 | C25: =IFERROR(B25/$B$26,"") -> 0.28916285 | D25: =IFERROR("Covers "&TEXT('0. Assumptions'!$B$35,"0")&IF('0. Assumptions'!$B$35=1," month"," months")&" of year-1 CASH fixed costs (the P&L fixed costs minus depreciation, which is not paid out), the minimum the Instructions of this workbook ask for","") -> Covers 3 months of year-1 CASH fixed costs (the P&L fixed costs minus depreciation, which is not paid out), the minimum the Instructions of this workbook ask for | E25: No
A26: TOTAL STARTUP COSTS (sum of the blocks) | B26: =IFERROR(B6+B24,"") -> 100290.2 | D26: =IFERROR("The percentages in column C are read on this figure, which includes the working capital ("&TEXT(C24,"0%")&" of the total). To compare the breakdown with another plan, use the CAPEX row below.","") -> The percentages in column C are read on this figure, which includes the working capital (29% of the total). To compare the breakdown with another plan, use the CAPEX row below.
A27: CAPEX (startup costs excluding working capital) | B27: =IFERROR(B26-B24,"") -> 71290 | D27: What you buy: the cart and the portable bar, the espresso machines and grinders, the trailer, power, launch and formation costs. The cash cushion is not an investment: it is working capital.
A28: Recoverable input tax on capex | B28: =IFERROR(IF(B26="","",SUMIF($E$7:$E$23,"Yes",$B$7:$B$23)*'0. Assumptions'!$B$41),"") -> 0 | D28: =IFERROR("At "&TEXT('0. Assumptions'!$B$41,"0%")&" on the items marked ""Yes"" in the tax column. US: the sales tax you pay on equipment is part of its cost and is not recovered, so this rate is 0. UK (VAT-registered): 20%, reclaimed on your VAT return, but you pay it first, so the loan has to cover it","") -> At 0% on the items marked "Yes" in the tax column. US: the sales tax you pay on equipment is part of its cost and is not recovered, so this rate is 0. UK (VAT-registered): 20%, reclaimed on your VAT return, but you pay it first, so the loan has to cover it
A29: TOTAL CASH NEEDED AT LAUNCH | B29: =IFERROR(B26+B28,"") -> 100290.2 | D29: This is the figure the Financing tab has to cover
A30: DEPRECIATION BASES (not added to startup costs)
A31: Espresso cart, portable bar, trailer, wrap and plan review (depreciated over the cart life) | B31: =IFERROR(IF(B7="","",B7+B8+B11+B12+B15+B23),"") -> 30690 | D31: =IFERROR("Depreciated over "&TEXT('0. Assumptions'!$B$44,"0")&" years","") -> Depreciated over 7 years
A32: Machinery, furniture and equipment | B32: =IFERROR(IF(B9="","",B9+B10+B16+B17+B20),"") -> 29800 | D32: =IFERROR("Depreciated over "&TEXT('0. Assumptions'!$B$45,"0")&" years","") -> Depreciated over 5 years
A33: Annual depreciation of fixed assets | B33: =IFERROR(B31/MAX(1,'0. Assumptions'!$B$44)+B32/MAX(1,'0. Assumptions'!$B$45),"") -> 10344.286 | D33: =IFERROR("Not depreciated, because they are not fixed assets: LLC formation and legal, first-year permits and certifications, opening inventory, website, photos and launch, the commissary deposit, pre-opening commissary rent and the working capital reserve. They add up to "&TEXT(B26-B31-B32,"#,##0")&" of the "&TEXT(B26,"#,##0")&" total investment.","") -> Not depreciated, because they are not fixed assets: LLC formation and legal, first-year permits and certifications, opening inventory, website, photos and launch, the commissary deposit, pre-opening commissary rent and the working capital reserve. They add up to 39800 of the 100290 total investment.

Sheet 3-Year P&L
A1: PRO FORMA P&L — 3 YEARS
A2: Base case — coffee catering company with two espresso stations
A4: Item | B4: Year 1 | C4: Year 2 | D4: Year 3 | E4: % of sales (year 1) | F4: Notes | G4: Sales tax rate on the line (%)
A5: REVENUE
A6: Events per year (average) | B6: =IFERROR(IF('0. Assumptions'!$B$4="","",'0. Assumptions'!$B$4),"") -> 170 | C6: =IFERROR(B6*(1+'0. Assumptions'!$B$7),"") -> 187 | D6: =IFERROR(C6*(1+'0. Assumptions'!$B$8),"") -> 198.22 | F6: Growth for years 2 and 3 is set in "0. Assumptions"
A7: Average price per guest (excl. sales tax) | B7: =IFERROR(IF('0. Assumptions'!$B$5="","",'0. Assumptions'!$B$5),"") -> 12.6 | C7: =IFERROR(IF(B7="","",B7),"") -> 12.6 | D7: =IFERROR(IF(C7="","",C7),"") -> 12.6 | F7: Held constant at year-1 prices: a price increase is a separate decision
A8: Average guests per event | B8: =IFERROR(IF('0. Assumptions'!$B$6="","",'0. Assumptions'!$B$6),"") -> 95 | C8: =IFERROR(IF(B8="","",B8),"") -> 95 | D8: =IFERROR(IF(C8="","",C8),"") -> 95
A9: TOTAL REVENUE (excl. sales tax) | B9: =IFERROR(IF(B6*B7*B8=0,"",B6*B7*B8),"") -> 203490 | C9: =IFERROR(IF(C6*C7*C8=0,"",C6*C7*C8),"") -> 223839 | D9: =IFERROR(IF(D6*D7*D8=0,"",D6*D7*D8),"") -> 237269.34 | E9: =IFERROR(IF(B9="","",1),"") -> 1
A10: Coffee bar package sales (baristas, espresso drinks, batch & cold brew, milks, syrups, cups) | B10: =IFERROR(IF(B9="","",B9*$E$10),"") -> 172966.5 | C10: =IFERROR(IF(C9="","",C9*$E$10),"") -> 190263.15 | D10: =IFERROR(IF(D9="","",D9*$E$10),"") -> 201678.94 | E10: =IFERROR(IF('0. Assumptions'!$B$11="","",'0. Assumptions'!$B$11),"") -> 0.85 | F10: Sales of coffee bar packages: the espresso bar with baristas, batch brew and cold brew, milks, syrups and compostable cups, across corporate events, weddings, private parties and festival days. All of it carries cost of goods sold at the package rate. | G10: =IFERROR(IF(B9="","",'0. Assumptions'!$B$39),"") -> 0.08
A11: Add-on sales (extra hours, branded cups & latte printing, pastries, travel fees) | B11: =IFERROR(IF(B9="","",B9*$E$11),"") -> 30523.5 | C11: =IFERROR(IF(C9="","",C9*$E$11),"") -> 33575.85 | D11: =IFERROR(IF(D9="","",D9*$E$11),"") -> 35590.401 | E11: =IFERROR(IF('0. Assumptions'!$B$12="","",'0. Assumptions'!$B$12),"") -> 0.15 | F11: Sales of add-ons: extra hours, branded cups and latte printing, pastries from a licensed bakery and travel fees. There is no alcohol revenue. | G11: =IFERROR(IF(B9="","",('0. Assumptions'!$B$62*((1-'0. Assumptions'!$B$16)*'0. Assumptions'!$B$63+'0. Assumptions'!$B$16*'0. Assumptions'!$B$40)+(1-'0. Assumptions'!$B$62)*'0. Assumptions'!$B$39)),"") -> 0.08
A12: VARIABLE COSTS
A13: Cost of goods — coffee bar packages (beans, milks, syrups, cold brew) | B13: =IFERROR(IF(B9="","",B9*'0. Assumptions'!$B$11*'0. Assumptions'!$B$13),"") -> 20755.98 | C13: =IFERROR(IF(C9="","",C9*'0. Assumptions'!$B$11*'0. Assumptions'!$B$13),"") -> 22831.578 | D13: =IFERROR(IF(D9="","",D9*'0. Assumptions'!$B$11*'0. Assumptions'!$B$13),"") -> 24201.473 | E13: =IFERROR(B13/$B$9,"") -> 0.102 | F13: =IFERROR("At "&TEXT('0. Assumptions'!$B$13,"0%")&" of COFFEE BAR PACKAGE sales (beans, milks, syrups and cold brew, with waste), not of total sales: add-ons have their own line","") -> At 12% of COFFEE BAR PACKAGE sales (beans, milks, syrups and cold brew, with waste), not of total sales: add-ons have their own line | G13: =IFERROR(IF(B9="","",'0. Assumptions'!$B$41),"") -> 0
A14: Cost of goods — add-ons | B14: =IFERROR(IF(B9="","",B9*'0. Assumptions'!$B$12*'0. Assumptions'!$B$14),"") -> 7630.875 | C14: =IFERROR(IF(C9="","",C9*'0. Assumptions'!$B$12*'0. Assumptions'!$B$14),"") -> 8393.9625 | D14: =IFERROR(IF(D9="","",D9*'0. Assumptions'!$B$12*'0. Assumptions'!$B$14),"") -> 8897.6003 | E14: =IFERROR(B14/$B$9,"") -> 0.0375 | F14: =IFERROR("At "&TEXT('0. Assumptions'!$B$14,"0%")&" of ADD-ON sales","") -> At 25% of ADD-ON sales | G14: =IFERROR(IF(B9="","",'0. Assumptions'!$B$41),"") -> 0
A15: Compostable cups, lids, sleeves & napkins | B15: =IFERROR(IF(B9="","",B9*'0. Assumptions'!$B$15),"") -> 8139.6 | C15: =IFERROR(IF(C9="","",C9*'0. Assumptions'!$B$15),"") -> 8953.56 | D15: =IFERROR(IF(D9="","",D9*'0. Assumptions'!$B$15),"") -> 9490.7736 | E15: =IFERROR(B15/$B$9,"") -> 0.04 | G15: =IFERROR(IF(B9="","",'0. Assumptions'!$B$41),"") -> 0
A16: Festival & market organizer fees | B16: =IFERROR(IF(B9="","",B9*'0. Assumptions'!$B$16*'0. Assumptions'!$B$17),"") -> 1526.175 | C16: =IFERROR(IF(C9="","",C9*'0. Assumptions'!$B$16*'0. Assumptions'!$B$17),"") -> 1678.7925 | D16: =IFERROR(IF(D9="","",D9*'0. Assumptions'!$B$16*'0. Assumptions'!$B$17),"") -> 1779.5201 | E16: =IFERROR(B16/$B$9,"") -> 0.0075 | F16: Applied to the sales of THAT CHANNEL. With 0% festival and farmers market sales in "0. Assumptions", this line is zero | G16: =IFERROR(IF(B9="","",'0. Assumptions'!$B$41),"") -> 0
A17: Card processing fees | B17: =IFERROR(IF(B9="","",B9*'0. Assumptions'!$B$18),"") -> 6104.7 | C17: =IFERROR(IF(C9="","",C9*'0. Assumptions'!$B$18),"") -> 6715.17 | D17: =IFERROR(IF(D9="","",D9*'0. Assumptions'!$B$18),"") -> 7118.0802 | E17: =IFERROR(B17/$B$9,"") -> 0.03 | F17: Card processing fees are not subject to sales tax: no tax is recovered or deducted for them | G17: 0
A18: Miscellaneous and contingency | B18: =IFERROR(IF(B9="","",B9*'0. Assumptions'!$B$28),"") -> 6104.7 | C18: =IFERROR(IF(C9="","",C9*'0. Assumptions'!$B$28),"") -> 6715.17 | D18: =IFERROR(IF(D9="","",D9*'0. Assumptions'!$B$28),"") -> 7118.0802 | E18: =IFERROR(B18/$B$9,"") -> 0.03 | F18: =IFERROR("At "&TEXT('0. Assumptions'!$B$28,"0%")&" of sales: a cushion for unbudgeted event costs (extra milk, ice, cables, venue parking). It is a VARIABLE cost: it moves with the number of events, so it cannot sit in fixed costs (tow vehicle and trailer fuel, maintenance and registration are in row 27; generator fuel is in utilities)","") -> At 3% of sales: a cushion for unbudgeted event costs (extra milk, ice, cables, venue parking). It is a VARIABLE cost: it moves with the number of events, so it cannot sit in fixed costs (tow vehicle and trailer fuel, maintenance and registration are in row 27; generator fuel is in utilities) | G18: =IFERROR(IF(B9="","",'0. Assumptions'!$B$41),"") -> 0
A19: TOTAL VARIABLE COSTS | B19: =IFERROR(IF(B9="","",SUM(B13:B18)),"") -> 50262.03 | C19: =IFERROR(IF(C9="","",SUM(C13:C18)),"") -> 55288.233 | D19: =IFERROR(IF(D9="","",SUM(D13:D18)),"") -> 58605.527 | E19: =IFERROR(B19/$B$9,"") -> 0.247
A20: GROSS MARGIN | B20: =IFERROR(IF(B9="","",B9-B19),"") -> 153227.97 | C20: =IFERROR(IF(C9="","",C9-C19),"") -> 168550.77 | D20: =IFERROR(IF(D9="","",D9-D19),"") -> 178663.81 | E20: =IFERROR(B20/$B$9,"") -> 0.753
A21: FIXED COSTS
A22: Commissary, cart storage & trailer parking | B22: =IFERROR(IF(B9="","",'0. Assumptions'!$B$24*12),"") -> 8400 | C22: =IFERROR(IF(C9="","",B22*(1+'0. Assumptions'!$B$48)),"") -> 8400 | D22: =IFERROR(IF(D9="","",C22*(1+'0. Assumptions'!$B$48)),"") -> 8400 | E22: =IFERROR(B22/$B$9,"") -> 0.04127967 | F22: The monthly amount is typed in "0. Assumptions"; here it is multiplied by twelve. It covers your commissary hours, cart storage and trailer parking, not storefront rent. The months before opening are on the "Startup Costs" tab and are NOT counted twice. | G22: =IFERROR(IF(B9="","",'0. Assumptions'!$B$41),"") -> 0
A23: Labor (wages + employer payroll taxes) | B23: =IFERROR(IF(B9="","",Staffing!$G$9),"") -> 74500.8 | C23: =IFERROR(IF(C9="","",Staffing!$B$13),"") -> 77500.8 | D23: =IFERROR(IF(D9="","",Staffing!$B$14),"") -> 80500.8 | E23: =IFERROR(B23/$B$9,"") -> 0.36611529 | F23: Comes from the Staffing tab: it is the SAME number, not a separate estimate. Years 2 and 3 add the new hires declared on that tab, not a percentage of volume | G23: 0
A24: Utilities (generator fuel, water and ice not covered by the commissary) | B24: =IFERROR(IF(B9="","",'0. Assumptions'!$B$26*12),"") -> 1200 | C24: =IFERROR(IF(C9="","",B24*(1+'0. Assumptions'!$B$48)),"") -> 1200 | D24: =IFERROR(IF(D9="","",C24*(1+'0. Assumptions'!$B$48)),"") -> 1200 | E24: =IFERROR(B24/$B$9,"") -> 0.0058970957 | F24: Generator fuel, water and ice that the commissary fee does not cover. Tow vehicle fuel is not here: it has its own fixed line on this tab. | G24: =IFERROR(IF(B9="","",'0. Assumptions'!$B$41),"") -> 0
A25: Insurance (general liability, commercial auto with the trailer, workers' comp, equipment) | B25: =IFERROR(IF(B9="","",'0. Assumptions'!$B$27),"") -> 3800 | C25: =IFERROR(IF(C9="","",B25*(1+'0. Assumptions'!$B$48)),"") -> 3800 | D25: =IFERROR(IF(D9="","",C25*(1+'0. Assumptions'!$B$48)),"") -> 3800 | E25: =IFERROR(B25/$B$9,"") -> 0.018674136 | F25: Insurance premiums are not subject to sales tax: there is no recoverable tax on them | G25: 0
A26: Annual permits and licenses (health permit renewal, temporary event and fire / generator permits) | B26: 1500 | C26: =IFERROR(IF(C9="","",B26*(1+'0. Assumptions'!$B$48)),"") -> 1500 | D26: =IFERROR(IF(D9="","",C26*(1+'0. Assumptions'!$B$48)),"") -> 1500 | E26: =IFERROR(B26/$B$9,"") -> 0.0073713696 | G26: =IFERROR(IF(B9="","",'0. Assumptions'!$B$41),"") -> 0
A27: Tow vehicle & trailer fuel, maintenance and registration | B27: 3500 | C27: =IFERROR(IF(C9="","",B27*(1+'0. Assumptions'!$B$48)),"") -> 3500 | D27: =IFERROR(IF(D9="","",C27*(1+'0. Assumptions'!$B$48)),"") -> 3500 | E27: =IFERROR(B27/$B$9,"") -> 0.017199862 | G27: =IFERROR(IF(B9="","",'0. Assumptions'!$B$41),"") -> 0
A28: Marketing and advertising | B28: 8000 | C28: =IFERROR(IF(C9="","",B28*(1+'0. Assumptions'!$B$48)),"") -> 8000 | D28: =IFERROR(IF(D9="","",C28*(1+'0. Assumptions'!$B$48)),"") -> 8000 | E28: =IFERROR(B28/$B$9,"") -> 0.039313971 | G28: =IFERROR(IF(B9="","",'0. Assumptions'!$B$41),"") -> 0
A29: Accounting / bookkeeping | B29: 2400 | C29: =IFERROR(IF(C9="","",B29*(1+'0. Assumptions'!$B$48)),"") -> 2400 | D29: =IFERROR(IF(D9="","",C29*(1+'0. Assumptions'!$B$48)),"") -> 2400 | E29: =IFERROR(B29/$B$9,"") -> 0.011794191 | G29: =IFERROR(IF(B9="","",'0. Assumptions'!$B$41),"") -> 0
A30: Software (quotes / booking / CRM, POS, e-signature, website) | B30: 1500 | C30: =IFERROR(IF(C9="","",B30*(1+'0. Assumptions'!$B$48)),"") -> 1500 | D30: =IFERROR(IF(D9="","",C30*(1+'0. Assumptions'!$B$48)),"") -> 1500 | E30: =IFERROR(B30/$B$9,"") -> 0.0073713696 | G30: =IFERROR(IF(B9="","",'0. Assumptions'!$B$41),"") -> 0
A31: Linens, signage, aprons and smallwares replacement | B31: 600 | C31: =IFERROR(IF(C9="","",B31*(1+'0. Assumptions'!$B$48)),"") -> 600 | D31: =IFERROR(IF(D9="","",C31*(1+'0. Assumptions'!$B$48)),"") -> 600 | E31: =IFERROR(B31/$B$9,"") -> 0.0029485478 | G31: =IFERROR(IF(B9="","",'0. Assumptions'!$B$41),"") -> 0
A32: Phone, internet & card-reader data plans | B32: 900 | C32: =IFERROR(IF(C9="","",B32*(1+'0. Assumptions'!$B$48)),"") -> 900 | D32: =IFERROR(IF(D9="","",C32*(1+'0. Assumptions'!$B$48)),"") -> 900 | E32: =IFERROR(B32/$B$9,"") -> 0.0044228218 | F32: Phone, internet and the data plans of your card readers and POS. Small, fixed and easy to forget. | G32: =IFERROR(IF(B9="","",'0. Assumptions'!$B$41),"") -> 0
A33: Espresso machine service, water filters & grinder burrs | B33: 1800 | C33: =IFERROR(IF(C9="","",B33*(1+'0. Assumptions'!$B$48)),"") -> 1800 | D33: =IFERROR(IF(D9="","",C33*(1+'0. Assumptions'!$B$48)),"") -> 1800 | E33: =IFERROR(B33/$B$9,"") -> 0.0088456435 | F33: Service for the espresso machines, water filters and grinder burrs. Gaskets and burrs wear out before the machine does. | G33: =IFERROR(IF(B9="","",'0. Assumptions'!$B$41),"") -> 0
A34: Food safety & barista training (CFPM, food handler cards) | B34: 400 | C34: =IFERROR(IF(C9="","",B34*(1+'0. Assumptions'!$B$48)),"") -> 400 | D34: =IFERROR(IF(D9="","",C34*(1+'0. Assumptions'!$B$48)),"") -> 400 | E34: =IFERROR(B34/$B$9,"") -> 0.0019656986 | F34: Certified Food Protection Manager (CFPM) and food handler cards for you and your team, plus their renewals, and barista training. The required cards vary by state. | G34: =IFERROR(IF(B9="","",'0. Assumptions'!$B$41),"") -> 0
A35: Tastings for prospects (corporate open house, couples) | B35: 400 | C35: =IFERROR(IF(C9="","",B35*(1+'0. Assumptions'!$B$48)),"") -> 400 | D35: =IFERROR(IF(D9="","",C35*(1+'0. Assumptions'!$B$48)),"") -> 400 | E35: =IFERROR(B35/$B$9,"") -> 0.0019656986 | F35: Food cost and labor for the tastings you offer couples and companies (a bridal tasting or a corporate open house). Many operators charge a fee and credit it toward the booking: if you do, lower this line. | G35: =IFERROR(IF(B9="","",'0. Assumptions'!$B$41),"") -> 0
A36: Depreciation of fixed assets | B36: =IFERROR(IF(B9="","",'Startup Costs'!$B$33),"") -> 10344.286 | C36: =IFERROR(IF(C9="","",B36),"") -> 10344.286 | D36: =IFERROR(IF(D9="","",B36),"") -> 10344.286 | E36: =IFERROR(B36/$B$9,"") -> 0.050834369 | F36: Comes from the depreciation bases on the Startup Costs tab: real fixed assets only. It does NOT rise with inflation: it is a charge on the HISTORICAL cost of the assets | G36: 0
A37: Interest expense (loan interest) | B37: =IFERROR(IF(B9="","",Financing!$B$44),"") -> 7100 | C37: =IFERROR(IF(C9="","",Financing!$B$46),"") -> 6351.621 | D37: =IFERROR(IF(D9="","",Financing!$B$48),"") -> 5528.404 | E37: =IFERROR(B37/$B$9,"") -> 0.034891149 | F37: Only INTEREST is an expense. Principal repaid appears on the cash flow tab | G37: 0
A38: TOTAL FIXED COSTS | B38: =IFERROR(IF(B9="","",SUM(B22:B37)),"") -> 126345.09 | C38: =IFERROR(IF(C9="","",SUM(C22:C37)),"") -> 128596.71 | D38: =IFERROR(IF(D9="","",SUM(D22:D37)),"") -> 130773.49 | E38: =IFERROR(B38/$B$9,"") -> 0.62089088
A39: Recoverable input tax on variable costs | B39: =IFERROR(IF(B9="","",SUMPRODUCT(B13:B18,G13:G18)),"") -> 0 | C39: =IFERROR(IF(C9="","",SUMPRODUCT(C13:C18,G13:G18)),"") -> 0 | D39: =IFERROR(IF(D9="","",SUMPRODUCT(D13:D18,G13:G18)),"") -> 0 | F39: Each line at ITS OWN rate, read from the column next to it. It is what the cash flow tab overpays to suppliers and later deducts (zero wherever no tax is recoverable)
A40: Recoverable input tax on fixed costs | B40: =IFERROR(IF(B9="","",SUMPRODUCT(B22:B37,G22:G37)),"") -> 0 | C40: =IFERROR(IF(C9="","",SUMPRODUCT(C22:C37,G22:G37)),"") -> 0 | D40: =IFERROR(IF(D9="","",SUMPRODUCT(D22:D37,G22:G37)),"") -> 0
A41: PRE-TAX INCOME (EBT) | B41: =IFERROR(IF(B9="","",B20-B38),"") -> 26882.884 | C41: =IFERROR(IF(C9="","",C20-C38),"") -> 39954.06 | D41: =IFERROR(IF(D9="","",D20-D38),"") -> 47890.323 | E41: =IFERROR(B41/$B$9,"") -> 0.13210912
A42: Net operating losses carried forward (opening) | B42: =IFERROR(IF(B9="","",'0. Assumptions'!$B$42),"") -> 0 | C42: =IFERROR(IF(C9="","",B47),"") -> 0 | D42: =IFERROR(IF(D9="","",C47),"") -> 0 | F42: Federal rules let a year's losses offset the profits of later years (the federal limit is 80% of taxable income; this model offsets 100% as a simplification)
A43: Taxable income (after loss offset) | B43: =IFERROR(IF(B9="","",MAX(0,B41-B42)),"") -> 26882.884 | C43: =IFERROR(IF(C9="","",MAX(0,C41-C42)),"") -> 39954.06 | D43: =IFERROR(IF(D9="","",MAX(0,D41-D42)),"") -> 47890.323
A44: Years with positive taxable income (cumulative) | B44: =IFERROR(IF(B9="","",IF(B43>0,1,0)),"") -> 1 | C44: =IFERROR(IF(C9="","",B44+IF(C43>0,1,0)),"") -> 2 | D44: =IFERROR(IF(D9="","",C44+IF(D43>0,1,0)),"") -> 3
A45: Effective income tax rate applied | B45: =IFERROR(IF(B9="","",IF(B43<=0,"",IF(B44<=2,'0. Assumptions'!$B$37,'0. Assumptions'!$B$38))),"") -> 0.25 | C45: =IFERROR(IF(C9="","",IF(C43<=0,"",IF(C44<=2,'0. Assumptions'!$B$37,'0. Assumptions'!$B$38))),"") -> 0.25 | D45: =IFERROR(IF(D9="","",IF(D43<=0,"",IF(D44<=2,'0. Assumptions'!$B$37,'0. Assumptions'!$B$38))),"") -> 0.25 | F45: The "years 1-2" rate applies to the first two years with positive taxable income, not to the first two calendar years of the business. The model approximates this by counting the first two profitable years
A46: Income tax | B46: =IFERROR(IF(B9="","",IF(B45="",0,B43*B45)),"") -> 6720.7211 | C46: =IFERROR(IF(C9="","",IF(C45="",0,C43*C45)),"") -> 9988.5151 | D46: =IFERROR(IF(D9="","",IF(D45="",0,D43*D45)),"") -> 11972.581
A47: Net operating losses carried forward (closing) | B47: =IFERROR(IF(B9="","",MAX(0,B42-B41)),"") -> 0 | C47: =IFERROR(IF(C9="","",MAX(0,C42-C41)),"") -> 0 | D47: =IFERROR(IF(D9="","",MAX(0,D42-D41)),"") -> 0
A48: NET INCOME | B48: =IFERROR(IF(B9="","",B41-B46),"") -> 20162.163 | C48: =IFERROR(IF(C9="","",C41-C46),"") -> 29965.545 | D48: =IFERROR(IF(D9="","",D41-D46),"") -> 35917.742 | E48: =IFERROR(B48/$B$9,"") -> 0.099081838
A49: KEY RATIOS
A50: Ratio | B50: Year 1 | C50: Year 2 | D50: Year 3 | E50: Threshold | F50: Comment
A51: Gross margin / Sales | B51: =IFERROR(IF(B9="","",B20/B9),"") -> 0.753 | C51: =IFERROR(IF(C9="","",C20/C9),"") -> 0.753 | D51: =IFERROR(IF(D9="","",D20/D9),"") -> 0.753 | E51: 0.72 | F51: Floor set by this workbook: kit benchmark (editable estimate). The workbook's gross margin also subtracts compostable cups, card fees, festival organizer fees and miscellaneous costs, so the floor sits below the margin you would see on cost of goods alone.
A52: Cost of goods sold (coffee bar packages + add-ons) | B52: =IFERROR(IF(B9="","",B13+B14),"") -> 28386.855 | C52: =IFERROR(IF(C9="","",C13+C14),"") -> 31225.541 | D52: =IFERROR(IF(D9="","",D13+D14),"") -> 33099.073
A53: Cost of goods sold / Sales | B53: =IFERROR(IF(B9="","",B52/B9),"") -> 0.1395 | C53: =IFERROR(IF(C9="","",C52/C9),"") -> 0.1395 | D53: =IFERROR(IF(D9="","",D52/D9),"") -> 0.1395 | E53: 0.2 | F53: Ceiling for cost of goods (compostable cups have their own line): kit benchmark (editable estimate), based on the 20-30% cost of goods that GrindKit reports for drink revenue.
A54: Labor cost / Sales | B54: =IFERROR(IF(B9="","",B23/B9),"") -> 0.36611529 | C54: =IFERROR(IF(C9="","",C23/C9),"") -> 0.34623457 | D54: =IFERROR(IF(D9="","",D23/D9),"") -> 0.33928025 | E54: 0.4 | F54: Ceiling: kit benchmark (editable estimate), set above what many pricing guides report because it includes the owner's own pay as lead barista and sales.
A55: Commissary & cart storage / Sales | B55: =IFERROR(IF(B9="","",B22/B9),"") -> 0.04127967 | C55: =IFERROR(IF(C9="","",C22/C9),"") -> 0.037526973 | D55: =IFERROR(IF(D9="","",D22/D9),"") -> 0.035402804 | E55: 0.06 | F55: There is no storefront rent in this workbook: 6% is a prudent ceiling for the commissary, cart storage and trailer parking, a kit benchmark (editable estimate). A business with its own fixed location carries a much higher occupancy cost.
A56: Net income / Sales | B56: =IFERROR(IF(B9="","",B48/B9),"") -> 0.099081838 | C56: =IFERROR(IF(C9="","",C48/C9),"") -> 0.13387098 | D56: =IFERROR(IF(D9="","",D48/D9),"") -> 0.15137962 | E56: 0.05 | F56: Floor of 5%: a kit benchmark (editable estimate). A new business with a loan to repay starts lower than established operators.
A57: Break-even reached | B57: =IFERROR(IF(B9="","",IF(B9>='Break-Even'!$B$16,"Yes","No")),"") -> Yes | C57: =IFERROR(IF(C9="","",IF(C9>='Break-Even'!$C$16,"Yes","No")),"") -> Yes | D57: =IFERROR(IF(D9="","",IF(D9>='Break-Even'!$D$16,"Yes","No")),"") -> Yes | F57: Compares each year's sales with that same year's threshold, which the Break-Even tab calculates with that year's fixed costs
A59: All figures are EXCL. SALES TAX. Years 2 and 3 are in year-1 prices unless you raise cost inflation in the "0. Assumptions" tab. The "Sales tax rate on the line (%)" column shows, on SALES lines, the rate collected on each one and, on COST lines, the rate paid on that item. The cash flow tab reads it: insurance and card fees carry no sales tax, and wages, depreciation and interest carry none either.

Sheet Break-Even
A1: BREAK-EVEN ANALYSIS
A2: Break-even — Coffee Cart
A4: Variable | B4: Year 1 | C4: Year 2 | D4: Year 3 | E4: Notes
A5: BASE DATA BY YEAR
A6: Annual fixed costs | B6: =IFERROR(IF('3-Year P&L'!$B$9="","",'3-Year P&L'!$B$38),"") -> 126345.09 | C6: =IFERROR(IF('3-Year P&L'!$C$9="","",'3-Year P&L'!$C$38),"") -> 128596.71 | D6: =IFERROR(IF('3-Year P&L'!$D$9="","",'3-Year P&L'!$D$38),"") -> 130773.49 | E6: The SAME fixed costs as the P&L. Each year has its own, which is why the threshold cannot be a single one for all three years
A7: Monthly fixed costs | B7: =IFERROR(IF('3-Year P&L'!$B$9="","",B6/12),"") -> 10528.757 | C7: =IFERROR(IF('3-Year P&L'!$C$9="","",C6/12),"") -> 10716.392 | D7: =IFERROR(IF('3-Year P&L'!$D$9="","",D6/12),"") -> 10897.791
A8: Average price per guest (excl. sales tax) | B8: =IFERROR(IF('3-Year P&L'!$B$9="","",'3-Year P&L'!$B$7),"") -> 12.6 | C8: =IFERROR(IF('3-Year P&L'!$C$9="","",'3-Year P&L'!$C$7),"") -> 12.6 | D8: =IFERROR(IF('3-Year P&L'!$D$9="","",'3-Year P&L'!$D$7),"") -> 12.6
A9: Variable cost per guest | B9: =IFERROR(IF('3-Year P&L'!$B$9="","",'3-Year P&L'!$B$19/('3-Year P&L'!$B$6*'3-Year P&L'!$B$8)),"") -> 3.1122 | C9: =IFERROR(IF('3-Year P&L'!$C$9="","",'3-Year P&L'!$C$19/('3-Year P&L'!$C$6*'3-Year P&L'!$C$8)),"") -> 3.1122 | D9: =IFERROR(IF('3-Year P&L'!$D$9="","",'3-Year P&L'!$D$19/('3-Year P&L'!$D$6*'3-Year P&L'!$D$8)),"") -> 3.1122 | E9: Comes from the P&L total variable costs, not from a separate estimate. It includes miscellaneous and contingency, which is a percentage of sales
A10: Contribution margin per guest | B10: =IFERROR(IF('3-Year P&L'!$B$9="","",B8-B9),"") -> 9.4878 | C10: =IFERROR(IF('3-Year P&L'!$C$9="","",C8-C9),"") -> 9.4878 | D10: =IFERROR(IF('3-Year P&L'!$D$9="","",D8-D9),"") -> 9.4878 | E10: Price per guest minus variable cost per guest
A11: Average guests per event | B11: =IFERROR(IF('3-Year P&L'!$B$9="","",'3-Year P&L'!$B$8),"") -> 95 | C11: =IFERROR(IF('3-Year P&L'!$C$9="","",'3-Year P&L'!$C$8),"") -> 95 | D11: =IFERROR(IF('3-Year P&L'!$D$9="","",'3-Year P&L'!$D$8),"") -> 95 | E11: The same calendar as the P&L and the scenarios
A12: Principal repaid in the year | B12: =IFERROR(IF('3-Year P&L'!$B$9="","",Financing!$B$45),"") -> 7483.7905 | C12: =IFERROR(IF('3-Year P&L'!$C$9="","",Financing!$B$47),"") -> 8232.1695 | D12: =IFERROR(IF('3-Year P&L'!$D$9="","",Financing!$B$49),"") -> 9055.3865 | E12: Principal is NOT a P&L expense, but it leaves the cash account. Without it, the published break-even threshold would sit below the real one
A13: ACCOUNTING BREAK-EVEN (includes depreciation)
A14: Guests needed per year | B14: =IFERROR(IF('3-Year P&L'!$B$9="","",IF(B10<=0,"",B6/B10)),"") -> 13316.584 | C14: =IFERROR(IF('3-Year P&L'!$C$9="","",IF(C10<=0,"",C6/C10)),"") -> 13553.902 | D14: =IFERROR(IF('3-Year P&L'!$D$9="","",IF(D10<=0,"",D6/D10)),"") -> 13783.331
A15: Events needed per year | B15: =IFERROR(IF('3-Year P&L'!$B$9="","",B14/B11),"") -> 140.17457 | C15: =IFERROR(IF('3-Year P&L'!$C$9="","",C14/C11),"") -> 142.67265 | D15: =IFERROR(IF('3-Year P&L'!$D$9="","",D14/D11),"") -> 145.0877
A16: Revenue needed per year | B16: =IFERROR(IF('3-Year P&L'!$B$9="","",B14*B8),"") -> 167788.96 | C16: =IFERROR(IF('3-Year P&L'!$C$9="","",C14*C8),"") -> 170779.16 | D16: =IFERROR(IF('3-Year P&L'!$D$9="","",D14*D8),"") -> 173669.97
A17: CASH BREAK-EVEN (loan payments in, depreciation out)
A18: Cash fixed costs + principal repaid for the year | B18: =IFERROR(IF('3-Year P&L'!$B$9="","",B6-'3-Year P&L'!$B$36+B12),"") -> 123484.59 | C18: =IFERROR(IF('3-Year P&L'!$C$9="","",C6-'3-Year P&L'!$C$36+C12),"") -> 126484.59 | D18: =IFERROR(IF('3-Year P&L'!$D$9="","",D6-'3-Year P&L'!$D$36+D12),"") -> 129484.59 | E18: The P&L fixed costs without depreciation (which is not paid in cash) and WITH principal repaid (which is). This is the threshold that decides whether cash holds up
A19: Guests needed per year (cash) | B19: =IFERROR(IF('3-Year P&L'!$B$9="","",IF(B10<=0,"",B18/B10)),"") -> 13015.092 | C19: =IFERROR(IF('3-Year P&L'!$C$9="","",IF(C10<=0,"",C18/C10)),"") -> 13331.288 | D19: =IFERROR(IF('3-Year P&L'!$D$9="","",IF(D10<=0,"",D18/D10)),"") -> 13647.483
A20: Events needed per year (cash) | B20: =IFERROR(IF('3-Year P&L'!$B$9="","",B19/B11),"") -> 137.00097 | C20: =IFERROR(IF('3-Year P&L'!$C$9="","",C19/C11),"") -> 140.32934 | D20: =IFERROR(IF('3-Year P&L'!$D$9="","",D19/D11),"") -> 143.65772
A21: Revenue needed per year (cash) | B21: =IFERROR(IF('3-Year P&L'!$B$9="","",B19*B8),"") -> 163990.16 | C21: =IFERROR(IF('3-Year P&L'!$C$9="","",C19*C8),"") -> 167974.22 | D21: =IFERROR(IF('3-Year P&L'!$D$9="","",D19*D8),"") -> 171958.29
A22: COMPARISON WITH THE PLAN
A23: Events per year in the plan | B23: =IFERROR(IF('3-Year P&L'!$B$9="","",'3-Year P&L'!$B$6),"") -> 170 | C23: =IFERROR(IF('3-Year P&L'!$C$9="","",'3-Year P&L'!$C$6),"") -> 187 | D23: =IFERROR(IF('3-Year P&L'!$D$9="","",'3-Year P&L'!$D$6),"") -> 198.22
A24: Cushion above CASH break-even (%) | B24: =IFERROR(IF('3-Year P&L'!$B$9="","",B23/B20-1),"") -> 0.24086713 | C24: =IFERROR(IF('3-Year P&L'!$C$9="","",C23/C20-1),"") -> 0.33257946 | D24: =IFERROR(IF('3-Year P&L'!$D$9="","",D23/D20-1),"") -> 0.37980753 | E24: How far the plan sits above the cash break-even (plan ÷ break-even − 1); the drop you can absorb is 1 − break-even ÷ plan. The required minimum is set in the "0. Assumptions" tab
A25: INTERPRETATION
A26: =IFERROR("With the average price per guest excl. sales tax above, you need "&TEXT(ROUNDUP(B15,0),"0")&" events a year at your average of "&TEXT(B11,"0")&" guests per event to avoid losing money (accounting break-even, depreciation included), and "&TEXT(ROUNDUP(B20,0),"0")&" for cash to hold (cash break-even: depreciation out, because it is not paid, and the year's loan payment in"&IF(B12=0,"; no principal is repaid this year (interest-only period or no loan)","")&"). The ""Revenue needed per year"" rows show the same figures in your currency.","") -> With the average price per guest excl. sales tax above, you need 141 events a year at your average of 95 guests per event to avoid losing money (accounting break-even, depreciation included), and 138 for cash to hold (cash break-even: depreciation out, because it is not paid, and the year's loan payment in). The "Revenue needed per year" rows show the same figures in your currency.
A28: BREAK-EVEN SENSITIVITY
A29: Events per year needed to cover costs for each price per guest (columns, in steps around the plan's price) and each variable cost per guest (rows). Green cells are below the events per year the plan forecasts.
A31: Events per year needed: price per guest excl. sales tax (columns) × variable cost per guest (rows) | B31: =IFERROR($B$8-1,"") -> 11.6 | C31: =IFERROR(IF($B$8="","",$B$8),"") -> 12.6 | D31: =IFERROR($B$8+1,"") -> 13.6 | E31: =IFERROR($B$8+2,"") -> 14.6
A32: =IFERROR($B$9*0.85,"") -> 2.64537 | B32: =IFERROR(IF($B$31-$A32<=0,"",$B$6/($B$31-$A32)/$B$11),"") -> 148.52074 | C32: =IFERROR(IF($C$31-$A32<=0,"",$B$6/($C$31-$A32)/$B$11),"") -> 133.60097 | D32: =IFERROR(IF($D$31-$A32<=0,"",$B$6/($D$31-$A32)/$B$11),"") -> 121.40513 | E32: =IFERROR(IF($E$31-$A32<=0,"",$B$6/($E$31-$A32)/$B$11),"") -> 111.24964
A33: =IFERROR($B$9*0.925,"") -> 2.878785 | B33: =IFERROR(IF($B$31-$A33<=0,"",$B$6/($B$31-$A33)/$B$11),"") -> 152.49576 | C33: =IFERROR(IF($C$31-$A33<=0,"",$B$6/($C$31-$A33)/$B$11),"") -> 136.80885 | D33: =IFERROR(IF($D$31-$A33<=0,"",$B$6/($D$31-$A33)/$B$11),"") -> 124.04828 | E33: =IFERROR(IF($E$31-$A33<=0,"",$B$6/($E$31-$A33)/$B$11),"") -> 113.46505
A34: =IFERROR($B$9*1.0,"") -> 3.1122 | B34: =IFERROR(IF($B$31-$A34<=0,"",$B$6/($B$31-$A34)/$B$11),"") -> 156.6894 | C34: =IFERROR(IF($C$31-$A34<=0,"",$B$6/($C$31-$A34)/$B$11),"") -> 140.17457 | D34: =IFERROR(IF($D$31-$A34<=0,"",$B$6/($D$31-$A34)/$B$11),"") -> 126.80908 | E34: =IFERROR(IF($E$31-$A34<=0,"",$B$6/($E$31-$A34)/$B$11),"") -> 115.77049
A35: =IFERROR($B$9*1.075,"") -> 3.345615 | B35: =IFERROR(IF($B$31-$A35<=0,"",$B$6/($B$31-$A35)/$B$11),"") -> 161.12021 | C35: =IFERROR(IF($C$31-$A35<=0,"",$B$6/($C$31-$A35)/$B$11),"") -> 143.71007 | D35: =IFERROR(IF($D$31-$A35<=0,"",$B$6/($D$31-$A35)/$B$11),"") -> 129.69557 | E35: =IFERROR(IF($E$31-$A35<=0,"",$B$6/($E$31-$A35)/$B$11),"") -> 118.17156
A36: =IFERROR($B$9*1.15,"") -> 3.57903 | B36: =IFERROR(IF($B$31-$A36<=0,"",$B$6/($B$31-$A36)/$B$11),"") -> 165.80891 | C36: =IFERROR(IF($C$31-$A36<=0,"",$B$6/($C$31-$A36)/$B$11),"") -> 147.42852 | D36: =IFERROR(IF($D$31-$A36<=0,"",$B$6/($D$31-$A36)/$B$11),"") -> 132.71652 | E36: =IFERROR(IF($E$31-$A36<=0,"",$B$6/($E$31-$A36)/$B$11),"") -> 120.67434

Sheet Scenarios
A1: SCENARIO ANALYSIS
A4: Metric | B4: Pessimistic | C4: Base | D4: Optimistic | E4: Notes
A5: Events per year | B5: 128 | C5: =IFERROR(IF('3-Year P&L'!$B$6="","",'3-Year P&L'!$B$6),"") -> 170 | D5: 212
A6: Average price per guest (excl. sales tax) | B6: 11.34 | C6: =IFERROR(IF('3-Year P&L'!$B$7="","",'3-Year P&L'!$B$7),"") -> 12.6 | D6: 13.86
A7: Average guests per event | B7: 86 | C7: =IFERROR(IF('3-Year P&L'!$B$8="","",'3-Year P&L'!$B$8),"") -> 95 | D7: 105
A8: ANNUAL REVENUE (excl. sales tax) | B8: =IFERROR(IF(B5*B6*B7=0,"",B5*B6*B7),"") -> 124830.72 | C8: =IFERROR(IF(C5*C6*C7=0,"",C5*C6*C7),"") -> 203490 | D8: =IFERROR(IF(D5*D6*D7=0,"",D5*D6*D7),"") -> 308523.6
A9: Cost of goods — coffee bar packages (beans, milks, syrups, cold brew) | B9: =IFERROR(IF(B8="","",B8*'0. Assumptions'!$B$11*'0. Assumptions'!$B$13),"") -> 12732.733 | C9: =IFERROR(IF(C8="","",C8*'0. Assumptions'!$B$11*'0. Assumptions'!$B$13),"") -> 20755.98 | D9: =IFERROR(IF(D8="","",D8*'0. Assumptions'!$B$11*'0. Assumptions'!$B$13),"") -> 31469.407
A10: Cost of goods — add-ons | B10: =IFERROR(IF(B8="","",B8*'0. Assumptions'!$B$12*'0. Assumptions'!$B$14),"") -> 4681.152 | C10: =IFERROR(IF(C8="","",C8*'0. Assumptions'!$B$12*'0. Assumptions'!$B$14),"") -> 7630.875 | D10: =IFERROR(IF(D8="","",D8*'0. Assumptions'!$B$12*'0. Assumptions'!$B$14),"") -> 11569.635
A11: Compostable cups, lids, sleeves & napkins | B11: =IFERROR(IF(B8="","",B8*'0. Assumptions'!$B$15),"") -> 4993.2288 | C11: =IFERROR(IF(C8="","",C8*'0. Assumptions'!$B$15),"") -> 8139.6 | D11: =IFERROR(IF(D8="","",D8*'0. Assumptions'!$B$15),"") -> 12340.944
A12: Festival & market organizer fees | B12: =IFERROR(IF(B8="","",B8*'0. Assumptions'!$B$16*'0. Assumptions'!$B$17),"") -> 936.2304 | C12: =IFERROR(IF(C8="","",C8*'0. Assumptions'!$B$16*'0. Assumptions'!$B$17),"") -> 1526.175 | D12: =IFERROR(IF(D8="","",D8*'0. Assumptions'!$B$16*'0. Assumptions'!$B$17),"") -> 2313.927
A13: Card processing fees | B13: =IFERROR(IF(B8="","",B8*'0. Assumptions'!$B$18),"") -> 3744.9216 | C13: =IFERROR(IF(C8="","",C8*'0. Assumptions'!$B$18),"") -> 6104.7 | D13: =IFERROR(IF(D8="","",D8*'0. Assumptions'!$B$18),"") -> 9255.708
A14: Miscellaneous and contingency | B14: =IFERROR(IF(B8="","",B8*'0. Assumptions'!$B$28),"") -> 3744.9216 | C14: =IFERROR(IF(C8="","",C8*'0. Assumptions'!$B$28),"") -> 6104.7 | D14: =IFERROR(IF(D8="","",D8*'0. Assumptions'!$B$28),"") -> 9255.708
A15: TOTAL VARIABLE COSTS | B15: =IFERROR(IF(B8="","",SUM(B9:B14)),"") -> 30833.188 | C15: =IFERROR(IF(C8="","",SUM(C9:C14)),"") -> 50262.03 | D15: =IFERROR(IF(D8="","",SUM(D9:D14)),"") -> 76205.329
A16: GROSS MARGIN | B16: =IFERROR(IF(B8="","",B8-B15),"") -> 93997.532 | C16: =IFERROR(IF(C8="","",C8-C15),"") -> 153227.97 | D16: =IFERROR(IF(D8="","",D8-D15),"") -> 232318.27
A17: FIXED COSTS (the P&L's) | B17: =IFERROR(IF(B8="","",'3-Year P&L'!$B$38),"") -> 126345.09 | C17: =IFERROR(IF(C8="","",'3-Year P&L'!$B$38),"") -> 126345.09 | D17: =IFERROR(IF(D8="","",'3-Year P&L'!$B$38),"") -> 126345.09 | E17: Fixed costs do not change with the scenario: that is why they are fixed
A18: PRE-TAX INCOME (EBT) | B18: =IFERROR(IF(B8="","",B16-B17),"") -> -32347.554 | C18: =IFERROR(IF(C8="","",C16-C17),"") -> 26882.884 | D18: =IFERROR(IF(D8="","",D16-D17),"") -> 105973.19
A19: Income tax | B19: =IFERROR(IF(B8="","",MAX(0,B18-'0. Assumptions'!$B$42)*'0. Assumptions'!$B$37),"") -> 0 | C19: =IFERROR(IF(C8="","",MAX(0,C18-'0. Assumptions'!$B$42)*'0. Assumptions'!$B$37),"") -> 6720.7211 | D19: =IFERROR(IF(D8="","",MAX(0,D18-'0. Assumptions'!$B$42)*'0. Assumptions'!$B$37),"") -> 26493.296 | E19: At the "years 1-2" effective income tax rate, offsetting prior net operating losses
A20: NET INCOME | B20: =IFERROR(IF(B8="","",B18-B19),"") -> -32347.554 | C20: =IFERROR(IF(C8="","",C18-C19),"") -> 20162.163 | D20: =IFERROR(IF(D8="","",D18-D19),"") -> 79479.889
A21: Events per year to break even | B21: =IFERROR(IF(B8="","",IF(B6-B15/(B5*B7)<=0,"",B17/(B6-B15/(B5*B7))/B7)),"") -> 172.04889 | C21: =IFERROR(IF(C8="","",IF(C6-C15/(C5*C7)<=0,"",C17/(C6-C15/(C5*C7))/C7)),"") -> 140.17457 | D21: =IFERROR(IF(D8="","",IF(D6-D15/(D5*D7)<=0,"",D17/(D6-D15/(D5*D7))/D7)),"") -> 115.2951
A22: WHAT EACH SCENARIO DEMANDS
A23: Labor cost / Sales | B23: =IFERROR(IF(B8="","",'3-Year P&L'!$B$23/B8),"") -> 0.59681463 | C23: =IFERROR(IF(C8="","",'3-Year P&L'!$B$23/C8),"") -> 0.36611529 | D23: =IFERROR(IF(D8="","",'3-Year P&L'!$B$23/D8),"") -> 0.24147521 | E23: The SAME staffing in all three scenarios. In the pessimistic case your real event-staff cost falls with the number of events (you pay hours per event), so the real result would be somewhat better than shown. If labor cost still blows up, adjust it in the "Staffing" tab, not here
A24: Guests per year per full-time equivalent | B24: =IFERROR(IF(B8="","",B5*B7/Staffing!$C$9),"") -> 7148.0519 | C24: =IFERROR(IF(C8="","",C5*C7/Staffing!$C$9),"") -> 10487.013 | D24: =IFERROR(IF(D8="","",D5*D7/Staffing!$C$9),"") -> 14454.545 | E24: Guests each full-time equivalent in the "Staffing" table would have to serve in a year. In the optimistic scenario it tells you whether you need to hire
A25: Year-1 closing cash balance (estimate, same method in all three scenarios) | B25: =IFERROR(IF(B8="","",'Startup Costs'!$B$25+B20+'3-Year P&L'!$B$36-Financing!$B$45),"") -> -486.85832 | C25: =IFERROR(IF(C8="","",'Startup Costs'!$B$25+C20+'3-Year P&L'!$B$36-Financing!$B$45),"") -> 52022.858 | D25: =IFERROR(IF(D8="","",'Startup Costs'!$B$25+D20+'3-Year P&L'!$B$36-Financing!$B$45),"") -> 111340.58 | E25: ESTIMATED balance: working capital plus the year's result, adding back depreciation (which is not paid) and subtracting loan principal. It does not include the timing gap between receipts and payments or the sales tax settlement, so the three columns can be compared with each other. In red, the scenario runs out of cash
A26: Actual month-12 balance from the 12-Month Cash Flow tab (Base case only) | C26: =IFERROR(IF(C8="","",'12-Month Cash Flow'!$M$22),"") -> 54257.173 | E26: The ACTUAL base-case balance, with its timing of receipts and payments and its sales tax settlement. It exists only for the Base scenario, the only one with its own monthly cash flow: that is why it is not in the row above, where it would be compared against two estimates
A28: The "Base" column reads its three inputs (events per year, price per guest and guests per event) from the "0. Assumptions" tab, so it reproduces EXACTLY year 1 of the P&L. The other two scenarios use the same cost rates: only events, price and guests change. FIXED COSTS are the same in all three, while variable costs follow the sales of each scenario.

Sheet Staffing
A1: STAFFING STRUCTURE AND COSTS
A2: =IFERROR("Payroll — "&TEXT('0. Assumptions'!$B$21,"0")&" pay periods + employer taxes "&TEXT('0. Assumptions'!$B$20*100,"0")&"%","") -> Payroll — 12 pay periods + employer taxes 10%
A4: Position | B4: People | C4: FTE | D4: Gross pay per month (total for the position) | E4: Employer payroll taxes (total for the position) | F4: Cost per month (total for the position) | G4: Cost per year | H4: Hours per week per person | I4: Hours per year for the position | J4: Notes
A5: Owner / Lead Barista & Sales | B5: 1 | C5: 1 | D5: 3813 | E5: =IFERROR(IF(D5="","",D5*'0. Assumptions'!$B$20),"") -> 381.3 | F5: =IFERROR(IF(D5="","",D5+E5),"") -> 4194.3 | G5: =IFERROR(IF(D5="","",F5*MAX(12,'0. Assumptions'!$B$21)),"") -> 50331.6 | H5: =IFERROR(IF(D5="","",C5*$B$16),"") -> 40 | I5: =IFERROR(IF(D5="","",H5*B5*$B$17),"") -> 2000 | J5: Sells to companies and couples, runs the tastings and works the espresso bar at the events. Covers the main shift at every event. The rest of the owner's pay comes from profit.
A6: Lead barista (part-time W-2) | B6: 1 | C6: 0.3 | D6: 1040 | E6: =IFERROR(IF(D6="","",D6*'0. Assumptions'!$B$20),"") -> 104 | F6: =IFERROR(IF(D6="","",D6+E6),"") -> 1144 | G6: =IFERROR(IF(D6="","",F6*MAX(12,'0. Assumptions'!$B$21)),"") -> 13728 | H6: =IFERROR(IF(D6="","",C6*$B$16),"") -> 12 | I6: =IFERROR(IF(D6="","",H6*B6*$B$17),"") -> 600 | J6: Lead barista, part-time W-2: runs the second station and the second event of the day. Paid at or above the pay floor in proportion to FTE, around the 90th percentile of occupation 35-3023 (BLS OEWS, May 2025: $20.51 per hour) because event baristas earn more ($20-35 per hour at grindkit.app).
A7: Event baristas (hourly W-2) | B7: 2 | C7: 0.08 | D7: 527 | E7: =IFERROR(IF(D7="","",D7*'0. Assumptions'!$B$20),"") -> 52.7 | F7: =IFERROR(IF(D7="","",D7+E7),"") -> 579.7 | G7: =IFERROR(IF(D7="","",F7*MAX(12,'0. Assumptions'!$B$21)),"") -> 6956.4 | H7: =IFERROR(IF(D7="","",C7*$B$16),"") -> 3.2 | I7: =IFERROR(IF(D7="","",H7*B7*$B$17),"") -> 320 | J7: Event baristas hired per event and paid hourly as W-2 employees, with one barista for every 50-65 drinks an hour (Flashquotes). Their FTE is a fraction because they only work event hours. Treating them as 1099 contractors is a misclassification risk (FLSA; California AB5). Paid at or above the pay floor in proportion to FTE. Voluntary tips are theirs.
A8: On-call barista / driver (hourly W-2, peak months) | B8: 1 | C8: 0.08 | D8: 264 | E8: =IFERROR(IF(D8="","",D8*'0. Assumptions'!$B$20),"") -> 26.4 | F8: =IFERROR(IF(D8="","",D8+E8),"") -> 290.4 | G8: =IFERROR(IF(D8="","",F8*MAX(12,'0. Assumptions'!$B$21)),"") -> 3484.8 | H8: =IFERROR(IF(D8="","",C8*$B$16),"") -> 3.2 | I8: =IFERROR(IF(D8="","",H8*B8*$B$17),"") -> 160 | J8: On-call barista and driver, hourly W-2: reinforces the team in March-May and December, loads the trailer and tows it to the venue. Paid at or above the pay floor in proportion to FTE.
A9: TOTAL STAFF | B9: =IFERROR(IF(COUNT(D5:D8)=0,"",SUM(B5:B8)),"") -> 5 | C9: =IFERROR(IF(COUNT(D5:D8)=0,"",SUMPRODUCT(B5:B8,C5:C8)),"") -> 1.54 | D9: =IFERROR(IF(COUNT(D5:D8)=0,"",SUM(D5:D8)),"") -> 5644 | E9: =IFERROR(IF(COUNT(D5:D8)=0,"",SUM(E5:E8)),"") -> 564.4 | F9: =IFERROR(IF(COUNT(D5:D8)=0,"",SUM(F5:F8)),"") -> 6208.4 | G9: =IFERROR(IF(COUNT(D5:D8)=0,"",SUM(G5:G8)),"") -> 74500.8 | I9: =IFERROR(IF(COUNT(D5:D8)=0,"",SUM(I5:I8)),"") -> 3080
A10: STAFF GROWTH (stepped cost)
A11: Annual cost of year-2 hires | B11: 3000 | J11: FULL ANNUAL cost (gross pay + employer payroll taxes, over all pay periods) of whoever you hire that year. The P&L adds it to the previous year's cost: staffing grows by people, not by a percentage
A12: Annual cost of year-3 hires | B12: 3000 | J12: FULL ANNUAL cost (gross pay + employer payroll taxes, over all pay periods) of whoever you hire that year. The P&L adds it to the previous year's cost: staffing grows by people, not by a percentage
A13: Labor cost, year 2 | B13: =IFERROR(IF(G9="","",G9*(1+'0. Assumptions'!$B$48)+B11),"") -> 77500.8
A14: Labor cost, year 3 | B14: =IFERROR(IF(B13="","",B13*(1+'0. Assumptions'!$B$48)+B12),"") -> 80500.8
A15: COVERAGE OF EVENT HOURS
A16: Full-time week (hours per week) | B16: 40 | J16: 40 hours a week is the FLSA overtime threshold for non-exempt employees; some states add daily overtime rules. Change it if your own full-time week is different
A17: Weeks worked per year per person | B17: 50 | J17: 50 weeks: 52 minus about two weeks of vacation, holidays and average absences. There is no federal vacation requirement in the US: adjust it to your own policy
A18: Hours per person per event (loading at the commissary, travel, setup, service, breakdown, cleaning) | B18: 7 | J18: Hours of work per person for one event: loading at the commissary, travel, about one hour of setup, 2-2.5 hours of service, and breakdown and cleanup. A 2-hour event takes 7-9 hours of shift (grindkit.app). Serving is only part of it. Hours × people × events per year sets the event staff cost.
A19: Baristas per event (average) | B19: 1.6 | J19: Average number of baristas working each event: 1 at small parties and quiet festivals, 2 at weddings and large company events (Kit estimate from 50-65 drinks per barista per hour). Weighted by the mix in the Word plan, the average is about 1.6. Raise it if you staff more heavily: the staffing sizes itself.
A20: Event hours to cover per year | B20: =IFERROR(IF(OR(B18="",B19="",'0. Assumptions'!$B$4=""),"",B18*B19*'0. Assumptions'!$B$4),"") -> 1904
A21: Hours hired per year | B21: =IFERROR(IF(I9="","",I9),"") -> 3080
A22: Coverage (hired / needed) | B22: =IFERROR(B21/B20,"") -> 1.6176471 | J22: Below 100% the staff cannot cover the hours the plan declares: either hire more or cut the hours
A24: Columns D-G are TOTALS for the row. Event baristas are hourly W-2 employees with payroll taxes and workers' comp: paying them as 1099 contractors is a misclassification risk (FLSA; California AB5). One barista serves about 50-65 drinks an hour.
A25: The pay floor is the HIGHER of the federal minimum wage and your state / local minimum wage, both in the "0. Assumptions" tab; part-time positions get it in proportion. There is no single national table above the federal floor: the state / local cell is delivered empty so you can enter the rate for your state and city.

Sheet Instructions
A1: HOW TO USE THIS WORKBOOK — Coffee Cart Financial Projections
A3: HOW TO USE THIS WORKBOOK
A4: This financial plan is a MODEL: you type only in the GREEN cells and everything else recalculates on its own.
A5: 1. "0. Assumptions" is the control sheet: events per year, price per guest excl. sales tax, guests per event, the mix of coffee bar packages and add-ons, cost of goods sold, commissary and cart storage, financing and taxes.
A6: 2. Startup cost items, fixed costs and staffing are typed in their own tab, also in green. No number is typed twice.
A7: 3. Only "Break-Even" is derived entirely from the rest. The other three tabs also have green cells you can edit: the pessimistic and optimistic scenarios in "Scenarios", seasonality and the launch ramp-up in "12-Month Cash Flow", and the other funding sources in "Financing" (rows 8-11 count as sources but are not amortized: your bank or SBA 7(a) loan goes in "Loan requested" on "0. Assumptions"). Everything else is calculated.
A8: 4. All figures are EXCL. SALES TAX. To turn a quoted price into a price excl. sales tax, divide it by 1 + your sales tax rate (with an 8% rate, divide by 1.08); if an item is taxed at a different rate in your state, use that rate. In many states the whole catering invoice is taxable, including staff and rentals; check yours. The rate of each sales line is in the "Sales tax rate on the line (%)" column of the P&L, and from it come the receipts, the sales tax collected and the equivalent price per guest incl. sales tax. With the default 0% recoverable input tax, the sales tax you pay on purchases and startup costs is treated as a cost; in the UK, enter 20% if you are VAT-registered.
A9: 5. If you change the staffing, the P&L reads it on its own: labor cost comes from the "Staffing" tab, not from a separate estimate.
A10: 6. The "12-Month Cash Flow" tab answers the question that decides a bank deal: in which month the cash runs out. The minimum balance of the year can never be in red.
A11: 7. The "Financing" tab matches what you need with what you put in and builds the amortization schedule of the loan. If the difference is red, the plan is not funded.
A12: 8. The Word business plan in this kit uses the same example figures as this workbook. The workbook is the one that recalculates on its own when you change a green cell: if you change one, update the matching figures in the Word document.
A14: RATIOS AUDITED BY THIS WORKBOOK
A15: Thresholds live in the "Threshold" column of the KEY RATIOS block of the P&L: change them there and the traffic light changes with them.
A17: Ratio | B17: Year 1 value | C17: Threshold | D17: Status
A18: Cost of goods sold / Sales | B18: =IFERROR(IF('3-Year P&L'!$B$53="","",'3-Year P&L'!$B$53),"") -> 0.1395 | C18: =IFERROR(IF('3-Year P&L'!$E$53="","",'3-Year P&L'!$E$53),"") -> 0.2 | D18: =IFERROR(IF(OR(B18="",C18=""),"",IF(B18<=C18,"OK","REVIEW")),"") -> OK
A19: Labor cost / Sales | B19: =IFERROR(IF('3-Year P&L'!$B$54="","",'3-Year P&L'!$B$54),"") -> 0.36611529 | C19: =IFERROR(IF('3-Year P&L'!$E$54="","",'3-Year P&L'!$E$54),"") -> 0.4 | D19: =IFERROR(IF(OR(B19="",C19=""),"",IF(B19<=C19,"OK","REVIEW")),"") -> OK
A20: Commissary & cart storage / Sales | B20: =IFERROR(IF('3-Year P&L'!$B$55="","",'3-Year P&L'!$B$55),"") -> 0.04127967 | C20: =IFERROR(IF('3-Year P&L'!$E$55="","",'3-Year P&L'!$E$55),"") -> 0.06 | D20: =IFERROR(IF(OR(B20="",C20=""),"",IF(B20<=C20,"OK","REVIEW")),"") -> OK
A21: Net income / Sales | B21: =IFERROR(IF('3-Year P&L'!$B$56="","",'3-Year P&L'!$B$56),"") -> 0.099081838 | C21: =IFERROR(IF('3-Year P&L'!$E$56="","",'3-Year P&L'!$E$56),"") -> 0.05 | D21: =IFERROR(IF(OR(B21="",C21=""),"",IF(B21>=C21,"OK","REVIEW")),"") -> OK
A22: Gross margin / Sales | B22: =IFERROR(IF('3-Year P&L'!$B$51="","",'3-Year P&L'!$B$51),"") -> 0.753 | C22: =IFERROR(IF('3-Year P&L'!$E$51="","",'3-Year P&L'!$E$51),"") -> 0.72 | D22: =IFERROR(IF(OR(B22="",C22=""),"",IF(B22>=C22,"OK","REVIEW")),"") -> OK
A24: THIS PLAN'S KEY FIGURES
A25: Total startup costs (sum of the blocks) | B25: =IFERROR(IF('Startup Costs'!$B$26="","",'Startup Costs'!$B$26),"") -> 100290.2
A26: Total cash needed at launch | B26: =IFERROR(IF('Startup Costs'!$B$29="","",'Startup Costs'!$B$29),"") -> 100290.2
A27: Working capital funded | B27: =IFERROR(IF('Startup Costs'!$B$25="","",'Startup Costs'!$B$25),"") -> 29000.2
A28: Forecast year-1 revenue | B28: =IFERROR(IF('3-Year P&L'!$B$9="","",'3-Year P&L'!$B$9),"") -> 203490
A29: Year-1 net income | B29: =IFERROR(IF('3-Year P&L'!$B$48="","",'3-Year P&L'!$B$48),"") -> 20162.163
A30: Events per year for the ACCOUNTING break-even (depreciation included) | B30: =IFERROR(IF('Break-Even'!$B$15="","",'Break-Even'!$B$15),"") -> 140.17457
A31: Project payback (years), before debt | B31: =IFERROR(IF('12-Month Cash Flow'!$B$31="","",'12-Month Cash Flow'!$B$31),"") -> 2.3
A33: WHY THIS MODEL IS BUILT THIS WAY
A34: Item | B34: Common shortcut | C34: This workbook | D34: Why
A35: Labor cost in the P&L | B35: A typed-in number that does not match the Staffing tab | C35: Read directly from the Staffing tab | D35: If you change a salary, the whole plan recalculates, so the P&L and the staffing table can never disagree.
A36: Staffing | B36: One line called "staff", with no link to event hours or pay floors | C36: Positions with their FTE, sized to the hours your events need, with event staff paid per event | D36: A plan staffed for fewer hours than it sells does not work on its own numbers. This layout makes that gap visible before a lender does.
A37: Events, guests and price | B37: Sales typed as one lump sum, with no link to bookings | C37: Revenue = events per year × guests per event × price per guest, one cell each for the whole workbook | D37: Break-even, scenarios and the P&L read the same three cells, so they always agree, and you can see which lever moves the result: more events, bigger events or a higher price.
A38: Price per guest | B38: A price with no statement of whether sales tax or service is included | C38: Declared EXCL. sales tax, with service included and the voluntary gratuity left out | D38: Declaring it changes no number: it just says what the number is. Price per guest incl. sales tax = price per guest × (1 + sales tax rate), and the workbook calculates it for you.
A39: Commissary, cart storage and trailer parking | B39: Left out: the model shows no cost of space | C39: A monthly cost for the commissary, cart storage and trailer parking, plus a deposit and rent for the months before opening | D39: The coffee is brewed at the event, but the water, the milk and the cart need a permitted commissary to start from and come back to. Leaving it out makes the business look like it has no occupancy cost.
A40: Working capital | B40: A round number labeled "3 months" that does not match the fixed costs | C40: Three months of cash fixed costs, calculated by formula | D40: A round number often covers far less than the label says. This cushion is what keeps you open through the summer dip, when July and August bookings fall well below the rest of the year.
A41: Depreciation | B41: One useful life for everything, including items that are not fixed assets | C41: Two useful lives: the cart, portable bar, trailer and their fit-out on one, and the espresso machines, grinders, generator and other equipment on the other. The Startup Costs tab calculates the annual charge. | D41: The cart, bar and trailer wear out at a different speed than the machines, grinders and generator. Working capital, opening inventory and launch marketing are not fixed assets, so they are not depreciated.
A42: Trailer and equipment insurance, and liability | B42: Counted twice: once in startup costs and again as an annual expense | C42: Counted once, as an annual expense | D42: Counting a premium in both places inflates the startup costs, the cash you need to raise and the loan you ask for.
A43: Generator fuel | B43: A separate fuel line, on top of utilities | C43: Included in the utilities line, in one monthly cell | D43: Generator fuel, water and ice rise and fall with how many events are outdoors: here they live in one cell, and the rest of the workbook follows.
A44: Startup contingency | B44: A lump sum typed by hand | C44: A percentage calculated on the cart, portable bar, trailer, wrap and plan review lines | D44: If you change the cart price, the contingency recalculates instead of staying at the old amount.
A45: Income tax | B45: A flat rate every year, with no offset for losses | C45: One effective rate for years 1-2 and another from year 3, offsetting net operating losses carried forward | D45: A loss in one year reduces taxable profit in later years. The model offsets losses fully as a simplification (federal rules cap the offset at 80% of taxable income). If you operate as a pass-through (sole proprietorship or LLC), set the rate to 0 and budget your personal tax separately.
... A51: Wages and minimum wage | B51: Wages never compared with any legal floor | C51: No row below the pay floor in proportion to its FTE, and a cell for your state or local minimum wage | D51: State and local minimums are often higher than the federal one: enter yours in "0. Assumptions" and the traffic light warns you when a wage falls short.
A53: US COFFEE CART & COFFEE CATERING BENCHMARKS (sourced) AND KIT ESTIMATES
A54: Benchmark | B54: Value | C54: Source | D54: Note
A55: Coffee cart price per booking | B55: Median $1,040; P25 $764; P75 $1,697 | C55: flashquotes.com | D55: Typical event: 100 guests. P10 $612, P90 $3,000. Based on 25,860 bookings from 578 operators (April 2023 to April 2026). Your price depends on hours, guests and market.
A56: Price per guest by event size | B56: Under 50 guests about $38; 50-99 about $18; 100-249 about $13; 250-499 about $11 | C56: flashquotes.com; grindkit.app | D56: GrindKit calls $5-11 per guest at 100 guests healthy and anything under $5 a loss. Price per guest drops as events get bigger.
A57: Drinks per guest | B57: Up to 2 hours 1.0; 2-4 hours 1.3-1.5; 4-6 hours 1.5-1.8; 6+ hours 2.0-2.5 | C57: grindkit.app | D57: Add 20-30% for morning events. At a festival, count each drink sold as one guest.
A58: Mobile food unit permit (one county) | B58: Plan review $1,100; annual permit $500, $745 or $1,025 by risk level | C58: snohd.org | D58: Snohomish County, WA, as an example: electrical approval comes first. Fees and rules differ by county, so ask yours before you buy a cart.
A59: Drinks per hour | B59: 1 cart with 1 barista 50-65; 2 carts with 2 baristas about 100 | C59: flashquotes.com; coffeecartboys.com | D59: Flashquotes suggests 2-3 baristas for about 250 guests, and Coffee Cart Boys cites 50 cups per hour. The "Staffing" tab uses this pace to size your crew.
A60: Cost per drink, all in | B60: $0.75-1.50 | C60: grindkit.app | D60: Double shot $0.25-0.45, milk $0.20-0.40, oat milk $0.60-1.10, cup and lid $0.20-0.45. Cost of goods runs 20-30% of drink revenue.
A61: Startup cost of a coffee cart | B61: $5,000-25,000 for a cart; a 2-group machine about $8,500 | C61: cart-king.com; Kit estimate | D61: Cart-king.com lists a typical cart at $24,000 and a premium one at $49,000. The $5,000-25,000 range and the machine price (store price) are Kit estimates.
A62: Coffee and milk prices | B62: Ground coffee $9.33 per lb; whole milk $4.11 per gal | C62: bls.gov | D62: National averages for September 2026 (series APU0000717311 and APU0000709112). Wholesale specialty coffee runs about $18 per lb (Kit estimate).
A63: Price structure | B63: Base fee $300-500 plus $150-200 per service hour; travel fee $1.25 per mile round trip | C63: flashquotes.com; grindkit.app | D63: Operators ask for a retainer of 30-50% to hold the date and the balance 14 days before the event. The kit's contract applies the retainer to the price.
A64: Hourly wage, occupation 35-3023 | B64: Median $15.00; P75 $17.34; P90 $20.51 (BLS OEWS, May 2025) | C64: bls.gov; grindkit.app | D64: BLS has no occupation of its own for baristas: they sit inside 35-3023, Fast Food and Counter Workers. Event baristas earn more, $20-35 per hour at grindkit.app.
A65: Shared kitchen rate | B65: $15-$45 per hour | C65: thefoodcorridor.com | D65: 2023 Shared Kitchen Operator Survey; 42% of operators charge $20-$29 per hour. A cart pays mostly for storage and water access, $200-600 per month (cart-king.com), and not every kitchen lets you park a trailer on site.
... A68: Close rate and lead time | B68: 20-30% of quotes become bookings; median 41 days' notice | C68: flashquotes.com | D68: A close rate above 30% suggests your prices are too low. The 41-day median is why the launch ramp in "0. Assumptions" starts slowly.
A70: To edit a cell that is not green: Review → Unprotect Sheet (there is no password).
A71: More templates and kits in the catalog at aichef.pro/en/digital-products
A72: Designed by John Guerrero — chef and restaurant consultant since 2010, in the kitchen since age 17 · johnguerrero.es
A73: Version 2.2 · October 2026 · aichef.pro/en/digital-products/coffee-cart-business-plan · info@aichef.pro
A74: Planning tool, not financial, tax or legal advice. Requirements vary by state, county and city — check with your accountant and local authorities.

Sheet 12-Month Cash Flow
A1: CASH FLOW FORECAST — YEAR 1
A2: The P&L tells you whether the business makes money; this tab tells you whether you have cash left to get to the end of the month. It is the first one a lender looks at.
A4: Item | B4: Month 1 | C4: Month 2 | D4: Month 3 | E4: Month 4 | F4: Month 5 | G4: Month 6 | H4: Month 7 | I4: Month 8 | J4: Month 9 | K4: Month 10 | L4: Month 11 | M4: Month 12 | N4: Year
A5: Monthly seasonality (adds up to 100%) | B5: 0.111 | C5: 0.108 | D5: 0.109 | E5: 0.059 | F5: 0.038 | G5: 0.053 | H5: 0.073 | I5: 0.095 | J5: 0.079 | K5: 0.117 | L5: 0.07 | M5: 0.088 | N5: =IFERROR(IF('3-Year P&L'!$B$9="","",SUM(B5:M5)),"") -> 1 | O5: Share of the year's events per month (100% in total). Month 1 = opening month (March in the example); July is the slowest month for coffee carts. The retainer is not modeled: it improves real cash.
A6: Launch ramp-up (% of steady-state activity) | B6: =IFERROR(IF('3-Year P&L'!$B$9="","",MIN(1,'0. Assumptions'!$B$52+(1-'0. Assumptions'!$B$52)*0/MAX(1,'0. Assumptions'!$B$53-1))),"") -> 0.45 | C6: =IFERROR(IF('3-Year P&L'!$B$9="","",MIN(1,'0. Assumptions'!$B$52+(1-'0. Assumptions'!$B$52)*1/MAX(1,'0. Assumptions'!$B$53-1))),"") -> 0.51875 | D6: =IFERROR(IF('3-Year P&L'!$B$9="","",MIN(1,'0. Assumptions'!$B$52+(1-'0. Assumptions'!$B$52)*2/MAX(1,'0. Assumptions'!$B$53-1))),"") -> 0.5875 | E6: =IFERROR(IF('3-Year P&L'!$B$9="","",MIN(1,'0. Assumptions'!$B$52+(1-'0. Assumptions'!$B$52)*3/MAX(1,'0. Assumptions'!$B$53-1))),"") -> 0.65625 | F6: =IFERROR(IF('3-Year P&L'!$B$9="","",MIN(1,'0. Assumptions'!$B$52+(1-'0. Assumptions'!$B$52)*4/MAX(1,'0. Assumptions'!$B$53-1))),"") -> 0.725 | G6: =IFERROR(IF('3-Year P&L'!$B$9="","",MIN(1,'0. Assumptions'!$B$52+(1-'0. Assumptions'!$B$52)*5/MAX(1,'0. Assumptions'!$B$53-1))),"") -> 0.79375 | H6: =IFERROR(IF('3-Year P&L'!$B$9="","",MIN(1,'0. Assumptions'!$B$52+(1-'0. Assumptions'!$B$52)*6/MAX(1,'0. Assumptions'!$B$53-1))),"") -> 0.8625 | I6: =IFERROR(IF('3-Year P&L'!$B$9="","",MIN(1,'0. Assumptions'!$B$52+(1-'0. Assumptions'!$B$52)*7/MAX(1,'0. Assumptions'!$B$53-1))),"") -> 0.93125 | J6: =IFERROR(IF('3-Year P&L'!$B$9="","",MIN(1,'0. Assumptions'!$B$52+(1-'0. Assumptions'!$B$52)*8/MAX(1,'0. Assumptions'!$B$53-1))),"") -> 1 | K6: =IFERROR(IF('3-Year P&L'!$B$9="","",MIN(1,'0. Assumptions'!$B$52+(1-'0. Assumptions'!$B$52)*9/MAX(1,'0. Assumptions'!$B$53-1))),"") -> 1 | L6: =IFERROR(IF('3-Year P&L'!$B$9="","",MIN(1,'0. Assumptions'!$B$52+(1-'0. Assumptions'!$B$52)*10/MAX(1,'0. Assumptions'!$B$53-1))),"") -> 1 | M6: =IFERROR(IF('3-Year P&L'!$B$9="","",MIN(1,'0. Assumptions'!$B$52+(1-'0. Assumptions'!$B$52)*11/MAX(1,'0. Assumptions'!$B$53-1))),"") -> 1 | O6: Rises in a straight line from the month-1 percentage to 100% over the number of months you set in Assumptions. With month 1 at 100%, the ramp disappears
A7: Split of activity by month (calculated) | B7: =IFERROR(IF('3-Year P&L'!$B$9="","",B5*B6/SUMPRODUCT($B$5:$M$5,$B$6:$M$6)),"") -> 0.063729516 | C7: =IFERROR(IF('3-Year P&L'!$B$9="","",C5*C6/SUMPRODUCT($B$5:$M$5,$B$6:$M$6)),"") -> 0.071480403 | D7: =IFERROR(IF('3-Year P&L'!$B$9="","",D5*D6/SUMPRODUCT($B$5:$M$5,$B$6:$M$6)),"") -> 0.081703281 | E7: =IFERROR(IF('3-Year P&L'!$B$9="","",E5*E6/SUMPRODUCT($B$5:$M$5,$B$6:$M$6)),"") -> 0.049399944 | F7: =IFERROR(IF('3-Year P&L'!$B$9="","",F5*F6/SUMPRODUCT($B$5:$M$5,$B$6:$M$6)),"") -> 0.035150114 | G7: =IFERROR(IF('3-Year P&L'!$B$9="","",G5*G6/SUMPRODUCT($B$5:$M$5,$B$6:$M$6)),"") -> 0.053674096 | H7: =IFERROR(IF('3-Year P&L'!$B$9="","",H5*H6/SUMPRODUCT($B$5:$M$5,$B$6:$M$6)),"") -> 0.080331725 | I7: =IFERROR(IF('3-Year P&L'!$B$9="","",I5*I6/SUMPRODUCT($B$5:$M$5,$B$6:$M$6)),"") -> 0.11287429 | ... M7: =IFERROR(IF('3-Year P&L'!$B$9="","",M5*M6/SUMPRODUCT($B$5:$M$5,$B$6:$M$6)),"") -> 0.11227623 | N7: =IFERROR(IF('3-Year P&L'!$B$9="","",SUM(B7:M7)),"") -> 1 | O7: Seasonality × ramp-up, normalized to 100%: the YEAR brings in what the P&L says, but split the way a business that has just opened would split it
A8: CASH IN
A9: Sales collected (incl. sales tax collected) | B9: =IFERROR(IF('3-Year P&L'!$B$9="","",('3-Year P&L'!$B$9+'3-Year P&L'!$B$9*SUMPRODUCT('3-Year P&L'!$E$10:$E$11,'3-Year P&L'!$G$10:$G$11))*B7*(1-MIN(30,'0. Assumptions'!$B$58)/30)),"") -> 7469.7519 | C9: =IFERROR(IF('3-Year P&L'!$B$9="","",('3-Year P&L'!$B$9+'3-Year P&L'!$B$9*SUMPRODUCT('3-Year P&L'!$E$10:$E$11,'3-Year P&L'!$G$10:$G$11))*(C7*(1-MIN(30,'0. Assumptions'!$B$58)/30)+B7*MIN(30,'0. Assumptions'!$B$58)/30)),"") -> 14914.268 | D9: =IFERROR(IF('3-Year P&L'!$B$9="","",('3-Year P&L'!$B$9+'3-Year P&L'!$B$9*SUMPRODUCT('3-Year P&L'!$E$10:$E$11,'3-Year P&L'!$G$10:$G$11))*(D7*(1-MIN(30,'0. Assumptions'!$B$58)/30)+C7*MIN(30,'0. Assumptions'!$B$58)/30)),"") -> 16907.417 | E9: =IFERROR(IF('3-Year P&L'!$B$9="","",('3-Year P&L'!$B$9+'3-Year P&L'!$B$9*SUMPRODUCT('3-Year P&L'!$E$10:$E$11,'3-Year P&L'!$G$10:$G$11))*(E7*(1-MIN(30,'0. Assumptions'!$B$58)/30)+D7*MIN(30,'0. Assumptions'!$B$58)/30)),"") -> 14169.583 | F9: =IFERROR(IF('3-Year P&L'!$B$9="","",('3-Year P&L'!$B$9+'3-Year P&L'!$B$9*SUMPRODUCT('3-Year P&L'!$E$10:$E$11,'3-Year P&L'!$G$10:$G$11))*(F7*(1-MIN(30,'0. Assumptions'!$B$58)/30)+E7*MIN(30,'0. Assumptions'!$B$58)/30)),"") -> 9186.3602 | G9: =IFERROR(IF('3-Year P&L'!$B$9="","",('3-Year P&L'!$B$9+'3-Year P&L'!$B$9*SUMPRODUCT('3-Year P&L'!$E$10:$E$11,'3-Year P&L'!$G$10:$G$11))*(G7*(1-MIN(30,'0. Assumptions'!$B$58)/30)+F7*MIN(30,'0. Assumptions'!$B$58)/30)),"") -> 9896.1128 | H9: =IFERROR(IF('3-Year P&L'!$B$9="","",('3-Year P&L'!$B$9+'3-Year P&L'!$B$9*SUMPRODUCT('3-Year P&L'!$E$10:$E$11,'3-Year P&L'!$G$10:$G$11))*(H7*(1-MIN(30,'0. Assumptions'!$B$58)/30)+G7*MIN(30,'0. Assumptions'!$B$58)/30)),"") -> 14920.46 | I9: =IFERROR(IF('3-Year P&L'!$B$9="","",('3-Year P&L'!$B$9+'3-Year P&L'!$B$9*SUMPRODUCT('3-Year P&L'!$E$10:$E$11,'3-Year P&L'!$G$10:$G$11))*(I7*(1-MIN(30,'0. Assumptions'!$B$58)/30)+H7*MIN(30,'0. Assumptions'!$B$58)/30)),"") -> 21468.76 | J9: =IFERROR(IF('3-Year P&L'!$B$9="","",('3-Year P&L'!$B$9+'3-Year P&L'!$B$9*SUMPRODUCT('3-Year P&L'!$E$10:$E$11,'3-Year P&L'!$G$10:$G$11))*(J7*(1-MIN(30,'0. Assumptions'!$B$58)/30)+I7*MIN(30,'0. Assumptions'!$B$58)/30)),"") -> 23390.292 | ... M9: =IFERROR(IF('3-Year P&L'!$B$9="","",('3-Year P&L'!$B$9+'3-Year P&L'!$B$9*SUMPRODUCT('3-Year P&L'!$E$10:$E$11,'3-Year P&L'!$G$10:$G$11))*(M7*(1-MIN(30,'0. Assumptions'!$B$58)/30)+L7*MIN(30,'0. Assumptions'!$B$58)/30)),"") -> 22319.529 | N9: =IFERROR(IF('3-Year P&L'!$B$9="","",SUM(B9:M9)),"") -> 208254.27 | O9: The month's sales plus the sales tax collected, adjusted by the average collection days from the Assumptions tab
A10: CASH OUT
A11: Purchases and variable costs (incl. sales tax) | B11: =IFERROR(IF('3-Year P&L'!$B$9="","",-('3-Year P&L'!$B$13*(1+'3-Year P&L'!$G$13)+'3-Year P&L'!$B$14*(1+'3-Year P&L'!$G$14)+'3-Year P&L'!$B$15*(1+'3-Year P&L'!$G$15)+'3-Year P&L'!$B$16*(1+'3-Year P&L'!$G$16)+'3-Year P&L'!$B$17*(1+'3-Year P&L'!$G$17)+'3-Year P&L'!$B$18*(1+'3-Year P&L'!$G$18))*B7*(1-MIN(30,'0. Assumptions'!$B$59)/30)),"") -> -2455.7674 | C11: =IFERROR(IF('3-Year P&L'!$B$9="","",-('3-Year P&L'!$B$13*(1+'3-Year P&L'!$G$13)+'3-Year P&L'!$B$14*(1+'3-Year P&L'!$G$14)+'3-Year P&L'!$B$15*(1+'3-Year P&L'!$G$15)+'3-Year P&L'!$B$16*(1+'3-Year P&L'!$G$16)+'3-Year P&L'!$B$17*(1+'3-Year P&L'!$G$17)+'3-Year P&L'!$B$18*(1+'3-Year P&L'!$G$18))*(C7*(1-MIN(30,'0. Assumptions'!$B$59)/30)+B7*MIN(30,'0. Assumptions'!$B$59)/30)),"") -> -3501.8493 | D11: =IFERROR(IF('3-Year P&L'!$B$9="","",-('3-Year P&L'!$B$13*(1+'3-Year P&L'!$G$13)+'3-Year P&L'!$B$14*(1+'3-Year P&L'!$G$14)+'3-Year P&L'!$B$15*(1+'3-Year P&L'!$G$15)+'3-Year P&L'!$B$16*(1+'3-Year P&L'!$G$16)+'3-Year P&L'!$B$17*(1+'3-Year P&L'!$G$17)+'3-Year P&L'!$B$18*(1+'3-Year P&L'!$G$18))*(D7*(1-MIN(30,'0. Assumptions'!$B$59)/30)+C7*MIN(30,'0. Assumptions'!$B$59)/30)),"") -> -3986.6808 | E11: =IFERROR(IF('3-Year P&L'!$B$9="","",-('3-Year P&L'!$B$13*(1+'3-Year P&L'!$G$13)+'3-Year P&L'!$B$14*(1+'3-Year P&L'!$G$14)+'3-Year P&L'!$B$15*(1+'3-Year P&L'!$G$15)+'3-Year P&L'!$B$16*(1+'3-Year P&L'!$G$16)+'3-Year P&L'!$B$17*(1+'3-Year P&L'!$G$17)+'3-Year P&L'!$B$18*(1+'3-Year P&L'!$G$18))*(E7*(1-MIN(30,'0. Assumptions'!$B$59)/30)+D7*MIN(30,'0. Assumptions'!$B$59)/30)),"") -> -2861.7888 | F11: =IFERROR(IF('3-Year P&L'!$B$9="","",-('3-Year P&L'!$B$13*(1+'3-Year P&L'!$G$13)+'3-Year P&L'!$B$14*(1+'3-Year P&L'!$G$14)+'3-Year P&L'!$B$15*(1+'3-Year P&L'!$G$15)+'3-Year P&L'!$B$16*(1+'3-Year P&L'!$G$16)+'3-Year P&L'!$B$17*(1+'3-Year P&L'!$G$17)+'3-Year P&L'!$B$18*(1+'3-Year P&L'!$G$18))*(F7*(1-MIN(30,'0. Assumptions'!$B$59)/30)+E7*MIN(30,'0. Assumptions'!$B$59)/30)),"") -> -1933.8353 | G11: =IFERROR(IF('3-Year P&L'!$B$9="","",-('3-Year P&L'!$B$13*(1+'3-Year P&L'!$G$13)+'3-Year P&L'!$B$14*(1+'3-Year P&L'!$G$14)+'3-Year P&L'!$B$15*(1+'3-Year P&L'!$G$15)+'3-Year P&L'!$B$16*(1+'3-Year P&L'!$G$16)+'3-Year P&L'!$B$17*(1+'3-Year P&L'!$G$17)+'3-Year P&L'!$B$18*(1+'3-Year P&L'!$G$18))*(G7*(1-MIN(30,'0. Assumptions'!$B$59)/30)+F7*MIN(30,'0. Assumptions'!$B$59)/30)),"") -> -2480.5233 | H11: =IFERROR(IF('3-Year P&L'!$B$9="","",-('3-Year P&L'!$B$13*(1+'3-Year P&L'!$G$13)+'3-Year P&L'!$B$14*(1+'3-Year P&L'!$G$14)+'3-Year P&L'!$B$15*(1+'3-Year P&L'!$G$15)+'3-Year P&L'!$B$16*(1+'3-Year P&L'!$G$16)+'3-Year P&L'!$B$17*(1+'3-Year P&L'!$G$17)+'3-Year P&L'!$B$18*(1+'3-Year P&L'!$G$18))*(H7*(1-MIN(30,'0. Assumptions'!$B$59)/30)+G7*MIN(30,'0. Assumptions'!$B$59)/30)),"") -> -3725.0001 | I11: =IFERROR(IF('3-Year P&L'!$B$9="","",-('3-Year P&L'!$B$13*(1+'3-Year P&L'!$G$13)+'3-Year P&L'!$B$14*(1+'3-Year P&L'!$G$14)+'3-Year P&L'!$B$15*(1+'3-Year P&L'!$G$15)+'3-Year P&L'!$B$16*(1+'3-Year P&L'!$G$16)+'3-Year P&L'!$B$17*(1+'3-Year P&L'!$G$17)+'3-Year P&L'!$B$18*(1+'3-Year P&L'!$G$18))*(I7*(1-MIN(30,'0. Assumptions'!$B$59)/30)+H7*MIN(30,'0. Assumptions'!$B$59)/30)),"") -> -5291.6379 | J11: =IFERROR(IF('3-Year P&L'!$B$9="","",-('3-Year P&L'!$B$13*(1+'3-Year P&L'!$G$13)+'3-Year P&L'!$B$14*(1+'3-Year P&L'!$G$14)+'3-Year P&L'!$B$15*(1+'3-Year P&L'!$G$15)+'3-Year P&L'!$B$16*(1+'3-Year P&L'!$G$16)+'3-Year P&L'!$B$17*(1+'3-Year P&L'!$G$17)+'3-Year P&L'!$B$18*(1+'3-Year P&L'!$G$18))*(J7*(1-MIN(30,'0. Assumptions'!$B$59)/30)+I7*MIN(30,'0. Assumptions'!$B$59)/30)),"") -> -5207.7643 | ... M11: =IFERROR(IF('3-Year P&L'!$B$9="","",-('3-Year P&L'!$B$13*(1+'3-Year P&L'!$G$13)+'3-Year P&L'!$B$14*(1+'3-Year P&L'!$G$14)+'3-Year P&L'!$B$15*(1+'3-Year P&L'!$G$15)+'3-Year P&L'!$B$16*(1+'3-Year P&L'!$G$16)+'3-Year P&L'!$B$17*(1+'3-Year P&L'!$G$17)+'3-Year P&L'!$B$18*(1+'3-Year P&L'!$G$18))*(M7*(1-MIN(30,'0. Assumptions'!$B$59)/30)+L7*MIN(30,'0. Assumptions'!$B$59)/30)),"") -> -5373.895 | N11: =IFERROR(IF('3-Year P&L'!$B$9="","",SUM(B11:M11)),"") -> -48945.276 | O11: =IFERROR("Coffee, milk and add-on purchases, compostable cups, fees and contingencies, each at ITS tax rate (column G of the P&L; 0 in the US, where the sales tax you pay is part of the cost) and with the supplier payment days from ""0. Assumptions""."&IF('0. Assumptions'!$B$59=0,""," With "&TEXT('0. Assumptions'!$B$59,"0")&" payment days, the last purchases of the year are paid next year: the ""Year"" column of this row holds "&TEXT(MAX(0,12-ROUNDUP('0. Assumptions'!$B$59/30,0)),"0")&" months of purchases, not the year's cost."),"") -> Coffee, milk and add-on purchases, compostable cups, fees and contingencies, each at ITS tax rate (column G of the P&L; 0 in the US, where the sales tax you pay is part of the cost) and with the supplier payment days from "0. Assumptions". With 7 payment days, the last purchases of the year are paid next year: the "Year" column of this row holds 11 months of purchases, not the year's cost.
A12: Operating fixed costs (incl. sales tax) | B12: =IFERROR(IF('3-Year P&L'!$B$9="","",-('3-Year P&L'!$B$38-'3-Year P&L'!$B$23-'3-Year P&L'!$B$36-'3-Year P&L'!$B$37+'3-Year P&L'!$B$40)/12),"") -> -2866.6667 | C12: =IFERROR(IF('3-Year P&L'!$B$9="","",-('3-Year P&L'!$B$38-'3-Year P&L'!$B$23-'3-Year P&L'!$B$36-'3-Year P&L'!$B$37+'3-Year P&L'!$B$40)/12),"") -> -2866.6667 | D12: =IFERROR(IF('3-Year P&L'!$B$9="","",-('3-Year P&L'!$B$38-'3-Year P&L'!$B$23-'3-Year P&L'!$B$36-'3-Year P&L'!$B$37+'3-Year P&L'!$B$40)/12),"") -> -2866.6667 | E12: =IFERROR(IF('3-Year P&L'!$B$9="","",-('3-Year P&L'!$B$38-'3-Year P&L'!$B$23-'3-Year P&L'!$B$36-'3-Year P&L'!$B$37+'3-Year P&L'!$B$40)/12),"") -> -2866.6667 | F12: =IFERROR(IF('3-Year P&L'!$B$9="","",-('3-Year P&L'!$B$38-'3-Year P&L'!$B$23-'3-Year P&L'!$B$36-'3-Year P&L'!$B$37+'3-Year P&L'!$B$40)/12),"") -> -2866.6667 | G12: =IFERROR(IF('3-Year P&L'!$B$9="","",-('3-Year P&L'!$B$38-'3-Year P&L'!$B$23-'3-Year P&L'!$B$36-'3-Year P&L'!$B$37+'3-Year P&L'!$B$40)/12),"") -> -2866.6667 | H12: =IFERROR(IF('3-Year P&L'!$B$9="","",-('3-Year P&L'!$B$38-'3-Year P&L'!$B$23-'3-Year P&L'!$B$36-'3-Year P&L'!$B$37+'3-Year P&L'!$B$40)/12),"") -> -2866.6667 | I12: =IFERROR(IF('3-Year P&L'!$B$9="","",-('3-Year P&L'!$B$38-'3-Year P&L'!$B$23-'3-Year P&L'!$B$36-'3-Year P&L'!$B$37+'3-Year P&L'!$B$40)/12),"") -> -2866.6667 | ... M12: =IFERROR(IF('3-Year P&L'!$B$9="","",-('3-Year P&L'!$B$38-'3-Year P&L'!$B$23-'3-Year P&L'!$B$36-'3-Year P&L'!$B$37+'3-Year P&L'!$B$40)/12),"") -> -2866.6667 | N12: =IFERROR(IF('3-Year P&L'!$B$9="","",SUM(B12:M12)),"") -> -34400 | O12: The fixed costs that leave cash, each with its own tax rate: insurance carries none
A13: Payroll and employer payroll taxes | B13: =IFERROR(IF('3-Year P&L'!$B$9="","",-'3-Year P&L'!$B$23/MAX(12,'0. Assumptions'!$B$21)*(1+IF(1='0. Assumptions'!$B$60,(MAX(12,'0. Assumptions'!$B$21)-12)/2,0)+IF(1='0. Assumptions'!$B$61,(MAX(12,'0. Assumptions'!$B$21)-12)/2,0))),"") -> -6208.4 | C13: =IFERROR(IF('3-Year P&L'!$B$9="","",-'3-Year P&L'!$B$23/MAX(12,'0. Assumptions'!$B$21)*(1+IF(2='0. Assumptions'!$B$60,(MAX(12,'0. Assumptions'!$B$21)-12)/2,0)+IF(2='0. Assumptions'!$B$61,(MAX(12,'0. Assumptions'!$B$21)-12)/2,0))),"") -> -6208.4 | D13: =IFERROR(IF('3-Year P&L'!$B$9="","",-'3-Year P&L'!$B$23/MAX(12,'0. Assumptions'!$B$21)*(1+IF(3='0. Assumptions'!$B$60,(MAX(12,'0. Assumptions'!$B$21)-12)/2,0)+IF(3='0. Assumptions'!$B$61,(MAX(12,'0. Assumptions'!$B$21)-12)/2,0))),"") -> -6208.4 | E13: =IFERROR(IF('3-Year P&L'!$B$9="","",-'3-Year P&L'!$B$23/MAX(12,'0. Assumptions'!$B$21)*(1+IF(4='0. Assumptions'!$B$60,(MAX(12,'0. Assumptions'!$B$21)-12)/2,0)+IF(4='0. Assumptions'!$B$61,(MAX(12,'0. Assumptions'!$B$21)-12)/2,0))),"") -> -6208.4 | F13: =IFERROR(IF('3-Year P&L'!$B$9="","",-'3-Year P&L'!$B$23/MAX(12,'0. Assumptions'!$B$21)*(1+IF(5='0. Assumptions'!$B$60,(MAX(12,'0. Assumptions'!$B$21)-12)/2,0)+IF(5='0. Assumptions'!$B$61,(MAX(12,'0. Assumptions'!$B$21)-12)/2,0))),"") -> -6208.4 | G13: =IFERROR(IF('3-Year P&L'!$B$9="","",-'3-Year P&L'!$B$23/MAX(12,'0. Assumptions'!$B$21)*(1+IF(6='0. Assumptions'!$B$60,(MAX(12,'0. Assumptions'!$B$21)-12)/2,0)+IF(6='0. Assumptions'!$B$61,(MAX(12,'0. Assumptions'!$B$21)-12)/2,0))),"") -> -6208.4 | H13: =IFERROR(IF('3-Year P&L'!$B$9="","",-'3-Year P&L'!$B$23/MAX(12,'0. Assumptions'!$B$21)*(1+IF(7='0. Assumptions'!$B$60,(MAX(12,'0. Assumptions'!$B$21)-12)/2,0)+IF(7='0. Assumptions'!$B$61,(MAX(12,'0. Assumptions'!$B$21)-12)/2,0))),"") -> -6208.4 | I13: =IFERROR(IF('3-Year P&L'!$B$9="","",-'3-Year P&L'!$B$23/MAX(12,'0. Assumptions'!$B$21)*(1+IF(8='0. Assumptions'!$B$60,(MAX(12,'0. Assumptions'!$B$21)-12)/2,0)+IF(8='0. Assumptions'!$B$61,(MAX(12,'0. Assumptions'!$B$21)-12)/2,0))),"") -> -6208.4 | J13: =IFERROR(IF('3-Year P&L'!$B$9="","",-'3-Year P&L'!$B$23/MAX(12,'0. Assumptions'!$B$21)*(1+IF(9='0. Assumptions'!$B$60,(MAX(12,'0. Assumptions'!$B$21)-12)/2,0)+IF(9='0. Assumptions'!$B$61,(MAX(12,'0. Assumptions'!$B$21)-12)/2,0))),"") -> -6208.4 | K13: =IFERROR(IF('3-Year P&L'!$B$9="","",-'3-Year P&L'!$B$23/MAX(12,'0. Assumptions'!$B$21)*(1+IF(10='0. Assumptions'!$B$60,(MAX(12,'0. Assumptions'!$B$21)-12)/2,0)+IF(10='0. Assumptions'!$B$61,(MAX(12,'0. Assumptions'!$B$21)-12)/2,0))),"") -> -6208.4 | L13: =IFERROR(IF('3-Year P&L'!$B$9="","",-'3-Year P&L'!$B$23/MAX(12,'0. Assumptions'!$B$21)*(1+IF(11='0. Assumptions'!$B$60,(MAX(12,'0. Assumptions'!$B$21)-12)/2,0)+IF(11='0. Assumptions'!$B$61,(MAX(12,'0. Assumptions'!$B$21)-12)/2,0))),"") -> -6208.4 | M13: =IFERROR(IF('3-Year P&L'!$B$9="","",-'3-Year P&L'!$B$23/MAX(12,'0. Assumptions'!$B$21)*(1+IF(12='0. Assumptions'!$B$60,(MAX(12,'0. Assumptions'!$B$21)-12)/2,0)+IF(12='0. Assumptions'!$B$61,(MAX(12,'0. Assumptions'!$B$21)-12)/2,0))),"") -> -6208.4 | N13: =IFERROR(IF('3-Year P&L'!$B$9="","",SUM(B13:M13)),"") -> -74500.8 | O13: Twelve monthly installments plus extra pay periods in the months you set in Assumptions (only if pay periods > 12). The total for the year is the same as the P&L's
A14: Loan interest | B14: =IFERROR(IF('3-Year P&L'!$B$9="","",-Financing!$B$44/12),"") -> -591.66667 | C14: =IFERROR(IF('3-Year P&L'!$B$9="","",-Financing!$B$44/12),"") -> -591.66667 | D14: =IFERROR(IF('3-Year P&L'!$B$9="","",-Financing!$B$44/12),"") -> -591.66667 | E14: =IFERROR(IF('3-Year P&L'!$B$9="","",-Financing!$B$44/12),"") -> -591.66667 | F14: =IFERROR(IF('3-Year P&L'!$B$9="","",-Financing!$B$44/12),"") -> -591.66667 | G14: =IFERROR(IF('3-Year P&L'!$B$9="","",-Financing!$B$44/12),"") -> -591.66667 | H14: =IFERROR(IF('3-Year P&L'!$B$9="","",-Financing!$B$44/12),"") -> -591.66667 | I14: =IFERROR(IF('3-Year P&L'!$B$9="","",-Financing!$B$44/12),"") -> -591.66667 | ... M14: =IFERROR(IF('3-Year P&L'!$B$9="","",-Financing!$B$44/12),"") -> -591.66667 | N14: =IFERROR(IF('3-Year P&L'!$B$9="","",SUM(B14:M14)),"") -> -7100
A15: Loan principal repaid | B15: =IFERROR(IF('3-Year P&L'!$B$9="","",-Financing!$B$45/12),"") -> -623.64921 | C15: =IFERROR(IF('3-Year P&L'!$B$9="","",-Financing!$B$45/12),"") -> -623.64921 | D15: =IFERROR(IF('3-Year P&L'!$B$9="","",-Financing!$B$45/12),"") -> -623.64921 | E15: =IFERROR(IF('3-Year P&L'!$B$9="","",-Financing!$B$45/12),"") -> -623.64921 | F15: =IFERROR(IF('3-Year P&L'!$B$9="","",-Financing!$B$45/12),"") -> -623.64921 | G15: =IFERROR(IF('3-Year P&L'!$B$9="","",-Financing!$B$45/12),"") -> -623.64921 | H15: =IFERROR(IF('3-Year P&L'!$B$9="","",-Financing!$B$45/12),"") -> -623.64921 | I15: =IFERROR(IF('3-Year P&L'!$B$9="","",-Financing!$B$45/12),"") -> -623.64921 | ... M15: =IFERROR(IF('3-Year P&L'!$B$9="","",-Financing!$B$45/12),"") -> -623.64921 | N15: =IFERROR(IF('3-Year P&L'!$B$9="","",SUM(B15:M15)),"") -> -7483.7905
A16: Sales tax collected (memo) | B16: =IFERROR(IF('3-Year P&L'!$B$9="","",'3-Year P&L'!$B$9*B7*SUMPRODUCT('3-Year P&L'!$E$10:$E$11,'3-Year P&L'!$G$10:$G$11)),"") -> 1037.4655 | C16: =IFERROR(IF('3-Year P&L'!$B$9="","",'3-Year P&L'!$B$9*C7*SUMPRODUCT('3-Year P&L'!$E$10:$E$11,'3-Year P&L'!$G$10:$G$11)),"") -> 1163.6438 | D16: =IFERROR(IF('3-Year P&L'!$B$9="","",'3-Year P&L'!$B$9*D7*SUMPRODUCT('3-Year P&L'!$E$10:$E$11,'3-Year P&L'!$G$10:$G$11)),"") -> 1330.0641 | E16: =IFERROR(IF('3-Year P&L'!$B$9="","",'3-Year P&L'!$B$9*E7*SUMPRODUCT('3-Year P&L'!$E$10:$E$11,'3-Year P&L'!$G$10:$G$11)),"") -> 804.19157 | F16: =IFERROR(IF('3-Year P&L'!$B$9="","",'3-Year P&L'!$B$9*F7*SUMPRODUCT('3-Year P&L'!$E$10:$E$11,'3-Year P&L'!$G$10:$G$11)),"") -> 572.21573 | G16: =IFERROR(IF('3-Year P&L'!$B$9="","",'3-Year P&L'!$B$9*G7*SUMPRODUCT('3-Year P&L'!$E$10:$E$11,'3-Year P&L'!$G$10:$G$11)),"") -> 873.77134 | H16: =IFERROR(IF('3-Year P&L'!$B$9="","",'3-Year P&L'!$B$9*H7*SUMPRODUCT('3-Year P&L'!$E$10:$E$11,'3-Year P&L'!$G$10:$G$11)),"") -> 1307.7362 | I16: =IFERROR(IF('3-Year P&L'!$B$9="","",'3-Year P&L'!$B$9*I7*SUMPRODUCT('3-Year P&L'!$E$10:$E$11,'3-Year P&L'!$G$10:$G$11)),"") -> 1837.5031 | ... M16: =IFERROR(IF('3-Year P&L'!$B$9="","",'3-Year P&L'!$B$9*M7*SUMPRODUCT('3-Year P&L'!$E$10:$E$11,'3-Year P&L'!$G$10:$G$11)),"") -> 1827.7671 | N16: =IFERROR(IF('3-Year P&L'!$B$9="","",SUM(B16:M16)),"") -> 16279.2 | O16: Each sales line at ITS OWN rate, read from the sales tax column of the P&L (alcohol to go has its own rate cell in the Assumptions tab)
A17: Recoverable input tax (memo) | B17: =IFERROR(IF('3-Year P&L'!$B$9="","",'3-Year P&L'!$B$39*B7+'3-Year P&L'!$B$40/12),"") -> 0 | C17: =IFERROR(IF('3-Year P&L'!$B$9="","",'3-Year P&L'!$B$39*C7+'3-Year P&L'!$B$40/12),"") -> 0 | D17: =IFERROR(IF('3-Year P&L'!$B$9="","",'3-Year P&L'!$B$39*D7+'3-Year P&L'!$B$40/12),"") -> 0 | E17: =IFERROR(IF('3-Year P&L'!$B$9="","",'3-Year P&L'!$B$39*E7+'3-Year P&L'!$B$40/12),"") -> 0 | F17: =IFERROR(IF('3-Year P&L'!$B$9="","",'3-Year P&L'!$B$39*F7+'3-Year P&L'!$B$40/12),"") -> 0 | G17: =IFERROR(IF('3-Year P&L'!$B$9="","",'3-Year P&L'!$B$39*G7+'3-Year P&L'!$B$40/12),"") -> 0 | H17: =IFERROR(IF('3-Year P&L'!$B$9="","",'3-Year P&L'!$B$39*H7+'3-Year P&L'!$B$40/12),"") -> 0 | I17: =IFERROR(IF('3-Year P&L'!$B$9="","",'3-Year P&L'!$B$39*I7+'3-Year P&L'!$B$40/12),"") -> 0 | ... M17: =IFERROR(IF('3-Year P&L'!$B$9="","",'3-Year P&L'!$B$39*M7+'3-Year P&L'!$B$40/12),"") -> 0 | N17: =IFERROR(IF('3-Year P&L'!$B$9="","",SUM(B17:M17)),"") -> 0 | O17: Each item at its own rate, read from the tax column of the P&L: insurance and card processing fees carry none
A18: Carried forward (capex input tax included) | E18: =IFERROR(IF('3-Year P&L'!$B$9="","",'Startup Costs'!$B$28),"") -> 0 | H18: =IFERROR(IF('3-Year P&L'!$B$9="","",MAX(0,-E19)),"") -> 0 | K18: =IFERROR(IF('3-Year P&L'!$B$9="","",MAX(0,-H19)),"") -> 0 | O18: Sales tax paid on STARTUP COSTS enters here: it is offset against the tax collected in later quarters until used up. With 0% recoverable input tax (the US default) this line stays at zero
A19: Quarterly sales tax return | E19: =IFERROR(IF('3-Year P&L'!$B$9="","",SUM(B16:D16)-SUM(B17:D17)-E18),"") -> 3531.1734 | H19: =IFERROR(IF('3-Year P&L'!$B$9="","",SUM(E16:G16)-SUM(E17:G17)-H18),"") -> 2250.1786 | K19: =IFERROR(IF('3-Year P&L'!$B$9="","",SUM(H16:J16)-SUM(H17:J17)-K18),"") -> 4786.0757 | O19: Sales tax collected minus recoverable input tax for the quarter, minus what was carried forward. If negative, nothing is paid: it is offset in the next quarter. With 0% recoverable input tax (the US default) it equals the sales tax collected in the quarter
A20: Sales tax remitted (quarterly filer) | E20: =IFERROR(IF('3-Year P&L'!$B$9="","",IF(E19<=0,"",-E19)),"") -> -3531.1734 | H20: =IFERROR(IF('3-Year P&L'!$B$9="","",IF(H19<=0,"",-H19)),"") -> -2250.1786 | K20: =IFERROR(IF('3-Year P&L'!$B$9="","",IF(K19<=0,"",-K19)),"") -> -4786.0757 | N20: =IFERROR(IF('3-Year P&L'!$B$9="","",SUM(B20:M20)),"") -> -10567.428 | O20: Cash only leaves when the quarter's result is positive. Months without a settlement are left blank, not zero. The cell turns RED when the payment takes more cash than is left that month. The model settles in the month after each plan quarter (Months 4, 7 and 10: June, September and December with Month 1 in March; the fourth quarter is remitted in Month 13): if your state requires monthly filing, expect smaller payments every month instead
A21: MONTHLY NET CASH FLOW | B21: =IFERROR(IF('3-Year P&L'!$B$9="","",SUM(B9:B15)+IF(B20="",0,B20)),"") -> -5276.398 | C21: =IFERROR(IF('3-Year P&L'!$B$9="","",SUM(C9:C15)+IF(C20="",0,C20)),"") -> 1122.0364 | D21: =IFERROR(IF('3-Year P&L'!$B$9="","",SUM(D9:D15)+IF(D20="",0,D20)),"") -> 2630.3537 | E21: =IFERROR(IF('3-Year P&L'!$B$9="","",SUM(E9:E15)+IF(E20="",0,E20)),"") -> -2513.7618 | F21: =IFERROR(IF('3-Year P&L'!$B$9="","",SUM(F9:F15)+IF(F20="",0,F20)),"") -> -3037.8577 | G21: =IFERROR(IF('3-Year P&L'!$B$9="","",SUM(G9:G15)+IF(G20="",0,G20)),"") -> -2874.7931 | H21: =IFERROR(IF('3-Year P&L'!$B$9="","",SUM(H9:H15)+IF(H20="",0,H20)),"") -> -1345.101 | I21: =IFERROR(IF('3-Year P&L'!$B$9="","",SUM(I9:I15)+IF(I20="",0,I20)),"") -> 5886.74 | ... M21: =IFERROR(IF('3-Year P&L'!$B$9="","",SUM(M9:M15)+IF(M20="",0,M20)),"") -> 6655.2515 | N21: =IFERROR(IF('3-Year P&L'!$B$9="","",SUM(B21:M21)),"") -> 25256.973
A22: CUMULATIVE CASH BALANCE | B22: =IFERROR(IF('3-Year P&L'!$B$9="","",'Startup Costs'!$B$25+B21),"") -> 23723.802 | C22: =IFERROR(IF('3-Year P&L'!$B$9="","",B22+C21),"") -> 24845.838 | D22: =IFERROR(IF('3-Year P&L'!$B$9="","",C22+D21),"") -> 27476.192 | E22: =IFERROR(IF('3-Year P&L'!$B$9="","",D22+E21),"") -> 24962.43 | F22: =IFERROR(IF('3-Year P&L'!$B$9="","",E22+F21),"") -> 21924.572 | G22: =IFERROR(IF('3-Year P&L'!$B$9="","",F22+G21),"") -> 19049.779 | H22: =IFERROR(IF('3-Year P&L'!$B$9="","",G22+H21),"") -> 17704.678 | I22: =IFERROR(IF('3-Year P&L'!$B$9="","",H22+I21),"") -> 23591.418 | J22: =IFERROR(IF('3-Year P&L'!$B$9="","",I22+J21),"") -> 31483.563 | ... M22: =IFERROR(IF('3-Year P&L'!$B$9="","",L22+M21),"") -> 54257.173
A23: Minimum balance of the year | B23: =IFERROR(IF('3-Year P&L'!$B$9="","",IF(COUNT(B22:M22)=0,"",MIN(B22:M22))),"") -> 17704.678 | D23: If negative, raise working capital or the loan: you run out of cash
A24: Month when cash bottoms out | B24: =IFERROR(IF('3-Year P&L'!$B$9="","",IF(COUNT(B22:M22)=0,"",MATCH(MIN(B22:M22),B22:M22,0))),"") -> 7 | D24: It answers the question that decides a bank deal: in which month the cash runs out
A25: RETURN ON INVESTMENT
A26: Free cash flow before debt, year 1 | B26: =IFERROR(IF('3-Year P&L'!$B$9="","",'3-Year P&L'!$B$48+'3-Year P&L'!$B$36+Financing!$B$44),"") -> 37606.449 | D26: Net income plus depreciation (which is not paid) plus that year's interest: principal is not subtracted because this flow is BEFORE debt. The SAME basis as years 2 and 3, so the payback compares like with like
A27: Free cash flow before debt, year 2 | B27: =IFERROR(IF('3-Year P&L'!$B$9="","",'3-Year P&L'!$C$48+'3-Year P&L'!$C$36+Financing!$B$46),"") -> 46661.452 | D27: Net income plus depreciation (which is not paid) plus that year's interest: principal is not subtracted because this flow is BEFORE debt. Without a monthly table, it is an estimate
A28: Free cash flow before debt, year 3 | B28: =IFERROR(IF('3-Year P&L'!$B$9="","",'3-Year P&L'!$D$48+'3-Year P&L'!$D$36+Financing!$B$48),"") -> 51790.432 | D28: Net income plus depreciation (which is not paid) plus that year's interest: principal is not subtracted because this flow is BEFORE debt. Without a monthly table, it is an estimate
A29: For reference: ACTUAL year-1 cash flow (monthly table, before debt) | B29: =IFERROR(IF('3-Year P&L'!$B$9="","",N21+Financing!$B$44+Financing!$B$45),"") -> 39840.763 | D29: The sum of the twelve monthly net cash flows above, adding back the interest and principal paid that year. It is NOT the one the payback uses: it includes sales tax not yet settled and supplier credit, two things that have to be paid back and that years 2 and 3 do not have
A30: Investment to recover (net of recoverable input tax) | B30: =IFERROR(IF('3-Year P&L'!$B$9="","",'Startup Costs'!$B$29-'Startup Costs'!$B$28),"") -> 100290.2 | D30: CAPEX plus working capital: the total cash needed MINUS the recoverable input tax on startup costs, which is not lost (it is recovered through the quarterly return, and this tab offsets it quarter by quarter; it is zero in the US default). Working capital is recovered when you close, but until then it is tied up
A31: Project payback (years), before debt | B31: =IFERROR(IF('3-Year P&L'!$B$9="","",IF(B26>=B30,ROUND(B30/B26,1),IF(B26+B27>=B30,ROUND(1+(B30-B26)/B27,1),IF(B26+B27+B28>=B30,ROUND(2+(B30-B26-B27)/B28,1),"Over 3 years")))),"") -> 2.3 | D31: Measures how long the business takes to repay the investment with what it generates BEFORE paying the lender, on the SAME cash flow basis in all three years. Whether you can afford the loan payment is shown by the DSCR in the Financing tab
A32: Payback on CAPEX, excluding working capital (years) | B32: =IFERROR(IF('3-Year P&L'!$B$9="","",IF(B26>='Startup Costs'!$B$27,ROUND('Startup Costs'!$B$27/B26,1),IF(B26+B27>='Startup Costs'!$B$27,ROUND(1+('Startup Costs'!$B$27-B26)/B27,1),IF(B26+B27+B28>='Startup Costs'!$B$27,ROUND(2+('Startup Costs'!$B$27-B26-B27)/B28,1),"Over 3 years")))),"") -> 1.7 | D32: The same calculation on what you BUY (the cart and the portable bar, machines and grinders, trailer, power, launch and formation costs), without working capital: that money is not spent, it is tied up and comes back when the business closes. For reference only: the payback that matters is the one above
A34: The fourth plan quarter's sales tax is settled in Month 13 (March of the following year with Month 1 in March), so it does not appear in this table. The model pays year-1 income tax in year 2 (a simplification: estimated tax payments are usually quarterly). The loan payment is spread in twelve equal parts following the ANNUAL schedule in the Financing tab, and payroll in twelve monthly installments (plus extra pay periods in their month, only if pay periods > 12).

Sheet Financing
A1: FINANCING PLAN
A2: What you need, where it comes from and what it costs to repay. It is the sheet your lender asks for along with the P&L.
A4: Item | B4: Amount | C4: Notes
A5: SOURCES OF FUNDS
A6: Owner's equity (your own money) | B6: =IFERROR(IF('0. Assumptions'!$B$30="","",'0. Assumptions'!$B$30),"") -> 30000
A7: Loan requested — bank or SBA 7(a) (amortized below) | B7: =IFERROR(IF('0. Assumptions'!$B$31="","",'0. Assumptions'!$B$31),"") -> 71000
A8: Other loan (not in the schedule or the DSCR — enter your loan in row 7) | B8: 0 | C8: A source of funds only: NOT amortized, so it is not in the schedule, the P&L interest or the DSCR. Enter your bank or SBA 7(a) loan in row 7 ("Loan requested" in "0. Assumptions"); use this row only for a second loan
A9: SBA Microloan (not in the schedule or the DSCR — enter your loan in row 7) | B9: 0 | C9: SBA Microloans go up to $50,000 through nonprofit intermediaries. Like row 8, a source of funds only: not in the schedule or the DSCR. If it is your only loan, enter it in row 7 instead
A10: Investors / partners (equity: dilutes, not repaid) | B10: 0 | C10: Equity: it dilutes your ownership and is not repaid
A11: Local grants (usually paid after you spend) | B11: 0 | C11: Usually paid AFTER you document the spending
A12: TOTAL SOURCES OF FUNDS | B12: =IFERROR(IF(COUNT(B6:B11)=0,"",SUM(B6:B11)),"") -> 101000
A13: USES OF FUNDS
A14: Total cash needed at launch | B14: =IFERROR(IF('Startup Costs'!$B$29="","",'Startup Costs'!$B$29),"") -> 100290.2 | C14: Startup costs plus any recoverable tax you have to advance (zero by default in the US)
A15: Difference (sources - uses) | B15: =IFERROR(B12-B14,"") -> 709.8 | C15: In red (negative), the plan is NOT funded. Far above zero is not free either: you pay interest on money you do not use
A16: Difference as a % of uses | B16: =IFERROR(B15/B14,"") -> 0.0070774612 | C16: Amber above the margin you set: it is debt you pay for without needing it
A17: Acceptable over-funding (%) | B17: 0.05 | C17: A small cushion over the need is healthy; 20% extra is interest thrown away
A18: Loan that would match sources to needs | B18: =IFERROR(MAX(0,B14-B12+B7),"") -> 70290.2 | C18: Copy it into "Loan requested" in the "0. Assumptions" tab and the difference goes to zero. Rows 8-11 lower this figure, but only the row-7 loan is amortized and counted in the DSCR
A19: LOAN TERMS
A20: Principal amount | B20: =IFERROR(IF('0. Assumptions'!$B$31=0,"",'0. Assumptions'!$B$31),"") -> 71000
A21: Nominal annual interest rate (not APR) | B21: =IFERROR(IF('0. Assumptions'!$B$32="","",'0. Assumptions'!$B$32),"") -> 0.1
A22: Total term (years) | B22: =IFERROR(IF('0. Assumptions'!$B$33="","",'0. Assumptions'!$B$33),"") -> 7
A23: Interest-only period applied (years) | B23: =IFERROR(IF(OR('0. Assumptions'!$B$34="",'0. Assumptions'!$B$33=""),"",IF('0. Assumptions'!$B$34>='0. Assumptions'!$B$33,0,'0. Assumptions'!$B$34)),"") -> 0 | C23: An interest-only period equal to or longer than the term does not exist: the sheet cancels it at the source
A24: Annual payment during repayment | B24: =IFERROR(IF(B22-B23<=0,"",IF(B21=0,B20/(B22-B23),B20*B21/(1-(1+B21)^-(B22-B23)))),"") -> 14583.79 | C24: Standard amortizing loan with a level annual payment. At a 0% rate it is the principal divided by the repayment years: without that branch the schedule would shut down entirely
A25: AMORTIZATION SCHEDULE
A26: Year | B26: Opening balance | C26: Interest | D26: Principal repaid | E26: Total payment | F26: Closing balance | G26: Cash flow available for debt service (after tax; from year 4 on, year 3 held flat) | H26: DSCR for the year
A27: 1 | B27: =IFERROR(IF(B20="","",B20),"") -> 71000 | C27: =IFERROR(IF(OR(1>B22,B27=""),"",B27*B21),"") -> 7100 | D27: =IFERROR(IF(OR(1>B22,B27=""),"",IF(1<=B23,0,MIN(B27,B24-C27))),"") -> 7483.7905 | E27: =IFERROR(IF(C27="","",C27+D27),"") -> 14583.79 | F27: =IFERROR(IF(D27="","",B27-D27),"") -> 63516.21 | G27: =IFERROR(IF(E27="","",'3-Year P&L'!$B$41-'3-Year P&L'!$B$46+'3-Year P&L'!$B$36+'3-Year P&L'!$B$37),"") -> 37606.449 | H27: =IFERROR(IF(OR(E27="",E27=0),"",G27/E27),"") -> 2.5786471
A28: 2 | B28: =IFERROR(IF(OR(2>B22,F27=""),"",F27),"") -> 63516.21 | C28: =IFERROR(IF(OR(2>B22,B28=""),"",B28*B21),"") -> 6351.621 | D28: =IFERROR(IF(OR(2>B22,B28=""),"",IF(2<=B23,0,MIN(B28,B24-C28))),"") -> 8232.1695 | E28: =IFERROR(IF(C28="","",C28+D28),"") -> 14583.79 | F28: =IFERROR(IF(D28="","",B28-D28),"") -> 55284.04 | G28: =IFERROR(IF(E28="","",'3-Year P&L'!$C$41-'3-Year P&L'!$C$46+'3-Year P&L'!$C$36+'3-Year P&L'!$C$37),"") -> 46661.452 | H28: =IFERROR(IF(OR(E28="",E28=0),"",G28/E28),"") -> 3.1995421
A29: 3 | B29: =IFERROR(IF(OR(3>B22,F28=""),"",F28),"") -> 55284.04 | C29: =IFERROR(IF(OR(3>B22,B29=""),"",B29*B21),"") -> 5528.404 | D29: =IFERROR(IF(OR(3>B22,B29=""),"",IF(3<=B23,0,MIN(B29,B24-C29))),"") -> 9055.3865 | E29: =IFERROR(IF(C29="","",C29+D29),"") -> 14583.79 | F29: =IFERROR(IF(D29="","",B29-D29),"") -> 46228.654 | G29: =IFERROR(IF(E29="","",'3-Year P&L'!$D$41-'3-Year P&L'!$D$46+'3-Year P&L'!$D$36+'3-Year P&L'!$D$37),"") -> 51790.432 | H29: =IFERROR(IF(OR(E29="",E29=0),"",G29/E29),"") -> 3.5512326
A30: 4 | B30: =IFERROR(IF(OR(4>B22,F29=""),"",F29),"") -> 46228.654 | C30: =IFERROR(IF(OR(4>B22,B30=""),"",B30*B21),"") -> 4622.8654 | D30: =IFERROR(IF(OR(4>B22,B30=""),"",IF(4<=B23,0,MIN(B30,B24-C30))),"") -> 9960.9251 | E30: =IFERROR(IF(C30="","",C30+D30),"") -> 14583.79 | F30: =IFERROR(IF(D30="","",B30-D30),"") -> 36267.728 | G30: =IFERROR(IF(E30="","",'3-Year P&L'!$D$41-'3-Year P&L'!$D$46+'3-Year P&L'!$D$36+'3-Year P&L'!$D$37),"") -> 51790.432 | H30: =IFERROR(IF(OR(E30="",E30=0),"",G30/E30),"") -> 3.5512326
A31: 5 | B31: =IFERROR(IF(OR(5>B22,F30=""),"",F30),"") -> 36267.728 | C31: =IFERROR(IF(OR(5>B22,B31=""),"",B31*B21),"") -> 3626.7728 | D31: =IFERROR(IF(OR(5>B22,B31=""),"",IF(5<=B23,0,MIN(B31,B24-C31))),"") -> 10957.018 | E31: =IFERROR(IF(C31="","",C31+D31),"") -> 14583.79 | F31: =IFERROR(IF(D31="","",B31-D31),"") -> 25310.711 | G31: =IFERROR(IF(E31="","",'3-Year P&L'!$D$41-'3-Year P&L'!$D$46+'3-Year P&L'!$D$36+'3-Year P&L'!$D$37),"") -> 51790.432 | H31: =IFERROR(IF(OR(E31="",E31=0),"",G31/E31),"") -> 3.5512326
A32: 6 | B32: =IFERROR(IF(OR(6>B22,F31=""),"",F31),"") -> 25310.711 | C32: =IFERROR(IF(OR(6>B22,B32=""),"",B32*B21),"") -> 2531.0711 | D32: =IFERROR(IF(OR(6>B22,B32=""),"",IF(6<=B23,0,MIN(B32,B24-C32))),"") -> 12052.719 | E32: =IFERROR(IF(C32="","",C32+D32),"") -> 14583.79 | F32: =IFERROR(IF(D32="","",B32-D32),"") -> 13257.991 | G32: =IFERROR(IF(E32="","",'3-Year P&L'!$D$41-'3-Year P&L'!$D$46+'3-Year P&L'!$D$36+'3-Year P&L'!$D$37),"") -> 51790.432 | H32: =IFERROR(IF(OR(E32="",E32=0),"",G32/E32),"") -> 3.5512326
A33: 7 | B33: =IFERROR(IF(OR(7>B22,F32=""),"",F32),"") -> 13257.991 | C33: =IFERROR(IF(OR(7>B22,B33=""),"",B33*B21),"") -> 1325.7991 | D33: =IFERROR(IF(OR(7>B22,B33=""),"",IF(7<=B23,0,MIN(B33,B24-C33))),"") -> 13257.991 | E33: =IFERROR(IF(C33="","",C33+D33),"") -> 14583.79 | F33: =IFERROR(IF(D33="","",B33-D33),"") -> 8.9130481e-11 | G33: =IFERROR(IF(E33="","",'3-Year P&L'!$D$41-'3-Year P&L'!$D$46+'3-Year P&L'!$D$36+'3-Year P&L'!$D$37),"") -> 51790.432 | H33: =IFERROR(IF(OR(E33="",E33=0),"",G33/E33),"") -> 3.5512326
A34: 8 | B34: =IFERROR(IF(OR(8>B22,F33=""),"",F33),"") | C34: =IFERROR(IF(OR(8>B22,B34=""),"",B34*B21),"") | D34: =IFERROR(IF(OR(8>B22,B34=""),"",IF(8<=B23,0,MIN(B34,B24-C34))),"") | E34: =IFERROR(IF(C34="","",C34+D34),"") | F34: =IFERROR(IF(D34="","",B34-D34),"") | G34: =IFERROR(IF(E34="","",'3-Year P&L'!$D$41-'3-Year P&L'!$D$46+'3-Year P&L'!$D$36+'3-Year P&L'!$D$37),"") | H34: =IFERROR(IF(OR(E34="",E34=0),"",G34/E34),"")
A35: 9 | B35: =IFERROR(IF(OR(9>B22,F34=""),"",F34),"") | C35: =IFERROR(IF(OR(9>B22,B35=""),"",B35*B21),"") | D35: =IFERROR(IF(OR(9>B22,B35=""),"",IF(9<=B23,0,MIN(B35,B24-C35))),"") | E35: =IFERROR(IF(C35="","",C35+D35),"") | F35: =IFERROR(IF(D35="","",B35-D35),"") | G35: =IFERROR(IF(E35="","",'3-Year P&L'!$D$41-'3-Year P&L'!$D$46+'3-Year P&L'!$D$36+'3-Year P&L'!$D$37),"") | H35: =IFERROR(IF(OR(E35="",E35=0),"",G35/E35),"")
A36: 10 | B36: =IFERROR(IF(OR(10>B22,F35=""),"",F35),"") | C36: =IFERROR(IF(OR(10>B22,B36=""),"",B36*B21),"") | D36: =IFERROR(IF(OR(10>B22,B36=""),"",IF(10<=B23,0,MIN(B36,B24-C36))),"") | E36: =IFERROR(IF(C36="","",C36+D36),"") | F36: =IFERROR(IF(D36="","",B36-D36),"") | G36: =IFERROR(IF(E36="","",'3-Year P&L'!$D$41-'3-Year P&L'!$D$46+'3-Year P&L'!$D$36+'3-Year P&L'!$D$37),"") | H36: =IFERROR(IF(OR(E36="",E36=0),"",G36/E36),"")
A37: 11 | B37: =IFERROR(IF(OR(11>B22,F36=""),"",F36),"") | C37: =IFERROR(IF(OR(11>B22,B37=""),"",B37*B21),"") | D37: =IFERROR(IF(OR(11>B22,B37=""),"",IF(11<=B23,0,MIN(B37,B24-C37))),"") | E37: =IFERROR(IF(C37="","",C37+D37),"") | F37: =IFERROR(IF(D37="","",B37-D37),"") | G37: =IFERROR(IF(E37="","",'3-Year P&L'!$D$41-'3-Year P&L'!$D$46+'3-Year P&L'!$D$36+'3-Year P&L'!$D$37),"") | H37: =IFERROR(IF(OR(E37="",E37=0),"",G37/E37),"")
A38: 12 | B38: =IFERROR(IF(OR(12>B22,F37=""),"",F37),"") | C38: =IFERROR(IF(OR(12>B22,B38=""),"",B38*B21),"") | D38: =IFERROR(IF(OR(12>B22,B38=""),"",IF(12<=B23,0,MIN(B38,B24-C38))),"") | E38: =IFERROR(IF(C38="","",C38+D38),"") | F38: =IFERROR(IF(D38="","",B38-D38),"") | G38: =IFERROR(IF(E38="","",'3-Year P&L'!$D$41-'3-Year P&L'!$D$46+'3-Year P&L'!$D$36+'3-Year P&L'!$D$37),"") | H38: =IFERROR(IF(OR(E38="",E38=0),"",G38/E38),"")
A39: 13 | B39: =IFERROR(IF(OR(13>B22,F38=""),"",F38),"") | C39: =IFERROR(IF(OR(13>B22,B39=""),"",B39*B21),"") | D39: =IFERROR(IF(OR(13>B22,B39=""),"",IF(13<=B23,0,MIN(B39,B24-C39))),"") | E39: =IFERROR(IF(C39="","",C39+D39),"") | F39: =IFERROR(IF(D39="","",B39-D39),"") | G39: =IFERROR(IF(E39="","",'3-Year P&L'!$D$41-'3-Year P&L'!$D$46+'3-Year P&L'!$D$36+'3-Year P&L'!$D$37),"") | H39: =IFERROR(IF(OR(E39="",E39=0),"",G39/E39),"")
A40: 14 | B40: =IFERROR(IF(OR(14>B22,F39=""),"",F39),"") | C40: =IFERROR(IF(OR(14>B22,B40=""),"",B40*B21),"") | D40: =IFERROR(IF(OR(14>B22,B40=""),"",IF(14<=B23,0,MIN(B40,B24-C40))),"") | E40: =IFERROR(IF(C40="","",C40+D40),"") | F40: =IFERROR(IF(D40="","",B40-D40),"") | G40: =IFERROR(IF(E40="","",'3-Year P&L'!$D$41-'3-Year P&L'!$D$46+'3-Year P&L'!$D$36+'3-Year P&L'!$D$37),"") | H40: =IFERROR(IF(OR(E40="",E40=0),"",G40/E40),"")
A41: 15 | B41: =IFERROR(IF(OR(15>B22,F40=""),"",F40),"") | C41: =IFERROR(IF(OR(15>B22,B41=""),"",B41*B21),"") | D41: =IFERROR(IF(OR(15>B22,B41=""),"",IF(15<=B23,0,MIN(B41,B24-C41))),"") | E41: =IFERROR(IF(C41="","",C41+D41),"") | F41: =IFERROR(IF(D41="","",B41-D41),"") | G41: =IFERROR(IF(E41="","",'3-Year P&L'!$D$41-'3-Year P&L'!$D$46+'3-Year P&L'!$D$36+'3-Year P&L'!$D$37),"") | H41: =IFERROR(IF(OR(E41="",E41=0),"",G41/E41),"")
A42: Schedule closing tolerance | B42: 0.01 | C42: Rounding margin. Above it, the schedule does not close and there is principal left unpaid
A43: Balance outstanding at maturity | B43: =IFERROR(IF(B20="","",ROUND(B20-SUM(D27:D41),2)),"") -> 0 | C43: Must be zero: the principal repaid in the schedule has to equal the amount borrowed. If it is positive, the term falls short
A44: Year-1 interest | B44: =IFERROR(IF(B20="","",IF(C27="",0,C27)),"") -> 7100
A45: Year-1 principal repaid | B45: =IFERROR(IF(B20="","",IF(D27="",0,D27)),"") -> 7483.7905
A46: Year-2 interest | B46: =IFERROR(IF(B20="","",IF(C28="",0,C28)),"") -> 6351.621
A47: Year-2 principal repaid | B47: =IFERROR(IF(B20="","",IF(D28="",0,D28)),"") -> 8232.1695
A48: Year-3 interest | B48: =IFERROR(IF(B20="","",IF(C29="",0,C29)),"") -> 5528.404
A49: Year-3 principal repaid | B49: =IFERROR(IF(B20="","",IF(D29="",0,D29)),"") -> 9055.3865
A50: DEBT SERVICE COVERAGE RATIO (DSCR)
A51: Year-1 DSCR | B51: =IFERROR(('3-Year P&L'!$B$41-'3-Year P&L'!$B$46+'3-Year P&L'!$B$36+B44)/(B44+B45),"") -> 2.5786471 | C51: An INTEREST-ONLY year, if there is one: with only interest in the denominator the ratio shoots up and does not measure the business
A52: Year-2 DSCR | B52: =IFERROR(('3-Year P&L'!$C$41-'3-Year P&L'!$C$46+'3-Year P&L'!$C$36+B46)/(B46+B47),"") -> 3.1995421
A53: Year-3 DSCR | B53: =IFERROR(('3-Year P&L'!$D$41-'3-Year P&L'!$D$46+'3-Year P&L'!$D$36+B48)/(B48+B49),"") -> 3.5512326
A54: Minimum DSCR across the whole schedule | B54: =IFERROR(IF(COUNT(H27:H41)=0,"",MIN(H27:H41)),"") -> 2.5786471 | C54: The worst year of the life of the loan, not the best of the three the P&L projects. It is the number that decides a loan. Mind the scope: years 1 to 3 come from the P&L, and from year 4 on the schedule HOLDS year 3's cash flow, so the minimum over those years is a sustained projection, not a calculated year. The cash flow is after tax
A56: DSCR is calculated BEFORE debt and AFTER tax: income tax is subtracted from pre-tax income, depreciation and interest are added back, and the result is divided by what has to be paid that year. Below the minimum in the "0. Assumptions" tab, the business does not generate enough to repay the loan. In the schedule, the available cash flow from year 4 on is held at year 3's: the P&L projects only three years, and no growth is invented here that has not been calculated.
