Workbook

Sheet Cost per Drink
A1: COST PER DRINK — 16 INGREDIENTS × 10 DRINKS, IN GRAMS, FLUID OUNCES AND UNITS
A2: Type only in the GREEN cells (prices, waste, units per price, quantities, mix and menu prices). Amounts are before sales tax. The prices are kit estimates: use your roaster's and suppliers'. The cost of one drink on this tab is NOT the cost of goods in the financial plan: that one is the average of the whole mix with waste, not a recipe.
A4: SETTINGS | B4: Value | F4: Notes
A5: Sales tax included in your menu prices (%) | B5: 0 | F5: US menus usually show prices before sales tax: leave 0%. If you post round prices with the tax included (common at festivals and markets), enter your rate and the sheet takes it out.
A6: Target cost of goods (% of the price before sales tax) | B6: 0.25 | F6: grindkit.app puts cost of goods at 20-30% of the revenue per drink. Use the one your financial plan targets.
A7: Watch band above the target (points) | B7: 0.05 | F7: Up to this band above the target, the traffic light says "Watch the cost"; beyond it, "Above target".
A8: Grams of coffee per double shot (g) | B8: 18 | F8: 18 g (0.63 oz) in, 36 g out (a 1:2 ratio). It moves the coffee row of every drink.
A10: INGREDIENT (recipe unit · price unit) | B10: Price before sales tax | C10: Waste | D10: Recipe units per price unit | E10: Net cost per recipe unit | F10: Espresso | G10: Americano | H10: Cortado | I10: Latte | J10: Cappuccino | K10: Flat white | L10: Mocha | M10: Chai latte | N10: Hot chocolate | O10: Cold brew | P10: WHERE THE EXAMPLE PRICE COMES FROM
A11: Menu price per drink | F11: 3.5 | G11: 4.5 | H11: 4.75 | I11: 6.5 | J11: 6 | K11: 6 | L11: 7 | M11: 6.5 | N11: 5.5 | O11: 6.5
A12: Sales mix (% of drinks) | F12: 0.06 | G12: 0.12 | H12: 0.06 | I12: 0.24 | J12: 0.14 | K12: 0.06 | L12: 0.08 | M12: 0.08 | N12: 0.04 | O12: 0.12
A13: Double shots per drink | F13: 1 | G13: 1 | H13: 1 | I13: 1 | J13: 1 | K13: 1 | L13: 1 | M13: 0 | N13: 0 | O13: 1.5
A14: Coffee beans (g · $ per lb) | B14: 14 | C14: 0.1 | D14: 453.6 | E14: =B14/(1-C14)/D14 -> 0.034293553 | F14: =F$13*$B$8 -> 18 | G14: =G$13*$B$8 -> 18 | H14: =H$13*$B$8 -> 18 | I14: =I$13*$B$8 -> 18 | J14: =J$13*$B$8 -> 18 | K14: =K$13*$B$8 -> 18 | L14: =L$13*$B$8 -> 18 | M14: =M$13*$B$8 -> 0 | ... O14: =O$13*$B$8 -> 27 | P14: Kit estimate: $14 per lb, between the national average for ground coffee ($9.33 per lb, BLS, September 2026) and specialty wholesale (about $18 per lb); 10% waste for purging and dialing in.
A15: Whole milk (fl oz · $ per gallon) | B15: 4.11 | C15: 0.1 | D15: 128 | E15: =B15/(1-C15)/D15 -> 0.035677083 | F15: 0 | G15: 0 | H15: 1.3 | I15: 6.5 | J15: 3.25 | K15: 3.25 | L15: 5.2 | M15: 3.9 | N15: 5.2 | O15: 0.65 | P15: National average, September 2026 (BLS: $4.106 per gallon).
A16: Lactose-free milk (fl oz · $ per gallon) | B16: 7.5 | C16: 0.1 | D16: 128 | E16: =B16/(1-C16)/D16 -> 0.065104167 | F16: 0 | G16: 0 | H16: 0.1 | I16: 0.5 | J16: 0.25 | K16: 0.25 | L16: 0.4 | M16: 0.3 | N16: 0.4 | O16: 0.05 | P16: Kit estimate.
A17: Oat milk, barista (fl oz · $ per gallon) | B17: 13 | C17: 0.1 | D17: 128 | E17: =B17/(1-C17)/D17 -> 0.11284722 | F17: 0 | G17: 0 | H17: 0.5 | I17: 2.5 | J17: 1.25 | K17: 1.25 | L17: 2 | M17: 1.5 | N17: 2 | O17: 0.25 | P17: Kit estimate: about $0.80 of oat milk in an 8-oz drink (grindkit.app gives $0.60-1.10).
A18: Almond milk, barista (fl oz · $ per gallon) | B18: 12 | C18: 0.1 | D18: 128 | E18: =B18/(1-C18)/D18 -> 0.10416667 | F18: 0 | G18: 0 | H18: 0.1 | I18: 0.5 | J18: 0.25 | K18: 0.25 | L18: 0.4 | M18: 0.3 | N18: 0.4 | O18: 0.05 | P18: Kit estimate.
A19: Cocoa powder (g · $ per lb) | B19: 8 | C19: 0.05 | D19: 453.6 | E19: =B19/(1-C19)/D19 -> 0.018564931 | F19: 0 | G19: 0 | H19: 0 | I19: 0 | J19: 2 | K19: 0 | L19: 15 | M19: 0 | N19: 25 | O19: 0 | P19: Kit estimate.
A20: Chai concentrate (fl oz · $ per gallon) | B20: 20 | C20: 0.05 | D20: 128 | E20: =B20/(1-C20)/D20 -> 0.16447368 | F20: 0 | G20: 0 | H20: 0 | I20: 0 | J20: 0 | K20: 0 | L20: 0 | M20: 6 | N20: 0 | O20: 0 | P20: Kit estimate.
A21: Vanilla or caramel syrup (fl oz · $ per bottle) | B21: 9 | C21: 0.05 | D21: 25.4 | E21: =B21/(1-C21)/D21 -> 0.37297969 | F21: 0 | G21: 0 | H21: 0 | I21: 0.25 | J21: 0 | K21: 0 | L21: 0 | M21: 0 | N21: 0 | O21: 0 | P21: Kit estimate: a standard bottle holds 25.4 fl oz (750 ml); one pump (0.25 fl oz) costs about $0.05-0.15 (grindkit.app).
A22: Tea (g · $ per lb) | B22: 30 | C22: 0.05 | D22: 453.6 | E22: =B22/(1-C22)/D22 -> 0.069618491 | F22: 0 | G22: 0 | H22: 0 | I22: 0 | J22: 0 | K22: 0 | L22: 0 | M22: 0 | N22: 0 | O22: 0 | P22: Free slot for your tea menu: empty in the example.
A23: Sugar (g · $ per lb) | B23: 0.9 | C23: 0 | D23: 453.6 | E23: =B23/(1-C23)/D23 -> 0.001984127 | F23: 0 | G23: 0 | H23: 0 | I23: 0 | J23: 0 | K23: 0 | L23: 8 | M23: 0 | N23: 10 | O23: 0 | P23: Kit estimate.
A24: 8-oz compostable hot cup (each) | B24: 0.1 | C24: 0.03 | D24: 1 | E24: =B24/(1-C24)/D24 -> 0.10309278 | F24: 1 | G24: 0 | H24: 1 | I24: 0 | J24: 1 | K24: 1 | L24: 0 | M24: 0 | N24: 0 | O24: 0 | P24: Kit estimate: cup, lid, sleeve, napkin and stirrer come to about $0.20-0.45 per drink (grindkit.app).
A25: 12-oz compostable hot cup (each) | B25: 0.13 | C25: 0.03 | D25: 1 | E25: =B25/(1-C25)/D25 -> 0.13402062 | F25: 0 | G25: 1 | H25: 0 | I25: 1 | J25: 0 | K25: 0 | L25: 1 | M25: 1 | N25: 1 | O25: 0 | P25: Same source.
A26: 16-oz compostable cup (each) | B26: 0.16 | C26: 0.03 | D26: 1 | E26: =B26/(1-C26)/D26 -> 0.16494845 | F26: 0 | G26: 0 | H26: 0 | I26: 0 | J26: 0 | K26: 0 | L26: 0 | M26: 0 | N26: 0 | O26: 1 | P26: Same source.
... A29: Napkin and wooden stirrer (each) | B29: 0.03 | C29: 0.03 | D29: 1 | E29: =B29/(1-C29)/D29 -> 0.030927835 | F29: 1 | G29: 1 | H29: 1 | I29: 1 | J29: 1 | K29: 1 | L29: 1 | M29: 1 | N29: 1 | O29: 1 | P29: Same source. Some cities require compostable single-use items (Seattle, as an example): check yours.
A31: RESULT PER DRINK | F31: =F10 -> Espresso | G31: =G10 -> Americano | H31: =H10 -> Cortado | I31: =I10 -> Latte | J31: =J10 -> Cappuccino | K31: =K10 -> Flat white | L31: =L10 -> Mocha | M31: =M10 -> Chai latte | ... O31: =O10 -> Cold brew
A32: Milk and plant-based milk in total (fl oz) | F32: =SUM(F15:F18) -> 0 | G32: =SUM(G15:G18) -> 0 | H32: =SUM(H15:H18) -> 2 | I32: =SUM(I15:I18) -> 10 | J32: =SUM(J15:J18) -> 5 | K32: =SUM(K15:K18) -> 5 | L32: =SUM(L15:L18) -> 8 | M32: =SUM(M15:M18) -> 6 | ... O32: =SUM(O15:O18) -> 1
A33: Ingredient cost | F33: =SUMPRODUCT(F$14:F$23,$E$14:$E$23) -> 0.61728395 | G33: =SUMPRODUCT(G$14:G$23,$E$14:$E$23) -> 0.61728395 | H33: =SUMPRODUCT(H$14:H$23,$E$14:$E$23) -> 0.73701485 | I33: =SUMPRODUCT(I$14:I$23,$E$14:$E$23) -> 1.3091834 | J33: =SUMPRODUCT(J$14:J$23,$E$14:$E$23) -> 0.95374107 | K33: =SUMPRODUCT(K$14:K$23,$E$14:$E$23) -> 0.91661121 | L33: =SUMPRODUCT(L$14:L$23,$E$14:$E$23) -> 1.3905545 | M33: =SUMPRODUCT(M$14:M$23,$E$14:$E$23) -> 1.3460348 | ... O33: =SUMPRODUCT(O$14:O$23,$E$14:$E$23) -> 0.98579138
A34: Cup and packaging cost | F34: =SUMPRODUCT(F$24:F$29,$E$24:$E$29) -> 0.13402062 | G34: =SUMPRODUCT(G$24:G$29,$E$24:$E$29) -> 0.27835052 | H34: =SUMPRODUCT(H$24:H$29,$E$24:$E$29) -> 0.13402062 | I34: =SUMPRODUCT(I$24:I$29,$E$24:$E$29) -> 0.27835052 | J34: =SUMPRODUCT(J$24:J$29,$E$24:$E$29) -> 0.24742268 | K34: =SUMPRODUCT(K$24:K$29,$E$24:$E$29) -> 0.24742268 | L34: =SUMPRODUCT(L$24:L$29,$E$24:$E$29) -> 0.27835052 | M34: =SUMPRODUCT(M$24:M$29,$E$24:$E$29) -> 0.27835052 | ... O34: =SUMPRODUCT(O$24:O$29,$E$24:$E$29) -> 0.25773196
A35: All-in cost per drink | F35: =F33+F34 -> 0.75130457 | G35: =G33+G34 -> 0.89563447 | H35: =H33+H34 -> 0.87103547 | I35: =I33+I34 -> 1.5875339 | J35: =J33+J34 -> 1.2011637 | K35: =K33+K34 -> 1.1640339 | L35: =L33+L34 -> 1.6689051 | M35: =M33+M34 -> 1.6243853 | ... O35: =O33+O34 -> 1.2435233
A36: Menu price before sales tax | F36: =F11/(1+$B$5) -> 3.5 | G36: =G11/(1+$B$5) -> 4.5 | H36: =H11/(1+$B$5) -> 4.75 | I36: =I11/(1+$B$5) -> 6.5 | J36: =J11/(1+$B$5) -> 6 | K36: =K11/(1+$B$5) -> 6 | L36: =L11/(1+$B$5) -> 7 | M36: =M11/(1+$B$5) -> 6.5 | ... O36: =O11/(1+$B$5) -> 6.5
A37: Cost of goods without the cup | F37: =F33/F36 -> 0.17636684 | G37: =G33/G36 -> 0.13717421 | H37: =H33/H36 -> 0.15516102 | I37: =I33/I36 -> 0.20141283 | J37: =J33/J36 -> 0.15895684 | K37: =K33/K36 -> 0.15276853 | L37: =L33/L36 -> 0.19865065 | M37: =M33/M36 -> 0.20708228 | ... O37: =O33/O36 -> 0.15166021
A38: Cost of goods with the cup | F38: =F35/F36 -> 0.21465845 | G38: =G35/G36 -> 0.19902988 | H38: =H35/H36 -> 0.18337589 | I38: =I35/I36 -> 0.24423599 | J38: =J35/J36 -> 0.20019396 | K38: =K35/K36 -> 0.19400565 | L38: =L35/L36 -> 0.23841501 | M38: =M35/M36 -> 0.24990544 | ... O38: =O35/O36 -> 0.19131128
A39: Cost of goods traffic light | F39: =IF(F38<=$B$6,"On target",IF(F38<=$B$6+$B$7,"Watch the cost","Above target")) -> On target | G39: =IF(G38<=$B$6,"On target",IF(G38<=$B$6+$B$7,"Watch the cost","Above target")) -> On target | H39: =IF(H38<=$B$6,"On target",IF(H38<=$B$6+$B$7,"Watch the cost","Above target")) -> On target | I39: =IF(I38<=$B$6,"On target",IF(I38<=$B$6+$B$7,"Watch the cost","Above target")) -> On target | J39: =IF(J38<=$B$6,"On target",IF(J38<=$B$6+$B$7,"Watch the cost","Above target")) -> On target | K39: =IF(K38<=$B$6,"On target",IF(K38<=$B$6+$B$7,"Watch the cost","Above target")) -> On target | L39: =IF(L38<=$B$6,"On target",IF(L38<=$B$6+$B$7,"Watch the cost","Above target")) -> On target | M39: =IF(M38<=$B$6,"On target",IF(M38<=$B$6+$B$7,"Watch the cost","Above target")) -> On target | ... O39: =IF(O38<=$B$6,"On target",IF(O38<=$B$6+$B$7,"Watch the cost","Above target")) -> On target
A40: Margin per drink | F40: =F36-F35 -> 2.7486954 | G40: =G36-G35 -> 3.6043655 | H40: =H36-H35 -> 3.8789645 | I40: =I36-I35 -> 4.9124661 | J40: =J36-J35 -> 4.7988363 | K40: =K36-K35 -> 4.8359661 | L40: =L36-L35 -> 5.3310949 | M40: =M36-M35 -> 4.8756147 | ... O40: =O36-O35 -> 5.2564767
A41: Menu price needed to hit your target | F41: =F35/$B$6*(1+$B$5) -> 3.0052183 | G41: =G35/$B$6*(1+$B$5) -> 3.5825379 | H41: =H35/$B$6*(1+$B$5) -> 3.4841419 | I41: =I35/$B$6*(1+$B$5) -> 6.3501356 | J41: =J35/$B$6*(1+$B$5) -> 4.804655 | K41: =K35/$B$6*(1+$B$5) -> 4.6561356 | L41: =L35/$B$6*(1+$B$5) -> 6.6756202 | M41: =M35/$B$6*(1+$B$5) -> 6.4975413 | ... O41: =O35/$B$6*(1+$B$5) -> 4.9740933
A43: COST OF THE MIX (read by the "Pricing Calculator" tab) | B43: Value
A44: Sum of the sales mix | B44: =SUM($F$12:$O$12) -> 1
A45: Mix check | B45: =IF(ROUND($B$44,2)=1,"OK: the mix adds up to 100%","Check the mix: it does not add up to 100%") -> OK: the mix adds up to 100%
A46: Average ingredient cost per drink | B46: =IF($B$44=0,0,VALUE(SUMPRODUCT($F$12:$O$12,$F$33:$O$33))/$B$44) -> 1.0337941
A47: Average cup and packaging cost per drink | B47: =IF($B$44=0,0,VALUE(SUMPRODUCT($F$12:$O$12,$F$34:$O$34))/$B$44) -> 0.25237113
A48: Average all-in cost per drink | B48: =$B$46+$B$47 -> 1.2861652
A49: Average coffee per drink (g) | B49: =IF($B$44=0,0,VALUE(SUMPRODUCT($F$12:$O$12,$F$14:$O$14))/$B$44) -> 16.92
A50: Average milk per drink (fl oz) | B50: =IF($B$44=0,0,VALUE(SUMPRODUCT($F$12:$O$12,$F$32:$O$32))/$B$44) -> 5.08
A51: Average menu price per drink before sales tax | B51: =IF($B$44=0,0,VALUE(SUMPRODUCT($F$12:$O$12,$F$36:$O$36))/$B$44) -> 5.875
A52: Cost of goods of the mix (with the cup) | B52: =IF($B$51=0,0,$B$48/$B$51) -> 0.21892174
A54: The all-in cost is the drink served in a single-use cup; with reusable cups only the ingredient cost counts. Milk is a TCS food: keep it at 41 °F (5 °C) or below (the FDA Food Code cold-holding limit). The cost of goods in the financial plan is something else: the average of the mix with waste.

Sheet Pricing Calculator
A1: COFFEE CART PRICING CALCULATOR — FROM THE COST PER DRINK TO THE QUOTE
A2: Type only in the GREEN cells: everything else is calculated. Amounts are before sales tax unless the row says otherwise. The defaults are kit estimates (US ratios for drinks and staffing): replace them with your own.
A4: EVENT DETAILS | B4: Value | C4: Notes
A5: Client type | B5: Private event (hosted) | C5: Private event, Corporate or Festival or market: they change the target margin, the organizer fee, the payments and the cancellation tiers (table at the bottom). At a festival, "guests" are the drinks you expect to sell.
A6: Expected guests (at a festival or market, expected drinks) | B6: 130 | C6: Whole number of guests you serve.
A7: Service length (sets the drinks per guest) | B7: Over 2 and up to 4 hours | C7: Drinks per guest by the hours the bar is open: table at the bottom (Kit estimate from US ratios). Not used at festivals.
A8: Time of day | B8: Evening (after dinner) | C8: Morning +25%, evening after dinner −10% (Kit estimate from US ratios). It adjusts the drinks per guest. Not used at festivals.
A9: Served in | B9: Single-use compostable cups | C9: Single-use compostable cups add the cup, lid and sleeve to the cost. Reusable cups (the venue's china) carry no cup cost; some venues and cities ask for them.
A10: Service hours (bar open) | B10: 3 | C10: Used for the drinks per hour and for staffing.
A11: Hours per person outside service (loading, travel, setup and cleanup) | B11: 5 | C11: Kit estimate: a 2-hour event takes a 7-9 hour shift (grindkit.app). Use your own.
A12: Pastries per guest (your cost, from a licensed bakery) | B12: 0.75 | C12: What the pastries you add to the package cost you. 0 if you do not offer them.
A13: Rentals billed to the client (tent, tables, extra cups) | B13: 0 | C13: What the rental company charges you for this event.
A14: Power at the venue | B14: Dedicated 220V circuit | C14: A standard 110-120V outlet on a 20-amp circuit gives about 2.4 kW. A 2-group machine at 220V draws about 3.4 kW (NEMA 6-20 plug, 15-17 A): it needs a dedicated 220V circuit or a generator. A compact machine can run on 110V.
A15: Generator: cost per event (fuel and wear, only without an outlet) | B15: 60 | C15: Kit estimate. Only added if you choose "No outlet (generator)".
A16: Power draw of your 2-group machine (kW) | B16: 3.4 | C16: The example machine: 3,400 W at 220V. Check the rating plate of yours.
A17: Hourly wage of a barista | B17: 20 | C17: Kit estimate: between the event barista ($19 per hour) and the lead barista ($20) of the financial plan; Flashquotes models $25 per hour. Use your own.
A18: Payroll taxes on wages (%) | B18: 0.1 | C18: FICA (7.65%) plus federal and state unemployment taxes, as in the financial plan. Workers' comp is in your insurance.
A19: Miles one way (base to venue) | B19: 25 | C19: Charged round trip on a separate line, with no margin (at a festival it is your own cost).
A20: Free travel radius (miles one way) | B20: 20 | C20: Many operators include the first 20-30 miles and charge beyond them (grindkit.app).
A21: Travel rate per mile (charged round trip) | B21: 1.25 | C21: flashquotes.com shows $1.25 per mile round trip. Use your own.
A22: Sales tax rate | B22: 0.08 | C22: Example rate applied to the whole invoice. Many states tax catering, including the staff and extras (some tax the travel fee too); at festivals you collect it on each drink. Look up your state and city.
A23: Festival: average price per drink you will charge (before sales tax) | B23: 6.5 | C23: Kit estimate: about $6.50 per drink. See the average menu price of your mix on the "Cost per Drink" tab. Only used for festivals and markets.
A24: Festival: flat booth fee | B24: 0 | C24: A flat fee per spot, if the organizer charges one. Festivals only.
A25: Festival: minimum sales guarantee from the organizer (0 if none) | B25: 0 | C25: Some organizers guarantee a minimum and pay the difference if your drink sales fall short. Festivals only.
A26: Days before the event if the client cancels | B26: 45 | C26: Pick the days and the sheet shows the tier and what you keep.
A28: CALCULATION | B28: Value | C28: Notes
A29: LOGISTICS (scaling table)
A30: Drinks per guest for this service length | B30: =INDEX('Pricing Calculator'!$B$113:$B$117,MATCH($B$7,'Pricing Calculator'!$A$113:$A$117,0)) -> 1.4 | C30: Looked up in the table at the bottom.
A31: Time-of-day adjustment | B31: =INDEX('Pricing Calculator'!$B$120:$B$122,MATCH($B$8,'Pricing Calculator'!$A$120:$A$122,0)) -> -0.1 | C31: Looked up in the table at the bottom.
A32: Drinks served | B32: =IF($B$5='Pricing Calculator'!$D$133,$B$6,ROUNDUP(ROUND($B$6*$B$30*(1+$B$31),2),0)) -> 164 | C32: Guests × drinks per guest × (1 + adjustment), rounded up. At a festival, the expected drinks.
A33: Drinks per hour (average) | B33: =$B$32/$B$10 -> 54.666667
A34: Baristas needed | B34: =MAX(1,ROUNDUP(ROUND($B$33*'Pricing Calculator'!$B$95/'Pricing Calculator'!$B$94,2),0)) -> 2 | C34: Drinks per hour × peak factor ÷ what one barista makes, rounded up.
A35: 2-group machines (stations) | B35: =ROUNDUP($B$34/'Pricing Calculator'!$B$96,0) -> 1 | C35: Two baristas per machine; a second station comes in when the peak does not fit on one.
A36: Groups in total | B36: =$B$35*'Pricing Calculator'!$B$97 -> 2
A37: Grinders | B37: =$B$35+'Pricing Calculator'!$B$98 -> 2 | C37: One per station plus a spare for decaf.
A38: Coffee beans (lb) | B38: =ROUNDUP($B$32*'Cost per Drink'!$B$49/'Pricing Calculator'!$B$109+'Pricing Calculator'!$B$99,1) -> 6.5 | C38: Drinks × average coffee of your mix ("Cost per Drink" tab) plus purging and dialing in.
A39: Milk and plant-based milks (gal) | B39: =ROUNDUP(ROUND($B$32*'Cost per Drink'!$B$50/'Pricing Calculator'!$B$110,2),0) -> 7 | C39: Drinks × average milk of your mix.
A40: Single-use cups or reusable cups | B40: =IF($B$9='Pricing Calculator'!$A$126,ROUNDUP(ROUND($B$6*'Pricing Calculator'!$B$101,2),0),ROUNDUP(ROUND($B$32*(1+'Pricing Calculator'!$B$100),2),0)) -> 181 | C40: Single-use: drinks plus the spares. Reusable: cups per guest with spares while they are washed.
A41: Fresh water (gal) | B41: =ROUNDUP(ROUND($B$32*'Pricing Calculator'!$B$102+'Pricing Calculator'!$B$103,2),0) -> 17 | C41: Bring a gray-water tank at least as large: you empty it at the commissary, never at the venue.
A42: POWER (warning for the contract)
A43: Power draw of the machines (kW) | B43: =$B$35*$B$16 -> 3.4 | C43: Stations × kW of your machine.
A44: Current on a 220V circuit (A) | B44: =$B$43*1000/'Pricing Calculator'!$B$104 -> 15.454545 | C44: kW × 1,000 ÷ circuit voltage.
A45: Power of a standard outlet (kW) | B45: ='Pricing Calculator'!$B$106*'Pricing Calculator'!$B$105/1000 -> 2.4 | C45: A 20-amp circuit at 120V gives about 2.4 kW. Grinders, fridge and lights need their own margin.
A46: Minimum inverter generator (kW running) | B46: =ROUNDUP(ROUND($B$43*'Pricing Calculator'!$B$107,2),1) -> 5.5 | C46: kW × sizing factor, rounded up: one 3.4 kW machine needs a 5.5 kW (5,500 W) inverter generator.
A47: Power needed · A compact machine can run on a standard outlet; a 220V 2-group machine cannot. | B47: =IF($B$43<=$B$45,'Pricing Calculator'!$A$129,"Dedicated 220V circuit or generator") -> Dedicated 220V circuit or generator
A48: POWER WARNING · The kit's contract asks for the circuit in writing: voltage, amps and distance. | B48: =IF($B$14='Pricing Calculator'!$A$131,"No outlet: bring the generator (minimum kW in its row) and ask the venue and the fire marshal where it can go",IF(AND($B$43>$B$45,$B$14='Pricing Calculator'!$A$129),"WARNING: a standard 110V outlet cannot run your machines: get a dedicated 220V circuit in writing or bring the generator","Power covered: confirm the circuit, its voltage and amps, and the distance in writing in your contract")) -> Power covered: confirm the circuit, its voltage and amps, and the distance in writing in your contract
A49: DIRECT COST
A50: Drink cost | B50: =$B$32*IF($B$9='Pricing Calculator'!$A$126,'Cost per Drink'!$B$46,'Cost per Drink'!$B$48) -> 210.93109 | C50: Drinks × average cost of the mix from the "Cost per Drink" tab (with the cup if single-use).
A51: Pastry cost | B51: =$B$12*$B$6 -> 97.5
A52: Staff cost (wages + payroll taxes) | B52: =$B$34*($B$10+$B$11)*$B$17*(1+$B$18) -> 352 | C52: Baristas × (service hours + hours outside service) × hourly cost. If you work the bar yourself, count yourself: it is your opportunity cost.
A53: Generator | B53: =IF($B$14='Pricing Calculator'!$A$131,$B$15,0) -> 0
A54: Rentals billed to the client | B54: =$B$13 -> 0
A55: Travel to the festival (your own cost) | B55: =IF($B$5='Pricing Calculator'!$D$133,$B$19*2*$B$21,0) -> 0 | C55: Nobody pays your travel at a festival: it is part of the cost. For hosted events it goes on its own line.
A56: Total direct cost | B56: =$B$50+$B$51+$B$52+$B$53+$B$54+$B$55 -> 660.43109
A57: Direct cost per guest | B57: =$B$56/$B$6 -> 5.0802392
A58: PRICE AND QUOTE
A59: Target margin for this client type | B59: =INDEX('Pricing Calculator'!$B$134:$D$134,MATCH($B$5,'Pricing Calculator'!$B$133:$D$133,0)) -> 0.65 | C59: From the client table at the bottom.
A60: Organizer fee for this client type | B60: =INDEX('Pricing Calculator'!$B$135:$D$135,MATCH($B$5,'Pricing Calculator'!$B$133:$D$133,0)) -> 0 | C60: From the client table at the bottom. Festivals only.
A61: PRICE PER GUEST BEFORE SALES TAX (MINIMUM) | B61: =ROUNDUP($B$56/(1-$B$59-$B$60)/$B$6*2,0)/2 -> 15 | C61: Cost ÷ (1 − margin − fee) ÷ guests, rounded up to the next $0.50: the lowest price that reaches your target margin. At a festival it is the lowest price per drink that covers cost, fee and margin: compare it with yours.
A62: Price per guest incl. sales tax | B62: =$B$61*(1+$B$22) -> 16.2 | C62: For reference: US quotes show the price before tax and add the sales tax on the invoice.
A63: Coffee service subtotal before sales tax | B63: =$B$61*$B$6 -> 1950 | C63: Price per guest × guests.
A64: Same price per service hour (before sales tax) | B64: =$B$63/$B$10 -> 650 | C64: Subtotal ÷ service hours: to compare with an hourly rate.
A65: Same price per drink (before sales tax) | B65: =$B$63/$B$32 -> 11.890244 | C65: Subtotal ÷ drinks: to compare with a per-drink price.
A66: Travel fee (round trip beyond the free radius, no margin) | B66: =IF($B$5='Pricing Calculator'!$D$133,0,MAX(0,$B$19-$B$20)*2*$B$21) -> 12.5 | C66: Its own line on the quote.
A67: Taxable amount | B67: =$B$63+$B$66 -> 1962.5
A68: Sales tax | B68: =$B$67*$B$22 -> 157
A69: QUOTE TOTAL (incl. sales tax) | B69: =$B$67+$B$68 -> 2119.5
A70: PAYMENTS
A71: Payment 1: retainer at booking | B71: =$B$69*INDEX('Pricing Calculator'!$B$136:$D$136,MATCH($B$5,'Pricing Calculator'!$B$133:$D$133,0)) -> 635.85 | C71: Credited toward the price. Send a receipt for every payment, the retainer too.
A72: Payment 2: balance before the event | B72: =$B$69*INDEX('Pricing Calculator'!$B$137:$D$137,MATCH($B$5,'Pricing Calculator'!$B$133:$D$133,0)) -> 1483.65 | C72: Private events: 14 days before.
A73: Payment 3: balance net 30 after the invoice | B73: =$B$69*INDEX('Pricing Calculator'!$B$138:$D$138,MATCH($B$5,'Pricing Calculator'!$B$133:$D$133,0)) -> 0 | C73: Corporate.
A74: Payment 4: at the point of sale | B74: =$B$69*INDEX('Pricing Calculator'!$B$139:$D$139,MATCH($B$5,'Pricing Calculator'!$B$133:$D$133,0)) -> 0 | C74: Festivals and markets.
A75: Organizer fee on the subtotal | B75: =$B$63*$B$60 -> 0
A76: Gross margin in dollars | B76: =$B$63-$B$56-$B$75 -> 1289.5689 | C76: On the subtotal, without the travel fee.
A77: Gross margin (calculated) | B77: =IF($B$63=0,0,$B$76/$B$63) -> 0.66131739 | C77: Comes from the costs, never typed. It stays at or above the target because the price is rounded up.
A78: CANCELLATION (tiers with no gaps)
A79: Tier for the days you chose · Looks at the "Days before the event" input. | B79: =IF($B$26>=INDEX('Pricing Calculator'!$B$140:$D$140,MATCH($B$5,'Pricing Calculator'!$B$133:$D$133,0)),INDEX('Pricing Calculator'!$B$147:$D$147,MATCH($B$5,'Pricing Calculator'!$B$133:$D$133,0)),IF($B$26>=INDEX('Pricing Calculator'!$B$141:$D$141,MATCH($B$5,'Pricing Calculator'!$B$133:$D$133,0)),INDEX('Pricing Calculator'!$B$148:$D$148,MATCH($B$5,'Pricing Calculator'!$B$133:$D$133,0)),IF($B$26>=INDEX('Pricing Calculator'!$B$142:$D$142,MATCH($B$5,'Pricing Calculator'!$B$133:$D$133,0)),INDEX('Pricing Calculator'!$B$149:$D$149,MATCH($B$5,'Pricing Calculator'!$B$133:$D$133,0)),INDEX('Pricing Calculator'!$B$150:$D$150,MATCH($B$5,'Pricing Calculator'!$B$133:$D$133,0))))) -> From 30 to less than 60 days
A80: Share you keep in that tier | B80: =IF($B$26>=INDEX('Pricing Calculator'!$B$140:$D$140,MATCH($B$5,'Pricing Calculator'!$B$133:$D$133,0)),INDEX('Pricing Calculator'!$B$143:$D$143,MATCH($B$5,'Pricing Calculator'!$B$133:$D$133,0)),IF($B$26>=INDEX('Pricing Calculator'!$B$141:$D$141,MATCH($B$5,'Pricing Calculator'!$B$133:$D$133,0)),INDEX('Pricing Calculator'!$B$144:$D$144,MATCH($B$5,'Pricing Calculator'!$B$133:$D$133,0)),IF($B$26>=INDEX('Pricing Calculator'!$B$142:$D$142,MATCH($B$5,'Pricing Calculator'!$B$133:$D$133,0)),INDEX('Pricing Calculator'!$B$145:$D$145,MATCH($B$5,'Pricing Calculator'!$B$133:$D$133,0)),INDEX('Pricing Calculator'!$B$146:$D$146,MATCH($B$5,'Pricing Calculator'!$B$133:$D$133,0))))) -> 0.3
A81: Amount you keep if the client cancels that day (in the last tier, before you deduct the costs you save) | B81: =$B$69*$B$80 -> 635.85
A82: Amount kept: tier 1 (the earliest) | B82: =$B$69*INDEX('Pricing Calculator'!$B$143:$D$143,MATCH($B$5,'Pricing Calculator'!$B$133:$D$133,0)) -> 211.95 | C82: The cutoffs of each client type are in the table at the bottom.
A83: Amount kept: tier 2 | B83: =$B$69*INDEX('Pricing Calculator'!$B$144:$D$144,MATCH($B$5,'Pricing Calculator'!$B$133:$D$133,0)) -> 635.85
A84: Amount kept: tier 3 | B84: =$B$69*INDEX('Pricing Calculator'!$B$145:$D$145,MATCH($B$5,'Pricing Calculator'!$B$133:$D$133,0)) -> 1271.7
A85: Amount kept: tier 4 (the latest, or a no-show) | B85: =$B$69*INDEX('Pricing Calculator'!$B$146:$D$146,MATCH($B$5,'Pricing Calculator'!$B$133:$D$133,0)) -> 2119.5
A86: FESTIVAL OR MARKET: THE DAY AHEAD (only if the client type is a festival)
A87: Variable cost per drink (drink + pastry) | B87: =($B$50+$B$51)/$B$6 -> 2.3725469
A88: Expected sales (drinks × average price, or the minimum sales guarantee if higher; before sales tax) | B88: =IF($B$5='Pricing Calculator'!$D$133,MAX($B$6*$B$23,$B$25),0) -> 0
A89: Organizer fee (% of sales + flat booth fee) | B89: =IF($B$5='Pricing Calculator'!$D$133,$B$88*$B$60+$B$24,0) -> 0
A90: Result of the day (sales − fee − cost) | B90: =IF($B$5='Pricing Calculator'!$D$133,$B$88-$B$89-$B$56,0) -> 0 | C90: Before income tax and the fixed costs of the business (cart, insurance, commissary).
A91: Drinks needed to cover the costs of the day | B91: =IF($B$5='Pricing Calculator'!$D$133,IF($B$23*(1-$B$60)-$B$87<=0,0,ROUNDUP(($B$52+$B$53+$B$54+$B$55+$B$24)/($B$23*(1-$B$60)-$B$87),0)),0) -> 0 | C91: Costs of the day that do not depend on the drinks ÷ what each drink leaves after the fee (without the guarantee).
A93: SCALING RULES (kit estimates from US ratios) | B93: Value
A94: Drinks per hour one barista makes on a 2-group machine | B94: 55 | C94: One cart and one barista make 50-65 drinks an hour (flashquotes.com; "50 cups per hour" at coffeecartboys.com). The kit uses 55.
A95: Peak factor over the hourly average (the line builds after dinner or at the breaks) | B95: 1.3 | C95: Kit estimate: the peak hour runs about 30% above the average.
A96: Baristas working one 2-group machine | B96: 2 | C96: Kit estimate: one pulls shots while the other steams milk; above that, add a second station.
A97: Groups on one machine | B97: 2 | C97: The example machines are 2-group machines.
A98: Spare grinders (decaf or batch brew) on top of one per station | B98: 1 | C98: Kit estimate: one espresso grinder per station plus one for decaf.
A99: Coffee for purging and dialing in per event (lb) | B99: 0.33 | C99: Kit estimate: about 150 g (0.33 lb) per event.
A100: Spare single-use cups on top of the drinks | B100: 0.1 | C100: Kit estimate: spills, remakes and courtesy drinks.
A101: Reusable cups per guest (with spares while they are washed) | B101: 1.25 | C101: Kit estimate: china for about 160 at a wedding of 130 guests.
A102: Fresh water per drink (gallons: shots, steam and rinsing pitchers) | B102: 0.07 | C102: Kit estimate: about 9 fl oz per drink.
A103: Fixed fresh water per event (gallons: hand sink, cleaning and reserve) | B103: 5 | C103: Kit estimate. Your county sets the size of the hand-sink tanks.
...

Sheet 3 Example Quotes
A1: 3 EXAMPLE QUOTES — with the same formulas as the "Pricing Calculator" tab
A2: Kit estimates to show how the calculation works, not market prices: change the inputs on "Pricing Calculator" to quote your own events. The tables (margin and payments by client type, service lengths, scaling) are at the bottom of that tab and the drink mix is on "Cost per Drink"; they move these examples too.
A4: EVENT DETAILS | B4: Wedding coffee bar after dinner | C4: Corporate morning meeting | D4: Community festival, guest-pay
A5: Client type | B5: Private event (hosted) | C5: Corporate (hosted) | D5: Festival or market (guest-pay)
A6: Expected guests (at a festival or market, expected drinks) | B6: 130 | C6: 90 | D6: 150
A7: Service length (sets the drinks per guest) | B7: Over 2 and up to 4 hours | C7: Up to 2 hours | D7: Up to 2 hours
A8: Time of day | B8: Evening (after dinner) | C8: Morning (breakfast and mid-morning coffee) | D8: Morning (breakfast and mid-morning coffee)
A9: Served in | B9: Single-use compostable cups | C9: Single-use compostable cups | D9: Single-use compostable cups
A10: Service hours (bar open) | B10: 3 | C10: 2 | D10: 4
A11: Hours per person outside service (loading, travel, setup and cleanup) | B11: 5 | C11: 5 | D11: 3
A12: Pastries per guest (your cost, from a licensed bakery) | B12: 0.75 | C12: 0 | D12: 0
A13: Rentals billed to the client (tent, tables, extra cups) | B13: 0 | C13: 0 | D13: 0
A14: Power at the venue | B14: Dedicated 220V circuit | C14: Dedicated 220V circuit | D14: No outlet (generator)
A15: Generator: cost per event (fuel and wear, only without an outlet) | B15: 60 | C15: 60 | D15: 60
A16: Power draw of your 2-group machine (kW) | B16: 3.4 | C16: 3.4 | D16: 3.4
A17: Hourly wage of a barista | B17: 20 | C17: 20 | D17: 20
A18: Payroll taxes on wages (%) | B18: 0.1 | C18: 0.1 | D18: 0.1
A19: Miles one way (base to venue) | B19: 25 | C19: 15 | D19: 15
A20: Free travel radius (miles one way) | B20: 20 | C20: 20 | D20: 20
A21: Travel rate per mile (charged round trip) | B21: 1.25 | C21: 1.25 | D21: 1.25
A22: Sales tax rate | B22: 0.08 | C22: 0.08 | D22: 0.08
A23: Festival: average price per drink you will charge (before sales tax) | B23: 6.5 | C23: 6.5 | D23: 6.5
A24: Festival: flat booth fee | B24: 0 | C24: 0 | D24: 0
A25: Festival: minimum sales guarantee from the organizer (0 if none) | B25: 0 | C25: 0 | D25: 800
A26: Days before the event if the client cancels | B26: 45 | C26: 20 | D26: 45
A28: RESULT | B28: Wedding coffee bar after dinner | C28: Corporate morning meeting | D28: Community festival, guest-pay
A29: LOGISTICS (scaling table)
A30: Drinks per guest for this service length | B30: =INDEX('Pricing Calculator'!$B$113:$B$117,MATCH($B$7,'Pricing Calculator'!$A$113:$A$117,0)) -> 1.4 | C30: =INDEX('Pricing Calculator'!$B$113:$B$117,MATCH($C$7,'Pricing Calculator'!$A$113:$A$117,0)) -> 1 | D30: =INDEX('Pricing Calculator'!$B$113:$B$117,MATCH($D$7,'Pricing Calculator'!$A$113:$A$117,0)) -> 1
A31: Time-of-day adjustment | B31: =INDEX('Pricing Calculator'!$B$120:$B$122,MATCH($B$8,'Pricing Calculator'!$A$120:$A$122,0)) -> -0.1 | C31: =INDEX('Pricing Calculator'!$B$120:$B$122,MATCH($C$8,'Pricing Calculator'!$A$120:$A$122,0)) -> 0.25 | D31: =INDEX('Pricing Calculator'!$B$120:$B$122,MATCH($D$8,'Pricing Calculator'!$A$120:$A$122,0)) -> 0.25
A32: Drinks served | B32: =IF($B$5='Pricing Calculator'!$D$133,$B$6,ROUNDUP(ROUND($B$6*$B$30*(1+$B$31),2),0)) -> 164 | C32: =IF($C$5='Pricing Calculator'!$D$133,$C$6,ROUNDUP(ROUND($C$6*$C$30*(1+$C$31),2),0)) -> 113 | D32: =IF($D$5='Pricing Calculator'!$D$133,$D$6,ROUNDUP(ROUND($D$6*$D$30*(1+$D$31),2),0)) -> 150
A33: Drinks per hour (average) | B33: =$B$32/$B$10 -> 54.666667 | C33: =$C$32/$C$10 -> 56.5 | D33: =$D$32/$D$10 -> 37.5
A34: Baristas needed | B34: =MAX(1,ROUNDUP(ROUND($B$33*'Pricing Calculator'!$B$95/'Pricing Calculator'!$B$94,2),0)) -> 2 | C34: =MAX(1,ROUNDUP(ROUND($C$33*'Pricing Calculator'!$B$95/'Pricing Calculator'!$B$94,2),0)) -> 2 | D34: =MAX(1,ROUNDUP(ROUND($D$33*'Pricing Calculator'!$B$95/'Pricing Calculator'!$B$94,2),0)) -> 1
A35: 2-group machines (stations) | B35: =ROUNDUP($B$34/'Pricing Calculator'!$B$96,0) -> 1 | C35: =ROUNDUP($C$34/'Pricing Calculator'!$B$96,0) -> 1 | D35: =ROUNDUP($D$34/'Pricing Calculator'!$B$96,0) -> 1
A36: Groups in total | B36: =$B$35*'Pricing Calculator'!$B$97 -> 2 | C36: =$C$35*'Pricing Calculator'!$B$97 -> 2 | D36: =$D$35*'Pricing Calculator'!$B$97 -> 2
A37: Grinders | B37: =$B$35+'Pricing Calculator'!$B$98 -> 2 | C37: =$C$35+'Pricing Calculator'!$B$98 -> 2 | D37: =$D$35+'Pricing Calculator'!$B$98 -> 2
A38: Coffee beans (lb) | B38: =ROUNDUP($B$32*'Cost per Drink'!$B$49/'Pricing Calculator'!$B$109+'Pricing Calculator'!$B$99,1) -> 6.5 | C38: =ROUNDUP($C$32*'Cost per Drink'!$B$49/'Pricing Calculator'!$B$109+'Pricing Calculator'!$B$99,1) -> 4.6 | D38: =ROUNDUP($D$32*'Cost per Drink'!$B$49/'Pricing Calculator'!$B$109+'Pricing Calculator'!$B$99,1) -> 6
A39: Milk and plant-based milks (gal) | B39: =ROUNDUP(ROUND($B$32*'Cost per Drink'!$B$50/'Pricing Calculator'!$B$110,2),0) -> 7 | C39: =ROUNDUP(ROUND($C$32*'Cost per Drink'!$B$50/'Pricing Calculator'!$B$110,2),0) -> 5 | D39: =ROUNDUP(ROUND($D$32*'Cost per Drink'!$B$50/'Pricing Calculator'!$B$110,2),0) -> 6
A40: Single-use cups or reusable cups | B40: =IF($B$9='Pricing Calculator'!$A$126,ROUNDUP(ROUND($B$6*'Pricing Calculator'!$B$101,2),0),ROUNDUP(ROUND($B$32*(1+'Pricing Calculator'!$B$100),2),0)) -> 181 | C40: =IF($C$9='Pricing Calculator'!$A$126,ROUNDUP(ROUND($C$6*'Pricing Calculator'!$B$101,2),0),ROUNDUP(ROUND($C$32*(1+'Pricing Calculator'!$B$100),2),0)) -> 125 | D40: =IF($D$9='Pricing Calculator'!$A$126,ROUNDUP(ROUND($D$6*'Pricing Calculator'!$B$101,2),0),ROUNDUP(ROUND($D$32*(1+'Pricing Calculator'!$B$100),2),0)) -> 165
A41: Fresh water (gal) | B41: =ROUNDUP(ROUND($B$32*'Pricing Calculator'!$B$102+'Pricing Calculator'!$B$103,2),0) -> 17 | C41: =ROUNDUP(ROUND($C$32*'Pricing Calculator'!$B$102+'Pricing Calculator'!$B$103,2),0) -> 13 | D41: =ROUNDUP(ROUND($D$32*'Pricing Calculator'!$B$102+'Pricing Calculator'!$B$103,2),0) -> 16
A42: POWER (warning for the contract)
A43: Power draw of the machines (kW) | B43: =$B$35*$B$16 -> 3.4 | C43: =$C$35*$C$16 -> 3.4 | D43: =$D$35*$D$16 -> 3.4
A44: Current on a 220V circuit (A) | B44: =$B$43*1000/'Pricing Calculator'!$B$104 -> 15.454545 | C44: =$C$43*1000/'Pricing Calculator'!$B$104 -> 15.454545 | D44: =$D$43*1000/'Pricing Calculator'!$B$104 -> 15.454545
A45: Power of a standard outlet (kW) | B45: ='Pricing Calculator'!$B$106*'Pricing Calculator'!$B$105/1000 -> 2.4 | C45: ='Pricing Calculator'!$B$106*'Pricing Calculator'!$B$105/1000 -> 2.4 | D45: ='Pricing Calculator'!$B$106*'Pricing Calculator'!$B$105/1000 -> 2.4
A46: Minimum inverter generator (kW running) | B46: =ROUNDUP(ROUND($B$43*'Pricing Calculator'!$B$107,2),1) -> 5.5 | C46: =ROUNDUP(ROUND($C$43*'Pricing Calculator'!$B$107,2),1) -> 5.5 | D46: =ROUNDUP(ROUND($D$43*'Pricing Calculator'!$B$107,2),1) -> 5.5
A47: Power needed | B47: =IF($B$43<=$B$45,'Pricing Calculator'!$A$129,"Dedicated 220V circuit or generator") -> Dedicated 220V circuit or generator | C47: =IF($C$43<=$C$45,'Pricing Calculator'!$A$129,"Dedicated 220V circuit or generator") -> Dedicated 220V circuit or generator | D47: =IF($D$43<=$D$45,'Pricing Calculator'!$A$129,"Dedicated 220V circuit or generator") -> Dedicated 220V circuit or generator
A48: POWER WARNING | B48: =IF($B$14='Pricing Calculator'!$A$131,"No outlet: bring the generator (minimum kW in its row) and ask the venue and the fire marshal where it can go",IF(AND($B$43>$B$45,$B$14='Pricing Calculator'!$A$129),"WARNING: a standard 110V outlet cannot run your machines: get a dedicated 220V circuit in writing or bring the generator","Power covered: confirm the circuit, its voltage and amps, and the distance in writing in your contract")) -> Power covered: confirm the circuit, its voltage and amps, and the distance in writing in your contract | C48: =IF($C$14='Pricing Calculator'!$A$131,"No outlet: bring the generator (minimum kW in its row) and ask the venue and the fire marshal where it can go",IF(AND($C$43>$C$45,$C$14='Pricing Calculator'!$A$129),"WARNING: a standard 110V outlet cannot run your machines: get a dedicated 220V circuit in writing or bring the generator","Power covered: confirm the circuit, its voltage and amps, and the distance in writing in your contract")) -> Power covered: confirm the circuit, its voltage and amps, and the distance in writing in your contract | D48: =IF($D$14='Pricing Calculator'!$A$131,"No outlet: bring the generator (minimum kW in its row) and ask the venue and the fire marshal where it can go",IF(AND($D$43>$D$45,$D$14='Pricing Calculator'!$A$129),"WARNING: a standard 110V outlet cannot run your machines: get a dedicated 220V circuit in writing or bring the generator","Power covered: confirm the circuit, its voltage and amps, and the distance in writing in your contract")) -> No outlet: bring the generator (minimum kW in its row) and ask the venue and the fire marshal where it can go
A49: DIRECT COST
A50: Drink cost | B50: =$B$32*IF($B$9='Pricing Calculator'!$A$126,'Cost per Drink'!$B$46,'Cost per Drink'!$B$48) -> 210.93109 | C50: =$C$32*IF($C$9='Pricing Calculator'!$A$126,'Cost per Drink'!$B$46,'Cost per Drink'!$B$48) -> 145.33667 | D50: =$D$32*IF($D$9='Pricing Calculator'!$A$126,'Cost per Drink'!$B$46,'Cost per Drink'!$B$48) -> 192.92478
A51: Pastry cost | B51: =$B$12*$B$6 -> 97.5 | C51: =$C$12*$C$6 -> 0 | D51: =$D$12*$D$6 -> 0
A52: Staff cost (wages + payroll taxes) | B52: =$B$34*($B$10+$B$11)*$B$17*(1+$B$18) -> 352 | C52: =$C$34*($C$10+$C$11)*$C$17*(1+$C$18) -> 308 | D52: =$D$34*($D$10+$D$11)*$D$17*(1+$D$18) -> 154
A53: Generator | B53: =IF($B$14='Pricing Calculator'!$A$131,$B$15,0) -> 0 | C53: =IF($C$14='Pricing Calculator'!$A$131,$C$15,0) -> 0 | D53: =IF($D$14='Pricing Calculator'!$A$131,$D$15,0) -> 60
A54: Rentals billed to the client | B54: =$B$13 -> 0 | C54: =$C$13 -> 0 | D54: =$D$13 -> 0
A55: Travel to the festival (your own cost) | B55: =IF($B$5='Pricing Calculator'!$D$133,$B$19*2*$B$21,0) -> 0 | C55: =IF($C$5='Pricing Calculator'!$D$133,$C$19*2*$C$21,0) -> 0 | D55: =IF($D$5='Pricing Calculator'!$D$133,$D$19*2*$D$21,0) -> 37.5
A56: Total direct cost | B56: =$B$50+$B$51+$B$52+$B$53+$B$54+$B$55 -> 660.43109 | C56: =$C$50+$C$51+$C$52+$C$53+$C$54+$C$55 -> 453.33667 | D56: =$D$50+$D$51+$D$52+$D$53+$D$54+$D$55 -> 444.42478
A57: Direct cost per guest | B57: =$B$56/$B$6 -> 5.0802392 | C57: =$C$56/$C$6 -> 5.0370741 | D57: =$D$56/$D$6 -> 2.9628319
A58: PRICE AND QUOTE
A59: Target margin for this client type | B59: =INDEX('Pricing Calculator'!$B$134:$D$134,MATCH($B$5,'Pricing Calculator'!$B$133:$D$133,0)) -> 0.65 | C59: =INDEX('Pricing Calculator'!$B$134:$D$134,MATCH($C$5,'Pricing Calculator'!$B$133:$D$133,0)) -> 0.6 | D59: =INDEX('Pricing Calculator'!$B$134:$D$134,MATCH($D$5,'Pricing Calculator'!$B$133:$D$133,0)) -> 0.2
A60: Organizer fee for this client type | B60: =INDEX('Pricing Calculator'!$B$135:$D$135,MATCH($B$5,'Pricing Calculator'!$B$133:$D$133,0)) -> 0 | C60: =INDEX('Pricing Calculator'!$B$135:$D$135,MATCH($C$5,'Pricing Calculator'!$B$133:$D$133,0)) -> 0 | D60: =INDEX('Pricing Calculator'!$B$135:$D$135,MATCH($D$5,'Pricing Calculator'!$B$133:$D$133,0)) -> 0.15
A61: PRICE PER GUEST BEFORE SALES TAX (MINIMUM) | B61: =ROUNDUP($B$56/(1-$B$59-$B$60)/$B$6*2,0)/2 -> 15 | C61: =ROUNDUP($C$56/(1-$C$59-$C$60)/$C$6*2,0)/2 -> 13 | D61: =ROUNDUP($D$56/(1-$D$59-$D$60)/$D$6*2,0)/2 -> 5
A62: Price per guest incl. sales tax | B62: =$B$61*(1+$B$22) -> 16.2 | C62: =$C$61*(1+$C$22) -> 14.04 | D62: =$D$61*(1+$D$22) -> 5.4
A63: Coffee service subtotal before sales tax | B63: =$B$61*$B$6 -> 1950 | C63: =$C$61*$C$6 -> 1170 | D63: =$D$61*$D$6 -> 750
A64: Same price per service hour (before sales tax) | B64: =$B$63/$B$10 -> 650 | C64: =$C$63/$C$10 -> 585 | D64: =$D$63/$D$10 -> 187.5
A65: Same price per drink (before sales tax) | B65: =$B$63/$B$32 -> 11.890244 | C65: =$C$63/$C$32 -> 10.353982 | D65: =$D$63/$D$32 -> 5
A66: Travel fee (round trip beyond the free radius, no margin) | B66: =IF($B$5='Pricing Calculator'!$D$133,0,MAX(0,$B$19-$B$20)*2*$B$21) -> 12.5 | C66: =IF($C$5='Pricing Calculator'!$D$133,0,MAX(0,$C$19-$C$20)*2*$C$21) -> 0 | D66: =IF($D$5='Pricing Calculator'!$D$133,0,MAX(0,$D$19-$D$20)*2*$D$21) -> 0
A67: Taxable amount | B67: =$B$63+$B$66 -> 1962.5 | C67: =$C$63+$C$66 -> 1170 | D67: =$D$63+$D$66 -> 750
A68: Sales tax | B68: =$B$67*$B$22 -> 157 | C68: =$C$67*$C$22 -> 93.6 | D68: =$D$67*$D$22 -> 60
A69: QUOTE TOTAL (incl. sales tax) | B69: =$B$67+$B$68 -> 2119.5 | C69: =$C$67+$C$68 -> 1263.6 | D69: =$D$67+$D$68 -> 810
A70: PAYMENTS
A71: Payment 1: retainer at booking | B71: =$B$69*INDEX('Pricing Calculator'!$B$136:$D$136,MATCH($B$5,'Pricing Calculator'!$B$133:$D$133,0)) -> 635.85 | C71: =$C$69*INDEX('Pricing Calculator'!$B$136:$D$136,MATCH($C$5,'Pricing Calculator'!$B$133:$D$133,0)) -> 379.08 | D71: =$D$69*INDEX('Pricing Calculator'!$B$136:$D$136,MATCH($D$5,'Pricing Calculator'!$B$133:$D$133,0)) -> 0
A72: Payment 2: balance before the event | B72: =$B$69*INDEX('Pricing Calculator'!$B$137:$D$137,MATCH($B$5,'Pricing Calculator'!$B$133:$D$133,0)) -> 1483.65 | C72: =$C$69*INDEX('Pricing Calculator'!$B$137:$D$137,MATCH($C$5,'Pricing Calculator'!$B$133:$D$133,0)) -> 0 | D72: =$D$69*INDEX('Pricing Calculator'!$B$137:$D$137,MATCH($D$5,'Pricing Calculator'!$B$133:$D$133,0)) -> 0
A73: Payment 3: balance net 30 after the invoice | B73: =$B$69*INDEX('Pricing Calculator'!$B$138:$D$138,MATCH($B$5,'Pricing Calculator'!$B$133:$D$133,0)) -> 0 | C73: =$C$69*INDEX('Pricing Calculator'!$B$138:$D$138,MATCH($C$5,'Pricing Calculator'!$B$133:$D$133,0)) -> 884.52 | D73: =$D$69*INDEX('Pricing Calculator'!$B$138:$D$138,MATCH($D$5,'Pricing Calculator'!$B$133:$D$133,0)) -> 0
A74: Payment 4: at the point of sale | B74: =$B$69*INDEX('Pricing Calculator'!$B$139:$D$139,MATCH($B$5,'Pricing Calculator'!$B$133:$D$133,0)) -> 0 | C74: =$C$69*INDEX('Pricing Calculator'!$B$139:$D$139,MATCH($C$5,'Pricing Calculator'!$B$133:$D$133,0)) -> 0 | D74: =$D$69*INDEX('Pricing Calculator'!$B$139:$D$139,MATCH($D$5,'Pricing Calculator'!$B$133:$D$133,0)) -> 810
A75: Organizer fee on the subtotal | B75: =$B$63*$B$60 -> 0 | C75: =$C$63*$C$60 -> 0 | D75: =$D$63*$D$60 -> 112.5
A76: Gross margin in dollars | B76: =$B$63-$B$56-$B$75 -> 1289.5689 | C76: =$C$63-$C$56-$C$75 -> 716.66333 | D76: =$D$63-$D$56-$D$75 -> 193.07522
A77: Gross margin (calculated) | B77: =IF($B$63=0,0,$B$76/$B$63) -> 0.66131739 | C77: =IF($C$63=0,0,$C$76/$C$63) -> 0.61253276 | D77: =IF($D$63=0,0,$D$76/$D$63) -> 0.25743362
A78: CANCELLATION (tiers with no gaps)
A79: Tier for the days you chose | B79: =IF($B$26>=INDEX('Pricing Calculator'!$B$140:$D$140,MATCH($B$5,'Pricing Calculator'!$B$133:$D$133,0)),INDEX('Pricing Calculator'!$B$147:$D$147,MATCH($B$5,'Pricing Calculator'!$B$133:$D$133,0)),IF($B$26>=INDEX('Pricing Calculator'!$B$141:$D$141,MATCH($B$5,'Pricing Calculator'!$B$133:$D$133,0)),INDEX('Pricing Calculator'!$B$148:$D$148,MATCH($B$5,'Pricing Calculator'!$B$133:$D$133,0)),IF($B$26>=INDEX('Pricing Calculator'!$B$142:$D$142,MATCH($B$5,'Pricing Calculator'!$B$133:$D$133,0)),INDEX('Pricing Calculator'!$B$149:$D$149,MATCH($B$5,'Pricing Calculator'!$B$133:$D$133,0)),INDEX('Pricing Calculator'!$B$150:$D$150,MATCH($B$5,'Pricing Calculator'!$B$133:$D$133,0))))) -> From 30 to less than 60 days | C79: =IF($C$26>=INDEX('Pricing Calculator'!$B$140:$D$140,MATCH($C$5,'Pricing Calculator'!$B$133:$D$133,0)),INDEX('Pricing Calculator'!$B$147:$D$147,MATCH($C$5,'Pricing Calculator'!$B$133:$D$133,0)),IF($C$26>=INDEX('Pricing Calculator'!$B$141:$D$141,MATCH($C$5,'Pricing Calculator'!$B$133:$D$133,0)),INDEX('Pricing Calculator'!$B$148:$D$148,MATCH($C$5,'Pricing Calculator'!$B$133:$D$133,0)),IF($C$26>=INDEX('Pricing Calculator'!$B$142:$D$142,MATCH($C$5,'Pricing Calculator'!$B$133:$D$133,0)),INDEX('Pricing Calculator'!$B$149:$D$149,MATCH($C$5,'Pricing Calculator'!$B$133:$D$133,0)),INDEX('Pricing Calculator'!$B$150:$D$150,MATCH($C$5,'Pricing Calculator'!$B$133:$D$133,0))))) -> From 15 to less than 30 days | D79: =IF($D$26>=INDEX('Pricing Calculator'!$B$140:$D$140,MATCH($D$5,'Pricing Calculator'!$B$133:$D$133,0)),INDEX('Pricing Calculator'!$B$147:$D$147,MATCH($D$5,'Pricing Calculator'!$B$133:$D$133,0)),IF($D$26>=INDEX('Pricing Calculator'!$B$141:$D$141,MATCH($D$5,'Pricing Calculator'!$B$133:$D$133,0)),INDEX('Pricing Calculator'!$B$148:$D$148,MATCH($D$5,'Pricing Calculator'!$B$133:$D$133,0)),IF($D$26>=INDEX('Pricing Calculator'!$B$142:$D$142,MATCH($D$5,'Pricing Calculator'!$B$133:$D$133,0)),INDEX('Pricing Calculator'!$B$149:$D$149,MATCH($D$5,'Pricing Calculator'!$B$133:$D$133,0)),INDEX('Pricing Calculator'!$B$150:$D$150,MATCH($D$5,'Pricing Calculator'!$B$133:$D$133,0))))) -> 30 days or more
A80: Share you keep in that tier | B80: =IF($B$26>=INDEX('Pricing Calculator'!$B$140:$D$140,MATCH($B$5,'Pricing Calculator'!$B$133:$D$133,0)),INDEX('Pricing Calculator'!$B$143:$D$143,MATCH($B$5,'Pricing Calculator'!$B$133:$D$133,0)),IF($B$26>=INDEX('Pricing Calculator'!$B$141:$D$141,MATCH($B$5,'Pricing Calculator'!$B$133:$D$133,0)),INDEX('Pricing Calculator'!$B$144:$D$144,MATCH($B$5,'Pricing Calculator'!$B$133:$D$133,0)),IF($B$26>=INDEX('Pricing Calculator'!$B$142:$D$142,MATCH($B$5,'Pricing Calculator'!$B$133:$D$133,0)),INDEX('Pricing Calculator'!$B$145:$D$145,MATCH($B$5,'Pricing Calculator'!$B$133:$D$133,0)),INDEX('Pricing Calculator'!$B$146:$D$146,MATCH($B$5,'Pricing Calculator'!$B$133:$D$133,0))))) -> 0.3 | C80: =IF($C$26>=INDEX('Pricing Calculator'!$B$140:$D$140,MATCH($C$5,'Pricing Calculator'!$B$133:$D$133,0)),INDEX('Pricing Calculator'!$B$143:$D$143,MATCH($C$5,'Pricing Calculator'!$B$133:$D$133,0)),IF($C$26>=INDEX('Pricing Calculator'!$B$141:$D$141,MATCH($C$5,'Pricing Calculator'!$B$133:$D$133,0)),INDEX('Pricing Calculator'!$B$144:$D$144,MATCH($C$5,'Pricing Calculator'!$B$133:$D$133,0)),IF($C$26>=INDEX('Pricing Calculator'!$B$142:$D$142,MATCH($C$5,'Pricing Calculator'!$B$133:$D$133,0)),INDEX('Pricing Calculator'!$B$145:$D$145,MATCH($C$5,'Pricing Calculator'!$B$133:$D$133,0)),INDEX('Pricing Calculator'!$B$146:$D$146,MATCH($C$5,'Pricing Calculator'!$B$133:$D$133,0))))) -> 0.3 | D80: =IF($D$26>=INDEX('Pricing Calculator'!$B$140:$D$140,MATCH($D$5,'Pricing Calculator'!$B$133:$D$133,0)),INDEX('Pricing Calculator'!$B$143:$D$143,MATCH($D$5,'Pricing Calculator'!$B$133:$D$133,0)),IF($D$26>=INDEX('Pricing Calculator'!$B$141:$D$141,MATCH($D$5,'Pricing Calculator'!$B$133:$D$133,0)),INDEX('Pricing Calculator'!$B$144:$D$144,MATCH($D$5,'Pricing Calculator'!$B$133:$D$133,0)),IF($D$26>=INDEX('Pricing Calculator'!$B$142:$D$142,MATCH($D$5,'Pricing Calculator'!$B$133:$D$133,0)),INDEX('Pricing Calculator'!$B$145:$D$145,MATCH($D$5,'Pricing Calculator'!$B$133:$D$133,0)),INDEX('Pricing Calculator'!$B$146:$D$146,MATCH($D$5,'Pricing Calculator'!$B$133:$D$133,0))))) -> 0
A81: Amount you keep if the client cancels that day (in the last tier, before you deduct the costs you save) | B81: =$B$69*$B$80 -> 635.85 | C81: =$C$69*$C$80 -> 379.08 | D81: =$D$69*$D$80 -> 0
A82: Amount kept: tier 1 (the earliest) | B82: =$B$69*INDEX('Pricing Calculator'!$B$143:$D$143,MATCH($B$5,'Pricing Calculator'!$B$133:$D$133,0)) -> 211.95 | C82: =$C$69*INDEX('Pricing Calculator'!$B$143:$D$143,MATCH($C$5,'Pricing Calculator'!$B$133:$D$133,0)) -> 126.36 | D82: =$D$69*INDEX('Pricing Calculator'!$B$143:$D$143,MATCH($D$5,'Pricing Calculator'!$B$133:$D$133,0)) -> 0
A83: Amount kept: tier 2 | B83: =$B$69*INDEX('Pricing Calculator'!$B$144:$D$144,MATCH($B$5,'Pricing Calculator'!$B$133:$D$133,0)) -> 635.85 | C83: =$C$69*INDEX('Pricing Calculator'!$B$144:$D$144,MATCH($C$5,'Pricing Calculator'!$B$133:$D$133,0)) -> 379.08 | D83: =$D$69*INDEX('Pricing Calculator'!$B$144:$D$144,MATCH($D$5,'Pricing Calculator'!$B$133:$D$133,0)) -> 0
A84: Amount kept: tier 3 | B84: =$B$69*INDEX('Pricing Calculator'!$B$145:$D$145,MATCH($B$5,'Pricing Calculator'!$B$133:$D$133,0)) -> 1271.7 | C84: =$C$69*INDEX('Pricing Calculator'!$B$145:$D$145,MATCH($C$5,'Pricing Calculator'!$B$133:$D$133,0)) -> 758.16 | D84: =$D$69*INDEX('Pricing Calculator'!$B$145:$D$145,MATCH($D$5,'Pricing Calculator'!$B$133:$D$133,0)) -> 0
A85: Amount kept: tier 4 (the latest, or a no-show) | B85: =$B$69*INDEX('Pricing Calculator'!$B$146:$D$146,MATCH($B$5,'Pricing Calculator'!$B$133:$D$133,0)) -> 2119.5 | C85: =$C$69*INDEX('Pricing Calculator'!$B$146:$D$146,MATCH($C$5,'Pricing Calculator'!$B$133:$D$133,0)) -> 1263.6 | D85: =$D$69*INDEX('Pricing Calculator'!$B$146:$D$146,MATCH($D$5,'Pricing Calculator'!$B$133:$D$133,0)) -> 0
A86: FESTIVAL OR MARKET: THE DAY AHEAD (only if the client type is a festival)
A87: Variable cost per drink (drink + pastry) | B87: =($B$50+$B$51)/$B$6 -> 2.3725469 | C87: =($C$50+$C$51)/$C$6 -> 1.6148519 | D87: =($D$50+$D$51)/$D$6 -> 1.2861652
A88: Expected sales (drinks × average price, or the minimum sales guarantee if higher; before sales tax) | B88: =IF($B$5='Pricing Calculator'!$D$133,MAX($B$6*$B$23,$B$25),0) -> 0 | C88: =IF($C$5='Pricing Calculator'!$D$133,MAX($C$6*$C$23,$C$25),0) -> 0 | D88: =IF($D$5='Pricing Calculator'!$D$133,MAX($D$6*$D$23,$D$25),0) -> 975
A89: Organizer fee (% of sales + flat booth fee) | B89: =IF($B$5='Pricing Calculator'!$D$133,$B$88*$B$60+$B$24,0) -> 0 | C89: =IF($C$5='Pricing Calculator'!$D$133,$C$88*$C$60+$C$24,0) -> 0 | D89: =IF($D$5='Pricing Calculator'!$D$133,$D$88*$D$60+$D$24,0) -> 146.25
A90: Result of the day (sales − fee − cost) | B90: =IF($B$5='Pricing Calculator'!$D$133,$B$88-$B$89-$B$56,0) -> 0 | C90: =IF($C$5='Pricing Calculator'!$D$133,$C$88-$C$89-$C$56,0) -> 0 | D90: =IF($D$5='Pricing Calculator'!$D$133,$D$88-$D$89-$D$56,0) -> 384.32522
A91: Drinks needed to cover the costs of the day | B91: =IF($B$5='Pricing Calculator'!$D$133,IF($B$23*(1-$B$60)-$B$87<=0,0,ROUNDUP(($B$52+$B$53+$B$54+$B$55+$B$24)/($B$23*(1-$B$60)-$B$87),0)),0) -> 0 | C91: =IF($C$5='Pricing Calculator'!$D$133,IF($C$23*(1-$C$60)-$C$87<=0,0,ROUNDUP(($C$52+$C$53+$C$54+$C$55+$C$24)/($C$23*(1-$C$60)-$C$87),0)),0) -> 0 | D91: =IF($D$5='Pricing Calculator'!$D$133,IF($D$23*(1-$D$60)-$D$87<=0,0,ROUNDUP(($D$52+$D$53+$D$54+$D$55+$D$24)/($D$23*(1-$D$60)-$D$87),0)),0) -> 60
A93: WHAT EACH EXAMPLE SHOWS
A94: Wedding coffee bar after dinner | B94: Private event, 130 guests (the wedding of the financial plan's example mix), a 3-hour bar after dinner in compostable cups, with a $0.75 pastry per guest and a dedicated 220V circuit. It quotes the lowest price that reaches the 65% target margin; the 30% retainer at booking and the 70% balance 14 days before. With 45 days to go, a cancellation falls in tier 2 and you keep 30%.
A95: Corporate morning meeting | B95: Corporate, 90 guests (the company event of the example mix), a 2-hour bar in the morning (+25% drinks), compostable cups and a dedicated circuit. The quote is before sales tax; 30% retainer at signing and the 70% balance net 30 after the invoice. With 20 days to go, the tier is the second and you keep 30%.
A96: Community festival, guest-pay | B96: Festival or market (a community festival): 150 drinks over 4 hours in the morning, compostable cups, a generator and a 15% organizer fee, with an $800 minimum sales guarantee. The "price per guest" is the lowest price per drink; at $6.50 a drink the day leaves about $384 before fixed costs, and, without the guarantee, below 60 drinks you would lose money: the $800 guarantee covers that risk.

Sheet Instructions
A1: HOW TO USE — Coffee Cart Pricing Calculator (Cost per Drink to Quote per Guest)
A2: Turns the cost of your drinks into a price per guest and a full quote: baristas, machines, grinders, pounds of coffee, gallons of milk, cups, power and water, subtotal, sales tax, total, payments and what you keep if the client cancels. Type only in the GREEN cells; the margin is calculated.
A3: "COST PER DRINK" TAB
A5: 1. Enter the price before sales tax, the waste and the recipe units per price unit of each ingredient (coffee, milks, cocoa, chai, syrup, tea, sugar, cups, lid, sleeve, napkin and stirrer), and the grams, fluid ounces or units of each drink. Coffee comes from the double shots per drink and the grams per double.
A6: 2. For each drink you see the ingredient cost, the all-in cost with the cup, the price before sales tax, the cost of goods with a traffic light, the margin and the menu price you would need to hit your target. The sales mix must add up to 100%: the sheet warns you.
A7: 3. The cost of ONE drink on this tab is not the cost of goods in the financial plan: that one is the average of the mix with waste (purging, dialing in and leftover milk), not a recipe. Do not copy one into the other.
A8: "PRICING CALCULATOR" TAB
A10: 4. Choose the client type (Private event, Corporate, or Festival or market), the guests, the service length (drinks per guest by the hours), the time of day and single-use or reusable cups. At a festival, guests are the drinks you expect to sell.
A11: 5. The scaling table at the bottom gives baristas, 2-group machines, grinders, pounds of coffee, gallons of milk, cups, power, the circuit you need and water. Its rules use the same assumptions as the business plan: drinks per guest by service length, 50-65 drinks per barista an hour and 18 g per double shot.
A12: 6. Enter the service hours and the hours outside service (loading, travel, setup and cleanup), the hourly wage and the payroll taxes. If you work the bar yourself, count your hours: it is your opportunity cost.
A13: 7. The price per guest is the direct cost divided by (1 − margin − fee), rounded up to the next $0.50: the lowest price that reaches your target. You also see the same price per service hour and per drink, to compare with hourly or per-drink rates.
A14: 8. US quotes show the price before sales tax and add the tax on the invoice. The travel fee goes on its own line, round trip beyond your free radius and with no margin. In the UK, prices to consumers include VAT: if you are VAT-registered, enter 0.20 as the tax rate.
... A40: Planning tool, not financial, tax or legal advice. Requirements vary by state, county and city — check with your accountant and local authorities.
