Workbook

Sheet 0. Assumptions
A1: ASSUMPTIONS — the RATES and DRIVERS of the model are typed here
A2: Change the GREEN cells: the rest of the workbook recalculates on its own. Expense items are typed on their own tab (also in green) and are not repeated here. Amounts are in your currency.
A3: BUSINESS ACTIVITY
A4: Covers per day (year-1 average) | B4: 115 | C4: Equivalent covers per day, year-1 average: about 60 dine-in (patio included from April through October) and about 55 from take-out, pickup and delivery marketplaces, which are the orders divided by the average check. A Saturday runs well above the average and a Tuesday well below it (Kit estimate). Compare it with the foot traffic on your street on a Friday night and a Tuesday at lunch, and with your own test orders
A5: Average check (excl. sales tax) | B5: 17.5 | C5: Per cover, EXCL. sales tax and tip: an order of street tacos, some quesadilla or gringa, chips & guac or a side, and a drink or so add up to about $17.50. The example uses a street taco at $4.00 on the menu (2.6 tacos per cover), a quesadilla or gringa at $11.50, chips & guac or sides at $7.00 and drinks at $3.60 (Kit estimate). Street tacos run $3.00-3.75 on casual menus in mid-size cities (menus read in October 2026). The "Menu price incl. sales tax (calculated)" row below shows the price with your local rate applied
A6: Operating days per year | B6: 308 | C6: 365 days minus 52 closed Mondays, the main holidays (Thanksgiving, Christmas, New Year's Day, July 4) and one inventory day, rounded to 308. It is the SAME figure for the P&L, break-even, scenarios and staffing hours
A7: Volume growth in year 2 | B7: 0.06 | C7: Repeat neighborhood regulars and more pickup in year 2. It applies to covers at the same average check; staffing does NOT rise with this percentage: it comes from the "Staffing" tab
A8: Volume growth in year 3 | B8: 0.04 | C8: On top of year 2. Conservative: the ceiling is set by the trompos, the griddle and the 30 seats on Friday and Saturday nights
A9: Menu price incl. sales tax (calculated) | B9: =IFERROR(IF($B$5="","",$B$5*(1+SUMPRODUCT('3-Year P&L'!$E$10:$E$11,'3-Year P&L'!$G$10:$G$11))),"") -> 18.9 | C9: =IFERROR("Average check excl. sales tax plus the weighted sales tax of your sales lines ("&TEXT(SUMPRODUCT('3-Year P&L'!$E$10:$E$11,'3-Year P&L'!$G$10:$G$11)*100,"0")&"%), rounded. In the US, menu prices usually exclude sales tax and it is added at the register; the beverage share in column H of the beverage line of the P&L only moves this average if your state taxes alcohol at another rate. In the UK, "&"menu prices include VAT.","") -> Average check excl. sales tax plus the weighted sales tax of your sales lines (8%), rounded. In the US, menu prices usually exclude sales tax and it is added at the register; the beverage share in column H of the beverage line of the P&L only moves this average if your state taxes alcohol at another rate. In the UK, menu prices include VAT.
A10: SALES MIX AND COST OF GOODS SOLD
A11: FOOD share of total sales | B11: 0.85 | C11: Share of FOOD in total sales. It is an INPUT: change it here and the P&L, the cash flow and the sales tax collected recalculate on their own
A12: BEVERAGE share of total sales | B12: =IFERROR(IF(COUNT(B11)=0,"",1-B11),"") -> 0.15 | C12: Calculated as the remainder: food + beverage = 100%
A13: Cost of goods sold on FOOD sales | B13: 0.27 | C13: Cost of goods sold on food sales: the menu averages about 25% of menu price (street tacos and quesadillas about 25%, chips & guac about 28% depending on the avocado, birria about 30%), plus 1.5 points of waste (leftover cone from the trompo and cut salsas that get thrown out) and a little prudence, because meat and tortilla prices are Kit estimates. Cost each taco with the Taco Cost & Trompo Yield Calculator
A14: Cost of goods sold on BEVERAGE sales | B14: 0.22 | C14: Weighted average of aguas frescas, sodas, water, Mexican beer and wine against their menu prices: aguas frescas and sodas cost a small share of their price, while beer and wine run higher and pull the average up. If your beer distributor lends you the tap equipment, get the keg price in writing
A15: Disposables and packaging as % of sales | B15: 0.04 | C15: Clamshells, foil, salsa cups, bags, paper, napkins and gloves for everything that leaves the shop, plus take-out containers for leftovers. Some cities and states restrict foam and single-use plastics or require utensils only on request: check your local packaging ordinances
A16: Delivery share of total sales | B16: 0.15 | C16: Sales through third-party delivery marketplaces (DoorDash, Uber Eats, Grubhub) as a share of total sales. Counter orders, pickup and direct phone or web orders pay no commission and do not go here. Tortillas travel worse than other dishes: a build-your-own order (meat, tortillas and toppings packed separately) holds up, but do not go above this share without testing it
A17: Delivery platform fee | B17: 0.25 | C17: The example uses 25%, a Plus plan on DoorDash or Uber Eats (the Basic plan is about 15% with little visibility, Premier is 30%, and app pickup orders add 6-10%). Check your contract. If you deliver yourself, enter 0 and add the driver to the "Staffing" tab as a W-2 employee, with hired and non-owned auto insurance (check your state)
A18: Card processing fee | B18: 0.03 | C18: Card and mobile wallet (contactless) processing fees on total sales. Ask your POS provider for its rate
A19: LABOR
A20: Employer payroll taxes | B20: 0.1 | C20: FICA (Social Security 6.2% + Medicare 1.45%) + federal and state unemployment taxes (FUTA / SUTA) + workers' comp. About 10% in total: adjust it to your state and your insurance carrier
A21: Monthly pay periods per year (keep 12) | B21: 12 | C21: Annual gross pay = monthly gross pay × this number. Keep 12 in the US: it counts the monthly salaries the model pays in a year, not how often you run payroll (weekly or biweekly payroll pays the same annual amount)
A22: Federal minimum wage, annual full-time | B22: 15080 | C22: US federal minimum wage: 7.25 per hour × 2,080 hours = 15,080 per year for a full-time job. Your state or city may set a higher floor: enter it in the state / local minimum wage cell below. Check the current rates at dol.gov
A23: RENT AND FIXED COSTS
A24: Monthly rent | B24: 2800 | C24: About 1,200 sq ft (111 sq m) with a hood and exhaust route to the roof possible (that is the filter for the space): a counter-service dining room with 30 seats, an open kitchen with the trompos, the griddle and the comal, restrooms (one ADA-accessible) and storage, on a street with steady foot traffic near a campus or a nightlife area in a mid-size city, second-generation space with no key money: about $28 per sq ft a year (Kit estimate, editable). The weight of rent on sales is calculated by the workbook itself in the rent row of the "3-Year P&L"
A25: Security deposit (months of rent) | B25: 2 | C25: Security deposit, in months of rent. The example uses two; commercial leases commonly ask for one to three, and some landlords also want a personal guarantee: check it with your attorney
A26: Monthly utilities (electricity, water, gas) | B26: 1300 | C26: Electricity (refrigeration, exhaust, HVAC and the dish machine), the gas for the vertical broilers, the griddle, the comal and the range, and water. Ask the landlord for the space's utility history
A27: Insurance (per year) | B27: 6000 | C27: General liability, liquor liability (beer & wine), property coverage with equipment breakdown for the refrigeration, and workers' comp. Tell the carrier you cook with gas vertical broilers, a griddle and a fryer: it changes the premium and the terms. Rates vary by state, so get at least two quotes
A28: Miscellaneous and contingency as % of sales | B28: 0.01 | C28: Cushion for unbudgeted running costs (small repairs, broken smallwares, menu tests)
A29: FINANCING
A30: Owner's equity contributed | B30: 100000 | C30: Owner's cash. Lenders usually expect an owner equity injection (often around 10% for SBA start-ups; many want 20-30%) toward the cash need
A31: Loan requested | B31: 176000 | C31: Principal requested. The "Financing" tab compares what you put in with the cash need on "Startup Costs" and tells you whether you have a surplus or a shortfall: adjust the loan with that figure. The example is an SBA 7(a) loan, which you apply for through your lender (SBA Microloans go up to $50,000)
A32: Nominal annual interest rate (not APR) | B32: 0.1 | C32: Nominal annual rate, not APR. The example uses 10%. Ask two lenders for a quote before you set it; the refrigeration and the kitchen equipment can also be financed through equipment financing or a lease: compare
A33: Loan term (years) | B33: 10 | C33: Total years, interest-only period included
A34: Interest-only period (years) | B34: 0 | C34: Years you pay interest only before principal repayment starts. The example uses 0, because SBA 7(a) loans amortize from the start. A year of interest only can ease the build-out and the first months of trading: ask your lender, and check the cash slack of the first repayment year on the "Break-Even" tab
A35: Working capital (months of fixed costs) | B35: 3 | C35: Three months of fixed costs: the cushion for the ramp-up, which with Month 1 in January falls on the slowest months of the year (January and February)
A36: TAXES
A37: Effective income tax rate (years 1-2) | B37: 0.25 | C37: Example: 21% federal rate for a C corporation plus state tax, rounded to 25%. If you operate as a sole proprietorship, LLC taxed as a pass-through or S corporation, the business itself pays 0% here and you pay tax on the profit personally: set this to 0 and budget for your personal tax separately. The model applies this rate to the first two years with positive taxable income
A38: Effective income tax rate (from year 3) | B38: 0.25 | C38: From the third year with positive taxable income. Same example rate (21% federal C corporation + state). Confirm the rate that applies to you with your accountant and change it here
A39: Sales tax rate on sales | B39: 0.08 | C39: Example rate: state + local sales tax combined. It varies widely by state and city: look up yours. UK: 20% VAT on hot food and dine-in
A40: Sales tax rate on alcohol to go | B40: 0.08 | C40: One sales tax rate for the whole example (8%: state plus local, so look up yours). In this workbook it also applies to alcohol sold to go, and it equals the on-site rate, so the two rows give the same result. There is no input credit: the workbook does not recover sales tax on purchases, so that row is 0. Some states tax food to go differently, so check yours. Utilities, equipment and services use the rate in the cell below
A41: Recoverable input tax on purchases and capex | B41: 0 | C41: In the US, the sales tax you pay on purchases is a cost, not a credit: leave this at 0%. UK: 20% if you are VAT-registered
A42: Net operating losses carried forward | B42: 0 | C42: Net operating losses from earlier years still to be offset at the start. Federal rules let you offset up to 80% of taxable income in a year; the model offsets 100% as a simplification
A43: DEPRECIATION
A44: Useful life of build-out and fixtures (years) | B44: 10 | C44: Build-out, Type I hood and exhaust, electrical service, plumbing, gas lines, HVAC, signage and facade. A 10-year straight-line life for the model; your tax depreciation schedule may differ (MACRS, Section 179), so confirm it with your CPA
A45: Useful life of machinery, furniture and equipment (years) | B45: 7 | C45: Vertical broilers, griddle and comal, fryer, walk-in and refrigeration, dish machine, furniture and POS: a 7-year straight-line life for the model; your tax depreciation schedule may differ, so confirm it with your CPA
A47: GROWTH AND COST INFLATION
A48: Annual increase in fixed costs | B48: 0 | C48: SET TO ZERO: all three columns are in year-1 prices (real terms). Raise it if you want to project in nominal terms
A49: RAMP-UP AND CAPACITY
A50: Implied seat turns per day (calculated) | B50: =IFERROR($B$4/$B$51,"") -> 3.8333333 | C50: =IFERROR("That is "&TEXT(INT(ROUND(B50,1)),"0")&"."&TEXT(ROUND(MOD(ROUND(B50,1),1)*10,0),"0")&" seat turns per day on the "&TEXT($B$51,"0")&" seats in the cell below. "&"It includes the take-out and delivery covers, which do not take a seat: the real turns of your dining room are lower (in the example, about half of the covers eat in). Compare it with the ceiling on seat turns typed in ""Break-Even"".","") -> That is 3.8 seat turns per day on the 30 seats in the cell below. It includes the take-out and delivery covers, which do not take a seat: the real turns of your dining room are lower (in the example, about half of the covers eat in). Compare it with the ceiling on seat turns typed in "Break-Even".
A51: Seating capacity of the space (indoor seats, patio not included) | B51: 30 | C51: Dining room seats. The patio adds 12 seats from April through October, with its own city patio permit, and guests who take their tacos to go or receive them at home do not use a seat: that is why the seat turns in the row above are higher than the real turns of your dining room
A52: Month-1 activity as a % of steady-state activity | B52: 0.75 | C52: A new taqueria draws the curious in the first month, but a regular base takes a quarter to build: Month 1 (January) bills 75% of what it will bill at four months. At 100% the ramp is removed
A53: Months to reach steady state | B53: 4 | C53: Four months to reach full pace: January through April, so you reach the spring patio season with a customer base
A54: Months of rent BEFORE opening (build-out and permits) | B54: 2 | C54: Two months of rent before opening: the build-out, the hood and exhaust route and the permits. If the lender funds the loan when build-out starts, add the interest for those months, which this workbook does not count, and remember that your repayment schedule starts at closing
A55: Contingency on the BUILD-OUT lines of the space block (%) | B55: 0.1 | C55: Cushion on the build-out and fixtures, which is where the surprises show up (the exhaust route to the roof, the gas lines, the grease interceptor). A lender will not finance a remodel without one
A57: RECEIPTS, PAYMENTS AND SALES TAX BREAKDOWN
A58: Average collection days | B58: 2 | C58: Weighted average: dine-in and pickup are paid at once, and the delivery marketplaces pay out what they sell every few days (15% of sales in this example)
A59: Average days to pay suppliers | B59: 14 | C59: Payment terms with your meat, tortilla, produce and beverage suppliers: what they finance for you. New accounts often start on COD, and terms are the first thing you lose if you pay late
A60: Month of extra pay period 1 (only if pay periods > 12) | B60: 7 | C60: Month of the 12-Month Cash Flow in which a summer extra payment falls. It only matters if you enter more than 12 pay periods; with 12 there are no extra payments. If you use it, July is Month 7, because Month 1 of the plan is January
A61: Month of extra pay period 2 (only if pay periods > 12) | B61: 12 | C61: Month of the 12-Month Cash Flow in which a holiday extra payment falls. It only matters if you enter more than 12 pay periods; with 12 there are no extra payments. If you use it, December is Month 12, because Month 1 of the plan is January
A62: Alcohol share of beverage purchases (reference only: no input credit in the US) | B62: 0.3 | C62: Reference only: in the US the sales tax you pay on purchases is a cost, not a credit (B41 = 0%), so this share moves no figure in the workbook. The sales tax you COLLECT on beverages is set by the beverage line of the P&L (column H)
A63: Sales tax rate on alcohol served on site | B63: 0.08 | C63: NO EFFECT in this workbook: the sales tax collected on beverages is set by the beverage line of the P&L. With the example, beer, wine, aguas frescas and food all pay the same 8% (state + local); if your state taxes alcohol at another rate, type it in B40 and the alcohol share in column H of that line
A64: CONTROL THRESHOLDS AND FLOORS
A65: DSCR limit (minimum acceptable) | B65: 1.15 | C65: Below 1.0 the business does not generate enough to repay the loan. Lenders often write a minimum DSCR into the loan covenants: ask yours. Kit default: 1.15×
A66: DSCR target (green) | B66: 1.25 | C66: What lenders commonly look for before approving a loan comfortably. Kit default: 1.25× (editable estimate)
A67: Minimum cushion above break-even | B67: 0.15 | C67: How far planned sales must sit above cash break-even (fixed costs and the loan payment). The drop you can absorb is somewhat smaller: with a 15% cushion, about 13% of plan
A68: State / local minimum wage, annual full-time | C68: Your state or local minimum wage as an annual full-time figure (hourly rate × 2,080 hours), if it is higher than the federal $7.25 an hour. With 0, the traffic light compares only against the federal floor

Sheet Startup Costs
A1: TACO SHOP BUSINESS PLAN: COUNTER-SERVICE TAQUERIA
A2: Estimated Startup Costs — counter-service taco shop with trompo and salsa bar, 30 seats + patio
A3: US kit example (2026) — replace with your own quotes.
A5: Item | B5: Amount | C5: % of startup costs | D5: Notes | E5: Taxable / recoverable tax?
A6: STARTUP COSTS | B6: =IFERROR(IF(COUNT(B7:B27)=0,"",SUM(B7:B27)),"") -> 197600 | C6: =IFERROR(B6/$B$30,"") -> 0.71694913
A7: Architect, MEP & hood drawings, plan review & permit fees | B7: 12000 | C7: =IFERROR(B7/$B$30,"") -> 0.043539421 | D7: Drawings for the build-out and the hood, plan review and permit fees. The beer & wine license varies widely by state in cost and timing: ask your state agency early and add your own quote; this line does not assume one | E7: Yes
A8: Build-out (second-generation space, 1,200 sq ft), signage & facade | B8: 42000 | C8: =IFERROR(B8/$B$30,"") -> 0.15238797 | D8: Kitchen with washable wall finish and slip-resistant floor, restrooms (one ADA-accessible), ceilings and acoustic treatment, the counter and service line, plus signage and facade (about $4,000). Kit estimate: get two bids | E8: Yes
A9: Type I hood, UL 300 fire suppression & makeup air | B9: 22000 | C9: =IFERROR(B9/$B$30,"") -> 0.079822272 | D9: A Type I hood of 10-12 ft with UL 300 fire suppression and makeup air over the griddle, the fryer and the gas vertical broilers. Hood packages run $5,000-$25,000 and the example budgets $22,000. A charcoal trompo is a solid-fuel appliance (NFPA 96: its own exhaust, a spark arrestor and daily ash removal), so it is a variant, not the example. No manufacturer posts a price per foot: ask your mechanical contractor for a quote with your drawings, and ask the fire marshal in writing | E9: Yes
A10: Electrical service, panel & gas lines | B10: 9000 | C10: =IFERROR(B10/$B$30,"") -> 0.032654566 | D10: Electrical service and panel for the refrigeration, exhaust, HVAC and dish machine, plus the gas lines to the broilers, the griddle and the range. Ask for the available electrical and gas capacity BEFORE you sign the lease: a new service from the utility can take weeks or months | E10: Yes
A11: Plumbing, grease interceptor & HVAC | B11: 11000 | C11: =IFERROR(B11/$B$30,"") -> 0.039911136 | D11: Hot and cold water in the kitchen, drains with a grease interceptor ($3,500-$7,500), HVAC for the dining room and exhaust with makeup air for the support kitchen | E11: Yes
A12: Vertical broilers (trompos) × 2 | B12: 4000 | C12: =IFERROR(B12/$B$30,"") -> 0.01451314 | D12: Two gas vertical broilers: one for the al pastor and a second cone or backup. WebstaurantStore lists the Avantco VB203 at $999 and the Visvardis DG8A at $2,844 (Oct 2026); cones run about 30 lb (13.6 kg). The example budgets the pair plus trays, slicing knives and a pineapple holder. A charcoal trompo is a solid-fuel variant (NFPA 96) | E12: Yes
A13: Flat-top griddle (36 in) & comal | B13: 4000 | C13: =IFERROR(B13/$B$30,"") -> 0.01451314 | D13: A 36 in (91 cm) flat-top griddle for the meats and a comal to warm the tortillas. At WebstaurantStore a Vulcan VCRG36-M1 lists at $2,501 and a Star 636MF at $2,129 (Oct 2026); the comal is Kit estimate: get a quote | E13: Yes
A14: Fryer, stock-pot range, steam table & tortilla warmers | B14: 6500 | C14: =IFERROR(B14/$B$30,"") -> 0.023583853 | D14: Fryer for the chips, stock-pot range for the carnitas and guisados, a 4-well steam table (listings start around $1,119) and tortilla warmers. Kit estimate | E14: Yes
A15: Walk-in cooler (6×8) | B15: 12800 | C15: =IFERROR(B15/$B$30,"") -> 0.046442049 | D15: A 6×8 ft (1.8×2.4 m) walk-in cooler for the marinated meat in volume. A Norlake Kold Locker lists at $12,808 (WebstaurantStore, Oct 2026) | E15: Yes
A16: Refrigerated prep table, salsa bar & freezer | B16: 6500 | C16: =IFERROR(B16/$B$30,"") -> 0.023583853 | D16: Refrigerated prep table for the garnishes, a refrigerated salsa bar and a freezer. No salsa bar price was read, so it is a Kit estimate: get two quotes | E16: Yes
A17: 3-comp sink, dish machine, hand sinks, shelving & stainless | B17: 11000 | C17: =IFERROR(B17/$B$30,"") -> 0.039911136 | D17: Three-compartment sink, dish machine, hands-free hand sinks, stainless tables and shelving | E17: Yes
A18: Smallwares & tortilla presses (hotel pans, blenders, probe thermometers, scales) | B18: 6500 | C18: =IFERROR(B18/$B$30,"") -> 0.023583853 | D18: Hotel pans, blenders for the salsas, probe thermometers, scales, dishware and baskets, manual tortilla presses (a Choice 7½ in (19 cm) press lists at $17.49), the required public notices (health permit, beer & wine license, labor law posters) and allergen signs (the 9 major allergens, including sesame: salsa macha = peanuts + sesame; flour tortillas = wheat). Food handler cards and the CFPM exam are budgeted in the P&L | E18: Yes
... A24: Opening inventory | B24: 5000 | C24: =IFERROR(B24/$B$30,"") -> 0.018141425 | D24: Meat, dried chiles and imported Mexican specialty products (ask for lead times: they can take weeks), corn tortillas, beer and wine, soft drinks and the take-out packaging | E24: Yes
A25: Security deposit | B25: =IFERROR(IF('0. Assumptions'!$B$24="","",'0. Assumptions'!$B$24*'0. Assumptions'!$B$25),"") -> 5600 | C25: =IFERROR(B25/$B$30,"") -> 0.020318397 | D25: =IFERROR(""&TEXT('0. Assumptions'!$B$25,"0")&IF('0. Assumptions'!$B$25=1," month"," months")&" of rent, from ""0. Assumptions"". Refundable when the lease ends: it is not depreciated and carries no tax","") -> 2 months of rent, from "0. Assumptions". Refundable when the lease ends: it is not depreciated and carries no tax | E25: No
A26: Rent paid before opening | B26: =IFERROR(IF('0. Assumptions'!$B$24="","",'0. Assumptions'!$B$24*'0. Assumptions'!$B$54),"") -> 5600 | C26: =IFERROR(B26/$B$30,"") -> 0.020318397 | D26: =IFERROR("Rent "&IF('0. Assumptions'!$B$54=1,"for the month","for the "&TEXT('0. Assumptions'!$B$54,"0")&" months")&" of build-out and permits before opening. It does not overlap the P&L, which starts on opening day: its twelve months are twelve trading months","") -> Rent for the 2 months of build-out and permits before opening. It does not overlap the P&L, which starts on opening day: its twelve months are twelve trading months | E26: Yes
A27: Build-out and setup contingency | B27: =IFERROR(IF(COUNT(B7,B8,B9,B10,B11)=0,"",ROUND((B7+B8+B9+B10+B11)*'0. Assumptions'!$B$55,0)),"") -> 9600 | C27: =IFERROR(B27/$B$30,"") -> 0.034831537 | D27: =IFERROR("At "&TEXT('0. Assumptions'!$B$55,"0%")&" of the BUILD-OUT items of this block (architect, MEP & hood drawings and permit fees; build-out, signage & facade; Type I hood, UL 300 fire suppression & makeup air; "&"electrical service, panel & gas lines; plumbing, grease interceptor & HVAC), not of the whole block: the trompos, the equipment and the other items are left out. No lender funds a build-out without a cushion: the percentage is in ""0. Assumptions""","") -> At 10% of the BUILD-OUT items of this block (architect, MEP & hood drawings and permit fees; build-out, signage & facade; Type I hood, UL 300 fire suppression & makeup air; electrical service, panel & gas lines; plumbing, grease interceptor & HVAC), not of the whole block: the trompos, the equipment and the other items are left out. No lender funds a build-out without a cushion: the percentage is in "0. Assumptions" | E27: Yes
A28: WORKING CAPITAL | B28: =IFERROR(IF(B29="","",B29),"") -> 78012.3 | C28: =IFERROR(B28/$B$30,"") -> 0.28305087
A29: Operating cushion until break-even | B29: =IFERROR(IF('0. Assumptions'!$B$35*('3-Year P&L'!$B$37-'3-Year P&L'!$B$35)=0,"",'0. Assumptions'!$B$35*('3-Year P&L'!$B$37-'3-Year P&L'!$B$35)/12),"") -> 78012.3 | C29: =IFERROR(B29/$B$30,"") -> 0.28305087 | D29: =IFERROR("Covers "&TEXT('0. Assumptions'!$B$35,"0")&IF('0. Assumptions'!$B$35=1," month"," months")&" of year-1 CASH fixed costs (the P&L fixed costs minus depreciation, which is not paid out), the minimum the Instructions of this workbook ask for","") -> Covers 3 months of year-1 CASH fixed costs (the P&L fixed costs minus depreciation, which is not paid out), the minimum the Instructions of this workbook ask for | E29: No
A30: TOTAL STARTUP COSTS (sum of the blocks) | B30: =IFERROR(B6+B28,"") -> 275612.3 | D30: =IFERROR("The percentages in column C are read on this figure, which includes the working capital ("&TEXT(C28,"0%")&" of the total). To compare the breakdown with another plan, use the CAPEX row below.","") -> The percentages in column C are read on this figure, which includes the working capital (28% of the total). To compare the breakdown with another plan, use the CAPEX row below.
A31: CAPEX (startup costs excluding working capital) | B31: =IFERROR(B30-B28,"") -> 197600 | D31: What you buy: build-out, equipment, launch and formation costs. The cash cushion is not an investment: it is working capital
A32: Recoverable input tax on capex | B32: =IFERROR(IF(B30="","",SUMIF($E$7:$E$27,"Yes",$B$7:$B$27)*'0. Assumptions'!$B$41),"") -> 0 | D32: =IFERROR("At "&TEXT('0. Assumptions'!$B$41,"0%")&" on the items marked ""Yes"" in the tax column. US: the sales tax you pay on equipment is part of its cost and is not recovered, so this rate is 0. UK (VAT-registered): 20%, reclaimed on your VAT return, but you pay it first, so the loan has to cover it","") -> At 0% on the items marked "Yes" in the tax column. US: the sales tax you pay on equipment is part of its cost and is not recovered, so this rate is 0. UK (VAT-registered): 20%, reclaimed on your VAT return, but you pay it first, so the loan has to cover it
A33: TOTAL CASH NEEDED AT LAUNCH | B33: =IFERROR(B30+B32,"") -> 275612.3 | D33: This is the figure the Financing tab has to cover
A34: DEPRECIATION BASES (not added to startup costs)
A35: Build-out, fixtures and setup | B35: =IFERROR(IF(B7="","",B7+B8+B9+B10+B11+B27),"") -> 105600 | D35: =IFERROR("Depreciated over "&TEXT('0. Assumptions'!$B$44,"0")&" years","") -> Depreciated over 10 years
A36: Machinery, furniture and equipment | B36: =IFERROR(IF(B12="","",B12+B13+B14+B15+B16+B17+B18+B19+B20+B21),"") -> 67800 | D36: =IFERROR("Depreciated over "&TEXT('0. Assumptions'!$B$45,"0")&" years","") -> Depreciated over 7 years
A37: Annual depreciation of fixed assets | B37: =IFERROR(B35/MAX(1,'0. Assumptions'!$B$44)+B36/MAX(1,'0. Assumptions'!$B$45),"") -> 20245.714 | D37: =IFERROR("Not depreciated, because they are not fixed assets: LLC, legal and food safety plan; branding, website, photos and launch; opening inventory; security deposit; pre-opening rent and the working capital reserve. They add up to "&TEXT(B30-B35-B36,"#,##0")&" of the "&TEXT(B30,"#,##0")&" total investment.","") -> Not depreciated, because they are not fixed assets: LLC, legal and food safety plan; branding, website, photos and launch; opening inventory; security deposit; pre-opening rent and the working capital reserve. They add up to 102212 of the 275612 total investment.

Sheet 3-Year P&L
A1: PRO FORMA P&L — 3 YEARS
A2: Base case — counter-service taco shop with trompo, salsa bar and take-out
A4: Item | B4: Year 1 | C4: Year 2 | D4: Year 3 | E4: % of sales (year 1) | F4: Notes | G4: Sales tax rate on the line (%) | H4: Beverage share taxed at the alcohol rate in B40 (%)
A5: REVENUE
A6: Covers per day (average) | B6: =IFERROR(IF('0. Assumptions'!$B$4="","",'0. Assumptions'!$B$4),"") -> 115 | C6: =IFERROR(B6*(1+'0. Assumptions'!$B$7),"") -> 121.9 | D6: =IFERROR(C6*(1+'0. Assumptions'!$B$8),"") -> 126.776 | F6: Growth for years 2 and 3 is set in "0. Assumptions"
A7: Average check (excl. sales tax) | B7: =IFERROR(IF('0. Assumptions'!$B$5="","",'0. Assumptions'!$B$5),"") -> 17.5 | C7: =IFERROR(IF(B7="","",B7),"") -> 17.5 | D7: =IFERROR(IF(C7="","",C7),"") -> 17.5 | F7: Held constant at year-1 prices: a price increase is a separate decision
A8: Operating days per year | B8: =IFERROR(IF('0. Assumptions'!$B$6="","",'0. Assumptions'!$B$6),"") -> 308 | C8: =IFERROR(IF(B8="","",B8),"") -> 308 | D8: =IFERROR(IF(C8="","",C8),"") -> 308
A9: TOTAL REVENUE (excl. sales tax) | B9: =IFERROR(IF(B6*B7*B8=0,"",B6*B7*B8),"") -> 619850 | C9: =IFERROR(IF(C6*C7*C8=0,"",C6*C7*C8),"") -> 657041 | D9: =IFERROR(IF(D6*D7*D8=0,"",D6*D7*D8),"") -> 683322.64 | E9: =IFERROR(IF(B9="","",1),"") -> 1
A10: Food sales (tacos, quesadillas, plates & sides: dine-in, take-out & delivery) | B10: =IFERROR(IF(B9="","",B9*$E$10),"") -> 526872.5 | C10: =IFERROR(IF(C9="","",C9*$E$10),"") -> 558484.85 | D10: =IFERROR(IF(D9="","",D9*$E$10),"") -> 580824.24 | E10: =IFERROR(IF('0. Assumptions'!$B$11="","",'0. Assumptions'!$B$11),"") -> 0.85 | F10: Tacos, gringas and quesadillas, plates and sides: about 52% dine-in, about 33% direct pickup and 15% through delivery marketplaces. One sales tax rate in the example, whether guests eat in or take it to go; some states tax food to go differently, so check yours | G10: =IFERROR(IF(B9="","",'0. Assumptions'!$B$39),"") -> 0.08
A11: Beverage sales (aguas frescas, sodas, Mexican beer & wine) | B11: =IFERROR(IF(B9="","",B9*$E$11),"") -> 92977.5 | C11: =IFERROR(IF(C9="","",C9*$E$11),"") -> 98556.15 | D11: =IFERROR(IF(D9="","",D9*$E$11),"") -> 102498.4 | E11: =IFERROR(IF('0. Assumptions'!$B$12="","",'0. Assumptions'!$B$12),"") -> 0.15 | F11: Dine-in beverages and the drinks that go out with orders (aguas frescas, sodas, Mexican beer & wine) · Column H is the share of beverage sales taxed at the alcohol rate in "0. Assumptions" B40. With the example rates (B39 = B40 = 8%: state + local) it changes nothing. Some states tax alcohol differently: type your alcohol rate in B40 and the alcohol share of beverage sales here | G11: =IFERROR(IF(B9="","",H11*'0. Assumptions'!$B$40+(1-H11)*'0. Assumptions'!$B$39),"") -> 0.08 | H11: 0.3
A12: VARIABLE COSTS
A13: Cost of goods sold — food | B13: =IFERROR(IF(B9="","",B9*'0. Assumptions'!$B$11*'0. Assumptions'!$B$13),"") -> 142255.58 | C13: =IFERROR(IF(C9="","",C9*'0. Assumptions'!$B$11*'0. Assumptions'!$B$13),"") -> 150790.91 | D13: =IFERROR(IF(D9="","",D9*'0. Assumptions'!$B$11*'0. Assumptions'!$B$13),"") -> 156822.55 | E13: =IFERROR(B13/$B$9,"") -> 0.2295 | F13: =IFERROR("At "&TEXT('0. Assumptions'!$B$13,"0%")&" of FOOD sales, not of total sales: beverages have their own line · pork shoulder and other meats, corn tortillas, chiles, produce, avocados and cheese: check it against your distributor invoices and the Taco Cost & Trompo Yield Calculator","") -> At 27% of FOOD sales, not of total sales: beverages have their own line · pork shoulder and other meats, corn tortillas, chiles, produce, avocados and cheese: check it against your distributor invoices and the Taco Cost & Trompo Yield Calculator | G13: 0
A14: Cost of goods sold — beverage | B14: =IFERROR(IF(B9="","",B9*'0. Assumptions'!$B$12*'0. Assumptions'!$B$14),"") -> 20455.05 | C14: =IFERROR(IF(C9="","",C9*'0. Assumptions'!$B$12*'0. Assumptions'!$B$14),"") -> 21682.353 | D14: =IFERROR(IF(D9="","",D9*'0. Assumptions'!$B$12*'0. Assumptions'!$B$14),"") -> 22549.647 | E14: =IFERROR(B14/$B$9,"") -> 0.033 | F14: =IFERROR("At "&TEXT('0. Assumptions'!$B$14,"0%")&" of BEVERAGE sales","") -> At 22% of BEVERAGE sales | G14: =IFERROR(IF(B9="","",'0. Assumptions'!$B$41),"") -> 0
A15: Disposables and packaging | B15: =IFERROR(IF(B9="","",B9*'0. Assumptions'!$B$15),"") -> 24794 | C15: =IFERROR(IF(C9="","",C9*'0. Assumptions'!$B$15),"") -> 26281.64 | D15: =IFERROR(IF(D9="","",D9*'0. Assumptions'!$B$15),"") -> 27332.906 | E15: =IFERROR(B15/$B$9,"") -> 0.04 | G15: =IFERROR(IF(B9="","",'0. Assumptions'!$B$41),"") -> 0
A16: Delivery platform fees | B16: =IFERROR(IF(B9="","",B9*'0. Assumptions'!$B$16*'0. Assumptions'!$B$17),"") -> 23244.375 | C16: =IFERROR(IF(C9="","",C9*'0. Assumptions'!$B$16*'0. Assumptions'!$B$17),"") -> 24639.037 | D16: =IFERROR(IF(D9="","",D9*'0. Assumptions'!$B$16*'0. Assumptions'!$B$17),"") -> 25624.599 | E16: =IFERROR(B16/$B$9,"") -> 0.0375 | F16: Applied to the sales of THAT CHANNEL. With 0% delivery in Assumptions, this line is zero | G16: =IFERROR(IF(B9="","",'0. Assumptions'!$B$41),"") -> 0
A17: Card processing fees | B17: =IFERROR(IF(B9="","",B9*'0. Assumptions'!$B$18),"") -> 18595.5 | C17: =IFERROR(IF(C9="","",C9*'0. Assumptions'!$B$18),"") -> 19711.23 | D17: =IFERROR(IF(D9="","",D9*'0. Assumptions'!$B$18),"") -> 20499.679 | E17: =IFERROR(B17/$B$9,"") -> 0.03 | F17: Card processing fees are not subject to sales tax: no tax is recovered or deducted for them | G17: 0
A18: Miscellaneous and contingency | B18: =IFERROR(IF(B9="","",B9*'0. Assumptions'!$B$28),"") -> 6198.5 | C18: =IFERROR(IF(C9="","",C9*'0. Assumptions'!$B$28),"") -> 6570.41 | D18: =IFERROR(IF(D9="","",D9*'0. Assumptions'!$B$28),"") -> 6833.2264 | E18: =IFERROR(B18/$B$9,"") -> 0.01 | F18: =IFERROR("At "&TEXT('0. Assumptions'!$B$28,"0%")&" of sales. It is a VARIABLE cost: it moves with revenue, so it cannot sit in fixed costs","") -> At 1% of sales. It is a VARIABLE cost: it moves with revenue, so it cannot sit in fixed costs | G18: =IFERROR(IF(B9="","",'0. Assumptions'!$B$41),"") -> 0
A19: TOTAL VARIABLE COSTS | B19: =IFERROR(IF(B9="","",SUM(B13:B18)),"") -> 235543 | C19: =IFERROR(IF(C9="","",SUM(C13:C18)),"") -> 249675.58 | D19: =IFERROR(IF(D9="","",SUM(D13:D18)),"") -> 259662.6 | E19: =IFERROR(B19/$B$9,"") -> 0.38
A20: GROSS MARGIN | B20: =IFERROR(IF(B9="","",B9-B19),"") -> 384307 | C20: =IFERROR(IF(C9="","",C9-C19),"") -> 407365.42 | D20: =IFERROR(IF(D9="","",D9-D19),"") -> 423660.04 | E20: =IFERROR(B20/$B$9,"") -> 0.62
A21: FIXED COSTS
A22: Rent | B22: =IFERROR(IF(B9="","",'0. Assumptions'!$B$24*12),"") -> 33600 | C22: =IFERROR(IF(C9="","",B22*(1+'0. Assumptions'!$B$48)),"") -> 33600 | D22: =IFERROR(IF(D9="","",C22*(1+'0. Assumptions'!$B$48)),"") -> 33600 | E22: =IFERROR(B22/$B$9,"") -> 0.054206663 | F22: The monthly amount is on the "0. Assumptions" tab; here it is multiplied by twelve. The two months of rent before opening are on "Startup Costs" and are NOT counted twice | G22: =IFERROR(IF(B9="","",'0. Assumptions'!$B$41),"") -> 0
A23: Labor (wages + employer payroll taxes) | B23: =IFERROR(IF(B9="","",Staffing!$G$12),"") -> 214249.2 | C23: =IFERROR(IF(C9="","",Staffing!$B$16),"") -> 219249.2 | D23: =IFERROR(IF(D9="","",Staffing!$B$17),"") -> 224249.2 | E23: =IFERROR(B23/$B$9,"") -> 0.34564685 | F23: Comes from the Staffing tab: it is the SAME number, not a separate estimate. Years 2 and 3 add the new hires declared on that tab, not a percentage of volume | G23: 0
A24: Utilities (electricity, water, gas) | B24: =IFERROR(IF(B9="","",'0. Assumptions'!$B$26*12),"") -> 15600 | C24: =IFERROR(IF(C9="","",B24*(1+'0. Assumptions'!$B$48)),"") -> 15600 | D24: =IFERROR(IF(D9="","",C24*(1+'0. Assumptions'!$B$48)),"") -> 15600 | E24: =IFERROR(B24/$B$9,"") -> 0.025167379 | F24: Enter the monthly bills excl. sales tax. The workbook applies a single tax treatment to this whole line, the one in the column next to it; if one utility is taxed differently in your area, give it its own line | G24: =IFERROR(IF(B9="","",'0. Assumptions'!$B$41),"") -> 0
A25: Insurance (general + liquor liability + property + workers' comp) | B25: =IFERROR(IF(B9="","",'0. Assumptions'!$B$27),"") -> 6000 | C25: =IFERROR(IF(C9="","",B25*(1+'0. Assumptions'!$B$48)),"") -> 6000 | D25: =IFERROR(IF(D9="","",C25*(1+'0. Assumptions'!$B$48)),"") -> 6000 | E25: =IFERROR(B25/$B$9,"") -> 0.0096797612 | F25: Insurance premiums are not subject to sales tax: there is no recoverable tax on them | G25: 0
A26: Accounting & bookkeeping | B26: 4200 | C26: =IFERROR(IF(C9="","",B26*(1+'0. Assumptions'!$B$48)),"") -> 4200 | D26: =IFERROR(IF(D9="","",C26*(1+'0. Assumptions'!$B$48)),"") -> 4200 | E26: =IFERROR(B26/$B$9,"") -> 0.0067758329 | F26: Bookkeeping, income tax and payroll filings for the LLC, payroll processing and the staff paperwork (offer letters, I-9, W-4) | G26: =IFERROR(IF(B9="","",'0. Assumptions'!$B$41),"") -> 0
A27: Maintenance (hood cleaning, broilers, refrigeration) | B27: 3000 | C27: =IFERROR(IF(C9="","",B27*(1+'0. Assumptions'!$B$48)),"") -> 3000 | D27: =IFERROR(IF(D9="","",C27*(1+'0. Assumptions'!$B$48)),"") -> 3000 | E27: =IFERROR(B27/$B$9,"") -> 0.0048398806 | F27: Hood and duct cleaning on the schedule that NFPA 96 and your local authority require, service for the gas vertical broilers, griddle and range, and the refrigeration technician | G27: =IFERROR(IF(B9="","",'0. Assumptions'!$B$41),"") -> 0
A28: Marketing and advertising | B28: 6000 | C28: =IFERROR(IF(C9="","",B28*(1+'0. Assumptions'!$B$48)),"") -> 6000 | D28: =IFERROR(IF(D9="","",C28*(1+'0. Assumptions'!$B$48)),"") -> 6000 | E28: =IFERROR(B28/$B$9,"") -> 0.0096797612 | F28: Google Business Profile, Yelp, social media, seasonal photos and promotions (Cinco de Mayo, Mexican Independence Day in September, Day of the Dead in November); the opening campaign is in "Startup Costs" | G28: =IFERROR(IF(B9="","",'0. Assumptions'!$B$41),"") -> 0
A29: Software, POS & online ordering | B29: 3600 | C29: =IFERROR(IF(C9="","",B29*(1+'0. Assumptions'!$B$48)),"") -> 3600 | D29: =IFERROR(IF(D9="","",C29*(1+'0. Assumptions'!$B$48)),"") -> 3600 | E29: =IFERROR(B29/$B$9,"") -> 0.0058078567 | F29: POS subscription, online ordering, the delivery marketplace tablets, phone and internet | G29: =IFERROR(IF(B9="","",'0. Assumptions'!$B$41),"") -> 0
A30: Cleaning, linens & uniforms | B30: 2000 | C30: =IFERROR(IF(C9="","",B30*(1+'0. Assumptions'!$B$48)),"") -> 2000 | D30: =IFERROR(IF(D9="","",C30*(1+'0. Assumptions'!$B$48)),"") -> 2000 | E30: =IFERROR(B30/$B$9,"") -> 0.0032265871 | F30: Cleaning supplies, uniform and towel laundry, gloves and any lab tests or records your written food safety plan calls for | G30: =IFERROR(IF(B9="","",'0. Assumptions'!$B$41),"") -> 0
A31: Waste, grease & used-oil hauling + permit renewals | B31: 3500 | C31: =IFERROR(IF(C9="","",B31*(1+'0. Assumptions'!$B$48)),"") -> 3500 | D31: =IFERROR(IF(D9="","",C31*(1+'0. Assumptions'!$B$48)),"") -> 3500 | E31: =IFERROR(B31/$B$9,"") -> 0.0056465274 | F31: Licensed hauler for trash, cardboard, used cooking oil and grease, plus annual permit renewals. If your city charges a patio or sidewalk café permit fee, add it here: this plan has not read any city fee schedule, so enter your city's own | G31: =IFERROR(IF(B9="","",'0. Assumptions'!$B$41),"") -> 0
A32: Pest control | B32: 900 | C32: =IFERROR(IF(C9="","",B32*(1+'0. Assumptions'!$B$48)),"") -> 900 | D32: =IFERROR(IF(D9="","",C32*(1+'0. Assumptions'!$B$48)),"") -> 900 | E32: =IFERROR(B32/$B$9,"") -> 0.0014519642 | F32: Contract with a licensed pest control operator: it is part of the prerequisites of your written food safety plan. | G32: =IFERROR(IF(B9="","",'0. Assumptions'!$B$41),"") -> 0
A33: Music licensing (ASCAP/BMI/SESAC) | B33: 1000 | C33: =IFERROR(IF(C9="","",B33*(1+'0. Assumptions'!$B$48)),"") -> 1000 | D33: =IFERROR(IF(D9="","",C33*(1+'0. Assumptions'!$B$48)),"") -> 1000 | E33: =IFERROR(B33/$B$9,"") -> 0.0016132935 | F33: ASCAP, BMI and SESAC are separate licenses; the fee depends on the square footage and the seating of your shop | G33: =IFERROR(IF(B9="","",'0. Assumptions'!$B$41),"") -> 0
A34: Food safety & staff training (CFPM, allergens, OSHA) | B34: 800 | C34: =IFERROR(IF(C9="","",B34*(1+'0. Assumptions'!$B$48)),"") -> 800 | D34: =IFERROR(IF(D9="","",C34*(1+'0. Assumptions'!$B$48)),"") -> 800 | E34: =IFERROR(B34/$B$9,"") -> 0.0012906348 | F34: CFPM certification and food handler cards, allergen training and OSHA basics for every employee: burns from the griddle and the fryer, cuts when slicing the trompo, gas and heat | G34: =IFERROR(IF(B9="","",'0. Assumptions'!$B$41),"") -> 0
A35: Depreciation of fixed assets | B35: =IFERROR(IF(B9="","",'Startup Costs'!$B$37),"") -> 20245.714 | C35: =IFERROR(IF(C9="","",B35),"") -> 20245.714 | D35: =IFERROR(IF(D9="","",B35),"") -> 20245.714 | E35: =IFERROR(B35/$B$9,"") -> 0.03266228 | F35: Comes from the depreciation bases on the Startup Costs tab: real fixed assets only. It does NOT rise with inflation: it is a charge on the HISTORICAL cost of the assets | G35: 0
A36: Interest expense (loan interest) | B36: =IFERROR(IF(B9="","",Financing!$B$44),"") -> 17600 | C36: =IFERROR(IF(C9="","",Financing!$B$46),"") -> 16495.681 | D36: =IFERROR(IF(D9="","",Financing!$B$48),"") -> 15280.93 | E36: =IFERROR(B36/$B$9,"") -> 0.028393966 | F36: Only INTEREST is an expense. Principal repaid appears on the cash flow tab | G36: 0
A37: TOTAL FIXED COSTS | B37: =IFERROR(IF(B9="","",SUM(B22:B36)),"") -> 332294.91 | C37: =IFERROR(IF(C9="","",SUM(C22:C36)),"") -> 336190.6 | D37: =IFERROR(IF(D9="","",SUM(D22:D36)),"") -> 339975.84 | E37: =IFERROR(B37/$B$9,"") -> 0.53608924
A38: Recoverable input tax on variable costs | B38: =IFERROR(IF(B9="","",SUMPRODUCT(B13:B18,G13:G18)),"") -> 0 | C38: =IFERROR(IF(C9="","",SUMPRODUCT(C13:C18,G13:G18)),"") -> 0 | D38: =IFERROR(IF(D9="","",SUMPRODUCT(D13:D18,G13:G18)),"") -> 0 | F38: Each line at ITS OWN rate, read from the column next to it. It is what the cash flow tab overpays to suppliers and later deducts (zero wherever no tax is recoverable)
A39: Recoverable input tax on fixed costs | B39: =IFERROR(IF(B9="","",SUMPRODUCT(B22:B36,G22:G36)),"") -> 0 | C39: =IFERROR(IF(C9="","",SUMPRODUCT(C22:C36,G22:G36)),"") -> 0 | D39: =IFERROR(IF(D9="","",SUMPRODUCT(D22:D36,G22:G36)),"") -> 0
A40: PRE-TAX INCOME (EBT) | B40: =IFERROR(IF(B9="","",B20-B37),"") -> 52012.086 | C40: =IFERROR(IF(C9="","",C20-C37),"") -> 71174.825 | D40: =IFERROR(IF(D9="","",D20-D37),"") -> 83684.192 | E40: =IFERROR(B40/$B$9,"") -> 0.083910762
A41: Net operating losses carried forward (opening) | B41: =IFERROR(IF(B9="","",'0. Assumptions'!$B$42),"") -> 0 | C41: =IFERROR(IF(C9="","",B46),"") -> 0 | D41: =IFERROR(IF(D9="","",C46),"") -> 0 | F41: Federal rules let a year's losses offset the profits of later years (the federal limit is 80% of taxable income; this model offsets 100% as a simplification)
A42: Taxable income (after loss offset) | B42: =IFERROR(IF(B9="","",MAX(0,B40-B41)),"") -> 52012.086 | C42: =IFERROR(IF(C9="","",MAX(0,C40-C41)),"") -> 71174.825 | D42: =IFERROR(IF(D9="","",MAX(0,D40-D41)),"") -> 83684.192
A43: Years with positive taxable income (cumulative) | B43: =IFERROR(IF(B9="","",IF(B42>0,1,0)),"") -> 1 | C43: =IFERROR(IF(C9="","",B43+IF(C42>0,1,0)),"") -> 2 | D43: =IFERROR(IF(D9="","",C43+IF(D42>0,1,0)),"") -> 3
A44: Effective income tax rate applied | B44: =IFERROR(IF(B9="","",IF(B42<=0,"",IF(B43<=2,'0. Assumptions'!$B$37,'0. Assumptions'!$B$38))),"") -> 0.25 | C44: =IFERROR(IF(C9="","",IF(C42<=0,"",IF(C43<=2,'0. Assumptions'!$B$37,'0. Assumptions'!$B$38))),"") -> 0.25 | D44: =IFERROR(IF(D9="","",IF(D42<=0,"",IF(D43<=2,'0. Assumptions'!$B$37,'0. Assumptions'!$B$38))),"") -> 0.25 | F44: The "years 1-2" rate applies to the first two years with positive taxable income, not to the first two calendar years of the business. The model approximates this by counting the first two profitable years
A45: Income tax | B45: =IFERROR(IF(B9="","",IF(B44="",0,B42*B44)),"") -> 13003.021 | C45: =IFERROR(IF(C9="","",IF(C44="",0,C42*C44)),"") -> 17793.706 | D45: =IFERROR(IF(D9="","",IF(D44="",0,D42*D44)),"") -> 20921.048
A46: Net operating losses carried forward (closing) | B46: =IFERROR(IF(B9="","",MAX(0,B41-B40)),"") -> 0 | C46: =IFERROR(IF(C9="","",MAX(0,C41-C40)),"") -> 0 | D46: =IFERROR(IF(D9="","",MAX(0,D41-D40)),"") -> 0
A47: NET INCOME | B47: =IFERROR(IF(B9="","",B40-B45),"") -> 39009.064 | C47: =IFERROR(IF(C9="","",C40-C45),"") -> 53381.118 | D47: =IFERROR(IF(D9="","",D40-D45),"") -> 62763.144 | E47: =IFERROR(B47/$B$9,"") -> 0.062933071
A48: KEY RATIOS
A49: Ratio | B49: Year 1 | C49: Year 2 | D49: Year 3 | E49: Threshold | F49: Comment
A50: Gross margin / Sales | B50: =IFERROR(IF(B9="","",B20/B9),"") -> 0.62 | C50: =IFERROR(IF(C9="","",C20/C9),"") -> 0.62 | D50: =IFERROR(IF(D9="","",D20/D9),"") -> 0.62 | E50: 0.6 | F50: Floor for the margin after ALL variable costs (cost of goods sold, packaging, delivery marketplaces, card fees and miscellaneous). With cost of goods sold alone, a taqueria keeps a much higher margin. Kit estimate
A51: Cost of goods sold (food + beverage) | B51: =IFERROR(IF(B9="","",B13+B14),"") -> 162710.62 | C51: =IFERROR(IF(C9="","",C13+C14),"") -> 172473.26 | D51: =IFERROR(IF(D9="","",D13+D14),"") -> 179372.19
A52: Cost of goods sold / Sales | B52: =IFERROR(IF(B9="","",B51/B9),"") -> 0.2625 | C52: =IFERROR(IF(C9="","",C51/C9),"") -> 0.2625 | D52: =IFERROR(IF(D9="","",D51/D9),"") -> 0.2625 | E52: 0.3 | F52: Ceiling for cost of goods sold on sales: the al pastor taco runs well below it, while carnitas, suadero, barbacoa, birria and avocado push it up. Kit estimate
A53: Labor cost / Sales | B53: =IFERROR(IF(B9="","",B23/B9),"") -> 0.34564685 | C53: =IFERROR(IF(C9="","",C23/C9),"") -> 0.33369181 | D53: =IFERROR(IF(D9="","",D23/D9),"") -> 0.3281747 | E53: 0.36 | F53: Ceiling for labor on sales with two taqueros and counter service. Kit estimate
A54: Rent / Sales | B54: =IFERROR(IF(B9="","",B22/B9),"") -> 0.054206663 | C54: =IFERROR(IF(C9="","",C22/C9),"") -> 0.051138361 | D54: =IFERROR(IF(D9="","",D22/D9),"") -> 0.049171501 | E54: 0.1 | F54: Ceiling for rent on sales for a space with a Type I hood and exhaust to the roof: Kit estimate
A55: Net income / Sales | B55: =IFERROR(IF(B9="","",B47/B9),"") -> 0.062933071 | C55: =IFERROR(IF(C9="","",C47/C9),"") -> 0.08124473 | D55: =IFERROR(IF(D9="","",D47/D9),"") -> 0.091849941 | E55: 0.05 | F55: Floor for steady-state net income so the plan holds up: 5% of sales. A well-run taqueria earns more, but this is a realistic floor, not a hope. Kit estimate
A56: Break-even reached | B56: =IFERROR(IF(B9="","",IF(B9>='Break-Even'!$B$16,"Yes","No")),"") -> Yes | C56: =IFERROR(IF(C9="","",IF(C9>='Break-Even'!$C$16,"Yes","No")),"") -> Yes | D56: =IFERROR(IF(D9="","",IF(D9>='Break-Even'!$D$16,"Yes","No")),"") -> Yes | F56: Compares each year's sales with that same year's threshold, which the Break-Even tab calculates with that year's fixed costs
A58: All figures are EXCL. SALES TAX. Years 2 and 3 are in year-1 prices unless you raise cost inflation in the "0. Assumptions" tab. The "Sales tax rate on the line (%)" column shows, on SALES lines, the rate collected on each one and, on COST lines, the rate paid on that item. The cash flow tab reads it: insurance and card fees carry no sales tax, and wages, depreciation and interest carry none either.

Sheet Break-Even
A1: BREAK-EVEN ANALYSIS
A2: Monthly and daily break-even — taco shop with trompo
A4: Variable | B4: Year 1 | C4: Year 2 | D4: Year 3 | E4: Notes
A5: BASE DATA BY YEAR
A6: Annual fixed costs | B6: =IFERROR(IF('3-Year P&L'!$B$9="","",'3-Year P&L'!$B$37),"") -> 332294.91 | C6: =IFERROR(IF('3-Year P&L'!$C$9="","",'3-Year P&L'!$C$37),"") -> 336190.6 | D6: =IFERROR(IF('3-Year P&L'!$D$9="","",'3-Year P&L'!$D$37),"") -> 339975.84 | E6: The SAME fixed costs as the P&L. Each year has its own, which is why the threshold cannot be a single one for all three years
A7: Monthly fixed costs | B7: =IFERROR(IF('3-Year P&L'!$B$9="","",B6/12),"") -> 27691.243 | C7: =IFERROR(IF('3-Year P&L'!$C$9="","",C6/12),"") -> 28015.883 | D7: =IFERROR(IF('3-Year P&L'!$D$9="","",D6/12),"") -> 28331.32
A8: Average check (excl. sales tax) | B8: =IFERROR(IF('3-Year P&L'!$B$9="","",'3-Year P&L'!$B$7),"") -> 17.5 | C8: =IFERROR(IF('3-Year P&L'!$C$9="","",'3-Year P&L'!$C$7),"") -> 17.5 | D8: =IFERROR(IF('3-Year P&L'!$D$9="","",'3-Year P&L'!$D$7),"") -> 17.5
A9: Variable cost per cover | B9: =IFERROR(IF('3-Year P&L'!$B$9="","",'3-Year P&L'!$B$19/('3-Year P&L'!$B$6*'3-Year P&L'!$B$8)),"") -> 6.65 | C9: =IFERROR(IF('3-Year P&L'!$C$9="","",'3-Year P&L'!$C$19/('3-Year P&L'!$C$6*'3-Year P&L'!$C$8)),"") -> 6.65 | D9: =IFERROR(IF('3-Year P&L'!$D$9="","",'3-Year P&L'!$D$19/('3-Year P&L'!$D$6*'3-Year P&L'!$D$8)),"") -> 6.65 | E9: Comes from the P&L total variable costs, not from a separate estimate. It includes miscellaneous and contingency, which is a percentage of sales
A10: Contribution margin per cover | B10: =IFERROR(IF('3-Year P&L'!$B$9="","",B8-B9),"") -> 10.85 | C10: =IFERROR(IF('3-Year P&L'!$C$9="","",C8-C9),"") -> 10.85 | D10: =IFERROR(IF('3-Year P&L'!$D$9="","",D8-D9),"") -> 10.85 | E10: Average check minus unit variable cost
A11: Operating days per year | B11: =IFERROR(IF('3-Year P&L'!$B$9="","",'3-Year P&L'!$B$8),"") -> 308 | C11: =IFERROR(IF('3-Year P&L'!$C$9="","",'3-Year P&L'!$C$8),"") -> 308 | D11: =IFERROR(IF('3-Year P&L'!$D$9="","",'3-Year P&L'!$D$8),"") -> 308 | E11: The same calendar as the P&L and the scenarios
A12: Principal repaid in the year | B12: =IFERROR(IF('3-Year P&L'!$B$9="","",Financing!$B$45),"") -> 11043.189 | C12: =IFERROR(IF('3-Year P&L'!$C$9="","",Financing!$B$47),"") -> 12147.508 | D12: =IFERROR(IF('3-Year P&L'!$D$9="","",Financing!$B$49),"") -> 13362.259 | E12: Principal is NOT a P&L expense, but it leaves the cash account. Without it, the published break-even threshold would sit below the real one
A13: ACCOUNTING BREAK-EVEN (includes depreciation)
A14: Covers needed per year | B14: =IFERROR(IF('3-Year P&L'!$B$9="","",IF(B10<=0,"",B6/B10)),"") -> 30626.259 | C14: =IFERROR(IF('3-Year P&L'!$C$9="","",IF(C10<=0,"",C6/C10)),"") -> 30985.308 | D14: =IFERROR(IF('3-Year P&L'!$D$9="","",IF(D10<=0,"",D6/D10)),"") -> 31334.179
A15: Covers needed per day | B15: =IFERROR(IF('3-Year P&L'!$B$9="","",B14/B11),"") -> 99.435907 | C15: =IFERROR(IF('3-Year P&L'!$C$9="","",C14/C11),"") -> 100.60165 | D15: =IFERROR(IF('3-Year P&L'!$D$9="","",D14/D11),"") -> 101.73435
A16: Revenue needed per year | B16: =IFERROR(IF('3-Year P&L'!$B$9="","",B14*B8),"") -> 535959.54 | C16: =IFERROR(IF('3-Year P&L'!$C$9="","",C14*C8),"") -> 542242.9 | D16: =IFERROR(IF('3-Year P&L'!$D$9="","",D14*D8),"") -> 548348.14
A17: CASH BREAK-EVEN (loan payments in, depreciation out)
A18: Cash fixed costs + principal repaid for the year | B18: =IFERROR(IF('3-Year P&L'!$B$9="","",B6-'3-Year P&L'!$B$35+B12),"") -> 323092.39 | C18: =IFERROR(IF('3-Year P&L'!$C$9="","",C6-'3-Year P&L'!$C$35+C12),"") -> 328092.39 | D18: =IFERROR(IF('3-Year P&L'!$D$9="","",D6-'3-Year P&L'!$D$35+D12),"") -> 333092.39 | E18: The P&L fixed costs without depreciation (which is not paid in cash) and WITH principal repaid (which is). This is the threshold that decides whether cash holds up
A19: Covers needed per year (cash) | B19: =IFERROR(IF('3-Year P&L'!$B$9="","",IF(B10<=0,"",B18/B10)),"") -> 29778.1 | C19: =IFERROR(IF('3-Year P&L'!$C$9="","",IF(C10<=0,"",C18/C10)),"") -> 30238.93 | D19: =IFERROR(IF('3-Year P&L'!$D$9="","",IF(D10<=0,"",D18/D10)),"") -> 30699.759
A20: Covers needed per day (cash) | B20: =IFERROR(IF('3-Year P&L'!$B$9="","",B19/B11),"") -> 96.682144 | C20: =IFERROR(IF('3-Year P&L'!$C$9="","",C19/C11),"") -> 98.178344 | D20: =IFERROR(IF('3-Year P&L'!$D$9="","",D19/D11),"") -> 99.674544
A21: Revenue needed per year (cash) | B21: =IFERROR(IF('3-Year P&L'!$B$9="","",B19*B8),"") -> 521116.76 | C21: =IFERROR(IF('3-Year P&L'!$C$9="","",C19*C8),"") -> 529181.27 | D21: =IFERROR(IF('3-Year P&L'!$D$9="","",D19*D8),"") -> 537245.79
A22: COMPARISON WITH THE PLAN
A23: Covers per day forecast in the plan | B23: =IFERROR(IF('3-Year P&L'!$B$9="","",'3-Year P&L'!$B$6),"") -> 115 | C23: =IFERROR(IF('3-Year P&L'!$C$9="","",'3-Year P&L'!$C$6),"") -> 121.9 | D23: =IFERROR(IF('3-Year P&L'!$D$9="","",'3-Year P&L'!$D$6),"") -> 126.776
A24: Cushion above CASH break-even (%) | B24: =IFERROR(IF('3-Year P&L'!$B$9="","",B23/B20-1),"") -> 0.18946472 | C24: =IFERROR(IF('3-Year P&L'!$C$9="","",C23/C20-1),"") -> 0.24161801 | D24: =IFERROR(IF('3-Year P&L'!$D$9="","",D23/D20-1),"") -> 0.27189948 | E24: How far planned sales sit above cash break-even. The drop you can absorb before you cannot pay the fixed costs and the loan payment is somewhat smaller: with a 25% cushion, 20%. The required minimum is set in the "0. Assumptions" tab
A25: Maximum seat turns per day the space allows | B25: 5 | E25: Full seatings per seat per day you can run, counting the take-out and delivery orders, which do not take a seat (almost half the covers in the example): about 3 dine-in turns in counter service (lunch and dinner, stays of 20-30 minutes) plus about 2 for take-out and delivery per seat. It is the physical ceiling of the space, not a target
A26: Seat turns per day that the cash break-even requires | B26: =IFERROR(IF('3-Year P&L'!$B$9="","",B20/'0. Assumptions'!$B$51),"") -> 3.2227381 | C26: =IFERROR(IF('3-Year P&L'!$C$9="","",C20/'0. Assumptions'!$B$51),"") -> 3.2726115 | D26: =IFERROR(IF('3-Year P&L'!$D$9="","",D20/'0. Assumptions'!$B$51),"") -> 3.3224848 | E26: Break-even covers spread across the seats declared on the "0. Assumptions" tab. If it is above the ceiling in the row above, the break-even is out of reach for the space
A27: INTERPRETATION
A28: =IFERROR("With the average check excl. sales tax above, you need "&TEXT(ROUNDUP(B15,0),"0")&" covers a day over your "&TEXT(B11,"0")&" opening days to avoid losing money (accounting break-even, depreciation included), and "&TEXT(ROUNDUP(B20,0),"0")&" for cash to hold (cash break-even: depreciation out, because it is not paid, and the year's loan payment in"&IF(B12=0,"; no principal is repaid this year (interest-only period or no loan)","")&"). The ""Revenue needed per year"" rows show the same figures in your currency.","") -> With the average check excl. sales tax above, you need 100 covers a day over your 308 opening days to avoid losing money (accounting break-even, depreciation included), and 97 for cash to hold (cash break-even: depreciation out, because it is not paid, and the year's loan payment in). The "Revenue needed per year" rows show the same figures in your currency.
A30: BREAK-EVEN SENSITIVITY
A31: Covers per day needed to cover costs for each average check (columns) and each variable cost per cover (rows). Green cells are below the covers per day the plan forecasts.
A33: Covers per day needed: average check excl. sales tax (columns) × variable cost per cover (rows) | B33: =IFERROR($B$8-2,"") -> 15.5 | C33: =IFERROR(IF($B$8="","",$B$8),"") -> 17.5 | D33: =IFERROR($B$8+2,"") -> 19.5 | E33: =IFERROR($B$8+4,"") -> 21.5
A34: =IFERROR($B$9*0.85,"") -> 5.6525 | B34: =IFERROR(IF($B$33-$A34<=0,"",$B$6/($B$33-$A34)/$B$11),"") -> 109.55873 | C34: =IFERROR(IF($C$33-$A34<=0,"",$B$6/($C$33-$A34)/$B$11),"") -> 91.063903 | D34: =IFERROR(IF($D$33-$A34<=0,"",$B$6/($D$33-$A34)/$B$11),"") -> 77.911507 | E34: =IFERROR(IF($E$33-$A34<=0,"",$B$6/($E$33-$A34)/$B$11),"") -> 68.078851
A35: =IFERROR($B$9*0.925,"") -> 6.15125 | B35: =IFERROR(IF($B$33-$A35<=0,"",$B$6/($B$33-$A35)/$B$11),"") -> 115.40362 | C35: =IFERROR(IF($C$33-$A35<=0,"",$B$6/($C$33-$A35)/$B$11),"") -> 95.06594 | D35: =IFERROR(IF($D$33-$A35<=0,"",$B$6/($D$33-$A35)/$B$11),"") -> 80.822518 | E35: =IFERROR(IF($E$33-$A35<=0,"",$B$6/($E$33-$A35)/$B$11),"") -> 70.291039
A36: =IFERROR($B$9*1.0,"") -> 6.65 | B36: =IFERROR(IF($B$33-$A36<=0,"",$B$6/($B$33-$A36)/$B$11),"") -> 121.9073 | C36: =IFERROR(IF($C$33-$A36<=0,"",$B$6/($C$33-$A36)/$B$11),"") -> 99.435907 | D36: =IFERROR(IF($D$33-$A36<=0,"",$B$6/($D$33-$A36)/$B$11),"") -> 83.959501 | E36: =IFERROR(IF($E$33-$A36<=0,"",$B$6/($E$33-$A36)/$B$11),"") -> 72.651824
A37: =IFERROR($B$9*1.075,"") -> 7.14875 | B37: =IFERROR(IF($B$33-$A37<=0,"",$B$6/($B$33-$A37)/$B$11),"") -> 129.1878 | C37: =IFERROR(IF($C$33-$A37<=0,"",$B$6/($C$33-$A37)/$B$11),"") -> 104.22699 | D37: =IFERROR(IF($D$33-$A37<=0,"",$B$6/($D$33-$A37)/$B$11),"") -> 87.34983 | E37: =IFERROR(IF($E$33-$A37<=0,"",$B$6/($E$33-$A37)/$B$11),"") -> 75.176698
A38: =IFERROR($B$9*1.15,"") -> 7.6475 | B38: =IFERROR(IF($B$33-$A38<=0,"",$B$6/($B$33-$A38)/$B$11),"") -> 137.39313 | C38: =IFERROR(IF($C$33-$A38<=0,"",$B$6/($C$33-$A38)/$B$11),"") -> 109.50313 | D38: =IFERROR(IF($D$33-$A38<=0,"",$B$6/($D$33-$A38)/$B$11),"") -> 91.025488 | E38: =IFERROR(IF($E$33-$A38<=0,"",$B$6/($E$33-$A38)/$B$11),"") -> 77.883385

Sheet Scenarios
A1: SCENARIO ANALYSIS
A2: Pessimistic / Base / Optimistic — Year 1
A4: Metric | B4: Pessimistic | C4: Base | D4: Optimistic | E4: Notes
A5: Covers per day | B5: 100 | C5: =IFERROR(IF('3-Year P&L'!$B$6="","",'3-Year P&L'!$B$6),"") -> 115 | D5: 130
A6: Average check (excl. sales tax) | B6: 16.5 | C6: =IFERROR(IF('3-Year P&L'!$B$7="","",'3-Year P&L'!$B$7),"") -> 17.5 | D6: 18.5
A7: Operating days per year | B7: 303 | C7: =IFERROR(IF('3-Year P&L'!$B$8="","",'3-Year P&L'!$B$8),"") -> 308 | D7: 312
A8: ANNUAL REVENUE (excl. sales tax) | B8: =IFERROR(IF(B5*B6*B7=0,"",B5*B6*B7),"") -> 499950 | C8: =IFERROR(IF(C5*C6*C7=0,"",C5*C6*C7),"") -> 619850 | D8: =IFERROR(IF(D5*D6*D7=0,"",D5*D6*D7),"") -> 750360
A9: Cost of goods sold — food | B9: =IFERROR(IF(B8="","",B8*'0. Assumptions'!$B$11*'0. Assumptions'!$B$13),"") -> 114738.53 | C9: =IFERROR(IF(C8="","",C8*'0. Assumptions'!$B$11*'0. Assumptions'!$B$13),"") -> 142255.58 | D9: =IFERROR(IF(D8="","",D8*'0. Assumptions'!$B$11*'0. Assumptions'!$B$13),"") -> 172207.62
A10: Cost of goods sold — beverage | B10: =IFERROR(IF(B8="","",B8*'0. Assumptions'!$B$12*'0. Assumptions'!$B$14),"") -> 16498.35 | C10: =IFERROR(IF(C8="","",C8*'0. Assumptions'!$B$12*'0. Assumptions'!$B$14),"") -> 20455.05 | D10: =IFERROR(IF(D8="","",D8*'0. Assumptions'!$B$12*'0. Assumptions'!$B$14),"") -> 24761.88
A11: Disposables and packaging | B11: =IFERROR(IF(B8="","",B8*'0. Assumptions'!$B$15),"") -> 19998 | C11: =IFERROR(IF(C8="","",C8*'0. Assumptions'!$B$15),"") -> 24794 | D11: =IFERROR(IF(D8="","",D8*'0. Assumptions'!$B$15),"") -> 30014.4
A12: Delivery platform fees | B12: =IFERROR(IF(B8="","",B8*'0. Assumptions'!$B$16*'0. Assumptions'!$B$17),"") -> 18748.125 | C12: =IFERROR(IF(C8="","",C8*'0. Assumptions'!$B$16*'0. Assumptions'!$B$17),"") -> 23244.375 | D12: =IFERROR(IF(D8="","",D8*'0. Assumptions'!$B$16*'0. Assumptions'!$B$17),"") -> 28138.5
A13: Card processing fees | B13: =IFERROR(IF(B8="","",B8*'0. Assumptions'!$B$18),"") -> 14998.5 | C13: =IFERROR(IF(C8="","",C8*'0. Assumptions'!$B$18),"") -> 18595.5 | D13: =IFERROR(IF(D8="","",D8*'0. Assumptions'!$B$18),"") -> 22510.8
A14: Miscellaneous and contingency | B14: =IFERROR(IF(B8="","",B8*'0. Assumptions'!$B$28),"") -> 4999.5 | C14: =IFERROR(IF(C8="","",C8*'0. Assumptions'!$B$28),"") -> 6198.5 | D14: =IFERROR(IF(D8="","",D8*'0. Assumptions'!$B$28),"") -> 7503.6
A15: TOTAL VARIABLE COSTS | B15: =IFERROR(IF(B8="","",SUM(B9:B14)),"") -> 189981 | C15: =IFERROR(IF(C8="","",SUM(C9:C14)),"") -> 235543 | D15: =IFERROR(IF(D8="","",SUM(D9:D14)),"") -> 285136.8
A16: GROSS MARGIN | B16: =IFERROR(IF(B8="","",B8-B15),"") -> 309969 | C16: =IFERROR(IF(C8="","",C8-C15),"") -> 384307 | D16: =IFERROR(IF(D8="","",D8-D15),"") -> 465223.2
A17: FIXED COSTS (the P&L's) | B17: =IFERROR(IF(B8="","",'3-Year P&L'!$B$37),"") -> 332294.91 | C17: =IFERROR(IF(C8="","",'3-Year P&L'!$B$37),"") -> 332294.91 | D17: =IFERROR(IF(D8="","",'3-Year P&L'!$B$37),"") -> 332294.91 | E17: Fixed costs do not change with the scenario: that is why they are fixed
A18: PRE-TAX INCOME (EBT) | B18: =IFERROR(IF(B8="","",B16-B17),"") -> -22325.914 | C18: =IFERROR(IF(C8="","",C16-C17),"") -> 52012.086 | D18: =IFERROR(IF(D8="","",D16-D17),"") -> 132928.29
A19: Income tax | B19: =IFERROR(IF(B8="","",MAX(0,B18-'0. Assumptions'!$B$42)*'0. Assumptions'!$B$37),"") -> 0 | C19: =IFERROR(IF(C8="","",MAX(0,C18-'0. Assumptions'!$B$42)*'0. Assumptions'!$B$37),"") -> 13003.021 | D19: =IFERROR(IF(D8="","",MAX(0,D18-'0. Assumptions'!$B$42)*'0. Assumptions'!$B$37),"") -> 33232.071 | E19: At the "years 1-2" effective income tax rate, offsetting prior net operating losses
A20: NET INCOME | B20: =IFERROR(IF(B8="","",B18-B19),"") -> -22325.914 | C20: =IFERROR(IF(C8="","",C18-C19),"") -> 39009.064 | D20: =IFERROR(IF(D8="","",D18-D19),"") -> 99696.214
A21: Covers per day to break even | B21: =IFERROR(IF(B8="","",IF(B6-B15/(B5*B7)<=0,"",B17/(B6-B15/(B5*B7))/B7)),"") -> 107.20263 | C21: =IFERROR(IF(C8="","",IF(C6-C15/(C5*C7)<=0,"",C17/(C6-C15/(C5*C7))/C7)),"") -> 99.435907 | D21: =IFERROR(IF(D8="","",IF(D6-D15/(D5*D7)<=0,"",D17/(D6-D15/(D5*D7))/D7)),"") -> 92.855083
A22: WHAT EACH SCENARIO DEMANDS
A23: Labor cost / Sales | B23: =IFERROR(IF(B8="","",'3-Year P&L'!$B$23/B8),"") -> 0.42854125 | C23: =IFERROR(IF(C8="","",'3-Year P&L'!$B$23/C8),"") -> 0.34564685 | D23: =IFERROR(IF(D8="","",'3-Year P&L'!$B$23/D8),"") -> 0.28552855 | E23: The SAME staffing in all three scenarios. If labor cost blows up in the pessimistic case, adjust it in the Staffing tab, not here
A24: Covers per year per full-time equivalent | B24: =IFERROR(IF(B8="","",B5*B7/Staffing!$C$12),"") -> 6029.8507 | C24: =IFERROR(IF(C8="","",C5*C7/Staffing!$C$12),"") -> 7048.7562 | D24: =IFERROR(IF(D8="","",D5*D7/Staffing!$C$12),"") -> 8071.6418 | E24: Covers each full-time employee in the "Staffing" tab would have to serve. In the optimistic scenario it tells you whether you need to hire
A25: Year-1 closing cash balance (estimate, same method in all three scenarios) | B25: =IFERROR(IF(B8="","",'Startup Costs'!$B$29+B20+'3-Year P&L'!$B$35-Financing!$B$45),"") -> 64888.911 | C25: =IFERROR(IF(C8="","",'Startup Costs'!$B$29+C20+'3-Year P&L'!$B$35-Financing!$B$45),"") -> 126223.89 | D25: =IFERROR(IF(D8="","",'Startup Costs'!$B$29+D20+'3-Year P&L'!$B$35-Financing!$B$45),"") -> 186911.04 | E25: ESTIMATED balance: working capital plus the year's result, adding back depreciation (which is not paid) and subtracting loan principal. It does not include the timing gap between receipts and payments or the sales tax settlement, so the three columns can be compared with each other. In red, the scenario runs out of cash
A26: Actual month-12 balance from the 12-Month Cash Flow tab (Base case only) | C26: =IFERROR(IF(C8="","",'12-Month Cash Flow'!$M$22),"") -> 157133.93 | E26: The ACTUAL base-case balance, with its timing of receipts and payments and its sales tax settlement. It exists only for the Base scenario, the only one with its own monthly cash flow: that is why it is not in the row above, where it would be compared against two estimates
A28: The "Base" column reads its three inputs from the "0. Assumptions" tab, so it reproduces EXACTLY year 1 of the P&L. The other two scenarios use the same cost rates: the only things that change are covers, average check and days. FIXED COSTS are the same in all three: miscellaneous and contingency, which is a percentage of sales, sits at the top with the variable costs and each scenario carries its own.

Sheet Staffing
A1: STAFFING STRUCTURE AND COSTS
A2: =IFERROR("Payroll — "&TEXT('0. Assumptions'!$B$21,"0")&" pay periods + employer taxes "&TEXT('0. Assumptions'!$B$20*100,"0")&"%","") -> Payroll — 12 pay periods + employer taxes 10%
A4: Position | B4: People | C4: FTE | D4: Gross pay per month (total for the position) | E4: Employer payroll taxes (total for the position) | F4: Cost per month (total for the position) | G4: Cost per year | H4: Hours per week per person | I4: Hours per year for the position | J4: Notes
A5: Owner / head taquero & GM | B5: 1 | C5: 1 | D5: 4500 | E5: =IFERROR(IF(D5="","",D5*'0. Assumptions'!$B$20),"") -> 450 | F5: =IFERROR(IF(D5="","",D5+E5),"") -> 4950 | G5: =IFERROR(IF(D5="","",F5*MAX(12,'0. Assumptions'!$B$21)),"") -> 59400 | H5: =IFERROR(IF(D5="","",C5*$B$19),"") -> 40 | I5: =IFERROR(IF(D5="","",H5*B5*$B$20),"") -> 1840 | J5: Marinates and builds the trompo, runs the cutting on the busy shift, buys (the dried chile and Mexican specialty distributor included) and manages. The workbook imputes a monthly salary as if on payroll, which is the prudent side; confirm with your CPA how you will pay yourself (owner's draw or W-2 under an S corp). The example pays the owner below a manager: owner's draw in addition from net profit
A6: Taquero / line cook (trompo & griddle) | B6: 1 | C6: 1 | D6: 3293 | E6: =IFERROR(IF(D6="","",D6*'0. Assumptions'!$B$20),"") -> 329.3 | F6: =IFERROR(IF(D6="","",D6+E6),"") -> 3622.3 | G6: =IFERROR(IF(D6="","",F6*MAX(12,'0. Assumptions'!$B$21)),"") -> 43467.6 | H6: =IFERROR(IF(D6="","",C6*$B$19),"") -> 40 | I6: =IFERROR(IF(D6="","",H6*B6*$B$20),"") -> 1840 | J6: Slices the trompo, runs the griddle and the comal and can marinate with the owner. It is an investment, not an expense: if only the owner can marinate and slice the trompo, a sick day closes the shop
A7: Prep cook (marinades, carnitas, salsas, aguas frescas) | B7: 1 | C7: 0.75 | D7: 2340 | E7: =IFERROR(IF(D7="","",D7*'0. Assumptions'!$B$20),"") -> 234 | F7: =IFERROR(IF(D7="","",D7+E7),"") -> 2574 | G7: =IFERROR(IF(D7="","",F7*MAX(12,'0. Assumptions'!$B$21)),"") -> 30888 | H7: =IFERROR(IF(D7="","",C7*$B$19),"") -> 30 | I7: =IFERROR(IF(D7="","",H7*B7*$B$20),"") -> 1380 | J7: Carnitas and guisados, salsas, aguas frescas, marinades, mise en place and prep, 30 hours a week
A8: Counter lead / cashier | B8: 1 | C8: 1 | D8: 2773 | E8: =IFERROR(IF(D8="","",D8*'0. Assumptions'!$B$20),"") -> 277.3 | F8: =IFERROR(IF(D8="","",D8+E8),"") -> 3050.3 | G8: =IFERROR(IF(D8="","",F8*MAX(12,'0. Assumptions'!$B$21)),"") -> 36603.6 | H8: =IFERROR(IF(D8="","",C8*$B$19),"") -> 40 | I8: =IFERROR(IF(D8="","",H8*B8*$B$20),"") -> 1840 | J8: Year-round: counter, register, take-out orders, the delivery marketplace tablets and allergen information
A9: Counter & expo (part-time W-2) | B9: 2 | C9: 0.4 | D9: 2080 | E9: =IFERROR(IF(D9="","",D9*'0. Assumptions'!$B$20),"") -> 208 | F9: =IFERROR(IF(D9="","",D9+E9),"") -> 2288 | G9: =IFERROR(IF(D9="","",F9*MAX(12,'0. Assumptions'!$B$21)),"") -> 27456 | H9: =IFERROR(IF(D9="","",C9*$B$19),"") -> 16 | I9: =IFERROR(IF(D9="","",H9*B9*$B$20),"") -> 1472 | J9: Dinner and weekend shifts at the counter and expo, when the shop fills. Part-time W-2 employees; tips are not modeled
A10: Dish & prep (part-time W-2) | B10: 1 | C10: 0.375 | D10: 975 | E10: =IFERROR(IF(D10="","",D10*'0. Assumptions'!$B$20),"") -> 97.5 | F10: =IFERROR(IF(D10="","",D10+E10),"") -> 1072.5 | G10: =IFERROR(IF(D10="","",F10*MAX(12,'0. Assumptions'!$B$21)),"") -> 12870 | H10: =IFERROR(IF(D10="","",C10*$B$19),"") -> 15 | I10: =IFERROR(IF(D10="","",H10*B10*$B$20),"") -> 690 | J10: Friday-to-Sunday help: dish, prep and the pickup counter, plus the patio in season. This plan has NO delivery drivers of its own: if you add them, they are W-2 employees in most states, never independent contractors by default (check yours), and you need hired and non-owned auto insurance
A11: Relief cover (vacations + days off) | B11: 1 | C11: 0.1 | D11: 270 | E11: =IFERROR(IF(D11="","",D11*'0. Assumptions'!$B$20),"") -> 27 | F11: =IFERROR(IF(D11="","",D11+E11),"") -> 297 | G11: =IFERROR(IF(D11="","",F11*MAX(12,'0. Assumptions'!$B$21)),"") -> 3564 | H11: =IFERROR(IF(D11="","",C11*$B$19),"") -> 4 | I11: =IFERROR(IF(D11="","",H11*B11*$B$20),"") -> 184 | J11: Coverage for vacations and the team's days off through the year. Paid sick leave is required by some states and cities: check yours
A12: TOTAL STAFF | B12: =IFERROR(IF(COUNT(D5:D11)=0,"",SUM(B5:B11)),"") -> 8 | C12: =IFERROR(IF(COUNT(D5:D11)=0,"",SUMPRODUCT(B5:B11,C5:C11)),"") -> 5.025 | D12: =IFERROR(IF(COUNT(D5:D11)=0,"",SUM(D5:D11)),"") -> 16231 | E12: =IFERROR(IF(COUNT(D5:D11)=0,"",SUM(E5:E11)),"") -> 1623.1 | F12: =IFERROR(IF(COUNT(D5:D11)=0,"",SUM(F5:F11)),"") -> 17854.1 | G12: =IFERROR(IF(COUNT(D5:D11)=0,"",SUM(G5:G11)),"") -> 214249.2 | I12: =IFERROR(IF(COUNT(D5:D11)=0,"",SUM(I5:I11)),"") -> 9246
A13: STAFF GROWTH (stepped cost)
A14: Annual cost of year-2 hires | B14: 5000 | J14: FULL ANNUAL cost (gross pay + employer payroll taxes, over all pay periods) of whoever you hire that year. The P&L adds it to the previous year's cost: staffing grows by people, not by a percentage
A15: Annual cost of year-3 hires | B15: 5000 | J15: FULL ANNUAL cost (gross pay + employer payroll taxes, over all pay periods) of whoever you hire that year. The P&L adds it to the previous year's cost: staffing grows by people, not by a percentage
A16: Labor cost, year 2 | B16: =IFERROR(IF(G12="","",G12*(1+'0. Assumptions'!$B$48)+B14),"") -> 219249.2
A17: Labor cost, year 3 | B17: =IFERROR(IF(B16="","",B16*(1+'0. Assumptions'!$B$48)+B15),"") -> 224249.2
A18: COVERAGE OF SERVICE HOURS
A19: Full-time week (hours per week) | B19: 40 | J19: 40 hours a week is the FLSA overtime threshold for non-exempt employees; some states add daily overtime rules. Change it if your own full-time week is different
A20: Weeks worked per year per person | B20: 46 | J20: 46 weeks: 52 minus about six weeks for vacation, holidays and average absences. There is no federal vacation requirement in the US: adjust it to your own policy
A21: Service hours per day to cover | B21: 10.5 | J21: Hours the shop is open to the public, adding the lunch and dinner rushes and the preparation for each. Any slow stretch between the two is not counted
A22: People needed at the same time in each shift | B22: 2.5 | J22: Average number of people on at once between the trompo, the griddle or comal, the counter and expo. On Saturday night five are needed: the weekend help and the dinner counter staff come in (the annual schedule does not see this: put it on the shift schedule)
A23: Production hours per day BEFORE opening | B23: 2.5 | J23: Next-day marinade, building the cone, carnitas and guisados, salsas and mise en place before opening
A24: People on the production shift | B24: 1.5 | J24: The owner with the prep cook. Closing, cleaning and purchasing are outside this schedule: they are the margin between the hours hired and the hours needed
A25: Service hours to cover per year | B25: =IFERROR(IF(OR(B21="",B22="",'0. Assumptions'!$B$6=""),"",B21*B22*'0. Assumptions'!$B$6+B23*B24*'0. Assumptions'!$B$6),"") -> 9240
A26: Hours hired per year | B26: =IFERROR(IF(I12="","",I12),"") -> 9246
A27: Coverage (hired / needed) | B27: =IFERROR(B26/B25,"") -> 1.0006494 | J27: Below 100% the staff cannot cover the hours the plan declares: either hire more or cut the hours
A29: The gross pay, employer payroll taxes, monthly cost and annual cost columns are TOTALS for the row: for a position with two people they include both. "FTE" is the share of a full-time week and is used to compare pay with the legal floor pro rata. The payroll tax rate and the number of pay periods are in the "0. Assumptions" tab. Tips are not modeled: this is counter service, every position is budgeted at a base wage of at least $15/h, and counter tips (tip jar or screen) belong to the staff, never to the owner or managers. Federal rules allow a $2.13/h cash wage with a tip credit of up to $5.12 where the state permits it; CA, OR, WA, AK, MN, MT and NV do not (DOL)
A30: The pay floor is the HIGHER of the federal minimum wage and your state / local minimum wage, both in the "0. Assumptions" tab; part-time positions get it in proportion. There is no single national table above the federal floor: the state / local cell is delivered empty so you can enter the rate for your state and city.

Sheet Instructions
A1: HOW TO USE THIS WORKBOOK — Taco Shop Financial Projections
A3: HOW TO USE THIS WORKBOOK
A4: This financial plan is a MODEL: you type only in the GREEN cells and everything else recalculates on its own.
A5: 1. "0. Assumptions" is the control sheet: covers per day, average check excl. sales tax, operating days, food and beverage mix, cost of goods sold, rent, financing and taxes.
A6: 2. Startup cost items, fixed costs and staffing are typed in their own tab, also in green. No number is typed twice.
A7: 3. On "Break-Even" you only type the seat-turn ceiling your space allows; everything else derives from the rest. The other three tabs also have green cells you can change: the pessimistic and optimistic scenarios on "Scenarios", the seasonality and the launch ramp-up on "12-Month Cash Flow", and the other financing sources on "Financing" (rows 8-11 count as sources but are not amortized: Your bank or SBA 7(a) loan goes in "Loan requested" on "0. Assumptions"). Everything else is calculated.
A8: 4. All figures are EXCL. SALES TAX. To turn a menu price into a price excl. sales tax, divide it by 1 plus your sales tax rate (a rate of 8% means dividing by 1.08). The example uses ONE rate for everything: dine-in, take-out, delivery and beverages; some states tax food to go or alcohol differently, so check yours. The P&L is excl. sales tax; the "12-Month Cash Flow" tab shows what you actually collect, sales tax included, and the sales tax you remit as a quarterly filer.
A9: 5. If you change the staffing, the P&L reads it on its own: labor cost comes from the "Staffing" tab, not from a separate estimate.
A10: 6. The "12-Month Cash Flow" tab answers the question that decides a bank deal: in which month the cash runs out. Its Month 1 is JANUARY, in calendar order: the ramp-up falls on January and February, the slowest months, and that is why working capital counts. If you open in another month, rotate the seasonality row. The minimum balance of the year can never show in red.
A11: 7. The "Financing" tab matches what you need with what you put in and builds the amortization schedule of the loan. If the difference is red, the plan is not funded.
A12: 8. The Word business plan in this pack quotes the figures in this Excel: if you change a green cell, the Excel rules. The Taco Cost & Trompo Yield Calculator is separate and is used to measure the yield of the cone and COST each taco: do not copy the food cost of one taco into the "0. Assumptions" tab. The "Cost of goods sold on FOOD sales" cell is the weighted average of the WHOLE menu (tacos, gringas, guisados, chips and guacamole and birria, each by what it sells) plus waste, and that is why it comes out higher than the food cost of the al pastor taco. With the costing of your own menu, check that this average holds.
A14: RATIOS AUDITED BY THIS WORKBOOK
A15: Thresholds live in the "Threshold" column of the KEY RATIOS block of the P&L: change them there and the traffic light changes with them.
A17: Ratio | B17: Year 1 value | C17: Threshold | D17: Status
A18: Cost of goods sold / Sales | B18: =IFERROR(IF('3-Year P&L'!$B$52="","",'3-Year P&L'!$B$52),"") -> 0.2625 | C18: =IFERROR(IF('3-Year P&L'!$E$52="","",'3-Year P&L'!$E$52),"") -> 0.3 | D18: =IFERROR(IF(OR(B18="",C18=""),"",IF(B18<=C18,"OK","REVIEW")),"") -> OK
A19: Labor cost / Sales | B19: =IFERROR(IF('3-Year P&L'!$B$53="","",'3-Year P&L'!$B$53),"") -> 0.34564685 | C19: =IFERROR(IF('3-Year P&L'!$E$53="","",'3-Year P&L'!$E$53),"") -> 0.36 | D19: =IFERROR(IF(OR(B19="",C19=""),"",IF(B19<=C19,"OK","REVIEW")),"") -> OK
A20: Rent / Sales | B20: =IFERROR(IF('3-Year P&L'!$B$54="","",'3-Year P&L'!$B$54),"") -> 0.054206663 | C20: =IFERROR(IF('3-Year P&L'!$E$54="","",'3-Year P&L'!$E$54),"") -> 0.1 | D20: =IFERROR(IF(OR(B20="",C20=""),"",IF(B20<=C20,"OK","REVIEW")),"") -> OK
A21: Net income / Sales | B21: =IFERROR(IF('3-Year P&L'!$B$55="","",'3-Year P&L'!$B$55),"") -> 0.062933071 | C21: =IFERROR(IF('3-Year P&L'!$E$55="","",'3-Year P&L'!$E$55),"") -> 0.05 | D21: =IFERROR(IF(OR(B21="",C21=""),"",IF(B21>=C21,"OK","REVIEW")),"") -> OK
A22: Gross margin / Sales | B22: =IFERROR(IF('3-Year P&L'!$B$50="","",'3-Year P&L'!$B$50),"") -> 0.62 | C22: =IFERROR(IF('3-Year P&L'!$E$50="","",'3-Year P&L'!$E$50),"") -> 0.6 | D22: =IFERROR(IF(OR(B22="",C22=""),"",IF(B22>=C22,"OK","REVIEW")),"") -> OK
A24: THIS PLAN'S KEY FIGURES
A25: Total startup costs (sum of the blocks) | B25: =IFERROR(IF('Startup Costs'!$B$30="","",'Startup Costs'!$B$30),"") -> 275612.3
A26: Total cash needed at launch | B26: =IFERROR(IF('Startup Costs'!$B$33="","",'Startup Costs'!$B$33),"") -> 275612.3
A27: Working capital funded | B27: =IFERROR(IF('Startup Costs'!$B$29="","",'Startup Costs'!$B$29),"") -> 78012.3
A28: Forecast year-1 revenue | B28: =IFERROR(IF('3-Year P&L'!$B$9="","",'3-Year P&L'!$B$9),"") -> 619850
A29: Year-1 net income | B29: =IFERROR(IF('3-Year P&L'!$B$47="","",'3-Year P&L'!$B$47),"") -> 39009.064
A30: Covers per day for the ACCOUNTING break-even (depreciation included) | B30: =IFERROR(IF('Break-Even'!$B$15="","",'Break-Even'!$B$15),"") -> 99.435907
A31: Project payback (years), before debt | B31: =IFERROR(IF('12-Month Cash Flow'!$B$31="","",'12-Month Cash Flow'!$B$31),"") -> Over 3 years
A33: US TAQUERIA BENCHMARKS (sourced) AND KIT ESTIMATES
A34: Benchmark | B34: Value | C34: Source | D34: Note
A35: Month 1 of the plan | B35: January | C35: Plan decision | D35: In calendar order: the ramp-up falls on the slowest months and working capital covers it. If you open in another month, rotate the seasonality row of the "12-Month Cash Flow" tab
A36: Street taco on the menu | B36: $3.00-3.75 in mid-size cities; about $5 in big cities | C36: Kit estimate (menu scan, Oct 2026) | D36: This plan prices it at $4.00 (a plate of 3 tacos with rice & beans comes to about $14)
A37: Al pastor taco food cost | B37: About 25% of its price excl. sales tax | C37: Kit estimate (Taco Cost & Trompo Yield Calculator) | D37: 2 corn tortillas (6 in), 1.5 oz (43 g) of meat served, garnish and salsa, with 5% waste. Meat and tortilla prices are Kit estimates: enter your distributor's
A38: Trompo yield | B38: About 7 tacos per raw lb (a 30 lb (13.6 kg) cone is about 207 tacos) | C38: Kit estimate (65% yield, 1.5 oz served) | D38: Measure your own with the Taco Cost & Trompo Yield Calculator (raw cone, leftover, served)
A39: Vertical broiler (trompo) | B39: $999-$2,844 each | C39: webstaurantstore.com (Avantco VB203, Visvardis DG8A), read Oct 2026 | D39: The example counts two gas trompos; a charcoal trompo is a solid-fuel variant (NFPA 96)
A40: Delivery marketplace commission | B40: DoorDash 15 / 25 / 30% + 6% pickup; Uber Eats 15-30% | C40: merchants.ubereats.com; DoorDash tiers (Oct 2026) | D40: This plan: 25% on the 15% of sales that go through marketplaces. Direct pickup pays no commission; check your contract
A41: Sales tax | B41: 8% (example: state + local) | C41: Kit example: look up your state and city rate | D41: One rate in the workbook; some states tax food to go differently
A42: Hot and cold holding | B42: ≥ 135 °F (57 °C) hot, ≤ 41 °F (5 °C) cold; reheat to 165 °F (74 °C) within 2 h; TPHC up to 4 h with a written procedure | C42: FDA Food Code 2022 (3-501.16, 3-403.11, 3-501.19) | D42: Each state adopts its own edition. A salsa bar run on TPHC needs the written procedure. Cut tomatoes (pico de gallo, fresh salsas) are TCS; for guacamole, treat it as TCS and ask your regulator
A43: Minimum wage | B43: Federal $7.25/h + your state | C43: U.S. Department of Labor (dol.gov) | D43: This plan budgets at least $15/h; enter your state's floor on "0. Assumptions"
A44: Labor cost / sales | B44: 25-35% | C44: UpMenu (upmenu.com) | D44: Counter service lands at the low end; two taqueros (the owner and a second one) are insurance, not a luxury
A45: Rent / sales | B45: ≤ 10% | C45: Kit estimate | D45: The threshold of the P&L traffic light; a space with a Type I hood already installed saves build-out
A46: Al pastor cook temperature | B46: Set by your county: 145 °F (63 °C) in some, 155 °F (68 °C) in others (165 °F (74 °C) for chicken) | C46: County vertical broiler guidance (summaries) | D46: Ask your health department in writing for the cook temperature, the maximum time on the broiler and what to do with the leftover cone; never rely on a single figure
A48: To edit a cell that is not green: Review → Unprotect Sheet (there is no password).
A49: More templates and kits in the catalog at aichef.pro/en/digital-products
A50: Designed by John Guerrero — chef and restaurant consultant since 2010, in the kitchen since age 17 · johnguerrero.es
A51: Version 2.2 · October 2026 · aichef.pro/en/digital-products/taco-shop-business-plan · info@aichef.pro
A52: Planning tool, not financial, tax or legal advice. Requirements vary by state, county and city — check with your accountant and local authorities.

Sheet 12-Month Cash Flow
A1: CASH FLOW FORECAST — YEAR 1
A2: The P&L tells you whether the business makes money; this tab tells you whether you have cash left to get to the end of the month. It is the first one a lender looks at.
A4: Item | B4: Month 1 | C4: Month 2 | D4: Month 3 | E4: Month 4 | F4: Month 5 | G4: Month 6 | H4: Month 7 | I4: Month 8 | J4: Month 9 | K4: Month 10 | L4: Month 11 | M4: Month 12 | N4: Year
A5: Monthly seasonality (adds up to 100%) | B5: 0.074 | C5: 0.076 | D5: 0.084 | E5: 0.086 | F5: 0.092 | G5: 0.088 | H5: 0.088 | I5: 0.086 | J5: 0.084 | K5: 0.084 | L5: 0.078 | M5: 0.08 | N5: =IFERROR(IF('3-Year P&L'!$B$9="","",SUM(B5:M5)),"") -> 1 | O5: Month 1 = JANUARY, in calendar order: January and February are the slowest months, May is the peak (Cinco de Mayo, celebrated mostly in the US, plus the start of patio season) and the summer stays strong with the patio. Kit weights for a mid-size US city: replace them with your area's pattern; if you open in another month, rotate the row. It must add up to 100%
A6: Launch ramp-up (% of steady-state activity) | B6: =IFERROR(IF('3-Year P&L'!$B$9="","",MIN(1,'0. Assumptions'!$B$52+(1-'0. Assumptions'!$B$52)*0/MAX(1,'0. Assumptions'!$B$53-1))),"") -> 0.75 | C6: =IFERROR(IF('3-Year P&L'!$B$9="","",MIN(1,'0. Assumptions'!$B$52+(1-'0. Assumptions'!$B$52)*1/MAX(1,'0. Assumptions'!$B$53-1))),"") -> 0.83333333 | D6: =IFERROR(IF('3-Year P&L'!$B$9="","",MIN(1,'0. Assumptions'!$B$52+(1-'0. Assumptions'!$B$52)*2/MAX(1,'0. Assumptions'!$B$53-1))),"") -> 0.91666667 | E6: =IFERROR(IF('3-Year P&L'!$B$9="","",MIN(1,'0. Assumptions'!$B$52+(1-'0. Assumptions'!$B$52)*3/MAX(1,'0. Assumptions'!$B$53-1))),"") -> 1 | F6: =IFERROR(IF('3-Year P&L'!$B$9="","",MIN(1,'0. Assumptions'!$B$52+(1-'0. Assumptions'!$B$52)*4/MAX(1,'0. Assumptions'!$B$53-1))),"") -> 1 | G6: =IFERROR(IF('3-Year P&L'!$B$9="","",MIN(1,'0. Assumptions'!$B$52+(1-'0. Assumptions'!$B$52)*5/MAX(1,'0. Assumptions'!$B$53-1))),"") -> 1 | H6: =IFERROR(IF('3-Year P&L'!$B$9="","",MIN(1,'0. Assumptions'!$B$52+(1-'0. Assumptions'!$B$52)*6/MAX(1,'0. Assumptions'!$B$53-1))),"") -> 1 | I6: =IFERROR(IF('3-Year P&L'!$B$9="","",MIN(1,'0. Assumptions'!$B$52+(1-'0. Assumptions'!$B$52)*7/MAX(1,'0. Assumptions'!$B$53-1))),"") -> 1 | J6: =IFERROR(IF('3-Year P&L'!$B$9="","",MIN(1,'0. Assumptions'!$B$52+(1-'0. Assumptions'!$B$52)*8/MAX(1,'0. Assumptions'!$B$53-1))),"") -> 1 | K6: =IFERROR(IF('3-Year P&L'!$B$9="","",MIN(1,'0. Assumptions'!$B$52+(1-'0. Assumptions'!$B$52)*9/MAX(1,'0. Assumptions'!$B$53-1))),"") -> 1 | L6: =IFERROR(IF('3-Year P&L'!$B$9="","",MIN(1,'0. Assumptions'!$B$52+(1-'0. Assumptions'!$B$52)*10/MAX(1,'0. Assumptions'!$B$53-1))),"") -> 1 | M6: =IFERROR(IF('3-Year P&L'!$B$9="","",MIN(1,'0. Assumptions'!$B$52+(1-'0. Assumptions'!$B$52)*11/MAX(1,'0. Assumptions'!$B$53-1))),"") -> 1 | O6: Rises in a straight line from the month-1 percentage to 100% over the number of months you set in Assumptions. With month 1 at 100%, the ramp disappears
A7: Split of activity by month (calculated) | B7: =IFERROR(IF('3-Year P&L'!$B$9="","",B5*B6/SUMPRODUCT($B$5:$M$5,$B$6:$M$6)),"") -> 0.057702305 | C7: =IFERROR(IF('3-Year P&L'!$B$9="","",C5*C6/SUMPRODUCT($B$5:$M$5,$B$6:$M$6)),"") -> 0.065846474 | D7: =IFERROR(IF('3-Year P&L'!$B$9="","",D5*D6/SUMPRODUCT($B$5:$M$5,$B$6:$M$6)),"") -> 0.08005545 | E7: =IFERROR(IF('3-Year P&L'!$B$9="","",E5*E6/SUMPRODUCT($B$5:$M$5,$B$6:$M$6)),"") -> 0.08941258 | F7: =IFERROR(IF('3-Year P&L'!$B$9="","",F5*F6/SUMPRODUCT($B$5:$M$5,$B$6:$M$6)),"") -> 0.095650667 | G7: =IFERROR(IF('3-Year P&L'!$B$9="","",G5*G6/SUMPRODUCT($B$5:$M$5,$B$6:$M$6)),"") -> 0.091491942 | H7: =IFERROR(IF('3-Year P&L'!$B$9="","",H5*H6/SUMPRODUCT($B$5:$M$5,$B$6:$M$6)),"") -> 0.091491942 | I7: =IFERROR(IF('3-Year P&L'!$B$9="","",I5*I6/SUMPRODUCT($B$5:$M$5,$B$6:$M$6)),"") -> 0.08941258 | ... M7: =IFERROR(IF('3-Year P&L'!$B$9="","",M5*M6/SUMPRODUCT($B$5:$M$5,$B$6:$M$6)),"") -> 0.083174493 | N7: =IFERROR(IF('3-Year P&L'!$B$9="","",SUM(B7:M7)),"") -> 1 | O7: Seasonality × ramp-up, normalized to 100%: the YEAR brings in what the P&L says, but split the way a business that has just opened would split it
A8: CASH IN
A9: Sales collected (incl. sales tax collected) | B9: =IFERROR(IF('3-Year P&L'!$B$9="","",('3-Year P&L'!$B$9+'3-Year P&L'!$B$9*SUMPRODUCT('3-Year P&L'!$E$10:$E$11,'3-Year P&L'!$G$10:$G$11))*B7*(1-MIN(30,'0. Assumptions'!$B$58)/30)),"") -> 36052.908 | C9: =IFERROR(IF('3-Year P&L'!$B$9="","",('3-Year P&L'!$B$9+'3-Year P&L'!$B$9*SUMPRODUCT('3-Year P&L'!$E$10:$E$11,'3-Year P&L'!$G$10:$G$11))*(C7*(1-MIN(30,'0. Assumptions'!$B$58)/30)+B7*MIN(30,'0. Assumptions'!$B$58)/30)),"") -> 43716.664 | D9: =IFERROR(IF('3-Year P&L'!$B$9="","",('3-Year P&L'!$B$9+'3-Year P&L'!$B$9*SUMPRODUCT('3-Year P&L'!$E$10:$E$11,'3-Year P&L'!$G$10:$G$11))*(D7*(1-MIN(30,'0. Assumptions'!$B$58)/30)+C7*MIN(30,'0. Assumptions'!$B$58)/30)),"") -> 52958.025 | E9: =IFERROR(IF('3-Year P&L'!$B$9="","",('3-Year P&L'!$B$9+'3-Year P&L'!$B$9*SUMPRODUCT('3-Year P&L'!$E$10:$E$11,'3-Year P&L'!$G$10:$G$11))*(E7*(1-MIN(30,'0. Assumptions'!$B$58)/30)+D7*MIN(30,'0. Assumptions'!$B$58)/30)),"") -> 59438.578 | F9: =IFERROR(IF('3-Year P&L'!$B$9="","",('3-Year P&L'!$B$9+'3-Year P&L'!$B$9*SUMPRODUCT('3-Year P&L'!$E$10:$E$11,'3-Year P&L'!$G$10:$G$11))*(F7*(1-MIN(30,'0. Assumptions'!$B$58)/30)+E7*MIN(30,'0. Assumptions'!$B$58)/30)),"") -> 63753.79 | G9: =IFERROR(IF('3-Year P&L'!$B$9="","",('3-Year P&L'!$B$9+'3-Year P&L'!$B$9*SUMPRODUCT('3-Year P&L'!$E$10:$E$11,'3-Year P&L'!$G$10:$G$11))*(G7*(1-MIN(30,'0. Assumptions'!$B$58)/30)+F7*MIN(30,'0. Assumptions'!$B$58)/30)),"") -> 61433.784 | H9: =IFERROR(IF('3-Year P&L'!$B$9="","",('3-Year P&L'!$B$9+'3-Year P&L'!$B$9*SUMPRODUCT('3-Year P&L'!$E$10:$E$11,'3-Year P&L'!$G$10:$G$11))*(H7*(1-MIN(30,'0. Assumptions'!$B$58)/30)+G7*MIN(30,'0. Assumptions'!$B$58)/30)),"") -> 61248.183 | I9: =IFERROR(IF('3-Year P&L'!$B$9="","",('3-Year P&L'!$B$9+'3-Year P&L'!$B$9*SUMPRODUCT('3-Year P&L'!$E$10:$E$11,'3-Year P&L'!$G$10:$G$11))*(I7*(1-MIN(30,'0. Assumptions'!$B$58)/30)+H7*MIN(30,'0. Assumptions'!$B$58)/30)),"") -> 59948.979 | J9: =IFERROR(IF('3-Year P&L'!$B$9="","",('3-Year P&L'!$B$9+'3-Year P&L'!$B$9*SUMPRODUCT('3-Year P&L'!$E$10:$E$11,'3-Year P&L'!$G$10:$G$11))*(J7*(1-MIN(30,'0. Assumptions'!$B$58)/30)+I7*MIN(30,'0. Assumptions'!$B$58)/30)),"") -> 58556.975 | ... M9: =IFERROR(IF('3-Year P&L'!$B$9="","",('3-Year P&L'!$B$9+'3-Year P&L'!$B$9*SUMPRODUCT('3-Year P&L'!$E$10:$E$11,'3-Year P&L'!$G$10:$G$11))*(M7*(1-MIN(30,'0. Assumptions'!$B$58)/30)+L7*MIN(30,'0. Assumptions'!$B$58)/30)),"") -> 55587.366 | N9: =IFERROR(IF('3-Year P&L'!$B$9="","",SUM(B9:M9)),"") -> 665725.99 | O9: The month's sales plus the sales tax collected, adjusted by the average collection days from the Assumptions tab
A10: CASH OUT
A11: Purchases and variable costs (incl. sales tax) | B11: =IFERROR(IF('3-Year P&L'!$B$9="","",-('3-Year P&L'!$B$13*(1+'3-Year P&L'!$G$13)+'3-Year P&L'!$B$14*(1+'3-Year P&L'!$G$14)+'3-Year P&L'!$B$15*(1+'3-Year P&L'!$G$15)+'3-Year P&L'!$B$16*(1+'3-Year P&L'!$G$16)+'3-Year P&L'!$B$17*(1+'3-Year P&L'!$G$17)+'3-Year P&L'!$B$18*(1+'3-Year P&L'!$G$18))*B7*(1-MIN(30,'0. Assumptions'!$B$59)/30)),"") -> -7248.7328 | C11: =IFERROR(IF('3-Year P&L'!$B$9="","",-('3-Year P&L'!$B$13*(1+'3-Year P&L'!$G$13)+'3-Year P&L'!$B$14*(1+'3-Year P&L'!$G$14)+'3-Year P&L'!$B$15*(1+'3-Year P&L'!$G$15)+'3-Year P&L'!$B$16*(1+'3-Year P&L'!$G$16)+'3-Year P&L'!$B$17*(1+'3-Year P&L'!$G$17)+'3-Year P&L'!$B$18*(1+'3-Year P&L'!$G$18))*(C7*(1-MIN(30,'0. Assumptions'!$B$59)/30)+B7*MIN(30,'0. Assumptions'!$B$59)/30)),"") -> -14614.468 | D11: =IFERROR(IF('3-Year P&L'!$B$9="","",-('3-Year P&L'!$B$13*(1+'3-Year P&L'!$G$13)+'3-Year P&L'!$B$14*(1+'3-Year P&L'!$G$14)+'3-Year P&L'!$B$15*(1+'3-Year P&L'!$G$15)+'3-Year P&L'!$B$16*(1+'3-Year P&L'!$G$16)+'3-Year P&L'!$B$17*(1+'3-Year P&L'!$G$17)+'3-Year P&L'!$B$18*(1+'3-Year P&L'!$G$18))*(D7*(1-MIN(30,'0. Assumptions'!$B$59)/30)+C7*MIN(30,'0. Assumptions'!$B$59)/30)),"") -> -17294.649 | E11: =IFERROR(IF('3-Year P&L'!$B$9="","",-('3-Year P&L'!$B$13*(1+'3-Year P&L'!$G$13)+'3-Year P&L'!$B$14*(1+'3-Year P&L'!$G$14)+'3-Year P&L'!$B$15*(1+'3-Year P&L'!$G$15)+'3-Year P&L'!$B$16*(1+'3-Year P&L'!$G$16)+'3-Year P&L'!$B$17*(1+'3-Year P&L'!$G$17)+'3-Year P&L'!$B$18*(1+'3-Year P&L'!$G$18))*(E7*(1-MIN(30,'0. Assumptions'!$B$59)/30)+D7*MIN(30,'0. Assumptions'!$B$59)/30)),"") -> -20031.971 | F11: =IFERROR(IF('3-Year P&L'!$B$9="","",-('3-Year P&L'!$B$13*(1+'3-Year P&L'!$G$13)+'3-Year P&L'!$B$14*(1+'3-Year P&L'!$G$14)+'3-Year P&L'!$B$15*(1+'3-Year P&L'!$G$15)+'3-Year P&L'!$B$16*(1+'3-Year P&L'!$G$16)+'3-Year P&L'!$B$17*(1+'3-Year P&L'!$G$17)+'3-Year P&L'!$B$18*(1+'3-Year P&L'!$G$18))*(F7*(1-MIN(30,'0. Assumptions'!$B$59)/30)+E7*MIN(30,'0. Assumptions'!$B$59)/30)),"") -> -21844.154 | G11: =IFERROR(IF('3-Year P&L'!$B$9="","",-('3-Year P&L'!$B$13*(1+'3-Year P&L'!$G$13)+'3-Year P&L'!$B$14*(1+'3-Year P&L'!$G$14)+'3-Year P&L'!$B$15*(1+'3-Year P&L'!$G$15)+'3-Year P&L'!$B$16*(1+'3-Year P&L'!$G$16)+'3-Year P&L'!$B$17*(1+'3-Year P&L'!$G$17)+'3-Year P&L'!$B$18*(1+'3-Year P&L'!$G$18))*(G7*(1-MIN(30,'0. Assumptions'!$B$59)/30)+F7*MIN(30,'0. Assumptions'!$B$59)/30)),"") -> -22007.414 | H11: =IFERROR(IF('3-Year P&L'!$B$9="","",-('3-Year P&L'!$B$13*(1+'3-Year P&L'!$G$13)+'3-Year P&L'!$B$14*(1+'3-Year P&L'!$G$14)+'3-Year P&L'!$B$15*(1+'3-Year P&L'!$G$15)+'3-Year P&L'!$B$16*(1+'3-Year P&L'!$G$16)+'3-Year P&L'!$B$17*(1+'3-Year P&L'!$G$17)+'3-Year P&L'!$B$18*(1+'3-Year P&L'!$G$18))*(H7*(1-MIN(30,'0. Assumptions'!$B$59)/30)+G7*MIN(30,'0. Assumptions'!$B$59)/30)),"") -> -21550.287 | I11: =IFERROR(IF('3-Year P&L'!$B$9="","",-('3-Year P&L'!$B$13*(1+'3-Year P&L'!$G$13)+'3-Year P&L'!$B$14*(1+'3-Year P&L'!$G$14)+'3-Year P&L'!$B$15*(1+'3-Year P&L'!$G$15)+'3-Year P&L'!$B$16*(1+'3-Year P&L'!$G$16)+'3-Year P&L'!$B$17*(1+'3-Year P&L'!$G$17)+'3-Year P&L'!$B$18*(1+'3-Year P&L'!$G$18))*(I7*(1-MIN(30,'0. Assumptions'!$B$59)/30)+H7*MIN(30,'0. Assumptions'!$B$59)/30)),"") -> -21289.071 | J11: =IFERROR(IF('3-Year P&L'!$B$9="","",-('3-Year P&L'!$B$13*(1+'3-Year P&L'!$G$13)+'3-Year P&L'!$B$14*(1+'3-Year P&L'!$G$14)+'3-Year P&L'!$B$15*(1+'3-Year P&L'!$G$15)+'3-Year P&L'!$B$16*(1+'3-Year P&L'!$G$16)+'3-Year P&L'!$B$17*(1+'3-Year P&L'!$G$17)+'3-Year P&L'!$B$18*(1+'3-Year P&L'!$G$18))*(J7*(1-MIN(30,'0. Assumptions'!$B$59)/30)+I7*MIN(30,'0. Assumptions'!$B$59)/30)),"") -> -20799.292 | ... M11: =IFERROR(IF('3-Year P&L'!$B$9="","",-('3-Year P&L'!$B$13*(1+'3-Year P&L'!$G$13)+'3-Year P&L'!$B$14*(1+'3-Year P&L'!$G$14)+'3-Year P&L'!$B$15*(1+'3-Year P&L'!$G$15)+'3-Year P&L'!$B$16*(1+'3-Year P&L'!$G$16)+'3-Year P&L'!$B$17*(1+'3-Year P&L'!$G$17)+'3-Year P&L'!$B$18*(1+'3-Year P&L'!$G$18))*(M7*(1-MIN(30,'0. Assumptions'!$B$59)/30)+L7*MIN(30,'0. Assumptions'!$B$59)/30)),"") -> -19362.606 | N11: =IFERROR(IF('3-Year P&L'!$B$9="","",SUM(B11:M11)),"") -> -226400.45 | O11: =IFERROR("Food and beverage purchases, consumables, fees and contingencies, each at ITS tax rate (column G of the P&L; 0 in the US, where the sales tax you pay is part of the cost) and with the supplier payment days from ""0. Assumptions""."&IF('0. Assumptions'!$B$59=0,""," With "&TEXT('0. Assumptions'!$B$59,"0")&" payment days, the last purchases of the year are paid next year: the ""Year"" column of this row holds "&TEXT(MAX(0,12-ROUNDUP('0. Assumptions'!$B$59/30,0)),"0")&" months of purchases, not the year's cost."),"") -> Food and beverage purchases, consumables, fees and contingencies, each at ITS tax rate (column G of the P&L; 0 in the US, where the sales tax you pay is part of the cost) and with the supplier payment days from "0. Assumptions". With 14 payment days, the last purchases of the year are paid next year: the "Year" column of this row holds 11 months of purchases, not the year's cost.
A12: Operating fixed costs (incl. sales tax) | B12: =IFERROR(IF('3-Year P&L'!$B$9="","",-('3-Year P&L'!$B$37-'3-Year P&L'!$B$23-'3-Year P&L'!$B$35-'3-Year P&L'!$B$36+'3-Year P&L'!$B$39)/12),"") -> -6683.3333 | C12: =IFERROR(IF('3-Year P&L'!$B$9="","",-('3-Year P&L'!$B$37-'3-Year P&L'!$B$23-'3-Year P&L'!$B$35-'3-Year P&L'!$B$36+'3-Year P&L'!$B$39)/12),"") -> -6683.3333 | D12: =IFERROR(IF('3-Year P&L'!$B$9="","",-('3-Year P&L'!$B$37-'3-Year P&L'!$B$23-'3-Year P&L'!$B$35-'3-Year P&L'!$B$36+'3-Year P&L'!$B$39)/12),"") -> -6683.3333 | E12: =IFERROR(IF('3-Year P&L'!$B$9="","",-('3-Year P&L'!$B$37-'3-Year P&L'!$B$23-'3-Year P&L'!$B$35-'3-Year P&L'!$B$36+'3-Year P&L'!$B$39)/12),"") -> -6683.3333 | F12: =IFERROR(IF('3-Year P&L'!$B$9="","",-('3-Year P&L'!$B$37-'3-Year P&L'!$B$23-'3-Year P&L'!$B$35-'3-Year P&L'!$B$36+'3-Year P&L'!$B$39)/12),"") -> -6683.3333 | G12: =IFERROR(IF('3-Year P&L'!$B$9="","",-('3-Year P&L'!$B$37-'3-Year P&L'!$B$23-'3-Year P&L'!$B$35-'3-Year P&L'!$B$36+'3-Year P&L'!$B$39)/12),"") -> -6683.3333 | H12: =IFERROR(IF('3-Year P&L'!$B$9="","",-('3-Year P&L'!$B$37-'3-Year P&L'!$B$23-'3-Year P&L'!$B$35-'3-Year P&L'!$B$36+'3-Year P&L'!$B$39)/12),"") -> -6683.3333 | I12: =IFERROR(IF('3-Year P&L'!$B$9="","",-('3-Year P&L'!$B$37-'3-Year P&L'!$B$23-'3-Year P&L'!$B$35-'3-Year P&L'!$B$36+'3-Year P&L'!$B$39)/12),"") -> -6683.3333 | ... M12: =IFERROR(IF('3-Year P&L'!$B$9="","",-('3-Year P&L'!$B$37-'3-Year P&L'!$B$23-'3-Year P&L'!$B$35-'3-Year P&L'!$B$36+'3-Year P&L'!$B$39)/12),"") -> -6683.3333 | N12: =IFERROR(IF('3-Year P&L'!$B$9="","",SUM(B12:M12)),"") -> -80200 | O12: The fixed costs that leave cash, each with its own tax rate: insurance carries none
A13: Payroll and employer payroll taxes | B13: =IFERROR(IF('3-Year P&L'!$B$9="","",-'3-Year P&L'!$B$23/MAX(12,'0. Assumptions'!$B$21)*(1+IF(1='0. Assumptions'!$B$60,(MAX(12,'0. Assumptions'!$B$21)-12)/2,0)+IF(1='0. Assumptions'!$B$61,(MAX(12,'0. Assumptions'!$B$21)-12)/2,0))),"") -> -17854.1 | C13: =IFERROR(IF('3-Year P&L'!$B$9="","",-'3-Year P&L'!$B$23/MAX(12,'0. Assumptions'!$B$21)*(1+IF(2='0. Assumptions'!$B$60,(MAX(12,'0. Assumptions'!$B$21)-12)/2,0)+IF(2='0. Assumptions'!$B$61,(MAX(12,'0. Assumptions'!$B$21)-12)/2,0))),"") -> -17854.1 | D13: =IFERROR(IF('3-Year P&L'!$B$9="","",-'3-Year P&L'!$B$23/MAX(12,'0. Assumptions'!$B$21)*(1+IF(3='0. Assumptions'!$B$60,(MAX(12,'0. Assumptions'!$B$21)-12)/2,0)+IF(3='0. Assumptions'!$B$61,(MAX(12,'0. Assumptions'!$B$21)-12)/2,0))),"") -> -17854.1 | E13: =IFERROR(IF('3-Year P&L'!$B$9="","",-'3-Year P&L'!$B$23/MAX(12,'0. Assumptions'!$B$21)*(1+IF(4='0. Assumptions'!$B$60,(MAX(12,'0. Assumptions'!$B$21)-12)/2,0)+IF(4='0. Assumptions'!$B$61,(MAX(12,'0. Assumptions'!$B$21)-12)/2,0))),"") -> -17854.1 | F13: =IFERROR(IF('3-Year P&L'!$B$9="","",-'3-Year P&L'!$B$23/MAX(12,'0. Assumptions'!$B$21)*(1+IF(5='0. Assumptions'!$B$60,(MAX(12,'0. Assumptions'!$B$21)-12)/2,0)+IF(5='0. Assumptions'!$B$61,(MAX(12,'0. Assumptions'!$B$21)-12)/2,0))),"") -> -17854.1 | G13: =IFERROR(IF('3-Year P&L'!$B$9="","",-'3-Year P&L'!$B$23/MAX(12,'0. Assumptions'!$B$21)*(1+IF(6='0. Assumptions'!$B$60,(MAX(12,'0. Assumptions'!$B$21)-12)/2,0)+IF(6='0. Assumptions'!$B$61,(MAX(12,'0. Assumptions'!$B$21)-12)/2,0))),"") -> -17854.1 | H13: =IFERROR(IF('3-Year P&L'!$B$9="","",-'3-Year P&L'!$B$23/MAX(12,'0. Assumptions'!$B$21)*(1+IF(7='0. Assumptions'!$B$60,(MAX(12,'0. Assumptions'!$B$21)-12)/2,0)+IF(7='0. Assumptions'!$B$61,(MAX(12,'0. Assumptions'!$B$21)-12)/2,0))),"") -> -17854.1 | I13: =IFERROR(IF('3-Year P&L'!$B$9="","",-'3-Year P&L'!$B$23/MAX(12,'0. Assumptions'!$B$21)*(1+IF(8='0. Assumptions'!$B$60,(MAX(12,'0. Assumptions'!$B$21)-12)/2,0)+IF(8='0. Assumptions'!$B$61,(MAX(12,'0. Assumptions'!$B$21)-12)/2,0))),"") -> -17854.1 | J13: =IFERROR(IF('3-Year P&L'!$B$9="","",-'3-Year P&L'!$B$23/MAX(12,'0. Assumptions'!$B$21)*(1+IF(9='0. Assumptions'!$B$60,(MAX(12,'0. Assumptions'!$B$21)-12)/2,0)+IF(9='0. Assumptions'!$B$61,(MAX(12,'0. Assumptions'!$B$21)-12)/2,0))),"") -> -17854.1 | K13: =IFERROR(IF('3-Year P&L'!$B$9="","",-'3-Year P&L'!$B$23/MAX(12,'0. Assumptions'!$B$21)*(1+IF(10='0. Assumptions'!$B$60,(MAX(12,'0. Assumptions'!$B$21)-12)/2,0)+IF(10='0. Assumptions'!$B$61,(MAX(12,'0. Assumptions'!$B$21)-12)/2,0))),"") -> -17854.1 | L13: =IFERROR(IF('3-Year P&L'!$B$9="","",-'3-Year P&L'!$B$23/MAX(12,'0. Assumptions'!$B$21)*(1+IF(11='0. Assumptions'!$B$60,(MAX(12,'0. Assumptions'!$B$21)-12)/2,0)+IF(11='0. Assumptions'!$B$61,(MAX(12,'0. Assumptions'!$B$21)-12)/2,0))),"") -> -17854.1 | M13: =IFERROR(IF('3-Year P&L'!$B$9="","",-'3-Year P&L'!$B$23/MAX(12,'0. Assumptions'!$B$21)*(1+IF(12='0. Assumptions'!$B$60,(MAX(12,'0. Assumptions'!$B$21)-12)/2,0)+IF(12='0. Assumptions'!$B$61,(MAX(12,'0. Assumptions'!$B$21)-12)/2,0))),"") -> -17854.1 | N13: =IFERROR(IF('3-Year P&L'!$B$9="","",SUM(B13:M13)),"") -> -214249.2 | O13: Twelve monthly installments plus extra pay periods in the months you set in Assumptions (only if pay periods > 12). The total for the year is the same as the P&L's
A14: Loan interest | B14: =IFERROR(IF('3-Year P&L'!$B$9="","",-Financing!$B$44/12),"") -> -1466.6667 | C14: =IFERROR(IF('3-Year P&L'!$B$9="","",-Financing!$B$44/12),"") -> -1466.6667 | D14: =IFERROR(IF('3-Year P&L'!$B$9="","",-Financing!$B$44/12),"") -> -1466.6667 | E14: =IFERROR(IF('3-Year P&L'!$B$9="","",-Financing!$B$44/12),"") -> -1466.6667 | F14: =IFERROR(IF('3-Year P&L'!$B$9="","",-Financing!$B$44/12),"") -> -1466.6667 | G14: =IFERROR(IF('3-Year P&L'!$B$9="","",-Financing!$B$44/12),"") -> -1466.6667 | H14: =IFERROR(IF('3-Year P&L'!$B$9="","",-Financing!$B$44/12),"") -> -1466.6667 | I14: =IFERROR(IF('3-Year P&L'!$B$9="","",-Financing!$B$44/12),"") -> -1466.6667 | ... M14: =IFERROR(IF('3-Year P&L'!$B$9="","",-Financing!$B$44/12),"") -> -1466.6667 | N14: =IFERROR(IF('3-Year P&L'!$B$9="","",SUM(B14:M14)),"") -> -17600
A15: Loan principal repaid | B15: =IFERROR(IF('3-Year P&L'!$B$9="","",-Financing!$B$45/12),"") -> -920.26579 | C15: =IFERROR(IF('3-Year P&L'!$B$9="","",-Financing!$B$45/12),"") -> -920.26579 | D15: =IFERROR(IF('3-Year P&L'!$B$9="","",-Financing!$B$45/12),"") -> -920.26579 | E15: =IFERROR(IF('3-Year P&L'!$B$9="","",-Financing!$B$45/12),"") -> -920.26579 | F15: =IFERROR(IF('3-Year P&L'!$B$9="","",-Financing!$B$45/12),"") -> -920.26579 | G15: =IFERROR(IF('3-Year P&L'!$B$9="","",-Financing!$B$45/12),"") -> -920.26579 | H15: =IFERROR(IF('3-Year P&L'!$B$9="","",-Financing!$B$45/12),"") -> -920.26579 | I15: =IFERROR(IF('3-Year P&L'!$B$9="","",-Financing!$B$45/12),"") -> -920.26579 | ... M15: =IFERROR(IF('3-Year P&L'!$B$9="","",-Financing!$B$45/12),"") -> -920.26579 | N15: =IFERROR(IF('3-Year P&L'!$B$9="","",SUM(B15:M15)),"") -> -11043.189
A16: Sales tax collected (memo) | B16: =IFERROR(IF('3-Year P&L'!$B$9="","",'3-Year P&L'!$B$9*B7*SUMPRODUCT('3-Year P&L'!$E$10:$E$11,'3-Year P&L'!$G$10:$G$11)),"") -> 2861.3419 | C16: =IFERROR(IF('3-Year P&L'!$B$9="","",'3-Year P&L'!$B$9*C7*SUMPRODUCT('3-Year P&L'!$E$10:$E$11,'3-Year P&L'!$G$10:$G$11)),"") -> 3265.1949 | D16: =IFERROR(IF('3-Year P&L'!$B$9="","",'3-Year P&L'!$B$9*D7*SUMPRODUCT('3-Year P&L'!$E$10:$E$11,'3-Year P&L'!$G$10:$G$11)),"") -> 3969.7896 | E16: =IFERROR(IF('3-Year P&L'!$B$9="","",'3-Year P&L'!$B$9*E7*SUMPRODUCT('3-Year P&L'!$E$10:$E$11,'3-Year P&L'!$G$10:$G$11)),"") -> 4433.791 | F16: =IFERROR(IF('3-Year P&L'!$B$9="","",'3-Year P&L'!$B$9*F7*SUMPRODUCT('3-Year P&L'!$E$10:$E$11,'3-Year P&L'!$G$10:$G$11)),"") -> 4743.1253 | G16: =IFERROR(IF('3-Year P&L'!$B$9="","",'3-Year P&L'!$B$9*G7*SUMPRODUCT('3-Year P&L'!$E$10:$E$11,'3-Year P&L'!$G$10:$G$11)),"") -> 4536.9024 | H16: =IFERROR(IF('3-Year P&L'!$B$9="","",'3-Year P&L'!$B$9*H7*SUMPRODUCT('3-Year P&L'!$E$10:$E$11,'3-Year P&L'!$G$10:$G$11)),"") -> 4536.9024 | I16: =IFERROR(IF('3-Year P&L'!$B$9="","",'3-Year P&L'!$B$9*I7*SUMPRODUCT('3-Year P&L'!$E$10:$E$11,'3-Year P&L'!$G$10:$G$11)),"") -> 4433.791 | ... M16: =IFERROR(IF('3-Year P&L'!$B$9="","",'3-Year P&L'!$B$9*M7*SUMPRODUCT('3-Year P&L'!$E$10:$E$11,'3-Year P&L'!$G$10:$G$11)),"") -> 4124.4568 | N16: =IFERROR(IF('3-Year P&L'!$B$9="","",SUM(B16:M16)),"") -> 49588 | O16: Each sales line at ITS rate, read from the sales tax column of the P&L. The example uses one rate for everything, so alcohol to go carries the same rate as dine-in; the share of beverages taxed at the alcohol rate is set in column H of its line on the P&L
A17: Recoverable input tax (memo) | B17: =IFERROR(IF('3-Year P&L'!$B$9="","",'3-Year P&L'!$B$38*B7+'3-Year P&L'!$B$39/12),"") -> 0 | C17: =IFERROR(IF('3-Year P&L'!$B$9="","",'3-Year P&L'!$B$38*C7+'3-Year P&L'!$B$39/12),"") -> 0 | D17: =IFERROR(IF('3-Year P&L'!$B$9="","",'3-Year P&L'!$B$38*D7+'3-Year P&L'!$B$39/12),"") -> 0 | E17: =IFERROR(IF('3-Year P&L'!$B$9="","",'3-Year P&L'!$B$38*E7+'3-Year P&L'!$B$39/12),"") -> 0 | F17: =IFERROR(IF('3-Year P&L'!$B$9="","",'3-Year P&L'!$B$38*F7+'3-Year P&L'!$B$39/12),"") -> 0 | G17: =IFERROR(IF('3-Year P&L'!$B$9="","",'3-Year P&L'!$B$38*G7+'3-Year P&L'!$B$39/12),"") -> 0 | H17: =IFERROR(IF('3-Year P&L'!$B$9="","",'3-Year P&L'!$B$38*H7+'3-Year P&L'!$B$39/12),"") -> 0 | I17: =IFERROR(IF('3-Year P&L'!$B$9="","",'3-Year P&L'!$B$38*I7+'3-Year P&L'!$B$39/12),"") -> 0 | ... M17: =IFERROR(IF('3-Year P&L'!$B$9="","",'3-Year P&L'!$B$38*M7+'3-Year P&L'!$B$39/12),"") -> 0 | N17: =IFERROR(IF('3-Year P&L'!$B$9="","",SUM(B17:M17)),"") -> 0 | O17: Each item at its own rate, read from the tax column of the P&L: insurance and card processing fees carry none
A18: Carried forward (capex input tax included) | E18: =IFERROR(IF('3-Year P&L'!$B$9="","",'Startup Costs'!$B$32),"") -> 0 | H18: =IFERROR(IF('3-Year P&L'!$B$9="","",MAX(0,-E19)),"") -> 0 | K18: =IFERROR(IF('3-Year P&L'!$B$9="","",MAX(0,-H19)),"") -> 0 | O18: Sales tax paid on STARTUP COSTS enters here: it is offset against the tax collected in later quarters until used up. With 0% recoverable input tax (the US default) this line stays at zero
A19: Quarterly sales tax return | E19: =IFERROR(IF('3-Year P&L'!$B$9="","",SUM(B16:D16)-SUM(B17:D17)-E18),"") -> 10096.326 | H19: =IFERROR(IF('3-Year P&L'!$B$9="","",SUM(E16:G16)-SUM(E17:G17)-H18),"") -> 13713.819 | K19: =IFERROR(IF('3-Year P&L'!$B$9="","",SUM(H16:J16)-SUM(H17:J17)-K18),"") -> 13301.373 | O19: Sales tax collected minus recoverable input tax for the quarter, minus what was carried forward. If negative, nothing is paid: it is offset in the next quarter. With 0% recoverable input tax (the US default) it equals the sales tax collected in the quarter
A20: Sales tax remitted (quarterly filer) | E20: =IFERROR(IF('3-Year P&L'!$B$9="","",IF(E19<=0,"",-E19)),"") -> -10096.326 | H20: =IFERROR(IF('3-Year P&L'!$B$9="","",IF(H19<=0,"",-H19)),"") -> -13713.819 | K20: =IFERROR(IF('3-Year P&L'!$B$9="","",IF(K19<=0,"",-K19)),"") -> -13301.373 | N20: =IFERROR(IF('3-Year P&L'!$B$9="","",SUM(B20:M20)),"") -> -37111.518 | O20: Cash only leaves when the quarter's result is positive. Months without a settlement are left blank, not zero. The cell turns RED when the payment takes more cash than is left that month. The model settles quarterly, in the month after each plan quarter (Months 4, 7 and 10: April, July and October with Month 1 in January; the fourth quarter is remitted in Month 13, January of the next year): if your state requires monthly filing, expect smaller payments every month instead
A21: MONTHLY NET CASH FLOW | B21: =IFERROR(IF('3-Year P&L'!$B$9="","",SUM(B9:B15)+IF(B20="",0,B20)),"") -> 1879.8092 | C21: =IFERROR(IF('3-Year P&L'!$B$9="","",SUM(C9:C15)+IF(C20="",0,C20)),"") -> 2177.8298 | D21: =IFERROR(IF('3-Year P&L'!$B$9="","",SUM(D9:D15)+IF(D20="",0,D20)),"") -> 8739.0099 | E21: =IFERROR(IF('3-Year P&L'!$B$9="","",SUM(E9:E15)+IF(E20="",0,E20)),"") -> 2385.9144 | F21: =IFERROR(IF('3-Year P&L'!$B$9="","",SUM(F9:F15)+IF(F20="",0,F20)),"") -> 14985.271 | G21: =IFERROR(IF('3-Year P&L'!$B$9="","",SUM(G9:G15)+IF(G20="",0,G20)),"") -> 12502.004 | H21: =IFERROR(IF('3-Year P&L'!$B$9="","",SUM(H9:H15)+IF(H20="",0,H20)),"") -> -940.28816 | I21: =IFERROR(IF('3-Year P&L'!$B$9="","",SUM(I9:I15)+IF(I20="",0,I20)),"") -> 11735.542 | ... M21: =IFERROR(IF('3-Year P&L'!$B$9="","",SUM(M9:M15)+IF(M20="",0,M20)),"") -> 9300.3943 | N21: =IFERROR(IF('3-Year P&L'!$B$9="","",SUM(B21:M21)),"") -> 79121.627
A22: CUMULATIVE CASH BALANCE | B22: =IFERROR(IF('3-Year P&L'!$B$9="","",'Startup Costs'!$B$29+B21),"") -> 79892.109 | C22: =IFERROR(IF('3-Year P&L'!$B$9="","",B22+C21),"") -> 82069.939 | D22: =IFERROR(IF('3-Year P&L'!$B$9="","",C22+D21),"") -> 90808.949 | E22: =IFERROR(IF('3-Year P&L'!$B$9="","",D22+E21),"") -> 93194.863 | F22: =IFERROR(IF('3-Year P&L'!$B$9="","",E22+F21),"") -> 108180.13 | G22: =IFERROR(IF('3-Year P&L'!$B$9="","",F22+G21),"") -> 120682.14 | H22: =IFERROR(IF('3-Year P&L'!$B$9="","",G22+H21),"") -> 119741.85 | I22: =IFERROR(IF('3-Year P&L'!$B$9="","",H22+I21),"") -> 131477.39 | J22: =IFERROR(IF('3-Year P&L'!$B$9="","",I22+J21),"") -> 142310.71 | ... M22: =IFERROR(IF('3-Year P&L'!$B$9="","",L22+M21),"") -> 157133.93
A23: Minimum balance of the year | B23: =IFERROR(IF('3-Year P&L'!$B$9="","",IF(COUNT(B22:M22)=0,"",MIN(B22:M22))),"") -> 79892.109 | D23: If negative, raise working capital or the loan: you run out of cash
A24: Month when cash bottoms out | B24: =IFERROR(IF('3-Year P&L'!$B$9="","",IF(COUNT(B22:M22)=0,"",MATCH(MIN(B22:M22),B22:M22,0))),"") -> 1 | D24: It answers the question that decides a bank deal: in which month the cash runs out
A25: RETURN ON INVESTMENT
A26: Free cash flow before debt, year 1 | B26: =IFERROR(IF('3-Year P&L'!$B$9="","",'3-Year P&L'!$B$47+'3-Year P&L'!$B$35+Financing!$B$44),"") -> 76854.779 | D26: Net income plus depreciation (which is not paid) plus that year's interest: principal is not subtracted because this flow is BEFORE debt. The SAME basis as years 2 and 3, so the payback compares like with like
A27: Free cash flow before debt, year 2 | B27: =IFERROR(IF('3-Year P&L'!$B$9="","",'3-Year P&L'!$C$47+'3-Year P&L'!$C$35+Financing!$B$46),"") -> 90122.514 | D27: Net income plus depreciation (which is not paid) plus that year's interest: principal is not subtracted because this flow is BEFORE debt. Without a monthly table, it is an estimate
A28: Free cash flow before debt, year 3 | B28: =IFERROR(IF('3-Year P&L'!$B$9="","",'3-Year P&L'!$D$47+'3-Year P&L'!$D$35+Financing!$B$48),"") -> 98289.789 | D28: Net income plus depreciation (which is not paid) plus that year's interest: principal is not subtracted because this flow is BEFORE debt. Without a monthly table, it is an estimate
A29: For reference: ACTUAL year-1 cash flow (monthly table, before debt) | B29: =IFERROR(IF('3-Year P&L'!$B$9="","",N21+Financing!$B$44+Financing!$B$45),"") -> 107764.82 | D29: The sum of the twelve monthly net cash flows above, adding back the interest and principal paid that year. It is NOT the one the payback uses: it includes sales tax not yet settled and supplier credit, two things that have to be paid back and that years 2 and 3 do not have
A30: Investment to recover (net of recoverable input tax) | B30: =IFERROR(IF('3-Year P&L'!$B$9="","",'Startup Costs'!$B$33-'Startup Costs'!$B$32),"") -> 275612.3 | D30: CAPEX plus working capital: the total cash needed MINUS the recoverable input tax on startup costs, which is not lost (it is recovered through the quarterly return, and this tab offsets it quarter by quarter; it is zero in the US default). Working capital is recovered when you close, but until then it is tied up
A31: Project payback (years), before debt | B31: =IFERROR(IF('3-Year P&L'!$B$9="","",IF(B26>=B30,ROUND(B30/B26,1),IF(B26+B27>=B30,ROUND(1+(B30-B26)/B27,1),IF(B26+B27+B28>=B30,ROUND(2+(B30-B26-B27)/B28,1),"Over 3 years")))),"") -> Over 3 years | D31: Measures how long the business takes to pay back the investment with what it generates BEFORE paying the lender, on the SAME cash flow basis in all three years; whether you can make the loan payment is answered by the DSCR on the "Financing" tab. The Word business plan quotes this figure; if you change a green cell, this workbook rules
A32: Payback on CAPEX, excluding working capital (years) | B32: =IFERROR(IF('3-Year P&L'!$B$9="","",IF(B26>='Startup Costs'!$B$31,ROUND('Startup Costs'!$B$31/B26,1),IF(B26+B27>='Startup Costs'!$B$31,ROUND(1+('Startup Costs'!$B$31-B26)/B27,1),IF(B26+B27+B28>='Startup Costs'!$B$31,ROUND(2+('Startup Costs'!$B$31-B26-B27)/B28,1),"Over 3 years")))),"") -> 2.3 | D32: The same calculation on what you BUY (build-out, equipment, launch and formation costs), without working capital: that money is not spent, it is tied up and comes back when the business closes. For reference only: the payback that matters is the one above
A34: Fourth-quarter sales tax is settled in Month 13 (January of the following year when Month 1 is January), so it does not appear in this table. The model pays year-1 income tax in July of year 2 (a simplification: estimated tax payments are usually quarterly). The loan payment is spread in twelve equal parts following the ANNUAL schedule in the Financing tab, and payroll in twelve monthly installments (plus extra pay periods in their month, only if pay periods > 12).

Sheet Financing
A1: FINANCING PLAN
A2: What you need, where it comes from and what it costs to repay. It is the sheet your lender asks for along with the P&L.
A4: Item | B4: Amount | C4: Notes
A5: SOURCES OF FUNDS
A6: Owner's equity (your own money) | B6: =IFERROR(IF('0. Assumptions'!$B$30="","",'0. Assumptions'!$B$30),"") -> 100000
A7: Loan requested — bank or SBA 7(a) (amortized below) | B7: =IFERROR(IF('0. Assumptions'!$B$31="","",'0. Assumptions'!$B$31),"") -> 176000
A8: Other loan (not in the schedule or the DSCR — enter your loan in row 7) | B8: 0 | C8: A source of funds only: NOT amortized, so it is not in the schedule, the P&L interest or the DSCR. Enter your bank or SBA 7(a) loan in row 7 ("Loan requested" in "0. Assumptions"); use this row only for a second loan
A9: SBA Microloan (not in the schedule or the DSCR — enter your loan in row 7) | B9: 0 | C9: SBA Microloans go up to $50,000 through nonprofit intermediaries. Like row 8, a source of funds only: not in the schedule or the DSCR. If it is your only loan, enter it in row 7 instead
A10: Investors / partners (equity: dilutes, not repaid) | B10: 0 | C10: Equity: it dilutes your ownership and is not repaid
A11: Local grants (usually paid after you spend) | B11: 0 | C11: Usually paid AFTER you document the spending
A12: TOTAL SOURCES OF FUNDS | B12: =IFERROR(IF(COUNT(B6:B11)=0,"",SUM(B6:B11)),"") -> 276000
A13: USES OF FUNDS
A14: Total cash needed at launch | B14: =IFERROR(IF('Startup Costs'!$B$33="","",'Startup Costs'!$B$33),"") -> 275612.3 | C14: Startup costs plus any recoverable tax you have to advance (zero by default in the US)
A15: Difference (sources - uses) | B15: =IFERROR(B12-B14,"") -> 387.7 | C15: In red (negative), the plan is NOT funded. Far above zero is not free either: you pay interest on money you do not use
A16: Difference as a % of uses | B16: =IFERROR(B15/B14,"") -> 0.0014066861 | C16: Amber above the margin you set: it is debt you pay for without needing it
A17: Acceptable over-funding (%) | B17: 0.05 | C17: A small cushion over the need is healthy; 20% extra is interest thrown away
A18: Loan that would match sources to needs | B18: =IFERROR(MAX(0,B14-B12+B7),"") -> 175612.3 | C18: Copy it into "Loan requested" in the "0. Assumptions" tab and the difference goes to zero. Rows 8-11 lower this figure, but only the row-7 loan is amortized and counted in the DSCR
A19: LOAN TERMS
A20: Principal amount | B20: =IFERROR(IF('0. Assumptions'!$B$31=0,"",'0. Assumptions'!$B$31),"") -> 176000
A21: Nominal annual interest rate (not APR) | B21: =IFERROR(IF('0. Assumptions'!$B$32="","",'0. Assumptions'!$B$32),"") -> 0.1
A22: Total term (years) | B22: =IFERROR(IF('0. Assumptions'!$B$33="","",'0. Assumptions'!$B$33),"") -> 10
A23: Interest-only period applied (years) | B23: =IFERROR(IF(OR('0. Assumptions'!$B$34="",'0. Assumptions'!$B$33=""),"",IF('0. Assumptions'!$B$34>='0. Assumptions'!$B$33,0,'0. Assumptions'!$B$34)),"") -> 0 | C23: An interest-only period equal to or longer than the term does not exist: the sheet cancels it at the source
A24: Annual payment during repayment | B24: =IFERROR(IF(B22-B23<=0,"",IF(B21=0,B20/(B22-B23),B20*B21/(1-(1+B21)^-(B22-B23)))),"") -> 28643.189 | C24: Standard amortizing loan with a level annual payment. At a 0% rate it is the principal divided by the repayment years: without that branch the schedule would shut down entirely
A25: AMORTIZATION SCHEDULE
A26: Year | B26: Opening balance | C26: Interest | D26: Principal repaid | E26: Total payment | F26: Closing balance | G26: Cash flow available for debt service (after tax; from year 4 on, year 3 held flat) | H26: DSCR for the year
A27: 1 | B27: =IFERROR(IF(B20="","",B20),"") -> 176000 | C27: =IFERROR(IF(OR(1>B22,B27=""),"",B27*B21),"") -> 17600 | D27: =IFERROR(IF(OR(1>B22,B27=""),"",IF(1<=B23,0,MIN(B27,B24-C27))),"") -> 11043.189 | E27: =IFERROR(IF(C27="","",C27+D27),"") -> 28643.189 | F27: =IFERROR(IF(D27="","",B27-D27),"") -> 164956.81 | G27: =IFERROR(IF(E27="","",'3-Year P&L'!$B$40-'3-Year P&L'!$B$45+'3-Year P&L'!$B$35+'3-Year P&L'!$B$36),"") -> 76854.779 | H27: =IFERROR(IF(OR(E27="",E27=0),"",G27/E27),"") -> 2.6831781
A28: 2 | B28: =IFERROR(IF(OR(2>B22,F27=""),"",F27),"") -> 164956.81 | C28: =IFERROR(IF(OR(2>B22,B28=""),"",B28*B21),"") -> 16495.681 | D28: =IFERROR(IF(OR(2>B22,B28=""),"",IF(2<=B23,0,MIN(B28,B24-C28))),"") -> 12147.508 | E28: =IFERROR(IF(C28="","",C28+D28),"") -> 28643.189 | F28: =IFERROR(IF(D28="","",B28-D28),"") -> 152809.3 | G28: =IFERROR(IF(E28="","",'3-Year P&L'!$C$40-'3-Year P&L'!$C$45+'3-Year P&L'!$C$35+'3-Year P&L'!$C$36),"") -> 90122.514 | H28: =IFERROR(IF(OR(E28="",E28=0),"",G28/E28),"") -> 3.1463854
A29: 3 | B29: =IFERROR(IF(OR(3>B22,F28=""),"",F28),"") -> 152809.3 | C29: =IFERROR(IF(OR(3>B22,B29=""),"",B29*B21),"") -> 15280.93 | D29: =IFERROR(IF(OR(3>B22,B29=""),"",IF(3<=B23,0,MIN(B29,B24-C29))),"") -> 13362.259 | E29: =IFERROR(IF(C29="","",C29+D29),"") -> 28643.189 | F29: =IFERROR(IF(D29="","",B29-D29),"") -> 139447.04 | G29: =IFERROR(IF(E29="","",'3-Year P&L'!$D$40-'3-Year P&L'!$D$45+'3-Year P&L'!$D$35+'3-Year P&L'!$D$36),"") -> 98289.789 | H29: =IFERROR(IF(OR(E29="",E29=0),"",G29/E29),"") -> 3.4315239
A30: 4 | B30: =IFERROR(IF(OR(4>B22,F29=""),"",F29),"") -> 139447.04 | C30: =IFERROR(IF(OR(4>B22,B30=""),"",B30*B21),"") -> 13944.704 | D30: =IFERROR(IF(OR(4>B22,B30=""),"",IF(4<=B23,0,MIN(B30,B24-C30))),"") -> 14698.485 | E30: =IFERROR(IF(C30="","",C30+D30),"") -> 28643.189 | F30: =IFERROR(IF(D30="","",B30-D30),"") -> 124748.56 | G30: =IFERROR(IF(E30="","",'3-Year P&L'!$D$40-'3-Year P&L'!$D$45+'3-Year P&L'!$D$35+'3-Year P&L'!$D$36),"") -> 98289.789 | H30: =IFERROR(IF(OR(E30="",E30=0),"",G30/E30),"") -> 3.4315239
A31: 5 | B31: =IFERROR(IF(OR(5>B22,F30=""),"",F30),"") -> 124748.56 | C31: =IFERROR(IF(OR(5>B22,B31=""),"",B31*B21),"") -> 12474.856 | D31: =IFERROR(IF(OR(5>B22,B31=""),"",IF(5<=B23,0,MIN(B31,B24-C31))),"") -> 16168.334 | E31: =IFERROR(IF(C31="","",C31+D31),"") -> 28643.189 | F31: =IFERROR(IF(D31="","",B31-D31),"") -> 108580.22 | G31: =IFERROR(IF(E31="","",'3-Year P&L'!$D$40-'3-Year P&L'!$D$45+'3-Year P&L'!$D$35+'3-Year P&L'!$D$36),"") -> 98289.789 | H31: =IFERROR(IF(OR(E31="",E31=0),"",G31/E31),"") -> 3.4315239
A32: 6 | B32: =IFERROR(IF(OR(6>B22,F31=""),"",F31),"") -> 108580.22 | C32: =IFERROR(IF(OR(6>B22,B32=""),"",B32*B21),"") -> 10858.022 | D32: =IFERROR(IF(OR(6>B22,B32=""),"",IF(6<=B23,0,MIN(B32,B24-C32))),"") -> 17785.167 | E32: =IFERROR(IF(C32="","",C32+D32),"") -> 28643.189 | F32: =IFERROR(IF(D32="","",B32-D32),"") -> 90795.057 | G32: =IFERROR(IF(E32="","",'3-Year P&L'!$D$40-'3-Year P&L'!$D$45+'3-Year P&L'!$D$35+'3-Year P&L'!$D$36),"") -> 98289.789 | H32: =IFERROR(IF(OR(E32="",E32=0),"",G32/E32),"") -> 3.4315239
A33: 7 | B33: =IFERROR(IF(OR(7>B22,F32=""),"",F32),"") -> 90795.057 | C33: =IFERROR(IF(OR(7>B22,B33=""),"",B33*B21),"") -> 9079.5057 | D33: =IFERROR(IF(OR(7>B22,B33=""),"",IF(7<=B23,0,MIN(B33,B24-C33))),"") -> 19563.684 | E33: =IFERROR(IF(C33="","",C33+D33),"") -> 28643.189 | F33: =IFERROR(IF(D33="","",B33-D33),"") -> 71231.373 | G33: =IFERROR(IF(E33="","",'3-Year P&L'!$D$40-'3-Year P&L'!$D$45+'3-Year P&L'!$D$35+'3-Year P&L'!$D$36),"") -> 98289.789 | H33: =IFERROR(IF(OR(E33="",E33=0),"",G33/E33),"") -> 3.4315239
A34: 8 | B34: =IFERROR(IF(OR(8>B22,F33=""),"",F33),"") -> 71231.373 | C34: =IFERROR(IF(OR(8>B22,B34=""),"",B34*B21),"") -> 7123.1373 | D34: =IFERROR(IF(OR(8>B22,B34=""),"",IF(8<=B23,0,MIN(B34,B24-C34))),"") -> 21520.052 | E34: =IFERROR(IF(C34="","",C34+D34),"") -> 28643.189 | F34: =IFERROR(IF(D34="","",B34-D34),"") -> 49711.321 | G34: =IFERROR(IF(E34="","",'3-Year P&L'!$D$40-'3-Year P&L'!$D$45+'3-Year P&L'!$D$35+'3-Year P&L'!$D$36),"") -> 98289.789 | H34: =IFERROR(IF(OR(E34="",E34=0),"",G34/E34),"") -> 3.4315239
A35: 9 | B35: =IFERROR(IF(OR(9>B22,F34=""),"",F34),"") -> 49711.321 | C35: =IFERROR(IF(OR(9>B22,B35=""),"",B35*B21),"") -> 4971.1321 | D35: =IFERROR(IF(OR(9>B22,B35=""),"",IF(9<=B23,0,MIN(B35,B24-C35))),"") -> 23672.057 | E35: =IFERROR(IF(C35="","",C35+D35),"") -> 28643.189 | F35: =IFERROR(IF(D35="","",B35-D35),"") -> 26039.263 | G35: =IFERROR(IF(E35="","",'3-Year P&L'!$D$40-'3-Year P&L'!$D$45+'3-Year P&L'!$D$35+'3-Year P&L'!$D$36),"") -> 98289.789 | H35: =IFERROR(IF(OR(E35="",E35=0),"",G35/E35),"") -> 3.4315239
A36: 10 | B36: =IFERROR(IF(OR(10>B22,F35=""),"",F35),"") -> 26039.263 | C36: =IFERROR(IF(OR(10>B22,B36=""),"",B36*B21),"") -> 2603.9263 | D36: =IFERROR(IF(OR(10>B22,B36=""),"",IF(10<=B23,0,MIN(B36,B24-C36))),"") -> 26039.263 | E36: =IFERROR(IF(C36="","",C36+D36),"") -> 28643.189 | F36: =IFERROR(IF(D36="","",B36-D36),"") -> 2.5102054e-10 | G36: =IFERROR(IF(E36="","",'3-Year P&L'!$D$40-'3-Year P&L'!$D$45+'3-Year P&L'!$D$35+'3-Year P&L'!$D$36),"") -> 98289.789 | H36: =IFERROR(IF(OR(E36="",E36=0),"",G36/E36),"") -> 3.4315239
A37: 11 | B37: =IFERROR(IF(OR(11>B22,F36=""),"",F36),"") | C37: =IFERROR(IF(OR(11>B22,B37=""),"",B37*B21),"") | D37: =IFERROR(IF(OR(11>B22,B37=""),"",IF(11<=B23,0,MIN(B37,B24-C37))),"") | E37: =IFERROR(IF(C37="","",C37+D37),"") | F37: =IFERROR(IF(D37="","",B37-D37),"") | G37: =IFERROR(IF(E37="","",'3-Year P&L'!$D$40-'3-Year P&L'!$D$45+'3-Year P&L'!$D$35+'3-Year P&L'!$D$36),"") | H37: =IFERROR(IF(OR(E37="",E37=0),"",G37/E37),"")
A38: 12 | B38: =IFERROR(IF(OR(12>B22,F37=""),"",F37),"") | C38: =IFERROR(IF(OR(12>B22,B38=""),"",B38*B21),"") | D38: =IFERROR(IF(OR(12>B22,B38=""),"",IF(12<=B23,0,MIN(B38,B24-C38))),"") | E38: =IFERROR(IF(C38="","",C38+D38),"") | F38: =IFERROR(IF(D38="","",B38-D38),"") | G38: =IFERROR(IF(E38="","",'3-Year P&L'!$D$40-'3-Year P&L'!$D$45+'3-Year P&L'!$D$35+'3-Year P&L'!$D$36),"") | H38: =IFERROR(IF(OR(E38="",E38=0),"",G38/E38),"")
A39: 13 | B39: =IFERROR(IF(OR(13>B22,F38=""),"",F38),"") | C39: =IFERROR(IF(OR(13>B22,B39=""),"",B39*B21),"") | D39: =IFERROR(IF(OR(13>B22,B39=""),"",IF(13<=B23,0,MIN(B39,B24-C39))),"") | E39: =IFERROR(IF(C39="","",C39+D39),"") | F39: =IFERROR(IF(D39="","",B39-D39),"") | G39: =IFERROR(IF(E39="","",'3-Year P&L'!$D$40-'3-Year P&L'!$D$45+'3-Year P&L'!$D$35+'3-Year P&L'!$D$36),"") | H39: =IFERROR(IF(OR(E39="",E39=0),"",G39/E39),"")
A40: 14 | B40: =IFERROR(IF(OR(14>B22,F39=""),"",F39),"") | C40: =IFERROR(IF(OR(14>B22,B40=""),"",B40*B21),"") | D40: =IFERROR(IF(OR(14>B22,B40=""),"",IF(14<=B23,0,MIN(B40,B24-C40))),"") | E40: =IFERROR(IF(C40="","",C40+D40),"") | F40: =IFERROR(IF(D40="","",B40-D40),"") | G40: =IFERROR(IF(E40="","",'3-Year P&L'!$D$40-'3-Year P&L'!$D$45+'3-Year P&L'!$D$35+'3-Year P&L'!$D$36),"") | H40: =IFERROR(IF(OR(E40="",E40=0),"",G40/E40),"")
A41: 15 | B41: =IFERROR(IF(OR(15>B22,F40=""),"",F40),"") | C41: =IFERROR(IF(OR(15>B22,B41=""),"",B41*B21),"") | D41: =IFERROR(IF(OR(15>B22,B41=""),"",IF(15<=B23,0,MIN(B41,B24-C41))),"") | E41: =IFERROR(IF(C41="","",C41+D41),"") | F41: =IFERROR(IF(D41="","",B41-D41),"") | G41: =IFERROR(IF(E41="","",'3-Year P&L'!$D$40-'3-Year P&L'!$D$45+'3-Year P&L'!$D$35+'3-Year P&L'!$D$36),"") | H41: =IFERROR(IF(OR(E41="",E41=0),"",G41/E41),"")
A42: Schedule closing tolerance | B42: 0.01 | C42: Rounding margin. Above it, the schedule does not close and there is principal left unpaid
A43: Balance outstanding at maturity | B43: =IFERROR(IF(B20="","",ROUND(B20-SUM(D27:D41),2)),"") -> 0 | C43: Must be zero: the principal repaid in the schedule has to equal the amount borrowed. If it is positive, the term falls short
A44: Year-1 interest | B44: =IFERROR(IF(B20="","",IF(C27="",0,C27)),"") -> 17600
A45: Year-1 principal repaid | B45: =IFERROR(IF(B20="","",IF(D27="",0,D27)),"") -> 11043.189
A46: Year-2 interest | B46: =IFERROR(IF(B20="","",IF(C28="",0,C28)),"") -> 16495.681
A47: Year-2 principal repaid | B47: =IFERROR(IF(B20="","",IF(D28="",0,D28)),"") -> 12147.508
A48: Year-3 interest | B48: =IFERROR(IF(B20="","",IF(C29="",0,C29)),"") -> 15280.93
A49: Year-3 principal repaid | B49: =IFERROR(IF(B20="","",IF(D29="",0,D29)),"") -> 13362.259
A50: DEBT SERVICE COVERAGE RATIO (DSCR)
A51: Year-1 DSCR | B51: =IFERROR(('3-Year P&L'!$B$40-'3-Year P&L'!$B$45+'3-Year P&L'!$B$35+B44)/(B44+B45),"") -> 2.6831781 | C51: An INTEREST-ONLY year, if there is one: with only interest in the denominator the ratio shoots up and does not measure the business
A52: Year-2 DSCR | B52: =IFERROR(('3-Year P&L'!$C$40-'3-Year P&L'!$C$45+'3-Year P&L'!$C$35+B46)/(B46+B47),"") -> 3.1463854
A53: Year-3 DSCR | B53: =IFERROR(('3-Year P&L'!$D$40-'3-Year P&L'!$D$45+'3-Year P&L'!$D$35+B48)/(B48+B49),"") -> 3.4315239
A54: Minimum DSCR across the whole schedule | B54: =IFERROR(IF(COUNT(H27:H41)=0,"",MIN(H27:H41)),"") -> 2.6831781 | C54: The worst year of the life of the loan, not the best of the three the P&L projects. It is the number that decides a loan. Mind the scope: years 1 to 3 come from the P&L, and from year 4 on the schedule HOLDS year 3's cash flow, so the minimum over those years is a sustained projection, not a calculated year. The cash flow is after tax
A56: DSCR is calculated BEFORE debt and AFTER tax: income tax is subtracted from pre-tax income, depreciation and interest are added back, and the result is divided by what has to be paid that year. Below the minimum in the "0. Assumptions" tab, the business does not generate enough to repay the loan. In the schedule, the available cash flow from year 4 on is held at year 3's: the P&L projects only three years, and no growth is invented here that has not been calculated.
