Workbook

Sheet Instrucciones
A1: Capacidad del obrador y ficha de visita al local
A2: AI Chef Pro · aichef.pro — Cómo Montar una Pastelería
A3: Para qué sirve: decidir si ESE local sirve y cuántas piezas al día aguanta el equipo que estás comprando.
A5: Instrucciones de uso
A6: 1. Hoja «Parámetros»: lo primero. Horas de turno, turnos al día, piezas que quieres sacar, superficie, potencia y tipo de energía de los hornos. Todo lo demás del libro se recalcula desde aquí; no hay ni un número escondido dentro de una fórmula.
A7: 2. Hoja «Zonas y m2»: reparte los metros entre las siete zonas obligatorias y numera el recorrido de la marcha adelante, del 1 al 7. La hoja te dice si el reparto cuadra con la superficie declarada, qué parte del local es obrador y si el recorrido tiene un cruce.
A8: 3. Hoja «Capacidad por Equipo»: una fila por máquina. Di si la tienes, cuánto cabe en un ciclo, cuántas piezas salen de esa cantidad, cuántos minutos dura el ciclo y qué parte de tu surtido pasa por ahí. La hoja devuelve las piezas al día que ESA máquina permite al obrador entero.
A9: 4. Hoja «Cuello de Botella»: el resultado. Cuál es la máquina que manda, cuántas piezas al día aguanta el conjunto, cuánta holgura te queda sobre el día normal y qué pasa en cada uno de los seis picos del año. Aquí es donde se ve si Reyes te cabe en el obrador que estás comprando.
A10: 5. Hoja «Ficha de Visita a Local»: imprímela y llévala a cada visita. Dieciocho comprobaciones, ocho de ellas eliminatorias. Un solo «No» en un ítem eliminatorio y el veredicto es DESCARTAR: no es pesimismo, es que ese defecto no se arregla con dinero razonable.
A12: Celdas verdes = campos editables
A14: Lo que conviene saber antes de empezar
A15: ESTE LIBRO DECIDE UNA COMPRA, NO UNA SEMANA DE TRABAJO. La producción del día a día -qué se hace el martes y cuánto- vive en kit-tareas-pasteleria/10-plan-produccion-semanal.xlsx. Aquí sólo se contesta cuántas piezas al día permite el equipo que estás a punto de pagar, que es la pregunta que ya no se puede contestar después.
... A21: Dónde acaba este libro y dónde sigue el Kit de Tareas Pastelería
A22: Lo que necesitas | B22: Dónde está | C22: Por qué no está aquí
A23: Qué se produce cada día de la semana y en qué orden | B23: kit-tareas-pasteleria/10-plan-produccion-semanal.xlsx | C23: Es la operación del obrador que YA tienes. Este libro decide la compra: cuántas piezas al día permite la máquina.
A24: Las fechas de cada campaña y qué se hace en cada una | B24: kit-tareas-pasteleria/BONUS-02-calendario-anual-tareas.xlsx | C24: El kit pone las fechas y el qué. Aquí el pico entra sólo como multiplicador de piezas al día; los euros de cada campaña son el libro 3 de esta guía.
A25: Cuánta gente hace falta y cuánto cuesta con la Seguridad Social | B25: Libro 8 de esta guía: plantilla-turnos-y-coste-personal.xlsx | C25: Aquí las horas de turno son un parámetro de capacidad, no un dimensionado de plantilla.
A26: Cuánto cuesta cada máquina y cuánto tarda en llegar | B26: Libros 2 y 7 de esta guía | C26: El precio y el plazo no cambian la capacidad. Se separan a propósito para poder decidir primero qué necesitas y después qué te cuesta.
A27: Es COPIA declarada, no vínculo: en toda la guía no hay ni una fórmula que apunte a otro fichero. Un enlace entre libros se rompe en cuanto alguien mueve una carpeta, y entonces el libro miente sin avisar. Donde una celda verde traería un dato del Kit, viene con un valor por defecto propio, declarado como supuesto, y su nota te dice qué fichero del Kit lo sustituye.
A29: Cada cuánto se usa este libro
A30: Cadencia: la hoja «Ficha de Visita a Local», UNA VEZ POR LOCAL que visites, y se guarda aunque descartes -la comparación entre tres locales es la que enseña qué estás aceptando-. Las hojas de capacidad, cada vez que cambies un equipo del presupuesto y, después de abrir, UNA VEZ AL AÑO antes de la campaña de Reyes.
A32: Para editar la estructura o una celda que no esté en verde: Revisar > Desproteger hoja (no tiene contraseña).
A34: Diseñado por John Guerrero — chef y consultor gastronómico desde 2010, en cocina desde los 17 años.
A35: Versión 1.0 · septiembre 2026 · aichef.pro/guia-pasteleria-obrador · info@aichef.pro

Sheet Parámetros
A1: Parámetros
A2: AI Chef Pro · aichef.pro — Cómo Montar una Pastelería
A3: Todo lo que el libro calcula sale de aquí. Ni un número vive dentro de una fórmula.
A5: Parámetro | B5: Valor | C5: Unidad | D5: Procedencia | E5: Qué es y de dónde sale
A6: Horas de turno del obrador | B6: 8 | C6: h por turno | D6: supuesto | E6: Duración del turno de obrador. Es el número que multiplica todo lo demás: con dos turnos, la capacidad se duplica sin comprar una sola máquina.
A7: Turnos de obrador al día | B7: 1 | C7: turnos | D7: supuesto | E7: La Clara trabaja a un turno de madrugada. El segundo turno es la palanca más barata que existe para subir capacidad, y la más cara en personal.
A8: Horas productivas sobre la jornada | B8: 0.85 | C8: % | D8: supuesto | E8: Parte de la jornada que la máquina está de verdad trabajando. El resto es recepción, limpieza, cambio de bandejas y esperas.
A9: Minutos disponibles al día | B9: =IFERROR(B6*B7*B8*60,"") -> 408 | C9: minutos | D9: Se calcula | E9: Horas de turno × turnos × horas productivas × 60. De aquí salen los ciclos al día de cada equipo.
A10: Días de apertura a la semana | B10: 6 | C10: días | D10: supuesto | E10: 6 días por semana × 52 semanas = 312, menos 12 días de cierre por vacaciones en agosto = 300. Los festivos NO se descuentan: la pastelería tiene libertad horaria por ley estatal cuando es la actividad principal (PA-39).
A11: Días de apertura al año | B11: 300 | C11: días | D11: supuesto | E11: 312 días de apertura menos 12 de cierre por vacaciones.
A12: Piezas al día en velocidad de crucero | B12: 476 | C12: piezas al día | D12: supuesto | E12: Lo que tienes que sacar todos los días una vez rodado el negocio. Sale de los clientes al día por las piezas por ticket, los dos supuestos: no existe dato público de tráfico de pastelería. Si ya tienes el Kit de Tareas Pastelería, sustitúyelo por tu dato real de kit-tareas-pasteleria/10-plan-produccion-semanal.xlsx.
A13: Margen de seguridad exigido sobre la capacidad | B13: 0.1 | C13: % | D13: supuesto | E13: Holgura mínima que quieres tener sobre el día normal. Por debajo de ella, el libro avisa: una avería, una baja o un pedido grande te dejan sin género aunque en teoría llegues.
A14: Superficie total del local | B14: 90 | C14: m2 | D14: D22 + PS-85a + PS-85b + PS-85c | E14: Los 90 m2 del caso de referencia. Es la superficie sobre la que casan los escenarios de obra de 600, 900 y 1.200 EUR/m2 del libro 2.
A15: Parte mínima del local dedicada a obrador | B15: 0.45 | C15: % | D15: supuesto | E15: Criterio de la casa, no norma: por debajo de esto la tienda se come al obrador y acabas comprando semielaborados. Si vendes sobre todo por encargo, bájalo; si el despacho es tu escaparate, súbelo.
A16: Potencia eléctrica de los hornos | B16: 34 | C16: kW | D16: PS-86a | E16: PS-86a da 20-80 kW SOLO para los hornos. 34 kW es el punto de trabajo de los dos hornos de convección de La Clara.
A17: Potencia instalada total prevista | B17: 62 | C17: kW | D17: supuesto | E17: PS-86a da 20-80 kW SOLO para los hornos. Los 62 kW de potencia instalada suman además frío, amasado, climatización e iluminación, y son un supuesto: la potencia a contratar la fija el proyecto eléctrico, no una tabla.
A18: Energía de los hornos | B18: Eléctrica | C18: Eléctrica o Gas | D18: supuesto | E18: Cambia el caudal de campana que necesitas y, si eliges gas, activa la inspección periódica obligatoria de la instalación receptora.
A19: Caudal de extracción por kW, equipos eléctricos | B19: 40 | C19: m3/h por kW | D19: PS-86b | E19: Regla de dimensionado de campana para equipos eléctricos.
A20: Caudal de extracción por kW, equipos de gas | B20: 50 | C20: m3/h por kW | D20: PS-86b | E20: Regla de dimensionado de campana para equipos de gas.
A21: Caudal de campana necesario | B21: =IFERROR(B16*IF(B18="Gas",B20,B19),"") -> 1360 | C21: m3/h | D21: Se calcula | E21: Potencia de los hornos × el caudal por kW que corresponda a tu energía. Es el número que hay que llevar a la visita: si el local no puede darlo, no hay pastelería.
A22: Altura libre mínima que exiges al local | B22: 3 | C22: m | D22: supuesto | E22: Con campana, conducto y falso techo, por debajo de 3 m el obrador se queda sin aire y sin sitio para el conducto.
A23: Número de zonas del local | B23: 7 | C23: zonas | D23: PS-86d | E23: Las zonas obligatorias de un obrador de pastelería. Si tu local no permite las siete, no es que quede apretado: es que falta una.
A25: Listas de validación (no las borres: las usan los desplegables)
A26: Energía de los hornos
A27: Eléctrica
A28: Gas
A30: Los valores marcados «supuesto» son de la pastelería de ejemplo «La Clara» (90 m2, obrador de 45 m2, un turno de madrugada). No son datos de sector: son un punto de partida coherente para que puedas ver el libro funcionando antes de meter los tuyos.

Sheet Zonas y m2
A1: Zonas y Metros Cuadrados
A2: AI Chef Pro · aichef.pro — Cómo Montar una Pastelería
A3: Las siete zonas obligatorias de un obrador de pastelería (PS-86d) y el recorrido de marcha adelante.
A5: Nº | B5: Zona | C5: Bloque | D5: m2 | E5: % del local | F5: Paso del recorrido | G5: Qué tiene que cumplir
A6: 1 | B6: Obrador | C6: Obrador | D6: 45 | E6: =IFERROR(D6/$D$14,"") -> 0.5 | F6: 3 | G6: Zona de elaboración, inaccesible al público (art. 2.2.h del RD 1021/2022, PA-03b). Principio de marcha adelante: la materia prima entra por un extremo y el producto terminado sale por el otro sin cruzarse con ella.
A7: 2 | B7: Zona de venta (despacho) | C7: Despacho | D7: 22 | E7: =IFERROR(D7/$D$14,"") -> 0.24444444 | F7: 5 | G7: Mostrador, vitrina refrigerada, vitrina de ambiente y espacio de cola.
A8: 3 | B8: Almacén de materia prima | C8: Cámara y almacén | D8: 5 | E8: =IFERROR(D8/$D$14,"") -> 0.055555556 | F8: 1 | G8: Harinas, azúcares y secos sobre estantería, nunca en el suelo.
A9: 4 | B9: Cámara frigorífica | C9: Cámara y almacén | D9: 4 | E9: =IFERROR(D9/$D$14,"") -> 0.044444444 | F9: 2 | G9: Conservación a 4 °C o menos de lo relleno (art. 4.1 fila 9, PA-12).
A10: 5 | B10: Almacén de producto terminado | C10: Cámara y almacén | D10: 3 | E10: =IFERROR(D10/$D$14,"") -> 0.033333333 | F10: 4 | G10: Producto estable a temperatura ambiente y packaging montado.
A11: 6 | B11: Vestuarios y aseos de personal | C11: Aseos y vestuario | D11: 8 | E11: =IFERROR(D11/$D$14,"") -> 0.088888889 | F11: 7 | G11: Aseo de personal separado del de clientes, con taquillas.
A12: 7 | B12: Almacén de residuos | C12: Aseos y vestuario | D12: 3 | E12: =IFERROR(D12/$D$14,"") -> 0.033333333 | F12: 6 | G12: Cerrado, con contenedores identificados; no puede abrir al obrador.
B14: TOTAL repartido | D14: =SUM(D6:D12) -> 90 | E14: =SUM(E6:E12) -> 1
B15: Superficie declarada en «Parámetros» | D15: ='Parámetros'!B14 -> 90
B16: Descuadre (m2) | D16: =IFERROR(D14-D15,"") -> 0 | G16: Si no es cero, o te sobran metros sin asignar o has repartido más de los que tiene el local.
B18: Metros de obrador | D18: =SUMIF(C6:C12,"Obrador",D6:D12) -> 45
B19: Parte del local dedicada a obrador | D19: =IFERROR(D18/D14,"") -> 0.5
B20: Metros de zona de venta (despacho) | D20: =SUMIF(C6:C12,"Despacho",D6:D12) -> 22
B21: Parte del local dedicada a venta | D21: =IFERROR(D20/D14,"") -> 0.24444444
B22: Mínimo de obrador que te has exigido | D22: ='Parámetros'!B15 -> 0.45
B23: Veredicto del reparto | D23: =IF(D19="","",IF(D19<D22,"El obrador se queda corto","Reparto suficiente")) -> Reparto suficiente
B25: Marcha adelante: la materia prima entra por un extremo y el producto sale por el otro
B26: Suma de los pasos que has numerado | D26: =SUM(F6:F12) -> 28
B27: Suma que debería dar (1 + 2 + ... + n) | D27: =IFERROR('Parámetros'!B23*('Parámetros'!B23+1)/2,"") -> 28
B28: ¿Están numerados del 1 al n sin repetir? | D28: =IF(AND(D26=D27,MIN(F6:F12)=1,MAX(F6:F12)='Parámetros'!B23),"Sí","Revisa la numeración") -> Sí | G28: Comprobación de numeración: la suma tiene que cuadrar y los pasos ir del 1 al número de zonas. No detecta una permutación que sume igual; lo que detecta -y es lo que pasa siempre- es un número repetido o uno saltado.
B29: La materia prima entra antes que el obrador | D29: =IF(F8<F6,"Sí","No") -> Sí
B30: La cámara de conservación va antes que el obrador | D30: =IF(F9<F6,"Sí","No") -> Sí
B31: El producto terminado sale después del obrador | D31: =IF(F10>F6,"Sí","No") -> Sí
B32: El producto terminado llega a la venta sin volver atrás | D32: =IF(F10<=F7,"Sí","No") -> Sí
B33: Los residuos salen después del obrador | D33: =IF(F12>F6,"Sí","No") -> Sí
B35: VEREDICTO DE MARCHA ADELANTE | D35: =IF(COUNTIF(D29:D33,"No")>0,"Hay un cruce en el recorrido","Marcha adelante correcta") -> Marcha adelante correcta
B37: La marcha adelante no es una preferencia de diseño: es que la materia prima sucia y el producto terminado no se crucen nunca. Cuando el local no la permite, no se arregla con un cartel ni con un horario; se arregla con obra o no se arregla. Por eso este recorrido se dibuja sobre el plano ANTES de firmar.

Sheet Capacidad por Equipo
A1: Capacidad Por Equipo
A2: AI Chef Pro · aichef.pro — Cómo Montar una Pastelería
A3: Un solo modelo para todas las máquinas: lo que cabe en un ciclo, cuántas piezas salen de eso, cuánto dura el ciclo y qué parte de tu surtido pasa por ahí.
A5: Nº | B5: Equipo | C5: Categoría | D5: ¿Lo tienes? | E5: Capacidad por ciclo | F5: Unidad de la capacidad | G5: Piezas por unidad | H5: Piezas por ciclo | I5: Minutos por ciclo | J5: Ciclos al día | K5: Piezas al día del equipo | L5: % del surtido que pasa | M5: Piezas/día de obrador que permite | N5: Cuenta para el cuello | O5: Procedencia | P5: Nota
A6: 1 | B6: Amasadora de espiral, 25 kg | C6: Amasado y batido | D6: Sí | E6: 25 | F6: kg de masa por amasada | G6: 19.6 | H6: =IFERROR(E6*G6,"") -> 490 | I6: 30 | J6: =IFERROR(INT('Parámetros'!$B$9/I6),"") -> 13 | K6: =IFERROR(H6*J6,"") -> 6370 | L6: 0.55 | M6: =IFERROR(K6/L6,"") -> 11581.818 | N6: =IF(D6="Sí",M6,"") -> 11581.818 | O6: supuesto | P6: Las piezas por kg salen de la tanda de croissant de la carta: 1,02 kg de masa para 20 piezas, es decir 19,6 piezas por kg. Cambia el número si tu surtido pesa más por pieza.
A7: 2 | B7: Batidora planetaria, 20 L | C7: Amasado y batido | D7: Sí | E7: 20 | F7: L de masa o crema por batida | G7: 8 | H7: =IFERROR(E7*G7,"") -> 160 | I7: 25 | J7: =IFERROR(INT('Parámetros'!$B$9/I7),"") -> 16 | K7: =IFERROR(H7*J7,"") -> 2560 | L7: 0.3 | M7: =IFERROR(K7/L7,"") -> 8533.3333 | N7: =IF(D7="Sí",M7,"") -> 8533.3333 | O7: PS-81 | P7: Sammic BP-20, 900 W. Es la que marca el ritmo de cremas, mousses y merengues, no de las masas.
A8: 3 | B8: Laminadora automática de masa, hasta 40 cm | C8: Laminación | D8: Sí | E8: 3 | F8: pastones por ciclo | G8: 20 | H8: =IFERROR(E8*G8,"") -> 60 | I8: 20 | J8: =IFERROR(INT('Parámetros'!$B$9/I8),"") -> 20 | K8: =IFERROR(H8*J8,"") -> 1200 | L8: 0.25 | M8: =IFERROR(K8/L8,"") -> 4800 | N8: =IF(D8="Sí",M8,"") -> 4800 | O8: PS-79 | P8: Sammic DF-40. Un pastón da una tanda de 20 piezas de bollería, así que tres pastones son 60 piezas por ciclo.
A9: 4 | B9: Horno de convección, 6 bandejas | C9: Calor | D9: Sí | E9: 6 | F9: bandejas por hornada | G9: 12 | H9: =IFERROR(E9*G9,"") -> 72 | I9: 25 | J9: =IFERROR(INT('Parámetros'!$B$9/I9),"") -> 16 | K9: =IFERROR(H9*J9,"") -> 1152 | L9: 0.6 | M9: =IFERROR(K9/L9,"") -> 1920 | N9: =IF(D9="Sí",M9,"") -> 1920 | O9: PS-72 | P9: UNOX XB693 Bakerlux. Las piezas por bandeja son de bollería mediana: bájalas para tartas y súbelas para petit four.
A10: 5 | B10: Horno de convección, 4 bandejas | C10: Calor | D10: Sí | E10: 4 | F10: bandejas por hornada | G10: 12 | H10: =IFERROR(E10*G10,"") -> 48 | I10: 25 | J10: =IFERROR(INT('Parámetros'!$B$9/I10),"") -> 16 | K10: =IFERROR(H10*J10,"") -> 768 | L10: 0.25 | M10: =IFERROR(K10/L10,"") -> 3072 | N10: =IF(D10="Sí",M10,"") -> 3072 | O10: PS-72 | P10: SMEG ALFA420E1HDS. El segundo horno no está para producir más: está para poder cocer a dos temperaturas a la vez.
A11: 6 | B11: Cámara de fermentación controlada (roll-in) | C11: Frío positivo | D11: Sí | E11: 2 | F11: carros por ciclo | G11: 90 | H11: =IFERROR(E11*G11,"") -> 180 | I11: 120 | J11: =IFERROR(INT('Parámetros'!$B$9/I11),"") -> 3 | K11: =IFERROR(H11*J11,"") -> 540 | L11: 0.35 | M11: =IFERROR(K11/L11,"") -> 1542.8571 | N11: =IF(D11="Sí",M11,"") -> 1542.8571 | O11: PS-83 | P11: Es lo que permite que la bollería esté horneada a las 7:00 sin entrar a las 3. Su ciclo es largo, así que limita más de lo que parece.
A12: 7 | B12: Abatidor de temperatura, 4 bandejas | C12: Frío negativo | D12: Sí | E12: 4 | F12: bandejas por ciclo | G12: 12 | H12: =IFERROR(E12*G12,"") -> 48 | I12: 90 | J12: =IFERROR(INT('Parámetros'!$B$9/I12),"") -> 4 | K12: =IFERROR(H12*J12,"") -> 192 | L12: 0.4 | M12: =IFERROR(K12/L12,"") -> 480 | N12: =IF(D12="Sí",M12,"") -> 480 | O12: PS-78 | P12: Irinox, gama Multifresh. Ciclo largo y obligatorio para lo relleno: es el candidato número uno a cuello de botella de una pastelería. Un arcón doméstico NO vale (art. 5 del RD 1021/2022).
A13: 8 | B13: Cámara frigorífica de conservación, 8 m3 | C13: Frío positivo | D13: Sí | E13: 8 | F13: m3 útiles por rotación | G13: 70 | H13: =IFERROR(E13*G13,"") -> 560 | I13: 400 | J13: =IFERROR(INT('Parámetros'!$B$9/I13),"") -> 1 | K13: =IFERROR(H13*J13,"") -> 560 | L13: 0.45 | M13: =IFERROR(K13/L13,"") -> 1244.4444 | N13: =IF(D13="Sí",M13,"") -> 1244.4444 | O13: supuesto | P13: Aquí el "ciclo" es una rotación de la cámara: con 400 minutos entra una rotación al día. Es la que sostiene los 4 °C de lo relleno.
A14: 9 | B14: Vitrina expositora pastelera refrigerada | C14: Tienda y vitrina | D14: Sí | E14: 0.93 | F14: m2 de exposición por reposición | G14: 130 | H14: =IFERROR(E14*G14,"") -> 120.9 | I14: 120 | J14: =IFERROR(INT('Parámetros'!$B$9/I14),"") -> 3 | K14: =IFERROR(H14*J14,"") -> 362.7 | L14: 0.35 | M14: =IFERROR(K14/L14,"") -> 1036.2857 | N14: =IF(D14="Sí",M14,"") -> 1036.2857 | O14: PS-76 | P14: Docriluc VEPD-9-15-C, 0,93 m2 de exposición. Con 120 minutos por reposición salen tres reposiciones de vitrina al día.
A15: 10 | B15: Horno de pisos modular (deck) | C15: Calor | D15: No | E15: 4 | F15: bandejas por hornada | G15: 14 | H15: =IFERROR(E15*G15,"") -> 56 | I15: 35 | J15: =IFERROR(INT('Parámetros'!$B$9/I15),"") -> 11 | K15: =IFERROR(H15*J15,"") -> 616 | L15: 0.2 | M15: =IFERROR(K15/L15,"") -> 3080 | N15: =IF(D15="Sí",M15,"") | O15: PS-73 | P15: OPCIONAL. Marcado como "No" a propósito: cámbialo a "Sí" y mira cómo se mueve el cuello de botella antes de gastarte el dinero.
B17: Minutos disponibles al día (de «Parámetros») | E17: ='Parámetros'!B9 -> 408
B18: Equipos que dices tener | E18: =COUNTIF(D6:D15,"Sí") -> 9
B19: Equipos que no cuentan (ciclo más largo que la jornada) | E19: =COUNTIF(J6:J15,0) -> 0 | P19: Un cero en «ciclos al día» quiere decir que el ciclo de esa máquina no cabe en la jornada que has declarado. No es un error del libro: es que con ese turno esa máquina no produce nada.
B21: Listas de validación (no las borres: las usan los desplegables)
B22: ¿Lo tienes?
B23: Sí
B24: No
B26: Las columnas verdes de esta hoja son las que tienes que pelear con el comercial: cuánto cabe de verdad en un ciclo, cuánto dura el ciclo completo (con carga y descarga, no el que pone el folleto) y qué parte de tu surtido pasa por ahí. Si ya tienes el Kit de Tareas Pastelería, el porcentaje real de cada máquina lo sacas de kit-tareas-pasteleria/10-plan-produccion-semanal.xlsx; mientras tanto, los valores por defecto son supuestos coherentes con la carta de 30 referencias de «La Clara».

Sheet Cuello de Botella
A1: Cuello de Botella
A2: AI Chef Pro · aichef.pro — Cómo Montar una Pastelería
A3: El equipo que manda, las piezas al día que aguanta el conjunto y qué pasa en cada uno de los seis picos del año.
A5: El día normal
A6: Piezas al día que quieres sacar | B6: ='Parámetros'!B12 -> 476
A7: Piezas al día que permite el conjunto | B7: =IFERROR(MIN('Capacidad por Equipo'!$N$6:$N$15),"") -> 480
A8: El equipo que limita | B8: =IFERROR(INDEX('Capacidad por Equipo'!$B$6:$B$15,MATCH(B7,'Capacidad por Equipo'!$N$6:$N$15,0)),"") -> Abatidor de temperatura, 4 bandejas
A9: Holgura sobre el día normal (piezas) | B9: =IFERROR(B7-B6,"") -> 4
A10: Holgura sobre el día normal (%) | B10: =IFERROR(B9/B6,"") -> 0.0084033613
A11: Margen de seguridad que te has exigido | B11: ='Parámetros'!B13 -> 0.1
A12: VEREDICTO DEL DÍA NORMAL | B12: =IF(B7="","",IF(B7<B6,"NO LLEGAS",IF(B10<B11,"AJUSTADO","SUFICIENTE"))) -> AJUSTADO | J12: «AJUSTADO» quiere decir que pasas el día normal, pero por debajo del margen de seguridad que tú mismo has pedido: una avería, una baja o un encargo grande te dejan sin género.
A13: El segundo equipo más justo permite | B13: =IFERROR(SMALL('Capacidad por Equipo'!$N$6:$N$15,2),"") -> 1036.2857
A14: Y es | B14: =IFERROR(INDEX('Capacidad por Equipo'!$B$6:$B$15,MATCH(B13,'Capacidad por Equipo'!$N$6:$N$15,0)),"") -> Vitrina expositora pastelera refrigerada | J14: Mira los dos juntos antes de comprar: si el segundo está muy cerca del primero, resolver sólo el cuello de botella te sube la capacidad cuatro piezas y te deja el dinero fuera.
A16: Los seis picos del año
A17: Pico | B17: Fechas | C17: Factor sobre el día normal | D17: Piezas/día que hacen falta | E17: Piezas/día que permite el conjunto | F17: Déficit (piezas/día) | G17: ¿Aguantas? | H17: Producto estrella | I17: Uds/día del estrella en campaña | J17: Nota
A18: Reyes | B18: 2 a 6 de enero | C18: 6 | D18: =IFERROR($B$6*C18,"") -> 2856 | E18: =IFERROR($B$7,"") -> 480 | F18: =IFERROR(E18-D18,"") -> -2376 | G18: =IF(F18="","",IF(F18<0,"NO","SÍ")) -> NO | H18: Roscón de Reyes | I18: 420 | J18: El pico que decide el año. Referencias de escala, nunca de precio ni de cuota: PS-35 (unos 30 millones de roscones en España en la campaña 2025/26), PS-36 (más de 2,9 millones en la Comunidad de Madrid) y PS-38 (El Corte Inglés 850.000, Viena Capellanes 72.000). PS-46: el supermercado entra con roscones premiados a 9 €. El roscón relleno de nata arrastra los 4 °C de la fila 9 y las 24 h del art. 9.3 justo el día de más producción: eso limita la producción tanto como el horno.
A19: San Valentín | B19: 13 y 14 de febrero | C19: 1.8 | D19: =IFERROR($B$6*C19,"") -> 856.8 | E19: =IFERROR($B$7,"") -> 480 | F19: =IFERROR(E19-D19,"") -> -376.8 | G19: =IF(F19="","",IF(F19<0,"NO","SÍ")) -> NO | H19: Macarons de frambuesa | I19: 260 | J19: Campaña de dos días y de ticket alto, no de volumen: se gana con cajas y presentación, no con más horno. En el kit, la producción especial de esta fecha son tartas corazón, bombones y macarons.
A20: Día del Padre y de la Madre | B20: 19 de marzo y primer domingo de mayo | C20: 1.9 | D20: =IFERROR($B$6*C20,"") -> 904.4 | E20: =IFERROR($B$7,"") -> 480 | F20: =IFERROR(E20-D20,"") -> -424.4 | G20: =IF(F20="","",IF(F20<0,"NO","SÍ")) -> NO | H20: Tarta de chocolate 70 % | I20: 96 | J20: Dos fechas con el mismo patrón de trabajo -tarta con dedicatoria, por encargo- y por eso van juntas como una sola campaña operativa. El kit las separa en su calendario porque a él le importan las fechas; a la guía le importa la carga de obrador.
A21: Semana Santa | B21: del Domingo de Ramos al Domingo de Resurrección | C21: 2.4 | D21: =IFERROR($B$6*C21,"") -> 1142.4 | E21: =IFERROR($B$7,"") -> 480 | F21: =IFERROR(E21-D21,"") -> -662.4 | G21: =IF(F21="","",IF(F21<0,"NO","SÍ")) -> NO | H21: Torrijas | I21: 240 | J21: Ocho días seguidos de producción extra, que es más agotador que los cinco de Reyes aunque el pico sea menor. Torrijas y monas a la vez: una necesita freidora y frío, la otra horno y chocolate.
A22: Comuniones | B22: de mediados de abril a mediados de junio | C22: 1.6 | D22: =IFERROR($B$6*C22,"") -> 761.6 | E22: =IFERROR($B$7,"") -> 480 | F22: =IFERROR(E22-D22,"") -> -281.6 | G22: =IF(F22="","",IF(F22<0,"NO","SÍ")) -> NO | H22: Tarta de nata y fresas | I22: 34 | J22: No es un pico, es una MESETA de dos meses, y por eso se aguanta con plantilla y no con horas extra. Todo va por encargo: anticipo, calendario de entrega y riesgo de anulación (cap. 16). La herramienta de gestión del encargo es el 11-control-encargos.xlsx del kit, que la guía no rehace (R2).
A23: Todos los Santos | B23: 30 y 31 de octubre y 1 de noviembre | C23: 2.6 | D23: =IFERROR($B$6*C23,"") -> 1237.6 | E23: =IFERROR($B$7,"") -> 480 | F23: =IFERROR(E23-D23,"") -> -757.6 | G23: =IF(F23="","",IF(F23<0,"NO","SÍ")) -> NO | H23: Buñuelos de viento | I23: 520 | J23: Tres días con tres referencias que sólo se hacen ahora: buñuelos, huesos de santo y panellets. Los buñuelos van rellenos (4 °C y 24 h) y los otros dos son estables a temperatura ambiente: por eso los buñuelos se hacen el mismo día y los huesos de santo se pueden adelantar. Ese detalle legal ES la planificación de la campaña.
A25: Picos que NO aguantas | B25: =COUNTIF(G18:G23,"NO") -> 6
A26: El peor déficit (piezas/día) | B26: =IFERROR(MIN(F18:F23),"") -> -2376
A27: Y es el pico de | B27: =IFERROR(INDEX($A$18:$A$23,MATCH(B26,$F$18:$F$23,0)),"") -> Reyes
A28: VEREDICTO DE CAMPAÑA | B28: =IF(B25=0,"Aguantas los seis picos",IF(B25=1,"Un pico se te va del obrador","Varios picos se te van del obrador")) -> Varios picos se te van del obrador
A30: Que un pico no quepa en el obrador NO es motivo para comprar más máquina: comprar para el día de Reyes es tener el dinero parado los otros 299 días. Lo que se hace es adelantar producción (congelación programada del art. 5, con abatidor, no con un arcón), cargar la campaña en lo estable a temperatura ambiente, que se puede hacer con días de antelación, y cerrar encargos con fecha. Las fechas de cada campaña y su lista de tareas están en el BONUS-02 del Kit de Tareas Pastelería; los euros que mueve cada una, en el libro 3 de esta guía.
A32: La columna «uds/día del estrella en campaña» está aquí como contraste, no como cálculo: son las unidades del producto que define el pico. Los 420 roscones al día de Reyes frente a los cero de un día normal son la razón por la que esta hoja existe.

Sheet Ficha de Visita a Local
A1: Ficha de Visita a Local
A2: AI Chef Pro · aichef.pro — Cómo Montar una Pastelería
A3: Imprímela y llévala a cada visita. Un solo «No» en un ítem eliminatorio y el veredicto es DESCARTAR.
A5: Nº | B5: Qué se comprueba | C5: ¿Eliminatorio? | D5: Cómo se comprueba | E5: Respuesta | F5: Dato medido | G5: Umbral | H5: ¿Cumple el dato? | I5: Veredicto | J5: Nota y norma
A6: 1 | B6: El local puede tener salida de humos propia hasta cubierta | C6: Sí | D6: Sube a la cubierta con el propietario y mira por dónde subiría el conducto. Pídelo por escrito antes de firmar. | E6: Sí | G6: No aplica | I6: =IF(H6="No",IF(C6="Sí","DESCARTAR","Punto débil"),IF(E6="","",IF(E6="No",IF(C6="Sí","DESCARTAR","Punto débil"),IF(E6="Por comprobar","Pendiente","OK")))) -> OK | J6: Referencia de sector, NO norma verificada (PS-86c): la salida suele tener que llegar a cubierta y rebasar la cumbrera en 1 m, pero la altura real la fija la ORDENANZA MUNICIPAL, no el CTE. Es la partida que más locales tumba y la que hay que resolver ANTES de firmar, no después.
A7: 2 | B7: La expulsión de la campana NO comparte conducto con el despacho ni con los aseos | C7: Sí | D7: Pide el plano de instalaciones o abre el falso techo. Si sólo hay un patinillo, ya tienes la respuesta. | E7: Sí | G7: No aplica | I7: =IF(H7="No",IF(C7="Sí","DESCARTAR","Punto débil"),IF(E7="","",IF(E7="No",IF(C7="Sí","DESCARTAR","Punto débil"),IF(E7="Por comprobar","Pendiente","OK")))) -> OK | J7: El aire de la campana de humos es categoría AE4 del RITE: no puede recircularse, no puede usarse como aire de transferencia y su expulsión no puede ser común con la del aire del despacho o los aseos. Ojo: esto NO sale del CTE DB-HS 3, que se aplica a viviendas y, en otros usos, sólo a aparcamientos y garajes.
A8: 3 | B8: El caudal de extracción disponible cubre el que necesitan tus hornos | C8: No | D8: Mide o pide la ficha del extractor existente. El umbral lo calcula la hoja «Parámetros» con tu potencia y tu tipo de energía. | E8: Sí | F8: 1400 | G8: ='Parámetros'!B21 -> 1360 | H8: =IF(AND(ISNUMBER(F8),ISNUMBER(G8)),IF(F8>=G8,"Sí","No"),"") -> Sí | I8: =IF(H8="No",IF(C8="Sí","DESCARTAR","Punto débil"),IF(E8="","",IF(E8="No",IF(C8="Sí","DESCARTAR","Punto débil"),IF(E8="Por comprobar","Pendiente","OK")))) -> OK | J8: Regla de dimensionado: 40 m3/h por kW en equipos eléctricos y 50 en equipos de gas (PS-86b). Si el local se queda corto, el coste de sustituir el extractor va al libro 2.
A9: 4 | B9: La potencia eléctrica contratable llega a la que vas a instalar | C9: Sí | D9: Pide el boletín eléctrico del local y consulta a la distribuidora la potencia disponible en la acometida. | E9: Sí | F9: 70 | G9: ='Parámetros'!B17 -> 62 | H9: =IF(AND(ISNUMBER(F9),ISNUMBER(G9)),IF(F9>=G9,"Sí","No"),"") -> Sí | I9: =IF(H9="No",IF(C9="Sí","DESCARTAR","Punto débil"),IF(E9="","",IF(E9="No",IF(C9="Sí","DESCARTAR","Punto débil"),IF(E9="Por comprobar","Pendiente","OK")))) -> OK | J9: Subir la potencia disponible de una acometida puede costar más que la obra entera y depende de la distribuidora, no de tu presupuesto.
A10: 5 | B10: El planeamiento urbanístico admite la actividad en esa finca | C10: Sí | D10: Consulta de compatibilidad urbanística en el ayuntamiento, por escrito y a nombre del local, no una llamada. | E10: Sí | G10: No aplica | I10: =IF(H10="No",IF(C10="Sí","DESCARTAR","Punto débil"),IF(E10="","",IF(E10="No",IF(C10="Sí","DESCARTAR","Punto débil"),IF(E10="Por comprobar","Pendiente","OK")))) -> OK | J10: Un local que hoy es un comercio no admite automáticamente un obrador: es actividad de transformación de alimentos, con humos y con horario de madrugada.
A11: 6 | B11: Los estatutos de la comunidad de propietarios no prohíben la actividad | C11: Sí | D11: Pide los estatutos inscritos y el acta de la última junta. Que el vecino de al lado sea un bar no basta. | E11: Sí | G11: No aplica | I11: =IF(H11="No",IF(C11="Sí","DESCARTAR","Punto débil"),IF(E11="","",IF(E11="No",IF(C11="Sí","DESCARTAR","Punto débil"),IF(E11="Por comprobar","Pendiente","OK")))) -> OK | J11: Una prohibición estatutaria inscrita se impone aunque el ayuntamiento te dé la licencia, y el conducto de humos suele pasar por zona común.
A12: 7 | B12: La altura libre del local llega a la que has fijado | C12: No | D12: Metro laser desde el suelo terminado a la cara inferior del forjado, en el punto más bajo, no en el más alto. | E12: Sí | F12: 3.2 | G12: ='Parámetros'!B22 -> 3 | H12: =IF(AND(ISNUMBER(F12),ISNUMBER(G12)),IF(F12>=G12,"Sí","No"),"") -> Sí | I12: =IF(H12="No",IF(C12="Sí","DESCARTAR","Punto débil"),IF(E12="","",IF(E12="No",IF(C12="Sí","DESCARTAR","Punto débil"),IF(E12="Por comprobar","Pendiente","OK")))) -> OK | J12: Con campana, conducto y falso techo, cada centímetro cuenta. Mide donde va el horno.
A13: 8 | B13: La superficie útil llega a los m2 que has repartido por zonas | C13: No | D13: Superficie útil real, sin contar muros ni patinillos. Compárala con el total de la hoja «Zonas y m2». | E13: Sí | F13: 92 | G13: ='Parámetros'!B14 -> 90 | H13: =IF(AND(ISNUMBER(F13),ISNUMBER(G13)),IF(F13>=G13,"Sí","No"),"") -> Sí | I13: =IF(H13="No",IF(C13="Sí","DESCARTAR","Punto débil"),IF(E13="","",IF(E13="No",IF(C13="Sí","DESCARTAR","Punto débil"),IF(E13="Por comprobar","Pendiente","OK")))) -> OK | J13: La superficie de un anuncio suele ser construida. La que te sirve es la útil, y entre una y otra se van con facilidad 10 m2.
A14: 9 | B14: Se puede separar el obrador para que quede inaccesible al público | C14: Sí | D14: Dibuja las siete zonas sobre el plano antes de firmar. Si no caben con la puerta donde está, no caben. | E14: Sí | G14: No aplica | I14: =IF(H14="No",IF(C14="Sí","DESCARTAR","Punto débil"),IF(E14="","",IF(E14="No",IF(C14="Sí","DESCARTAR","Punto débil"),IF(E14="Por comprobar","Pendiente","OK")))) -> OK | J14: El obrador es zona de elaboración inaccesible al público. No es una recomendación de diseño: es lo que separa un obrador de una cocina a la vista.
A15: 10 | B15: Las siete zonas caben con marcha adelante y sin cruces | C15: No | D15: Comprueba el recorrido en la hoja «Zonas y m2»: materia prima, obrador, producto terminado, venta. | E15: Sí | G15: No aplica | I15: =IF(H15="No",IF(C15="Sí","DESCARTAR","Punto débil"),IF(E15="","",IF(E15="No",IF(C15="Sí","DESCARTAR","Punto débil"),IF(E15="Por comprobar","Pendiente","OK")))) -> OK | J15: Que quepan los metros no quiere decir que quepa el recorrido. Un obrador donde la basura sale por donde entra la harina no pasa una inspección.
A16: 11 | B16: Hay acometida de agua fría y caliente y desagüe donde van los equipos | C16: No | D16: Localiza el desagüe existente. Mover un desagüe obliga a levantar el suelo del local entero. | E16: Sí | G16: No aplica | I16: =IF(H16="No",IF(C16="Sí","DESCARTAR","Punto débil"),IF(E16="","",IF(E16="No",IF(C16="Sí","DESCARTAR","Punto débil"),IF(E16="Por comprobar","Pendiente","OK")))) -> OK | J16: El horno con generador de vapor, el abatidor y el fregadero necesitan desagüe en su punto, no al fondo del local.
A17: 12 | B17: Suelos y paredes admiten acabado liso, lavable e impermeable | C17: No | D17: Mira el estado real: azulejo roto, yeso, hormigón visto. El acabado del obrador es obra, no pintura. | E17: Sí | G17: No aplica | I17: =IF(H17="No",IF(C17="Sí","DESCARTAR","Punto débil"),IF(E17="","",IF(E17="No",IF(C17="Sí","DESCARTAR","Punto débil"),IF(E17="Por comprobar","Pendiente","OK")))) -> OK | J17: Superficies lisas, lavables e impermeables, encuentros pared-suelo redondeados y lavamanos no manual por zona (PS-86e). No es un extra: es requisito.
A18: 13 | B18: Caben aseo y vestuario de personal separados de los de clientes | C18: No | D18: Cuenta los metros y mira dónde están los bajantes. Un aseo nuevo sin bajante cerca es obra grande. | E18: Sí | G18: No aplica | I18: =IF(H18="No",IF(C18="Sí","DESCARTAR","Punto débil"),IF(E18="","",IF(E18="No",IF(C18="Sí","DESCARTAR","Punto débil"),IF(E18="Por comprobar","Pendiente","OK")))) -> OK | J18: El personal necesita su aseo y su taquilla; el cliente, el suyo. Los 11 m2 de la hoja de zonas ya lo contemplan.
A19: 14 | B19: Se puede descargar género sin cruzar la zona de clientes | C19: No | D19: Ve a la hora a la que descargarías, no a mediodía. Mira si hay carga y descarga y si el portal lo permite. | E19: Sí | G19: No aplica | I19: =IF(H19="No",IF(C19="Sí","DESCARTAR","Punto débil"),IF(E19="","",IF(E19="No",IF(C19="Sí","DESCARTAR","Punto débil"),IF(E19="Por comprobar","Pendiente","OK")))) -> OK | J19: La harina entra en sacos y a diario. Si entra por la puerta del despacho, entra por delante del cliente todas las mañanas.
A20: 15 | B20: La basura sale sin abrir al obrador | C20: No | D20: Localiza el cuarto de residuos y su puerta. Debe estar cerrado y con contenedores identificados. | E20: Sí | G20: No aplica | I20: =IF(H20="No",IF(C20="Sí","DESCARTAR","Punto débil"),IF(E20="","",IF(E20="No",IF(C20="Sí","DESCARTAR","Punto débil"),IF(E20="Por comprobar","Pendiente","OK")))) -> OK | J20: El almacén de residuos no puede abrir al obrador. Es de los pocos defectos de plano que no tienen arreglo barato.
A21: 16 | B21: El local es accesible o admite ajustes razonables | C21: No | D21: Mide el escalón de entrada y el ancho de la puerta. Un escalón en fachada puede depender del ayuntamiento, no de ti. | E21: Sí | G21: No aplica | I21: =IF(H21="No",IF(C21="Sí","DESCARTAR","Punto débil"),IF(E21="","",IF(E21="No",IF(C21="Sí","DESCARTAR","Punto débil"),IF(E21="Por comprobar","Pendiente","OK")))) -> OK | J21: El calendario del RD 193/2023 para titularidad privada es el 1-ene-2029 en bienes y servicios nuevos y el 1-ene-2030 en los existentes; el art. 25.2 obliga sin umbral de superficie a garantizar la accesibilidad o a hacer ajustes razonables.
A22: 17 | B22: Si el horno es de gas, la instalación receptora está al día | C22: Sí | D22: Pide el certificado de la última inspección periódica y la fecha de puesta en servicio. | E22: Por comprobar | G22: No aplica | I22: =IF(H22="No",IF(C22="Sí","DESCARTAR","Punto débil"),IF(E22="","",IF(E22="No",IF(C22="Sí","DESCARTAR","Punto débil"),IF(E22="Por comprobar","Pendiente","OK")))) -> Pendiente | J22: Las instalaciones receptoras alimentadas desde red se inspeccionan cada cinco años, y el coste se repercute al usuario. Hasta 70 kW instalados la inspección incluye los aparatos de gas.
A23: 18 | B23: El contrato y las cargas del local están claros antes de firmar | C23: Sí | D23: Nota simple del Registro, contrato de arrendamiento leído entero y quién paga la obra de adecuación. | E23: Por comprobar | G23: No aplica | I23: =IF(H23="No",IF(C23="Sí","DESCARTAR","Punto débil"),IF(E23="","",IF(E23="No",IF(C23="Sí","DESCARTAR","Punto débil"),IF(E23="Por comprobar","Pendiente","OK")))) -> Pendiente | J23: Quién paga la obra, cuántos años dura el contrato y qué pasa con la obra al terminar son tres números del libro 2, no tres detalles.
B25: Ítems de la ficha | E25: =COUNTIF(C6:C23,"Sí")+COUNTIF(C6:C23,"No") -> 18
B26: De los cuales, eliminatorios | E26: =COUNTIF(C6:C23,"Sí") -> 8
B27: Motivos de descarte | E27: =COUNTIF(I6:I23,"DESCARTAR") -> 0
B28: Puntos débiles | E28: =COUNTIF(I6:I23,"Punto débil") -> 0
B29: Pendientes de comprobar | E29: =COUNTIF(I6:I23,"Pendiente") -> 2
B30: Resueltos sin problema | E30: =COUNTIF(I6:I23,"OK") -> 16
B31: Ficha comprobada | E31: =IFERROR((E25-E29)/E25,"") -> 0.88888889
B32: VEREDICTO DEL LOCAL | E32: =IF(E27>0,"DESCARTAR ESTE LOCAL",IF(E29>0,"NO DECIDAS TODAVÍA",IF(E28>0,"SIGUE ADELANTE CON RESERVAS","SIGUE ADELANTE"))) -> NO DECIDAS TODAVÍA
B34: Listas de validación (no las borres: las usan los desplegables)
B35: Respuesta
B36: Sí
B37: No
B38: Por comprobar
B40: Los ocho ítems eliminatorios no lo son por gusto: son los defectos que no se arreglan con dinero razonable, o que no dependen de ti (la comunidad, el planeamiento, la acometida, la cubierta). El resto encarecen la obra y hay que llevarlos al libro 2 como partida, no descartar el local por ellos. Y guarda la ficha de los locales que descartes: comparar tres fichas es lo que enseña qué estás aceptando sin darte cuenta.
