Workbook

Sheet Instrucciones
A1: Carta de Apertura y Escandallo por Tanda
A2: AI Chef Pro · aichef.pro — Cómo Montar una Pastelería
A3: Para qué sirve: decidir qué vendes, a cuánto, y con qué vía legal de huevo -con su temperatura y su plazo-.
A5: Instrucciones de uso
A6: 1. Hoja «Parámetros»: empieza por el bloque de personal de obrador. El coste hora de obrador NO es un dato del sector y no se teclea: se calcula con el bruto de tu convenio, las pagas, la jornada de cada persona y la Seguridad Social a cargo de la empresa. Debajo están los precios de compra, uno por ingrediente: es la única tabla donde se tocan los precios y de ella beben las 226 líneas del escandallo.
A7: 2. Hoja «Escandallo por Tanda»: una fila por ingrediente y por referencia. La unidad de costeo es LA TANDA, no la pieza: es como se trabaja en un obrador y es la única forma de que la mano de obra cuadre. Escribe la cantidad neta que usas, el factor que convierte la unidad de compra en la de uso (12 para pasar de docena a unidad, 1 si coinciden) y la merma. El coste de la línea sale solo.
A8: 3. Hoja «Coste Hora y Mano de Obra»: los minutos que te lleva cada tanda y el precio de venta. De ahí salen el coste de mano de obra por pieza, el coste total, el food cost y el margen en euros. Es el capítulo que enseña a dejar de regalar tu trabajo.
A9: 4. Hoja «Decisión de Huevo y Temperatura»: para cada referencia, elige la vía legal del huevo, di si va rellena y si el producto terminado es estable a temperatura ambiente. El libro devuelve la temperatura de conservación, cuál de los dos artículos manda y el plazo legal del art. 9.3. La vida útil la declaras tú.
A10: 5. Hoja «Mix y Ticket Medio»: reparte el 100 % de tus unidades entre las 30 referencias. De ahí sale tu ticket medio, que no se copia de ningún estudio porque no existe un ticket medio publicado de pastelería.
A11: 6. Hoja «Decisión de Surtido»: cruza margen y rotación y te dice qué mantener, a qué revisarle el precio y qué retirar. Repásala a los tres meses de abrir, con ventas reales, y otra vez al cambiar de temporada.
A13: Celdas verdes = campos editables
A15: Lo que conviene saber antes de empezar
... A30: Versión 1.0 · septiembre 2026 · aichef.pro/guia-pasteleria-obrador · info@aichef.pro

Sheet Parámetros
A1: Parámetros
A2: AI Chef Pro · aichef.pro — Cómo Montar una Pastelería
A3: El coste hora de obrador se CALCULA aquí desde tu plantilla y tu convenio. No es un dato del sector.
A5: Personal de obrador | B5: Jornada | C5: Grupo de convenio | D5: Bruto mensual del convenio (€) | E5: Bruto anual con las pagas (€) | F5: Coste de empresa anual con SS (€) | G5: Nota
A6: Jefe Pastelero (P1) | B6: 1 | C6: 2 · Dirección, jefes y encargados | D6: 1427.89 | E6: =IFERROR(D6*'Parámetros'!$B$11,"") -> 21418.35 | F6: =IFERROR(E6*B6*(1+'Parámetros'!$B$12),"") -> 28486.406 | G6: Turno: Madrugada (04:30-12:30). Sólo el área OBRADOR entra en el coste hora: el despacho no fabrica.
A7: Pastelero (P2) | B7: 1 | C7: 3 · Personal especialista | D7: 1376.91 | E7: =IFERROR(D7*'Parámetros'!$B$11,"") -> 20653.65 | F7: =IFERROR(E7*B7*(1+'Parámetros'!$B$12),"") -> 27469.355 | G7: Turno: Madrugada (05:00-13:00). Sólo el área OBRADOR entra en el coste hora: el despacho no fabrica.
A8: Ayudante (P3) | B8: 0.5 | C8: 5 · Personal de apoyo | D8: 1192.42 | E8: =IFERROR(D8*'Parámetros'!$B$11,"") -> 17886.3 | F8: =IFERROR(E8*B8*(1+'Parámetros'!$B$12),"") -> 11894.39 | G8: Turno: Mañana (07:00-11:00). Sólo el área OBRADOR entra en el coste hora: el despacho no fabrica.
A9: TOTAL OBRADOR | B9: =SUM(B6:B8) -> 2.5 | F9: =SUM(F6:F8) -> 67850.15
A11: Pagas del convenio al año | B11: 15 | C11: pagas | D11: PA-33 | G11: El convenio de la Comunidad de Madrid (código 28001025011981, revisión 2026 en el BOCM núm. 50, de 28 de febrero de 2026) paga 15, no 14. Sustitúyelo por el de tu convenio provincial.
A12: Seguridad Social a cargo de la empresa | B12: 0.33 | C12: sobre bruto | D12: motor.PARAMETROS | G12: Cotización empresarial aproximada sobre el bruto: contingencias comunes, desempleo, FOGASA y formación. Es el renglón que convierte un bruto en un coste, y el que más sorprende.
A13: Horas anuales de contrato | B13: 1780 | C13: horas/año | D13: supuesto | G13: 40 horas por 52 semanas son 2.080, menos 30 días naturales de vacaciones y los festivos del calendario laboral.
A14: Horas productivas sobre la jornada | B14: 0.85 | C14: de la jornada | D14: supuesto | G14: Parte de la jornada que se pasa a pie de mesa. El resto es recepción, limpieza, formación y reuniones: horas que pagas y no producen.
A15: Horas productivas del obrador al año | B15: =IFERROR($B$9*'Parámetros'!$B$13*'Parámetros'!$B$14,"") -> 3782.5 | C15: horas/año | D15: calculado | G15: Jornadas de obrador por horas anuales de contrato por el ratio productivo.
A16: COSTE HORA PRODUCTIVA DE OBRADOR | B16: =IFERROR($F$9/'Parámetros'!$B$15,"") -> 17.937911 | C16: €/hora | D16: calculado | G16: Coste de empresa anual del obrador dividido por sus horas PRODUCTIVAS (con el factor de 85 % de más arriba). Éste es el número que hay que meter en cada tanda, y el que casi nadie imputa. NO lo confundas con el «coste medio por hora PAGADA de la plantilla» del libro 8 (14,89 €, plantilla-turnos-y-coste-personal.xlsx) ni con el «coste por hora PAGADA del refuerzo» del libro 3 (13,36 €, estacionalidad-y-picos.xlsx): las tres son correctas y las tres miden un denominador distinto.
A18: IVA por familia de producto
A19: IVA de pastelería, bollería y confitería | B19: 0.1 | C19: sobre base | D19: PA-36 | G19: Regla general de alimentos del art. 91.Uno.1.1.º de la Ley 37/1992: no porque un precepto los nombre, sino porque no están en la lista cerrada del 4 % ni excluidos del 10 %.
A20: IVA del pan del RD 308/2019 | B20: 0.04 | C20: sobre base | D20: PA-36b | G20: Todos los productos del RD 308/2019 -pan común, pan especial y semielaborados, con o sin gluten- van al 4 % desde la Resolución vinculante de la DGT de 24-02-2025, que acoge la STS 1610/2024. El cruasán sigue al 10 %: el RD 308/2019 sólo regula el pan y no menciona la bollería.
A21: IVA en zona de degustación | B21: 0.1 | C21: sobre base | D21: PA-36c | G21: Si pones mesas, ahí no vendes un bien: prestas un servicio de hostelería (art. 91.Uno.2.2.º). Tu TPV tiene que separar los tipos.
A23: La regla del margen: UN número, y el otro se deriva
A24: Food cost objetivo | B24: 0.32 | C24: sobre PVP sin IVA | D24: PS-55 + PS-56 | G24: Éste es el ÚNICO número de margen que se teclea. La banda del sector es 30-35 % de food cost, que es exactamente lo mismo que decir 65-70 % de margen bruto.
A25: Margen bruto objetivo (derivado) | B25: =IFERROR(1-'Parámetros'!$B$24,"") -> 0.68 | C25: sobre PVP sin IVA | D25: calculado | G25: Uno menos el food cost objetivo. No se teclea a propósito: pedir los dos números permite ponerlos incoherentes y es el error de método más repetido del oficio.
A27: Techos y plazos legales (RD 1021/2022, verificado el 10-09-2026)
A28: Techo de la fila 9 del art. 4.1 | B28: 4 | C28: °C | D28: PA-12 | G28: Productos de pastelería RELLENOS, salvo que sean estables a temperatura ambiente. Es el techo más bajo de los dos y por eso suele mandar él.
A29: Techo del art. 9.3 | B29: 8 | C29: °C | D29: PA-15 | G29: Lo elaborado por la vía del art. 9.1.a) que no sea estable a temperatura ambiente, y lo hecho con ovoproducto del art. 9.2.
A30: Plazo de consumo del art. 9.3 | B30: 24 | C30: horas | D30: PA-15 | G30: Desde la elaboración, con REGISTRO de fecha y hora. No es una vida útil: es un plazo legal, y sólo alcanza a lo que dice el propio art. 9.3.
A31: Umbral analítico de «sin gluten» | B31: 20 | C31: mg/kg | D31: PA-23 | G31: No es una declaración libre: por debajo de 20 mg/kg de gluten en el producto tal y como se vende. Con harina de arroz no basta si el obrador comparte utillaje con harina de trigo.
A33: Merma, packaging y comercial
A34: Merma objetivo | B34: 0.05 | C34: de la producción | D34: kit-tareas-pasteleria/10 | G34: Objetivo precargado en el plan de producción del kit. En una pastelería artesanal se mueve entre el 3 y el 8 %; por encima del 10 % hay que revisar el plan de producción, no el escandallo.
A35: Packaging sobre el coste del producto | B35: 0.1 | C35: del coste | D35: PS-59 | G35: Entre el 5 y el 15 % del coste total del producto. Aquí, el punto medio. En pastelería la caja no es un extra: es parte del producto.
A36: Piezas por cliente | B36: 2.6 | C36: piezas/ticket | D36: supuesto | G36: De aquí sale el ticket medio, que NO se teclea. No existe un ticket medio publicado de pastelería: el tuyo se calcula desde tu carta y tu mix, y por eso se puede publicar diciendo lo que es.
A37: Umbral de rotación del semáforo de surtido | B37: 1 | C37: % del mix | D37: supuesto | G37: Por debajo de este porcentaje del mix, la referencia se considera de rotación baja en la hoja «Decisión de Surtido». Criterio de la casa, no del sector: súbelo si tu carta es más corta.
A39: Precios de compra (la única tabla de precios)
A40: Ingrediente | B40: Precio de compra (€) | C40: Unidad de compra | D40: De dónde sale | G40: Nota
A41: Aceite de girasol | B41: 1.8 | C41: L | D41: supuesto
A42: Aceite de oliva virgen extra | B42: 7.2 | C42: L | D42: supuesto
A43: Agua de azahar | B43: 14 | C43: L | D43: supuesto
A44: Almendra marcona cruda | B44: 15.5 | C44: kg | D44: supuesto
A45: Almendra molida | B45: 13.5 | C45: kg | D45: supuesto
A46: Almidón de maíz | B46: 2.1 | C46: kg | D46: supuesto
A47: Azúcar | B47: 1.2 | C47: kg | D47: copiado del kit
A48: Azúcar glas | B48: 2.5 | C48: kg | D48: copiado del kit
A49: Cacao en polvo | B49: 12 | C49: kg | D49: copiado del kit
A50: Canela molida | B50: 18 | C50: kg | D50: supuesto
A51: Chocolate blanco | B51: 15 | C51: kg | D51: copiado del kit
A52: Chocolate negro 70% | B52: 18 | C52: kg | D52: copiado del kit
... A89: Zanahoria | B89: 1.1 | C89: kg | D89: supuesto
A91: Los diecinueve precios marcados «copiado del kit» son los mismos que usa el «kit-escandallos/05-pasteleria.xlsx»: son los que hacen que el mismo croissant cueste lo mismo en los dos productos. Ojo con la mantequilla: la cotización de commodity a granel que publican los observatorios NO es el precio de la mantequilla de laminado 82-84 % que compra un obrador. Sirve para modelar la volatilidad, nunca para fijar un precio.
A93: Versión 1.0 · septiembre 2026 · aichef.pro/guia-pasteleria-obrador · info@aichef.pro

Sheet Escandallo por Tanda
A1: Escandallo por Tanda
A2: AI Chef Pro · aichef.pro — Cómo Montar una Pastelería
A3: La unidad de costeo es LA TANDA, no la pieza. Los precios salen de la tabla única de «Parámetros».
A5: Ref | B5: Referencia | C5: Familia | D5: Ingrediente | E5: Cantidad neta | F5: Unidad de uso | G5: Factor de conversión | H5: Merma | I5: Cantidad bruta | J5: Precio de compra (€) | K5: Unidad de compra | L5: Coste de la línea (€) | M5: Procedencia
A6: B1 | B6: Croissant de mantequilla | C6: Bollería | D6: Harina de fuerza | E6: 0.5 | F6: kg | G6: 1 | H6: 0.08 | I6: =IFERROR(E6/(1-H6),"") -> 0.54347826 | J6: =IFERROR(VLOOKUP($D6,'Parámetros'!$A$41:$C$89,2,FALSE),"") -> 1.1 | K6: kg | L6: =IFERROR(I6/G6*J6,"") -> 0.59782609 | M6: COPIA EXACTA de kit-escandallos/05-pasteleria.xlsx, hoja «Croissants». Mismo escandallo en los dos productos: un cliente con los dos no puede ver dos costes distintos de la misma pieza.
A7: B1 | D7: Mantequilla seca (82% MG) | E7: 0.28 | F7: kg | G7: 1 | H7: 0.03 | I7: =IFERROR(E7/(1-H7),"") -> 0.28865979 | J7: =IFERROR(VLOOKUP($D7,'Parámetros'!$A$41:$C$89,2,FALSE),"") -> 12 | K7: kg | L7: =IFERROR(I7/G7*J7,"") -> 3.4639175
A8: B1 | D8: Leche entera | E8: 0.15 | F8: L | G8: 1 | H8: 0.03 | I8: =IFERROR(E8/(1-H8),"") -> 0.15463918 | J8: =IFERROR(VLOOKUP($D8,'Parámetros'!$A$41:$C$89,2,FALSE),"") -> 1.1 | K8: L | L8: =IFERROR(I8/G8*J8,"") -> 0.17010309
A9: B1 | D9: Azúcar | E9: 0.06 | F9: kg | G9: 1 | H9: 0.02 | I9: =IFERROR(E9/(1-H9),"") -> 0.06122449 | J9: =IFERROR(VLOOKUP($D9,'Parámetros'!$A$41:$C$89,2,FALSE),"") -> 1.2 | K9: kg | L9: =IFERROR(I9/G9*J9,"") -> 0.073469388
A10: B1 | D10: Levadura fresca | E10: 0.02 | F10: kg | G10: 1 | H10: 0.05 | I10: =IFERROR(E10/(1-H10),"") -> 0.021052632 | J10: =IFERROR(VLOOKUP($D10,'Parámetros'!$A$41:$C$89,2,FALSE),"") -> 5 | K10: kg | L10: =IFERROR(I10/G10*J10,"") -> 0.10526316
A11: B1 | D11: Sal | E11: 0.01 | F11: kg | G11: 1 | H11: 0.02 | I11: =IFERROR(E11/(1-H11),"") -> 0.010204082 | J11: =IFERROR(VLOOKUP($D11,'Parámetros'!$A$41:$C$89,2,FALSE),"") -> 0.6 | K11: kg | L11: =IFERROR(I11/G11*J11,"") -> 0.006122449
A12: B1 | D12: Huevo (para pintar) | E12: 1 | F12: ud | G12: 12 | H12: 0 | I12: =IFERROR(E12/(1-H12),"") -> 1 | J12: =IFERROR(VLOOKUP($D12,'Parámetros'!$A$41:$C$89,2,FALSE),"") -> 3.6 | K12: docena | L12: =IFERROR(I12/G12*J12,"") -> 0.3
A13: B2 | B13: Pain au chocolat | C13: Bollería | D13: Harina de fuerza | E13: 0.5 | F13: kg | G13: 1 | H13: 0.08 | I13: =IFERROR(E13/(1-H13),"") -> 0.54347826 | J13: =IFERROR(VLOOKUP($D13,'Parámetros'!$A$41:$C$89,2,FALSE),"") -> 1.1 | K13: kg | L13: =IFERROR(I13/G13*J13,"") -> 0.59782609 | M13: supuesto (misma masa que B1, del kit, más dos barras por pieza)
A14: B2 | D14: Mantequilla seca (82% MG) | E14: 0.28 | F14: kg | G14: 1 | H14: 0.03 | I14: =IFERROR(E14/(1-H14),"") -> 0.28865979 | J14: =IFERROR(VLOOKUP($D14,'Parámetros'!$A$41:$C$89,2,FALSE),"") -> 12 | K14: kg | L14: =IFERROR(I14/G14*J14,"") -> 3.4639175
A15: B2 | D15: Leche entera | E15: 0.15 | F15: L | G15: 1 | H15: 0.03 | I15: =IFERROR(E15/(1-H15),"") -> 0.15463918 | J15: =IFERROR(VLOOKUP($D15,'Parámetros'!$A$41:$C$89,2,FALSE),"") -> 1.1 | K15: L | L15: =IFERROR(I15/G15*J15,"") -> 0.17010309
A16: B2 | D16: Azúcar | E16: 0.06 | F16: kg | G16: 1 | H16: 0.02 | I16: =IFERROR(E16/(1-H16),"") -> 0.06122449 | J16: =IFERROR(VLOOKUP($D16,'Parámetros'!$A$41:$C$89,2,FALSE),"") -> 1.2 | K16: kg | L16: =IFERROR(I16/G16*J16,"") -> 0.073469388
A17: B2 | D17: Levadura fresca | E17: 0.02 | F17: kg | G17: 1 | H17: 0.05 | I17: =IFERROR(E17/(1-H17),"") -> 0.021052632 | J17: =IFERROR(VLOOKUP($D17,'Parámetros'!$A$41:$C$89,2,FALSE),"") -> 5 | K17: kg | L17: =IFERROR(I17/G17*J17,"") -> 0.10526316
A18: B2 | D18: Sal | E18: 0.01 | F18: kg | G18: 1 | H18: 0.02 | I18: =IFERROR(E18/(1-H18),"") -> 0.010204082 | J18: =IFERROR(VLOOKUP($D18,'Parámetros'!$A$41:$C$89,2,FALSE),"") -> 0.6 | K18: kg | L18: =IFERROR(I18/G18*J18,"") -> 0.006122449
A19: B2 | D19: Chocolate negro 70% | E19: 0.2 | F19: kg | G19: 1 | H19: 0.02 | I19: =IFERROR(E19/(1-H19),"") -> 0.20408163 | J19: =IFERROR(VLOOKUP($D19,'Parámetros'!$A$41:$C$89,2,FALSE),"") -> 18 | K19: kg | L19: =IFERROR(I19/G19*J19,"") -> 3.6734694
A20: B2 | D20: Huevo (para pintar) | E20: 1 | F20: ud | G20: 12 | H20: 0 | I20: =IFERROR(E20/(1-H20),"") -> 1 | J20: =IFERROR(VLOOKUP($D20,'Parámetros'!$A$41:$C$89,2,FALSE),"") -> 3.6 | K20: docena | L20: =IFERROR(I20/G20*J20,"") -> 0.3
A21: B3 | B21: Napolitana de crema | C21: Bollería | D21: Harina de fuerza | E21: 0.5 | F21: kg | G21: 1 | H21: 0.08 | I21: =IFERROR(E21/(1-H21),"") -> 0.54347826 | J21: =IFERROR(VLOOKUP($D21,'Parámetros'!$A$41:$C$89,2,FALSE),"") -> 1.1 | K21: kg | L21: =IFERROR(I21/G21*J21,"") -> 0.59782609 | M21: supuesto (masa del kit más crema pastelera de ejemplo)
A22: B3 | D22: Mantequilla seca (82% MG) | E22: 0.28 | F22: kg | G22: 1 | H22: 0.03 | I22: =IFERROR(E22/(1-H22),"") -> 0.28865979 | J22: =IFERROR(VLOOKUP($D22,'Parámetros'!$A$41:$C$89,2,FALSE),"") -> 12 | K22: kg | L22: =IFERROR(I22/G22*J22,"") -> 3.4639175
A23: B3 | D23: Leche entera | E23: 0.15 | F23: L | G23: 1 | H23: 0.03 | I23: =IFERROR(E23/(1-H23),"") -> 0.15463918 | J23: =IFERROR(VLOOKUP($D23,'Parámetros'!$A$41:$C$89,2,FALSE),"") -> 1.1 | K23: L | L23: =IFERROR(I23/G23*J23,"") -> 0.17010309
A24: B3 | D24: Azúcar | E24: 0.06 | F24: kg | G24: 1 | H24: 0.02 | I24: =IFERROR(E24/(1-H24),"") -> 0.06122449 | J24: =IFERROR(VLOOKUP($D24,'Parámetros'!$A$41:$C$89,2,FALSE),"") -> 1.2 | K24: kg | L24: =IFERROR(I24/G24*J24,"") -> 0.073469388
A25: B3 | D25: Levadura fresca | E25: 0.02 | F25: kg | G25: 1 | H25: 0.05 | I25: =IFERROR(E25/(1-H25),"") -> 0.021052632 | J25: =IFERROR(VLOOKUP($D25,'Parámetros'!$A$41:$C$89,2,FALSE),"") -> 5 | K25: kg | L25: =IFERROR(I25/G25*J25,"") -> 0.10526316
A26: B3 | D26: Sal | E26: 0.01 | F26: kg | G26: 1 | H26: 0.02 | I26: =IFERROR(E26/(1-H26),"") -> 0.010204082 | J26: =IFERROR(VLOOKUP($D26,'Parámetros'!$A$41:$C$89,2,FALSE),"") -> 0.6 | K26: kg | L26: =IFERROR(I26/G26*J26,"") -> 0.006122449
A27: B3 | D27: Leche entera | E27: 0.6 | F27: L | G27: 1 | H27: 0.02 | I27: =IFERROR(E27/(1-H27),"") -> 0.6122449 | J27: =IFERROR(VLOOKUP($D27,'Parámetros'!$A$41:$C$89,2,FALSE),"") -> 1.1 | K27: L | L27: =IFERROR(I27/G27*J27,"") -> 0.67346939
A28: B3 | D28: Azúcar | E28: 0.14 | F28: kg | G28: 1 | H28: 0.02 | I28: =IFERROR(E28/(1-H28),"") -> 0.14285714 | J28: =IFERROR(VLOOKUP($D28,'Parámetros'!$A$41:$C$89,2,FALSE),"") -> 1.2 | K28: kg | L28: =IFERROR(I28/G28*J28,"") -> 0.17142857
A29: B3 | D29: Huevos (unidades) | E29: 4 | F29: ud | G29: 12 | H29: 0 | I29: =IFERROR(E29/(1-H29),"") -> 4 | J29: =IFERROR(VLOOKUP($D29,'Parámetros'!$A$41:$C$89,2,FALSE),"") -> 3.6 | K29: docena | L29: =IFERROR(I29/G29*J29,"") -> 1.2
A30: B3 | D30: Almidón de maíz | E30: 0.05 | F30: kg | G30: 1 | H30: 0.02 | I30: =IFERROR(E30/(1-H30),"") -> 0.051020408 | J30: =IFERROR(VLOOKUP($D30,'Parámetros'!$A$41:$C$89,2,FALSE),"") -> 2.1 | K30: kg | L30: =IFERROR(I30/G30*J30,"") -> 0.10714286
A31: B3 | D31: Vainilla en pasta | E31: 0.002 | F31: kg | G31: 1 | H31: 0 | I31: =IFERROR(E31/(1-H31),"") -> 0.002 | J31: =IFERROR(VLOOKUP($D31,'Parámetros'!$A$41:$C$89,2,FALSE),"") -> 92 | K31: kg | L31: =IFERROR(I31/G31*J31,"") -> 0.184
A32: B3 | D32: Huevo (para pintar) | E32: 1 | F32: ud | G32: 12 | H32: 0 | I32: =IFERROR(E32/(1-H32),"") -> 1 | J32: =IFERROR(VLOOKUP($D32,'Parámetros'!$A$41:$C$89,2,FALSE),"") -> 3.6 | K32: docena | L32: =IFERROR(I32/G32*J32,"") -> 0.3
A33: B4 | B33: Palmera de hojaldre | C33: Bollería | D33: Harina floja | E33: 0.45 | F33: kg | G33: 1 | H33: 0.08 | I33: =IFERROR(E33/(1-H33),"") -> 0.48913043 | J33: =IFERROR(VLOOKUP($D33,'Parámetros'!$A$41:$C$89,2,FALSE),"") -> 0.9 | K33: kg | L33: =IFERROR(I33/G33*J33,"") -> 0.44021739 | M33: supuesto
A34: B4 | D34: Mantequilla seca (82% MG) | E34: 0.36 | F34: kg | G34: 1 | H34: 0.03 | I34: =IFERROR(E34/(1-H34),"") -> 0.37113402 | J34: =IFERROR(VLOOKUP($D34,'Parámetros'!$A$41:$C$89,2,FALSE),"") -> 12 | K34: kg | L34: =IFERROR(I34/G34*J34,"") -> 4.4536082
A35: B4 | D35: Azúcar | E35: 0.3 | F35: kg | G35: 1 | H35: 0.02 | I35: =IFERROR(E35/(1-H35),"") -> 0.30612245 | J35: =IFERROR(VLOOKUP($D35,'Parámetros'!$A$41:$C$89,2,FALSE),"") -> 1.2 | K35: kg | L35: =IFERROR(I35/G35*J35,"") -> 0.36734694
A36: B4 | D36: Sal | E36: 0.01 | F36: kg | G36: 1 | H36: 0.02 | I36: =IFERROR(E36/(1-H36),"") -> 0.010204082 | J36: =IFERROR(VLOOKUP($D36,'Parámetros'!$A$41:$C$89,2,FALSE),"") -> 0.6 | K36: kg | L36: =IFERROR(I36/G36*J36,"") -> 0.006122449
A37: B5 | B37: Caracola de pasas | C37: Bollería | D37: Harina de fuerza | E37: 0.45 | F37: kg | G37: 1 | H37: 0.08 | I37: =IFERROR(E37/(1-H37),"") -> 0.48913043 | J37: =IFERROR(VLOOKUP($D37,'Parámetros'!$A$41:$C$89,2,FALSE),"") -> 1.1 | K37: kg | L37: =IFERROR(I37/G37*J37,"") -> 0.53804348 | M37: supuesto
A38: B5 | D38: Mantequilla seca (82% MG) | E38: 0.22 | F38: kg | G38: 1 | H38: 0.03 | I38: =IFERROR(E38/(1-H38),"") -> 0.22680412 | J38: =IFERROR(VLOOKUP($D38,'Parámetros'!$A$41:$C$89,2,FALSE),"") -> 12 | K38: kg | L38: =IFERROR(I38/G38*J38,"") -> 2.7216495
A39: B5 | D39: Leche entera | E39: 0.14 | F39: L | G39: 1 | H39: 0.03 | I39: =IFERROR(E39/(1-H39),"") -> 0.1443299 | J39: =IFERROR(VLOOKUP($D39,'Parámetros'!$A$41:$C$89,2,FALSE),"") -> 1.1 | K39: L | L39: =IFERROR(I39/G39*J39,"") -> 0.15876289
A40: B5 | D40: Azúcar | E40: 0.05 | F40: kg | G40: 1 | H40: 0.02 | I40: =IFERROR(E40/(1-H40),"") -> 0.051020408 | J40: =IFERROR(VLOOKUP($D40,'Parámetros'!$A$41:$C$89,2,FALSE),"") -> 1.2 | K40: kg | L40: =IFERROR(I40/G40*J40,"") -> 0.06122449
A41: B5 | D41: Levadura fresca | E41: 0.018 | F41: kg | G41: 1 | H41: 0.05 | I41: =IFERROR(E41/(1-H41),"") -> 0.018947368 | J41: =IFERROR(VLOOKUP($D41,'Parámetros'!$A$41:$C$89,2,FALSE),"") -> 5 | K41: kg | L41: =IFERROR(I41/G41*J41,"") -> 0.094736842
A42: B5 | D42: Sal | E42: 0.009 | F42: kg | G42: 1 | H42: 0.02 | I42: =IFERROR(E42/(1-H42),"") -> 0.0091836735 | J42: =IFERROR(VLOOKUP($D42,'Parámetros'!$A$41:$C$89,2,FALSE),"") -> 0.6 | K42: kg | L42: =IFERROR(I42/G42*J42,"") -> 0.0055102041
A43: B5 | D43: Pasas | E43: 0.15 | F43: kg | G43: 1 | H43: 0.02 | I43: =IFERROR(E43/(1-H43),"") -> 0.15306122 | J43: =IFERROR(VLOOKUP($D43,'Parámetros'!$A$41:$C$89,2,FALSE),"") -> 5.2 | K43: kg | L43: =IFERROR(I43/G43*J43,"") -> 0.79591837
A44: B5 | D44: Ron | E44: 0.03 | F44: L | G44: 1 | H44: 0 | I44: =IFERROR(E44/(1-H44),"") -> 0.03 | J44: =IFERROR(VLOOKUP($D44,'Parámetros'!$A$41:$C$89,2,FALSE),"") -> 9.8 | K44: L | L44: =IFERROR(I44/G44*J44,"") -> 0.294
A45: B5 | D45: Leche entera | E45: 0.35 | F45: L | G45: 1 | H45: 0.02 | I45: =IFERROR(E45/(1-H45),"") -> 0.35714286 | J45: =IFERROR(VLOOKUP($D45,'Parámetros'!$A$41:$C$89,2,FALSE),"") -> 1.1 | K45: L | L45: =IFERROR(I45/G45*J45,"") -> 0.39285714
A46: B5 | D46: Azúcar | E46: 0.08 | F46: kg | G46: 1 | H46: 0.02 | I46: =IFERROR(E46/(1-H46),"") -> 0.081632653 | J46: =IFERROR(VLOOKUP($D46,'Parámetros'!$A$41:$C$89,2,FALSE),"") -> 1.2 | K46: kg | L46: =IFERROR(I46/G46*J46,"") -> 0.097959184
A47: B5 | D47: Huevos (unidades) | E47: 2 | F47: ud | G47: 12 | H47: 0 | I47: =IFERROR(E47/(1-H47),"") -> 2 | J47: =IFERROR(VLOOKUP($D47,'Parámetros'!$A$41:$C$89,2,FALSE),"") -> 3.6 | K47: docena | L47: =IFERROR(I47/G47*J47,"") -> 0.6
A48: B5 | D48: Almidón de maíz | E48: 0.03 | F48: kg | G48: 1 | H48: 0.02 | I48: =IFERROR(E48/(1-H48),"") -> 0.030612245 | J48: =IFERROR(VLOOKUP($D48,'Parámetros'!$A$41:$C$89,2,FALSE),"") -> 2.1 | K48: kg | L48: =IFERROR(I48/G48*J48,"") -> 0.064285714
A49: B5 | D49: Huevo (para pintar) | E49: 1 | F49: ud | G49: 12 | H49: 0 | I49: =IFERROR(E49/(1-H49),"") -> 1 | J49: =IFERROR(VLOOKUP($D49,'Parámetros'!$A$41:$C$89,2,FALSE),"") -> 3.6 | K49: docena | L49: =IFERROR(I49/G49*J49,"") -> 0.3
A50: B6 | B50: Ensaimada | C50: Bollería | D50: Harina de fuerza | E50: 0.6 | F50: kg | G50: 1 | H50: 0.08 | I50: =IFERROR(E50/(1-H50),"") -> 0.65217391 | J50: =IFERROR(VLOOKUP($D50,'Parámetros'!$A$41:$C$89,2,FALSE),"") -> 1.1 | K50: kg | L50: =IFERROR(I50/G50*J50,"") -> 0.7173913 | M50: supuesto
A51: B6 | D51: Manteca de cerdo | E51: 0.2 | F51: kg | G51: 1 | H51: 0.03 | I51: =IFERROR(E51/(1-H51),"") -> 0.20618557 | J51: =IFERROR(VLOOKUP($D51,'Parámetros'!$A$41:$C$89,2,FALSE),"") -> 4.4 | K51: kg | L51: =IFERROR(I51/G51*J51,"") -> 0.90721649
A52: B6 | D52: Azúcar | E52: 0.12 | F52: kg | G52: 1 | H52: 0.02 | I52: =IFERROR(E52/(1-H52),"") -> 0.12244898 | J52: =IFERROR(VLOOKUP($D52,'Parámetros'!$A$41:$C$89,2,FALSE),"") -> 1.2 | K52: kg | L52: =IFERROR(I52/G52*J52,"") -> 0.14693878
A53: B6 | D53: Huevos (unidades) | E53: 3 | F53: ud | G53: 12 | H53: 0 | I53: =IFERROR(E53/(1-H53),"") -> 3 | J53: =IFERROR(VLOOKUP($D53,'Parámetros'!$A$41:$C$89,2,FALSE),"") -> 3.6 | K53: docena | L53: =IFERROR(I53/G53*J53,"") -> 0.9
A54: B6 | D54: Levadura fresca | E54: 0.02 | F54: kg | G54: 1 | H54: 0.05 | I54: =IFERROR(E54/(1-H54),"") -> 0.021052632 | J54: =IFERROR(VLOOKUP($D54,'Parámetros'!$A$41:$C$89,2,FALSE),"") -> 5 | K54: kg | L54: =IFERROR(I54/G54*J54,"") -> 0.10526316
A55: B6 | D55: Sal | E55: 0.008 | F55: kg | G55: 1 | H55: 0.02 | I55: =IFERROR(E55/(1-H55),"") -> 0.0081632653 | J55: =IFERROR(VLOOKUP($D55,'Parámetros'!$A$41:$C$89,2,FALSE),"") -> 0.6 | K55: kg | L55: =IFERROR(I55/G55*J55,"") -> 0.0048979592
A56: B6 | D56: Azúcar glas | E56: 0.04 | F56: kg | G56: 1 | H56: 0.02 | I56: =IFERROR(E56/(1-H56),"") -> 0.040816327 | J56: =IFERROR(VLOOKUP($D56,'Parámetros'!$A$41:$C$89,2,FALSE),"") -> 2.5 | K56: kg | L56: =IFERROR(I56/G56*J56,"") -> 0.10204082
A57: PI1 | B57: Milhojas | C57: Pastelería individual | D57: Harina floja | E57: 0.35 | F57: kg | G57: 1 | H57: 0.08 | I57: =IFERROR(E57/(1-H57),"") -> 0.38043478 | J57: =IFERROR(VLOOKUP($D57,'Parámetros'!$A$41:$C$89,2,FALSE),"") -> 0.9 | K57: kg | L57: =IFERROR(I57/G57*J57,"") -> 0.3423913 | M57: supuesto
A58: PI1 | D58: Mantequilla seca (82% MG) | E58: 0.28 | F58: kg | G58: 1 | H58: 0.03 | I58: =IFERROR(E58/(1-H58),"") -> 0.28865979 | J58: =IFERROR(VLOOKUP($D58,'Parámetros'!$A$41:$C$89,2,FALSE),"") -> 12 | K58: kg | L58: =IFERROR(I58/G58*J58,"") -> 3.4639175
A59: PI1 | D59: Sal | E59: 0.008 | F59: kg | G59: 1 | H59: 0.02 | I59: =IFERROR(E59/(1-H59),"") -> 0.0081632653 | J59: =IFERROR(VLOOKUP($D59,'Parámetros'!$A$41:$C$89,2,FALSE),"") -> 0.6 | K59: kg | L59: =IFERROR(I59/G59*J59,"") -> 0.0048979592
A60: PI1 | D60: Leche entera | E60: 0.8 | F60: L | G60: 1 | H60: 0.02 | I60: =IFERROR(E60/(1-H60),"") -> 0.81632653 | J60: =IFERROR(VLOOKUP($D60,'Parámetros'!$A$41:$C$89,2,FALSE),"") -> 1.1 | K60: L | L60: =IFERROR(I60/G60*J60,"") -> 0.89795918
A61: PI1 | D61: Azúcar | E61: 0.18 | F61: kg | G61: 1 | H61: 0.02 | I61: =IFERROR(E61/(1-H61),"") -> 0.18367347 | J61: =IFERROR(VLOOKUP($D61,'Parámetros'!$A$41:$C$89,2,FALSE),"") -> 1.2 | K61: kg | L61: =IFERROR(I61/G61*J61,"") -> 0.22040816
A62: PI1 | D62: Huevos (unidades) | E62: 5 | F62: ud | G62: 12 | H62: 0 | I62: =IFERROR(E62/(1-H62),"") -> 5 | J62: =IFERROR(VLOOKUP($D62,'Parámetros'!$A$41:$C$89,2,FALSE),"") -> 3.6 | K62: docena | L62: =IFERROR(I62/G62*J62,"") -> 1.5
A63: PI1 | D63: Almidón de maíz | E63: 0.06 | F63: kg | G63: 1 | H63: 0.02 | I63: =IFERROR(E63/(1-H63),"") -> 0.06122449 | J63: =IFERROR(VLOOKUP($D63,'Parámetros'!$A$41:$C$89,2,FALSE),"") -> 2.1 | K63: kg | L63: =IFERROR(I63/G63*J63,"") -> 0.12857143
A64: PI1 | D64: Vainilla en pasta | E64: 0.002 | F64: kg | G64: 1 | H64: 0 | I64: =IFERROR(E64/(1-H64),"") -> 0.002 | J64: =IFERROR(VLOOKUP($D64,'Parámetros'!$A$41:$C$89,2,FALSE),"") -> 92 | K64: kg | L64: =IFERROR(I64/G64*J64,"") -> 0.184
A65: PI1 | D65: Nata 35% MG | E65: 0.3 | F65: L | G65: 1 | H65: 0.03 | I65: =IFERROR(E65/(1-H65),"") -> 0.30927835 | J65: =IFERROR(VLOOKUP($D65,'Parámetros'!$A$41:$C$89,2,FALSE),"") -> 3.8 | K65: L | L65: =IFERROR(I65/G65*J65,"") -> 1.1752577
A66: PI1 | D66: Azúcar glas | E66: 0.05 | F66: kg | G66: 1 | H66: 0.02 | I66: =IFERROR(E66/(1-H66),"") -> 0.051020408 | J66: =IFERROR(VLOOKUP($D66,'Parámetros'!$A$41:$C$89,2,FALSE),"") -> 2.5 | K66: kg | L66: =IFERROR(I66/G66*J66,"") -> 0.12755102
A67: PI2 | B67: Éclair | C67: Pastelería individual | D67: Harina floja | E67: 0.18 | F67: kg | G67: 1 | H67: 0.08 | I67: =IFERROR(E67/(1-H67),"") -> 0.19565217 | J67: =IFERROR(VLOOKUP($D67,'Parámetros'!$A$41:$C$89,2,FALSE),"") -> 0.9 | K67: kg | L67: =IFERROR(I67/G67*J67,"") -> 0.17608696 | M67: supuesto
A68: PI2 | D68: Mantequilla | E68: 0.14 | F68: kg | G68: 1 | H68: 0.03 | I68: =IFERROR(E68/(1-H68),"") -> 0.1443299 | J68: =IFERROR(VLOOKUP($D68,'Parámetros'!$A$41:$C$89,2,FALSE),"") -> 9 | K68: kg | L68: =IFERROR(I68/G68*J68,"") -> 1.2989691
A69: PI2 | D69: Huevos (unidades) | E69: 6 | F69: ud | G69: 12 | H69: 0 | I69: =IFERROR(E69/(1-H69),"") -> 6 | J69: =IFERROR(VLOOKUP($D69,'Parámetros'!$A$41:$C$89,2,FALSE),"") -> 3.6 | K69: docena | L69: =IFERROR(I69/G69*J69,"") -> 1.8
A70: PI2 | D70: Sal | E70: 0.004 | F70: kg | G70: 1 | H70: 0.02 | I70: =IFERROR(E70/(1-H70),"") -> 0.0040816327 | J70: =IFERROR(VLOOKUP($D70,'Parámetros'!$A$41:$C$89,2,FALSE),"") -> 0.6 | K70: kg | L70: =IFERROR(I70/G70*J70,"") -> 0.0024489796
A71: PI2 | D71: Leche entera | E71: 0.7 | F71: L | G71: 1 | H71: 0.02 | I71: =IFERROR(E71/(1-H71),"") -> 0.71428571 | J71: =IFERROR(VLOOKUP($D71,'Parámetros'!$A$41:$C$89,2,FALSE),"") -> 1.1 | K71: L | L71: =IFERROR(I71/G71*J71,"") -> 0.78571429
A72: PI2 | D72: Azúcar | E72: 0.16 | F72: kg | G72: 1 | H72: 0.02 | I72: =IFERROR(E72/(1-H72),"") -> 0.16326531 | J72: =IFERROR(VLOOKUP($D72,'Parámetros'!$A$41:$C$89,2,FALSE),"") -> 1.2 | K72: kg | L72: =IFERROR(I72/G72*J72,"") -> 0.19591837
A73: PI2 | D73: Huevos (unidades) | E73: 4 | F73: ud | G73: 12 | H73: 0 | I73: =IFERROR(E73/(1-H73),"") -> 4 | J73: =IFERROR(VLOOKUP($D73,'Parámetros'!$A$41:$C$89,2,FALSE),"") -> 3.6 | K73: docena | L73: =IFERROR(I73/G73*J73,"") -> 1.2
A74: PI2 | D74: Almidón de maíz | E74: 0.055 | F74: kg | G74: 1 | H74: 0.02 | I74: =IFERROR(E74/(1-H74),"") -> 0.056122449 | J74: =IFERROR(VLOOKUP($D74,'Parámetros'!$A$41:$C$89,2,FALSE),"") -> 2.1 | K74: kg | L74: =IFERROR(I74/G74*J74,"") -> 0.11785714
A75: PI2 | D75: Vainilla en pasta | E75: 0.002 | F75: kg | G75: 1 | H75: 0 | I75: =IFERROR(E75/(1-H75),"") -> 0.002 | J75: =IFERROR(VLOOKUP($D75,'Parámetros'!$A$41:$C$89,2,FALSE),"") -> 92 | K75: kg | L75: =IFERROR(I75/G75*J75,"") -> 0.184
A76: PI2 | D76: Chocolate negro 70% | E76: 0.12 | F76: kg | G76: 1 | H76: 0.02 | I76: =IFERROR(E76/(1-H76),"") -> 0.12244898 | J76: =IFERROR(VLOOKUP($D76,'Parámetros'!$A$41:$C$89,2,FALSE),"") -> 18 | K76: kg | L76: =IFERROR(I76/G76*J76,"") -> 2.2040816
A77: PI2 | D77: Azúcar glas | E77: 0.06 | F77: kg | G77: 1 | H77: 0.02 | I77: =IFERROR(E77/(1-H77),"") -> 0.06122449 | J77: =IFERROR(VLOOKUP($D77,'Parámetros'!$A$41:$C$89,2,FALSE),"") -> 2.5 | K77: kg | L77: =IFERROR(I77/G77*J77,"") -> 0.15306122
A78: PI3 | B78: Macarons de frambuesa | C78: Pastelería individual | D78: Harina de almendra | E78: 0.15 | F78: kg | G78: 1 | H78: 0.02 | I78: =IFERROR(E78/(1-H78),"") -> 0.15306122 | J78: =IFERROR(VLOOKUP($D78,'Parámetros'!$A$41:$C$89,2,FALSE),"") -> 14 | K78: kg | L78: =IFERROR(I78/G78*J78,"") -> 2.1428571 | M78: COPIA EXACTA de kit-escandallos/05-pasteleria.xlsx, hoja «Macarons». Mismo escandallo en los dos productos: un cliente con los dos no puede ver dos costes distintos de la misma pieza.
A79: PI3 | D79: Azúcar glas | E79: 0.15 | F79: kg | G79: 1 | H79: 0.02 | I79: =IFERROR(E79/(1-H79),"") -> 0.15306122 | J79: =IFERROR(VLOOKUP($D79,'Parámetros'!$A$41:$C$89,2,FALSE),"") -> 2.5 | K79: kg | L79: =IFERROR(I79/G79*J79,"") -> 0.38265306
A80: PI3 | D80: Claras de huevo | E80: 0.11 | F80: kg | G80: 1 | H80: 0.05 | I80: =IFERROR(E80/(1-H80),"") -> 0.11578947 | J80: =IFERROR(VLOOKUP($D80,'Parámetros'!$A$41:$C$89,2,FALSE),"") -> 6 | K80: kg | L80: =IFERROR(I80/G80*J80,"") -> 0.69473684
A81: PI3 | D81: Azúcar | E81: 0.15 | F81: kg | G81: 1 | H81: 0.02 | I81: =IFERROR(E81/(1-H81),"") -> 0.15306122 | J81: =IFERROR(VLOOKUP($D81,'Parámetros'!$A$41:$C$89,2,FALSE),"") -> 1.2 | K81: kg | L81: =IFERROR(I81/G81*J81,"") -> 0.18367347
A82: PI3 | D82: Frambuesa congelada | E82: 0.1 | F82: kg | G82: 1 | H82: 0.07 | I82: =IFERROR(E82/(1-H82),"") -> 0.10752688 | J82: =IFERROR(VLOOKUP($D82,'Parámetros'!$A$41:$C$89,2,FALSE),"") -> 9 | K82: kg | L82: =IFERROR(I82/G82*J82,"") -> 0.96774194
A83: PI3 | D83: Chocolate blanco | E83: 0.08 | F83: kg | G83: 1 | H83: 0.12 | I83: =IFERROR(E83/(1-H83),"") -> 0.090909091 | J83: =IFERROR(VLOOKUP($D83,'Parámetros'!$A$41:$C$89,2,FALSE),"") -> 15 | K83: kg | L83: =IFERROR(I83/G83*J83,"") -> 1.3636364
A84: PI3 | D84: Colorante rojo (bote 50 g · 2 g/tanda) | E84: 0.04 | F84: ud | G84: 1 | H84: 0 | I84: =IFERROR(E84/(1-H84),"") -> 0.04 | J84: =IFERROR(VLOOKUP($D84,'Parámetros'!$A$41:$C$89,2,FALSE),"") -> 4 | K84: ud | L84: =IFERROR(I84/G84*J84,"") -> 0.16
A85: PI4 | B85: Tartaleta de frutas | C85: Pastelería individual | D85: Harina floja | E85: 0.4 | F85: kg | G85: 1 | H85: 0.08 | I85: =IFERROR(E85/(1-H85),"") -> 0.43478261 | J85: =IFERROR(VLOOKUP($D85,'Parámetros'!$A$41:$C$89,2,FALSE),"") -> 0.9 | K85: kg | L85: =IFERROR(I85/G85*J85,"") -> 0.39130435 | M85: supuesto
A86: PI4 | D86: Mantequilla | E86: 0.2 | F86: kg | G86: 1 | H86: 0.03 | I86: =IFERROR(E86/(1-H86),"") -> 0.20618557 | J86: =IFERROR(VLOOKUP($D86,'Parámetros'!$A$41:$C$89,2,FALSE),"") -> 9 | K86: kg | L86: =IFERROR(I86/G86*J86,"") -> 1.8556701
A87: PI4 | D87: Azúcar glas | E87: 0.12 | F87: kg | G87: 1 | H87: 0.02 | I87: =IFERROR(E87/(1-H87),"") -> 0.12244898 | J87: =IFERROR(VLOOKUP($D87,'Parámetros'!$A$41:$C$89,2,FALSE),"") -> 2.5 | K87: kg | L87: =IFERROR(I87/G87*J87,"") -> 0.30612245
A88: PI4 | D88: Huevos (unidades) | E88: 2 | F88: ud | G88: 12 | H88: 0 | I88: =IFERROR(E88/(1-H88),"") -> 2 | J88: =IFERROR(VLOOKUP($D88,'Parámetros'!$A$41:$C$89,2,FALSE),"") -> 3.6 | K88: docena | L88: =IFERROR(I88/G88*J88,"") -> 0.6
A89: PI4 | D89: Sal | E89: 0.004 | F89: kg | G89: 1 | H89: 0.02 | I89: =IFERROR(E89/(1-H89),"") -> 0.0040816327 | J89: =IFERROR(VLOOKUP($D89,'Parámetros'!$A$41:$C$89,2,FALSE),"") -> 0.6 | K89: kg | L89: =IFERROR(I89/G89*J89,"") -> 0.0024489796
A90: PI4 | D90: Leche entera | E90: 0.5 | F90: L | G90: 1 | H90: 0.02 | I90: =IFERROR(E90/(1-H90),"") -> 0.51020408 | J90: =IFERROR(VLOOKUP($D90,'Parámetros'!$A$41:$C$89,2,FALSE),"") -> 1.1 | K90: L | L90: =IFERROR(I90/G90*J90,"") -> 0.56122449
A91: PI4 | D91: Azúcar | E91: 0.11 | F91: kg | G91: 1 | H91: 0.02 | I91: =IFERROR(E91/(1-H91),"") -> 0.1122449 | J91: =IFERROR(VLOOKUP($D91,'Parámetros'!$A$41:$C$89,2,FALSE),"") -> 1.2 | K91: kg | L91: =IFERROR(I91/G91*J91,"") -> 0.13469388
A92: PI4 | D92: Huevos (unidades) | E92: 3 | F92: ud | G92: 12 | H92: 0 | I92: =IFERROR(E92/(1-H92),"") -> 3 | J92: =IFERROR(VLOOKUP($D92,'Parámetros'!$A$41:$C$89,2,FALSE),"") -> 3.6 | K92: docena | L92: =IFERROR(I92/G92*J92,"") -> 0.9
A93: PI4 | D93: Almidón de maíz | E93: 0.04 | F93: kg | G93: 1 | H93: 0.02 | I93: =IFERROR(E93/(1-H93),"") -> 0.040816327 | J93: =IFERROR(VLOOKUP($D93,'Parámetros'!$A$41:$C$89,2,FALSE),"") -> 2.1 | K93: kg | L93: =IFERROR(I93/G93*J93,"") -> 0.085714286
A94: PI4 | D94: Fresa fresca | E94: 0.35 | F94: kg | G94: 1 | H94: 0.12 | I94: =IFERROR(E94/(1-H94),"") -> 0.39772727 | J94: =IFERROR(VLOOKUP($D94,'Parámetros'!$A$41:$C$89,2,FALSE),"") -> 6.2 | K94: kg | L94: =IFERROR(I94/G94*J94,"") -> 2.4659091
A95: PI4 | D95: Kiwi | E95: 0.2 | F95: kg | G95: 1 | H95: 0.18 | I95: =IFERROR(E95/(1-H95),"") -> 0.24390244 | J95: =IFERROR(VLOOKUP($D95,'Parámetros'!$A$41:$C$89,2,FALSE),"") -> 2.6 | K95: kg | L95: =IFERROR(I95/G95*J95,"") -> 0.63414634
A96: PI4 | D96: Frutos rojos congelados | E96: 0.15 | F96: kg | G96: 1 | H96: 0.03 | I96: =IFERROR(E96/(1-H96),"") -> 0.15463918 | J96: =IFERROR(VLOOKUP($D96,'Parámetros'!$A$41:$C$89,2,FALSE),"") -> 10.5 | K96: kg | L96: =IFERROR(I96/G96*J96,"") -> 1.6237113
A97: PI4 | D97: Gelatina neutra de brillo | E97: 0.08 | F97: kg | G97: 1 | H97: 0.02 | I97: =IFERROR(E97/(1-H97),"") -> 0.081632653 | J97: =IFERROR(VLOOKUP($D97,'Parámetros'!$A$41:$C$89,2,FALSE),"") -> 11.5 | K97: kg | L97: =IFERROR(I97/G97*J97,"") -> 0.93877551
A98: PI5 | B98: Lionesa o profiterol | C98: Pastelería individual | D98: Harina floja | E98: 0.2 | F98: kg | G98: 1 | H98: 0.08 | I98: =IFERROR(E98/(1-H98),"") -> 0.2173913 | J98: =IFERROR(VLOOKUP($D98,'Parámetros'!$A$41:$C$89,2,FALSE),"") -> 0.9 | K98: kg | L98: =IFERROR(I98/G98*J98,"") -> 0.19565217 | M98: supuesto
A99: PI5 | D99: Mantequilla | E99: 0.16 | F99: kg | G99: 1 | H99: 0.03 | I99: =IFERROR(E99/(1-H99),"") -> 0.16494845 | J99: =IFERROR(VLOOKUP($D99,'Parámetros'!$A$41:$C$89,2,FALSE),"") -> 9 | K99: kg | L99: =IFERROR(I99/G99*J99,"") -> 1.4845361
A100: PI5 | D100: Huevos (unidades) | E100: 7 | F100: ud | G100: 12 | H100: 0 | I100: =IFERROR(E100/(1-H100),"") -> 7 | J100: =IFERROR(VLOOKUP($D100,'Parámetros'!$A$41:$C$89,2,FALSE),"") -> 3.6 | K100: docena | L100: =IFERROR(I100/G100*J100,"") -> 2.1
A101: PI5 | D101: Sal | E101: 0.004 | F101: kg | G101: 1 | H101: 0.02 | I101: =IFERROR(E101/(1-H101),"") -> 0.0040816327 | J101: =IFERROR(VLOOKUP($D101,'Parámetros'!$A$41:$C$89,2,FALSE),"") -> 0.6 | K101: kg | L101: =IFERROR(I101/G101*J101,"") -> 0.0024489796
...

Sheet Coste Hora y Mano de Obra
A1: Coste Hora y Mano de Obra
A2: AI Chef Pro · aichef.pro — Cómo Montar una Pastelería
A3: La mano de obra imputada por pieza. Es el capítulo que enseña a dejar de regalar tu trabajo.
A5: Ref | B5: Referencia | C5: Familia | D5: Uds por tanda | E5: Minutos de mano de obra por tanda | F5: Horas de mano de obra por tanda | G5: Coste hora de obrador (€) | H5: Coste de mano de obra de la tanda (€) | I5: Coste de mano de obra por unidad (€) | J5: Coste de materia por unidad (€) | K5: Coste total por unidad (€) | L5: PVP con IVA (€) | M5: IVA | N5: PVP sin IVA (€) | O5: Food cost | P5: Margen bruto | Q5: Margen por unidad (€) | R5: Peso de la mano de obra sobre el coste | S5: Minutos por pieza
A6: B1 | B6: Croissant de mantequilla | C6: Bollería | D6: ='Escandallo por Tanda'!D236 -> 20 | E6: 55 | F6: =IFERROR(E6/60,"") -> 0.91666667 | G6: ='Parámetros'!$B$16 -> 17.937911 | H6: =IFERROR(F6*G6,"") -> 16.443085 | I6: =IFERROR(H6/D6,"") -> 0.82215427 | J6: ='Escandallo por Tanda'!G236 -> 0.23583509 | K6: =IFERROR(I6+J6,"") -> 1.0579894 | L6: 1.6 | M6: 0.1 | N6: =IFERROR(L6/(1+M6),"") -> 1.4545455 | O6: =IFERROR(J6/N6,"") -> 0.16213662 | P6: =IFERROR(1-O6,"") -> 0.83786338 | Q6: =IFERROR(N6-K6,"") -> 0.3965561 | R6: =IFERROR(I6/K6,"") -> 0.77709125 | S6: =IFERROR(E6/D6,"") -> 2.75
A7: B2 | B7: Pain au chocolat | C7: Bollería | D7: ='Escandallo por Tanda'!D237 -> 20 | E7: 55 | F7: =IFERROR(E7/60,"") -> 0.91666667 | G7: ='Parámetros'!$B$16 -> 17.937911 | H7: =IFERROR(F7*G7,"") -> 16.443085 | I7: =IFERROR(H7/D7,"") -> 0.82215427 | J7: ='Escandallo por Tanda'!G237 -> 0.41950855 | K7: =IFERROR(I7+J7,"") -> 1.2416628 | L7: 1.85 | M7: 0.1 | N7: =IFERROR(L7/(1+M7),"") -> 1.6818182 | O7: =IFERROR(J7/N7,"") -> 0.24943752 | P7: =IFERROR(1-O7,"") -> 0.75056248 | Q7: =IFERROR(N7-K7,"") -> 0.44015536 | R7: =IFERROR(I7/K7,"") -> 0.66213972 | S7: =IFERROR(E7/D7,"") -> 2.75
A8: B3 | B8: Napolitana de crema | C8: Bollería | D8: ='Escandallo por Tanda'!D238 -> 20 | E8: 65 | F8: =IFERROR(E8/60,"") -> 1.0833333 | G8: ='Parámetros'!$B$16 -> 17.937911 | H8: =IFERROR(F8*G8,"") -> 19.432737 | I8: =IFERROR(H8/D8,"") -> 0.97163686 | J8: ='Escandallo por Tanda'!G238 -> 0.35263713 | K8: =IFERROR(I8+J8,"") -> 1.324274 | L8: 1.85 | M8: 0.1 | N8: =IFERROR(L8/(1+M8),"") -> 1.6818182 | O8: =IFERROR(J8/N8,"") -> 0.20967613 | P8: =IFERROR(1-O8,"") -> 0.79032387 | Q8: =IFERROR(N8-K8,"") -> 0.35754419 | R8: =IFERROR(I8/K8,"") -> 0.73371287 | S8: =IFERROR(E8/D8,"") -> 3.25
A9: B4 | B9: Palmera de hojaldre | C9: Bollería | D9: ='Escandallo por Tanda'!D239 -> 24 | E9: 40 | F9: =IFERROR(E9/60,"") -> 0.66666667 | G9: ='Parámetros'!$B$16 -> 17.937911 | H9: =IFERROR(F9*G9,"") -> 11.958608 | I9: =IFERROR(H9/D9,"") -> 0.49827531 | J9: ='Escandallo por Tanda'!G239 -> 0.21947063 | K9: =IFERROR(I9+J9,"") -> 0.71774594 | L9: 1.7 | M9: 0.1 | N9: =IFERROR(L9/(1+M9),"") -> 1.5454545 | O9: =IFERROR(J9/N9,"") -> 0.14201041 | P9: =IFERROR(1-O9,"") -> 0.85798959 | Q9: =IFERROR(N9-K9,"") -> 0.82770861 | R9: =IFERROR(I9/K9,"") -> 0.69422241 | S9: =IFERROR(E9/D9,"") -> 1.6666667
A10: B5 | B10: Caracola de pasas | C10: Bollería | D10: ='Escandallo por Tanda'!D240 -> 20 | E10: 60 | F10: =IFERROR(E10/60,"") -> 1 | G10: ='Parámetros'!$B$16 -> 17.937911 | H10: =IFERROR(F10*G10,"") -> 17.937911 | I10: =IFERROR(H10/D10,"") -> 0.89689557 | J10: ='Escandallo por Tanda'!G240 -> 0.30624739 | K10: =IFERROR(I10+J10,"") -> 1.203143 | L10: 1.85 | M10: 0.1 | N10: =IFERROR(L10/(1+M10),"") -> 1.6818182 | O10: =IFERROR(J10/N10,"") -> 0.18209304 | P10: =IFERROR(1-O10,"") -> 0.81790696 | Q10: =IFERROR(N10-K10,"") -> 0.47867523 | R10: =IFERROR(I10/K10,"") -> 0.74546051 | S10: =IFERROR(E10/D10,"") -> 3
A11: B6 | B11: Ensaimada | C11: Bollería | D11: ='Escandallo por Tanda'!D241 -> 16 | E11: 70 | F11: =IFERROR(E11/60,"") -> 1.1666667 | G11: ='Parámetros'!$B$16 -> 17.937911 | H11: =IFERROR(F11*G11,"") -> 20.927563 | I11: =IFERROR(H11/D11,"") -> 1.3079727 | J11: ='Escandallo por Tanda'!G241 -> 0.18023428 | K11: =IFERROR(I11+J11,"") -> 1.488207 | L11: 1.95 | M11: 0.1 | N11: =IFERROR(L11/(1+M11),"") -> 1.7727273 | O11: =IFERROR(J11/N11,"") -> 0.10167062 | P11: =IFERROR(1-O11,"") -> 0.89832938 | Q11: =IFERROR(N11-K11,"") -> 0.28452029 | R11: =IFERROR(I11/K11,"") -> 0.87889166 | S11: =IFERROR(E11/D11,"") -> 4.375
A12: PI1 | B12: Milhojas | C12: Pastelería individual | D12: ='Escandallo por Tanda'!D242 -> 18 | E12: 75 | F12: =IFERROR(E12/60,"") -> 1.25 | G12: ='Parámetros'!$B$16 -> 17.937911 | H12: =IFERROR(F12*G12,"") -> 22.422389 | I12: =IFERROR(H12/D12,"") -> 1.2456883 | J12: ='Escandallo por Tanda'!G242 -> 0.44694191 | K12: =IFERROR(I12+J12,"") -> 1.6926302 | L12: 3.6 | M12: 0.1 | N12: =IFERROR(L12/(1+M12),"") -> 3.2727273 | O12: =IFERROR(J12/N12,"") -> 0.13656558 | P12: =IFERROR(1-O12,"") -> 0.86343442 | Q12: =IFERROR(N12-K12,"") -> 1.5800971 | R12: =IFERROR(I12/K12,"") -> 0.73594828 | S12: =IFERROR(E12/D12,"") -> 4.1666667
A13: PI2 | B13: Éclair | C13: Pastelería individual | D13: ='Escandallo por Tanda'!D243 -> 24 | E13: 65 | F13: =IFERROR(E13/60,"") -> 1.0833333 | G13: ='Parámetros'!$B$16 -> 17.937911 | H13: =IFERROR(F13*G13,"") -> 19.432737 | I13: =IFERROR(H13/D13,"") -> 0.80969739 | J13: ='Escandallo por Tanda'!G243 -> 0.33825574 | K13: =IFERROR(I13+J13,"") -> 1.1479531 | L13: 3.2 | M13: 0.1 | N13: =IFERROR(L13/(1+M13),"") -> 2.9090909 | O13: =IFERROR(J13/N13,"") -> 0.11627541 | P13: =IFERROR(1-O13,"") -> 0.88372459 | Q13: =IFERROR(N13-K13,"") -> 1.7611378 | R13: =IFERROR(I13/K13,"") -> 0.70534011 | S13: =IFERROR(E13/D13,"") -> 2.7083333
A14: PI3 | B14: Macarons de frambuesa | C14: Pastelería individual | D14: ='Escandallo por Tanda'!D244 -> 30 | E14: 80 | F14: =IFERROR(E14/60,"") -> 1.3333333 | G14: ='Parámetros'!$B$16 -> 17.937911 | H14: =IFERROR(F14*G14,"") -> 23.917215 | I14: =IFERROR(H14/D14,"") -> 0.7972405 | J14: ='Escandallo por Tanda'!G244 -> 0.19650996 | K14: =IFERROR(I14+J14,"") -> 0.99375046 | L14: 2.1 | M14: 0.1 | N14: =IFERROR(L14/(1+M14),"") -> 1.9090909 | O14: =IFERROR(J14/N14,"") -> 0.10293379 | P14: =IFERROR(1-O14,"") -> 0.89706621 | Q14: =IFERROR(N14-K14,"") -> 0.91534045 | R14: =IFERROR(I14/K14,"") -> 0.80225422 | S14: =IFERROR(E14/D14,"") -> 2.6666667
A15: PI4 | B15: Tartaleta de frutas | C15: Pastelería individual | D15: ='Escandallo por Tanda'!D245 -> 20 | E15: 85 | F15: =IFERROR(E15/60,"") -> 1.4166667 | G15: ='Parámetros'!$B$16 -> 17.937911 | H15: =IFERROR(F15*G15,"") -> 25.412041 | I15: =IFERROR(H15/D15,"") -> 1.2706021 | J15: ='Escandallo por Tanda'!G245 -> 0.52498604 | K15: =IFERROR(I15+J15,"") -> 1.7955881 | L15: 3.8 | M15: 0.1 | N15: =IFERROR(L15/(1+M15),"") -> 3.4545455 | O15: =IFERROR(J15/N15,"") -> 0.15196964 | P15: =IFERROR(1-O15,"") -> 0.84803036 | Q15: =IFERROR(N15-K15,"") -> 1.6589574 | R15: =IFERROR(I15/K15,"") -> 0.70762446 | S15: =IFERROR(E15/D15,"") -> 4.25
A16: PI5 | B16: Lionesa o profiterol | C16: Pastelería individual | D16: ='Escandallo por Tanda'!D246 -> 40 | E16: 60 | F16: =IFERROR(E16/60,"") -> 1 | G16: ='Parámetros'!$B$16 -> 17.937911 | H16: =IFERROR(F16*G16,"") -> 17.937911 | I16: =IFERROR(H16/D16,"") -> 0.44844778 | J16: ='Escandallo por Tanda'!G246 -> 0.19817681 | K16: =IFERROR(I16+J16,"") -> 0.64662459 | L16: 2.3 | M16: 0.1 | N16: =IFERROR(L16/(1+M16),"") -> 2.0909091 | O16: =IFERROR(J16/N16,"") -> 0.094780213 | P16: =IFERROR(1-O16,"") -> 0.90521979 | Q16: =IFERROR(N16-K16,"") -> 1.4442845 | R16: =IFERROR(I16/K16,"") -> 0.69352108 | S16: =IFERROR(E16/D16,"") -> 1.5
A17: PI6 | B17: Entremet individual | C17: Pastelería individual | D17: ='Escandallo por Tanda'!D247 -> 16 | E17: 95 | F17: =IFERROR(E17/60,"") -> 1.5833333 | G17: ='Parámetros'!$B$16 -> 17.937911 | H17: =IFERROR(F17*G17,"") -> 28.401693 | I17: =IFERROR(H17/D17,"") -> 1.7751058 | J17: ='Escandallo por Tanda'!G247 -> 0.82474126 | K17: =IFERROR(I17+J17,"") -> 2.5998471 | L17: 4.5 | M17: 0.1 | N17: =IFERROR(L17/(1+M17),"") -> 4.0909091 | O17: =IFERROR(J17/N17,"") -> 0.20160342 | P17: =IFERROR(1-O17,"") -> 0.79839658 | Q17: =IFERROR(N17-K17,"") -> 1.491062 | R17: =IFERROR(I17/K17,"") -> 0.68277316 | S17: =IFERROR(E17/D17,"") -> 5.9375
... A35: TP8 | B35: Mona de Pascua | C35: Temporada | D35: ='Escandallo por Tanda'!D265 -> 14 | E35: 80 | F35: =IFERROR(E35/60,"") -> 1.3333333 | G35: ='Parámetros'!$B$16 -> 17.937911 | H35: =IFERROR(F35*G35,"") -> 23.917215 | I35: =IFERROR(H35/D35,"") -> 1.7083725 | J35: ='Escandallo por Tanda'!G265 -> 2.0148755 | K35: =IFERROR(I35+J35,"") -> 3.723248 | L35: 13.5 | M35: 0.1 | N35: =IFERROR(L35/(1+M35),"") -> 12.272727 | O35: =IFERROR(J35/N35,"") -> 0.16417504 | P35: =IFERROR(1-O35,"") -> 0.83582496 | Q35: =IFERROR(N35-K35,"") -> 8.5494793 | R35: =IFERROR(I35/K35,"") -> 0.4588393 | S35: =IFERROR(E35/D35,"") -> 5.7142857
A36: MEDIA / TOTAL | H36: =SUM(H6:H35) -> 542.62182 | O36: =IFERROR(AVERAGE(O6:O35),"") -> 0.19140911 | Q36: =IFERROR(AVERAGE(Q6:Q35),"") -> 1.7494637 | R36: =IFERROR(AVERAGE(R6:R35),"") -> 0.63296267
A38: El food cost de esta hoja compara MATERIA con PVP sin IVA, que es la definición del sector. La mano de obra no entra en el food cost: entra en el coste total y se le come el margen. Por eso una referencia puede tener un food cost estupendo y dejarte menos dinero que otra peor: mira siempre las dos columnas juntas.
A39: El margen bruto de la columna P es uno menos el food cost, calculado, no tecleado. Es la misma regla dicha del revés, y por eso el libro no te pide los dos números en ningún sitio.
A40: La columna R es la que duele: en las referencias de más trabajo la mano de obra es más de la mitad del coste. Ahí no se gana bajando el precio de la harina, se gana cambiando el proceso o el precio.
A41: Las celdas en rojo del food cost son las que se pasan de tu objetivo de «Parámetros»; las del margen, las que no dejan dinero. Lo que hacer con ellas está en la hoja «Decisión de Surtido».
A43: Versión 1.0 · septiembre 2026 · aichef.pro/guia-pasteleria-obrador · info@aichef.pro

Sheet Decisión de Huevo y Temperatura
A1: Decisión de Huevo y Temperatura
A2: AI Chef Pro · aichef.pro — Cómo Montar una Pastelería
A3: Dos salidas separadas, cada una con su artículo: la TEMPERATURA (el más bajo de los techos que apliquen) y el PLAZO legal del art. 9.3. La vida útil la declaras tú.
A5: Ref | B5: Referencia | C5: Familia | D5: Vía legal del huevo | E5: ¿Producto relleno? | F5: ¿Estable a temperatura ambiente? | G5: Techo del art. 4.1 fila 9 (°C) | H5: Techo del art. 9.3 (°C) | I5: Temperatura de conservación (°C) | J5: Cuál manda | K5: Plazo legal (art. 9.3) | L5: Vida útil declarada por ti (días) | M5: Dónde va en el mostrador | N5: Qué dice esa vía | O5: Coherencia D / F
A6: B1 | B6: Croissant de mantequilla | C6: Bollería | D6: estable a ambiente | E6: No | F6: Sí | G6: =IF(AND($E6="Sí",$F6="No"),'Parámetros'!$B$28,"") | H6: =IF(AND(OR($D6="70/2",$D6="ovoproducto"),$F6="No"),'Parámetros'!$B$29,"") | I6: =IF(AND(G6="",H6=""),"",IF(G6="",H6,IF(H6="",G6,MIN(G6,H6)))) | J6: =IF(AND(G6="",H6=""),"Ni la fila 9 del art. 4.1 ni el art. 9.3 le fijan techo: vitrina de ambiente.",IF(AND(G6<>"",H6<>""),"Le aplican los DOS techos y manda el más bajo, el de la fila 9 del art. 4.1. No es un conflicto: son dos topes distintos.",IF(G6<>"","Manda la fila 9 del art. 4.1: producto de pastelería relleno que no es estable a temperatura ambiente.","Manda el art. 9.3: elaborado por la vía del art. 9.1.a) sin ser estable, o con ovoproducto del art. 9.2."))) -> Ni la fila 9 del art. 4.1 ni el art. 9.3 le fijan techo: vitrina de ambiente. | K6: =IF(AND(OR($D6="70/2",$D6="ovoproducto"),$F6="No"),'Parámetros'!$B$30,"No aplica") -> No aplica | L6: Por declarar en tu APPCC | M6: =IF(I6="","Vitrina de ambiente","Vitrina refrigerada") -> Vitrina de ambiente | N6: Vía 1.a) y el producto terminado ES estable a temperatura ambiente: el art. 9.3 no le fija ni temperatura ni plazo, y la fila 9 del art. 4.1 lo exceptúa aunque vaya relleno. | O6: =IF(AND($D6="estable a ambiente",$F6="No"),"Incoherente: has elegido la vía de producto estable y luego has dicho que no lo es","")
A7: B2 | B7: Pain au chocolat | C7: Bollería | D7: estable a ambiente | E7: No | F7: Sí | G7: =IF(AND($E7="Sí",$F7="No"),'Parámetros'!$B$28,"") | H7: =IF(AND(OR($D7="70/2",$D7="ovoproducto"),$F7="No"),'Parámetros'!$B$29,"") | I7: =IF(AND(G7="",H7=""),"",IF(G7="",H7,IF(H7="",G7,MIN(G7,H7)))) | J7: =IF(AND(G7="",H7=""),"Ni la fila 9 del art. 4.1 ni el art. 9.3 le fijan techo: vitrina de ambiente.",IF(AND(G7<>"",H7<>""),"Le aplican los DOS techos y manda el más bajo, el de la fila 9 del art. 4.1. No es un conflicto: son dos topes distintos.",IF(G7<>"","Manda la fila 9 del art. 4.1: producto de pastelería relleno que no es estable a temperatura ambiente.","Manda el art. 9.3: elaborado por la vía del art. 9.1.a) sin ser estable, o con ovoproducto del art. 9.2."))) -> Ni la fila 9 del art. 4.1 ni el art. 9.3 le fijan techo: vitrina de ambiente. | K7: =IF(AND(OR($D7="70/2",$D7="ovoproducto"),$F7="No"),'Parámetros'!$B$30,"No aplica") -> No aplica | L7: Por declarar en tu APPCC | M7: =IF(I7="","Vitrina de ambiente","Vitrina refrigerada") -> Vitrina de ambiente | N7: Vía 1.a) y el producto terminado ES estable a temperatura ambiente: el art. 9.3 no le fija ni temperatura ni plazo, y la fila 9 del art. 4.1 lo exceptúa aunque vaya relleno. | O7: =IF(AND($D7="estable a ambiente",$F7="No"),"Incoherente: has elegido la vía de producto estable y luego has dicho que no lo es","")
A8: B3 | B8: Napolitana de crema | C8: Bollería | D8: 70/2 | E8: Sí | F8: No | G8: =IF(AND($E8="Sí",$F8="No"),'Parámetros'!$B$28,"") -> 4 | H8: =IF(AND(OR($D8="70/2",$D8="ovoproducto"),$F8="No"),'Parámetros'!$B$29,"") -> 8 | I8: =IF(AND(G8="",H8=""),"",IF(G8="",H8,IF(H8="",G8,MIN(G8,H8)))) -> 4 | J8: =IF(AND(G8="",H8=""),"Ni la fila 9 del art. 4.1 ni el art. 9.3 le fijan techo: vitrina de ambiente.",IF(AND(G8<>"",H8<>""),"Le aplican los DOS techos y manda el más bajo, el de la fila 9 del art. 4.1. No es un conflicto: son dos topes distintos.",IF(G8<>"","Manda la fila 9 del art. 4.1: producto de pastelería relleno que no es estable a temperatura ambiente.","Manda el art. 9.3: elaborado por la vía del art. 9.1.a) sin ser estable, o con ovoproducto del art. 9.2."))) -> Le aplican los DOS techos y manda el más bajo, el de la fila 9 del art. 4.1. No es un conflicto: son dos topes distintos. | K8: =IF(AND(OR($D8="70/2",$D8="ovoproducto"),$F8="No"),'Parámetros'!$B$30,"No aplica") -> 24 | L8: Por declarar en tu APPCC | M8: =IF(I8="","Vitrina de ambiente","Vitrina refrigerada") -> Vitrina refrigerada | N8: Tratamiento térmico de 70 °C durante 2 s en el centro del producto, o cualquier combinación equivalente (art. 9.1.a). | O8: =IF(AND($D8="estable a ambiente",$F8="No"),"Incoherente: has elegido la vía de producto estable y luego has dicho que no lo es","")
A9: B4 | B9: Palmera de hojaldre | C9: Bollería | D9: sin huevo | E9: No | F9: Sí | G9: =IF(AND($E9="Sí",$F9="No"),'Parámetros'!$B$28,"") | H9: =IF(AND(OR($D9="70/2",$D9="ovoproducto"),$F9="No"),'Parámetros'!$B$29,"") | I9: =IF(AND(G9="",H9=""),"",IF(G9="",H9,IF(H9="",G9,MIN(G9,H9)))) | J9: =IF(AND(G9="",H9=""),"Ni la fila 9 del art. 4.1 ni el art. 9.3 le fijan techo: vitrina de ambiente.",IF(AND(G9<>"",H9<>""),"Le aplican los DOS techos y manda el más bajo, el de la fila 9 del art. 4.1. No es un conflicto: son dos topes distintos.",IF(G9<>"","Manda la fila 9 del art. 4.1: producto de pastelería relleno que no es estable a temperatura ambiente.","Manda el art. 9.3: elaborado por la vía del art. 9.1.a) sin ser estable, o con ovoproducto del art. 9.2."))) -> Ni la fila 9 del art. 4.1 ni el art. 9.3 le fijan techo: vitrina de ambiente. | K9: =IF(AND(OR($D9="70/2",$D9="ovoproducto"),$F9="No"),'Parámetros'!$B$30,"No aplica") -> No aplica | L9: Por declarar en tu APPCC | M9: =IF(I9="","Vitrina de ambiente","Vitrina refrigerada") -> Vitrina de ambiente | N9: La elaboración no lleva huevo en ninguna forma: el art. 9 no le aplica. | O9: =IF(AND($D9="estable a ambiente",$F9="No"),"Incoherente: has elegido la vía de producto estable y luego has dicho que no lo es","")
A10: B5 | B10: Caracola de pasas | C10: Bollería | D10: 70/2 | E10: Sí | F10: No | G10: =IF(AND($E10="Sí",$F10="No"),'Parámetros'!$B$28,"") -> 4 | H10: =IF(AND(OR($D10="70/2",$D10="ovoproducto"),$F10="No"),'Parámetros'!$B$29,"") -> 8 | I10: =IF(AND(G10="",H10=""),"",IF(G10="",H10,IF(H10="",G10,MIN(G10,H10)))) -> 4 | J10: =IF(AND(G10="",H10=""),"Ni la fila 9 del art. 4.1 ni el art. 9.3 le fijan techo: vitrina de ambiente.",IF(AND(G10<>"",H10<>""),"Le aplican los DOS techos y manda el más bajo, el de la fila 9 del art. 4.1. No es un conflicto: son dos topes distintos.",IF(G10<>"","Manda la fila 9 del art. 4.1: producto de pastelería relleno que no es estable a temperatura ambiente.","Manda el art. 9.3: elaborado por la vía del art. 9.1.a) sin ser estable, o con ovoproducto del art. 9.2."))) -> Le aplican los DOS techos y manda el más bajo, el de la fila 9 del art. 4.1. No es un conflicto: son dos topes distintos. | K10: =IF(AND(OR($D10="70/2",$D10="ovoproducto"),$F10="No"),'Parámetros'!$B$30,"No aplica") -> 24 | L10: Por declarar en tu APPCC | M10: =IF(I10="","Vitrina de ambiente","Vitrina refrigerada") -> Vitrina refrigerada | N10: Tratamiento térmico de 70 °C durante 2 s en el centro del producto, o cualquier combinación equivalente (art. 9.1.a). | O10: =IF(AND($D10="estable a ambiente",$F10="No"),"Incoherente: has elegido la vía de producto estable y luego has dicho que no lo es","")
A11: B6 | B11: Ensaimada | C11: Bollería | D11: estable a ambiente | E11: No | F11: Sí | G11: =IF(AND($E11="Sí",$F11="No"),'Parámetros'!$B$28,"") | H11: =IF(AND(OR($D11="70/2",$D11="ovoproducto"),$F11="No"),'Parámetros'!$B$29,"") | I11: =IF(AND(G11="",H11=""),"",IF(G11="",H11,IF(H11="",G11,MIN(G11,H11)))) | J11: =IF(AND(G11="",H11=""),"Ni la fila 9 del art. 4.1 ni el art. 9.3 le fijan techo: vitrina de ambiente.",IF(AND(G11<>"",H11<>""),"Le aplican los DOS techos y manda el más bajo, el de la fila 9 del art. 4.1. No es un conflicto: son dos topes distintos.",IF(G11<>"","Manda la fila 9 del art. 4.1: producto de pastelería relleno que no es estable a temperatura ambiente.","Manda el art. 9.3: elaborado por la vía del art. 9.1.a) sin ser estable, o con ovoproducto del art. 9.2."))) -> Ni la fila 9 del art. 4.1 ni el art. 9.3 le fijan techo: vitrina de ambiente. | K11: =IF(AND(OR($D11="70/2",$D11="ovoproducto"),$F11="No"),'Parámetros'!$B$30,"No aplica") -> No aplica | L11: Por declarar en tu APPCC | M11: =IF(I11="","Vitrina de ambiente","Vitrina refrigerada") -> Vitrina de ambiente | N11: Vía 1.a) y el producto terminado ES estable a temperatura ambiente: el art. 9.3 no le fija ni temperatura ni plazo, y la fila 9 del art. 4.1 lo exceptúa aunque vaya relleno. | O11: =IF(AND($D11="estable a ambiente",$F11="No"),"Incoherente: has elegido la vía de producto estable y luego has dicho que no lo es","")
A12: PI1 | B12: Milhojas | C12: Pastelería individual | D12: 70/2 | E12: Sí | F12: No | G12: =IF(AND($E12="Sí",$F12="No"),'Parámetros'!$B$28,"") -> 4 | H12: =IF(AND(OR($D12="70/2",$D12="ovoproducto"),$F12="No"),'Parámetros'!$B$29,"") -> 8 | I12: =IF(AND(G12="",H12=""),"",IF(G12="",H12,IF(H12="",G12,MIN(G12,H12)))) -> 4 | J12: =IF(AND(G12="",H12=""),"Ni la fila 9 del art. 4.1 ni el art. 9.3 le fijan techo: vitrina de ambiente.",IF(AND(G12<>"",H12<>""),"Le aplican los DOS techos y manda el más bajo, el de la fila 9 del art. 4.1. No es un conflicto: son dos topes distintos.",IF(G12<>"","Manda la fila 9 del art. 4.1: producto de pastelería relleno que no es estable a temperatura ambiente.","Manda el art. 9.3: elaborado por la vía del art. 9.1.a) sin ser estable, o con ovoproducto del art. 9.2."))) -> Le aplican los DOS techos y manda el más bajo, el de la fila 9 del art. 4.1. No es un conflicto: son dos topes distintos. | K12: =IF(AND(OR($D12="70/2",$D12="ovoproducto"),$F12="No"),'Parámetros'!$B$30,"No aplica") -> 24 | L12: Por declarar en tu APPCC | M12: =IF(I12="","Vitrina de ambiente","Vitrina refrigerada") -> Vitrina refrigerada | N12: Tratamiento térmico de 70 °C durante 2 s en el centro del producto, o cualquier combinación equivalente (art. 9.1.a). | O12: =IF(AND($D12="estable a ambiente",$F12="No"),"Incoherente: has elegido la vía de producto estable y luego has dicho que no lo es","")
A13: PI2 | B13: Éclair | C13: Pastelería individual | D13: 70/2 | E13: Sí | F13: No | G13: =IF(AND($E13="Sí",$F13="No"),'Parámetros'!$B$28,"") -> 4 | H13: =IF(AND(OR($D13="70/2",$D13="ovoproducto"),$F13="No"),'Parámetros'!$B$29,"") -> 8 | I13: =IF(AND(G13="",H13=""),"",IF(G13="",H13,IF(H13="",G13,MIN(G13,H13)))) -> 4 | J13: =IF(AND(G13="",H13=""),"Ni la fila 9 del art. 4.1 ni el art. 9.3 le fijan techo: vitrina de ambiente.",IF(AND(G13<>"",H13<>""),"Le aplican los DOS techos y manda el más bajo, el de la fila 9 del art. 4.1. No es un conflicto: son dos topes distintos.",IF(G13<>"","Manda la fila 9 del art. 4.1: producto de pastelería relleno que no es estable a temperatura ambiente.","Manda el art. 9.3: elaborado por la vía del art. 9.1.a) sin ser estable, o con ovoproducto del art. 9.2."))) -> Le aplican los DOS techos y manda el más bajo, el de la fila 9 del art. 4.1. No es un conflicto: son dos topes distintos. | K13: =IF(AND(OR($D13="70/2",$D13="ovoproducto"),$F13="No"),'Parámetros'!$B$30,"No aplica") -> 24 | L13: Por declarar en tu APPCC | M13: =IF(I13="","Vitrina de ambiente","Vitrina refrigerada") -> Vitrina refrigerada | N13: Tratamiento térmico de 70 °C durante 2 s en el centro del producto, o cualquier combinación equivalente (art. 9.1.a). | O13: =IF(AND($D13="estable a ambiente",$F13="No"),"Incoherente: has elegido la vía de producto estable y luego has dicho que no lo es","")
A14: PI3 | B14: Macarons de frambuesa | C14: Pastelería individual | D14: 70/2 | E14: Sí | F14: No | G14: =IF(AND($E14="Sí",$F14="No"),'Parámetros'!$B$28,"") -> 4 | H14: =IF(AND(OR($D14="70/2",$D14="ovoproducto"),$F14="No"),'Parámetros'!$B$29,"") -> 8 | I14: =IF(AND(G14="",H14=""),"",IF(G14="",H14,IF(H14="",G14,MIN(G14,H14)))) -> 4 | J14: =IF(AND(G14="",H14=""),"Ni la fila 9 del art. 4.1 ni el art. 9.3 le fijan techo: vitrina de ambiente.",IF(AND(G14<>"",H14<>""),"Le aplican los DOS techos y manda el más bajo, el de la fila 9 del art. 4.1. No es un conflicto: son dos topes distintos.",IF(G14<>"","Manda la fila 9 del art. 4.1: producto de pastelería relleno que no es estable a temperatura ambiente.","Manda el art. 9.3: elaborado por la vía del art. 9.1.a) sin ser estable, o con ovoproducto del art. 9.2."))) -> Le aplican los DOS techos y manda el más bajo, el de la fila 9 del art. 4.1. No es un conflicto: son dos topes distintos. | K14: =IF(AND(OR($D14="70/2",$D14="ovoproducto"),$F14="No"),'Parámetros'!$B$30,"No aplica") -> 24 | L14: Por declarar en tu APPCC | M14: =IF(I14="","Vitrina de ambiente","Vitrina refrigerada") -> Vitrina refrigerada | N14: Tratamiento térmico de 70 °C durante 2 s en el centro del producto, o cualquier combinación equivalente (art. 9.1.a). | O14: =IF(AND($D14="estable a ambiente",$F14="No"),"Incoherente: has elegido la vía de producto estable y luego has dicho que no lo es","")
A15: PI4 | B15: Tartaleta de frutas | C15: Pastelería individual | D15: 70/2 | E15: Sí | F15: No | G15: =IF(AND($E15="Sí",$F15="No"),'Parámetros'!$B$28,"") -> 4 | H15: =IF(AND(OR($D15="70/2",$D15="ovoproducto"),$F15="No"),'Parámetros'!$B$29,"") -> 8 | I15: =IF(AND(G15="",H15=""),"",IF(G15="",H15,IF(H15="",G15,MIN(G15,H15)))) -> 4 | J15: =IF(AND(G15="",H15=""),"Ni la fila 9 del art. 4.1 ni el art. 9.3 le fijan techo: vitrina de ambiente.",IF(AND(G15<>"",H15<>""),"Le aplican los DOS techos y manda el más bajo, el de la fila 9 del art. 4.1. No es un conflicto: son dos topes distintos.",IF(G15<>"","Manda la fila 9 del art. 4.1: producto de pastelería relleno que no es estable a temperatura ambiente.","Manda el art. 9.3: elaborado por la vía del art. 9.1.a) sin ser estable, o con ovoproducto del art. 9.2."))) -> Le aplican los DOS techos y manda el más bajo, el de la fila 9 del art. 4.1. No es un conflicto: son dos topes distintos. | K15: =IF(AND(OR($D15="70/2",$D15="ovoproducto"),$F15="No"),'Parámetros'!$B$30,"No aplica") -> 24 | L15: Por declarar en tu APPCC | M15: =IF(I15="","Vitrina de ambiente","Vitrina refrigerada") -> Vitrina refrigerada | N15: Tratamiento térmico de 70 °C durante 2 s en el centro del producto, o cualquier combinación equivalente (art. 9.1.a). | O15: =IF(AND($D15="estable a ambiente",$F15="No"),"Incoherente: has elegido la vía de producto estable y luego has dicho que no lo es","")
A16: PI5 | B16: Lionesa o profiterol | C16: Pastelería individual | D16: 70/2 | E16: Sí | F16: No | G16: =IF(AND($E16="Sí",$F16="No"),'Parámetros'!$B$28,"") -> 4 | H16: =IF(AND(OR($D16="70/2",$D16="ovoproducto"),$F16="No"),'Parámetros'!$B$29,"") -> 8 | I16: =IF(AND(G16="",H16=""),"",IF(G16="",H16,IF(H16="",G16,MIN(G16,H16)))) -> 4 | J16: =IF(AND(G16="",H16=""),"Ni la fila 9 del art. 4.1 ni el art. 9.3 le fijan techo: vitrina de ambiente.",IF(AND(G16<>"",H16<>""),"Le aplican los DOS techos y manda el más bajo, el de la fila 9 del art. 4.1. No es un conflicto: son dos topes distintos.",IF(G16<>"","Manda la fila 9 del art. 4.1: producto de pastelería relleno que no es estable a temperatura ambiente.","Manda el art. 9.3: elaborado por la vía del art. 9.1.a) sin ser estable, o con ovoproducto del art. 9.2."))) -> Le aplican los DOS techos y manda el más bajo, el de la fila 9 del art. 4.1. No es un conflicto: son dos topes distintos. | K16: =IF(AND(OR($D16="70/2",$D16="ovoproducto"),$F16="No"),'Parámetros'!$B$30,"No aplica") -> 24 | L16: Por declarar en tu APPCC | M16: =IF(I16="","Vitrina de ambiente","Vitrina refrigerada") -> Vitrina refrigerada | N16: Tratamiento térmico de 70 °C durante 2 s en el centro del producto, o cualquier combinación equivalente (art. 9.1.a). | O16: =IF(AND($D16="estable a ambiente",$F16="No"),"Incoherente: has elegido la vía de producto estable y luego has dicho que no lo es","")
A17: PI6 | B17: Entremet individual | C17: Pastelería individual | D17: ovoproducto | E17: Sí | F17: No | G17: =IF(AND($E17="Sí",$F17="No"),'Parámetros'!$B$28,"") -> 4 | H17: =IF(AND(OR($D17="70/2",$D17="ovoproducto"),$F17="No"),'Parámetros'!$B$29,"") -> 8 | I17: =IF(AND(G17="",H17=""),"",IF(G17="",H17,IF(H17="",G17,MIN(G17,H17)))) -> 4 | J17: =IF(AND(G17="",H17=""),"Ni la fila 9 del art. 4.1 ni el art. 9.3 le fijan techo: vitrina de ambiente.",IF(AND(G17<>"",H17<>""),"Le aplican los DOS techos y manda el más bajo, el de la fila 9 del art. 4.1. No es un conflicto: son dos topes distintos.",IF(G17<>"","Manda la fila 9 del art. 4.1: producto de pastelería relleno que no es estable a temperatura ambiente.","Manda el art. 9.3: elaborado por la vía del art. 9.1.a) sin ser estable, o con ovoproducto del art. 9.2."))) -> Le aplican los DOS techos y manda el más bajo, el de la fila 9 del art. 4.1. No es un conflicto: son dos topes distintos. | K17: =IF(AND(OR($D17="70/2",$D17="ovoproducto"),$F17="No"),'Parámetros'!$B$30,"No aplica") -> 24 | L17: Por declarar en tu APPCC | M17: =IF(I17="","Vitrina de ambiente","Vitrina refrigerada") -> Vitrina refrigerada | N17: El producto se consume sin un tratamiento térmico que cumpla el apartado 1, así que el huevo crudo se sustituye por ovoproducto de establecimiento autorizado (art. 9.2). | O17: =IF(AND($D17="estable a ambiente",$F17="No"),"Incoherente: has elegido la vía de producto estable y luego has dicho que no lo es","")
... A35: TP8 | B35: Mona de Pascua | C35: Temporada | D35: estable a ambiente | E35: No | F35: Sí | G35: =IF(AND($E35="Sí",$F35="No"),'Parámetros'!$B$28,"") | H35: =IF(AND(OR($D35="70/2",$D35="ovoproducto"),$F35="No"),'Parámetros'!$B$29,"") | I35: =IF(AND(G35="",H35=""),"",IF(G35="",H35,IF(H35="",G35,MIN(G35,H35)))) | J35: =IF(AND(G35="",H35=""),"Ni la fila 9 del art. 4.1 ni el art. 9.3 le fijan techo: vitrina de ambiente.",IF(AND(G35<>"",H35<>""),"Le aplican los DOS techos y manda el más bajo, el de la fila 9 del art. 4.1. No es un conflicto: son dos topes distintos.",IF(G35<>"","Manda la fila 9 del art. 4.1: producto de pastelería relleno que no es estable a temperatura ambiente.","Manda el art. 9.3: elaborado por la vía del art. 9.1.a) sin ser estable, o con ovoproducto del art. 9.2."))) -> Ni la fila 9 del art. 4.1 ni el art. 9.3 le fijan techo: vitrina de ambiente. | K35: =IF(AND(OR($D35="70/2",$D35="ovoproducto"),$F35="No"),'Parámetros'!$B$30,"No aplica") -> No aplica | L35: Por declarar en tu APPCC | M35: =IF(I35="","Vitrina de ambiente","Vitrina refrigerada") -> Vitrina de ambiente | N35: Vía 1.a) y el producto terminado ES estable a temperatura ambiente: el art. 9.3 no le fija ni temperatura ni plazo, y la fila 9 del art. 4.1 lo exceptúa aunque vaya relleno. | O35: =IF(AND($D35="estable a ambiente",$F35="No"),"Incoherente: has elegido la vía de producto estable y luego has dicho que no lo es","")
A37: Lo que sale de esta hoja
B38: Referencias que necesitan vitrina REFRIGERADA | G38: =COUNTIF(M6:M35,"Vitrina refrigerada") -> 15 | J38: Cuántos metros de vitrina refrigerada tienes que comprar lo decide esta cuenta, no el gusto.
B39: Referencias que van en vitrina de AMBIENTE | G39: =COUNTIF(M6:M35,"Vitrina de ambiente") -> 15 | J39: Palmeras, Sacher, huesos de santo, turrón y panes. Son las que se pueden adelantar y las que aguantan el pico.
B40: Referencias con el techo de la fila 9 del art. 4.1 | G40: =SUMPRODUCT(--(G6:G35<>"")) -> 13 | J40: Producto relleno que no es estable a temperatura ambiente.
B41: Referencias con el techo del art. 9.3 | G41: =SUMPRODUCT(--(H6:H35<>"")) -> 15 | J41: Vía del art. 9.1.a) sin ser estable, u ovoproducto del art. 9.2.
B42: Referencias a las que aplican LOS DOS techos | G42: =SUMPRODUCT(--(G6:G35<>""),--(H6:H35<>"")) -> 13 | J42: Aquí manda el más bajo. Es el caso que la SERP vende como «conflicto sin resolver» y no lo es.
B43: Referencias con plazo legal de 24 horas | G43: =SUMPRODUCT(--(K6:K35<>"No aplica")) -> 15 | J43: Con registro de fecha y hora de elaboración. Es la obligación del art. 9.3 que casi nadie cuenta.
B44: Referencias que no llevan huevo en ninguna forma | G44: =COUNTIF(D6:D35,"sin huevo") -> 6 | J44: El art. 9 no les aplica.
B45: Referencias por la vía 63/20 con consumo inmediato | G45: =COUNTIF(D6:D35,"63/20") -> 0 | J45: Debería salir cero: la vía del art. 9.1.b) es la de los huevos fritos y las tortillas, no la de la pastelería. Está en la lista para que sepas que existe y que NO es tuya.
A49: Listas de los desplegables (no se tocan)
A50: 70/2 | B50: Tratamiento térmico de 70 °C durante 2 s en el centro del producto, o cualquier combinación equivalente (art. 9.1.a). | D50: Sí
A51: 63/20 | B51: 63 °C durante 20 s en el centro Y servido para consumo inmediato (art. 9.1.b): huevos fritos, tortillas. No es una vía de pastelería. | D51: No
A52: ovoproducto | B52: El producto se consume sin un tratamiento térmico que cumpla el apartado 1, así que el huevo crudo se sustituye por ovoproducto de establecimiento autorizado (art. 9.2).
A53: sin huevo | B53: La elaboración no lleva huevo en ninguna forma: el art. 9 no le aplica.
A54: estable a ambiente | B54: Vía 1.a) y el producto terminado ES estable a temperatura ambiente: el art. 9.3 no le fija ni temperatura ni plazo, y la fila 9 del art. 4.1 lo exceptúa aunque vaya relleno.
A57: CÓMO SE LEE ESTA HOJA. Eliges la vía legal del huevo, dices si la pieza va rellena y si el producto TERMINADO es estable a temperatura ambiente. Con eso el libro te devuelve la temperatura a la que tienes que conservarla, cuál de los dos artículos manda y si te aplica el plazo de 24 horas. Nada más, y nada menos.
A58: LA VIDA ÚTIL ES TUYA. La columna L viene con el texto «Por declarar en tu APPCC» a propósito: el RD 1021/2022 NO establece vidas útiles y este libro no se las va a inventar para tus 30 referencias. La fijas tú, con tu proceso y tus analíticas, y tiene que constar en tu plan de APPCC. El plazo del art. 9.3 de la columna K es otra cosa: es legal, es de 24 horas y sólo alcanza a lo que dice el artículo.
A59: LO QUE ESTA HOJA CAMBIA EN TU DINERO. Cada referencia que sale «Vitrina refrigerada» son metros de mueble frigorífico que hay que comprar, y cada una con plazo de 24 horas es producto que no se puede adelantar: hay que hacerlo el mismo día, también el 5 de enero. Por eso esta hoja se lee ANTES de cerrar la carta y ANTES de comprar la vitrina.
A60: DÓNDE NO ESTÁ LO DEMÁS. Los alérgenos de vitrina son el «12-control-alergenos-vitrina.xlsx» del Kit de Tareas Pastelería y el «08» del Pack APPCC; el registro diario de temperaturas y de vidas útiles es el «13-registro-temperaturas-recepcion.xlsx» del mismo kit. Este libro no los rehace: hace la decisión previa, que no está en ningún fichero del catálogo.
A61: LA NORMA DEROGADA QUE SIGUE VIVA EN INTERNET. Casi todo lo que vas a leer sobre «huevo a 8 °C y 24 horas» cita el RD 1254/1991, derogado el 22 de diciembre de 2022. Y en producto relleno no estable no mandan los 8 °C: mandan los 4 °C de la fila 9 del art. 4.1. Cada celda con dato legal de esta hoja lleva su nota con la norma, el artículo y el enlace al BOE, verificados el 10-09-2026.
A62: ALCANCE LEGAL DE ESTA HOJA: QUÉ NO RESUELVE Y POR QUÉ. La congelación (PA-13, art. 5) es del PROCESO, no de la vitrina: va en el APPCC y en el «13-registro-temperaturas-recepcion.xlsx» del Kit de Tareas, no aquí. Los 14 alérgenos (PA-21) tienen su propia matriz dedicada, el «12-control-alergenos-vitrina.xlsx»: repetirlos en esta tabla sería mantener el mismo dato en dos sitios y que se desincronicen. El RD 496/2010 de calidad (PA-24) fija denominaciones y composición, no temperaturas ni plazos: no cambia ni una celda de esta hoja. Y el RD 308/2019 del pan (PA-25) sólo aplica si tu carta incluye pan de verdad, cosa que decides en el libro 6, no aquí.
A64: Versión 1.0 · septiembre 2026 · aichef.pro/guia-pasteleria-obrador · info@aichef.pro

Sheet Mix y Ticket Medio
A1: Mix y Ticket Medio
A2: AI Chef Pro · aichef.pro — Cómo Montar una Pastelería
A3: No existe un ticket medio publicado de pastelería. El tuyo se calcula desde tu carta y tu mix.
A5: Ref | B5: Referencia | C5: Familia | D5: Mix (% de las unidades) | E5: PVP con IVA (€) | F5: PVP sin IVA (€) | G5: Aporte al PVP medio con IVA (€) | H5: Aporte al ticket medio (€) | I5: Ingresos relativos sin IVA | J5: Materia relativa | K5: Margen relativo | L5: Food cost de la referencia | M5: Qué aporta esta referencia
A6: B1 | B6: Croissant de mantequilla | C6: Bollería | D6: 12 | E6: ='Coste Hora y Mano de Obra'!L6 -> 1.6 | F6: ='Coste Hora y Mano de Obra'!N6 -> 1.4545455 | G6: =IFERROR(E6*D6/100,"") -> 0.192 | H6: =IFERROR(G6*'Parámetros'!$B$36,"") -> 0.4992 | I6: =IFERROR(F6*D6/100,"") -> 0.17454545 | J6: =IFERROR('Escandallo por Tanda'!G236*D6/100,"") -> 0.02830021 | K6: =IFERROR('Coste Hora y Mano de Obra'!Q6*D6/100,"") -> 0.047586732 | L6: ='Coste Hora y Mano de Obra'!O6 -> 0.16213662
A7: B2 | B7: Pain au chocolat | C7: Bollería | D7: 8 | E7: ='Coste Hora y Mano de Obra'!L7 -> 1.85 | F7: ='Coste Hora y Mano de Obra'!N7 -> 1.6818182 | G7: =IFERROR(E7*D7/100,"") -> 0.148 | H7: =IFERROR(G7*'Parámetros'!$B$36,"") -> 0.3848 | I7: =IFERROR(F7*D7/100,"") -> 0.13454545 | J7: =IFERROR('Escandallo por Tanda'!G237*D7/100,"") -> 0.033560684 | K7: =IFERROR('Coste Hora y Mano de Obra'!Q7*D7/100,"") -> 0.035212429 | L7: ='Coste Hora y Mano de Obra'!O7 -> 0.24943752
A8: B3 | B8: Napolitana de crema | C8: Bollería | D8: 7 | E8: ='Coste Hora y Mano de Obra'!L8 -> 1.85 | F8: ='Coste Hora y Mano de Obra'!N8 -> 1.6818182 | G8: =IFERROR(E8*D8/100,"") -> 0.1295 | H8: =IFERROR(G8*'Parámetros'!$B$36,"") -> 0.3367 | I8: =IFERROR(F8*D8/100,"") -> 0.11772727 | J8: =IFERROR('Escandallo por Tanda'!G238*D8/100,"") -> 0.024684599 | K8: =IFERROR('Coste Hora y Mano de Obra'!Q8*D8/100,"") -> 0.025028094 | L8: ='Coste Hora y Mano de Obra'!O8 -> 0.20967613
A9: B4 | B9: Palmera de hojaldre | C9: Bollería | D9: 4.5 | E9: ='Coste Hora y Mano de Obra'!L9 -> 1.7 | F9: ='Coste Hora y Mano de Obra'!N9 -> 1.5454545 | G9: =IFERROR(E9*D9/100,"") -> 0.0765 | H9: =IFERROR(G9*'Parámetros'!$B$36,"") -> 0.1989 | I9: =IFERROR(F9*D9/100,"") -> 0.069545455 | J9: =IFERROR('Escandallo por Tanda'!G239*D9/100,"") -> 0.0098761782 | K9: =IFERROR('Coste Hora y Mano de Obra'!Q9*D9/100,"") -> 0.037246887 | L9: ='Coste Hora y Mano de Obra'!O9 -> 0.14201041
A10: B5 | B10: Caracola de pasas | C10: Bollería | D10: 3.5 | E10: ='Coste Hora y Mano de Obra'!L10 -> 1.85 | F10: ='Coste Hora y Mano de Obra'!N10 -> 1.6818182 | G10: =IFERROR(E10*D10/100,"") -> 0.06475 | H10: =IFERROR(G10*'Parámetros'!$B$36,"") -> 0.16835 | I10: =IFERROR(F10*D10/100,"") -> 0.058863636 | J10: =IFERROR('Escandallo por Tanda'!G240*D10/100,"") -> 0.010718659 | K10: =IFERROR('Coste Hora y Mano de Obra'!Q10*D10/100,"") -> 0.016753633 | L10: ='Coste Hora y Mano de Obra'!O10 -> 0.18209304
A11: B6 | B11: Ensaimada | C11: Bollería | D11: 3 | E11: ='Coste Hora y Mano de Obra'!L11 -> 1.95 | F11: ='Coste Hora y Mano de Obra'!N11 -> 1.7727273 | G11: =IFERROR(E11*D11/100,"") -> 0.0585 | H11: =IFERROR(G11*'Parámetros'!$B$36,"") -> 0.1521 | I11: =IFERROR(F11*D11/100,"") -> 0.053181818 | J11: =IFERROR('Escandallo por Tanda'!G241*D11/100,"") -> 0.0054070285 | K11: =IFERROR('Coste Hora y Mano de Obra'!Q11*D11/100,"") -> 0.0085356088 | L11: ='Coste Hora y Mano de Obra'!O11 -> 0.10167062
A12: PI1 | B12: Milhojas | C12: Pastelería individual | D12: 4 | E12: ='Coste Hora y Mano de Obra'!L12 -> 3.6 | F12: ='Coste Hora y Mano de Obra'!N12 -> 3.2727273 | G12: =IFERROR(E12*D12/100,"") -> 0.144 | H12: =IFERROR(G12*'Parámetros'!$B$36,"") -> 0.3744 | I12: =IFERROR(F12*D12/100,"") -> 0.13090909 | J12: =IFERROR('Escandallo por Tanda'!G242*D12/100,"") -> 0.017877676 | K12: =IFERROR('Coste Hora y Mano de Obra'!Q12*D12/100,"") -> 0.063203883 | L12: ='Coste Hora y Mano de Obra'!O12 -> 0.13656558
A13: PI2 | B13: Éclair | C13: Pastelería individual | D13: 3.5 | E13: ='Coste Hora y Mano de Obra'!L13 -> 3.2 | F13: ='Coste Hora y Mano de Obra'!N13 -> 2.9090909 | G13: =IFERROR(E13*D13/100,"") -> 0.112 | H13: =IFERROR(G13*'Parámetros'!$B$36,"") -> 0.2912 | I13: =IFERROR(F13*D13/100,"") -> 0.10181818 | J13: =IFERROR('Escandallo por Tanda'!G243*D13/100,"") -> 0.011838951 | K13: =IFERROR('Coste Hora y Mano de Obra'!Q13*D13/100,"") -> 0.061639823 | L13: ='Coste Hora y Mano de Obra'!O13 -> 0.11627541
A14: PI3 | B14: Macarons de frambuesa | C14: Pastelería individual | D14: 7 | E14: ='Coste Hora y Mano de Obra'!L14 -> 2.1 | F14: ='Coste Hora y Mano de Obra'!N14 -> 1.9090909 | G14: =IFERROR(E14*D14/100,"") -> 0.147 | H14: =IFERROR(G14*'Parámetros'!$B$36,"") -> 0.3822 | I14: =IFERROR(F14*D14/100,"") -> 0.13363636 | J14: =IFERROR('Escandallo por Tanda'!G244*D14/100,"") -> 0.013755697 | K14: =IFERROR('Coste Hora y Mano de Obra'!Q14*D14/100,"") -> 0.064073831 | L14: ='Coste Hora y Mano de Obra'!O14 -> 0.10293379
A15: PI4 | B15: Tartaleta de frutas | C15: Pastelería individual | D15: 3 | E15: ='Coste Hora y Mano de Obra'!L15 -> 3.8 | F15: ='Coste Hora y Mano de Obra'!N15 -> 3.4545455 | G15: =IFERROR(E15*D15/100,"") -> 0.114 | H15: =IFERROR(G15*'Parámetros'!$B$36,"") -> 0.2964 | I15: =IFERROR(F15*D15/100,"") -> 0.10363636 | J15: =IFERROR('Escandallo por Tanda'!G245*D15/100,"") -> 0.015749581 | K15: =IFERROR('Coste Hora y Mano de Obra'!Q15*D15/100,"") -> 0.049768721 | L15: ='Coste Hora y Mano de Obra'!O15 -> 0.15196964
A16: PI5 | B16: Lionesa o profiterol | C16: Pastelería individual | D16: 3 | E16: ='Coste Hora y Mano de Obra'!L16 -> 2.3 | F16: ='Coste Hora y Mano de Obra'!N16 -> 2.0909091 | G16: =IFERROR(E16*D16/100,"") -> 0.069 | H16: =IFERROR(G16*'Parámetros'!$B$36,"") -> 0.1794 | I16: =IFERROR(F16*D16/100,"") -> 0.062727273 | J16: =IFERROR('Escandallo por Tanda'!G246*D16/100,"") -> 0.0059453042 | K16: =IFERROR('Coste Hora y Mano de Obra'!Q16*D16/100,"") -> 0.043328535 | L16: ='Coste Hora y Mano de Obra'!O16 -> 0.094780213
A17: PI6 | B17: Entremet individual | C17: Pastelería individual | D17: 1.5 | E17: ='Coste Hora y Mano de Obra'!L17 -> 4.5 | F17: ='Coste Hora y Mano de Obra'!N17 -> 4.0909091 | G17: =IFERROR(E17*D17/100,"") -> 0.0675 | H17: =IFERROR(G17*'Parámetros'!$B$36,"") -> 0.1755 | I17: =IFERROR(F17*D17/100,"") -> 0.061363636 | J17: =IFERROR('Escandallo por Tanda'!G247*D17/100,"") -> 0.012371119 | K17: =IFERROR('Coste Hora y Mano de Obra'!Q17*D17/100,"") -> 0.02236593 | L17: ='Coste Hora y Mano de Obra'!O17 -> 0.20160342
... A35: TP8 | B35: Mona de Pascua | C35: Temporada | D35: 0.7 | E35: ='Coste Hora y Mano de Obra'!L35 -> 13.5 | F35: ='Coste Hora y Mano de Obra'!N35 -> 12.272727 | G35: =IFERROR(E35*D35/100,"") -> 0.0945 | H35: =IFERROR(G35*'Parámetros'!$B$36,"") -> 0.2457 | I35: =IFERROR(F35*D35/100,"") -> 0.085909091 | J35: =IFERROR('Escandallo por Tanda'!G265*D35/100,"") -> 0.014104128 | K35: =IFERROR('Coste Hora y Mano de Obra'!Q35*D35/100,"") -> 0.059846355 | L35: ='Coste Hora y Mano de Obra'!O35 -> 0.16417504
A36: TOTAL DE LA CARTA | D36: =SUM(D6:D35) -> 100 | G36: =SUM(G6:G35) -> 2.4557 | H36: =SUM(H6:H35) -> 6.38482 | I36: =SUM(I6:I35) -> 2.257236 | J36: =SUM(J6:J35) -> 0.39624846 | K36: =SUM(K6:K35) -> 1.0710505 | M36: La suma del mix tiene que dar 100,00. Si no, la celda se pone en rojo: el ticket medio de abajo estaría mintiendo.
A38: El ticket medio de tu pastelería
B39: PVP medio ponderado con IVA | F39: =IFERROR($G$36,"") -> 2.4557 | I39: Suma de los aportes de las 30 referencias, ponderados por el mix de unidades.
B40: Piezas por cliente | F40: ='Parámetros'!$B$36 -> 2.6 | I40: Parámetro de la hoja «Parámetros». Es lo único que se supone: el resto sale de tu carta.
B41: TICKET MEDIO CON IVA | F41: =IFERROR($G$36*'Parámetros'!$B$36,"") -> 6.38482 | I41: PVP medio ponderado por piezas por cliente. No se copia de ningún estudio porque no hay ninguno: éste es el tuyo, y por eso se puede defender delante de un banco.
B42: Ticket medio sin IVA | F42: =IFERROR($I$36*'Parámetros'!$B$36,"") -> 5.8688136 | I42: El que entra en el plan financiero: la cuenta de resultados va sin IVA.
B43: IVA medio de la carta | F43: =IFERROR($G$36/$I$36-1,"") -> 0.087923454 | I43: No es un tipo legal: es el que hace falta para pasar de caja a ventas netas, y existe porque los panes van al 4 % y el resto al 10 %.
B44: Food cost de MATERIA de la carta | F44: =IFERROR($J$36/$I$36,"") -> 0.17554587 | I44: Ponderado por euros vendidos, que es como se pondera de verdad, no por piezas.
B45: Food cost SERVIDO (con merma y packaging) | F45: =IFERROR($J$36/$I$36/(1-'Parámetros'!$B$34)*(1+'Parámetros'!$B$35),"") -> 0.20326364 | I45: El de escandallo más lo que se produce y no se vende, más la caja. Es el que se acerca al de la cuenta de resultados.
B46: Food cost objetivo de la casa | F46: ='Parámetros'!$B$24 -> 0.32 | I46: El de «Parámetros». La regla del sector es 30-35 %.
B47: Margen de contribución medio por pieza (€) | F47: =IFERROR($K$36/$D$36*100,"") -> 1.0710505 | I47: Después de materia Y de mano de obra. Es el euro que queda para pagar alquiler, luz y tu sueldo.
A50: POR QUÉ EL FOOD COST DE LA CARTA Y EL DEL PLAN FINANCIERO NO COINCIDEN. El de escandallo sólo cuenta materia prima de lo que tú fabricas. Al que llega a la cuenta de resultados hay que sumarle cuatro cosas, en este orden de tamaño: el producto de TERCEROS que revende el despacho -bebida, café, helado, bombonería comprada-, que no tiene escandallo propio; la merma real, que en producto fresco se va por encima del objetivo; el packaging; y la subida de la materia prima, que en mantequilla y cacao no es teórica. Por eso el plan financiero se proyecta con la regla del sector y no con tu escandallo: es el supuesto conservador. La diferencia entre los dos números es tu colchón.
A51: EL MIX SE MIDE, NO SE ADIVINA. El del ejemplo es un supuesto. El tuyo lo saca tu TPV en dos clics a los tres meses de abrir, y hasta entonces cualquier ticket medio que calcules es una hipótesis. Dilo así cuando lo lleves al banco.
A53: Versión 1.0 · septiembre 2026 · aichef.pro/guia-pasteleria-obrador · info@aichef.pro

Sheet Decisión de Surtido
A1: Decisión de Surtido
A2: AI Chef Pro · aichef.pro — Cómo Montar una Pastelería
A3: Margen contra rotación: qué mantener, a qué revisarle el precio y qué retirar.
A5: Ref | B5: Referencia | C5: Familia | D5: Food cost | E5: Margen por unidad (€) | F5: Mix (% de las unidades) | G5: Margen ponderado (€) | H5: ¿Food cost dentro del objetivo? | I5: ¿Rotación por encima del umbral? | J5: Veredicto | K5: Por qué
A6: B1 | B6: Croissant de mantequilla | C6: Bollería | D6: ='Coste Hora y Mano de Obra'!O6 -> 0.16213662 | E6: ='Coste Hora y Mano de Obra'!Q6 -> 0.3965561 | F6: ='Mix y Ticket Medio'!D6 -> 12 | G6: =IFERROR(E6*F6/100,"") -> 0.047586732 | H6: =IF(NOT(ISNUMBER(D6)),"",IF(D6<='Parámetros'!$B$24,"Sí","No")) -> Sí | I6: =IF(NOT(ISNUMBER(F6)),"",IF(F6>='Parámetros'!$B$37,"Sí","No")) -> Sí | J6: =IF(OR(H6="",I6=""),"",IF(AND(H6="No",I6="No"),"Retirar",IF(H6="No","Revisar precio","Mantener"))) -> Mantener | K6: =IF(J6="","",IF(J6="Retirar","Se pasa del food cost objetivo Y casi no rota: ocupa vitrina, genera merma y no paga el hueco. Fuera de la carta de apertura.",IF(J6="Revisar precio","Rota bien pero se pasa del food cost objetivo: sube el precio, cambia el gramaje o renegocia el ingrediente que la encarece. Retirarla te quitaría rotación.","Dentro del objetivo y con rotación: es la que sostiene la carta. Vigila que no se te vaya el coste de materia."))) -> Dentro del objetivo y con rotación: es la que sostiene la carta. Vigila que no se te vaya el coste de materia.
A7: B2 | B7: Pain au chocolat | C7: Bollería | D7: ='Coste Hora y Mano de Obra'!O7 -> 0.24943752 | E7: ='Coste Hora y Mano de Obra'!Q7 -> 0.44015536 | F7: ='Mix y Ticket Medio'!D7 -> 8 | G7: =IFERROR(E7*F7/100,"") -> 0.035212429 | H7: =IF(NOT(ISNUMBER(D7)),"",IF(D7<='Parámetros'!$B$24,"Sí","No")) -> Sí | I7: =IF(NOT(ISNUMBER(F7)),"",IF(F7>='Parámetros'!$B$37,"Sí","No")) -> Sí | J7: =IF(OR(H7="",I7=""),"",IF(AND(H7="No",I7="No"),"Retirar",IF(H7="No","Revisar precio","Mantener"))) -> Mantener | K7: =IF(J7="","",IF(J7="Retirar","Se pasa del food cost objetivo Y casi no rota: ocupa vitrina, genera merma y no paga el hueco. Fuera de la carta de apertura.",IF(J7="Revisar precio","Rota bien pero se pasa del food cost objetivo: sube el precio, cambia el gramaje o renegocia el ingrediente que la encarece. Retirarla te quitaría rotación.","Dentro del objetivo y con rotación: es la que sostiene la carta. Vigila que no se te vaya el coste de materia."))) -> Dentro del objetivo y con rotación: es la que sostiene la carta. Vigila que no se te vaya el coste de materia.
A8: B3 | B8: Napolitana de crema | C8: Bollería | D8: ='Coste Hora y Mano de Obra'!O8 -> 0.20967613 | E8: ='Coste Hora y Mano de Obra'!Q8 -> 0.35754419 | F8: ='Mix y Ticket Medio'!D8 -> 7 | G8: =IFERROR(E8*F8/100,"") -> 0.025028094 | H8: =IF(NOT(ISNUMBER(D8)),"",IF(D8<='Parámetros'!$B$24,"Sí","No")) -> Sí | I8: =IF(NOT(ISNUMBER(F8)),"",IF(F8>='Parámetros'!$B$37,"Sí","No")) -> Sí | J8: =IF(OR(H8="",I8=""),"",IF(AND(H8="No",I8="No"),"Retirar",IF(H8="No","Revisar precio","Mantener"))) -> Mantener | K8: =IF(J8="","",IF(J8="Retirar","Se pasa del food cost objetivo Y casi no rota: ocupa vitrina, genera merma y no paga el hueco. Fuera de la carta de apertura.",IF(J8="Revisar precio","Rota bien pero se pasa del food cost objetivo: sube el precio, cambia el gramaje o renegocia el ingrediente que la encarece. Retirarla te quitaría rotación.","Dentro del objetivo y con rotación: es la que sostiene la carta. Vigila que no se te vaya el coste de materia."))) -> Dentro del objetivo y con rotación: es la que sostiene la carta. Vigila que no se te vaya el coste de materia.
A9: B4 | B9: Palmera de hojaldre | C9: Bollería | D9: ='Coste Hora y Mano de Obra'!O9 -> 0.14201041 | E9: ='Coste Hora y Mano de Obra'!Q9 -> 0.82770861 | F9: ='Mix y Ticket Medio'!D9 -> 4.5 | G9: =IFERROR(E9*F9/100,"") -> 0.037246887 | H9: =IF(NOT(ISNUMBER(D9)),"",IF(D9<='Parámetros'!$B$24,"Sí","No")) -> Sí | I9: =IF(NOT(ISNUMBER(F9)),"",IF(F9>='Parámetros'!$B$37,"Sí","No")) -> Sí | J9: =IF(OR(H9="",I9=""),"",IF(AND(H9="No",I9="No"),"Retirar",IF(H9="No","Revisar precio","Mantener"))) -> Mantener | K9: =IF(J9="","",IF(J9="Retirar","Se pasa del food cost objetivo Y casi no rota: ocupa vitrina, genera merma y no paga el hueco. Fuera de la carta de apertura.",IF(J9="Revisar precio","Rota bien pero se pasa del food cost objetivo: sube el precio, cambia el gramaje o renegocia el ingrediente que la encarece. Retirarla te quitaría rotación.","Dentro del objetivo y con rotación: es la que sostiene la carta. Vigila que no se te vaya el coste de materia."))) -> Dentro del objetivo y con rotación: es la que sostiene la carta. Vigila que no se te vaya el coste de materia.
A10: B5 | B10: Caracola de pasas | C10: Bollería | D10: ='Coste Hora y Mano de Obra'!O10 -> 0.18209304 | E10: ='Coste Hora y Mano de Obra'!Q10 -> 0.47867523 | F10: ='Mix y Ticket Medio'!D10 -> 3.5 | G10: =IFERROR(E10*F10/100,"") -> 0.016753633 | H10: =IF(NOT(ISNUMBER(D10)),"",IF(D10<='Parámetros'!$B$24,"Sí","No")) -> Sí | I10: =IF(NOT(ISNUMBER(F10)),"",IF(F10>='Parámetros'!$B$37,"Sí","No")) -> Sí | J10: =IF(OR(H10="",I10=""),"",IF(AND(H10="No",I10="No"),"Retirar",IF(H10="No","Revisar precio","Mantener"))) -> Mantener | K10: =IF(J10="","",IF(J10="Retirar","Se pasa del food cost objetivo Y casi no rota: ocupa vitrina, genera merma y no paga el hueco. Fuera de la carta de apertura.",IF(J10="Revisar precio","Rota bien pero se pasa del food cost objetivo: sube el precio, cambia el gramaje o renegocia el ingrediente que la encarece. Retirarla te quitaría rotación.","Dentro del objetivo y con rotación: es la que sostiene la carta. Vigila que no se te vaya el coste de materia."))) -> Dentro del objetivo y con rotación: es la que sostiene la carta. Vigila que no se te vaya el coste de materia.
A11: B6 | B11: Ensaimada | C11: Bollería | D11: ='Coste Hora y Mano de Obra'!O11 -> 0.10167062 | E11: ='Coste Hora y Mano de Obra'!Q11 -> 0.28452029 | F11: ='Mix y Ticket Medio'!D11 -> 3 | G11: =IFERROR(E11*F11/100,"") -> 0.0085356088 | H11: =IF(NOT(ISNUMBER(D11)),"",IF(D11<='Parámetros'!$B$24,"Sí","No")) -> Sí | I11: =IF(NOT(ISNUMBER(F11)),"",IF(F11>='Parámetros'!$B$37,"Sí","No")) -> Sí | J11: =IF(OR(H11="",I11=""),"",IF(AND(H11="No",I11="No"),"Retirar",IF(H11="No","Revisar precio","Mantener"))) -> Mantener | K11: =IF(J11="","",IF(J11="Retirar","Se pasa del food cost objetivo Y casi no rota: ocupa vitrina, genera merma y no paga el hueco. Fuera de la carta de apertura.",IF(J11="Revisar precio","Rota bien pero se pasa del food cost objetivo: sube el precio, cambia el gramaje o renegocia el ingrediente que la encarece. Retirarla te quitaría rotación.","Dentro del objetivo y con rotación: es la que sostiene la carta. Vigila que no se te vaya el coste de materia."))) -> Dentro del objetivo y con rotación: es la que sostiene la carta. Vigila que no se te vaya el coste de materia.
A12: PI1 | B12: Milhojas | C12: Pastelería individual | D12: ='Coste Hora y Mano de Obra'!O12 -> 0.13656558 | E12: ='Coste Hora y Mano de Obra'!Q12 -> 1.5800971 | F12: ='Mix y Ticket Medio'!D12 -> 4 | G12: =IFERROR(E12*F12/100,"") -> 0.063203883 | H12: =IF(NOT(ISNUMBER(D12)),"",IF(D12<='Parámetros'!$B$24,"Sí","No")) -> Sí | I12: =IF(NOT(ISNUMBER(F12)),"",IF(F12>='Parámetros'!$B$37,"Sí","No")) -> Sí | J12: =IF(OR(H12="",I12=""),"",IF(AND(H12="No",I12="No"),"Retirar",IF(H12="No","Revisar precio","Mantener"))) -> Mantener | K12: =IF(J12="","",IF(J12="Retirar","Se pasa del food cost objetivo Y casi no rota: ocupa vitrina, genera merma y no paga el hueco. Fuera de la carta de apertura.",IF(J12="Revisar precio","Rota bien pero se pasa del food cost objetivo: sube el precio, cambia el gramaje o renegocia el ingrediente que la encarece. Retirarla te quitaría rotación.","Dentro del objetivo y con rotación: es la que sostiene la carta. Vigila que no se te vaya el coste de materia."))) -> Dentro del objetivo y con rotación: es la que sostiene la carta. Vigila que no se te vaya el coste de materia.
A13: PI2 | B13: Éclair | C13: Pastelería individual | D13: ='Coste Hora y Mano de Obra'!O13 -> 0.11627541 | E13: ='Coste Hora y Mano de Obra'!Q13 -> 1.7611378 | F13: ='Mix y Ticket Medio'!D13 -> 3.5 | G13: =IFERROR(E13*F13/100,"") -> 0.061639823 | H13: =IF(NOT(ISNUMBER(D13)),"",IF(D13<='Parámetros'!$B$24,"Sí","No")) -> Sí | I13: =IF(NOT(ISNUMBER(F13)),"",IF(F13>='Parámetros'!$B$37,"Sí","No")) -> Sí | J13: =IF(OR(H13="",I13=""),"",IF(AND(H13="No",I13="No"),"Retirar",IF(H13="No","Revisar precio","Mantener"))) -> Mantener | K13: =IF(J13="","",IF(J13="Retirar","Se pasa del food cost objetivo Y casi no rota: ocupa vitrina, genera merma y no paga el hueco. Fuera de la carta de apertura.",IF(J13="Revisar precio","Rota bien pero se pasa del food cost objetivo: sube el precio, cambia el gramaje o renegocia el ingrediente que la encarece. Retirarla te quitaría rotación.","Dentro del objetivo y con rotación: es la que sostiene la carta. Vigila que no se te vaya el coste de materia."))) -> Dentro del objetivo y con rotación: es la que sostiene la carta. Vigila que no se te vaya el coste de materia.
A14: PI3 | B14: Macarons de frambuesa | C14: Pastelería individual | D14: ='Coste Hora y Mano de Obra'!O14 -> 0.10293379 | E14: ='Coste Hora y Mano de Obra'!Q14 -> 0.91534045 | F14: ='Mix y Ticket Medio'!D14 -> 7 | G14: =IFERROR(E14*F14/100,"") -> 0.064073831 | H14: =IF(NOT(ISNUMBER(D14)),"",IF(D14<='Parámetros'!$B$24,"Sí","No")) -> Sí | I14: =IF(NOT(ISNUMBER(F14)),"",IF(F14>='Parámetros'!$B$37,"Sí","No")) -> Sí | J14: =IF(OR(H14="",I14=""),"",IF(AND(H14="No",I14="No"),"Retirar",IF(H14="No","Revisar precio","Mantener"))) -> Mantener | K14: =IF(J14="","",IF(J14="Retirar","Se pasa del food cost objetivo Y casi no rota: ocupa vitrina, genera merma y no paga el hueco. Fuera de la carta de apertura.",IF(J14="Revisar precio","Rota bien pero se pasa del food cost objetivo: sube el precio, cambia el gramaje o renegocia el ingrediente que la encarece. Retirarla te quitaría rotación.","Dentro del objetivo y con rotación: es la que sostiene la carta. Vigila que no se te vaya el coste de materia."))) -> Dentro del objetivo y con rotación: es la que sostiene la carta. Vigila que no se te vaya el coste de materia.
A15: PI4 | B15: Tartaleta de frutas | C15: Pastelería individual | D15: ='Coste Hora y Mano de Obra'!O15 -> 0.15196964 | E15: ='Coste Hora y Mano de Obra'!Q15 -> 1.6589574 | F15: ='Mix y Ticket Medio'!D15 -> 3 | G15: =IFERROR(E15*F15/100,"") -> 0.049768721 | H15: =IF(NOT(ISNUMBER(D15)),"",IF(D15<='Parámetros'!$B$24,"Sí","No")) -> Sí | I15: =IF(NOT(ISNUMBER(F15)),"",IF(F15>='Parámetros'!$B$37,"Sí","No")) -> Sí | J15: =IF(OR(H15="",I15=""),"",IF(AND(H15="No",I15="No"),"Retirar",IF(H15="No","Revisar precio","Mantener"))) -> Mantener | K15: =IF(J15="","",IF(J15="Retirar","Se pasa del food cost objetivo Y casi no rota: ocupa vitrina, genera merma y no paga el hueco. Fuera de la carta de apertura.",IF(J15="Revisar precio","Rota bien pero se pasa del food cost objetivo: sube el precio, cambia el gramaje o renegocia el ingrediente que la encarece. Retirarla te quitaría rotación.","Dentro del objetivo y con rotación: es la que sostiene la carta. Vigila que no se te vaya el coste de materia."))) -> Dentro del objetivo y con rotación: es la que sostiene la carta. Vigila que no se te vaya el coste de materia.
A16: PI5 | B16: Lionesa o profiterol | C16: Pastelería individual | D16: ='Coste Hora y Mano de Obra'!O16 -> 0.094780213 | E16: ='Coste Hora y Mano de Obra'!Q16 -> 1.4442845 | F16: ='Mix y Ticket Medio'!D16 -> 3 | G16: =IFERROR(E16*F16/100,"") -> 0.043328535 | H16: =IF(NOT(ISNUMBER(D16)),"",IF(D16<='Parámetros'!$B$24,"Sí","No")) -> Sí | I16: =IF(NOT(ISNUMBER(F16)),"",IF(F16>='Parámetros'!$B$37,"Sí","No")) -> Sí | J16: =IF(OR(H16="",I16=""),"",IF(AND(H16="No",I16="No"),"Retirar",IF(H16="No","Revisar precio","Mantener"))) -> Mantener | K16: =IF(J16="","",IF(J16="Retirar","Se pasa del food cost objetivo Y casi no rota: ocupa vitrina, genera merma y no paga el hueco. Fuera de la carta de apertura.",IF(J16="Revisar precio","Rota bien pero se pasa del food cost objetivo: sube el precio, cambia el gramaje o renegocia el ingrediente que la encarece. Retirarla te quitaría rotación.","Dentro del objetivo y con rotación: es la que sostiene la carta. Vigila que no se te vaya el coste de materia."))) -> Dentro del objetivo y con rotación: es la que sostiene la carta. Vigila que no se te vaya el coste de materia.
A17: PI6 | B17: Entremet individual | C17: Pastelería individual | D17: ='Coste Hora y Mano de Obra'!O17 -> 0.20160342 | E17: ='Coste Hora y Mano de Obra'!Q17 -> 1.491062 | F17: ='Mix y Ticket Medio'!D17 -> 1.5 | G17: =IFERROR(E17*F17/100,"") -> 0.02236593 | H17: =IF(NOT(ISNUMBER(D17)),"",IF(D17<='Parámetros'!$B$24,"Sí","No")) -> Sí | I17: =IF(NOT(ISNUMBER(F17)),"",IF(F17>='Parámetros'!$B$37,"Sí","No")) -> Sí | J17: =IF(OR(H17="",I17=""),"",IF(AND(H17="No",I17="No"),"Retirar",IF(H17="No","Revisar precio","Mantener"))) -> Mantener | K17: =IF(J17="","",IF(J17="Retirar","Se pasa del food cost objetivo Y casi no rota: ocupa vitrina, genera merma y no paga el hueco. Fuera de la carta de apertura.",IF(J17="Revisar precio","Rota bien pero se pasa del food cost objetivo: sube el precio, cambia el gramaje o renegocia el ingrediente que la encarece. Retirarla te quitaría rotación.","Dentro del objetivo y con rotación: es la que sostiene la carta. Vigila que no se te vaya el coste de materia."))) -> Dentro del objetivo y con rotación: es la que sostiene la carta. Vigila que no se te vaya el coste de materia.
... A35: TP8 | B35: Mona de Pascua | C35: Temporada | D35: ='Coste Hora y Mano de Obra'!O35 -> 0.16417504 | E35: ='Coste Hora y Mano de Obra'!Q35 -> 8.5494793 | F35: ='Mix y Ticket Medio'!D35 -> 0.7 | G35: =IFERROR(E35*F35/100,"") -> 0.059846355 | H35: =IF(NOT(ISNUMBER(D35)),"",IF(D35<='Parámetros'!$B$24,"Sí","No")) -> Sí | I35: =IF(NOT(ISNUMBER(F35)),"",IF(F35>='Parámetros'!$B$37,"Sí","No")) -> No | J35: =IF(OR(H35="",I35=""),"",IF(AND(H35="No",I35="No"),"Retirar",IF(H35="No","Revisar precio","Mantener"))) -> Mantener | K35: =IF(J35="","",IF(J35="Retirar","Se pasa del food cost objetivo Y casi no rota: ocupa vitrina, genera merma y no paga el hueco. Fuera de la carta de apertura.",IF(J35="Revisar precio","Rota bien pero se pasa del food cost objetivo: sube el precio, cambia el gramaje o renegocia el ingrediente que la encarece. Retirarla te quitaría rotación.","Dentro del objetivo y con rotación: es la que sostiene la carta. Vigila que no se te vaya el coste de materia."))) -> Dentro del objetivo y con rotación: es la que sostiene la carta. Vigila que no se te vaya el coste de materia.
A36: TOTAL DE LA CARTA | F36: =SUM(F6:F35) -> 100 | G36: =SUM(G6:G35) -> 1.0710505 | K36: El margen ponderado del total es el margen de contribución de 100 piezas vendidas con este mix.
A38: Cómo queda la carta
B39: Referencias con veredicto «Mantener» | E39: =COUNTIF(J6:J35,"Mantener") -> 27 | F39: =IFERROR(SUMPRODUCT(--(J6:J35="Mantener"),G6:G35),"") -> 1.0278667 | G39: euros de margen ponderado que aportan
B40: Referencias con veredicto «Revisar precio» | E40: =COUNTIF(J6:J35,"Revisar precio") -> 1 | F40: =IFERROR(SUMPRODUCT(--(J6:J35="Revisar precio"),G6:G35),"") -> 0.011991309 | G40: euros de margen ponderado que aportan
B41: Referencias con veredicto «Retirar» | E41: =COUNTIF(J6:J35,"Retirar") -> 2 | F41: =IFERROR(SUMPRODUCT(--(J6:J35="Retirar"),G6:G35),"") -> 0.031192538 | G41: euros de margen ponderado que aportan
B42: Margen ponderado medio de la carta (€) | E42: =IFERROR(AVERAGE(G6:G35),"") -> 0.035701684
A45: CÓMO SE DECIDE. Dos preguntas, no cuatro. ¿El food cost está dentro de tu objetivo? ¿La referencia rota por encima de tu umbral? Si falla el margen y además no rota, fuera. Si falla sólo el margen, el problema es de precio o de proceso, no de carta: retirarla te quitaría rotación. Si no falla ninguna, se queda.
A46: ESTO NO ES INGENIERÍA DE MENÚ. La ingeniería de menú -Kasavana-Smith, Miller, Pavesic, Goal Value- está en la Guía Food Cost, con sus cuatro métodos y su comparativa. Aquí hay una decisión de surtido de APERTURA, que es otra cosa: se toma antes de vender nada y con el mix que TÚ supones.
A47: CUÁNDO SE VUELVE A MIRAR. A los tres meses de abrir, con ventas reales del TPV en la columna del mix, y luego cada cambio de temporada. Una carta de apertura que sigue igual al año es una carta que nadie ha mirado.
A48: UNA REFERENCIA PUEDE QUEDARSE AUNQUE PIERDA DINERO, Y HAY QUE SABERLO. El pan de barra es el caso clásico: margen corto y mucha rotación, pero es lo que trae al cliente todos los días. Si decides mantener algo que el semáforo manda retirar, escríbelo y ponle una fecha para revisarlo: eso es una decisión, no un despiste.
A50: Versión 1.0 · septiembre 2026 · aichef.pro/guia-pasteleria-obrador · info@aichef.pro
