Workbook

Sheet Instrucciones
A1: Estacionalidad y Picos de Campaña
A2: AI Chef Pro · aichef.pro — Cómo Montar una Pastelería
A3: Para qué sirve: saber si aguantas Reyes antes de que llegue, y cuánto dinero inmoviliza cada campaña.
A5: Instrucciones de uso
A6: 1. Hoja «Parámetros»: lo primero es la capacidad de tu obrador en piezas por hora. Ese número sale de la hoja «Cuello de Botella» del libro «capacidad-obrador-y-local.xlsx» de este mismo pack: ábrelo, mira qué equipo te limita y copia aquí sus piezas por hora. Viene con un valor por defecto para que el libro funcione desde el primer minuto, pero es un SUPUESTO, no tu obrador.
A7: 2. Hoja «Calendario de 6 Picos»: seis campañas con su producto estrella, sus días, su precio y las unidades que esperas vender al día dentro y fuera de campaña. Es la única hoja donde tecleas expectativas de venta.
A8: 3. Hoja «Peso sobre el Año»: reparte tus ventas anuales entre los doce meses y verás qué porcentaje del año se juega en cada campaña. Es el número que decide si merece la pena montar la campaña o no.
A9: 4. Hoja «Capacidad vs Demanda del Pico»: aquí está la pregunta del libro. La demanda del pico se calcula multiplicando tus piezas de un día normal por el factor de la campaña; la capacidad, con las horas que puedas tener el obrador en marcha. Si sale déficit, tienes tres palancas y en este orden: más horas de máquina, producción adelantada y congelada, y refuerzo de personal.
A10: 5. Hoja «Refuerzo y Tesorería»: cuánto cuesta el refuerzo con el coste de empresa de verdad (bruto de convenio más Seguridad Social) y, sobre todo, cuánto dinero deja inmovilizado la compra de materia prima de la campaña y durante cuántos días. Ese dinero sale de tu caja semanas antes de que entre el primer euro de la campaña.
A11: 6. Repite el ciclo cada año en enero, con las cifras reales de la campaña que acabas de cerrar: el libro sólo vale si le metes lo que pasó de verdad, no lo que esperabas que pasara.
A13: Celdas verdes = campos editables
A15: Lo que conviene saber antes de empezar
... A28: Versión 1.0 · septiembre 2026 · aichef.pro/guia-pasteleria-obrador · info@aichef.pro

Sheet Parámetros
A1: Parámetros
A2: AI Chef Pro · aichef.pro — Cómo Montar una Pastelería
A5: Parámetro | B5: Valor | C5: Unidad | D5: De dónde sale | E5: Nota
A6: Ventas anuales sin IVA en velocidad de crucero | B6: 322197.87 | C6: €/año | D6: supuesto | E6: Sale de la carta y del tráfico supuesto de La Clara: clientes al día por piezas por cliente por PVP medio ponderado. No es un dato del sector. Sustitúyelo por el de tu plan financiero.
A7: Piezas al día en velocidad de crucero | B7: 476 | C7: piezas/día | D7: supuesto | E7: Clientes al día por piezas por cliente. Es la base sobre la que el factor de cada campaña multiplica.
A8: Días de apertura al año | B8: 300 | C8: días | D8: supuesto | E8: 6 días por semana × 52 semanas = 312, menos 12 días de cierre por vacaciones en agosto = 300. Los festivos NO se descuentan: la pastelería tiene libertad horaria por ley estatal cuando es la actividad principal (PA-39).
A9: Capacidad del obrador en jornada normal | B9: 480 | C9: piezas/día | D9: libro 1 | E9: COPIA a mano el resultado de la hoja «Cuello de Botella» del libro «capacidad-obrador-y-local.xlsx» de este pack: la casilla «Piezas al día que permite el conjunto». En el ejemplo son 480 y el equipo que limita es el abatidor de 4 bandejas, contra 476 piezas de velocidad de crucero: cuatro piezas de holgura. No hay fórmula entre libros: si cambias de equipo, vuelve a copiarlo.
A10: Horas de obrador al día en jornada normal | B10: 8 | C10: horas | D10: supuesto | E10: Horas de reloj que el obrador está en marcha un día cualquiera, no horas de apertura de la tienda.
A11: Piezas por hora de reloj del equipo que limita | B11: =IFERROR('Parámetros'!$B$9/'Parámetros'!$B$10,"") -> 60 | C11: piezas/hora | D11: calculado | E11: Capacidad de la jornada normal dividida por sus horas. Va por hora de RELOJ, con las paradas ya dentro: el libro 1 ya descontó la parte de la jornada que no se pasa a pie de mesa.
A12: Excedente diario sobre la velocidad de crucero | B12: =IFERROR('Parámetros'!$B$9-'Parámetros'!$B$7,"") -> 4 | C12: piezas/día | D12: calculado | E12: Lo que te sobra un día normal. Es la munición para adelantar producción y congelarla antes de la campaña; si sale negativo, ya vas justo en crucero y el pico no lo arreglas adelantando.
A13: Horas máximas de obrador al día que admites | B13: 24 | C13: horas | D13: supuesto | E13: Techo que te pones tú. Por encima de este número la hoja se pone en rojo: no es un límite legal, es el aviso de que ese día no existe.
A14: Horas por persona y día del refuerzo | B14: 8 | C14: horas | D14: supuesto | E14: Jornada del personal de refuerzo durante la campaña. Con ella se calcula cuántas personas hacen falta para cubrir las horas de máquina que faltan.
A16: Coste del refuerzo (convenio de pastelería)
A17: Bruto mensual del grupo de convenio del refuerzo | B17: 1192.42 | C17: €/mes | D17: PA-33 | E17: Grupo 5, «Personal de apoyo», del convenio de la Comunidad de Madrid (código 28001025011981, revisión 2026 en el BOCM núm. 50, de 28 de febrero de 2026). Sustitúyelo por el de TU convenio provincial.
A18: Pagas del convenio al año | B18: 15 | C18: pagas | D18: PA-33 | E18: El convenio de Madrid paga 15, no 14: cambia el coste mes a mes.
A19: Seguridad Social a cargo de la empresa | B19: 0.33 | C19: sobre bruto | D19: motor.PARAMETROS | E19: Cotización empresarial aproximada sobre el bruto (contingencias comunes, desempleo, FOGASA y formación). Ajústala a tu convenio y a tus contratos.
A20: Horas anuales de contrato | B20: 1780 | C20: horas/año | D20: supuesto | E20: 40 horas por 52 semanas son 2.080, menos vacaciones y festivos del calendario laboral.
A21: Coste por hora PAGADA del refuerzo (grupo 5) | B21: =IFERROR('Parámetros'!$B$17*'Parámetros'!$B$18*(1+'Parámetros'!$B$19)/'Parámetros'!$B$20,"") -> 13.364483 | C21: €/hora | D21: calculado | E21: Bruto mensual por pagas por (1 más Seguridad Social), dividido por las horas anuales de contrato. Es el coste de verdad, no el bruto. NO es el «coste hora productiva de obrador» del libro 4 (17,94 €) ni el «coste medio por hora pagada de la plantilla» del libro 8 (14,89 €): las tres son correctas y miden un denominador distinto.
A23: Dinero, IVA y umbrales
A24: Tipo de interés anual del circulante | B24: 0.062 | C24: anual | D24: supuesto | E24: Coste del dinero que tienes parado en materia prima de campaña. Si financias la compra con póliza, pon el tipo de tu póliza; si la pagas de tu caja, pon lo que te costaría pedirla.
A25: IVA de pastelería, bollería y confitería | B25: 0.1 | C25: sobre base | D25: PA-36 | E25: Regla general de alimentos del art. 91.Uno.1.1.º de la Ley 37/1992: no porque un precepto los nombre, sino porque no están en la lista cerrada del 4 % ni excluidos del 10 %.
A26: IVA del pan del RD 308/2019 | B26: 0.04 | C26: sobre base | D26: PA-36b | E26: Todos los productos del RD 308/2019 van al 4 % desde la Resolución vinculante de la DGT de 24-02-2025. El cruasán sigue al 10 %: el RD 308/2019 sólo regula el pan.
A27: Umbral para marcar una campaña como grande | B27: 0.05 | C27: del año | D27: supuesto | E27: Porcentaje de las ventas del año por encima del cual la hoja «Peso sobre el Año» resalta la campaña. Criterio de la casa, no del sector.
A29: Versión 1.0 · septiembre 2026 · aichef.pro/guia-pasteleria-obrador · info@aichef.pro

Sheet Calendario de 6 Picos
A1: Calendario de 6 Picos
A2: AI Chef Pro · aichef.pro — Cómo Montar una Pastelería
A3: Las FECHAS y el qué hacer están en el «BONUS-02-calendario-anual-tareas.xlsx» del Kit de Tareas Pastelería. Esta hoja pone los EUROS.
A5: # | B5: Campaña | C5: Fechas de referencia | D5: Mes | E5: Días de campaña | F5: Producto estrella | G5: IVA | H5: PVP con IVA (€) | I5: PVP sin IVA (€) | J5: Uds/día fuera de campaña | K5: Uds/día en campaña | L5: Uds/día incrementales | M5: Uds de toda la campaña | N5: Facturación de la campaña sin IVA (€) | O5: Facturación incremental sin IVA (€) | P5: Factor sobre el obrador | Q5: Antelación de compra (semanas) | R5: Qué hay que saber de esta campaña
A6: 1 | B6: Reyes | C6: 2 a 6 de enero | D6: 1 | E6: 5 | F6: Roscón de Reyes | G6: 0.1 | H6: 16.5 | I6: =IFERROR(H6/(1+G6),"") -> 15 | J6: 0 | K6: 420 | L6: =IFERROR(K6-J6,"") -> 420 | M6: =IFERROR(K6*E6,"") -> 2100 | N6: =IFERROR(M6*I6,"") -> 31500 | O6: =IFERROR(L6*E6*I6,"") -> 31500 | P6: 6 | Q6: 6 | R6: El pico que decide el año. Referencias de escala, nunca de precio ni de cuota: PS-35 (unos 30 millones de roscones en España en la campaña 2025/26), PS-36 (más de 2,9 millones en la Comunidad de Madrid) y PS-38 (El Corte Inglés 850.000, Viena Capellanes 72.000). PS-46: el supermercado entra con roscones premiados a 9 €. El roscón relleno de nata arrastra los 4 °C de la fila 9 y las 24 h del art. 9.3 justo el día de más producción: eso limita la producción tanto como el horno.
A7: 2 | B7: San Valentín | C7: 13 y 14 de febrero | D7: 2 | E7: 2 | F7: Macarons de frambuesa | G7: 0.1 | H7: 2.1 | I7: =IFERROR(H7/(1+G7),"") -> 1.9090909 | J7: 95 | K7: 260 | L7: =IFERROR(K7-J7,"") -> 165 | M7: =IFERROR(K7*E7,"") -> 520 | N7: =IFERROR(M7*I7,"") -> 992.72727 | O7: =IFERROR(L7*E7*I7,"") -> 630 | P7: 1.8 | Q7: 3 | R7: Campaña de dos días y de ticket alto, no de volumen: se gana con cajas y presentación, no con más horno. En el kit, la producción especial de esta fecha son tartas corazón, bombones y macarons.
A8: 3 | B8: Día del Padre y de la Madre | C8: 19 de marzo y primer domingo de mayo | D8: 3 | E8: 4 | F8: Tarta de chocolate 70 % | G8: 0.1 | H8: 3.6 | I8: =IFERROR(H8/(1+G8),"") -> 3.2727273 | J8: 16 | K8: 96 | L8: =IFERROR(K8-J8,"") -> 80 | M8: =IFERROR(K8*E8,"") -> 384 | N8: =IFERROR(M8*I8,"") -> 1256.7273 | O8: =IFERROR(L8*E8*I8,"") -> 1047.2727 | P8: 1.9 | Q8: 3 | R8: Dos fechas con el mismo patrón de trabajo -tarta con dedicatoria, por encargo- y por eso van juntas como una sola campaña operativa. El kit las separa en su calendario porque a él le importan las fechas; a la guía le importa la carga de obrador.
A9: 4 | B9: Semana Santa | C9: del Domingo de Ramos al Domingo de Resurrección | D9: 4 | E9: 8 | F9: Torrijas | G9: 0.1 | H9: 2.4 | I9: =IFERROR(H9/(1+G9),"") -> 2.1818182 | J9: 0 | K9: 240 | L9: =IFERROR(K9-J9,"") -> 240 | M9: =IFERROR(K9*E9,"") -> 1920 | N9: =IFERROR(M9*I9,"") -> 4189.0909 | O9: =IFERROR(L9*E9*I9,"") -> 4189.0909 | P9: 2.4 | Q9: 4 | R9: Ocho días seguidos de producción extra, que es más agotador que los cinco de Reyes aunque el pico sea menor. Torrijas y monas a la vez: una necesita freidora y frío, la otra horno y chocolate.
A10: 5 | B10: Comuniones | C10: de mediados de abril a mediados de junio | D10: 5 | E10: 20 | F10: Tarta de nata y fresas | G10: 0.1 | H10: 3.5 | I10: =IFERROR(H10/(1+G10),"") -> 3.1818182 | J10: 10 | K10: 34 | L10: =IFERROR(K10-J10,"") -> 24 | M10: =IFERROR(K10*E10,"") -> 680 | N10: =IFERROR(M10*I10,"") -> 2163.6364 | O10: =IFERROR(L10*E10*I10,"") -> 1527.2727 | P10: 1.6 | Q10: 5 | R10: No es un pico, es una MESETA de dos meses, y por eso se aguanta con plantilla y no con horas extra. Todo va por encargo: anticipo, calendario de entrega y riesgo de anulación (cap. 16). La herramienta de gestión del encargo es el 11-control-encargos.xlsx del kit, que la guía no rehace (R2).
A11: 6 | B11: Todos los Santos | C11: 30 y 31 de octubre y 1 de noviembre | D11: 11 | E11: 3 | F11: Buñuelos de viento | G11: 0.1 | H11: 1.6 | I11: =IFERROR(H11/(1+G11),"") -> 1.4545455 | J11: 0 | K11: 520 | L11: =IFERROR(K11-J11,"") -> 520 | M11: =IFERROR(K11*E11,"") -> 1560 | N11: =IFERROR(M11*I11,"") -> 2269.0909 | O11: =IFERROR(L11*E11*I11,"") -> 2269.0909 | P11: 2.6 | Q11: 4 | R11: Tres días con tres referencias que sólo se hacen ahora: buñuelos, huesos de santo y panellets. Los buñuelos van rellenos (4 °C y 24 h) y los otros dos son estables a temperatura ambiente: por eso los buñuelos se hacen el mismo día y los huesos de santo se pueden adelantar. Ese detalle legal ES la planificación de la campaña.
B13: TOTAL DE LAS SEIS CAMPAÑAS | E13: =SUM(E6:E11) -> 42 | M13: =SUM(M6:M11) -> 7164 | N13: =SUM(N6:N11) -> 42371.273 | O13: =SUM(O6:O11) -> 41162.727
A15: El factor de campaña multiplica las piezas del OBRADOR ENTERO, no las del producto estrella: por eso Reyes lleva un 6,0 y San Valentín un 1,8 aunque las dos sean campañas. Las unidades del producto estrella son las de esta hoja; el obrador entero se trata en «Capacidad vs Demanda del Pico».
A17: Versión 1.0 · septiembre 2026 · aichef.pro/guia-pasteleria-obrador · info@aichef.pro

Sheet Peso sobre el Año
A1: Peso sobre el Año
A2: AI Chef Pro · aichef.pro — Cómo Montar una Pastelería
A3: Qué parte del año se juega en cada campaña. Es el número que decide si merece la pena montarla.
A5: Mes | B5: Coeficiente sobre el mes medio | C5: Ventas del mes sin IVA (€) | D5: % sobre el año | E5: Campañas que caen en el mes | F5: Por qué ese coeficiente
A6: Enero | B6: 1.18 | C6: =IFERROR('Parámetros'!$B$6*B6/$B$18,"") -> 31682.791 | D6: =IFERROR(C6/'Parámetros'!$B$6,"") -> 0.098333333 | E6: Reyes | F6: Reyes. Es el mes más alto del año y el que decide la campaña.
A7: Febrero | B7: 0.94 | C7: =IFERROR('Parámetros'!$B$6*B7/$B$18,"") -> 25238.833 | D7: =IFERROR(C7/'Parámetros'!$B$6,"") -> 0.078333333 | E7: San Valentín | F7: San Valentín son dos días y febrero tiene 28: una campaña de esa longitud no levanta un mes entero.
A8: Marzo | B8: 0.98 | C8: =IFERROR('Parámetros'!$B$6*B8/$B$18,"") -> 26312.826 | D8: =IFERROR(C8/'Parámetros'!$B$6,"") -> 0.081666667 | E8: Día del Padre y de la Madre | F8: El Día del Padre es un día. Mismo razonamiento que febrero.
A9: Abril | B9: 1.05 | C9: =IFERROR('Parámetros'!$B$6*B9/$B$18,"") -> 28192.314 | D9: =IFERROR(C9/'Parámetros'!$B$6,"") -> 0.0875 | E9: Semana Santa | F9: Semana Santa y el arranque de las comuniones.
A10: Mayo | B10: 1.08 | C10: =IFERROR('Parámetros'!$B$6*B10/$B$18,"") -> 28997.808 | D10: =IFERROR(C10/'Parámetros'!$B$6,"") -> 0.09 | E10: Comuniones | F10: Día de la Madre y meseta de comuniones: dos meses de encargos.
A11: Junio | B11: 0.98 | C11: =IFERROR('Parámetros'!$B$6*B11/$B$18,"") -> 26312.826 | D11: =IFERROR(C11/'Parámetros'!$B$6,"") -> 0.081666667 | E11: - | F11: Final de comuniones y caída del consumo con el calor.
A12: Julio | B12: 0.86 | C12: =IFERROR('Parámetros'!$B$6*B12/$B$18,"") -> 23090.847 | D12: =IFERROR(C12/'Parámetros'!$B$6,"") -> 0.071666667 | E12: - | F12: Verano: baja el consumo de pastelería y sube el de helado, que no está en la carta de La Clara.
A13: Agosto | B13: 0.68 | C13: =IFERROR('Parámetros'!$B$6*B13/$B$18,"") -> 18257.879 | D13: =IFERROR(C13/'Parámetros'!$B$6,"") -> 0.056666667 | E13: - | F13: La Clara cierra dos semanas en agosto (los 300 días de apertura del año salen de ahí).
A14: Septiembre | B14: 0.92 | C14: =IFERROR('Parámetros'!$B$6*B14/$B$18,"") -> 24701.837 | D14: =IFERROR(C14/'Parámetros'!$B$6,"") -> 0.076666667 | E14: - | F14: Vuelta al colegio y mes de apertura recomendado: fuera de pico y con tres meses y medio de rodaje antes de Reyes.
A15: Octubre | B15: 0.96 | C15: =IFERROR('Parámetros'!$B$6*B15/$B$18,"") -> 25775.83 | D15: =IFERROR(C15/'Parámetros'!$B$6,"") -> 0.08 | E15: - | F15: Mes de transición; Todos los Santos empieza el día 30.
A16: Noviembre | B16: 1.09 | C16: =IFERROR('Parámetros'!$B$6*B16/$B$18,"") -> 29266.307 | D16: =IFERROR(C16/'Parámetros'!$B$6,"") -> 0.090833333 | E16: Todos los Santos | F16: Todos los Santos y arranque de la producción de Navidad.
A17: Diciembre | B17: 1.28 | C17: =IFERROR('Parámetros'!$B$6*B17/$B$18,"") -> 34367.773 | D17: =IFERROR(C17/'Parámetros'!$B$6,"") -> 0.10666667 | E17: - | F17: Navidad: turrones, polvorones y el prólogo de Reyes.
A18: TOTAL AÑO | B18: =SUM(B6:B17) -> 12 | C18: =SUM(C6:C17) -> 322197.87 | D18: =SUM(D6:D17) -> 1 | F18: Los doce coeficientes se reparten sobre el mes medio, así que su suma tiene que dar 12,00. Si cambias uno, el reparto se recalcula solo y las ventas del año no se mueven.
A21: Lo que pesa cada campaña
A23: Campaña | B23: Días de campaña | C23: Facturación de la campaña sin IVA (€) | D23: % sobre el año | E23: Facturación incremental sin IVA (€) | F23: % incremental sobre el año | G23: € por día de campaña | H23: € por día medio del año | I23: Cuántas veces un día normal
A24: Reyes | B24: ='Calendario de 6 Picos'!E6 -> 5 | C24: ='Calendario de 6 Picos'!N6 -> 31500 | D24: =IFERROR(C24/'Parámetros'!$B$6,"") -> 0.097766009 | E24: ='Calendario de 6 Picos'!O6 -> 31500 | F24: =IFERROR(E24/'Parámetros'!$B$6,"") -> 0.097766009 | G24: =IFERROR(C24/B24,"") -> 6300 | H24: =IFERROR('Parámetros'!$B$6/'Parámetros'!$B$8,"") -> 1073.9929 | I24: =IFERROR(G24/H24,"") -> 5.8659606
A25: San Valentín | B25: ='Calendario de 6 Picos'!E7 -> 2 | C25: ='Calendario de 6 Picos'!N7 -> 992.72727 | D25: =IFERROR(C25/'Parámetros'!$B$6,"") -> 0.0030811106 | E25: ='Calendario de 6 Picos'!O7 -> 630 | F25: =IFERROR(E25/'Parámetros'!$B$6,"") -> 0.0019553202 | G25: =IFERROR(C25/B25,"") -> 496.36364 | H25: =IFERROR('Parámetros'!$B$6/'Parámetros'!$B$8,"") -> 1073.9929 | I25: =IFERROR(G25/H25,"") -> 0.46216659
A26: Día del Padre y de la Madre | B26: ='Calendario de 6 Picos'!E8 -> 4 | C26: ='Calendario de 6 Picos'!N8 -> 1256.7273 | D26: =IFERROR(C26/'Parámetros'!$B$6,"") -> 0.0039004829 | E26: ='Calendario de 6 Picos'!O8 -> 1047.2727 | F26: =IFERROR(E26/'Parámetros'!$B$6,"") -> 0.0032504024 | G26: =IFERROR(C26/B26,"") -> 314.18182 | H26: =IFERROR('Parámetros'!$B$6/'Parámetros'!$B$8,"") -> 1073.9929 | I26: =IFERROR(G26/H26,"") -> 0.29253622
A27: Semana Santa | B27: ='Calendario de 6 Picos'!E9 -> 8 | C27: ='Calendario de 6 Picos'!N9 -> 4189.0909 | D27: =IFERROR(C27/'Parámetros'!$B$6,"") -> 0.01300161 | E27: ='Calendario de 6 Picos'!O9 -> 4189.0909 | F27: =IFERROR(E27/'Parámetros'!$B$6,"") -> 0.01300161 | G27: =IFERROR(C27/B27,"") -> 523.63636 | H27: =IFERROR('Parámetros'!$B$6/'Parámetros'!$B$8,"") -> 1073.9929 | I27: =IFERROR(G27/H27,"") -> 0.48756036
A28: Comuniones | B28: ='Calendario de 6 Picos'!E10 -> 20 | C28: ='Calendario de 6 Picos'!N10 -> 2163.6364 | D28: =IFERROR(C28/'Parámetros'!$B$6,"") -> 0.0067152411 | E28: ='Calendario de 6 Picos'!O10 -> 1527.2727 | F28: =IFERROR(E28/'Parámetros'!$B$6,"") -> 0.0047401702 | G28: =IFERROR(C28/B28,"") -> 108.18182 | H28: =IFERROR('Parámetros'!$B$6/'Parámetros'!$B$8,"") -> 1073.9929 | I28: =IFERROR(G28/H28,"") -> 0.10072862
A29: Todos los Santos | B29: ='Calendario de 6 Picos'!E11 -> 3 | C29: ='Calendario de 6 Picos'!N11 -> 2269.0909 | D29: =IFERROR(C29/'Parámetros'!$B$6,"") -> 0.0070425385 | E29: ='Calendario de 6 Picos'!O11 -> 2269.0909 | F29: =IFERROR(E29/'Parámetros'!$B$6,"") -> 0.0070425385 | G29: =IFERROR(C29/B29,"") -> 756.36364 | H29: =IFERROR('Parámetros'!$B$6/'Parámetros'!$B$8,"") -> 1073.9929 | I29: =IFERROR(G29/H29,"") -> 0.70425385
A30: TOTAL DE LAS SEIS CAMPAÑAS | B30: =SUM(B24:B29) -> 42 | C30: =SUM(C24:C29) -> 42371.273 | D30: =SUM(D24:D29) -> 0.13150699 | E30: =SUM(E24:E29) -> 41162.727 | F30: =SUM(F24:F29) -> 0.12775605
A32: La «facturación de la campaña» cuenta TODAS las unidades del producto estrella que vendes esos días; la «incremental» sólo las que no habrías vendido de todas formas. Para decidir si montas la campaña manda la incremental. Para saber si aguantas, manda la total.
A34: Versión 1.0 · septiembre 2026 · aichef.pro/guia-pasteleria-obrador · info@aichef.pro

Sheet Capacidad vs Demanda del Pico
A1: Capacidad vs Demanda del Pico
A2: AI Chef Pro · aichef.pro — Cómo Montar una Pastelería
A3: La pregunta del libro: ¿aguantas Reyes con el equipo que estás comprando?
A5: Campaña | B5: Días de campaña | C5: Factor sobre el crucero | D5: Demanda piezas/día | E5: Demanda de toda la campaña | F5: Horas de obrador al día en campaña | G5: Capacidad piezas/día en campaña | H5: Déficit diario | I5: Déficit de toda la campaña | J5: Días de producción adelantada | K5: Piezas que puedes adelantar | L5: Déficit tras adelantar | M5: Horas de obrador al día que harían falta | N5: ¿Aguantas? | O5: Horas de obrador que faltan | P5: Personas de refuerzo necesarias | Q5: Qué palanca te falta
A6: Reyes | B6: ='Calendario de 6 Picos'!E6 -> 5 | C6: ='Calendario de 6 Picos'!P6 -> 6 | D6: =IFERROR('Parámetros'!$B$7*C6,"") -> 2856 | E6: =IFERROR(D6*B6,"") -> 14280 | F6: 20 | G6: =IFERROR('Parámetros'!$B$11*F6,"") -> 1200 | H6: =IFERROR(MAX(0,D6-G6),"") -> 1656 | I6: =IFERROR(H6*B6,"") -> 8280 | J6: 15 | K6: =IFERROR(MIN(I6,MAX(0,'Parámetros'!$B$12)*J6),"") -> 60 | L6: =IFERROR(MAX(0,I6-K6),"") -> 8220 | M6: =IFERROR((E6-K6)/B6/'Parámetros'!$B$11,"") -> 47.4 | N6: =IF(L6="","",IF(L6<=0,"Sí","No")) -> No | O6: =IFERROR(L6/'Parámetros'!$B$11,"") -> 137 | P6: =IFERROR(ROUNDUP(O6/(B6*'Parámetros'!$B$14),0),"") -> 4 | Q6: =IF(L6="","",IF(L6<=0,"Con estas horas y este adelanto, la campaña cabe.",IF(M6>'Parámetros'!$B$13,"No cabe ni con el día entero: hay que adelantar y congelar más, o recortar el surtido de campaña.","Cabe alargando el turno con refuerzo: mira la hoja Refuerzo y Tesorería."))) -> No cabe ni con el día entero: hay que adelantar y congelar más, o recortar el surtido de campaña.
A7: San Valentín | B7: ='Calendario de 6 Picos'!E7 -> 2 | C7: ='Calendario de 6 Picos'!P7 -> 1.8 | D7: =IFERROR('Parámetros'!$B$7*C7,"") -> 856.8 | E7: =IFERROR(D7*B7,"") -> 1713.6 | F7: 10 | G7: =IFERROR('Parámetros'!$B$11*F7,"") -> 600 | H7: =IFERROR(MAX(0,D7-G7),"") -> 256.8 | I7: =IFERROR(H7*B7,"") -> 513.6 | J7: 5 | K7: =IFERROR(MIN(I7,MAX(0,'Parámetros'!$B$12)*J7),"") -> 20 | L7: =IFERROR(MAX(0,I7-K7),"") -> 493.6 | M7: =IFERROR((E7-K7)/B7/'Parámetros'!$B$11,"") -> 14.113333 | N7: =IF(L7="","",IF(L7<=0,"Sí","No")) -> No | O7: =IFERROR(L7/'Parámetros'!$B$11,"") -> 8.2266667 | P7: =IFERROR(ROUNDUP(O7/(B7*'Parámetros'!$B$14),0),"") -> 1 | Q7: =IF(L7="","",IF(L7<=0,"Con estas horas y este adelanto, la campaña cabe.",IF(M7>'Parámetros'!$B$13,"No cabe ni con el día entero: hay que adelantar y congelar más, o recortar el surtido de campaña.","Cabe alargando el turno con refuerzo: mira la hoja Refuerzo y Tesorería."))) -> Cabe alargando el turno con refuerzo: mira la hoja Refuerzo y Tesorería.
A8: Día del Padre y de la Madre | B8: ='Calendario de 6 Picos'!E8 -> 4 | C8: ='Calendario de 6 Picos'!P8 -> 1.9 | D8: =IFERROR('Parámetros'!$B$7*C8,"") -> 904.4 | E8: =IFERROR(D8*B8,"") -> 3617.6 | F8: 10 | G8: =IFERROR('Parámetros'!$B$11*F8,"") -> 600 | H8: =IFERROR(MAX(0,D8-G8),"") -> 304.4 | I8: =IFERROR(H8*B8,"") -> 1217.6 | J8: 5 | K8: =IFERROR(MIN(I8,MAX(0,'Parámetros'!$B$12)*J8),"") -> 20 | L8: =IFERROR(MAX(0,I8-K8),"") -> 1197.6 | M8: =IFERROR((E8-K8)/B8/'Parámetros'!$B$11,"") -> 14.99 | N8: =IF(L8="","",IF(L8<=0,"Sí","No")) -> No | O8: =IFERROR(L8/'Parámetros'!$B$11,"") -> 19.96 | P8: =IFERROR(ROUNDUP(O8/(B8*'Parámetros'!$B$14),0),"") -> 1 | Q8: =IF(L8="","",IF(L8<=0,"Con estas horas y este adelanto, la campaña cabe.",IF(M8>'Parámetros'!$B$13,"No cabe ni con el día entero: hay que adelantar y congelar más, o recortar el surtido de campaña.","Cabe alargando el turno con refuerzo: mira la hoja Refuerzo y Tesorería."))) -> Cabe alargando el turno con refuerzo: mira la hoja Refuerzo y Tesorería.
A9: Semana Santa | B9: ='Calendario de 6 Picos'!E9 -> 8 | C9: ='Calendario de 6 Picos'!P9 -> 2.4 | D9: =IFERROR('Parámetros'!$B$7*C9,"") -> 1142.4 | E9: =IFERROR(D9*B9,"") -> 9139.2 | F9: 14 | G9: =IFERROR('Parámetros'!$B$11*F9,"") -> 840 | H9: =IFERROR(MAX(0,D9-G9),"") -> 302.4 | I9: =IFERROR(H9*B9,"") -> 2419.2 | J9: 10 | K9: =IFERROR(MIN(I9,MAX(0,'Parámetros'!$B$12)*J9),"") -> 40 | L9: =IFERROR(MAX(0,I9-K9),"") -> 2379.2 | M9: =IFERROR((E9-K9)/B9/'Parámetros'!$B$11,"") -> 18.956667 | N9: =IF(L9="","",IF(L9<=0,"Sí","No")) -> No | O9: =IFERROR(L9/'Parámetros'!$B$11,"") -> 39.653333 | P9: =IFERROR(ROUNDUP(O9/(B9*'Parámetros'!$B$14),0),"") -> 1 | Q9: =IF(L9="","",IF(L9<=0,"Con estas horas y este adelanto, la campaña cabe.",IF(M9>'Parámetros'!$B$13,"No cabe ni con el día entero: hay que adelantar y congelar más, o recortar el surtido de campaña.","Cabe alargando el turno con refuerzo: mira la hoja Refuerzo y Tesorería."))) -> Cabe alargando el turno con refuerzo: mira la hoja Refuerzo y Tesorería.
A10: Comuniones | B10: ='Calendario de 6 Picos'!E10 -> 20 | C10: ='Calendario de 6 Picos'!P10 -> 1.6 | D10: =IFERROR('Parámetros'!$B$7*C10,"") -> 761.6 | E10: =IFERROR(D10*B10,"") -> 15232 | F10: 10 | G10: =IFERROR('Parámetros'!$B$11*F10,"") -> 600 | H10: =IFERROR(MAX(0,D10-G10),"") -> 161.6 | I10: =IFERROR(H10*B10,"") -> 3232 | J10: 0 | K10: =IFERROR(MIN(I10,MAX(0,'Parámetros'!$B$12)*J10),"") -> 0 | L10: =IFERROR(MAX(0,I10-K10),"") -> 3232 | M10: =IFERROR((E10-K10)/B10/'Parámetros'!$B$11,"") -> 12.693333 | N10: =IF(L10="","",IF(L10<=0,"Sí","No")) -> No | O10: =IFERROR(L10/'Parámetros'!$B$11,"") -> 53.866667 | P10: =IFERROR(ROUNDUP(O10/(B10*'Parámetros'!$B$14),0),"") -> 1 | Q10: =IF(L10="","",IF(L10<=0,"Con estas horas y este adelanto, la campaña cabe.",IF(M10>'Parámetros'!$B$13,"No cabe ni con el día entero: hay que adelantar y congelar más, o recortar el surtido de campaña.","Cabe alargando el turno con refuerzo: mira la hoja Refuerzo y Tesorería."))) -> Cabe alargando el turno con refuerzo: mira la hoja Refuerzo y Tesorería.
A11: Todos los Santos | B11: ='Calendario de 6 Picos'!E11 -> 3 | C11: ='Calendario de 6 Picos'!P11 -> 2.6 | D11: =IFERROR('Parámetros'!$B$7*C11,"") -> 1237.6 | E11: =IFERROR(D11*B11,"") -> 3712.8 | F11: 16 | G11: =IFERROR('Parámetros'!$B$11*F11,"") -> 960 | H11: =IFERROR(MAX(0,D11-G11),"") -> 277.6 | I11: =IFERROR(H11*B11,"") -> 832.8 | J11: 10 | K11: =IFERROR(MIN(I11,MAX(0,'Parámetros'!$B$12)*J11),"") -> 40 | L11: =IFERROR(MAX(0,I11-K11),"") -> 792.8 | M11: =IFERROR((E11-K11)/B11/'Parámetros'!$B$11,"") -> 20.404444 | N11: =IF(L11="","",IF(L11<=0,"Sí","No")) -> No | O11: =IFERROR(L11/'Parámetros'!$B$11,"") -> 13.213333 | P11: =IFERROR(ROUNDUP(O11/(B11*'Parámetros'!$B$14),0),"") -> 1 | Q11: =IF(L11="","",IF(L11<=0,"Con estas horas y este adelanto, la campaña cabe.",IF(M11>'Parámetros'!$B$13,"No cabe ni con el día entero: hay que adelantar y congelar más, o recortar el surtido de campaña.","Cabe alargando el turno con refuerzo: mira la hoja Refuerzo y Tesorería."))) -> Cabe alargando el turno con refuerzo: mira la hoja Refuerzo y Tesorería.
A13: TOTAL DE LAS SEIS CAMPAÑAS | E13: =SUM(E6:E11) -> 47695.2 | I13: =SUM(I6:I11) -> 16495.2 | K13: =SUM(K6:K11) -> 180 | L13: =SUM(L6:L11) -> 16315.2 | N13: =COUNTIF(N6:N11,"No") -> 6 | O13: campañas que NO aguantas
A15: Cómo se lee: la demanda del pico sale de multiplicar tus piezas de un día normal por el factor de la campaña. La capacidad sale de las piezas por hora del equipo que te limita por las horas que tengas el obrador en marcha. La diferencia es el déficit, y se ataca en este orden: primero horas de máquina, después producción adelantada y congelada, y sólo al final refuerzo de personal, que es lo que cuesta dinero todos los días de la campaña.
A16: Las piezas que puedes adelantar están limitadas por el excedente de un día normal: si en crucero ya vas al límite, no tienes de dónde sacarlas. Y por lo que te quepa en el congelador, que esta hoja no sabe. Comprueba los metros cúbicos antes de dar por buena la cifra.
A17: Lo que NO se puede adelantar: todo lo que el art. 9.3 del RD 1021/2022 obliga a consumir en 24 horas desde su elaboración, y lo relleno no estable que va a 4 °C por la fila 9 del art. 4.1. El roscón relleno de nata es el caso de manual: se hace el mismo día. Los huesos de santo, que son estables a temperatura ambiente, sí se adelantan. Ese detalle legal ES la planificación de la campaña, y la hoja «Decisión de Huevo y Temperatura» del libro «carta-de-apertura-y-escandallo.xlsx» dice cuál es cuál.
A19: Versión 1.0 · septiembre 2026 · aichef.pro/guia-pasteleria-obrador · info@aichef.pro

Sheet Refuerzo y Tesorería
A1: Refuerzo y Tesorería
A2: AI Chef Pro · aichef.pro — Cómo Montar una Pastelería
A3: Cuánto cuesta el refuerzo con la Seguridad Social dentro, y cuánto dinero deja parado cada campaña.
A5: Campaña | B5: Personas de refuerzo | C5: Horas por persona en la campaña | D5: Horas totales de refuerzo | E5: Coste hora de empresa (€) | F5: Coste del refuerzo (€) | G5: Personas necesarias | H5: ¿Cubre el refuerzo? | I5: Coste de materia por unidad (€) | J5: Uds de toda la campaña | K5: Compra de materia de la campaña (€) | L5: Antelación de compra (semanas) | M5: Días con el dinero parado | N5: Coste financiero del inmovilizado (€) | O5: Materia de las uds incrementales (€) | P5: Facturación incremental sin IVA (€) | Q5: Resultado incremental de la campaña (€) | R5: Qué mirar en esta campaña
A6: Reyes | B6: 3 | C6: 40 | D6: =IFERROR(B6*C6,"") -> 120 | E6: ='Parámetros'!$B$21 -> 13.364483 | F6: =IFERROR(D6*E6,"") -> 1603.7379 | G6: ='Capacidad vs Demanda del Pico'!P6 -> 4 | H6: =IF(G6="","",IF(B6>=G6,"Sí","No")) -> No | I6: 2.5988 | J6: ='Calendario de 6 Picos'!M6 -> 2100 | K6: =IFERROR(I6*J6,"") -> 5457.48 | L6: ='Calendario de 6 Picos'!Q6 -> 6 | M6: =IFERROR(L6*7+'Calendario de 6 Picos'!E6,"") -> 47 | N6: =IFERROR(K6*'Parámetros'!$B$24*M6/365,"") -> 43.570128 | O6: =IFERROR(I6*'Calendario de 6 Picos'!L6*'Calendario de 6 Picos'!E6,"") -> 5457.48 | P6: ='Calendario de 6 Picos'!O6 -> 31500 | Q6: =IFERROR(P6-O6-F6-N6,"") -> 24395.212 | R6: La campaña que decide el año. Seis semanas de antelación de compra: la almendra, la naranja confitada y el agua de azahar se piden en noviembre. El roscón relleno no se puede adelantar: 4 °C y 24 horas.
A7: San Valentín | B7: 0 | C7: 0 | D7: =IFERROR(B7*C7,"") -> 0 | E7: ='Parámetros'!$B$21 -> 13.364483 | F7: =IFERROR(D7*E7,"") -> 0 | G7: ='Capacidad vs Demanda del Pico'!P7 -> 1 | H7: =IF(G7="","",IF(B7>=G7,"Sí","No")) -> No | I7: 0.1965 | J7: ='Calendario de 6 Picos'!M7 -> 520 | K7: =IFERROR(I7*J7,"") -> 102.18 | L7: ='Calendario de 6 Picos'!Q7 -> 3 | M7: =IFERROR(L7*7+'Calendario de 6 Picos'!E7,"") -> 23 | N7: =IFERROR(K7*'Parámetros'!$B$24*M7/365,"") -> 0.39920186 | O7: =IFERROR(I7*'Calendario de 6 Picos'!L7*'Calendario de 6 Picos'!E7,"") -> 64.845 | P7: ='Calendario de 6 Picos'!O7 -> 630 | Q7: =IFERROR(P7-O7-F7-N7,"") -> 564.7558 | R7: Dos días y ticket alto: se gana con cajas y presentación, no con más horno. El refuerzo sale a CERO personas y CERO euros a propósito -la persona que hace falta ya está en la plantilla base-, y por eso «¿Cubre el refuerzo?» dice «No»: no es un fallo, es que aquí no se contrata refuerzo, se cubre con plantilla.
A8: Día del Padre y de la Madre | B8: 1 | C8: 16 | D8: =IFERROR(B8*C8,"") -> 16 | E8: ='Parámetros'!$B$21 -> 13.364483 | F8: =IFERROR(D8*E8,"") -> 213.83172 | G8: ='Capacidad vs Demanda del Pico'!P8 -> 1 | H8: =IF(G8="","",IF(B8>=G8,"Sí","No")) -> Sí | I8: 1.1523 | J8: ='Calendario de 6 Picos'!M8 -> 384 | K8: =IFERROR(I8*J8,"") -> 442.4832 | L8: ='Calendario de 6 Picos'!Q8 -> 3 | M8: =IFERROR(L8*7+'Calendario de 6 Picos'!E8,"") -> 25 | N8: =IFERROR(K8*'Parámetros'!$B$24*M8/365,"") -> 1.8790382 | O8: =IFERROR(I8*'Calendario de 6 Picos'!L8*'Calendario de 6 Picos'!E8,"") -> 368.736 | P8: ='Calendario de 6 Picos'!O8 -> 1047.2727 | Q8: =IFERROR(P8-O8-F8-N8,"") -> 462.82597 | R8: Dos fechas con el mismo patrón de trabajo -tarta con dedicatoria, por encargo- y por eso van juntas como una sola campaña operativa.
A9: Semana Santa | B9: 1 | C9: 40 | D9: =IFERROR(B9*C9,"") -> 40 | E9: ='Parámetros'!$B$21 -> 13.364483 | F9: =IFERROR(D9*E9,"") -> 534.5793 | G9: ='Capacidad vs Demanda del Pico'!P9 -> 1 | H9: =IF(G9="","",IF(B9>=G9,"Sí","No")) -> Sí | I9: 0.2601 | J9: ='Calendario de 6 Picos'!M9 -> 1920 | K9: =IFERROR(I9*J9,"") -> 499.392 | L9: ='Calendario de 6 Picos'!Q9 -> 4 | M9: =IFERROR(L9*7+'Calendario de 6 Picos'!E9,"") -> 36 | N9: =IFERROR(K9*'Parámetros'!$B$24*M9/365,"") -> 3.0538163 | O9: =IFERROR(I9*'Calendario de 6 Picos'!L9*'Calendario de 6 Picos'!E9,"") -> 499.392 | P9: ='Calendario de 6 Picos'!O9 -> 4189.0909 | Q9: =IFERROR(P9-O9-F9-N9,"") -> 3152.0658 | R9: Ocho días seguidos de producción extra, más agotador que los cinco de Reyes aunque el pico sea menor. Torrijas y monas a la vez: una pide freidora y frío, la otra horno y chocolate.
A10: Comuniones | B10: 1 | C10: 60 | D10: =IFERROR(B10*C10,"") -> 60 | E10: ='Parámetros'!$B$21 -> 13.364483 | F10: =IFERROR(D10*E10,"") -> 801.86896 | G10: ='Capacidad vs Demanda del Pico'!P10 -> 1 | H10: =IF(G10="","",IF(B10>=G10,"Sí","No")) -> Sí | I10: 0.7584 | J10: ='Calendario de 6 Picos'!M10 -> 680 | K10: =IFERROR(I10*J10,"") -> 515.712 | L10: ='Calendario de 6 Picos'!Q10 -> 5 | M10: =IFERROR(L10*7+'Calendario de 6 Picos'!E10,"") -> 55 | N10: =IFERROR(K10*'Parámetros'!$B$24*M10/365,"") -> 4.8180217 | O10: =IFERROR(I10*'Calendario de 6 Picos'!L10*'Calendario de 6 Picos'!E10,"") -> 364.032 | P10: ='Calendario de 6 Picos'!O10 -> 1527.2727 | Q10: =IFERROR(P10-O10-F10-N10,"") -> 356.55375 | R10: No es un pico, es una meseta de dos meses: se aguanta con plantilla, no con horas extra, y por eso los días de adelanto van a cero. Todo por encargo, con anticipo y riesgo de anulación.
A11: Todos los Santos | B11: 2 | C11: 24 | D11: =IFERROR(B11*C11,"") -> 48 | E11: ='Parámetros'!$B$21 -> 13.364483 | F11: =IFERROR(D11*E11,"") -> 641.49516 | G11: ='Capacidad vs Demanda del Pico'!P11 -> 1 | H11: =IF(G11="","",IF(B11>=G11,"Sí","No")) -> Sí | I11: 0.1695 | J11: ='Calendario de 6 Picos'!M11 -> 1560 | K11: =IFERROR(I11*J11,"") -> 264.42 | L11: ='Calendario de 6 Picos'!Q11 -> 4 | M11: =IFERROR(L11*7+'Calendario de 6 Picos'!E11,"") -> 31 | N11: =IFERROR(K11*'Parámetros'!$B$24*M11/365,"") -> 1.3923705 | O11: =IFERROR(I11*'Calendario de 6 Picos'!L11*'Calendario de 6 Picos'!E11,"") -> 264.42 | P11: ='Calendario de 6 Picos'!O11 -> 2269.0909 | Q11: =IFERROR(P11-O11-F11-N11,"") -> 1361.7834 | R11: Tres días con tres referencias que sólo se hacen ahora. Los buñuelos van rellenos (4 °C y 24 horas) y los huesos de santo son estables a temperatura ambiente: por eso éstos sí se adelantan y aquéllos no.
A13: TOTAL DEL AÑO | D13: =SUM(D6:D11) -> 284 | F13: =SUM(F6:F11) -> 3795.5131 | H13: =COUNTIF(H6:H11,"No") -> 2 | I13: campañas con refuerzo corto | K13: =SUM(K6:K11) -> 7281.6672 | N13: =SUM(N6:N11) -> 55.112577 | O13: =SUM(O6:O11) -> 7018.905 | P13: =SUM(P6:P11) -> 41162.727 | Q13: =SUM(Q6:Q11) -> 30293.197
A15: El coste hora de empresa no es el bruto: es el bruto por las pagas del convenio, más la Seguridad Social a cargo de la empresa, dividido por las horas anuales de contrato. Sale de la hoja «Parámetros» y en el ejemplo es casi un tercio más que el bruto. Contratar refuerzo por debajo de ese número es contratar a pérdida.
A16: La «compra de materia de la campaña» es el dinero que sale de tu caja ANTES de que entre el primero de la campaña. Multiplicado por los días que está parado y por el coste del dinero, tienes el coste financiero de la campaña, que casi nadie cuenta y que en Reyes es real.
A17: El «resultado incremental» descuenta sólo lo que la campaña añade: la materia de las unidades de más, el refuerzo y el coste financiero. No descuenta alquiler ni personal fijo, que los pagas igual. Si sale negativo, la campaña te está costando dinero.
A18: Frontera con el Kit de Tareas Pastelería (12 €): el «BONUS-02-calendario-anual-tareas.xlsx» te dice QUÉ hacer y CUÁNDO en cada campaña, y el «06-eventos-festivos.xlsx» lleva el detalle de cada evento. Este libro te dice CUÁNTO cuesta y SI aguantas. Si ya tienes el kit, sustituye las estimaciones de unidades por tus datos reales de producción del «10-plan-produccion-semanal.xlsx».
A20: Versión 1.0 · septiembre 2026 · aichef.pro/guia-pasteleria-obrador · info@aichef.pro
