Workbook

Sheet 0. Supuestos
A1: SUPUESTOS — aquí se teclean las TASAS y los DRIVERS del modelo
A2: Cambia las celdas VERDES: el resto del libro se recalcula solo. Las partidas de gasto se teclean en su hoja (también en verde) y no se repiten aquí.
A3: ACTIVIDAD
A4: Transacciones/día (media del año 1) | B4: 180 | C4: Transacciones servidas al día de media del año (barra de pan, bollería y café, más lo que recoge el canal mayorista). Dentro del rango 80-200 que este mismo libro publica en «Escenarios» (pesimista/optimista): el «objetivo» de la v1.1 (148) era una cifra DERIVADA de la facturación buscada, no un input real. Con menos transacciones el resultado neto se quedaba por debajo del 5 % que este libro fija como suelo, porque los costes fijos (personal, alquiler, seguros…) no crecen con el volumen y cada transacción de más va casi entera al resultado. OJO: el caso base es exigente por los DOS lados a la vez —el 90 % del volumen del escenario optimista que publica «Escenarios» y el ticket de ese mismo escenario optimista—; si sólo se cumple uno de los dos, el resultado neto cae por debajo de ese suelo. Contrástalo con tu zona antes de darlo por bueno
A5: Ticket medio SIN IVA (€) | B5: 5.5 | C5: SIN IVA. Dentro del rango 3-6 € que este mismo kit declara en la tabla «Datos de referencia del sector» de la hoja de Instrucciones («Ticket medio panadería»), en el tercio alto porque incluye bollería y café además de la barra de pan, no sólo la barra. Ojo: coincide con el ticket que la versión anterior usaba en su escenario OPTIMISTA, así que compruébalo con tu carta antes de darlo por bueno — si tu ticket real es menor, bájalo aquí y mira qué le pasa al resultado
A6: Días de apertura al año | B6: 310 | C6: El MISMO dato lo usan el P&L, el punto de equilibrio y los escenarios: el fichero v1.1 tenía DOS calendarios distintos («Punto Equilibrio!C8»: «30 días apertura», mensual; «Escenarios!C7»: 310 días/año, realista)
A7: Crecimiento de volumen del año 2 | B7: 0.12 | C7: Segundo año con el canal mayorista (restaurantes y hoteles) ya consolidado y sin gastos de lanzamiento. Muy por debajo del salto que proyectaba la versión anterior de este libro (de 200.000 € a 250.000 €, un 25 %)
A8: Crecimiento de volumen del año 3 | B8: 0.07 | C8: Tercer año, cerca del techo de producción del horno instalado. La versión anterior proyectaba un 20 % de subida en este año
A9: PVP equivalente con IVA (calculado) | B9: =IFERROR(IF($B$5="","",$B$5*(1+SUMPRODUCT('PyG 3 Años'!$E$10:$E$11,'PyG 3 Años'!$G$10:$G$11))),"") -> 5.81801 | C9: =IFERROR("Ticket sin IVA más el IVA medio ponderado de tus líneas de venta: "&TEXT(SUMPRODUCT('PyG 3 Años'!$E$10:$E$11,'PyG 3 Años'!$G$10:$G$11)*100,"0")&" %. En mostrador todo va al 10 % (art. 91.Uno.2.2.º de la Ley 37/1992, alcohol incluido); el alcohol que sale por delivery y el pan común, si los tienes, mueven la media. Aquí va redondeado. Compáralo con el rango del sector, que va con IVA.","") -> Ticket sin IVA más el IVA medio ponderado de tus líneas de venta: 6 %. En mostrador todo va al 10 % (art. 91.Uno.2.2.º de la Ley 37/1992, alcohol incluido); el alcohol que sale por delivery y el pan común, si los tienes, mueven la media. Aquí va redondeado. Compáralo con el rango del sector, que va con IVA.
A10: MIX Y COSTE DE MERCANCÍA
A11: Ventas de COMIDA sobre el total | B11: 0.925 | C11: Peso de la COMIDA sobre el total de ventas. Es un INPUT: cámbialo aquí y el P&L, la tesorería y el IVA repercutido se recalculan solos
A12: Ventas de BEBIDA sobre el total | B12: =IFERROR(IF(COUNT(B11)=0,"",1-B11),"") -> 0.075 | C12: Se calcula como el resto: comida + bebida = 100 %
A13: Coste de mercancía sobre las ventas de COMIDA | B13: 0.29 | C13: Food cost de pan y bollería, ponderado con los rangos que este mismo kit publica en la tabla «Datos de referencia del sector» de la hoja de Instrucciones: pan 25-30 % y bollería 32-38 %. El pan pesa más del mix, así que el blend queda cerca del extremo bajo del rango de bollería
A14: Coste de mercancía sobre las ventas de BEBIDA | B14: 0.27 | C14: Coste de café y bebidas sobre sus propias ventas: dentro del 25-30 % que declara la tabla «Datos de referencia del sector» de la hoja de Instrucciones de este mismo libro
A15: Consumibles sobre ventas | B15: 0.02 | C15: Bolsas de papel, cajas de bollería y servilletas de mostrador
A16: Ventas por delivery sobre el total | B16: 0 | C16: A CERO por defecto: el pan recién horneado no viaja bien y este plan no lo vende a domicilio el día 1. Súbelo si activas un canal de reparto de bollería/desayunos
A17: Comisión de la plataforma de delivery | B17: 0.3 | C17: Comisión típica de Glovo/Uber Eats sobre el pedido servido por ese canal, si algún día lo activas
A18: Comisión de los medios de pago | B18: 0.008 | C18: Tarjeta y bizum sobre el total facturado en tienda
A19: PERSONAL
A20: Seguridad Social a cargo de la empresa | B20: 0.33 | C20: Contingencias comunes + AT/EP + desempleo + FOGASA + FP; ajusta a tu convenio y bonificaciones
A21: Número de pagas anuales | B21: 14 | C21: Salario bruto anual = bruto mensual × pagas
A22: SMI anual de referencia (€) | B22: 17094 | C22: SMI 2026: 17.094 € al año (1.221 €/mes en 14 pagas), suelo legal por jornada completa. Comprueba el importe vigente si presentas el plan en otro ejercicio
A23: LOCAL Y FIJOS
A24: Alquiler mensual del local (€) | B24: 2100 | C24: Local de obrador + tienda (mínimo 80 m² entre obrador, tienda y almacén, checklist F2). Lo que pesa sobre las ventas lo calcula el propio libro en la fila «Alquiler / Ventas» del bloque de ratios del P&L: en el caso base queda por DEBAJO del 10-14 % que la tabla de referencias de la hoja de Instrucciones da como habitual del sector
A25: Fianza del alquiler (meses) | B25: 3 | C25: Tres meses de renta, como en el contrato tipo de local de negocio
A26: Suministros mensuales de luz, agua y gas (€) | B26: 875 | C26: Luz (hornos, potencia 30-40 kW — checklist F2), agua y gas: pide el histórico del local antes de firmar
A27: Seguros (€/año) | B27: 2100 | C27: Responsabilidad civil (mínimo 300.000 € — checklist F1) + multirriesgo del local con hornos («incendio crítico por hornos», checklist F2)
A28: Varios e imprevistos sobre ventas | B28: 0.02 | C28: Colchón de gasto corriente no presupuestado
A29: FINANCIACIÓN
A30: Recursos propios aportados (€) | B30: 50000 | C30: Aportación de los socios. Con menos, el banco no entra: pide un 25-30 % de fondos propios sobre la necesidad de caja de este plan
A31: Préstamo bancario solicitado (€) | B31: 120000 | C31: Principal solicitado. La hoja de Financiación comprueba que origen y usos cuadran con la necesidad de caja calculada en la hoja 1
A32: Tipo de interés nominal anual | B32: 0.06 | C32: Tipo nominal anual; pide oferta a dos entidades y a una línea ICO antes de fijarlo (el horno y la maquinaria de un obrador son objeto habitual de leasing/renting: compáralo)
A33: Plazo del préstamo (años) | B33: 7 | C33: Años totales, carencia incluida
A34: Carencia de principal (años) | B34: 1 | C34: Primer año pagando sólo intereses, que es cuando la caja está más tensa (obra y maquinaria antes de facturar nada). Al salir de la carencia la devolución del principal entra de golpe: la hoja de Punto de Equilibrio mide esa holgura año a año
A35: Fondo de maniobra (meses de costes fijos) | B35: 3 | C35: Mínimo que exige este mismo libro (Instrucciones): un colchón por debajo de 3 meses no cubre un bache de temporada baja
A36: FISCAL
A37: Impuesto de Sociedades, nueva creación | B37: 0.15 | C37: Art. 29.1 LIS: el PRIMER ejercicio con base imponible positiva y el SIGUIENTE. El libro lo aproxima contando los dos primeros ejercicios con base positiva: coincide con la ley salvo que entre ellos haya un ejercicio en pérdidas
A38: Impuesto de Sociedades, tipo general | B38: 0.25 | C38: A partir del tercer ejercicio con base positiva. Es el tipo general del art. 29.1 LIS: si tu cifra de negocios queda por debajo de 1 M € (microempresa) o de 10 M € (reducida dimensión), desde 2025 hay tipos más bajos que se implantan de forma gradual; confirma el de tu ejercicio con tu asesor y cámbialo aquí
A39: IVA repercutido de restauración | B39: 0.1 | C39: Tipo reducido de hostelería
A40: IVA repercutido/soportado general | B40: 0.21 | C40: Tipo general. En este libro lo usan dos cosas: el IVA que soportas al comprar el alcohol (el proveedor lo factura al 21 %) y el que repercutes por el alcohol que sale por delivery (es una entrega de bienes). El alcohol servido en mostrador va al reducido: su tipo está en el bloque de desglose del IVA. Suministros, equipamiento y servicios tienen su tipo en la celda de abajo. El libro manda al general sólo el alcohol: si compras refrescos o zumos con azúcares añadidos, su factura también va al 21 % (art. 91.Uno.1.1.º de la Ley 37/1992)
A41: IVA soportado en compras e inversión | B41: 0.21 | C41: Recuperable vía modelo 303, pero hay que adelantarlo
A42: Bases negativas de ejercicios anteriores (€) | B42: 0 | C42: Pérdidas pendientes de compensar al empezar (art. 26 LIS)
A43: AMORTIZACIÓN
A44: Vida útil de obra e instalaciones (años) | B44: 10 | C44: Obra, instalación eléctrica de potencia y salida de humos de un obrador. Coeficientes de la tabla del art. 12.1 LIS: confírmalo con tu asesor
A45: Vida útil de maquinaria y mobiliario (años) | B45: 9 | C45: Horno, amasadora, divisora, cámaras y vitrina. El coeficiente lineal máximo del art. 12.1 LIS para maquinaria es del 12 % anual: por debajo de 9 años el exceso no sería deducible. Confírmalo con tu asesor
A47: CRECIMIENTO Y ACTUALIZACIÓN DE COSTES
A48: Subida anual de los costes fijos | B48: 0 | C48: A CERO: las tres columnas están en euros del año 1 (términos reales). Súbela si quieres proyectar en euros corrientes
A49: ARRANQUE Y AFORO
A51: Aforo del local (plazas sentadas + barra) | B51: 15 | C51: La mayoría de las transacciones son de mostrador (llevar), no de mesa: este número cubre sólo el rincón de café con asientos, no la cola de la barra de pan. Sirve para dimensionar el espacio de consumo del local; el volumen del negocio se proyecta con las transacciones de mostrador, no con la rotación de las plazas
A52: Actividad del mes 1 sobre la de crucero | B52: 0.55 | C52: Un local que abre no factura desde el primer día lo mismo que a los seis meses. Con 100 % se elimina la rampa y el año 1 se proyecta a velocidad de crucero
A53: Meses hasta alcanzar el régimen de crucero | B53: 6 | C53: La rampa sube en línea recta desde el porcentaje de arriba hasta el 100 % en este número de meses
A54: Meses de alquiler ANTES de abrir (obra y licencias) | B54: 1 | C54: El local se paga desde que se firma. Estos meses son inversión: NO se solapan con el P&L, que arranca el día de la apertura
A55: Imprevistos sobre las partidas de OBRA del bloque de local (%) | B55: 0.1 | C55: Colchón sobre la partida de obra y acondicionamiento. Un banco no financia una reforma sin él
A57: COBROS, PAGOS Y DESGLOSE DEL IVA
A58: Días medios de cobro | B58: 3 | C58: Media ponderada: el mostrador cobra al contado (0 días) y el canal mayorista —restaurantes y hoteles— paga a 30 días, que es el plazo por defecto del art. 4 de la Ley 3/2004 contra la morosidad (60 como máximo, y sólo si se pacta). Con el peso que este plan da al mayorista salen 3 días de media: súbelo si tu reparto a otros negocios pesa más
A59: Días medios de pago a proveedor | B59: 30 | C59: Lo que te financian tus proveedores. Es lo primero que se pierde si te retrasas en un pago
A60: Mes de la paga extra de verano | B60: 7 | C60: Mes del año (1-12) en el que sale de caja la primera paga extra
A61: Mes de la paga extra de Navidad | B61: 12 | C61: Mes del año (1-12) en el que sale de caja la segunda paga extra
A62: Bebida ALCOHÓLICA sobre el total de bebida | B62: 0 | C62: A CERO: la línea de bebida de este plan es café e infusiones, sin alcohol (a diferencia de cafetería, que sí sirve algún mimosa de celebración). Si añades cava para desayunos de celebración, sube este parámetro
A63: IVA de la bebida ALCOHÓLICA servida en mostrador | B63: 0.1 | C63: 10 %, igual que el resto del consumo en mostrador: el art. 91.Uno.2.2.º de la Ley 37/1992 del IVA grava al tipo reducido los servicios de hostelería y «el suministro de comidas y bebidas para consumir en el acto», sin excluir el alcohol. El 21 % es el tipo GENERAL y, fuera del consumo en el acto, alcanza al alcohol y también a los refrescos y zumos con azúcares o edulcorantes añadidos vendidos para llevar o a domicilio (art. 91.Uno.1.1.º de la misma ley). El libro lo aplica sólo a la parte ALCOHÓLICA de la bebida que sale por el canal de la celda «Ventas por delivery sobre el total»; los refrescos azucarados repartidos irían también al general y el libro no los separa
A64: UMBRALES Y SUELOS DE CONTROL
A65: DSCR mínimo aceptable | B65: 1 | C65: Por debajo de 1 el negocio no genera para pagar el préstamo. Ponlo en el covenant que te exija tu banco
A66: DSCR objetivo (verde) | B66: 1.25 | C66: Lo que suele pedir una entidad para dar el préstamo sin garantías adicionales
A67: Holgura mínima sobre el punto de equilibrio | B67: 0.15 | C67: Cuánto deben superar las ventas previstas a las del punto de equilibrio. La caída que aguantas antes de entrar en pérdidas es algo menor: con un 15 % de holgura, un 13 % de lo previsto
A68: Suelo salarial anual del convenio provincial (€) | B68: 0 | C68: El convenio PROVINCIAL de panadería/pastelería, no el SMI, es el suelo real del sector: cópialo de la tabla salarial de tu provincia («Convenio hostelería/alimentación», checklist F4). Con 0 el semáforo compara sólo contra el SMI

Sheet Inversión Inicial
A1: PLAN DE NEGOCIO: PANADERÍA / OBRADOR
A2: Inversión Inicial — España 2026
A3: Ajusta las cifras a tu proyecto.
A5: Concepto | B5: Importe | C5: % s/inversión | D5: Notas | E5: ¿Lleva IVA?
A6: INVERSIÓN | B6: =IFERROR(IF(COUNT(B7:B28)=0,"",SUM(B7:B28)),"") -> 101600 | C6: =IFERROR(B6/$B$31,"") -> 0.69965067
A7: Constitución SL + notaría | B7: 800 | C7: =IFERROR(B7/$B$31,"") -> 0.0055090604 | D7: SL unipersonal express | E7: No
A8: Licencia actividad (clasificada) | B8: 1200 | C8: =IFERROR(B8/$B$31,"") -> 0.0082635906 | D8: Obrador con horno = actividad clasificada | E8: No
A9: Proyecto técnico + certificación | B9: 3500 | C9: =IFERROR(B9/$B$31,"") -> 0.024102139 | D9: Obligatorio: salida humos, potencia eléctrica | E9: Sí
A10: Obra civil y adecuación local | B10: 20000 | C10: =IFERROR(B10/$B$31,"") -> 0.13772651 | D10: Suelo técnico, revestimientos lavables, obrador | E10: Sí
A11: Instalación eléctrica (potencia 30-40 kW) | B11: 7000 | C11: =IFERROR(B11/$B$31,"") -> 0.048204279 | D11: Hornos eléctricos consumen mucha potencia | E11: Sí
A12: Salida humos + ventilación obrador | B12: 5000 | C12: =IFERROR(B12/$B$31,"") -> 0.034431628 | D12: Obligatoria: campana + extractor + filtros | E12: Sí
A13: Horno de pisos / rotativo profesional | B13: 18000 | C13: =IFERROR(B13/$B$31,"") -> 0.12395386 | D13: Horno de pisos (artesanal) o rotativo (volumen) | E13: Sí
A14: Amasadora espiral (25-50 kg) | B14: 4000 | C14: =IFERROR(B14/$B$31,"") -> 0.027545302 | D14: Capacidad según producción diaria | E14: Sí
A15: Divisora + boleadora | B15: 3000 | C15: =IFERROR(B15/$B$31,"") -> 0.020658977 | D15: Para producción en serie de piezas | E15: Sí
A16: Cámara de fermentación controlada | B16: 5000 | C16: =IFERROR(B16/$B$31,"") -> 0.034431628 | D16: Fermentación lenta programable, clave calidad | E16: Sí
A17: Cámara frigorífica + congelador | B17: 4000 | C17: =IFERROR(B17/$B$31,"") -> 0.027545302 | D17: Almacén materia prima + masa congelada | E17: Sí
A18: Mesa de trabajo inox + estanterías | B18: 2500 | C18: =IFERROR(B18/$B$31,"") -> 0.017215814 | D18: Superficie de trabajo obrador | E18: Sí
... A25: Stock inicial (harinas, levaduras, etc.) | B25: 1500 | C25: =IFERROR(B25/$B$31,"") -> 0.010329488 | D25: Harina fuerza, centeno, masa madre, levadura | E25: Sí
A26: Fianza del alquiler | B26: =IFERROR(IF('0. Supuestos'!$B$24="","",'0. Supuestos'!$B$24*'0. Supuestos'!$B$25),"") -> 6300 | C26: =IFERROR(B26/$B$31,"") -> 0.043383851 | D26: =IFERROR(""&TEXT('0. Supuestos'!$B$25,"0")&" meses de renta, al tipo de la hoja de Supuestos. Es un activo recuperable al cerrar: ni se amortiza ni lleva IVA","") -> 3 meses de renta, al tipo de la hoja de Supuestos. Es un activo recuperable al cerrar: ni se amortiza ni lleva IVA | E26: No
A27: Alquiler de los meses previos a la apertura | B27: =IFERROR(IF('0. Supuestos'!$B$24="","",'0. Supuestos'!$B$24*'0. Supuestos'!$B$54),"") -> 2100 | C27: =IFERROR(B27/$B$31,"") -> 0.014461284 | D27: =IFERROR("Renta "&IF('0. Supuestos'!$B$54=1,"del mes","de los "&TEXT('0. Supuestos'!$B$54,"0")&" meses")&" de obra y licencias. NO se solapa con el P&L, que arranca el día de la apertura: los doce meses del P&L son los doce de explotación","") -> Renta del mes de obra y licencias. NO se solapa con el P&L, que arranca el día de la apertura: los doce meses del P&L son los doce de explotación | E27: Sí
A28: Imprevistos de obra y acondicionamiento | B28: =IFERROR(IF(COUNT(B9,B10,B11,B12,B23)=0,"",ROUND((B9+B10+B11+B12+B23)*'0. Supuestos'!$B$55,0)),"") -> 3700 | C28: =IFERROR(B28/$B$31,"") -> 0.025479404 | D28: =IFERROR("Al "&TEXT('0. Supuestos'!$B$55,"0%")&" de las partidas de OBRA Y ACONDICIONAMIENTO de este bloque (Proyecto técnico + certificación, Obra civil y adecuación local, Instalación eléctrica (potencia 30-40 kW), Salida humos + ventilación obrador y Rotulación + imagen exterior), no "&"del bloque entero: el resto de partidas del bloque quedan fuera. Un banco no financia una reforma sin colchón: el porcentaje está en la hoja de Supuestos","") -> Al 10% de las partidas de OBRA Y ACONDICIONAMIENTO de este bloque (Proyecto técnico + certificación, Obra civil y adecuación local, Instalación eléctrica (potencia 30-40 kW), Salida humos + ventilación obrador y Rotulación + imagen exterior), no del bloque entero: el resto de partidas del bloque quedan fuera. Un banco no financia una reforma sin colchón: el porcentaje está en la hoja de Supuestos | E28: Sí
A29: FONDO DE MANIOBRA | B29: =IFERROR(IF(B30="","",B30),"") -> 43615.325 | C29: =IFERROR(B29/$B$31,"") -> 0.30034933
A30: Colchón operativo hasta alcanzar el equilibrio | B30: =IFERROR(IF('0. Supuestos'!$B$35*('PyG 3 Años'!$B$38-'PyG 3 Años'!$B$36)=0,"",'0. Supuestos'!$B$35*('PyG 3 Años'!$B$38-'PyG 3 Años'!$B$36)/12),"") -> 43615.325 | C30: =IFERROR(B30/$B$31,"") -> 0.30034933 | D30: =IFERROR("Cubre "&TEXT('0. Supuestos'!$B$35,"0")&IF('0. Supuestos'!$B$35=1," mes"," meses")&" de costes fijos DE CAJA del año 1 (los del P&L menos la amortización, que no se paga), que es el mínimo que exigen las Instrucciones de este libro","") -> Cubre 3 meses de costes fijos DE CAJA del año 1 (los del P&L menos la amortización, que no se paga), que es el mínimo que exigen las Instrucciones de este libro | E30: No
A31: INVERSIÓN TOTAL (suma de los bloques) | B31: =IFERROR(B6+B29,"") -> 145215.33 | D31: =IFERROR("Los porcentajes de la columna C se leen sobre esta cifra, que incluye el fondo de maniobra ("&TEXT(C29,"0%")&" del total). Para comparar el desglose con otro plan, usa la fila de CAPEX de abajo.","") -> Los porcentajes de la columna C se leen sobre esta cifra, que incluye el fondo de maniobra (30% del total). Para comparar el desglose con otro plan, usa la fila de CAPEX de abajo.
A32: CAPEX (inversión sin el fondo de maniobra) | B32: =IFERROR(B31-B29,"") -> 101600 | D32: Es lo que se compra: obra, equipamiento, lanzamiento y gastos de constitución. El colchón de caja no es inversión, es circulante
A33: IVA soportado sobre la inversión (recuperable) | B33: =IFERROR(IF(B31="","",SUMIF($E$7:$E$28,"Sí",$B$7:$B$28)*'0. Supuestos'!$B$41),"") -> 19593 | D33: =IFERROR("Al "&TEXT('0. Supuestos'!$B$41,"0%")&" sobre las partidas marcadas con «Sí» en la columna de IVA. Las tasas y licencias no están sujetas y los seguros están exentos (art. 20.Uno.16 LIVA). Las tasas y aranceles registrales no llevan IVA; los honorarios de notaría y gestoría sí "&"(21 %, deducible). Se recupera con el modelo 303, pero hay que adelantarlo","") -> Al 21% sobre las partidas marcadas con «Sí» en la columna de IVA. Las tasas y licencias no están sujetas y los seguros están exentos (art. 20.Uno.16 LIVA). Las tasas y aranceles registrales no llevan IVA; los honorarios de notaría y gestoría sí (21 %, deducible). Se recupera con el modelo 303, pero hay que adelantarlo
A34: NECESIDAD TOTAL DE CAJA AL ARRANQUE | B34: =IFERROR(B31+B33,"") -> 164808.33 | D34: Es la cifra que tiene que cubrir la hoja de Financiación
A35: BASES DE AMORTIZACIÓN (no suman a la inversión)
A36: Obra, instalaciones y acondicionamiento | B36: =IFERROR(IF(B9="","",B9+B10+B11+B12+B23+B28),"") -> 40700 | D36: =IFERROR("Se amortiza en "&TEXT('0. Supuestos'!$B$44,"0")&" años","") -> Se amortiza en 10 años
A37: Maquinaria, mobiliario y equipos | B37: =IFERROR(IF(B13="","",B13+B14+B15+B16+B17+B18+B19+B20+B21+B22),"") -> 47000 | D37: =IFERROR("Se amortiza en "&TEXT('0. Supuestos'!$B$45,"0")&" años","") -> Se amortiza en 9 años
A38: Amortización anual del inmovilizado | B38: =IFERROR(B36/MAX(1,'0. Supuestos'!$B$44)+B37/MAX(1,'0. Supuestos'!$B$45),"") -> 9292.2222 | D38: =IFERROR("No se amortizan, por no ser inmovilizado, Constitución SL + notaría, Licencia actividad (clasificada), Marketing lanzamiento, Stock inicial (harinas, levaduras, etc.), Fianza del alquiler, Alquiler de los meses previos a la apertura ni "&"Colchón operativo hasta alcanzar el equilibrio. Suman "&TEXT(B31-B36-B37,"0")&" € de los "&TEXT(B31,"0")&" € de inversión.","") -> No se amortizan, por no ser inmovilizado, Constitución SL + notaría, Licencia actividad (clasificada), Marketing lanzamiento, Stock inicial (harinas, levaduras, etc.), Fianza del alquiler, Alquiler de los meses previos a la apertura ni Colchón operativo hasta alcanzar el equilibrio. Suman 57515 € de los 145215 € de inversión.

Sheet PyG 3 Años
A1: CUENTA DE RESULTADOS — 3 AÑOS
A2: Escenario realista — Panadería / Obrador
A4: Concepto | B4: Año 1 | C4: Año 2 | D4: Año 3 | E4: % s/ventas (año 1) | F4: Notas | G4: Tipo de IVA de la línea (%) | H4: Pan común sobre la línea (%)
A5: INGRESOS
A6: Transacciones/día (media) | B6: =IFERROR(IF('0. Supuestos'!$B$4="","",'0. Supuestos'!$B$4),"") -> 180 | C6: =IFERROR(B6*(1+'0. Supuestos'!$B$7),"") -> 201.6 | D6: =IFERROR(C6*(1+'0. Supuestos'!$B$8),"") -> 215.712 | F6: El crecimiento de los años 2 y 3 está en la hoja de Supuestos
A7: Ticket medio sin IVA | B7: =IFERROR(IF('0. Supuestos'!$B$5="","",'0. Supuestos'!$B$5),"") -> 5.5 | C7: =IFERROR(IF(B7="","",B7),"") -> 5.5 | D7: =IFERROR(IF(C7="","",C7),"") -> 5.5 | F7: Constante en euros del año 1: una subida de precios es una decisión aparte
A8: Días de apertura al año | B8: =IFERROR(IF('0. Supuestos'!$B$6="","",'0. Supuestos'!$B$6),"") -> 310 | C8: =IFERROR(IF(B8="","",B8),"") -> 310 | D8: =IFERROR(IF(C8="","",C8),"") -> 310
A9: INGRESOS TOTALES (sin IVA) | B9: =IFERROR(IF(B6*B7*B8=0,"",B6*B7*B8),"") -> 306900 | C9: =IFERROR(IF(C6*C7*C8=0,"",C6*C7*C8),"") -> 343728 | D9: =IFERROR(IF(D6*D7*D8=0,"",D6*D7*D8),"") -> 367788.96 | E9: =IFERROR(IF(B9="","",1),"") -> 1
A10: Ventas de pan, bollería y mayorista (obrador + reparto HORECA) | B10: =IFERROR(IF(B9="","",B9*$E$10),"") -> 283882.5 | C10: =IFERROR(IF(C9="","",C9*$E$10),"") -> 317948.4 | D10: =IFERROR(IF(D9="","",D9*$E$10),"") -> 340204.79 | E10: =IFERROR(IF('0. Supuestos'!$B$11="","",'0. Supuestos'!$B$11),"") -> 0.925 | F10: Barra de pan artesanal y bollería/pastelería de tienda, más el canal mayorista a restaurantes y hoteles (el pan que se vende a otro negocio sigue siendo la misma partida de producto que el que se vende en mostrador, sólo cambia el canal). OJO: el modelo proyecta las ventas con UN solo motor —transacciones × ticket × días—, así que el reparto a otro negocio entra aquí como una transacción más y no como un pedido grande. Lo que sí recoge el libro es su efecto en la caja, con los días medios de cobro de la hoja de Supuestos. Si el mayorista pesa de verdad en tu proyecto, proyéctalo aparte · El 4 % es el tipo SUPERREDUCIDO del pan común y de las harinas panificables (art. 91.Dos.1.1.º de la Ley 37/1992); la bollería, la pastelería y el consumo en el propio local van al 10 %. El porcentaje de la derecha dice qué parte de esta línea es pan común: sale del desglose de la versión anterior de este plan (pan artesanal 120.000 € + mayorista 20.000 € sobre 185.000 €). Ajústalo a tu carta: un pan especial NO es pan común | G10: =IFERROR(IF(B9="","",H10*0.04+(1-H10)*'0. Supuestos'!$B$39),"") -> 0.0544 | H10: 0.76
A11: Ventas de café y bebidas (sin alcohol) | B11: =IFERROR(IF(B9="","",B9*$E$11),"") -> 23017.5 | C11: =IFERROR(IF(C9="","",C9*$E$11),"") -> 25779.6 | D11: =IFERROR(IF(D9="","",D9*$E$11),"") -> 27584.172 | E11: =IFERROR(IF('0. Supuestos'!$B$12="","",'0. Supuestos'!$B$12),"") -> 0.075 | F11: Café de grano, tés e infusiones de mostrador, para acompañar el desayuno o la merienda: el coste es alto por el grano de calidad, y la tabla de referencias de la hoja de Instrucciones lo sitúa en el 25-30 % de sus propias ventas | G11: =IFERROR(IF(B9="","",('0. Supuestos'!$B$62*((1-'0. Supuestos'!$B$16)*'0. Supuestos'!$B$63+'0. Supuestos'!$B$16*'0. Supuestos'!$B$40)+(1-'0. Supuestos'!$B$62)*'0. Supuestos'!$B$39)),"") -> 0.1
A12: COSTES VARIABLES
A13: Coste de mercancía — comida | B13: =IFERROR(IF(B9="","",B9*'0. Supuestos'!$B$11*'0. Supuestos'!$B$13),"") -> 82325.925 | C13: =IFERROR(IF(C9="","",C9*'0. Supuestos'!$B$11*'0. Supuestos'!$B$13),"") -> 92205.036 | D13: =IFERROR(IF(D9="","",D9*'0. Supuestos'!$B$11*'0. Supuestos'!$B$13),"") -> 98659.389 | E13: =IFERROR(B13/$B$9,"") -> 0.26825 | F13: =IFERROR("Al "&TEXT('0. Supuestos'!$B$13,"0%")&" de las ventas de COMIDA, no del total: la bebida tiene su propia línea · El IVA que SOPORTAS al comprar es el ponderado de las harinas panificables al 4 % (art. 91.Dos.1.1.º de la Ley 37/1992) y del resto de la materia prima al 10 %, con "&"el mismo peso de pan común que declara la línea de ventas de arriba","") -> Al 29% de las ventas de COMIDA, no del total: la bebida tiene su propia línea · El IVA que SOPORTAS al comprar es el ponderado de las harinas panificables al 4 % (art. 91.Dos.1.1.º de la Ley 37/1992) y del resto de la materia prima al 10 %, con el mismo peso de pan común que declara la línea de ventas de arriba | G13: =IFERROR(IF(B9="","",$H$10*0.04+(1-$H$10)*'0. Supuestos'!$B$39),"") -> 0.0544
A14: Coste de mercancía — bebida | B14: =IFERROR(IF(B9="","",B9*'0. Supuestos'!$B$12*'0. Supuestos'!$B$14),"") -> 6214.725 | C14: =IFERROR(IF(C9="","",C9*'0. Supuestos'!$B$12*'0. Supuestos'!$B$14),"") -> 6960.492 | D14: =IFERROR(IF(D9="","",D9*'0. Supuestos'!$B$12*'0. Supuestos'!$B$14),"") -> 7447.7264 | E14: =IFERROR(B14/$B$9,"") -> 0.02025 | F14: =IFERROR("Al "&TEXT('0. Supuestos'!$B$14,"0%")&" de las ventas de BEBIDA","") -> Al 27% de las ventas de BEBIDA | G14: =IFERROR(IF(B9="","",('0. Supuestos'!$B$62*'0. Supuestos'!$B$40+(1-'0. Supuestos'!$B$62)*'0. Supuestos'!$B$39)),"") -> 0.1
A15: Consumibles y envases | B15: =IFERROR(IF(B9="","",B9*'0. Supuestos'!$B$15),"") -> 6138 | C15: =IFERROR(IF(C9="","",C9*'0. Supuestos'!$B$15),"") -> 6874.56 | D15: =IFERROR(IF(D9="","",D9*'0. Supuestos'!$B$15),"") -> 7355.7792 | E15: =IFERROR(B15/$B$9,"") -> 0.02 | G15: =IFERROR(IF(B9="","",'0. Supuestos'!$B$41),"") -> 0.21
A16: Comisiones de delivery | B16: =IFERROR(IF(B9="","",B9*'0. Supuestos'!$B$16*'0. Supuestos'!$B$17),"") -> 0 | C16: =IFERROR(IF(C9="","",C9*'0. Supuestos'!$B$16*'0. Supuestos'!$B$17),"") -> 0 | D16: =IFERROR(IF(D9="","",D9*'0. Supuestos'!$B$16*'0. Supuestos'!$B$17),"") -> 0 | E16: =IFERROR(B16/$B$9,"") -> 0 | F16: Sobre las ventas DEL CANAL. Con 0 % de delivery en Supuestos, esta línea vale cero | G16: =IFERROR(IF(B9="","",'0. Supuestos'!$B$41),"") -> 0.21
A17: Comisiones de los medios de pago | B17: =IFERROR(IF(B9="","",B9*'0. Supuestos'!$B$18),"") -> 2455.2 | C17: =IFERROR(IF(C9="","",C9*'0. Supuestos'!$B$18),"") -> 2749.824 | D17: =IFERROR(IF(D9="","",D9*'0. Supuestos'!$B$18),"") -> 2942.3117 | E17: =IFERROR(B17/$B$9,"") -> 0.008 | F17: Las comisiones de los medios de pago están EXENTAS de IVA (art. 20.Uno.18 LIVA): no se deduce nada por ellas | G17: 0
A18: Varios e imprevistos | B18: =IFERROR(IF(B9="","",B9*'0. Supuestos'!$B$28),"") -> 6138 | C18: =IFERROR(IF(C9="","",C9*'0. Supuestos'!$B$28),"") -> 6874.56 | D18: =IFERROR(IF(D9="","",D9*'0. Supuestos'!$B$28),"") -> 7355.7792 | E18: =IFERROR(B18/$B$9,"") -> 0.02 | F18: =IFERROR("Al "&TEXT('0. Supuestos'!$B$28,"0%")&" de las ventas. Es un coste VARIABLE: sube y baja con la facturación, así que no puede vivir en los costes fijos","") -> Al 2% de las ventas. Es un coste VARIABLE: sube y baja con la facturación, así que no puede vivir en los costes fijos | G18: =IFERROR(IF(B9="","",'0. Supuestos'!$B$41),"") -> 0.21
A19: TOTAL COSTES VARIABLES | B19: =IFERROR(IF(B9="","",SUM(B13:B18)),"") -> 103271.85 | C19: =IFERROR(IF(C9="","",SUM(C13:C18)),"") -> 115664.47 | D19: =IFERROR(IF(D9="","",SUM(D13:D18)),"") -> 123760.99 | E19: =IFERROR(B19/$B$9,"") -> 0.3365
A20: MARGEN BRUTO | B20: =IFERROR(IF(B9="","",B9-B19),"") -> 203628.15 | C20: =IFERROR(IF(C9="","",C9-C19),"") -> 228063.53 | D20: =IFERROR(IF(D9="","",D9-D19),"") -> 244027.97 | E20: =IFERROR(B20/$B$9,"") -> 0.6635
A21: COSTES FIJOS
A22: Alquiler del local | B22: =IFERROR(IF(B9="","",'0. Supuestos'!$B$24*12),"") -> 25200 | C22: =IFERROR(IF(C9="","",B22*(1+'0. Supuestos'!$B$48)),"") -> 25200 | D22: =IFERROR(IF(D9="","",C22*(1+'0. Supuestos'!$B$48)),"") -> 25200 | E22: =IFERROR(B22/$B$9,"") -> 0.082111437 | F22: El importe mensual está en la hoja de Supuestos; aquí se multiplica por doce. La renta de los meses de obra, que es anterior a la apertura, está en la hoja de Inversión y NO se cuenta dos veces | G22: =IFERROR(IF(B9="","",'0. Supuestos'!$B$41),"") -> 0.21
A23: Personal (nóminas + Seguridad Social) | B23: =IFERROR(IF(B9="","",'Personal'!$G$11),"") -> 113861.3 | C23: =IFERROR(IF(C9="","",'Personal'!$B$15),"") -> 119861.3 | D23: =IFERROR(IF(D9="","",'Personal'!$B$16),"") -> 125861.3 | E23: =IFERROR(B23/$B$9,"") -> 0.37100456 | F23: Sale de la hoja de Personal: es el MISMO número, no una estimación aparte. Los años 2 y 3 suman las INCORPORACIONES declaradas en esa hoja, no un porcentaje de volumen | G23: 0
A24: Suministros (luz, agua, gas) | B24: =IFERROR(IF(B9="","",'0. Supuestos'!$B$26*12),"") -> 10500 | C24: =IFERROR(IF(C9="","",B24*(1+'0. Supuestos'!$B$48)),"") -> 10500 | D24: =IFERROR(IF(D9="","",C24*(1+'0. Supuestos'!$B$48)),"") -> 10500 | E24: =IFERROR(B24/$B$9,"") -> 0.034213099 | F24: Luz y gas van al 21 %; la factura del agua, al 10 %. El libro aplica a toda esta partida el tipo de la columna de al lado (21 %): si el agua pesa mucho en tu local, sepárala en su línea | G24: =IFERROR(IF(B9="","",'0. Supuestos'!$B$41),"") -> 0.21
A25: Seguros (RC + multirriesgo) | B25: =IFERROR(IF(B9="","",'0. Supuestos'!$B$27),"") -> 2100 | C25: =IFERROR(IF(C9="","",B25*(1+'0. Supuestos'!$B$48)),"") -> 2100 | D25: =IFERROR(IF(D9="","",C25*(1+'0. Supuestos'!$B$48)),"") -> 2100 | E25: =IFERROR(B25/$B$9,"") -> 0.0068426197 | F25: Las operaciones de seguro están EXENTAS de IVA (art. 20.Uno.16 LIVA): la prima no lleva IVA deducible | G25: 0
A26: Gestoría | B26: 2400 | C26: =IFERROR(IF(C9="","",B26*(1+'0. Supuestos'!$B$48)),"") -> 2400 | D26: =IFERROR(IF(D9="","",C26*(1+'0. Supuestos'!$B$48)),"") -> 2400 | E26: =IFERROR(B26/$B$9,"") -> 0.0078201369 | G26: =IFERROR(IF(B9="","",'0. Supuestos'!$B$41),"") -> 0.21
A27: Mantenimiento hornos y maquinaria | B27: 2500 | C27: =IFERROR(IF(C9="","",B27*(1+'0. Supuestos'!$B$48)),"") -> 2500 | D27: =IFERROR(IF(D9="","",C27*(1+'0. Supuestos'!$B$48)),"") -> 2500 | E27: =IFERROR(B27/$B$9,"") -> 0.0081459759 | G27: =IFERROR(IF(B9="","",'0. Supuestos'!$B$41),"") -> 0.21
A28: Marketing | B28: 3600 | C28: =IFERROR(IF(C9="","",B28*(1+'0. Supuestos'!$B$48)),"") -> 3600 | D28: =IFERROR(IF(D9="","",C28*(1+'0. Supuestos'!$B$48)),"") -> 3600 | E28: =IFERROR(B28/$B$9,"") -> 0.011730205 | G28: =IFERROR(IF(B9="","",'0. Supuestos'!$B$41),"") -> 0.21
A29: Software | B29: 600 | C29: =IFERROR(IF(C9="","",B29*(1+'0. Supuestos'!$B$48)),"") -> 600 | D29: =IFERROR(IF(D9="","",C29*(1+'0. Supuestos'!$B$48)),"") -> 600 | E29: =IFERROR(B29/$B$9,"") -> 0.0019550342 | G29: =IFERROR(IF(B9="","",'0. Supuestos'!$B$41),"") -> 0.21
A30: Limpieza | B30: 1800 | C30: =IFERROR(IF(C9="","",B30*(1+'0. Supuestos'!$B$48)),"") -> 1800 | D30: =IFERROR(IF(D9="","",C30*(1+'0. Supuestos'!$B$48)),"") -> 1800 | E30: =IFERROR(B30/$B$9,"") -> 0.0058651026 | G30: =IFERROR(IF(B9="","",'0. Supuestos'!$B$41),"") -> 0.21
A31: Varios | B31: 2000 | C31: =IFERROR(IF(C9="","",B31*(1+'0. Supuestos'!$B$48)),"") -> 2000 | D31: =IFERROR(IF(D9="","",C31*(1+'0. Supuestos'!$B$48)),"") -> 2000 | E31: =IFERROR(B31/$B$9,"") -> 0.0065167807 | G31: =IFERROR(IF(B9="","",'0. Supuestos'!$B$41),"") -> 0.21
A32: Gestión de residuos (orgánico de obrador, cartón; sin aceite de fritura) | B32: 700 | C32: =IFERROR(IF(C9="","",B32*(1+'0. Supuestos'!$B$48)),"") -> 700 | D32: =IFERROR(IF(D9="","",C32*(1+'0. Supuestos'!$B$48)),"") -> 700 | E32: =IFERROR(B32/$B$9,"") -> 0.0022808732 | F32: Gestor autorizado; el checklist lo pide antes de abrir. Este plan no fríe (licencia «inocua»), así que el volumen es menor que en un restaurante — pide presupuesto en tu zona | G32: =IFERROR(IF(B9="","",'0. Supuestos'!$B$41),"") -> 0.21
A33: Desinsectación, desratización y desinfección (DDD) | B33: 750 | C33: =IFERROR(IF(C9="","",B33*(1+'0. Supuestos'!$B$48)),"") -> 750 | D33: =IFERROR(IF(D9="","",C33*(1+'0. Supuestos'!$B$48)),"") -> 750 | E33: =IFERROR(B33/$B$9,"") -> 0.0024437928 | F33: Empresa inscrita en el ROESB; forma parte del plan APPCC que el checklist ya exige (F4). La harina almacenada atrae plaga con más facilidad que en un restaurante: presupuesto ligeramente mayor | G33: =IFERROR(IF(B9="","",'0. Supuestos'!$B$41),"") -> 0.21
A34: Derechos de autor por música ambiental | B34: 700 | C34: =IFERROR(IF(C9="","",B34*(1+'0. Supuestos'!$B$48)),"") -> 700 | D34: =IFERROR(IF(D9="","",C34*(1+'0. Supuestos'!$B$48)),"") -> 700 | E34: =IFERROR(B34/$B$9,"") -> 0.0022808732 | F34: SGAE y AGEDI-AIE son dos licencias distintas; el importe depende de los metros y del aforo de tu tienda | G34: =IFERROR(IF(B9="","",'0. Supuestos'!$B$41),"") -> 0.21
A35: Prevención de riesgos laborales y vigilancia de la salud | B35: 550 | C35: =IFERROR(IF(C9="","",B35*(1+'0. Supuestos'!$B$48)),"") -> 550 | D35: =IFERROR(IF(D9="","",C35*(1+'0. Supuestos'!$B$48)),"") -> 550 | E35: =IFERROR(B35/$B$9,"") -> 0.0017921147 | F35: El plan de prevención es obligatorio; el proveedor externo, no (art. 30.5 de la Ley 31/1995) — el checklist F4 lo corrige. Un obrador tiene riesgos específicos (quemaduras, cargas, harina en suspensión) que el propio checklist ya nombra (F4!E10) | G35: =IFERROR(IF(B9="","",'0. Supuestos'!$B$41),"") -> 0.21
A36: Amortización del inmovilizado | B36: =IFERROR(IF(B9="","",'Inversión Inicial'!$B$38),"") -> 9292.2222 | C36: =IFERROR(IF(C9="","",B36),"") -> 9292.2222 | D36: =IFERROR(IF(D9="","",B36),"") -> 9292.2222 | E36: =IFERROR(B36/$B$9,"") -> 0.030277687 | F36: Sale de las bases de amortización de la hoja de Inversión: sólo inmovilizado real. NO sube con el IPC: es una cuota sobre el coste HISTÓRICO del inmovilizado | G36: 0
A37: Gastos financieros (intereses del préstamo) | B37: =IFERROR(IF(B9="","",'Financiación'!$B$44),"") -> 7200 | C37: =IFERROR(IF(C9="","",'Financiación'!$B$46),"") -> 7200 | D37: =IFERROR(IF(D9="","",'Financiación'!$B$48),"") -> 6167.7891 | E37: =IFERROR(B37/$B$9,"") -> 0.023460411 | F37: Sólo los INTERESES son gasto. La devolución del principal va en la hoja de Tesorería | G37: 0
A38: TOTAL COSTES FIJOS | B38: =IFERROR(IF(B9="","",SUM(B22:B37)),"") -> 183753.52 | C38: =IFERROR(IF(C9="","",SUM(C22:C37)),"") -> 189753.52 | D38: =IFERROR(IF(D9="","",SUM(D22:D37)),"") -> 194721.31 | E38: =IFERROR(B38/$B$9,"") -> 0.5987407
A39: IVA soportado de los costes variables | B39: =IFERROR(IF(B9="","",SUMPRODUCT(B13:B18,G13:G18)),"") -> 7677.9628 | C39: =IFERROR(IF(C9="","",SUMPRODUCT(C13:C18,G13:G18)),"") -> 8599.3184 | D39: =IFERROR(IF(D9="","",SUMPRODUCT(D13:D18,G13:G18)),"") -> 9201.2706 | F39: Cada línea a SU tipo, leído de la columna de al lado. Es lo que la hoja de Tesorería paga de más a los proveedores y luego se deduce
A40: IVA soportado de los costes fijos | B40: =IFERROR(IF(B9="","",SUMPRODUCT(B22:B37,G22:G37)),"") -> 10773 | C40: =IFERROR(IF(C9="","",SUMPRODUCT(C22:C37,G22:G37)),"") -> 10773 | D40: =IFERROR(IF(D9="","",SUMPRODUCT(D22:D37,G22:G37)),"") -> 10773
A41: RESULTADO ANTES DE IMPUESTOS | B41: =IFERROR(IF(B9="","",B20-B38),"") -> 19874.628 | C41: =IFERROR(IF(C9="","",C20-C38),"") -> 38310.006 | D41: =IFERROR(IF(D9="","",D20-D38),"") -> 49306.664 | E41: =IFERROR(B41/$B$9,"") -> 0.064759295
A42: Bases negativas pendientes al inicio | B42: =IFERROR(IF(B9="","",'0. Supuestos'!$B$42),"") -> 0 | C42: =IFERROR(IF(C9="","",B47),"") -> 0 | D42: =IFERROR(IF(D9="","",C47),"") -> 0 | F42: Art. 26 LIS: las pérdidas de un ejercicio se compensan con los beneficios de los siguientes
A43: Base imponible (después de compensar) | B43: =IFERROR(IF(B9="","",MAX(0,B41-B42)),"") -> 19874.628 | C43: =IFERROR(IF(C9="","",MAX(0,C41-C42)),"") -> 38310.006 | D43: =IFERROR(IF(D9="","",MAX(0,D41-D42)),"") -> 49306.664
A44: Ejercicios con base positiva (acumulado) | B44: =IFERROR(IF(B9="","",IF(B43>0,1,0)),"") -> 1 | C44: =IFERROR(IF(C9="","",B44+IF(C43>0,1,0)),"") -> 2 | D44: =IFERROR(IF(D9="","",C44+IF(D43>0,1,0)),"") -> 3
A45: Tipo de Impuesto de Sociedades aplicado | B45: =IFERROR(IF(B9="","",IF(B43<=0,"",IF(B44<=2,'0. Supuestos'!$B$37,'0. Supuestos'!$B$38))),"") -> 0.15 | C45: =IFERROR(IF(C9="","",IF(C43<=0,"",IF(C44<=2,'0. Supuestos'!$B$37,'0. Supuestos'!$B$38))),"") -> 0.15 | D45: =IFERROR(IF(D9="","",IF(D43<=0,"",IF(D44<=2,'0. Supuestos'!$B$37,'0. Supuestos'!$B$38))),"") -> 0.25 | F45: Art. 29.1 LIS: el 15 % de entidad de nueva creación se aplica al PRIMER ejercicio con base positiva y al SIGUIENTE, no al primer año de vida. El libro lo aproxima contando los dos primeros ejercicios con base positiva
A46: Impuesto de Sociedades | B46: =IFERROR(IF(B9="","",IF(B45="",0,B43*B45)),"") -> 2981.1942 | C46: =IFERROR(IF(C9="","",IF(C45="",0,C43*C45)),"") -> 5746.5009 | D46: =IFERROR(IF(D9="","",IF(D45="",0,D43*D45)),"") -> 12326.666
A47: Bases negativas pendientes al cierre | B47: =IFERROR(IF(B9="","",MAX(0,B42-B41)),"") -> 0 | C47: =IFERROR(IF(C9="","",MAX(0,C42-C41)),"") -> 0 | D47: =IFERROR(IF(D9="","",MAX(0,D42-D41)),"") -> 0
A48: RESULTADO NETO | B48: =IFERROR(IF(B9="","",B41-B46),"") -> 16893.434 | C48: =IFERROR(IF(C9="","",C41-C46),"") -> 32563.505 | D48: =IFERROR(IF(D9="","",D41-D46),"") -> 36979.998 | E48: =IFERROR(B48/$B$9,"") -> 0.055045401
A49: RATIOS CLAVE
A50: Ratio | B50: Año 1 | C50: Año 2 | D50: Año 3 | E50: Umbral | F50: Comentario
A51: Margen bruto / Ventas | B51: =IFERROR(IF(B9="","",B20/B9),"") -> 0.6635 | C51: =IFERROR(IF(C9="","",C20/C9),"") -> 0.6635 | D51: =IFERROR(IF(D9="","",D20/D9),"") -> 0.6635 | E51: 0.62 | F51: Suelo que declara este mismo kit en la tabla «Datos de referencia del sector» de la hoja de Instrucciones: «Margen bruto objetivo: > 62 %»
A52: Coste de mercancía (comida + bebida) | B52: =IFERROR(IF(B9="","",B13+B14),"") -> 88540.65 | C52: =IFERROR(IF(C9="","",C13+C14),"") -> 99165.528 | D52: =IFERROR(IF(D9="","",D13+D14),"") -> 106107.11
A53: Coste de mercancía / Ventas | B53: =IFERROR(IF(B9="","",B52/B9),"") -> 0.2885 | C53: =IFERROR(IF(C9="","",C52/C9),"") -> 0.2885 | D53: =IFERROR(IF(D9="","",D52/D9),"") -> 0.2885 | E53: 0.32 | F53: Techo del blend que publica este producto en esa misma tabla de referencias: pan 25-30 %, bollería 32-38 % y café 25-30 %
A54: Coste de personal / Ventas | B54: =IFERROR(IF(B9="","",B23/B9),"") -> 0.37100456 | C54: =IFERROR(IF(C9="","",C23/C9),"") -> 0.34870974 | D54: =IFERROR(IF(D9="","",D23/D9),"") -> 0.34221065 | E54: 0.42 | F54: Techo del extremo ALTO del rango que publica este producto en la tabla de referencias de la hoja de Instrucciones («Coste de personal sobre ventas: 35-42 %»), el más alto de los cinco planes de restauración de esta línea. La nota de esa misma fila explica por qué: turno de madrugada y doble oficio (producción + venta). Usar el extremo bajo (35 %, el criterio de una cafetería) habría exigido una plantilla por debajo del mínimo operable de un obrador con horno diario
A55: Alquiler / Ventas | B55: =IFERROR(IF(B9="","",B22/B9),"") -> 0.082111437 | C55: =IFERROR(IF(C9="","",C22/C9),"") -> 0.073313783 | D55: =IFERROR(IF(D9="","",D22/D9),"") -> 0.068517554 | E55: 0.1 | F55: Techo del extremo estricto que declara este mismo kit en la tabla de referencias de la hoja de Instrucciones: «Alquiler sobre ventas: 10-14 %»
A56: Resultado neto / Ventas | B56: =IFERROR(IF(B9="","",B48/B9),"") -> 0.055045401 | C56: =IFERROR(IF(C9="","",C48/C9),"") -> 0.094736259 | D56: =IFERROR(IF(D9="","",D48/D9),"") -> 0.10054679 | E56: 0.05 | F56: Derivado del suelo de EBITDA que declara este producto para el año 2 en la tabla de referencias de la hoja de Instrucciones («EBITDA objetivo (año 2): 10-18 %, el primer año puede ser negativo»): descontando amortización, intereses e Impuesto de Sociedades, un EBITDA en la franja baja deja un resultado neto en torno al 5 %
A57: Punto de equilibrio alcanzado | B57: =IFERROR(IF(B9="","",IF(B9>='Punto Equilibrio'!$B$16,"Sí","No")),"") -> Sí | C57: =IFERROR(IF(C9="","",IF(C9>='Punto Equilibrio'!$C$16,"Sí","No")),"") -> Sí | D57: =IFERROR(IF(D9="","",IF(D9>='Punto Equilibrio'!$D$16,"Sí","No")),"") -> Sí | F57: Compara las ventas de CADA año con el umbral de ese mismo año, que calcula la hoja de Punto de Equilibrio con los costes fijos del año
A59: Todas las cifras van SIN IVA. Las columnas de los años 2 y 3 están en euros del año 1 salvo que subas la actualización de costes en la hoja de Supuestos. La columna «Tipo de IVA de la línea» dice, en las líneas de VENTA, a qué tipo se repercute cada una, y en las de COSTE a qué tipo se compra la partida. La lee la hoja de Tesorería: los seguros y las comisiones de los medios de pago están exentos, y las nóminas, la amortización y los intereses no llevan IVA.

Sheet Punto Equilibrio
A1: PUNTO DE EQUILIBRIO
A4: Variable | B4: Año 1 | C4: Año 2 | D4: Año 3 | E4: Notas
A5: DATOS BASE POR AÑO
A6: Costes fijos anuales | B6: =IFERROR(IF('PyG 3 Años'!$B$9="","",'PyG 3 Años'!$B$38),"") -> 183753.52 | C6: =IFERROR(IF('PyG 3 Años'!$C$9="","",'PyG 3 Años'!$C$38),"") -> 189753.52 | D6: =IFERROR(IF('PyG 3 Años'!$D$9="","",'PyG 3 Años'!$D$38),"") -> 194721.31 | E6: Los MISMOS costes fijos del P&L. Cada año tiene los suyos: por eso el umbral no puede ser uno solo para los tres
A7: Costes fijos mensuales | B7: =IFERROR(IF('PyG 3 Años'!$B$9="","",B6/12),"") -> 15312.794 | C7: =IFERROR(IF('PyG 3 Años'!$C$9="","",C6/12),"") -> 15812.794 | D7: =IFERROR(IF('PyG 3 Años'!$D$9="","",D6/12),"") -> 16226.776
A8: Ticket medio sin IVA | B8: =IFERROR(IF('PyG 3 Años'!$B$9="","",'PyG 3 Años'!$B$7),"") -> 5.5 | C8: =IFERROR(IF('PyG 3 Años'!$C$9="","",'PyG 3 Años'!$C$7),"") -> 5.5 | D8: =IFERROR(IF('PyG 3 Años'!$D$9="","",'PyG 3 Años'!$D$7),"") -> 5.5
A9: Coste variable por transacción | B9: =IFERROR(IF('PyG 3 Años'!$B$9="","",'PyG 3 Años'!$B$19/('PyG 3 Años'!$B$6*'PyG 3 Años'!$B$8)),"") -> 1.85075 | C9: =IFERROR(IF('PyG 3 Años'!$C$9="","",'PyG 3 Años'!$C$19/('PyG 3 Años'!$C$6*'PyG 3 Años'!$C$8)),"") -> 1.85075 | D9: =IFERROR(IF('PyG 3 Años'!$D$9="","",'PyG 3 Años'!$D$19/('PyG 3 Años'!$D$6*'PyG 3 Años'!$D$8)),"") -> 1.85075 | E9: Sale del total de costes variables del P&L, no de una estimación aparte. Incluye los varios e imprevistos, que son un porcentaje de las ventas
A10: Margen de contribución por transacción | B10: =IFERROR(IF('PyG 3 Años'!$B$9="","",B8-B9),"") -> 3.64925 | C10: =IFERROR(IF('PyG 3 Años'!$C$9="","",C8-C9),"") -> 3.64925 | D10: =IFERROR(IF('PyG 3 Años'!$D$9="","",D8-D9),"") -> 3.64925 | E10: Ticket menos coste variable unitario
A11: Días de apertura al año | B11: =IFERROR(IF('PyG 3 Años'!$B$9="","",'PyG 3 Años'!$B$8),"") -> 310 | C11: =IFERROR(IF('PyG 3 Años'!$C$9="","",'PyG 3 Años'!$C$8),"") -> 310 | D11: =IFERROR(IF('PyG 3 Años'!$D$9="","",'PyG 3 Años'!$D$8),"") -> 310 | E11: El mismo calendario que el P&L y que los escenarios
A12: Devolución de principal del año (cuota) | B12: =IFERROR(IF('PyG 3 Años'!$B$9="","",'Financiación'!$B$45),"") -> 0 | C12: =IFERROR(IF('PyG 3 Años'!$C$9="","",'Financiación'!$B$47),"") -> 17203.515 | D12: =IFERROR(IF('PyG 3 Años'!$D$9="","",'Financiación'!$B$49),"") -> 18235.726 | E12: El principal NO es gasto del P&L, pero sale de la caja. Sin él, el umbral de equilibrio se publica por debajo del real
A13: PUNTO DE EQUILIBRIO CONTABLE (incluye amortización)
A14: Transacciones necesarias al año | B14: =IFERROR(IF('PyG 3 Años'!$B$9="","",IF(B10<=0,"",B6/B10)),"") -> 50353.777 | C14: =IFERROR(IF('PyG 3 Años'!$C$9="","",IF(C10<=0,"",C6/C10)),"") -> 51997.951 | D14: =IFERROR(IF('PyG 3 Años'!$D$9="","",IF(D10<=0,"",D6/D10)),"") -> 53359.269
A15: Transacciones necesarias al día | B15: =IFERROR(IF('PyG 3 Años'!$B$9="","",B14/B11),"") -> 162.43154 | C15: =IFERROR(IF('PyG 3 Años'!$C$9="","",C14/C11),"") -> 167.73533 | D15: =IFERROR(IF('PyG 3 Años'!$D$9="","",D14/D11),"") -> 172.12667
A16: Ingresos necesarios al año | B16: =IFERROR(IF('PyG 3 Años'!$B$9="","",B14*B8),"") -> 276945.78 | C16: =IFERROR(IF('PyG 3 Años'!$C$9="","",C14*C8),"") -> 285988.73 | D16: =IFERROR(IF('PyG 3 Años'!$D$9="","",D14*D8),"") -> 293475.98
A17: PUNTO DE EQUILIBRIO DE CAJA (incluye la cuota del préstamo)
A18: Costes fijos de caja + principal del año | B18: =IFERROR(IF('PyG 3 Años'!$B$9="","",B6-'PyG 3 Años'!$B$36+B12),"") -> 174461.3 | C18: =IFERROR(IF('PyG 3 Años'!$C$9="","",C6-'PyG 3 Años'!$C$36+C12),"") -> 197664.82 | D18: =IFERROR(IF('PyG 3 Años'!$D$9="","",D6-'PyG 3 Años'!$D$36+D12),"") -> 203664.82 | E18: Los fijos del P&L sin la amortización (que no se paga) y CON la devolución de principal (que sí). Es el umbral que decide si la caja aguanta
A19: Transacciones necesarias al año (caja) | B19: =IFERROR(IF('PyG 3 Años'!$B$9="","",IF(B10<=0,"",B18/B10)),"") -> 47807.44 | C19: =IFERROR(IF('PyG 3 Años'!$C$9="","",IF(C10<=0,"",C18/C10)),"") -> 54165.874 | D19: =IFERROR(IF('PyG 3 Años'!$D$9="","",IF(D10<=0,"",D18/D10)),"") -> 55810.047
A20: Transacciones necesarias al día (caja) | B20: =IFERROR(IF('PyG 3 Años'!$B$9="","",B19/B11),"") -> 154.21755 | C20: =IFERROR(IF('PyG 3 Años'!$C$9="","",C19/C11),"") -> 174.72863 | D20: =IFERROR(IF('PyG 3 Años'!$D$9="","",D19/D11),"") -> 180.03241
A21: Ingresos necesarios al año (caja) | B21: =IFERROR(IF('PyG 3 Años'!$B$9="","",B19*B8),"") -> 262940.92 | C21: =IFERROR(IF('PyG 3 Años'!$C$9="","",C19*C8),"") -> 297912.31 | D21: =IFERROR(IF('PyG 3 Años'!$D$9="","",D19*D8),"") -> 306955.26
A22: CONTRASTE CON EL PLAN
A23: Transacciones/día previstos en el plan | B23: =IFERROR(IF('PyG 3 Años'!$B$9="","",'PyG 3 Años'!$B$6),"") -> 180 | C23: =IFERROR(IF('PyG 3 Años'!$C$9="","",'PyG 3 Años'!$C$6),"") -> 201.6 | D23: =IFERROR(IF('PyG 3 Años'!$D$9="","",'PyG 3 Años'!$D$6),"") -> 215.712
A24: Holgura sobre el equilibrio de CAJA (%) | B24: =IFERROR(IF('PyG 3 Años'!$B$9="","",B23/B20-1),"") -> 0.16718235 | C24: =IFERROR(IF('PyG 3 Años'!$C$9="","",C23/C20-1),"") -> 0.15378919 | D24: =IFERROR(IF('PyG 3 Años'!$D$9="","",D23/D20-1),"") -> 0.19818425 | E24: Cuánto superan tus ventas previstas a las del equilibrio de caja. La caída que aguantas antes de no poder pagar los costes fijos y la cuota es algo menor: con un 25 % de holgura, un 20 %. El mínimo exigible está en la hoja de Supuestos
A25: INTERPRETACIÓN
A26: =IFERROR("Con el ticket medio sin IVA de la fila de arriba necesitas "&TEXT(ROUNDUP(B15,0),"0")&" transacciones al día durante los "&TEXT(B11,"0")&" días que abres para no perder dinero (equilibrio contable, con la amortización dentro), y "&TEXT(ROUNDUP(B20,0),"0")&" para que la caja aguante (equilibrio de caja: sin la amortización, que no se paga, y con la cuota del préstamo del año"&IF(B12=0,"; este año sólo intereses, porque el préstamo está en carencia","")&"). En las filas «Ingresos necesarios al año» tienes esas mismas cifras en euros.","") -> Con el ticket medio sin IVA de la fila de arriba necesitas 163 transacciones al día durante los 310 días que abres para no perder dinero (equilibrio contable, con la amortización dentro), y 155 para que la caja aguante (equilibrio de caja: sin la amortización, que no se paga, y con la cuota del préstamo del año; este año sólo intereses, porque el préstamo está en carencia). En las filas «Ingresos necesarios al año» tienes esas mismas cifras en euros.
A28: SENSIBILIDAD DEL PUNTO DE EQUILIBRIO
A29: Transacciones/día necesarios para cubrir costes según el ticket medio (columnas) y el coste variable por transacción (filas). En verde, los que están por debajo de las transacciones que prevé el plan.
A31: Transacciones/día necesarios: ticket medio sin IVA (columnas) × coste variable por transacción (filas) | B31: =IFERROR($B$8-2,"") -> 3.5 | C31: =IFERROR(IF($B$8="","",$B$8),"") -> 5.5 | D31: =IFERROR($B$8+2,"") -> 7.5 | E31: =IFERROR($B$8+4,"") -> 9.5
A32: =IFERROR($B$9*0.85,"") -> 1.5731375 | B32: =IFERROR(IF($B$31-$A32<=0,"",$B$6/($B$31-$A32)/$B$11),"") -> 307.62615 | C32: =IFERROR(IF($C$31-$A32<=0,"",$B$6/($C$31-$A32)/$B$11),"") -> 150.94832 | D32: =IFERROR(IF($D$31-$A32<=0,"",$B$6/($D$31-$A32)/$B$11),"") -> 100.01131 | E32: =IFERROR(IF($E$31-$A32<=0,"",$B$6/($E$31-$A32)/$B$11),"") -> 74.777795
A33: =IFERROR($B$9*0.925,"") -> 1.7119437 | B33: =IFERROR(IF($B$31-$A33<=0,"",$B$6/($B$31-$A33)/$B$11),"") -> 331.50708 | C33: =IFERROR(IF($C$31-$A33<=0,"",$B$6/($C$31-$A33)/$B$11),"") -> 156.47954 | D33: =IFERROR(IF($D$31-$A33<=0,"",$B$6/($D$31-$A33)/$B$11),"") -> 102.40973 | E33: =IFERROR(IF($E$31-$A33<=0,"",$B$6/($E$31-$A33)/$B$11),"") -> 76.110557
A34: =IFERROR($B$9*1.0,"") -> 1.85075 | B34: =IFERROR(IF($B$31-$A34<=0,"",$B$6/($B$31-$A34)/$B$11),"") -> 359.40779 | C34: =IFERROR(IF($C$31-$A34<=0,"",$B$6/($C$31-$A34)/$B$11),"") -> 162.43154 | D34: =IFERROR(IF($D$31-$A34<=0,"",$B$6/($D$31-$A34)/$B$11),"") -> 104.92602 | E34: =IFERROR(IF($E$31-$A34<=0,"",$B$6/($E$31-$A34)/$B$11),"") -> 77.491688
A35: =IFERROR($B$9*1.075,"") -> 1.9895562 | B35: =IFERROR(IF($B$31-$A35<=0,"",$B$6/($B$31-$A35)/$B$11),"") -> 392.43653 | C35: =IFERROR(IF($C$31-$A35<=0,"",$B$6/($C$31-$A35)/$B$11),"") -> 168.85424 | D35: =IFERROR(IF($D$31-$A35<=0,"",$B$6/($D$31-$A35)/$B$11),"") -> 107.56907 | E35: =IFERROR(IF($E$31-$A35<=0,"",$B$6/($E$31-$A35)/$B$11),"") -> 78.923872
A36: =IFERROR($B$9*1.15,"") -> 2.1283625 | B36: =IFERROR(IF($B$31-$A36<=0,"",$B$6/($B$31-$A36)/$B$11),"") -> 432.15011 | C36: =IFERROR(IF($C$31-$A36<=0,"",$B$6/($C$31-$A36)/$B$11),"") -> 175.80576 | D36: =IFERROR(IF($D$31-$A36<=0,"",$B$6/($D$31-$A36)/$B$11),"") -> 110.34872 | E36: =IFERROR(IF($E$31-$A36<=0,"",$B$6/($E$31-$A36)/$B$11),"") -> 80.40999

Sheet Escenarios
A1: ESCENARIOS
A4: Métrica | B4: Pesimista | C4: Realista | D4: Optimista | E4: Notas
A5: Transacciones/día | B5: 120 | C5: =IFERROR(IF('PyG 3 Años'!$B$6="","",'PyG 3 Años'!$B$6),"") -> 180 | D5: 200
A6: Ticket medio sin IVA | B6: 4.2 | C6: =IFERROR(IF('PyG 3 Años'!$B$7="","",'PyG 3 Años'!$B$7),"") -> 5.5 | D6: 6
A7: Días de apertura al año | B7: 300 | C7: =IFERROR(IF('PyG 3 Años'!$B$8="","",'PyG 3 Años'!$B$8),"") -> 310 | D7: 320
A8: INGRESOS ANUALES (sin IVA) | B8: =IFERROR(IF(B5*B6*B7=0,"",B5*B6*B7),"") -> 151200 | C8: =IFERROR(IF(C5*C6*C7=0,"",C5*C6*C7),"") -> 306900 | D8: =IFERROR(IF(D5*D6*D7=0,"",D5*D6*D7),"") -> 384000
A9: Coste de mercancía — comida | B9: =IFERROR(IF(B8="","",B8*'0. Supuestos'!$B$11*'0. Supuestos'!$B$13),"") -> 40559.4 | C9: =IFERROR(IF(C8="","",C8*'0. Supuestos'!$B$11*'0. Supuestos'!$B$13),"") -> 82325.925 | D9: =IFERROR(IF(D8="","",D8*'0. Supuestos'!$B$11*'0. Supuestos'!$B$13),"") -> 103008
A10: Coste de mercancía — bebida | B10: =IFERROR(IF(B8="","",B8*'0. Supuestos'!$B$12*'0. Supuestos'!$B$14),"") -> 3061.8 | C10: =IFERROR(IF(C8="","",C8*'0. Supuestos'!$B$12*'0. Supuestos'!$B$14),"") -> 6214.725 | D10: =IFERROR(IF(D8="","",D8*'0. Supuestos'!$B$12*'0. Supuestos'!$B$14),"") -> 7776
A11: Consumibles y envases | B11: =IFERROR(IF(B8="","",B8*'0. Supuestos'!$B$15),"") -> 3024 | C11: =IFERROR(IF(C8="","",C8*'0. Supuestos'!$B$15),"") -> 6138 | D11: =IFERROR(IF(D8="","",D8*'0. Supuestos'!$B$15),"") -> 7680
A12: Comisiones de delivery | B12: =IFERROR(IF(B8="","",B8*'0. Supuestos'!$B$16*'0. Supuestos'!$B$17),"") -> 0 | C12: =IFERROR(IF(C8="","",C8*'0. Supuestos'!$B$16*'0. Supuestos'!$B$17),"") -> 0 | D12: =IFERROR(IF(D8="","",D8*'0. Supuestos'!$B$16*'0. Supuestos'!$B$17),"") -> 0
A13: Comisiones de los medios de pago | B13: =IFERROR(IF(B8="","",B8*'0. Supuestos'!$B$18),"") -> 1209.6 | C13: =IFERROR(IF(C8="","",C8*'0. Supuestos'!$B$18),"") -> 2455.2 | D13: =IFERROR(IF(D8="","",D8*'0. Supuestos'!$B$18),"") -> 3072
A14: Varios e imprevistos | B14: =IFERROR(IF(B8="","",B8*'0. Supuestos'!$B$28),"") -> 3024 | C14: =IFERROR(IF(C8="","",C8*'0. Supuestos'!$B$28),"") -> 6138 | D14: =IFERROR(IF(D8="","",D8*'0. Supuestos'!$B$28),"") -> 7680
A15: TOTAL COSTES VARIABLES | B15: =IFERROR(IF(B8="","",SUM(B9:B14)),"") -> 50878.8 | C15: =IFERROR(IF(C8="","",SUM(C9:C14)),"") -> 103271.85 | D15: =IFERROR(IF(D8="","",SUM(D9:D14)),"") -> 129216
A16: MARGEN BRUTO | B16: =IFERROR(IF(B8="","",B8-B15),"") -> 100321.2 | C16: =IFERROR(IF(C8="","",C8-C15),"") -> 203628.15 | D16: =IFERROR(IF(D8="","",D8-D15),"") -> 254784
A17: COSTES FIJOS (los del P&L) | B17: =IFERROR(IF(B8="","",'PyG 3 Años'!$B$38),"") -> 183753.52 | C17: =IFERROR(IF(C8="","",'PyG 3 Años'!$B$38),"") -> 183753.52 | D17: =IFERROR(IF(D8="","",'PyG 3 Años'!$B$38),"") -> 183753.52 | E17: Los costes fijos no cambian con el escenario: por eso son fijos
A18: RESULTADO ANTES DE IMPUESTOS | B18: =IFERROR(IF(B8="","",B16-B17),"") -> -83432.322 | C18: =IFERROR(IF(C8="","",C16-C17),"") -> 19874.628 | D18: =IFERROR(IF(D8="","",D16-D17),"") -> 71030.478
A19: Impuesto de Sociedades | B19: =IFERROR(IF(B8="","",MAX(0,B18-'0. Supuestos'!$B$42)*'0. Supuestos'!$B$37),"") -> 0 | C19: =IFERROR(IF(C8="","",MAX(0,C18-'0. Supuestos'!$B$42)*'0. Supuestos'!$B$37),"") -> 2981.1942 | D19: =IFERROR(IF(D8="","",MAX(0,D18-'0. Supuestos'!$B$42)*'0. Supuestos'!$B$37),"") -> 10654.572 | E19: Al tipo de entidad de nueva creación, compensando las bases negativas anteriores
A20: RESULTADO NETO | B20: =IFERROR(IF(B8="","",B18-B19),"") -> -83432.322 | C20: =IFERROR(IF(C8="","",C18-C19),"") -> 16893.434 | D20: =IFERROR(IF(D8="","",D18-D19),"") -> 60375.906
A21: Transacciones/día para el equilibrio | B21: =IFERROR(IF(B8="","",IF(B6-B15/(B5*B7)<=0,"",B17/(B6-B15/(B5*B7))/B7)),"") -> 219.79823 | C21: =IFERROR(IF(C8="","",IF(C6-C15/(C5*C7)<=0,"",C17/(C6-C15/(C5*C7))/C7)),"") -> 162.43154 | D21: =IFERROR(IF(D8="","",IF(D6-D15/(D5*D7)<=0,"",D17/(D6-D15/(D5*D7))/D7)),"") -> 144.24259
A22: LO QUE CADA ESCENARIO EXIGE
A23: Coste de personal / Ventas | B23: =IFERROR(IF(B8="","",'PyG 3 Años'!$B$23/B8),"") -> 0.75305093 | C23: =IFERROR(IF(C8="","",'PyG 3 Años'!$B$23/C8),"") -> 0.37100456 | D23: =IFERROR(IF(D8="","",'PyG 3 Años'!$B$23/D8),"") -> 0.2965138 | E23: La MISMA plantilla en los tres escenarios. Si en el pesimista se dispara, el ajuste hay que hacerlo en la hoja de Personal, no aquí
A24: Transacciones al año por jornada equivalente | B24: =IFERROR(IF(B8="","",B5*B7/'Personal'!$C$11),"") -> 8200.4556 | C24: =IFERROR(IF(C8="","",C5*C7/'Personal'!$C$11),"") -> 12710.706 | D24: =IFERROR(IF(D8="","",D5*D7/'Personal'!$C$11),"") -> 14578.588 | E24: Transacciones que tendría que sacar cada jornada completa del cuadro de Personal. En el optimista dice si hace falta contratar
A25: Saldo de caja al cierre del año 1 (estimado, el mismo método en los tres escenarios) | B25: =IFERROR(IF(B8="","",'Inversión Inicial'!$B$30+B20+'PyG 3 Años'!$B$36-'Financiación'!$B$45),"") -> -30524.775 | C25: =IFERROR(IF(C8="","",'Inversión Inicial'!$B$30+C20+'PyG 3 Años'!$B$36-'Financiación'!$B$45),"") -> 69800.981 | D25: =IFERROR(IF(D8="","",'Inversión Inicial'!$B$30+D20+'PyG 3 Años'!$B$36-'Financiación'!$B$45),"") -> 113283.45 | E25: Saldo ESTIMADO: fondo de maniobra más el resultado del año, devolviendo la amortización (que no se paga) y restando el principal del préstamo. No incluye el desfase de cobros y pagos ni la liquidación del IVA, así que las tres columnas se pueden comparar entre sí. En rojo, el escenario se queda sin caja
A26: Saldo real del mes 12 de la hoja de Tesorería (sólo realista) | C26: =IFERROR(IF(C8="","",'Tesorería 12 meses'!$M$22),"") -> 82842.211 | E26: El saldo REAL del caso base, con su desfase de cobros y pagos y su liquidación de IVA. Sólo existe para el escenario realista, que es el único con tesorería mensual propia: por eso no está en la fila de arriba, donde se compararía contra dos estimaciones
A28: La columna «Realista» lee sus tres datos de la hoja de Supuestos, así que reproduce EXACTAMENTE el año 1 del P&L. Los otros dos escenarios usan las mismas tasas de coste: lo único que cambia son las transacciones, el ticket y los días. Los COSTES FIJOS sí son los mismos en los tres: los varios e imprevistos, que son un porcentaje de las ventas, van arriba con los variables y cada escenario carga los suyos.

Sheet Personal
A1: PERSONAL Y COSTES
A2: =IFERROR("Convenio Hostelería — "&TEXT('0. Supuestos'!$B$21,"0")&" pagas + SS "&TEXT('0. Supuestos'!$B$20*100,"0")&" %","") -> Convenio Hostelería — 14 pagas + SS 33 %
A4: Puesto | B4: Personas | C4: Jornada | D4: Bruto mes (€, total del puesto) | E4: Seg. Social a cargo de la empresa (€) | F4: Coste mes (€, total del puesto) | G4: Coste año (€) | H4: Horas/semana por persona | I4: Horas/año del puesto | J4: Notas
A5: Maestro panadero / Propietario/a | B5: 1 | C5: 1 | D5: 1750 | E5: =IFERROR(IF(D5="","",D5*'0. Supuestos'!$B$20),"") -> 577.5 | F5: =IFERROR(IF(D5="","",D5+E5),"") -> 2327.5 | G5: =IFERROR(IF(D5="","",F5*MAX(12,'0. Supuestos'!$B$21)),"") -> 32585 | H5: =IFERROR(IF(D5="","",C5*$B$18),"") -> 40 | I5: =IFERROR(IF(D5="","",H5*B5*$B$19),"") -> 1840 | J5: Turno de madrugada (4:00-5:00 AM, checklist F4): amasado, formado y horneado de la primera hornada, más gestión y compras. Es el puesto de mayor cualificación del obrador
A6: Oficial panadero | B6: 1 | C6: 1 | D6: 1400 | E6: =IFERROR(IF(D6="","",D6*'0. Supuestos'!$B$20),"") -> 462 | F6: =IFERROR(IF(D6="","",D6+E6),"") -> 1862 | G6: =IFERROR(IF(D6="","",F6*MAX(12,'0. Supuestos'!$B$21)),"") -> 26068 | H6: =IFERROR(IF(D6="","",C6*$B$18),"") -> 40 | I6: =IFERROR(IF(D6="","",H6*B6*$B$19),"") -> 1840 | J6: Segunda hornada y bollería del turno de mañana; cubre al maestro panadero en sus descansos
A7: Ayudante/a de obrador | B7: 1 | C7: 1 | D7: 1235 | E7: =IFERROR(IF(D7="","",D7*'0. Supuestos'!$B$20),"") -> 407.55 | F7: =IFERROR(IF(D7="","",D7+E7),"") -> 1642.55 | G7: =IFERROR(IF(D7="","",F7*MAX(12,'0. Supuestos'!$B$21)),"") -> 22995.7 | H7: =IFERROR(IF(D7="","",C7*$B$18),"") -> 40 | I7: =IFERROR(IF(D7="","",H7*B7*$B$19),"") -> 1840 | J7: Pesaje, limpieza, carga/descarga de hornos y apoyo en fermentación (Personal!F7 de la v1.1)
A8: Dependienta/e de tienda | B8: 1 | C8: 1 | D8: 1235 | E8: =IFERROR(IF(D8="","",D8*'0. Supuestos'!$B$20),"") -> 407.55 | F8: =IFERROR(IF(D8="","",D8+E8),"") -> 1642.55 | G8: =IFERROR(IF(D8="","",F8*MAX(12,'0. Supuestos'!$B$21)),"") -> 22995.7 | H8: =IFERROR(IF(D8="","",C8*$B$18),"") -> 40 | I8: =IFERROR(IF(D8="","",H8*B8*$B$19),"") -> 1840 | J8: Atención al cliente, caja y reposición de vitrina durante toda la jornada de apertura
A9: Extra de fin de semana | B9: 1 | C9: 0.3 | D9: 380 | E9: =IFERROR(IF(D9="","",D9*'0. Supuestos'!$B$20),"") -> 125.4 | F9: =IFERROR(IF(D9="","",D9+E9),"") -> 505.4 | G9: =IFERROR(IF(D9="","",F9*MAX(12,'0. Supuestos'!$B$21)),"") -> 7075.6 | H9: =IFERROR(IF(D9="","",C9*$B$18),"") -> 12 | I9: =IFERROR(IF(D9="","",H9*B9*$B$19),"") -> 552 | J9: Refuerzo del pico de sábado-domingo mañana, cuando la demanda de bollería sube (Personal!F9 de la v1.1)
A10: Suplencias de vacaciones y descansos | B10: 1 | C10: 0.09 | D10: 115 | E10: =IFERROR(IF(D10="","",D10*'0. Supuestos'!$B$20),"") -> 37.95 | F10: =IFERROR(IF(D10="","",D10+E10),"") -> 152.95 | G10: =IFERROR(IF(D10="","",F10*MAX(12,'0. Supuestos'!$B$21)),"") -> 2141.3 | H10: =IFERROR(IF(D10="","",C10*$B$18),"") -> 3.6 | I10: =IFERROR(IF(D10="","",H10*B10*$B$19),"") -> 165.6 | J10: Cobertura de los 30 días de vacaciones (art. 38 ET) y del descanso semanal del equipo de obrador
A11: TOTAL PLANTILLA | B11: =IFERROR(IF(COUNT(D5:D10)=0,"",SUM(B5:B10)),"") -> 6 | C11: =IFERROR(IF(COUNT(D5:D10)=0,"",SUM(C5:C10)),"") -> 4.39 | D11: =IFERROR(IF(COUNT(D5:D10)=0,"",SUM(D5:D10)),"") -> 6115 | E11: =IFERROR(IF(COUNT(D5:D10)=0,"",SUM(E5:E10)),"") -> 2017.95 | F11: =IFERROR(IF(COUNT(D5:D10)=0,"",SUM(F5:F10)),"") -> 8132.95 | G11: =IFERROR(IF(COUNT(D5:D10)=0,"",SUM(G5:G10)),"") -> 113861.3 | I11: =IFERROR(IF(COUNT(D5:D10)=0,"",SUM(I5:I10)),"") -> 8077.6
A12: CRECIMIENTO DE LA PLANTILLA (coste escalonado)
A13: Coste anual de las incorporaciones del año 2 (€) | B13: 6000 | J13: Coste ANUAL completo (bruto + Seguridad Social × pagas) de lo que se contrate ese año. El P&L lo suma al coste del año anterior: la plantilla no crece con un porcentaje, crece con personas
A14: Coste anual de las incorporaciones del año 3 (€) | B14: 6000 | J14: Coste ANUAL completo (bruto + Seguridad Social × pagas) de lo que se contrate ese año. El P&L lo suma al coste del año anterior: la plantilla no crece con un porcentaje, crece con personas
A15: Coste de personal del año 2 | B15: =IFERROR(IF(G11="","",G11*(1+'0. Supuestos'!$B$48)+B13),"") -> 119861.3
A16: Coste de personal del año 3 | B16: =IFERROR(IF(B15="","",B15*(1+'0. Supuestos'!$B$48)+B14),"") -> 125861.3
A17: COBERTURA POR HORAS DE SERVICIO
A18: Jornada completa del convenio (horas/semana) | B18: 40 | J18: Art. 34.1 del Estatuto de los Trabajadores; tu convenio provincial puede fijar menos
A19: Semanas trabajadas al año por persona | B19: 46 | J19: 46 semanas: 52 menos las vacaciones (30 días naturales, art. 38 ET), los festivos y las ausencias medias
A20: Horas de servicio al día que hay que cubrir | B20: 13 | J20: De la apertura al cierre de la TIENDA. El turno de obrador va en la fila de abajo y no se solapa con el mostrador. Cuéntalas sobre tu horario real
A21: Personas necesarias a la vez en cada franja | B21: 1.7 | J21: Presencia media simultánea en el mostrador a lo largo del día: una persona fija más el refuerzo de las puntas de la mañana y de la merienda
A22: Horas de producción al día ANTES de abrir | B22: 3.5 | J22: Turno de madrugada (4:00-5:00 AM, checklist F4): amasado, formado y horneado de la primera hornada, ANTES de abrir la tienda
A23: Personas en el turno de producción | B23: 1 | J23: El maestro panadero. Si tu obrador arranca con dos personas, súbelo aquí
A24: Horas de servicio a cubrir al año | B24: =IFERROR(IF(OR(B20="",B21="",'0. Supuestos'!$B$6=""),"",B20*B21*'0. Supuestos'!$B$6+B22*B23*'0. Supuestos'!$B$6),"") -> 7936
A25: Horas contratadas al año | B25: =IFERROR(IF(I11="","",I11),"") -> 8077.6
A26: Cobertura (contratadas / necesarias) | B26: =IFERROR(B25/B24,"") -> 1.0178427 | J26: Por debajo del 100 % la plantilla no llega a cubrir el horario que declara el plan: o se contrata más o se recorta el horario
A28: Las columnas «Bruto mes», «Seg. Social», «Coste mes» y «Coste año» son TOTALES de la fila: en un puesto con dos personas incluyen a las dos. «Jornada» es el porcentaje sobre la jornada completa del convenio y sirve para comparar el salario con el suelo legal en proporción. El tipo de Seguridad Social y el número de pagas están en la hoja «0. Supuestos».
A29: El suelo salarial es el MAYOR entre el SMI y el salario de convenio, los dos en la hoja «0. Supuestos»; las jornadas parciales lo llevan en proporción. El convenio aplicable es el PROVINCIAL de hostelería: no existe una tabla salarial estatal única, así que la celda del convenio se entrega vacía para que copies la de tu provincia.

Sheet Instrucciones
A1: INSTRUCCIONES DE USO — Plan financiero Panadería / Obrador
A3: CÓMO SE USA ESTE LIBRO
A4: Este plan financiero es un MODELO: sólo se teclea en las celdas VERDES y el resto se recalcula solo.
A5: 1. «0. Supuestos» es la hoja de mando: transacciones, ticket sin IVA, días de apertura, mezcla de comida y bebida, coste de mercancía, alquiler, financiación e impuestos.
A6: 2. Las partidas de la inversión, los costes fijos y la plantilla se teclean en su propia hoja, también en verde. Ningún número se escribe dos veces.
A7: 3. Sólo «Punto Equilibrio» se deriva entera de lo anterior. En las otras tres hojas también hay celdas verdes que puedes tocar: el escenario pesimista y el optimista en «Escenarios», la estacionalidad y la rampa de arranque en «Tesorería 12 meses», y las cuatro fuentes alternativas de financiación en «Financiación». Todo lo demás se calcula.
A8: 4. Todas las cifras van SIN IVA. Para pasar un PVP a precio sin IVA, divide por el tipo que le corresponda: entre 1,04 el pan común y las harinas panificables (tipo superreducido, art. 91.Dos.1.1.º de la Ley 37/1992 del IVA); entre 1,10 todo el consumo en el acto —comida y bebida, alcohol incluido— (art. 91.Uno.2.2.º) y, cuando se venden para llevar, los demás alimentos, bollería y pastelería incluidas, que son productos alimenticios al tipo reducido por el art. 91.Uno.1.1.º; y entre 1,21 el tipo general, que en hostelería sólo alcanza a lo que sale del local como entrega de bienes excluida del reducido: el alcohol y los refrescos o zumos con azúcares añadidos para llevar o a domicilio (la comida para llevar sigue al 10 %); el libro lo aplica al alcohol del canal de delivery. El tipo de cada línea de venta está en la columna «Tipo de IVA de la línea» del P&L y de ahí salen los cobros, el IVA repercutido y el PVP equivalente. El IVA de la inversión se adelanta y se recupera con el modelo 303.
A9: 5. Si cambias la plantilla, el P&L la lee sola: el coste de personal sale de la hoja «Personal», no de una estimación aparte.
A10: 6. La hoja «Tesorería 12 meses» responde la pregunta que decide una operación bancaria: en qué mes se agota la caja. El saldo mínimo del año nunca puede salir en rojo.
A11: 7. La hoja «Financiación» cuadra lo que hace falta con lo que se aporta y monta el cuadro de amortización del préstamo. Si la diferencia sale en rojo, el plan no está financiado.
A12: 8. El documento Word de este pack es el de la versión 1.1: las cifras válidas son las de este Excel, que es el que se recalcula solo cuando cambias un supuesto.
A14: RATIOS QUE AUDITA EL LIBRO
A15: Los umbrales viven en la columna «Umbral» del bloque RATIOS CLAVE del P&L: cámbialos ahí y el semáforo cambia con ellos.
A17: Ratio | B17: Valor del año 1 | C17: Umbral | D17: Estado
A18: Coste de mercancía / Ventas | B18: =IFERROR(IF('PyG 3 Años'!$B$53="","",'PyG 3 Años'!$B$53),"") -> 0.2885 | C18: =IFERROR(IF('PyG 3 Años'!$E$53="","",'PyG 3 Años'!$E$53),"") -> 0.32 | D18: =IFERROR(IF(OR(B18="",C18=""),"",IF(B18<=C18,"CUMPLE","REVISAR")),"") -> CUMPLE
A19: Coste de personal / Ventas | B19: =IFERROR(IF('PyG 3 Años'!$B$54="","",'PyG 3 Años'!$B$54),"") -> 0.37100456 | C19: =IFERROR(IF('PyG 3 Años'!$E$54="","",'PyG 3 Años'!$E$54),"") -> 0.42 | D19: =IFERROR(IF(OR(B19="",C19=""),"",IF(B19<=C19,"CUMPLE","REVISAR")),"") -> CUMPLE
A20: Alquiler / Ventas | B20: =IFERROR(IF('PyG 3 Años'!$B$55="","",'PyG 3 Años'!$B$55),"") -> 0.082111437 | C20: =IFERROR(IF('PyG 3 Años'!$E$55="","",'PyG 3 Años'!$E$55),"") -> 0.1 | D20: =IFERROR(IF(OR(B20="",C20=""),"",IF(B20<=C20,"CUMPLE","REVISAR")),"") -> CUMPLE
A21: Resultado neto / Ventas | B21: =IFERROR(IF('PyG 3 Años'!$B$56="","",'PyG 3 Años'!$B$56),"") -> 0.055045401 | C21: =IFERROR(IF('PyG 3 Años'!$E$56="","",'PyG 3 Años'!$E$56),"") -> 0.05 | D21: =IFERROR(IF(OR(B21="",C21=""),"",IF(B21>=C21,"CUMPLE","REVISAR")),"") -> CUMPLE
A22: Margen bruto / Ventas | B22: =IFERROR(IF('PyG 3 Años'!$B$51="","",'PyG 3 Años'!$B$51),"") -> 0.6635 | C22: =IFERROR(IF('PyG 3 Años'!$E$51="","",'PyG 3 Años'!$E$51),"") -> 0.62 | D22: =IFERROR(IF(OR(B22="",C22=""),"",IF(B22>=C22,"CUMPLE","REVISAR")),"") -> CUMPLE
A24: CIFRAS DE ESTE PLAN
A25: Inversión total (suma de los bloques) | B25: =IFERROR(IF('Inversión Inicial'!$B$31="","",'Inversión Inicial'!$B$31),"") -> 145215.33
A26: Necesidad total de caja al arranque | B26: =IFERROR(IF('Inversión Inicial'!$B$34="","",'Inversión Inicial'!$B$34),"") -> 164808.33
A27: Fondo de maniobra dotado | B27: =IFERROR(IF('Inversión Inicial'!$B$30="","",'Inversión Inicial'!$B$30),"") -> 43615.325
A28: Facturación prevista del año 1 | B28: =IFERROR(IF('PyG 3 Años'!$B$9="","",'PyG 3 Años'!$B$9),"") -> 306900
A29: Resultado neto del año 1 | B29: =IFERROR(IF('PyG 3 Años'!$B$48="","",'PyG 3 Años'!$B$48),"") -> 16893.434
A30: Transacciones/día para el punto de equilibrio CONTABLE (con la amortización dentro) | B30: =IFERROR(IF('Punto Equilibrio'!$B$15="","",'Punto Equilibrio'!$B$15),"") -> 162.43154
A31: Payback del proyecto (años), antes de la deuda | B31: =IFERROR(IF('Tesorería 12 meses'!$B$31="","",'Tesorería 12 meses'!$B$31),"") -> Más de 3 años
A33: QUÉ HA CAMBIADO RESPECTO DE LA VERSIÓN 1.1
A34: Concepto | B34: v1.1 | C34: v2.2 | D34: Por qué
A35: Coste de personal imputado al P&L | B35: 72.000 € | C35: Sale de la hoja Personal, por fórmula | D35: La cuenta de resultados llevaba tecleada una cifra distinta de la que sumaba su propia hoja de Personal (135.408 €): 63.408 € de diferencia. Con la cifra buena, el coste laboral se comía el 67,7 % de las ventas y el negocio no se sostenía
A36: Plantilla | B36: 5 puestos / 135.408 € | C36: 6 puestos con las jornadas ajustadas / 113.861 € | D36: Dimensionada por las horas que hay que cubrir de verdad —turno de madrugada del obrador, jornada de tienda y una línea para las suplencias de vacaciones y descansos, que antes no existía— y con el techo del 42 % de coste de personal sobre ventas que declara este mismo libro. Ninguna nómina baja del salario mínimo en proporción a su jornada
A37: Transacciones al día | B37: 148 (200.000 € ÷ 4,50 € ÷ 300 días: una cifra derivada, no un dato) | C37: 180 | D37: Dentro del rango 80-200 que la versión anterior publicaba como escenario pesimista y optimista. Con 165 el resultado neto se quedaba por debajo del 5 % que este libro fija como suelo: los costes fijos no crecen con el volumen, así que cada transacción de más va casi entera al resultado
A38: Ticket medio | B38: 4,50 € (sin decir si llevaba IVA) | C38: 5,50 € SIN IVA | D38: Ahora se declara sin IVA, que es como se proyecta un negocio. Está en el tercio alto del rango 3-6 € del propio libro porque el ticket combina barra de pan, bollería y café, no sólo la barra
A39: Alquiler | B39: 2.000 €/mes (24.000 €/año) | C39: 2.100 €/mes | D39: Un obrador necesita más metros que una tienda sola: obrador, tienda y almacén suman los 80 m² mínimos que pide el checklist. Con las ventas del caso base son el 8,2 % de la facturación, por debajo del 10-14 % que declara este mismo libro
A40: Suministros | B40: 800 €/mes (9.600 €/año) | C40: 875 €/mes | D40: Hornos de 30-40 kW de potencia contratada: el consumo eléctrico de un obrador no es el de una tienda. Pide el histórico del local antes de firmar el contrato
A41: Calendario de apertura | B41: Punto de equilibrio calculado a 30 días al mes y escenarios a 300-320 días al año | C41: 310 días al año, un único dato en Supuestos | D41: El libro traía dos calendarios distintos y el punto de equilibrio diario salía entre un 17 y un 20 % por debajo del que corresponde a los días que el propio libro declaraba abrir
A42: Fondo de maniobra | B42: 8.000 € etiquetados «3 meses» | C42: 3 × los costes fijos de caja mensuales, por fórmula | D42: Los 8.000 € cubrían 0,80 meses, no 3. Ahora el colchón se calcula solo y se mueve cuando cambian los costes: si subes el alquiler o la plantilla, sube con ellos
A43: Amortización | B43: 10.450 €/año a 10 años planos sobre TODA la inversión, colchón de caja e imprevistos incluidos | C43: Obra e instalaciones a 10 años y maquinaria a 9 / 9.292 €/año | D43: Sólo se amortiza el inmovilizado: ni el colchón de caja, ni las existencias, ni los imprevistos, que no son bienes. Y la maquinaria a 9 años porque el coeficiente lineal máximo del art. 12.1 de la Ley del Impuesto sobre Sociedades es del 12 % anual: a 8 años el exceso no sería deducible
A44: Imprevistos de obra | B44: 7.500 € redondos bajo el rótulo «Imprevistos (8%)» | C44: 3.700 € (10 % sobre las partidas de obra, por fórmula) | D44: La cifra anterior era un número redondo escrito a mano que no salía de ningún porcentaje del propio libro. Ahora el colchón se calcula sólo sobre lo que de verdad se puede desviar en una reforma —proyecto técnico, obra civil, instalación eléctrica, salida de humos y rotulación—, y no sobre el equipamiento, que se compra con precio cerrado: por eso la cifra BAJA aunque el porcentaje que la calcula sea mayor. Ese porcentaje vive en la hoja de Supuestos: cámbialo y la cifra se recalcula sola, en vez de rehacerse a mano cada vez que se toca un presupuesto
A45: Impuesto de Sociedades | B45: 25 % en los años 2 y 3, sin compensar las pérdidas del año 1 | C45: 15 % en los dos primeros ejercicios con beneficio, compensando las bases negativas | D45: Es lo que fijan los artículos 26 y 29.1 de la Ley del Impuesto sobre Sociedades para una entidad de nueva creación
... A51: Registro sanitario | B51: exigía el registro estatal sin matices | C51: Registro de tu Comunidad Autónoma, con aviso para el canal mayorista | D51: El registro estatal no alcanza al minorista que vende al consumidor final (art. 2.2 del RD 191/2011). Pero la exención del minorista puro no cubre automáticamente la venta a otros negocios: si el mayorista crece, consúltalo con tu gestoría
A53: DATOS DE REFERENCIA DEL SECTOR
A54: Referencia | B54: Valor | C54: Fuente | D54: Nota
A55: Food cost pan artesanal | B55: 25-30 % | C55: Versión anterior de este kit — contrástalo en tu zona | D55: Harina + levadura + agua = bajo coste unitario
A56: Food cost bollería | B56: 32-38 % | C56: Versión anterior de este kit — contrástalo en tu zona | D56: Mantequilla y chocolate suben el coste
A57: Food cost café | B57: 25-30 % | C57: Versión anterior de este kit — contrástalo en tu zona | D57: Café de grano, margen alto
A58: Coste de personal sobre ventas | B58: 35-42 % | C58: Versión anterior de este kit — contrástalo con tu convenio | D58: El más alto de la línea de planes de restauración: turno de madrugada y doble oficio (producción + venta)
A59: Alquiler sobre ventas | B59: 10-14 % | C59: Versión anterior de este kit — contrástalo en tu zona | D59: Un obrador necesita más metros que una tienda sola: el alquiler pesa más que en una cafetería
A60: Ticket medio panadería | B60: 3-6 € | C60: Versión anterior de este kit — contrástalo en tu zona | D60: Barra de pan + bollería + café. El ticket SIN IVA de ESTE plan lo calcula la hoja 0. Supuestos
A61: Producción diaria (kg pan) | B61: 80-200 kg | C61: Versión anterior de este kit — depende de tu horno | D61: Depende del horno y del equipo instalado
A62: Merma de pan (no vendido) | B62: 5-10 % | C62: Versión anterior de este kit — mídela tú cada semana | D62: Pan del día: lo que no se vende se pierde — vigílalo cada semana (checklist F6)
A63: Margen bruto objetivo | B63: > 62 % | C63: Versión anterior de este kit — contrástalo en tu zona | D63: El pan artesanal tiene mejor margen que el industrial
A64: Hora de inicio de producción | B64: 4:00-5:00 AM | C64: Versión anterior de este kit | D64: Turno de madrugada crítico para tener pan a las 7:30
A65: EBITDA objetivo (año 2) | B65: 10-18 % | C65: Versión anterior de este kit — contrástalo en tu zona | D65: El primer año puede ser negativo: es normal en un obrador nuevo
... A67: Convenio colectivo aplicable | B67: PROVINCIAL de hostelería/alimentación | C67: Checklist de apertura, fase 4 | D67: No existe una tabla salarial estatal única: copia la tabla de tu provincia en la celda de Supuestos
A69: Para editar una celda que no esté en verde: Revisar → Desproteger hoja (no tiene contraseña).
A70: Más plantillas y kits del catálogo en aichef.pro/productos-digitales
A71: Diseñado por John Guerrero — chef y consultor gastronómico desde 2010, en cocina desde los 17 años · johnguerrero.es
A72: Versión 2.2 · septiembre 2026 · aichef.pro/plan-negocio-panaderia · info@aichef.pro

Sheet Tesorería 12 meses
A1: PREVISIÓN DE TESORERÍA — AÑO 1
A2: El P&L dice si el negocio gana dinero; esta hoja dice si le queda caja para llegar a fin de mes. Es la primera que mira un banco.
A4: Concepto | B4: Mes 1 (€) | C4: Mes 2 (€) | D4: Mes 3 (€) | E4: Mes 4 (€) | F4: Mes 5 (€) | G4: Mes 6 (€) | H4: Mes 7 (€) | I4: Mes 8 (€) | J4: Mes 9 (€) | K4: Mes 10 (€) | L4: Mes 11 (€) | M4: Mes 12 (€) | N4: Año (€)
A5: Estacionalidad del mes (suma 100 %) | B5: 0.083 | C5: 0.078 | D5: 0.083 | E5: 0.085 | F5: 0.083 | G5: 0.08 | H5: 0.075 | I5: 0.06 | J5: 0.083 | K5: 0.085 | L5: 0.083 | M5: 0.122 | N5: =IFERROR(IF('PyG 3 Años'!$B$9="","",SUM(B5:M5)),"") -> 1 | O5: Perfil de tu zona: agosto flojo en ciudad y fuerte en costa. Tiene que sumar 100 %
A6: Rampa de arranque (% de la actividad de crucero) | B6: =IFERROR(IF('PyG 3 Años'!$B$9="","",MIN(1,'0. Supuestos'!$B$52+(1-'0. Supuestos'!$B$52)*0/MAX(1,'0. Supuestos'!$B$53-1))),"") -> 0.55 | C6: =IFERROR(IF('PyG 3 Años'!$B$9="","",MIN(1,'0. Supuestos'!$B$52+(1-'0. Supuestos'!$B$52)*1/MAX(1,'0. Supuestos'!$B$53-1))),"") -> 0.64 | D6: =IFERROR(IF('PyG 3 Años'!$B$9="","",MIN(1,'0. Supuestos'!$B$52+(1-'0. Supuestos'!$B$52)*2/MAX(1,'0. Supuestos'!$B$53-1))),"") -> 0.73 | E6: =IFERROR(IF('PyG 3 Años'!$B$9="","",MIN(1,'0. Supuestos'!$B$52+(1-'0. Supuestos'!$B$52)*3/MAX(1,'0. Supuestos'!$B$53-1))),"") -> 0.82 | F6: =IFERROR(IF('PyG 3 Años'!$B$9="","",MIN(1,'0. Supuestos'!$B$52+(1-'0. Supuestos'!$B$52)*4/MAX(1,'0. Supuestos'!$B$53-1))),"") -> 0.91 | G6: =IFERROR(IF('PyG 3 Años'!$B$9="","",MIN(1,'0. Supuestos'!$B$52+(1-'0. Supuestos'!$B$52)*5/MAX(1,'0. Supuestos'!$B$53-1))),"") -> 1 | H6: =IFERROR(IF('PyG 3 Años'!$B$9="","",MIN(1,'0. Supuestos'!$B$52+(1-'0. Supuestos'!$B$52)*6/MAX(1,'0. Supuestos'!$B$53-1))),"") -> 1 | I6: =IFERROR(IF('PyG 3 Años'!$B$9="","",MIN(1,'0. Supuestos'!$B$52+(1-'0. Supuestos'!$B$52)*7/MAX(1,'0. Supuestos'!$B$53-1))),"") -> 1 | J6: =IFERROR(IF('PyG 3 Años'!$B$9="","",MIN(1,'0. Supuestos'!$B$52+(1-'0. Supuestos'!$B$52)*8/MAX(1,'0. Supuestos'!$B$53-1))),"") -> 1 | K6: =IFERROR(IF('PyG 3 Años'!$B$9="","",MIN(1,'0. Supuestos'!$B$52+(1-'0. Supuestos'!$B$52)*9/MAX(1,'0. Supuestos'!$B$53-1))),"") -> 1 | L6: =IFERROR(IF('PyG 3 Años'!$B$9="","",MIN(1,'0. Supuestos'!$B$52+(1-'0. Supuestos'!$B$52)*10/MAX(1,'0. Supuestos'!$B$53-1))),"") -> 1 | M6: =IFERROR(IF('PyG 3 Años'!$B$9="","",MIN(1,'0. Supuestos'!$B$52+(1-'0. Supuestos'!$B$52)*11/MAX(1,'0. Supuestos'!$B$53-1))),"") -> 1 | O6: Sube en línea recta desde el porcentaje del mes 1 hasta el 100 % en los meses que digas en Supuestos. Con el mes 1 al 100 % la rampa desaparece
A7: Reparto de la actividad por mes (calculado) | B7: =IFERROR(IF('PyG 3 Años'!$B$9="","",B5*B6/SUMPRODUCT($B$5:$M$5,$B$6:$M$6)),"") -> 0.051327314 | C7: =IFERROR(IF('PyG 3 Años'!$B$9="","",C5*C6/SUMPRODUCT($B$5:$M$5,$B$6:$M$6)),"") -> 0.056128358 | D7: =IFERROR(IF('PyG 3 Años'!$B$9="","",D5*D6/SUMPRODUCT($B$5:$M$5,$B$6:$M$6)),"") -> 0.068125344 | E7: =IFERROR(IF('PyG 3 Años'!$B$9="","",E5*E6/SUMPRODUCT($B$5:$M$5,$B$6:$M$6)),"") -> 0.07836832 | F7: =IFERROR(IF('PyG 3 Años'!$B$9="","",F5*F6/SUMPRODUCT($B$5:$M$5,$B$6:$M$6)),"") -> 0.084923374 | G7: =IFERROR(IF('PyG 3 Años'!$B$9="","",G5*G6/SUMPRODUCT($B$5:$M$5,$B$6:$M$6)),"") -> 0.089949291 | H7: =IFERROR(IF('PyG 3 Años'!$B$9="","",H5*H6/SUMPRODUCT($B$5:$M$5,$B$6:$M$6)),"") -> 0.08432746 | I7: =IFERROR(IF('PyG 3 Años'!$B$9="","",I5*I6/SUMPRODUCT($B$5:$M$5,$B$6:$M$6)),"") -> 0.067461968 | ... M7: =IFERROR(IF('PyG 3 Años'!$B$9="","",M5*M6/SUMPRODUCT($B$5:$M$5,$B$6:$M$6)),"") -> 0.13717267 | N7: =IFERROR(IF('PyG 3 Años'!$B$9="","",SUM(B7:M7)),"") -> 1 | O7: Estacionalidad × rampa, normalizado a 100 %: el AÑO factura lo que dice el P&L, pero repartido como lo reparte un local que acaba de abrir
A8: COBROS
A9: Ventas cobradas (con IVA repercutido) | B9: =IFERROR(IF('PyG 3 Años'!$B$9="","",('PyG 3 Años'!$B$9+'PyG 3 Años'!$B$9*SUMPRODUCT('PyG 3 Años'!$E$10:$E$11,'PyG 3 Años'!$G$10:$G$11))*B7*(1-MIN(30,'0. Supuestos'!$B$58)/30)),"") -> 14996.838 | C9: =IFERROR(IF('PyG 3 Años'!$B$9="","",('PyG 3 Años'!$B$9+'PyG 3 Años'!$B$9*SUMPRODUCT('PyG 3 Años'!$E$10:$E$11,'PyG 3 Años'!$G$10:$G$11))*(C7*(1-MIN(30,'0. Supuestos'!$B$58)/30)+B7*MIN(30,'0. Supuestos'!$B$58)/30)),"") -> 18065.925 | D9: =IFERROR(IF('PyG 3 Años'!$B$9="","",('PyG 3 Años'!$B$9+'PyG 3 Años'!$B$9*SUMPRODUCT('PyG 3 Años'!$E$10:$E$11,'PyG 3 Años'!$G$10:$G$11))*(D7*(1-MIN(30,'0. Supuestos'!$B$58)/30)+C7*MIN(30,'0. Supuestos'!$B$58)/30)),"") -> 21727.073 | E9: =IFERROR(IF('PyG 3 Años'!$B$9="","",('PyG 3 Años'!$B$9+'PyG 3 Años'!$B$9*SUMPRODUCT('PyG 3 Años'!$E$10:$E$11,'PyG 3 Años'!$G$10:$G$11))*(E7*(1-MIN(30,'0. Supuestos'!$B$58)/30)+D7*MIN(30,'0. Supuestos'!$B$58)/30)),"") -> 25109.347 | F9: =IFERROR(IF('PyG 3 Años'!$B$9="","",('PyG 3 Años'!$B$9+'PyG 3 Años'!$B$9*SUMPRODUCT('PyG 3 Años'!$E$10:$E$11,'PyG 3 Años'!$G$10:$G$11))*(F7*(1-MIN(30,'0. Supuestos'!$B$58)/30)+E7*MIN(30,'0. Supuestos'!$B$58)/30)),"") -> 27357.139 | G9: =IFERROR(IF('PyG 3 Años'!$B$9="","",('PyG 3 Años'!$B$9+'PyG 3 Años'!$B$9*SUMPRODUCT('PyG 3 Años'!$E$10:$E$11,'PyG 3 Años'!$G$10:$G$11))*(G7*(1-MIN(30,'0. Supuestos'!$B$58)/30)+F7*MIN(30,'0. Supuestos'!$B$58)/30)),"") -> 29038.42 | H9: =IFERROR(IF('PyG 3 Años'!$B$9="","",('PyG 3 Años'!$B$9+'PyG 3 Años'!$B$9*SUMPRODUCT('PyG 3 Años'!$E$10:$E$11,'PyG 3 Años'!$G$10:$G$11))*(H7*(1-MIN(30,'0. Supuestos'!$B$58)/30)+G7*MIN(30,'0. Supuestos'!$B$58)/30)),"") -> 27558.995 | I9: =IFERROR(IF('PyG 3 Años'!$B$9="","",('PyG 3 Años'!$B$9+'PyG 3 Años'!$B$9*SUMPRODUCT('PyG 3 Años'!$E$10:$E$11,'PyG 3 Años'!$G$10:$G$11))*(I7*(1-MIN(30,'0. Supuestos'!$B$58)/30)+H7*MIN(30,'0. Supuestos'!$B$58)/30)),"") -> 22448.718 | J9: =IFERROR(IF('PyG 3 Años'!$B$9="","",('PyG 3 Años'!$B$9+'PyG 3 Años'!$B$9*SUMPRODUCT('PyG 3 Años'!$E$10:$E$11,'PyG 3 Años'!$G$10:$G$11))*(J7*(1-MIN(30,'0. Supuestos'!$B$58)/30)+I7*MIN(30,'0. Supuestos'!$B$58)/30)),"") -> 29457.098 | ... M9: =IFERROR(IF('PyG 3 Años'!$B$9="","",('PyG 3 Años'!$B$9+'PyG 3 Años'!$B$9*SUMPRODUCT('PyG 3 Años'!$E$10:$E$11,'PyG 3 Años'!$G$10:$G$11))*(M7*(1-MIN(30,'0. Supuestos'!$B$58)/30)+L7*MIN(30,'0. Supuestos'!$B$58)/30)),"") -> 43108.838 | N9: =IFERROR(IF('PyG 3 Años'!$B$9="","",SUM(B9:M9)),"") -> 320191.72 | O9: Ventas del mes con el IVA repercutido, corregidas por los días medios de cobro de la hoja de Supuestos
A10: PAGOS
A11: Compras y costes variables (IVA incluido) | B11: =IFERROR(IF('PyG 3 Años'!$B$9="","",-('PyG 3 Años'!$B$13*(1+'PyG 3 Años'!$G$13)+'PyG 3 Años'!$B$14*(1+'PyG 3 Años'!$G$14)+'PyG 3 Años'!$B$15*(1+'PyG 3 Años'!$G$15)+'PyG 3 Años'!$B$16*(1+'PyG 3 Años'!$G$16)+'PyG 3 Años'!$B$17*(1+'PyG 3 Años'!$G$17)+'PyG 3 Años'!$B$18*(1+'PyG 3 Años'!$G$18))*B7*(1-MIN(30,'0. Supuestos'!$B$59)/30)),"") -> 0 | C11: =IFERROR(IF('PyG 3 Años'!$B$9="","",-('PyG 3 Años'!$B$13*(1+'PyG 3 Años'!$G$13)+'PyG 3 Años'!$B$14*(1+'PyG 3 Años'!$G$14)+'PyG 3 Años'!$B$15*(1+'PyG 3 Años'!$G$15)+'PyG 3 Años'!$B$16*(1+'PyG 3 Años'!$G$16)+'PyG 3 Años'!$B$17*(1+'PyG 3 Años'!$G$17)+'PyG 3 Años'!$B$18*(1+'PyG 3 Años'!$G$18))*(C7*(1-MIN(30,'0. Supuestos'!$B$59)/30)+B7*MIN(30,'0. Supuestos'!$B$59)/30)),"") -> -5694.7559 | D11: =IFERROR(IF('PyG 3 Años'!$B$9="","",-('PyG 3 Años'!$B$13*(1+'PyG 3 Años'!$G$13)+'PyG 3 Años'!$B$14*(1+'PyG 3 Años'!$G$14)+'PyG 3 Años'!$B$15*(1+'PyG 3 Años'!$G$15)+'PyG 3 Años'!$B$16*(1+'PyG 3 Años'!$G$16)+'PyG 3 Años'!$B$17*(1+'PyG 3 Años'!$G$17)+'PyG 3 Años'!$B$18*(1+'PyG 3 Años'!$G$18))*(D7*(1-MIN(30,'0. Supuestos'!$B$59)/30)+C7*MIN(30,'0. Supuestos'!$B$59)/30)),"") -> -6227.4308 | E11: =IFERROR(IF('PyG 3 Años'!$B$9="","",-('PyG 3 Años'!$B$13*(1+'PyG 3 Años'!$G$13)+'PyG 3 Años'!$B$14*(1+'PyG 3 Años'!$G$14)+'PyG 3 Años'!$B$15*(1+'PyG 3 Años'!$G$15)+'PyG 3 Años'!$B$16*(1+'PyG 3 Años'!$G$16)+'PyG 3 Años'!$B$17*(1+'PyG 3 Años'!$G$17)+'PyG 3 Años'!$B$18*(1+'PyG 3 Años'!$G$18))*(E7*(1-MIN(30,'0. Supuestos'!$B$59)/30)+D7*MIN(30,'0. Supuestos'!$B$59)/30)),"") -> -7558.4942 | F11: =IFERROR(IF('PyG 3 Años'!$B$9="","",-('PyG 3 Años'!$B$13*(1+'PyG 3 Años'!$G$13)+'PyG 3 Años'!$B$14*(1+'PyG 3 Años'!$G$14)+'PyG 3 Años'!$B$15*(1+'PyG 3 Años'!$G$15)+'PyG 3 Años'!$B$16*(1+'PyG 3 Años'!$G$16)+'PyG 3 Años'!$B$17*(1+'PyG 3 Años'!$G$17)+'PyG 3 Años'!$B$18*(1+'PyG 3 Años'!$G$18))*(F7*(1-MIN(30,'0. Supuestos'!$B$59)/30)+E7*MIN(30,'0. Supuestos'!$B$59)/30)),"") -> -8694.9504 | G11: =IFERROR(IF('PyG 3 Años'!$B$9="","",-('PyG 3 Años'!$B$13*(1+'PyG 3 Años'!$G$13)+'PyG 3 Años'!$B$14*(1+'PyG 3 Años'!$G$14)+'PyG 3 Años'!$B$15*(1+'PyG 3 Años'!$G$15)+'PyG 3 Años'!$B$16*(1+'PyG 3 Años'!$G$16)+'PyG 3 Años'!$B$17*(1+'PyG 3 Años'!$G$17)+'PyG 3 Años'!$B$18*(1+'PyG 3 Años'!$G$18))*(G7*(1-MIN(30,'0. Supuestos'!$B$59)/30)+F7*MIN(30,'0. Supuestos'!$B$59)/30)),"") -> -9422.2325 | H11: =IFERROR(IF('PyG 3 Años'!$B$9="","",-('PyG 3 Años'!$B$13*(1+'PyG 3 Años'!$G$13)+'PyG 3 Años'!$B$14*(1+'PyG 3 Años'!$G$14)+'PyG 3 Años'!$B$15*(1+'PyG 3 Años'!$G$15)+'PyG 3 Años'!$B$16*(1+'PyG 3 Años'!$G$16)+'PyG 3 Años'!$B$17*(1+'PyG 3 Años'!$G$17)+'PyG 3 Años'!$B$18*(1+'PyG 3 Años'!$G$18))*(H7*(1-MIN(30,'0. Supuestos'!$B$59)/30)+G7*MIN(30,'0. Supuestos'!$B$59)/30)),"") -> -9979.857 | I11: =IFERROR(IF('PyG 3 Años'!$B$9="","",-('PyG 3 Años'!$B$13*(1+'PyG 3 Años'!$G$13)+'PyG 3 Años'!$B$14*(1+'PyG 3 Años'!$G$14)+'PyG 3 Años'!$B$15*(1+'PyG 3 Años'!$G$15)+'PyG 3 Años'!$B$16*(1+'PyG 3 Años'!$G$16)+'PyG 3 Años'!$B$17*(1+'PyG 3 Años'!$G$17)+'PyG 3 Años'!$B$18*(1+'PyG 3 Años'!$G$18))*(I7*(1-MIN(30,'0. Supuestos'!$B$59)/30)+H7*MIN(30,'0. Supuestos'!$B$59)/30)),"") -> -9356.1159 | J11: =IFERROR(IF('PyG 3 Años'!$B$9="","",-('PyG 3 Años'!$B$13*(1+'PyG 3 Años'!$G$13)+'PyG 3 Años'!$B$14*(1+'PyG 3 Años'!$G$14)+'PyG 3 Años'!$B$15*(1+'PyG 3 Años'!$G$15)+'PyG 3 Años'!$B$16*(1+'PyG 3 Años'!$G$16)+'PyG 3 Años'!$B$17*(1+'PyG 3 Años'!$G$17)+'PyG 3 Años'!$B$18*(1+'PyG 3 Años'!$G$18))*(J7*(1-MIN(30,'0. Supuestos'!$B$59)/30)+I7*MIN(30,'0. Supuestos'!$B$59)/30)),"") -> -7484.8928 | ... M11: =IFERROR(IF('PyG 3 Años'!$B$9="","",-('PyG 3 Años'!$B$13*(1+'PyG 3 Años'!$G$13)+'PyG 3 Años'!$B$14*(1+'PyG 3 Años'!$G$14)+'PyG 3 Años'!$B$15*(1+'PyG 3 Años'!$G$15)+'PyG 3 Años'!$B$16*(1+'PyG 3 Años'!$G$16)+'PyG 3 Años'!$B$17*(1+'PyG 3 Años'!$G$17)+'PyG 3 Años'!$B$18*(1+'PyG 3 Años'!$G$18))*(M7*(1-MIN(30,'0. Supuestos'!$B$59)/30)+L7*MIN(30,'0. Supuestos'!$B$59)/30)),"") -> -10354.102 | N11: =IFERROR(IF('PyG 3 Años'!$B$9="","",SUM(B11:M11)),"") -> -95730.531 | O11: =IFERROR("Materia prima, consumibles, comisiones e imprevistos, cada uno con SU tipo de IVA (la columna del P&L) y con los días de pago a proveedor de Supuestos."&IF('0. Supuestos'!$B$59=0,""," Con "&TEXT('0. Supuestos'!$B$59,"0")&" días de pago, las primeras compras se pagan ya en el año siguiente: la columna «Año» de esta fila recoge "&TEXT(MAX(0,12-ROUNDUP('0. Supuestos'!$B$59/30,0)),"0")&" mensualidades de compra, no el coste del ejercicio."),"") -> Materia prima, consumibles, comisiones e imprevistos, cada uno con SU tipo de IVA (la columna del P&L) y con los días de pago a proveedor de Supuestos. Con 30 días de pago, las primeras compras se pagan ya en el año siguiente: la columna «Año» de esta fila recoge 11 mensualidades de compra, no el coste del ejercicio.
A12: Costes fijos de explotación (IVA incluido) | B12: =IFERROR(IF('PyG 3 Años'!$B$9="","",-('PyG 3 Años'!$B$38-'PyG 3 Años'!$B$23-'PyG 3 Años'!$B$36-'PyG 3 Años'!$B$37+'PyG 3 Años'!$B$40)/12),"") -> -5347.75 | C12: =IFERROR(IF('PyG 3 Años'!$B$9="","",-('PyG 3 Años'!$B$38-'PyG 3 Años'!$B$23-'PyG 3 Años'!$B$36-'PyG 3 Años'!$B$37+'PyG 3 Años'!$B$40)/12),"") -> -5347.75 | D12: =IFERROR(IF('PyG 3 Años'!$B$9="","",-('PyG 3 Años'!$B$38-'PyG 3 Años'!$B$23-'PyG 3 Años'!$B$36-'PyG 3 Años'!$B$37+'PyG 3 Años'!$B$40)/12),"") -> -5347.75 | E12: =IFERROR(IF('PyG 3 Años'!$B$9="","",-('PyG 3 Años'!$B$38-'PyG 3 Años'!$B$23-'PyG 3 Años'!$B$36-'PyG 3 Años'!$B$37+'PyG 3 Años'!$B$40)/12),"") -> -5347.75 | F12: =IFERROR(IF('PyG 3 Años'!$B$9="","",-('PyG 3 Años'!$B$38-'PyG 3 Años'!$B$23-'PyG 3 Años'!$B$36-'PyG 3 Años'!$B$37+'PyG 3 Años'!$B$40)/12),"") -> -5347.75 | G12: =IFERROR(IF('PyG 3 Años'!$B$9="","",-('PyG 3 Años'!$B$38-'PyG 3 Años'!$B$23-'PyG 3 Años'!$B$36-'PyG 3 Años'!$B$37+'PyG 3 Años'!$B$40)/12),"") -> -5347.75 | H12: =IFERROR(IF('PyG 3 Años'!$B$9="","",-('PyG 3 Años'!$B$38-'PyG 3 Años'!$B$23-'PyG 3 Años'!$B$36-'PyG 3 Años'!$B$37+'PyG 3 Años'!$B$40)/12),"") -> -5347.75 | I12: =IFERROR(IF('PyG 3 Años'!$B$9="","",-('PyG 3 Años'!$B$38-'PyG 3 Años'!$B$23-'PyG 3 Años'!$B$36-'PyG 3 Años'!$B$37+'PyG 3 Años'!$B$40)/12),"") -> -5347.75 | ... M12: =IFERROR(IF('PyG 3 Años'!$B$9="","",-('PyG 3 Años'!$B$38-'PyG 3 Años'!$B$23-'PyG 3 Años'!$B$36-'PyG 3 Años'!$B$37+'PyG 3 Años'!$B$40)/12),"") -> -5347.75 | N12: =IFERROR(IF('PyG 3 Años'!$B$9="","",SUM(B12:M12)),"") -> -64173 | O12: Los fijos que salen de caja, cada uno con su tipo de IVA: los seguros están exentos y no llevan
A13: Nóminas y Seguridad Social | B13: =IFERROR(IF('PyG 3 Años'!$B$9="","",-'PyG 3 Años'!$B$23/MAX(12,'0. Supuestos'!$B$21)*(1+IF(1='0. Supuestos'!$B$60,(MAX(12,'0. Supuestos'!$B$21)-12)/2,0)+IF(1='0. Supuestos'!$B$61,(MAX(12,'0. Supuestos'!$B$21)-12)/2,0))),"") -> -8132.95 | C13: =IFERROR(IF('PyG 3 Años'!$B$9="","",-'PyG 3 Años'!$B$23/MAX(12,'0. Supuestos'!$B$21)*(1+IF(2='0. Supuestos'!$B$60,(MAX(12,'0. Supuestos'!$B$21)-12)/2,0)+IF(2='0. Supuestos'!$B$61,(MAX(12,'0. Supuestos'!$B$21)-12)/2,0))),"") -> -8132.95 | D13: =IFERROR(IF('PyG 3 Años'!$B$9="","",-'PyG 3 Años'!$B$23/MAX(12,'0. Supuestos'!$B$21)*(1+IF(3='0. Supuestos'!$B$60,(MAX(12,'0. Supuestos'!$B$21)-12)/2,0)+IF(3='0. Supuestos'!$B$61,(MAX(12,'0. Supuestos'!$B$21)-12)/2,0))),"") -> -8132.95 | E13: =IFERROR(IF('PyG 3 Años'!$B$9="","",-'PyG 3 Años'!$B$23/MAX(12,'0. Supuestos'!$B$21)*(1+IF(4='0. Supuestos'!$B$60,(MAX(12,'0. Supuestos'!$B$21)-12)/2,0)+IF(4='0. Supuestos'!$B$61,(MAX(12,'0. Supuestos'!$B$21)-12)/2,0))),"") -> -8132.95 | F13: =IFERROR(IF('PyG 3 Años'!$B$9="","",-'PyG 3 Años'!$B$23/MAX(12,'0. Supuestos'!$B$21)*(1+IF(5='0. Supuestos'!$B$60,(MAX(12,'0. Supuestos'!$B$21)-12)/2,0)+IF(5='0. Supuestos'!$B$61,(MAX(12,'0. Supuestos'!$B$21)-12)/2,0))),"") -> -8132.95 | G13: =IFERROR(IF('PyG 3 Años'!$B$9="","",-'PyG 3 Años'!$B$23/MAX(12,'0. Supuestos'!$B$21)*(1+IF(6='0. Supuestos'!$B$60,(MAX(12,'0. Supuestos'!$B$21)-12)/2,0)+IF(6='0. Supuestos'!$B$61,(MAX(12,'0. Supuestos'!$B$21)-12)/2,0))),"") -> -8132.95 | H13: =IFERROR(IF('PyG 3 Años'!$B$9="","",-'PyG 3 Años'!$B$23/MAX(12,'0. Supuestos'!$B$21)*(1+IF(7='0. Supuestos'!$B$60,(MAX(12,'0. Supuestos'!$B$21)-12)/2,0)+IF(7='0. Supuestos'!$B$61,(MAX(12,'0. Supuestos'!$B$21)-12)/2,0))),"") -> -16265.9 | I13: =IFERROR(IF('PyG 3 Años'!$B$9="","",-'PyG 3 Años'!$B$23/MAX(12,'0. Supuestos'!$B$21)*(1+IF(8='0. Supuestos'!$B$60,(MAX(12,'0. Supuestos'!$B$21)-12)/2,0)+IF(8='0. Supuestos'!$B$61,(MAX(12,'0. Supuestos'!$B$21)-12)/2,0))),"") -> -8132.95 | J13: =IFERROR(IF('PyG 3 Años'!$B$9="","",-'PyG 3 Años'!$B$23/MAX(12,'0. Supuestos'!$B$21)*(1+IF(9='0. Supuestos'!$B$60,(MAX(12,'0. Supuestos'!$B$21)-12)/2,0)+IF(9='0. Supuestos'!$B$61,(MAX(12,'0. Supuestos'!$B$21)-12)/2,0))),"") -> -8132.95 | K13: =IFERROR(IF('PyG 3 Años'!$B$9="","",-'PyG 3 Años'!$B$23/MAX(12,'0. Supuestos'!$B$21)*(1+IF(10='0. Supuestos'!$B$60,(MAX(12,'0. Supuestos'!$B$21)-12)/2,0)+IF(10='0. Supuestos'!$B$61,(MAX(12,'0. Supuestos'!$B$21)-12)/2,0))),"") -> -8132.95 | L13: =IFERROR(IF('PyG 3 Años'!$B$9="","",-'PyG 3 Años'!$B$23/MAX(12,'0. Supuestos'!$B$21)*(1+IF(11='0. Supuestos'!$B$60,(MAX(12,'0. Supuestos'!$B$21)-12)/2,0)+IF(11='0. Supuestos'!$B$61,(MAX(12,'0. Supuestos'!$B$21)-12)/2,0))),"") -> -8132.95 | M13: =IFERROR(IF('PyG 3 Años'!$B$9="","",-'PyG 3 Años'!$B$23/MAX(12,'0. Supuestos'!$B$21)*(1+IF(12='0. Supuestos'!$B$60,(MAX(12,'0. Supuestos'!$B$21)-12)/2,0)+IF(12='0. Supuestos'!$B$61,(MAX(12,'0. Supuestos'!$B$21)-12)/2,0))),"") -> -16265.9 | N13: =IFERROR(IF('PyG 3 Años'!$B$9="","",SUM(B13:M13)),"") -> -113861.3 | O13: Doce mensualidades más las pagas extra en los meses que digas en Supuestos. La suma del año es la misma que la del P&L
A14: Intereses del préstamo | B14: =IFERROR(IF('PyG 3 Años'!$B$9="","",-'Financiación'!$B$44/12),"") -> -600 | C14: =IFERROR(IF('PyG 3 Años'!$B$9="","",-'Financiación'!$B$44/12),"") -> -600 | D14: =IFERROR(IF('PyG 3 Años'!$B$9="","",-'Financiación'!$B$44/12),"") -> -600 | E14: =IFERROR(IF('PyG 3 Años'!$B$9="","",-'Financiación'!$B$44/12),"") -> -600 | F14: =IFERROR(IF('PyG 3 Años'!$B$9="","",-'Financiación'!$B$44/12),"") -> -600 | G14: =IFERROR(IF('PyG 3 Años'!$B$9="","",-'Financiación'!$B$44/12),"") -> -600 | H14: =IFERROR(IF('PyG 3 Años'!$B$9="","",-'Financiación'!$B$44/12),"") -> -600 | I14: =IFERROR(IF('PyG 3 Años'!$B$9="","",-'Financiación'!$B$44/12),"") -> -600 | ... M14: =IFERROR(IF('PyG 3 Años'!$B$9="","",-'Financiación'!$B$44/12),"") -> -600 | N14: =IFERROR(IF('PyG 3 Años'!$B$9="","",SUM(B14:M14)),"") -> -7200
A15: Devolución de principal del préstamo | B15: =IFERROR(IF('PyG 3 Años'!$B$9="","",-'Financiación'!$B$45/12),"") -> 0 | C15: =IFERROR(IF('PyG 3 Años'!$B$9="","",-'Financiación'!$B$45/12),"") -> 0 | D15: =IFERROR(IF('PyG 3 Años'!$B$9="","",-'Financiación'!$B$45/12),"") -> 0 | E15: =IFERROR(IF('PyG 3 Años'!$B$9="","",-'Financiación'!$B$45/12),"") -> 0 | F15: =IFERROR(IF('PyG 3 Años'!$B$9="","",-'Financiación'!$B$45/12),"") -> 0 | G15: =IFERROR(IF('PyG 3 Años'!$B$9="","",-'Financiación'!$B$45/12),"") -> 0 | H15: =IFERROR(IF('PyG 3 Años'!$B$9="","",-'Financiación'!$B$45/12),"") -> 0 | I15: =IFERROR(IF('PyG 3 Años'!$B$9="","",-'Financiación'!$B$45/12),"") -> 0 | ... M15: =IFERROR(IF('PyG 3 Años'!$B$9="","",-'Financiación'!$B$45/12),"") -> 0 | N15: =IFERROR(IF('PyG 3 Años'!$B$9="","",SUM(B15:M15)),"") -> 0
A16: IVA repercutido del mes (memoria) | B16: =IFERROR(IF('PyG 3 Años'!$B$9="","",'PyG 3 Años'!$B$9*B7*SUMPRODUCT('PyG 3 Años'!$E$10:$E$11,'PyG 3 Años'!$G$10:$G$11)),"") -> 910.80104 | C16: =IFERROR(IF('PyG 3 Años'!$B$9="","",'PyG 3 Años'!$B$9*C7*SUMPRODUCT('PyG 3 Años'!$E$10:$E$11,'PyG 3 Años'!$G$10:$G$11)),"") -> 995.99535 | D16: =IFERROR(IF('PyG 3 Años'!$B$9="","",'PyG 3 Años'!$B$9*D7*SUMPRODUCT('PyG 3 Años'!$E$10:$E$11,'PyG 3 Años'!$G$10:$G$11)),"") -> 1208.8814 | E16: =IFERROR(IF('PyG 3 Años'!$B$9="","",'PyG 3 Años'!$B$9*E7*SUMPRODUCT('PyG 3 Años'!$E$10:$E$11,'PyG 3 Años'!$G$10:$G$11)),"") -> 1390.6425 | F16: =IFERROR(IF('PyG 3 Años'!$B$9="","",'PyG 3 Años'!$B$9*F7*SUMPRODUCT('PyG 3 Años'!$E$10:$E$11,'PyG 3 Años'!$G$10:$G$11)),"") -> 1506.9617 | G16: =IFERROR(IF('PyG 3 Años'!$B$9="","",'PyG 3 Años'!$B$9*G7*SUMPRODUCT('PyG 3 Años'!$E$10:$E$11,'PyG 3 Años'!$G$10:$G$11)),"") -> 1596.1464 | H16: =IFERROR(IF('PyG 3 Años'!$B$9="","",'PyG 3 Años'!$B$9*H7*SUMPRODUCT('PyG 3 Años'!$E$10:$E$11,'PyG 3 Años'!$G$10:$G$11)),"") -> 1496.3872 | I16: =IFERROR(IF('PyG 3 Años'!$B$9="","",'PyG 3 Años'!$B$9*I7*SUMPRODUCT('PyG 3 Años'!$E$10:$E$11,'PyG 3 Años'!$G$10:$G$11)),"") -> 1197.1098 | ... M16: =IFERROR(IF('PyG 3 Años'!$B$9="","",'PyG 3 Años'!$B$9*M7*SUMPRODUCT('PyG 3 Años'!$E$10:$E$11,'PyG 3 Años'!$G$10:$G$11)),"") -> 2434.1232 | N16: =IFERROR(IF('PyG 3 Años'!$B$9="","",SUM(B16:M16)),"") -> 17744.958 | O16: Cada línea de venta a SU tipo, leído de la columna de IVA del P&L: en mostrador, alcohol incluido, el reducido (art. 91.Uno.2.2.º de la Ley 37/1992 del IVA); el alcohol que sale por delivery, al general; el pan común y las harinas panificables, al superreducido (art. 91.Dos.1.1.º)
A17: IVA soportado del mes (memoria) | B17: =IFERROR(IF('PyG 3 Años'!$B$9="","",'PyG 3 Años'!$B$39*B7+'PyG 3 Años'!$B$40/12),"") -> 1291.8392 | C17: =IFERROR(IF('PyG 3 Años'!$B$9="","",'PyG 3 Años'!$B$39*C7+'PyG 3 Años'!$B$40/12),"") -> 1328.7014 | D17: =IFERROR(IF('PyG 3 Años'!$B$9="","",'PyG 3 Años'!$B$39*D7+'PyG 3 Años'!$B$40/12),"") -> 1420.8139 | E17: =IFERROR(IF('PyG 3 Años'!$B$9="","",'PyG 3 Años'!$B$39*E7+'PyG 3 Años'!$B$40/12),"") -> 1499.459 | F17: =IFERROR(IF('PyG 3 Años'!$B$9="","",'PyG 3 Años'!$B$39*F7+'PyG 3 Años'!$B$40/12),"") -> 1549.7885 | G17: =IFERROR(IF('PyG 3 Años'!$B$9="","",'PyG 3 Años'!$B$39*G7+'PyG 3 Años'!$B$40/12),"") -> 1588.3773 | H17: =IFERROR(IF('PyG 3 Años'!$B$9="","",'PyG 3 Años'!$B$39*H7+'PyG 3 Años'!$B$40/12),"") -> 1545.2131 | I17: =IFERROR(IF('PyG 3 Años'!$B$9="","",'PyG 3 Años'!$B$39*I7+'PyG 3 Años'!$B$40/12),"") -> 1415.7205 | ... M17: =IFERROR(IF('PyG 3 Años'!$B$9="","",'PyG 3 Años'!$B$39*M7+'PyG 3 Años'!$B$40/12),"") -> 1950.9567 | N17: =IFERROR(IF('PyG 3 Años'!$B$9="","",SUM(B17:M17)),"") -> 18450.963 | O17: Cada partida a su tipo, leído de la columna de IVA del P&L: los seguros y las comisiones de los medios de pago están exentos
A18: IVA a compensar arrastrado (inversión incluida) | E18: =IFERROR(IF('PyG 3 Años'!$B$9="","",'Inversión Inicial'!$B$33),"") -> 19593 | H18: =IFERROR(IF('PyG 3 Años'!$B$9="","",MAX(0,-E19)),"") -> 20518.677 | K18: =IFERROR(IF('PyG 3 Años'!$B$9="","",MAX(0,-H19)),"") -> 20662.551 | O18: El IVA soportado de la INVERSIÓN entra aquí: se compensa contra el repercutido de los trimestres siguientes hasta agotarlo (modelo 303)
A19: Resultado de la liquidación trimestral | E19: =IFERROR(IF('PyG 3 Años'!$B$9="","",SUM(B16:D16)-SUM(B17:D17)-E18),"") -> -20518.677 | H19: =IFERROR(IF('PyG 3 Años'!$B$9="","",SUM(E16:G16)-SUM(E17:G17)-H18),"") -> -20662.551 | K19: =IFERROR(IF('PyG 3 Años'!$B$9="","",SUM(H16:J16)-SUM(H17:J17)-K18),"") -> -20888.261 | O19: Repercutido menos soportado del trimestre menos lo que venía arrastrado. En negativo NO se paga: se compensa en el trimestre siguiente
A20: Pago del IVA (modelo 303) | E20: =IFERROR(IF('PyG 3 Años'!$B$9="","",IF(E19<=0,"",-E19)),"") | H20: =IFERROR(IF('PyG 3 Años'!$B$9="","",IF(H19<=0,"",-H19)),"") | K20: =IFERROR(IF('PyG 3 Años'!$B$9="","",IF(K19<=0,"",-K19)),"") | N20: =IFERROR(IF('PyG 3 Años'!$B$9="","",SUM(B20:M20)),"") -> 0 | O20: Sólo sale caja cuando el resultado del trimestre es positivo. Los meses sin liquidación van en blanco, no a cero. La celda se pinta en ROJO cuando el pago del 303 se lleva más caja de la que queda ese mes
A21: FLUJO DEL MES | B21: =IFERROR(IF('PyG 3 Años'!$B$9="","",SUM(B9:B15)+IF(B20="",0,B20)),"") -> 916.13839 | C21: =IFERROR(IF('PyG 3 Años'!$B$9="","",SUM(C9:C15)+IF(C20="",0,C20)),"") -> -1709.5311 | D21: =IFERROR(IF('PyG 3 Años'!$B$9="","",SUM(D9:D15)+IF(D20="",0,D20)),"") -> 1418.9427 | E21: =IFERROR(IF('PyG 3 Años'!$B$9="","",SUM(E9:E15)+IF(E20="",0,E20)),"") -> 3470.1527 | F21: =IFERROR(IF('PyG 3 Años'!$B$9="","",SUM(F9:F15)+IF(F20="",0,F20)),"") -> 4581.4884 | G21: =IFERROR(IF('PyG 3 Años'!$B$9="","",SUM(G9:G15)+IF(G20="",0,G20)),"") -> 5535.4875 | H21: =IFERROR(IF('PyG 3 Años'!$B$9="","",SUM(H9:H15)+IF(H20="",0,H20)),"") -> -4634.5123 | I21: =IFERROR(IF('PyG 3 Años'!$B$9="","",SUM(I9:I15)+IF(I20="",0,I20)),"") -> -988.09838 | ... M21: =IFERROR(IF('PyG 3 Años'!$B$9="","",SUM(M9:M15)+IF(M20="",0,M20)),"") -> 10541.086 | N21: =IFERROR(IF('PyG 3 Años'!$B$9="","",SUM(B21:M21)),"") -> 39226.886
A22: SALDO ACUMULADO DE CAJA | B22: =IFERROR(IF('PyG 3 Años'!$B$9="","",'Inversión Inicial'!$B$30+B21),"") -> 44531.463 | C22: =IFERROR(IF('PyG 3 Años'!$B$9="","",B22+C21),"") -> 42821.932 | D22: =IFERROR(IF('PyG 3 Años'!$B$9="","",C22+D21),"") -> 44240.875 | E22: =IFERROR(IF('PyG 3 Años'!$B$9="","",D22+E21),"") -> 47711.028 | F22: =IFERROR(IF('PyG 3 Años'!$B$9="","",E22+F21),"") -> 52292.516 | G22: =IFERROR(IF('PyG 3 Años'!$B$9="","",F22+G21),"") -> 57828.004 | H22: =IFERROR(IF('PyG 3 Años'!$B$9="","",G22+H21),"") -> 53193.491 | I22: =IFERROR(IF('PyG 3 Años'!$B$9="","",H22+I21),"") -> 52205.393 | J22: =IFERROR(IF('PyG 3 Años'!$B$9="","",I22+J21),"") -> 60096.898 | ... M22: =IFERROR(IF('PyG 3 Años'!$B$9="","",L22+M21),"") -> 82842.211
A23: Saldo mínimo del año | B23: =IFERROR(IF('PyG 3 Años'!$B$9="","",IF(COUNT(B22:M22)=0,"",MIN(B22:M22))),"") -> 42821.932 | D23: Si es negativo, sube el fondo de maniobra o el préstamo: te quedas sin caja
A24: Mes en el que la caja toca fondo | B24: =IFERROR(IF('PyG 3 Años'!$B$9="","",IF(COUNT(B22:M22)=0,"",MATCH(MIN(B22:M22),B22:M22,0))),"") -> 2 | D24: Es la respuesta a la pregunta que decide una operación bancaria: en qué mes se agota la caja
A25: RETORNO DE LA INVERSIÓN
A26: Flujo de caja libre antes de la deuda, año 1 | B26: =IFERROR(IF('PyG 3 Años'!$B$9="","",'PyG 3 Años'!$B$48+'PyG 3 Años'!$B$36+'Financiación'!$B$44),"") -> 33385.656 | D26: Resultado neto más amortización (que no se paga) más los intereses de ese año: el principal no se resta porque este flujo es ANTES de la deuda. La MISMA base que los años 2 y 3, para que el payback compare peras con peras
A27: Flujo de caja libre antes de la deuda, año 2 | B27: =IFERROR(IF('PyG 3 Años'!$B$9="","",'PyG 3 Años'!$C$48+'PyG 3 Años'!$C$36+'Financiación'!$B$46),"") -> 49055.727 | D27: Resultado neto más amortización (que no se paga) más los intereses de ese año: el principal no se resta porque este flujo es ANTES de la deuda. Sin tabla mensual, es una estimación
A28: Flujo de caja libre antes de la deuda, año 3 | B28: =IFERROR(IF('PyG 3 Años'!$B$9="","",'PyG 3 Años'!$D$48+'PyG 3 Años'!$D$36+'Financiación'!$B$48),"") -> 52440.009 | D28: Resultado neto más amortización (que no se paga) más los intereses de ese año: el principal no se resta porque este flujo es ANTES de la deuda. Sin tabla mensual, es una estimación
A29: Informativo: flujo REAL de caja del año 1 (tabla mensual, antes de la deuda) | B29: =IFERROR(IF('PyG 3 Años'!$B$9="","",N21+'Financiación'!$B$44+'Financiación'!$B$45),"") -> 46426.886 | D29: La suma de los doce FLUJO DEL MES de arriba, devolviéndole los intereses y el principal que se pagaron ese año. NO es la que usa el payback: lleva dentro el IVA que todavía no se ha liquidado y el crédito del proveedor, dos cosas que hay que devolver y que los años 2 y 3 no tienen
A30: Inversión a recuperar (sin el IVA, que se recupera por el 303) | B30: =IFERROR(IF('PyG 3 Años'!$B$9="","",'Inversión Inicial'!$B$34-'Inversión Inicial'!$B$33),"") -> 145215.33 | D30: CAPEX más fondo de maniobra: la necesidad total de caja MENOS el IVA soportado de la inversión, que no se pierde (se recupera con el modelo 303 y esta misma hoja lo compensa trimestre a trimestre). El fondo de maniobra sí se recupera al cerrar, pero hasta entonces está inmovilizado
A31: Payback del proyecto (años), antes de la deuda | B31: =IFERROR(IF('PyG 3 Años'!$B$9="","",IF(B26>=B30,ROUND(B30/B26,1),IF(B26+B27>=B30,ROUND(1+(B30-B26)/B27,1),IF(B26+B27+B28>=B30,ROUND(2+(B30-B26-B27)/B28,1),"Más de 3 años")))),"") -> Más de 3 años | D31: Mide cuánto tarda el negocio en devolver la inversión con lo que genera ANTES de pagar al banco, con la MISMA base de flujo en los tres años; si puedes pagar la cuota lo dice el DSCR de la hoja de Financiación. El documento Word del pack sigue en la versión 1.1 y no lee esta celda: las cifras válidas son las de este libro
A32: Payback sobre el CAPEX, sin fondo de maniobra (años) | B32: =IFERROR(IF('PyG 3 Años'!$B$9="","",IF(B26>='Inversión Inicial'!$B$32,ROUND('Inversión Inicial'!$B$32/B26,1),IF(B26+B27>='Inversión Inicial'!$B$32,ROUND(1+('Inversión Inicial'!$B$32-B26)/B27,1),IF(B26+B27+B28>='Inversión Inicial'!$B$32,ROUND(2+('Inversión Inicial'!$B$32-B26-B27)/B28,1),"Más de 3 años")))),"") -> 2.4 | D32: El mismo cálculo sobre lo que se COMPRA (obra, equipamiento, lanzamiento y constitución), sin el fondo de maniobra: ese dinero no se gasta, se inmoviliza y vuelve al cerrar el negocio. Informativo: el payback que se publica es el de arriba
A34: El IVA del cuarto trimestre se liquida en enero del año siguiente, así que no aparece en este cuadro. El Impuesto de Sociedades del año 1 se paga en julio del año 2. La cuota del préstamo se reparte en doce partes iguales siguiendo el cuadro ANUAL de la hoja de Financiación, y las nóminas en doce mensualidades más las dos pagas extra en su mes.

Sheet Financiación
A1: PLAN DE FINANCIACIÓN
A2: Qué hace falta, de dónde sale y cuánto cuesta devolverlo. Es la hoja que el banco pide junto con el P&L.
A4: Concepto | B4: Importe | C4: Notas
A5: ORIGEN DE FONDOS
A6: Recursos propios de los socios | B6: =IFERROR(IF('0. Supuestos'!$B$30="","",'0. Supuestos'!$B$30),"") -> 50000
A7: Préstamo bancario | B7: =IFERROR(IF('0. Supuestos'!$B$31="","",'0. Supuestos'!$B$31),"") -> 120000
A8: Línea ICO (avalada por el ICO, la concede tu banco) | B8: 0 | C8: Consulta las líneas del ejercicio en curso en ico.es
A9: Préstamo participativo ENISA | B9: 0 | C9: Para sociedades; sin garantías personales
A10: Business angels o socios inversores | B10: 0 | C10: Entra en el capital: diluye, no se devuelve
A11: Subvenciones autonómicas o locales | B11: 0 | C11: Suelen cobrarse DESPUÉS de justificar el gasto
A12: TOTAL ORIGEN DE FONDOS | B12: =IFERROR(IF(COUNT(B6:B11)=0,"",SUM(B6:B11)),"") -> 170000
A13: USOS
A14: Necesidad total de caja al arranque | B14: =IFERROR(IF('Inversión Inicial'!$B$34="","",'Inversión Inicial'!$B$34),"") -> 164808.33 | C14: Inversión más el IVA que hay que adelantar
A15: Diferencia (origen - usos) | B15: =IFERROR(B12-B14,"") -> 5191.675 | C15: En rojo (negativa) el plan NO está financiado. Muy por encima de cero tampoco es gratis: se pagan intereses por un dinero que no se usa
A16: Diferencia sobre los usos (%) | B16: =IFERROR(B15/B14,"") -> 0.031501291 | C16: Ámbar por encima del margen que fijes: es deuda que pagas sin necesitarla
A17: Exceso de financiación admisible (%) | B17: 0.05 | C17: Un pequeño colchón sobre la necesidad es sano; un 20 % de más son intereses tirados
A18: Préstamo que ajustaría el origen a la necesidad | B18: =IFERROR(MAX(0,B14-B12+B7),"") -> 114808.33 | C18: Cópialo en «Préstamo bancario solicitado» de la hoja de Supuestos y la diferencia se pone a cero
A19: CONDICIONES DEL PRÉSTAMO
A20: Importe del principal | B20: =IFERROR(IF('0. Supuestos'!$B$31=0,"",'0. Supuestos'!$B$31),"") -> 120000
A21: Tipo de interés nominal anual | B21: =IFERROR(IF('0. Supuestos'!$B$32="","",'0. Supuestos'!$B$32),"") -> 0.06
A22: Plazo total (años) | B22: =IFERROR(IF('0. Supuestos'!$B$33="","",'0. Supuestos'!$B$33),"") -> 7
A23: Carencia de principal aplicada (años) | B23: =IFERROR(IF(OR('0. Supuestos'!$B$34="",'0. Supuestos'!$B$33=""),"",IF('0. Supuestos'!$B$34>='0. Supuestos'!$B$33,0,'0. Supuestos'!$B$34)),"") -> 1 | C23: Una carencia igual o mayor que el plazo no existe: la hoja la anula en origen
A24: Cuota anual durante la amortización | B24: =IFERROR(IF(B22-B23<=0,"",IF(B21=0,B20/(B22-B23),B20*B21/(1-(1+B21)^-(B22-B23)))),"") -> 24403.515 | C24: Sistema francés, anualidad algebraica. Con el tipo al 0 % es el principal entre los años de amortización: sin esa rama el cuadro se apagaba entero
A25: CUADRO DE AMORTIZACIÓN
A26: Año | B26: Capital pendiente | C26: Intereses | D26: Amortización de principal | E26: Cuota total | F26: Capital al cierre | G26: Flujo disponible para la deuda (después de impuestos; del año 4 en adelante, el del año 3 mantenido) | H26: DSCR del año
A27: 1 | B27: =IFERROR(IF(B20="","",B20),"") -> 120000 | C27: =IFERROR(IF(OR(1>B22,B27=""),"",B27*B21),"") -> 7200 | D27: =IFERROR(IF(OR(1>B22,B27=""),"",IF(1<=B23,0,MIN(B27,B24-C27))),"") -> 0 | E27: =IFERROR(IF(C27="","",C27+D27),"") -> 7200 | F27: =IFERROR(IF(D27="","",B27-D27),"") -> 120000 | G27: =IFERROR(IF(E27="","",'PyG 3 Años'!$B$41-'PyG 3 Años'!$B$46+'PyG 3 Años'!$B$36+'PyG 3 Años'!$B$37),"") -> 33385.656 | H27: =IFERROR(IF(OR(E27="",E27=0),"",G27/E27),"") -> 4.6368966
A28: 2 | B28: =IFERROR(IF(OR(2>B22,F27=""),"",F27),"") -> 120000 | C28: =IFERROR(IF(OR(2>B22,B28=""),"",B28*B21),"") -> 7200 | D28: =IFERROR(IF(OR(2>B22,B28=""),"",IF(2<=B23,0,MIN(B28,B24-C28))),"") -> 17203.515 | E28: =IFERROR(IF(C28="","",C28+D28),"") -> 24403.515 | F28: =IFERROR(IF(D28="","",B28-D28),"") -> 102796.48 | G28: =IFERROR(IF(E28="","",'PyG 3 Años'!$C$41-'PyG 3 Años'!$C$46+'PyG 3 Años'!$C$36+'PyG 3 Años'!$C$37),"") -> 49055.727 | H28: =IFERROR(IF(OR(E28="",E28=0),"",G28/E28),"") -> 2.010191
A29: 3 | B29: =IFERROR(IF(OR(3>B22,F28=""),"",F28),"") -> 102796.48 | C29: =IFERROR(IF(OR(3>B22,B29=""),"",B29*B21),"") -> 6167.7891 | D29: =IFERROR(IF(OR(3>B22,B29=""),"",IF(3<=B23,0,MIN(B29,B24-C29))),"") -> 18235.726 | E29: =IFERROR(IF(C29="","",C29+D29),"") -> 24403.515 | F29: =IFERROR(IF(D29="","",B29-D29),"") -> 84560.758 | G29: =IFERROR(IF(E29="","",'PyG 3 Años'!$D$41-'PyG 3 Años'!$D$46+'PyG 3 Años'!$D$36+'PyG 3 Años'!$D$37),"") -> 52440.009 | H29: =IFERROR(IF(OR(E29="",E29=0),"",G29/E29),"") -> 2.1488711
A30: 4 | B30: =IFERROR(IF(OR(4>B22,F29=""),"",F29),"") -> 84560.758 | C30: =IFERROR(IF(OR(4>B22,B30=""),"",B30*B21),"") -> 5073.6455 | D30: =IFERROR(IF(OR(4>B22,B30=""),"",IF(4<=B23,0,MIN(B30,B24-C30))),"") -> 19329.87 | E30: =IFERROR(IF(C30="","",C30+D30),"") -> 24403.515 | F30: =IFERROR(IF(D30="","",B30-D30),"") -> 65230.888 | G30: =IFERROR(IF(E30="","",'PyG 3 Años'!$D$41-'PyG 3 Años'!$D$46+'PyG 3 Años'!$D$36+'PyG 3 Años'!$D$37),"") -> 52440.009 | H30: =IFERROR(IF(OR(E30="",E30=0),"",G30/E30),"") -> 2.1488711
A31: 5 | B31: =IFERROR(IF(OR(5>B22,F30=""),"",F30),"") -> 65230.888 | C31: =IFERROR(IF(OR(5>B22,B31=""),"",B31*B21),"") -> 3913.8533 | D31: =IFERROR(IF(OR(5>B22,B31=""),"",IF(5<=B23,0,MIN(B31,B24-C31))),"") -> 20489.662 | E31: =IFERROR(IF(C31="","",C31+D31),"") -> 24403.515 | F31: =IFERROR(IF(D31="","",B31-D31),"") -> 44741.226 | G31: =IFERROR(IF(E31="","",'PyG 3 Años'!$D$41-'PyG 3 Años'!$D$46+'PyG 3 Años'!$D$36+'PyG 3 Años'!$D$37),"") -> 52440.009 | H31: =IFERROR(IF(OR(E31="",E31=0),"",G31/E31),"") -> 2.1488711
A32: 6 | B32: =IFERROR(IF(OR(6>B22,F31=""),"",F31),"") -> 44741.226 | C32: =IFERROR(IF(OR(6>B22,B32=""),"",B32*B21),"") -> 2684.4736 | D32: =IFERROR(IF(OR(6>B22,B32=""),"",IF(6<=B23,0,MIN(B32,B24-C32))),"") -> 21719.042 | E32: =IFERROR(IF(C32="","",C32+D32),"") -> 24403.515 | F32: =IFERROR(IF(D32="","",B32-D32),"") -> 23022.184 | G32: =IFERROR(IF(E32="","",'PyG 3 Años'!$D$41-'PyG 3 Años'!$D$46+'PyG 3 Años'!$D$36+'PyG 3 Años'!$D$37),"") -> 52440.009 | H32: =IFERROR(IF(OR(E32="",E32=0),"",G32/E32),"") -> 2.1488711
A33: 7 | B33: =IFERROR(IF(OR(7>B22,F32=""),"",F32),"") -> 23022.184 | C33: =IFERROR(IF(OR(7>B22,B33=""),"",B33*B21),"") -> 1381.3311 | D33: =IFERROR(IF(OR(7>B22,B33=""),"",IF(7<=B23,0,MIN(B33,B24-C33))),"") -> 23022.184 | E33: =IFERROR(IF(C33="","",C33+D33),"") -> 24403.515 | F33: =IFERROR(IF(D33="","",B33-D33),"") -> 1.0913936e-10 | G33: =IFERROR(IF(E33="","",'PyG 3 Años'!$D$41-'PyG 3 Años'!$D$46+'PyG 3 Años'!$D$36+'PyG 3 Años'!$D$37),"") -> 52440.009 | H33: =IFERROR(IF(OR(E33="",E33=0),"",G33/E33),"") -> 2.1488711
A34: 8 | B34: =IFERROR(IF(OR(8>B22,F33=""),"",F33),"") | C34: =IFERROR(IF(OR(8>B22,B34=""),"",B34*B21),"") | D34: =IFERROR(IF(OR(8>B22,B34=""),"",IF(8<=B23,0,MIN(B34,B24-C34))),"") | E34: =IFERROR(IF(C34="","",C34+D34),"") | F34: =IFERROR(IF(D34="","",B34-D34),"") | G34: =IFERROR(IF(E34="","",'PyG 3 Años'!$D$41-'PyG 3 Años'!$D$46+'PyG 3 Años'!$D$36+'PyG 3 Años'!$D$37),"") | H34: =IFERROR(IF(OR(E34="",E34=0),"",G34/E34),"")
A35: 9 | B35: =IFERROR(IF(OR(9>B22,F34=""),"",F34),"") | C35: =IFERROR(IF(OR(9>B22,B35=""),"",B35*B21),"") | D35: =IFERROR(IF(OR(9>B22,B35=""),"",IF(9<=B23,0,MIN(B35,B24-C35))),"") | E35: =IFERROR(IF(C35="","",C35+D35),"") | F35: =IFERROR(IF(D35="","",B35-D35),"") | G35: =IFERROR(IF(E35="","",'PyG 3 Años'!$D$41-'PyG 3 Años'!$D$46+'PyG 3 Años'!$D$36+'PyG 3 Años'!$D$37),"") | H35: =IFERROR(IF(OR(E35="",E35=0),"",G35/E35),"")
A36: 10 | B36: =IFERROR(IF(OR(10>B22,F35=""),"",F35),"") | C36: =IFERROR(IF(OR(10>B22,B36=""),"",B36*B21),"") | D36: =IFERROR(IF(OR(10>B22,B36=""),"",IF(10<=B23,0,MIN(B36,B24-C36))),"") | E36: =IFERROR(IF(C36="","",C36+D36),"") | F36: =IFERROR(IF(D36="","",B36-D36),"") | G36: =IFERROR(IF(E36="","",'PyG 3 Años'!$D$41-'PyG 3 Años'!$D$46+'PyG 3 Años'!$D$36+'PyG 3 Años'!$D$37),"") | H36: =IFERROR(IF(OR(E36="",E36=0),"",G36/E36),"")
A37: 11 | B37: =IFERROR(IF(OR(11>B22,F36=""),"",F36),"") | C37: =IFERROR(IF(OR(11>B22,B37=""),"",B37*B21),"") | D37: =IFERROR(IF(OR(11>B22,B37=""),"",IF(11<=B23,0,MIN(B37,B24-C37))),"") | E37: =IFERROR(IF(C37="","",C37+D37),"") | F37: =IFERROR(IF(D37="","",B37-D37),"") | G37: =IFERROR(IF(E37="","",'PyG 3 Años'!$D$41-'PyG 3 Años'!$D$46+'PyG 3 Años'!$D$36+'PyG 3 Años'!$D$37),"") | H37: =IFERROR(IF(OR(E37="",E37=0),"",G37/E37),"")
A38: 12 | B38: =IFERROR(IF(OR(12>B22,F37=""),"",F37),"") | C38: =IFERROR(IF(OR(12>B22,B38=""),"",B38*B21),"") | D38: =IFERROR(IF(OR(12>B22,B38=""),"",IF(12<=B23,0,MIN(B38,B24-C38))),"") | E38: =IFERROR(IF(C38="","",C38+D38),"") | F38: =IFERROR(IF(D38="","",B38-D38),"") | G38: =IFERROR(IF(E38="","",'PyG 3 Años'!$D$41-'PyG 3 Años'!$D$46+'PyG 3 Años'!$D$36+'PyG 3 Años'!$D$37),"") | H38: =IFERROR(IF(OR(E38="",E38=0),"",G38/E38),"")
A39: 13 | B39: =IFERROR(IF(OR(13>B22,F38=""),"",F38),"") | C39: =IFERROR(IF(OR(13>B22,B39=""),"",B39*B21),"") | D39: =IFERROR(IF(OR(13>B22,B39=""),"",IF(13<=B23,0,MIN(B39,B24-C39))),"") | E39: =IFERROR(IF(C39="","",C39+D39),"") | F39: =IFERROR(IF(D39="","",B39-D39),"") | G39: =IFERROR(IF(E39="","",'PyG 3 Años'!$D$41-'PyG 3 Años'!$D$46+'PyG 3 Años'!$D$36+'PyG 3 Años'!$D$37),"") | H39: =IFERROR(IF(OR(E39="",E39=0),"",G39/E39),"")
A40: 14 | B40: =IFERROR(IF(OR(14>B22,F39=""),"",F39),"") | C40: =IFERROR(IF(OR(14>B22,B40=""),"",B40*B21),"") | D40: =IFERROR(IF(OR(14>B22,B40=""),"",IF(14<=B23,0,MIN(B40,B24-C40))),"") | E40: =IFERROR(IF(C40="","",C40+D40),"") | F40: =IFERROR(IF(D40="","",B40-D40),"") | G40: =IFERROR(IF(E40="","",'PyG 3 Años'!$D$41-'PyG 3 Años'!$D$46+'PyG 3 Años'!$D$36+'PyG 3 Años'!$D$37),"") | H40: =IFERROR(IF(OR(E40="",E40=0),"",G40/E40),"")
A41: 15 | B41: =IFERROR(IF(OR(15>B22,F40=""),"",F40),"") | C41: =IFERROR(IF(OR(15>B22,B41=""),"",B41*B21),"") | D41: =IFERROR(IF(OR(15>B22,B41=""),"",IF(15<=B23,0,MIN(B41,B24-C41))),"") | E41: =IFERROR(IF(C41="","",C41+D41),"") | F41: =IFERROR(IF(D41="","",B41-D41),"") | G41: =IFERROR(IF(E41="","",'PyG 3 Años'!$D$41-'PyG 3 Años'!$D$46+'PyG 3 Años'!$D$36+'PyG 3 Años'!$D$37),"") | H41: =IFERROR(IF(OR(E41="",E41=0),"",G41/E41),"")
A42: Tolerancia de cierre del cuadro (€) | B42: 0.01 | C42: Margen por redondeo. Por encima, el cuadro no cierra y hay capital sin devolver
A43: Capital pendiente al vencimiento | B43: =IFERROR(IF(B20="","",ROUND(B20-SUM(D27:D41),2)),"") -> 0 | C43: Tiene que ser cero: el principal devuelto en el cuadro tiene que ser el prestado. Si sale positivo, el plazo no llega
A44: Intereses del año 1 | B44: =IFERROR(IF(B20="","",IF(C27="",0,C27)),"") -> 7200
A45: Devolución de principal del año 1 | B45: =IFERROR(IF(B20="","",IF(D27="",0,D27)),"") -> 0
A46: Intereses del año 2 | B46: =IFERROR(IF(B20="","",IF(C28="",0,C28)),"") -> 7200
A47: Devolución de principal del año 2 | B47: =IFERROR(IF(B20="","",IF(D28="",0,D28)),"") -> 17203.515
A48: Intereses del año 3 | B48: =IFERROR(IF(B20="","",IF(C29="",0,C29)),"") -> 6167.7891
A49: Devolución de principal del año 3 | B49: =IFERROR(IF(B20="","",IF(D29="",0,D29)),"") -> 18235.726
A50: COBERTURA DEL SERVICIO DE LA DEUDA (DSCR)
A51: DSCR del año 1 | B51: =IFERROR(('PyG 3 Años'!$B$41-'PyG 3 Años'!$B$46+'PyG 3 Años'!$B$36+B44)/(B44+B45),"") -> 4.6368966 | C51: Año de CARENCIA si la hay: con sólo intereses en el denominador el ratio se dispara y no mide el negocio
A52: DSCR del año 2 | B52: =IFERROR(('PyG 3 Años'!$C$41-'PyG 3 Años'!$C$46+'PyG 3 Años'!$C$36+B46)/(B46+B47),"") -> 2.010191
A53: DSCR del año 3 | B53: =IFERROR(('PyG 3 Años'!$D$41-'PyG 3 Años'!$D$46+'PyG 3 Años'!$D$36+B48)/(B48+B49),"") -> 2.1488711
A54: DSCR mínimo de todo el cuadro | B54: =IFERROR(IF(COUNT(H27:H41)=0,"",MIN(H27:H41)),"") -> 2.010191 | C54: El peor año de los que dura el préstamo, no el mejor de los tres que proyecta el P&L. Es el número que decide una operación. Ojo al alcance: los años 1 a 3 salen del P&L y del año 4 en adelante el cuadro MANTIENE el flujo del año 3, así que el mínimo de esos años es una proyección sostenida, no un año calculado. El flujo va después de impuestos
A56: El DSCR se calcula ANTES de la deuda y DESPUÉS de impuestos: al resultado antes de impuestos se le resta el Impuesto de Sociedades y se le devuelven la amortización contable y los intereses; el resultado se divide entre lo que hay que pagar ese año. Por debajo del mínimo de la hoja de Supuestos, el negocio no genera para pagar el préstamo. En el cuadro, el flujo de caja disponible de los años 4 en adelante se mantiene en el del año 3: el P&L sólo proyecta tres, y aquí no se inventa un crecimiento que no está calculado.
