Workbook

Sheet Instructions
A1: Multi-Method Menu Engineering Matrix
A2: AI Chef Pro · aichef.pro — Food Cost + Menu Engineering Guide
A4: How to use this workbook
A5: 1. Enter your menu on the "Data" sheet: dish, category, units sold last month, plate cost and menu price BEFORE tax.
A6: 2. The plate cost comes from your recipe cost card (recipe-cost-card.xlsx, in this same pack). The workbook works out the dine-in menu price with tax.
A7: 3. The Kasavana-Smith, Miller, Pavesic and Goal Value sheets read that data and classify each dish with their own method. You don't type anything there.
A8: 4. Each method is applied WITHIN its category: a dessert is compared with the desserts, not with the ribeyes.
A9: 5. Open "Comparison": it shows the four readings of the same dish, how many fall outside the best category and a diagnosis of what to do.
A10: 6. Take the decisions to 90-day-action-plan.xlsx with an owner and a date. An analysis without a date changes nothing.
A11: 7. The "Prix Fixe Menu" sheet stands apart: on a set-price menu the margin isn't decided by the price, it's decided by the mix of choices your guests make.
A12: 8. Adjust the popularity threshold factor and the labor and other variable cost percentages if your restaurant doesn't look like the example.
A14: Green cells = editable fields
... A30: Version 1.0 · October 2026 · aichef.pro/en/digital-products/food-cost-menu-engineering-guide · info@aichef.pro

Sheet Data
A1: Menu data
A2: AI Chef Pro · aichef.pro — Food Cost + Menu Engineering Guide
E3: The plate cost comes from your recipe cost card; the menu price goes in BEFORE tax.
A4: # | B4: Dish | C4: Category | D4: Units sold (month) | E4: Plate cost | F4: Menu price pre-tax | G4: Contribution margin | H4: Food cost (%) | I4: Dine-in menu price WITH tax | J4: Units in its category | K4: Dishes in its category with sales | L4: Menu Mix in Category (MM%) | M4: Popularity threshold in its category (%) | N4: Category weighted avg CM | O4: Category weighted avg food cost (%) | P4: Dish weighted CM: CM × units | Q4: Category average of weighted CM
A5: 1 | B5: Iberico ham croquettes (6 pcs) | C5: Starters | D5: 420 | E5: 2.1 | F5: 8.6 | G5: =IFERROR(IF(OR($E5="",$F5=""),"",$F5-$E5),"") -> 6.5 | H5: =IFERROR(IF(OR($E5="",$F5="",$F5=0),"",$E5/$F5),"") -> 0.24418605 | I5: =IFERROR(IF(OR($F5="",$D$34=""),"",$F5*(1+$D$34)),"") -> 8.6 | J5: =IFERROR(IF($C5="","",SUMPRODUCT(--($C$5:$C$29=$C5),$D$5:$D$29)),"") -> 1730 | K5: =IFERROR(IF($C5="","",SUMPRODUCT(--($C$5:$C$29=$C5),--($D$5:$D$29>0))),"") -> 7 | L5: =IFERROR(IF(OR($D5="",$J5="",$J5=0),"",$D5/$J5),"") -> 0.24277457 | M5: =IFERROR(IF(OR($K5="",$K5=0,$D$33=""),"",$D$33/$K5),"") -> 0.1 | N5: =IFERROR(IF(OR($J5="",$J5=0),"",SUMPRODUCT(--($C$5:$C$29=$C5),$D$5:$D$29,$G$5:$G$29)/$J5),"") -> 7.4635838 | O5: =IFERROR(IF(SUMPRODUCT(--($C$5:$C$29=$C5),$D$5:$D$29,$F$5:$F$29)=0,"",SUMPRODUCT(--($C$5:$C$29=$C5),$D$5:$D$29,$E$5:$E$29)/SUMPRODUCT(--($C$5:$C$29=$C5),$D$5:$D$29,$F$5:$F$29)),"") -> 0.30714746 | P5: =IFERROR(IF(OR($G5="",$D5=""),"",$G5*$D5),"") -> 2730 | Q5: =IFERROR(IF(OR($K5="",$K5=0),"",SUMPRODUCT(--($C$5:$C$29=$C5),$D$5:$D$29,$G$5:$G$29)/$K5),"") -> 1844.5714
A6: 2 | B6: Heirloom tomato salad with tuna belly and scallions | C6: Starters | D6: 310 | E6: 3.6 | F6: 11.8 | G6: =IFERROR(IF(OR($E6="",$F6=""),"",$F6-$E6),"") -> 8.2 | H6: =IFERROR(IF(OR($E6="",$F6="",$F6=0),"",$E6/$F6),"") -> 0.30508475 | I6: =IFERROR(IF(OR($F6="",$D$34=""),"",$F6*(1+$D$34)),"") -> 11.8 | J6: =IFERROR(IF($C6="","",SUMPRODUCT(--($C$5:$C$29=$C6),$D$5:$D$29)),"") -> 1730 | K6: =IFERROR(IF($C6="","",SUMPRODUCT(--($C$5:$C$29=$C6),--($D$5:$D$29>0))),"") -> 7 | L6: =IFERROR(IF(OR($D6="",$J6="",$J6=0),"",$D6/$J6),"") -> 0.17919075 | M6: =IFERROR(IF(OR($K6="",$K6=0,$D$33=""),"",$D$33/$K6),"") -> 0.1 | N6: =IFERROR(IF(OR($J6="",$J6=0),"",SUMPRODUCT(--($C$5:$C$29=$C6),$D$5:$D$29,$G$5:$G$29)/$J6),"") -> 7.4635838 | O6: =IFERROR(IF(SUMPRODUCT(--($C$5:$C$29=$C6),$D$5:$D$29,$F$5:$F$29)=0,"",SUMPRODUCT(--($C$5:$C$29=$C6),$D$5:$D$29,$E$5:$E$29)/SUMPRODUCT(--($C$5:$C$29=$C6),$D$5:$D$29,$F$5:$F$29)),"") -> 0.30714746 | P6: =IFERROR(IF(OR($G6="",$D6=""),"",$G6*$D6),"") -> 2542 | Q6: =IFERROR(IF(OR($K6="",$K6=0),"",SUMPRODUCT(--($C$5:$C$29=$C6),$D$5:$D$29,$G$5:$G$29)/$K6),"") -> 1844.5714
A7: 3 | B7: Garlic shrimp | C7: Starters | D7: 260 | E7: 6.9 | F7: 15.5 | G7: =IFERROR(IF(OR($E7="",$F7=""),"",$F7-$E7),"") -> 8.6 | H7: =IFERROR(IF(OR($E7="",$F7="",$F7=0),"",$E7/$F7),"") -> 0.44516129 | I7: =IFERROR(IF(OR($F7="",$D$34=""),"",$F7*(1+$D$34)),"") -> 15.5 | J7: =IFERROR(IF($C7="","",SUMPRODUCT(--($C$5:$C$29=$C7),$D$5:$D$29)),"") -> 1730 | K7: =IFERROR(IF($C7="","",SUMPRODUCT(--($C$5:$C$29=$C7),--($D$5:$D$29>0))),"") -> 7 | L7: =IFERROR(IF(OR($D7="",$J7="",$J7=0),"",$D7/$J7),"") -> 0.15028902 | M7: =IFERROR(IF(OR($K7="",$K7=0,$D$33=""),"",$D$33/$K7),"") -> 0.1 | N7: =IFERROR(IF(OR($J7="",$J7=0),"",SUMPRODUCT(--($C$5:$C$29=$C7),$D$5:$D$29,$G$5:$G$29)/$J7),"") -> 7.4635838 | O7: =IFERROR(IF(SUMPRODUCT(--($C$5:$C$29=$C7),$D$5:$D$29,$F$5:$F$29)=0,"",SUMPRODUCT(--($C$5:$C$29=$C7),$D$5:$D$29,$E$5:$E$29)/SUMPRODUCT(--($C$5:$C$29=$C7),$D$5:$D$29,$F$5:$F$29)),"") -> 0.30714746 | P7: =IFERROR(IF(OR($G7="",$D7=""),"",$G7*$D7),"") -> 2236 | Q7: =IFERROR(IF(OR($K7="",$K7=0),"",SUMPRODUCT(--($C$5:$C$29=$C7),$D$5:$D$29,$G$5:$G$29)/$K7),"") -> 1844.5714
A8: 4 | B8: Broken eggs with potatoes and chistorra sausage | C8: Starters | D8: 380 | E8: 2.4 | F8: 9.8 | G8: =IFERROR(IF(OR($E8="",$F8=""),"",$F8-$E8),"") -> 7.4 | H8: =IFERROR(IF(OR($E8="",$F8="",$F8=0),"",$E8/$F8),"") -> 0.24489796 | I8: =IFERROR(IF(OR($F8="",$D$34=""),"",$F8*(1+$D$34)),"") -> 9.8 | J8: =IFERROR(IF($C8="","",SUMPRODUCT(--($C$5:$C$29=$C8),$D$5:$D$29)),"") -> 1730 | K8: =IFERROR(IF($C8="","",SUMPRODUCT(--($C$5:$C$29=$C8),--($D$5:$D$29>0))),"") -> 7 | L8: =IFERROR(IF(OR($D8="",$J8="",$J8=0),"",$D8/$J8),"") -> 0.21965318 | M8: =IFERROR(IF(OR($K8="",$K8=0,$D$33=""),"",$D$33/$K8),"") -> 0.1 | N8: =IFERROR(IF(OR($J8="",$J8=0),"",SUMPRODUCT(--($C$5:$C$29=$C8),$D$5:$D$29,$G$5:$G$29)/$J8),"") -> 7.4635838 | O8: =IFERROR(IF(SUMPRODUCT(--($C$5:$C$29=$C8),$D$5:$D$29,$F$5:$F$29)=0,"",SUMPRODUCT(--($C$5:$C$29=$C8),$D$5:$D$29,$E$5:$E$29)/SUMPRODUCT(--($C$5:$C$29=$C8),$D$5:$D$29,$F$5:$F$29)),"") -> 0.30714746 | P8: =IFERROR(IF(OR($G8="",$D8=""),"",$G8*$D8),"") -> 2812 | Q8: =IFERROR(IF(OR($K8="",$K8=0),"",SUMPRODUCT(--($C$5:$C$29=$C8),$D$5:$D$29,$G$5:$G$29)/$K8),"") -> 1844.5714
A9: 5 | B9: Local cheese board | C9: Starters | D9: 90 | E9: 5.2 | F9: 13.6 | G9: =IFERROR(IF(OR($E9="",$F9=""),"",$F9-$E9),"") -> 8.4 | H9: =IFERROR(IF(OR($E9="",$F9="",$F9=0),"",$E9/$F9),"") -> 0.38235294 | I9: =IFERROR(IF(OR($F9="",$D$34=""),"",$F9*(1+$D$34)),"") -> 13.6 | J9: =IFERROR(IF($C9="","",SUMPRODUCT(--($C$5:$C$29=$C9),$D$5:$D$29)),"") -> 1730 | K9: =IFERROR(IF($C9="","",SUMPRODUCT(--($C$5:$C$29=$C9),--($D$5:$D$29>0))),"") -> 7 | L9: =IFERROR(IF(OR($D9="",$J9="",$J9=0),"",$D9/$J9),"") -> 0.052023121 | M9: =IFERROR(IF(OR($K9="",$K9=0,$D$33=""),"",$D$33/$K9),"") -> 0.1 | N9: =IFERROR(IF(OR($J9="",$J9=0),"",SUMPRODUCT(--($C$5:$C$29=$C9),$D$5:$D$29,$G$5:$G$29)/$J9),"") -> 7.4635838 | O9: =IFERROR(IF(SUMPRODUCT(--($C$5:$C$29=$C9),$D$5:$D$29,$F$5:$F$29)=0,"",SUMPRODUCT(--($C$5:$C$29=$C9),$D$5:$D$29,$E$5:$E$29)/SUMPRODUCT(--($C$5:$C$29=$C9),$D$5:$D$29,$F$5:$F$29)),"") -> 0.30714746 | P9: =IFERROR(IF(OR($G9="",$D9=""),"",$G9*$D9),"") -> 756 | Q9: =IFERROR(IF(OR($K9="",$K9=0),"",SUMPRODUCT(--($C$5:$C$29=$C9),$D$5:$D$29,$G$5:$G$29)/$K9),"") -> 1844.5714
A10: 6 | B10: Confit artichokes with ham | C10: Starters | D10: 120 | E10: 3.1 | F10: 10.9 | G10: =IFERROR(IF(OR($E10="",$F10=""),"",$F10-$E10),"") -> 7.8 | H10: =IFERROR(IF(OR($E10="",$F10="",$F10=0),"",$E10/$F10),"") -> 0.28440367 | I10: =IFERROR(IF(OR($F10="",$D$34=""),"",$F10*(1+$D$34)),"") -> 10.9 | J10: =IFERROR(IF($C10="","",SUMPRODUCT(--($C$5:$C$29=$C10),$D$5:$D$29)),"") -> 1730 | K10: =IFERROR(IF($C10="","",SUMPRODUCT(--($C$5:$C$29=$C10),--($D$5:$D$29>0))),"") -> 7 | L10: =IFERROR(IF(OR($D10="",$J10="",$J10=0),"",$D10/$J10),"") -> 0.069364162 | M10: =IFERROR(IF(OR($K10="",$K10=0,$D$33=""),"",$D$33/$K10),"") -> 0.1 | N10: =IFERROR(IF(OR($J10="",$J10=0),"",SUMPRODUCT(--($C$5:$C$29=$C10),$D$5:$D$29,$G$5:$G$29)/$J10),"") -> 7.4635838 | O10: =IFERROR(IF(SUMPRODUCT(--($C$5:$C$29=$C10),$D$5:$D$29,$F$5:$F$29)=0,"",SUMPRODUCT(--($C$5:$C$29=$C10),$D$5:$D$29,$E$5:$E$29)/SUMPRODUCT(--($C$5:$C$29=$C10),$D$5:$D$29,$F$5:$F$29)),"") -> 0.30714746 | P10: =IFERROR(IF(OR($G10="",$D10=""),"",$G10*$D10),"") -> 936 | Q10: =IFERROR(IF(OR($K10="",$K10=0),"",SUMPRODUCT(--($C$5:$C$29=$C10),$D$5:$D$29,$G$5:$G$29)/$K10),"") -> 1844.5714
A11: 7 | B11: Roasted tomato soup with basil | C11: Starters | D11: 150 | E11: 1.2 | F11: 7.2 | G11: =IFERROR(IF(OR($E11="",$F11=""),"",$F11-$E11),"") -> 6 | H11: =IFERROR(IF(OR($E11="",$F11="",$F11=0),"",$E11/$F11),"") -> 0.16666667 | I11: =IFERROR(IF(OR($F11="",$D$34=""),"",$F11*(1+$D$34)),"") -> 7.2 | J11: =IFERROR(IF($C11="","",SUMPRODUCT(--($C$5:$C$29=$C11),$D$5:$D$29)),"") -> 1730 | K11: =IFERROR(IF($C11="","",SUMPRODUCT(--($C$5:$C$29=$C11),--($D$5:$D$29>0))),"") -> 7 | L11: =IFERROR(IF(OR($D11="",$J11="",$J11=0),"",$D11/$J11),"") -> 0.086705202 | M11: =IFERROR(IF(OR($K11="",$K11=0,$D$33=""),"",$D$33/$K11),"") -> 0.1 | N11: =IFERROR(IF(OR($J11="",$J11=0),"",SUMPRODUCT(--($C$5:$C$29=$C11),$D$5:$D$29,$G$5:$G$29)/$J11),"") -> 7.4635838 | O11: =IFERROR(IF(SUMPRODUCT(--($C$5:$C$29=$C11),$D$5:$D$29,$F$5:$F$29)=0,"",SUMPRODUCT(--($C$5:$C$29=$C11),$D$5:$D$29,$E$5:$E$29)/SUMPRODUCT(--($C$5:$C$29=$C11),$D$5:$D$29,$F$5:$F$29)),"") -> 0.30714746 | P11: =IFERROR(IF(OR($G11="",$D11=""),"",$G11*$D11),"") -> 900 | Q11: =IFERROR(IF(OR($K11="",$K11=0),"",SUMPRODUCT(--($C$5:$C$29=$C11),$D$5:$D$29,$G$5:$G$29)/$K11),"") -> 1844.5714
A12: 8 | B12: Iberico pork tenderloin with sweet potato purée | C12: Mains | D12: 340 | E12: 5.67 | F12: 17.3 | G12: =IFERROR(IF(OR($E12="",$F12=""),"",$F12-$E12),"") -> 11.63 | H12: =IFERROR(IF(OR($E12="",$F12="",$F12=0),"",$E12/$F12),"") -> 0.32774566 | I12: =IFERROR(IF(OR($F12="",$D$34=""),"",$F12*(1+$D$34)),"") -> 17.3 | J12: =IFERROR(IF($C12="","",SUMPRODUCT(--($C$5:$C$29=$C12),$D$5:$D$29)),"") -> 2020 | K12: =IFERROR(IF($C12="","",SUMPRODUCT(--($C$5:$C$29=$C12),--($D$5:$D$29>0))),"") -> 9 | L12: =IFERROR(IF(OR($D12="",$J12="",$J12=0),"",$D12/$J12),"") -> 0.16831683 | M12: =IFERROR(IF(OR($K12="",$K12=0,$D$33=""),"",$D$33/$K12),"") -> 0.077777778 | N12: =IFERROR(IF(OR($J12="",$J12=0),"",SUMPRODUCT(--($C$5:$C$29=$C12),$D$5:$D$29,$G$5:$G$29)/$J12),"") -> 10.795149 | O12: =IFERROR(IF(SUMPRODUCT(--($C$5:$C$29=$C12),$D$5:$D$29,$F$5:$F$29)=0,"",SUMPRODUCT(--($C$5:$C$29=$C12),$D$5:$D$29,$E$5:$E$29)/SUMPRODUCT(--($C$5:$C$29=$C12),$D$5:$D$29,$F$5:$F$29)),"") -> 0.35587523 | P12: =IFERROR(IF(OR($G12="",$D12=""),"",$G12*$D12),"") -> 3954.2 | Q12: =IFERROR(IF(OR($K12="",$K12=0),"",SUMPRODUCT(--($C$5:$C$29=$C12),$D$5:$D$29,$G$5:$G$29)/$K12),"") -> 2422.9111
A13: 9 | B13: Confit cod in pil-pil sauce | C13: Mains | D13: 190 | E13: 7.4 | F13: 19.1 | G13: =IFERROR(IF(OR($E13="",$F13=""),"",$F13-$E13),"") -> 11.7 | H13: =IFERROR(IF(OR($E13="",$F13="",$F13=0),"",$E13/$F13),"") -> 0.38743455 | I13: =IFERROR(IF(OR($F13="",$D$34=""),"",$F13*(1+$D$34)),"") -> 19.1 | J13: =IFERROR(IF($C13="","",SUMPRODUCT(--($C$5:$C$29=$C13),$D$5:$D$29)),"") -> 2020 | K13: =IFERROR(IF($C13="","",SUMPRODUCT(--($C$5:$C$29=$C13),--($D$5:$D$29>0))),"") -> 9 | L13: =IFERROR(IF(OR($D13="",$J13="",$J13=0),"",$D13/$J13),"") -> 0.094059406 | M13: =IFERROR(IF(OR($K13="",$K13=0,$D$33=""),"",$D$33/$K13),"") -> 0.077777778 | N13: =IFERROR(IF(OR($J13="",$J13=0),"",SUMPRODUCT(--($C$5:$C$29=$C13),$D$5:$D$29,$G$5:$G$29)/$J13),"") -> 10.795149 | O13: =IFERROR(IF(SUMPRODUCT(--($C$5:$C$29=$C13),$D$5:$D$29,$F$5:$F$29)=0,"",SUMPRODUCT(--($C$5:$C$29=$C13),$D$5:$D$29,$E$5:$E$29)/SUMPRODUCT(--($C$5:$C$29=$C13),$D$5:$D$29,$F$5:$F$29)),"") -> 0.35587523 | P13: =IFERROR(IF(OR($G13="",$D13=""),"",$G13*$D13),"") -> 2223 | Q13: =IFERROR(IF(OR($K13="",$K13=0),"",SUMPRODUCT(--($C$5:$C$29=$C13),$D$5:$D$29,$G$5:$G$29)/$K13),"") -> 2422.9111
A14: 10 | B14: Dry-aged beef burger with fries | C14: Mains | D14: 460 | E14: 4.3 | F14: 13.6 | G14: =IFERROR(IF(OR($E14="",$F14=""),"",$F14-$E14),"") -> 9.3 | H14: =IFERROR(IF(OR($E14="",$F14="",$F14=0),"",$E14/$F14),"") -> 0.31617647 | I14: =IFERROR(IF(OR($F14="",$D$34=""),"",$F14*(1+$D$34)),"") -> 13.6 | J14: =IFERROR(IF($C14="","",SUMPRODUCT(--($C$5:$C$29=$C14),$D$5:$D$29)),"") -> 2020 | K14: =IFERROR(IF($C14="","",SUMPRODUCT(--($C$5:$C$29=$C14),--($D$5:$D$29>0))),"") -> 9 | L14: =IFERROR(IF(OR($D14="",$J14="",$J14=0),"",$D14/$J14),"") -> 0.22772277 | M14: =IFERROR(IF(OR($K14="",$K14=0,$D$33=""),"",$D$33/$K14),"") -> 0.077777778 | N14: =IFERROR(IF(OR($J14="",$J14=0),"",SUMPRODUCT(--($C$5:$C$29=$C14),$D$5:$D$29,$G$5:$G$29)/$J14),"") -> 10.795149 | O14: =IFERROR(IF(SUMPRODUCT(--($C$5:$C$29=$C14),$D$5:$D$29,$F$5:$F$29)=0,"",SUMPRODUCT(--($C$5:$C$29=$C14),$D$5:$D$29,$E$5:$E$29)/SUMPRODUCT(--($C$5:$C$29=$C14),$D$5:$D$29,$F$5:$F$29)),"") -> 0.35587523 | P14: =IFERROR(IF(OR($G14="",$D14=""),"",$G14*$D14),"") -> 4278 | Q14: =IFERROR(IF(OR($K14="",$K14=0),"",SUMPRODUCT(--($C$5:$C$29=$C14),$D$5:$D$29,$G$5:$G$29)/$K14),"") -> 2422.9111
A15: 11 | B15: Creamy rice with Iberico pork secreto and mushrooms | C15: Mains | D15: 270 | E15: 6.2 | F15: 16.4 | G15: =IFERROR(IF(OR($E15="",$F15=""),"",$F15-$E15),"") -> 10.2 | H15: =IFERROR(IF(OR($E15="",$F15="",$F15=0),"",$E15/$F15),"") -> 0.37804878 | I15: =IFERROR(IF(OR($F15="",$D$34=""),"",$F15*(1+$D$34)),"") -> 16.4 | J15: =IFERROR(IF($C15="","",SUMPRODUCT(--($C$5:$C$29=$C15),$D$5:$D$29)),"") -> 2020 | K15: =IFERROR(IF($C15="","",SUMPRODUCT(--($C$5:$C$29=$C15),--($D$5:$D$29>0))),"") -> 9 | L15: =IFERROR(IF(OR($D15="",$J15="",$J15=0),"",$D15/$J15),"") -> 0.13366337 | M15: =IFERROR(IF(OR($K15="",$K15=0,$D$33=""),"",$D$33/$K15),"") -> 0.077777778 | N15: =IFERROR(IF(OR($J15="",$J15=0),"",SUMPRODUCT(--($C$5:$C$29=$C15),$D$5:$D$29,$G$5:$G$29)/$J15),"") -> 10.795149 | O15: =IFERROR(IF(SUMPRODUCT(--($C$5:$C$29=$C15),$D$5:$D$29,$F$5:$F$29)=0,"",SUMPRODUCT(--($C$5:$C$29=$C15),$D$5:$D$29,$E$5:$E$29)/SUMPRODUCT(--($C$5:$C$29=$C15),$D$5:$D$29,$F$5:$F$29)),"") -> 0.35587523 | P15: =IFERROR(IF(OR($G15="",$D15=""),"",$G15*$D15),"") -> 2754 | Q15: =IFERROR(IF(OR($K15="",$K15=0),"",SUMPRODUCT(--($C$5:$C$29=$C15),$D$5:$D$29,$G$5:$G$29)/$K15),"") -> 2422.9111
A16: 12 | B16: Dry-aged bone-in ribeye (17.64 oz) | C16: Mains | D16: 110 | E16: 14.8 | F16: 32.7 | G16: =IFERROR(IF(OR($E16="",$F16=""),"",$F16-$E16),"") -> 17.9 | H16: =IFERROR(IF(OR($E16="",$F16="",$F16=0),"",$E16/$F16),"") -> 0.45259939 | I16: =IFERROR(IF(OR($F16="",$D$34=""),"",$F16*(1+$D$34)),"") -> 32.7 | J16: =IFERROR(IF($C16="","",SUMPRODUCT(--($C$5:$C$29=$C16),$D$5:$D$29)),"") -> 2020 | K16: =IFERROR(IF($C16="","",SUMPRODUCT(--($C$5:$C$29=$C16),--($D$5:$D$29>0))),"") -> 9 | L16: =IFERROR(IF(OR($D16="",$J16="",$J16=0),"",$D16/$J16),"") -> 0.054455446 | M16: =IFERROR(IF(OR($K16="",$K16=0,$D$33=""),"",$D$33/$K16),"") -> 0.077777778 | N16: =IFERROR(IF(OR($J16="",$J16=0),"",SUMPRODUCT(--($C$5:$C$29=$C16),$D$5:$D$29,$G$5:$G$29)/$J16),"") -> 10.795149 | O16: =IFERROR(IF(SUMPRODUCT(--($C$5:$C$29=$C16),$D$5:$D$29,$F$5:$F$29)=0,"",SUMPRODUCT(--($C$5:$C$29=$C16),$D$5:$D$29,$E$5:$E$29)/SUMPRODUCT(--($C$5:$C$29=$C16),$D$5:$D$29,$F$5:$F$29)),"") -> 0.35587523 | P16: =IFERROR(IF(OR($G16="",$D16=""),"",$G16*$D16),"") -> 1969 | Q16: =IFERROR(IF(OR($K16="",$K16=0),"",SUMPRODUCT(--($C$5:$C$29=$C16),$D$5:$D$29,$G$5:$G$29)/$K16),"") -> 2422.9111
... A24: 20 | B24: Prepared seasonal fruit | C24: Desserts | D24: 60 | E24: 1.4 | F24: 4.5 | G24: =IFERROR(IF(OR($E24="",$F24=""),"",$F24-$E24),"") -> 3.1 | H24: =IFERROR(IF(OR($E24="",$F24="",$F24=0),"",$E24/$F24),"") -> 0.31111111 | I24: =IFERROR(IF(OR($F24="",$D$34=""),"",$F24*(1+$D$34)),"") -> 4.5 | J24: =IFERROR(IF($C24="","",SUMPRODUCT(--($C$5:$C$29=$C24),$D$5:$D$29)),"") -> 1120 | K24: =IFERROR(IF($C24="","",SUMPRODUCT(--($C$5:$C$29=$C24),--($D$5:$D$29>0))),"") -> 4 | L24: =IFERROR(IF(OR($D24="",$J24="",$J24=0),"",$D24/$J24),"") -> 0.053571429 | M24: =IFERROR(IF(OR($K24="",$K24=0,$D$33=""),"",$D$33/$K24),"") -> 0.175 | N24: =IFERROR(IF(OR($J24="",$J24=0),"",SUMPRODUCT(--($C$5:$C$29=$C24),$D$5:$D$29,$G$5:$G$29)/$J24),"") -> 4.4821429 | O24: =IFERROR(IF(SUMPRODUCT(--($C$5:$C$29=$C24),$D$5:$D$29,$F$5:$F$29)=0,"",SUMPRODUCT(--($C$5:$C$29=$C24),$D$5:$D$29,$E$5:$E$29)/SUMPRODUCT(--($C$5:$C$29=$C24),$D$5:$D$29,$F$5:$F$29)),"") -> 0.23229852 | P24: =IFERROR(IF(OR($G24="",$D24=""),"",$G24*$D24),"") -> 186 | Q24: =IFERROR(IF(OR($K24="",$K24=0),"",SUMPRODUCT(--($C$5:$C$29=$C24),$D$5:$D$29,$G$5:$G$29)/$K24),"") -> 1255
A25: 21 | G25: =IFERROR(IF(OR($E25="",$F25=""),"",$F25-$E25),"") | H25: =IFERROR(IF(OR($E25="",$F25="",$F25=0),"",$E25/$F25),"") | I25: =IFERROR(IF(OR($F25="",$D$34=""),"",$F25*(1+$D$34)),"") | J25: =IFERROR(IF($C25="","",SUMPRODUCT(--($C$5:$C$29=$C25),$D$5:$D$29)),"") | K25: =IFERROR(IF($C25="","",SUMPRODUCT(--($C$5:$C$29=$C25),--($D$5:$D$29>0))),"") | L25: =IFERROR(IF(OR($D25="",$J25="",$J25=0),"",$D25/$J25),"") | M25: =IFERROR(IF(OR($K25="",$K25=0,$D$33=""),"",$D$33/$K25),"") | N25: =IFERROR(IF(OR($J25="",$J25=0),"",SUMPRODUCT(--($C$5:$C$29=$C25),$D$5:$D$29,$G$5:$G$29)/$J25),"") | O25: =IFERROR(IF(SUMPRODUCT(--($C$5:$C$29=$C25),$D$5:$D$29,$F$5:$F$29)=0,"",SUMPRODUCT(--($C$5:$C$29=$C25),$D$5:$D$29,$E$5:$E$29)/SUMPRODUCT(--($C$5:$C$29=$C25),$D$5:$D$29,$F$5:$F$29)),"") | P25: =IFERROR(IF(OR($G25="",$D25=""),"",$G25*$D25),"") | Q25: =IFERROR(IF(OR($K25="",$K25=0),"",SUMPRODUCT(--($C$5:$C$29=$C25),$D$5:$D$29,$G$5:$G$29)/$K25),"")
A26: 22 | G26: =IFERROR(IF(OR($E26="",$F26=""),"",$F26-$E26),"") | H26: =IFERROR(IF(OR($E26="",$F26="",$F26=0),"",$E26/$F26),"") | I26: =IFERROR(IF(OR($F26="",$D$34=""),"",$F26*(1+$D$34)),"") | J26: =IFERROR(IF($C26="","",SUMPRODUCT(--($C$5:$C$29=$C26),$D$5:$D$29)),"") | K26: =IFERROR(IF($C26="","",SUMPRODUCT(--($C$5:$C$29=$C26),--($D$5:$D$29>0))),"") | L26: =IFERROR(IF(OR($D26="",$J26="",$J26=0),"",$D26/$J26),"") | M26: =IFERROR(IF(OR($K26="",$K26=0,$D$33=""),"",$D$33/$K26),"") | N26: =IFERROR(IF(OR($J26="",$J26=0),"",SUMPRODUCT(--($C$5:$C$29=$C26),$D$5:$D$29,$G$5:$G$29)/$J26),"") | O26: =IFERROR(IF(SUMPRODUCT(--($C$5:$C$29=$C26),$D$5:$D$29,$F$5:$F$29)=0,"",SUMPRODUCT(--($C$5:$C$29=$C26),$D$5:$D$29,$E$5:$E$29)/SUMPRODUCT(--($C$5:$C$29=$C26),$D$5:$D$29,$F$5:$F$29)),"") | P26: =IFERROR(IF(OR($G26="",$D26=""),"",$G26*$D26),"") | Q26: =IFERROR(IF(OR($K26="",$K26=0),"",SUMPRODUCT(--($C$5:$C$29=$C26),$D$5:$D$29,$G$5:$G$29)/$K26),"")
A27: 23 | G27: =IFERROR(IF(OR($E27="",$F27=""),"",$F27-$E27),"") | H27: =IFERROR(IF(OR($E27="",$F27="",$F27=0),"",$E27/$F27),"") | I27: =IFERROR(IF(OR($F27="",$D$34=""),"",$F27*(1+$D$34)),"") | J27: =IFERROR(IF($C27="","",SUMPRODUCT(--($C$5:$C$29=$C27),$D$5:$D$29)),"") | K27: =IFERROR(IF($C27="","",SUMPRODUCT(--($C$5:$C$29=$C27),--($D$5:$D$29>0))),"") | L27: =IFERROR(IF(OR($D27="",$J27="",$J27=0),"",$D27/$J27),"") | M27: =IFERROR(IF(OR($K27="",$K27=0,$D$33=""),"",$D$33/$K27),"") | N27: =IFERROR(IF(OR($J27="",$J27=0),"",SUMPRODUCT(--($C$5:$C$29=$C27),$D$5:$D$29,$G$5:$G$29)/$J27),"") | O27: =IFERROR(IF(SUMPRODUCT(--($C$5:$C$29=$C27),$D$5:$D$29,$F$5:$F$29)=0,"",SUMPRODUCT(--($C$5:$C$29=$C27),$D$5:$D$29,$E$5:$E$29)/SUMPRODUCT(--($C$5:$C$29=$C27),$D$5:$D$29,$F$5:$F$29)),"") | P27: =IFERROR(IF(OR($G27="",$D27=""),"",$G27*$D27),"") | Q27: =IFERROR(IF(OR($K27="",$K27=0),"",SUMPRODUCT(--($C$5:$C$29=$C27),$D$5:$D$29,$G$5:$G$29)/$K27),"")
A28: 24 | G28: =IFERROR(IF(OR($E28="",$F28=""),"",$F28-$E28),"") | H28: =IFERROR(IF(OR($E28="",$F28="",$F28=0),"",$E28/$F28),"") | I28: =IFERROR(IF(OR($F28="",$D$34=""),"",$F28*(1+$D$34)),"") | J28: =IFERROR(IF($C28="","",SUMPRODUCT(--($C$5:$C$29=$C28),$D$5:$D$29)),"") | K28: =IFERROR(IF($C28="","",SUMPRODUCT(--($C$5:$C$29=$C28),--($D$5:$D$29>0))),"") | L28: =IFERROR(IF(OR($D28="",$J28="",$J28=0),"",$D28/$J28),"") | M28: =IFERROR(IF(OR($K28="",$K28=0,$D$33=""),"",$D$33/$K28),"") | N28: =IFERROR(IF(OR($J28="",$J28=0),"",SUMPRODUCT(--($C$5:$C$29=$C28),$D$5:$D$29,$G$5:$G$29)/$J28),"") | O28: =IFERROR(IF(SUMPRODUCT(--($C$5:$C$29=$C28),$D$5:$D$29,$F$5:$F$29)=0,"",SUMPRODUCT(--($C$5:$C$29=$C28),$D$5:$D$29,$E$5:$E$29)/SUMPRODUCT(--($C$5:$C$29=$C28),$D$5:$D$29,$F$5:$F$29)),"") | P28: =IFERROR(IF(OR($G28="",$D28=""),"",$G28*$D28),"") | Q28: =IFERROR(IF(OR($K28="",$K28=0),"",SUMPRODUCT(--($C$5:$C$29=$C28),$D$5:$D$29,$G$5:$G$29)/$K28),"")
A29: 25 | G29: =IFERROR(IF(OR($E29="",$F29=""),"",$F29-$E29),"") | H29: =IFERROR(IF(OR($E29="",$F29="",$F29=0),"",$E29/$F29),"") | I29: =IFERROR(IF(OR($F29="",$D$34=""),"",$F29*(1+$D$34)),"") | J29: =IFERROR(IF($C29="","",SUMPRODUCT(--($C$5:$C$29=$C29),$D$5:$D$29)),"") | K29: =IFERROR(IF($C29="","",SUMPRODUCT(--($C$5:$C$29=$C29),--($D$5:$D$29>0))),"") | L29: =IFERROR(IF(OR($D29="",$J29="",$J29=0),"",$D29/$J29),"") | M29: =IFERROR(IF(OR($K29="",$K29=0,$D$33=""),"",$D$33/$K29),"") | N29: =IFERROR(IF(OR($J29="",$J29=0),"",SUMPRODUCT(--($C$5:$C$29=$C29),$D$5:$D$29,$G$5:$G$29)/$J29),"") | O29: =IFERROR(IF(SUMPRODUCT(--($C$5:$C$29=$C29),$D$5:$D$29,$F$5:$F$29)=0,"",SUMPRODUCT(--($C$5:$C$29=$C29),$D$5:$D$29,$E$5:$E$29)/SUMPRODUCT(--($C$5:$C$29=$C29),$D$5:$D$29,$F$5:$F$29)),"") | P29: =IFERROR(IF(OR($G29="",$D29=""),"",$G29*$D29),"") | Q29: =IFERROR(IF(OR($K29="",$K29=0),"",SUMPRODUCT(--($C$5:$C$29=$C29),$D$5:$D$29,$G$5:$G$29)/$K29),"")
A31: SUMMARY AND INPUTS — calculated by the workbook
B32: MENU TOTAL | D32: =IFERROR(SUM($D$5:$D$29),"") -> 4870 | G32: =IFERROR(IF($D$32=0,"",SUMPRODUCT($D$5:$D$29,$G$5:$G$29)/$D$32),"") -> 8.1597947 | H32: =IFERROR(IF(SUMPRODUCT($D$5:$D$29,$F$5:$F$29)=0,"",SUMPRODUCT($D$5:$D$29,$E$5:$E$29)/SUMPRODUCT($D$5:$D$29,$F$5:$F$29)),"") -> 0.32680208 | I32: =IFERROR(SUMPRODUCT($D$5:$D$29,$F$5:$F$29),"") -> 59029 | J32: Units · weighted avg CM · weighted avg food cost · net sales for the month
B33: Popularity threshold factor (%) | D33: 0.7 | F33: The classic is 70% of the average mix: each category's threshold = this factor ÷ number of dishes in the category with sales. Raise it if the category is very short.
B34: Tax rate (%) | D34: 0 | F34: Ships at 0%: US and Canadian menus are printed pre-tax. In the UK type 20% (VAT is included in printed prices); in Australia type 10% (GST included). Change it here and the whole workbook recalculates.
B35: Dishes with sales on the menu | D35: =COUNTIF($D$5:$D$29,">0") -> 20
B36: Dishes listed on the menu | D36: =COUNTIF($B$5:$B$29,"<>") -> 20
A38: SUMMARY BY CATEGORY — calculated by the workbook
B39: Category | C39: Dishes on the menu | D39: Dishes with sales | E39: Units sold | F39: Share of menu mix (%) | G39: Weighted avg CM | H39: Weighted avg food cost (%) | I39: Net sales for the month
B40: Starters | C40: =COUNTIF($C$5:$C$29,$B40) -> 7 | D40: =IFERROR(IF($C40=0,"",SUMPRODUCT(--($C$5:$C$29=$B40),--($D$5:$D$29>0))),"") -> 7 | E40: =IFERROR(IF($C40=0,"",SUMIF($C$5:$C$29,$B40,$D$5:$D$29)),"") -> 1730 | F40: =IFERROR(IF(OR($D$32=0,$C40=0),"",$E40/$D$32),"") -> 0.35523614 | G40: =IFERROR(IF($E40=0,"",SUMPRODUCT(--($C$5:$C$29=$B40),$D$5:$D$29,$G$5:$G$29)/$E40),"") -> 7.4635838 | H40: =IFERROR(IF(SUMPRODUCT(--($C$5:$C$29=$B40),$D$5:$D$29,$F$5:$F$29)=0,"",SUMPRODUCT(--($C$5:$C$29=$B40),$D$5:$D$29,$E$5:$E$29)/SUMPRODUCT(--($C$5:$C$29=$B40),$D$5:$D$29,$F$5:$F$29)),"") -> 0.30714746 | I40: =IFERROR(SUMPRODUCT(--($C$5:$C$29=$B40),$D$5:$D$29,$F$5:$F$29),"") -> 18636
B41: Mains | C41: =COUNTIF($C$5:$C$29,$B41) -> 9 | D41: =IFERROR(IF($C41=0,"",SUMPRODUCT(--($C$5:$C$29=$B41),--($D$5:$D$29>0))),"") -> 9 | E41: =IFERROR(IF($C41=0,"",SUMIF($C$5:$C$29,$B41,$D$5:$D$29)),"") -> 2020 | F41: =IFERROR(IF(OR($D$32=0,$C41=0),"",$E41/$D$32),"") -> 0.41478439 | G41: =IFERROR(IF($E41=0,"",SUMPRODUCT(--($C$5:$C$29=$B41),$D$5:$D$29,$G$5:$G$29)/$E41),"") -> 10.795149 | H41: =IFERROR(IF(SUMPRODUCT(--($C$5:$C$29=$B41),$D$5:$D$29,$F$5:$F$29)=0,"",SUMPRODUCT(--($C$5:$C$29=$B41),$D$5:$D$29,$E$5:$E$29)/SUMPRODUCT(--($C$5:$C$29=$B41),$D$5:$D$29,$F$5:$F$29)),"") -> 0.35587523 | I41: =IFERROR(SUMPRODUCT(--($C$5:$C$29=$B41),$D$5:$D$29,$F$5:$F$29),"") -> 33854
B42: Desserts | C42: =COUNTIF($C$5:$C$29,$B42) -> 4 | D42: =IFERROR(IF($C42=0,"",SUMPRODUCT(--($C$5:$C$29=$B42),--($D$5:$D$29>0))),"") -> 4 | E42: =IFERROR(IF($C42=0,"",SUMIF($C$5:$C$29,$B42,$D$5:$D$29)),"") -> 1120 | F42: =IFERROR(IF(OR($D$32=0,$C42=0),"",$E42/$D$32),"") -> 0.22997947 | G42: =IFERROR(IF($E42=0,"",SUMPRODUCT(--($C$5:$C$29=$B42),$D$5:$D$29,$G$5:$G$29)/$E42),"") -> 4.4821429 | H42: =IFERROR(IF(SUMPRODUCT(--($C$5:$C$29=$B42),$D$5:$D$29,$F$5:$F$29)=0,"",SUMPRODUCT(--($C$5:$C$29=$B42),$D$5:$D$29,$E$5:$E$29)/SUMPRODUCT(--($C$5:$C$29=$B42),$D$5:$D$29,$F$5:$F$29)),"") -> 0.23229852 | I42: =IFERROR(SUMPRODUCT(--($C$5:$C$29=$B42),$D$5:$D$29,$F$5:$F$29),"") -> 6539
B43: Prix fixe | C43: =COUNTIF($C$5:$C$29,$B43) -> 0 | D43: =IFERROR(IF($C43=0,"",SUMPRODUCT(--($C$5:$C$29=$B43),--($D$5:$D$29>0))),"") | E43: =IFERROR(IF($C43=0,"",SUMIF($C$5:$C$29,$B43,$D$5:$D$29)),"") | F43: =IFERROR(IF(OR($D$32=0,$C43=0),"",$E43/$D$32),"") | G43: =IFERROR(IF($E43=0,"",SUMPRODUCT(--($C$5:$C$29=$B43),$D$5:$D$29,$G$5:$G$29)/$E43),"") | H43: =IFERROR(IF(SUMPRODUCT(--($C$5:$C$29=$B43),$D$5:$D$29,$F$5:$F$29)=0,"",SUMPRODUCT(--($C$5:$C$29=$B43),$D$5:$D$29,$E$5:$E$29)/SUMPRODUCT(--($C$5:$C$29=$B43),$D$5:$D$29,$F$5:$F$29)),"") | I43: =IFERROR(SUMPRODUCT(--($C$5:$C$29=$B43),$D$5:$D$29,$F$5:$F$29),"") -> 0

Sheet Kasavana-Smith
A1: Kasavana & Smith — popularity × contribution margin
A2: AI Chef Pro · aichef.pro — Food Cost + Menu Engineering Guide
E3: Everything is calculated from the "Data" sheet. You don't type anything here.
A4: # | B4: Dish | C4: Category | D4: Units sold | E4: Menu Mix in Category (MM%) | F4: Popularity threshold in its category (%) | G4: Popularity | H4: Dish CM | I4: Category weighted avg CM | J4: Margin level | K4: Classification | L4: What it means | M4: Recommended action
A5: 1 | B5: =IFERROR(IF('Data'!$B5="","",'Data'!$B5),"") -> Iberico ham croquettes (6 pcs) | C5: =IFERROR(IF('Data'!$C5="","",'Data'!$C5),"") -> Starters | D5: =IFERROR(IF('Data'!$D5="","",'Data'!$D5),"") -> 420 | E5: =IFERROR(IF('Data'!$L5="","",'Data'!$L5),"") -> 0.24277457 | F5: =IFERROR(IF('Data'!$M5="","",'Data'!$M5),"") -> 0.1 | G5: =IFERROR(IF(OR($E5="",$F5=""),"",IF($E5>=$F5,"High","Low")),"") -> High | H5: =IFERROR(IF('Data'!$G5="","",'Data'!$G5),"") -> 6.5 | I5: =IFERROR(IF('Data'!$N5="","",'Data'!$N5),"") -> 7.4635838 | J5: =IFERROR(IF(OR($H5="",$I5=""),"",IF($H5>=$I5,"High","Low")),"") -> Low | K5: =IFERROR(IF(OR($G5="",$J5=""),"",IF(AND($G5="High",$J5="High"),"Star",IF(AND($G5="High",$J5="Low"),"Plowhorse",IF(AND($G5="Low",$J5="High"),"Puzzle","Dog")))),"") -> Plowhorse | L5: =IFERROR(IF($K5="","",IF($K5="Star","It sells and leaves margin: it's the dish that carries its category.",IF($K5="Plowhorse","It sells a lot, but leaves little margin in dollars per unit.",IF($K5="Puzzle","It leaves a good margin in dollars, but few guests order it.","It neither sells nor leaves margin.")))),"") -> It sells a lot, but leaves little margin in dollars per unit. | M5: =IFERROR(IF($K5="","",IF($K5="Star","Keep the recipe and the supplier, and give it a prominent spot on the menu.",IF($K5="Plowhorse","Raise the price carefully or lower the cost without touching the portion.",IF($K5="Puzzle","Move it on the menu, rename it and have the floor staff suggest it.","Remove or rework it: it takes up space on the menu and in the kitchen.")))),"") -> Raise the price carefully or lower the cost without touching the portion.
A6: 2 | B6: =IFERROR(IF('Data'!$B6="","",'Data'!$B6),"") -> Heirloom tomato salad with tuna belly and scallions | C6: =IFERROR(IF('Data'!$C6="","",'Data'!$C6),"") -> Starters | D6: =IFERROR(IF('Data'!$D6="","",'Data'!$D6),"") -> 310 | E6: =IFERROR(IF('Data'!$L6="","",'Data'!$L6),"") -> 0.17919075 | F6: =IFERROR(IF('Data'!$M6="","",'Data'!$M6),"") -> 0.1 | G6: =IFERROR(IF(OR($E6="",$F6=""),"",IF($E6>=$F6,"High","Low")),"") -> High | H6: =IFERROR(IF('Data'!$G6="","",'Data'!$G6),"") -> 8.2 | I6: =IFERROR(IF('Data'!$N6="","",'Data'!$N6),"") -> 7.4635838 | J6: =IFERROR(IF(OR($H6="",$I6=""),"",IF($H6>=$I6,"High","Low")),"") -> High | K6: =IFERROR(IF(OR($G6="",$J6=""),"",IF(AND($G6="High",$J6="High"),"Star",IF(AND($G6="High",$J6="Low"),"Plowhorse",IF(AND($G6="Low",$J6="High"),"Puzzle","Dog")))),"") -> Star | L6: =IFERROR(IF($K6="","",IF($K6="Star","It sells and leaves margin: it's the dish that carries its category.",IF($K6="Plowhorse","It sells a lot, but leaves little margin in dollars per unit.",IF($K6="Puzzle","It leaves a good margin in dollars, but few guests order it.","It neither sells nor leaves margin.")))),"") -> It sells and leaves margin: it's the dish that carries its category. | M6: =IFERROR(IF($K6="","",IF($K6="Star","Keep the recipe and the supplier, and give it a prominent spot on the menu.",IF($K6="Plowhorse","Raise the price carefully or lower the cost without touching the portion.",IF($K6="Puzzle","Move it on the menu, rename it and have the floor staff suggest it.","Remove or rework it: it takes up space on the menu and in the kitchen.")))),"") -> Keep the recipe and the supplier, and give it a prominent spot on the menu.
A7: 3 | B7: =IFERROR(IF('Data'!$B7="","",'Data'!$B7),"") -> Garlic shrimp | C7: =IFERROR(IF('Data'!$C7="","",'Data'!$C7),"") -> Starters | D7: =IFERROR(IF('Data'!$D7="","",'Data'!$D7),"") -> 260 | E7: =IFERROR(IF('Data'!$L7="","",'Data'!$L7),"") -> 0.15028902 | F7: =IFERROR(IF('Data'!$M7="","",'Data'!$M7),"") -> 0.1 | G7: =IFERROR(IF(OR($E7="",$F7=""),"",IF($E7>=$F7,"High","Low")),"") -> High | H7: =IFERROR(IF('Data'!$G7="","",'Data'!$G7),"") -> 8.6 | I7: =IFERROR(IF('Data'!$N7="","",'Data'!$N7),"") -> 7.4635838 | J7: =IFERROR(IF(OR($H7="",$I7=""),"",IF($H7>=$I7,"High","Low")),"") -> High | K7: =IFERROR(IF(OR($G7="",$J7=""),"",IF(AND($G7="High",$J7="High"),"Star",IF(AND($G7="High",$J7="Low"),"Plowhorse",IF(AND($G7="Low",$J7="High"),"Puzzle","Dog")))),"") -> Star | L7: =IFERROR(IF($K7="","",IF($K7="Star","It sells and leaves margin: it's the dish that carries its category.",IF($K7="Plowhorse","It sells a lot, but leaves little margin in dollars per unit.",IF($K7="Puzzle","It leaves a good margin in dollars, but few guests order it.","It neither sells nor leaves margin.")))),"") -> It sells and leaves margin: it's the dish that carries its category. | M7: =IFERROR(IF($K7="","",IF($K7="Star","Keep the recipe and the supplier, and give it a prominent spot on the menu.",IF($K7="Plowhorse","Raise the price carefully or lower the cost without touching the portion.",IF($K7="Puzzle","Move it on the menu, rename it and have the floor staff suggest it.","Remove or rework it: it takes up space on the menu and in the kitchen.")))),"") -> Keep the recipe and the supplier, and give it a prominent spot on the menu.
A8: 4 | B8: =IFERROR(IF('Data'!$B8="","",'Data'!$B8),"") -> Broken eggs with potatoes and chistorra sausage | C8: =IFERROR(IF('Data'!$C8="","",'Data'!$C8),"") -> Starters | D8: =IFERROR(IF('Data'!$D8="","",'Data'!$D8),"") -> 380 | E8: =IFERROR(IF('Data'!$L8="","",'Data'!$L8),"") -> 0.21965318 | F8: =IFERROR(IF('Data'!$M8="","",'Data'!$M8),"") -> 0.1 | G8: =IFERROR(IF(OR($E8="",$F8=""),"",IF($E8>=$F8,"High","Low")),"") -> High | H8: =IFERROR(IF('Data'!$G8="","",'Data'!$G8),"") -> 7.4 | I8: =IFERROR(IF('Data'!$N8="","",'Data'!$N8),"") -> 7.4635838 | J8: =IFERROR(IF(OR($H8="",$I8=""),"",IF($H8>=$I8,"High","Low")),"") -> Low | K8: =IFERROR(IF(OR($G8="",$J8=""),"",IF(AND($G8="High",$J8="High"),"Star",IF(AND($G8="High",$J8="Low"),"Plowhorse",IF(AND($G8="Low",$J8="High"),"Puzzle","Dog")))),"") -> Plowhorse | L8: =IFERROR(IF($K8="","",IF($K8="Star","It sells and leaves margin: it's the dish that carries its category.",IF($K8="Plowhorse","It sells a lot, but leaves little margin in dollars per unit.",IF($K8="Puzzle","It leaves a good margin in dollars, but few guests order it.","It neither sells nor leaves margin.")))),"") -> It sells a lot, but leaves little margin in dollars per unit. | M8: =IFERROR(IF($K8="","",IF($K8="Star","Keep the recipe and the supplier, and give it a prominent spot on the menu.",IF($K8="Plowhorse","Raise the price carefully or lower the cost without touching the portion.",IF($K8="Puzzle","Move it on the menu, rename it and have the floor staff suggest it.","Remove or rework it: it takes up space on the menu and in the kitchen.")))),"") -> Raise the price carefully or lower the cost without touching the portion.
A9: 5 | B9: =IFERROR(IF('Data'!$B9="","",'Data'!$B9),"") -> Local cheese board | C9: =IFERROR(IF('Data'!$C9="","",'Data'!$C9),"") -> Starters | D9: =IFERROR(IF('Data'!$D9="","",'Data'!$D9),"") -> 90 | E9: =IFERROR(IF('Data'!$L9="","",'Data'!$L9),"") -> 0.052023121 | F9: =IFERROR(IF('Data'!$M9="","",'Data'!$M9),"") -> 0.1 | G9: =IFERROR(IF(OR($E9="",$F9=""),"",IF($E9>=$F9,"High","Low")),"") -> Low | H9: =IFERROR(IF('Data'!$G9="","",'Data'!$G9),"") -> 8.4 | I9: =IFERROR(IF('Data'!$N9="","",'Data'!$N9),"") -> 7.4635838 | J9: =IFERROR(IF(OR($H9="",$I9=""),"",IF($H9>=$I9,"High","Low")),"") -> High | K9: =IFERROR(IF(OR($G9="",$J9=""),"",IF(AND($G9="High",$J9="High"),"Star",IF(AND($G9="High",$J9="Low"),"Plowhorse",IF(AND($G9="Low",$J9="High"),"Puzzle","Dog")))),"") -> Puzzle | L9: =IFERROR(IF($K9="","",IF($K9="Star","It sells and leaves margin: it's the dish that carries its category.",IF($K9="Plowhorse","It sells a lot, but leaves little margin in dollars per unit.",IF($K9="Puzzle","It leaves a good margin in dollars, but few guests order it.","It neither sells nor leaves margin.")))),"") -> It leaves a good margin in dollars, but few guests order it. | M9: =IFERROR(IF($K9="","",IF($K9="Star","Keep the recipe and the supplier, and give it a prominent spot on the menu.",IF($K9="Plowhorse","Raise the price carefully or lower the cost without touching the portion.",IF($K9="Puzzle","Move it on the menu, rename it and have the floor staff suggest it.","Remove or rework it: it takes up space on the menu and in the kitchen.")))),"") -> Move it on the menu, rename it and have the floor staff suggest it.
A10: 6 | B10: =IFERROR(IF('Data'!$B10="","",'Data'!$B10),"") -> Confit artichokes with ham | C10: =IFERROR(IF('Data'!$C10="","",'Data'!$C10),"") -> Starters | D10: =IFERROR(IF('Data'!$D10="","",'Data'!$D10),"") -> 120 | E10: =IFERROR(IF('Data'!$L10="","",'Data'!$L10),"") -> 0.069364162 | F10: =IFERROR(IF('Data'!$M10="","",'Data'!$M10),"") -> 0.1 | G10: =IFERROR(IF(OR($E10="",$F10=""),"",IF($E10>=$F10,"High","Low")),"") -> Low | H10: =IFERROR(IF('Data'!$G10="","",'Data'!$G10),"") -> 7.8 | I10: =IFERROR(IF('Data'!$N10="","",'Data'!$N10),"") -> 7.4635838 | J10: =IFERROR(IF(OR($H10="",$I10=""),"",IF($H10>=$I10,"High","Low")),"") -> High | K10: =IFERROR(IF(OR($G10="",$J10=""),"",IF(AND($G10="High",$J10="High"),"Star",IF(AND($G10="High",$J10="Low"),"Plowhorse",IF(AND($G10="Low",$J10="High"),"Puzzle","Dog")))),"") -> Puzzle | L10: =IFERROR(IF($K10="","",IF($K10="Star","It sells and leaves margin: it's the dish that carries its category.",IF($K10="Plowhorse","It sells a lot, but leaves little margin in dollars per unit.",IF($K10="Puzzle","It leaves a good margin in dollars, but few guests order it.","It neither sells nor leaves margin.")))),"") -> It leaves a good margin in dollars, but few guests order it. | M10: =IFERROR(IF($K10="","",IF($K10="Star","Keep the recipe and the supplier, and give it a prominent spot on the menu.",IF($K10="Plowhorse","Raise the price carefully or lower the cost without touching the portion.",IF($K10="Puzzle","Move it on the menu, rename it and have the floor staff suggest it.","Remove or rework it: it takes up space on the menu and in the kitchen.")))),"") -> Move it on the menu, rename it and have the floor staff suggest it.
A11: 7 | B11: =IFERROR(IF('Data'!$B11="","",'Data'!$B11),"") -> Roasted tomato soup with basil | C11: =IFERROR(IF('Data'!$C11="","",'Data'!$C11),"") -> Starters | D11: =IFERROR(IF('Data'!$D11="","",'Data'!$D11),"") -> 150 | E11: =IFERROR(IF('Data'!$L11="","",'Data'!$L11),"") -> 0.086705202 | F11: =IFERROR(IF('Data'!$M11="","",'Data'!$M11),"") -> 0.1 | G11: =IFERROR(IF(OR($E11="",$F11=""),"",IF($E11>=$F11,"High","Low")),"") -> Low | H11: =IFERROR(IF('Data'!$G11="","",'Data'!$G11),"") -> 6 | I11: =IFERROR(IF('Data'!$N11="","",'Data'!$N11),"") -> 7.4635838 | J11: =IFERROR(IF(OR($H11="",$I11=""),"",IF($H11>=$I11,"High","Low")),"") -> Low | K11: =IFERROR(IF(OR($G11="",$J11=""),"",IF(AND($G11="High",$J11="High"),"Star",IF(AND($G11="High",$J11="Low"),"Plowhorse",IF(AND($G11="Low",$J11="High"),"Puzzle","Dog")))),"") -> Dog | L11: =IFERROR(IF($K11="","",IF($K11="Star","It sells and leaves margin: it's the dish that carries its category.",IF($K11="Plowhorse","It sells a lot, but leaves little margin in dollars per unit.",IF($K11="Puzzle","It leaves a good margin in dollars, but few guests order it.","It neither sells nor leaves margin.")))),"") -> It neither sells nor leaves margin. | M11: =IFERROR(IF($K11="","",IF($K11="Star","Keep the recipe and the supplier, and give it a prominent spot on the menu.",IF($K11="Plowhorse","Raise the price carefully or lower the cost without touching the portion.",IF($K11="Puzzle","Move it on the menu, rename it and have the floor staff suggest it.","Remove or rework it: it takes up space on the menu and in the kitchen.")))),"") -> Remove or rework it: it takes up space on the menu and in the kitchen.
A12: 8 | B12: =IFERROR(IF('Data'!$B12="","",'Data'!$B12),"") -> Iberico pork tenderloin with sweet potato purée | C12: =IFERROR(IF('Data'!$C12="","",'Data'!$C12),"") -> Mains | D12: =IFERROR(IF('Data'!$D12="","",'Data'!$D12),"") -> 340 | E12: =IFERROR(IF('Data'!$L12="","",'Data'!$L12),"") -> 0.16831683 | F12: =IFERROR(IF('Data'!$M12="","",'Data'!$M12),"") -> 0.077777778 | G12: =IFERROR(IF(OR($E12="",$F12=""),"",IF($E12>=$F12,"High","Low")),"") -> High | H12: =IFERROR(IF('Data'!$G12="","",'Data'!$G12),"") -> 11.63 | I12: =IFERROR(IF('Data'!$N12="","",'Data'!$N12),"") -> 10.795149 | J12: =IFERROR(IF(OR($H12="",$I12=""),"",IF($H12>=$I12,"High","Low")),"") -> High | K12: =IFERROR(IF(OR($G12="",$J12=""),"",IF(AND($G12="High",$J12="High"),"Star",IF(AND($G12="High",$J12="Low"),"Plowhorse",IF(AND($G12="Low",$J12="High"),"Puzzle","Dog")))),"") -> Star | L12: =IFERROR(IF($K12="","",IF($K12="Star","It sells and leaves margin: it's the dish that carries its category.",IF($K12="Plowhorse","It sells a lot, but leaves little margin in dollars per unit.",IF($K12="Puzzle","It leaves a good margin in dollars, but few guests order it.","It neither sells nor leaves margin.")))),"") -> It sells and leaves margin: it's the dish that carries its category. | M12: =IFERROR(IF($K12="","",IF($K12="Star","Keep the recipe and the supplier, and give it a prominent spot on the menu.",IF($K12="Plowhorse","Raise the price carefully or lower the cost without touching the portion.",IF($K12="Puzzle","Move it on the menu, rename it and have the floor staff suggest it.","Remove or rework it: it takes up space on the menu and in the kitchen.")))),"") -> Keep the recipe and the supplier, and give it a prominent spot on the menu.
A13: 9 | B13: =IFERROR(IF('Data'!$B13="","",'Data'!$B13),"") -> Confit cod in pil-pil sauce | C13: =IFERROR(IF('Data'!$C13="","",'Data'!$C13),"") -> Mains | D13: =IFERROR(IF('Data'!$D13="","",'Data'!$D13),"") -> 190 | E13: =IFERROR(IF('Data'!$L13="","",'Data'!$L13),"") -> 0.094059406 | F13: =IFERROR(IF('Data'!$M13="","",'Data'!$M13),"") -> 0.077777778 | G13: =IFERROR(IF(OR($E13="",$F13=""),"",IF($E13>=$F13,"High","Low")),"") -> High | H13: =IFERROR(IF('Data'!$G13="","",'Data'!$G13),"") -> 11.7 | I13: =IFERROR(IF('Data'!$N13="","",'Data'!$N13),"") -> 10.795149 | J13: =IFERROR(IF(OR($H13="",$I13=""),"",IF($H13>=$I13,"High","Low")),"") -> High | K13: =IFERROR(IF(OR($G13="",$J13=""),"",IF(AND($G13="High",$J13="High"),"Star",IF(AND($G13="High",$J13="Low"),"Plowhorse",IF(AND($G13="Low",$J13="High"),"Puzzle","Dog")))),"") -> Star | L13: =IFERROR(IF($K13="","",IF($K13="Star","It sells and leaves margin: it's the dish that carries its category.",IF($K13="Plowhorse","It sells a lot, but leaves little margin in dollars per unit.",IF($K13="Puzzle","It leaves a good margin in dollars, but few guests order it.","It neither sells nor leaves margin.")))),"") -> It sells and leaves margin: it's the dish that carries its category. | M13: =IFERROR(IF($K13="","",IF($K13="Star","Keep the recipe and the supplier, and give it a prominent spot on the menu.",IF($K13="Plowhorse","Raise the price carefully or lower the cost without touching the portion.",IF($K13="Puzzle","Move it on the menu, rename it and have the floor staff suggest it.","Remove or rework it: it takes up space on the menu and in the kitchen.")))),"") -> Keep the recipe and the supplier, and give it a prominent spot on the menu.
A14: 10 | B14: =IFERROR(IF('Data'!$B14="","",'Data'!$B14),"") -> Dry-aged beef burger with fries | C14: =IFERROR(IF('Data'!$C14="","",'Data'!$C14),"") -> Mains | D14: =IFERROR(IF('Data'!$D14="","",'Data'!$D14),"") -> 460 | E14: =IFERROR(IF('Data'!$L14="","",'Data'!$L14),"") -> 0.22772277 | F14: =IFERROR(IF('Data'!$M14="","",'Data'!$M14),"") -> 0.077777778 | G14: =IFERROR(IF(OR($E14="",$F14=""),"",IF($E14>=$F14,"High","Low")),"") -> High | H14: =IFERROR(IF('Data'!$G14="","",'Data'!$G14),"") -> 9.3 | I14: =IFERROR(IF('Data'!$N14="","",'Data'!$N14),"") -> 10.795149 | J14: =IFERROR(IF(OR($H14="",$I14=""),"",IF($H14>=$I14,"High","Low")),"") -> Low | K14: =IFERROR(IF(OR($G14="",$J14=""),"",IF(AND($G14="High",$J14="High"),"Star",IF(AND($G14="High",$J14="Low"),"Plowhorse",IF(AND($G14="Low",$J14="High"),"Puzzle","Dog")))),"") -> Plowhorse | L14: =IFERROR(IF($K14="","",IF($K14="Star","It sells and leaves margin: it's the dish that carries its category.",IF($K14="Plowhorse","It sells a lot, but leaves little margin in dollars per unit.",IF($K14="Puzzle","It leaves a good margin in dollars, but few guests order it.","It neither sells nor leaves margin.")))),"") -> It sells a lot, but leaves little margin in dollars per unit. | M14: =IFERROR(IF($K14="","",IF($K14="Star","Keep the recipe and the supplier, and give it a prominent spot on the menu.",IF($K14="Plowhorse","Raise the price carefully or lower the cost without touching the portion.",IF($K14="Puzzle","Move it on the menu, rename it and have the floor staff suggest it.","Remove or rework it: it takes up space on the menu and in the kitchen.")))),"") -> Raise the price carefully or lower the cost without touching the portion.
A15: 11 | B15: =IFERROR(IF('Data'!$B15="","",'Data'!$B15),"") -> Creamy rice with Iberico pork secreto and mushrooms | C15: =IFERROR(IF('Data'!$C15="","",'Data'!$C15),"") -> Mains | D15: =IFERROR(IF('Data'!$D15="","",'Data'!$D15),"") -> 270 | E15: =IFERROR(IF('Data'!$L15="","",'Data'!$L15),"") -> 0.13366337 | F15: =IFERROR(IF('Data'!$M15="","",'Data'!$M15),"") -> 0.077777778 | G15: =IFERROR(IF(OR($E15="",$F15=""),"",IF($E15>=$F15,"High","Low")),"") -> High | H15: =IFERROR(IF('Data'!$G15="","",'Data'!$G15),"") -> 10.2 | I15: =IFERROR(IF('Data'!$N15="","",'Data'!$N15),"") -> 10.795149 | J15: =IFERROR(IF(OR($H15="",$I15=""),"",IF($H15>=$I15,"High","Low")),"") -> Low | K15: =IFERROR(IF(OR($G15="",$J15=""),"",IF(AND($G15="High",$J15="High"),"Star",IF(AND($G15="High",$J15="Low"),"Plowhorse",IF(AND($G15="Low",$J15="High"),"Puzzle","Dog")))),"") -> Plowhorse | L15: =IFERROR(IF($K15="","",IF($K15="Star","It sells and leaves margin: it's the dish that carries its category.",IF($K15="Plowhorse","It sells a lot, but leaves little margin in dollars per unit.",IF($K15="Puzzle","It leaves a good margin in dollars, but few guests order it.","It neither sells nor leaves margin.")))),"") -> It sells a lot, but leaves little margin in dollars per unit. | M15: =IFERROR(IF($K15="","",IF($K15="Star","Keep the recipe and the supplier, and give it a prominent spot on the menu.",IF($K15="Plowhorse","Raise the price carefully or lower the cost without touching the portion.",IF($K15="Puzzle","Move it on the menu, rename it and have the floor staff suggest it.","Remove or rework it: it takes up space on the menu and in the kitchen.")))),"") -> Raise the price carefully or lower the cost without touching the portion.
A16: 12 | B16: =IFERROR(IF('Data'!$B16="","",'Data'!$B16),"") -> Dry-aged bone-in ribeye (17.64 oz) | C16: =IFERROR(IF('Data'!$C16="","",'Data'!$C16),"") -> Mains | D16: =IFERROR(IF('Data'!$D16="","",'Data'!$D16),"") -> 110 | E16: =IFERROR(IF('Data'!$L16="","",'Data'!$L16),"") -> 0.054455446 | F16: =IFERROR(IF('Data'!$M16="","",'Data'!$M16),"") -> 0.077777778 | G16: =IFERROR(IF(OR($E16="",$F16=""),"",IF($E16>=$F16,"High","Low")),"") -> Low | H16: =IFERROR(IF('Data'!$G16="","",'Data'!$G16),"") -> 17.9 | I16: =IFERROR(IF('Data'!$N16="","",'Data'!$N16),"") -> 10.795149 | J16: =IFERROR(IF(OR($H16="",$I16=""),"",IF($H16>=$I16,"High","Low")),"") -> High | K16: =IFERROR(IF(OR($G16="",$J16=""),"",IF(AND($G16="High",$J16="High"),"Star",IF(AND($G16="High",$J16="Low"),"Plowhorse",IF(AND($G16="Low",$J16="High"),"Puzzle","Dog")))),"") -> Puzzle | L16: =IFERROR(IF($K16="","",IF($K16="Star","It sells and leaves margin: it's the dish that carries its category.",IF($K16="Plowhorse","It sells a lot, but leaves little margin in dollars per unit.",IF($K16="Puzzle","It leaves a good margin in dollars, but few guests order it.","It neither sells nor leaves margin.")))),"") -> It leaves a good margin in dollars, but few guests order it. | M16: =IFERROR(IF($K16="","",IF($K16="Star","Keep the recipe and the supplier, and give it a prominent spot on the menu.",IF($K16="Plowhorse","Raise the price carefully or lower the cost without touching the portion.",IF($K16="Puzzle","Move it on the menu, rename it and have the floor staff suggest it.","Remove or rework it: it takes up space on the menu and in the kitchen.")))),"") -> Move it on the menu, rename it and have the floor staff suggest it.
... A29: 25 | B29: =IFERROR(IF('Data'!$B29="","",'Data'!$B29),"") | C29: =IFERROR(IF('Data'!$C29="","",'Data'!$C29),"") | D29: =IFERROR(IF('Data'!$D29="","",'Data'!$D29),"") | E29: =IFERROR(IF('Data'!$L29="","",'Data'!$L29),"") | F29: =IFERROR(IF('Data'!$M29="","",'Data'!$M29),"") | G29: =IFERROR(IF(OR($E29="",$F29=""),"",IF($E29>=$F29,"High","Low")),"") | H29: =IFERROR(IF('Data'!$G29="","",'Data'!$G29),"") | I29: =IFERROR(IF('Data'!$N29="","",'Data'!$N29),"") | J29: =IFERROR(IF(OR($H29="",$I29=""),"",IF($H29>=$I29,"High","Low")),"") | K29: =IFERROR(IF(OR($G29="",$J29=""),"",IF(AND($G29="High",$J29="High"),"Star",IF(AND($G29="High",$J29="Low"),"Plowhorse",IF(AND($G29="Low",$J29="High"),"Puzzle","Dog")))),"") | L29: =IFERROR(IF($K29="","",IF($K29="Star","It sells and leaves margin: it's the dish that carries its category.",IF($K29="Plowhorse","It sells a lot, but leaves little margin in dollars per unit.",IF($K29="Puzzle","It leaves a good margin in dollars, but few guests order it.","It neither sells nor leaves margin.")))),"") | M29: =IFERROR(IF($K29="","",IF($K29="Star","Keep the recipe and the supplier, and give it a prominent spot on the menu.",IF($K29="Plowhorse","Raise the price carefully or lower the cost without touching the portion.",IF($K29="Puzzle","Move it on the menu, rename it and have the floor staff suggest it.","Remove or rework it: it takes up space on the menu and in the kitchen.")))),"")
A31: SUMMARY — calculated by the workbook
B32: Classification | C32: Dishes | D32: Units sold | E32: % of menu units | F32: Total CM contributed
B33: Star | C33: =COUNTIF($K$5:$K$29,$B33) -> 6 | D33: =IFERROR(SUMIF($K$5:$K$29,$B33,$D$5:$D$29),"") -> 1950 | E33: =IFERROR(IF(SUM($D$5:$D$29)=0,"",$D33/SUM($D$5:$D$29)),"") -> 0.40041068 | F33: =IFERROR(SUMPRODUCT(--($K$5:$K$29=$B33),$D$5:$D$29,$H$5:$H$29),"") -> 14865.2
B34: Plowhorse | C34: =COUNTIF($K$5:$K$29,$B34) -> 6 | D34: =IFERROR(SUMIF($K$5:$K$29,$B34,$D$5:$D$29),"") -> 2040 | E34: =IFERROR(IF(SUM($D$5:$D$29)=0,"",$D34/SUM($D$5:$D$29)),"") -> 0.41889117 | F34: =IFERROR(SUMPRODUCT(--($K$5:$K$29=$B34),$D$5:$D$29,$H$5:$H$29),"") -> 16198
B35: Puzzle | C35: =COUNTIF($K$5:$K$29,$B35) -> 5 | D35: =IFERROR(SUMIF($K$5:$K$29,$B35,$D$5:$D$29),"") -> 530 | E35: =IFERROR(IF(SUM($D$5:$D$29)=0,"",$D35/SUM($D$5:$D$29)),"") -> 0.10882957 | F35: =IFERROR(SUMPRODUCT(--($K$5:$K$29=$B35),$D$5:$D$29,$H$5:$H$29),"") -> 6357
B36: Dog | C36: =COUNTIF($K$5:$K$29,$B36) -> 3 | D36: =IFERROR(SUMIF($K$5:$K$29,$B36,$D$5:$D$29),"") -> 350 | E36: =IFERROR(IF(SUM($D$5:$D$29)=0,"",$D36/SUM($D$5:$D$29)),"") -> 0.071868583 | F36: =IFERROR(SUMPRODUCT(--($K$5:$K$29=$B36),$D$5:$D$29,$H$5:$H$29),"") -> 2318

Sheet Miller
A1: Miller — popularity × food cost %
A2: AI Chef Pro · aichef.pro — Food Cost + Menu Engineering Guide
E3: Miller rewards low food cost; Kasavana & Smith rewards margin in dollars. They don't always agree.
A4: # | B4: Dish | C4: Category | D4: Units sold | E4: Menu Mix in Category (MM%) | F4: Popularity threshold in its category (%) | G4: Popularity | H4: Dish food cost (%) | I4: Category weighted avg food cost (%) | J4: Food cost level | K4: Classification | L4: What it means | M4: Recommended action
A5: 1 | B5: =IFERROR(IF('Data'!$B5="","",'Data'!$B5),"") -> Iberico ham croquettes (6 pcs) | C5: =IFERROR(IF('Data'!$C5="","",'Data'!$C5),"") -> Starters | D5: =IFERROR(IF('Data'!$D5="","",'Data'!$D5),"") -> 420 | E5: =IFERROR(IF('Data'!$L5="","",'Data'!$L5),"") -> 0.24277457 | F5: =IFERROR(IF('Data'!$M5="","",'Data'!$M5),"") -> 0.1 | G5: =IFERROR(IF(OR($E5="",$F5=""),"",IF($E5>=$F5,"High","Low")),"") -> High | H5: =IFERROR(IF('Data'!$H5="","",'Data'!$H5),"") -> 0.24418605 | I5: =IFERROR(IF('Data'!$O5="","",'Data'!$O5),"") -> 0.30714746 | J5: =IFERROR(IF(OR($H5="",$I5=""),"",IF($H5<=$I5,"Low","High")),"") -> Low | K5: =IFERROR(IF(OR($G5="",$J5=""),"",IF(AND($G5="High",$J5="Low"),"Winner",IF(AND($G5="Low",$J5="High"),"Loser","Marginal"))),"") -> Winner | L5: =IFERROR(IF($K5="","",IF($K5="Winner","Popular, with a food cost below its category's average.",IF($K5="Marginal","It meets only one of the two: either it sells, or its food cost is healthy.","Rarely ordered, with a food cost above its category."))),"") -> Popular, with a food cost below its category's average. | M5: =IFERROR(IF($K5="","",IF($K5="Winner","Keep it and protect its cost card: it's the one that can absorb a supplier increase.",IF($K5="Marginal","Check the other readings before touching it: the problem is either price or menu placement.","Rework the recipe or take it off the menu."))),"") -> Keep it and protect its cost card: it's the one that can absorb a supplier increase.
A6: 2 | B6: =IFERROR(IF('Data'!$B6="","",'Data'!$B6),"") -> Heirloom tomato salad with tuna belly and scallions | C6: =IFERROR(IF('Data'!$C6="","",'Data'!$C6),"") -> Starters | D6: =IFERROR(IF('Data'!$D6="","",'Data'!$D6),"") -> 310 | E6: =IFERROR(IF('Data'!$L6="","",'Data'!$L6),"") -> 0.17919075 | F6: =IFERROR(IF('Data'!$M6="","",'Data'!$M6),"") -> 0.1 | G6: =IFERROR(IF(OR($E6="",$F6=""),"",IF($E6>=$F6,"High","Low")),"") -> High | H6: =IFERROR(IF('Data'!$H6="","",'Data'!$H6),"") -> 0.30508475 | I6: =IFERROR(IF('Data'!$O6="","",'Data'!$O6),"") -> 0.30714746 | J6: =IFERROR(IF(OR($H6="",$I6=""),"",IF($H6<=$I6,"Low","High")),"") -> Low | K6: =IFERROR(IF(OR($G6="",$J6=""),"",IF(AND($G6="High",$J6="Low"),"Winner",IF(AND($G6="Low",$J6="High"),"Loser","Marginal"))),"") -> Winner | L6: =IFERROR(IF($K6="","",IF($K6="Winner","Popular, with a food cost below its category's average.",IF($K6="Marginal","It meets only one of the two: either it sells, or its food cost is healthy.","Rarely ordered, with a food cost above its category."))),"") -> Popular, with a food cost below its category's average. | M6: =IFERROR(IF($K6="","",IF($K6="Winner","Keep it and protect its cost card: it's the one that can absorb a supplier increase.",IF($K6="Marginal","Check the other readings before touching it: the problem is either price or menu placement.","Rework the recipe or take it off the menu."))),"") -> Keep it and protect its cost card: it's the one that can absorb a supplier increase.
A7: 3 | B7: =IFERROR(IF('Data'!$B7="","",'Data'!$B7),"") -> Garlic shrimp | C7: =IFERROR(IF('Data'!$C7="","",'Data'!$C7),"") -> Starters | D7: =IFERROR(IF('Data'!$D7="","",'Data'!$D7),"") -> 260 | E7: =IFERROR(IF('Data'!$L7="","",'Data'!$L7),"") -> 0.15028902 | F7: =IFERROR(IF('Data'!$M7="","",'Data'!$M7),"") -> 0.1 | G7: =IFERROR(IF(OR($E7="",$F7=""),"",IF($E7>=$F7,"High","Low")),"") -> High | H7: =IFERROR(IF('Data'!$H7="","",'Data'!$H7),"") -> 0.44516129 | I7: =IFERROR(IF('Data'!$O7="","",'Data'!$O7),"") -> 0.30714746 | J7: =IFERROR(IF(OR($H7="",$I7=""),"",IF($H7<=$I7,"Low","High")),"") -> High | K7: =IFERROR(IF(OR($G7="",$J7=""),"",IF(AND($G7="High",$J7="Low"),"Winner",IF(AND($G7="Low",$J7="High"),"Loser","Marginal"))),"") -> Marginal | L7: =IFERROR(IF($K7="","",IF($K7="Winner","Popular, with a food cost below its category's average.",IF($K7="Marginal","It meets only one of the two: either it sells, or its food cost is healthy.","Rarely ordered, with a food cost above its category."))),"") -> It meets only one of the two: either it sells, or its food cost is healthy. | M7: =IFERROR(IF($K7="","",IF($K7="Winner","Keep it and protect its cost card: it's the one that can absorb a supplier increase.",IF($K7="Marginal","Check the other readings before touching it: the problem is either price or menu placement.","Rework the recipe or take it off the menu."))),"") -> Check the other readings before touching it: the problem is either price or menu placement.
A8: 4 | B8: =IFERROR(IF('Data'!$B8="","",'Data'!$B8),"") -> Broken eggs with potatoes and chistorra sausage | C8: =IFERROR(IF('Data'!$C8="","",'Data'!$C8),"") -> Starters | D8: =IFERROR(IF('Data'!$D8="","",'Data'!$D8),"") -> 380 | E8: =IFERROR(IF('Data'!$L8="","",'Data'!$L8),"") -> 0.21965318 | F8: =IFERROR(IF('Data'!$M8="","",'Data'!$M8),"") -> 0.1 | G8: =IFERROR(IF(OR($E8="",$F8=""),"",IF($E8>=$F8,"High","Low")),"") -> High | H8: =IFERROR(IF('Data'!$H8="","",'Data'!$H8),"") -> 0.24489796 | I8: =IFERROR(IF('Data'!$O8="","",'Data'!$O8),"") -> 0.30714746 | J8: =IFERROR(IF(OR($H8="",$I8=""),"",IF($H8<=$I8,"Low","High")),"") -> Low | K8: =IFERROR(IF(OR($G8="",$J8=""),"",IF(AND($G8="High",$J8="Low"),"Winner",IF(AND($G8="Low",$J8="High"),"Loser","Marginal"))),"") -> Winner | L8: =IFERROR(IF($K8="","",IF($K8="Winner","Popular, with a food cost below its category's average.",IF($K8="Marginal","It meets only one of the two: either it sells, or its food cost is healthy.","Rarely ordered, with a food cost above its category."))),"") -> Popular, with a food cost below its category's average. | M8: =IFERROR(IF($K8="","",IF($K8="Winner","Keep it and protect its cost card: it's the one that can absorb a supplier increase.",IF($K8="Marginal","Check the other readings before touching it: the problem is either price or menu placement.","Rework the recipe or take it off the menu."))),"") -> Keep it and protect its cost card: it's the one that can absorb a supplier increase.
A9: 5 | B9: =IFERROR(IF('Data'!$B9="","",'Data'!$B9),"") -> Local cheese board | C9: =IFERROR(IF('Data'!$C9="","",'Data'!$C9),"") -> Starters | D9: =IFERROR(IF('Data'!$D9="","",'Data'!$D9),"") -> 90 | E9: =IFERROR(IF('Data'!$L9="","",'Data'!$L9),"") -> 0.052023121 | F9: =IFERROR(IF('Data'!$M9="","",'Data'!$M9),"") -> 0.1 | G9: =IFERROR(IF(OR($E9="",$F9=""),"",IF($E9>=$F9,"High","Low")),"") -> Low | H9: =IFERROR(IF('Data'!$H9="","",'Data'!$H9),"") -> 0.38235294 | I9: =IFERROR(IF('Data'!$O9="","",'Data'!$O9),"") -> 0.30714746 | J9: =IFERROR(IF(OR($H9="",$I9=""),"",IF($H9<=$I9,"Low","High")),"") -> High | K9: =IFERROR(IF(OR($G9="",$J9=""),"",IF(AND($G9="High",$J9="Low"),"Winner",IF(AND($G9="Low",$J9="High"),"Loser","Marginal"))),"") -> Loser | L9: =IFERROR(IF($K9="","",IF($K9="Winner","Popular, with a food cost below its category's average.",IF($K9="Marginal","It meets only one of the two: either it sells, or its food cost is healthy.","Rarely ordered, with a food cost above its category."))),"") -> Rarely ordered, with a food cost above its category. | M9: =IFERROR(IF($K9="","",IF($K9="Winner","Keep it and protect its cost card: it's the one that can absorb a supplier increase.",IF($K9="Marginal","Check the other readings before touching it: the problem is either price or menu placement.","Rework the recipe or take it off the menu."))),"") -> Rework the recipe or take it off the menu.
A10: 6 | B10: =IFERROR(IF('Data'!$B10="","",'Data'!$B10),"") -> Confit artichokes with ham | C10: =IFERROR(IF('Data'!$C10="","",'Data'!$C10),"") -> Starters | D10: =IFERROR(IF('Data'!$D10="","",'Data'!$D10),"") -> 120 | E10: =IFERROR(IF('Data'!$L10="","",'Data'!$L10),"") -> 0.069364162 | F10: =IFERROR(IF('Data'!$M10="","",'Data'!$M10),"") -> 0.1 | G10: =IFERROR(IF(OR($E10="",$F10=""),"",IF($E10>=$F10,"High","Low")),"") -> Low | H10: =IFERROR(IF('Data'!$H10="","",'Data'!$H10),"") -> 0.28440367 | I10: =IFERROR(IF('Data'!$O10="","",'Data'!$O10),"") -> 0.30714746 | J10: =IFERROR(IF(OR($H10="",$I10=""),"",IF($H10<=$I10,"Low","High")),"") -> Low | K10: =IFERROR(IF(OR($G10="",$J10=""),"",IF(AND($G10="High",$J10="Low"),"Winner",IF(AND($G10="Low",$J10="High"),"Loser","Marginal"))),"") -> Marginal | L10: =IFERROR(IF($K10="","",IF($K10="Winner","Popular, with a food cost below its category's average.",IF($K10="Marginal","It meets only one of the two: either it sells, or its food cost is healthy.","Rarely ordered, with a food cost above its category."))),"") -> It meets only one of the two: either it sells, or its food cost is healthy. | M10: =IFERROR(IF($K10="","",IF($K10="Winner","Keep it and protect its cost card: it's the one that can absorb a supplier increase.",IF($K10="Marginal","Check the other readings before touching it: the problem is either price or menu placement.","Rework the recipe or take it off the menu."))),"") -> Check the other readings before touching it: the problem is either price or menu placement.
A11: 7 | B11: =IFERROR(IF('Data'!$B11="","",'Data'!$B11),"") -> Roasted tomato soup with basil | C11: =IFERROR(IF('Data'!$C11="","",'Data'!$C11),"") -> Starters | D11: =IFERROR(IF('Data'!$D11="","",'Data'!$D11),"") -> 150 | E11: =IFERROR(IF('Data'!$L11="","",'Data'!$L11),"") -> 0.086705202 | F11: =IFERROR(IF('Data'!$M11="","",'Data'!$M11),"") -> 0.1 | G11: =IFERROR(IF(OR($E11="",$F11=""),"",IF($E11>=$F11,"High","Low")),"") -> Low | H11: =IFERROR(IF('Data'!$H11="","",'Data'!$H11),"") -> 0.16666667 | I11: =IFERROR(IF('Data'!$O11="","",'Data'!$O11),"") -> 0.30714746 | J11: =IFERROR(IF(OR($H11="",$I11=""),"",IF($H11<=$I11,"Low","High")),"") -> Low | K11: =IFERROR(IF(OR($G11="",$J11=""),"",IF(AND($G11="High",$J11="Low"),"Winner",IF(AND($G11="Low",$J11="High"),"Loser","Marginal"))),"") -> Marginal | L11: =IFERROR(IF($K11="","",IF($K11="Winner","Popular, with a food cost below its category's average.",IF($K11="Marginal","It meets only one of the two: either it sells, or its food cost is healthy.","Rarely ordered, with a food cost above its category."))),"") -> It meets only one of the two: either it sells, or its food cost is healthy. | M11: =IFERROR(IF($K11="","",IF($K11="Winner","Keep it and protect its cost card: it's the one that can absorb a supplier increase.",IF($K11="Marginal","Check the other readings before touching it: the problem is either price or menu placement.","Rework the recipe or take it off the menu."))),"") -> Check the other readings before touching it: the problem is either price or menu placement.
A12: 8 | B12: =IFERROR(IF('Data'!$B12="","",'Data'!$B12),"") -> Iberico pork tenderloin with sweet potato purée | C12: =IFERROR(IF('Data'!$C12="","",'Data'!$C12),"") -> Mains | D12: =IFERROR(IF('Data'!$D12="","",'Data'!$D12),"") -> 340 | E12: =IFERROR(IF('Data'!$L12="","",'Data'!$L12),"") -> 0.16831683 | F12: =IFERROR(IF('Data'!$M12="","",'Data'!$M12),"") -> 0.077777778 | G12: =IFERROR(IF(OR($E12="",$F12=""),"",IF($E12>=$F12,"High","Low")),"") -> High | H12: =IFERROR(IF('Data'!$H12="","",'Data'!$H12),"") -> 0.32774566 | I12: =IFERROR(IF('Data'!$O12="","",'Data'!$O12),"") -> 0.35587523 | J12: =IFERROR(IF(OR($H12="",$I12=""),"",IF($H12<=$I12,"Low","High")),"") -> Low | K12: =IFERROR(IF(OR($G12="",$J12=""),"",IF(AND($G12="High",$J12="Low"),"Winner",IF(AND($G12="Low",$J12="High"),"Loser","Marginal"))),"") -> Winner | L12: =IFERROR(IF($K12="","",IF($K12="Winner","Popular, with a food cost below its category's average.",IF($K12="Marginal","It meets only one of the two: either it sells, or its food cost is healthy.","Rarely ordered, with a food cost above its category."))),"") -> Popular, with a food cost below its category's average. | M12: =IFERROR(IF($K12="","",IF($K12="Winner","Keep it and protect its cost card: it's the one that can absorb a supplier increase.",IF($K12="Marginal","Check the other readings before touching it: the problem is either price or menu placement.","Rework the recipe or take it off the menu."))),"") -> Keep it and protect its cost card: it's the one that can absorb a supplier increase.
A13: 9 | B13: =IFERROR(IF('Data'!$B13="","",'Data'!$B13),"") -> Confit cod in pil-pil sauce | C13: =IFERROR(IF('Data'!$C13="","",'Data'!$C13),"") -> Mains | D13: =IFERROR(IF('Data'!$D13="","",'Data'!$D13),"") -> 190 | E13: =IFERROR(IF('Data'!$L13="","",'Data'!$L13),"") -> 0.094059406 | F13: =IFERROR(IF('Data'!$M13="","",'Data'!$M13),"") -> 0.077777778 | G13: =IFERROR(IF(OR($E13="",$F13=""),"",IF($E13>=$F13,"High","Low")),"") -> High | H13: =IFERROR(IF('Data'!$H13="","",'Data'!$H13),"") -> 0.38743455 | I13: =IFERROR(IF('Data'!$O13="","",'Data'!$O13),"") -> 0.35587523 | J13: =IFERROR(IF(OR($H13="",$I13=""),"",IF($H13<=$I13,"Low","High")),"") -> High | K13: =IFERROR(IF(OR($G13="",$J13=""),"",IF(AND($G13="High",$J13="Low"),"Winner",IF(AND($G13="Low",$J13="High"),"Loser","Marginal"))),"") -> Marginal | L13: =IFERROR(IF($K13="","",IF($K13="Winner","Popular, with a food cost below its category's average.",IF($K13="Marginal","It meets only one of the two: either it sells, or its food cost is healthy.","Rarely ordered, with a food cost above its category."))),"") -> It meets only one of the two: either it sells, or its food cost is healthy. | M13: =IFERROR(IF($K13="","",IF($K13="Winner","Keep it and protect its cost card: it's the one that can absorb a supplier increase.",IF($K13="Marginal","Check the other readings before touching it: the problem is either price or menu placement.","Rework the recipe or take it off the menu."))),"") -> Check the other readings before touching it: the problem is either price or menu placement.
A14: 10 | B14: =IFERROR(IF('Data'!$B14="","",'Data'!$B14),"") -> Dry-aged beef burger with fries | C14: =IFERROR(IF('Data'!$C14="","",'Data'!$C14),"") -> Mains | D14: =IFERROR(IF('Data'!$D14="","",'Data'!$D14),"") -> 460 | E14: =IFERROR(IF('Data'!$L14="","",'Data'!$L14),"") -> 0.22772277 | F14: =IFERROR(IF('Data'!$M14="","",'Data'!$M14),"") -> 0.077777778 | G14: =IFERROR(IF(OR($E14="",$F14=""),"",IF($E14>=$F14,"High","Low")),"") -> High | H14: =IFERROR(IF('Data'!$H14="","",'Data'!$H14),"") -> 0.31617647 | I14: =IFERROR(IF('Data'!$O14="","",'Data'!$O14),"") -> 0.35587523 | J14: =IFERROR(IF(OR($H14="",$I14=""),"",IF($H14<=$I14,"Low","High")),"") -> Low | K14: =IFERROR(IF(OR($G14="",$J14=""),"",IF(AND($G14="High",$J14="Low"),"Winner",IF(AND($G14="Low",$J14="High"),"Loser","Marginal"))),"") -> Winner | L14: =IFERROR(IF($K14="","",IF($K14="Winner","Popular, with a food cost below its category's average.",IF($K14="Marginal","It meets only one of the two: either it sells, or its food cost is healthy.","Rarely ordered, with a food cost above its category."))),"") -> Popular, with a food cost below its category's average. | M14: =IFERROR(IF($K14="","",IF($K14="Winner","Keep it and protect its cost card: it's the one that can absorb a supplier increase.",IF($K14="Marginal","Check the other readings before touching it: the problem is either price or menu placement.","Rework the recipe or take it off the menu."))),"") -> Keep it and protect its cost card: it's the one that can absorb a supplier increase.
A15: 11 | B15: =IFERROR(IF('Data'!$B15="","",'Data'!$B15),"") -> Creamy rice with Iberico pork secreto and mushrooms | C15: =IFERROR(IF('Data'!$C15="","",'Data'!$C15),"") -> Mains | D15: =IFERROR(IF('Data'!$D15="","",'Data'!$D15),"") -> 270 | E15: =IFERROR(IF('Data'!$L15="","",'Data'!$L15),"") -> 0.13366337 | F15: =IFERROR(IF('Data'!$M15="","",'Data'!$M15),"") -> 0.077777778 | G15: =IFERROR(IF(OR($E15="",$F15=""),"",IF($E15>=$F15,"High","Low")),"") -> High | H15: =IFERROR(IF('Data'!$H15="","",'Data'!$H15),"") -> 0.37804878 | I15: =IFERROR(IF('Data'!$O15="","",'Data'!$O15),"") -> 0.35587523 | J15: =IFERROR(IF(OR($H15="",$I15=""),"",IF($H15<=$I15,"Low","High")),"") -> High | K15: =IFERROR(IF(OR($G15="",$J15=""),"",IF(AND($G15="High",$J15="Low"),"Winner",IF(AND($G15="Low",$J15="High"),"Loser","Marginal"))),"") -> Marginal | L15: =IFERROR(IF($K15="","",IF($K15="Winner","Popular, with a food cost below its category's average.",IF($K15="Marginal","It meets only one of the two: either it sells, or its food cost is healthy.","Rarely ordered, with a food cost above its category."))),"") -> It meets only one of the two: either it sells, or its food cost is healthy. | M15: =IFERROR(IF($K15="","",IF($K15="Winner","Keep it and protect its cost card: it's the one that can absorb a supplier increase.",IF($K15="Marginal","Check the other readings before touching it: the problem is either price or menu placement.","Rework the recipe or take it off the menu."))),"") -> Check the other readings before touching it: the problem is either price or menu placement.
A16: 12 | B16: =IFERROR(IF('Data'!$B16="","",'Data'!$B16),"") -> Dry-aged bone-in ribeye (17.64 oz) | C16: =IFERROR(IF('Data'!$C16="","",'Data'!$C16),"") -> Mains | D16: =IFERROR(IF('Data'!$D16="","",'Data'!$D16),"") -> 110 | E16: =IFERROR(IF('Data'!$L16="","",'Data'!$L16),"") -> 0.054455446 | F16: =IFERROR(IF('Data'!$M16="","",'Data'!$M16),"") -> 0.077777778 | G16: =IFERROR(IF(OR($E16="",$F16=""),"",IF($E16>=$F16,"High","Low")),"") -> Low | H16: =IFERROR(IF('Data'!$H16="","",'Data'!$H16),"") -> 0.45259939 | I16: =IFERROR(IF('Data'!$O16="","",'Data'!$O16),"") -> 0.35587523 | J16: =IFERROR(IF(OR($H16="",$I16=""),"",IF($H16<=$I16,"Low","High")),"") -> High | K16: =IFERROR(IF(OR($G16="",$J16=""),"",IF(AND($G16="High",$J16="Low"),"Winner",IF(AND($G16="Low",$J16="High"),"Loser","Marginal"))),"") -> Loser | L16: =IFERROR(IF($K16="","",IF($K16="Winner","Popular, with a food cost below its category's average.",IF($K16="Marginal","It meets only one of the two: either it sells, or its food cost is healthy.","Rarely ordered, with a food cost above its category."))),"") -> Rarely ordered, with a food cost above its category. | M16: =IFERROR(IF($K16="","",IF($K16="Winner","Keep it and protect its cost card: it's the one that can absorb a supplier increase.",IF($K16="Marginal","Check the other readings before touching it: the problem is either price or menu placement.","Rework the recipe or take it off the menu."))),"") -> Rework the recipe or take it off the menu.
... A29: 25 | B29: =IFERROR(IF('Data'!$B29="","",'Data'!$B29),"") | C29: =IFERROR(IF('Data'!$C29="","",'Data'!$C29),"") | D29: =IFERROR(IF('Data'!$D29="","",'Data'!$D29),"") | E29: =IFERROR(IF('Data'!$L29="","",'Data'!$L29),"") | F29: =IFERROR(IF('Data'!$M29="","",'Data'!$M29),"") | G29: =IFERROR(IF(OR($E29="",$F29=""),"",IF($E29>=$F29,"High","Low")),"") | H29: =IFERROR(IF('Data'!$H29="","",'Data'!$H29),"") | I29: =IFERROR(IF('Data'!$O29="","",'Data'!$O29),"") | J29: =IFERROR(IF(OR($H29="",$I29=""),"",IF($H29<=$I29,"Low","High")),"") | K29: =IFERROR(IF(OR($G29="",$J29=""),"",IF(AND($G29="High",$J29="Low"),"Winner",IF(AND($G29="Low",$J29="High"),"Loser","Marginal"))),"") | L29: =IFERROR(IF($K29="","",IF($K29="Winner","Popular, with a food cost below its category's average.",IF($K29="Marginal","It meets only one of the two: either it sells, or its food cost is healthy.","Rarely ordered, with a food cost above its category."))),"") | M29: =IFERROR(IF($K29="","",IF($K29="Winner","Keep it and protect its cost card: it's the one that can absorb a supplier increase.",IF($K29="Marginal","Check the other readings before touching it: the problem is either price or menu placement.","Rework the recipe or take it off the menu."))),"")
A31: SUMMARY — calculated by the workbook
B32: Classification | C32: Dishes | D32: Units sold | E32: % of menu units | F32: Weighted avg food cost of the group (%)
B33: Winner | C33: =COUNTIF($K$5:$K$29,$B33) -> 8 | D33: =IFERROR(SUMIF($K$5:$K$29,$B33,$D$5:$D$29),"") -> 2940 | E33: =IFERROR(IF(SUM($D$5:$D$29)=0,"",$D33/SUM($D$5:$D$29)),"") -> 0.6036961 | F33: =IFERROR(IF($D33=0,"",SUMPRODUCT(--($K$5:$K$29=$B33),$D$5:$D$29,$H$5:$H$29)/$D33),"") -> 0.26906401
B34: Marginal | C34: =COUNTIF($K$5:$K$29,$B34) -> 7 | D34: =IFERROR(SUMIF($K$5:$K$29,$B34,$D$5:$D$29),"") -> 1460 | E34: =IFERROR(IF(SUM($D$5:$D$29)=0,"",$D34/SUM($D$5:$D$29)),"") -> 0.29979466 | F34: =IFERROR(IF($D34=0,"",SUMPRODUCT(--($K$5:$K$29=$B34),$D$5:$D$29,$H$5:$H$29)/$D34),"") -> 0.32030632
B35: Loser | C35: =COUNTIF($K$5:$K$29,$B35) -> 5 | D35: =IFERROR(SUMIF($K$5:$K$29,$B35,$D$5:$D$29),"") -> 470 | E35: =IFERROR(IF(SUM($D$5:$D$29)=0,"",$D35/SUM($D$5:$D$29)),"") -> 0.09650924 | F35: =IFERROR(IF($D35=0,"",SUMPRODUCT(--($K$5:$K$29=$B35),$D$5:$D$29,$H$5:$H$29)/$D35),"") -> 0.40689192

Sheet Pavesic
A1: Pavesic — food cost % × margin weighted by units
A2: AI Chef Pro · aichef.pro — Food Cost + Menu Engineering Guide
E3: Weighted margin (CM × units) measures how much money the dish brings to the total, not how much it leaves per unit.
A4: # | B4: Dish | C4: Category | D4: Units sold | E4: Dish food cost (%) | F4: Category weighted avg food cost (%) | G4: Food cost level | H4: Weighted CM: CM × units | I4: Category average of weighted CM | J4: Weighted CM level | K4: Classification | L4: What it means | M4: Recommended action
A5: 1 | B5: =IFERROR(IF('Data'!$B5="","",'Data'!$B5),"") -> Iberico ham croquettes (6 pcs) | C5: =IFERROR(IF('Data'!$C5="","",'Data'!$C5),"") -> Starters | D5: =IFERROR(IF('Data'!$D5="","",'Data'!$D5),"") -> 420 | E5: =IFERROR(IF('Data'!$H5="","",'Data'!$H5),"") -> 0.24418605 | F5: =IFERROR(IF('Data'!$O5="","",'Data'!$O5),"") -> 0.30714746 | G5: =IFERROR(IF(OR($E5="",$F5=""),"",IF($E5<=$F5,"Low","High")),"") -> Low | H5: =IFERROR(IF('Data'!$P5="","",'Data'!$P5),"") -> 2730 | I5: =IFERROR(IF('Data'!$Q5="","",'Data'!$Q5),"") -> 1844.5714 | J5: =IFERROR(IF(OR($H5="",$I5=""),"",IF($H5>=$I5,"High","Low")),"") -> High | K5: =IFERROR(IF(OR($G5="",$J5=""),"",IF(AND($G5="Low",$J5="High"),"Prime",IF(AND($G5="High",$J5="High"),"Standard",IF(AND($G5="Low",$J5="Low"),"Sleeper","Problem")))),"") -> Prime | L5: =IFERROR(IF($K5="","",IF($K5="Prime","Low food cost and it brings a lot of margin in dollars to the total.",IF($K5="Standard","It brings a lot of margin in dollars despite a high food cost.",IF($K5="Sleeper","Healthy food cost, but it brings little margin in dollars to the total.","High food cost and it brings little margin in dollars to the total.")))),"") -> Low food cost and it brings a lot of margin in dollars to the total. | M5: =IFERROR(IF($K5="","",IF($K5="Prime","Keep it and promote it: this is where the category's money is.",IF($K5="Standard","Watch its cost card: it wins on volume, not on efficiency.",IF($K5="Sleeper","Give it visibility: the margin is there, it just needs to be ordered.","Rework the recipe or take it off the menu.")))),"") -> Keep it and promote it: this is where the category's money is.
A6: 2 | B6: =IFERROR(IF('Data'!$B6="","",'Data'!$B6),"") -> Heirloom tomato salad with tuna belly and scallions | C6: =IFERROR(IF('Data'!$C6="","",'Data'!$C6),"") -> Starters | D6: =IFERROR(IF('Data'!$D6="","",'Data'!$D6),"") -> 310 | E6: =IFERROR(IF('Data'!$H6="","",'Data'!$H6),"") -> 0.30508475 | F6: =IFERROR(IF('Data'!$O6="","",'Data'!$O6),"") -> 0.30714746 | G6: =IFERROR(IF(OR($E6="",$F6=""),"",IF($E6<=$F6,"Low","High")),"") -> Low | H6: =IFERROR(IF('Data'!$P6="","",'Data'!$P6),"") -> 2542 | I6: =IFERROR(IF('Data'!$Q6="","",'Data'!$Q6),"") -> 1844.5714 | J6: =IFERROR(IF(OR($H6="",$I6=""),"",IF($H6>=$I6,"High","Low")),"") -> High | K6: =IFERROR(IF(OR($G6="",$J6=""),"",IF(AND($G6="Low",$J6="High"),"Prime",IF(AND($G6="High",$J6="High"),"Standard",IF(AND($G6="Low",$J6="Low"),"Sleeper","Problem")))),"") -> Prime | L6: =IFERROR(IF($K6="","",IF($K6="Prime","Low food cost and it brings a lot of margin in dollars to the total.",IF($K6="Standard","It brings a lot of margin in dollars despite a high food cost.",IF($K6="Sleeper","Healthy food cost, but it brings little margin in dollars to the total.","High food cost and it brings little margin in dollars to the total.")))),"") -> Low food cost and it brings a lot of margin in dollars to the total. | M6: =IFERROR(IF($K6="","",IF($K6="Prime","Keep it and promote it: this is where the category's money is.",IF($K6="Standard","Watch its cost card: it wins on volume, not on efficiency.",IF($K6="Sleeper","Give it visibility: the margin is there, it just needs to be ordered.","Rework the recipe or take it off the menu.")))),"") -> Keep it and promote it: this is where the category's money is.
A7: 3 | B7: =IFERROR(IF('Data'!$B7="","",'Data'!$B7),"") -> Garlic shrimp | C7: =IFERROR(IF('Data'!$C7="","",'Data'!$C7),"") -> Starters | D7: =IFERROR(IF('Data'!$D7="","",'Data'!$D7),"") -> 260 | E7: =IFERROR(IF('Data'!$H7="","",'Data'!$H7),"") -> 0.44516129 | F7: =IFERROR(IF('Data'!$O7="","",'Data'!$O7),"") -> 0.30714746 | G7: =IFERROR(IF(OR($E7="",$F7=""),"",IF($E7<=$F7,"Low","High")),"") -> High | H7: =IFERROR(IF('Data'!$P7="","",'Data'!$P7),"") -> 2236 | I7: =IFERROR(IF('Data'!$Q7="","",'Data'!$Q7),"") -> 1844.5714 | J7: =IFERROR(IF(OR($H7="",$I7=""),"",IF($H7>=$I7,"High","Low")),"") -> High | K7: =IFERROR(IF(OR($G7="",$J7=""),"",IF(AND($G7="Low",$J7="High"),"Prime",IF(AND($G7="High",$J7="High"),"Standard",IF(AND($G7="Low",$J7="Low"),"Sleeper","Problem")))),"") -> Standard | L7: =IFERROR(IF($K7="","",IF($K7="Prime","Low food cost and it brings a lot of margin in dollars to the total.",IF($K7="Standard","It brings a lot of margin in dollars despite a high food cost.",IF($K7="Sleeper","Healthy food cost, but it brings little margin in dollars to the total.","High food cost and it brings little margin in dollars to the total.")))),"") -> It brings a lot of margin in dollars despite a high food cost. | M7: =IFERROR(IF($K7="","",IF($K7="Prime","Keep it and promote it: this is where the category's money is.",IF($K7="Standard","Watch its cost card: it wins on volume, not on efficiency.",IF($K7="Sleeper","Give it visibility: the margin is there, it just needs to be ordered.","Rework the recipe or take it off the menu.")))),"") -> Watch its cost card: it wins on volume, not on efficiency.
A8: 4 | B8: =IFERROR(IF('Data'!$B8="","",'Data'!$B8),"") -> Broken eggs with potatoes and chistorra sausage | C8: =IFERROR(IF('Data'!$C8="","",'Data'!$C8),"") -> Starters | D8: =IFERROR(IF('Data'!$D8="","",'Data'!$D8),"") -> 380 | E8: =IFERROR(IF('Data'!$H8="","",'Data'!$H8),"") -> 0.24489796 | F8: =IFERROR(IF('Data'!$O8="","",'Data'!$O8),"") -> 0.30714746 | G8: =IFERROR(IF(OR($E8="",$F8=""),"",IF($E8<=$F8,"Low","High")),"") -> Low | H8: =IFERROR(IF('Data'!$P8="","",'Data'!$P8),"") -> 2812 | I8: =IFERROR(IF('Data'!$Q8="","",'Data'!$Q8),"") -> 1844.5714 | J8: =IFERROR(IF(OR($H8="",$I8=""),"",IF($H8>=$I8,"High","Low")),"") -> High | K8: =IFERROR(IF(OR($G8="",$J8=""),"",IF(AND($G8="Low",$J8="High"),"Prime",IF(AND($G8="High",$J8="High"),"Standard",IF(AND($G8="Low",$J8="Low"),"Sleeper","Problem")))),"") -> Prime | L8: =IFERROR(IF($K8="","",IF($K8="Prime","Low food cost and it brings a lot of margin in dollars to the total.",IF($K8="Standard","It brings a lot of margin in dollars despite a high food cost.",IF($K8="Sleeper","Healthy food cost, but it brings little margin in dollars to the total.","High food cost and it brings little margin in dollars to the total.")))),"") -> Low food cost and it brings a lot of margin in dollars to the total. | M8: =IFERROR(IF($K8="","",IF($K8="Prime","Keep it and promote it: this is where the category's money is.",IF($K8="Standard","Watch its cost card: it wins on volume, not on efficiency.",IF($K8="Sleeper","Give it visibility: the margin is there, it just needs to be ordered.","Rework the recipe or take it off the menu.")))),"") -> Keep it and promote it: this is where the category's money is.
A9: 5 | B9: =IFERROR(IF('Data'!$B9="","",'Data'!$B9),"") -> Local cheese board | C9: =IFERROR(IF('Data'!$C9="","",'Data'!$C9),"") -> Starters | D9: =IFERROR(IF('Data'!$D9="","",'Data'!$D9),"") -> 90 | E9: =IFERROR(IF('Data'!$H9="","",'Data'!$H9),"") -> 0.38235294 | F9: =IFERROR(IF('Data'!$O9="","",'Data'!$O9),"") -> 0.30714746 | G9: =IFERROR(IF(OR($E9="",$F9=""),"",IF($E9<=$F9,"Low","High")),"") -> High | H9: =IFERROR(IF('Data'!$P9="","",'Data'!$P9),"") -> 756 | I9: =IFERROR(IF('Data'!$Q9="","",'Data'!$Q9),"") -> 1844.5714 | J9: =IFERROR(IF(OR($H9="",$I9=""),"",IF($H9>=$I9,"High","Low")),"") -> Low | K9: =IFERROR(IF(OR($G9="",$J9=""),"",IF(AND($G9="Low",$J9="High"),"Prime",IF(AND($G9="High",$J9="High"),"Standard",IF(AND($G9="Low",$J9="Low"),"Sleeper","Problem")))),"") -> Problem | L9: =IFERROR(IF($K9="","",IF($K9="Prime","Low food cost and it brings a lot of margin in dollars to the total.",IF($K9="Standard","It brings a lot of margin in dollars despite a high food cost.",IF($K9="Sleeper","Healthy food cost, but it brings little margin in dollars to the total.","High food cost and it brings little margin in dollars to the total.")))),"") -> High food cost and it brings little margin in dollars to the total. | M9: =IFERROR(IF($K9="","",IF($K9="Prime","Keep it and promote it: this is where the category's money is.",IF($K9="Standard","Watch its cost card: it wins on volume, not on efficiency.",IF($K9="Sleeper","Give it visibility: the margin is there, it just needs to be ordered.","Rework the recipe or take it off the menu.")))),"") -> Rework the recipe or take it off the menu.
A10: 6 | B10: =IFERROR(IF('Data'!$B10="","",'Data'!$B10),"") -> Confit artichokes with ham | C10: =IFERROR(IF('Data'!$C10="","",'Data'!$C10),"") -> Starters | D10: =IFERROR(IF('Data'!$D10="","",'Data'!$D10),"") -> 120 | E10: =IFERROR(IF('Data'!$H10="","",'Data'!$H10),"") -> 0.28440367 | F10: =IFERROR(IF('Data'!$O10="","",'Data'!$O10),"") -> 0.30714746 | G10: =IFERROR(IF(OR($E10="",$F10=""),"",IF($E10<=$F10,"Low","High")),"") -> Low | H10: =IFERROR(IF('Data'!$P10="","",'Data'!$P10),"") -> 936 | I10: =IFERROR(IF('Data'!$Q10="","",'Data'!$Q10),"") -> 1844.5714 | J10: =IFERROR(IF(OR($H10="",$I10=""),"",IF($H10>=$I10,"High","Low")),"") -> Low | K10: =IFERROR(IF(OR($G10="",$J10=""),"",IF(AND($G10="Low",$J10="High"),"Prime",IF(AND($G10="High",$J10="High"),"Standard",IF(AND($G10="Low",$J10="Low"),"Sleeper","Problem")))),"") -> Sleeper | L10: =IFERROR(IF($K10="","",IF($K10="Prime","Low food cost and it brings a lot of margin in dollars to the total.",IF($K10="Standard","It brings a lot of margin in dollars despite a high food cost.",IF($K10="Sleeper","Healthy food cost, but it brings little margin in dollars to the total.","High food cost and it brings little margin in dollars to the total.")))),"") -> Healthy food cost, but it brings little margin in dollars to the total. | M10: =IFERROR(IF($K10="","",IF($K10="Prime","Keep it and promote it: this is where the category's money is.",IF($K10="Standard","Watch its cost card: it wins on volume, not on efficiency.",IF($K10="Sleeper","Give it visibility: the margin is there, it just needs to be ordered.","Rework the recipe or take it off the menu.")))),"") -> Give it visibility: the margin is there, it just needs to be ordered.
A11: 7 | B11: =IFERROR(IF('Data'!$B11="","",'Data'!$B11),"") -> Roasted tomato soup with basil | C11: =IFERROR(IF('Data'!$C11="","",'Data'!$C11),"") -> Starters | D11: =IFERROR(IF('Data'!$D11="","",'Data'!$D11),"") -> 150 | E11: =IFERROR(IF('Data'!$H11="","",'Data'!$H11),"") -> 0.16666667 | F11: =IFERROR(IF('Data'!$O11="","",'Data'!$O11),"") -> 0.30714746 | G11: =IFERROR(IF(OR($E11="",$F11=""),"",IF($E11<=$F11,"Low","High")),"") -> Low | H11: =IFERROR(IF('Data'!$P11="","",'Data'!$P11),"") -> 900 | I11: =IFERROR(IF('Data'!$Q11="","",'Data'!$Q11),"") -> 1844.5714 | J11: =IFERROR(IF(OR($H11="",$I11=""),"",IF($H11>=$I11,"High","Low")),"") -> Low | K11: =IFERROR(IF(OR($G11="",$J11=""),"",IF(AND($G11="Low",$J11="High"),"Prime",IF(AND($G11="High",$J11="High"),"Standard",IF(AND($G11="Low",$J11="Low"),"Sleeper","Problem")))),"") -> Sleeper | L11: =IFERROR(IF($K11="","",IF($K11="Prime","Low food cost and it brings a lot of margin in dollars to the total.",IF($K11="Standard","It brings a lot of margin in dollars despite a high food cost.",IF($K11="Sleeper","Healthy food cost, but it brings little margin in dollars to the total.","High food cost and it brings little margin in dollars to the total.")))),"") -> Healthy food cost, but it brings little margin in dollars to the total. | M11: =IFERROR(IF($K11="","",IF($K11="Prime","Keep it and promote it: this is where the category's money is.",IF($K11="Standard","Watch its cost card: it wins on volume, not on efficiency.",IF($K11="Sleeper","Give it visibility: the margin is there, it just needs to be ordered.","Rework the recipe or take it off the menu.")))),"") -> Give it visibility: the margin is there, it just needs to be ordered.
A12: 8 | B12: =IFERROR(IF('Data'!$B12="","",'Data'!$B12),"") -> Iberico pork tenderloin with sweet potato purée | C12: =IFERROR(IF('Data'!$C12="","",'Data'!$C12),"") -> Mains | D12: =IFERROR(IF('Data'!$D12="","",'Data'!$D12),"") -> 340 | E12: =IFERROR(IF('Data'!$H12="","",'Data'!$H12),"") -> 0.32774566 | F12: =IFERROR(IF('Data'!$O12="","",'Data'!$O12),"") -> 0.35587523 | G12: =IFERROR(IF(OR($E12="",$F12=""),"",IF($E12<=$F12,"Low","High")),"") -> Low | H12: =IFERROR(IF('Data'!$P12="","",'Data'!$P12),"") -> 3954.2 | I12: =IFERROR(IF('Data'!$Q12="","",'Data'!$Q12),"") -> 2422.9111 | J12: =IFERROR(IF(OR($H12="",$I12=""),"",IF($H12>=$I12,"High","Low")),"") -> High | K12: =IFERROR(IF(OR($G12="",$J12=""),"",IF(AND($G12="Low",$J12="High"),"Prime",IF(AND($G12="High",$J12="High"),"Standard",IF(AND($G12="Low",$J12="Low"),"Sleeper","Problem")))),"") -> Prime | L12: =IFERROR(IF($K12="","",IF($K12="Prime","Low food cost and it brings a lot of margin in dollars to the total.",IF($K12="Standard","It brings a lot of margin in dollars despite a high food cost.",IF($K12="Sleeper","Healthy food cost, but it brings little margin in dollars to the total.","High food cost and it brings little margin in dollars to the total.")))),"") -> Low food cost and it brings a lot of margin in dollars to the total. | M12: =IFERROR(IF($K12="","",IF($K12="Prime","Keep it and promote it: this is where the category's money is.",IF($K12="Standard","Watch its cost card: it wins on volume, not on efficiency.",IF($K12="Sleeper","Give it visibility: the margin is there, it just needs to be ordered.","Rework the recipe or take it off the menu.")))),"") -> Keep it and promote it: this is where the category's money is.
A13: 9 | B13: =IFERROR(IF('Data'!$B13="","",'Data'!$B13),"") -> Confit cod in pil-pil sauce | C13: =IFERROR(IF('Data'!$C13="","",'Data'!$C13),"") -> Mains | D13: =IFERROR(IF('Data'!$D13="","",'Data'!$D13),"") -> 190 | E13: =IFERROR(IF('Data'!$H13="","",'Data'!$H13),"") -> 0.38743455 | F13: =IFERROR(IF('Data'!$O13="","",'Data'!$O13),"") -> 0.35587523 | G13: =IFERROR(IF(OR($E13="",$F13=""),"",IF($E13<=$F13,"Low","High")),"") -> High | H13: =IFERROR(IF('Data'!$P13="","",'Data'!$P13),"") -> 2223 | I13: =IFERROR(IF('Data'!$Q13="","",'Data'!$Q13),"") -> 2422.9111 | J13: =IFERROR(IF(OR($H13="",$I13=""),"",IF($H13>=$I13,"High","Low")),"") -> Low | K13: =IFERROR(IF(OR($G13="",$J13=""),"",IF(AND($G13="Low",$J13="High"),"Prime",IF(AND($G13="High",$J13="High"),"Standard",IF(AND($G13="Low",$J13="Low"),"Sleeper","Problem")))),"") -> Problem | L13: =IFERROR(IF($K13="","",IF($K13="Prime","Low food cost and it brings a lot of margin in dollars to the total.",IF($K13="Standard","It brings a lot of margin in dollars despite a high food cost.",IF($K13="Sleeper","Healthy food cost, but it brings little margin in dollars to the total.","High food cost and it brings little margin in dollars to the total.")))),"") -> High food cost and it brings little margin in dollars to the total. | M13: =IFERROR(IF($K13="","",IF($K13="Prime","Keep it and promote it: this is where the category's money is.",IF($K13="Standard","Watch its cost card: it wins on volume, not on efficiency.",IF($K13="Sleeper","Give it visibility: the margin is there, it just needs to be ordered.","Rework the recipe or take it off the menu.")))),"") -> Rework the recipe or take it off the menu.
A14: 10 | B14: =IFERROR(IF('Data'!$B14="","",'Data'!$B14),"") -> Dry-aged beef burger with fries | C14: =IFERROR(IF('Data'!$C14="","",'Data'!$C14),"") -> Mains | D14: =IFERROR(IF('Data'!$D14="","",'Data'!$D14),"") -> 460 | E14: =IFERROR(IF('Data'!$H14="","",'Data'!$H14),"") -> 0.31617647 | F14: =IFERROR(IF('Data'!$O14="","",'Data'!$O14),"") -> 0.35587523 | G14: =IFERROR(IF(OR($E14="",$F14=""),"",IF($E14<=$F14,"Low","High")),"") -> Low | H14: =IFERROR(IF('Data'!$P14="","",'Data'!$P14),"") -> 4278 | I14: =IFERROR(IF('Data'!$Q14="","",'Data'!$Q14),"") -> 2422.9111 | J14: =IFERROR(IF(OR($H14="",$I14=""),"",IF($H14>=$I14,"High","Low")),"") -> High | K14: =IFERROR(IF(OR($G14="",$J14=""),"",IF(AND($G14="Low",$J14="High"),"Prime",IF(AND($G14="High",$J14="High"),"Standard",IF(AND($G14="Low",$J14="Low"),"Sleeper","Problem")))),"") -> Prime | L14: =IFERROR(IF($K14="","",IF($K14="Prime","Low food cost and it brings a lot of margin in dollars to the total.",IF($K14="Standard","It brings a lot of margin in dollars despite a high food cost.",IF($K14="Sleeper","Healthy food cost, but it brings little margin in dollars to the total.","High food cost and it brings little margin in dollars to the total.")))),"") -> Low food cost and it brings a lot of margin in dollars to the total. | M14: =IFERROR(IF($K14="","",IF($K14="Prime","Keep it and promote it: this is where the category's money is.",IF($K14="Standard","Watch its cost card: it wins on volume, not on efficiency.",IF($K14="Sleeper","Give it visibility: the margin is there, it just needs to be ordered.","Rework the recipe or take it off the menu.")))),"") -> Keep it and promote it: this is where the category's money is.
A15: 11 | B15: =IFERROR(IF('Data'!$B15="","",'Data'!$B15),"") -> Creamy rice with Iberico pork secreto and mushrooms | C15: =IFERROR(IF('Data'!$C15="","",'Data'!$C15),"") -> Mains | D15: =IFERROR(IF('Data'!$D15="","",'Data'!$D15),"") -> 270 | E15: =IFERROR(IF('Data'!$H15="","",'Data'!$H15),"") -> 0.37804878 | F15: =IFERROR(IF('Data'!$O15="","",'Data'!$O15),"") -> 0.35587523 | G15: =IFERROR(IF(OR($E15="",$F15=""),"",IF($E15<=$F15,"Low","High")),"") -> High | H15: =IFERROR(IF('Data'!$P15="","",'Data'!$P15),"") -> 2754 | I15: =IFERROR(IF('Data'!$Q15="","",'Data'!$Q15),"") -> 2422.9111 | J15: =IFERROR(IF(OR($H15="",$I15=""),"",IF($H15>=$I15,"High","Low")),"") -> High | K15: =IFERROR(IF(OR($G15="",$J15=""),"",IF(AND($G15="Low",$J15="High"),"Prime",IF(AND($G15="High",$J15="High"),"Standard",IF(AND($G15="Low",$J15="Low"),"Sleeper","Problem")))),"") -> Standard | L15: =IFERROR(IF($K15="","",IF($K15="Prime","Low food cost and it brings a lot of margin in dollars to the total.",IF($K15="Standard","It brings a lot of margin in dollars despite a high food cost.",IF($K15="Sleeper","Healthy food cost, but it brings little margin in dollars to the total.","High food cost and it brings little margin in dollars to the total.")))),"") -> It brings a lot of margin in dollars despite a high food cost. | M15: =IFERROR(IF($K15="","",IF($K15="Prime","Keep it and promote it: this is where the category's money is.",IF($K15="Standard","Watch its cost card: it wins on volume, not on efficiency.",IF($K15="Sleeper","Give it visibility: the margin is there, it just needs to be ordered.","Rework the recipe or take it off the menu.")))),"") -> Watch its cost card: it wins on volume, not on efficiency.
A16: 12 | B16: =IFERROR(IF('Data'!$B16="","",'Data'!$B16),"") -> Dry-aged bone-in ribeye (17.64 oz) | C16: =IFERROR(IF('Data'!$C16="","",'Data'!$C16),"") -> Mains | D16: =IFERROR(IF('Data'!$D16="","",'Data'!$D16),"") -> 110 | E16: =IFERROR(IF('Data'!$H16="","",'Data'!$H16),"") -> 0.45259939 | F16: =IFERROR(IF('Data'!$O16="","",'Data'!$O16),"") -> 0.35587523 | G16: =IFERROR(IF(OR($E16="",$F16=""),"",IF($E16<=$F16,"Low","High")),"") -> High | H16: =IFERROR(IF('Data'!$P16="","",'Data'!$P16),"") -> 1969 | I16: =IFERROR(IF('Data'!$Q16="","",'Data'!$Q16),"") -> 2422.9111 | J16: =IFERROR(IF(OR($H16="",$I16=""),"",IF($H16>=$I16,"High","Low")),"") -> Low | K16: =IFERROR(IF(OR($G16="",$J16=""),"",IF(AND($G16="Low",$J16="High"),"Prime",IF(AND($G16="High",$J16="High"),"Standard",IF(AND($G16="Low",$J16="Low"),"Sleeper","Problem")))),"") -> Problem | L16: =IFERROR(IF($K16="","",IF($K16="Prime","Low food cost and it brings a lot of margin in dollars to the total.",IF($K16="Standard","It brings a lot of margin in dollars despite a high food cost.",IF($K16="Sleeper","Healthy food cost, but it brings little margin in dollars to the total.","High food cost and it brings little margin in dollars to the total.")))),"") -> High food cost and it brings little margin in dollars to the total. | M16: =IFERROR(IF($K16="","",IF($K16="Prime","Keep it and promote it: this is where the category's money is.",IF($K16="Standard","Watch its cost card: it wins on volume, not on efficiency.",IF($K16="Sleeper","Give it visibility: the margin is there, it just needs to be ordered.","Rework the recipe or take it off the menu.")))),"") -> Rework the recipe or take it off the menu.
... A29: 25 | B29: =IFERROR(IF('Data'!$B29="","",'Data'!$B29),"") | C29: =IFERROR(IF('Data'!$C29="","",'Data'!$C29),"") | D29: =IFERROR(IF('Data'!$D29="","",'Data'!$D29),"") | E29: =IFERROR(IF('Data'!$H29="","",'Data'!$H29),"") | F29: =IFERROR(IF('Data'!$O29="","",'Data'!$O29),"") | G29: =IFERROR(IF(OR($E29="",$F29=""),"",IF($E29<=$F29,"Low","High")),"") | H29: =IFERROR(IF('Data'!$P29="","",'Data'!$P29),"") | I29: =IFERROR(IF('Data'!$Q29="","",'Data'!$Q29),"") | J29: =IFERROR(IF(OR($H29="",$I29=""),"",IF($H29>=$I29,"High","Low")),"") | K29: =IFERROR(IF(OR($G29="",$J29=""),"",IF(AND($G29="Low",$J29="High"),"Prime",IF(AND($G29="High",$J29="High"),"Standard",IF(AND($G29="Low",$J29="Low"),"Sleeper","Problem")))),"") | L29: =IFERROR(IF($K29="","",IF($K29="Prime","Low food cost and it brings a lot of margin in dollars to the total.",IF($K29="Standard","It brings a lot of margin in dollars despite a high food cost.",IF($K29="Sleeper","Healthy food cost, but it brings little margin in dollars to the total.","High food cost and it brings little margin in dollars to the total.")))),"") | M29: =IFERROR(IF($K29="","",IF($K29="Prime","Keep it and promote it: this is where the category's money is.",IF($K29="Standard","Watch its cost card: it wins on volume, not on efficiency.",IF($K29="Sleeper","Give it visibility: the margin is there, it just needs to be ordered.","Rework the recipe or take it off the menu.")))),"")
A31: SUMMARY — calculated by the workbook
B32: Classification | C32: Dishes | D32: Units sold | E32: % of menu units | F32: Total weighted CM of the group
B33: Prime | C33: =COUNTIF($K$5:$K$29,$B33) -> 7 | D33: =IFERROR(SUMIF($K$5:$K$29,$B33,$D$5:$D$29),"") -> 2730 | E33: =IFERROR(IF(SUM($D$5:$D$29)=0,"",$D33/SUM($D$5:$D$29)),"") -> 0.56057495 | F33: =IFERROR(SUMIF($K$5:$K$29,$B33,$H$5:$H$29),"") -> 21408.2
B34: Standard | C34: =COUNTIF($K$5:$K$29,$B34) -> 3 | D34: =IFERROR(SUMIF($K$5:$K$29,$B34,$D$5:$D$29),"") -> 860 | E34: =IFERROR(IF(SUM($D$5:$D$29)=0,"",$D34/SUM($D$5:$D$29)),"") -> 0.17659138 | F34: =IFERROR(SUMIF($K$5:$K$29,$B34,$H$5:$H$29),"") -> 6508
B35: Sleeper | C35: =COUNTIF($K$5:$K$29,$B35) -> 4 | D35: =IFERROR(SUMIF($K$5:$K$29,$B35,$D$5:$D$29),"") -> 620 | E35: =IFERROR(IF(SUM($D$5:$D$29)=0,"",$D35/SUM($D$5:$D$29)),"") -> 0.12731006 | F35: =IFERROR(SUMIF($K$5:$K$29,$B35,$H$5:$H$29),"") -> 3992
B36: Problem | C36: =COUNTIF($K$5:$K$29,$B36) -> 6 | D36: =IFERROR(SUMIF($K$5:$K$29,$B36,$D$5:$D$29),"") -> 660 | E36: =IFERROR(IF(SUM($D$5:$D$29)=0,"",$D36/SUM($D$5:$D$29)),"") -> 0.13552361 | F36: =IFERROR(SUMIF($K$5:$K$29,$B36,$H$5:$H$29),"") -> 7830

Sheet Goal Value
A1: Goal Value (Hayes & Huffman) — the method that brings labor in
A2: AI Chef Pro · aichef.pro — Food Cost + Menu Engineering Guide
E3: Goal Value = (1 − food cost %) × units × menu price × (1 − (labor % + other variable % + food cost %)) — food cost counts twice: that's what sets Goal Value apart from Pavesic and penalizes the dish that's expensive to produce.
A4: # | B4: Dish | C4: Category | D4: Units sold | E4: Dish food cost (%) | F4: Menu price pre-tax | G4: Dish Goal Value | H4: Average units in its category | I4: Category weighted avg menu price | J4: Category weighted avg food cost (%) | K4: Category Goal Value target | L4: Reading | M4: Distance from target (index) | N4: What to check
A5: 1 | B5: =IFERROR(IF('Data'!$B5="","",'Data'!$B5),"") -> Iberico ham croquettes (6 pcs) | C5: =IFERROR(IF('Data'!$C5="","",'Data'!$C5),"") -> Starters | D5: =IFERROR(IF('Data'!$D5="","",'Data'!$D5),"") -> 420 | E5: =IFERROR(IF('Data'!$H5="","",'Data'!$H5),"") -> 0.24418605 | F5: =IFERROR(IF('Data'!$F5="","",'Data'!$F5),"") -> 8.6 | G5: =IFERROR(IF(OR($D5="",$E5="",$F5="",$D$33+$D$34+$E5>=1),"",(1-$E5)*$D5*$F5*(1-($D$33+$D$34+$E5))),"") -> 916.77209 | H5: =IFERROR(IF(OR('Data'!$K5="",'Data'!$K5=0),"",'Data'!$J5/'Data'!$K5),"") -> 247.14286 | I5: =IFERROR(IF(OR('Data'!$J5="",'Data'!$J5=0),"",SUMPRODUCT(--('Data'!$C$5:$C$29='Data'!$C5),'Data'!$D$5:$D$29,'Data'!$F$5:$F$29)/'Data'!$J5),"") -> 10.772254 | J5: =IFERROR(IF('Data'!$O5="","",'Data'!$O5),"") -> 0.30714746 | K5: =IFERROR(IF(OR($H5="",$I5="",$J5="",$D$33+$D$34+$J5>=1),"",(1-$J5)*$H5*$I5*(1-($D$33+$D$34+$J5))),"") -> 503.29601 | L5: =IFERROR(IF(OR($G5="",$K5=""),"",IF($G5>=$K5,"Above target","Below target")),"") -> Above target | M5: =IFERROR(IF(OR($G5="",$K5=""),"",$G5-$K5),"") -> 413.47609 | N5: =IFERROR(IF($L5="","",IF($L5="Above target","It meets its category's target: keep it and protect it.",IF($E5>$J5,"Its food cost is above the category average: lower the cost or raise the price.",IF($D5<$H5,"It sells less than its category average: it's a menu and floor problem, not a cost problem.","Its price is below its category average: check it before you touch the recipe.")))),"") -> It meets its category's target: keep it and protect it.
A6: 2 | B6: =IFERROR(IF('Data'!$B6="","",'Data'!$B6),"") -> Heirloom tomato salad with tuna belly and scallions | C6: =IFERROR(IF('Data'!$C6="","",'Data'!$C6),"") -> Starters | D6: =IFERROR(IF('Data'!$D6="","",'Data'!$D6),"") -> 310 | E6: =IFERROR(IF('Data'!$H6="","",'Data'!$H6),"") -> 0.30508475 | F6: =IFERROR(IF('Data'!$F6="","",'Data'!$F6),"") -> 11.8 | G6: =IFERROR(IF(OR($D6="",$E6="",$F6="",$D$33+$D$34+$E6>=1),"",(1-$E6)*$D6*$F6*(1-($D$33+$D$34+$E6))),"") -> 698.83458 | H6: =IFERROR(IF(OR('Data'!$K6="",'Data'!$K6=0),"",'Data'!$J6/'Data'!$K6),"") -> 247.14286 | I6: =IFERROR(IF(OR('Data'!$J6="",'Data'!$J6=0),"",SUMPRODUCT(--('Data'!$C$5:$C$29='Data'!$C6),'Data'!$D$5:$D$29,'Data'!$F$5:$F$29)/'Data'!$J6),"") -> 10.772254 | J6: =IFERROR(IF('Data'!$O6="","",'Data'!$O6),"") -> 0.30714746 | K6: =IFERROR(IF(OR($H6="",$I6="",$J6="",$D$33+$D$34+$J6>=1),"",(1-$J6)*$H6*$I6*(1-($D$33+$D$34+$J6))),"") -> 503.29601 | L6: =IFERROR(IF(OR($G6="",$K6=""),"",IF($G6>=$K6,"Above target","Below target")),"") -> Above target | M6: =IFERROR(IF(OR($G6="",$K6=""),"",$G6-$K6),"") -> 195.53857 | N6: =IFERROR(IF($L6="","",IF($L6="Above target","It meets its category's target: keep it and protect it.",IF($E6>$J6,"Its food cost is above the category average: lower the cost or raise the price.",IF($D6<$H6,"It sells less than its category average: it's a menu and floor problem, not a cost problem.","Its price is below its category average: check it before you touch the recipe.")))),"") -> It meets its category's target: keep it and protect it.
A7: 3 | B7: =IFERROR(IF('Data'!$B7="","",'Data'!$B7),"") -> Garlic shrimp | C7: =IFERROR(IF('Data'!$C7="","",'Data'!$C7),"") -> Starters | D7: =IFERROR(IF('Data'!$D7="","",'Data'!$D7),"") -> 260 | E7: =IFERROR(IF('Data'!$H7="","",'Data'!$H7),"") -> 0.44516129 | F7: =IFERROR(IF('Data'!$F7="","",'Data'!$F7),"") -> 15.5 | G7: =IFERROR(IF(OR($D7="",$E7="",$F7="",$D$33+$D$34+$E7>=1),"",(1-$E7)*$D7*$F7*(1-($D$33+$D$34+$E7))),"") -> 301.49935 | H7: =IFERROR(IF(OR('Data'!$K7="",'Data'!$K7=0),"",'Data'!$J7/'Data'!$K7),"") -> 247.14286 | I7: =IFERROR(IF(OR('Data'!$J7="",'Data'!$J7=0),"",SUMPRODUCT(--('Data'!$C$5:$C$29='Data'!$C7),'Data'!$D$5:$D$29,'Data'!$F$5:$F$29)/'Data'!$J7),"") -> 10.772254 | J7: =IFERROR(IF('Data'!$O7="","",'Data'!$O7),"") -> 0.30714746 | K7: =IFERROR(IF(OR($H7="",$I7="",$J7="",$D$33+$D$34+$J7>=1),"",(1-$J7)*$H7*$I7*(1-($D$33+$D$34+$J7))),"") -> 503.29601 | L7: =IFERROR(IF(OR($G7="",$K7=""),"",IF($G7>=$K7,"Above target","Below target")),"") -> Below target | M7: =IFERROR(IF(OR($G7="",$K7=""),"",$G7-$K7),"") -> -201.79665 | N7: =IFERROR(IF($L7="","",IF($L7="Above target","It meets its category's target: keep it and protect it.",IF($E7>$J7,"Its food cost is above the category average: lower the cost or raise the price.",IF($D7<$H7,"It sells less than its category average: it's a menu and floor problem, not a cost problem.","Its price is below its category average: check it before you touch the recipe.")))),"") -> Its food cost is above the category average: lower the cost or raise the price.
A8: 4 | B8: =IFERROR(IF('Data'!$B8="","",'Data'!$B8),"") -> Broken eggs with potatoes and chistorra sausage | C8: =IFERROR(IF('Data'!$C8="","",'Data'!$C8),"") -> Starters | D8: =IFERROR(IF('Data'!$D8="","",'Data'!$D8),"") -> 380 | E8: =IFERROR(IF('Data'!$H8="","",'Data'!$H8),"") -> 0.24489796 | F8: =IFERROR(IF('Data'!$F8="","",'Data'!$F8),"") -> 9.8 | G8: =IFERROR(IF(OR($D8="",$E8="",$F8="",$D$33+$D$34+$E8>=1),"",(1-$E8)*$D8*$F8*(1-($D$33+$D$34+$E8))),"") -> 942.30694 | H8: =IFERROR(IF(OR('Data'!$K8="",'Data'!$K8=0),"",'Data'!$J8/'Data'!$K8),"") -> 247.14286 | I8: =IFERROR(IF(OR('Data'!$J8="",'Data'!$J8=0),"",SUMPRODUCT(--('Data'!$C$5:$C$29='Data'!$C8),'Data'!$D$5:$D$29,'Data'!$F$5:$F$29)/'Data'!$J8),"") -> 10.772254 | J8: =IFERROR(IF('Data'!$O8="","",'Data'!$O8),"") -> 0.30714746 | K8: =IFERROR(IF(OR($H8="",$I8="",$J8="",$D$33+$D$34+$J8>=1),"",(1-$J8)*$H8*$I8*(1-($D$33+$D$34+$J8))),"") -> 503.29601 | L8: =IFERROR(IF(OR($G8="",$K8=""),"",IF($G8>=$K8,"Above target","Below target")),"") -> Above target | M8: =IFERROR(IF(OR($G8="",$K8=""),"",$G8-$K8),"") -> 439.01093 | N8: =IFERROR(IF($L8="","",IF($L8="Above target","It meets its category's target: keep it and protect it.",IF($E8>$J8,"Its food cost is above the category average: lower the cost or raise the price.",IF($D8<$H8,"It sells less than its category average: it's a menu and floor problem, not a cost problem.","Its price is below its category average: check it before you touch the recipe.")))),"") -> It meets its category's target: keep it and protect it.
A9: 5 | B9: =IFERROR(IF('Data'!$B9="","",'Data'!$B9),"") -> Local cheese board | C9: =IFERROR(IF('Data'!$C9="","",'Data'!$C9),"") -> Starters | D9: =IFERROR(IF('Data'!$D9="","",'Data'!$D9),"") -> 90 | E9: =IFERROR(IF('Data'!$H9="","",'Data'!$H9),"") -> 0.38235294 | F9: =IFERROR(IF('Data'!$F9="","",'Data'!$F9),"") -> 13.6 | G9: =IFERROR(IF(OR($D9="",$E9="",$F9="",$D$33+$D$34+$E9>=1),"",(1-$E9)*$D9*$F9*(1-($D$33+$D$34+$E9))),"") -> 149.42118 | H9: =IFERROR(IF(OR('Data'!$K9="",'Data'!$K9=0),"",'Data'!$J9/'Data'!$K9),"") -> 247.14286 | I9: =IFERROR(IF(OR('Data'!$J9="",'Data'!$J9=0),"",SUMPRODUCT(--('Data'!$C$5:$C$29='Data'!$C9),'Data'!$D$5:$D$29,'Data'!$F$5:$F$29)/'Data'!$J9),"") -> 10.772254 | J9: =IFERROR(IF('Data'!$O9="","",'Data'!$O9),"") -> 0.30714746 | K9: =IFERROR(IF(OR($H9="",$I9="",$J9="",$D$33+$D$34+$J9>=1),"",(1-$J9)*$H9*$I9*(1-($D$33+$D$34+$J9))),"") -> 503.29601 | L9: =IFERROR(IF(OR($G9="",$K9=""),"",IF($G9>=$K9,"Above target","Below target")),"") -> Below target | M9: =IFERROR(IF(OR($G9="",$K9=""),"",$G9-$K9),"") -> -353.87483 | N9: =IFERROR(IF($L9="","",IF($L9="Above target","It meets its category's target: keep it and protect it.",IF($E9>$J9,"Its food cost is above the category average: lower the cost or raise the price.",IF($D9<$H9,"It sells less than its category average: it's a menu and floor problem, not a cost problem.","Its price is below its category average: check it before you touch the recipe.")))),"") -> Its food cost is above the category average: lower the cost or raise the price.
A10: 6 | B10: =IFERROR(IF('Data'!$B10="","",'Data'!$B10),"") -> Confit artichokes with ham | C10: =IFERROR(IF('Data'!$C10="","",'Data'!$C10),"") -> Starters | D10: =IFERROR(IF('Data'!$D10="","",'Data'!$D10),"") -> 120 | E10: =IFERROR(IF('Data'!$H10="","",'Data'!$H10),"") -> 0.28440367 | F10: =IFERROR(IF('Data'!$F10="","",'Data'!$F10),"") -> 10.9 | G10: =IFERROR(IF(OR($D10="",$E10="",$F10="",$D$33+$D$34+$E10>=1),"",(1-$E10)*$D10*$F10*(1-($D$33+$D$34+$E10))),"") -> 276.67817 | H10: =IFERROR(IF(OR('Data'!$K10="",'Data'!$K10=0),"",'Data'!$J10/'Data'!$K10),"") -> 247.14286 | I10: =IFERROR(IF(OR('Data'!$J10="",'Data'!$J10=0),"",SUMPRODUCT(--('Data'!$C$5:$C$29='Data'!$C10),'Data'!$D$5:$D$29,'Data'!$F$5:$F$29)/'Data'!$J10),"") -> 10.772254 | J10: =IFERROR(IF('Data'!$O10="","",'Data'!$O10),"") -> 0.30714746 | K10: =IFERROR(IF(OR($H10="",$I10="",$J10="",$D$33+$D$34+$J10>=1),"",(1-$J10)*$H10*$I10*(1-($D$33+$D$34+$J10))),"") -> 503.29601 | L10: =IFERROR(IF(OR($G10="",$K10=""),"",IF($G10>=$K10,"Above target","Below target")),"") -> Below target | M10: =IFERROR(IF(OR($G10="",$K10=""),"",$G10-$K10),"") -> -226.61784 | N10: =IFERROR(IF($L10="","",IF($L10="Above target","It meets its category's target: keep it and protect it.",IF($E10>$J10,"Its food cost is above the category average: lower the cost or raise the price.",IF($D10<$H10,"It sells less than its category average: it's a menu and floor problem, not a cost problem.","Its price is below its category average: check it before you touch the recipe.")))),"") -> It sells less than its category average: it's a menu and floor problem, not a cost problem.
A11: 7 | B11: =IFERROR(IF('Data'!$B11="","",'Data'!$B11),"") -> Roasted tomato soup with basil | C11: =IFERROR(IF('Data'!$C11="","",'Data'!$C11),"") -> Starters | D11: =IFERROR(IF('Data'!$D11="","",'Data'!$D11),"") -> 150 | E11: =IFERROR(IF('Data'!$H11="","",'Data'!$H11),"") -> 0.16666667 | F11: =IFERROR(IF('Data'!$F11="","",'Data'!$F11),"") -> 7.2 | G11: =IFERROR(IF(OR($D11="",$E11="",$F11="",$D$33+$D$34+$E11>=1),"",(1-$E11)*$D11*$F11*(1-($D$33+$D$34+$E11))),"") -> 372 | H11: =IFERROR(IF(OR('Data'!$K11="",'Data'!$K11=0),"",'Data'!$J11/'Data'!$K11),"") -> 247.14286 | I11: =IFERROR(IF(OR('Data'!$J11="",'Data'!$J11=0),"",SUMPRODUCT(--('Data'!$C$5:$C$29='Data'!$C11),'Data'!$D$5:$D$29,'Data'!$F$5:$F$29)/'Data'!$J11),"") -> 10.772254 | J11: =IFERROR(IF('Data'!$O11="","",'Data'!$O11),"") -> 0.30714746 | K11: =IFERROR(IF(OR($H11="",$I11="",$J11="",$D$33+$D$34+$J11>=1),"",(1-$J11)*$H11*$I11*(1-($D$33+$D$34+$J11))),"") -> 503.29601 | L11: =IFERROR(IF(OR($G11="",$K11=""),"",IF($G11>=$K11,"Above target","Below target")),"") -> Below target | M11: =IFERROR(IF(OR($G11="",$K11=""),"",$G11-$K11),"") -> -131.29601 | N11: =IFERROR(IF($L11="","",IF($L11="Above target","It meets its category's target: keep it and protect it.",IF($E11>$J11,"Its food cost is above the category average: lower the cost or raise the price.",IF($D11<$H11,"It sells less than its category average: it's a menu and floor problem, not a cost problem.","Its price is below its category average: check it before you touch the recipe.")))),"") -> It sells less than its category average: it's a menu and floor problem, not a cost problem.
A12: 8 | B12: =IFERROR(IF('Data'!$B12="","",'Data'!$B12),"") -> Iberico pork tenderloin with sweet potato purée | C12: =IFERROR(IF('Data'!$C12="","",'Data'!$C12),"") -> Mains | D12: =IFERROR(IF('Data'!$D12="","",'Data'!$D12),"") -> 340 | E12: =IFERROR(IF('Data'!$H12="","",'Data'!$H12),"") -> 0.32774566 | F12: =IFERROR(IF('Data'!$F12="","",'Data'!$F12),"") -> 17.3 | G12: =IFERROR(IF(OR($D12="",$E12="",$F12="",$D$33+$D$34+$E12>=1),"",(1-$E12)*$D12*$F12*(1-($D$33+$D$34+$E12))),"") -> 997.46409 | H12: =IFERROR(IF(OR('Data'!$K12="",'Data'!$K12=0),"",'Data'!$J12/'Data'!$K12),"") -> 224.44444 | I12: =IFERROR(IF(OR('Data'!$J12="",'Data'!$J12=0),"",SUMPRODUCT(--('Data'!$C$5:$C$29='Data'!$C12),'Data'!$D$5:$D$29,'Data'!$F$5:$F$29)/'Data'!$J12),"") -> 16.759406 | J12: =IFERROR(IF('Data'!$O12="","",'Data'!$O12),"") -> 0.35587523 | K12: =IFERROR(IF(OR($H12="",$I12="",$J12="",$D$33+$D$34+$J12>=1),"",(1-$J12)*$H12*$I12*(1-($D$33+$D$34+$J12))),"") -> 543.0344 | L12: =IFERROR(IF(OR($G12="",$K12=""),"",IF($G12>=$K12,"Above target","Below target")),"") -> Above target | M12: =IFERROR(IF(OR($G12="",$K12=""),"",$G12-$K12),"") -> 454.42969 | N12: =IFERROR(IF($L12="","",IF($L12="Above target","It meets its category's target: keep it and protect it.",IF($E12>$J12,"Its food cost is above the category average: lower the cost or raise the price.",IF($D12<$H12,"It sells less than its category average: it's a menu and floor problem, not a cost problem.","Its price is below its category average: check it before you touch the recipe.")))),"") -> It meets its category's target: keep it and protect it.
A13: 9 | B13: =IFERROR(IF('Data'!$B13="","",'Data'!$B13),"") -> Confit cod in pil-pil sauce | C13: =IFERROR(IF('Data'!$C13="","",'Data'!$C13),"") -> Mains | D13: =IFERROR(IF('Data'!$D13="","",'Data'!$D13),"") -> 190 | E13: =IFERROR(IF('Data'!$H13="","",'Data'!$H13),"") -> 0.38743455 | F13: =IFERROR(IF('Data'!$F13="","",'Data'!$F13),"") -> 19.1 | G13: =IFERROR(IF(OR($D13="",$E13="",$F13="",$D$33+$D$34+$E13>=1),"",(1-$E13)*$D13*$F13*(1-($D$33+$D$34+$E13))),"") -> 428.07298 | H13: =IFERROR(IF(OR('Data'!$K13="",'Data'!$K13=0),"",'Data'!$J13/'Data'!$K13),"") -> 224.44444 | I13: =IFERROR(IF(OR('Data'!$J13="",'Data'!$J13=0),"",SUMPRODUCT(--('Data'!$C$5:$C$29='Data'!$C13),'Data'!$D$5:$D$29,'Data'!$F$5:$F$29)/'Data'!$J13),"") -> 16.759406 | J13: =IFERROR(IF('Data'!$O13="","",'Data'!$O13),"") -> 0.35587523 | K13: =IFERROR(IF(OR($H13="",$I13="",$J13="",$D$33+$D$34+$J13>=1),"",(1-$J13)*$H13*$I13*(1-($D$33+$D$34+$J13))),"") -> 543.0344 | L13: =IFERROR(IF(OR($G13="",$K13=""),"",IF($G13>=$K13,"Above target","Below target")),"") -> Below target | M13: =IFERROR(IF(OR($G13="",$K13=""),"",$G13-$K13),"") -> -114.96141 | N13: =IFERROR(IF($L13="","",IF($L13="Above target","It meets its category's target: keep it and protect it.",IF($E13>$J13,"Its food cost is above the category average: lower the cost or raise the price.",IF($D13<$H13,"It sells less than its category average: it's a menu and floor problem, not a cost problem.","Its price is below its category average: check it before you touch the recipe.")))),"") -> Its food cost is above the category average: lower the cost or raise the price.
A14: 10 | B14: =IFERROR(IF('Data'!$B14="","",'Data'!$B14),"") -> Dry-aged beef burger with fries | C14: =IFERROR(IF('Data'!$C14="","",'Data'!$C14),"") -> Mains | D14: =IFERROR(IF('Data'!$D14="","",'Data'!$D14),"") -> 460 | E14: =IFERROR(IF('Data'!$H14="","",'Data'!$H14),"") -> 0.31617647 | F14: =IFERROR(IF('Data'!$F14="","",'Data'!$F14),"") -> 13.6 | G14: =IFERROR(IF(OR($D14="",$E14="",$F14="",$D$33+$D$34+$E14>=1),"",(1-$E14)*$D14*$F14*(1-($D$33+$D$34+$E14))),"") -> 1128.6371 | H14: =IFERROR(IF(OR('Data'!$K14="",'Data'!$K14=0),"",'Data'!$J14/'Data'!$K14),"") -> 224.44444 | I14: =IFERROR(IF(OR('Data'!$J14="",'Data'!$J14=0),"",SUMPRODUCT(--('Data'!$C$5:$C$29='Data'!$C14),'Data'!$D$5:$D$29,'Data'!$F$5:$F$29)/'Data'!$J14),"") -> 16.759406 | J14: =IFERROR(IF('Data'!$O14="","",'Data'!$O14),"") -> 0.35587523 | K14: =IFERROR(IF(OR($H14="",$I14="",$J14="",$D$33+$D$34+$J14>=1),"",(1-$J14)*$H14*$I14*(1-($D$33+$D$34+$J14))),"") -> 543.0344 | L14: =IFERROR(IF(OR($G14="",$K14=""),"",IF($G14>=$K14,"Above target","Below target")),"") -> Above target | M14: =IFERROR(IF(OR($G14="",$K14=""),"",$G14-$K14),"") -> 585.60266 | N14: =IFERROR(IF($L14="","",IF($L14="Above target","It meets its category's target: keep it and protect it.",IF($E14>$J14,"Its food cost is above the category average: lower the cost or raise the price.",IF($D14<$H14,"It sells less than its category average: it's a menu and floor problem, not a cost problem.","Its price is below its category average: check it before you touch the recipe.")))),"") -> It meets its category's target: keep it and protect it.
A15: 11 | B15: =IFERROR(IF('Data'!$B15="","",'Data'!$B15),"") -> Creamy rice with Iberico pork secreto and mushrooms | C15: =IFERROR(IF('Data'!$C15="","",'Data'!$C15),"") -> Mains | D15: =IFERROR(IF('Data'!$D15="","",'Data'!$D15),"") -> 270 | E15: =IFERROR(IF('Data'!$H15="","",'Data'!$H15),"") -> 0.37804878 | F15: =IFERROR(IF('Data'!$F15="","",'Data'!$F15),"") -> 16.4 | G15: =IFERROR(IF(OR($D15="",$E15="",$F15="",$D$33+$D$34+$E15>=1),"",(1-$E15)*$D15*$F15*(1-($D$33+$D$34+$E15))),"") -> 556.17366 | H15: =IFERROR(IF(OR('Data'!$K15="",'Data'!$K15=0),"",'Data'!$J15/'Data'!$K15),"") -> 224.44444 | I15: =IFERROR(IF(OR('Data'!$J15="",'Data'!$J15=0),"",SUMPRODUCT(--('Data'!$C$5:$C$29='Data'!$C15),'Data'!$D$5:$D$29,'Data'!$F$5:$F$29)/'Data'!$J15),"") -> 16.759406 | J15: =IFERROR(IF('Data'!$O15="","",'Data'!$O15),"") -> 0.35587523 | K15: =IFERROR(IF(OR($H15="",$I15="",$J15="",$D$33+$D$34+$J15>=1),"",(1-$J15)*$H15*$I15*(1-($D$33+$D$34+$J15))),"") -> 543.0344 | L15: =IFERROR(IF(OR($G15="",$K15=""),"",IF($G15>=$K15,"Above target","Below target")),"") -> Above target | M15: =IFERROR(IF(OR($G15="",$K15=""),"",$G15-$K15),"") -> 13.13926 | N15: =IFERROR(IF($L15="","",IF($L15="Above target","It meets its category's target: keep it and protect it.",IF($E15>$J15,"Its food cost is above the category average: lower the cost or raise the price.",IF($D15<$H15,"It sells less than its category average: it's a menu and floor problem, not a cost problem.","Its price is below its category average: check it before you touch the recipe.")))),"") -> It meets its category's target: keep it and protect it.
A16: 12 | B16: =IFERROR(IF('Data'!$B16="","",'Data'!$B16),"") -> Dry-aged bone-in ribeye (17.64 oz) | C16: =IFERROR(IF('Data'!$C16="","",'Data'!$C16),"") -> Mains | D16: =IFERROR(IF('Data'!$D16="","",'Data'!$D16),"") -> 110 | E16: =IFERROR(IF('Data'!$H16="","",'Data'!$H16),"") -> 0.45259939 | F16: =IFERROR(IF('Data'!$F16="","",'Data'!$F16),"") -> 32.7 | G16: =IFERROR(IF(OR($D16="",$E16="",$F16="",$D$33+$D$34+$E16>=1),"",(1-$E16)*$D16*$F16*(1-($D$33+$D$34+$E16))),"") -> 250.8518 | H16: =IFERROR(IF(OR('Data'!$K16="",'Data'!$K16=0),"",'Data'!$J16/'Data'!$K16),"") -> 224.44444 | I16: =IFERROR(IF(OR('Data'!$J16="",'Data'!$J16=0),"",SUMPRODUCT(--('Data'!$C$5:$C$29='Data'!$C16),'Data'!$D$5:$D$29,'Data'!$F$5:$F$29)/'Data'!$J16),"") -> 16.759406 | J16: =IFERROR(IF('Data'!$O16="","",'Data'!$O16),"") -> 0.35587523 | K16: =IFERROR(IF(OR($H16="",$I16="",$J16="",$D$33+$D$34+$J16>=1),"",(1-$J16)*$H16*$I16*(1-($D$33+$D$34+$J16))),"") -> 543.0344 | L16: =IFERROR(IF(OR($G16="",$K16=""),"",IF($G16>=$K16,"Above target","Below target")),"") -> Below target | M16: =IFERROR(IF(OR($G16="",$K16=""),"",$G16-$K16),"") -> -292.18259 | N16: =IFERROR(IF($L16="","",IF($L16="Above target","It meets its category's target: keep it and protect it.",IF($E16>$J16,"Its food cost is above the category average: lower the cost or raise the price.",IF($D16<$H16,"It sells less than its category average: it's a menu and floor problem, not a cost problem.","Its price is below its category average: check it before you touch the recipe.")))),"") -> Its food cost is above the category average: lower the cost or raise the price.
... A29: 25 | B29: =IFERROR(IF('Data'!$B29="","",'Data'!$B29),"") | C29: =IFERROR(IF('Data'!$C29="","",'Data'!$C29),"") | D29: =IFERROR(IF('Data'!$D29="","",'Data'!$D29),"") | E29: =IFERROR(IF('Data'!$H29="","",'Data'!$H29),"") | F29: =IFERROR(IF('Data'!$F29="","",'Data'!$F29),"") | G29: =IFERROR(IF(OR($D29="",$E29="",$F29="",$D$33+$D$34+$E29>=1),"",(1-$E29)*$D29*$F29*(1-($D$33+$D$34+$E29))),"") | H29: =IFERROR(IF(OR('Data'!$K29="",'Data'!$K29=0),"",'Data'!$J29/'Data'!$K29),"") | I29: =IFERROR(IF(OR('Data'!$J29="",'Data'!$J29=0),"",SUMPRODUCT(--('Data'!$C$5:$C$29='Data'!$C29),'Data'!$D$5:$D$29,'Data'!$F$5:$F$29)/'Data'!$J29),"") | J29: =IFERROR(IF('Data'!$O29="","",'Data'!$O29),"") | K29: =IFERROR(IF(OR($H29="",$I29="",$J29="",$D$33+$D$34+$J29>=1),"",(1-$J29)*$H29*$I29*(1-($D$33+$D$34+$J29))),"") | L29: =IFERROR(IF(OR($G29="",$K29=""),"",IF($G29>=$K29,"Above target","Below target")),"") | M29: =IFERROR(IF(OR($G29="",$K29=""),"",$G29-$K29),"") | N29: =IFERROR(IF($L29="","",IF($L29="Above target","It meets its category's target: keep it and protect it.",IF($E29>$J29,"Its food cost is above the category average: lower the cost or raise the price.",IF($D29<$H29,"It sells less than its category average: it's a menu and floor problem, not a cost problem.","Its price is below its category average: check it before you touch the recipe.")))),"")
A32: INPUTS AND SUMMARY — calculated by the workbook
B33: Labor cost as % of sales | D33: 0.32 | F33: Labor including employer payroll taxes and benefits, over net sales. 32% is the midpoint of the commonly cited 30-35% range for full service; it's lower for counter or self-service. Replace it with yours.
B34: Other variable costs as % of sales | D34: 0.1 | F34: What moves with sales and is neither product nor labor: kitchen energy, consumables, and card and delivery platform fees. Replace it with yours.
B35: Average menu Goal Value (index) | D35: =IFERROR(AVERAGE($G$5:$G$29),"") -> 520.55159
B36: Dishes above their category target | D36: =COUNTIF($L$5:$L$29,"Above target") -> 9
B37: Dishes below their category target | D37: =COUNTIF($L$5:$L$29,"Below target") -> 11

Sheet Comparison
A1: Comparison — where the four methods disagree
A2: AI Chef Pro · aichef.pro — Food Cost + Menu Engineering Guide
E3: Agreement doesn't give more certainty: it only says the dish looks the same from any angle. The value is in the rows that disagree.
A4: # | B4: Dish | C4: Category | D4: Kasavana & Smith | E4: Miller | F4: Pavesic | G4: Goal Value | H4: Readings off the best category | I4: Diagnosis | J4: Suggested decision
A5: 1 | B5: =IFERROR(IF('Data'!$B5="","",'Data'!$B5),"") -> Iberico ham croquettes (6 pcs) | C5: =IFERROR(IF('Data'!$C5="","",'Data'!$C5),"") -> Starters | D5: =IFERROR(IF('Kasavana-Smith'!$K5="","",'Kasavana-Smith'!$K5),"") -> Plowhorse | E5: =IFERROR(IF('Miller'!$K5="","",'Miller'!$K5),"") -> Winner | F5: =IFERROR(IF('Pavesic'!$K5="","",'Pavesic'!$K5),"") -> Prime | G5: =IFERROR(IF('Goal Value'!$L5="","",'Goal Value'!$L5),"") -> Above target | H5: =IFERROR(IF($B5="","",IF($D5="Star",0,1)+IF($E5="Winner",0,1)+IF($F5="Prime",0,1)+IF($G5="Above target",0,1)),"") -> 1 | I5: =IFERROR(IF($B5="","",IF($H5=0,"All four readings agree on the best: keep it, feature it on the menu and protect the recipe and the supplier.",IF(AND($D5="Dog",$E5="Loser",$F5="Problem"),"Rarely ordered, high food cost and little margin to the total: a candidate to remove or to rework from the ground up.",IF(AND($D5="Plowhorse",$E5="Winner"),"Popular with a low margin: raise the price or lower the cost.",IF(AND($D5="Plowhorse",$E5="Loser"),"Popular but expensive to produce and short on margin: rework the recipe before you touch the price.",IF(AND('Data'!$G5>='Data'!$N5,'Data'!$H5>'Data'!$O5),"High CM with a poor food cost: protect the margin in dollars, review the price, don't remove it.",IF(AND($D5="Puzzle",$E5="Winner"),"Profitable with a healthy food cost, but rarely ordered: it's a menu problem, not a kitchen one. Rename it, move it up or have the floor staff suggest it.",IF($F5="Sleeper","Healthy food cost but little margin to the total: give it visibility before you remove it.",IF(AND($G5="Below target",$D5="Star"),"It sells and leaves margin, but falls below its category's Goal Value: little room to spare, review the price.",IF($D5="Dog","Rarely ordered: before removing it, check whether it's seasonal or goes with another dish that does sell.","The readings disagree: each method measures two of the three variables (popularity, margin in dollars and food cost). Decide with the one that hurts most this month.")))))))))),"") -> Popular with a low margin: raise the price or lower the cost. | J5: =IFERROR(IF($B5="","",IF($H5=0,"Keep",IF(AND($D5="Dog",$E5="Loser"),"Remove",IF($D5="Plowhorse","Reprice",IF($D5="Puzzle","Redesign",IF($F5="Problem","Reformulate","Review")))))),"") -> Reprice
A6: 2 | B6: =IFERROR(IF('Data'!$B6="","",'Data'!$B6),"") -> Heirloom tomato salad with tuna belly and scallions | C6: =IFERROR(IF('Data'!$C6="","",'Data'!$C6),"") -> Starters | D6: =IFERROR(IF('Kasavana-Smith'!$K6="","",'Kasavana-Smith'!$K6),"") -> Star | E6: =IFERROR(IF('Miller'!$K6="","",'Miller'!$K6),"") -> Winner | F6: =IFERROR(IF('Pavesic'!$K6="","",'Pavesic'!$K6),"") -> Prime | G6: =IFERROR(IF('Goal Value'!$L6="","",'Goal Value'!$L6),"") -> Above target | H6: =IFERROR(IF($B6="","",IF($D6="Star",0,1)+IF($E6="Winner",0,1)+IF($F6="Prime",0,1)+IF($G6="Above target",0,1)),"") -> 0 | I6: =IFERROR(IF($B6="","",IF($H6=0,"All four readings agree on the best: keep it, feature it on the menu and protect the recipe and the supplier.",IF(AND($D6="Dog",$E6="Loser",$F6="Problem"),"Rarely ordered, high food cost and little margin to the total: a candidate to remove or to rework from the ground up.",IF(AND($D6="Plowhorse",$E6="Winner"),"Popular with a low margin: raise the price or lower the cost.",IF(AND($D6="Plowhorse",$E6="Loser"),"Popular but expensive to produce and short on margin: rework the recipe before you touch the price.",IF(AND('Data'!$G6>='Data'!$N6,'Data'!$H6>'Data'!$O6),"High CM with a poor food cost: protect the margin in dollars, review the price, don't remove it.",IF(AND($D6="Puzzle",$E6="Winner"),"Profitable with a healthy food cost, but rarely ordered: it's a menu problem, not a kitchen one. Rename it, move it up or have the floor staff suggest it.",IF($F6="Sleeper","Healthy food cost but little margin to the total: give it visibility before you remove it.",IF(AND($G6="Below target",$D6="Star"),"It sells and leaves margin, but falls below its category's Goal Value: little room to spare, review the price.",IF($D6="Dog","Rarely ordered: before removing it, check whether it's seasonal or goes with another dish that does sell.","The readings disagree: each method measures two of the three variables (popularity, margin in dollars and food cost). Decide with the one that hurts most this month.")))))))))),"") -> All four readings agree on the best: keep it, feature it on the menu and protect the recipe and the supplier. | J6: =IFERROR(IF($B6="","",IF($H6=0,"Keep",IF(AND($D6="Dog",$E6="Loser"),"Remove",IF($D6="Plowhorse","Reprice",IF($D6="Puzzle","Redesign",IF($F6="Problem","Reformulate","Review")))))),"") -> Keep
A7: 3 | B7: =IFERROR(IF('Data'!$B7="","",'Data'!$B7),"") -> Garlic shrimp | C7: =IFERROR(IF('Data'!$C7="","",'Data'!$C7),"") -> Starters | D7: =IFERROR(IF('Kasavana-Smith'!$K7="","",'Kasavana-Smith'!$K7),"") -> Star | E7: =IFERROR(IF('Miller'!$K7="","",'Miller'!$K7),"") -> Marginal | F7: =IFERROR(IF('Pavesic'!$K7="","",'Pavesic'!$K7),"") -> Standard | G7: =IFERROR(IF('Goal Value'!$L7="","",'Goal Value'!$L7),"") -> Below target | H7: =IFERROR(IF($B7="","",IF($D7="Star",0,1)+IF($E7="Winner",0,1)+IF($F7="Prime",0,1)+IF($G7="Above target",0,1)),"") -> 3 | I7: =IFERROR(IF($B7="","",IF($H7=0,"All four readings agree on the best: keep it, feature it on the menu and protect the recipe and the supplier.",IF(AND($D7="Dog",$E7="Loser",$F7="Problem"),"Rarely ordered, high food cost and little margin to the total: a candidate to remove or to rework from the ground up.",IF(AND($D7="Plowhorse",$E7="Winner"),"Popular with a low margin: raise the price or lower the cost.",IF(AND($D7="Plowhorse",$E7="Loser"),"Popular but expensive to produce and short on margin: rework the recipe before you touch the price.",IF(AND('Data'!$G7>='Data'!$N7,'Data'!$H7>'Data'!$O7),"High CM with a poor food cost: protect the margin in dollars, review the price, don't remove it.",IF(AND($D7="Puzzle",$E7="Winner"),"Profitable with a healthy food cost, but rarely ordered: it's a menu problem, not a kitchen one. Rename it, move it up or have the floor staff suggest it.",IF($F7="Sleeper","Healthy food cost but little margin to the total: give it visibility before you remove it.",IF(AND($G7="Below target",$D7="Star"),"It sells and leaves margin, but falls below its category's Goal Value: little room to spare, review the price.",IF($D7="Dog","Rarely ordered: before removing it, check whether it's seasonal or goes with another dish that does sell.","The readings disagree: each method measures two of the three variables (popularity, margin in dollars and food cost). Decide with the one that hurts most this month.")))))))))),"") -> High CM with a poor food cost: protect the margin in dollars, review the price, don't remove it. | J7: =IFERROR(IF($B7="","",IF($H7=0,"Keep",IF(AND($D7="Dog",$E7="Loser"),"Remove",IF($D7="Plowhorse","Reprice",IF($D7="Puzzle","Redesign",IF($F7="Problem","Reformulate","Review")))))),"") -> Review
A8: 4 | B8: =IFERROR(IF('Data'!$B8="","",'Data'!$B8),"") -> Broken eggs with potatoes and chistorra sausage | C8: =IFERROR(IF('Data'!$C8="","",'Data'!$C8),"") -> Starters | D8: =IFERROR(IF('Kasavana-Smith'!$K8="","",'Kasavana-Smith'!$K8),"") -> Plowhorse | E8: =IFERROR(IF('Miller'!$K8="","",'Miller'!$K8),"") -> Winner | F8: =IFERROR(IF('Pavesic'!$K8="","",'Pavesic'!$K8),"") -> Prime | G8: =IFERROR(IF('Goal Value'!$L8="","",'Goal Value'!$L8),"") -> Above target | H8: =IFERROR(IF($B8="","",IF($D8="Star",0,1)+IF($E8="Winner",0,1)+IF($F8="Prime",0,1)+IF($G8="Above target",0,1)),"") -> 1 | I8: =IFERROR(IF($B8="","",IF($H8=0,"All four readings agree on the best: keep it, feature it on the menu and protect the recipe and the supplier.",IF(AND($D8="Dog",$E8="Loser",$F8="Problem"),"Rarely ordered, high food cost and little margin to the total: a candidate to remove or to rework from the ground up.",IF(AND($D8="Plowhorse",$E8="Winner"),"Popular with a low margin: raise the price or lower the cost.",IF(AND($D8="Plowhorse",$E8="Loser"),"Popular but expensive to produce and short on margin: rework the recipe before you touch the price.",IF(AND('Data'!$G8>='Data'!$N8,'Data'!$H8>'Data'!$O8),"High CM with a poor food cost: protect the margin in dollars, review the price, don't remove it.",IF(AND($D8="Puzzle",$E8="Winner"),"Profitable with a healthy food cost, but rarely ordered: it's a menu problem, not a kitchen one. Rename it, move it up or have the floor staff suggest it.",IF($F8="Sleeper","Healthy food cost but little margin to the total: give it visibility before you remove it.",IF(AND($G8="Below target",$D8="Star"),"It sells and leaves margin, but falls below its category's Goal Value: little room to spare, review the price.",IF($D8="Dog","Rarely ordered: before removing it, check whether it's seasonal or goes with another dish that does sell.","The readings disagree: each method measures two of the three variables (popularity, margin in dollars and food cost). Decide with the one that hurts most this month.")))))))))),"") -> Popular with a low margin: raise the price or lower the cost. | J8: =IFERROR(IF($B8="","",IF($H8=0,"Keep",IF(AND($D8="Dog",$E8="Loser"),"Remove",IF($D8="Plowhorse","Reprice",IF($D8="Puzzle","Redesign",IF($F8="Problem","Reformulate","Review")))))),"") -> Reprice
A9: 5 | B9: =IFERROR(IF('Data'!$B9="","",'Data'!$B9),"") -> Local cheese board | C9: =IFERROR(IF('Data'!$C9="","",'Data'!$C9),"") -> Starters | D9: =IFERROR(IF('Kasavana-Smith'!$K9="","",'Kasavana-Smith'!$K9),"") -> Puzzle | E9: =IFERROR(IF('Miller'!$K9="","",'Miller'!$K9),"") -> Loser | F9: =IFERROR(IF('Pavesic'!$K9="","",'Pavesic'!$K9),"") -> Problem | G9: =IFERROR(IF('Goal Value'!$L9="","",'Goal Value'!$L9),"") -> Below target | H9: =IFERROR(IF($B9="","",IF($D9="Star",0,1)+IF($E9="Winner",0,1)+IF($F9="Prime",0,1)+IF($G9="Above target",0,1)),"") -> 4 | I9: =IFERROR(IF($B9="","",IF($H9=0,"All four readings agree on the best: keep it, feature it on the menu and protect the recipe and the supplier.",IF(AND($D9="Dog",$E9="Loser",$F9="Problem"),"Rarely ordered, high food cost and little margin to the total: a candidate to remove or to rework from the ground up.",IF(AND($D9="Plowhorse",$E9="Winner"),"Popular with a low margin: raise the price or lower the cost.",IF(AND($D9="Plowhorse",$E9="Loser"),"Popular but expensive to produce and short on margin: rework the recipe before you touch the price.",IF(AND('Data'!$G9>='Data'!$N9,'Data'!$H9>'Data'!$O9),"High CM with a poor food cost: protect the margin in dollars, review the price, don't remove it.",IF(AND($D9="Puzzle",$E9="Winner"),"Profitable with a healthy food cost, but rarely ordered: it's a menu problem, not a kitchen one. Rename it, move it up or have the floor staff suggest it.",IF($F9="Sleeper","Healthy food cost but little margin to the total: give it visibility before you remove it.",IF(AND($G9="Below target",$D9="Star"),"It sells and leaves margin, but falls below its category's Goal Value: little room to spare, review the price.",IF($D9="Dog","Rarely ordered: before removing it, check whether it's seasonal or goes with another dish that does sell.","The readings disagree: each method measures two of the three variables (popularity, margin in dollars and food cost). Decide with the one that hurts most this month.")))))))))),"") -> High CM with a poor food cost: protect the margin in dollars, review the price, don't remove it. | J9: =IFERROR(IF($B9="","",IF($H9=0,"Keep",IF(AND($D9="Dog",$E9="Loser"),"Remove",IF($D9="Plowhorse","Reprice",IF($D9="Puzzle","Redesign",IF($F9="Problem","Reformulate","Review")))))),"") -> Redesign
A10: 6 | B10: =IFERROR(IF('Data'!$B10="","",'Data'!$B10),"") -> Confit artichokes with ham | C10: =IFERROR(IF('Data'!$C10="","",'Data'!$C10),"") -> Starters | D10: =IFERROR(IF('Kasavana-Smith'!$K10="","",'Kasavana-Smith'!$K10),"") -> Puzzle | E10: =IFERROR(IF('Miller'!$K10="","",'Miller'!$K10),"") -> Marginal | F10: =IFERROR(IF('Pavesic'!$K10="","",'Pavesic'!$K10),"") -> Sleeper | G10: =IFERROR(IF('Goal Value'!$L10="","",'Goal Value'!$L10),"") -> Below target | H10: =IFERROR(IF($B10="","",IF($D10="Star",0,1)+IF($E10="Winner",0,1)+IF($F10="Prime",0,1)+IF($G10="Above target",0,1)),"") -> 4 | I10: =IFERROR(IF($B10="","",IF($H10=0,"All four readings agree on the best: keep it, feature it on the menu and protect the recipe and the supplier.",IF(AND($D10="Dog",$E10="Loser",$F10="Problem"),"Rarely ordered, high food cost and little margin to the total: a candidate to remove or to rework from the ground up.",IF(AND($D10="Plowhorse",$E10="Winner"),"Popular with a low margin: raise the price or lower the cost.",IF(AND($D10="Plowhorse",$E10="Loser"),"Popular but expensive to produce and short on margin: rework the recipe before you touch the price.",IF(AND('Data'!$G10>='Data'!$N10,'Data'!$H10>'Data'!$O10),"High CM with a poor food cost: protect the margin in dollars, review the price, don't remove it.",IF(AND($D10="Puzzle",$E10="Winner"),"Profitable with a healthy food cost, but rarely ordered: it's a menu problem, not a kitchen one. Rename it, move it up or have the floor staff suggest it.",IF($F10="Sleeper","Healthy food cost but little margin to the total: give it visibility before you remove it.",IF(AND($G10="Below target",$D10="Star"),"It sells and leaves margin, but falls below its category's Goal Value: little room to spare, review the price.",IF($D10="Dog","Rarely ordered: before removing it, check whether it's seasonal or goes with another dish that does sell.","The readings disagree: each method measures two of the three variables (popularity, margin in dollars and food cost). Decide with the one that hurts most this month.")))))))))),"") -> Healthy food cost but little margin to the total: give it visibility before you remove it. | J10: =IFERROR(IF($B10="","",IF($H10=0,"Keep",IF(AND($D10="Dog",$E10="Loser"),"Remove",IF($D10="Plowhorse","Reprice",IF($D10="Puzzle","Redesign",IF($F10="Problem","Reformulate","Review")))))),"") -> Redesign
A11: 7 | B11: =IFERROR(IF('Data'!$B11="","",'Data'!$B11),"") -> Roasted tomato soup with basil | C11: =IFERROR(IF('Data'!$C11="","",'Data'!$C11),"") -> Starters | D11: =IFERROR(IF('Kasavana-Smith'!$K11="","",'Kasavana-Smith'!$K11),"") -> Dog | E11: =IFERROR(IF('Miller'!$K11="","",'Miller'!$K11),"") -> Marginal | F11: =IFERROR(IF('Pavesic'!$K11="","",'Pavesic'!$K11),"") -> Sleeper | G11: =IFERROR(IF('Goal Value'!$L11="","",'Goal Value'!$L11),"") -> Below target | H11: =IFERROR(IF($B11="","",IF($D11="Star",0,1)+IF($E11="Winner",0,1)+IF($F11="Prime",0,1)+IF($G11="Above target",0,1)),"") -> 4 | I11: =IFERROR(IF($B11="","",IF($H11=0,"All four readings agree on the best: keep it, feature it on the menu and protect the recipe and the supplier.",IF(AND($D11="Dog",$E11="Loser",$F11="Problem"),"Rarely ordered, high food cost and little margin to the total: a candidate to remove or to rework from the ground up.",IF(AND($D11="Plowhorse",$E11="Winner"),"Popular with a low margin: raise the price or lower the cost.",IF(AND($D11="Plowhorse",$E11="Loser"),"Popular but expensive to produce and short on margin: rework the recipe before you touch the price.",IF(AND('Data'!$G11>='Data'!$N11,'Data'!$H11>'Data'!$O11),"High CM with a poor food cost: protect the margin in dollars, review the price, don't remove it.",IF(AND($D11="Puzzle",$E11="Winner"),"Profitable with a healthy food cost, but rarely ordered: it's a menu problem, not a kitchen one. Rename it, move it up or have the floor staff suggest it.",IF($F11="Sleeper","Healthy food cost but little margin to the total: give it visibility before you remove it.",IF(AND($G11="Below target",$D11="Star"),"It sells and leaves margin, but falls below its category's Goal Value: little room to spare, review the price.",IF($D11="Dog","Rarely ordered: before removing it, check whether it's seasonal or goes with another dish that does sell.","The readings disagree: each method measures two of the three variables (popularity, margin in dollars and food cost). Decide with the one that hurts most this month.")))))))))),"") -> Healthy food cost but little margin to the total: give it visibility before you remove it. | J11: =IFERROR(IF($B11="","",IF($H11=0,"Keep",IF(AND($D11="Dog",$E11="Loser"),"Remove",IF($D11="Plowhorse","Reprice",IF($D11="Puzzle","Redesign",IF($F11="Problem","Reformulate","Review")))))),"") -> Review
A12: 8 | B12: =IFERROR(IF('Data'!$B12="","",'Data'!$B12),"") -> Iberico pork tenderloin with sweet potato purée | C12: =IFERROR(IF('Data'!$C12="","",'Data'!$C12),"") -> Mains | D12: =IFERROR(IF('Kasavana-Smith'!$K12="","",'Kasavana-Smith'!$K12),"") -> Star | E12: =IFERROR(IF('Miller'!$K12="","",'Miller'!$K12),"") -> Winner | F12: =IFERROR(IF('Pavesic'!$K12="","",'Pavesic'!$K12),"") -> Prime | G12: =IFERROR(IF('Goal Value'!$L12="","",'Goal Value'!$L12),"") -> Above target | H12: =IFERROR(IF($B12="","",IF($D12="Star",0,1)+IF($E12="Winner",0,1)+IF($F12="Prime",0,1)+IF($G12="Above target",0,1)),"") -> 0 | I12: =IFERROR(IF($B12="","",IF($H12=0,"All four readings agree on the best: keep it, feature it on the menu and protect the recipe and the supplier.",IF(AND($D12="Dog",$E12="Loser",$F12="Problem"),"Rarely ordered, high food cost and little margin to the total: a candidate to remove or to rework from the ground up.",IF(AND($D12="Plowhorse",$E12="Winner"),"Popular with a low margin: raise the price or lower the cost.",IF(AND($D12="Plowhorse",$E12="Loser"),"Popular but expensive to produce and short on margin: rework the recipe before you touch the price.",IF(AND('Data'!$G12>='Data'!$N12,'Data'!$H12>'Data'!$O12),"High CM with a poor food cost: protect the margin in dollars, review the price, don't remove it.",IF(AND($D12="Puzzle",$E12="Winner"),"Profitable with a healthy food cost, but rarely ordered: it's a menu problem, not a kitchen one. Rename it, move it up or have the floor staff suggest it.",IF($F12="Sleeper","Healthy food cost but little margin to the total: give it visibility before you remove it.",IF(AND($G12="Below target",$D12="Star"),"It sells and leaves margin, but falls below its category's Goal Value: little room to spare, review the price.",IF($D12="Dog","Rarely ordered: before removing it, check whether it's seasonal or goes with another dish that does sell.","The readings disagree: each method measures two of the three variables (popularity, margin in dollars and food cost). Decide with the one that hurts most this month.")))))))))),"") -> All four readings agree on the best: keep it, feature it on the menu and protect the recipe and the supplier. | J12: =IFERROR(IF($B12="","",IF($H12=0,"Keep",IF(AND($D12="Dog",$E12="Loser"),"Remove",IF($D12="Plowhorse","Reprice",IF($D12="Puzzle","Redesign",IF($F12="Problem","Reformulate","Review")))))),"") -> Keep
A13: 9 | B13: =IFERROR(IF('Data'!$B13="","",'Data'!$B13),"") -> Confit cod in pil-pil sauce | C13: =IFERROR(IF('Data'!$C13="","",'Data'!$C13),"") -> Mains | D13: =IFERROR(IF('Kasavana-Smith'!$K13="","",'Kasavana-Smith'!$K13),"") -> Star | E13: =IFERROR(IF('Miller'!$K13="","",'Miller'!$K13),"") -> Marginal | F13: =IFERROR(IF('Pavesic'!$K13="","",'Pavesic'!$K13),"") -> Problem | G13: =IFERROR(IF('Goal Value'!$L13="","",'Goal Value'!$L13),"") -> Below target | H13: =IFERROR(IF($B13="","",IF($D13="Star",0,1)+IF($E13="Winner",0,1)+IF($F13="Prime",0,1)+IF($G13="Above target",0,1)),"") -> 3 | I13: =IFERROR(IF($B13="","",IF($H13=0,"All four readings agree on the best: keep it, feature it on the menu and protect the recipe and the supplier.",IF(AND($D13="Dog",$E13="Loser",$F13="Problem"),"Rarely ordered, high food cost and little margin to the total: a candidate to remove or to rework from the ground up.",IF(AND($D13="Plowhorse",$E13="Winner"),"Popular with a low margin: raise the price or lower the cost.",IF(AND($D13="Plowhorse",$E13="Loser"),"Popular but expensive to produce and short on margin: rework the recipe before you touch the price.",IF(AND('Data'!$G13>='Data'!$N13,'Data'!$H13>'Data'!$O13),"High CM with a poor food cost: protect the margin in dollars, review the price, don't remove it.",IF(AND($D13="Puzzle",$E13="Winner"),"Profitable with a healthy food cost, but rarely ordered: it's a menu problem, not a kitchen one. Rename it, move it up or have the floor staff suggest it.",IF($F13="Sleeper","Healthy food cost but little margin to the total: give it visibility before you remove it.",IF(AND($G13="Below target",$D13="Star"),"It sells and leaves margin, but falls below its category's Goal Value: little room to spare, review the price.",IF($D13="Dog","Rarely ordered: before removing it, check whether it's seasonal or goes with another dish that does sell.","The readings disagree: each method measures two of the three variables (popularity, margin in dollars and food cost). Decide with the one that hurts most this month.")))))))))),"") -> High CM with a poor food cost: protect the margin in dollars, review the price, don't remove it. | J13: =IFERROR(IF($B13="","",IF($H13=0,"Keep",IF(AND($D13="Dog",$E13="Loser"),"Remove",IF($D13="Plowhorse","Reprice",IF($D13="Puzzle","Redesign",IF($F13="Problem","Reformulate","Review")))))),"") -> Reformulate
A14: 10 | B14: =IFERROR(IF('Data'!$B14="","",'Data'!$B14),"") -> Dry-aged beef burger with fries | C14: =IFERROR(IF('Data'!$C14="","",'Data'!$C14),"") -> Mains | D14: =IFERROR(IF('Kasavana-Smith'!$K14="","",'Kasavana-Smith'!$K14),"") -> Plowhorse | E14: =IFERROR(IF('Miller'!$K14="","",'Miller'!$K14),"") -> Winner | F14: =IFERROR(IF('Pavesic'!$K14="","",'Pavesic'!$K14),"") -> Prime | G14: =IFERROR(IF('Goal Value'!$L14="","",'Goal Value'!$L14),"") -> Above target | H14: =IFERROR(IF($B14="","",IF($D14="Star",0,1)+IF($E14="Winner",0,1)+IF($F14="Prime",0,1)+IF($G14="Above target",0,1)),"") -> 1 | I14: =IFERROR(IF($B14="","",IF($H14=0,"All four readings agree on the best: keep it, feature it on the menu and protect the recipe and the supplier.",IF(AND($D14="Dog",$E14="Loser",$F14="Problem"),"Rarely ordered, high food cost and little margin to the total: a candidate to remove or to rework from the ground up.",IF(AND($D14="Plowhorse",$E14="Winner"),"Popular with a low margin: raise the price or lower the cost.",IF(AND($D14="Plowhorse",$E14="Loser"),"Popular but expensive to produce and short on margin: rework the recipe before you touch the price.",IF(AND('Data'!$G14>='Data'!$N14,'Data'!$H14>'Data'!$O14),"High CM with a poor food cost: protect the margin in dollars, review the price, don't remove it.",IF(AND($D14="Puzzle",$E14="Winner"),"Profitable with a healthy food cost, but rarely ordered: it's a menu problem, not a kitchen one. Rename it, move it up or have the floor staff suggest it.",IF($F14="Sleeper","Healthy food cost but little margin to the total: give it visibility before you remove it.",IF(AND($G14="Below target",$D14="Star"),"It sells and leaves margin, but falls below its category's Goal Value: little room to spare, review the price.",IF($D14="Dog","Rarely ordered: before removing it, check whether it's seasonal or goes with another dish that does sell.","The readings disagree: each method measures two of the three variables (popularity, margin in dollars and food cost). Decide with the one that hurts most this month.")))))))))),"") -> Popular with a low margin: raise the price or lower the cost. | J14: =IFERROR(IF($B14="","",IF($H14=0,"Keep",IF(AND($D14="Dog",$E14="Loser"),"Remove",IF($D14="Plowhorse","Reprice",IF($D14="Puzzle","Redesign",IF($F14="Problem","Reformulate","Review")))))),"") -> Reprice
A15: 11 | B15: =IFERROR(IF('Data'!$B15="","",'Data'!$B15),"") -> Creamy rice with Iberico pork secreto and mushrooms | C15: =IFERROR(IF('Data'!$C15="","",'Data'!$C15),"") -> Mains | D15: =IFERROR(IF('Kasavana-Smith'!$K15="","",'Kasavana-Smith'!$K15),"") -> Plowhorse | E15: =IFERROR(IF('Miller'!$K15="","",'Miller'!$K15),"") -> Marginal | F15: =IFERROR(IF('Pavesic'!$K15="","",'Pavesic'!$K15),"") -> Standard | G15: =IFERROR(IF('Goal Value'!$L15="","",'Goal Value'!$L15),"") -> Above target | H15: =IFERROR(IF($B15="","",IF($D15="Star",0,1)+IF($E15="Winner",0,1)+IF($F15="Prime",0,1)+IF($G15="Above target",0,1)),"") -> 3 | I15: =IFERROR(IF($B15="","",IF($H15=0,"All four readings agree on the best: keep it, feature it on the menu and protect the recipe and the supplier.",IF(AND($D15="Dog",$E15="Loser",$F15="Problem"),"Rarely ordered, high food cost and little margin to the total: a candidate to remove or to rework from the ground up.",IF(AND($D15="Plowhorse",$E15="Winner"),"Popular with a low margin: raise the price or lower the cost.",IF(AND($D15="Plowhorse",$E15="Loser"),"Popular but expensive to produce and short on margin: rework the recipe before you touch the price.",IF(AND('Data'!$G15>='Data'!$N15,'Data'!$H15>'Data'!$O15),"High CM with a poor food cost: protect the margin in dollars, review the price, don't remove it.",IF(AND($D15="Puzzle",$E15="Winner"),"Profitable with a healthy food cost, but rarely ordered: it's a menu problem, not a kitchen one. Rename it, move it up or have the floor staff suggest it.",IF($F15="Sleeper","Healthy food cost but little margin to the total: give it visibility before you remove it.",IF(AND($G15="Below target",$D15="Star"),"It sells and leaves margin, but falls below its category's Goal Value: little room to spare, review the price.",IF($D15="Dog","Rarely ordered: before removing it, check whether it's seasonal or goes with another dish that does sell.","The readings disagree: each method measures two of the three variables (popularity, margin in dollars and food cost). Decide with the one that hurts most this month.")))))))))),"") -> The readings disagree: each method measures two of the three variables (popularity, margin in dollars and food cost). Decide with the one that hurts most this month. | J15: =IFERROR(IF($B15="","",IF($H15=0,"Keep",IF(AND($D15="Dog",$E15="Loser"),"Remove",IF($D15="Plowhorse","Reprice",IF($D15="Puzzle","Redesign",IF($F15="Problem","Reformulate","Review")))))),"") -> Reprice
A16: 12 | B16: =IFERROR(IF('Data'!$B16="","",'Data'!$B16),"") -> Dry-aged bone-in ribeye (17.64 oz) | C16: =IFERROR(IF('Data'!$C16="","",'Data'!$C16),"") -> Mains | D16: =IFERROR(IF('Kasavana-Smith'!$K16="","",'Kasavana-Smith'!$K16),"") -> Puzzle | E16: =IFERROR(IF('Miller'!$K16="","",'Miller'!$K16),"") -> Loser | F16: =IFERROR(IF('Pavesic'!$K16="","",'Pavesic'!$K16),"") -> Problem | G16: =IFERROR(IF('Goal Value'!$L16="","",'Goal Value'!$L16),"") -> Below target | H16: =IFERROR(IF($B16="","",IF($D16="Star",0,1)+IF($E16="Winner",0,1)+IF($F16="Prime",0,1)+IF($G16="Above target",0,1)),"") -> 4 | I16: =IFERROR(IF($B16="","",IF($H16=0,"All four readings agree on the best: keep it, feature it on the menu and protect the recipe and the supplier.",IF(AND($D16="Dog",$E16="Loser",$F16="Problem"),"Rarely ordered, high food cost and little margin to the total: a candidate to remove or to rework from the ground up.",IF(AND($D16="Plowhorse",$E16="Winner"),"Popular with a low margin: raise the price or lower the cost.",IF(AND($D16="Plowhorse",$E16="Loser"),"Popular but expensive to produce and short on margin: rework the recipe before you touch the price.",IF(AND('Data'!$G16>='Data'!$N16,'Data'!$H16>'Data'!$O16),"High CM with a poor food cost: protect the margin in dollars, review the price, don't remove it.",IF(AND($D16="Puzzle",$E16="Winner"),"Profitable with a healthy food cost, but rarely ordered: it's a menu problem, not a kitchen one. Rename it, move it up or have the floor staff suggest it.",IF($F16="Sleeper","Healthy food cost but little margin to the total: give it visibility before you remove it.",IF(AND($G16="Below target",$D16="Star"),"It sells and leaves margin, but falls below its category's Goal Value: little room to spare, review the price.",IF($D16="Dog","Rarely ordered: before removing it, check whether it's seasonal or goes with another dish that does sell.","The readings disagree: each method measures two of the three variables (popularity, margin in dollars and food cost). Decide with the one that hurts most this month.")))))))))),"") -> High CM with a poor food cost: protect the margin in dollars, review the price, don't remove it. | J16: =IFERROR(IF($B16="","",IF($H16=0,"Keep",IF(AND($D16="Dog",$E16="Loser"),"Remove",IF($D16="Plowhorse","Reprice",IF($D16="Puzzle","Redesign",IF($F16="Problem","Reformulate","Review")))))),"") -> Redesign
... A29: 25 | B29: =IFERROR(IF('Data'!$B29="","",'Data'!$B29),"") | C29: =IFERROR(IF('Data'!$C29="","",'Data'!$C29),"") | D29: =IFERROR(IF('Kasavana-Smith'!$K29="","",'Kasavana-Smith'!$K29),"") | E29: =IFERROR(IF('Miller'!$K29="","",'Miller'!$K29),"") | F29: =IFERROR(IF('Pavesic'!$K29="","",'Pavesic'!$K29),"") | G29: =IFERROR(IF('Goal Value'!$L29="","",'Goal Value'!$L29),"") | H29: =IFERROR(IF($B29="","",IF($D29="Star",0,1)+IF($E29="Winner",0,1)+IF($F29="Prime",0,1)+IF($G29="Above target",0,1)),"") | I29: =IFERROR(IF($B29="","",IF($H29=0,"All four readings agree on the best: keep it, feature it on the menu and protect the recipe and the supplier.",IF(AND($D29="Dog",$E29="Loser",$F29="Problem"),"Rarely ordered, high food cost and little margin to the total: a candidate to remove or to rework from the ground up.",IF(AND($D29="Plowhorse",$E29="Winner"),"Popular with a low margin: raise the price or lower the cost.",IF(AND($D29="Plowhorse",$E29="Loser"),"Popular but expensive to produce and short on margin: rework the recipe before you touch the price.",IF(AND('Data'!$G29>='Data'!$N29,'Data'!$H29>'Data'!$O29),"High CM with a poor food cost: protect the margin in dollars, review the price, don't remove it.",IF(AND($D29="Puzzle",$E29="Winner"),"Profitable with a healthy food cost, but rarely ordered: it's a menu problem, not a kitchen one. Rename it, move it up or have the floor staff suggest it.",IF($F29="Sleeper","Healthy food cost but little margin to the total: give it visibility before you remove it.",IF(AND($G29="Below target",$D29="Star"),"It sells and leaves margin, but falls below its category's Goal Value: little room to spare, review the price.",IF($D29="Dog","Rarely ordered: before removing it, check whether it's seasonal or goes with another dish that does sell.","The readings disagree: each method measures two of the three variables (popularity, margin in dollars and food cost). Decide with the one that hurts most this month.")))))))))),"") | J29: =IFERROR(IF($B29="","",IF($H29=0,"Keep",IF(AND($D29="Dog",$E29="Loser"),"Remove",IF($D29="Plowhorse","Reprice",IF($D29="Puzzle","Redesign",IF($F29="Problem","Reformulate","Review")))))),"")
A31: SUMMARY — calculated by the workbook
B32: Readings off the best category | C32: Dishes | D32: % of the menu
B33: 0 | C33: =COUNTIF($H$5:$H$29,$B33) -> 3 | D33: =IFERROR(IF(COUNTIF($B$5:$B$29,"<>")=0,"",$C33/COUNTIF($B$5:$B$29,"<>")),"") -> 0.15
B34: 1 | C34: =COUNTIF($H$5:$H$29,$B34) -> 4 | D34: =IFERROR(IF(COUNTIF($B$5:$B$29,"<>")=0,"",$C34/COUNTIF($B$5:$B$29,"<>")),"") -> 0.2
B35: 2 | C35: =COUNTIF($H$5:$H$29,$B35) -> 1 | D35: =IFERROR(IF(COUNTIF($B$5:$B$29,"<>")=0,"",$C35/COUNTIF($B$5:$B$29,"<>")),"") -> 0.05
B36: 3 | C36: =COUNTIF($H$5:$H$29,$B36) -> 4 | D36: =IFERROR(IF(COUNTIF($B$5:$B$29,"<>")=0,"",$C36/COUNTIF($B$5:$B$29,"<>")),"") -> 0.2
B37: 4 | C37: =COUNTIF($H$5:$H$29,$B37) -> 8 | D37: =IFERROR(IF(COUNTIF($B$5:$B$29,"<>")=0,"",$C37/COUNTIF($B$5:$B$29,"<>")),"") -> 0.4
B39: Dishes with all four readings in the best category | C39: =COUNTIF($H$5:$H$29,0) -> 3
B40: Dishes with three or four readings off | C40: =COUNTIF($H$5:$H$29,3)+COUNTIF($H$5:$H$29,4) -> 12

Sheet Prix Fixe Menu
A1: Prix fixe menu — the mix decides the margin
A2: AI Chef Pro · aichef.pro — Food Cost + Menu Engineering Guide
D3: On a set-price menu the price is already fixed: what moves the margin is what people choose.
A4: Course | B4: Option | C4: Plate cost | D4: Base mix (%) | E4: Scenario A mix (%) | F4: Scenario B mix (%) | G4: Note
A5: First courses | B5: Garden salad | C5: 1.1 | D5: 0.4 | E5: 0.25 | F5: 0.35 | G5: Each course adds up to 100%: it's the split of choices, not a discount.
A6: First courses | B6: Pumpkin soup | C6: 1.05 | D6: 0.25 | E6: 0.2 | F6: 0.45
A7: First courses | B7: Pasta with pesto | C7: 1.6 | D7: 0.35 | E7: 0.55 | F7: 0.2
A8: First courses
A9: Main courses | B9: Roast chicken with potatoes | C9: 2.8 | D9: 0.45 | E9: 0.3 | F9: 0.6 | G9: Scenario A: guests go for the most expensive option. Scenario B: they go for the cheapest.
A10: Main courses | B10: Battered hake | C10: 3.9 | D10: 0.3 | E10: 0.45 | F10: 0.15
A11: Main courses | B11: Beef meatballs | C11: 3.2 | D11: 0.25 | E11: 0.25 | F11: 0.25
A12: Main courses
A13: Desserts | B13: Homemade flan | C13: 0.5 | D13: 0.55 | E13: 0.4 | F13: 0.7
A14: Desserts | B14: Seasonal fruit | C14: 0.7 | D14: 0.45 | E14: 0.6 | F14: 0.3
A15: Desserts
A18: MENU INPUTS
A19: Prix fixe price WITH tax | C19: 13.181818 | E19: The price the guest sees on the board or the menu. US and Canada: it's the pre-tax price, with the tax rate at 0%. UK and Australia: type the printed price and the rate.
A20: Tax rate (%) | C20: 0 | E20: Ships at 0%: US and Canadian menus are printed pre-tax. In the UK type 20% (VAT is included in printed prices); in Australia type 10% (GST included). Change it here and the whole workbook recalculates.
A21: Prix fixe price pre-tax | C21: =IFERROR(IF(OR($C$19="",$C$20=""),"",$C$19/(1+$C$20)),"") -> 13.181818
A22: Fixed costs per menu | C22: 0.55 | E22: Table bread, coffee and any included drink, allocated per menu served.
A23: Menu target food cost (%) | C23: 0.3 | E23: The house target. If the menu goes over it, the "Menu food cost" row turns red.
A24: Prix fixe menus served per month | C24: 100 | E24: How many of these menus you serve a month: it scales the margin per menu up to the month.
A25: WEIGHTED AVERAGE COST BY COURSE — calculated by the workbook
A26: Course | B26: Base mix total (%) | C26: Base average cost | D26: Mix A total (%) | E26: Scenario A average cost | F26: Mix B total (%) | G26: Scenario B average cost
A27: First courses | B27: =IFERROR(SUMIF($A$5:$A$16,$A27,$D$5:$D$16),"") -> 1 | C27: =IFERROR(SUMPRODUCT(--($A$5:$A$16=$A27),$C$5:$C$16,$D$5:$D$16),"") -> 1.2625 | D27: =IFERROR(SUMIF($A$5:$A$16,$A27,$E$5:$E$16),"") -> 1 | E27: =IFERROR(SUMPRODUCT(--($A$5:$A$16=$A27),$C$5:$C$16,$E$5:$E$16),"") -> 1.365 | F27: =IFERROR(SUMIF($A$5:$A$16,$A27,$F$5:$F$16),"") -> 1 | G27: =IFERROR(SUMPRODUCT(--($A$5:$A$16=$A27),$C$5:$C$16,$F$5:$F$16),"") -> 1.1775
A28: Main courses | B28: =IFERROR(SUMIF($A$5:$A$16,$A28,$D$5:$D$16),"") -> 1 | C28: =IFERROR(SUMPRODUCT(--($A$5:$A$16=$A28),$C$5:$C$16,$D$5:$D$16),"") -> 3.23 | D28: =IFERROR(SUMIF($A$5:$A$16,$A28,$E$5:$E$16),"") -> 1 | E28: =IFERROR(SUMPRODUCT(--($A$5:$A$16=$A28),$C$5:$C$16,$E$5:$E$16),"") -> 3.395 | F28: =IFERROR(SUMIF($A$5:$A$16,$A28,$F$5:$F$16),"") -> 1 | G28: =IFERROR(SUMPRODUCT(--($A$5:$A$16=$A28),$C$5:$C$16,$F$5:$F$16),"") -> 3.065
A29: Desserts | B29: =IFERROR(SUMIF($A$5:$A$16,$A29,$D$5:$D$16),"") -> 1 | C29: =IFERROR(SUMPRODUCT(--($A$5:$A$16=$A29),$C$5:$C$16,$D$5:$D$16),"") -> 0.59 | D29: =IFERROR(SUMIF($A$5:$A$16,$A29,$E$5:$E$16),"") -> 1 | E29: =IFERROR(SUMPRODUCT(--($A$5:$A$16=$A29),$C$5:$C$16,$E$5:$E$16),"") -> 0.62 | F29: =IFERROR(SUMIF($A$5:$A$16,$A29,$F$5:$F$16),"") -> 1 | G29: =IFERROR(SUMPRODUCT(--($A$5:$A$16=$A29),$C$5:$C$16,$F$5:$F$16),"") -> 0.56
A30: If a mix total doesn't come to 100% it turns red: that course's split is wrong.
A32: MENU RESULT — calculated by the workbook
A33: Item | B33: Base mix | C33: Scenario A | D33: Scenario B
A34: Average cost of first courses | B34: =IFERROR($C$27,"") -> 1.2625 | C34: =IFERROR($E$27,"") -> 1.365 | D34: =IFERROR($G$27,"") -> 1.1775
A35: Average cost of main courses | B35: =IFERROR($C$28,"") -> 3.23 | C35: =IFERROR($E$28,"") -> 3.395 | D35: =IFERROR($G$28,"") -> 3.065
A36: Average cost of desserts | B36: =IFERROR($C$29,"") -> 0.59 | C36: =IFERROR($E$29,"") -> 0.62 | D36: =IFERROR($G$29,"") -> 0.56
A37: Fixed costs per menu | B37: =IFERROR($C$22,"") -> 0.55 | C37: =IFERROR($C$22,"") -> 0.55 | D37: =IFERROR($C$22,"") -> 0.55
A38: Total average menu cost | B38: =IFERROR(SUM(B34:B37),"") -> 5.6325 | C38: =IFERROR(SUM(C34:C37),"") -> 5.93 | D38: =IFERROR(SUM(D34:D37),"") -> 5.3525
A39: Menu food cost (%) | B39: =IFERROR(IF(OR($C$21="",$C$21=0,B38=""),"",B38/$C$21),"") -> 0.4272931 | C39: =IFERROR(IF(OR($C$21="",$C$21=0,C38=""),"",C38/$C$21),"") -> 0.44986207 | D39: =IFERROR(IF(OR($C$21="",$C$21=0,D38=""),"",D38/$C$21),"") -> 0.40605172 | F39: Red = above the menu's target food cost.
A40: Contribution margin per menu | B40: =IFERROR(IF(OR($C$21="",B38=""),"",$C$21-B38),"") -> 7.5493182 | C40: =IFERROR(IF(OR($C$21="",C38=""),"",$C$21-C38),"") -> 7.2518182 | D40: =IFERROR(IF(OR($C$21="",D38=""),"",$C$21-D38),"") -> 7.8293182
A41: Margin on prix fixe menus served per month | B41: =IFERROR(IF(B40="","",B40*$C$24),"") -> 754.93182 | C41: =IFERROR(IF(C40="","",C40*$C$24),"") -> 725.18182 | D41: =IFERROR(IF(D40="","",D40*$C$24),"") -> 782.93182
A43: All three scenarios use the SAME price and the SAME costs: the only thing that changes is the split of choices. That difference is the margin you're playing for every day on the menu.
A44: In the example, the menu ends up ABOVE the house target food cost. That's normal on a set-price menu: either you raise the price, change the options you offer, or accept that the menu brings in guests and the à la carte menu makes the margin. What doesn't work is not knowing it.
