Workbook

Sheet Instructions
A1: Prime Cost Dashboard
A2: AI Chef Pro · aichef.pro — Food Cost + Menu Engineering Guide
A4: How to use this workbook
A5: 1. "Inputs" sheet: choose your business type. The prime cost target changes on its own (65% for full service, 55% for counter or self-service), and both targets are green cells you can adjust.
A6: 2. Check the employer payroll taxes and benefits rate and your target food cost: the whole workbook reads those two cells.
A7: 3. "Monthly" sheet: for each month, net food and beverage sales, beginning inventory, purchases, ending inventory, gross wages and other labor costs. All PRE-TAX.
A8: 4. Product usage is calculated on its own: beginning inventory + purchases − ending inventory. It isn't the same as the month's purchases.
A9: 5. Labor cost adds employer payroll taxes and benefits to gross wages: $15,400 of wages costs $20,482 with a 33% load. Counting gross wages alone is the most expensive mistake on this sheet.
A10: 6. Read the "Prime cost" column: if it's above target, it turns red. The chart shows the twelve months against the target line.
A11: 7. The TOTAL / AVERAGE row is a WEIGHTED average: it divides the year's usage by the year's sales; it doesn't average the twelve percentages.
A13: Green cells = editable fields
A15: All figures are PRE-TAX; amounts carry no currency symbol and are in your currency. Food cost and prime cost are measured on NET sales (before sales tax, VAT or GST, and without tips) and on cost NET of any tax you get back: in the US, sales tax you pay on supplies is a cost; if you're registered for VAT or GST/HST, the tax on purchases is cash flow, not cost.
... A23: Version 1.0 · October 2026 · aichef.pro/en/digital-products/food-cost-menu-engineering-guide · info@aichef.pro

Sheet Inputs
A1: Dashboard inputs
A2: AI Chef Pro · aichef.pro — Food Cost + Menu Engineering Guide
A4: BUSINESS TYPE AND PRIME COST TARGET
A5: Business type | B5: Full service
A7: Business type | B7: Prime cost target (%)
A8: Full service | B8: 0.65
A9: Counter / self-service | B9: 0.55
A11: Prime cost target in use (%) | B11: =IF($B$5=$A$8,$B$8,IF($B$5=$A$9,$B$9,"")) -> 0.65
A13: Commonly cited reference structure: product cost around 30% and labor cost of 30-35% for full service (15-25% for counter or self-service). Hence the two targets: 65% and 55%.
A14: Source: Toast, How to Calculate Prime Cost (2026): 60% at most; 60-65% for full service and 55-60% for quick service.
A15: The 60% often quoted as the prime cost ceiling comes from Toast, a US benchmark. This workbook ships with 65% and 55% as a starting point: tighten them if you want to work to that benchmark.
A16: Both targets are green cells: if your labor setup, your hours or your service model are different, change them and the traffic light on the "Monthly" sheet recalculates.
A18: OTHER INPUTS
A19: Input | B19: Value
A20: Employer payroll taxes and benefits (%) | B20: 0.33
A21: Target food cost (%) | B21: 0.3
A23: An approximate load on top of gross wages (employer payroll taxes, insurance and benefits). It's a model parameter: replace it with your own.
A24: The target food cost is your restaurant's own. A 2026 European industry study puts the average around 30%, with food at 28% and beverage at 34.5% of their own revenue.

Sheet Monthly
A1: Prime cost month by month
A2: AI Chef Pro · aichef.pro — Food Cost + Menu Engineering Guide
A3: All figures are pre-tax. Usage is beginning inventory + purchases − ending inventory, not the month's purchases.
A4: Month | B4: Net food sales | C4: Net beverage sales | D4: Total net sales | E4: Beginning inventory | F4: Purchases for the month | G4: Ending inventory | H4: Product usage | I4: Product cost on total sales (%) | J4: Gross wages | K4: Other labor costs | L4: Labor cost with payroll taxes and benefits | M4: Labor cost (%) | N4: Prime cost (%) | O4: Prime cost target (%) | P4: Margin after prime cost | Q4: Margin after prime cost (%) | R4: Prime cost reading
A5: January | B5: 51500 | C5: 38100 | D5: =IFERROR(IF(AND($B5="",$C5=""),"",IF($B5="",0,$B5)+IF($C5="",0,$C5)),"") -> 89600 | E5: 9700 | F5: 28100 | G5: 9400 | H5: =IFERROR(IF(OR($E5="",$F5="",$G5=""),"",$E5+$F5-$G5),"") -> 28400 | I5: =IFERROR(IF(OR($H5="",$D5="",$D5=0),"",$H5/$D5),"") -> 0.31696429 | J5: 21600 | K5: 1260 | L5: =IFERROR(IF($J5="","",$J5*(1+Inputs!$B$20)+IF($K5="",0,$K5)),"") -> 29988 | M5: =IFERROR(IF(OR($L5="",$D5="",$D5=0),"",$L5/$D5),"") -> 0.3346875 | N5: =IFERROR(IF(OR($H5="",$L5="",$D5="",$D5=0),"",($H5+$L5)/$D5),"") -> 0.65165179 | O5: =IF(Inputs!$B$11="","",Inputs!$B$11) -> 0.65 | P5: =IFERROR(IF(OR($D5="",$H5="",$L5=""),"",$D5-$H5-$L5),"") -> 31212 | Q5: =IFERROR(IF(OR($P5="",$D5="",$D5=0),"",$P5/$D5),"") -> 0.34834821 | R5: =IF(OR($N5="",$O5=""),"",IF($N5<=$O5,"On target","Above target")) -> Above target
A6: February | B6: 48400 | C6: 35700 | D6: =IFERROR(IF(AND($B6="",$C6=""),"",IF($B6="",0,$B6)+IF($C6="",0,$C6)),"") -> 84100 | E6: 9400 | F6: 27000 | G6: 9100 | H6: =IFERROR(IF(OR($E6="",$F6="",$G6=""),"",$E6+$F6-$G6),"") -> 27300 | I6: =IFERROR(IF(OR($H6="",$D6="",$D6=0),"",$H6/$D6),"") -> 0.32461356 | J6: 21600 | K6: 1190 | L6: =IFERROR(IF($J6="","",$J6*(1+Inputs!$B$20)+IF($K6="",0,$K6)),"") -> 29918 | M6: =IFERROR(IF(OR($L6="",$D6="",$D6=0),"",$L6/$D6),"") -> 0.35574316 | N6: =IFERROR(IF(OR($H6="",$L6="",$D6="",$D6=0),"",($H6+$L6)/$D6),"") -> 0.68035672 | O6: =IF(Inputs!$B$11="","",Inputs!$B$11) -> 0.65 | P6: =IFERROR(IF(OR($D6="",$H6="",$L6=""),"",$D6-$H6-$L6),"") -> 26882 | Q6: =IFERROR(IF(OR($P6="",$D6="",$D6=0),"",$P6/$D6),"") -> 0.31964328 | R6: =IF(OR($N6="",$O6=""),"",IF($N6<=$O6,"On target","Above target")) -> Above target
A7: March | B7: 54700 | C7: 40500 | D7: =IFERROR(IF(AND($B7="",$C7=""),"",IF($B7="",0,$B7)+IF($C7="",0,$C7)),"") -> 95200 | E7: 9100 | F7: 30700 | G7: 9500 | H7: =IFERROR(IF(OR($E7="",$F7="",$G7=""),"",$E7+$F7-$G7),"") -> 30300 | I7: =IFERROR(IF(OR($H7="",$D7="",$D7=0),"",$H7/$D7),"") -> 0.31827731 | J7: 22300 | K7: 1260 | L7: =IFERROR(IF($J7="","",$J7*(1+Inputs!$B$20)+IF($K7="",0,$K7)),"") -> 30919 | M7: =IFERROR(IF(OR($L7="",$D7="",$D7=0),"",$L7/$D7),"") -> 0.32477941 | N7: =IFERROR(IF(OR($H7="",$L7="",$D7="",$D7=0),"",($H7+$L7)/$D7),"") -> 0.64305672 | O7: =IF(Inputs!$B$11="","",Inputs!$B$11) -> 0.65 | P7: =IFERROR(IF(OR($D7="",$H7="",$L7=""),"",$D7-$H7-$L7),"") -> 33981 | Q7: =IFERROR(IF(OR($P7="",$D7="",$D7=0),"",$P7/$D7),"") -> 0.35694328 | R7: =IF(OR($N7="",$O7=""),"",IF($N7<=$O7,"On target","Above target")) -> On target
A8: April | B8: 57700 | C8: 42700 | D8: =IFERROR(IF(AND($B8="",$C8=""),"",IF($B8="",0,$B8)+IF($C8="",0,$C8)),"") -> 100400 | E8: 9500 | F8: 31400 | G8: 9200 | H8: =IFERROR(IF(OR($E8="",$F8="",$G8=""),"",$E8+$F8-$G8),"") -> 31700 | I8: =IFERROR(IF(OR($H8="",$D8="",$D8=0),"",$H8/$D8),"") -> 0.31573705 | J8: 22500 | K8: 1330 | L8: =IFERROR(IF($J8="","",$J8*(1+Inputs!$B$20)+IF($K8="",0,$K8)),"") -> 31255 | M8: =IFERROR(IF(OR($L8="",$D8="",$D8=0),"",$L8/$D8),"") -> 0.31130478 | N8: =IFERROR(IF(OR($H8="",$L8="",$D8="",$D8=0),"",($H8+$L8)/$D8),"") -> 0.62704183 | O8: =IF(Inputs!$B$11="","",Inputs!$B$11) -> 0.65 | P8: =IFERROR(IF(OR($D8="",$H8="",$L8=""),"",$D8-$H8-$L8),"") -> 37445 | Q8: =IFERROR(IF(OR($P8="",$D8="",$D8=0),"",$P8/$D8),"") -> 0.37295817 | R8: =IF(OR($N8="",$O8=""),"",IF($N8<=$O8,"On target","Above target")) -> On target
A9: May | B9: 62000 | C9: 45900 | D9: =IFERROR(IF(AND($B9="",$C9=""),"",IF($B9="",0,$B9)+IF($C9="",0,$C9)),"") -> 107900 | E9: 9200 | F9: 34700 | G9: 9700 | H9: =IFERROR(IF(OR($E9="",$F9="",$G9=""),"",$E9+$F9-$G9),"") -> 34200 | I9: =IFERROR(IF(OR($H9="",$D9="",$D9=0),"",$H9/$D9),"") -> 0.31696015 | J9: 23200 | K9: 1400 | L9: =IFERROR(IF($J9="","",$J9*(1+Inputs!$B$20)+IF($K9="",0,$K9)),"") -> 32256 | M9: =IFERROR(IF(OR($L9="",$D9="",$D9=0),"",$L9/$D9),"") -> 0.29894347 | N9: =IFERROR(IF(OR($H9="",$L9="",$D9="",$D9=0),"",($H9+$L9)/$D9),"") -> 0.61590361 | O9: =IF(Inputs!$B$11="","",Inputs!$B$11) -> 0.65 | P9: =IFERROR(IF(OR($D9="",$H9="",$L9=""),"",$D9-$H9-$L9),"") -> 41444 | Q9: =IFERROR(IF(OR($P9="",$D9="",$D9=0),"",$P9/$D9),"") -> 0.38409639 | R9: =IF(OR($N9="",$O9=""),"",IF($N9<=$O9,"On target","Above target")) -> On target
A10: June | B10: 63700 | C10: 47000 | D10: =IFERROR(IF(AND($B10="",$C10=""),"",IF($B10="",0,$B10)+IF($C10="",0,$C10)),"") -> 110700 | E10: 9700 | F10: 37700 | G10: 9000 | H10: =IFERROR(IF(OR($E10="",$F10="",$G10=""),"",$E10+$F10-$G10),"") -> 38400 | I10: =IFERROR(IF(OR($H10="",$D10="",$D10=0),"",$H10/$D10),"") -> 0.34688347 | J10: 24200 | K10: 1470 | L10: =IFERROR(IF($J10="","",$J10*(1+Inputs!$B$20)+IF($K10="",0,$K10)),"") -> 33656 | M10: =IFERROR(IF(OR($L10="",$D10="",$D10=0),"",$L10/$D10),"") -> 0.30402891 | N10: =IFERROR(IF(OR($H10="",$L10="",$D10="",$D10=0),"",($H10+$L10)/$D10),"") -> 0.65091238 | O10: =IF(Inputs!$B$11="","",Inputs!$B$11) -> 0.65 | P10: =IFERROR(IF(OR($D10="",$H10="",$L10=""),"",$D10-$H10-$L10),"") -> 38644 | Q10: =IFERROR(IF(OR($P10="",$D10="",$D10=0),"",$P10/$D10),"") -> 0.34908762 | R10: =IF(OR($N10="",$O10=""),"",IF($N10<=$O10,"On target","Above target")) -> Above target
A11: July | B11: 66800 | C11: 49400 | D11: =IFERROR(IF(AND($B11="",$C11=""),"",IF($B11="",0,$B11)+IF($C11="",0,$C11)),"") -> 116200 | E11: 9000 | F11: 38100 | G11: 9400 | H11: =IFERROR(IF(OR($E11="",$F11="",$G11=""),"",$E11+$F11-$G11),"") -> 37700 | I11: =IFERROR(IF(OR($H11="",$D11="",$D11=0),"",$H11/$D11),"") -> 0.32444062 | J11: 24900 | K11: 1540 | L11: =IFERROR(IF($J11="","",$J11*(1+Inputs!$B$20)+IF($K11="",0,$K11)),"") -> 34657 | M11: =IFERROR(IF(OR($L11="",$D11="",$D11=0),"",$L11/$D11),"") -> 0.29825301 | N11: =IFERROR(IF(OR($H11="",$L11="",$D11="",$D11=0),"",($H11+$L11)/$D11),"") -> 0.62269363 | O11: =IF(Inputs!$B$11="","",Inputs!$B$11) -> 0.65 | P11: =IFERROR(IF(OR($D11="",$H11="",$L11=""),"",$D11-$H11-$L11),"") -> 43843 | Q11: =IFERROR(IF(OR($P11="",$D11="",$D11=0),"",$P11/$D11),"") -> 0.37730637 | R11: =IF(OR($N11="",$O11=""),"",IF($N11<=$O11,"On target","Above target")) -> On target
A12: August | B12: 57300 | C12: 42300 | D12: =IFERROR(IF(AND($B12="",$C12=""),"",IF($B12="",0,$B12)+IF($C12="",0,$C12)),"") -> 99600 | E12: 9400 | F12: 34400 | G12: 8700 | H12: =IFERROR(IF(OR($E12="",$F12="",$G12=""),"",$E12+$F12-$G12),"") -> 35100 | I12: =IFERROR(IF(OR($H12="",$D12="",$D12=0),"",$H12/$D12),"") -> 0.35240964 | J12: 24900 | K12: 1400 | L12: =IFERROR(IF($J12="","",$J12*(1+Inputs!$B$20)+IF($K12="",0,$K12)),"") -> 34517 | M12: =IFERROR(IF(OR($L12="",$D12="",$D12=0),"",$L12/$D12),"") -> 0.34655622 | N12: =IFERROR(IF(OR($H12="",$L12="",$D12="",$D12=0),"",($H12+$L12)/$D12),"") -> 0.69896586 | O12: =IF(Inputs!$B$11="","",Inputs!$B$11) -> 0.65 | P12: =IFERROR(IF(OR($D12="",$H12="",$L12=""),"",$D12-$H12-$L12),"") -> 29983 | Q12: =IFERROR(IF(OR($P12="",$D12="",$D12=0),"",$P12/$D12),"") -> 0.30103414 | R12: =IF(OR($N12="",$O12=""),"",IF($N12<=$O12,"On target","Above target")) -> Above target
A13: September | B13: 60600 | C13: 44900 | D13: =IFERROR(IF(AND($B13="",$C13=""),"",IF($B13="",0,$B13)+IF($C13="",0,$C13)),"") -> 105500 | E13: 8700 | F13: 32600 | G13: 9500 | H13: =IFERROR(IF(OR($E13="",$F13="",$G13=""),"",$E13+$F13-$G13),"") -> 31800 | I13: =IFERROR(IF(OR($H13="",$D13="",$D13=0),"",$H13/$D13),"") -> 0.3014218 | J13: 23000 | K13: 1330 | L13: =IFERROR(IF($J13="","",$J13*(1+Inputs!$B$20)+IF($K13="",0,$K13)),"") -> 31920 | M13: =IFERROR(IF(OR($L13="",$D13="",$D13=0),"",$L13/$D13),"") -> 0.30255924 | N13: =IFERROR(IF(OR($H13="",$L13="",$D13="",$D13=0),"",($H13+$L13)/$D13),"") -> 0.60398104 | O13: =IF(Inputs!$B$11="","",Inputs!$B$11) -> 0.65 | P13: =IFERROR(IF(OR($D13="",$H13="",$L13=""),"",$D13-$H13-$L13),"") -> 41780 | Q13: =IFERROR(IF(OR($P13="",$D13="",$D13=0),"",$P13/$D13),"") -> 0.39601896 | R13: =IF(OR($N13="",$O13=""),"",IF($N13<=$O13,"On target","Above target")) -> On target
A14: October | B14: 59000 | C14: 43700 | D14: =IFERROR(IF(AND($B14="",$C14=""),"",IF($B14="",0,$B14)+IF($C14="",0,$C14)),"") -> 102700 | E14: 9500 | F14: 31800 | G14: 9200 | H14: =IFERROR(IF(OR($E14="",$F14="",$G14=""),"",$E14+$F14-$G14),"") -> 32100 | I14: =IFERROR(IF(OR($H14="",$D14="",$D14=0),"",$H14/$D14),"") -> 0.31256086 | J14: 22500 | K14: 1330 | L14: =IFERROR(IF($J14="","",$J14*(1+Inputs!$B$20)+IF($K14="",0,$K14)),"") -> 31255 | M14: =IFERROR(IF(OR($L14="",$D14="",$D14=0),"",$L14/$D14),"") -> 0.30433301 | N14: =IFERROR(IF(OR($H14="",$L14="",$D14="",$D14=0),"",($H14+$L14)/$D14),"") -> 0.61689387 | O14: =IF(Inputs!$B$11="","",Inputs!$B$11) -> 0.65 | P14: =IFERROR(IF(OR($D14="",$H14="",$L14=""),"",$D14-$H14-$L14),"") -> 39345 | Q14: =IFERROR(IF(OR($P14="",$D14="",$D14=0),"",$P14/$D14),"") -> 0.38310613 | R14: =IF(OR($N14="",$O14=""),"",IF($N14<=$O14,"On target","Above target")) -> On target
A15: November | B15: 56200 | C15: 41700 | D15: =IFERROR(IF(AND($B15="",$C15=""),"",IF($B15="",0,$B15)+IF($C15="",0,$C15)),"") -> 97900 | E15: 9200 | F15: 30500 | G15: 9700 | H15: =IFERROR(IF(OR($E15="",$F15="",$G15=""),"",$E15+$F15-$G15),"") -> 30000 | I15: =IFERROR(IF(OR($H15="",$D15="",$D15=0),"",$H15/$D15),"") -> 0.30643514 | J15: 22300 | K15: 1260 | L15: =IFERROR(IF($J15="","",$J15*(1+Inputs!$B$20)+IF($K15="",0,$K15)),"") -> 30919 | M15: =IFERROR(IF(OR($L15="",$D15="",$D15=0),"",$L15/$D15),"") -> 0.31582227 | N15: =IFERROR(IF(OR($H15="",$L15="",$D15="",$D15=0),"",($H15+$L15)/$D15),"") -> 0.62225741 | O15: =IF(Inputs!$B$11="","",Inputs!$B$11) -> 0.65 | P15: =IFERROR(IF(OR($D15="",$H15="",$L15=""),"",$D15-$H15-$L15),"") -> 36981 | Q15: =IFERROR(IF(OR($P15="",$D15="",$D15=0),"",$P15/$D15),"") -> 0.37774259 | R15: =IF(OR($N15="",$O15=""),"",IF($N15<=$O15,"On target","Above target")) -> On target
A16: December | B16: 70400 | C16: 52000 | D16: =IFERROR(IF(AND($B16="",$C16=""),"",IF($B16="",0,$B16)+IF($C16="",0,$C16)),"") -> 122400 | E16: 9700 | F16: 39100 | G16: 10400 | H16: =IFERROR(IF(OR($E16="",$F16="",$G16=""),"",$E16+$F16-$G16),"") -> 38400 | I16: =IFERROR(IF(OR($H16="",$D16="",$D16=0),"",$H16/$D16),"") -> 0.31372549 | J16: 24600 | K16: 1680 | L16: =IFERROR(IF($J16="","",$J16*(1+Inputs!$B$20)+IF($K16="",0,$K16)),"") -> 34398 | M16: =IFERROR(IF(OR($L16="",$D16="",$D16=0),"",$L16/$D16),"") -> 0.28102941 | N16: =IFERROR(IF(OR($H16="",$L16="",$D16="",$D16=0),"",($H16+$L16)/$D16),"") -> 0.5947549 | O16: =IF(Inputs!$B$11="","",Inputs!$B$11) -> 0.65 | P16: =IFERROR(IF(OR($D16="",$H16="",$L16=""),"",$D16-$H16-$L16),"") -> 49602 | Q16: =IFERROR(IF(OR($P16="",$D16="",$D16=0),"",$P16/$D16),"") -> 0.4052451 | R16: =IF(OR($N16="",$O16=""),"",IF($N16<=$O16,"On target","Above target")) -> On target
A17: TOTAL / AVERAGE | B17: =IF(COUNT(B5:B16)=0,"",SUM(B5:B16)) -> 708300 | C17: =IF(COUNT(C5:C16)=0,"",SUM(C5:C16)) -> 523900 | D17: =IF(COUNT(D5:D16)=0,"",SUM(D5:D16)) -> 1232200 | F17: =IF(COUNT(F5:F16)=0,"",SUM(F5:F16)) -> 396100 | H17: =IF(COUNT(H5:H16)=0,"",SUM(H5:H16)) -> 395400 | I17: =IFERROR(IF(OR($H$17="",$D$17="",$D$17=0),"",$H$17/$D$17),"") -> 0.32088947 | J17: =IF(COUNT(J5:J16)=0,"",SUM(J5:J16)) -> 277600 | K17: =IF(COUNT(K5:K16)=0,"",SUM(K5:K16)) -> 16450 | L17: =IF(COUNT(L5:L16)=0,"",SUM(L5:L16)) -> 385658 | M17: =IFERROR(IF(OR($L$17="",$D$17="",$D$17=0),"",$L$17/$D$17),"") -> 0.31298328 | N17: =IFERROR(IF(OR($H$17="",$L$17="",$D$17="",$D$17=0),"",($H$17+$L$17)/$D$17),"") -> 0.63387275 | O17: =IF(Inputs!$B$11="","",Inputs!$B$11) -> 0.65 | P17: =IF(COUNT(P5:P16)=0,"",SUM(P5:P16)) -> 451142 | Q17: =IFERROR(IF(OR($P$17="",$D$17="",$D$17=0),"",$P$17/$D$17),"") -> 0.36612725 | R17: =IF(OR($N$17="",$O$17=""),"",IF($N$17<=$O$17,"On target","Above target")) -> On target
A18: Inventories aren't added up in the TOTAL row: the year's usage is the sum of the twelve months' usage, and the percentages are weighted averages over the year's sales.
A20: INPUTS IN USE — read from the "Inputs" sheet; change them there, not here
A21: Business type | E21: =Inputs!$B$5 -> Full service
A22: Prime cost target (%) | E22: =IF(Inputs!$B$11="","",Inputs!$B$11) -> 0.65
A23: Target food cost (%) | E23: =IF(Inputs!$B$21="","",Inputs!$B$21) -> 0.3
A24: Employer payroll taxes and benefits (%) | E24: =IF(Inputs!$B$20="","",Inputs!$B$20) -> 0.33
