Workbook

Sheet 0. Supuestos
A1: SUPUESTOS — aquí se teclean las TASAS y los DRIVERS del modelo
A2: Cambia las celdas VERDES: el resto del libro se recalcula solo. Las partidas de gasto se teclean en su hoja (también en verde) y no se repiten aquí.
A3: ACTIVIDAD
A4: Cubiertos/día (media del año 1) | B4: 80 | C4: Comensales servidos al día de media del año, contando todos los servicios. La rotación que implica sobre el aforo la calcula la celda «Rotaciones al día implícitas» de esta misma hoja; el documento del plan pide un MÍNIMO de 1,8 covers por mesa y servicio en temporada alta
A5: Ticket medio SIN IVA (€) | B5: 18.2 | C5: SIN IVA. El PVP equivalente lo calcula la celda «PVP equivalente con IVA» de abajo (al 10 % en sala son 20,02 € con los supuestos de partida): dentro del rango 15-22 € que declara este mismo libro y del 18-25 € que fija el documento del plan
A6: Días de apertura al año | B6: 310 | C6: Cierre semanal de un día y vacaciones. El MISMO dato lo usan el P&L, el punto de equilibrio y los escenarios
A7: Crecimiento de volumen del año 2 | B7: 0.1 | C7: Segundo año con la clientela ya asentada
A8: Crecimiento de volumen del año 3 | B8: 0.06 | C8: Tercer año, cerca del techo de rotación del local
A9: PVP equivalente con IVA (calculado) | B9: =IFERROR(IF($B$5="","",$B$5*(1+SUMPRODUCT('2. P&L 3 Años'!$E$11:$E$12,'2. P&L 3 Años'!$G$11:$G$12))),"") -> 20.02 | C9: =IFERROR("Ticket sin IVA más el IVA medio ponderado de tus líneas de venta: "&TEXT(SUMPRODUCT('2. P&L 3 Años'!$E$11:$E$12,'2. P&L 3 Años'!$G$11:$G$12)*100,"0")&" %. En sala todo va al 10 % (art. 91.Uno.2.2.º de la Ley 37/1992, alcohol incluido); el alcohol que sale por delivery y el pan común, si los tienes, mueven la media. Aquí va redondeado. Compáralo con el rango del sector, que va con IVA.","") -> Ticket sin IVA más el IVA medio ponderado de tus líneas de venta: 10 %. En sala todo va al 10 % (art. 91.Uno.2.2.º de la Ley 37/1992, alcohol incluido); el alcohol que sale por delivery y el pan común, si los tienes, mueven la media. Aquí va redondeado. Compáralo con el rango del sector, que va con IVA.
A10: MIX Y COSTE DE MERCANCÍA
A11: Ventas de COMIDA sobre el total | B11: 0.65 | C11: Peso de la COMIDA sobre el total de ventas. Es un INPUT: cámbialo aquí y el P&L, la tesorería y el IVA repercutido se recalculan solos
A12: Ventas de BEBIDA sobre el total | B12: =IFERROR(IF(COUNT(B11)=0,"",1-B11),"") -> 0.35 | C12: Se calcula como el resto: comida + bebida = 100 %
A13: Coste de mercancía sobre las ventas de COMIDA | B13: 0.3 | C13: Food cost objetivo del bar-restaurante casual: 28-32 % según las referencias de este mismo libro. Se aplica SOLO a la comida
A14: Coste de mercancía sobre las ventas de BEBIDA | B14: 0.22 | C14: Coste de la bebida sobre las ventas de bebida, no sobre el total
A15: Consumibles sobre ventas | B15: 0.015 | C15: Servilletas, papel, productos de limpieza y envases de llevar
A16: Ventas por delivery sobre el total | B16: 0 | C16: A CERO por defecto: si no repartes no arrastras un coste inventado. Súbelo al peso REAL del canal y la comisión se aplica sólo sobre esa parte
A17: Comisión de la plataforma de delivery | B17: 0.28 | C17: Comisión típica de las plataformas sobre el pedido servido por ese canal; confírmala en tu contrato antes de proyectar
A18: Comisión de los medios de pago | B18: 0.008 | C18: Tarjeta y bizum sobre el total facturado; pide oferta a dos proveedores de TPV
A19: PERSONAL
A20: Seguridad Social a cargo de la empresa | B20: 0.33 | C20: Contingencias comunes + AT/EP + desempleo + FOGASA + FP; ajusta a tu convenio y bonificaciones
A21: Número de pagas anuales | B21: 14 | C21: Salario bruto anual = bruto mensual × pagas
A22: SMI anual de referencia (€) | B22: 17094 | C22: SMI 2026: 17.094 € al año (1.221 €/mes en 14 pagas), suelo legal por jornada completa. Comprueba el importe vigente si presentas el plan en otro ejercicio
A23: LOCAL Y FIJOS
A24: Alquiler mensual del local (€) | B24: 3000 | C24: Dentro del rango 2.000-4.500 €/mes que declara este libro para un local de 80-120 m² en zona urbana, y respetando el techo del 10 % sobre ventas
A25: Fianza del alquiler (meses) | B25: 3 | C25: Tres meses de renta, como en el contrato tipo de local de negocio
A26: Suministros mensuales de luz, agua y gas (€) | B26: 1800 | C26: Luz, agua y gas de una cocina con horno, cámaras y campana: pide el histórico del local antes de firmar
A27: Seguros (€/año) | B27: 2000 | C27: Responsabilidad civil + multirriesgo del local + convenio
A28: Varios e imprevistos sobre ventas | B28: 0.02 | C28: Colchón de gasto corriente no presupuestado
A29: FINANCIACIÓN
A30: Recursos propios aportados (€) | B30: 75000 | C30: Aportación de los socios. Con menos, el banco no entra: pide un 35-40 % de fondos propios sobre la inversión
A31: Préstamo bancario solicitado (€) | B31: 128000 | C31: Principal solicitado. La hoja de Financiación comprueba que origen y usos cuadran, y trae una celda que calcula el importe exacto que los ajusta
A32: Tipo de interés nominal anual | B32: 0.06 | C32: Tipo nominal anual; pide oferta a dos entidades y a una línea ICO antes de fijarlo
A33: Plazo del préstamo (años) | B33: 7 | C33: Años totales, carencia incluida
A34: Carencia de principal (años) | B34: 1 | C34: Primer año sólo intereses, que es cuando la caja está más tensa
A35: Fondo de maniobra (meses de costes fijos) | B35: 3 | C35: Mínimo que exige este mismo libro: «Fondo de maniobra: mínimo 3 meses de costes fijos antes de abrir»
A36: FISCAL
A37: Impuesto de Sociedades, nueva creación | B37: 0.15 | C37: Art. 29.1 LIS: el PRIMER ejercicio con base imponible positiva y el SIGUIENTE. El libro lo aproxima contando los dos primeros ejercicios con base positiva: coincide con la ley salvo que entre ellos haya un ejercicio en pérdidas
A38: Impuesto de Sociedades, tipo general | B38: 0.25 | C38: A partir del tercer ejercicio con base positiva. Es el tipo general del art. 29.1 LIS: si tu cifra de negocios queda por debajo de 1 M € (microempresa) o de 10 M € (reducida dimensión), desde 2025 hay tipos más bajos que se implantan de forma gradual; confirma el de tu ejercicio con tu asesor y cámbialo aquí
A39: IVA repercutido de restauración | B39: 0.1 | C39: Tipo reducido de hostelería
A40: IVA repercutido/soportado general | B40: 0.21 | C40: Tipo general. En este libro lo usan dos cosas: el IVA que soportas al comprar el alcohol (el proveedor lo factura al 21 %) y el que repercutes por el alcohol que sale por delivery (es una entrega de bienes). El alcohol servido en sala va al reducido: su tipo está en el bloque de desglose del IVA. Suministros, equipamiento y servicios tienen su tipo en la celda de abajo. El libro manda al general sólo el alcohol: si compras refrescos o zumos con azúcares añadidos, su factura también va al 21 % (art. 91.Uno.1.1.º de la Ley 37/1992)
A41: IVA soportado en compras e inversión | B41: 0.21 | C41: Recuperable vía modelo 303, pero hay que adelantarlo
A42: Bases negativas de ejercicios anteriores (€) | B42: 0 | C42: Pérdidas pendientes de compensar al empezar (art. 26 LIS)
A43: AMORTIZACIÓN
A44: Vida útil de obra e instalaciones (años) | B44: 10 | C44: Obra, instalaciones y decoración. Coeficientes de la tabla del art. 12.1 LIS: confírmalo con tu asesor
A45: Vida útil de maquinaria y mobiliario (años) | B45: 10 | C45: Maquinaria de cocina, mobiliario y equipos. El coeficiente lineal máximo de la tabla del art. 12.1 LIS es del 12 % para maquinaria y del 10 % para mobiliario: por debajo de 9-10 años el exceso no es deducible. Confírmalo con tu asesor
A47: CRECIMIENTO Y ACTUALIZACIÓN DE COSTES
A48: Subida anual de los costes fijos | B48: 0 | C48: A CERO: las tres columnas están en euros del año 1 (términos reales). Súbela si quieres proyectar en euros corrientes
A49: ARRANQUE Y AFORO
A50: Rotaciones al día implícitas (calculado) | B50: =IFERROR($B$4/$B$51,"") -> 1.4285714 | C50: =IFERROR("Son "&TEXT(INT(ROUND(B50,1)),"0")&","&TEXT(ROUND(MOD(ROUND(B50,1),1)*10,0),"0")&" servicios por plaza y día sobre las "&TEXT($B$51,"0")&" plazas de la celda de arriba. El documento de este plan pide un MÍNIMO de 1,8 rotaciones por mesa y servicio en temporada alta: compáralo con tu horario real antes de darlo por bueno.","") -> Son 1,4 servicios por plaza y día sobre las 56 plazas de la celda de arriba. El documento de este plan pide un MÍNIMO de 1,8 rotaciones por mesa y servicio en temporada alta: compáralo con tu horario real antes de darlo por bueno.
A51: Aforo del local (plazas sentadas + barra) | B51: 56 | C51: De aquí sale la rotación implícita: cubiertos/día ÷ aforo. Cuéntalo sobre el plano de tu local, no lo copies
A52: Actividad del mes 1 sobre la de crucero | B52: 0.55 | C52: Un local que abre no factura desde el primer día lo mismo que a los seis meses. Con 100 % se elimina la rampa y el año 1 se proyecta a velocidad de crucero
A53: Meses hasta alcanzar el régimen de crucero | B53: 6 | C53: La rampa sube en línea recta desde el porcentaje de arriba hasta el 100 % en este número de meses
A54: Meses de alquiler ANTES de abrir (obra y licencias) | B54: 1 | C54: El local se paga desde que se firma. Estos meses son inversión: NO se solapan con el P&L, que arranca el día de la apertura
A55: Imprevistos sobre las partidas de OBRA del bloque de local (%) | B55: 0.1 | C55: Colchón sobre la partida de obra y acondicionamiento. Un banco no financia una reforma sin él
A57: COBROS, PAGOS Y DESGLOSE DEL IVA
A58: Días medios de cobro | B58: 0 | C58: En barra y sala se cobra al contado (0 días). Súbelo si trabajas con plataformas de reserva o de reparto, que liquidan a D+1/D+30
A59: Días medios de pago a proveedor | B59: 30 | C59: Lo que te financian tus proveedores. Es lo primero que se pierde si te retrasas en un pago
A60: Mes de la paga extra de verano | B60: 7 | C60: Mes del año (1-12) en el que sale de caja la primera paga extra
A61: Mes de la paga extra de Navidad | B61: 12 | C61: Mes del año (1-12) en el que sale de caja la segunda paga extra
A62: Bebida ALCOHÓLICA sobre el total de bebida | B62: 0.6 | C62: Peso del alcohol dentro de la línea de bebida. Se usa igual en ventas y en compras, y es una aproximación (el alcohol suele pesar algo más en el coste que en la venta). En sala todo se repercute al 10 %, refrescos incluidos. En la factura del proveedor, el alcohol va al tipo general; el agua, el café y los zumos naturales al 10 %; los refrescos y zumos con azúcares o edulcorantes añadidos al 21 % desde 2021, que el libro aproxima al 10 %
A63: IVA de la bebida ALCOHÓLICA servida en sala | B63: 0.1 | C63: 10 %, igual que el resto del consumo en sala: el art. 91.Uno.2.2.º de la Ley 37/1992 del IVA grava al tipo reducido los servicios de hostelería y «el suministro de comidas y bebidas para consumir en el acto», sin excluir el alcohol. El 21 % es el tipo GENERAL y, fuera del consumo en el acto, alcanza al alcohol y también a los refrescos y zumos con azúcares o edulcorantes añadidos vendidos para llevar o a domicilio (art. 91.Uno.1.1.º de la misma ley). El libro lo aplica sólo a la parte ALCOHÓLICA de la bebida que sale por el canal de la celda «Ventas por delivery sobre el total»; los refrescos azucarados repartidos irían también al general y el libro no los separa
A64: UMBRALES Y SUELOS DE CONTROL
A65: DSCR mínimo aceptable | B65: 1 | C65: Por debajo de 1 el negocio no genera para pagar el préstamo. Ponlo en el covenant que te exija tu banco
A66: DSCR objetivo (verde) | B66: 1.25 | C66: Lo que suele pedir una entidad para dar el préstamo sin garantías adicionales
A67: Holgura mínima sobre el punto de equilibrio | B67: 0.15 | C67: Cuánto deben superar las ventas previstas a las del equilibrio de caja (costes fijos y cuota del préstamo). La caída que aguantas es algo menor: con un 15 % de holgura, un 13 % de lo previsto
A68: Suelo salarial anual del convenio provincial (€) | B68: 0 | C68: El convenio PROVINCIAL de hostelería, no el SMI, es el suelo real. Cópialo de la tabla salarial de tu provincia; con 0 el semáforo compara sólo contra el SMI

Sheet 1. Inversión Inicial
A1: ChefBusiness Consultoría Gastronómica
A2: Inversión Inicial — Bar-Restaurante
A3: Plan de Negocio: Bar-Restaurante / Restaurante Casual — España 2026
A5: Concepto | B5: Importe | C5: % s/inversión | D5: Notas | E5: ¿Lleva IVA?
A6: LOCAL Y ACONDICIONAMIENTO | B6: =IFERROR(IF(COUNT(B7:B13)=0,"",SUM(B7:B13)),"") -> 53650 | C6: =IFERROR(B6/$B$48,"") -> 0.29969589
A7: Honorarios inmobiliaria | B7: 1500 | C7: =IFERROR(B7/$B$48,"") -> 0.0083791955 | D7: Medio mes de alquiler | E7: Sí
A8: Obra civil y reforma local | B8: 25000 | C8: =IFERROR(B8/$B$48,"") -> 0.13965326 | D8: Cocina, extracción, instalaciones, suelo, pintura | E8: Sí
A9: Proyecto técnico + licencia actividad | B9: 3500 | C9: =IFERROR(B9/$B$48,"") -> 0.019551456 | D9: Ingeniero + tasas ayuntamiento | E9: Sí
A10: Decoración e interiorismo | B10: 8000 | C10: =IFERROR(B10/$B$48,"") -> 0.044689042 | D10: Mobiliario sala, iluminación, rotulación | E10: Sí
A11: Fianza del alquiler | B11: =IFERROR(IF('0. Supuestos'!$B$24="","",'0. Supuestos'!$B$24*'0. Supuestos'!$B$25),"") -> 9000 | C11: =IFERROR(B11/$B$48,"") -> 0.050275173 | D11: =IFERROR(""&TEXT('0. Supuestos'!$B$25,"0")&" meses de renta, al tipo de la hoja de Supuestos. Es un activo recuperable al cerrar: ni se amortiza ni lleva IVA","") -> 3 meses de renta, al tipo de la hoja de Supuestos. Es un activo recuperable al cerrar: ni se amortiza ni lleva IVA | E11: No
A12: Alquiler de los meses previos a la apertura | B12: =IFERROR(IF('0. Supuestos'!$B$24="","",'0. Supuestos'!$B$24*'0. Supuestos'!$B$54),"") -> 3000 | C12: =IFERROR(B12/$B$48,"") -> 0.016758391 | D12: =IFERROR("Renta "&IF('0. Supuestos'!$B$54=1,"del mes","de los "&TEXT('0. Supuestos'!$B$54,"0")&" meses")&" de obra y licencias. NO se solapa con el P&L, que arranca el día de la apertura: los doce meses del P&L son los doce de explotación","") -> Renta del mes de obra y licencias. NO se solapa con el P&L, que arranca el día de la apertura: los doce meses del P&L son los doce de explotación | E12: Sí
A13: Imprevistos de obra y acondicionamiento | B13: =IFERROR(IF(COUNT(B8,B9,B10)=0,"",ROUND((B8+B9+B10)*'0. Supuestos'!$B$55,0)),"") -> 3650 | C13: =IFERROR(B13/$B$48,"") -> 0.020389376 | D13: =IFERROR("Al "&TEXT('0. Supuestos'!$B$55,"0%")&" de las partidas de OBRA Y ACONDICIONAMIENTO de este bloque (Obra civil y reforma local, Proyecto técnico + licencia actividad y Decoración e interiorismo), no del bloque entero: el resto de partidas del bloque quedan fuera. Un banco no "&"financia una reforma sin colchón: el porcentaje está en la hoja de Supuestos","") -> Al 10% de las partidas de OBRA Y ACONDICIONAMIENTO de este bloque (Obra civil y reforma local, Proyecto técnico + licencia actividad y Decoración e interiorismo), no del bloque entero: el resto de partidas del bloque quedan fuera. Un banco no financia una reforma sin colchón: el porcentaje está en la hoja de Supuestos | E13: Sí
A14: EQUIPAMIENTO COCINA | B14: =IFERROR(IF(COUNT(B15:B24)=0,"",SUM(B15:B24)),"") -> 25700 | C14: =IFERROR(B14/$B$48,"") -> 0.14356355
A15: Cocina industrial (fuegos + plancha) | B15: 4500 | C15: =IFERROR(B15/$B$48,"") -> 0.025137586 | D15: 4 fuegos + plancha 80cm | E15: Sí
A16: Horno mixto (convección + vapor) | B16: 5500 | C16: =IFERROR(B16/$B$48,"") -> 0.030723717 | D16: 10 bandejas GN 1/1 | E16: Sí
A17: Freidora profesional | B17: 800 | C17: =IFERROR(B17/$B$48,"") -> 0.0044689042 | D17: 2 cubetas x 8L | E17: Sí
A18: Mesa refrigerada bajo mostrador | B18: 2200 | C18: =IFERROR(B18/$B$48,"") -> 0.012289487 | D18: 3 puertas, 400L | E18: Sí
A19: Cámara frigorífica | B19: 3500 | C19: =IFERROR(B19/$B$48,"") -> 0.019551456 | D19: Positiva + negativa | E19: Sí
A20: Campana extractora + motor | B20: 3000 | C20: =IFERROR(B20/$B$48,"") -> 0.016758391 | D20: Instalación incluida | E20: Sí
A21: Lavavajillas industrial | B21: 2800 | C21: =IFERROR(B21/$B$48,"") -> 0.015641165 | D21: Cesta 50x50 | E21: Sí
A22: Menaje y utensilios cocina | B22: 2000 | C22: =IFERROR(B22/$B$48,"") -> 0.011172261 | D22: Sartenes, ollas, GN, cuchillos, tablas | E22: Sí
A23: Fregadero industrial doble seno | B23: 600 | C23: =IFERROR(B23/$B$48,"") -> 0.0033516782 | E23: Sí
A24: Estanterías inox almacén | B24: 800 | C24: =IFERROR(B24/$B$48,"") -> 0.0044689042 | D24: 4 niveles x 3 unidades | E24: Sí
A25: EQUIPAMIENTO SALA Y BARRA | B25: =IFERROR(IF(COUNT(B26:B35)=0,"",SUM(B26:B35)),"") -> 21760 | C25: =IFERROR(B25/$B$48,"") -> 0.1215542
A26: Barra de bar (fabricación + instalación) | B26: 4000 | C26: =IFERROR(B26/$B$48,"") -> 0.022344521 | D26: 5 metros lineales | E26: Sí
A27: Mesas y sillas (12 mesas x 4 sillas) | B27: 3600 | C27: =IFERROR(B27/$B$48,"") -> 0.020110069 | D27: Set 120 €/mesa | E27: Sí
A28: Taburetes barra (8 unidades) | B28: 960 | C28: =IFERROR(B28/$B$48,"") -> 0.0053626851 | D28: 120 €/ud | E28: Sí
A29: Cafetera espresso profesional | B29: 3500 | C29: =IFERROR(B29/$B$48,"") -> 0.019551456 | D29: 2 grupos | E29: Sí
A30: Molinillo café profesional | B30: 500 | C30: =IFERROR(B30/$B$48,"") -> 0.0027930652 | E30: Sí
A31: Grifo cerveza (2 tomas) | B31: 1200 | C31: =IFERROR(B31/$B$48,"") -> 0.0067033564 | D31: Instalación + barril inicial | E31: Sí
A32: Vinoteca / nevera vinos | B32: 800 | C32: =IFERROR(B32/$B$48,"") -> 0.0044689042 | D32: 24 botellas | E32: Sí
A33: Cristalería, vajilla, cubertería | B33: 1500 | C33: =IFERROR(B33/$B$48,"") -> 0.0083791955 | D33: Servicio completo 50 pax | E33: Sí
A34: TPV + software hostelería | B34: 1500 | C34: =IFERROR(B34/$B$48,"") -> 0.0083791955 | D34: Terminal + licencia anual | E34: Sí
A35: Mobiliario y toldo de terraza | B35: 4200 | C35: =IFERROR(B35/$B$48,"") -> 0.023461747 | D35: Mesas, sillas, toldo y estufas para las plazas de terraza que describe el plan. Ponlo a 0 si tu local no tiene terraza o si la licencia no sale | E35: Sí
A36: MARKETING Y LANZAMIENTO | B36: =IFERROR(IF(COUNT(B37:B39)=0,"",SUM(B37:B39)),"") -> 4000 | C36: =IFERROR(B36/$B$48,"") -> 0.022344521
A37: Diseño marca e identidad visual | B37: 1500 | C37: =IFERROR(B37/$B$48,"") -> 0.0083791955 | D37: Logo, carta, señalética | E37: Sí
A38: Web + Google My Business | B38: 1000 | C38: =IFERROR(B38/$B$48,"") -> 0.0055861303 | D38: Página básica + ficha GMB | E38: Sí
A39: Campaña lanzamiento RRSS + inauguración | B39: 1500 | C39: =IFERROR(B39/$B$48,"") -> 0.0083791955 | D39: 3 meses iniciales | E39: Sí
A40: GASTOS LEGALES Y CONSTITUCIÓN | B40: =IFERROR(IF(COUNT(B41:B42)=0,"",SUM(B41:B42)),"") -> 1100 | C40: =IFERROR(B40/$B$48,"") -> 0.0061447433
A41: Constitución SL (notaría + registro) | B41: 600 | C41: =IFERROR(B41/$B$48,"") -> 0.0033516782 | D41: Capital social mín. 1 € (Ley Crea y Crece) | E41: No
A42: Licencias y permisos varios | B42: 500 | C42: =IFERROR(B42/$B$48,"") -> 0.0027930652 | E42: No
A43: EXISTENCIAS INICIALES | B43: =IFERROR(IF(COUNT(B44:B45)=0,"",SUM(B44:B45)),"") -> 12000 | C43: =IFERROR(B43/$B$48,"") -> 0.067033564
A44: Primera compra de despensa y cámaras | B44: 6500 | C44: =IFERROR(B44/$B$48,"") -> 0.036309847 | D44: Materia prima para arrancar el servicio: seco, fresco y congelado. NO se amortiza, es circulante | E44: Sí
A45: Primera compra de bodega y barra | B45: 5500 | C45: =IFERROR(B45/$B$48,"") -> 0.030723717 | D45: Vinos, cervezas, destilados y refrescos de la carta de salida. Pide depósito a tus distribuidores antes de presupuestarlo | E45: Sí
A46: FONDO DE MANIOBRA | B46: =IFERROR(IF(B47="","",B47),"") -> 60804.8 | C46: =IFERROR(B46/$B$48,"") -> 0.33966354
A47: Colchón operativo hasta alcanzar el equilibrio | B47: =IFERROR(IF('0. Supuestos'!$B$35*('2. P&L 3 Años'!$B$40-'2. P&L 3 Años'!$B$38)=0,"",'0. Supuestos'!$B$35*('2. P&L 3 Años'!$B$40-'2. P&L 3 Años'!$B$38)/12),"") -> 60804.8 | C47: =IFERROR(B47/$B$48,"") -> 0.33966354 | D47: =IFERROR("Cubre "&TEXT('0. Supuestos'!$B$35,"0")&IF('0. Supuestos'!$B$35=1," mes"," meses")&" de costes fijos DE CAJA del año 1 (los del P&L menos la amortización, que no se paga), que es el mínimo que exigen las Instrucciones de este libro","") -> Cubre 3 meses de costes fijos DE CAJA del año 1 (los del P&L menos la amortización, que no se paga), que es el mínimo que exigen las Instrucciones de este libro | E47: No
A48: INVERSIÓN TOTAL (suma de los bloques) | B48: =IFERROR(B6+B14+B25+B36+B40+B43+B46,"") -> 179014.8 | D48: =IFERROR("Los porcentajes de la columna C se leen sobre esta cifra, que incluye el fondo de maniobra ("&TEXT(C46,"0%")&" del total). Para comparar el desglose con otro plan, usa la fila de CAPEX de abajo.","") -> Los porcentajes de la columna C se leen sobre esta cifra, que incluye el fondo de maniobra (34% del total). Para comparar el desglose con otro plan, usa la fila de CAPEX de abajo.
A49: CAPEX (inversión sin el fondo de maniobra) | B49: =IFERROR(B48-B46,"") -> 118210 | D49: Es lo que se compra: obra, equipamiento, lanzamiento y gastos de constitución. El colchón de caja no es inversión, es circulante
A50: IVA soportado sobre la inversión (recuperable) | B50: =IFERROR(IF(B48="","",SUMIF($E$7:$E$45,"Sí",$B$7:$B$45)*'0. Supuestos'!$B$41),"") -> 22703.1 | D50: =IFERROR("Al "&TEXT('0. Supuestos'!$B$41,"0%")&" sobre las partidas marcadas con «Sí» en la columna de IVA. Las tasas y licencias no están sujetas y los seguros están exentos (art. 20.Uno.16 LIVA). Las tasas y aranceles registrales no llevan IVA; los honorarios de notaría y gestoría sí "&"(21 %, deducible). Se recupera con el modelo 303, pero hay que adelantarlo","") -> Al 21% sobre las partidas marcadas con «Sí» en la columna de IVA. Las tasas y licencias no están sujetas y los seguros están exentos (art. 20.Uno.16 LIVA). Las tasas y aranceles registrales no llevan IVA; los honorarios de notaría y gestoría sí (21 %, deducible). Se recupera con el modelo 303, pero hay que adelantarlo
A51: NECESIDAD TOTAL DE CAJA AL ARRANQUE | B51: =IFERROR(B48+B50,"") -> 201717.9 | D51: Es la cifra que tiene que cubrir la hoja de Financiación
A52: BASES DE AMORTIZACIÓN (no suman a la inversión)
A53: Obra, instalaciones y acondicionamiento | B53: =IFERROR(IF(B8="","",B8+B9+B10+B13+B20+B26),"") -> 47150 | D53: =IFERROR("Se amortiza en "&TEXT('0. Supuestos'!$B$44,"0")&" años","") -> Se amortiza en 10 años
A54: Maquinaria, mobiliario y equipos | B54: =IFERROR(IF(B15="","",B15+B16+B17+B18+B19+B21+B22+B23+B24+B27+B28+B29+B30+B31+B32+B33+B34+B35),"") -> 40460 | D54: =IFERROR("Se amortiza en "&TEXT('0. Supuestos'!$B$45,"0")&" años","") -> Se amortiza en 10 años
A55: Amortización anual del inmovilizado | B55: =IFERROR(B53/MAX(1,'0. Supuestos'!$B$44)+B54/MAX(1,'0. Supuestos'!$B$45),"") -> 8761 | D55: =IFERROR("No se amortizan, por no ser inmovilizado, Honorarios inmobiliaria, Fianza del alquiler, Alquiler de los meses previos a la apertura, Diseño marca e identidad visual, Web + Google My Business, Campaña lanzamiento RRSS + inauguración, "&"Constitución SL (notaría + registro), Licencias y permisos varios, Primera compra de despensa y cámaras, Primera compra de bodega y barra ni Colchón operativo hasta alcanzar el equilibrio. Suman "&TEXT(B48-B53-B54,"0")&" € de los "&TEXT(B48,"0")&" € de inversión.","") -> No se amortizan, por no ser inmovilizado, Honorarios inmobiliaria, Fianza del alquiler, Alquiler de los meses previos a la apertura, Diseño marca e identidad visual, Web + Google My Business, Campaña lanzamiento RRSS + inauguración, Constitución SL (notaría + registro), Licencias y permisos varios, Primera compra de despensa y cámaras, Primera compra de bodega y barra ni Colchón operativo hasta alcanzar el equilibrio. Suman 91405 € de los 179015 € de inversión.
A57: NOTA: Todos los importes son estimaciones basadas en precios de mercado en España 2026. Ajusta cada partida a tu situación real.
A58: ChefBusiness.co — Plan de Negocio: Bar-Restaurante

Sheet 2. P&L 3 Años
A1: ChefBusiness Consultoría Gastronómica
A2: Cuenta de Resultados Previsional — 3 Años
A3: Plan de Negocio: Bar-Restaurante / Restaurante Casual — España 2026
A5: Concepto | B5: Año 1 | C5: Año 2 | D5: Año 3 | E5: % s/ventas (año 1) | F5: Notas | G5: Tipo de IVA de la línea (%)
A6: INGRESOS
A7: Cubiertos/día (media) | B7: =IFERROR(IF('0. Supuestos'!$B$4="","",'0. Supuestos'!$B$4),"") -> 80 | C7: =IFERROR(B7*(1+'0. Supuestos'!$B$7),"") -> 88 | D7: =IFERROR(C7*(1+'0. Supuestos'!$B$8),"") -> 93.28 | F7: El crecimiento de los años 2 y 3 está en la hoja de Supuestos
A8: Ticket medio sin IVA | B8: =IFERROR(IF('0. Supuestos'!$B$5="","",'0. Supuestos'!$B$5),"") -> 18.2 | C8: =IFERROR(IF(B8="","",B8),"") -> 18.2 | D8: =IFERROR(IF(C8="","",C8),"") -> 18.2 | F8: Constante en euros del año 1: una subida de precios es una decisión aparte
A9: Días de apertura al año | B9: =IFERROR(IF('0. Supuestos'!$B$6="","",'0. Supuestos'!$B$6),"") -> 310 | C9: =IFERROR(IF(B9="","",B9),"") -> 310 | D9: =IFERROR(IF(C9="","",C9),"") -> 310
A10: INGRESOS TOTALES (sin IVA) | B10: =IFERROR(IF(B7*B8*B9=0,"",B7*B8*B9),"") -> 451360 | C10: =IFERROR(IF(C7*C8*C9=0,"",C7*C8*C9),"") -> 496496 | D10: =IFERROR(IF(D7*D8*D9=0,"",D7*D8*D9),"") -> 526285.76 | E10: =IFERROR(IF(B10="","",1),"") -> 1
A11: Ventas de comida (cocina y barra) | B11: =IFERROR(IF(B10="","",B10*$E$11),"") -> 293384 | C11: =IFERROR(IF(C10="","",C10*$E$11),"") -> 322722.4 | D11: =IFERROR(IF(D10="","",D10*$E$11),"") -> 342085.74 | E11: =IFERROR(IF('0. Supuestos'!$B$11="","",'0. Supuestos'!$B$11),"") -> 0.65 | F11: Menú del mediodía, carta y raciones | G11: =IFERROR(IF(B10="","",'0. Supuestos'!$B$39),"") -> 0.1
A12: Ventas de bebida (cañas, vinos, cafés y copas) | B12: =IFERROR(IF(B10="","",B10*$E$12),"") -> 157976 | C12: =IFERROR(IF(C10="","",C10*$E$12),"") -> 173773.6 | D12: =IFERROR(IF(D10="","",D10*$E$12),"") -> 184200.02 | E12: =IFERROR(IF('0. Supuestos'!$B$12="","",'0. Supuestos'!$B$12),"") -> 0.35 | F12: Se calcula como el resto: comida + bebida = 100 % | G12: =IFERROR(IF(B10="","",('0. Supuestos'!$B$62*((1-'0. Supuestos'!$B$16)*'0. Supuestos'!$B$63+'0. Supuestos'!$B$16*'0. Supuestos'!$B$40)+(1-'0. Supuestos'!$B$62)*'0. Supuestos'!$B$39)),"") -> 0.1
A13: COSTES VARIABLES
A14: Coste de mercancía — comida | B14: =IFERROR(IF(B10="","",B10*'0. Supuestos'!$B$11*'0. Supuestos'!$B$13),"") -> 88015.2 | C14: =IFERROR(IF(C10="","",C10*'0. Supuestos'!$B$11*'0. Supuestos'!$B$13),"") -> 96816.72 | D14: =IFERROR(IF(D10="","",D10*'0. Supuestos'!$B$11*'0. Supuestos'!$B$13),"") -> 102625.72 | E14: =IFERROR(B14/$B$10,"") -> 0.195 | F14: =IFERROR("Al "&TEXT('0. Supuestos'!$B$13,"0%")&" de las ventas de COMIDA, no del total: la bebida tiene su propia línea","") -> Al 30% de las ventas de COMIDA, no del total: la bebida tiene su propia línea | G14: =IFERROR(IF(B10="","",'0. Supuestos'!$B$39),"") -> 0.1
A15: Coste de mercancía — bebida | B15: =IFERROR(IF(B10="","",B10*'0. Supuestos'!$B$12*'0. Supuestos'!$B$14),"") -> 34754.72 | C15: =IFERROR(IF(C10="","",C10*'0. Supuestos'!$B$12*'0. Supuestos'!$B$14),"") -> 38230.192 | D15: =IFERROR(IF(D10="","",D10*'0. Supuestos'!$B$12*'0. Supuestos'!$B$14),"") -> 40524.004 | E15: =IFERROR(B15/$B$10,"") -> 0.077 | F15: =IFERROR("Al "&TEXT('0. Supuestos'!$B$14,"0%")&" de las ventas de BEBIDA","") -> Al 22% de las ventas de BEBIDA | G15: =IFERROR(IF(B10="","",('0. Supuestos'!$B$62*'0. Supuestos'!$B$40+(1-'0. Supuestos'!$B$62)*'0. Supuestos'!$B$39)),"") -> 0.166
A16: Consumibles y envases | B16: =IFERROR(IF(B10="","",B10*'0. Supuestos'!$B$15),"") -> 6770.4 | C16: =IFERROR(IF(C10="","",C10*'0. Supuestos'!$B$15),"") -> 7447.44 | D16: =IFERROR(IF(D10="","",D10*'0. Supuestos'!$B$15),"") -> 7894.2864 | E16: =IFERROR(B16/$B$10,"") -> 0.015 | G16: =IFERROR(IF(B10="","",'0. Supuestos'!$B$41),"") -> 0.21
A17: Comisiones de delivery | B17: =IFERROR(IF(B10="","",B10*'0. Supuestos'!$B$16*'0. Supuestos'!$B$17),"") -> 0 | C17: =IFERROR(IF(C10="","",C10*'0. Supuestos'!$B$16*'0. Supuestos'!$B$17),"") -> 0 | D17: =IFERROR(IF(D10="","",D10*'0. Supuestos'!$B$16*'0. Supuestos'!$B$17),"") -> 0 | E17: =IFERROR(B17/$B$10,"") -> 0 | F17: Sobre las ventas DEL CANAL. Con 0 % de delivery en Supuestos, esta línea vale cero | G17: =IFERROR(IF(B10="","",'0. Supuestos'!$B$41),"") -> 0.21
A18: Comisiones de los medios de pago | B18: =IFERROR(IF(B10="","",B10*'0. Supuestos'!$B$18),"") -> 3610.88 | C18: =IFERROR(IF(C10="","",C10*'0. Supuestos'!$B$18),"") -> 3971.968 | D18: =IFERROR(IF(D10="","",D10*'0. Supuestos'!$B$18),"") -> 4210.2861 | E18: =IFERROR(B18/$B$10,"") -> 0.008 | F18: Las comisiones de los medios de pago están EXENTAS de IVA (art. 20.Uno.18 LIVA): no se deduce nada por ellas | G18: 0
A19: Varios e imprevistos | B19: =IFERROR(IF(B10="","",B10*'0. Supuestos'!$B$28),"") -> 9027.2 | C19: =IFERROR(IF(C10="","",C10*'0. Supuestos'!$B$28),"") -> 9929.92 | D19: =IFERROR(IF(D10="","",D10*'0. Supuestos'!$B$28),"") -> 10525.715 | E19: =IFERROR(B19/$B$10,"") -> 0.02 | F19: =IFERROR("Al "&TEXT('0. Supuestos'!$B$28,"0%")&" de las ventas. Es un coste VARIABLE: sube y baja con la facturación, así que no puede vivir en los costes fijos","") -> Al 2% de las ventas. Es un coste VARIABLE: sube y baja con la facturación, así que no puede vivir en los costes fijos | G19: =IFERROR(IF(B10="","",'0. Supuestos'!$B$41),"") -> 0.21
A20: TOTAL COSTES VARIABLES | B20: =IFERROR(IF(B10="","",SUM(B14:B19)),"") -> 142178.4 | C20: =IFERROR(IF(C10="","",SUM(C14:C19)),"") -> 156396.24 | D20: =IFERROR(IF(D10="","",SUM(D14:D19)),"") -> 165780.01 | E20: =IFERROR(B20/$B$10,"") -> 0.315
A21: MARGEN BRUTO | B21: =IFERROR(IF(B10="","",B10-B20),"") -> 309181.6 | C21: =IFERROR(IF(C10="","",C10-C20),"") -> 340099.76 | D21: =IFERROR(IF(D10="","",D10-D20),"") -> 360505.75 | E21: =IFERROR(B21/$B$10,"") -> 0.685
A22: COSTES FIJOS
A23: Alquiler del local | B23: =IFERROR(IF(B10="","",'0. Supuestos'!$B$24*12),"") -> 36000 | C23: =IFERROR(IF(C10="","",B23*(1+'0. Supuestos'!$B$48)),"") -> 36000 | D23: =IFERROR(IF(D10="","",C23*(1+'0. Supuestos'!$B$48)),"") -> 36000 | E23: =IFERROR(B23/$B$10,"") -> 0.079758951 | F23: El importe mensual está en la hoja de Supuestos; aquí se multiplica por doce. La renta de los meses de obra, que es anterior a la apertura, está en la hoja de Inversión y NO se cuenta dos veces | G23: =IFERROR(IF(B10="","",'0. Supuestos'!$B$41),"") -> 0.21
A24: Personal (nóminas + Seguridad Social) | B24: =IFERROR(IF(B10="","",'5. Personal'!$G$13),"") -> 151939.2 | C24: =IFERROR(IF(C10="","",'5. Personal'!$B$17),"") -> 157939.2 | D24: =IFERROR(IF(D10="","",'5. Personal'!$B$18),"") -> 163939.2 | E24: =IFERROR(B24/$B$10,"") -> 0.33662531 | F24: Sale de la hoja de Personal: es el MISMO número, no una estimación aparte. Los años 2 y 3 suman las INCORPORACIONES declaradas en esa hoja, no un porcentaje de volumen | G24: 0
A25: Suministros (luz, agua, gas) | B25: =IFERROR(IF(B10="","",'0. Supuestos'!$B$26*12),"") -> 21600 | C25: =IFERROR(IF(C10="","",B25*(1+'0. Supuestos'!$B$48)),"") -> 21600 | D25: =IFERROR(IF(D10="","",C25*(1+'0. Supuestos'!$B$48)),"") -> 21600 | E25: =IFERROR(B25/$B$10,"") -> 0.04785537 | F25: Luz y gas van al 21 %; la factura del agua, al 10 %. El libro aplica a toda esta partida el tipo de la columna de al lado (21 %): si el agua pesa mucho en tu local, sepárala en su línea | G25: =IFERROR(IF(B10="","",'0. Supuestos'!$B$41),"") -> 0.21
A26: Seguros (RC + multirriesgo) | B26: =IFERROR(IF(B10="","",'0. Supuestos'!$B$27),"") -> 2000 | C26: =IFERROR(IF(C10="","",B26*(1+'0. Supuestos'!$B$48)),"") -> 2000 | D26: =IFERROR(IF(D10="","",C26*(1+'0. Supuestos'!$B$48)),"") -> 2000 | E26: =IFERROR(B26/$B$10,"") -> 0.0044310528 | F26: Las operaciones de seguro están EXENTAS de IVA (art. 20.Uno.16 LIVA): la prima no lleva IVA deducible | G26: 0
A27: Gestoría + contabilidad | B27: 1800 | C27: =IFERROR(IF(C10="","",B27*(1+'0. Supuestos'!$B$48)),"") -> 1800 | D27: =IFERROR(IF(D10="","",C27*(1+'0. Supuestos'!$B$48)),"") -> 1800 | E27: =IFERROR(B27/$B$10,"") -> 0.0039879475 | G27: =IFERROR(IF(B10="","",'0. Supuestos'!$B$41),"") -> 0.21
A28: Marketing y publicidad | B28: 6000 | C28: =IFERROR(IF(C10="","",B28*(1+'0. Supuestos'!$B$48)),"") -> 6000 | D28: =IFERROR(IF(D10="","",C28*(1+'0. Supuestos'!$B$48)),"") -> 6000 | E28: =IFERROR(B28/$B$10,"") -> 0.013293158 | G28: =IFERROR(IF(B10="","",'0. Supuestos'!$B$41),"") -> 0.21
A29: Mantenimiento y reparaciones | B29: 2400 | C29: =IFERROR(IF(C10="","",B29*(1+'0. Supuestos'!$B$48)),"") -> 2400 | D29: =IFERROR(IF(D10="","",C29*(1+'0. Supuestos'!$B$48)),"") -> 2400 | E29: =IFERROR(B29/$B$10,"") -> 0.0053172634 | G29: =IFERROR(IF(B10="","",'0. Supuestos'!$B$41),"") -> 0.21
A30: Software (TPV, reservas, RRSS) | B30: 1800 | C30: =IFERROR(IF(C10="","",B30*(1+'0. Supuestos'!$B$48)),"") -> 1800 | D30: =IFERROR(IF(D10="","",C30*(1+'0. Supuestos'!$B$48)),"") -> 1800 | E30: =IFERROR(B30/$B$10,"") -> 0.0039879475 | G30: =IFERROR(IF(B10="","",'0. Supuestos'!$B$41),"") -> 0.21
A31: Limpieza, lavandería y lencería | B31: 3600 | C31: =IFERROR(IF(C10="","",B31*(1+'0. Supuestos'!$B$48)),"") -> 3600 | D31: =IFERROR(IF(D10="","",C31*(1+'0. Supuestos'!$B$48)),"") -> 3600 | E31: =IFERROR(B31/$B$10,"") -> 0.0079758951 | F31: Mantelería, paños y uniformes. Pide presupuesto en tu zona: es un importe orientativo y editable | G31: =IFERROR(IF(B10="","",'0. Supuestos'!$B$41),"") -> 0.21
A32: Gestión de residuos y de aceite vegetal usado | B32: 1200 | C32: =IFERROR(IF(C10="","",B32*(1+'0. Supuestos'!$B$48)),"") -> 1200 | D32: =IFERROR(IF(D10="","",C32*(1+'0. Supuestos'!$B$48)),"") -> 1200 | E32: =IFERROR(B32/$B$10,"") -> 0.0026586317 | F32: Gestor autorizado. Lo pide la inspección y el aceite no puede ir al desagüe | G32: =IFERROR(IF(B10="","",'0. Supuestos'!$B$41),"") -> 0.21
A33: Desinsectación, desratización y desinfección (DDD) | B33: 900 | C33: =IFERROR(IF(C10="","",B33*(1+'0. Supuestos'!$B$48)),"") -> 900 | D33: =IFERROR(IF(D10="","",C33*(1+'0. Supuestos'!$B$48)),"") -> 900 | E33: =IFERROR(B33/$B$10,"") -> 0.0019939738 | F33: Empresa inscrita en el ROESB; forma parte del plan APPCC | G33: =IFERROR(IF(B10="","",'0. Supuestos'!$B$41),"") -> 0.21
A34: Derechos de autor por música ambiental | B34: 900 | C34: =IFERROR(IF(C10="","",B34*(1+'0. Supuestos'!$B$48)),"") -> 900 | D34: =IFERROR(IF(D10="","",C34*(1+'0. Supuestos'!$B$48)),"") -> 900 | E34: =IFERROR(B34/$B$10,"") -> 0.0019939738 | F34: SGAE y AGEDI-AIE son dos licencias distintas; el importe depende de los metros y del aforo | G34: =IFERROR(IF(B10="","",'0. Supuestos'!$B$41),"") -> 0.21
A35: Prevención de riesgos laborales y vigilancia de la salud | B35: 600 | C35: =IFERROR(IF(C10="","",B35*(1+'0. Supuestos'!$B$48)),"") -> 600 | D35: =IFERROR(IF(D10="","",C35*(1+'0. Supuestos'!$B$48)),"") -> 600 | E35: =IFERROR(B35/$B$10,"") -> 0.0013293158 | F35: El plan de prevención es obligatorio; el proveedor externo, no (art. 30.5 de la Ley 31/1995) | G35: =IFERROR(IF(B10="","",'0. Supuestos'!$B$41),"") -> 0.21
A36: Comisiones de reservas online | B36: 2400 | C36: =IFERROR(IF(C10="","",B36*(1+'0. Supuestos'!$B$48)),"") -> 2400 | D36: =IFERROR(IF(D10="","",C36*(1+'0. Supuestos'!$B$48)),"") -> 2400 | E36: =IFERROR(B36/$B$10,"") -> 0.0053172634 | F36: TheFork y similares cobran por comensal sentado: mira la letra pequeña antes de firmar | G36: =IFERROR(IF(B10="","",'0. Supuestos'!$B$41),"") -> 0.21
A37: Reposición de menaje, cristalería y vajilla | B37: 2400 | C37: =IFERROR(IF(C10="","",B37*(1+'0. Supuestos'!$B$48)),"") -> 2400 | D37: =IFERROR(IF(D10="","",C37*(1+'0. Supuestos'!$B$48)),"") -> 2400 | E37: =IFERROR(B37/$B$10,"") -> 0.0053172634 | F37: Roturas del ejercicio. En un casual con barra se rompe más de lo que se presupuesta | G37: =IFERROR(IF(B10="","",'0. Supuestos'!$B$41),"") -> 0.21
A38: Amortización del inmovilizado | B38: =IFERROR(IF(B10="","",'1. Inversión Inicial'!$B$55),"") -> 8761 | C38: =IFERROR(IF(C10="","",B38),"") -> 8761 | D38: =IFERROR(IF(D10="","",B38),"") -> 8761 | E38: =IFERROR(B38/$B$10,"") -> 0.019410227 | F38: Sale de las bases de amortización de la hoja de Inversión: sólo inmovilizado real. NO sube con el IPC: es una cuota sobre el coste HISTÓRICO del inmovilizado | G38: 0
A39: Gastos financieros (intereses del préstamo) | B39: =IFERROR(IF(B10="","",'7. Financiación'!$B$44),"") -> 7680 | C39: =IFERROR(IF(C10="","",'7. Financiación'!$B$46),"") -> 7680 | D39: =IFERROR(IF(D10="","",'7. Financiación'!$B$48),"") -> 6578.975 | E39: =IFERROR(B39/$B$10,"") -> 0.017015243 | F39: Sólo los INTERESES son gasto. La devolución del principal va en la hoja de Tesorería | G39: 0
A40: TOTAL COSTES FIJOS | B40: =IFERROR(IF(B10="","",SUM(B23:B39)),"") -> 251980.2 | C40: =IFERROR(IF(C10="","",SUM(C23:C39)),"") -> 257980.2 | D40: =IFERROR(IF(D10="","",SUM(D23:D39)),"") -> 262879.18 | E40: =IFERROR(B40/$B$10,"") -> 0.55826879
A41: IVA soportado de los costes variables | B41: =IFERROR(IF(B10="","",SUMPRODUCT(B14:B19,G14:G19)),"") -> 17888.3 | C41: =IFERROR(IF(C10="","",SUMPRODUCT(C14:C19,G14:G19)),"") -> 19677.129 | D41: =IFERROR(IF(D10="","",SUMPRODUCT(D14:D19,G14:G19)),"") -> 20857.757 | F41: Cada línea a SU tipo, leído de la columna de al lado. Es lo que la hoja de Tesorería paga de más a los proveedores y luego se deduce
A42: IVA soportado de los costes fijos | B42: =IFERROR(IF(B10="","",SUMPRODUCT(B23:B39,G23:G39)),"") -> 17136 | C42: =IFERROR(IF(C10="","",SUMPRODUCT(C23:C39,G23:G39)),"") -> 17136 | D42: =IFERROR(IF(D10="","",SUMPRODUCT(D23:D39,G23:G39)),"") -> 17136
A43: RESULTADO ANTES DE IMPUESTOS | B43: =IFERROR(IF(B10="","",B21-B40),"") -> 57201.4 | C43: =IFERROR(IF(C10="","",C21-C40),"") -> 82119.56 | D43: =IFERROR(IF(D10="","",D21-D40),"") -> 97626.571 | E43: =IFERROR(B43/$B$10,"") -> 0.12673121
A44: Bases negativas pendientes al inicio | B44: =IFERROR(IF(B10="","",'0. Supuestos'!$B$42),"") -> 0 | C44: =IFERROR(IF(C10="","",B49),"") -> 0 | D44: =IFERROR(IF(D10="","",C49),"") -> 0 | F44: Art. 26 LIS: las pérdidas de un ejercicio se compensan con los beneficios de los siguientes
A45: Base imponible (después de compensar) | B45: =IFERROR(IF(B10="","",MAX(0,B43-B44)),"") -> 57201.4 | C45: =IFERROR(IF(C10="","",MAX(0,C43-C44)),"") -> 82119.56 | D45: =IFERROR(IF(D10="","",MAX(0,D43-D44)),"") -> 97626.571
A46: Ejercicios con base positiva (acumulado) | B46: =IFERROR(IF(B10="","",IF(B45>0,1,0)),"") -> 1 | C46: =IFERROR(IF(C10="","",B46+IF(C45>0,1,0)),"") -> 2 | D46: =IFERROR(IF(D10="","",C46+IF(D45>0,1,0)),"") -> 3
A47: Tipo de Impuesto de Sociedades aplicado | B47: =IFERROR(IF(B10="","",IF(B45<=0,"",IF(B46<=2,'0. Supuestos'!$B$37,'0. Supuestos'!$B$38))),"") -> 0.15 | C47: =IFERROR(IF(C10="","",IF(C45<=0,"",IF(C46<=2,'0. Supuestos'!$B$37,'0. Supuestos'!$B$38))),"") -> 0.15 | D47: =IFERROR(IF(D10="","",IF(D45<=0,"",IF(D46<=2,'0. Supuestos'!$B$37,'0. Supuestos'!$B$38))),"") -> 0.25 | F47: Art. 29.1 LIS: el 15 % de entidad de nueva creación se aplica al PRIMER ejercicio con base positiva y al SIGUIENTE, no al primer año de vida. El libro lo aproxima contando los dos primeros ejercicios con base positiva
A48: Impuesto de Sociedades | B48: =IFERROR(IF(B10="","",IF(B47="",0,B45*B47)),"") -> 8580.21 | C48: =IFERROR(IF(C10="","",IF(C47="",0,C45*C47)),"") -> 12317.934 | D48: =IFERROR(IF(D10="","",IF(D47="",0,D45*D47)),"") -> 24406.643
A49: Bases negativas pendientes al cierre | B49: =IFERROR(IF(B10="","",MAX(0,B44-B43)),"") -> 0 | C49: =IFERROR(IF(C10="","",MAX(0,C44-C43)),"") -> 0 | D49: =IFERROR(IF(D10="","",MAX(0,D44-D43)),"") -> 0
A50: RESULTADO NETO | B50: =IFERROR(IF(B10="","",B43-B48),"") -> 48621.19 | C50: =IFERROR(IF(C10="","",C43-C48),"") -> 69801.626 | D50: =IFERROR(IF(D10="","",D43-D48),"") -> 73219.928 | E50: =IFERROR(B50/$B$10,"") -> 0.10772153
A51: RATIOS CLAVE
A52: Ratio | B52: Año 1 | C52: Año 2 | D52: Año 3 | E52: Umbral | F52: Comentario
A53: Margen bruto / Ventas | B53: =IFERROR(IF(B10="","",B21/B10),"") -> 0.685 | C53: =IFERROR(IF(C10="","",C21/C10),"") -> 0.685 | D53: =IFERROR(IF(D10="","",D21/D10),"") -> 0.685 | E53: 0.65 | F53: Por debajo, revisa precios de carta y escandallos
A54: Coste de mercancía (comida + bebida) | B54: =IFERROR(IF(B10="","",B14+B15),"") -> 122769.92 | C54: =IFERROR(IF(C10="","",C14+C15),"") -> 135046.91 | D54: =IFERROR(IF(D10="","",D14+D15),"") -> 143149.73
A55: Coste de mercancía / Ventas | B55: =IFERROR(IF(B10="","",B54/B10),"") -> 0.272 | C55: =IFERROR(IF(C10="","",C54/C10),"") -> 0.272 | D55: =IFERROR(IF(D10="","",D54/D10),"") -> 0.272 | E55: 0.32 | F55: Techo del propio libro: «Food cost objetivo 28-32 %»
A56: Coste de personal / Ventas | B56: =IFERROR(IF(B10="","",B24/B10),"") -> 0.33662531 | C56: =IFERROR(IF(C10="","",C24/C10),"") -> 0.3181077 | D56: =IFERROR(IF(D10="","",D24/D10),"") -> 0.31150225 | E56: 0.34 | F56: Techo MÁS ESTRICTO de los que publica este producto: «el labor cost no debe superar el 34 %». Es el que manda
A57: Alquiler / Ventas | B57: =IFERROR(IF(B10="","",B23/B10),"") -> 0.079758951 | C57: =IFERROR(IF(C10="","",C23/C10),"") -> 0.072508137 | D57: =IFERROR(IF(D10="","",D23/D10),"") -> 0.068403903 | E57: 0.1 | F57: Techo del propio libro: «Alquiler: no superar 8-10 % de los ingresos»
A58: Resultado neto / Ventas | B58: =IFERROR(IF(B10="","",B50/B10),"") -> 0.10772153 | C58: =IFERROR(IF(C10="","",C50/C10),"") -> 0.1405885 | D58: =IFERROR(IF(D10="","",D50/D10),"") -> 0.1391258 | E58: 0.05 | F58: Suelo del propio libro: «Margen neto medio sector: 5-10 %»
A59: Punto de equilibrio alcanzado | B59: =IFERROR(IF(B10="","",IF(B10>='3. Punto Equilibrio'!$B$17,"Sí","No")),"") -> Sí | C59: =IFERROR(IF(C10="","",IF(C10>='3. Punto Equilibrio'!$C$17,"Sí","No")),"") -> Sí | D59: =IFERROR(IF(D10="","",IF(D10>='3. Punto Equilibrio'!$D$17,"Sí","No")),"") -> Sí | F59: Compara las ventas de CADA año con el umbral de ese mismo año, que calcula la hoja de Punto de Equilibrio con los costes fijos del año
A61: Todas las cifras van SIN IVA. Las columnas de los años 2 y 3 están en euros del año 1 salvo que subas la actualización de costes en la hoja de Supuestos. La columna «Tipo de IVA de la línea» dice, en las líneas de VENTA, a qué tipo se repercute cada una, y en las de COSTE a qué tipo se compra la partida. La lee la hoja de Tesorería: los seguros y las comisiones de los medios de pago están exentos, y las nóminas, la amortización y los intereses no llevan IVA.
A62: ChefBusiness.co — Plan de Negocio: Bar-Restaurante

Sheet 3. Punto Equilibrio
A1: ChefBusiness Consultoría Gastronómica
A2: Punto de Equilibrio (Break-Even) — Bar-Restaurante
A3: Plan de Negocio: Bar-Restaurante / Restaurante Casual — España 2026
A5: Variable | B5: Año 1 | C5: Año 2 | D5: Año 3 | E5: Notas
A6: DATOS BASE POR AÑO
A7: Costes fijos anuales | B7: =IFERROR(IF('2. P&L 3 Años'!$B$10="","",'2. P&L 3 Años'!$B$40),"") -> 251980.2 | C7: =IFERROR(IF('2. P&L 3 Años'!$C$10="","",'2. P&L 3 Años'!$C$40),"") -> 257980.2 | D7: =IFERROR(IF('2. P&L 3 Años'!$D$10="","",'2. P&L 3 Años'!$D$40),"") -> 262879.18 | E7: Los MISMOS costes fijos del P&L. Cada año tiene los suyos: por eso el umbral no puede ser uno solo para los tres
A8: Costes fijos mensuales | B8: =IFERROR(IF('2. P&L 3 Años'!$B$10="","",B7/12),"") -> 20998.35 | C8: =IFERROR(IF('2. P&L 3 Años'!$C$10="","",C7/12),"") -> 21498.35 | D8: =IFERROR(IF('2. P&L 3 Años'!$D$10="","",D7/12),"") -> 21906.598
A9: Ticket medio sin IVA | B9: =IFERROR(IF('2. P&L 3 Años'!$B$10="","",'2. P&L 3 Años'!$B$8),"") -> 18.2 | C9: =IFERROR(IF('2. P&L 3 Años'!$C$10="","",'2. P&L 3 Años'!$C$8),"") -> 18.2 | D9: =IFERROR(IF('2. P&L 3 Años'!$D$10="","",'2. P&L 3 Años'!$D$8),"") -> 18.2
A10: Coste variable por cubierto | B10: =IFERROR(IF('2. P&L 3 Años'!$B$10="","",'2. P&L 3 Años'!$B$20/('2. P&L 3 Años'!$B$7*'2. P&L 3 Años'!$B$9)),"") -> 5.733 | C10: =IFERROR(IF('2. P&L 3 Años'!$C$10="","",'2. P&L 3 Años'!$C$20/('2. P&L 3 Años'!$C$7*'2. P&L 3 Años'!$C$9)),"") -> 5.733 | D10: =IFERROR(IF('2. P&L 3 Años'!$D$10="","",'2. P&L 3 Años'!$D$20/('2. P&L 3 Años'!$D$7*'2. P&L 3 Años'!$D$9)),"") -> 5.733 | E10: Sale del total de costes variables del P&L, no de una estimación aparte. Incluye los varios e imprevistos, que son un porcentaje de las ventas
A11: Margen de contribución por cubierto | B11: =IFERROR(IF('2. P&L 3 Años'!$B$10="","",B9-B10),"") -> 12.467 | C11: =IFERROR(IF('2. P&L 3 Años'!$C$10="","",C9-C10),"") -> 12.467 | D11: =IFERROR(IF('2. P&L 3 Años'!$D$10="","",D9-D10),"") -> 12.467 | E11: Ticket menos coste variable unitario
A12: Días de apertura al año | B12: =IFERROR(IF('2. P&L 3 Años'!$B$10="","",'2. P&L 3 Años'!$B$9),"") -> 310 | C12: =IFERROR(IF('2. P&L 3 Años'!$C$10="","",'2. P&L 3 Años'!$C$9),"") -> 310 | D12: =IFERROR(IF('2. P&L 3 Años'!$D$10="","",'2. P&L 3 Años'!$D$9),"") -> 310 | E12: El mismo calendario que el P&L y que los escenarios
A13: Devolución de principal del año (cuota) | B13: =IFERROR(IF('2. P&L 3 Años'!$B$10="","",'7. Financiación'!$B$45),"") -> 0 | C13: =IFERROR(IF('2. P&L 3 Años'!$C$10="","",'7. Financiación'!$B$47),"") -> 18350.416 | D13: =IFERROR(IF('2. P&L 3 Años'!$D$10="","",'7. Financiación'!$B$49),"") -> 19451.441 | E13: El principal NO es gasto del P&L, pero sale de la caja. Sin él, el umbral de equilibrio se publica por debajo del real
A14: PUNTO DE EQUILIBRIO CONTABLE (incluye amortización)
A15: Cubiertos necesarios al año | B15: =IFERROR(IF('2. P&L 3 Años'!$B$10="","",IF(B11<=0,"",B7/B11)),"") -> 20211.775 | C15: =IFERROR(IF('2. P&L 3 Años'!$C$10="","",IF(C11<=0,"",C7/C11)),"") -> 20693.046 | D15: =IFERROR(IF('2. P&L 3 Años'!$D$10="","",IF(D11<=0,"",D7/D11)),"") -> 21086.001
A16: Cubiertos necesarios al día | B16: =IFERROR(IF('2. P&L 3 Años'!$B$10="","",B15/B12),"") -> 65.199274 | C16: =IFERROR(IF('2. P&L 3 Años'!$C$10="","",C15/C12),"") -> 66.75176 | D16: =IFERROR(IF('2. P&L 3 Años'!$D$10="","",D15/D12),"") -> 68.019358
A17: Ingresos necesarios al año | B17: =IFERROR(IF('2. P&L 3 Años'!$B$10="","",B15*B9),"") -> 367854.31 | C17: =IFERROR(IF('2. P&L 3 Años'!$C$10="","",C15*C9),"") -> 376613.43 | D17: =IFERROR(IF('2. P&L 3 Años'!$D$10="","",D15*D9),"") -> 383765.22
A18: PUNTO DE EQUILIBRIO DE CAJA (incluye la cuota del préstamo)
A19: Costes fijos de caja + principal del año | B19: =IFERROR(IF('2. P&L 3 Años'!$B$10="","",B7-'2. P&L 3 Años'!$B$38+B13),"") -> 243219.2 | C19: =IFERROR(IF('2. P&L 3 Años'!$C$10="","",C7-'2. P&L 3 Años'!$C$38+C13),"") -> 267569.62 | D19: =IFERROR(IF('2. P&L 3 Años'!$D$10="","",D7-'2. P&L 3 Años'!$D$38+D13),"") -> 273569.62 | E19: Los fijos del P&L sin la amortización (que no se paga) y CON la devolución de principal (que sí). Es el umbral que decide si la caja aguanta
A20: Cubiertos necesarios al año (caja) | B20: =IFERROR(IF('2. P&L 3 Años'!$B$10="","",IF(B11<=0,"",B19/B11)),"") -> 19509.04 | C20: =IFERROR(IF('2. P&L 3 Años'!$C$10="","",IF(C11<=0,"",C19/C11)),"") -> 21462.23 | D20: =IFERROR(IF('2. P&L 3 Años'!$D$10="","",IF(D11<=0,"",D19/D11)),"") -> 21943.5
A21: Cubiertos necesarios al día (caja) | B21: =IFERROR(IF('2. P&L 3 Años'!$B$10="","",B20/B12),"") -> 62.932387 | C21: =IFERROR(IF('2. P&L 3 Años'!$C$10="","",C20/C12),"") -> 69.232999 | D21: =IFERROR(IF('2. P&L 3 Años'!$D$10="","",D20/D12),"") -> 70.785484
A22: Ingresos necesarios al año (caja) | B22: =IFERROR(IF('2. P&L 3 Años'!$B$10="","",B20*B9),"") -> 355064.53 | C22: =IFERROR(IF('2. P&L 3 Años'!$C$10="","",C20*C9),"") -> 390612.58 | D22: =IFERROR(IF('2. P&L 3 Años'!$D$10="","",D20*D9),"") -> 399371.7
A23: CONTRASTE CON EL PLAN
A24: Cubiertos/día previstos en el plan | B24: =IFERROR(IF('2. P&L 3 Años'!$B$10="","",'2. P&L 3 Años'!$B$7),"") -> 80 | C24: =IFERROR(IF('2. P&L 3 Años'!$C$10="","",'2. P&L 3 Años'!$C$7),"") -> 88 | D24: =IFERROR(IF('2. P&L 3 Años'!$D$10="","",'2. P&L 3 Años'!$D$7),"") -> 93.28
A25: Holgura sobre el equilibrio de CAJA (%) | B25: =IFERROR(IF('2. P&L 3 Años'!$B$10="","",B24/B21-1),"") -> 0.27120556 | C25: =IFERROR(IF('2. P&L 3 Años'!$C$10="","",C24/C21-1),"") -> 0.27107018 | D25: =IFERROR(IF('2. P&L 3 Años'!$D$10="","",D24/D21-1),"") -> 0.3177843 | E25: Cuánto superan tus ventas previstas a las del equilibrio de caja. La caída que aguantas antes de no poder pagar los costes fijos y la cuota es algo menor: con un 25 % de holgura, un 20 %. El mínimo exigible está en la hoja de Supuestos
A26: Rotaciones al día que da el local como máximo | B26: 3 | E26: Servicios completos por plaza y día que puedes llegar a hacer con tu horario. Es el techo físico del local, no un objetivo
A27: Rotaciones al día que exige el equilibrio de caja | B27: =IFERROR(IF('2. P&L 3 Años'!$B$10="","",B21/'0. Supuestos'!$B$51),"") -> 1.1237926 | C27: =IFERROR(IF('2. P&L 3 Años'!$C$10="","",C21/'0. Supuestos'!$B$51),"") -> 1.2363035 | D27: =IFERROR(IF('2. P&L 3 Años'!$D$10="","",D21/'0. Supuestos'!$B$51),"") -> 1.2640265 | E27: Cubiertos de equilibrio entre las plazas que declara la hoja de Supuestos. Por encima del techo de arriba, el punto de equilibrio está fuera del alcance del local
A28: INTERPRETACIÓN
A29: =IFERROR("Con el ticket medio sin IVA de la fila de arriba necesitas "&TEXT(ROUNDUP(B16,0),"0")&" cubiertos al día durante los "&TEXT(B12,"0")&" días que abres para no perder dinero (equilibrio contable, con la amortización dentro), y "&TEXT(ROUNDUP(B21,0),"0")&" para que la caja aguante (equilibrio de caja: sin la amortización, que no se paga, y con la cuota del préstamo del año"&IF(B13=0,"; este año sólo intereses, porque el préstamo está en carencia","")&"). En las filas «Ingresos necesarios al año» tienes esas mismas cifras en euros.","") -> Con el ticket medio sin IVA de la fila de arriba necesitas 66 cubiertos al día durante los 310 días que abres para no perder dinero (equilibrio contable, con la amortización dentro), y 63 para que la caja aguante (equilibrio de caja: sin la amortización, que no se paga, y con la cuota del préstamo del año; este año sólo intereses, porque el préstamo está en carencia). En las filas «Ingresos necesarios al año» tienes esas mismas cifras en euros.
A31: SENSIBILIDAD DEL PUNTO DE EQUILIBRIO
A32: Cubiertos/día necesarios para cubrir costes según el ticket medio (columnas) y el coste variable por cubierto (filas). En verde, los que están por debajo de los cubiertos que prevé el plan.
A34: Cubiertos/día necesarios: ticket medio sin IVA (columnas) × coste variable por cubierto (filas) | B34: =IFERROR($B$9-2,"") -> 16.2 | C34: =IFERROR(IF($B$9="","",$B$9),"") -> 18.2 | D34: =IFERROR($B$9+2,"") -> 20.2 | E34: =IFERROR($B$9+4,"") -> 22.2
A35: =IFERROR($B$10*0.85,"") -> 4.87305 | B35: =IFERROR(IF($B$34-$A35<=0,"",$B$7/($B$34-$A35)/$B$12),"") -> 71.761538 | C35: =IFERROR(IF($C$34-$A35<=0,"",$B$7/($C$34-$A35)/$B$12),"") -> 60.992152 | D35: =IFERROR(IF($D$34-$A35<=0,"",$B$7/($D$34-$A35)/$B$12),"") -> 53.03334 | E35: =IFERROR(IF($E$34-$A35<=0,"",$B$7/($E$34-$A35)/$B$12),"") -> 46.911854
A36: =IFERROR($B$10*0.925,"") -> 5.303025 | B36: =IFERROR(IF($B$34-$A36<=0,"",$B$7/($B$34-$A36)/$B$12),"") -> 74.593119 | C36: =IFERROR(IF($C$34-$A36<=0,"",$B$7/($C$34-$A36)/$B$12),"") -> 63.025582 | D36: =IFERROR(IF($D$34-$A36<=0,"",$B$7/($D$34-$A36)/$B$12),"") -> 54.564054 | E36: =IFERROR(IF($E$34-$A36<=0,"",$B$7/($E$34-$A36)/$B$12),"") -> 48.105614
A37: =IFERROR($B$10*1.0,"") -> 5.733 | B37: =IFERROR(IF($B$34-$A37<=0,"",$B$7/($B$34-$A37)/$B$12),"") -> 77.657338 | C37: =IFERROR(IF($C$34-$A37<=0,"",$B$7/($C$34-$A37)/$B$12),"") -> 65.199274 | D37: =IFERROR(IF($D$34-$A37<=0,"",$B$7/($D$34-$A37)/$B$12),"") -> 56.185758 | E37: =IFERROR(IF($E$34-$A37<=0,"",$B$7/($E$34-$A37)/$B$12),"") -> 49.361715
A38: =IFERROR($B$10*1.075,"") -> 6.162975 | B38: =IFERROR(IF($B$34-$A38<=0,"",$B$7/($B$34-$A38)/$B$12),"") -> 80.984092 | C38: =IFERROR(IF($C$34-$A38<=0,"",$B$7/($C$34-$A38)/$B$12),"") -> 67.52826 | D38: =IFERROR(IF($D$34-$A38<=0,"",$B$7/($D$34-$A38)/$B$12),"") -> 57.906811 | E38: =IFERROR(IF($E$34-$A38<=0,"",$B$7/($E$34-$A38)/$B$12),"") -> 50.685171
A39: =IFERROR($B$10*1.15,"") -> 6.59295 | B39: =IFERROR(IF($B$34-$A39<=0,"",$B$7/($B$34-$A39)/$B$12),"") -> 84.608632 | C39: =IFERROR(IF($C$34-$A39<=0,"",$B$7/($C$34-$A39)/$B$12),"") -> 70.029797 | D39: =IFERROR(IF($D$34-$A39<=0,"",$B$7/($D$34-$A39)/$B$12),"") -> 59.736633 | E39: =IFERROR(IF($E$34-$A39<=0,"",$B$7/($E$34-$A39)/$B$12),"") -> 52.08155
A41: ChefBusiness.co — Plan de Negocio: Bar-Restaurante

Sheet 4. Escenarios
A1: ChefBusiness Consultoría Gastronómica
A2: Análisis de Escenarios — Año 1
A3: Plan de Negocio: Bar-Restaurante / Restaurante Casual — España 2026
A5: Métrica | B5: Pesimista | C5: Realista | D5: Optimista | E5: Notas
A6: Cubiertos/día | B6: 58 | C6: =IFERROR(IF('2. P&L 3 Años'!$B$7="","",'2. P&L 3 Años'!$B$7),"") -> 80 | D6: 95
A7: Ticket medio sin IVA | B7: 15.9 | C7: =IFERROR(IF('2. P&L 3 Años'!$B$8="","",'2. P&L 3 Años'!$B$8),"") -> 18.2 | D7: 18.5
A8: Días de apertura al año | B8: 300 | C8: =IFERROR(IF('2. P&L 3 Años'!$B$9="","",'2. P&L 3 Años'!$B$9),"") -> 310 | D8: 320
A9: INGRESOS ANUALES (sin IVA) | B9: =IFERROR(IF(B6*B7*B8=0,"",B6*B7*B8),"") -> 276660 | C9: =IFERROR(IF(C6*C7*C8=0,"",C6*C7*C8),"") -> 451360 | D9: =IFERROR(IF(D6*D7*D8=0,"",D6*D7*D8),"") -> 562400
A10: Coste de mercancía — comida | B10: =IFERROR(IF(B9="","",B9*'0. Supuestos'!$B$11*'0. Supuestos'!$B$13),"") -> 53948.7 | C10: =IFERROR(IF(C9="","",C9*'0. Supuestos'!$B$11*'0. Supuestos'!$B$13),"") -> 88015.2 | D10: =IFERROR(IF(D9="","",D9*'0. Supuestos'!$B$11*'0. Supuestos'!$B$13),"") -> 109668
A11: Coste de mercancía — bebida | B11: =IFERROR(IF(B9="","",B9*'0. Supuestos'!$B$12*'0. Supuestos'!$B$14),"") -> 21302.82 | C11: =IFERROR(IF(C9="","",C9*'0. Supuestos'!$B$12*'0. Supuestos'!$B$14),"") -> 34754.72 | D11: =IFERROR(IF(D9="","",D9*'0. Supuestos'!$B$12*'0. Supuestos'!$B$14),"") -> 43304.8
A12: Consumibles y envases | B12: =IFERROR(IF(B9="","",B9*'0. Supuestos'!$B$15),"") -> 4149.9 | C12: =IFERROR(IF(C9="","",C9*'0. Supuestos'!$B$15),"") -> 6770.4 | D12: =IFERROR(IF(D9="","",D9*'0. Supuestos'!$B$15),"") -> 8436
A13: Comisiones de delivery | B13: =IFERROR(IF(B9="","",B9*'0. Supuestos'!$B$16*'0. Supuestos'!$B$17),"") -> 0 | C13: =IFERROR(IF(C9="","",C9*'0. Supuestos'!$B$16*'0. Supuestos'!$B$17),"") -> 0 | D13: =IFERROR(IF(D9="","",D9*'0. Supuestos'!$B$16*'0. Supuestos'!$B$17),"") -> 0
A14: Comisiones de los medios de pago | B14: =IFERROR(IF(B9="","",B9*'0. Supuestos'!$B$18),"") -> 2213.28 | C14: =IFERROR(IF(C9="","",C9*'0. Supuestos'!$B$18),"") -> 3610.88 | D14: =IFERROR(IF(D9="","",D9*'0. Supuestos'!$B$18),"") -> 4499.2
A15: Varios e imprevistos | B15: =IFERROR(IF(B9="","",B9*'0. Supuestos'!$B$28),"") -> 5533.2 | C15: =IFERROR(IF(C9="","",C9*'0. Supuestos'!$B$28),"") -> 9027.2 | D15: =IFERROR(IF(D9="","",D9*'0. Supuestos'!$B$28),"") -> 11248
A16: TOTAL COSTES VARIABLES | B16: =IFERROR(IF(B9="","",SUM(B10:B15)),"") -> 87147.9 | C16: =IFERROR(IF(C9="","",SUM(C10:C15)),"") -> 142178.4 | D16: =IFERROR(IF(D9="","",SUM(D10:D15)),"") -> 177156
A17: MARGEN BRUTO | B17: =IFERROR(IF(B9="","",B9-B16),"") -> 189512.1 | C17: =IFERROR(IF(C9="","",C9-C16),"") -> 309181.6 | D17: =IFERROR(IF(D9="","",D9-D16),"") -> 385244
A18: COSTES FIJOS (los del P&L) | B18: =IFERROR(IF(B9="","",'2. P&L 3 Años'!$B$40),"") -> 251980.2 | C18: =IFERROR(IF(C9="","",'2. P&L 3 Años'!$B$40),"") -> 251980.2 | D18: =IFERROR(IF(D9="","",'2. P&L 3 Años'!$B$40),"") -> 251980.2 | E18: Los costes fijos no cambian con el escenario: por eso son fijos
A19: RESULTADO ANTES DE IMPUESTOS | B19: =IFERROR(IF(B9="","",B17-B18),"") -> -62468.1 | C19: =IFERROR(IF(C9="","",C17-C18),"") -> 57201.4 | D19: =IFERROR(IF(D9="","",D17-D18),"") -> 133263.8
A20: Impuesto de Sociedades | B20: =IFERROR(IF(B9="","",MAX(0,B19-'0. Supuestos'!$B$42)*'0. Supuestos'!$B$37),"") -> 0 | C20: =IFERROR(IF(C9="","",MAX(0,C19-'0. Supuestos'!$B$42)*'0. Supuestos'!$B$37),"") -> 8580.21 | D20: =IFERROR(IF(D9="","",MAX(0,D19-'0. Supuestos'!$B$42)*'0. Supuestos'!$B$37),"") -> 19989.57 | E20: Al tipo de entidad de nueva creación, compensando las bases negativas anteriores
A21: RESULTADO NETO | B21: =IFERROR(IF(B9="","",B19-B20),"") -> -62468.1 | C21: =IFERROR(IF(C9="","",C19-C20),"") -> 48621.19 | D21: =IFERROR(IF(D9="","",D19-D20),"") -> 113274.23
A22: Cubiertos/día para el equilibrio | B22: =IFERROR(IF(B9="","",IF(B7-B16/(B6*B8)<=0,"",B18/(B7-B16/(B6*B8))/B8)),"") -> 77.118303 | C22: =IFERROR(IF(C9="","",IF(C7-C16/(C6*C8)<=0,"",C18/(C7-C16/(C6*C8))/C8)),"") -> 65.199274 | D22: =IFERROR(IF(D9="","",IF(D7-D16/(D6*D8)<=0,"",D18/(D7-D16/(D6*D8))/D8)),"") -> 62.137552
A23: LO QUE CADA ESCENARIO EXIGE
A24: Coste de personal / Ventas | B24: =IFERROR(IF(B9="","",'2. P&L 3 Años'!$B$24/B9),"") -> 0.54919106 | C24: =IFERROR(IF(C9="","",'2. P&L 3 Años'!$B$24/C9),"") -> 0.33662531 | D24: =IFERROR(IF(D9="","",'2. P&L 3 Años'!$B$24/D9),"") -> 0.27016216 | E24: La MISMA plantilla en los tres escenarios. Si en el pesimista se dispara, el ajuste hay que hacerlo en la hoja de Personal, no aquí
A25: Cubiertos al año por jornada equivalente | B25: =IFERROR(IF(B9="","",B6*B8/'5. Personal'!$C$13),"") -> 3222.2222 | C25: =IFERROR(IF(C9="","",C6*C8/'5. Personal'!$C$13),"") -> 4592.5926 | D25: =IFERROR(IF(D9="","",D6*D8/'5. Personal'!$C$13),"") -> 5629.6296 | E25: Cubiertos que tendría que sacar cada jornada completa del cuadro de Personal. En el optimista dice si hace falta contratar
A26: Saldo de caja al cierre del año 1 (estimado, el mismo método en los tres escenarios) | B26: =IFERROR(IF(B9="","",'1. Inversión Inicial'!$B$47+B21+'2. P&L 3 Años'!$B$38-'7. Financiación'!$B$45),"") -> 7097.7 | C26: =IFERROR(IF(C9="","",'1. Inversión Inicial'!$B$47+C21+'2. P&L 3 Años'!$B$38-'7. Financiación'!$B$45),"") -> 118186.99 | D26: =IFERROR(IF(D9="","",'1. Inversión Inicial'!$B$47+D21+'2. P&L 3 Años'!$B$38-'7. Financiación'!$B$45),"") -> 182840.03 | E26: Saldo ESTIMADO: fondo de maniobra más el resultado del año, devolviendo la amortización (que no se paga) y restando el principal del préstamo. No incluye el desfase de cobros y pagos ni la liquidación del IVA, así que las tres columnas se pueden comparar entre sí. En rojo, el escenario se queda sin caja
A27: Saldo real del mes 12 de la hoja de Tesorería (sólo realista) | C27: =IFERROR(IF(C9="","",'6. Tesorería 12 meses'!$M$22),"") -> 155793.41 | E27: El saldo REAL del caso base, con su desfase de cobros y pagos y su liquidación de IVA. Sólo existe para el escenario realista, que es el único con tesorería mensual propia: por eso no está en la fila de arriba, donde se compararía contra dos estimaciones
A29: La columna «Realista» lee sus tres datos de la hoja de Supuestos, así que reproduce EXACTAMENTE el año 1 del P&L. Los otros dos escenarios usan las mismas tasas de coste: lo único que cambia son los cubiertos, el ticket y los días. Los COSTES FIJOS sí son los mismos en los tres: los varios e imprevistos, que son un porcentaje de las ventas, van arriba con los variables y cada escenario carga los suyos.
A30: NOTA: El escenario pesimista refleja un arranque lento con menor afluencia. El optimista asume alta ocupación y ticket medio superior. Los costes fijos son constantes en los 3 escenarios.
A31: ChefBusiness.co — Plan de Negocio: Bar-Restaurante

Sheet 5. Personal
A1: ChefBusiness Consultoría Gastronómica
A2: Cuadro de Personal y Coste Laboral
A3: Plan de Negocio: Bar-Restaurante / Restaurante Casual — España 2026
A5: Puesto | B5: Personas | C5: Jornada | D5: Bruto mes (€, total del puesto) | E5: Seg. Social a cargo de la empresa (€) | F5: Coste mes (€, total del puesto) | G5: Coste año (€) | H5: Horas/semana por persona | I5: Horas/año del puesto | J5: Notas
A6: Gerente / Propietario | B6: 1 | C6: 1 | D6: 1900 | E6: =IFERROR(IF(D6="","",D6*'0. Supuestos'!$B$20),"") -> 627 | F6: =IFERROR(IF(D6="","",D6+E6),"") -> 2527 | G6: =IFERROR(IF(D6="","",F6*MAX(12,'0. Supuestos'!$B$21)),"") -> 35378 | H6: =IFERROR(IF(D6="","",C6*$B$20),"") -> 40 | I6: =IFERROR(IF(D6="","",H6*B6*$B$21),"") -> 1840 | J6: Trabaja en sala: compras, cierre de caja, proveedores y RRSS
A7: Jefe de cocina | B7: 1 | C7: 1 | D7: 1800 | E7: =IFERROR(IF(D7="","",D7*'0. Supuestos'!$B$20),"") -> 594 | F7: =IFERROR(IF(D7="","",D7+E7),"") -> 2394 | G7: =IFERROR(IF(D7="","",F7*MAX(12,'0. Supuestos'!$B$21)),"") -> 33516 | H7: =IFERROR(IF(D7="","",C7*$B$20),"") -> 40 | I7: =IFERROR(IF(D7="","",H7*B7*$B$21),"") -> 1840 | J7: Escandallos, pedidos y línea caliente
A8: Ayudante de cocina | B8: 1 | C8: 1 | D8: 1250 | E8: =IFERROR(IF(D8="","",D8*'0. Supuestos'!$B$20),"") -> 412.5 | F8: =IFERROR(IF(D8="","",D8+E8),"") -> 1662.5 | G8: =IFERROR(IF(D8="","",F8*MAX(12,'0. Supuestos'!$B$21)),"") -> 23275 | H8: =IFERROR(IF(D8="","",C8*$B$20),"") -> 40 | I8: =IFERROR(IF(D8="","",H8*B8*$B$21),"") -> 1840 | J8: Mise en place, fríos y limpieza de cocina. Por encima del SMI de jornada completa
A9: Camarero/a de barra y sala | B9: 1 | C9: 1 | D9: 1300 | E9: =IFERROR(IF(D9="","",D9*'0. Supuestos'!$B$20),"") -> 429 | F9: =IFERROR(IF(D9="","",D9+E9),"") -> 1729 | G9: =IFERROR(IF(D9="","",F9*MAX(12,'0. Supuestos'!$B$21)),"") -> 24206 | H9: =IFERROR(IF(D9="","",C9*$B$20),"") -> 40 | I9: =IFERROR(IF(D9="","",H9*B9*$B$21),"") -> 1840 | J9: Jornada completa, con el servicio de mediodía y el de noche
A10: Camarero/a a tiempo parcial | B10: 1 | C10: 0.75 | D10: 1000 | E10: =IFERROR(IF(D10="","",D10*'0. Supuestos'!$B$20),"") -> 330 | F10: =IFERROR(IF(D10="","",D10+E10),"") -> 1330 | G10: =IFERROR(IF(D10="","",F10*MAX(12,'0. Supuestos'!$B$21)),"") -> 18620 | H10: =IFERROR(IF(D10="","",C10*$B$20),"") -> 30 | I10: =IFERROR(IF(D10="","",H10*B10*$B$21),"") -> 1380 | J10: Refuerzo de los dos servicios fuertes, 30 horas semanales
A11: Extra de fin de semana | B11: 1 | C11: 0.5 | D11: 650 | E11: =IFERROR(IF(D11="","",D11*'0. Supuestos'!$B$20),"") -> 214.5 | F11: =IFERROR(IF(D11="","",D11+E11),"") -> 864.5 | G11: =IFERROR(IF(D11="","",F11*MAX(12,'0. Supuestos'!$B$21)),"") -> 12103 | H11: =IFERROR(IF(D11="","",C11*$B$20),"") -> 20 | I11: =IFERROR(IF(D11="","",H11*B11*$B$21),"") -> 920 | J11: Viernes, sábado y domingo, 20 horas semanales
A12: Suplencias de vacaciones y descansos | B12: 1 | C12: 0.15 | D12: 260 | E12: =IFERROR(IF(D12="","",D12*'0. Supuestos'!$B$20),"") -> 85.8 | F12: =IFERROR(IF(D12="","",D12+E12),"") -> 345.8 | G12: =IFERROR(IF(D12="","",F12*MAX(12,'0. Supuestos'!$B$21)),"") -> 4841.2 | H12: =IFERROR(IF(D12="","",C12*$B$20),"") -> 6 | I12: =IFERROR(IF(D12="","",H12*B12*$B$21),"") -> 276 | J12: Cobertura de los 30 días de vacaciones (art. 38 ET) y del descanso semanal de los seis puestos. Equivale a una jornada del 15 %
A13: TOTAL PLANTILLA | B13: =IFERROR(IF(COUNT(D6:D12)=0,"",SUM(B6:B12)),"") -> 7 | C13: =IFERROR(IF(COUNT(D6:D12)=0,"",SUM(C6:C12)),"") -> 5.4 | D13: =IFERROR(IF(COUNT(D6:D12)=0,"",SUM(D6:D12)),"") -> 8160 | E13: =IFERROR(IF(COUNT(D6:D12)=0,"",SUM(E6:E12)),"") -> 2692.8 | F13: =IFERROR(IF(COUNT(D6:D12)=0,"",SUM(F6:F12)),"") -> 10852.8 | G13: =IFERROR(IF(COUNT(D6:D12)=0,"",SUM(G6:G12)),"") -> 151939.2 | I13: =IFERROR(IF(COUNT(D6:D12)=0,"",SUM(I6:I12)),"") -> 9936
A14: CRECIMIENTO DE LA PLANTILLA (coste escalonado)
A15: Coste anual de las incorporaciones del año 2 (€) | B15: 6000 | J15: Coste ANUAL completo (bruto + Seguridad Social × pagas) de lo que se contrate ese año. El P&L lo suma al coste del año anterior: la plantilla no crece con un porcentaje, crece con personas
A16: Coste anual de las incorporaciones del año 3 (€) | B16: 6000 | J16: Coste ANUAL completo (bruto + Seguridad Social × pagas) de lo que se contrate ese año. El P&L lo suma al coste del año anterior: la plantilla no crece con un porcentaje, crece con personas
A17: Coste de personal del año 2 | B17: =IFERROR(IF(G13="","",G13*(1+'0. Supuestos'!$B$48)+B15),"") -> 157939.2
A18: Coste de personal del año 3 | B18: =IFERROR(IF(B17="","",B17*(1+'0. Supuestos'!$B$48)+B16),"") -> 163939.2
A19: COBERTURA POR HORAS DE SERVICIO
A20: Jornada completa del convenio (horas/semana) | B20: 40 | J20: Art. 34.1 del Estatuto de los Trabajadores; tu convenio provincial puede fijar menos
A21: Semanas trabajadas al año por persona | B21: 46 | J21: 46 semanas: 52 menos las vacaciones (30 días naturales, art. 38 ET), los festivos y las ausencias medias
A22: Horas de servicio al día que hay que cubrir | B22: 13 | J22: De la apertura al cierre, barra incluida. Cuéntalas sobre tu horario real
A23: Personas necesarias a la vez en cada franja | B23: 2 | J23: Media de presencia simultánea entre cocina, barra y sala. En los dos servicios fuertes hará falta más y a media tarde menos
A24: Horas de servicio a cubrir al año | B24: =IFERROR(IF(OR(B22="",B23="",'0. Supuestos'!$B$6=""),"",B22*B23*'0. Supuestos'!$B$6),"") -> 8060
A25: Horas contratadas al año | B25: =IFERROR(IF(I13="","",I13),"") -> 9936
A26: Cobertura (contratadas / necesarias) | B26: =IFERROR(B25/B24,"") -> 1.2327543 | J26: Por debajo del 100 % la plantilla no llega a cubrir el horario que declara el plan: o se contrata más o se recorta el horario
A28: Las columnas «Bruto mes», «Seg. Social», «Coste mes» y «Coste año» son TOTALES de la fila: en un puesto con dos personas incluyen a las dos. «Jornada» es el porcentaje sobre la jornada completa del convenio y sirve para comparar el salario con el suelo legal en proporción. El tipo de Seguridad Social y el número de pagas están en la hoja «0. Supuestos».
A29: El suelo salarial es el MAYOR entre el SMI y el salario de convenio, los dos en la hoja «0. Supuestos»; las jornadas parciales lo llevan en proporción. El convenio aplicable es el PROVINCIAL de hostelería: no existe una tabla salarial estatal única, así que la celda del convenio se entrega vacía para que copies la de tu provincia.
A30: ChefBusiness.co — Plan de Negocio: Bar-Restaurante

Sheet Instrucciones
A1: INSTRUCCIONES DE USO — Plan financiero Bar-Restaurante / Restaurante Casual
A3: CÓMO SE USA ESTE LIBRO
A4: Este plan financiero es un MODELO: sólo se teclea en las celdas VERDES y el resto se recalcula solo.
A5: 1. «0. Supuestos» es la hoja de mando: cubiertos, ticket sin IVA, días de apertura, mezcla de comida y bebida, coste de mercancía, alquiler, financiación e impuestos.
A6: 2. Las partidas de la inversión, los costes fijos y la plantilla se teclean en su propia hoja, también en verde. Ningún número se escribe dos veces.
A7: 3. En «3. Punto Equilibrio» sólo se teclea el techo de rotaciones que da tu local; todo lo demás se deriva de lo anterior. En las otras tres hojas también hay celdas verdes que puedes tocar: el escenario pesimista y el optimista en «4. Escenarios», la estacionalidad y la rampa de arranque en «6. Tesorería 12 meses», y las cuatro fuentes alternativas de financiación en «7. Financiación». Todo lo demás se calcula.
A8: 4. Todas las cifras van SIN IVA. Para pasar un PVP a precio sin IVA, divide por el tipo que le corresponda: entre 1,10 en sala (comida y bebida, alcohol incluido: art. 91.Uno.2.2.º de la Ley 37/1992 del IVA) y, cuando se venden para llevar, los alimentos —bollería y pastelería incluidas—, que son productos alimenticios al tipo reducido por el art. 91.Uno.1.1.º; y entre 1,21 el tipo general, que en hostelería sólo alcanza a lo que sale del local como entrega de bienes excluida del reducido: el alcohol y los refrescos o zumos con azúcares añadidos para llevar o a domicilio (la comida para llevar sigue al 10 %); el libro lo aplica al alcohol del canal de delivery. El tipo de cada línea de venta está en la columna «Tipo de IVA de la línea» del P&L y de ahí salen los cobros, el IVA repercutido y el PVP equivalente. El IVA de la inversión se adelanta y se recupera con el modelo 303.
A9: 5. Si cambias la plantilla, el P&L la lee sola: el coste de personal sale de la hoja «Personal», no de una estimación aparte.
A10: 6. La hoja «6. Tesorería 12 meses» responde la pregunta que decide una operación bancaria: en qué mes se agota la caja. El saldo mínimo del año nunca puede salir en rojo.
A11: 7. La hoja «7. Financiación» cuadra lo que hace falta con lo que se aporta y monta el cuadro de amortización del préstamo. Si la diferencia sale en rojo, el plan no está financiado.
A13: RATIOS QUE AUDITA EL LIBRO
A14: Los umbrales viven en la columna «Umbral» del bloque RATIOS CLAVE del P&L: cámbialos ahí y el semáforo cambia con ellos.
A16: Ratio | B16: Valor del año 1 | C16: Umbral | D16: Estado
A17: Coste de mercancía / Ventas | B17: =IFERROR(IF('2. P&L 3 Años'!$B$55="","",'2. P&L 3 Años'!$B$55),"") -> 0.272 | C17: =IFERROR(IF('2. P&L 3 Años'!$E$55="","",'2. P&L 3 Años'!$E$55),"") -> 0.32 | D17: =IFERROR(IF(OR(B17="",C17=""),"",IF(B17<=C17,"CUMPLE","REVISAR")),"") -> CUMPLE
A18: Coste de personal / Ventas | B18: =IFERROR(IF('2. P&L 3 Años'!$B$56="","",'2. P&L 3 Años'!$B$56),"") -> 0.33662531 | C18: =IFERROR(IF('2. P&L 3 Años'!$E$56="","",'2. P&L 3 Años'!$E$56),"") -> 0.34 | D18: =IFERROR(IF(OR(B18="",C18=""),"",IF(B18<=C18,"CUMPLE","REVISAR")),"") -> CUMPLE
A19: Alquiler / Ventas | B19: =IFERROR(IF('2. P&L 3 Años'!$B$57="","",'2. P&L 3 Años'!$B$57),"") -> 0.079758951 | C19: =IFERROR(IF('2. P&L 3 Años'!$E$57="","",'2. P&L 3 Años'!$E$57),"") -> 0.1 | D19: =IFERROR(IF(OR(B19="",C19=""),"",IF(B19<=C19,"CUMPLE","REVISAR")),"") -> CUMPLE
A20: Resultado neto / Ventas | B20: =IFERROR(IF('2. P&L 3 Años'!$B$58="","",'2. P&L 3 Años'!$B$58),"") -> 0.10772153 | C20: =IFERROR(IF('2. P&L 3 Años'!$E$58="","",'2. P&L 3 Años'!$E$58),"") -> 0.05 | D20: =IFERROR(IF(OR(B20="",C20=""),"",IF(B20>=C20,"CUMPLE","REVISAR")),"") -> CUMPLE
A21: Margen bruto / Ventas | B21: =IFERROR(IF('2. P&L 3 Años'!$B$53="","",'2. P&L 3 Años'!$B$53),"") -> 0.685 | C21: =IFERROR(IF('2. P&L 3 Años'!$E$53="","",'2. P&L 3 Años'!$E$53),"") -> 0.65 | D21: =IFERROR(IF(OR(B21="",C21=""),"",IF(B21>=C21,"CUMPLE","REVISAR")),"") -> CUMPLE
A23: CIFRAS DE ESTE PLAN
A24: Inversión total (suma de los bloques) | B24: =IFERROR(IF('1. Inversión Inicial'!$B$48="","",'1. Inversión Inicial'!$B$48),"") -> 179014.8
A25: Necesidad total de caja al arranque | B25: =IFERROR(IF('1. Inversión Inicial'!$B$51="","",'1. Inversión Inicial'!$B$51),"") -> 201717.9
A26: Fondo de maniobra dotado | B26: =IFERROR(IF('1. Inversión Inicial'!$B$47="","",'1. Inversión Inicial'!$B$47),"") -> 60804.8
A27: Facturación prevista del año 1 | B27: =IFERROR(IF('2. P&L 3 Años'!$B$10="","",'2. P&L 3 Años'!$B$10),"") -> 451360
A28: Resultado neto del año 1 | B28: =IFERROR(IF('2. P&L 3 Años'!$B$50="","",'2. P&L 3 Años'!$B$50),"") -> 48621.19
A29: Cubiertos/día para el punto de equilibrio CONTABLE (con la amortización dentro) | B29: =IFERROR(IF('3. Punto Equilibrio'!$B$16="","",'3. Punto Equilibrio'!$B$16),"") -> 65.199274
A30: Payback del proyecto (años), antes de la deuda | B30: =IFERROR(IF('6. Tesorería 12 meses'!$B$31="","",'6. Tesorería 12 meses'!$B$31),"") -> 2.3
A32: QUÉ HA CAMBIADO RESPECTO DE LA VERSIÓN 1.1
A33: Concepto | B33: v1.1 | C33: v2.2 | D33: Por qué
A34: Coste de personal imputado al P&L | B34: 115.200 € | C34: Sale de la hoja Personal, por fórmula | D34: El P&L decía «ver hoja Personal» y usaba otra cifra; ahora lee la hoja
A35: Plantilla | B35: 7 personas / 209.171 € | C35: 7 puestos, tres a tiempo parcial (uno de ellos, suplencias) / 151.939 € | D35: Dimensionada por horas de servicio para 56 plazas; con la plantilla anterior el coste laboral era el 66,3 % de las ventas
A36: Cubiertos/día del año 1 | B36: 55 | C36: 80 | D36: 1,43 rotaciones sobre las 56 plazas del propio pack; el documento pide un MÍNIMO de 1,8 en temporada alta, así que el caso base se proyecta por debajo a propósito
A37: Ticket medio | B37: 18,50 € (sin declarar IVA) | C37: 18,20 € SIN IVA | D37: El ticket de la versión 1.1 no decía si llevaba IVA; ahora se declara sin IVA y equivale a 20,02 € de PVP al 10 % en sala, dentro del rango 15-22 € del propio libro
A38: Alquiler | B38: 3.000 €/mes | C38: 3.000 €/mes (sin cambio) | D38: Con el ticket recalibrado son el 8,0 % de las ventas, dentro del techo de 8-10 % del propio libro
A39: Suministros | B39: 1.200 €/mes | C39: 1.800 €/mes | D39: Una cocina con horno, cámaras y campana no consume el 3,2 % de las ventas
A40: Fondo de maniobra | B40: 30.000 € etiquetados «3 meses» | C40: 3 × costes fijos de caja mensuales, por fórmula | D40: Los 30.000 € cubrían 1,8 meses, no 3
A41: Amortización | B41: 5.000 €/año (base implícita 50.000 €) | C41: Base amortizable real / vida útil, por fórmula | D41: El inmovilizado del propio libro suma bastante más, y el fondo de maniobra no se amortiza
A42: Cuota del préstamo en el P&L | B42: 7.200 €/año de cuota completa | C42: sólo los intereses; el principal va a tesorería | D42: Meter la cuota entera antes del resultado convierte el P&L en un flujo de caja
A43: Impuesto de Sociedades | B43: 25 % en los años 2 y 3, sin compensar la BIN | C43: 15 % los dos primeros ejercicios con base positiva y compensación de bases negativas | D43: Artículos 26 y 29.1 de la Ley del Impuesto sobre Sociedades
A44: Comisiones de delivery | B44: 5 % de TODA la facturación, sin interruptor | C44: % del canal × comisión de la plataforma, a 0 por defecto | D44: Si no repartes, no arrastras un coste inventado
A45: Coste de la bebida | B45: food cost del 30 % sobre el total MÁS un 22 % sobre la bebida | C45: cada familia paga su propio coste | D45: 33.119,63 € cobrados dos veces en el año 1
A47: DATOS DE REFERENCIA DEL SECTOR
A48: Referencia | B48: Valor | C48: Fuente | D48: Nota
A49: Ticket medio de restaurante casual (PVP) | B49: 15-22 € | C49: Fichero v1.1 | D49: El PVP equivalente de este plan lo calcula la hoja 0. Supuestos
A50: Alquiler de local de 80-120 m² en zona urbana | B50: 2.000-4.500 €/mes | C50: Fichero v1.1
A51: Food cost objetivo | B51: 28-32 % | C51: Fichero v1.1
A52: Coste de personal sobre ventas | B52: máx. 34 % | C52: Fichero v1.1 | D52: Se aplica el más estricto de los techos que publica este producto
A53: Margen neto medio del sector | B53: 5-10 % | C53: Fichero v1.1
A54: Punto de equilibrio | B54: alcanzable en menos de 12 meses | C54: Fichero v1.1
A55: Inversión media de apertura | B55: 80.000-150.000 € | C55: Fichero v1.1 | D55: Es el rango de referencia del sector. La inversión de ESTE plan la calcula la hoja 1: si queda por encima, es porque incluye el fondo de maniobra, las existencias iniciales y el IVA que hay que adelantar, que ese rango no siempre cuenta
A56: Tasa de cierre de restaurantes en el primer año | B56: 25 % | C56: Fichero v1.1 | D56: Es el dato que más pesa en un comité de riesgos: por eso el plan lleva fondo de maniobra, escenario pesimista y tesorería mes a mes
A57: Tasa de cierre de restaurantes a los cinco años | B57: 50 % | C57: Fichero v1.1
A58: Convenio colectivo aplicable | B58: PROVINCIAL de hostelería | C58: DOM-24 / checklist F37 | D58: No existe una tabla salarial estatal única: copia la tabla de tu provincia en la celda de Supuestos
A60: Para editar una celda que no esté en verde: Revisar → Desproteger hoja (no tiene contraseña).
A61: Más plantillas y kits del catálogo en aichef.pro/productos-digitales
A62: Diseñado por John Guerrero — chef y consultor gastronómico desde 2010, en cocina desde los 17 años · johnguerrero.es
A63: Versión 2.2 · septiembre 2026 · aichef.pro/plan-negocio-bar-restaurante · info@aichef.pro

Sheet 6. Tesorería 12 meses
A1: PREVISIÓN DE TESORERÍA — AÑO 1
A2: El P&L dice si el negocio gana dinero; esta hoja dice si le queda caja para llegar a fin de mes. Es la primera que mira un banco.
A4: Concepto | B4: Mes 1 (€) | C4: Mes 2 (€) | D4: Mes 3 (€) | E4: Mes 4 (€) | F4: Mes 5 (€) | G4: Mes 6 (€) | H4: Mes 7 (€) | I4: Mes 8 (€) | J4: Mes 9 (€) | K4: Mes 10 (€) | L4: Mes 11 (€) | M4: Mes 12 (€) | N4: Año (€)
A5: Estacionalidad del mes (suma 100 %) | B5: 0.07 | C5: 0.072 | D5: 0.082 | E5: 0.085 | F5: 0.09 | G5: 0.088 | H5: 0.085 | I5: 0.062 | J5: 0.085 | K5: 0.088 | L5: 0.087 | M5: 0.106 | N5: =IFERROR(IF('2. P&L 3 Años'!$B$10="","",SUM(B5:M5)),"") -> 1 | O5: Perfil de tu zona: agosto flojo en ciudad y fuerte en costa. Tiene que sumar 100 %
A6: Rampa de arranque (% de la actividad de crucero) | B6: =IFERROR(IF('2. P&L 3 Años'!$B$10="","",MIN(1,'0. Supuestos'!$B$52+(1-'0. Supuestos'!$B$52)*0/MAX(1,'0. Supuestos'!$B$53-1))),"") -> 0.55 | C6: =IFERROR(IF('2. P&L 3 Años'!$B$10="","",MIN(1,'0. Supuestos'!$B$52+(1-'0. Supuestos'!$B$52)*1/MAX(1,'0. Supuestos'!$B$53-1))),"") -> 0.64 | D6: =IFERROR(IF('2. P&L 3 Años'!$B$10="","",MIN(1,'0. Supuestos'!$B$52+(1-'0. Supuestos'!$B$52)*2/MAX(1,'0. Supuestos'!$B$53-1))),"") -> 0.73 | E6: =IFERROR(IF('2. P&L 3 Años'!$B$10="","",MIN(1,'0. Supuestos'!$B$52+(1-'0. Supuestos'!$B$52)*3/MAX(1,'0. Supuestos'!$B$53-1))),"") -> 0.82 | F6: =IFERROR(IF('2. P&L 3 Años'!$B$10="","",MIN(1,'0. Supuestos'!$B$52+(1-'0. Supuestos'!$B$52)*4/MAX(1,'0. Supuestos'!$B$53-1))),"") -> 0.91 | G6: =IFERROR(IF('2. P&L 3 Años'!$B$10="","",MIN(1,'0. Supuestos'!$B$52+(1-'0. Supuestos'!$B$52)*5/MAX(1,'0. Supuestos'!$B$53-1))),"") -> 1 | H6: =IFERROR(IF('2. P&L 3 Años'!$B$10="","",MIN(1,'0. Supuestos'!$B$52+(1-'0. Supuestos'!$B$52)*6/MAX(1,'0. Supuestos'!$B$53-1))),"") -> 1 | I6: =IFERROR(IF('2. P&L 3 Años'!$B$10="","",MIN(1,'0. Supuestos'!$B$52+(1-'0. Supuestos'!$B$52)*7/MAX(1,'0. Supuestos'!$B$53-1))),"") -> 1 | J6: =IFERROR(IF('2. P&L 3 Años'!$B$10="","",MIN(1,'0. Supuestos'!$B$52+(1-'0. Supuestos'!$B$52)*8/MAX(1,'0. Supuestos'!$B$53-1))),"") -> 1 | K6: =IFERROR(IF('2. P&L 3 Años'!$B$10="","",MIN(1,'0. Supuestos'!$B$52+(1-'0. Supuestos'!$B$52)*9/MAX(1,'0. Supuestos'!$B$53-1))),"") -> 1 | L6: =IFERROR(IF('2. P&L 3 Años'!$B$10="","",MIN(1,'0. Supuestos'!$B$52+(1-'0. Supuestos'!$B$52)*10/MAX(1,'0. Supuestos'!$B$53-1))),"") -> 1 | M6: =IFERROR(IF('2. P&L 3 Años'!$B$10="","",MIN(1,'0. Supuestos'!$B$52+(1-'0. Supuestos'!$B$52)*11/MAX(1,'0. Supuestos'!$B$53-1))),"") -> 1 | O6: Sube en línea recta desde el porcentaje del mes 1 hasta el 100 % en los meses que digas en Supuestos. Con el mes 1 al 100 % la rampa desaparece
A7: Reparto de la actividad por mes (calculado) | B7: =IFERROR(IF('2. P&L 3 Años'!$B$10="","",B5*B6/SUMPRODUCT($B$5:$M$5,$B$6:$M$6)),"") -> 0.042918933 | C7: =IFERROR(IF('2. P&L 3 Años'!$B$10="","",C5*C6/SUMPRODUCT($B$5:$M$5,$B$6:$M$6)),"") -> 0.051368947 | D7: =IFERROR(IF('2. P&L 3 Años'!$B$10="","",D5*D6/SUMPRODUCT($B$5:$M$5,$B$6:$M$6)),"") -> 0.066730581 | E7: =IFERROR(IF('2. P&L 3 Años'!$B$10="","",E5*E6/SUMPRODUCT($B$5:$M$5,$B$6:$M$6)),"") -> 0.077699991 | F7: =IFERROR(IF('2. P&L 3 Años'!$B$10="","",F5*F6/SUMPRODUCT($B$5:$M$5,$B$6:$M$6)),"") -> 0.091300276 | G7: =IFERROR(IF('2. P&L 3 Años'!$B$10="","",G5*G6/SUMPRODUCT($B$5:$M$5,$B$6:$M$6)),"") -> 0.098100419 | H7: =IFERROR(IF('2. P&L 3 Años'!$B$10="","",H5*H6/SUMPRODUCT($B$5:$M$5,$B$6:$M$6)),"") -> 0.094756087 | I7: =IFERROR(IF('2. P&L 3 Años'!$B$10="","",I5*I6/SUMPRODUCT($B$5:$M$5,$B$6:$M$6)),"") -> 0.069116204 | ... M7: =IFERROR(IF('2. P&L 3 Años'!$B$10="","",M5*M6/SUMPRODUCT($B$5:$M$5,$B$6:$M$6)),"") -> 0.11816641 | N7: =IFERROR(IF('2. P&L 3 Años'!$B$10="","",SUM(B7:M7)),"") -> 1 | O7: Estacionalidad × rampa, normalizado a 100 %: el AÑO factura lo que dice el P&L, pero repartido como lo reparte un local que acaba de abrir
A8: COBROS
A9: Ventas cobradas (con IVA repercutido) | B9: =IFERROR(IF('2. P&L 3 Años'!$B$10="","",('2. P&L 3 Años'!$B$10+'2. P&L 3 Años'!$B$10*SUMPRODUCT('2. P&L 3 Años'!$E$11:$E$12,'2. P&L 3 Años'!$G$11:$G$12))*B7*(1-MIN(30,'0. Supuestos'!$B$58)/30)),"") -> 21309.079 | C9: =IFERROR(IF('2. P&L 3 Años'!$B$10="","",('2. P&L 3 Años'!$B$10+'2. P&L 3 Años'!$B$10*SUMPRODUCT('2. P&L 3 Años'!$E$11:$E$12,'2. P&L 3 Años'!$G$11:$G$12))*(C7*(1-MIN(30,'0. Supuestos'!$B$58)/30)+B7*MIN(30,'0. Supuestos'!$B$58)/30)),"") -> 25504.477 | D9: =IFERROR(IF('2. P&L 3 Años'!$B$10="","",('2. P&L 3 Años'!$B$10+'2. P&L 3 Años'!$B$10*SUMPRODUCT('2. P&L 3 Años'!$E$11:$E$12,'2. P&L 3 Años'!$G$11:$G$12))*(D7*(1-MIN(30,'0. Supuestos'!$B$58)/30)+C7*MIN(30,'0. Supuestos'!$B$58)/30)),"") -> 33131.466 | E9: =IFERROR(IF('2. P&L 3 Años'!$B$10="","",('2. P&L 3 Años'!$B$10+'2. P&L 3 Años'!$B$10*SUMPRODUCT('2. P&L 3 Años'!$E$11:$E$12,'2. P&L 3 Años'!$G$11:$G$12))*(E7*(1-MIN(30,'0. Supuestos'!$B$58)/30)+D7*MIN(30,'0. Supuestos'!$B$58)/30)),"") -> 38577.735 | F9: =IFERROR(IF('2. P&L 3 Años'!$B$10="","",('2. P&L 3 Años'!$B$10+'2. P&L 3 Años'!$B$10*SUMPRODUCT('2. P&L 3 Años'!$E$11:$E$12,'2. P&L 3 Años'!$G$11:$G$12))*(F7*(1-MIN(30,'0. Supuestos'!$B$58)/30)+E7*MIN(30,'0. Supuestos'!$B$58)/30)),"") -> 45330.222 | G9: =IFERROR(IF('2. P&L 3 Años'!$B$10="","",('2. P&L 3 Años'!$B$10+'2. P&L 3 Años'!$B$10*SUMPRODUCT('2. P&L 3 Años'!$E$11:$E$12,'2. P&L 3 Años'!$G$11:$G$12))*(G7*(1-MIN(30,'0. Supuestos'!$B$58)/30)+F7*MIN(30,'0. Supuestos'!$B$58)/30)),"") -> 48706.466 | H9: =IFERROR(IF('2. P&L 3 Años'!$B$10="","",('2. P&L 3 Años'!$B$10+'2. P&L 3 Años'!$B$10*SUMPRODUCT('2. P&L 3 Años'!$E$11:$E$12,'2. P&L 3 Años'!$G$11:$G$12))*(H7*(1-MIN(30,'0. Supuestos'!$B$58)/30)+G7*MIN(30,'0. Supuestos'!$B$58)/30)),"") -> 47046.018 | I9: =IFERROR(IF('2. P&L 3 Años'!$B$10="","",('2. P&L 3 Años'!$B$10+'2. P&L 3 Años'!$B$10*SUMPRODUCT('2. P&L 3 Años'!$E$11:$E$12,'2. P&L 3 Años'!$G$11:$G$12))*(I7*(1-MIN(30,'0. Supuestos'!$B$58)/30)+H7*MIN(30,'0. Supuestos'!$B$58)/30)),"") -> 34315.919 | J9: =IFERROR(IF('2. P&L 3 Años'!$B$10="","",('2. P&L 3 Años'!$B$10+'2. P&L 3 Años'!$B$10*SUMPRODUCT('2. P&L 3 Años'!$E$11:$E$12,'2. P&L 3 Años'!$G$11:$G$12))*(J7*(1-MIN(30,'0. Supuestos'!$B$58)/30)+I7*MIN(30,'0. Supuestos'!$B$58)/30)),"") -> 47046.018 | ... M9: =IFERROR(IF('2. P&L 3 Años'!$B$10="","",('2. P&L 3 Años'!$B$10+'2. P&L 3 Años'!$B$10*SUMPRODUCT('2. P&L 3 Años'!$E$11:$E$12,'2. P&L 3 Años'!$G$11:$G$12))*(M7*(1-MIN(30,'0. Supuestos'!$B$58)/30)+L7*MIN(30,'0. Supuestos'!$B$58)/30)),"") -> 58669.152 | N9: =IFERROR(IF('2. P&L 3 Años'!$B$10="","",SUM(B9:M9)),"") -> 496496 | O9: Ventas del mes con el IVA repercutido, corregidas por los días medios de cobro de la hoja de Supuestos
A10: PAGOS
A11: Compras y costes variables (IVA incluido) | B11: =IFERROR(IF('2. P&L 3 Años'!$B$10="","",-('2. P&L 3 Años'!$B$14*(1+'2. P&L 3 Años'!$G$14)+'2. P&L 3 Años'!$B$15*(1+'2. P&L 3 Años'!$G$15)+'2. P&L 3 Años'!$B$16*(1+'2. P&L 3 Años'!$G$16)+'2. P&L 3 Años'!$B$17*(1+'2. P&L 3 Años'!$G$17)+'2. P&L 3 Años'!$B$18*(1+'2. P&L 3 Años'!$G$18)+'2. P&L 3 Años'!$B$19*(1+'2. P&L 3 Años'!$G$19))*B7*(1-MIN(30,'0. Supuestos'!$B$59)/30)),"") -> 0 | C11: =IFERROR(IF('2. P&L 3 Años'!$B$10="","",-('2. P&L 3 Años'!$B$14*(1+'2. P&L 3 Años'!$G$14)+'2. P&L 3 Años'!$B$15*(1+'2. P&L 3 Años'!$G$15)+'2. P&L 3 Años'!$B$16*(1+'2. P&L 3 Años'!$G$16)+'2. P&L 3 Años'!$B$17*(1+'2. P&L 3 Años'!$G$17)+'2. P&L 3 Años'!$B$18*(1+'2. P&L 3 Años'!$G$18)+'2. P&L 3 Años'!$B$19*(1+'2. P&L 3 Años'!$G$19))*(C7*(1-MIN(30,'0. Supuestos'!$B$59)/30)+B7*MIN(30,'0. Supuestos'!$B$59)/30)),"") -> -6869.892 | D11: =IFERROR(IF('2. P&L 3 Años'!$B$10="","",-('2. P&L 3 Años'!$B$14*(1+'2. P&L 3 Años'!$G$14)+'2. P&L 3 Años'!$B$15*(1+'2. P&L 3 Años'!$G$15)+'2. P&L 3 Años'!$B$16*(1+'2. P&L 3 Años'!$G$16)+'2. P&L 3 Años'!$B$17*(1+'2. P&L 3 Años'!$G$17)+'2. P&L 3 Años'!$B$18*(1+'2. P&L 3 Años'!$G$18)+'2. P&L 3 Años'!$B$19*(1+'2. P&L 3 Años'!$G$19))*(D7*(1-MIN(30,'0. Supuestos'!$B$59)/30)+C7*MIN(30,'0. Supuestos'!$B$59)/30)),"") -> -8222.4578 | E11: =IFERROR(IF('2. P&L 3 Años'!$B$10="","",-('2. P&L 3 Años'!$B$14*(1+'2. P&L 3 Años'!$G$14)+'2. P&L 3 Años'!$B$15*(1+'2. P&L 3 Años'!$G$15)+'2. P&L 3 Años'!$B$16*(1+'2. P&L 3 Años'!$G$16)+'2. P&L 3 Años'!$B$17*(1+'2. P&L 3 Años'!$G$17)+'2. P&L 3 Años'!$B$18*(1+'2. P&L 3 Años'!$G$18)+'2. P&L 3 Años'!$B$19*(1+'2. P&L 3 Años'!$G$19))*(E7*(1-MIN(30,'0. Supuestos'!$B$59)/30)+D7*MIN(30,'0. Supuestos'!$B$59)/30)),"") -> -10681.344 | F11: =IFERROR(IF('2. P&L 3 Años'!$B$10="","",-('2. P&L 3 Años'!$B$14*(1+'2. P&L 3 Años'!$G$14)+'2. P&L 3 Años'!$B$15*(1+'2. P&L 3 Años'!$G$15)+'2. P&L 3 Años'!$B$16*(1+'2. P&L 3 Años'!$G$16)+'2. P&L 3 Años'!$B$17*(1+'2. P&L 3 Años'!$G$17)+'2. P&L 3 Años'!$B$18*(1+'2. P&L 3 Años'!$G$18)+'2. P&L 3 Años'!$B$19*(1+'2. P&L 3 Años'!$G$19))*(F7*(1-MIN(30,'0. Supuestos'!$B$59)/30)+E7*MIN(30,'0. Supuestos'!$B$59)/30)),"") -> -12437.181 | G11: =IFERROR(IF('2. P&L 3 Años'!$B$10="","",-('2. P&L 3 Años'!$B$14*(1+'2. P&L 3 Años'!$G$14)+'2. P&L 3 Años'!$B$15*(1+'2. P&L 3 Años'!$G$15)+'2. P&L 3 Años'!$B$16*(1+'2. P&L 3 Años'!$G$16)+'2. P&L 3 Años'!$B$17*(1+'2. P&L 3 Años'!$G$17)+'2. P&L 3 Años'!$B$18*(1+'2. P&L 3 Años'!$G$18)+'2. P&L 3 Años'!$B$19*(1+'2. P&L 3 Años'!$G$19))*(G7*(1-MIN(30,'0. Supuestos'!$B$59)/30)+F7*MIN(30,'0. Supuestos'!$B$59)/30)),"") -> -14614.134 | H11: =IFERROR(IF('2. P&L 3 Años'!$B$10="","",-('2. P&L 3 Años'!$B$14*(1+'2. P&L 3 Años'!$G$14)+'2. P&L 3 Años'!$B$15*(1+'2. P&L 3 Años'!$G$15)+'2. P&L 3 Años'!$B$16*(1+'2. P&L 3 Años'!$G$16)+'2. P&L 3 Años'!$B$17*(1+'2. P&L 3 Años'!$G$17)+'2. P&L 3 Años'!$B$18*(1+'2. P&L 3 Años'!$G$18)+'2. P&L 3 Años'!$B$19*(1+'2. P&L 3 Años'!$G$19))*(H7*(1-MIN(30,'0. Supuestos'!$B$59)/30)+G7*MIN(30,'0. Supuestos'!$B$59)/30)),"") -> -15702.61 | I11: =IFERROR(IF('2. P&L 3 Años'!$B$10="","",-('2. P&L 3 Años'!$B$14*(1+'2. P&L 3 Años'!$G$14)+'2. P&L 3 Años'!$B$15*(1+'2. P&L 3 Años'!$G$15)+'2. P&L 3 Años'!$B$16*(1+'2. P&L 3 Años'!$G$16)+'2. P&L 3 Años'!$B$17*(1+'2. P&L 3 Años'!$G$17)+'2. P&L 3 Años'!$B$18*(1+'2. P&L 3 Años'!$G$18)+'2. P&L 3 Años'!$B$19*(1+'2. P&L 3 Años'!$G$19))*(I7*(1-MIN(30,'0. Supuestos'!$B$59)/30)+H7*MIN(30,'0. Supuestos'!$B$59)/30)),"") -> -15167.294 | J11: =IFERROR(IF('2. P&L 3 Años'!$B$10="","",-('2. P&L 3 Años'!$B$14*(1+'2. P&L 3 Años'!$G$14)+'2. P&L 3 Años'!$B$15*(1+'2. P&L 3 Años'!$G$15)+'2. P&L 3 Años'!$B$16*(1+'2. P&L 3 Años'!$G$16)+'2. P&L 3 Años'!$B$17*(1+'2. P&L 3 Años'!$G$17)+'2. P&L 3 Años'!$B$18*(1+'2. P&L 3 Años'!$G$18)+'2. P&L 3 Años'!$B$19*(1+'2. P&L 3 Años'!$G$19))*(J7*(1-MIN(30,'0. Supuestos'!$B$59)/30)+I7*MIN(30,'0. Supuestos'!$B$59)/30)),"") -> -11063.203 | ... M11: =IFERROR(IF('2. P&L 3 Años'!$B$10="","",-('2. P&L 3 Años'!$B$14*(1+'2. P&L 3 Años'!$G$14)+'2. P&L 3 Años'!$B$15*(1+'2. P&L 3 Años'!$G$15)+'2. P&L 3 Años'!$B$16*(1+'2. P&L 3 Años'!$G$16)+'2. P&L 3 Años'!$B$17*(1+'2. P&L 3 Años'!$G$17)+'2. P&L 3 Años'!$B$18*(1+'2. P&L 3 Años'!$G$18)+'2. P&L 3 Años'!$B$19*(1+'2. P&L 3 Años'!$G$19))*(M7*(1-MIN(30,'0. Supuestos'!$B$59)/30)+L7*MIN(30,'0. Supuestos'!$B$59)/30)),"") -> -15524.172 | N11: =IFERROR(IF('2. P&L 3 Años'!$B$10="","",SUM(B11:M11)),"") -> -141152.19 | O11: =IFERROR("Materia prima, consumibles, comisiones e imprevistos, cada uno con SU tipo de IVA (la columna del P&L) y con los días de pago a proveedor de Supuestos."&IF('0. Supuestos'!$B$59=0,""," Con "&TEXT('0. Supuestos'!$B$59,"0")&" días de pago, las primeras compras se pagan ya en el año siguiente: la columna «Año» de esta fila recoge "&TEXT(MAX(0,12-ROUNDUP('0. Supuestos'!$B$59/30,0)),"0")&" mensualidades de compra, no el coste del ejercicio."),"") -> Materia prima, consumibles, comisiones e imprevistos, cada uno con SU tipo de IVA (la columna del P&L) y con los días de pago a proveedor de Supuestos. Con 30 días de pago, las primeras compras se pagan ya en el año siguiente: la columna «Año» de esta fila recoge 11 mensualidades de compra, no el coste del ejercicio.
A12: Costes fijos de explotación (IVA incluido) | B12: =IFERROR(IF('2. P&L 3 Años'!$B$10="","",-('2. P&L 3 Años'!$B$40-'2. P&L 3 Años'!$B$24-'2. P&L 3 Años'!$B$38-'2. P&L 3 Años'!$B$39+'2. P&L 3 Años'!$B$42)/12),"") -> -8394.6667 | C12: =IFERROR(IF('2. P&L 3 Años'!$B$10="","",-('2. P&L 3 Años'!$B$40-'2. P&L 3 Años'!$B$24-'2. P&L 3 Años'!$B$38-'2. P&L 3 Años'!$B$39+'2. P&L 3 Años'!$B$42)/12),"") -> -8394.6667 | D12: =IFERROR(IF('2. P&L 3 Años'!$B$10="","",-('2. P&L 3 Años'!$B$40-'2. P&L 3 Años'!$B$24-'2. P&L 3 Años'!$B$38-'2. P&L 3 Años'!$B$39+'2. P&L 3 Años'!$B$42)/12),"") -> -8394.6667 | E12: =IFERROR(IF('2. P&L 3 Años'!$B$10="","",-('2. P&L 3 Años'!$B$40-'2. P&L 3 Años'!$B$24-'2. P&L 3 Años'!$B$38-'2. P&L 3 Años'!$B$39+'2. P&L 3 Años'!$B$42)/12),"") -> -8394.6667 | F12: =IFERROR(IF('2. P&L 3 Años'!$B$10="","",-('2. P&L 3 Años'!$B$40-'2. P&L 3 Años'!$B$24-'2. P&L 3 Años'!$B$38-'2. P&L 3 Años'!$B$39+'2. P&L 3 Años'!$B$42)/12),"") -> -8394.6667 | G12: =IFERROR(IF('2. P&L 3 Años'!$B$10="","",-('2. P&L 3 Años'!$B$40-'2. P&L 3 Años'!$B$24-'2. P&L 3 Años'!$B$38-'2. P&L 3 Años'!$B$39+'2. P&L 3 Años'!$B$42)/12),"") -> -8394.6667 | H12: =IFERROR(IF('2. P&L 3 Años'!$B$10="","",-('2. P&L 3 Años'!$B$40-'2. P&L 3 Años'!$B$24-'2. P&L 3 Años'!$B$38-'2. P&L 3 Años'!$B$39+'2. P&L 3 Años'!$B$42)/12),"") -> -8394.6667 | I12: =IFERROR(IF('2. P&L 3 Años'!$B$10="","",-('2. P&L 3 Años'!$B$40-'2. P&L 3 Años'!$B$24-'2. P&L 3 Años'!$B$38-'2. P&L 3 Años'!$B$39+'2. P&L 3 Años'!$B$42)/12),"") -> -8394.6667 | ... M12: =IFERROR(IF('2. P&L 3 Años'!$B$10="","",-('2. P&L 3 Años'!$B$40-'2. P&L 3 Años'!$B$24-'2. P&L 3 Años'!$B$38-'2. P&L 3 Años'!$B$39+'2. P&L 3 Años'!$B$42)/12),"") -> -8394.6667 | N12: =IFERROR(IF('2. P&L 3 Años'!$B$10="","",SUM(B12:M12)),"") -> -100736 | O12: Los fijos que salen de caja, cada uno con su tipo de IVA: los seguros están exentos y no llevan
A13: Nóminas y Seguridad Social | B13: =IFERROR(IF('2. P&L 3 Años'!$B$10="","",-'2. P&L 3 Años'!$B$24/MAX(12,'0. Supuestos'!$B$21)*(1+IF(1='0. Supuestos'!$B$60,(MAX(12,'0. Supuestos'!$B$21)-12)/2,0)+IF(1='0. Supuestos'!$B$61,(MAX(12,'0. Supuestos'!$B$21)-12)/2,0))),"") -> -10852.8 | C13: =IFERROR(IF('2. P&L 3 Años'!$B$10="","",-'2. P&L 3 Años'!$B$24/MAX(12,'0. Supuestos'!$B$21)*(1+IF(2='0. Supuestos'!$B$60,(MAX(12,'0. Supuestos'!$B$21)-12)/2,0)+IF(2='0. Supuestos'!$B$61,(MAX(12,'0. Supuestos'!$B$21)-12)/2,0))),"") -> -10852.8 | D13: =IFERROR(IF('2. P&L 3 Años'!$B$10="","",-'2. P&L 3 Años'!$B$24/MAX(12,'0. Supuestos'!$B$21)*(1+IF(3='0. Supuestos'!$B$60,(MAX(12,'0. Supuestos'!$B$21)-12)/2,0)+IF(3='0. Supuestos'!$B$61,(MAX(12,'0. Supuestos'!$B$21)-12)/2,0))),"") -> -10852.8 | E13: =IFERROR(IF('2. P&L 3 Años'!$B$10="","",-'2. P&L 3 Años'!$B$24/MAX(12,'0. Supuestos'!$B$21)*(1+IF(4='0. Supuestos'!$B$60,(MAX(12,'0. Supuestos'!$B$21)-12)/2,0)+IF(4='0. Supuestos'!$B$61,(MAX(12,'0. Supuestos'!$B$21)-12)/2,0))),"") -> -10852.8 | F13: =IFERROR(IF('2. P&L 3 Años'!$B$10="","",-'2. P&L 3 Años'!$B$24/MAX(12,'0. Supuestos'!$B$21)*(1+IF(5='0. Supuestos'!$B$60,(MAX(12,'0. Supuestos'!$B$21)-12)/2,0)+IF(5='0. Supuestos'!$B$61,(MAX(12,'0. Supuestos'!$B$21)-12)/2,0))),"") -> -10852.8 | G13: =IFERROR(IF('2. P&L 3 Años'!$B$10="","",-'2. P&L 3 Años'!$B$24/MAX(12,'0. Supuestos'!$B$21)*(1+IF(6='0. Supuestos'!$B$60,(MAX(12,'0. Supuestos'!$B$21)-12)/2,0)+IF(6='0. Supuestos'!$B$61,(MAX(12,'0. Supuestos'!$B$21)-12)/2,0))),"") -> -10852.8 | H13: =IFERROR(IF('2. P&L 3 Años'!$B$10="","",-'2. P&L 3 Años'!$B$24/MAX(12,'0. Supuestos'!$B$21)*(1+IF(7='0. Supuestos'!$B$60,(MAX(12,'0. Supuestos'!$B$21)-12)/2,0)+IF(7='0. Supuestos'!$B$61,(MAX(12,'0. Supuestos'!$B$21)-12)/2,0))),"") -> -21705.6 | I13: =IFERROR(IF('2. P&L 3 Años'!$B$10="","",-'2. P&L 3 Años'!$B$24/MAX(12,'0. Supuestos'!$B$21)*(1+IF(8='0. Supuestos'!$B$60,(MAX(12,'0. Supuestos'!$B$21)-12)/2,0)+IF(8='0. Supuestos'!$B$61,(MAX(12,'0. Supuestos'!$B$21)-12)/2,0))),"") -> -10852.8 | J13: =IFERROR(IF('2. P&L 3 Años'!$B$10="","",-'2. P&L 3 Años'!$B$24/MAX(12,'0. Supuestos'!$B$21)*(1+IF(9='0. Supuestos'!$B$60,(MAX(12,'0. Supuestos'!$B$21)-12)/2,0)+IF(9='0. Supuestos'!$B$61,(MAX(12,'0. Supuestos'!$B$21)-12)/2,0))),"") -> -10852.8 | K13: =IFERROR(IF('2. P&L 3 Años'!$B$10="","",-'2. P&L 3 Años'!$B$24/MAX(12,'0. Supuestos'!$B$21)*(1+IF(10='0. Supuestos'!$B$60,(MAX(12,'0. Supuestos'!$B$21)-12)/2,0)+IF(10='0. Supuestos'!$B$61,(MAX(12,'0. Supuestos'!$B$21)-12)/2,0))),"") -> -10852.8 | L13: =IFERROR(IF('2. P&L 3 Años'!$B$10="","",-'2. P&L 3 Años'!$B$24/MAX(12,'0. Supuestos'!$B$21)*(1+IF(11='0. Supuestos'!$B$60,(MAX(12,'0. Supuestos'!$B$21)-12)/2,0)+IF(11='0. Supuestos'!$B$61,(MAX(12,'0. Supuestos'!$B$21)-12)/2,0))),"") -> -10852.8 | M13: =IFERROR(IF('2. P&L 3 Años'!$B$10="","",-'2. P&L 3 Años'!$B$24/MAX(12,'0. Supuestos'!$B$21)*(1+IF(12='0. Supuestos'!$B$60,(MAX(12,'0. Supuestos'!$B$21)-12)/2,0)+IF(12='0. Supuestos'!$B$61,(MAX(12,'0. Supuestos'!$B$21)-12)/2,0))),"") -> -21705.6 | N13: =IFERROR(IF('2. P&L 3 Años'!$B$10="","",SUM(B13:M13)),"") -> -151939.2 | O13: Doce mensualidades más las pagas extra en los meses que digas en Supuestos. La suma del año es la misma que la del P&L
A14: Intereses del préstamo | B14: =IFERROR(IF('2. P&L 3 Años'!$B$10="","",-'7. Financiación'!$B$44/12),"") -> -640 | C14: =IFERROR(IF('2. P&L 3 Años'!$B$10="","",-'7. Financiación'!$B$44/12),"") -> -640 | D14: =IFERROR(IF('2. P&L 3 Años'!$B$10="","",-'7. Financiación'!$B$44/12),"") -> -640 | E14: =IFERROR(IF('2. P&L 3 Años'!$B$10="","",-'7. Financiación'!$B$44/12),"") -> -640 | F14: =IFERROR(IF('2. P&L 3 Años'!$B$10="","",-'7. Financiación'!$B$44/12),"") -> -640 | G14: =IFERROR(IF('2. P&L 3 Años'!$B$10="","",-'7. Financiación'!$B$44/12),"") -> -640 | H14: =IFERROR(IF('2. P&L 3 Años'!$B$10="","",-'7. Financiación'!$B$44/12),"") -> -640 | I14: =IFERROR(IF('2. P&L 3 Años'!$B$10="","",-'7. Financiación'!$B$44/12),"") -> -640 | ... M14: =IFERROR(IF('2. P&L 3 Años'!$B$10="","",-'7. Financiación'!$B$44/12),"") -> -640 | N14: =IFERROR(IF('2. P&L 3 Años'!$B$10="","",SUM(B14:M14)),"") -> -7680
A15: Devolución de principal del préstamo | B15: =IFERROR(IF('2. P&L 3 Años'!$B$10="","",-'7. Financiación'!$B$45/12),"") -> 0 | C15: =IFERROR(IF('2. P&L 3 Años'!$B$10="","",-'7. Financiación'!$B$45/12),"") -> 0 | D15: =IFERROR(IF('2. P&L 3 Años'!$B$10="","",-'7. Financiación'!$B$45/12),"") -> 0 | E15: =IFERROR(IF('2. P&L 3 Años'!$B$10="","",-'7. Financiación'!$B$45/12),"") -> 0 | F15: =IFERROR(IF('2. P&L 3 Años'!$B$10="","",-'7. Financiación'!$B$45/12),"") -> 0 | G15: =IFERROR(IF('2. P&L 3 Años'!$B$10="","",-'7. Financiación'!$B$45/12),"") -> 0 | H15: =IFERROR(IF('2. P&L 3 Años'!$B$10="","",-'7. Financiación'!$B$45/12),"") -> 0 | I15: =IFERROR(IF('2. P&L 3 Años'!$B$10="","",-'7. Financiación'!$B$45/12),"") -> 0 | ... M15: =IFERROR(IF('2. P&L 3 Años'!$B$10="","",-'7. Financiación'!$B$45/12),"") -> 0 | N15: =IFERROR(IF('2. P&L 3 Años'!$B$10="","",SUM(B15:M15)),"") -> 0
A16: IVA repercutido del mes (memoria) | B16: =IFERROR(IF('2. P&L 3 Años'!$B$10="","",'2. P&L 3 Años'!$B$10*B7*SUMPRODUCT('2. P&L 3 Años'!$E$11:$E$12,'2. P&L 3 Años'!$G$11:$G$12)),"") -> 1937.189 | C16: =IFERROR(IF('2. P&L 3 Años'!$B$10="","",'2. P&L 3 Años'!$B$10*C7*SUMPRODUCT('2. P&L 3 Años'!$E$11:$E$12,'2. P&L 3 Años'!$G$11:$G$12)),"") -> 2318.5888 | D16: =IFERROR(IF('2. P&L 3 Años'!$B$10="","",'2. P&L 3 Años'!$B$10*D7*SUMPRODUCT('2. P&L 3 Años'!$E$11:$E$12,'2. P&L 3 Años'!$G$11:$G$12)),"") -> 3011.9515 | E16: =IFERROR(IF('2. P&L 3 Años'!$B$10="","",'2. P&L 3 Años'!$B$10*E7*SUMPRODUCT('2. P&L 3 Años'!$E$11:$E$12,'2. P&L 3 Años'!$G$11:$G$12)),"") -> 3507.0668 | F16: =IFERROR(IF('2. P&L 3 Años'!$B$10="","",'2. P&L 3 Años'!$B$10*F7*SUMPRODUCT('2. P&L 3 Años'!$E$11:$E$12,'2. P&L 3 Años'!$G$11:$G$12)),"") -> 4120.9293 | G16: =IFERROR(IF('2. P&L 3 Años'!$B$10="","",'2. P&L 3 Años'!$B$10*G7*SUMPRODUCT('2. P&L 3 Años'!$E$11:$E$12,'2. P&L 3 Años'!$G$11:$G$12)),"") -> 4427.8605 | H16: =IFERROR(IF('2. P&L 3 Años'!$B$10="","",'2. P&L 3 Años'!$B$10*H7*SUMPRODUCT('2. P&L 3 Años'!$E$11:$E$12,'2. P&L 3 Años'!$G$11:$G$12)),"") -> 4276.9107 | I16: =IFERROR(IF('2. P&L 3 Años'!$B$10="","",'2. P&L 3 Años'!$B$10*I7*SUMPRODUCT('2. P&L 3 Años'!$E$11:$E$12,'2. P&L 3 Años'!$G$11:$G$12)),"") -> 3119.629 | ... M16: =IFERROR(IF('2. P&L 3 Años'!$B$10="","",'2. P&L 3 Años'!$B$10*M7*SUMPRODUCT('2. P&L 3 Años'!$E$11:$E$12,'2. P&L 3 Años'!$G$11:$G$12)),"") -> 5333.5593 | N16: =IFERROR(IF('2. P&L 3 Años'!$B$10="","",SUM(B16:M16)),"") -> 45136 | O16: Cada línea de venta a SU tipo, leído de la columna de IVA del P&L: en sala, alcohol incluido, el reducido (art. 91.Uno.2.2.º de la Ley 37/1992 del IVA); el alcohol que sale por delivery, al general; el pan común y las harinas panificables, al superreducido (art. 91.Dos.1.1.º)
A17: IVA soportado del mes (memoria) | B17: =IFERROR(IF('2. P&L 3 Años'!$B$10="","",'2. P&L 3 Años'!$B$41*B7+'2. P&L 3 Años'!$B$42/12),"") -> 2195.7467 | C17: =IFERROR(IF('2. P&L 3 Años'!$B$10="","",'2. P&L 3 Años'!$B$41*C7+'2. P&L 3 Años'!$B$42/12),"") -> 2346.9031 | D17: =IFERROR(IF('2. P&L 3 Años'!$B$10="","",'2. P&L 3 Años'!$B$41*D7+'2. P&L 3 Años'!$B$42/12),"") -> 2621.6966 | E17: =IFERROR(IF('2. P&L 3 Años'!$B$10="","",'2. P&L 3 Años'!$B$41*E7+'2. P&L 3 Años'!$B$42/12),"") -> 2817.9207 | F17: =IFERROR(IF('2. P&L 3 Años'!$B$10="","",'2. P&L 3 Años'!$B$41*F7+'2. P&L 3 Años'!$B$42/12),"") -> 3061.2067 | G17: =IFERROR(IF('2. P&L 3 Años'!$B$10="","",'2. P&L 3 Años'!$B$41*G7+'2. P&L 3 Años'!$B$42/12),"") -> 3182.8497 | H17: =IFERROR(IF('2. P&L 3 Años'!$B$10="","",'2. P&L 3 Años'!$B$41*H7+'2. P&L 3 Años'!$B$42/12),"") -> 3123.0253 | I17: =IFERROR(IF('2. P&L 3 Años'!$B$10="","",'2. P&L 3 Años'!$B$41*I7+'2. P&L 3 Años'!$B$42/12),"") -> 2664.3714 | ... M17: =IFERROR(IF('2. P&L 3 Años'!$B$10="","",'2. P&L 3 Años'!$B$41*M7+'2. P&L 3 Años'!$B$42/12),"") -> 3541.7962 | N17: =IFERROR(IF('2. P&L 3 Años'!$B$10="","",SUM(B17:M17)),"") -> 35024.3 | O17: Cada partida a su tipo, leído de la columna de IVA del P&L: los seguros y las comisiones de los medios de pago están exentos
A18: IVA a compensar arrastrado (inversión incluida) | E18: =IFERROR(IF('2. P&L 3 Años'!$B$10="","",'1. Inversión Inicial'!$B$50),"") -> 22703.1 | H18: =IFERROR(IF('2. P&L 3 Años'!$B$10="","",MAX(0,-E19)),"") -> 22599.717 | K18: =IFERROR(IF('2. P&L 3 Años'!$B$10="","",MAX(0,-H19)),"") -> 19605.838 | O18: El IVA soportado de la INVERSIÓN entra aquí: se compensa contra el repercutido de los trimestres siguientes hasta agotarlo (modelo 303)
A19: Resultado de la liquidación trimestral | E19: =IFERROR(IF('2. P&L 3 Años'!$B$10="","",SUM(B16:D16)-SUM(B17:D17)-E18),"") -> -22599.717 | H19: =IFERROR(IF('2. P&L 3 Años'!$B$10="","",SUM(E16:G16)-SUM(E17:G17)-H18),"") -> -19605.838 | K19: =IFERROR(IF('2. P&L 3 Años'!$B$10="","",SUM(H16:J16)-SUM(H17:J17)-K18),"") -> -16842.809 | O19: Repercutido menos soportado del trimestre menos lo que venía arrastrado. En negativo NO se paga: se compensa en el trimestre siguiente
A20: Pago del IVA (modelo 303) | E20: =IFERROR(IF('2. P&L 3 Años'!$B$10="","",IF(E19<=0,"",-E19)),"") | H20: =IFERROR(IF('2. P&L 3 Años'!$B$10="","",IF(H19<=0,"",-H19)),"") | K20: =IFERROR(IF('2. P&L 3 Años'!$B$10="","",IF(K19<=0,"",-K19)),"") | N20: =IFERROR(IF('2. P&L 3 Años'!$B$10="","",SUM(B20:M20)),"") -> 0 | O20: Sólo sale caja cuando el resultado del trimestre es positivo. Los meses sin liquidación van en blanco, no a cero. La celda se pinta en ROJO cuando el pago del 303 se lleva más caja de la que queda ese mes
A21: FLUJO DEL MES | B21: =IFERROR(IF('2. P&L 3 Años'!$B$10="","",SUM(B9:B15)+IF(B20="",0,B20)),"") -> 1421.6121 | C21: =IFERROR(IF('2. P&L 3 Años'!$B$10="","",SUM(C9:C15)+IF(C20="",0,C20)),"") -> -1252.8821 | D21: =IFERROR(IF('2. P&L 3 Años'!$B$10="","",SUM(D9:D15)+IF(D20="",0,D20)),"") -> 5021.5419 | E21: =IFERROR(IF('2. P&L 3 Años'!$B$10="","",SUM(E9:E15)+IF(E20="",0,E20)),"") -> 8008.9243 | F21: =IFERROR(IF('2. P&L 3 Años'!$B$10="","",SUM(F9:F15)+IF(F20="",0,F20)),"") -> 13005.574 | G21: =IFERROR(IF('2. P&L 3 Años'!$B$10="","",SUM(G9:G15)+IF(G20="",0,G20)),"") -> 14204.865 | H21: =IFERROR(IF('2. P&L 3 Años'!$B$10="","",SUM(H9:H15)+IF(H20="",0,H20)),"") -> 603.14103 | I21: =IFERROR(IF('2. P&L 3 Años'!$B$10="","",SUM(I9:I15)+IF(I20="",0,I20)),"") -> -738.8417 | ... M21: =IFERROR(IF('2. P&L 3 Años'!$B$10="","",SUM(M9:M15)+IF(M20="",0,M20)),"") -> 12404.714 | N21: =IFERROR(IF('2. P&L 3 Años'!$B$10="","",SUM(B21:M21)),"") -> 94988.608
A22: SALDO ACUMULADO DE CAJA | B22: =IFERROR(IF('2. P&L 3 Años'!$B$10="","",'1. Inversión Inicial'!$B$47+B21),"") -> 62226.412 | C22: =IFERROR(IF('2. P&L 3 Años'!$B$10="","",B22+C21),"") -> 60973.53 | D22: =IFERROR(IF('2. P&L 3 Años'!$B$10="","",C22+D21),"") -> 65995.072 | E22: =IFERROR(IF('2. P&L 3 Años'!$B$10="","",D22+E21),"") -> 74003.996 | F22: =IFERROR(IF('2. P&L 3 Años'!$B$10="","",E22+F21),"") -> 87009.57 | G22: =IFERROR(IF('2. P&L 3 Años'!$B$10="","",F22+G21),"") -> 101214.44 | H22: =IFERROR(IF('2. P&L 3 Años'!$B$10="","",G22+H21),"") -> 101817.58 | I22: =IFERROR(IF('2. P&L 3 Años'!$B$10="","",H22+I21),"") -> 101078.73 | J22: =IFERROR(IF('2. P&L 3 Años'!$B$10="","",I22+J21),"") -> 117174.08 | ... M22: =IFERROR(IF('2. P&L 3 Años'!$B$10="","",L22+M21),"") -> 155793.41
A23: Saldo mínimo del año | B23: =IFERROR(IF('2. P&L 3 Años'!$B$10="","",IF(COUNT(B22:M22)=0,"",MIN(B22:M22))),"") -> 60973.53 | D23: Si es negativo, sube el fondo de maniobra o el préstamo: te quedas sin caja
A24: Mes en el que la caja toca fondo | B24: =IFERROR(IF('2. P&L 3 Años'!$B$10="","",IF(COUNT(B22:M22)=0,"",MATCH(MIN(B22:M22),B22:M22,0))),"") -> 2 | D24: Es la respuesta a la pregunta que decide una operación bancaria: en qué mes se agota la caja
A25: RETORNO DE LA INVERSIÓN
A26: Flujo de caja libre antes de la deuda, año 1 | B26: =IFERROR(IF('2. P&L 3 Años'!$B$10="","",'2. P&L 3 Años'!$B$50+'2. P&L 3 Años'!$B$38+'7. Financiación'!$B$44),"") -> 65062.19 | D26: Resultado neto más amortización (que no se paga) más los intereses de ese año: el principal no se resta porque este flujo es ANTES de la deuda. La MISMA base que los años 2 y 3, para que el payback compare peras con peras
A27: Flujo de caja libre antes de la deuda, año 2 | B27: =IFERROR(IF('2. P&L 3 Años'!$B$10="","",'2. P&L 3 Años'!$C$50+'2. P&L 3 Años'!$C$38+'7. Financiación'!$B$46),"") -> 86242.626 | D27: Resultado neto más amortización (que no se paga) más los intereses de ese año: el principal no se resta porque este flujo es ANTES de la deuda. Sin tabla mensual, es una estimación
A28: Flujo de caja libre antes de la deuda, año 3 | B28: =IFERROR(IF('2. P&L 3 Años'!$B$10="","",'2. P&L 3 Años'!$D$50+'2. P&L 3 Años'!$D$38+'7. Financiación'!$B$48),"") -> 88559.903 | D28: Resultado neto más amortización (que no se paga) más los intereses de ese año: el principal no se resta porque este flujo es ANTES de la deuda. Sin tabla mensual, es una estimación
A29: Informativo: flujo REAL de caja del año 1 (tabla mensual, antes de la deuda) | B29: =IFERROR(IF('2. P&L 3 Años'!$B$10="","",N21+'7. Financiación'!$B$44+'7. Financiación'!$B$45),"") -> 102668.61 | D29: La suma de los doce FLUJO DEL MES de arriba, devolviéndole los intereses y el principal que se pagaron ese año. NO es la que usa el payback: lleva dentro el IVA que todavía no se ha liquidado y el crédito del proveedor, dos cosas que hay que devolver y que los años 2 y 3 no tienen
A30: Inversión a recuperar (sin el IVA, que se recupera por el 303) | B30: =IFERROR(IF('2. P&L 3 Años'!$B$10="","",'1. Inversión Inicial'!$B$51-'1. Inversión Inicial'!$B$50),"") -> 179014.8 | D30: CAPEX más fondo de maniobra: la necesidad total de caja MENOS el IVA soportado de la inversión, que no se pierde (se recupera con el modelo 303 y esta misma hoja lo compensa trimestre a trimestre). El fondo de maniobra sí se recupera al cerrar, pero hasta entonces está inmovilizado
A31: Payback del proyecto (años), antes de la deuda | B31: =IFERROR(IF('2. P&L 3 Años'!$B$10="","",IF(B26>=B30,ROUND(B30/B26,1),IF(B26+B27>=B30,ROUND(1+(B30-B26)/B27,1),IF(B26+B27+B28>=B30,ROUND(2+(B30-B26-B27)/B28,1),"Más de 3 años")))),"") -> 2.3 | D31: Mide cuánto tarda el negocio en devolver la inversión con lo que genera ANTES de pagar al banco, con la MISMA base de flujo en los tres años; si puedes pagar la cuota lo dice el DSCR de la hoja de Financiación. El documento Word del pack sigue en la versión 1.1 y no lee esta celda: las cifras válidas son las de este libro
A32: Payback sobre el CAPEX, sin fondo de maniobra (años) | B32: =IFERROR(IF('2. P&L 3 Años'!$B$10="","",IF(B26>='1. Inversión Inicial'!$B$49,ROUND('1. Inversión Inicial'!$B$49/B26,1),IF(B26+B27>='1. Inversión Inicial'!$B$49,ROUND(1+('1. Inversión Inicial'!$B$49-B26)/B27,1),IF(B26+B27+B28>='1. Inversión Inicial'!$B$49,ROUND(2+('1. Inversión Inicial'!$B$49-B26-B27)/B28,1),"Más de 3 años")))),"") -> 1.6 | D32: El mismo cálculo sobre lo que se COMPRA (obra, equipamiento, lanzamiento y constitución), sin el fondo de maniobra: ese dinero no se gasta, se inmoviliza y vuelve al cerrar el negocio. Informativo: el payback que se publica es el de arriba
A34: El IVA del cuarto trimestre se liquida en enero del año siguiente, así que no aparece en este cuadro. El Impuesto de Sociedades del año 1 se paga en julio del año 2. La cuota del préstamo se reparte en doce partes iguales siguiendo el cuadro ANUAL de la hoja de Financiación, y las nóminas en doce mensualidades más las dos pagas extra en su mes.

Sheet 7. Financiación
A1: PLAN DE FINANCIACIÓN
A2: Qué hace falta, de dónde sale y cuánto cuesta devolverlo. Es la hoja que el banco pide junto con el P&L.
A4: Concepto | B4: Importe | C4: Notas
A5: ORIGEN DE FONDOS
A6: Recursos propios de los socios | B6: =IFERROR(IF('0. Supuestos'!$B$30="","",'0. Supuestos'!$B$30),"") -> 75000
A7: Préstamo bancario | B7: =IFERROR(IF('0. Supuestos'!$B$31="","",'0. Supuestos'!$B$31),"") -> 128000
A8: Línea ICO (avalada por el ICO, la concede tu banco) | B8: 0 | C8: Consulta las líneas del ejercicio en curso en ico.es
A9: Préstamo participativo ENISA | B9: 0 | C9: Para sociedades; sin garantías personales
A10: Business angels o socios inversores | B10: 0 | C10: Entra en el capital: diluye, no se devuelve
A11: Subvenciones autonómicas o locales | B11: 0 | C11: Suelen cobrarse DESPUÉS de justificar el gasto
A12: TOTAL ORIGEN DE FONDOS | B12: =IFERROR(IF(COUNT(B6:B11)=0,"",SUM(B6:B11)),"") -> 203000
A13: USOS
A14: Necesidad total de caja al arranque | B14: =IFERROR(IF('1. Inversión Inicial'!$B$51="","",'1. Inversión Inicial'!$B$51),"") -> 201717.9 | C14: Inversión más el IVA que hay que adelantar
A15: Diferencia (origen - usos) | B15: =IFERROR(B12-B14,"") -> 1282.1 | C15: En rojo (negativa) el plan NO está financiado. Muy por encima de cero tampoco es gratis: se pagan intereses por un dinero que no se usa
A16: Diferencia sobre los usos (%) | B16: =IFERROR(B15/B14,"") -> 0.0063559059 | C16: Ámbar por encima del margen que fijes: es deuda que pagas sin necesitarla
A17: Exceso de financiación admisible (%) | B17: 0.05 | C17: Un pequeño colchón sobre la necesidad es sano; un 20 % de más son intereses tirados
A18: Préstamo que ajustaría el origen a la necesidad | B18: =IFERROR(MAX(0,B14-B12+B7),"") -> 126717.9 | C18: Cópialo en «Préstamo bancario solicitado» de la hoja de Supuestos y la diferencia se pone a cero
A19: CONDICIONES DEL PRÉSTAMO
A20: Importe del principal | B20: =IFERROR(IF('0. Supuestos'!$B$31=0,"",'0. Supuestos'!$B$31),"") -> 128000
A21: Tipo de interés nominal anual | B21: =IFERROR(IF('0. Supuestos'!$B$32="","",'0. Supuestos'!$B$32),"") -> 0.06
A22: Plazo total (años) | B22: =IFERROR(IF('0. Supuestos'!$B$33="","",'0. Supuestos'!$B$33),"") -> 7
A23: Carencia de principal aplicada (años) | B23: =IFERROR(IF(OR('0. Supuestos'!$B$34="",'0. Supuestos'!$B$33=""),"",IF('0. Supuestos'!$B$34>='0. Supuestos'!$B$33,0,'0. Supuestos'!$B$34)),"") -> 1 | C23: Una carencia igual o mayor que el plazo no existe: la hoja la anula en origen
A24: Cuota anual durante la amortización | B24: =IFERROR(IF(B22-B23<=0,"",IF(B21=0,B20/(B22-B23),B20*B21/(1-(1+B21)^-(B22-B23)))),"") -> 26030.416 | C24: Sistema francés, anualidad algebraica. Con el tipo al 0 % es el principal entre los años de amortización: sin esa rama el cuadro se apagaba entero
A25: CUADRO DE AMORTIZACIÓN
A26: Año | B26: Capital pendiente | C26: Intereses | D26: Amortización de principal | E26: Cuota total | F26: Capital al cierre | G26: Flujo disponible para la deuda (después de impuestos; del año 4 en adelante, el del año 3 mantenido) | H26: DSCR del año
A27: 1 | B27: =IFERROR(IF(B20="","",B20),"") -> 128000 | C27: =IFERROR(IF(OR(1>B22,B27=""),"",B27*B21),"") -> 7680 | D27: =IFERROR(IF(OR(1>B22,B27=""),"",IF(1<=B23,0,MIN(B27,B24-C27))),"") -> 0 | E27: =IFERROR(IF(C27="","",C27+D27),"") -> 7680 | F27: =IFERROR(IF(D27="","",B27-D27),"") -> 128000 | G27: =IFERROR(IF(E27="","",'2. P&L 3 Años'!$B$43-'2. P&L 3 Años'!$B$48+'2. P&L 3 Años'!$B$38+'2. P&L 3 Años'!$B$39),"") -> 65062.19 | H27: =IFERROR(IF(OR(E27="",E27=0),"",G27/E27),"") -> 8.4716393
A28: 2 | B28: =IFERROR(IF(OR(2>B22,F27=""),"",F27),"") -> 128000 | C28: =IFERROR(IF(OR(2>B22,B28=""),"",B28*B21),"") -> 7680 | D28: =IFERROR(IF(OR(2>B22,B28=""),"",IF(2<=B23,0,MIN(B28,B24-C28))),"") -> 18350.416 | E28: =IFERROR(IF(C28="","",C28+D28),"") -> 26030.416 | F28: =IFERROR(IF(D28="","",B28-D28),"") -> 109649.58 | G28: =IFERROR(IF(E28="","",'2. P&L 3 Años'!$C$43-'2. P&L 3 Años'!$C$48+'2. P&L 3 Años'!$C$38+'2. P&L 3 Años'!$C$39),"") -> 86242.626 | H28: =IFERROR(IF(OR(E28="",E28=0),"",G28/E28),"") -> 3.3131481
A29: 3 | B29: =IFERROR(IF(OR(3>B22,F28=""),"",F28),"") -> 109649.58 | C29: =IFERROR(IF(OR(3>B22,B29=""),"",B29*B21),"") -> 6578.975 | D29: =IFERROR(IF(OR(3>B22,B29=""),"",IF(3<=B23,0,MIN(B29,B24-C29))),"") -> 19451.441 | E29: =IFERROR(IF(C29="","",C29+D29),"") -> 26030.416 | F29: =IFERROR(IF(D29="","",B29-D29),"") -> 90198.142 | G29: =IFERROR(IF(E29="","",'2. P&L 3 Años'!$D$43-'2. P&L 3 Años'!$D$48+'2. P&L 3 Años'!$D$38+'2. P&L 3 Años'!$D$39),"") -> 88559.903 | H29: =IFERROR(IF(OR(E29="",E29=0),"",G29/E29),"") -> 3.40217
A30: 4 | B30: =IFERROR(IF(OR(4>B22,F29=""),"",F29),"") -> 90198.142 | C30: =IFERROR(IF(OR(4>B22,B30=""),"",B30*B21),"") -> 5411.8885 | D30: =IFERROR(IF(OR(4>B22,B30=""),"",IF(4<=B23,0,MIN(B30,B24-C30))),"") -> 20618.528 | E30: =IFERROR(IF(C30="","",C30+D30),"") -> 26030.416 | F30: =IFERROR(IF(D30="","",B30-D30),"") -> 69579.614 | G30: =IFERROR(IF(E30="","",'2. P&L 3 Años'!$D$43-'2. P&L 3 Años'!$D$48+'2. P&L 3 Años'!$D$38+'2. P&L 3 Años'!$D$39),"") -> 88559.903 | H30: =IFERROR(IF(OR(E30="",E30=0),"",G30/E30),"") -> 3.40217
A31: 5 | B31: =IFERROR(IF(OR(5>B22,F30=""),"",F30),"") -> 69579.614 | C31: =IFERROR(IF(OR(5>B22,B31=""),"",B31*B21),"") -> 4174.7769 | D31: =IFERROR(IF(OR(5>B22,B31=""),"",IF(5<=B23,0,MIN(B31,B24-C31))),"") -> 21855.64 | E31: =IFERROR(IF(C31="","",C31+D31),"") -> 26030.416 | F31: =IFERROR(IF(D31="","",B31-D31),"") -> 47723.975 | G31: =IFERROR(IF(E31="","",'2. P&L 3 Años'!$D$43-'2. P&L 3 Años'!$D$48+'2. P&L 3 Años'!$D$38+'2. P&L 3 Años'!$D$39),"") -> 88559.903 | H31: =IFERROR(IF(OR(E31="",E31=0),"",G31/E31),"") -> 3.40217
A32: 6 | B32: =IFERROR(IF(OR(6>B22,F31=""),"",F31),"") -> 47723.975 | C32: =IFERROR(IF(OR(6>B22,B32=""),"",B32*B21),"") -> 2863.4385 | D32: =IFERROR(IF(OR(6>B22,B32=""),"",IF(6<=B23,0,MIN(B32,B24-C32))),"") -> 23166.978 | E32: =IFERROR(IF(C32="","",C32+D32),"") -> 26030.416 | F32: =IFERROR(IF(D32="","",B32-D32),"") -> 24556.997 | G32: =IFERROR(IF(E32="","",'2. P&L 3 Años'!$D$43-'2. P&L 3 Años'!$D$48+'2. P&L 3 Años'!$D$38+'2. P&L 3 Años'!$D$39),"") -> 88559.903 | H32: =IFERROR(IF(OR(E32="",E32=0),"",G32/E32),"") -> 3.40217
A33: 7 | B33: =IFERROR(IF(OR(7>B22,F32=""),"",F32),"") -> 24556.997 | C33: =IFERROR(IF(OR(7>B22,B33=""),"",B33*B21),"") -> 1473.4198 | D33: =IFERROR(IF(OR(7>B22,B33=""),"",IF(7<=B23,0,MIN(B33,B24-C33))),"") -> 24556.997 | E33: =IFERROR(IF(C33="","",C33+D33),"") -> 26030.416 | F33: =IFERROR(IF(D33="","",B33-D33),"") -> 1.2369128e-10 | G33: =IFERROR(IF(E33="","",'2. P&L 3 Años'!$D$43-'2. P&L 3 Años'!$D$48+'2. P&L 3 Años'!$D$38+'2. P&L 3 Años'!$D$39),"") -> 88559.903 | H33: =IFERROR(IF(OR(E33="",E33=0),"",G33/E33),"") -> 3.40217
A34: 8 | B34: =IFERROR(IF(OR(8>B22,F33=""),"",F33),"") | C34: =IFERROR(IF(OR(8>B22,B34=""),"",B34*B21),"") | D34: =IFERROR(IF(OR(8>B22,B34=""),"",IF(8<=B23,0,MIN(B34,B24-C34))),"") | E34: =IFERROR(IF(C34="","",C34+D34),"") | F34: =IFERROR(IF(D34="","",B34-D34),"") | G34: =IFERROR(IF(E34="","",'2. P&L 3 Años'!$D$43-'2. P&L 3 Años'!$D$48+'2. P&L 3 Años'!$D$38+'2. P&L 3 Años'!$D$39),"") | H34: =IFERROR(IF(OR(E34="",E34=0),"",G34/E34),"")
A35: 9 | B35: =IFERROR(IF(OR(9>B22,F34=""),"",F34),"") | C35: =IFERROR(IF(OR(9>B22,B35=""),"",B35*B21),"") | D35: =IFERROR(IF(OR(9>B22,B35=""),"",IF(9<=B23,0,MIN(B35,B24-C35))),"") | E35: =IFERROR(IF(C35="","",C35+D35),"") | F35: =IFERROR(IF(D35="","",B35-D35),"") | G35: =IFERROR(IF(E35="","",'2. P&L 3 Años'!$D$43-'2. P&L 3 Años'!$D$48+'2. P&L 3 Años'!$D$38+'2. P&L 3 Años'!$D$39),"") | H35: =IFERROR(IF(OR(E35="",E35=0),"",G35/E35),"")
A36: 10 | B36: =IFERROR(IF(OR(10>B22,F35=""),"",F35),"") | C36: =IFERROR(IF(OR(10>B22,B36=""),"",B36*B21),"") | D36: =IFERROR(IF(OR(10>B22,B36=""),"",IF(10<=B23,0,MIN(B36,B24-C36))),"") | E36: =IFERROR(IF(C36="","",C36+D36),"") | F36: =IFERROR(IF(D36="","",B36-D36),"") | G36: =IFERROR(IF(E36="","",'2. P&L 3 Años'!$D$43-'2. P&L 3 Años'!$D$48+'2. P&L 3 Años'!$D$38+'2. P&L 3 Años'!$D$39),"") | H36: =IFERROR(IF(OR(E36="",E36=0),"",G36/E36),"")
A37: 11 | B37: =IFERROR(IF(OR(11>B22,F36=""),"",F36),"") | C37: =IFERROR(IF(OR(11>B22,B37=""),"",B37*B21),"") | D37: =IFERROR(IF(OR(11>B22,B37=""),"",IF(11<=B23,0,MIN(B37,B24-C37))),"") | E37: =IFERROR(IF(C37="","",C37+D37),"") | F37: =IFERROR(IF(D37="","",B37-D37),"") | G37: =IFERROR(IF(E37="","",'2. P&L 3 Años'!$D$43-'2. P&L 3 Años'!$D$48+'2. P&L 3 Años'!$D$38+'2. P&L 3 Años'!$D$39),"") | H37: =IFERROR(IF(OR(E37="",E37=0),"",G37/E37),"")
A38: 12 | B38: =IFERROR(IF(OR(12>B22,F37=""),"",F37),"") | C38: =IFERROR(IF(OR(12>B22,B38=""),"",B38*B21),"") | D38: =IFERROR(IF(OR(12>B22,B38=""),"",IF(12<=B23,0,MIN(B38,B24-C38))),"") | E38: =IFERROR(IF(C38="","",C38+D38),"") | F38: =IFERROR(IF(D38="","",B38-D38),"") | G38: =IFERROR(IF(E38="","",'2. P&L 3 Años'!$D$43-'2. P&L 3 Años'!$D$48+'2. P&L 3 Años'!$D$38+'2. P&L 3 Años'!$D$39),"") | H38: =IFERROR(IF(OR(E38="",E38=0),"",G38/E38),"")
A39: 13 | B39: =IFERROR(IF(OR(13>B22,F38=""),"",F38),"") | C39: =IFERROR(IF(OR(13>B22,B39=""),"",B39*B21),"") | D39: =IFERROR(IF(OR(13>B22,B39=""),"",IF(13<=B23,0,MIN(B39,B24-C39))),"") | E39: =IFERROR(IF(C39="","",C39+D39),"") | F39: =IFERROR(IF(D39="","",B39-D39),"") | G39: =IFERROR(IF(E39="","",'2. P&L 3 Años'!$D$43-'2. P&L 3 Años'!$D$48+'2. P&L 3 Años'!$D$38+'2. P&L 3 Años'!$D$39),"") | H39: =IFERROR(IF(OR(E39="",E39=0),"",G39/E39),"")
A40: 14 | B40: =IFERROR(IF(OR(14>B22,F39=""),"",F39),"") | C40: =IFERROR(IF(OR(14>B22,B40=""),"",B40*B21),"") | D40: =IFERROR(IF(OR(14>B22,B40=""),"",IF(14<=B23,0,MIN(B40,B24-C40))),"") | E40: =IFERROR(IF(C40="","",C40+D40),"") | F40: =IFERROR(IF(D40="","",B40-D40),"") | G40: =IFERROR(IF(E40="","",'2. P&L 3 Años'!$D$43-'2. P&L 3 Años'!$D$48+'2. P&L 3 Años'!$D$38+'2. P&L 3 Años'!$D$39),"") | H40: =IFERROR(IF(OR(E40="",E40=0),"",G40/E40),"")
A41: 15 | B41: =IFERROR(IF(OR(15>B22,F40=""),"",F40),"") | C41: =IFERROR(IF(OR(15>B22,B41=""),"",B41*B21),"") | D41: =IFERROR(IF(OR(15>B22,B41=""),"",IF(15<=B23,0,MIN(B41,B24-C41))),"") | E41: =IFERROR(IF(C41="","",C41+D41),"") | F41: =IFERROR(IF(D41="","",B41-D41),"") | G41: =IFERROR(IF(E41="","",'2. P&L 3 Años'!$D$43-'2. P&L 3 Años'!$D$48+'2. P&L 3 Años'!$D$38+'2. P&L 3 Años'!$D$39),"") | H41: =IFERROR(IF(OR(E41="",E41=0),"",G41/E41),"")
A42: Tolerancia de cierre del cuadro (€) | B42: 0.01 | C42: Margen por redondeo. Por encima, el cuadro no cierra y hay capital sin devolver
A43: Capital pendiente al vencimiento | B43: =IFERROR(IF(B20="","",ROUND(B20-SUM(D27:D41),2)),"") -> 0 | C43: Tiene que ser cero: el principal devuelto en el cuadro tiene que ser el prestado. Si sale positivo, el plazo no llega
A44: Intereses del año 1 | B44: =IFERROR(IF(B20="","",IF(C27="",0,C27)),"") -> 7680
A45: Devolución de principal del año 1 | B45: =IFERROR(IF(B20="","",IF(D27="",0,D27)),"") -> 0
A46: Intereses del año 2 | B46: =IFERROR(IF(B20="","",IF(C28="",0,C28)),"") -> 7680
A47: Devolución de principal del año 2 | B47: =IFERROR(IF(B20="","",IF(D28="",0,D28)),"") -> 18350.416
A48: Intereses del año 3 | B48: =IFERROR(IF(B20="","",IF(C29="",0,C29)),"") -> 6578.975
A49: Devolución de principal del año 3 | B49: =IFERROR(IF(B20="","",IF(D29="",0,D29)),"") -> 19451.441
A50: COBERTURA DEL SERVICIO DE LA DEUDA (DSCR)
A51: DSCR del año 1 | B51: =IFERROR(('2. P&L 3 Años'!$B$43-'2. P&L 3 Años'!$B$48+'2. P&L 3 Años'!$B$38+B44)/(B44+B45),"") -> 8.4716393 | C51: Año de CARENCIA si la hay: con sólo intereses en el denominador el ratio se dispara y no mide el negocio
A52: DSCR del año 2 | B52: =IFERROR(('2. P&L 3 Años'!$C$43-'2. P&L 3 Años'!$C$48+'2. P&L 3 Años'!$C$38+B46)/(B46+B47),"") -> 3.3131481
A53: DSCR del año 3 | B53: =IFERROR(('2. P&L 3 Años'!$D$43-'2. P&L 3 Años'!$D$48+'2. P&L 3 Años'!$D$38+B48)/(B48+B49),"") -> 3.40217
A54: DSCR mínimo de todo el cuadro | B54: =IFERROR(IF(COUNT(H27:H41)=0,"",MIN(H27:H41)),"") -> 3.3131481 | C54: El peor año de los que dura el préstamo, no el mejor de los tres que proyecta el P&L. Es el número que decide una operación. Ojo al alcance: los años 1 a 3 salen del P&L y del año 4 en adelante el cuadro MANTIENE el flujo del año 3, así que el mínimo de esos años es una proyección sostenida, no un año calculado. El flujo va después de impuestos
A56: El DSCR se calcula ANTES de la deuda y DESPUÉS de impuestos: al resultado antes de impuestos se le resta el Impuesto de Sociedades y se le devuelven la amortización contable y los intereses; el resultado se divide entre lo que hay que pagar ese año. Por debajo del mínimo de la hoja de Supuestos, el negocio no genera para pagar el préstamo. En el cuadro, el flujo de caja disponible de los años 4 en adelante se mantiene en el del año 3: el P&L sólo proyecta tres, y aquí no se inventa un crecimiento que no está calculado.
