Workbook

Sheet Instrucciones
A1: Matriz de formación y polivalencia
A2: AI Chef Pro · aichef.pro — Manual del Manager de Restaurante
A3: Para qué sirve: saber quién cubre una baja, dónde hay una sola persona que sepa hacer algo y cuánto cuesta perderla.
A5: Instrucciones de uso
A6: 1. Hoja «Matriz»: escribe a tu gente en las filas y tus estaciones en la fila verde de cabecera. Vienen sembradas 12 personas y 6 estaciones; caben 30 personas y 12 estaciones sin tocar nada.
A7: 2. Puntúa cada cruce de 0 a 3 con el desplegable. La leyenda está arriba: 0 no formado, 1 formado pero necesita supervisión, 2 autónomo, 3 puede formar a otra persona.
A8: 3. Puntúa quién SOSTIENE la estación en un servicio lleno, no quién ha estado alguna vez. Es el error que vacía de sentido toda la matriz: si todos salen a 2, la matriz no avisa de nada.
A9: 4. Hoja «Cobertura por Estación»: te dice cuántas personas sostienen cada estación y te enciende la alerta cuando sólo hay una. Ése es tu riesgo real: el día que esa persona se pone mala, cierras esa partida.
A10: 5. Hoja «Plan de Cross-Training»: una fila por acción de formación. Quién, qué estación, de qué nivel a qué nivel, quién le enseña y para cuándo. El libro calcula los días que faltan y avisa de lo vencido.
A11: 6. Hoja «Coste de una Baja»: pon TUS horas y TUS costes por hora. Ninguna de las cifras que trae es una referencia de mercado; son un ejemplo para que veas el orden de magnitud y lo rehagas con tus números.
A12: 7. Revisa la matriz una vez al trimestre, no cuando ya tienes el problema encima. Una estación pasa de cubierta a descubierta con una sola baja.
A14: Celdas verdes = campos editables
... A28: Versión 1.0 · septiembre 2026 · aichef.pro/manual-manager-restaurante · info@aichef.pro

Sheet Matriz
A1: Matriz de polivalencia
A2: AI Chef Pro · aichef.pro — Manual del Manager de Restaurante
A3: Puntúa quién puede SOSTENER la estación en un servicio lleno, no quién ha estado alguna vez.
A5: Nivel | B5: Qué significa
A6: 0 | B6: No formado
A7: 1 | B7: Formado, necesita supervisión
A8: 2 | B8: Autónomo: puede llevar la estación en un servicio
A9: 3 | B9: Puede formar a otra persona
A11: Parámetro | B11: Valor
A12: Nivel mínimo para dar una estación por cubierta | B12: 2
A13: Nivel a partir del cual se puede enseñar la estación | B13: 3
A14: Punto único de fallo: personas o menos por estación | B14: 1
A15: Los tres son celdas verdes: ninguna de estas cifras vive dentro de una fórmula. Si en tu casa una estación no está cubierta hasta que hay dos personas, sube el umbral de riesgo a 2.
A17: Id | B17: Nombre | C17: Puesto | D17: Estación principal | E17: Pase y caliente | F17: Fríos y entrantes | G17: Postres y panadería | H17: Barra y bebidas | I17: Sala y servicio | J17: Caja y cierre | Q17: Estaciones que puede sostener | R17: Estaciones que puede enseñar
A18: P01 | B18: Marta L. | C18: Gerente / encargada general (manager) | D18: Caja y cierre | E18: 1 | F18: 0 | G18: 0 | H18: 2 | I18: 3 | J18: 3 | Q18: =IF(OR($A18="",ISNUMBER($B$12)=FALSE),"",COUNTIFS($E18:$P18,">="&$B$12)) -> 3 | R18: =IF(OR($A18="",ISNUMBER($B$13)=FALSE),"",COUNTIFS($E18:$P18,">="&$B$13)) -> 2
A19: P02 | B19: Iván R. | C19: Jefe de cocina | D19: Pase y caliente | E19: 3 | F19: 1 | G19: 2 | H19: 0 | I19: 0 | J19: 1 | Q19: =IF(OR($A19="",ISNUMBER($B$12)=FALSE),"",COUNTIFS($E19:$P19,">="&$B$12)) -> 2 | R19: =IF(OR($A19="",ISNUMBER($B$13)=FALSE),"",COUNTIFS($E19:$P19,">="&$B$13)) -> 1
A20: P03 | B20: Nuria C. | C20: Jefa de sala | D20: Sala y servicio | E20: 0 | F20: 0 | G20: 1 | H20: 3 | I20: 3 | J20: 3 | Q20: =IF(OR($A20="",ISNUMBER($B$12)=FALSE),"",COUNTIFS($E20:$P20,">="&$B$12)) -> 3 | R20: =IF(OR($A20="",ISNUMBER($B$13)=FALSE),"",COUNTIFS($E20:$P20,">="&$B$13)) -> 3
A21: P04 | B21: Diego M. | C21: Cocinero (partida caliente) | D21: Pase y caliente | E21: 3 | F21: 1 | G21: 1 | H21: 0 | I21: 0 | J21: 0 | Q21: =IF(OR($A21="",ISNUMBER($B$12)=FALSE),"",COUNTIFS($E21:$P21,">="&$B$12)) -> 1 | R21: =IF(OR($A21="",ISNUMBER($B$13)=FALSE),"",COUNTIFS($E21:$P21,">="&$B$13)) -> 1
A22: P05 | B22: Laura S. | C22: Cocinera (partida fría) | D22: Fríos y entrantes | E22: 2 | F22: 3 | G22: 2 | H22: 0 | I22: 0 | J22: 0 | Q22: =IF(OR($A22="",ISNUMBER($B$12)=FALSE),"",COUNTIFS($E22:$P22,">="&$B$12)) -> 3 | R22: =IF(OR($A22="",ISNUMBER($B$13)=FALSE),"",COUNTIFS($E22:$P22,">="&$B$13)) -> 1
A23: P06 | B23: Omar B. | C23: Ayudante de cocina | D23: Pase y caliente | E23: 2 | F23: 1 | G23: 1 | H23: 0 | I23: 0 | J23: 0 | Q23: =IF(OR($A23="",ISNUMBER($B$12)=FALSE),"",COUNTIFS($E23:$P23,">="&$B$12)) -> 1 | R23: =IF(OR($A23="",ISNUMBER($B$13)=FALSE),"",COUNTIFS($E23:$P23,">="&$B$13)) -> 0
A24: P07 | B24: Rocío F. | C24: Ayudante de cocina y postres | D24: Postres y panadería | E24: 1 | F24: 1 | G24: 3 | H24: 0 | I24: 0 | J24: 0 | Q24: =IF(OR($A24="",ISNUMBER($B$12)=FALSE),"",COUNTIFS($E24:$P24,">="&$B$12)) -> 1 | R24: =IF(OR($A24="",ISNUMBER($B$13)=FALSE),"",COUNTIFS($E24:$P24,">="&$B$13)) -> 1
A25: P08 | B25: Carlos V. | C25: Camarero, jefe de rango | D25: Sala y servicio | E25: 0 | F25: 0 | G25: 0 | H25: 2 | I25: 3 | J25: 2 | Q25: =IF(OR($A25="",ISNUMBER($B$12)=FALSE),"",COUNTIFS($E25:$P25,">="&$B$12)) -> 3 | R25: =IF(OR($A25="",ISNUMBER($B$13)=FALSE),"",COUNTIFS($E25:$P25,">="&$B$13)) -> 1
A26: P09 | B26: Elena T. | C26: Camarera | D26: Barra y bebidas | E26: 0 | F26: 0 | G26: 0 | H26: 3 | I26: 3 | J26: 1 | Q26: =IF(OR($A26="",ISNUMBER($B$12)=FALSE),"",COUNTIFS($E26:$P26,">="&$B$12)) -> 2 | R26: =IF(OR($A26="",ISNUMBER($B$13)=FALSE),"",COUNTIFS($E26:$P26,">="&$B$13)) -> 2
A27: P10 | B27: Youssef A. | C27: Camarero | D27: Sala y servicio | E27: 0 | F27: 0 | G27: 0 | H27: 1 | I27: 2 | J27: 1 | Q27: =IF(OR($A27="",ISNUMBER($B$12)=FALSE),"",COUNTIFS($E27:$P27,">="&$B$12)) -> 1 | R27: =IF(OR($A27="",ISNUMBER($B$13)=FALSE),"",COUNTIFS($E27:$P27,">="&$B$13)) -> 0
A28: P11 | B28: Paula G. | C28: Ayudante de camarera | D28: Barra y bebidas | E28: 0 | F28: 0 | G28: 0 | H28: 1 | I28: 1 | J28: 0 | Q28: =IF(OR($A28="",ISNUMBER($B$12)=FALSE),"",COUNTIFS($E28:$P28,">="&$B$12)) -> 0 | R28: =IF(OR($A28="",ISNUMBER($B$13)=FALSE),"",COUNTIFS($E28:$P28,">="&$B$13)) -> 0
A29: P12 | B29: Andrés P. | C29: Friegaplatos y office | D29: Pase y caliente | E29: 1 | F29: 0 | G29: 0 | H29: 0 | I29: 0 | J29: 0 | Q29: =IF(OR($A29="",ISNUMBER($B$12)=FALSE),"",COUNTIFS($E29:$P29,">="&$B$12)) -> 0 | R29: =IF(OR($A29="",ISNUMBER($B$13)=FALSE),"",COUNTIFS($E29:$P29,">="&$B$13)) -> 0
Q30: =IF(OR($A30="",ISNUMBER($B$12)=FALSE),"",COUNTIFS($E30:$P30,">="&$B$12)) | R30: =IF(OR($A30="",ISNUMBER($B$13)=FALSE),"",COUNTIFS($E30:$P30,">="&$B$13))
Q31: =IF(OR($A31="",ISNUMBER($B$12)=FALSE),"",COUNTIFS($E31:$P31,">="&$B$12)) | R31: =IF(OR($A31="",ISNUMBER($B$13)=FALSE),"",COUNTIFS($E31:$P31,">="&$B$13))
Q32: =IF(OR($A32="",ISNUMBER($B$12)=FALSE),"",COUNTIFS($E32:$P32,">="&$B$12)) | R32: =IF(OR($A32="",ISNUMBER($B$13)=FALSE),"",COUNTIFS($E32:$P32,">="&$B$13))
Q33: =IF(OR($A33="",ISNUMBER($B$12)=FALSE),"",COUNTIFS($E33:$P33,">="&$B$12)) | R33: =IF(OR($A33="",ISNUMBER($B$13)=FALSE),"",COUNTIFS($E33:$P33,">="&$B$13))
Q34: =IF(OR($A34="",ISNUMBER($B$12)=FALSE),"",COUNTIFS($E34:$P34,">="&$B$12)) | R34: =IF(OR($A34="",ISNUMBER($B$13)=FALSE),"",COUNTIFS($E34:$P34,">="&$B$13))
Q35: =IF(OR($A35="",ISNUMBER($B$12)=FALSE),"",COUNTIFS($E35:$P35,">="&$B$12)) | R35: =IF(OR($A35="",ISNUMBER($B$13)=FALSE),"",COUNTIFS($E35:$P35,">="&$B$13))
Q36: =IF(OR($A36="",ISNUMBER($B$12)=FALSE),"",COUNTIFS($E36:$P36,">="&$B$12)) | R36: =IF(OR($A36="",ISNUMBER($B$13)=FALSE),"",COUNTIFS($E36:$P36,">="&$B$13))
Q37: =IF(OR($A37="",ISNUMBER($B$12)=FALSE),"",COUNTIFS($E37:$P37,">="&$B$12)) | R37: =IF(OR($A37="",ISNUMBER($B$13)=FALSE),"",COUNTIFS($E37:$P37,">="&$B$13))
Q38: =IF(OR($A38="",ISNUMBER($B$12)=FALSE),"",COUNTIFS($E38:$P38,">="&$B$12)) | R38: =IF(OR($A38="",ISNUMBER($B$13)=FALSE),"",COUNTIFS($E38:$P38,">="&$B$13))
Q39: =IF(OR($A39="",ISNUMBER($B$12)=FALSE),"",COUNTIFS($E39:$P39,">="&$B$12)) | R39: =IF(OR($A39="",ISNUMBER($B$13)=FALSE),"",COUNTIFS($E39:$P39,">="&$B$13))
Q40: =IF(OR($A40="",ISNUMBER($B$12)=FALSE),"",COUNTIFS($E40:$P40,">="&$B$12)) | R40: =IF(OR($A40="",ISNUMBER($B$13)=FALSE),"",COUNTIFS($E40:$P40,">="&$B$13))
Q41: =IF(OR($A41="",ISNUMBER($B$12)=FALSE),"",COUNTIFS($E41:$P41,">="&$B$12)) | R41: =IF(OR($A41="",ISNUMBER($B$13)=FALSE),"",COUNTIFS($E41:$P41,">="&$B$13))
... Q47: =IF(OR($A47="",ISNUMBER($B$12)=FALSE),"",COUNTIFS($E47:$P47,">="&$B$12)) | R47: =IF(OR($A47="",ISNUMBER($B$13)=FALSE),"",COUNTIFS($E47:$P47,">="&$B$13))

Sheet Plan de Cross-Training
A1: Plan de cross-training
A2: AI Chef Pro · aichef.pro — Manual del Manager de Restaurante
A3: Una fila por acción de formación: quién, qué estación, de qué nivel a qué nivel, quién le enseña y para cuándo.
A5: Fecha de corte (desde cuándo se cuentan los días) | C5: 46269
A6: Avisar cuando falten estos días o menos | C6: 30
A7: Las dos son celdas verdes. La fecha de corte no se toma del reloj a propósito: así el libro enseña siempre lo mismo cada vez que se abre y no cambia de color solo.
A9: # | B9: Id del empleado | C9: Nombre | D9: Estación objetivo | E9: Nivel actual | F9: Nivel objetivo | G9: Quién le enseña | H9: Fecha objetivo | I9: Estado | J9: Niveles que faltan | K9: Días hasta la fecha | L9: Situación del plazo
A10: 1 | B10: P06 | C10: Omar B. | D10: Fríos y entrantes | E10: 1 | F10: 2 | G10: Laura S. | H10: 46310 | I10: En curso | J10: =IFERROR(IF(OR($E10="",$F10=""),"",$F10-$E10),"") -> 1 | K10: =IFERROR(IF(OR($H10="",$C$5=""),"",$H10-$C$5),"") -> 41 | L10: =IF($K10="","",IF($I10="Completado","Completado",IF($I10="Descartado","Descartado",IF($K10<0,"Vencido",IF(AND(ISNUMBER($C$6),$K10<=$C$6),"Vence pronto","En plazo"))))) -> En plazo
A11: 2 | B11: P04 | C11: Diego M. | D11: Fríos y entrantes | E11: 1 | F11: 2 | G11: Laura S. | H11: 46356 | I11: Planificado | J11: =IFERROR(IF(OR($E11="",$F11=""),"",$F11-$E11),"") -> 1 | K11: =IFERROR(IF(OR($H11="",$C$5=""),"",$H11-$C$5),"") -> 87 | L11: =IF($K11="","",IF($I11="Completado","Completado",IF($I11="Descartado","Descartado",IF($K11<0,"Vencido",IF(AND(ISNUMBER($C$6),$K11<=$C$6),"Vence pronto","En plazo"))))) -> En plazo
A12: 3 | B12: P02 | C12: Iván R. | D12: Fríos y entrantes | E12: 1 | F12: 3 | G12: Laura S. | H12: 46371 | I12: Planificado | J12: =IFERROR(IF(OR($E12="",$F12=""),"",$F12-$E12),"") -> 2 | K12: =IFERROR(IF(OR($H12="",$C$5=""),"",$H12-$C$5),"") -> 102 | L12: =IF($K12="","",IF($I12="Completado","Completado",IF($I12="Descartado","Descartado",IF($K12<0,"Vencido",IF(AND(ISNUMBER($C$6),$K12<=$C$6),"Vence pronto","En plazo"))))) -> En plazo
A13: 4 | B13: P10 | C13: Youssef A. | D13: Barra y bebidas | E13: 1 | F13: 2 | G13: Elena T. | H13: 46326 | I13: En curso | J13: =IFERROR(IF(OR($E13="",$F13=""),"",$F13-$E13),"") -> 1 | K13: =IFERROR(IF(OR($H13="",$C$5=""),"",$H13-$C$5),"") -> 57 | L13: =IF($K13="","",IF($I13="Completado","Completado",IF($I13="Descartado","Descartado",IF($K13<0,"Vencido",IF(AND(ISNUMBER($C$6),$K13<=$C$6),"Vence pronto","En plazo"))))) -> En plazo
A14: 5 | B14: P11 | C14: Paula G. | D14: Sala y servicio | E14: 1 | F14: 2 | G14: Nuria C. | H14: 46341 | I14: Planificado | J14: =IFERROR(IF(OR($E14="",$F14=""),"",$F14-$E14),"") -> 1 | K14: =IFERROR(IF(OR($H14="",$C$5=""),"",$H14-$C$5),"") -> 72 | L14: =IF($K14="","",IF($I14="Completado","Completado",IF($I14="Descartado","Descartado",IF($K14<0,"Vencido",IF(AND(ISNUMBER($C$6),$K14<=$C$6),"Vence pronto","En plazo"))))) -> En plazo
A15: 6 | B15: P08 | C15: Carlos V. | D15: Caja y cierre | E15: 2 | F15: 3 | G15: Marta L. | H15: 46315 | I15: En curso | J15: =IFERROR(IF(OR($E15="",$F15=""),"",$F15-$E15),"") -> 1 | K15: =IFERROR(IF(OR($H15="",$C$5=""),"",$H15-$C$5),"") -> 46 | L15: =IF($K15="","",IF($I15="Completado","Completado",IF($I15="Descartado","Descartado",IF($K15<0,"Vencido",IF(AND(ISNUMBER($C$6),$K15<=$C$6),"Vence pronto","En plazo"))))) -> En plazo
A16: 7 | B16: P12 | C16: Andrés P. | D16: Pase y caliente | E16: 1 | F16: 2 | G16: Diego M. | H16: 46418 | I16: Planificado | J16: =IFERROR(IF(OR($E16="",$F16=""),"",$F16-$E16),"") -> 1 | K16: =IFERROR(IF(OR($H16="",$C$5=""),"",$H16-$C$5),"") -> 149 | L16: =IF($K16="","",IF($I16="Completado","Completado",IF($I16="Descartado","Descartado",IF($K16<0,"Vencido",IF(AND(ISNUMBER($C$6),$K16<=$C$6),"Vence pronto","En plazo"))))) -> En plazo
A17: 8 | B17: P07 | C17: Rocío F. | D17: Pase y caliente | E17: 1 | F17: 2 | G17: Iván R. | H17: 46446 | I17: Planificado | J17: =IFERROR(IF(OR($E17="",$F17=""),"",$F17-$E17),"") -> 1 | K17: =IFERROR(IF(OR($H17="",$C$5=""),"",$H17-$C$5),"") -> 177 | L17: =IF($K17="","",IF($I17="Completado","Completado",IF($I17="Descartado","Descartado",IF($K17<0,"Vencido",IF(AND(ISNUMBER($C$6),$K17<=$C$6),"Vence pronto","En plazo"))))) -> En plazo
A18: 9 | J18: =IFERROR(IF(OR($E18="",$F18=""),"",$F18-$E18),"") | K18: =IFERROR(IF(OR($H18="",$C$5=""),"",$H18-$C$5),"") | L18: =IF($K18="","",IF($I18="Completado","Completado",IF($I18="Descartado","Descartado",IF($K18<0,"Vencido",IF(AND(ISNUMBER($C$6),$K18<=$C$6),"Vence pronto","En plazo")))))
A19: 10 | J19: =IFERROR(IF(OR($E19="",$F19=""),"",$F19-$E19),"") | K19: =IFERROR(IF(OR($H19="",$C$5=""),"",$H19-$C$5),"") | L19: =IF($K19="","",IF($I19="Completado","Completado",IF($I19="Descartado","Descartado",IF($K19<0,"Vencido",IF(AND(ISNUMBER($C$6),$K19<=$C$6),"Vence pronto","En plazo")))))
A20: 11 | J20: =IFERROR(IF(OR($E20="",$F20=""),"",$F20-$E20),"") | K20: =IFERROR(IF(OR($H20="",$C$5=""),"",$H20-$C$5),"") | L20: =IF($K20="","",IF($I20="Completado","Completado",IF($I20="Descartado","Descartado",IF($K20<0,"Vencido",IF(AND(ISNUMBER($C$6),$K20<=$C$6),"Vence pronto","En plazo")))))
A21: 12 | J21: =IFERROR(IF(OR($E21="",$F21=""),"",$F21-$E21),"") | K21: =IFERROR(IF(OR($H21="",$C$5=""),"",$H21-$C$5),"") | L21: =IF($K21="","",IF($I21="Completado","Completado",IF($I21="Descartado","Descartado",IF($K21<0,"Vencido",IF(AND(ISNUMBER($C$6),$K21<=$C$6),"Vence pronto","En plazo")))))
A22: 13 | J22: =IFERROR(IF(OR($E22="",$F22=""),"",$F22-$E22),"") | K22: =IFERROR(IF(OR($H22="",$C$5=""),"",$H22-$C$5),"") | L22: =IF($K22="","",IF($I22="Completado","Completado",IF($I22="Descartado","Descartado",IF($K22<0,"Vencido",IF(AND(ISNUMBER($C$6),$K22<=$C$6),"Vence pronto","En plazo")))))
A23: 14 | J23: =IFERROR(IF(OR($E23="",$F23=""),"",$F23-$E23),"") | K23: =IFERROR(IF(OR($H23="",$C$5=""),"",$H23-$C$5),"") | L23: =IF($K23="","",IF($I23="Completado","Completado",IF($I23="Descartado","Descartado",IF($K23<0,"Vencido",IF(AND(ISNUMBER($C$6),$K23<=$C$6),"Vence pronto","En plazo")))))
A24: 15 | J24: =IFERROR(IF(OR($E24="",$F24=""),"",$F24-$E24),"") | K24: =IFERROR(IF(OR($H24="",$C$5=""),"",$H24-$C$5),"") | L24: =IF($K24="","",IF($I24="Completado","Completado",IF($I24="Descartado","Descartado",IF($K24<0,"Vencido",IF(AND(ISNUMBER($C$6),$K24<=$C$6),"Vence pronto","En plazo")))))
A25: 16 | J25: =IFERROR(IF(OR($E25="",$F25=""),"",$F25-$E25),"") | K25: =IFERROR(IF(OR($H25="",$C$5=""),"",$H25-$C$5),"") | L25: =IF($K25="","",IF($I25="Completado","Completado",IF($I25="Descartado","Descartado",IF($K25<0,"Vencido",IF(AND(ISNUMBER($C$6),$K25<=$C$6),"Vence pronto","En plazo")))))
A26: 17 | J26: =IFERROR(IF(OR($E26="",$F26=""),"",$F26-$E26),"") | K26: =IFERROR(IF(OR($H26="",$C$5=""),"",$H26-$C$5),"") | L26: =IF($K26="","",IF($I26="Completado","Completado",IF($I26="Descartado","Descartado",IF($K26<0,"Vencido",IF(AND(ISNUMBER($C$6),$K26<=$C$6),"Vence pronto","En plazo")))))
A27: 18 | J27: =IFERROR(IF(OR($E27="",$F27=""),"",$F27-$E27),"") | K27: =IFERROR(IF(OR($H27="",$C$5=""),"",$H27-$C$5),"") | L27: =IF($K27="","",IF($I27="Completado","Completado",IF($I27="Descartado","Descartado",IF($K27<0,"Vencido",IF(AND(ISNUMBER($C$6),$K27<=$C$6),"Vence pronto","En plazo")))))
A28: 19 | J28: =IFERROR(IF(OR($E28="",$F28=""),"",$F28-$E28),"") | K28: =IFERROR(IF(OR($H28="",$C$5=""),"",$H28-$C$5),"") | L28: =IF($K28="","",IF($I28="Completado","Completado",IF($I28="Descartado","Descartado",IF($K28<0,"Vencido",IF(AND(ISNUMBER($C$6),$K28<=$C$6),"Vence pronto","En plazo")))))
A29: 20 | J29: =IFERROR(IF(OR($E29="",$F29=""),"",$F29-$E29),"") | K29: =IFERROR(IF(OR($H29="",$C$5=""),"",$H29-$C$5),"") | L29: =IF($K29="","",IF($I29="Completado","Completado",IF($I29="Descartado","Descartado",IF($K29<0,"Vencido",IF(AND(ISNUMBER($C$6),$K29<=$C$6),"Vence pronto","En plazo")))))
A31: RESUMEN DEL PLAN
A32: Acciones registradas | C32: =COUNTIF($B$10:$B$29,"<>") -> 8
A33: Completadas | C33: =COUNTIF($I$10:$I$29,"Completado") -> 0
A34: En curso | C34: =COUNTIF($I$10:$I$29,"En curso") -> 3
A35: Planificadas | C35: =COUNTIF($I$10:$I$29,"Planificado") -> 5
A36: Vencidas | C36: =COUNTIF($L$10:$L$29,"Vencido") -> 0
A37: Que vencen pronto | C37: =COUNTIF($L$10:$L$29,"Vence pronto") -> 0
A38: Acciones completadas (%) | C38: =IFERROR(IF(OR($C$32="",$C$32=0),"",$C$33/$C$32),"") -> 0

Sheet Cobertura por Estación
A1: Cobertura por estación
A2: AI Chef Pro · aichef.pro — Manual del Manager de Restaurante
A3: Se calcula sola desde la hoja «Matriz». Si una estación tiene una sola persona que la sostenga, aquí se enciende.
A5: PARÁMETROS EN VIGOR — se leen de la hoja «Matriz»; cámbialos allí, no aquí
A6: Nivel mínimo para dar una estación por cubierta | C6: =IF(Matriz!$B$12="","",Matriz!$B$12) -> 2
A7: Nivel a partir del cual se puede enseñar | C7: =IF(Matriz!$B$13="","",Matriz!$B$13) -> 3
A8: Punto único de fallo: personas o menos | C8: =IF(Matriz!$B$14="","",Matriz!$B$14) -> 1
A9: Se copian aquí porque el formato condicional no puede leer otra hoja: los colores de esta tabla necesitan tener el umbral al lado.
A11: Estación | B11: Personas que la sostienen | C11: Personas que pueden enseñarla | D11: Personas en la matriz | E11: Cobertura (%) | F11: Alerta
A12: =IF(Matriz!E$17="","",Matriz!E$17) -> Pase y caliente | B12: =IF(OR($A12="",ISNUMBER($C$6)=FALSE),"",COUNTIFS(Matriz!$E$18:$E$47,">="&$C$6)) -> 4 | C12: =IF(OR($A12="",ISNUMBER($C$7)=FALSE),"",COUNTIFS(Matriz!$E$18:$E$47,">="&$C$7)) -> 2 | D12: =IF($A12="","",COUNTIF(Matriz!$A$18:$A$47,"<>")) -> 12 | E12: =IFERROR(IF(OR($B12="",$D12="",$D12=0),"",$B12/$D12),"") -> 0.33333333 | F12: =IF($B12="","",IF($B12=0,"RIESGO: nadie puede sostener esta estación",IF($B12=1,"RIESGO: punto único de fallo, solo 1 persona puede sostener esta estación",IF(AND(ISNUMBER($C$8),$B12<=$C$8),"Cobertura por debajo del umbral","Cobertura suficiente")))) -> Cobertura suficiente
A13: =IF(Matriz!F$17="","",Matriz!F$17) -> Fríos y entrantes | B13: =IF(OR($A13="",ISNUMBER($C$6)=FALSE),"",COUNTIFS(Matriz!$F$18:$F$47,">="&$C$6)) -> 1 | C13: =IF(OR($A13="",ISNUMBER($C$7)=FALSE),"",COUNTIFS(Matriz!$F$18:$F$47,">="&$C$7)) -> 1 | D13: =IF($A13="","",COUNTIF(Matriz!$A$18:$A$47,"<>")) -> 12 | E13: =IFERROR(IF(OR($B13="",$D13="",$D13=0),"",$B13/$D13),"") -> 0.083333333 | F13: =IF($B13="","",IF($B13=0,"RIESGO: nadie puede sostener esta estación",IF($B13=1,"RIESGO: punto único de fallo, solo 1 persona puede sostener esta estación",IF(AND(ISNUMBER($C$8),$B13<=$C$8),"Cobertura por debajo del umbral","Cobertura suficiente")))) -> RIESGO: punto único de fallo, solo 1 persona puede sostener esta estación
A14: =IF(Matriz!G$17="","",Matriz!G$17) -> Postres y panadería | B14: =IF(OR($A14="",ISNUMBER($C$6)=FALSE),"",COUNTIFS(Matriz!$G$18:$G$47,">="&$C$6)) -> 3 | C14: =IF(OR($A14="",ISNUMBER($C$7)=FALSE),"",COUNTIFS(Matriz!$G$18:$G$47,">="&$C$7)) -> 1 | D14: =IF($A14="","",COUNTIF(Matriz!$A$18:$A$47,"<>")) -> 12 | E14: =IFERROR(IF(OR($B14="",$D14="",$D14=0),"",$B14/$D14),"") -> 0.25 | F14: =IF($B14="","",IF($B14=0,"RIESGO: nadie puede sostener esta estación",IF($B14=1,"RIESGO: punto único de fallo, solo 1 persona puede sostener esta estación",IF(AND(ISNUMBER($C$8),$B14<=$C$8),"Cobertura por debajo del umbral","Cobertura suficiente")))) -> Cobertura suficiente
A15: =IF(Matriz!H$17="","",Matriz!H$17) -> Barra y bebidas | B15: =IF(OR($A15="",ISNUMBER($C$6)=FALSE),"",COUNTIFS(Matriz!$H$18:$H$47,">="&$C$6)) -> 4 | C15: =IF(OR($A15="",ISNUMBER($C$7)=FALSE),"",COUNTIFS(Matriz!$H$18:$H$47,">="&$C$7)) -> 2 | D15: =IF($A15="","",COUNTIF(Matriz!$A$18:$A$47,"<>")) -> 12 | E15: =IFERROR(IF(OR($B15="",$D15="",$D15=0),"",$B15/$D15),"") -> 0.33333333 | F15: =IF($B15="","",IF($B15=0,"RIESGO: nadie puede sostener esta estación",IF($B15=1,"RIESGO: punto único de fallo, solo 1 persona puede sostener esta estación",IF(AND(ISNUMBER($C$8),$B15<=$C$8),"Cobertura por debajo del umbral","Cobertura suficiente")))) -> Cobertura suficiente
A16: =IF(Matriz!I$17="","",Matriz!I$17) -> Sala y servicio | B16: =IF(OR($A16="",ISNUMBER($C$6)=FALSE),"",COUNTIFS(Matriz!$I$18:$I$47,">="&$C$6)) -> 5 | C16: =IF(OR($A16="",ISNUMBER($C$7)=FALSE),"",COUNTIFS(Matriz!$I$18:$I$47,">="&$C$7)) -> 4 | D16: =IF($A16="","",COUNTIF(Matriz!$A$18:$A$47,"<>")) -> 12 | E16: =IFERROR(IF(OR($B16="",$D16="",$D16=0),"",$B16/$D16),"") -> 0.41666667 | F16: =IF($B16="","",IF($B16=0,"RIESGO: nadie puede sostener esta estación",IF($B16=1,"RIESGO: punto único de fallo, solo 1 persona puede sostener esta estación",IF(AND(ISNUMBER($C$8),$B16<=$C$8),"Cobertura por debajo del umbral","Cobertura suficiente")))) -> Cobertura suficiente
A17: =IF(Matriz!J$17="","",Matriz!J$17) -> Caja y cierre | B17: =IF(OR($A17="",ISNUMBER($C$6)=FALSE),"",COUNTIFS(Matriz!$J$18:$J$47,">="&$C$6)) -> 3 | C17: =IF(OR($A17="",ISNUMBER($C$7)=FALSE),"",COUNTIFS(Matriz!$J$18:$J$47,">="&$C$7)) -> 2 | D17: =IF($A17="","",COUNTIF(Matriz!$A$18:$A$47,"<>")) -> 12 | E17: =IFERROR(IF(OR($B17="",$D17="",$D17=0),"",$B17/$D17),"") -> 0.25 | F17: =IF($B17="","",IF($B17=0,"RIESGO: nadie puede sostener esta estación",IF($B17=1,"RIESGO: punto único de fallo, solo 1 persona puede sostener esta estación",IF(AND(ISNUMBER($C$8),$B17<=$C$8),"Cobertura por debajo del umbral","Cobertura suficiente")))) -> Cobertura suficiente
A18: =IF(Matriz!K$17="","",Matriz!K$17) | B18: =IF(OR($A18="",ISNUMBER($C$6)=FALSE),"",COUNTIFS(Matriz!$K$18:$K$47,">="&$C$6)) | C18: =IF(OR($A18="",ISNUMBER($C$7)=FALSE),"",COUNTIFS(Matriz!$K$18:$K$47,">="&$C$7)) | D18: =IF($A18="","",COUNTIF(Matriz!$A$18:$A$47,"<>")) | E18: =IFERROR(IF(OR($B18="",$D18="",$D18=0),"",$B18/$D18),"") | F18: =IF($B18="","",IF($B18=0,"RIESGO: nadie puede sostener esta estación",IF($B18=1,"RIESGO: punto único de fallo, solo 1 persona puede sostener esta estación",IF(AND(ISNUMBER($C$8),$B18<=$C$8),"Cobertura por debajo del umbral","Cobertura suficiente"))))
A19: =IF(Matriz!L$17="","",Matriz!L$17) | B19: =IF(OR($A19="",ISNUMBER($C$6)=FALSE),"",COUNTIFS(Matriz!$L$18:$L$47,">="&$C$6)) | C19: =IF(OR($A19="",ISNUMBER($C$7)=FALSE),"",COUNTIFS(Matriz!$L$18:$L$47,">="&$C$7)) | D19: =IF($A19="","",COUNTIF(Matriz!$A$18:$A$47,"<>")) | E19: =IFERROR(IF(OR($B19="",$D19="",$D19=0),"",$B19/$D19),"") | F19: =IF($B19="","",IF($B19=0,"RIESGO: nadie puede sostener esta estación",IF($B19=1,"RIESGO: punto único de fallo, solo 1 persona puede sostener esta estación",IF(AND(ISNUMBER($C$8),$B19<=$C$8),"Cobertura por debajo del umbral","Cobertura suficiente"))))
A20: =IF(Matriz!M$17="","",Matriz!M$17) | B20: =IF(OR($A20="",ISNUMBER($C$6)=FALSE),"",COUNTIFS(Matriz!$M$18:$M$47,">="&$C$6)) | C20: =IF(OR($A20="",ISNUMBER($C$7)=FALSE),"",COUNTIFS(Matriz!$M$18:$M$47,">="&$C$7)) | D20: =IF($A20="","",COUNTIF(Matriz!$A$18:$A$47,"<>")) | E20: =IFERROR(IF(OR($B20="",$D20="",$D20=0),"",$B20/$D20),"") | F20: =IF($B20="","",IF($B20=0,"RIESGO: nadie puede sostener esta estación",IF($B20=1,"RIESGO: punto único de fallo, solo 1 persona puede sostener esta estación",IF(AND(ISNUMBER($C$8),$B20<=$C$8),"Cobertura por debajo del umbral","Cobertura suficiente"))))
A21: =IF(Matriz!N$17="","",Matriz!N$17) | B21: =IF(OR($A21="",ISNUMBER($C$6)=FALSE),"",COUNTIFS(Matriz!$N$18:$N$47,">="&$C$6)) | C21: =IF(OR($A21="",ISNUMBER($C$7)=FALSE),"",COUNTIFS(Matriz!$N$18:$N$47,">="&$C$7)) | D21: =IF($A21="","",COUNTIF(Matriz!$A$18:$A$47,"<>")) | E21: =IFERROR(IF(OR($B21="",$D21="",$D21=0),"",$B21/$D21),"") | F21: =IF($B21="","",IF($B21=0,"RIESGO: nadie puede sostener esta estación",IF($B21=1,"RIESGO: punto único de fallo, solo 1 persona puede sostener esta estación",IF(AND(ISNUMBER($C$8),$B21<=$C$8),"Cobertura por debajo del umbral","Cobertura suficiente"))))
A22: =IF(Matriz!O$17="","",Matriz!O$17) | B22: =IF(OR($A22="",ISNUMBER($C$6)=FALSE),"",COUNTIFS(Matriz!$O$18:$O$47,">="&$C$6)) | C22: =IF(OR($A22="",ISNUMBER($C$7)=FALSE),"",COUNTIFS(Matriz!$O$18:$O$47,">="&$C$7)) | D22: =IF($A22="","",COUNTIF(Matriz!$A$18:$A$47,"<>")) | E22: =IFERROR(IF(OR($B22="",$D22="",$D22=0),"",$B22/$D22),"") | F22: =IF($B22="","",IF($B22=0,"RIESGO: nadie puede sostener esta estación",IF($B22=1,"RIESGO: punto único de fallo, solo 1 persona puede sostener esta estación",IF(AND(ISNUMBER($C$8),$B22<=$C$8),"Cobertura por debajo del umbral","Cobertura suficiente"))))
A23: =IF(Matriz!P$17="","",Matriz!P$17) | B23: =IF(OR($A23="",ISNUMBER($C$6)=FALSE),"",COUNTIFS(Matriz!$P$18:$P$47,">="&$C$6)) | C23: =IF(OR($A23="",ISNUMBER($C$7)=FALSE),"",COUNTIFS(Matriz!$P$18:$P$47,">="&$C$7)) | D23: =IF($A23="","",COUNTIF(Matriz!$A$18:$A$47,"<>")) | E23: =IFERROR(IF(OR($B23="",$D23="",$D23=0),"",$B23/$D23),"") | F23: =IF($B23="","",IF($B23=0,"RIESGO: nadie puede sostener esta estación",IF($B23=1,"RIESGO: punto único de fallo, solo 1 persona puede sostener esta estación",IF(AND(ISNUMBER($C$8),$B23<=$C$8),"Cobertura por debajo del umbral","Cobertura suficiente"))))
A25: RESUMEN
A26: Estaciones registradas | C26: =COUNTIF($A$12:$A$23,"<>") -> 6
A27: Personas registradas en la matriz | C27: =COUNTIF(Matriz!$A$18:$A$47,"<>") -> 12
A28: Estaciones en riesgo (en el umbral o por debajo) | C28: =IF(ISNUMBER($C$8)=FALSE,"",SUMPRODUCT(--(ISNUMBER($B$12:$B$23)),--($B$12:$B$23<=$C$8))) -> 1
A29: Personas que sostienen la estación mejor cubierta | C29: =IF(COUNT($B$12:$B$23)=0,"",MAX($B$12:$B$23)) -> 5
A30: Personas que sostienen la estación peor cubierta | C30: =IF(COUNT($B$12:$B$23)=0,"",MIN($B$12:$B$23)) -> 1
A31: Estaciones en riesgo (%) | C31: =IFERROR(IF(OR($C$26="",$C$26=0,$C$28=""),"",$C$28/$C$26),"") -> 0.16666667
A33: Una estación en riesgo no se arregla contratando: se arregla formando. Llévala a la hoja «Plan de Cross-Training» con nombre, responsable y fecha.

Sheet Coste de una Baja
A1: Coste de una baja
A2: AI Chef Pro · aichef.pro — Manual del Manager de Restaurante
A3: Todas las cifras son de ejemplo y todas son editables: aquí no hay ni una referencia de mercado. Pon las tuyas.
A4: A. COSTE DIRECTO DE CUBRIR LA BAJA
A5: Concepto | B5: Valor | C5: Nota
A6: Horas dedicadas a seleccionar y contratar | B6: 12 | C6: Publicar la oferta, cribar, entrevistar y hacer el alta.
A7: Coste por hora de quien selecciona | B7: 22 | C7: Coste-empresa por hora de quien dedica ese tiempo, no su salario bruto por hora.
A8: Coste de la selección | B8: =IFERROR(IF(OR($B$6="",$B$7=""),"",$B$6*$B$7),"") -> 264
A9: Horas que dedica quien enseña | B9: 25 | C9: Horas en las que el formador está enseñando en vez de produciendo.
A10: Coste por hora de quien enseña | B10: 18
A11: Coste de las horas de quien enseña | B11: =IFERROR(IF(OR($B$9="",$B$10=""),"",$B$9*$B$10),"") -> 450
A12: Horas de formación de la persona nueva | B12: 40 | C12: Horas pagadas en las que todavía no rinde como el puesto pide.
A13: Coste por hora de la persona nueva | B13: 12
A14: Coste de las horas de la persona nueva | B14: =IFERROR(IF(OR($B$12="",$B$13=""),"",$B$12*$B$13),"") -> 480
A15: TOTAL COSTE DIRECTO (A) | B15: =IF(COUNT($B$8,$B$11,$B$14)=0,"",SUM($B$8,$B$11,$B$14)) -> 1194
A17: B. VENTA QUE SE DEJA DE HACER MIENTRAS EL EQUIPO NO ESTÁ A PLENO RENDIMIENTO
A18: Concepto | B18: Valor | C18: Nota
A19: Días hasta que el equipo vuelve a su ritmo | B19: 30 | C19: Desde que se va la persona hasta que la nueva rinde como el puesto pide.
A20: Caída estimada del rendimiento (%) | B20: 0.35 | C20: Cuánto rinde de menos el conjunto del turno durante esos días.
A21: Venta media de un día | B21: 3370 | C21: Sin IVA. En el ejemplo es la venta anual dividida entre los 364 días de las 52 semanas.
A22: VENTA ESTIMADA QUE NO SE HACE (B) | B22: =IFERROR(IF(OR($B$19="",$B$20="",$B$21=""),"",$B$19*$B$20*$B$21),"") -> 35385
A24: C. IMPACTO ESTIMADO DE LA BAJA
A25: Concepto | B25: Valor | C25: Nota
A26: Coste directo (A) | B26: =IF($B$15="","",$B$15) -> 1194
A27: Venta que no se hace (B) | B27: =IF($B$22="","",$B$22) -> 35385
A28: IMPACTO ESTIMADO TOTAL (A + B) | B28: =IF(COUNT($B$26,$B$27)=0,"",SUM($B$26,$B$27)) -> 36579
A30: A y B no son la misma clase de número. A es gasto: sale de tu cuenta. B es venta que no entra, y por eso no se apunta como coste en la cuenta de resultados. Se suman aquí porque juntas son lo que le cuesta al negocio perder a una persona, que es la cifra que justifica dedicar horas a formar antes de necesitarlo.
A32: Ninguna de estas nueve cifras es una referencia del sector: son un ejemplo. El dato bueno es el tuyo, y sale de tus nóminas, de tu registro de jornada y de tu TPV.
