Workbook

Sheet 0. Supuestos
A1: SUPUESTOS — aquí se teclean las TASAS y los DRIVERS del modelo
A2: Cambia las celdas VERDES: el resto del libro se recalcula solo. Las partidas de gasto se teclean en su hoja (también en verde) y no se repiten aquí.
A3: ACTIVIDAD
A4: Invitados por evento (media del año 1) | B4: 135 | C4: Invitados de media por evento en el año 1; en la venta directa, cada taza vendida cuenta como un invitado. Sale de la mezcla de la tabla de referencias de la hoja de Instrucciones: bodas de 120, empresa de 80, congresos o ferias de 300 asistentes, celebraciones privadas de 50 y unas 250 tazas por jornada de venta directa. Es una media: la capacidad por evento está más abajo
A5: Precio medio por invitado SIN IVA (€) | B5: 6.2 | C5: SIN IVA, por invitado: el precio del servicio de barra (paquete de bebidas ilimitadas durante unas horas) repartido entre los invitados y, en la venta directa, el precio de cada taza. Media ponderada de la mezcla: 9,00 € la boda, 8,00 € el evento de empresa, 4,50 € el asistente a un congreso, 9,50 € la celebración privada y 3,00 € la taza en la feria. Por eso la media baja. El precio con IVA (10 %) está en la fila de abajo
A6: Eventos al año | B6: 130 | C6: Eventos servidos en el año: 30 bodas, 40 de empresa (presentaciones, jornadas, team building, Navidad), 22 jornadas de congreso o feria con stand de marca, 25 celebraciones privadas y rodajes, y 12 jornadas de venta directa en mercados y festivales (la mezcla suma 129; el plan redondea a 130). Es el MISMO dato para la cuenta de resultados, el punto de equilibrio, los escenarios y las horas de personal
A7: Crecimiento de volumen del año 2 | B7: 0.1 | C7: Más actividad el segundo año: empresas y agencias que repiten, bodas que llegan por recomendación y planners que ya te conocen, sobre un primer año con la agenda aún por llenar. El libro lo aplica a los invitados por evento con los mismos eventos; en euros es lo mismo que un 10 % más de eventos del mismo tamaño. El personal no sube con este porcentaje: crece con las incorporaciones de la hoja Personal
A8: Crecimiento de volumen del año 3 | B8: 0.08 | C8: Sobre el año 2. El techo lo ponen los sábados de temporada, el calendario de congresos y una sola barra con su titular: más allá hace falta una segunda estación
A9: PVP equivalente con IVA (calculado) | B9: =IFERROR(IF($B$5="","",$B$5*(1+SUMPRODUCT('PyG 3 Años'!$E$10:$E$11,'PyG 3 Años'!$G$10:$G$11))),"") -> 6.82 | C9: =IFERROR("Precio por invitado sin IVA más el IVA medio ponderado de tus líneas de venta: "&TEXT(SUMPRODUCT('PyG 3 Años'!$E$10:$E$11,'PyG 3 Años'!$G$10:$G$11)*100,"0")&" %. Todo lo que sirve la cafetería, en la barra o en la venta directa, va al 10 % (art. 91.Uno.2.2.º de la Ley 37/1992). Aquí va redondeado. Compáralo con el precio por invitado de las barras de tu zona, que suele ir con IVA.","") -> Precio por invitado sin IVA más el IVA medio ponderado de tus líneas de venta: 10 %. Todo lo que sirve la cafetería, en la barra o en la venta directa, va al 10 % (art. 91.Uno.2.2.º de la Ley 37/1992). Aquí va redondeado. Compáralo con el precio por invitado de las barras de tu zona, que suele ir con IVA.
A10: MIX Y COSTE DE MERCANCÍA
A11: Ventas de COMIDA sobre el total | B11: 0.11 | C11: Peso de la COMIDA sobre el total de ventas. Es un INPUT: cámbialo aquí y el P&L, la tesorería y el IVA repercutido se recalculan solos
A12: Ventas de BEBIDA sobre el total | B12: =IFERROR(IF(COUNT(B11)=0,"",1-B11),"") -> 0.89 | C12: Se calcula como el resto: comida + bebida = 100 %
A13: Coste de mercancía sobre las ventas de COMIDA | B13: 0.46 | C13: Bollería y dulces comprados hechos a un obrador (cruasanes pequeños, galletas, bizcocho) sobre su venta: se sirven tal cual, sin elaborar nada en la base. Pide la ficha de alérgenos de cada pieza
A14: Coste de mercancía sobre las ventas de BEBIDA | B14: 0.16 | C14: Café, leche, bebidas vegetales, cacao, chai y siropes sobre las ventas de bebida, con la merma (purga del molino, leche que sobra en la jarra) y un punto de catas y pruebas: unos 0,59 € por bebida. Es la MEDIA de la mezcla del año, no la receta de una bebida: el coste de un espresso o de un latte concreto está en la calculadora del kit y no se copia aquí. Los vasos y las tapas van en los consumibles
A15: Consumibles sobre ventas | B15: 0.04 | C15: Vasos, tapas, servilletas y palillos de madera (unos 0,12 € por bebida servida en vaso de un solo uso), hielo, filtros de agua, detergente de grupos y gasolina del generador. En bodas y empresa se sirve en loza (se lava en la base); el vaso de un solo uso, con su precio aparte en el tique (Ley 7/2022, art. 55.2), sólo en la venta directa
A16: Ventas directas en ferias y mercados sobre el total | B16: 0.084 | C16: Parte de las ventas que se hace en VENTA DIRECTA al público, en mercados gastronómicos, ferias y festivales: 12 jornadas al año con unas 250 tazas a 3,00 € sin IVA. Va también al 10 %. En la vía pública es venta no sedentaria y necesita autorización municipal (RD 199/2010); en un recinto privado, contrato con el organizador. No es venta diaria en la calle: ese es otro negocio
A17: Canon o comisión del organizador de la feria | B17: 0.15 | C17: Canon del organizador de la feria o del mercado, como porcentaje de lo que vendes allí. Si cobra una cuota fija por jornada o por emplazamiento, divídela entre lo que prevés vender: 110 € por una jornada de 750 € sin IVA son un 15 %
A18: Comisión de los medios de pago | B18: 0.006 | C18: Casi todo se cobra por transferencia (señales de los particulares y facturas de empresa); el datáfono queda para la venta directa
A19: PERSONAL
A20: Seguridad Social a cargo de la empresa | B20: 0.33 | C20: Contingencias comunes + AT/EP + desempleo + FOGASA + FP; ajusta a tu convenio y bonificaciones
A21: Número de pagas anuales | B21: 14 | C21: Salario bruto anual = bruto mensual × pagas
A22: SMI anual de referencia (€) | B22: 17094 | C22: SMI 2026: 17.094 € al año (1.221 €/mes en 14 pagas), suelo legal por jornada completa. Comprueba el importe vigente si presentas el plan en otro ejercicio
A23: ALMACÉN BASE Y FIJOS
A24: Cuota mensual del almacén base (€) | B24: 400 | C24: Cuota del almacén base: una nave o un garaje con fregadero y punto de agua donde se lavan la loza, las jarras y los depósitos, se guardan el café, la leche y los vasos, y duerme la furgoneta. No hay cocina ni se elabora comida: no se prepara nada en casa para un evento (RD 1021/2022, art. 13.5.b), y un trastero sin agua no sirve para lavar loza ni depósitos. Pide dos presupuestos en tu zona
A25: Fianza del almacén base (meses) | B25: 2 | C25: Dos cuotas de fianza, lo habitual en un alquiler de nave o garaje
A26: Suministros mensuales (teléfono, datos y luz del almacén base) (€) | B26: 60 | C26: Teléfono, datos y luz del almacén base fuera de la cuota. La gasolina del generador va en los consumibles y el combustible de la furgoneta en varios, porque suben y bajan con los eventos
A27: Seguros (€/año) | B27: 1300 | C27: Responsabilidad civil de explotación y de producto de 300.000 a 600.000 € (unos 500 €), seguro de la furgoneta de uso comercial (650 €) y de los equipos que salen a cada evento (150 €)
A28: Varios e imprevistos sobre ventas | B28: 0.04 | C28: Combustible de los desplazamientos (2 puntos), imprevistos (1 punto) y escaparates de bodas y planners (1 punto). Es variable: sube y baja con los eventos. El desplazamiento que cobras aparte por kilómetro no está en las ventas del libro: compensa este gasto
A29: FINANCIACIÓN
A30: Recursos propios aportados (€) | B30: 25000 | C30: Aportación del socio. Un banco pide entre el 25 y el 30 % de la necesidad de caja con dinero propio
A31: Préstamo bancario solicitado (€) | B31: 44500 | C31: Principal solicitado. La hoja de Financiación compara lo que aportas con la necesidad de caja de la hoja de inversión y te dice si sobra o falta: ajústalo con ese dato
A32: Tipo de interés nominal anual | B32: 0.065 | C32: Tipo nominal anual de un préstamo de empresa sin garantía inmobiliaria. Pide oferta a dos entidades y a una línea ICO o ENISA antes de fijarlo
A33: Plazo del préstamo (años) | B33: 6 | C33: Años totales, carencia incluida: la vida de la cafetera y del equipo
A34: Carencia de principal (años) | B34: 1 | C34: El primer año sólo intereses: es cuando la caja está más tensa, con la agenda de bodas y empresas aún por llenar. Desde el segundo año se devuelve el principal: mira la holgura de caja de ese año en el Punto de Equilibrio
A35: Fondo de maniobra (meses de costes fijos) | B35: 3 | C35: Tres meses de costes fijos: cubren el valle de agosto y el de enero y febrero, y los 30-60 días que tardan en pagar empresas y agencias
A36: FISCAL
A37: Impuesto de Sociedades, nueva creación | B37: 0.15 | C37: Art. 29.1 LIS: el PRIMER ejercicio con base imponible positiva y el SIGUIENTE. El libro lo aproxima contando los dos primeros ejercicios con base positiva: coincide con la ley salvo que entre ellos haya un ejercicio en pérdidas
A38: Impuesto de Sociedades, tipo general | B38: 0.25 | C38: A partir del tercer ejercicio con base positiva. Es el tipo general del art. 29.1 LIS: si tu cifra de negocios queda por debajo de 1 M € (microempresa) o de 10 M € (reducida dimensión), desde 2025 hay tipos más bajos que se implantan de forma gradual; confirma el de tu ejercicio con tu asesor y cámbialo aquí
A39: IVA repercutido de restauración | B39: 0.1 | C39: Tipo reducido de hostelería
A40: IVA repercutido/soportado general | B40: 0.21 | C40: Tipo general. En este plan es el de los extras con precio propio (personalización de la barra, talleres de latte art o alquiler de la cafetera sin barista), que no están en este libro; suministros, equipamiento y servicios tienen su tipo en la celda de abajo. La cafetería no sirve alcohol: todo lo que vende va al reducido, y el libro carga la compra de café y bebidas al 10 %. La leche se factura al 4 %, así que el IVA que soportas de verdad es algo menor que el del libro (art. 91.Dos.1.1.º de la Ley 37/1992)
A41: IVA soportado en compras e inversión | B41: 0.21 | C41: Recuperable vía modelo 303, pero hay que adelantarlo
A42: Bases negativas de ejercicios anteriores (€) | B42: 0 | C42: Pérdidas pendientes de compensar al empezar (art. 26 LIS)
A43: AMORTIZACIÓN
A44: Vida útil de la furgoneta y su rotulación (años) | B44: 8 | C44: La furgoneta, su rotulación y sus anclajes se amortizan en ocho años, el 12,5 % anual, por debajo del 16 % máximo para elementos de transporte de la tabla del art. 12.1 de la Ley del Impuesto sobre Sociedades. Confírmalo con tu asesor
A45: Vida útil de maquinaria y mobiliario (años) | B45: 10 | C45: Cafetera, molinos, generador o baterías, depósitos y bomba, frío, barra-carro, carpa, menaje y TPV: el coeficiente máximo de la tabla del art. 12.1 de la Ley del Impuesto sobre Sociedades es del 12 % para maquinaria y del 10 % para mobiliario
A47: CRECIMIENTO Y ACTUALIZACIÓN DE COSTES
A48: Subida anual de los costes fijos | B48: 0 | C48: A CERO: las tres columnas están en euros del año 1 (términos reales). Súbela si quieres proyectar en euros corrientes
A49: ARRANQUE Y CAPACIDAD
A51: Capacidad máxima por evento (invitados) | B51: 350 | C51: DATO INFORMATIVO: no entra en ningún cálculo. Es el evento más grande del caso con una cafetera de dos grupos y dos baristas cuando el servicio es largo (una jornada de congreso con pausas); en una barra de 3 horas esa cafetera llega a unos 180 invitados y por encima hace falta una segunda estación: mira la tabla de escalado de la hoja Instrucciones
A52: Actividad del mes 1 sobre la de crucero | B52: 0.45 | C52: Una cafetería móvil que arranca factura poco el primer mes: el café se contrata después que la finca y el catering, de una semana a seis meses antes, y las empresas tardan en repetir. Con 100 % se elimina la rampa
A53: Meses hasta alcanzar el régimen de crucero | B53: 9 | C53: Nueve meses hasta el ritmo de crucero: la primera temporada de bodas, empresa y congresos
A54: Meses de cuota del almacén base ANTES del primer evento | B54: 1 | C54: Un mes de cuota para montar el almacén, calibrar la cafetera y los molinos y hacer las primeras catas antes de facturar
A55: Imprevistos sobre la compra y la preparación de la furgoneta (%) | B55: 0.08 | C55: Se calcula sobre la furgoneta y su rotulación: es donde aparecen las sorpresas (neumáticos, frenos, anclajes, y el informe y la ITV de la reforma si fijas en ella el mueble o los depósitos)
A57: COBROS, PAGOS Y DESGLOSE DEL IVA
A58: Días medios de cobro | B58: 20 | C58: Media ponderada: los particulares (bodas y celebraciones) pagan el 30 % de señal al firmar y el 70 % siete días antes del evento, y la venta directa se cobra en el momento; las empresas, agencias y congresos, la mitad de las ventas, pagan el 30 % al confirmar y el 70 % a 30 días de la factura (contrato y calculadora del kit). El libro no admite días negativos, así que las señales no se modelan: tu caja real será algo MEJOR que la de la hoja de Tesorería
A59: Días medios de pago a proveedor | B59: 30 | C59: El tostador, los lácteos y los vasos, a 30 días: lo que te financian. Es lo primero que se pierde si te retrasas en un pago
A60: Mes de la paga extra de verano | B60: 5 | C60: Mes de la TESORERÍA en el que sale la paga extra de verano: julio es el Mes 5, porque el Mes 1 del plan es marzo
A61: Mes de la paga extra de Navidad | B61: 10 | C61: Mes de la TESORERÍA en el que sale la paga extra de Navidad: diciembre es el Mes 10, porque el Mes 1 del plan es marzo
A62: Bebida ALCOHÓLICA sobre el total de bebida (a cero: no se sirve) | B62: 0 | C62: A CERO: la cafetería móvil del plan no sirve alcohol. Una barra de cócteles es otro negocio, con su propio plan. Con 0 esta celda no mueve nada
A63: IVA de la bebida ALCOHÓLICA servida (sin efecto en este plan) | B63: 0.1 | C63: Sin efecto: la cafetería no sirve alcohol (la celda de la bebida alcohólica está a cero). Todo lo que sirve, en la barra del evento o en la venta directa, va al 10 % (art. 91.Uno.2.2.º de la Ley 37/1992)
A64: UMBRALES Y SUELOS DE CONTROL
A65: DSCR mínimo aceptable | B65: 1 | C65: Por debajo de 1 el negocio no genera para pagar el préstamo. Ponlo en el covenant que te exija tu banco
A66: DSCR objetivo (verde) | B66: 1.25 | C66: Lo que suele pedir una entidad para dar el préstamo sin garantías adicionales
A67: Holgura mínima sobre el punto de equilibrio | B67: 0.15 | C67: Cuánto deben superar las ventas previstas a las del equilibrio de caja (costes fijos y cuota del préstamo). La caída que aguantas es algo menor: con un 15 % de holgura, un 13 % de lo previsto
A68: Suelo salarial anual del convenio provincial (€) | B68: 0 | C68: El VI Acuerdo Laboral de ámbito Estatal para el sector de Hostelería (art. 4) incluye la hostelería en «instalaciones fijas o móviles»: el barista se contrata como camarero/a. Copia aquí el salario base de esa categoría en la tabla de TU provincia. Con 0 el semáforo compara sólo contra el SMI

Sheet Inversión Inicial
A1: PLAN DE NEGOCIO: CAFETERÍA MÓVIL PARA EVENTOS
A2: Inversión inicial estimada — barra de café de especialidad para bodas, empresas y ferias
A3: Ajusta las cifras a tu proyecto.
A5: Concepto | B5: Importe | C5: % s/inversión | D5: Notas | E5: ¿Lleva IVA?
A6: INVERSIÓN | B6: =IFERROR(IF(COUNT(B7:B23)=0,"",SUM(B7:B23)),"") -> 44416 | C6: =IFERROR(B6/$B$26,"") -> 0.73951969
A7: Furgoneta usada con rotulación y anclajes | B7: 15200 | C7: =IFERROR(B7/$B$26,"") -> 0.2530777 | D7: Furgoneta de ocasión tipo Kangoo L2 o Trafic (12.000-16.000 € en el mercado; el caso, 14.000 €) con la rotulación de la marca, estanterías y anclajes para llevar la barra, la cafetera y los depósitos sujetos. Si fijas en ella fregadero, depósitos o mueble, es una reforma de vehículo: informe de conformidad e ITV. Estimación del kit. Si la compras a un particular no hay IVA, sino el impuesto de transmisiones; en un concesionario, en REBU, el IVA no se deduce: pon «No» en la columna de al lado | E7: Sí
A8: Barra-carro a medida con ruedas y depósitos ocultos, carpa e iluminación | B8: 4400 | C8: =IFERROR(B8/$B$26,"") -> 0.073259335 | D8: Barra móvil fabricada a medida, con los depósitos de agua escondidos y ruedas para entrar en salones y pabellones, más una carpa de 3 × 3 m y la iluminación para los servicios de noche. Una mesa de barista básica ronda los 1.800 € sin máquina. Estimación del kit | E8: Sí
A9: Cafetera de dos grupos de gama media (3,5 kW como máximo) | B9: 5500 | C9: =IFERROR(B9/$B$26,"") -> 0.091574169 | D9: Máquina de espresso de dos grupos de gama media (3.000-6.000 €). Que no pase de 3,5 kW: así cabe en un enchufe de 16 A (unos 3,7 kW) y no dependes del generador en cada finca. Estimación del kit | E9: Sí
A10: Molinos: espresso bajo demanda y descafeinado o filtro | B10: 2100 | C10: =IFERROR(B10/$B$26,"") -> 0.034964683 | D10: Un molino de espresso bajo demanda profesional (unos 1.430 € sin IVA) y otro para el descafeinado o el filtro (unos 620 €): el invitado español pide descafeinado de máquina. Fichas de distribuidor | E10: Sí
A11: Energía: generador inverter de 5-7 kVA o primera batería, y cuadro con protecciones | B11: 4500 | C11: =IFERROR(B11/$B$26,"") -> 0.07492432 | D11: Para las fincas sin toma suficiente: un generador inverter de 5 kVA o más (los de 7 kVA, 4.300-5.350 €) o una primera batería de litio con inversor, silenciosa para bodas (un sistema completo, 6.000-10.000 €), con un cuadro con protecciones. Estimación del kit | E11: Sí
A12: Agua e higiene: depósitos alimentarios, bomba, filtro descalcificador y lavamanos | B12: 1000 | C12: =IFERROR(B12/$B$26,"") -> 0.016649849 | D12: Dos depósitos de uso alimentario (agua limpia y gris), bomba, filtro descalcificador para la cafetera y un lavamanos autónomo. El agua se carga en red pública y el operador responde de ella hasta el punto de uso (RD 3/2023, arts. 65.3 y 66.b) | E12: Sí
A13: Frío: nevera bajo barra, neveras portátiles, acumuladores y termómetro | B13: 900 | C13: =IFERROR(B13/$B$26,"") -> 0.014984864 | D13: Leche y bebidas vegetales a la temperatura de su etiqueta desde la base hasta la barra, y un termómetro para el registro del APPCC | E13: Sí
A14: Menaje: jarras por tipo de leche, tampers, básculas, cajón de posos y loza | B14: 1500 | C14: =IFERROR(B14/$B$26,"") -> 0.024974773 | D14: Una jarra por cada tipo de leche (alérgenos), tampers, básculas de extracción, cajón de posos, loza para 150 invitados y cajas para transportarla. En bodas y eventos de empresa se sirve en loza: es la opción segura con la normativa de envases | E14: Sí
A15: TPV, datáfono y software | B15: 600 | C15: =IFERROR(B15/$B$26,"") -> 0.0099899094 | D15: Cobro en la venta directa y facturación conforme a Veri*factu | E15: Sí
A16: Marca, web, fotos y dossier | B16: 2000 | C16: =IFERROR(B16/$B$26,"") -> 0.033299698 | D16: Identidad, web con formulario de presupuesto, sesión de fotos de la barra y dossier para novios, empresas, agencias y planners | E16: Sí
A17: Constitución SL + notaría + registro | B17: 1000 | C17: =IFERROR(B17/$B$26,"") -> 0.016649849 | D17: SL unipersonal. Las tasas y el arancel del Registro no llevan IVA; los honorarios del notario y de la gestoría sí: cambia la columna de al lado a «Sí» si tu presupuesto es sobre todo de honorarios | E17: No
A18: Declaración responsable, APPCC, alérgenos y formación de barista | B18: 1000 | C18: =IFERROR(B18/$B$26,"") -> 0.016649849 | D18: Redacción del plan APPCC itinerante, fichas de alérgenos de cada bebida y de la bollería, formación en higiene alimentaria y curso de barista | E18: Sí
... A20: Lanzamiento: feria nupcial, escaparate de bodas y catas para agencias | B20: 1500 | C20: =IFERROR(B20/$B$26,"") -> 0.024974773 | D20: Stand en una feria nupcial, alta destacada en un portal de bodas y catas para agencias y planners antes del primer evento | E20: Sí
A21: Fianza del almacén base | B21: =IFERROR(IF('0. Supuestos'!$B$24="","",'0. Supuestos'!$B$24*'0. Supuestos'!$B$25),"") -> 800 | C21: =IFERROR(B21/$B$26,"") -> 0.013319879 | D21: =IFERROR(""&TEXT('0. Supuestos'!$B$25,"0")&" cuotas del almacén base, al tipo de la hoja de Supuestos. Es un activo recuperable al cerrar: ni se amortiza ni lleva IVA","") -> 2 cuotas del almacén base, al tipo de la hoja de Supuestos. Es un activo recuperable al cerrar: ni se amortiza ni lleva IVA | E21: No
A22: Cuota del almacén base de los meses previos al arranque | B22: =IFERROR(IF('0. Supuestos'!$B$24="","",'0. Supuestos'!$B$24*'0. Supuestos'!$B$54),"") -> 400 | C22: =IFERROR(B22/$B$26,"") -> 0.0066599396 | D22: =IFERROR("Cuota "&IF('0. Supuestos'!$B$54=1,"del mes","de los "&TEXT('0. Supuestos'!$B$54,"0")&" meses")&" de puesta en marcha (montaje del almacén, calibrado de la cafetera, catas y primeras reservas). NO se solapa con el P&L, que arranca el día de la apertura: los doce meses del P&L son los doce de explotación","") -> Cuota del mes de puesta en marcha (montaje del almacén, calibrado de la cafetera, catas y primeras reservas). NO se solapa con el P&L, que arranca el día de la apertura: los doce meses del P&L son los doce de explotación | E22: Sí
A23: Imprevistos de la compra y preparación de la furgoneta | B23: =IFERROR(IF(COUNT(B7)=0,"",ROUND((B7)*'0. Supuestos'!$B$55,0)),"") -> 1216 | C23: =IFERROR(B23/$B$26,"") -> 0.020246216 | D23: =IFERROR("Al "&TEXT('0. Supuestos'!$B$55,"0%")&" de las partidas de la furgoneta de este bloque (Furgoneta usada con rotulación y anclajes), no del bloque entero: el resto de partidas del bloque quedan fuera. Un banco no financia una compra así sin colchón: el porcentaje está en la hoja de Supuestos","") -> Al 8% de las partidas de la furgoneta de este bloque (Furgoneta usada con rotulación y anclajes), no del bloque entero: el resto de partidas del bloque quedan fuera. Un banco no financia una compra así sin colchón: el porcentaje está en la hoja de Supuestos | E23: Sí
A24: FONDO DE MANIOBRA | B24: =IFERROR(IF(B25="","",B25),"") -> 15644.605 | C24: =IFERROR(B24/$B$26,"") -> 0.26048031
A25: Colchón operativo hasta alcanzar el equilibrio | B25: =IFERROR(IF('0. Supuestos'!$B$35*('PyG 3 Años'!$B$38-'PyG 3 Años'!$B$36)=0,"",'0. Supuestos'!$B$35*('PyG 3 Años'!$B$38-'PyG 3 Años'!$B$36)/12),"") -> 15644.605 | C25: =IFERROR(B25/$B$26,"") -> 0.26048031 | D25: =IFERROR("Cubre "&TEXT('0. Supuestos'!$B$35,"0")&IF('0. Supuestos'!$B$35=1," mes"," meses")&" de costes fijos DE CAJA del año 1 (los del P&L menos la amortización, que no se paga), que es el mínimo que exigen las Instrucciones de este libro","") -> Cubre 3 meses de costes fijos DE CAJA del año 1 (los del P&L menos la amortización, que no se paga), que es el mínimo que exigen las Instrucciones de este libro | E25: No
A26: INVERSIÓN TOTAL (suma de los bloques) | B26: =IFERROR(B6+B24,"") -> 60060.605 | D26: =IFERROR("Los porcentajes de la columna C se leen sobre esta cifra, que incluye el fondo de maniobra ("&TEXT(C24,"0%")&" del total). Para comparar el desglose con otro plan, usa la fila de CAPEX de abajo.","") -> Los porcentajes de la columna C se leen sobre esta cifra, que incluye el fondo de maniobra (26% del total). Para comparar el desglose con otro plan, usa la fila de CAPEX de abajo.
A27: CAPEX (inversión sin el fondo de maniobra) | B27: =IFERROR(B26-B24,"") -> 44416 | D27: Es lo que se compra: furgoneta, equipamiento, lanzamiento y gastos de constitución. El colchón de caja no es inversión, es circulante
A28: IVA soportado sobre la inversión (recuperable) | B28: =IFERROR(IF(B26="","",SUMIF($E$7:$E$23,"Sí",$B$7:$B$23)*'0. Supuestos'!$B$41),"") -> 8949.36 | D28: =IFERROR("Al "&TEXT('0. Supuestos'!$B$41,"0%")&" sobre las partidas marcadas con «Sí» en la columna de IVA. Las tasas y licencias no están sujetas y los seguros están exentos (art. 20.Uno.16 LIVA). Las tasas y aranceles registrales no llevan IVA; los honorarios de notaría y gestoría sí "&"(21 %, deducible). Se recupera con el modelo 303, pero hay que adelantarlo","") -> Al 21% sobre las partidas marcadas con «Sí» en la columna de IVA. Las tasas y licencias no están sujetas y los seguros están exentos (art. 20.Uno.16 LIVA). Las tasas y aranceles registrales no llevan IVA; los honorarios de notaría y gestoría sí (21 %, deducible). Se recupera con el modelo 303, pero hay que adelantarlo
A29: NECESIDAD TOTAL DE CAJA AL ARRANQUE | B29: =IFERROR(B26+B28,"") -> 69009.965 | D29: Es la cifra que tiene que cubrir la hoja de Financiación
A30: BASES DE AMORTIZACIÓN (no suman a la inversión)
A31: Furgoneta, rotulación e imprevistos | B31: =IFERROR(IF(B7="","",B7+B23),"") -> 16416 | D31: =IFERROR("Se amortiza en "&TEXT('0. Supuestos'!$B$44,"0")&" años","") -> Se amortiza en 8 años
A32: Maquinaria, mobiliario y equipos | B32: =IFERROR(IF(B8="","",B8+B9+B10+B11+B12+B13+B14+B15),"") -> 20500 | D32: =IFERROR("Se amortiza en "&TEXT('0. Supuestos'!$B$45,"0")&" años","") -> Se amortiza en 10 años
A33: Amortización anual del inmovilizado | B33: =IFERROR(B31/MAX(1,'0. Supuestos'!$B$44)+B32/MAX(1,'0. Supuestos'!$B$45),"") -> 4102 | D33: =IFERROR("No se amortizan, por no ser inmovilizado, Marca, web, fotos y dossier, Constitución SL + notaría + registro, Declaración responsable, APPCC, alérgenos y formación de barista, Stock inicial: café, leche UHT y vasos, Lanzamiento: feria "&"nupcial, escaparate de bodas y catas para agencias, Fianza del almacén base, Cuota del almacén base de los meses previos al arranque ni Colchón operativo hasta alcanzar el equilibrio. Suman "&TEXT(B26-B31-B32,"0")&" € de los "&TEXT(B26,"0")&" € de inversión.","") -> No se amortizan, por no ser inmovilizado, Marca, web, fotos y dossier, Constitución SL + notaría + registro, Declaración responsable, APPCC, alérgenos y formación de barista, Stock inicial: café, leche UHT y vasos, Lanzamiento: feria nupcial, escaparate de bodas y catas para agencias, Fianza del almacén base, Cuota del almacén base de los meses previos al arranque ni Colchón operativo hasta alcanzar el equilibrio. Suman 23145 € de los 60061 € de inversión.

Sheet PyG 3 Años
A1: CUENTA DE RESULTADOS PREVISIONAL — 3 AÑOS
A2: Escenario realista — cafetería móvil para eventos
A4: Concepto | B4: Año 1 | C4: Año 2 | D4: Año 3 | E4: % s/ventas (año 1) | F4: Notas | G4: Tipo de IVA de la línea (%)
A5: INGRESOS
A6: Invitados por evento (media) | B6: =IFERROR(IF('0. Supuestos'!$B$4="","",'0. Supuestos'!$B$4),"") -> 135 | C6: =IFERROR(B6*(1+'0. Supuestos'!$B$7),"") -> 148.5 | D6: =IFERROR(C6*(1+'0. Supuestos'!$B$8),"") -> 160.38 | F6: El crecimiento de los años 2 y 3 está en la hoja de Supuestos
A7: Precio medio por invitado sin IVA | B7: =IFERROR(IF('0. Supuestos'!$B$5="","",'0. Supuestos'!$B$5),"") -> 6.2 | C7: =IFERROR(IF(B7="","",B7),"") -> 6.2 | D7: =IFERROR(IF(C7="","",C7),"") -> 6.2 | F7: Constante en euros del año 1: una subida de precios es una decisión aparte
A8: Eventos al año | B8: =IFERROR(IF('0. Supuestos'!$B$6="","",'0. Supuestos'!$B$6),"") -> 130 | C8: =IFERROR(IF(B8="","",B8),"") -> 130 | D8: =IFERROR(IF(C8="","",C8),"") -> 130
A9: INGRESOS TOTALES (sin IVA) | B9: =IFERROR(IF(B6*B7*B8=0,"",B6*B7*B8),"") -> 108810 | C9: =IFERROR(IF(C6*C7*C8=0,"",C6*C7*C8),"") -> 119691 | D9: =IFERROR(IF(D6*D7*D8=0,"",D6*D7*D8),"") -> 129266.28 | E9: =IFERROR(IF(B9="","",1),"") -> 1
A10: Dulces y bollería de obrador | B10: =IFERROR(IF(B9="","",B9*$E$10),"") -> 11969.1 | C10: =IFERROR(IF(C9="","",C9*$E$10),"") -> 13166.01 | D10: =IFERROR(IF(D9="","",D9*$E$10),"") -> 14219.291 | E10: =IFERROR(IF('0. Supuestos'!$B$11="","",'0. Supuestos'!$B$11),"") -> 0.11 | F10: Bollería y dulces comprados a un obrador que se añaden al paquete de café o se venden en la feria: se sirven tal cual, sin elaborar. Al 10 % de IVA | G10: =IFERROR(IF(B9="","",'0. Supuestos'!$B$39),"") -> 0.1
A11: Bebidas de café y sin café | B11: =IFERROR(IF(B9="","",B9*$E$11),"") -> 96840.9 | C11: =IFERROR(IF(C9="","",C9*$E$11),"") -> 106524.99 | D11: =IFERROR(IF(D9="","",D9*$E$11),"") -> 115046.99 | E11: =IFERROR(IF('0. Supuestos'!$B$12="","",'0. Supuestos'!$B$12),"") -> 0.89 | F11: Espresso, americano, cortado, café con leche, flat white, capuchino, latte, mocha, chai y chocolate, con leche entera, sin lactosa o bebida vegetal. Sin alcohol. Al 10 % de IVA, en la barra del evento y en la venta directa | G11: =IFERROR(IF(B9="","",('0. Supuestos'!$B$62*((1-'0. Supuestos'!$B$16)*'0. Supuestos'!$B$63+'0. Supuestos'!$B$16*'0. Supuestos'!$B$40)+(1-'0. Supuestos'!$B$62)*'0. Supuestos'!$B$39)),"") -> 0.1
A12: COSTES VARIABLES
A13: Coste de mercancía — comida | B13: =IFERROR(IF(B9="","",B9*'0. Supuestos'!$B$11*'0. Supuestos'!$B$13),"") -> 5505.786 | C13: =IFERROR(IF(C9="","",C9*'0. Supuestos'!$B$11*'0. Supuestos'!$B$13),"") -> 6056.3646 | D13: =IFERROR(IF(D9="","",D9*'0. Supuestos'!$B$11*'0. Supuestos'!$B$13),"") -> 6540.8738 | E13: =IFERROR(B13/$B$9,"") -> 0.0506 | F13: =IFERROR("Al "&TEXT('0. Supuestos'!$B$13,"0%")&" de las ventas de COMIDA, no del total: la bebida tiene su propia línea","") -> Al 46% de las ventas de COMIDA, no del total: la bebida tiene su propia línea | G13: =IFERROR(IF(B9="","",'0. Supuestos'!$B$39),"") -> 0.1
A14: Coste de mercancía — bebida | B14: =IFERROR(IF(B9="","",B9*'0. Supuestos'!$B$12*'0. Supuestos'!$B$14),"") -> 15494.544 | C14: =IFERROR(IF(C9="","",C9*'0. Supuestos'!$B$12*'0. Supuestos'!$B$14),"") -> 17043.998 | D14: =IFERROR(IF(D9="","",D9*'0. Supuestos'!$B$12*'0. Supuestos'!$B$14),"") -> 18407.518 | E14: =IFERROR(B14/$B$9,"") -> 0.1424 | F14: =IFERROR("Al "&TEXT('0. Supuestos'!$B$14,"0%")&" de las ventas de BEBIDA","") -> Al 16% de las ventas de BEBIDA | G14: =IFERROR(IF(B9="","",('0. Supuestos'!$B$62*'0. Supuestos'!$B$40+(1-'0. Supuestos'!$B$62)*'0. Supuestos'!$B$39)),"") -> 0.1
A15: Consumibles y envases | B15: =IFERROR(IF(B9="","",B9*'0. Supuestos'!$B$15),"") -> 4352.4 | C15: =IFERROR(IF(C9="","",C9*'0. Supuestos'!$B$15),"") -> 4787.64 | D15: =IFERROR(IF(D9="","",D9*'0. Supuestos'!$B$15),"") -> 5170.6512 | E15: =IFERROR(B15/$B$9,"") -> 0.04 | G15: =IFERROR(IF(B9="","",'0. Supuestos'!$B$41),"") -> 0.21
A16: Canon de ferias y mercados | B16: =IFERROR(IF(B9="","",B9*'0. Supuestos'!$B$16*'0. Supuestos'!$B$17),"") -> 1371.006 | C16: =IFERROR(IF(C9="","",C9*'0. Supuestos'!$B$16*'0. Supuestos'!$B$17),"") -> 1508.1066 | D16: =IFERROR(IF(D9="","",D9*'0. Supuestos'!$B$16*'0. Supuestos'!$B$17),"") -> 1628.7551 | E16: =IFERROR(B16/$B$9,"") -> 0.0126 | F16: Sobre las ventas DEL CANAL. Con 0 % de ferias y mercados en Supuestos, esta línea vale cero | G16: =IFERROR(IF(B9="","",'0. Supuestos'!$B$41),"") -> 0.21
A17: Comisiones de los medios de pago | B17: =IFERROR(IF(B9="","",B9*'0. Supuestos'!$B$18),"") -> 652.86 | C17: =IFERROR(IF(C9="","",C9*'0. Supuestos'!$B$18),"") -> 718.146 | D17: =IFERROR(IF(D9="","",D9*'0. Supuestos'!$B$18),"") -> 775.59768 | E17: =IFERROR(B17/$B$9,"") -> 0.006 | F17: Las comisiones de los medios de pago están EXENTAS de IVA (art. 20.Uno.18 LIVA): no se deduce nada por ellas | G17: 0
A18: Varios e imprevistos | B18: =IFERROR(IF(B9="","",B9*'0. Supuestos'!$B$28),"") -> 4352.4 | C18: =IFERROR(IF(C9="","",C9*'0. Supuestos'!$B$28),"") -> 4787.64 | D18: =IFERROR(IF(D9="","",D9*'0. Supuestos'!$B$28),"") -> 5170.6512 | E18: =IFERROR(B18/$B$9,"") -> 0.04 | F18: =IFERROR("Al "&TEXT('0. Supuestos'!$B$28,"0%")&" de las ventas. Es un coste VARIABLE: sube y baja con la facturación, así que no puede vivir en los costes fijos","") -> Al 4% de las ventas. Es un coste VARIABLE: sube y baja con la facturación, así que no puede vivir en los costes fijos | G18: =IFERROR(IF(B9="","",'0. Supuestos'!$B$41),"") -> 0.21
A19: TOTAL COSTES VARIABLES | B19: =IFERROR(IF(B9="","",SUM(B13:B18)),"") -> 31728.996 | C19: =IFERROR(IF(C9="","",SUM(C13:C18)),"") -> 34901.896 | D19: =IFERROR(IF(D9="","",SUM(D13:D18)),"") -> 37694.047 | E19: =IFERROR(B19/$B$9,"") -> 0.2916
A20: MARGEN BRUTO | B20: =IFERROR(IF(B9="","",B9-B19),"") -> 77081.004 | C20: =IFERROR(IF(C9="","",C9-C19),"") -> 84789.104 | D20: =IFERROR(IF(D9="","",D9-D19),"") -> 91572.233 | E20: =IFERROR(B20/$B$9,"") -> 0.7084
A21: COSTES FIJOS
A22: Cuota del almacén base | B22: =IFERROR(IF(B9="","",'0. Supuestos'!$B$24*12),"") -> 4800 | C22: =IFERROR(IF(C9="","",B22*(1+'0. Supuestos'!$B$48)),"") -> 4800 | D22: =IFERROR(IF(D9="","",C22*(1+'0. Supuestos'!$B$48)),"") -> 4800 | E22: =IFERROR(B22/$B$9,"") -> 0.044113593 | F22: El importe mensual está en la hoja de Supuestos; aquí se multiplica por doce. Es la cuota de una nave o un garaje con fregadero y punto de agua (lavado de loza, jarras y depósitos, almacén de café, leche y vasos, y plaza para la furgoneta). El mes previo al primer evento está en la hoja de Inversión y NO se cuenta dos veces | G22: =IFERROR(IF(B9="","",'0. Supuestos'!$B$41),"") -> 0.21
A23: Personal (nóminas + Seguridad Social) | B23: =IFERROR(IF(B9="","",'Personal'!$G$9),"") -> 44985.92 | C23: =IFERROR(IF(C9="","",'Personal'!$B$13),"") -> 50985.92 | D23: =IFERROR(IF(D9="","",'Personal'!$B$14),"") -> 56985.92 | E23: =IFERROR(B23/$B$9,"") -> 0.41343553 | F23: Sale de la hoja de Personal: es el MISMO número, no una estimación aparte. Los años 2 y 3 suman las INCORPORACIONES declaradas en esa hoja, no un porcentaje de volumen | G23: 0
A24: Suministros (teléfono, datos y luz del almacén base) | B24: =IFERROR(IF(B9="","",'0. Supuestos'!$B$26*12),"") -> 720 | C24: =IFERROR(IF(C9="","",B24*(1+'0. Supuestos'!$B$48)),"") -> 720 | D24: =IFERROR(IF(D9="","",C24*(1+'0. Supuestos'!$B$48)),"") -> 720 | E24: =IFERROR(B24/$B$9,"") -> 0.0066170389 | F24: Teléfono, datos y luz del almacén base. La gasolina del generador va en los consumibles. Va al 21 % de IVA | G24: =IFERROR(IF(B9="","",'0. Supuestos'!$B$41),"") -> 0.21
A25: Seguros (RC + multirriesgo) | B25: =IFERROR(IF(B9="","",'0. Supuestos'!$B$27),"") -> 1300 | C25: =IFERROR(IF(C9="","",B25*(1+'0. Supuestos'!$B$48)),"") -> 1300 | D25: =IFERROR(IF(D9="","",C25*(1+'0. Supuestos'!$B$48)),"") -> 1300 | E25: =IFERROR(B25/$B$9,"") -> 0.011947431 | F25: Las operaciones de seguro están EXENTAS de IVA (art. 20.Uno.16 LIVA): la prima no lleva IVA deducible | G25: 0
A26: Asesoría fiscal y laboral (nóminas de fijos discontinuos) | B26: 1680 | C26: =IFERROR(IF(C9="","",B26*(1+'0. Supuestos'!$B$48)),"") -> 1680 | D26: =IFERROR(IF(D9="","",C26*(1+'0. Supuestos'!$B$48)),"") -> 1680 | E26: =IFERROR(B26/$B$9,"") -> 0.015439757 | F26: Contabilidad, impuestos de la SL y nóminas de los fijos discontinuos de cada mes con llamamientos | G26: =IFERROR(IF(B9="","",'0. Supuestos'!$B$41),"") -> 0.21
A27: Furgoneta: mantenimiento, neumáticos e ITV | B27: 800 | C27: =IFERROR(IF(C9="","",B27*(1+'0. Supuestos'!$B$48)),"") -> 800 | D27: =IFERROR(IF(D9="","",C27*(1+'0. Supuestos'!$B$48)),"") -> 800 | E27: =IFERROR(B27/$B$9,"") -> 0.0073522654 | F27: Taller, neumáticos e ITV de la furgoneta (y del remolque, si lo usas) | G27: =IFERROR(IF(B9="","",'0. Supuestos'!$B$41),"") -> 0.21
A28: Marketing: escaparate de bodas, Google Ads local, redes y feria nupcial | B28: 3000 | C28: =IFERROR(IF(C9="","",B28*(1+'0. Supuestos'!$B$48)),"") -> 3000 | D28: =IFERROR(IF(D9="","",C28*(1+'0. Supuestos'!$B$48)),"") -> 3000 | E28: =IFERROR(B28/$B$9,"") -> 0.027570995 | F28: Ficha en los portales de bodas, Google Ads local, redes sociales y una feria nupcial al año | G28: =IFERROR(IF(B9="","",'0. Supuestos'!$B$41),"") -> 0.21
A29: Software de gestión comercial, CRM y teléfono | B29: 500 | C29: =IFERROR(IF(C9="","",B29*(1+'0. Supuestos'!$B$48)),"") -> 500 | D29: =IFERROR(IF(D9="","",C29*(1+'0. Supuestos'!$B$48)),"") -> 500 | E29: =IFERROR(B29/$B$9,"") -> 0.0045951659 | F29: Presupuestos, agenda de eventos, CRM de clientes y línea de teléfono | G29: =IFERROR(IF(B9="","",'0. Supuestos'!$B$41),"") -> 0.21
A30: Mantenimiento de la cafetera y los molinos (técnico, juntas y filtros) | B30: 600 | C30: =IFERROR(IF(C9="","",B30*(1+'0. Supuestos'!$B$48)),"") -> 600 | D30: =IFERROR(IF(D9="","",C30*(1+'0. Supuestos'!$B$48)),"") -> 600 | E30: =IFERROR(B30/$B$9,"") -> 0.0055141991 | F30: Revisión anual del técnico, juntas y duchas de los grupos, fresas del molino y cartuchos del filtro descalcificador | G30: =IFERROR(IF(B9="","",'0. Supuestos'!$B$41),"") -> 0.21
A31: Uniformes y lavandería | B31: 300 | C31: =IFERROR(IF(C9="","",B31*(1+'0. Supuestos'!$B$48)),"") -> 300 | D31: =IFERROR(IF(D9="","",C31*(1+'0. Supuestos'!$B$48)),"") -> 300 | E31: =IFERROR(B31/$B$9,"") -> 0.0027570995 | F31: Delantales, camisas y paños: lavado y reposición | G31: =IFERROR(IF(B9="","",'0. Supuestos'!$B$41),"") -> 0.21
A32: Gestión de residuos (posos de café y envases) | B32: 100 | C32: =IFERROR(IF(C9="","",B32*(1+'0. Supuestos'!$B$48)),"") -> 100 | D32: =IFERROR(IF(D9="","",C32*(1+'0. Supuestos'!$B$48)),"") -> 100 | E32: =IFERROR(B32/$B$9,"") -> 0.00091903318 | F32: Retirada de posos y envases al punto autorizado; el agua gris de los depósitos, nunca al terreno de la finca | G32: =IFERROR(IF(B9="","",'0. Supuestos'!$B$41),"") -> 0.21
A33: Prevención de riesgos laborales y vigilancia de la salud | B33: 300 | C33: =IFERROR(IF(C9="","",B33*(1+'0. Supuestos'!$B$48)),"") -> 300 | D33: =IFERROR(IF(D9="","",C33*(1+'0. Supuestos'!$B$48)),"") -> 300 | E33: =IFERROR(B33/$B$9,"") -> 0.0027570995 | F33: Plan de prevención obligatorio (Ley 31/1995): quemaduras de vapor, cargas, conducción y posturas, y reconocimientos médicos | G33: =IFERROR(IF(B9="","",'0. Supuestos'!$B$41),"") -> 0.21
A34: Catas y degustaciones comerciales | B34: 300 | C34: =IFERROR(IF(C9="","",B34*(1+'0. Supuestos'!$B$48)),"") -> 300 | D34: =IFERROR(IF(D9="","",C34*(1+'0. Supuestos'!$B$48)),"") -> 300 | E34: =IFERROR(B34/$B$9,"") -> 0.0027570995 | F34: Café, leche y horas de las catas para novios, agencias y planners que no se cobran | G34: =IFERROR(IF(B9="","",'0. Supuestos'!$B$41),"") -> 0.21
A35: Licencias y tasas de venta en ferias y mercados | B35: 300 | C35: =IFERROR(IF(C9="","",B35*(1+'0. Supuestos'!$B$48)),"") -> 300 | D35: =IFERROR(IF(D9="","",C35*(1+'0. Supuestos'!$B$48)),"") -> 300 | E35: =IFERROR(B35/$B$9,"") -> 0.0027570995 | F35: Autorizaciones municipales de venta no sedentaria y tasas de ocupación de las jornadas de venta directa (RD 199/2010). Pon las de tu ayuntamiento. Las tasas municipales no llevan IVA, pero el libro aplica a todos los costes fijos el tipo general de la columna de al lado: aquí suma unos 63 € al año de IVA que pagas y te deduces en el mismo trimestre, sin efecto en el resultado | G35: =IFERROR(IF(B9="","",'0. Supuestos'!$B$41),"") -> 0.21
A36: Amortización del inmovilizado | B36: =IFERROR(IF(B9="","",'Inversión Inicial'!$B$33),"") -> 4102 | C36: =IFERROR(IF(C9="","",B36),"") -> 4102 | D36: =IFERROR(IF(D9="","",B36),"") -> 4102 | E36: =IFERROR(B36/$B$9,"") -> 0.037698741 | F36: Sale de las bases de amortización de la hoja de Inversión: sólo inmovilizado real. NO sube con el IPC: es una cuota sobre el coste HISTÓRICO del inmovilizado | G36: 0
A37: Gastos financieros (intereses del préstamo) | B37: =IFERROR(IF(B9="","",'Financiación'!$B$44),"") -> 2892.5 | C37: =IFERROR(IF(C9="","",'Financiación'!$B$46),"") -> 2892.5 | D37: =IFERROR(IF(D9="","",'Financiación'!$B$48),"") -> 2384.4771 | E37: =IFERROR(B37/$B$9,"") -> 0.026583035 | F37: Sólo los INTERESES son gasto. La devolución del principal va en la hoja de Tesorería | G37: 0
A38: TOTAL COSTES FIJOS | B38: =IFERROR(IF(B9="","",SUM(B22:B37)),"") -> 66680.42 | C38: =IFERROR(IF(C9="","",SUM(C22:C37)),"") -> 72680.42 | D38: =IFERROR(IF(D9="","",SUM(D22:D37)),"") -> 78172.397 | E38: =IFERROR(B38/$B$9,"") -> 0.61281518
A39: IVA soportado de los costes variables | B39: =IFERROR(IF(B9="","",SUMPRODUCT(B13:B18,G13:G18)),"") -> 4215.9523 | C39: =IFERROR(IF(C9="","",SUMPRODUCT(C13:C18,G13:G18)),"") -> 4637.5475 | D39: =IFERROR(IF(D9="","",SUMPRODUCT(D13:D18,G13:G18)),"") -> 5008.5513 | F39: Cada línea a SU tipo, leído de la columna de al lado. Es lo que la hoja de Tesorería paga de más a los proveedores y luego se deduce
A40: IVA soportado de los costes fijos | B40: =IFERROR(IF(B9="","",SUMPRODUCT(B22:B37,G22:G37)),"") -> 2814 | C40: =IFERROR(IF(C9="","",SUMPRODUCT(C22:C37,G22:G37)),"") -> 2814 | D40: =IFERROR(IF(D9="","",SUMPRODUCT(D22:D37,G22:G37)),"") -> 2814
A41: RESULTADO ANTES DE IMPUESTOS | B41: =IFERROR(IF(B9="","",B20-B38),"") -> 10400.584 | C41: =IFERROR(IF(C9="","",C20-C38),"") -> 12108.684 | D41: =IFERROR(IF(D9="","",D20-D38),"") -> 13399.836 | E41: =IFERROR(B41/$B$9,"") -> 0.095584818
A42: Bases negativas pendientes al inicio | B42: =IFERROR(IF(B9="","",'0. Supuestos'!$B$42),"") -> 0 | C42: =IFERROR(IF(C9="","",B47),"") -> 0 | D42: =IFERROR(IF(D9="","",C47),"") -> 0 | F42: Art. 26 LIS: las pérdidas de un ejercicio se compensan con los beneficios de los siguientes
A43: Base imponible (después de compensar) | B43: =IFERROR(IF(B9="","",MAX(0,B41-B42)),"") -> 10400.584 | C43: =IFERROR(IF(C9="","",MAX(0,C41-C42)),"") -> 12108.684 | D43: =IFERROR(IF(D9="","",MAX(0,D41-D42)),"") -> 13399.836
A44: Ejercicios con base positiva (acumulado) | B44: =IFERROR(IF(B9="","",IF(B43>0,1,0)),"") -> 1 | C44: =IFERROR(IF(C9="","",B44+IF(C43>0,1,0)),"") -> 2 | D44: =IFERROR(IF(D9="","",C44+IF(D43>0,1,0)),"") -> 3
A45: Tipo de Impuesto de Sociedades aplicado | B45: =IFERROR(IF(B9="","",IF(B43<=0,"",IF(B44<=2,'0. Supuestos'!$B$37,'0. Supuestos'!$B$38))),"") -> 0.15 | C45: =IFERROR(IF(C9="","",IF(C43<=0,"",IF(C44<=2,'0. Supuestos'!$B$37,'0. Supuestos'!$B$38))),"") -> 0.15 | D45: =IFERROR(IF(D9="","",IF(D43<=0,"",IF(D44<=2,'0. Supuestos'!$B$37,'0. Supuestos'!$B$38))),"") -> 0.25 | F45: Art. 29.1 LIS: el 15 % de entidad de nueva creación se aplica al PRIMER ejercicio con base positiva y al SIGUIENTE, no al primer año de vida. El libro lo aproxima contando los dos primeros ejercicios con base positiva
A46: Impuesto de Sociedades | B46: =IFERROR(IF(B9="","",IF(B45="",0,B43*B45)),"") -> 1560.0876 | C46: =IFERROR(IF(C9="","",IF(C45="",0,C43*C45)),"") -> 1816.3027 | D46: =IFERROR(IF(D9="","",IF(D45="",0,D43*D45)),"") -> 3349.9589
A47: Bases negativas pendientes al cierre | B47: =IFERROR(IF(B9="","",MAX(0,B42-B41)),"") -> 0 | C47: =IFERROR(IF(C9="","",MAX(0,C42-C41)),"") -> 0 | D47: =IFERROR(IF(D9="","",MAX(0,D42-D41)),"") -> 0
A48: RESULTADO NETO | B48: =IFERROR(IF(B9="","",B41-B46),"") -> 8840.4964 | C48: =IFERROR(IF(C9="","",C41-C46),"") -> 10292.382 | D48: =IFERROR(IF(D9="","",D41-D46),"") -> 10049.877 | E48: =IFERROR(B48/$B$9,"") -> 0.081247095
A49: RATIOS CLAVE
A50: Ratio | B50: Año 1 | C50: Año 2 | D50: Año 3 | E50: Umbral | F50: Comentario
A51: Margen bruto / Ventas | B51: =IFERROR(IF(B9="","",B20/B9),"") -> 0.7084 | C51: =IFERROR(IF(C9="","",C20/C9),"") -> 0.7084 | D51: =IFERROR(IF(D9="","",D20/D9),"") -> 0.7084 | E51: 0.65 | F51: Los costes variables de la barra incluyen vasos, gasolina, combustible, canon de ferias y medios de pago además de la mercancía: un margen bruto por debajo del 65 % no paga la plantilla. Estimación del kit
A52: Coste de mercancía (comida + bebida) | B52: =IFERROR(IF(B9="","",B13+B14),"") -> 21000.33 | C52: =IFERROR(IF(C9="","",C13+C14),"") -> 23100.363 | D52: =IFERROR(IF(D9="","",D13+D14),"") -> 24948.392
A53: Coste de mercancía / Ventas | B53: =IFERROR(IF(B9="","",B52/B9),"") -> 0.193 | C53: =IFERROR(IF(C9="","",C52/C9),"") -> 0.193 | D53: =IFERROR(IF(D9="","",D52/D9),"") -> 0.193 | E53: 0.22 | F53: Techo de la mercancía (café, leche y bollería) sobre ventas. Estimación del kit
A54: Coste de personal / Ventas | B54: =IFERROR(IF(B9="","",B23/B9),"") -> 0.41343553 | C54: =IFERROR(IF(C9="","",C23/C9),"") -> 0.42597956 | D54: =IFERROR(IF(D9="","",D23/D9),"") -> 0.44084134 | E54: 0.45 | F54: Techo del personal sobre ventas: carga, viaje, montaje, servicio y limpieza en cada evento. Estimación del kit
A55: Cuota del almacén base / Ventas | B55: =IFERROR(IF(B9="","",B22/B9),"") -> 0.044113593 | C55: =IFERROR(IF(C9="","",C22/C9),"") -> 0.040103266 | D55: =IFERROR(IF(D9="","",D22/D9),"") -> 0.037132654 | E55: 0.06 | F55: Techo de la cuota del almacén base sobre las ventas: estimación del kit
A56: Resultado neto / Ventas | B56: =IFERROR(IF(B9="","",B48/B9),"") -> 0.081247095 | C56: =IFERROR(IF(C9="","",C48/C9),"") -> 0.085991275 | D56: =IFERROR(IF(D9="","",D48/D9),"") -> 0.07774554 | E56: 0.05 | F56: Suelo de resultado neto para que el plan se sostenga: estimación del kit
A57: Punto de equilibrio alcanzado | B57: =IFERROR(IF(B9="","",IF(B9>='Punto Equilibrio'!$B$16,"Sí","No")),"") -> Sí | C57: =IFERROR(IF(C9="","",IF(C9>='Punto Equilibrio'!$C$16,"Sí","No")),"") -> Sí | D57: =IFERROR(IF(D9="","",IF(D9>='Punto Equilibrio'!$D$16,"Sí","No")),"") -> Sí | F57: Compara las ventas de CADA año con el umbral de ese mismo año, que calcula la hoja de Punto de Equilibrio con los costes fijos del año
A59: Todas las cifras van SIN IVA. Las columnas de los años 2 y 3 están en euros del año 1 salvo que subas la actualización de costes en la hoja de Supuestos. La columna «Tipo de IVA de la línea» dice, en las líneas de VENTA, a qué tipo se repercute cada una, y en las de COSTE a qué tipo se compra la partida. La lee la hoja de Tesorería: los seguros y las comisiones de los medios de pago están exentos, y las nóminas, la amortización y los intereses no llevan IVA.

Sheet Punto Equilibrio
A1: ANÁLISIS DE PUNTO DE EQUILIBRIO
A2: Punto de equilibrio — cafetería móvil para eventos
A4: Variable | B4: Año 1 | C4: Año 2 | D4: Año 3 | E4: Notas
A5: DATOS BASE POR AÑO
A6: Costes fijos anuales | B6: =IFERROR(IF('PyG 3 Años'!$B$9="","",'PyG 3 Años'!$B$38),"") -> 66680.42 | C6: =IFERROR(IF('PyG 3 Años'!$C$9="","",'PyG 3 Años'!$C$38),"") -> 72680.42 | D6: =IFERROR(IF('PyG 3 Años'!$D$9="","",'PyG 3 Años'!$D$38),"") -> 78172.397 | E6: Los MISMOS costes fijos del P&L. Cada año tiene los suyos: por eso el umbral no puede ser uno solo para los tres
A7: Costes fijos mensuales | B7: =IFERROR(IF('PyG 3 Años'!$B$9="","",B6/12),"") -> 5556.7017 | C7: =IFERROR(IF('PyG 3 Años'!$C$9="","",C6/12),"") -> 6056.7017 | D7: =IFERROR(IF('PyG 3 Años'!$D$9="","",D6/12),"") -> 6514.3664
A8: Precio medio por invitado sin IVA | B8: =IFERROR(IF('PyG 3 Años'!$B$9="","",'PyG 3 Años'!$B$7),"") -> 6.2 | C8: =IFERROR(IF('PyG 3 Años'!$C$9="","",'PyG 3 Años'!$C$7),"") -> 6.2 | D8: =IFERROR(IF('PyG 3 Años'!$D$9="","",'PyG 3 Años'!$D$7),"") -> 6.2
A9: Coste variable por invitado | B9: =IFERROR(IF('PyG 3 Años'!$B$9="","",'PyG 3 Años'!$B$19/('PyG 3 Años'!$B$6*'PyG 3 Años'!$B$8)),"") -> 1.80792 | C9: =IFERROR(IF('PyG 3 Años'!$C$9="","",'PyG 3 Años'!$C$19/('PyG 3 Años'!$C$6*'PyG 3 Años'!$C$8)),"") -> 1.80792 | D9: =IFERROR(IF('PyG 3 Años'!$D$9="","",'PyG 3 Años'!$D$19/('PyG 3 Años'!$D$6*'PyG 3 Años'!$D$8)),"") -> 1.80792 | E9: Sale del total de costes variables del P&L, no de una estimación aparte. Incluye los varios e imprevistos, que son un porcentaje de las ventas
A10: Margen de contribución por invitado | B10: =IFERROR(IF('PyG 3 Años'!$B$9="","",B8-B9),"") -> 4.39208 | C10: =IFERROR(IF('PyG 3 Años'!$C$9="","",C8-C9),"") -> 4.39208 | D10: =IFERROR(IF('PyG 3 Años'!$D$9="","",D8-D9),"") -> 4.39208 | E10: Precio por invitado menos coste variable unitario
A11: Eventos al año | B11: =IFERROR(IF('PyG 3 Años'!$B$9="","",'PyG 3 Años'!$B$8),"") -> 130 | C11: =IFERROR(IF('PyG 3 Años'!$C$9="","",'PyG 3 Años'!$C$8),"") -> 130 | D11: =IFERROR(IF('PyG 3 Años'!$D$9="","",'PyG 3 Años'!$D$8),"") -> 130 | E11: El mismo calendario que el P&L y que los escenarios
A12: Devolución de principal del año (cuota) | B12: =IFERROR(IF('PyG 3 Años'!$B$9="","",'Financiación'!$B$45),"") -> 0 | C12: =IFERROR(IF('PyG 3 Años'!$C$9="","",'Financiación'!$B$47),"") -> 7815.7369 | D12: =IFERROR(IF('PyG 3 Años'!$D$9="","",'Financiación'!$B$49),"") -> 8323.7598 | E12: El principal NO es gasto del P&L, pero sale de la caja. Sin él, el umbral de equilibrio se publica por debajo del real
A13: PUNTO DE EQUILIBRIO CONTABLE (incluye amortización)
A14: Invitados necesarios al año | B14: =IFERROR(IF('PyG 3 Años'!$B$9="","",IF(B10<=0,"",B6/B10)),"") -> 15181.968 | C14: =IFERROR(IF('PyG 3 Años'!$C$9="","",IF(C10<=0,"",C6/C10)),"") -> 16548.064 | D14: =IFERROR(IF('PyG 3 Años'!$D$9="","",IF(D10<=0,"",D6/D10)),"") -> 17798.491
A15: Invitados necesarios por evento | B15: =IFERROR(IF('PyG 3 Años'!$B$9="","",B14/B11),"") -> 116.78437 | C15: =IFERROR(IF('PyG 3 Años'!$C$9="","",C14/C11),"") -> 127.2928 | D15: =IFERROR(IF('PyG 3 Años'!$D$9="","",D14/D11),"") -> 136.91147
A16: Ingresos necesarios al año | B16: =IFERROR(IF('PyG 3 Años'!$B$9="","",B14*B8),"") -> 94128.204 | C16: =IFERROR(IF('PyG 3 Años'!$C$9="","",C14*C8),"") -> 102598 | D16: =IFERROR(IF('PyG 3 Años'!$D$9="","",D14*D8),"") -> 110350.65
A17: PUNTO DE EQUILIBRIO DE CAJA (incluye la cuota del préstamo)
A18: Costes fijos de caja + principal del año | B18: =IFERROR(IF('PyG 3 Años'!$B$9="","",B6-'PyG 3 Años'!$B$36+B12),"") -> 62578.42 | C18: =IFERROR(IF('PyG 3 Años'!$C$9="","",C6-'PyG 3 Años'!$C$36+C12),"") -> 76394.157 | D18: =IFERROR(IF('PyG 3 Años'!$D$9="","",D6-'PyG 3 Años'!$D$36+D12),"") -> 82394.157 | E18: Los fijos del P&L sin la amortización (que no se paga) y CON la devolución de principal (que sí). Es el umbral que decide si la caja aguanta
A19: Invitados necesarios al año (caja) | B19: =IFERROR(IF('PyG 3 Años'!$B$9="","",IF(B10<=0,"",B18/B10)),"") -> 14248.015 | C19: =IFERROR(IF('PyG 3 Años'!$C$9="","",IF(C10<=0,"",C18/C10)),"") -> 17393.617 | D19: =IFERROR(IF('PyG 3 Años'!$D$9="","",IF(D10<=0,"",D18/D10)),"") -> 18759.712
A20: Invitados necesarios por evento (caja) | B20: =IFERROR(IF('PyG 3 Años'!$B$9="","",B19/B11),"") -> 109.60011 | C20: =IFERROR(IF('PyG 3 Años'!$C$9="","",C19/C11),"") -> 133.79705 | D20: =IFERROR(IF('PyG 3 Años'!$D$9="","",D19/D11),"") -> 144.30548
A21: Ingresos necesarios al año (caja) | B21: =IFERROR(IF('PyG 3 Años'!$B$9="","",B19*B8),"") -> 88337.691 | C21: =IFERROR(IF('PyG 3 Años'!$C$9="","",C19*C8),"") -> 107840.42 | D21: =IFERROR(IF('PyG 3 Años'!$D$9="","",D19*D8),"") -> 116310.22
A22: CONTRASTE CON EL PLAN
A23: Invitados por evento previstos en el plan | B23: =IFERROR(IF('PyG 3 Años'!$B$9="","",'PyG 3 Años'!$B$6),"") -> 135 | C23: =IFERROR(IF('PyG 3 Años'!$C$9="","",'PyG 3 Años'!$C$6),"") -> 148.5 | D23: =IFERROR(IF('PyG 3 Años'!$D$9="","",'PyG 3 Años'!$D$6),"") -> 160.38
A24: Holgura sobre el equilibrio de CAJA (%) | B24: =IFERROR(IF('PyG 3 Años'!$B$9="","",B23/B20-1),"") -> 0.23175056 | C24: =IFERROR(IF('PyG 3 Años'!$C$9="","",C23/C20-1),"") -> 0.10988992 | D24: =IFERROR(IF('PyG 3 Años'!$D$9="","",D23/D20-1),"") -> 0.11139231 | E24: Cuánto superan tus ventas previstas a las del equilibrio de caja. La caída que aguantas antes de no poder pagar los costes fijos y la cuota es algo menor: con un 25 % de holgura, un 20 %. El mínimo exigible está en la hoja de Supuestos
A25: INTERPRETACIÓN
A26: =IFERROR("Con el precio medio por invitado sin IVA de la fila de arriba necesitas "&TEXT(ROUNDUP(B15,0),"0")&" invitados por evento durante los "&TEXT(B11,"0")&" eventos del año para no perder dinero (equilibrio contable, con la amortización dentro), y "&TEXT(ROUNDUP(B20,0),"0")&" para que la caja aguante (equilibrio de caja: sin la amortización, que no se paga, y con la cuota del préstamo del año"&IF(B12=0,"; este año sólo intereses, porque el préstamo está en carencia","")&"). En las filas «Ingresos necesarios al año» tienes esas mismas cifras en euros.","") -> Con el precio medio por invitado sin IVA de la fila de arriba necesitas 117 invitados por evento durante los 130 eventos del año para no perder dinero (equilibrio contable, con la amortización dentro), y 110 para que la caja aguante (equilibrio de caja: sin la amortización, que no se paga, y con la cuota del préstamo del año; este año sólo intereses, porque el préstamo está en carencia). En las filas «Ingresos necesarios al año» tienes esas mismas cifras en euros.
A28: SENSIBILIDAD DEL PUNTO DE EQUILIBRIO
A29: Invitados por evento necesarios para cubrir costes según el precio medio por invitado (columnas) y el coste variable por invitado (filas). En verde, los que están por debajo de los invitados que prevé el plan.
A31: Invitados por evento necesarios: precio medio por invitado sin IVA (columnas) × coste variable por invitado (filas) | B31: =IFERROR($B$8-2,"") -> 4.2 | C31: =IFERROR(IF($B$8="","",$B$8),"") -> 6.2 | D31: =IFERROR($B$8+2,"") -> 8.2 | E31: =IFERROR($B$8+4,"") -> 10.2
A32: =IFERROR($B$9*0.85,"") -> 1.536732 | B32: =IFERROR(IF($B$31-$A32<=0,"",$B$6/($B$31-$A32)/$B$11),"") -> 192.59282 | C32: =IFERROR(IF($C$31-$A32<=0,"",$B$6/($C$31-$A32)/$B$11),"") -> 109.99289 | D32: =IFERROR(IF($D$31-$A32<=0,"",$B$6/($D$31-$A32)/$B$11),"") -> 76.97819 | E32: =IFERROR(IF($E$31-$A32<=0,"",$B$6/($E$31-$A32)/$B$11),"") -> 59.207023
A33: =IFERROR($B$9*0.925,"") -> 1.672326 | B33: =IFERROR(IF($B$31-$A33<=0,"",$B$6/($B$31-$A33)/$B$11),"") -> 202.92423 | C33: =IFERROR(IF($C$31-$A33<=0,"",$B$6/($C$31-$A33)/$B$11),"") -> 113.28693 | D33: =IFERROR(IF($D$31-$A33<=0,"",$B$6/($D$31-$A33)/$B$11),"") -> 78.577194 | E33: =IFERROR(IF($E$31-$A33<=0,"",$B$6/($E$31-$A33)/$B$11),"") -> 60.148442
A34: =IFERROR($B$9*1.0,"") -> 1.80792 | B34: =IFERROR(IF($B$31-$A34<=0,"",$B$6/($B$31-$A34)/$B$11),"") -> 214.4269 | C34: =IFERROR(IF($C$31-$A34<=0,"",$B$6/($C$31-$A34)/$B$11),"") -> 116.78437 | D34: =IFERROR(IF($D$31-$A34<=0,"",$B$6/($D$31-$A34)/$B$11),"") -> 80.244038 | E34: =IFERROR(IF($E$31-$A34<=0,"",$B$6/($E$31-$A34)/$B$11),"") -> 61.120283
A35: =IFERROR($B$9*1.075,"") -> 1.943514 | B35: =IFERROR(IF($B$31-$A35<=0,"",$B$6/($B$31-$A35)/$B$11),"") -> 227.31198 | C35: =IFERROR(IF($C$31-$A35<=0,"",$B$6/($C$31-$A35)/$B$11),"") -> 120.50464 | D35: =IFERROR(IF($D$31-$A35<=0,"",$B$6/($D$31-$A35)/$B$11),"") -> 81.98313 | E35: =IFERROR(IF($E$31-$A35<=0,"",$B$6/($E$31-$A35)/$B$11),"") -> 62.124045
A36: =IFERROR($B$9*1.15,"") -> 2.079108 | B36: =IFERROR(IF($B$31-$A36<=0,"",$B$6/($B$31-$A36)/$B$11),"") -> 241.84461 | C36: =IFERROR(IF($C$31-$A36<=0,"",$B$6/($C$31-$A36)/$B$11),"") -> 124.46973 | D36: =IFERROR(IF($D$31-$A36<=0,"",$B$6/($D$31-$A36)/$B$11),"") -> 83.799274 | E36: =IFERROR(IF($E$31-$A36<=0,"",$B$6/($E$31-$A36)/$B$11),"") -> 63.161326

Sheet Escenarios
A1: ANÁLISIS DE ESCENARIOS
A4: Métrica | B4: Pesimista | C4: Realista | D4: Optimista | E4: Notas
A5: Invitados por evento | B5: 130 | C5: =IFERROR(IF('PyG 3 Años'!$B$6="","",'PyG 3 Años'!$B$6),"") -> 135 | D5: 140
A6: Precio medio por invitado sin IVA | B6: 5.7 | C6: =IFERROR(IF('PyG 3 Años'!$B$7="","",'PyG 3 Años'!$B$7),"") -> 6.2 | D6: 6.3
A7: Eventos al año | B7: 110 | C7: =IFERROR(IF('PyG 3 Años'!$B$8="","",'PyG 3 Años'!$B$8),"") -> 130 | D7: 145
A8: INGRESOS ANUALES (sin IVA) | B8: =IFERROR(IF(B5*B6*B7=0,"",B5*B6*B7),"") -> 81510 | C8: =IFERROR(IF(C5*C6*C7=0,"",C5*C6*C7),"") -> 108810 | D8: =IFERROR(IF(D5*D6*D7=0,"",D5*D6*D7),"") -> 127890
A9: Coste de mercancía — comida | B9: =IFERROR(IF(B8="","",B8*'0. Supuestos'!$B$11*'0. Supuestos'!$B$13),"") -> 4124.406 | C9: =IFERROR(IF(C8="","",C8*'0. Supuestos'!$B$11*'0. Supuestos'!$B$13),"") -> 5505.786 | D9: =IFERROR(IF(D8="","",D8*'0. Supuestos'!$B$11*'0. Supuestos'!$B$13),"") -> 6471.234
A10: Coste de mercancía — bebida | B10: =IFERROR(IF(B8="","",B8*'0. Supuestos'!$B$12*'0. Supuestos'!$B$14),"") -> 11607.024 | C10: =IFERROR(IF(C8="","",C8*'0. Supuestos'!$B$12*'0. Supuestos'!$B$14),"") -> 15494.544 | D10: =IFERROR(IF(D8="","",D8*'0. Supuestos'!$B$12*'0. Supuestos'!$B$14),"") -> 18211.536
A11: Consumibles y envases | B11: =IFERROR(IF(B8="","",B8*'0. Supuestos'!$B$15),"") -> 3260.4 | C11: =IFERROR(IF(C8="","",C8*'0. Supuestos'!$B$15),"") -> 4352.4 | D11: =IFERROR(IF(D8="","",D8*'0. Supuestos'!$B$15),"") -> 5115.6
A12: Canon de ferias y mercados | B12: =IFERROR(IF(B8="","",B8*'0. Supuestos'!$B$16*'0. Supuestos'!$B$17),"") -> 1027.026 | C12: =IFERROR(IF(C8="","",C8*'0. Supuestos'!$B$16*'0. Supuestos'!$B$17),"") -> 1371.006 | D12: =IFERROR(IF(D8="","",D8*'0. Supuestos'!$B$16*'0. Supuestos'!$B$17),"") -> 1611.414
A13: Comisiones de los medios de pago | B13: =IFERROR(IF(B8="","",B8*'0. Supuestos'!$B$18),"") -> 489.06 | C13: =IFERROR(IF(C8="","",C8*'0. Supuestos'!$B$18),"") -> 652.86 | D13: =IFERROR(IF(D8="","",D8*'0. Supuestos'!$B$18),"") -> 767.34
A14: Varios e imprevistos | B14: =IFERROR(IF(B8="","",B8*'0. Supuestos'!$B$28),"") -> 3260.4 | C14: =IFERROR(IF(C8="","",C8*'0. Supuestos'!$B$28),"") -> 4352.4 | D14: =IFERROR(IF(D8="","",D8*'0. Supuestos'!$B$28),"") -> 5115.6
A15: TOTAL COSTES VARIABLES | B15: =IFERROR(IF(B8="","",SUM(B9:B14)),"") -> 23768.316 | C15: =IFERROR(IF(C8="","",SUM(C9:C14)),"") -> 31728.996 | D15: =IFERROR(IF(D8="","",SUM(D9:D14)),"") -> 37292.724
A16: MARGEN BRUTO | B16: =IFERROR(IF(B8="","",B8-B15),"") -> 57741.684 | C16: =IFERROR(IF(C8="","",C8-C15),"") -> 77081.004 | D16: =IFERROR(IF(D8="","",D8-D15),"") -> 90597.276
A17: COSTES FIJOS (los del P&L) | B17: =IFERROR(IF(B8="","",'PyG 3 Años'!$B$38),"") -> 66680.42 | C17: =IFERROR(IF(C8="","",'PyG 3 Años'!$B$38),"") -> 66680.42 | D17: =IFERROR(IF(D8="","",'PyG 3 Años'!$B$38),"") -> 66680.42 | E17: Los costes fijos no cambian con el escenario: por eso son fijos
A18: RESULTADO ANTES DE IMPUESTOS | B18: =IFERROR(IF(B8="","",B16-B17),"") -> -8938.736 | C18: =IFERROR(IF(C8="","",C16-C17),"") -> 10400.584 | D18: =IFERROR(IF(D8="","",D16-D17),"") -> 23916.856
A19: Impuesto de Sociedades | B19: =IFERROR(IF(B8="","",MAX(0,B18-'0. Supuestos'!$B$42)*'0. Supuestos'!$B$37),"") -> 0 | C19: =IFERROR(IF(C8="","",MAX(0,C18-'0. Supuestos'!$B$42)*'0. Supuestos'!$B$37),"") -> 1560.0876 | D19: =IFERROR(IF(D8="","",MAX(0,D18-'0. Supuestos'!$B$42)*'0. Supuestos'!$B$37),"") -> 3587.5284 | E19: Al tipo de entidad de nueva creación, compensando las bases negativas anteriores
A20: RESULTADO NETO | B20: =IFERROR(IF(B8="","",B18-B19),"") -> -8938.736 | C20: =IFERROR(IF(C8="","",C18-C19),"") -> 8840.4964 | D20: =IFERROR(IF(D8="","",D18-D19),"") -> 20329.328
A21: Invitados por evento para el equilibrio | B21: =IFERROR(IF(B8="","",IF(B6-B15/(B5*B7)<=0,"",B17/(B6-B15/(B5*B7))/B7)),"") -> 150.12473 | C21: =IFERROR(IF(C8="","",IF(C6-C15/(C5*C7)<=0,"",C17/(C6-C15/(C5*C7))/C7)),"") -> 116.78437 | D21: =IFERROR(IF(D8="","",IF(D6-D15/(D5*D7)<=0,"",D17/(D6-D15/(D5*D7))/D7)),"") -> 103.04127
A22: LO QUE CADA ESCENARIO EXIGE
A23: Coste de personal / Ventas | B23: =IFERROR(IF(B8="","",'PyG 3 Años'!$B$23/B8),"") -> 0.55190676 | C23: =IFERROR(IF(C8="","",'PyG 3 Años'!$B$23/C8),"") -> 0.41343553 | D23: =IFERROR(IF(D8="","",'PyG 3 Años'!$B$23/D8),"") -> 0.35175479 | E23: La MISMA plantilla en los tres escenarios. Si en el pesimista se dispara, el ajuste hay que hacerlo en la hoja de Personal, no aquí
A24: Invitados al año por jornada equivalente | B24: =IFERROR(IF(B8="","",B5*B7/'Personal'!$C$9),"") -> 9930.5556 | C24: =IFERROR(IF(C8="","",C5*C7/'Personal'!$C$9),"") -> 12187.5 | D24: =IFERROR(IF(D8="","",D5*D7/'Personal'!$C$9),"") -> 14097.222 | E24: Invitados que tendría que servir cada jornada completa del cuadro de Personal. En el optimista dice si hace falta contratar
A25: Saldo de caja al cierre del año 1 (estimado, el mismo método en los tres escenarios) | B25: =IFERROR(IF(B8="","",'Inversión Inicial'!$B$25+B20+'PyG 3 Años'!$B$36-'Financiación'!$B$45),"") -> 10807.869 | C25: =IFERROR(IF(C8="","",'Inversión Inicial'!$B$25+C20+'PyG 3 Años'!$B$36-'Financiación'!$B$45),"") -> 28587.101 | D25: =IFERROR(IF(D8="","",'Inversión Inicial'!$B$25+D20+'PyG 3 Años'!$B$36-'Financiación'!$B$45),"") -> 40075.933 | E25: Saldo ESTIMADO: fondo de maniobra más el resultado del año, devolviendo la amortización (que no se paga) y restando el principal del préstamo. No incluye el desfase de cobros y pagos ni la liquidación del IVA, así que las tres columnas se pueden comparar entre sí. En rojo, el escenario se queda sin caja
A26: Saldo real del mes 12 de la hoja de Tesorería (sólo realista) | C26: =IFERROR(IF(C8="","",'Tesorería 12 meses'!$M$22),"") -> 30156.196 | E26: El saldo REAL del caso base, con su desfase de cobros y pagos y su liquidación de IVA. Sólo existe para el escenario realista, que es el único con tesorería mensual propia: por eso no está en la fila de arriba, donde se compararía contra dos estimaciones
A28: La columna «Realista» lee sus tres datos de la hoja de Supuestos, así que reproduce EXACTAMENTE el año 1 del P&L. Los otros dos escenarios usan las mismas tasas de coste: lo único que cambia son los invitados, el precio por invitado y los eventos. Los COSTES FIJOS sí son los mismos en los tres: los varios e imprevistos, que son un porcentaje de las ventas, van arriba con los variables y cada escenario carga los suyos.

Sheet Personal
A1: ESTRUCTURA DE PERSONAL Y COSTES
A2: =IFERROR("Convenio Hostelería — "&TEXT('0. Supuestos'!$B$21,"0")&" pagas + SS "&TEXT('0. Supuestos'!$B$20*100,"0")&" %","") -> Convenio Hostelería — 14 pagas + SS 33 %
A4: Puesto | B4: Personas | C4: Jornada | D4: Bruto mes (€, total del puesto) | E4: Seg. Social a cargo de la empresa (€) | F4: Coste mes (€, total del puesto) | G4: Coste año (€) | H4: Horas/semana por persona | I4: Horas/año del puesto | J4: Notas
A5: Propietario/a — titular-barista, ventas y compras | B5: 1 | C5: 1 | D5: 1800 | E5: =IFERROR(IF(D5="","",D5*'0. Supuestos'!$B$20),"") -> 594 | F5: =IFERROR(IF(D5="","",D5+E5),"") -> 2394 | G5: =IFERROR(IF(D5="","",F5*MAX(12,'0. Supuestos'!$B$21)),"") -> 33516 | H5: =IFERROR(IF(D5="","",C5*$B$16),"") -> 40 | I5: =IFERROR(IF(D5="","",H5*B5*$B$17),"") -> 1840 | J5: Sirve en cada evento, conduce, vende a novios, empresas y agencias, compra el café y lleva la agenda. Como administrador de la SL cotiza en el régimen de autónomos: confirma con tu gestoría la cuota y si te aplica la reducida de inicio
A6: Camarero/a de barra (barista), fijo discontinuo | B6: 1 | C6: 0.36 | D6: 504 | E6: =IFERROR(IF(D6="","",D6*'0. Supuestos'!$B$20),"") -> 166.32 | F6: =IFERROR(IF(D6="","",D6+E6),"") -> 670.32 | G6: =IFERROR(IF(D6="","",F6*MAX(12,'0. Supuestos'!$B$21)),"") -> 9384.48 | H6: =IFERROR(IF(D6="","",C6*$B$16),"") -> 14.4 | I6: =IFERROR(IF(D6="","",H6*B6*$B$17),"") -> 662.4 | J6: Contrato fijo discontinuo (art. 16 del Estatuto de los Trabajadores) al 36 % de jornada en cómputo anual: segundo barista en bodas, congresos, la mitad de los eventos de empresa y la venta directa (unas 650 horas). «Barista» no es categoría del convenio: se contrata como camarero/a. Bruto a jornada completa: 1.400 € en 14 pagas
A7: Suplencias y refuerzo de temporada (fijo discontinuo) | B7: 1 | C7: 0.04 | D7: 56 | E7: =IFERROR(IF(D7="","",D7*'0. Supuestos'!$B$20),"") -> 18.48 | F7: =IFERROR(IF(D7="","",D7+E7),"") -> 74.48 | G7: =IFERROR(IF(D7="","",F7*MAX(12,'0. Supuestos'!$B$21)),"") -> 1042.72 | H7: =IFERROR(IF(D7="","",C7*$B$16),"") -> 1.6 | I7: =IFERROR(IF(D7="","",H7*B7*$B$17),"") -> 73.6 | J7: Bolsa para cubrir las vacaciones del camarero/a y los picos de temporada: unas 75 horas al año, mismo contrato y misma categoría. Para cubrir una baja concreta, el contrato es de sustitución (art. 15.3 del Estatuto de los Trabajadores). Nunca como autónomo que te factura: con tu horario y tu dirección es falso autónomo (art. 1.1)
A8: Refuerzo para eventos grandes (fijo discontinuo) | B8: 1 | C8: 0.04 | D8: 56 | E8: =IFERROR(IF(D8="","",D8*'0. Supuestos'!$B$20),"") -> 18.48 | F8: =IFERROR(IF(D8="","",D8+E8),"") -> 74.48 | G8: =IFERROR(IF(D8="","",F8*MAX(12,'0. Supuestos'!$B$21)),"") -> 1042.72 | H8: =IFERROR(IF(D8="","",C8*$B$16),"") -> 1.6 | I8: =IFERROR(IF(D8="","",H8*B8*$B$17),"") -> 73.6 | J8: Tercer barista para los congresos y las bodas de más de 200 invitados que pidan una segunda estación (tabla de escalado de la hoja Instrucciones): unas 75 horas al año. Por encima del SMI en proporción a su jornada
A9: TOTAL PLANTILLA | B9: =IFERROR(IF(COUNT(D5:D8)=0,"",SUM(B5:B8)),"") -> 4 | C9: =IFERROR(IF(COUNT(D5:D8)=0,"",SUM(C5:C8)),"") -> 1.44 | D9: =IFERROR(IF(COUNT(D5:D8)=0,"",SUM(D5:D8)),"") -> 2416 | E9: =IFERROR(IF(COUNT(D5:D8)=0,"",SUM(E5:E8)),"") -> 797.28 | F9: =IFERROR(IF(COUNT(D5:D8)=0,"",SUM(F5:F8)),"") -> 3213.28 | G9: =IFERROR(IF(COUNT(D5:D8)=0,"",SUM(G5:G8)),"") -> 44985.92 | I9: =IFERROR(IF(COUNT(D5:D8)=0,"",SUM(I5:I8)),"") -> 2649.6
A10: CRECIMIENTO DE LA PLANTILLA (coste escalonado)
A11: Coste anual de las incorporaciones del año 2 (€) | B11: 6000 | J11: Coste ANUAL completo (bruto + Seguridad Social × pagas) de lo que se contrate ese año. El P&L lo suma al coste del año anterior: la plantilla no crece con un porcentaje, crece con personas
A12: Coste anual de las incorporaciones del año 3 (€) | B12: 6000 | J12: Coste ANUAL completo (bruto + Seguridad Social × pagas) de lo que se contrate ese año. El P&L lo suma al coste del año anterior: la plantilla no crece con un porcentaje, crece con personas
A13: Coste de personal del año 2 | B13: =IFERROR(IF(G9="","",G9*(1+'0. Supuestos'!$B$48)+B11),"") -> 50985.92
A14: Coste de personal del año 3 | B14: =IFERROR(IF(B13="","",B13*(1+'0. Supuestos'!$B$48)+B12),"") -> 56985.92
A15: COBERTURA POR HORAS DE SERVICIO
A16: Jornada completa del convenio (horas/semana) | B16: 40 | J16: Art. 34.1 del Estatuto de los Trabajadores; tu convenio provincial puede fijar menos
A17: Semanas trabajadas al año por persona | B17: 46 | J17: 46 semanas: 52 menos las vacaciones (30 días naturales, art. 38 ET), los festivos y las ausencias medias
A18: Horas de trabajo por evento que hay que cubrir | B18: 7.5 | J18: Horas por evento y persona: carga en la base, viaje, llegada una hora antes, montaje, servicio, desmontaje, limpieza y descarga. Un servicio «de 2 horas» es una jornada de 7 a 9 horas. La oficina y la limpieza de la base van aparte
A19: Personas necesarias a la vez en cada evento | B19: 1.6 | J19: Personas trabajando a la vez en un evento medio: dos baristas en bodas, congresos, ferias y la mitad de los eventos de empresa, y el titular solo en los pequeños. Ajústalo y la hoja te dice si llega la plantilla
A20: Horas de servicio a cubrir al año | B20: =IFERROR(IF(OR(B18="",B19="",'0. Supuestos'!$B$6=""),"",B18*B19*'0. Supuestos'!$B$6),"") -> 1560
A21: Horas contratadas al año | B21: =IFERROR(IF(I9="","",I9),"") -> 2649.6
A22: Cobertura (contratadas / necesarias) | B22: =IFERROR(B21/B20,"") -> 1.6984615 | J22: Por debajo del 100 % la plantilla no llega a cubrir el horario que declara el plan: o se contrata más o se recorta el horario
A24: Las columnas «Bruto mes», «Seg. Social», «Coste mes» y «Coste año» son TOTALES de la fila: en un puesto con dos personas incluyen a las dos. «Jornada» es el porcentaje sobre la jornada completa del convenio y sirve para comparar el salario con el suelo legal en proporción. El tipo de Seguridad Social y el número de pagas están en la hoja «0. Supuestos».
A25: El suelo salarial es el MAYOR entre el SMI y el salario de convenio, los dos en la hoja «0. Supuestos»; las jornadas parciales lo llevan en proporción. El convenio aplicable es el PROVINCIAL de hostelería: no existe una tabla salarial estatal única, así que la celda del convenio se entrega vacía para que copies la de tu provincia.

Sheet Instrucciones
A1: INSTRUCCIONES DE USO — Plan financiero Cafetería Móvil para Eventos
A3: CÓMO SE USA ESTE LIBRO
A4: Este plan financiero es un MODELO: sólo se teclea en las celdas VERDES y el resto se recalcula solo.
A5: 1. «0. Supuestos» es la hoja de mando: invitados, precio por invitado sin IVA, eventos, mezcla de comida y bebida, coste de mercancía, alquiler, financiación e impuestos.
A6: 2. Las partidas de la inversión, los costes fijos y la plantilla se teclean en su propia hoja, también en verde. Ningún número se escribe dos veces.
A7: 3. Sólo «Punto Equilibrio» se deriva entera de lo anterior. En las otras tres hojas también hay celdas verdes que puedes tocar: el escenario pesimista y el optimista en «Escenarios», la estacionalidad y la rampa de arranque en «Tesorería 12 meses», y las cuatro fuentes alternativas de financiación en «Financiación». Todo lo demás se calcula.
A8: 4. Todas las cifras van SIN IVA. Para pasar un PVP a precio sin IVA, divide entre 1,10: todo lo que sirve la cafetería móvil, en la barra del evento o en la venta directa de ferias y mercados, va al 10 % (art. 91.Uno.2.2.º de la Ley 37/1992 del IVA; la bollería y el café que se llevan, al mismo tipo por el art. 91.Uno.1.1.º). Entre 1,21 sólo van los extras con precio propio (personalización de la barra, talleres de latte art, alquiler de la cafetera sin barista) y un refresco envasado con azúcares o edulcorantes añadidos que se venda para llevar: ninguno de los dos está en este libro. El tipo de cada línea de venta está en la columna «Tipo de IVA de la línea» del P&L y de ahí salen los cobros, el IVA repercutido y el PVP equivalente. El IVA de la inversión se adelanta y se recupera con el modelo 303.
A9: 5. Si cambias la plantilla, el P&L la lee sola: el coste de personal sale de la hoja «Personal», no de una estimación aparte.
A10: 6. La hoja «Tesorería 12 meses» responde la pregunta que decide una operación bancaria: en qué mes se agota la caja. Su Mes 1 es MARZO: la cafetería arranca en primavera y llega al primer invierno con la caja de la temporada. El saldo mínimo del año nunca puede salir en rojo. Las señales de los particulares no se modelan: tu caja real será algo mejor.
A11: 7. La hoja «Financiación» cuadra lo que hace falta con lo que se aporta y monta el cuadro de amortización del préstamo. Si la diferencia sale en rojo, el plan no está financiado.
A12: 8. El documento Word de este pack usa las cifras de este Excel; la calculadora de presupuestos y el modelo de contrato usan los mismos porcentajes de cobro y de cancelación, y la misma tabla de escalado. Si cambias una celda verde, el Excel manda. El coste de mercancía de Supuestos es la media de la mezcla con la merma: el de una bebida concreta está en la calculadora y no se copia aquí.
A14: RATIOS QUE AUDITA EL LIBRO
A15: Los umbrales viven en la columna «Umbral» del bloque RATIOS CLAVE del P&L: cámbialos ahí y el semáforo cambia con ellos.
A17: Ratio | B17: Valor del año 1 | C17: Umbral | D17: Estado
A18: Coste de mercancía / Ventas | B18: =IFERROR(IF('PyG 3 Años'!$B$53="","",'PyG 3 Años'!$B$53),"") -> 0.193 | C18: =IFERROR(IF('PyG 3 Años'!$E$53="","",'PyG 3 Años'!$E$53),"") -> 0.22 | D18: =IFERROR(IF(OR(B18="",C18=""),"",IF(B18<=C18,"CUMPLE","REVISAR")),"") -> CUMPLE
A19: Coste de personal / Ventas | B19: =IFERROR(IF('PyG 3 Años'!$B$54="","",'PyG 3 Años'!$B$54),"") -> 0.41343553 | C19: =IFERROR(IF('PyG 3 Años'!$E$54="","",'PyG 3 Años'!$E$54),"") -> 0.45 | D19: =IFERROR(IF(OR(B19="",C19=""),"",IF(B19<=C19,"CUMPLE","REVISAR")),"") -> CUMPLE
A20: Cuota del almacén base / Ventas | B20: =IFERROR(IF('PyG 3 Años'!$B$55="","",'PyG 3 Años'!$B$55),"") -> 0.044113593 | C20: =IFERROR(IF('PyG 3 Años'!$E$55="","",'PyG 3 Años'!$E$55),"") -> 0.06 | D20: =IFERROR(IF(OR(B20="",C20=""),"",IF(B20<=C20,"CUMPLE","REVISAR")),"") -> CUMPLE
A21: Resultado neto / Ventas | B21: =IFERROR(IF('PyG 3 Años'!$B$56="","",'PyG 3 Años'!$B$56),"") -> 0.081247095 | C21: =IFERROR(IF('PyG 3 Años'!$E$56="","",'PyG 3 Años'!$E$56),"") -> 0.05 | D21: =IFERROR(IF(OR(B21="",C21=""),"",IF(B21>=C21,"CUMPLE","REVISAR")),"") -> CUMPLE
A22: Margen bruto / Ventas | B22: =IFERROR(IF('PyG 3 Años'!$B$51="","",'PyG 3 Años'!$B$51),"") -> 0.7084 | C22: =IFERROR(IF('PyG 3 Años'!$E$51="","",'PyG 3 Años'!$E$51),"") -> 0.65 | D22: =IFERROR(IF(OR(B22="",C22=""),"",IF(B22>=C22,"CUMPLE","REVISAR")),"") -> CUMPLE
A24: CIFRAS DE ESTE PLAN
A25: Inversión total (suma de los bloques) | B25: =IFERROR(IF('Inversión Inicial'!$B$26="","",'Inversión Inicial'!$B$26),"") -> 60060.605
A26: Necesidad total de caja al arranque | B26: =IFERROR(IF('Inversión Inicial'!$B$29="","",'Inversión Inicial'!$B$29),"") -> 69009.965
A27: Fondo de maniobra dotado | B27: =IFERROR(IF('Inversión Inicial'!$B$25="","",'Inversión Inicial'!$B$25),"") -> 15644.605
A28: Facturación prevista del año 1 | B28: =IFERROR(IF('PyG 3 Años'!$B$9="","",'PyG 3 Años'!$B$9),"") -> 108810
A29: Resultado neto del año 1 | B29: =IFERROR(IF('PyG 3 Años'!$B$48="","",'PyG 3 Años'!$B$48),"") -> 8840.4964
A30: Invitados por evento para el punto de equilibrio CONTABLE (con la amortización dentro) | B30: =IFERROR(IF('Punto Equilibrio'!$B$15="","",'Punto Equilibrio'!$B$15),"") -> 116.78437
A31: Payback del proyecto (años), antes de la deuda | B31: =IFERROR(IF('Tesorería 12 meses'!$B$31="","",'Tesorería 12 meses'!$B$31),"") -> Más de 3 años
A33: DATOS DE REFERENCIA DEL SECTOR
A34: Referencia | B34: Valor | C34: Fuente | D34: Nota
A35: Mes 1 del plan | B35: Marzo | C35: Decisión del plan | D35: El café se reserva de una semana a seis meses antes: se arranca en primavera, con la empresa y las comuniones, y enero y febrero (los meses más flojos) llegan con la caja de la temporada. La fila de estacionalidad de la Tesorería ya va girada
A36: Mezcla de eventos del plan | B36: 130 eventos: 30 bodas, 40 de empresa, 22 jornadas de congreso o feria, 25 privados y 12 de venta directa | C36: Estimación del kit | D36: Bodas (30 × 120 invitados × 9,00 €), empresa (40 × 80 × 8,00 €), congresos (22 × 300 × 4,50 €), privados y rodajes (25 × 50 × 9,50 €) y venta directa (12 × 250 tazas × 3,00 €), sin IVA: 129 servicios y 108.575 €. El plan redondea a 130 eventos de 135 invitados a 6,20 €
A37: Escalado: barra de 3 horas para 50 invitados | B37: 70 bebidas · 1 barista · 1 cafetera de dos grupos · 2 molinos | C37: Estimación del kit (ratios de EE. UU.) | D37: 1,2 kg de café · 9 l de leche · 77 vasos desechables (o tazas de loza) · 3,5 kW: enchufe de 16 A · 38 l de agua limpia. Con 1,4 bebidas por invitado (barra de 2 a 4 horas); la calculadora lo hace con tus horas y tus invitados
A38: Escalado: barra de 3 horas para 100 invitados | B38: 140 bebidas · 2 baristas · 1 cafetera de dos grupos · 2 molinos | C38: Estimación del kit (ratios de EE. UU.) | D38: 2,3 kg de café · 18 l de leche · 154 vasos desechables (o tazas de loza) · 3,5 kW: enchufe de 16 A · 55 l de agua limpia. Con 1,4 bebidas por invitado (barra de 2 a 4 horas); la calculadora lo hace con tus horas y tus invitados
A39: Escalado: barra de 3 horas para 200 invitados | B39: 280 bebidas · 3 baristas · 2 cafeteras de dos grupos · 3 molinos | C39: Estimación del kit (ratios de EE. UU.) | D39: 4,3 kg de café · 35 l de leche · 308 vasos desechables (o tazas de loza) · 7,0 kW: toma dedicada o generador · 90 l de agua limpia. Con 1,4 bebidas por invitado (barra de 2 a 4 horas); la calculadora lo hace con tus horas y tus invitados
A40: Escalado: barra de 3 horas para 300 invitados | B40: 420 bebidas · 4 baristas · 2 cafeteras de dos grupos · 3 molinos | C40: Estimación del kit (ratios de EE. UU.) | D40: 6,4 kg de café · 53 l de leche · 462 vasos desechables (o tazas de loza) · 7,0 kW: toma dedicada o generador · 125 l de agua limpia. Con 1,4 bebidas por invitado (barra de 2 a 4 horas); la calculadora lo hace con tus horas y tus invitados
A41: Bebidas por invitado según las horas | B41: Hasta 2 horas 1,0 · más de 2 y hasta 4 horas 1,3-1,5 · más de 4 y hasta 6 horas 1,5-1,8 · más de 6 horas 2,0-2,5 | C41: Estimación del kit (ratios de EE. UU.) | D41: Por la mañana, un 20-30 % más; en una boda de noche, un 10 % menos. Un barista con dos grupos saca unas 50-60 bebidas por hora y dos baristas, 100-120
A42: Electricidad de la barra | B42: Cafetera de dos grupos: 2,4-4,5 kW · un enchufe de 16 A da unos 3,7 kW | C42: Ficha técnica de fabricante y cálculo (230 V × 16 A) | D42: Cafetera de 3,5 kW como máximo o toma dedicada; si no, generador inverter o baterías. El contrato del kit pide la toma por escrito
A43: Coste de una bebida | B43: Unos 0,59 € de café, leche y siropes, más unos 0,12 € de vaso y tapa | C43: Calculadora del kit (estimación con precios de proveedor) | D43: Media de la mezcla de diez bebidas, con un doble de 16 g de café de especialidad a unos 22 €/kg y la merma. En loza sólo cuenta el producto. El coste de mercancía de Supuestos es la media del año con la merma
A44: Precios publicados de barras de café para bodas | B44: Desde 295 € hasta 1.300 € por evento | C44: Fichas de proveedores en Bodas.net, consulta del 28-10-2026 | D44: Precios «desde» de escaparate y sin desglose: sirven para situarte, no para copiarlos. Señal del 30-50 % y el resto antes del evento; hora extra de 37 a 50 €
A45: Cobro y cancelación del kit | B45: Particular: 30 % al firmar y 70 % siete días antes · Empresa: 30 % y 70 % a 30 días de la factura | C45: Contrato y calculadora del kit | D45: Cancelación en cuatro tramos (particular: 60, 30 y 7 días; empresa: 30, 15 y 7): se retiene el 10, el 30 o el 60 % del precio, y en el último tramo el 100 % menos los costes que te ahorras; recíproca si cancelas tú. En la feria se cobra en el acto
... A52: Epígrafe del IAE | B52: 677.9 (y 675 si vendes en mercados) | C52: Tarifas del IAE (RDLeg 1175/1990) | D52: Elegir el epígrafe es criterio de asesoría: confírmalo con tu gestoría. Exento de cuota por debajo de 1 millón de euros de cifra de negocio
A54: Para editar una celda que no esté en verde: Revisar → Desproteger hoja (no tiene contraseña).
A55: Más plantillas y kits del catálogo en aichef.pro/productos-digitales
A56: Diseñado por John Guerrero — chef y consultor gastronómico desde 2010, en cocina desde los 17 años · johnguerrero.es
A57: Versión 1.0 · octubre 2026 · aichef.pro/plan-negocio-cafeteria-movil-eventos · info@aichef.pro

Sheet Tesorería 12 meses
A1: PREVISIÓN DE TESORERÍA — AÑO 1
A2: El P&L dice si el negocio gana dinero; esta hoja dice si le queda caja para llegar a fin de mes. Es la primera que mira un banco.
A4: Concepto | B4: Mes 1 (€) | C4: Mes 2 (€) | D4: Mes 3 (€) | E4: Mes 4 (€) | F4: Mes 5 (€) | G4: Mes 6 (€) | H4: Mes 7 (€) | I4: Mes 8 (€) | J4: Mes 9 (€) | K4: Mes 10 (€) | L4: Mes 11 (€) | M4: Mes 12 (€) | N4: Año (€)
A5: Estacionalidad del mes (suma 100 %) | B5: 0.081 | C5: 0.089 | D5: 0.114 | E5: 0.116 | F5: 0.068 | G5: 0.039 | H5: 0.11 | I5: 0.113 | J5: 0.09 | K5: 0.069 | L5: 0.043 | M5: 0.068 | N5: =IFERROR(IF('PyG 3 Años'!$B$9="","",SUM(B5:M5)),"") -> 1 | O5: Mes 1 = MARZO: el café se reserva de una semana a seis meses antes y se arranca en primavera, con la empresa y las comuniones. Los picos son mayo y junio (Meses 3 y 4) y septiembre y octubre (Meses 7 y 8); el valle, agosto (Mes 6) y enero (Mes 11). Si arrancas en otro mes, gira la fila. Tiene que sumar 100 %
A6: Rampa de arranque (% de la actividad de crucero) | B6: =IFERROR(IF('PyG 3 Años'!$B$9="","",MIN(1,'0. Supuestos'!$B$52+(1-'0. Supuestos'!$B$52)*0/MAX(1,'0. Supuestos'!$B$53-1))),"") -> 0.45 | C6: =IFERROR(IF('PyG 3 Años'!$B$9="","",MIN(1,'0. Supuestos'!$B$52+(1-'0. Supuestos'!$B$52)*1/MAX(1,'0. Supuestos'!$B$53-1))),"") -> 0.51875 | D6: =IFERROR(IF('PyG 3 Años'!$B$9="","",MIN(1,'0. Supuestos'!$B$52+(1-'0. Supuestos'!$B$52)*2/MAX(1,'0. Supuestos'!$B$53-1))),"") -> 0.5875 | E6: =IFERROR(IF('PyG 3 Años'!$B$9="","",MIN(1,'0. Supuestos'!$B$52+(1-'0. Supuestos'!$B$52)*3/MAX(1,'0. Supuestos'!$B$53-1))),"") -> 0.65625 | F6: =IFERROR(IF('PyG 3 Años'!$B$9="","",MIN(1,'0. Supuestos'!$B$52+(1-'0. Supuestos'!$B$52)*4/MAX(1,'0. Supuestos'!$B$53-1))),"") -> 0.725 | G6: =IFERROR(IF('PyG 3 Años'!$B$9="","",MIN(1,'0. Supuestos'!$B$52+(1-'0. Supuestos'!$B$52)*5/MAX(1,'0. Supuestos'!$B$53-1))),"") -> 0.79375 | H6: =IFERROR(IF('PyG 3 Años'!$B$9="","",MIN(1,'0. Supuestos'!$B$52+(1-'0. Supuestos'!$B$52)*6/MAX(1,'0. Supuestos'!$B$53-1))),"") -> 0.8625 | I6: =IFERROR(IF('PyG 3 Años'!$B$9="","",MIN(1,'0. Supuestos'!$B$52+(1-'0. Supuestos'!$B$52)*7/MAX(1,'0. Supuestos'!$B$53-1))),"") -> 0.93125 | J6: =IFERROR(IF('PyG 3 Años'!$B$9="","",MIN(1,'0. Supuestos'!$B$52+(1-'0. Supuestos'!$B$52)*8/MAX(1,'0. Supuestos'!$B$53-1))),"") -> 1 | K6: =IFERROR(IF('PyG 3 Años'!$B$9="","",MIN(1,'0. Supuestos'!$B$52+(1-'0. Supuestos'!$B$52)*9/MAX(1,'0. Supuestos'!$B$53-1))),"") -> 1 | L6: =IFERROR(IF('PyG 3 Años'!$B$9="","",MIN(1,'0. Supuestos'!$B$52+(1-'0. Supuestos'!$B$52)*10/MAX(1,'0. Supuestos'!$B$53-1))),"") -> 1 | M6: =IFERROR(IF('PyG 3 Años'!$B$9="","",MIN(1,'0. Supuestos'!$B$52+(1-'0. Supuestos'!$B$52)*11/MAX(1,'0. Supuestos'!$B$53-1))),"") -> 1 | O6: Sube en línea recta desde el porcentaje del mes 1 hasta el 100 % en los meses que digas en Supuestos. Con el mes 1 al 100 % la rampa desaparece
A7: Reparto de la actividad por mes (calculado) | B7: =IFERROR(IF('PyG 3 Años'!$B$9="","",B5*B6/SUMPRODUCT($B$5:$M$5,$B$6:$M$6)),"") -> 0.046966732 | C7: =IFERROR(IF('PyG 3 Años'!$B$9="","",C5*C6/SUMPRODUCT($B$5:$M$5,$B$6:$M$6)),"") -> 0.059489583 | D7: =IFERROR(IF('PyG 3 Años'!$B$9="","",D5*D6/SUMPRODUCT($B$5:$M$5,$B$6:$M$6)),"") -> 0.086298954 | E7: =IFERROR(IF('PyG 3 Años'!$B$9="","",E5*E6/SUMPRODUCT($B$5:$M$5,$B$6:$M$6)),"") -> 0.098088957 | F7: =IFERROR(IF('PyG 3 Años'!$B$9="","",F5*F6/SUMPRODUCT($B$5:$M$5,$B$6:$M$6)),"") -> 0.063524277 | G7: =IFERROR(IF('PyG 3 Años'!$B$9="","",G5*G6/SUMPRODUCT($B$5:$M$5,$B$6:$M$6)),"") -> 0.039887898 | H7: =IFERROR(IF('PyG 3 Años'!$B$9="","",H5*H6/SUMPRODUCT($B$5:$M$5,$B$6:$M$6)),"") -> 0.1222488 | I7: =IFERROR(IF('PyG 3 Años'!$B$9="","",I5*I6/SUMPRODUCT($B$5:$M$5,$B$6:$M$6)),"") -> 0.13559308 | ... M7: =IFERROR(IF('PyG 3 Años'!$B$9="","",M5*M6/SUMPRODUCT($B$5:$M$5,$B$6:$M$6)),"") -> 0.087619692 | N7: =IFERROR(IF('PyG 3 Años'!$B$9="","",SUM(B7:M7)),"") -> 1 | O7: Estacionalidad × rampa, normalizado a 100 %: el AÑO factura lo que dice el P&L, pero repartido como lo reparte una cafetería móvil que acaba de arrancar
A8: COBROS
A9: Ventas cobradas (con IVA repercutido) | B9: =IFERROR(IF('PyG 3 Años'!$B$9="","",('PyG 3 Años'!$B$9+'PyG 3 Años'!$B$9*SUMPRODUCT('PyG 3 Años'!$E$10:$E$11,'PyG 3 Años'!$G$10:$G$11))*B7*(1-MIN(30,'0. Supuestos'!$B$58)/30)),"") -> 1873.8317 | C9: =IFERROR(IF('PyG 3 Años'!$B$9="","",('PyG 3 Años'!$B$9+'PyG 3 Años'!$B$9*SUMPRODUCT('PyG 3 Años'!$E$10:$E$11,'PyG 3 Años'!$G$10:$G$11))*(C7*(1-MIN(30,'0. Supuestos'!$B$58)/30)+B7*MIN(30,'0. Supuestos'!$B$58)/30)),"") -> 6121.1193 | D9: =IFERROR(IF('PyG 3 Años'!$B$9="","",('PyG 3 Años'!$B$9+'PyG 3 Años'!$B$9*SUMPRODUCT('PyG 3 Años'!$E$10:$E$11,'PyG 3 Años'!$G$10:$G$11))*(D7*(1-MIN(30,'0. Supuestos'!$B$58)/30)+C7*MIN(30,'0. Supuestos'!$B$58)/30)),"") -> 8189.9812 | E9: =IFERROR(IF('PyG 3 Años'!$B$9="","",('PyG 3 Años'!$B$9+'PyG 3 Años'!$B$9*SUMPRODUCT('PyG 3 Años'!$E$10:$E$11,'PyG 3 Años'!$G$10:$G$11))*(E7*(1-MIN(30,'0. Supuestos'!$B$58)/30)+D7*MIN(30,'0. Supuestos'!$B$58)/30)),"") -> 10799.594 | F9: =IFERROR(IF('PyG 3 Años'!$B$9="","",('PyG 3 Años'!$B$9+'PyG 3 Años'!$B$9*SUMPRODUCT('PyG 3 Años'!$E$10:$E$11,'PyG 3 Años'!$G$10:$G$11))*(F7*(1-MIN(30,'0. Supuestos'!$B$58)/30)+E7*MIN(30,'0. Supuestos'!$B$58)/30)),"") -> 10361.338 | G9: =IFERROR(IF('PyG 3 Años'!$B$9="","",('PyG 3 Años'!$B$9+'PyG 3 Años'!$B$9*SUMPRODUCT('PyG 3 Años'!$E$10:$E$11,'PyG 3 Años'!$G$10:$G$11))*(G7*(1-MIN(30,'0. Supuestos'!$B$58)/30)+F7*MIN(30,'0. Supuestos'!$B$58)/30)),"") -> 6660.2636 | H9: =IFERROR(IF('PyG 3 Años'!$B$9="","",('PyG 3 Años'!$B$9+'PyG 3 Años'!$B$9*SUMPRODUCT('PyG 3 Años'!$E$10:$E$11,'PyG 3 Años'!$G$10:$G$11))*(H7*(1-MIN(30,'0. Supuestos'!$B$58)/30)+G7*MIN(30,'0. Supuestos'!$B$58)/30)),"") -> 8060.1753 | I9: =IFERROR(IF('PyG 3 Años'!$B$9="","",('PyG 3 Años'!$B$9+'PyG 3 Años'!$B$9*SUMPRODUCT('PyG 3 Años'!$E$10:$E$11,'PyG 3 Años'!$G$10:$G$11))*(I7*(1-MIN(30,'0. Supuestos'!$B$58)/30)+H7*MIN(30,'0. Supuestos'!$B$58)/30)),"") -> 15164.478 | J9: =IFERROR(IF('PyG 3 Años'!$B$9="","",('PyG 3 Años'!$B$9+'PyG 3 Años'!$B$9*SUMPRODUCT('PyG 3 Años'!$E$10:$E$11,'PyG 3 Años'!$G$10:$G$11))*(J7*(1-MIN(30,'0. Supuestos'!$B$58)/30)+I7*MIN(30,'0. Supuestos'!$B$58)/30)),"") -> 15446.259 | ... M9: =IFERROR(IF('PyG 3 Años'!$B$9="","",('PyG 3 Años'!$B$9+'PyG 3 Años'!$B$9*SUMPRODUCT('PyG 3 Años'!$E$10:$E$11,'PyG 3 Años'!$G$10:$G$11))*(M7*(1-MIN(30,'0. Supuestos'!$B$58)/30)+L7*MIN(30,'0. Supuestos'!$B$58)/30)),"") -> 7916.8747 | N9: =IFERROR(IF('PyG 3 Años'!$B$9="","",SUM(B9:M9)),"") -> 112699.47 | O9: Ventas del mes con el IVA repercutido, corregidas por los días medios de cobro de la hoja de Supuestos
A10: PAGOS
A11: Compras y costes variables (IVA incluido) | B11: =IFERROR(IF('PyG 3 Años'!$B$9="","",-('PyG 3 Años'!$B$13*(1+'PyG 3 Años'!$G$13)+'PyG 3 Años'!$B$14*(1+'PyG 3 Años'!$G$14)+'PyG 3 Años'!$B$15*(1+'PyG 3 Años'!$G$15)+'PyG 3 Años'!$B$16*(1+'PyG 3 Años'!$G$16)+'PyG 3 Años'!$B$17*(1+'PyG 3 Años'!$G$17)+'PyG 3 Años'!$B$18*(1+'PyG 3 Años'!$G$18))*B7*(1-MIN(30,'0. Supuestos'!$B$59)/30)),"") -> 0 | C11: =IFERROR(IF('PyG 3 Años'!$B$9="","",-('PyG 3 Años'!$B$13*(1+'PyG 3 Años'!$G$13)+'PyG 3 Años'!$B$14*(1+'PyG 3 Años'!$G$14)+'PyG 3 Años'!$B$15*(1+'PyG 3 Años'!$G$15)+'PyG 3 Años'!$B$16*(1+'PyG 3 Años'!$G$16)+'PyG 3 Años'!$B$17*(1+'PyG 3 Años'!$G$17)+'PyG 3 Años'!$B$18*(1+'PyG 3 Años'!$G$18))*(C7*(1-MIN(30,'0. Supuestos'!$B$59)/30)+B7*MIN(30,'0. Supuestos'!$B$59)/30)),"") -> -1688.2167 | D11: =IFERROR(IF('PyG 3 Años'!$B$9="","",-('PyG 3 Años'!$B$13*(1+'PyG 3 Años'!$G$13)+'PyG 3 Años'!$B$14*(1+'PyG 3 Años'!$G$14)+'PyG 3 Años'!$B$15*(1+'PyG 3 Años'!$G$15)+'PyG 3 Años'!$B$16*(1+'PyG 3 Años'!$G$16)+'PyG 3 Años'!$B$17*(1+'PyG 3 Años'!$G$17)+'PyG 3 Años'!$B$18*(1+'PyG 3 Años'!$G$18))*(D7*(1-MIN(30,'0. Supuestos'!$B$59)/30)+C7*MIN(30,'0. Supuestos'!$B$59)/30)),"") -> -2138.35 | E11: =IFERROR(IF('PyG 3 Años'!$B$9="","",-('PyG 3 Años'!$B$13*(1+'PyG 3 Años'!$G$13)+'PyG 3 Años'!$B$14*(1+'PyG 3 Años'!$G$14)+'PyG 3 Años'!$B$15*(1+'PyG 3 Años'!$G$15)+'PyG 3 Años'!$B$16*(1+'PyG 3 Años'!$G$16)+'PyG 3 Años'!$B$17*(1+'PyG 3 Años'!$G$17)+'PyG 3 Años'!$B$18*(1+'PyG 3 Años'!$G$18))*(E7*(1-MIN(30,'0. Supuestos'!$B$59)/30)+D7*MIN(30,'0. Supuestos'!$B$59)/30)),"") -> -3102.0114 | F11: =IFERROR(IF('PyG 3 Años'!$B$9="","",-('PyG 3 Años'!$B$13*(1+'PyG 3 Años'!$G$13)+'PyG 3 Años'!$B$14*(1+'PyG 3 Años'!$G$14)+'PyG 3 Años'!$B$15*(1+'PyG 3 Años'!$G$15)+'PyG 3 Años'!$B$16*(1+'PyG 3 Años'!$G$16)+'PyG 3 Años'!$B$17*(1+'PyG 3 Años'!$G$17)+'PyG 3 Años'!$B$18*(1+'PyG 3 Años'!$G$18))*(F7*(1-MIN(30,'0. Supuestos'!$B$59)/30)+E7*MIN(30,'0. Supuestos'!$B$59)/30)),"") -> -3525.8025 | G11: =IFERROR(IF('PyG 3 Años'!$B$9="","",-('PyG 3 Años'!$B$13*(1+'PyG 3 Años'!$G$13)+'PyG 3 Años'!$B$14*(1+'PyG 3 Años'!$G$14)+'PyG 3 Años'!$B$15*(1+'PyG 3 Años'!$G$15)+'PyG 3 Años'!$B$16*(1+'PyG 3 Años'!$G$16)+'PyG 3 Años'!$B$17*(1+'PyG 3 Años'!$G$17)+'PyG 3 Años'!$B$18*(1+'PyG 3 Años'!$G$18))*(G7*(1-MIN(30,'0. Supuestos'!$B$59)/30)+F7*MIN(30,'0. Supuestos'!$B$59)/30)),"") -> -2283.3768 | H11: =IFERROR(IF('PyG 3 Años'!$B$9="","",-('PyG 3 Años'!$B$13*(1+'PyG 3 Años'!$G$13)+'PyG 3 Años'!$B$14*(1+'PyG 3 Años'!$G$14)+'PyG 3 Años'!$B$15*(1+'PyG 3 Años'!$G$15)+'PyG 3 Años'!$B$16*(1+'PyG 3 Años'!$G$16)+'PyG 3 Años'!$B$17*(1+'PyG 3 Años'!$G$17)+'PyG 3 Años'!$B$18*(1+'PyG 3 Años'!$G$18))*(H7*(1-MIN(30,'0. Supuestos'!$B$59)/30)+G7*MIN(30,'0. Supuestos'!$B$59)/30)),"") -> -1433.7684 | I11: =IFERROR(IF('PyG 3 Años'!$B$9="","",-('PyG 3 Años'!$B$13*(1+'PyG 3 Años'!$G$13)+'PyG 3 Años'!$B$14*(1+'PyG 3 Años'!$G$14)+'PyG 3 Años'!$B$15*(1+'PyG 3 Años'!$G$15)+'PyG 3 Años'!$B$16*(1+'PyG 3 Años'!$G$16)+'PyG 3 Años'!$B$17*(1+'PyG 3 Años'!$G$17)+'PyG 3 Años'!$B$18*(1+'PyG 3 Años'!$G$18))*(I7*(1-MIN(30,'0. Supuestos'!$B$59)/30)+H7*MIN(30,'0. Supuestos'!$B$59)/30)),"") -> -4394.2267 | J11: =IFERROR(IF('PyG 3 Años'!$B$9="","",-('PyG 3 Años'!$B$13*(1+'PyG 3 Años'!$G$13)+'PyG 3 Años'!$B$14*(1+'PyG 3 Años'!$G$14)+'PyG 3 Años'!$B$15*(1+'PyG 3 Años'!$G$15)+'PyG 3 Años'!$B$16*(1+'PyG 3 Años'!$G$16)+'PyG 3 Años'!$B$17*(1+'PyG 3 Años'!$G$17)+'PyG 3 Años'!$B$18*(1+'PyG 3 Años'!$G$18))*(J7*(1-MIN(30,'0. Supuestos'!$B$59)/30)+I7*MIN(30,'0. Supuestos'!$B$59)/30)),"") -> -4873.8864 | ... M11: =IFERROR(IF('PyG 3 Años'!$B$9="","",-('PyG 3 Años'!$B$13*(1+'PyG 3 Años'!$G$13)+'PyG 3 Años'!$B$14*(1+'PyG 3 Años'!$G$14)+'PyG 3 Años'!$B$15*(1+'PyG 3 Años'!$G$15)+'PyG 3 Años'!$B$16*(1+'PyG 3 Años'!$G$16)+'PyG 3 Años'!$B$17*(1+'PyG 3 Años'!$G$17)+'PyG 3 Años'!$B$18*(1+'PyG 3 Años'!$G$18))*(M7*(1-MIN(30,'0. Supuestos'!$B$59)/30)+L7*MIN(30,'0. Supuestos'!$B$59)/30)),"") -> -1991.5863 | N11: =IFERROR(IF('PyG 3 Años'!$B$9="","",SUM(B11:M11)),"") -> -32795.463 | O11: =IFERROR("Materia prima, consumibles, comisiones e imprevistos, cada uno con SU tipo de IVA (la columna del P&L) y con los días de pago a proveedor de Supuestos."&IF('0. Supuestos'!$B$59=0,""," Con "&TEXT('0. Supuestos'!$B$59,"0")&" días de pago, las primeras compras se pagan ya en el año siguiente: la columna «Año» de esta fila recoge "&TEXT(MAX(0,12-ROUNDUP('0. Supuestos'!$B$59/30,0)),"0")&" mensualidades de compra, no el coste del ejercicio."),"") -> Materia prima, consumibles, comisiones e imprevistos, cada uno con SU tipo de IVA (la columna del P&L) y con los días de pago a proveedor de Supuestos. Con 30 días de pago, las primeras compras se pagan ya en el año siguiente: la columna «Año» de esta fila recoge 11 mensualidades de compra, no el coste del ejercicio.
A12: Costes fijos de explotación (IVA incluido) | B12: =IFERROR(IF('PyG 3 Años'!$B$9="","",-('PyG 3 Años'!$B$38-'PyG 3 Años'!$B$23-'PyG 3 Años'!$B$36-'PyG 3 Años'!$B$37+'PyG 3 Años'!$B$40)/12),"") -> -1459.5 | C12: =IFERROR(IF('PyG 3 Años'!$B$9="","",-('PyG 3 Años'!$B$38-'PyG 3 Años'!$B$23-'PyG 3 Años'!$B$36-'PyG 3 Años'!$B$37+'PyG 3 Años'!$B$40)/12),"") -> -1459.5 | D12: =IFERROR(IF('PyG 3 Años'!$B$9="","",-('PyG 3 Años'!$B$38-'PyG 3 Años'!$B$23-'PyG 3 Años'!$B$36-'PyG 3 Años'!$B$37+'PyG 3 Años'!$B$40)/12),"") -> -1459.5 | E12: =IFERROR(IF('PyG 3 Años'!$B$9="","",-('PyG 3 Años'!$B$38-'PyG 3 Años'!$B$23-'PyG 3 Años'!$B$36-'PyG 3 Años'!$B$37+'PyG 3 Años'!$B$40)/12),"") -> -1459.5 | F12: =IFERROR(IF('PyG 3 Años'!$B$9="","",-('PyG 3 Años'!$B$38-'PyG 3 Años'!$B$23-'PyG 3 Años'!$B$36-'PyG 3 Años'!$B$37+'PyG 3 Años'!$B$40)/12),"") -> -1459.5 | G12: =IFERROR(IF('PyG 3 Años'!$B$9="","",-('PyG 3 Años'!$B$38-'PyG 3 Años'!$B$23-'PyG 3 Años'!$B$36-'PyG 3 Años'!$B$37+'PyG 3 Años'!$B$40)/12),"") -> -1459.5 | H12: =IFERROR(IF('PyG 3 Años'!$B$9="","",-('PyG 3 Años'!$B$38-'PyG 3 Años'!$B$23-'PyG 3 Años'!$B$36-'PyG 3 Años'!$B$37+'PyG 3 Años'!$B$40)/12),"") -> -1459.5 | I12: =IFERROR(IF('PyG 3 Años'!$B$9="","",-('PyG 3 Años'!$B$38-'PyG 3 Años'!$B$23-'PyG 3 Años'!$B$36-'PyG 3 Años'!$B$37+'PyG 3 Años'!$B$40)/12),"") -> -1459.5 | ... M12: =IFERROR(IF('PyG 3 Años'!$B$9="","",-('PyG 3 Años'!$B$38-'PyG 3 Años'!$B$23-'PyG 3 Años'!$B$36-'PyG 3 Años'!$B$37+'PyG 3 Años'!$B$40)/12),"") -> -1459.5 | N12: =IFERROR(IF('PyG 3 Años'!$B$9="","",SUM(B12:M12)),"") -> -17514 | O12: Los fijos que salen de caja, cada uno con su tipo de IVA: los seguros están exentos y no llevan
A13: Nóminas y Seguridad Social | B13: =IFERROR(IF('PyG 3 Años'!$B$9="","",-'PyG 3 Años'!$B$23/MAX(12,'0. Supuestos'!$B$21)*(1+IF(1='0. Supuestos'!$B$60,(MAX(12,'0. Supuestos'!$B$21)-12)/2,0)+IF(1='0. Supuestos'!$B$61,(MAX(12,'0. Supuestos'!$B$21)-12)/2,0))),"") -> -3213.28 | C13: =IFERROR(IF('PyG 3 Años'!$B$9="","",-'PyG 3 Años'!$B$23/MAX(12,'0. Supuestos'!$B$21)*(1+IF(2='0. Supuestos'!$B$60,(MAX(12,'0. Supuestos'!$B$21)-12)/2,0)+IF(2='0. Supuestos'!$B$61,(MAX(12,'0. Supuestos'!$B$21)-12)/2,0))),"") -> -3213.28 | D13: =IFERROR(IF('PyG 3 Años'!$B$9="","",-'PyG 3 Años'!$B$23/MAX(12,'0. Supuestos'!$B$21)*(1+IF(3='0. Supuestos'!$B$60,(MAX(12,'0. Supuestos'!$B$21)-12)/2,0)+IF(3='0. Supuestos'!$B$61,(MAX(12,'0. Supuestos'!$B$21)-12)/2,0))),"") -> -3213.28 | E13: =IFERROR(IF('PyG 3 Años'!$B$9="","",-'PyG 3 Años'!$B$23/MAX(12,'0. Supuestos'!$B$21)*(1+IF(4='0. Supuestos'!$B$60,(MAX(12,'0. Supuestos'!$B$21)-12)/2,0)+IF(4='0. Supuestos'!$B$61,(MAX(12,'0. Supuestos'!$B$21)-12)/2,0))),"") -> -3213.28 | F13: =IFERROR(IF('PyG 3 Años'!$B$9="","",-'PyG 3 Años'!$B$23/MAX(12,'0. Supuestos'!$B$21)*(1+IF(5='0. Supuestos'!$B$60,(MAX(12,'0. Supuestos'!$B$21)-12)/2,0)+IF(5='0. Supuestos'!$B$61,(MAX(12,'0. Supuestos'!$B$21)-12)/2,0))),"") -> -6426.56 | G13: =IFERROR(IF('PyG 3 Años'!$B$9="","",-'PyG 3 Años'!$B$23/MAX(12,'0. Supuestos'!$B$21)*(1+IF(6='0. Supuestos'!$B$60,(MAX(12,'0. Supuestos'!$B$21)-12)/2,0)+IF(6='0. Supuestos'!$B$61,(MAX(12,'0. Supuestos'!$B$21)-12)/2,0))),"") -> -3213.28 | H13: =IFERROR(IF('PyG 3 Años'!$B$9="","",-'PyG 3 Años'!$B$23/MAX(12,'0. Supuestos'!$B$21)*(1+IF(7='0. Supuestos'!$B$60,(MAX(12,'0. Supuestos'!$B$21)-12)/2,0)+IF(7='0. Supuestos'!$B$61,(MAX(12,'0. Supuestos'!$B$21)-12)/2,0))),"") -> -3213.28 | I13: =IFERROR(IF('PyG 3 Años'!$B$9="","",-'PyG 3 Años'!$B$23/MAX(12,'0. Supuestos'!$B$21)*(1+IF(8='0. Supuestos'!$B$60,(MAX(12,'0. Supuestos'!$B$21)-12)/2,0)+IF(8='0. Supuestos'!$B$61,(MAX(12,'0. Supuestos'!$B$21)-12)/2,0))),"") -> -3213.28 | J13: =IFERROR(IF('PyG 3 Años'!$B$9="","",-'PyG 3 Años'!$B$23/MAX(12,'0. Supuestos'!$B$21)*(1+IF(9='0. Supuestos'!$B$60,(MAX(12,'0. Supuestos'!$B$21)-12)/2,0)+IF(9='0. Supuestos'!$B$61,(MAX(12,'0. Supuestos'!$B$21)-12)/2,0))),"") -> -3213.28 | K13: =IFERROR(IF('PyG 3 Años'!$B$9="","",-'PyG 3 Años'!$B$23/MAX(12,'0. Supuestos'!$B$21)*(1+IF(10='0. Supuestos'!$B$60,(MAX(12,'0. Supuestos'!$B$21)-12)/2,0)+IF(10='0. Supuestos'!$B$61,(MAX(12,'0. Supuestos'!$B$21)-12)/2,0))),"") -> -6426.56 | L13: =IFERROR(IF('PyG 3 Años'!$B$9="","",-'PyG 3 Años'!$B$23/MAX(12,'0. Supuestos'!$B$21)*(1+IF(11='0. Supuestos'!$B$60,(MAX(12,'0. Supuestos'!$B$21)-12)/2,0)+IF(11='0. Supuestos'!$B$61,(MAX(12,'0. Supuestos'!$B$21)-12)/2,0))),"") -> -3213.28 | M13: =IFERROR(IF('PyG 3 Años'!$B$9="","",-'PyG 3 Años'!$B$23/MAX(12,'0. Supuestos'!$B$21)*(1+IF(12='0. Supuestos'!$B$60,(MAX(12,'0. Supuestos'!$B$21)-12)/2,0)+IF(12='0. Supuestos'!$B$61,(MAX(12,'0. Supuestos'!$B$21)-12)/2,0))),"") -> -3213.28 | N13: =IFERROR(IF('PyG 3 Años'!$B$9="","",SUM(B13:M13)),"") -> -44985.92 | O13: Doce mensualidades más las pagas extra en los meses que digas en Supuestos. La suma del año es la misma que la del P&L. El personal se reparte en doce meses, pero los fijos discontinuos sólo trabajan en los meses con eventos: aquí la temporada sale algo más barata y el invierno algo más caro que en la realidad
A14: Intereses del préstamo | B14: =IFERROR(IF('PyG 3 Años'!$B$9="","",-'Financiación'!$B$44/12),"") -> -241.04167 | C14: =IFERROR(IF('PyG 3 Años'!$B$9="","",-'Financiación'!$B$44/12),"") -> -241.04167 | D14: =IFERROR(IF('PyG 3 Años'!$B$9="","",-'Financiación'!$B$44/12),"") -> -241.04167 | E14: =IFERROR(IF('PyG 3 Años'!$B$9="","",-'Financiación'!$B$44/12),"") -> -241.04167 | F14: =IFERROR(IF('PyG 3 Años'!$B$9="","",-'Financiación'!$B$44/12),"") -> -241.04167 | G14: =IFERROR(IF('PyG 3 Años'!$B$9="","",-'Financiación'!$B$44/12),"") -> -241.04167 | H14: =IFERROR(IF('PyG 3 Años'!$B$9="","",-'Financiación'!$B$44/12),"") -> -241.04167 | I14: =IFERROR(IF('PyG 3 Años'!$B$9="","",-'Financiación'!$B$44/12),"") -> -241.04167 | ... M14: =IFERROR(IF('PyG 3 Años'!$B$9="","",-'Financiación'!$B$44/12),"") -> -241.04167 | N14: =IFERROR(IF('PyG 3 Años'!$B$9="","",SUM(B14:M14)),"") -> -2892.5
A15: Devolución de principal del préstamo | B15: =IFERROR(IF('PyG 3 Años'!$B$9="","",-'Financiación'!$B$45/12),"") -> 0 | C15: =IFERROR(IF('PyG 3 Años'!$B$9="","",-'Financiación'!$B$45/12),"") -> 0 | D15: =IFERROR(IF('PyG 3 Años'!$B$9="","",-'Financiación'!$B$45/12),"") -> 0 | E15: =IFERROR(IF('PyG 3 Años'!$B$9="","",-'Financiación'!$B$45/12),"") -> 0 | F15: =IFERROR(IF('PyG 3 Años'!$B$9="","",-'Financiación'!$B$45/12),"") -> 0 | G15: =IFERROR(IF('PyG 3 Años'!$B$9="","",-'Financiación'!$B$45/12),"") -> 0 | H15: =IFERROR(IF('PyG 3 Años'!$B$9="","",-'Financiación'!$B$45/12),"") -> 0 | I15: =IFERROR(IF('PyG 3 Años'!$B$9="","",-'Financiación'!$B$45/12),"") -> 0 | ... M15: =IFERROR(IF('PyG 3 Años'!$B$9="","",-'Financiación'!$B$45/12),"") -> 0 | N15: =IFERROR(IF('PyG 3 Años'!$B$9="","",SUM(B15:M15)),"") -> 0
A16: IVA repercutido del mes (memoria) | B16: =IFERROR(IF('PyG 3 Años'!$B$9="","",'PyG 3 Años'!$B$9*B7*SUMPRODUCT('PyG 3 Años'!$E$10:$E$11,'PyG 3 Años'!$G$10:$G$11)),"") -> 511.04501 | C16: =IFERROR(IF('PyG 3 Años'!$B$9="","",'PyG 3 Años'!$B$9*C7*SUMPRODUCT('PyG 3 Años'!$E$10:$E$11,'PyG 3 Años'!$G$10:$G$11)),"") -> 647.30615 | D16: =IFERROR(IF('PyG 3 Años'!$B$9="","",'PyG 3 Años'!$B$9*D7*SUMPRODUCT('PyG 3 Años'!$E$10:$E$11,'PyG 3 Años'!$G$10:$G$11)),"") -> 939.01892 | E16: =IFERROR(IF('PyG 3 Años'!$B$9="","",'PyG 3 Años'!$B$9*E7*SUMPRODUCT('PyG 3 Años'!$E$10:$E$11,'PyG 3 Años'!$G$10:$G$11)),"") -> 1067.3059 | F16: =IFERROR(IF('PyG 3 Años'!$B$9="","",'PyG 3 Años'!$B$9*F7*SUMPRODUCT('PyG 3 Años'!$E$10:$E$11,'PyG 3 Años'!$G$10:$G$11)),"") -> 691.20765 | G16: =IFERROR(IF('PyG 3 Años'!$B$9="","",'PyG 3 Años'!$B$9*G7*SUMPRODUCT('PyG 3 Años'!$E$10:$E$11,'PyG 3 Años'!$G$10:$G$11)),"") -> 434.02022 | H16: =IFERROR(IF('PyG 3 Años'!$B$9="","",'PyG 3 Años'!$B$9*H7*SUMPRODUCT('PyG 3 Años'!$E$10:$E$11,'PyG 3 Años'!$G$10:$G$11)),"") -> 1330.1892 | I16: =IFERROR(IF('PyG 3 Años'!$B$9="","",'PyG 3 Años'!$B$9*I7*SUMPRODUCT('PyG 3 Años'!$E$10:$E$11,'PyG 3 Años'!$G$10:$G$11)),"") -> 1475.3883 | ... M16: =IFERROR(IF('PyG 3 Años'!$B$9="","",'PyG 3 Años'!$B$9*M7*SUMPRODUCT('PyG 3 Años'!$E$10:$E$11,'PyG 3 Años'!$G$10:$G$11)),"") -> 953.38987 | N16: =IFERROR(IF('PyG 3 Años'!$B$9="","",SUM(B16:M16)),"") -> 10881 | O16: Cada línea de venta a SU tipo, leído de la columna de IVA del P&L: las bebidas y la bollería, en la barra del evento y en la venta directa de ferias y mercados, al reducido del 10 % (art. 91.Uno.2.2.º de la Ley 37/1992)
A17: IVA soportado del mes (memoria) | B17: =IFERROR(IF('PyG 3 Años'!$B$9="","",'PyG 3 Años'!$B$39*B7+'PyG 3 Años'!$B$40/12),"") -> 432.5095 | C17: =IFERROR(IF('PyG 3 Años'!$B$9="","",'PyG 3 Años'!$B$39*C7+'PyG 3 Años'!$B$40/12),"") -> 485.30524 | D17: =IFERROR(IF('PyG 3 Años'!$B$9="","",'PyG 3 Años'!$B$39*D7+'PyG 3 Años'!$B$40/12),"") -> 598.33227 | E17: =IFERROR(IF('PyG 3 Años'!$B$9="","",'PyG 3 Años'!$B$39*E7+'PyG 3 Años'!$B$40/12),"") -> 648.03836 | F17: =IFERROR(IF('PyG 3 Años'!$B$9="","",'PyG 3 Años'!$B$39*F7+'PyG 3 Años'!$B$40/12),"") -> 502.31532 | G17: =IFERROR(IF('PyG 3 Años'!$B$9="","",'PyG 3 Años'!$B$39*G7+'PyG 3 Años'!$B$40/12),"") -> 402.66548 | H17: =IFERROR(IF('PyG 3 Años'!$B$9="","",'PyG 3 Años'!$B$39*H7+'PyG 3 Años'!$B$40/12),"") -> 749.8951 | I17: =IFERROR(IF('PyG 3 Años'!$B$9="","",'PyG 3 Años'!$B$39*I7+'PyG 3 Años'!$B$40/12),"") -> 806.15397 | ... M17: =IFERROR(IF('PyG 3 Años'!$B$9="","",'PyG 3 Años'!$B$39*M7+'PyG 3 Años'!$B$40/12),"") -> 603.90044 | N17: =IFERROR(IF('PyG 3 Años'!$B$9="","",SUM(B17:M17)),"") -> 7029.9523 | O17: Cada partida a su tipo, leído de la columna de IVA del P&L: los seguros y las comisiones de los medios de pago están exentos
A18: IVA a compensar arrastrado (inversión incluida) | E18: =IFERROR(IF('PyG 3 Años'!$B$9="","",'Inversión Inicial'!$B$28),"") -> 8949.36 | H18: =IFERROR(IF('PyG 3 Años'!$B$9="","",MAX(0,-E19)),"") -> 8368.1369 | K18: =IFERROR(IF('PyG 3 Años'!$B$9="","",MAX(0,-H19)),"") -> 7728.6223 | O18: El IVA soportado de la INVERSIÓN entra aquí: se compensa contra el repercutido de los trimestres siguientes hasta agotarlo (modelo 303)
A19: Resultado de la liquidación trimestral | E19: =IFERROR(IF('PyG 3 Años'!$B$9="","",SUM(B16:D16)-SUM(B17:D17)-E18),"") -> -8368.1369 | H19: =IFERROR(IF('PyG 3 Años'!$B$9="","",SUM(E16:G16)-SUM(E17:G17)-H18),"") -> -7728.6223 | K19: =IFERROR(IF('PyG 3 Años'!$B$9="","",SUM(H16:J16)-SUM(H17:J17)-K18),"") -> -5940.6666 | O19: Repercutido menos soportado del trimestre menos lo que venía arrastrado. En negativo NO se paga: se compensa en el trimestre siguiente
A20: Pago del IVA (modelo 303) | E20: =IFERROR(IF('PyG 3 Años'!$B$9="","",IF(E19<=0,"",-E19)),"") | H20: =IFERROR(IF('PyG 3 Años'!$B$9="","",IF(H19<=0,"",-H19)),"") | K20: =IFERROR(IF('PyG 3 Años'!$B$9="","",IF(K19<=0,"",-K19)),"") | N20: =IFERROR(IF('PyG 3 Años'!$B$9="","",SUM(B20:M20)),"") -> 0 | O20: Sólo sale caja cuando el resultado del trimestre es positivo. Los meses sin liquidación van en blanco, no a cero. La celda se pinta en ROJO cuando el pago del 303 se lleva más caja de la que queda ese mes
A21: FLUJO DEL MES | B21: =IFERROR(IF('PyG 3 Años'!$B$9="","",SUM(B9:B15)+IF(B20="",0,B20)),"") -> -3039.99 | C21: =IFERROR(IF('PyG 3 Años'!$B$9="","",SUM(C9:C15)+IF(C20="",0,C20)),"") -> -480.91911 | D21: =IFERROR(IF('PyG 3 Años'!$B$9="","",SUM(D9:D15)+IF(D20="",0,D20)),"") -> 1137.8095 | E21: =IFERROR(IF('PyG 3 Años'!$B$9="","",SUM(E9:E15)+IF(E20="",0,E20)),"") -> 2783.7607 | F21: =IFERROR(IF('PyG 3 Años'!$B$9="","",SUM(F9:F15)+IF(F20="",0,F20)),"") -> -1291.5659 | G21: =IFERROR(IF('PyG 3 Años'!$B$9="","",SUM(G9:G15)+IF(G20="",0,G20)),"") -> -536.93489 | H21: =IFERROR(IF('PyG 3 Años'!$B$9="","",SUM(H9:H15)+IF(H20="",0,H20)),"") -> 1712.5851 | I21: =IFERROR(IF('PyG 3 Años'!$B$9="","",SUM(I9:I15)+IF(I20="",0,I20)),"") -> 5856.4295 | ... M21: =IFERROR(IF('PyG 3 Años'!$B$9="","",SUM(M9:M15)+IF(M20="",0,M20)),"") -> 1011.4667 | N21: =IFERROR(IF('PyG 3 Años'!$B$9="","",SUM(B21:M21)),"") -> 14511.591
A22: SALDO ACUMULADO DE CAJA | B22: =IFERROR(IF('PyG 3 Años'!$B$9="","",'Inversión Inicial'!$B$25+B21),"") -> 12604.615 | C22: =IFERROR(IF('PyG 3 Años'!$B$9="","",B22+C21),"") -> 12123.696 | D22: =IFERROR(IF('PyG 3 Años'!$B$9="","",C22+D21),"") -> 13261.505 | E22: =IFERROR(IF('PyG 3 Años'!$B$9="","",D22+E21),"") -> 16045.266 | F22: =IFERROR(IF('PyG 3 Años'!$B$9="","",E22+F21),"") -> 14753.7 | G22: =IFERROR(IF('PyG 3 Años'!$B$9="","",F22+G21),"") -> 14216.765 | H22: =IFERROR(IF('PyG 3 Años'!$B$9="","",G22+H21),"") -> 15929.351 | I22: =IFERROR(IF('PyG 3 Años'!$B$9="","",H22+I21),"") -> 21785.78 | J22: =IFERROR(IF('PyG 3 Años'!$B$9="","",I22+J21),"") -> 27444.331 | ... M22: =IFERROR(IF('PyG 3 Años'!$B$9="","",L22+M21),"") -> 30156.196
A23: Saldo mínimo del año | B23: =IFERROR(IF('PyG 3 Años'!$B$9="","",IF(COUNT(B22:M22)=0,"",MIN(B22:M22))),"") -> 12123.696 | D23: Si es negativo, sube el fondo de maniobra o el préstamo: te quedas sin caja
A24: Mes en el que la caja toca fondo | B24: =IFERROR(IF('PyG 3 Años'!$B$9="","",IF(COUNT(B22:M22)=0,"",MATCH(MIN(B22:M22),B22:M22,0))),"") -> 2 | D24: Es la respuesta a la pregunta que decide una operación bancaria: en qué mes se agota la caja
A25: RETORNO DE LA INVERSIÓN
A26: Flujo de caja libre antes de la deuda, año 1 | B26: =IFERROR(IF('PyG 3 Años'!$B$9="","",'PyG 3 Años'!$B$48+'PyG 3 Años'!$B$36+'Financiación'!$B$44),"") -> 15834.996 | D26: Resultado neto más amortización (que no se paga) más los intereses de ese año: el principal no se resta porque este flujo es ANTES de la deuda. La MISMA base que los años 2 y 3, para que el payback compare peras con peras
A27: Flujo de caja libre antes de la deuda, año 2 | B27: =IFERROR(IF('PyG 3 Años'!$B$9="","",'PyG 3 Años'!$C$48+'PyG 3 Años'!$C$36+'Financiación'!$B$46),"") -> 17286.882 | D27: Resultado neto más amortización (que no se paga) más los intereses de ese año: el principal no se resta porque este flujo es ANTES de la deuda. Sin tabla mensual, es una estimación
A28: Flujo de caja libre antes de la deuda, año 3 | B28: =IFERROR(IF('PyG 3 Años'!$B$9="","",'PyG 3 Años'!$D$48+'PyG 3 Años'!$D$36+'Financiación'!$B$48),"") -> 16536.354 | D28: Resultado neto más amortización (que no se paga) más los intereses de ese año: el principal no se resta porque este flujo es ANTES de la deuda. Sin tabla mensual, es una estimación
A29: Informativo: flujo REAL de caja del año 1 (tabla mensual, antes de la deuda) | B29: =IFERROR(IF('PyG 3 Años'!$B$9="","",N21+'Financiación'!$B$44+'Financiación'!$B$45),"") -> 17404.091 | D29: La suma de los doce FLUJO DEL MES de arriba, devolviéndole los intereses y el principal que se pagaron ese año. NO es la que usa el payback: lleva dentro el IVA que todavía no se ha liquidado y el crédito del proveedor, dos cosas que hay que devolver y que los años 2 y 3 no tienen
A30: Inversión a recuperar (sin el IVA, que se recupera por el 303) | B30: =IFERROR(IF('PyG 3 Años'!$B$9="","",'Inversión Inicial'!$B$29-'Inversión Inicial'!$B$28),"") -> 60060.605 | D30: CAPEX más fondo de maniobra: la necesidad total de caja MENOS el IVA soportado de la inversión, que no se pierde (se recupera con el modelo 303 y esta misma hoja lo compensa trimestre a trimestre). El fondo de maniobra sí se recupera al cerrar, pero hasta entonces está inmovilizado
A31: Payback del proyecto (años), antes de la deuda | B31: =IFERROR(IF('PyG 3 Años'!$B$9="","",IF(B26>=B30,ROUND(B30/B26,1),IF(B26+B27>=B30,ROUND(1+(B30-B26)/B27,1),IF(B26+B27+B28>=B30,ROUND(2+(B30-B26-B27)/B28,1),"Más de 3 años")))),"") -> Más de 3 años | D31: Mide cuánto tarda el negocio en devolver la inversión con lo que genera ANTES de pagar al banco, con la MISMA base de flujo en los tres años; si puedes pagar la cuota lo dice el DSCR de la hoja de Financiación. El plan de negocio en Word cita esta cifra; si cambias una celda verde, manda este libro
A32: Payback sobre el CAPEX, sin fondo de maniobra (años) | B32: =IFERROR(IF('PyG 3 Años'!$B$9="","",IF(B26>='Inversión Inicial'!$B$27,ROUND('Inversión Inicial'!$B$27/B26,1),IF(B26+B27>='Inversión Inicial'!$B$27,ROUND(1+('Inversión Inicial'!$B$27-B26)/B27,1),IF(B26+B27+B28>='Inversión Inicial'!$B$27,ROUND(2+('Inversión Inicial'!$B$27-B26-B27)/B28,1),"Más de 3 años")))),"") -> 2.7 | D32: El mismo cálculo sobre lo que se COMPRA (furgoneta, equipamiento, lanzamiento y constitución), sin el fondo de maniobra: ese dinero no se gasta, se inmoviliza y vuelve al cerrar el negocio. Informativo: el payback que se publica es el de arriba
A34: Los trimestres de esta hoja son de tres meses del plan (marzo-mayo, junio-agosto y septiembre-noviembre), no los naturales: con el Mes 1 en marzo, el modelo 303 se presenta en abril (por marzo), julio, octubre y enero (por octubre-diciembre, ya en el Mes 11). El IVA de la inversión se descuenta del que repercutes en las primeras liquidaciones. El Impuesto de Sociedades del año 1 se paga en julio del año 2. La cuota del préstamo se reparte en doce partes iguales siguiendo el cuadro ANUAL de la hoja de Financiación, y las nóminas en doce mensualidades más las dos pagas extra en su mes.

Sheet Financiación
A1: PLAN DE FINANCIACIÓN
A2: Qué hace falta, de dónde sale y cuánto cuesta devolverlo. Es la hoja que el banco pide junto con el P&L.
A4: Concepto | B4: Importe | C4: Notas
A5: ORIGEN DE FONDOS
A6: Recursos propios de los socios | B6: =IFERROR(IF('0. Supuestos'!$B$30="","",'0. Supuestos'!$B$30),"") -> 25000
A7: Préstamo bancario | B7: =IFERROR(IF('0. Supuestos'!$B$31="","",'0. Supuestos'!$B$31),"") -> 44500
A8: Línea ICO (avalada por el ICO, la concede tu banco) | B8: 0 | C8: Consulta las líneas del ejercicio en curso en ico.es
A9: Préstamo participativo ENISA | B9: 0 | C9: Para sociedades; sin garantías personales
A10: Business angels o socios inversores | B10: 0 | C10: Entra en el capital: diluye, no se devuelve
A11: Subvenciones autonómicas o locales | B11: 0 | C11: Suelen cobrarse DESPUÉS de justificar el gasto
A12: TOTAL ORIGEN DE FONDOS | B12: =IFERROR(IF(COUNT(B6:B11)=0,"",SUM(B6:B11)),"") -> 69500
A13: USOS
A14: Necesidad total de caja al arranque | B14: =IFERROR(IF('Inversión Inicial'!$B$29="","",'Inversión Inicial'!$B$29),"") -> 69009.965 | C14: Inversión más el IVA que hay que adelantar
A15: Diferencia (origen - usos) | B15: =IFERROR(B12-B14,"") -> 490.035 | C15: En rojo (negativa) el plan NO está financiado. Muy por encima de cero tampoco es gratis: se pagan intereses por un dinero que no se usa
A16: Diferencia sobre los usos (%) | B16: =IFERROR(B15/B14,"") -> 0.007100931 | C16: Ámbar por encima del margen que fijes: es deuda que pagas sin necesitarla
A17: Exceso de financiación admisible (%) | B17: 0.05 | C17: Un pequeño colchón sobre la necesidad es sano; un 20 % de más son intereses tirados
A18: Préstamo que ajustaría el origen a la necesidad | B18: =IFERROR(MAX(0,B14-B12+B7),"") -> 44009.965 | C18: Cópialo en «Préstamo bancario solicitado» de la hoja de Supuestos y la diferencia se pone a cero
A19: CONDICIONES DEL PRÉSTAMO
A20: Importe del principal | B20: =IFERROR(IF('0. Supuestos'!$B$31=0,"",'0. Supuestos'!$B$31),"") -> 44500
A21: Tipo de interés nominal anual | B21: =IFERROR(IF('0. Supuestos'!$B$32="","",'0. Supuestos'!$B$32),"") -> 0.065
A22: Plazo total (años) | B22: =IFERROR(IF('0. Supuestos'!$B$33="","",'0. Supuestos'!$B$33),"") -> 6
A23: Carencia de principal aplicada (años) | B23: =IFERROR(IF(OR('0. Supuestos'!$B$34="",'0. Supuestos'!$B$33=""),"",IF('0. Supuestos'!$B$34>='0. Supuestos'!$B$33,0,'0. Supuestos'!$B$34)),"") -> 1 | C23: Una carencia igual o mayor que el plazo no existe: la hoja la anula en origen
A24: Cuota anual durante la amortización | B24: =IFERROR(IF(B22-B23<=0,"",IF(B21=0,B20/(B22-B23),B20*B21/(1-(1+B21)^-(B22-B23)))),"") -> 10708.237 | C24: Sistema francés, anualidad algebraica. Con el tipo al 0 % es el principal entre los años de amortización: sin esa rama el cuadro se apagaba entero
A25: CUADRO DE AMORTIZACIÓN
A26: Año | B26: Capital pendiente | C26: Intereses | D26: Amortización de principal | E26: Cuota total | F26: Capital al cierre | G26: Flujo disponible para la deuda (después de impuestos; del año 4 en adelante, el del año 3 mantenido) | H26: DSCR del año
A27: 1 | B27: =IFERROR(IF(B20="","",B20),"") -> 44500 | C27: =IFERROR(IF(OR(1>B22,B27=""),"",B27*B21),"") -> 2892.5 | D27: =IFERROR(IF(OR(1>B22,B27=""),"",IF(1<=B23,0,MIN(B27,B24-C27))),"") -> 0 | E27: =IFERROR(IF(C27="","",C27+D27),"") -> 2892.5 | F27: =IFERROR(IF(D27="","",B27-D27),"") -> 44500 | G27: =IFERROR(IF(E27="","",'PyG 3 Años'!$B$41-'PyG 3 Años'!$B$46+'PyG 3 Años'!$B$36+'PyG 3 Años'!$B$37),"") -> 15834.996 | H27: =IFERROR(IF(OR(E27="",E27=0),"",G27/E27),"") -> 5.4745018
A28: 2 | B28: =IFERROR(IF(OR(2>B22,F27=""),"",F27),"") -> 44500 | C28: =IFERROR(IF(OR(2>B22,B28=""),"",B28*B21),"") -> 2892.5 | D28: =IFERROR(IF(OR(2>B22,B28=""),"",IF(2<=B23,0,MIN(B28,B24-C28))),"") -> 7815.7369 | E28: =IFERROR(IF(C28="","",C28+D28),"") -> 10708.237 | F28: =IFERROR(IF(D28="","",B28-D28),"") -> 36684.263 | G28: =IFERROR(IF(E28="","",'PyG 3 Años'!$C$41-'PyG 3 Años'!$C$46+'PyG 3 Años'!$C$36+'PyG 3 Años'!$C$37),"") -> 17286.882 | H28: =IFERROR(IF(OR(E28="",E28=0),"",G28/E28),"") -> 1.6143537
A29: 3 | B29: =IFERROR(IF(OR(3>B22,F28=""),"",F28),"") -> 36684.263 | C29: =IFERROR(IF(OR(3>B22,B29=""),"",B29*B21),"") -> 2384.4771 | D29: =IFERROR(IF(OR(3>B22,B29=""),"",IF(3<=B23,0,MIN(B29,B24-C29))),"") -> 8323.7598 | E29: =IFERROR(IF(C29="","",C29+D29),"") -> 10708.237 | F29: =IFERROR(IF(D29="","",B29-D29),"") -> 28360.503 | G29: =IFERROR(IF(E29="","",'PyG 3 Años'!$D$41-'PyG 3 Años'!$D$46+'PyG 3 Años'!$D$36+'PyG 3 Años'!$D$37),"") -> 16536.354 | H29: =IFERROR(IF(OR(E29="",E29=0),"",G29/E29),"") -> 1.5442648
A30: 4 | B30: =IFERROR(IF(OR(4>B22,F29=""),"",F29),"") -> 28360.503 | C30: =IFERROR(IF(OR(4>B22,B30=""),"",B30*B21),"") -> 1843.4327 | D30: =IFERROR(IF(OR(4>B22,B30=""),"",IF(4<=B23,0,MIN(B30,B24-C30))),"") -> 8864.8042 | E30: =IFERROR(IF(C30="","",C30+D30),"") -> 10708.237 | F30: =IFERROR(IF(D30="","",B30-D30),"") -> 19495.699 | G30: =IFERROR(IF(E30="","",'PyG 3 Años'!$D$41-'PyG 3 Años'!$D$46+'PyG 3 Años'!$D$36+'PyG 3 Años'!$D$37),"") -> 16536.354 | H30: =IFERROR(IF(OR(E30="",E30=0),"",G30/E30),"") -> 1.5442648
A31: 5 | B31: =IFERROR(IF(OR(5>B22,F30=""),"",F30),"") -> 19495.699 | C31: =IFERROR(IF(OR(5>B22,B31=""),"",B31*B21),"") -> 1267.2204 | D31: =IFERROR(IF(OR(5>B22,B31=""),"",IF(5<=B23,0,MIN(B31,B24-C31))),"") -> 9441.0165 | E31: =IFERROR(IF(C31="","",C31+D31),"") -> 10708.237 | F31: =IFERROR(IF(D31="","",B31-D31),"") -> 10054.683 | G31: =IFERROR(IF(E31="","",'PyG 3 Años'!$D$41-'PyG 3 Años'!$D$46+'PyG 3 Años'!$D$36+'PyG 3 Años'!$D$37),"") -> 16536.354 | H31: =IFERROR(IF(OR(E31="",E31=0),"",G31/E31),"") -> 1.5442648
A32: 6 | B32: =IFERROR(IF(OR(6>B22,F31=""),"",F31),"") -> 10054.683 | C32: =IFERROR(IF(OR(6>B22,B32=""),"",B32*B21),"") -> 653.55437 | D32: =IFERROR(IF(OR(6>B22,B32=""),"",IF(6<=B23,0,MIN(B32,B24-C32))),"") -> 10054.683 | E32: =IFERROR(IF(C32="","",C32+D32),"") -> 10708.237 | F32: =IFERROR(IF(D32="","",B32-D32),"") -> 0 | G32: =IFERROR(IF(E32="","",'PyG 3 Años'!$D$41-'PyG 3 Años'!$D$46+'PyG 3 Años'!$D$36+'PyG 3 Años'!$D$37),"") -> 16536.354 | H32: =IFERROR(IF(OR(E32="",E32=0),"",G32/E32),"") -> 1.5442648
A33: 7 | B33: =IFERROR(IF(OR(7>B22,F32=""),"",F32),"") | C33: =IFERROR(IF(OR(7>B22,B33=""),"",B33*B21),"") | D33: =IFERROR(IF(OR(7>B22,B33=""),"",IF(7<=B23,0,MIN(B33,B24-C33))),"") | E33: =IFERROR(IF(C33="","",C33+D33),"") | F33: =IFERROR(IF(D33="","",B33-D33),"") | G33: =IFERROR(IF(E33="","",'PyG 3 Años'!$D$41-'PyG 3 Años'!$D$46+'PyG 3 Años'!$D$36+'PyG 3 Años'!$D$37),"") | H33: =IFERROR(IF(OR(E33="",E33=0),"",G33/E33),"")
A34: 8 | B34: =IFERROR(IF(OR(8>B22,F33=""),"",F33),"") | C34: =IFERROR(IF(OR(8>B22,B34=""),"",B34*B21),"") | D34: =IFERROR(IF(OR(8>B22,B34=""),"",IF(8<=B23,0,MIN(B34,B24-C34))),"") | E34: =IFERROR(IF(C34="","",C34+D34),"") | F34: =IFERROR(IF(D34="","",B34-D34),"") | G34: =IFERROR(IF(E34="","",'PyG 3 Años'!$D$41-'PyG 3 Años'!$D$46+'PyG 3 Años'!$D$36+'PyG 3 Años'!$D$37),"") | H34: =IFERROR(IF(OR(E34="",E34=0),"",G34/E34),"")
A35: 9 | B35: =IFERROR(IF(OR(9>B22,F34=""),"",F34),"") | C35: =IFERROR(IF(OR(9>B22,B35=""),"",B35*B21),"") | D35: =IFERROR(IF(OR(9>B22,B35=""),"",IF(9<=B23,0,MIN(B35,B24-C35))),"") | E35: =IFERROR(IF(C35="","",C35+D35),"") | F35: =IFERROR(IF(D35="","",B35-D35),"") | G35: =IFERROR(IF(E35="","",'PyG 3 Años'!$D$41-'PyG 3 Años'!$D$46+'PyG 3 Años'!$D$36+'PyG 3 Años'!$D$37),"") | H35: =IFERROR(IF(OR(E35="",E35=0),"",G35/E35),"")
A36: 10 | B36: =IFERROR(IF(OR(10>B22,F35=""),"",F35),"") | C36: =IFERROR(IF(OR(10>B22,B36=""),"",B36*B21),"") | D36: =IFERROR(IF(OR(10>B22,B36=""),"",IF(10<=B23,0,MIN(B36,B24-C36))),"") | E36: =IFERROR(IF(C36="","",C36+D36),"") | F36: =IFERROR(IF(D36="","",B36-D36),"") | G36: =IFERROR(IF(E36="","",'PyG 3 Años'!$D$41-'PyG 3 Años'!$D$46+'PyG 3 Años'!$D$36+'PyG 3 Años'!$D$37),"") | H36: =IFERROR(IF(OR(E36="",E36=0),"",G36/E36),"")
A37: 11 | B37: =IFERROR(IF(OR(11>B22,F36=""),"",F36),"") | C37: =IFERROR(IF(OR(11>B22,B37=""),"",B37*B21),"") | D37: =IFERROR(IF(OR(11>B22,B37=""),"",IF(11<=B23,0,MIN(B37,B24-C37))),"") | E37: =IFERROR(IF(C37="","",C37+D37),"") | F37: =IFERROR(IF(D37="","",B37-D37),"") | G37: =IFERROR(IF(E37="","",'PyG 3 Años'!$D$41-'PyG 3 Años'!$D$46+'PyG 3 Años'!$D$36+'PyG 3 Años'!$D$37),"") | H37: =IFERROR(IF(OR(E37="",E37=0),"",G37/E37),"")
A38: 12 | B38: =IFERROR(IF(OR(12>B22,F37=""),"",F37),"") | C38: =IFERROR(IF(OR(12>B22,B38=""),"",B38*B21),"") | D38: =IFERROR(IF(OR(12>B22,B38=""),"",IF(12<=B23,0,MIN(B38,B24-C38))),"") | E38: =IFERROR(IF(C38="","",C38+D38),"") | F38: =IFERROR(IF(D38="","",B38-D38),"") | G38: =IFERROR(IF(E38="","",'PyG 3 Años'!$D$41-'PyG 3 Años'!$D$46+'PyG 3 Años'!$D$36+'PyG 3 Años'!$D$37),"") | H38: =IFERROR(IF(OR(E38="",E38=0),"",G38/E38),"")
A39: 13 | B39: =IFERROR(IF(OR(13>B22,F38=""),"",F38),"") | C39: =IFERROR(IF(OR(13>B22,B39=""),"",B39*B21),"") | D39: =IFERROR(IF(OR(13>B22,B39=""),"",IF(13<=B23,0,MIN(B39,B24-C39))),"") | E39: =IFERROR(IF(C39="","",C39+D39),"") | F39: =IFERROR(IF(D39="","",B39-D39),"") | G39: =IFERROR(IF(E39="","",'PyG 3 Años'!$D$41-'PyG 3 Años'!$D$46+'PyG 3 Años'!$D$36+'PyG 3 Años'!$D$37),"") | H39: =IFERROR(IF(OR(E39="",E39=0),"",G39/E39),"")
A40: 14 | B40: =IFERROR(IF(OR(14>B22,F39=""),"",F39),"") | C40: =IFERROR(IF(OR(14>B22,B40=""),"",B40*B21),"") | D40: =IFERROR(IF(OR(14>B22,B40=""),"",IF(14<=B23,0,MIN(B40,B24-C40))),"") | E40: =IFERROR(IF(C40="","",C40+D40),"") | F40: =IFERROR(IF(D40="","",B40-D40),"") | G40: =IFERROR(IF(E40="","",'PyG 3 Años'!$D$41-'PyG 3 Años'!$D$46+'PyG 3 Años'!$D$36+'PyG 3 Años'!$D$37),"") | H40: =IFERROR(IF(OR(E40="",E40=0),"",G40/E40),"")
A41: 15 | B41: =IFERROR(IF(OR(15>B22,F40=""),"",F40),"") | C41: =IFERROR(IF(OR(15>B22,B41=""),"",B41*B21),"") | D41: =IFERROR(IF(OR(15>B22,B41=""),"",IF(15<=B23,0,MIN(B41,B24-C41))),"") | E41: =IFERROR(IF(C41="","",C41+D41),"") | F41: =IFERROR(IF(D41="","",B41-D41),"") | G41: =IFERROR(IF(E41="","",'PyG 3 Años'!$D$41-'PyG 3 Años'!$D$46+'PyG 3 Años'!$D$36+'PyG 3 Años'!$D$37),"") | H41: =IFERROR(IF(OR(E41="",E41=0),"",G41/E41),"")
A42: Tolerancia de cierre del cuadro (€) | B42: 0.01 | C42: Margen por redondeo. Por encima, el cuadro no cierra y hay capital sin devolver
A43: Capital pendiente al vencimiento | B43: =IFERROR(IF(B20="","",ROUND(B20-SUM(D27:D41),2)),"") -> 0 | C43: Tiene que ser cero: el principal devuelto en el cuadro tiene que ser el prestado. Si sale positivo, el plazo no llega
A44: Intereses del año 1 | B44: =IFERROR(IF(B20="","",IF(C27="",0,C27)),"") -> 2892.5
A45: Devolución de principal del año 1 | B45: =IFERROR(IF(B20="","",IF(D27="",0,D27)),"") -> 0
A46: Intereses del año 2 | B46: =IFERROR(IF(B20="","",IF(C28="",0,C28)),"") -> 2892.5
A47: Devolución de principal del año 2 | B47: =IFERROR(IF(B20="","",IF(D28="",0,D28)),"") -> 7815.7369
A48: Intereses del año 3 | B48: =IFERROR(IF(B20="","",IF(C29="",0,C29)),"") -> 2384.4771
A49: Devolución de principal del año 3 | B49: =IFERROR(IF(B20="","",IF(D29="",0,D29)),"") -> 8323.7598
A50: COBERTURA DEL SERVICIO DE LA DEUDA (DSCR)
A51: DSCR del año 1 | B51: =IFERROR(('PyG 3 Años'!$B$41-'PyG 3 Años'!$B$46+'PyG 3 Años'!$B$36+B44)/(B44+B45),"") -> 5.4745018 | C51: Año de CARENCIA si la hay: con sólo intereses en el denominador el ratio se dispara y no mide el negocio
A52: DSCR del año 2 | B52: =IFERROR(('PyG 3 Años'!$C$41-'PyG 3 Años'!$C$46+'PyG 3 Años'!$C$36+B46)/(B46+B47),"") -> 1.6143537
A53: DSCR del año 3 | B53: =IFERROR(('PyG 3 Años'!$D$41-'PyG 3 Años'!$D$46+'PyG 3 Años'!$D$36+B48)/(B48+B49),"") -> 1.5442648
A54: DSCR mínimo de todo el cuadro | B54: =IFERROR(IF(COUNT(H27:H41)=0,"",MIN(H27:H41)),"") -> 1.5442648 | C54: El peor año de los que dura el préstamo, no el mejor de los tres que proyecta el P&L. Es el número que decide una operación. Ojo al alcance: los años 1 a 3 salen del P&L y del año 4 en adelante el cuadro MANTIENE el flujo del año 3, así que el mínimo de esos años es una proyección sostenida, no un año calculado. El flujo va después de impuestos
A56: El DSCR se calcula ANTES de la deuda y DESPUÉS de impuestos: al resultado antes de impuestos se le resta el Impuesto de Sociedades y se le devuelven la amortización contable y los intereses; el resultado se divide entre lo que hay que pagar ese año. Por debajo del mínimo de la hoja de Supuestos, el negocio no genera para pagar el préstamo. En el cuadro, el flujo de caja disponible de los años 4 en adelante se mantiene en el del año 3: el P&L sólo proyecta tres, y aquí no se inventa un crecimiento que no está calculado.
