Workbook

Sheet Instrucciones
A1: Matriz Multi-Método de la Carta
A2: AI Chef Pro · aichef.pro — Guía Food Cost + Ingeniería de Menú
A4: Instrucciones de uso
A5: 1. Vuelca tu carta en la hoja «Datos»: plato, familia, unidades vendidas del último mes, coste por ración y precio de venta SIN IVA.
A6: 2. El coste por ración sale de tu ficha de escandallo (libro «ficha-escandallo-base» de este mismo pack). El PVP con IVA de sala lo calcula el libro.
A7: 3. Las hojas Kasavana-Smith, Miller, Pavesic y Goal Value leen esos datos y clasifican cada plato con su método. En ellas no se teclea nada.
A8: 4. Cada método se aplica DENTRO de su familia: un postre se compara con los postres, no con los chuletones.
A9: 5. Abre «Comparativa»: ahí tienes las cuatro lecturas del mismo plato, cuántas se salen de la mejor categoría y un diagnóstico de qué hacer.
A10: 6. Lleva las decisiones al libro «plan-accion-90-dias» con responsable y fecha. Un análisis sin fecha no cambia nada.
A11: 7. La hoja «Menú Precio Fijo» va aparte: en un menú cerrado el margen no lo decide el precio, lo decide el mix de elecciones de tus comensales.
A12: 8. Ajusta el factor del umbral de popularidad y los porcentajes de personal y de otros costes variables si tu casa no se parece al ejemplo.
A14: Celdas verdes = campos editables
... A30: Versión 1.0 · septiembre 2026 · aichef.pro/guia-food-cost-ingenieria-menu · info@aichef.pro

Sheet Datos
A1: Datos de la carta
A2: AI Chef Pro · aichef.pro — Guía Food Cost + Ingeniería de Menú
E3: El coste por ración sale de tu ficha de escandallo; el PVP va SIN IVA.
A4: # | B4: Plato | C4: Familia | D4: Uds vendidas (mes) | E4: Coste por ración (€) | F4: PVP sin IVA (€) | G4: Margen de contribución (€) | H4: Food cost (%) | I4: PVP con IVA en sala (€) | J4: Uds de su familia | K4: Platos de su familia con ventas | L4: Mix dentro de su familia (%) | M4: Umbral de popularidad de su familia (%) | N4: MC medio ponderado de su familia (€) | O4: Food cost medio ponderado de su familia (%) | P4: MC ponderado del plato: MC × uds (€) | Q4: Media del MC ponderado de su familia (€)
A5: 1 | B5: Croquetas de jamón ibérico (6 ud) | C5: Entrantes | D5: 420 | E5: 2.1 | F5: 8.6 | G5: =IFERROR(IF(OR($E5="",$F5=""),"",$F5-$E5),"") -> 6.5 | H5: =IFERROR(IF(OR($E5="",$F5="",$F5=0),"",$E5/$F5),"") -> 0.24418605 | I5: =IFERROR(IF(OR($F5="",$D$34=""),"",$F5*(1+$D$34)),"") -> 9.46 | J5: =IFERROR(IF($C5="","",SUMPRODUCT(--($C$5:$C$29=$C5),$D$5:$D$29)),"") -> 1730 | K5: =IFERROR(IF($C5="","",SUMPRODUCT(--($C$5:$C$29=$C5),--($D$5:$D$29>0))),"") -> 7 | L5: =IFERROR(IF(OR($D5="",$J5="",$J5=0),"",$D5/$J5),"") -> 0.24277457 | M5: =IFERROR(IF(OR($K5="",$K5=0,$D$33=""),"",$D$33/$K5),"") -> 0.1 | N5: =IFERROR(IF(OR($J5="",$J5=0),"",SUMPRODUCT(--($C$5:$C$29=$C5),$D$5:$D$29,$G$5:$G$29)/$J5),"") -> 7.4635838 | O5: =IFERROR(IF(SUMPRODUCT(--($C$5:$C$29=$C5),$D$5:$D$29,$F$5:$F$29)=0,"",SUMPRODUCT(--($C$5:$C$29=$C5),$D$5:$D$29,$E$5:$E$29)/SUMPRODUCT(--($C$5:$C$29=$C5),$D$5:$D$29,$F$5:$F$29)),"") -> 0.30714746 | P5: =IFERROR(IF(OR($G5="",$D5=""),"",$G5*$D5),"") -> 2730 | Q5: =IFERROR(IF(OR($K5="",$K5=0),"",SUMPRODUCT(--($C$5:$C$29=$C5),$D$5:$D$29,$G$5:$G$29)/$K5),"") -> 1844.5714
A6: 2 | B6: Ensalada de tomate rosa, ventresca y cebolleta | C6: Entrantes | D6: 310 | E6: 3.6 | F6: 11.8 | G6: =IFERROR(IF(OR($E6="",$F6=""),"",$F6-$E6),"") -> 8.2 | H6: =IFERROR(IF(OR($E6="",$F6="",$F6=0),"",$E6/$F6),"") -> 0.30508475 | I6: =IFERROR(IF(OR($F6="",$D$34=""),"",$F6*(1+$D$34)),"") -> 12.98 | J6: =IFERROR(IF($C6="","",SUMPRODUCT(--($C$5:$C$29=$C6),$D$5:$D$29)),"") -> 1730 | K6: =IFERROR(IF($C6="","",SUMPRODUCT(--($C$5:$C$29=$C6),--($D$5:$D$29>0))),"") -> 7 | L6: =IFERROR(IF(OR($D6="",$J6="",$J6=0),"",$D6/$J6),"") -> 0.17919075 | M6: =IFERROR(IF(OR($K6="",$K6=0,$D$33=""),"",$D$33/$K6),"") -> 0.1 | N6: =IFERROR(IF(OR($J6="",$J6=0),"",SUMPRODUCT(--($C$5:$C$29=$C6),$D$5:$D$29,$G$5:$G$29)/$J6),"") -> 7.4635838 | O6: =IFERROR(IF(SUMPRODUCT(--($C$5:$C$29=$C6),$D$5:$D$29,$F$5:$F$29)=0,"",SUMPRODUCT(--($C$5:$C$29=$C6),$D$5:$D$29,$E$5:$E$29)/SUMPRODUCT(--($C$5:$C$29=$C6),$D$5:$D$29,$F$5:$F$29)),"") -> 0.30714746 | P6: =IFERROR(IF(OR($G6="",$D6=""),"",$G6*$D6),"") -> 2542 | Q6: =IFERROR(IF(OR($K6="",$K6=0),"",SUMPRODUCT(--($C$5:$C$29=$C6),$D$5:$D$29,$G$5:$G$29)/$K6),"") -> 1844.5714
A7: 3 | B7: Gambas al ajillo | C7: Entrantes | D7: 260 | E7: 6.9 | F7: 15.5 | G7: =IFERROR(IF(OR($E7="",$F7=""),"",$F7-$E7),"") -> 8.6 | H7: =IFERROR(IF(OR($E7="",$F7="",$F7=0),"",$E7/$F7),"") -> 0.44516129 | I7: =IFERROR(IF(OR($F7="",$D$34=""),"",$F7*(1+$D$34)),"") -> 17.05 | J7: =IFERROR(IF($C7="","",SUMPRODUCT(--($C$5:$C$29=$C7),$D$5:$D$29)),"") -> 1730 | K7: =IFERROR(IF($C7="","",SUMPRODUCT(--($C$5:$C$29=$C7),--($D$5:$D$29>0))),"") -> 7 | L7: =IFERROR(IF(OR($D7="",$J7="",$J7=0),"",$D7/$J7),"") -> 0.15028902 | M7: =IFERROR(IF(OR($K7="",$K7=0,$D$33=""),"",$D$33/$K7),"") -> 0.1 | N7: =IFERROR(IF(OR($J7="",$J7=0),"",SUMPRODUCT(--($C$5:$C$29=$C7),$D$5:$D$29,$G$5:$G$29)/$J7),"") -> 7.4635838 | O7: =IFERROR(IF(SUMPRODUCT(--($C$5:$C$29=$C7),$D$5:$D$29,$F$5:$F$29)=0,"",SUMPRODUCT(--($C$5:$C$29=$C7),$D$5:$D$29,$E$5:$E$29)/SUMPRODUCT(--($C$5:$C$29=$C7),$D$5:$D$29,$F$5:$F$29)),"") -> 0.30714746 | P7: =IFERROR(IF(OR($G7="",$D7=""),"",$G7*$D7),"") -> 2236 | Q7: =IFERROR(IF(OR($K7="",$K7=0),"",SUMPRODUCT(--($C$5:$C$29=$C7),$D$5:$D$29,$G$5:$G$29)/$K7),"") -> 1844.5714
A8: 4 | B8: Huevos rotos con patatas y chistorra | C8: Entrantes | D8: 380 | E8: 2.4 | F8: 9.8 | G8: =IFERROR(IF(OR($E8="",$F8=""),"",$F8-$E8),"") -> 7.4 | H8: =IFERROR(IF(OR($E8="",$F8="",$F8=0),"",$E8/$F8),"") -> 0.24489796 | I8: =IFERROR(IF(OR($F8="",$D$34=""),"",$F8*(1+$D$34)),"") -> 10.78 | J8: =IFERROR(IF($C8="","",SUMPRODUCT(--($C$5:$C$29=$C8),$D$5:$D$29)),"") -> 1730 | K8: =IFERROR(IF($C8="","",SUMPRODUCT(--($C$5:$C$29=$C8),--($D$5:$D$29>0))),"") -> 7 | L8: =IFERROR(IF(OR($D8="",$J8="",$J8=0),"",$D8/$J8),"") -> 0.21965318 | M8: =IFERROR(IF(OR($K8="",$K8=0,$D$33=""),"",$D$33/$K8),"") -> 0.1 | N8: =IFERROR(IF(OR($J8="",$J8=0),"",SUMPRODUCT(--($C$5:$C$29=$C8),$D$5:$D$29,$G$5:$G$29)/$J8),"") -> 7.4635838 | O8: =IFERROR(IF(SUMPRODUCT(--($C$5:$C$29=$C8),$D$5:$D$29,$F$5:$F$29)=0,"",SUMPRODUCT(--($C$5:$C$29=$C8),$D$5:$D$29,$E$5:$E$29)/SUMPRODUCT(--($C$5:$C$29=$C8),$D$5:$D$29,$F$5:$F$29)),"") -> 0.30714746 | P8: =IFERROR(IF(OR($G8="",$D8=""),"",$G8*$D8),"") -> 2812 | Q8: =IFERROR(IF(OR($K8="",$K8=0),"",SUMPRODUCT(--($C$5:$C$29=$C8),$D$5:$D$29,$G$5:$G$29)/$K8),"") -> 1844.5714
A9: 5 | B9: Tabla de quesos de la zona | C9: Entrantes | D9: 90 | E9: 5.2 | F9: 13.6 | G9: =IFERROR(IF(OR($E9="",$F9=""),"",$F9-$E9),"") -> 8.4 | H9: =IFERROR(IF(OR($E9="",$F9="",$F9=0),"",$E9/$F9),"") -> 0.38235294 | I9: =IFERROR(IF(OR($F9="",$D$34=""),"",$F9*(1+$D$34)),"") -> 14.96 | J9: =IFERROR(IF($C9="","",SUMPRODUCT(--($C$5:$C$29=$C9),$D$5:$D$29)),"") -> 1730 | K9: =IFERROR(IF($C9="","",SUMPRODUCT(--($C$5:$C$29=$C9),--($D$5:$D$29>0))),"") -> 7 | L9: =IFERROR(IF(OR($D9="",$J9="",$J9=0),"",$D9/$J9),"") -> 0.052023121 | M9: =IFERROR(IF(OR($K9="",$K9=0,$D$33=""),"",$D$33/$K9),"") -> 0.1 | N9: =IFERROR(IF(OR($J9="",$J9=0),"",SUMPRODUCT(--($C$5:$C$29=$C9),$D$5:$D$29,$G$5:$G$29)/$J9),"") -> 7.4635838 | O9: =IFERROR(IF(SUMPRODUCT(--($C$5:$C$29=$C9),$D$5:$D$29,$F$5:$F$29)=0,"",SUMPRODUCT(--($C$5:$C$29=$C9),$D$5:$D$29,$E$5:$E$29)/SUMPRODUCT(--($C$5:$C$29=$C9),$D$5:$D$29,$F$5:$F$29)),"") -> 0.30714746 | P9: =IFERROR(IF(OR($G9="",$D9=""),"",$G9*$D9),"") -> 756 | Q9: =IFERROR(IF(OR($K9="",$K9=0),"",SUMPRODUCT(--($C$5:$C$29=$C9),$D$5:$D$29,$G$5:$G$29)/$K9),"") -> 1844.5714
A10: 6 | B10: Alcachofas confitadas con jamón | C10: Entrantes | D10: 120 | E10: 3.1 | F10: 10.9 | G10: =IFERROR(IF(OR($E10="",$F10=""),"",$F10-$E10),"") -> 7.8 | H10: =IFERROR(IF(OR($E10="",$F10="",$F10=0),"",$E10/$F10),"") -> 0.28440367 | I10: =IFERROR(IF(OR($F10="",$D$34=""),"",$F10*(1+$D$34)),"") -> 11.99 | J10: =IFERROR(IF($C10="","",SUMPRODUCT(--($C$5:$C$29=$C10),$D$5:$D$29)),"") -> 1730 | K10: =IFERROR(IF($C10="","",SUMPRODUCT(--($C$5:$C$29=$C10),--($D$5:$D$29>0))),"") -> 7 | L10: =IFERROR(IF(OR($D10="",$J10="",$J10=0),"",$D10/$J10),"") -> 0.069364162 | M10: =IFERROR(IF(OR($K10="",$K10=0,$D$33=""),"",$D$33/$K10),"") -> 0.1 | N10: =IFERROR(IF(OR($J10="",$J10=0),"",SUMPRODUCT(--($C$5:$C$29=$C10),$D$5:$D$29,$G$5:$G$29)/$J10),"") -> 7.4635838 | O10: =IFERROR(IF(SUMPRODUCT(--($C$5:$C$29=$C10),$D$5:$D$29,$F$5:$F$29)=0,"",SUMPRODUCT(--($C$5:$C$29=$C10),$D$5:$D$29,$E$5:$E$29)/SUMPRODUCT(--($C$5:$C$29=$C10),$D$5:$D$29,$F$5:$F$29)),"") -> 0.30714746 | P10: =IFERROR(IF(OR($G10="",$D10=""),"",$G10*$D10),"") -> 936 | Q10: =IFERROR(IF(OR($K10="",$K10=0),"",SUMPRODUCT(--($C$5:$C$29=$C10),$D$5:$D$29,$G$5:$G$29)/$K10),"") -> 1844.5714
A11: 7 | B11: Sopa de tomate asado con albahaca | C11: Entrantes | D11: 150 | E11: 1.2 | F11: 7.2 | G11: =IFERROR(IF(OR($E11="",$F11=""),"",$F11-$E11),"") -> 6 | H11: =IFERROR(IF(OR($E11="",$F11="",$F11=0),"",$E11/$F11),"") -> 0.16666667 | I11: =IFERROR(IF(OR($F11="",$D$34=""),"",$F11*(1+$D$34)),"") -> 7.92 | J11: =IFERROR(IF($C11="","",SUMPRODUCT(--($C$5:$C$29=$C11),$D$5:$D$29)),"") -> 1730 | K11: =IFERROR(IF($C11="","",SUMPRODUCT(--($C$5:$C$29=$C11),--($D$5:$D$29>0))),"") -> 7 | L11: =IFERROR(IF(OR($D11="",$J11="",$J11=0),"",$D11/$J11),"") -> 0.086705202 | M11: =IFERROR(IF(OR($K11="",$K11=0,$D$33=""),"",$D$33/$K11),"") -> 0.1 | N11: =IFERROR(IF(OR($J11="",$J11=0),"",SUMPRODUCT(--($C$5:$C$29=$C11),$D$5:$D$29,$G$5:$G$29)/$J11),"") -> 7.4635838 | O11: =IFERROR(IF(SUMPRODUCT(--($C$5:$C$29=$C11),$D$5:$D$29,$F$5:$F$29)=0,"",SUMPRODUCT(--($C$5:$C$29=$C11),$D$5:$D$29,$E$5:$E$29)/SUMPRODUCT(--($C$5:$C$29=$C11),$D$5:$D$29,$F$5:$F$29)),"") -> 0.30714746 | P11: =IFERROR(IF(OR($G11="",$D11=""),"",$G11*$D11),"") -> 900 | Q11: =IFERROR(IF(OR($K11="",$K11=0),"",SUMPRODUCT(--($C$5:$C$29=$C11),$D$5:$D$29,$G$5:$G$29)/$K11),"") -> 1844.5714
A12: 8 | B12: Solomillo de cerdo ibérico con puré de boniato | C12: Principales | D12: 340 | E12: 5.67 | F12: 17.3 | G12: =IFERROR(IF(OR($E12="",$F12=""),"",$F12-$E12),"") -> 11.63 | H12: =IFERROR(IF(OR($E12="",$F12="",$F12=0),"",$E12/$F12),"") -> 0.32774566 | I12: =IFERROR(IF(OR($F12="",$D$34=""),"",$F12*(1+$D$34)),"") -> 19.03 | J12: =IFERROR(IF($C12="","",SUMPRODUCT(--($C$5:$C$29=$C12),$D$5:$D$29)),"") -> 2020 | K12: =IFERROR(IF($C12="","",SUMPRODUCT(--($C$5:$C$29=$C12),--($D$5:$D$29>0))),"") -> 9 | L12: =IFERROR(IF(OR($D12="",$J12="",$J12=0),"",$D12/$J12),"") -> 0.16831683 | M12: =IFERROR(IF(OR($K12="",$K12=0,$D$33=""),"",$D$33/$K12),"") -> 0.077777778 | N12: =IFERROR(IF(OR($J12="",$J12=0),"",SUMPRODUCT(--($C$5:$C$29=$C12),$D$5:$D$29,$G$5:$G$29)/$J12),"") -> 10.795149 | O12: =IFERROR(IF(SUMPRODUCT(--($C$5:$C$29=$C12),$D$5:$D$29,$F$5:$F$29)=0,"",SUMPRODUCT(--($C$5:$C$29=$C12),$D$5:$D$29,$E$5:$E$29)/SUMPRODUCT(--($C$5:$C$29=$C12),$D$5:$D$29,$F$5:$F$29)),"") -> 0.35587523 | P12: =IFERROR(IF(OR($G12="",$D12=""),"",$G12*$D12),"") -> 3954.2 | Q12: =IFERROR(IF(OR($K12="",$K12=0),"",SUMPRODUCT(--($C$5:$C$29=$C12),$D$5:$D$29,$G$5:$G$29)/$K12),"") -> 2422.9111
A13: 9 | B13: Bacalao confitado al pil-pil | C13: Principales | D13: 190 | E13: 7.4 | F13: 19.1 | G13: =IFERROR(IF(OR($E13="",$F13=""),"",$F13-$E13),"") -> 11.7 | H13: =IFERROR(IF(OR($E13="",$F13="",$F13=0),"",$E13/$F13),"") -> 0.38743455 | I13: =IFERROR(IF(OR($F13="",$D$34=""),"",$F13*(1+$D$34)),"") -> 21.01 | J13: =IFERROR(IF($C13="","",SUMPRODUCT(--($C$5:$C$29=$C13),$D$5:$D$29)),"") -> 2020 | K13: =IFERROR(IF($C13="","",SUMPRODUCT(--($C$5:$C$29=$C13),--($D$5:$D$29>0))),"") -> 9 | L13: =IFERROR(IF(OR($D13="",$J13="",$J13=0),"",$D13/$J13),"") -> 0.094059406 | M13: =IFERROR(IF(OR($K13="",$K13=0,$D$33=""),"",$D$33/$K13),"") -> 0.077777778 | N13: =IFERROR(IF(OR($J13="",$J13=0),"",SUMPRODUCT(--($C$5:$C$29=$C13),$D$5:$D$29,$G$5:$G$29)/$J13),"") -> 10.795149 | O13: =IFERROR(IF(SUMPRODUCT(--($C$5:$C$29=$C13),$D$5:$D$29,$F$5:$F$29)=0,"",SUMPRODUCT(--($C$5:$C$29=$C13),$D$5:$D$29,$E$5:$E$29)/SUMPRODUCT(--($C$5:$C$29=$C13),$D$5:$D$29,$F$5:$F$29)),"") -> 0.35587523 | P13: =IFERROR(IF(OR($G13="",$D13=""),"",$G13*$D13),"") -> 2223 | Q13: =IFERROR(IF(OR($K13="",$K13=0),"",SUMPRODUCT(--($C$5:$C$29=$C13),$D$5:$D$29,$G$5:$G$29)/$K13),"") -> 2422.9111
A14: 10 | B14: Hamburguesa de vaca madurada con patatas | C14: Principales | D14: 460 | E14: 4.3 | F14: 13.6 | G14: =IFERROR(IF(OR($E14="",$F14=""),"",$F14-$E14),"") -> 9.3 | H14: =IFERROR(IF(OR($E14="",$F14="",$F14=0),"",$E14/$F14),"") -> 0.31617647 | I14: =IFERROR(IF(OR($F14="",$D$34=""),"",$F14*(1+$D$34)),"") -> 14.96 | J14: =IFERROR(IF($C14="","",SUMPRODUCT(--($C$5:$C$29=$C14),$D$5:$D$29)),"") -> 2020 | K14: =IFERROR(IF($C14="","",SUMPRODUCT(--($C$5:$C$29=$C14),--($D$5:$D$29>0))),"") -> 9 | L14: =IFERROR(IF(OR($D14="",$J14="",$J14=0),"",$D14/$J14),"") -> 0.22772277 | M14: =IFERROR(IF(OR($K14="",$K14=0,$D$33=""),"",$D$33/$K14),"") -> 0.077777778 | N14: =IFERROR(IF(OR($J14="",$J14=0),"",SUMPRODUCT(--($C$5:$C$29=$C14),$D$5:$D$29,$G$5:$G$29)/$J14),"") -> 10.795149 | O14: =IFERROR(IF(SUMPRODUCT(--($C$5:$C$29=$C14),$D$5:$D$29,$F$5:$F$29)=0,"",SUMPRODUCT(--($C$5:$C$29=$C14),$D$5:$D$29,$E$5:$E$29)/SUMPRODUCT(--($C$5:$C$29=$C14),$D$5:$D$29,$F$5:$F$29)),"") -> 0.35587523 | P14: =IFERROR(IF(OR($G14="",$D14=""),"",$G14*$D14),"") -> 4278 | Q14: =IFERROR(IF(OR($K14="",$K14=0),"",SUMPRODUCT(--($C$5:$C$29=$C14),$D$5:$D$29,$G$5:$G$29)/$K14),"") -> 2422.9111
A15: 11 | B15: Arroz meloso de secreto ibérico y setas | C15: Principales | D15: 270 | E15: 6.2 | F15: 16.4 | G15: =IFERROR(IF(OR($E15="",$F15=""),"",$F15-$E15),"") -> 10.2 | H15: =IFERROR(IF(OR($E15="",$F15="",$F15=0),"",$E15/$F15),"") -> 0.37804878 | I15: =IFERROR(IF(OR($F15="",$D$34=""),"",$F15*(1+$D$34)),"") -> 18.04 | J15: =IFERROR(IF($C15="","",SUMPRODUCT(--($C$5:$C$29=$C15),$D$5:$D$29)),"") -> 2020 | K15: =IFERROR(IF($C15="","",SUMPRODUCT(--($C$5:$C$29=$C15),--($D$5:$D$29>0))),"") -> 9 | L15: =IFERROR(IF(OR($D15="",$J15="",$J15=0),"",$D15/$J15),"") -> 0.13366337 | M15: =IFERROR(IF(OR($K15="",$K15=0,$D$33=""),"",$D$33/$K15),"") -> 0.077777778 | N15: =IFERROR(IF(OR($J15="",$J15=0),"",SUMPRODUCT(--($C$5:$C$29=$C15),$D$5:$D$29,$G$5:$G$29)/$J15),"") -> 10.795149 | O15: =IFERROR(IF(SUMPRODUCT(--($C$5:$C$29=$C15),$D$5:$D$29,$F$5:$F$29)=0,"",SUMPRODUCT(--($C$5:$C$29=$C15),$D$5:$D$29,$E$5:$E$29)/SUMPRODUCT(--($C$5:$C$29=$C15),$D$5:$D$29,$F$5:$F$29)),"") -> 0.35587523 | P15: =IFERROR(IF(OR($G15="",$D15=""),"",$G15*$D15),"") -> 2754 | Q15: =IFERROR(IF(OR($K15="",$K15=0),"",SUMPRODUCT(--($C$5:$C$29=$C15),$D$5:$D$29,$G$5:$G$29)/$K15),"") -> 2422.9111
A16: 12 | B16: Chuletón de vaca madurada (500 g) | C16: Principales | D16: 110 | E16: 14.8 | F16: 32.7 | G16: =IFERROR(IF(OR($E16="",$F16=""),"",$F16-$E16),"") -> 17.9 | H16: =IFERROR(IF(OR($E16="",$F16="",$F16=0),"",$E16/$F16),"") -> 0.45259939 | I16: =IFERROR(IF(OR($F16="",$D$34=""),"",$F16*(1+$D$34)),"") -> 35.97 | J16: =IFERROR(IF($C16="","",SUMPRODUCT(--($C$5:$C$29=$C16),$D$5:$D$29)),"") -> 2020 | K16: =IFERROR(IF($C16="","",SUMPRODUCT(--($C$5:$C$29=$C16),--($D$5:$D$29>0))),"") -> 9 | L16: =IFERROR(IF(OR($D16="",$J16="",$J16=0),"",$D16/$J16),"") -> 0.054455446 | M16: =IFERROR(IF(OR($K16="",$K16=0,$D$33=""),"",$D$33/$K16),"") -> 0.077777778 | N16: =IFERROR(IF(OR($J16="",$J16=0),"",SUMPRODUCT(--($C$5:$C$29=$C16),$D$5:$D$29,$G$5:$G$29)/$J16),"") -> 10.795149 | O16: =IFERROR(IF(SUMPRODUCT(--($C$5:$C$29=$C16),$D$5:$D$29,$F$5:$F$29)=0,"",SUMPRODUCT(--($C$5:$C$29=$C16),$D$5:$D$29,$E$5:$E$29)/SUMPRODUCT(--($C$5:$C$29=$C16),$D$5:$D$29,$F$5:$F$29)),"") -> 0.35587523 | P16: =IFERROR(IF(OR($G16="",$D16=""),"",$G16*$D16),"") -> 1969 | Q16: =IFERROR(IF(OR($K16="",$K16=0),"",SUMPRODUCT(--($C$5:$C$29=$C16),$D$5:$D$29,$G$5:$G$29)/$K16),"") -> 2422.9111
... A24: 20 | B24: Fruta de temporada preparada | C24: Postres | D24: 60 | E24: 1.4 | F24: 4.5 | G24: =IFERROR(IF(OR($E24="",$F24=""),"",$F24-$E24),"") -> 3.1 | H24: =IFERROR(IF(OR($E24="",$F24="",$F24=0),"",$E24/$F24),"") -> 0.31111111 | I24: =IFERROR(IF(OR($F24="",$D$34=""),"",$F24*(1+$D$34)),"") -> 4.95 | J24: =IFERROR(IF($C24="","",SUMPRODUCT(--($C$5:$C$29=$C24),$D$5:$D$29)),"") -> 1120 | K24: =IFERROR(IF($C24="","",SUMPRODUCT(--($C$5:$C$29=$C24),--($D$5:$D$29>0))),"") -> 4 | L24: =IFERROR(IF(OR($D24="",$J24="",$J24=0),"",$D24/$J24),"") -> 0.053571429 | M24: =IFERROR(IF(OR($K24="",$K24=0,$D$33=""),"",$D$33/$K24),"") -> 0.175 | N24: =IFERROR(IF(OR($J24="",$J24=0),"",SUMPRODUCT(--($C$5:$C$29=$C24),$D$5:$D$29,$G$5:$G$29)/$J24),"") -> 4.4821429 | O24: =IFERROR(IF(SUMPRODUCT(--($C$5:$C$29=$C24),$D$5:$D$29,$F$5:$F$29)=0,"",SUMPRODUCT(--($C$5:$C$29=$C24),$D$5:$D$29,$E$5:$E$29)/SUMPRODUCT(--($C$5:$C$29=$C24),$D$5:$D$29,$F$5:$F$29)),"") -> 0.23229852 | P24: =IFERROR(IF(OR($G24="",$D24=""),"",$G24*$D24),"") -> 186 | Q24: =IFERROR(IF(OR($K24="",$K24=0),"",SUMPRODUCT(--($C$5:$C$29=$C24),$D$5:$D$29,$G$5:$G$29)/$K24),"") -> 1255
A25: 21 | G25: =IFERROR(IF(OR($E25="",$F25=""),"",$F25-$E25),"") | H25: =IFERROR(IF(OR($E25="",$F25="",$F25=0),"",$E25/$F25),"") | I25: =IFERROR(IF(OR($F25="",$D$34=""),"",$F25*(1+$D$34)),"") | J25: =IFERROR(IF($C25="","",SUMPRODUCT(--($C$5:$C$29=$C25),$D$5:$D$29)),"") | K25: =IFERROR(IF($C25="","",SUMPRODUCT(--($C$5:$C$29=$C25),--($D$5:$D$29>0))),"") | L25: =IFERROR(IF(OR($D25="",$J25="",$J25=0),"",$D25/$J25),"") | M25: =IFERROR(IF(OR($K25="",$K25=0,$D$33=""),"",$D$33/$K25),"") | N25: =IFERROR(IF(OR($J25="",$J25=0),"",SUMPRODUCT(--($C$5:$C$29=$C25),$D$5:$D$29,$G$5:$G$29)/$J25),"") | O25: =IFERROR(IF(SUMPRODUCT(--($C$5:$C$29=$C25),$D$5:$D$29,$F$5:$F$29)=0,"",SUMPRODUCT(--($C$5:$C$29=$C25),$D$5:$D$29,$E$5:$E$29)/SUMPRODUCT(--($C$5:$C$29=$C25),$D$5:$D$29,$F$5:$F$29)),"") | P25: =IFERROR(IF(OR($G25="",$D25=""),"",$G25*$D25),"") | Q25: =IFERROR(IF(OR($K25="",$K25=0),"",SUMPRODUCT(--($C$5:$C$29=$C25),$D$5:$D$29,$G$5:$G$29)/$K25),"")
A26: 22 | G26: =IFERROR(IF(OR($E26="",$F26=""),"",$F26-$E26),"") | H26: =IFERROR(IF(OR($E26="",$F26="",$F26=0),"",$E26/$F26),"") | I26: =IFERROR(IF(OR($F26="",$D$34=""),"",$F26*(1+$D$34)),"") | J26: =IFERROR(IF($C26="","",SUMPRODUCT(--($C$5:$C$29=$C26),$D$5:$D$29)),"") | K26: =IFERROR(IF($C26="","",SUMPRODUCT(--($C$5:$C$29=$C26),--($D$5:$D$29>0))),"") | L26: =IFERROR(IF(OR($D26="",$J26="",$J26=0),"",$D26/$J26),"") | M26: =IFERROR(IF(OR($K26="",$K26=0,$D$33=""),"",$D$33/$K26),"") | N26: =IFERROR(IF(OR($J26="",$J26=0),"",SUMPRODUCT(--($C$5:$C$29=$C26),$D$5:$D$29,$G$5:$G$29)/$J26),"") | O26: =IFERROR(IF(SUMPRODUCT(--($C$5:$C$29=$C26),$D$5:$D$29,$F$5:$F$29)=0,"",SUMPRODUCT(--($C$5:$C$29=$C26),$D$5:$D$29,$E$5:$E$29)/SUMPRODUCT(--($C$5:$C$29=$C26),$D$5:$D$29,$F$5:$F$29)),"") | P26: =IFERROR(IF(OR($G26="",$D26=""),"",$G26*$D26),"") | Q26: =IFERROR(IF(OR($K26="",$K26=0),"",SUMPRODUCT(--($C$5:$C$29=$C26),$D$5:$D$29,$G$5:$G$29)/$K26),"")
A27: 23 | G27: =IFERROR(IF(OR($E27="",$F27=""),"",$F27-$E27),"") | H27: =IFERROR(IF(OR($E27="",$F27="",$F27=0),"",$E27/$F27),"") | I27: =IFERROR(IF(OR($F27="",$D$34=""),"",$F27*(1+$D$34)),"") | J27: =IFERROR(IF($C27="","",SUMPRODUCT(--($C$5:$C$29=$C27),$D$5:$D$29)),"") | K27: =IFERROR(IF($C27="","",SUMPRODUCT(--($C$5:$C$29=$C27),--($D$5:$D$29>0))),"") | L27: =IFERROR(IF(OR($D27="",$J27="",$J27=0),"",$D27/$J27),"") | M27: =IFERROR(IF(OR($K27="",$K27=0,$D$33=""),"",$D$33/$K27),"") | N27: =IFERROR(IF(OR($J27="",$J27=0),"",SUMPRODUCT(--($C$5:$C$29=$C27),$D$5:$D$29,$G$5:$G$29)/$J27),"") | O27: =IFERROR(IF(SUMPRODUCT(--($C$5:$C$29=$C27),$D$5:$D$29,$F$5:$F$29)=0,"",SUMPRODUCT(--($C$5:$C$29=$C27),$D$5:$D$29,$E$5:$E$29)/SUMPRODUCT(--($C$5:$C$29=$C27),$D$5:$D$29,$F$5:$F$29)),"") | P27: =IFERROR(IF(OR($G27="",$D27=""),"",$G27*$D27),"") | Q27: =IFERROR(IF(OR($K27="",$K27=0),"",SUMPRODUCT(--($C$5:$C$29=$C27),$D$5:$D$29,$G$5:$G$29)/$K27),"")
A28: 24 | G28: =IFERROR(IF(OR($E28="",$F28=""),"",$F28-$E28),"") | H28: =IFERROR(IF(OR($E28="",$F28="",$F28=0),"",$E28/$F28),"") | I28: =IFERROR(IF(OR($F28="",$D$34=""),"",$F28*(1+$D$34)),"") | J28: =IFERROR(IF($C28="","",SUMPRODUCT(--($C$5:$C$29=$C28),$D$5:$D$29)),"") | K28: =IFERROR(IF($C28="","",SUMPRODUCT(--($C$5:$C$29=$C28),--($D$5:$D$29>0))),"") | L28: =IFERROR(IF(OR($D28="",$J28="",$J28=0),"",$D28/$J28),"") | M28: =IFERROR(IF(OR($K28="",$K28=0,$D$33=""),"",$D$33/$K28),"") | N28: =IFERROR(IF(OR($J28="",$J28=0),"",SUMPRODUCT(--($C$5:$C$29=$C28),$D$5:$D$29,$G$5:$G$29)/$J28),"") | O28: =IFERROR(IF(SUMPRODUCT(--($C$5:$C$29=$C28),$D$5:$D$29,$F$5:$F$29)=0,"",SUMPRODUCT(--($C$5:$C$29=$C28),$D$5:$D$29,$E$5:$E$29)/SUMPRODUCT(--($C$5:$C$29=$C28),$D$5:$D$29,$F$5:$F$29)),"") | P28: =IFERROR(IF(OR($G28="",$D28=""),"",$G28*$D28),"") | Q28: =IFERROR(IF(OR($K28="",$K28=0),"",SUMPRODUCT(--($C$5:$C$29=$C28),$D$5:$D$29,$G$5:$G$29)/$K28),"")
A29: 25 | G29: =IFERROR(IF(OR($E29="",$F29=""),"",$F29-$E29),"") | H29: =IFERROR(IF(OR($E29="",$F29="",$F29=0),"",$E29/$F29),"") | I29: =IFERROR(IF(OR($F29="",$D$34=""),"",$F29*(1+$D$34)),"") | J29: =IFERROR(IF($C29="","",SUMPRODUCT(--($C$5:$C$29=$C29),$D$5:$D$29)),"") | K29: =IFERROR(IF($C29="","",SUMPRODUCT(--($C$5:$C$29=$C29),--($D$5:$D$29>0))),"") | L29: =IFERROR(IF(OR($D29="",$J29="",$J29=0),"",$D29/$J29),"") | M29: =IFERROR(IF(OR($K29="",$K29=0,$D$33=""),"",$D$33/$K29),"") | N29: =IFERROR(IF(OR($J29="",$J29=0),"",SUMPRODUCT(--($C$5:$C$29=$C29),$D$5:$D$29,$G$5:$G$29)/$J29),"") | O29: =IFERROR(IF(SUMPRODUCT(--($C$5:$C$29=$C29),$D$5:$D$29,$F$5:$F$29)=0,"",SUMPRODUCT(--($C$5:$C$29=$C29),$D$5:$D$29,$E$5:$E$29)/SUMPRODUCT(--($C$5:$C$29=$C29),$D$5:$D$29,$F$5:$F$29)),"") | P29: =IFERROR(IF(OR($G29="",$D29=""),"",$G29*$D29),"") | Q29: =IFERROR(IF(OR($K29="",$K29=0),"",SUMPRODUCT(--($C$5:$C$29=$C29),$D$5:$D$29,$G$5:$G$29)/$K29),"")
A31: RESUMEN Y PARÁMETROS — lo calcula el libro
B32: TOTAL DE LA CARTA | D32: =IFERROR(SUM($D$5:$D$29),"") -> 4870 | G32: =IFERROR(IF($D$32=0,"",SUMPRODUCT($D$5:$D$29,$G$5:$G$29)/$D$32),"") -> 8.1597947 | H32: =IFERROR(IF(SUMPRODUCT($D$5:$D$29,$F$5:$F$29)=0,"",SUMPRODUCT($D$5:$D$29,$E$5:$E$29)/SUMPRODUCT($D$5:$D$29,$F$5:$F$29)),"") -> 0.32680208 | I32: =IFERROR(SUMPRODUCT($D$5:$D$29,$F$5:$F$29),"") -> 59029 | J32: Uds · MC medio ponderado · food cost medio ponderado · ventas netas del mes
B33: Factor del umbral de popularidad (%) | D33: 0.7 | F33: El clásico es el 70 % del mix medio: el umbral de cada familia = este factor ÷ número de platos de la familia con ventas. Súbelo si la familia es muy corta.
B34: Tipo de IVA de restauración (%) | D34: 0.1 | F34: 10 % en restauración, INCLUIDA la bebida alcohólica servida en sala: el art. 91.Uno.2.2 de la Ley del IVA grava a ese tipo los servicios de hostelería y «el suministro de comidas y bebidas para consumir en el acto», y no excluye el alcohol. Cámbialo aquí y se recalcula todo el libro.
B35: Platos con ventas en la carta | D35: =COUNTIF($D$5:$D$29,">0") -> 20
B36: Platos dados de alta en la carta | D36: =COUNTIF($B$5:$B$29,"<>") -> 20
A38: RESUMEN POR FAMILIA — lo calcula el libro
B39: Familia | C39: Platos en carta | D39: Platos con ventas | E39: Uds vendidas | F39: Mix sobre la carta (%) | G39: MC medio ponderado (€) | H39: Food cost medio ponderado (%) | I39: Ventas netas del mes (€)
B40: Entrantes | C40: =COUNTIF($C$5:$C$29,$B40) -> 7 | D40: =IFERROR(IF($C40=0,"",SUMPRODUCT(--($C$5:$C$29=$B40),--($D$5:$D$29>0))),"") -> 7 | E40: =IFERROR(IF($C40=0,"",SUMIF($C$5:$C$29,$B40,$D$5:$D$29)),"") -> 1730 | F40: =IFERROR(IF(OR($D$32=0,$C40=0),"",$E40/$D$32),"") -> 0.35523614 | G40: =IFERROR(IF($E40=0,"",SUMPRODUCT(--($C$5:$C$29=$B40),$D$5:$D$29,$G$5:$G$29)/$E40),"") -> 7.4635838 | H40: =IFERROR(IF(SUMPRODUCT(--($C$5:$C$29=$B40),$D$5:$D$29,$F$5:$F$29)=0,"",SUMPRODUCT(--($C$5:$C$29=$B40),$D$5:$D$29,$E$5:$E$29)/SUMPRODUCT(--($C$5:$C$29=$B40),$D$5:$D$29,$F$5:$F$29)),"") -> 0.30714746 | I40: =IFERROR(SUMPRODUCT(--($C$5:$C$29=$B40),$D$5:$D$29,$F$5:$F$29),"") -> 18636
B41: Principales | C41: =COUNTIF($C$5:$C$29,$B41) -> 9 | D41: =IFERROR(IF($C41=0,"",SUMPRODUCT(--($C$5:$C$29=$B41),--($D$5:$D$29>0))),"") -> 9 | E41: =IFERROR(IF($C41=0,"",SUMIF($C$5:$C$29,$B41,$D$5:$D$29)),"") -> 2020 | F41: =IFERROR(IF(OR($D$32=0,$C41=0),"",$E41/$D$32),"") -> 0.41478439 | G41: =IFERROR(IF($E41=0,"",SUMPRODUCT(--($C$5:$C$29=$B41),$D$5:$D$29,$G$5:$G$29)/$E41),"") -> 10.795149 | H41: =IFERROR(IF(SUMPRODUCT(--($C$5:$C$29=$B41),$D$5:$D$29,$F$5:$F$29)=0,"",SUMPRODUCT(--($C$5:$C$29=$B41),$D$5:$D$29,$E$5:$E$29)/SUMPRODUCT(--($C$5:$C$29=$B41),$D$5:$D$29,$F$5:$F$29)),"") -> 0.35587523 | I41: =IFERROR(SUMPRODUCT(--($C$5:$C$29=$B41),$D$5:$D$29,$F$5:$F$29),"") -> 33854
B42: Postres | C42: =COUNTIF($C$5:$C$29,$B42) -> 4 | D42: =IFERROR(IF($C42=0,"",SUMPRODUCT(--($C$5:$C$29=$B42),--($D$5:$D$29>0))),"") -> 4 | E42: =IFERROR(IF($C42=0,"",SUMIF($C$5:$C$29,$B42,$D$5:$D$29)),"") -> 1120 | F42: =IFERROR(IF(OR($D$32=0,$C42=0),"",$E42/$D$32),"") -> 0.22997947 | G42: =IFERROR(IF($E42=0,"",SUMPRODUCT(--($C$5:$C$29=$B42),$D$5:$D$29,$G$5:$G$29)/$E42),"") -> 4.4821429 | H42: =IFERROR(IF(SUMPRODUCT(--($C$5:$C$29=$B42),$D$5:$D$29,$F$5:$F$29)=0,"",SUMPRODUCT(--($C$5:$C$29=$B42),$D$5:$D$29,$E$5:$E$29)/SUMPRODUCT(--($C$5:$C$29=$B42),$D$5:$D$29,$F$5:$F$29)),"") -> 0.23229852 | I42: =IFERROR(SUMPRODUCT(--($C$5:$C$29=$B42),$D$5:$D$29,$F$5:$F$29),"") -> 6539
B43: Menú | C43: =COUNTIF($C$5:$C$29,$B43) -> 0 | D43: =IFERROR(IF($C43=0,"",SUMPRODUCT(--($C$5:$C$29=$B43),--($D$5:$D$29>0))),"") | E43: =IFERROR(IF($C43=0,"",SUMIF($C$5:$C$29,$B43,$D$5:$D$29)),"") | F43: =IFERROR(IF(OR($D$32=0,$C43=0),"",$E43/$D$32),"") | G43: =IFERROR(IF($E43=0,"",SUMPRODUCT(--($C$5:$C$29=$B43),$D$5:$D$29,$G$5:$G$29)/$E43),"") | H43: =IFERROR(IF(SUMPRODUCT(--($C$5:$C$29=$B43),$D$5:$D$29,$F$5:$F$29)=0,"",SUMPRODUCT(--($C$5:$C$29=$B43),$D$5:$D$29,$E$5:$E$29)/SUMPRODUCT(--($C$5:$C$29=$B43),$D$5:$D$29,$F$5:$F$29)),"") | I43: =IFERROR(SUMPRODUCT(--($C$5:$C$29=$B43),$D$5:$D$29,$F$5:$F$29),"") -> 0

Sheet Kasavana-Smith
A1: Kasavana & Smith — popularidad × margen de contribución
A2: AI Chef Pro · aichef.pro — Guía Food Cost + Ingeniería de Menú
E3: Todo se calcula desde la hoja «Datos». Aquí no se teclea nada.
A4: # | B4: Plato | C4: Familia | D4: Uds vendidas | E4: Mix dentro de su familia (%) | F4: Umbral de popularidad de su familia (%) | G4: Popularidad | H4: MC del plato (€) | I4: MC medio ponderado de su familia (€) | J4: Nivel de margen | K4: Clasificación | L4: Qué significa | M4: Acción recomendada
A5: 1 | B5: =IFERROR(IF('Datos'!$B5="","",'Datos'!$B5),"") -> Croquetas de jamón ibérico (6 ud) | C5: =IFERROR(IF('Datos'!$C5="","",'Datos'!$C5),"") -> Entrantes | D5: =IFERROR(IF('Datos'!$D5="","",'Datos'!$D5),"") -> 420 | E5: =IFERROR(IF('Datos'!$L5="","",'Datos'!$L5),"") -> 0.24277457 | F5: =IFERROR(IF('Datos'!$M5="","",'Datos'!$M5),"") -> 0.1 | G5: =IFERROR(IF(OR($E5="",$F5=""),"",IF($E5>=$F5,"Alta","Baja")),"") -> Alta | H5: =IFERROR(IF('Datos'!$G5="","",'Datos'!$G5),"") -> 6.5 | I5: =IFERROR(IF('Datos'!$N5="","",'Datos'!$N5),"") -> 7.4635838 | J5: =IFERROR(IF(OR($H5="",$I5=""),"",IF($H5>=$I5,"Alto","Bajo")),"") -> Bajo | K5: =IFERROR(IF(OR($G5="",$J5=""),"",IF(AND($G5="Alta",$J5="Alto"),"Star",IF(AND($G5="Alta",$J5="Bajo"),"Plowhorse",IF(AND($G5="Baja",$J5="Alto"),"Puzzle","Dog")))),"") -> Plowhorse | L5: =IFERROR(IF($K5="","",IF($K5="Star","Se vende y deja margen: es el plato que sostiene a su familia.",IF($K5="Plowhorse","Se vende mucho, pero deja poco margen en euros por unidad.",IF($K5="Puzzle","Deja buen margen en euros, pero se pide poco.","Ni se vende ni deja margen.")))),"") -> Se vende mucho, pero deja poco margen en euros por unidad. | M5: =IFERROR(IF($K5="","",IF($K5="Star","Mantener receta y proveedor, y darle sitio destacado en la carta.",IF($K5="Plowhorse","Subir precio con cuidado o bajar coste sin tocar la ración.",IF($K5="Puzzle","Reubicar en la carta, renombrar y que la sala lo sugiera.","Retirar o reformular: ocupa sitio en la carta y en la cocina.")))),"") -> Subir precio con cuidado o bajar coste sin tocar la ración.
A6: 2 | B6: =IFERROR(IF('Datos'!$B6="","",'Datos'!$B6),"") -> Ensalada de tomate rosa, ventresca y cebolleta | C6: =IFERROR(IF('Datos'!$C6="","",'Datos'!$C6),"") -> Entrantes | D6: =IFERROR(IF('Datos'!$D6="","",'Datos'!$D6),"") -> 310 | E6: =IFERROR(IF('Datos'!$L6="","",'Datos'!$L6),"") -> 0.17919075 | F6: =IFERROR(IF('Datos'!$M6="","",'Datos'!$M6),"") -> 0.1 | G6: =IFERROR(IF(OR($E6="",$F6=""),"",IF($E6>=$F6,"Alta","Baja")),"") -> Alta | H6: =IFERROR(IF('Datos'!$G6="","",'Datos'!$G6),"") -> 8.2 | I6: =IFERROR(IF('Datos'!$N6="","",'Datos'!$N6),"") -> 7.4635838 | J6: =IFERROR(IF(OR($H6="",$I6=""),"",IF($H6>=$I6,"Alto","Bajo")),"") -> Alto | K6: =IFERROR(IF(OR($G6="",$J6=""),"",IF(AND($G6="Alta",$J6="Alto"),"Star",IF(AND($G6="Alta",$J6="Bajo"),"Plowhorse",IF(AND($G6="Baja",$J6="Alto"),"Puzzle","Dog")))),"") -> Star | L6: =IFERROR(IF($K6="","",IF($K6="Star","Se vende y deja margen: es el plato que sostiene a su familia.",IF($K6="Plowhorse","Se vende mucho, pero deja poco margen en euros por unidad.",IF($K6="Puzzle","Deja buen margen en euros, pero se pide poco.","Ni se vende ni deja margen.")))),"") -> Se vende y deja margen: es el plato que sostiene a su familia. | M6: =IFERROR(IF($K6="","",IF($K6="Star","Mantener receta y proveedor, y darle sitio destacado en la carta.",IF($K6="Plowhorse","Subir precio con cuidado o bajar coste sin tocar la ración.",IF($K6="Puzzle","Reubicar en la carta, renombrar y que la sala lo sugiera.","Retirar o reformular: ocupa sitio en la carta y en la cocina.")))),"") -> Mantener receta y proveedor, y darle sitio destacado en la carta.
A7: 3 | B7: =IFERROR(IF('Datos'!$B7="","",'Datos'!$B7),"") -> Gambas al ajillo | C7: =IFERROR(IF('Datos'!$C7="","",'Datos'!$C7),"") -> Entrantes | D7: =IFERROR(IF('Datos'!$D7="","",'Datos'!$D7),"") -> 260 | E7: =IFERROR(IF('Datos'!$L7="","",'Datos'!$L7),"") -> 0.15028902 | F7: =IFERROR(IF('Datos'!$M7="","",'Datos'!$M7),"") -> 0.1 | G7: =IFERROR(IF(OR($E7="",$F7=""),"",IF($E7>=$F7,"Alta","Baja")),"") -> Alta | H7: =IFERROR(IF('Datos'!$G7="","",'Datos'!$G7),"") -> 8.6 | I7: =IFERROR(IF('Datos'!$N7="","",'Datos'!$N7),"") -> 7.4635838 | J7: =IFERROR(IF(OR($H7="",$I7=""),"",IF($H7>=$I7,"Alto","Bajo")),"") -> Alto | K7: =IFERROR(IF(OR($G7="",$J7=""),"",IF(AND($G7="Alta",$J7="Alto"),"Star",IF(AND($G7="Alta",$J7="Bajo"),"Plowhorse",IF(AND($G7="Baja",$J7="Alto"),"Puzzle","Dog")))),"") -> Star | L7: =IFERROR(IF($K7="","",IF($K7="Star","Se vende y deja margen: es el plato que sostiene a su familia.",IF($K7="Plowhorse","Se vende mucho, pero deja poco margen en euros por unidad.",IF($K7="Puzzle","Deja buen margen en euros, pero se pide poco.","Ni se vende ni deja margen.")))),"") -> Se vende y deja margen: es el plato que sostiene a su familia. | M7: =IFERROR(IF($K7="","",IF($K7="Star","Mantener receta y proveedor, y darle sitio destacado en la carta.",IF($K7="Plowhorse","Subir precio con cuidado o bajar coste sin tocar la ración.",IF($K7="Puzzle","Reubicar en la carta, renombrar y que la sala lo sugiera.","Retirar o reformular: ocupa sitio en la carta y en la cocina.")))),"") -> Mantener receta y proveedor, y darle sitio destacado en la carta.
A8: 4 | B8: =IFERROR(IF('Datos'!$B8="","",'Datos'!$B8),"") -> Huevos rotos con patatas y chistorra | C8: =IFERROR(IF('Datos'!$C8="","",'Datos'!$C8),"") -> Entrantes | D8: =IFERROR(IF('Datos'!$D8="","",'Datos'!$D8),"") -> 380 | E8: =IFERROR(IF('Datos'!$L8="","",'Datos'!$L8),"") -> 0.21965318 | F8: =IFERROR(IF('Datos'!$M8="","",'Datos'!$M8),"") -> 0.1 | G8: =IFERROR(IF(OR($E8="",$F8=""),"",IF($E8>=$F8,"Alta","Baja")),"") -> Alta | H8: =IFERROR(IF('Datos'!$G8="","",'Datos'!$G8),"") -> 7.4 | I8: =IFERROR(IF('Datos'!$N8="","",'Datos'!$N8),"") -> 7.4635838 | J8: =IFERROR(IF(OR($H8="",$I8=""),"",IF($H8>=$I8,"Alto","Bajo")),"") -> Bajo | K8: =IFERROR(IF(OR($G8="",$J8=""),"",IF(AND($G8="Alta",$J8="Alto"),"Star",IF(AND($G8="Alta",$J8="Bajo"),"Plowhorse",IF(AND($G8="Baja",$J8="Alto"),"Puzzle","Dog")))),"") -> Plowhorse | L8: =IFERROR(IF($K8="","",IF($K8="Star","Se vende y deja margen: es el plato que sostiene a su familia.",IF($K8="Plowhorse","Se vende mucho, pero deja poco margen en euros por unidad.",IF($K8="Puzzle","Deja buen margen en euros, pero se pide poco.","Ni se vende ni deja margen.")))),"") -> Se vende mucho, pero deja poco margen en euros por unidad. | M8: =IFERROR(IF($K8="","",IF($K8="Star","Mantener receta y proveedor, y darle sitio destacado en la carta.",IF($K8="Plowhorse","Subir precio con cuidado o bajar coste sin tocar la ración.",IF($K8="Puzzle","Reubicar en la carta, renombrar y que la sala lo sugiera.","Retirar o reformular: ocupa sitio en la carta y en la cocina.")))),"") -> Subir precio con cuidado o bajar coste sin tocar la ración.
A9: 5 | B9: =IFERROR(IF('Datos'!$B9="","",'Datos'!$B9),"") -> Tabla de quesos de la zona | C9: =IFERROR(IF('Datos'!$C9="","",'Datos'!$C9),"") -> Entrantes | D9: =IFERROR(IF('Datos'!$D9="","",'Datos'!$D9),"") -> 90 | E9: =IFERROR(IF('Datos'!$L9="","",'Datos'!$L9),"") -> 0.052023121 | F9: =IFERROR(IF('Datos'!$M9="","",'Datos'!$M9),"") -> 0.1 | G9: =IFERROR(IF(OR($E9="",$F9=""),"",IF($E9>=$F9,"Alta","Baja")),"") -> Baja | H9: =IFERROR(IF('Datos'!$G9="","",'Datos'!$G9),"") -> 8.4 | I9: =IFERROR(IF('Datos'!$N9="","",'Datos'!$N9),"") -> 7.4635838 | J9: =IFERROR(IF(OR($H9="",$I9=""),"",IF($H9>=$I9,"Alto","Bajo")),"") -> Alto | K9: =IFERROR(IF(OR($G9="",$J9=""),"",IF(AND($G9="Alta",$J9="Alto"),"Star",IF(AND($G9="Alta",$J9="Bajo"),"Plowhorse",IF(AND($G9="Baja",$J9="Alto"),"Puzzle","Dog")))),"") -> Puzzle | L9: =IFERROR(IF($K9="","",IF($K9="Star","Se vende y deja margen: es el plato que sostiene a su familia.",IF($K9="Plowhorse","Se vende mucho, pero deja poco margen en euros por unidad.",IF($K9="Puzzle","Deja buen margen en euros, pero se pide poco.","Ni se vende ni deja margen.")))),"") -> Deja buen margen en euros, pero se pide poco. | M9: =IFERROR(IF($K9="","",IF($K9="Star","Mantener receta y proveedor, y darle sitio destacado en la carta.",IF($K9="Plowhorse","Subir precio con cuidado o bajar coste sin tocar la ración.",IF($K9="Puzzle","Reubicar en la carta, renombrar y que la sala lo sugiera.","Retirar o reformular: ocupa sitio en la carta y en la cocina.")))),"") -> Reubicar en la carta, renombrar y que la sala lo sugiera.
A10: 6 | B10: =IFERROR(IF('Datos'!$B10="","",'Datos'!$B10),"") -> Alcachofas confitadas con jamón | C10: =IFERROR(IF('Datos'!$C10="","",'Datos'!$C10),"") -> Entrantes | D10: =IFERROR(IF('Datos'!$D10="","",'Datos'!$D10),"") -> 120 | E10: =IFERROR(IF('Datos'!$L10="","",'Datos'!$L10),"") -> 0.069364162 | F10: =IFERROR(IF('Datos'!$M10="","",'Datos'!$M10),"") -> 0.1 | G10: =IFERROR(IF(OR($E10="",$F10=""),"",IF($E10>=$F10,"Alta","Baja")),"") -> Baja | H10: =IFERROR(IF('Datos'!$G10="","",'Datos'!$G10),"") -> 7.8 | I10: =IFERROR(IF('Datos'!$N10="","",'Datos'!$N10),"") -> 7.4635838 | J10: =IFERROR(IF(OR($H10="",$I10=""),"",IF($H10>=$I10,"Alto","Bajo")),"") -> Alto | K10: =IFERROR(IF(OR($G10="",$J10=""),"",IF(AND($G10="Alta",$J10="Alto"),"Star",IF(AND($G10="Alta",$J10="Bajo"),"Plowhorse",IF(AND($G10="Baja",$J10="Alto"),"Puzzle","Dog")))),"") -> Puzzle | L10: =IFERROR(IF($K10="","",IF($K10="Star","Se vende y deja margen: es el plato que sostiene a su familia.",IF($K10="Plowhorse","Se vende mucho, pero deja poco margen en euros por unidad.",IF($K10="Puzzle","Deja buen margen en euros, pero se pide poco.","Ni se vende ni deja margen.")))),"") -> Deja buen margen en euros, pero se pide poco. | M10: =IFERROR(IF($K10="","",IF($K10="Star","Mantener receta y proveedor, y darle sitio destacado en la carta.",IF($K10="Plowhorse","Subir precio con cuidado o bajar coste sin tocar la ración.",IF($K10="Puzzle","Reubicar en la carta, renombrar y que la sala lo sugiera.","Retirar o reformular: ocupa sitio en la carta y en la cocina.")))),"") -> Reubicar en la carta, renombrar y que la sala lo sugiera.
A11: 7 | B11: =IFERROR(IF('Datos'!$B11="","",'Datos'!$B11),"") -> Sopa de tomate asado con albahaca | C11: =IFERROR(IF('Datos'!$C11="","",'Datos'!$C11),"") -> Entrantes | D11: =IFERROR(IF('Datos'!$D11="","",'Datos'!$D11),"") -> 150 | E11: =IFERROR(IF('Datos'!$L11="","",'Datos'!$L11),"") -> 0.086705202 | F11: =IFERROR(IF('Datos'!$M11="","",'Datos'!$M11),"") -> 0.1 | G11: =IFERROR(IF(OR($E11="",$F11=""),"",IF($E11>=$F11,"Alta","Baja")),"") -> Baja | H11: =IFERROR(IF('Datos'!$G11="","",'Datos'!$G11),"") -> 6 | I11: =IFERROR(IF('Datos'!$N11="","",'Datos'!$N11),"") -> 7.4635838 | J11: =IFERROR(IF(OR($H11="",$I11=""),"",IF($H11>=$I11,"Alto","Bajo")),"") -> Bajo | K11: =IFERROR(IF(OR($G11="",$J11=""),"",IF(AND($G11="Alta",$J11="Alto"),"Star",IF(AND($G11="Alta",$J11="Bajo"),"Plowhorse",IF(AND($G11="Baja",$J11="Alto"),"Puzzle","Dog")))),"") -> Dog | L11: =IFERROR(IF($K11="","",IF($K11="Star","Se vende y deja margen: es el plato que sostiene a su familia.",IF($K11="Plowhorse","Se vende mucho, pero deja poco margen en euros por unidad.",IF($K11="Puzzle","Deja buen margen en euros, pero se pide poco.","Ni se vende ni deja margen.")))),"") -> Ni se vende ni deja margen. | M11: =IFERROR(IF($K11="","",IF($K11="Star","Mantener receta y proveedor, y darle sitio destacado en la carta.",IF($K11="Plowhorse","Subir precio con cuidado o bajar coste sin tocar la ración.",IF($K11="Puzzle","Reubicar en la carta, renombrar y que la sala lo sugiera.","Retirar o reformular: ocupa sitio en la carta y en la cocina.")))),"") -> Retirar o reformular: ocupa sitio en la carta y en la cocina.
A12: 8 | B12: =IFERROR(IF('Datos'!$B12="","",'Datos'!$B12),"") -> Solomillo de cerdo ibérico con puré de boniato | C12: =IFERROR(IF('Datos'!$C12="","",'Datos'!$C12),"") -> Principales | D12: =IFERROR(IF('Datos'!$D12="","",'Datos'!$D12),"") -> 340 | E12: =IFERROR(IF('Datos'!$L12="","",'Datos'!$L12),"") -> 0.16831683 | F12: =IFERROR(IF('Datos'!$M12="","",'Datos'!$M12),"") -> 0.077777778 | G12: =IFERROR(IF(OR($E12="",$F12=""),"",IF($E12>=$F12,"Alta","Baja")),"") -> Alta | H12: =IFERROR(IF('Datos'!$G12="","",'Datos'!$G12),"") -> 11.63 | I12: =IFERROR(IF('Datos'!$N12="","",'Datos'!$N12),"") -> 10.795149 | J12: =IFERROR(IF(OR($H12="",$I12=""),"",IF($H12>=$I12,"Alto","Bajo")),"") -> Alto | K12: =IFERROR(IF(OR($G12="",$J12=""),"",IF(AND($G12="Alta",$J12="Alto"),"Star",IF(AND($G12="Alta",$J12="Bajo"),"Plowhorse",IF(AND($G12="Baja",$J12="Alto"),"Puzzle","Dog")))),"") -> Star | L12: =IFERROR(IF($K12="","",IF($K12="Star","Se vende y deja margen: es el plato que sostiene a su familia.",IF($K12="Plowhorse","Se vende mucho, pero deja poco margen en euros por unidad.",IF($K12="Puzzle","Deja buen margen en euros, pero se pide poco.","Ni se vende ni deja margen.")))),"") -> Se vende y deja margen: es el plato que sostiene a su familia. | M12: =IFERROR(IF($K12="","",IF($K12="Star","Mantener receta y proveedor, y darle sitio destacado en la carta.",IF($K12="Plowhorse","Subir precio con cuidado o bajar coste sin tocar la ración.",IF($K12="Puzzle","Reubicar en la carta, renombrar y que la sala lo sugiera.","Retirar o reformular: ocupa sitio en la carta y en la cocina.")))),"") -> Mantener receta y proveedor, y darle sitio destacado en la carta.
A13: 9 | B13: =IFERROR(IF('Datos'!$B13="","",'Datos'!$B13),"") -> Bacalao confitado al pil-pil | C13: =IFERROR(IF('Datos'!$C13="","",'Datos'!$C13),"") -> Principales | D13: =IFERROR(IF('Datos'!$D13="","",'Datos'!$D13),"") -> 190 | E13: =IFERROR(IF('Datos'!$L13="","",'Datos'!$L13),"") -> 0.094059406 | F13: =IFERROR(IF('Datos'!$M13="","",'Datos'!$M13),"") -> 0.077777778 | G13: =IFERROR(IF(OR($E13="",$F13=""),"",IF($E13>=$F13,"Alta","Baja")),"") -> Alta | H13: =IFERROR(IF('Datos'!$G13="","",'Datos'!$G13),"") -> 11.7 | I13: =IFERROR(IF('Datos'!$N13="","",'Datos'!$N13),"") -> 10.795149 | J13: =IFERROR(IF(OR($H13="",$I13=""),"",IF($H13>=$I13,"Alto","Bajo")),"") -> Alto | K13: =IFERROR(IF(OR($G13="",$J13=""),"",IF(AND($G13="Alta",$J13="Alto"),"Star",IF(AND($G13="Alta",$J13="Bajo"),"Plowhorse",IF(AND($G13="Baja",$J13="Alto"),"Puzzle","Dog")))),"") -> Star | L13: =IFERROR(IF($K13="","",IF($K13="Star","Se vende y deja margen: es el plato que sostiene a su familia.",IF($K13="Plowhorse","Se vende mucho, pero deja poco margen en euros por unidad.",IF($K13="Puzzle","Deja buen margen en euros, pero se pide poco.","Ni se vende ni deja margen.")))),"") -> Se vende y deja margen: es el plato que sostiene a su familia. | M13: =IFERROR(IF($K13="","",IF($K13="Star","Mantener receta y proveedor, y darle sitio destacado en la carta.",IF($K13="Plowhorse","Subir precio con cuidado o bajar coste sin tocar la ración.",IF($K13="Puzzle","Reubicar en la carta, renombrar y que la sala lo sugiera.","Retirar o reformular: ocupa sitio en la carta y en la cocina.")))),"") -> Mantener receta y proveedor, y darle sitio destacado en la carta.
A14: 10 | B14: =IFERROR(IF('Datos'!$B14="","",'Datos'!$B14),"") -> Hamburguesa de vaca madurada con patatas | C14: =IFERROR(IF('Datos'!$C14="","",'Datos'!$C14),"") -> Principales | D14: =IFERROR(IF('Datos'!$D14="","",'Datos'!$D14),"") -> 460 | E14: =IFERROR(IF('Datos'!$L14="","",'Datos'!$L14),"") -> 0.22772277 | F14: =IFERROR(IF('Datos'!$M14="","",'Datos'!$M14),"") -> 0.077777778 | G14: =IFERROR(IF(OR($E14="",$F14=""),"",IF($E14>=$F14,"Alta","Baja")),"") -> Alta | H14: =IFERROR(IF('Datos'!$G14="","",'Datos'!$G14),"") -> 9.3 | I14: =IFERROR(IF('Datos'!$N14="","",'Datos'!$N14),"") -> 10.795149 | J14: =IFERROR(IF(OR($H14="",$I14=""),"",IF($H14>=$I14,"Alto","Bajo")),"") -> Bajo | K14: =IFERROR(IF(OR($G14="",$J14=""),"",IF(AND($G14="Alta",$J14="Alto"),"Star",IF(AND($G14="Alta",$J14="Bajo"),"Plowhorse",IF(AND($G14="Baja",$J14="Alto"),"Puzzle","Dog")))),"") -> Plowhorse | L14: =IFERROR(IF($K14="","",IF($K14="Star","Se vende y deja margen: es el plato que sostiene a su familia.",IF($K14="Plowhorse","Se vende mucho, pero deja poco margen en euros por unidad.",IF($K14="Puzzle","Deja buen margen en euros, pero se pide poco.","Ni se vende ni deja margen.")))),"") -> Se vende mucho, pero deja poco margen en euros por unidad. | M14: =IFERROR(IF($K14="","",IF($K14="Star","Mantener receta y proveedor, y darle sitio destacado en la carta.",IF($K14="Plowhorse","Subir precio con cuidado o bajar coste sin tocar la ración.",IF($K14="Puzzle","Reubicar en la carta, renombrar y que la sala lo sugiera.","Retirar o reformular: ocupa sitio en la carta y en la cocina.")))),"") -> Subir precio con cuidado o bajar coste sin tocar la ración.
A15: 11 | B15: =IFERROR(IF('Datos'!$B15="","",'Datos'!$B15),"") -> Arroz meloso de secreto ibérico y setas | C15: =IFERROR(IF('Datos'!$C15="","",'Datos'!$C15),"") -> Principales | D15: =IFERROR(IF('Datos'!$D15="","",'Datos'!$D15),"") -> 270 | E15: =IFERROR(IF('Datos'!$L15="","",'Datos'!$L15),"") -> 0.13366337 | F15: =IFERROR(IF('Datos'!$M15="","",'Datos'!$M15),"") -> 0.077777778 | G15: =IFERROR(IF(OR($E15="",$F15=""),"",IF($E15>=$F15,"Alta","Baja")),"") -> Alta | H15: =IFERROR(IF('Datos'!$G15="","",'Datos'!$G15),"") -> 10.2 | I15: =IFERROR(IF('Datos'!$N15="","",'Datos'!$N15),"") -> 10.795149 | J15: =IFERROR(IF(OR($H15="",$I15=""),"",IF($H15>=$I15,"Alto","Bajo")),"") -> Bajo | K15: =IFERROR(IF(OR($G15="",$J15=""),"",IF(AND($G15="Alta",$J15="Alto"),"Star",IF(AND($G15="Alta",$J15="Bajo"),"Plowhorse",IF(AND($G15="Baja",$J15="Alto"),"Puzzle","Dog")))),"") -> Plowhorse | L15: =IFERROR(IF($K15="","",IF($K15="Star","Se vende y deja margen: es el plato que sostiene a su familia.",IF($K15="Plowhorse","Se vende mucho, pero deja poco margen en euros por unidad.",IF($K15="Puzzle","Deja buen margen en euros, pero se pide poco.","Ni se vende ni deja margen.")))),"") -> Se vende mucho, pero deja poco margen en euros por unidad. | M15: =IFERROR(IF($K15="","",IF($K15="Star","Mantener receta y proveedor, y darle sitio destacado en la carta.",IF($K15="Plowhorse","Subir precio con cuidado o bajar coste sin tocar la ración.",IF($K15="Puzzle","Reubicar en la carta, renombrar y que la sala lo sugiera.","Retirar o reformular: ocupa sitio en la carta y en la cocina.")))),"") -> Subir precio con cuidado o bajar coste sin tocar la ración.
A16: 12 | B16: =IFERROR(IF('Datos'!$B16="","",'Datos'!$B16),"") -> Chuletón de vaca madurada (500 g) | C16: =IFERROR(IF('Datos'!$C16="","",'Datos'!$C16),"") -> Principales | D16: =IFERROR(IF('Datos'!$D16="","",'Datos'!$D16),"") -> 110 | E16: =IFERROR(IF('Datos'!$L16="","",'Datos'!$L16),"") -> 0.054455446 | F16: =IFERROR(IF('Datos'!$M16="","",'Datos'!$M16),"") -> 0.077777778 | G16: =IFERROR(IF(OR($E16="",$F16=""),"",IF($E16>=$F16,"Alta","Baja")),"") -> Baja | H16: =IFERROR(IF('Datos'!$G16="","",'Datos'!$G16),"") -> 17.9 | I16: =IFERROR(IF('Datos'!$N16="","",'Datos'!$N16),"") -> 10.795149 | J16: =IFERROR(IF(OR($H16="",$I16=""),"",IF($H16>=$I16,"Alto","Bajo")),"") -> Alto | K16: =IFERROR(IF(OR($G16="",$J16=""),"",IF(AND($G16="Alta",$J16="Alto"),"Star",IF(AND($G16="Alta",$J16="Bajo"),"Plowhorse",IF(AND($G16="Baja",$J16="Alto"),"Puzzle","Dog")))),"") -> Puzzle | L16: =IFERROR(IF($K16="","",IF($K16="Star","Se vende y deja margen: es el plato que sostiene a su familia.",IF($K16="Plowhorse","Se vende mucho, pero deja poco margen en euros por unidad.",IF($K16="Puzzle","Deja buen margen en euros, pero se pide poco.","Ni se vende ni deja margen.")))),"") -> Deja buen margen en euros, pero se pide poco. | M16: =IFERROR(IF($K16="","",IF($K16="Star","Mantener receta y proveedor, y darle sitio destacado en la carta.",IF($K16="Plowhorse","Subir precio con cuidado o bajar coste sin tocar la ración.",IF($K16="Puzzle","Reubicar en la carta, renombrar y que la sala lo sugiera.","Retirar o reformular: ocupa sitio en la carta y en la cocina.")))),"") -> Reubicar en la carta, renombrar y que la sala lo sugiera.
... A29: 25 | B29: =IFERROR(IF('Datos'!$B29="","",'Datos'!$B29),"") | C29: =IFERROR(IF('Datos'!$C29="","",'Datos'!$C29),"") | D29: =IFERROR(IF('Datos'!$D29="","",'Datos'!$D29),"") | E29: =IFERROR(IF('Datos'!$L29="","",'Datos'!$L29),"") | F29: =IFERROR(IF('Datos'!$M29="","",'Datos'!$M29),"") | G29: =IFERROR(IF(OR($E29="",$F29=""),"",IF($E29>=$F29,"Alta","Baja")),"") | H29: =IFERROR(IF('Datos'!$G29="","",'Datos'!$G29),"") | I29: =IFERROR(IF('Datos'!$N29="","",'Datos'!$N29),"") | J29: =IFERROR(IF(OR($H29="",$I29=""),"",IF($H29>=$I29,"Alto","Bajo")),"") | K29: =IFERROR(IF(OR($G29="",$J29=""),"",IF(AND($G29="Alta",$J29="Alto"),"Star",IF(AND($G29="Alta",$J29="Bajo"),"Plowhorse",IF(AND($G29="Baja",$J29="Alto"),"Puzzle","Dog")))),"") | L29: =IFERROR(IF($K29="","",IF($K29="Star","Se vende y deja margen: es el plato que sostiene a su familia.",IF($K29="Plowhorse","Se vende mucho, pero deja poco margen en euros por unidad.",IF($K29="Puzzle","Deja buen margen en euros, pero se pide poco.","Ni se vende ni deja margen.")))),"") | M29: =IFERROR(IF($K29="","",IF($K29="Star","Mantener receta y proveedor, y darle sitio destacado en la carta.",IF($K29="Plowhorse","Subir precio con cuidado o bajar coste sin tocar la ración.",IF($K29="Puzzle","Reubicar en la carta, renombrar y que la sala lo sugiera.","Retirar o reformular: ocupa sitio en la carta y en la cocina.")))),"")
A31: RESUMEN — lo calcula el libro
B32: Clasificación | C32: Platos | D32: Uds vendidas | E32: % de las uds de la carta | F32: MC total aportado (€)
B33: Star | C33: =COUNTIF($K$5:$K$29,$B33) -> 6 | D33: =IFERROR(SUMIF($K$5:$K$29,$B33,$D$5:$D$29),"") -> 1950 | E33: =IFERROR(IF(SUM($D$5:$D$29)=0,"",$D33/SUM($D$5:$D$29)),"") -> 0.40041068 | F33: =IFERROR(SUMPRODUCT(--($K$5:$K$29=$B33),$D$5:$D$29,$H$5:$H$29),"") -> 14865.2
B34: Plowhorse | C34: =COUNTIF($K$5:$K$29,$B34) -> 6 | D34: =IFERROR(SUMIF($K$5:$K$29,$B34,$D$5:$D$29),"") -> 2040 | E34: =IFERROR(IF(SUM($D$5:$D$29)=0,"",$D34/SUM($D$5:$D$29)),"") -> 0.41889117 | F34: =IFERROR(SUMPRODUCT(--($K$5:$K$29=$B34),$D$5:$D$29,$H$5:$H$29),"") -> 16198
B35: Puzzle | C35: =COUNTIF($K$5:$K$29,$B35) -> 5 | D35: =IFERROR(SUMIF($K$5:$K$29,$B35,$D$5:$D$29),"") -> 530 | E35: =IFERROR(IF(SUM($D$5:$D$29)=0,"",$D35/SUM($D$5:$D$29)),"") -> 0.10882957 | F35: =IFERROR(SUMPRODUCT(--($K$5:$K$29=$B35),$D$5:$D$29,$H$5:$H$29),"") -> 6357
B36: Dog | C36: =COUNTIF($K$5:$K$29,$B36) -> 3 | D36: =IFERROR(SUMIF($K$5:$K$29,$B36,$D$5:$D$29),"") -> 350 | E36: =IFERROR(IF(SUM($D$5:$D$29)=0,"",$D36/SUM($D$5:$D$29)),"") -> 0.071868583 | F36: =IFERROR(SUMPRODUCT(--($K$5:$K$29=$B36),$D$5:$D$29,$H$5:$H$29),"") -> 2318

Sheet Miller
A1: Miller — popularidad × food cost %
A2: AI Chef Pro · aichef.pro — Guía Food Cost + Ingeniería de Menú
E3: Miller premia el food cost bajo; Kasavana & Smith premia el margen en euros. No siempre coinciden.
A4: # | B4: Plato | C4: Familia | D4: Uds vendidas | E4: Mix dentro de su familia (%) | F4: Umbral de popularidad de su familia (%) | G4: Popularidad | H4: Food cost del plato (%) | I4: Food cost medio ponderado de su familia (%) | J4: Nivel de food cost | K4: Clasificación | L4: Qué significa | M4: Acción recomendada
A5: 1 | B5: =IFERROR(IF('Datos'!$B5="","",'Datos'!$B5),"") -> Croquetas de jamón ibérico (6 ud) | C5: =IFERROR(IF('Datos'!$C5="","",'Datos'!$C5),"") -> Entrantes | D5: =IFERROR(IF('Datos'!$D5="","",'Datos'!$D5),"") -> 420 | E5: =IFERROR(IF('Datos'!$L5="","",'Datos'!$L5),"") -> 0.24277457 | F5: =IFERROR(IF('Datos'!$M5="","",'Datos'!$M5),"") -> 0.1 | G5: =IFERROR(IF(OR($E5="",$F5=""),"",IF($E5>=$F5,"Alta","Baja")),"") -> Alta | H5: =IFERROR(IF('Datos'!$H5="","",'Datos'!$H5),"") -> 0.24418605 | I5: =IFERROR(IF('Datos'!$O5="","",'Datos'!$O5),"") -> 0.30714746 | J5: =IFERROR(IF(OR($H5="",$I5=""),"",IF($H5<=$I5,"Bajo","Alto")),"") -> Bajo | K5: =IFERROR(IF(OR($G5="",$J5=""),"",IF(AND($G5="Alta",$J5="Bajo"),"Winner",IF(AND($G5="Baja",$J5="Alto"),"Loser","Marginal"))),"") -> Winner | L5: =IFERROR(IF($K5="","",IF($K5="Winner","Popular y con el food cost por debajo de la media de su familia.",IF($K5="Marginal","Cumple en una sola de las dos: o vende, o tiene el food cost sano.","Poco pedido y con el food cost por encima de su familia."))),"") -> Popular y con el food cost por debajo de la media de su familia. | M5: =IFERROR(IF($K5="","",IF($K5="Winner","Mantener y proteger el escandallo: es el que aguanta una subida del proveedor.",IF($K5="Marginal","Mirar las otras lecturas antes de tocarlo: el problema es de precio o es de carta.","Reformular la receta o retirarlo de la carta."))),"") -> Mantener y proteger el escandallo: es el que aguanta una subida del proveedor.
A6: 2 | B6: =IFERROR(IF('Datos'!$B6="","",'Datos'!$B6),"") -> Ensalada de tomate rosa, ventresca y cebolleta | C6: =IFERROR(IF('Datos'!$C6="","",'Datos'!$C6),"") -> Entrantes | D6: =IFERROR(IF('Datos'!$D6="","",'Datos'!$D6),"") -> 310 | E6: =IFERROR(IF('Datos'!$L6="","",'Datos'!$L6),"") -> 0.17919075 | F6: =IFERROR(IF('Datos'!$M6="","",'Datos'!$M6),"") -> 0.1 | G6: =IFERROR(IF(OR($E6="",$F6=""),"",IF($E6>=$F6,"Alta","Baja")),"") -> Alta | H6: =IFERROR(IF('Datos'!$H6="","",'Datos'!$H6),"") -> 0.30508475 | I6: =IFERROR(IF('Datos'!$O6="","",'Datos'!$O6),"") -> 0.30714746 | J6: =IFERROR(IF(OR($H6="",$I6=""),"",IF($H6<=$I6,"Bajo","Alto")),"") -> Bajo | K6: =IFERROR(IF(OR($G6="",$J6=""),"",IF(AND($G6="Alta",$J6="Bajo"),"Winner",IF(AND($G6="Baja",$J6="Alto"),"Loser","Marginal"))),"") -> Winner | L6: =IFERROR(IF($K6="","",IF($K6="Winner","Popular y con el food cost por debajo de la media de su familia.",IF($K6="Marginal","Cumple en una sola de las dos: o vende, o tiene el food cost sano.","Poco pedido y con el food cost por encima de su familia."))),"") -> Popular y con el food cost por debajo de la media de su familia. | M6: =IFERROR(IF($K6="","",IF($K6="Winner","Mantener y proteger el escandallo: es el que aguanta una subida del proveedor.",IF($K6="Marginal","Mirar las otras lecturas antes de tocarlo: el problema es de precio o es de carta.","Reformular la receta o retirarlo de la carta."))),"") -> Mantener y proteger el escandallo: es el que aguanta una subida del proveedor.
A7: 3 | B7: =IFERROR(IF('Datos'!$B7="","",'Datos'!$B7),"") -> Gambas al ajillo | C7: =IFERROR(IF('Datos'!$C7="","",'Datos'!$C7),"") -> Entrantes | D7: =IFERROR(IF('Datos'!$D7="","",'Datos'!$D7),"") -> 260 | E7: =IFERROR(IF('Datos'!$L7="","",'Datos'!$L7),"") -> 0.15028902 | F7: =IFERROR(IF('Datos'!$M7="","",'Datos'!$M7),"") -> 0.1 | G7: =IFERROR(IF(OR($E7="",$F7=""),"",IF($E7>=$F7,"Alta","Baja")),"") -> Alta | H7: =IFERROR(IF('Datos'!$H7="","",'Datos'!$H7),"") -> 0.44516129 | I7: =IFERROR(IF('Datos'!$O7="","",'Datos'!$O7),"") -> 0.30714746 | J7: =IFERROR(IF(OR($H7="",$I7=""),"",IF($H7<=$I7,"Bajo","Alto")),"") -> Alto | K7: =IFERROR(IF(OR($G7="",$J7=""),"",IF(AND($G7="Alta",$J7="Bajo"),"Winner",IF(AND($G7="Baja",$J7="Alto"),"Loser","Marginal"))),"") -> Marginal | L7: =IFERROR(IF($K7="","",IF($K7="Winner","Popular y con el food cost por debajo de la media de su familia.",IF($K7="Marginal","Cumple en una sola de las dos: o vende, o tiene el food cost sano.","Poco pedido y con el food cost por encima de su familia."))),"") -> Cumple en una sola de las dos: o vende, o tiene el food cost sano. | M7: =IFERROR(IF($K7="","",IF($K7="Winner","Mantener y proteger el escandallo: es el que aguanta una subida del proveedor.",IF($K7="Marginal","Mirar las otras lecturas antes de tocarlo: el problema es de precio o es de carta.","Reformular la receta o retirarlo de la carta."))),"") -> Mirar las otras lecturas antes de tocarlo: el problema es de precio o es de carta.
A8: 4 | B8: =IFERROR(IF('Datos'!$B8="","",'Datos'!$B8),"") -> Huevos rotos con patatas y chistorra | C8: =IFERROR(IF('Datos'!$C8="","",'Datos'!$C8),"") -> Entrantes | D8: =IFERROR(IF('Datos'!$D8="","",'Datos'!$D8),"") -> 380 | E8: =IFERROR(IF('Datos'!$L8="","",'Datos'!$L8),"") -> 0.21965318 | F8: =IFERROR(IF('Datos'!$M8="","",'Datos'!$M8),"") -> 0.1 | G8: =IFERROR(IF(OR($E8="",$F8=""),"",IF($E8>=$F8,"Alta","Baja")),"") -> Alta | H8: =IFERROR(IF('Datos'!$H8="","",'Datos'!$H8),"") -> 0.24489796 | I8: =IFERROR(IF('Datos'!$O8="","",'Datos'!$O8),"") -> 0.30714746 | J8: =IFERROR(IF(OR($H8="",$I8=""),"",IF($H8<=$I8,"Bajo","Alto")),"") -> Bajo | K8: =IFERROR(IF(OR($G8="",$J8=""),"",IF(AND($G8="Alta",$J8="Bajo"),"Winner",IF(AND($G8="Baja",$J8="Alto"),"Loser","Marginal"))),"") -> Winner | L8: =IFERROR(IF($K8="","",IF($K8="Winner","Popular y con el food cost por debajo de la media de su familia.",IF($K8="Marginal","Cumple en una sola de las dos: o vende, o tiene el food cost sano.","Poco pedido y con el food cost por encima de su familia."))),"") -> Popular y con el food cost por debajo de la media de su familia. | M8: =IFERROR(IF($K8="","",IF($K8="Winner","Mantener y proteger el escandallo: es el que aguanta una subida del proveedor.",IF($K8="Marginal","Mirar las otras lecturas antes de tocarlo: el problema es de precio o es de carta.","Reformular la receta o retirarlo de la carta."))),"") -> Mantener y proteger el escandallo: es el que aguanta una subida del proveedor.
A9: 5 | B9: =IFERROR(IF('Datos'!$B9="","",'Datos'!$B9),"") -> Tabla de quesos de la zona | C9: =IFERROR(IF('Datos'!$C9="","",'Datos'!$C9),"") -> Entrantes | D9: =IFERROR(IF('Datos'!$D9="","",'Datos'!$D9),"") -> 90 | E9: =IFERROR(IF('Datos'!$L9="","",'Datos'!$L9),"") -> 0.052023121 | F9: =IFERROR(IF('Datos'!$M9="","",'Datos'!$M9),"") -> 0.1 | G9: =IFERROR(IF(OR($E9="",$F9=""),"",IF($E9>=$F9,"Alta","Baja")),"") -> Baja | H9: =IFERROR(IF('Datos'!$H9="","",'Datos'!$H9),"") -> 0.38235294 | I9: =IFERROR(IF('Datos'!$O9="","",'Datos'!$O9),"") -> 0.30714746 | J9: =IFERROR(IF(OR($H9="",$I9=""),"",IF($H9<=$I9,"Bajo","Alto")),"") -> Alto | K9: =IFERROR(IF(OR($G9="",$J9=""),"",IF(AND($G9="Alta",$J9="Bajo"),"Winner",IF(AND($G9="Baja",$J9="Alto"),"Loser","Marginal"))),"") -> Loser | L9: =IFERROR(IF($K9="","",IF($K9="Winner","Popular y con el food cost por debajo de la media de su familia.",IF($K9="Marginal","Cumple en una sola de las dos: o vende, o tiene el food cost sano.","Poco pedido y con el food cost por encima de su familia."))),"") -> Poco pedido y con el food cost por encima de su familia. | M9: =IFERROR(IF($K9="","",IF($K9="Winner","Mantener y proteger el escandallo: es el que aguanta una subida del proveedor.",IF($K9="Marginal","Mirar las otras lecturas antes de tocarlo: el problema es de precio o es de carta.","Reformular la receta o retirarlo de la carta."))),"") -> Reformular la receta o retirarlo de la carta.
A10: 6 | B10: =IFERROR(IF('Datos'!$B10="","",'Datos'!$B10),"") -> Alcachofas confitadas con jamón | C10: =IFERROR(IF('Datos'!$C10="","",'Datos'!$C10),"") -> Entrantes | D10: =IFERROR(IF('Datos'!$D10="","",'Datos'!$D10),"") -> 120 | E10: =IFERROR(IF('Datos'!$L10="","",'Datos'!$L10),"") -> 0.069364162 | F10: =IFERROR(IF('Datos'!$M10="","",'Datos'!$M10),"") -> 0.1 | G10: =IFERROR(IF(OR($E10="",$F10=""),"",IF($E10>=$F10,"Alta","Baja")),"") -> Baja | H10: =IFERROR(IF('Datos'!$H10="","",'Datos'!$H10),"") -> 0.28440367 | I10: =IFERROR(IF('Datos'!$O10="","",'Datos'!$O10),"") -> 0.30714746 | J10: =IFERROR(IF(OR($H10="",$I10=""),"",IF($H10<=$I10,"Bajo","Alto")),"") -> Bajo | K10: =IFERROR(IF(OR($G10="",$J10=""),"",IF(AND($G10="Alta",$J10="Bajo"),"Winner",IF(AND($G10="Baja",$J10="Alto"),"Loser","Marginal"))),"") -> Marginal | L10: =IFERROR(IF($K10="","",IF($K10="Winner","Popular y con el food cost por debajo de la media de su familia.",IF($K10="Marginal","Cumple en una sola de las dos: o vende, o tiene el food cost sano.","Poco pedido y con el food cost por encima de su familia."))),"") -> Cumple en una sola de las dos: o vende, o tiene el food cost sano. | M10: =IFERROR(IF($K10="","",IF($K10="Winner","Mantener y proteger el escandallo: es el que aguanta una subida del proveedor.",IF($K10="Marginal","Mirar las otras lecturas antes de tocarlo: el problema es de precio o es de carta.","Reformular la receta o retirarlo de la carta."))),"") -> Mirar las otras lecturas antes de tocarlo: el problema es de precio o es de carta.
A11: 7 | B11: =IFERROR(IF('Datos'!$B11="","",'Datos'!$B11),"") -> Sopa de tomate asado con albahaca | C11: =IFERROR(IF('Datos'!$C11="","",'Datos'!$C11),"") -> Entrantes | D11: =IFERROR(IF('Datos'!$D11="","",'Datos'!$D11),"") -> 150 | E11: =IFERROR(IF('Datos'!$L11="","",'Datos'!$L11),"") -> 0.086705202 | F11: =IFERROR(IF('Datos'!$M11="","",'Datos'!$M11),"") -> 0.1 | G11: =IFERROR(IF(OR($E11="",$F11=""),"",IF($E11>=$F11,"Alta","Baja")),"") -> Baja | H11: =IFERROR(IF('Datos'!$H11="","",'Datos'!$H11),"") -> 0.16666667 | I11: =IFERROR(IF('Datos'!$O11="","",'Datos'!$O11),"") -> 0.30714746 | J11: =IFERROR(IF(OR($H11="",$I11=""),"",IF($H11<=$I11,"Bajo","Alto")),"") -> Bajo | K11: =IFERROR(IF(OR($G11="",$J11=""),"",IF(AND($G11="Alta",$J11="Bajo"),"Winner",IF(AND($G11="Baja",$J11="Alto"),"Loser","Marginal"))),"") -> Marginal | L11: =IFERROR(IF($K11="","",IF($K11="Winner","Popular y con el food cost por debajo de la media de su familia.",IF($K11="Marginal","Cumple en una sola de las dos: o vende, o tiene el food cost sano.","Poco pedido y con el food cost por encima de su familia."))),"") -> Cumple en una sola de las dos: o vende, o tiene el food cost sano. | M11: =IFERROR(IF($K11="","",IF($K11="Winner","Mantener y proteger el escandallo: es el que aguanta una subida del proveedor.",IF($K11="Marginal","Mirar las otras lecturas antes de tocarlo: el problema es de precio o es de carta.","Reformular la receta o retirarlo de la carta."))),"") -> Mirar las otras lecturas antes de tocarlo: el problema es de precio o es de carta.
A12: 8 | B12: =IFERROR(IF('Datos'!$B12="","",'Datos'!$B12),"") -> Solomillo de cerdo ibérico con puré de boniato | C12: =IFERROR(IF('Datos'!$C12="","",'Datos'!$C12),"") -> Principales | D12: =IFERROR(IF('Datos'!$D12="","",'Datos'!$D12),"") -> 340 | E12: =IFERROR(IF('Datos'!$L12="","",'Datos'!$L12),"") -> 0.16831683 | F12: =IFERROR(IF('Datos'!$M12="","",'Datos'!$M12),"") -> 0.077777778 | G12: =IFERROR(IF(OR($E12="",$F12=""),"",IF($E12>=$F12,"Alta","Baja")),"") -> Alta | H12: =IFERROR(IF('Datos'!$H12="","",'Datos'!$H12),"") -> 0.32774566 | I12: =IFERROR(IF('Datos'!$O12="","",'Datos'!$O12),"") -> 0.35587523 | J12: =IFERROR(IF(OR($H12="",$I12=""),"",IF($H12<=$I12,"Bajo","Alto")),"") -> Bajo | K12: =IFERROR(IF(OR($G12="",$J12=""),"",IF(AND($G12="Alta",$J12="Bajo"),"Winner",IF(AND($G12="Baja",$J12="Alto"),"Loser","Marginal"))),"") -> Winner | L12: =IFERROR(IF($K12="","",IF($K12="Winner","Popular y con el food cost por debajo de la media de su familia.",IF($K12="Marginal","Cumple en una sola de las dos: o vende, o tiene el food cost sano.","Poco pedido y con el food cost por encima de su familia."))),"") -> Popular y con el food cost por debajo de la media de su familia. | M12: =IFERROR(IF($K12="","",IF($K12="Winner","Mantener y proteger el escandallo: es el que aguanta una subida del proveedor.",IF($K12="Marginal","Mirar las otras lecturas antes de tocarlo: el problema es de precio o es de carta.","Reformular la receta o retirarlo de la carta."))),"") -> Mantener y proteger el escandallo: es el que aguanta una subida del proveedor.
A13: 9 | B13: =IFERROR(IF('Datos'!$B13="","",'Datos'!$B13),"") -> Bacalao confitado al pil-pil | C13: =IFERROR(IF('Datos'!$C13="","",'Datos'!$C13),"") -> Principales | D13: =IFERROR(IF('Datos'!$D13="","",'Datos'!$D13),"") -> 190 | E13: =IFERROR(IF('Datos'!$L13="","",'Datos'!$L13),"") -> 0.094059406 | F13: =IFERROR(IF('Datos'!$M13="","",'Datos'!$M13),"") -> 0.077777778 | G13: =IFERROR(IF(OR($E13="",$F13=""),"",IF($E13>=$F13,"Alta","Baja")),"") -> Alta | H13: =IFERROR(IF('Datos'!$H13="","",'Datos'!$H13),"") -> 0.38743455 | I13: =IFERROR(IF('Datos'!$O13="","",'Datos'!$O13),"") -> 0.35587523 | J13: =IFERROR(IF(OR($H13="",$I13=""),"",IF($H13<=$I13,"Bajo","Alto")),"") -> Alto | K13: =IFERROR(IF(OR($G13="",$J13=""),"",IF(AND($G13="Alta",$J13="Bajo"),"Winner",IF(AND($G13="Baja",$J13="Alto"),"Loser","Marginal"))),"") -> Marginal | L13: =IFERROR(IF($K13="","",IF($K13="Winner","Popular y con el food cost por debajo de la media de su familia.",IF($K13="Marginal","Cumple en una sola de las dos: o vende, o tiene el food cost sano.","Poco pedido y con el food cost por encima de su familia."))),"") -> Cumple en una sola de las dos: o vende, o tiene el food cost sano. | M13: =IFERROR(IF($K13="","",IF($K13="Winner","Mantener y proteger el escandallo: es el que aguanta una subida del proveedor.",IF($K13="Marginal","Mirar las otras lecturas antes de tocarlo: el problema es de precio o es de carta.","Reformular la receta o retirarlo de la carta."))),"") -> Mirar las otras lecturas antes de tocarlo: el problema es de precio o es de carta.
A14: 10 | B14: =IFERROR(IF('Datos'!$B14="","",'Datos'!$B14),"") -> Hamburguesa de vaca madurada con patatas | C14: =IFERROR(IF('Datos'!$C14="","",'Datos'!$C14),"") -> Principales | D14: =IFERROR(IF('Datos'!$D14="","",'Datos'!$D14),"") -> 460 | E14: =IFERROR(IF('Datos'!$L14="","",'Datos'!$L14),"") -> 0.22772277 | F14: =IFERROR(IF('Datos'!$M14="","",'Datos'!$M14),"") -> 0.077777778 | G14: =IFERROR(IF(OR($E14="",$F14=""),"",IF($E14>=$F14,"Alta","Baja")),"") -> Alta | H14: =IFERROR(IF('Datos'!$H14="","",'Datos'!$H14),"") -> 0.31617647 | I14: =IFERROR(IF('Datos'!$O14="","",'Datos'!$O14),"") -> 0.35587523 | J14: =IFERROR(IF(OR($H14="",$I14=""),"",IF($H14<=$I14,"Bajo","Alto")),"") -> Bajo | K14: =IFERROR(IF(OR($G14="",$J14=""),"",IF(AND($G14="Alta",$J14="Bajo"),"Winner",IF(AND($G14="Baja",$J14="Alto"),"Loser","Marginal"))),"") -> Winner | L14: =IFERROR(IF($K14="","",IF($K14="Winner","Popular y con el food cost por debajo de la media de su familia.",IF($K14="Marginal","Cumple en una sola de las dos: o vende, o tiene el food cost sano.","Poco pedido y con el food cost por encima de su familia."))),"") -> Popular y con el food cost por debajo de la media de su familia. | M14: =IFERROR(IF($K14="","",IF($K14="Winner","Mantener y proteger el escandallo: es el que aguanta una subida del proveedor.",IF($K14="Marginal","Mirar las otras lecturas antes de tocarlo: el problema es de precio o es de carta.","Reformular la receta o retirarlo de la carta."))),"") -> Mantener y proteger el escandallo: es el que aguanta una subida del proveedor.
A15: 11 | B15: =IFERROR(IF('Datos'!$B15="","",'Datos'!$B15),"") -> Arroz meloso de secreto ibérico y setas | C15: =IFERROR(IF('Datos'!$C15="","",'Datos'!$C15),"") -> Principales | D15: =IFERROR(IF('Datos'!$D15="","",'Datos'!$D15),"") -> 270 | E15: =IFERROR(IF('Datos'!$L15="","",'Datos'!$L15),"") -> 0.13366337 | F15: =IFERROR(IF('Datos'!$M15="","",'Datos'!$M15),"") -> 0.077777778 | G15: =IFERROR(IF(OR($E15="",$F15=""),"",IF($E15>=$F15,"Alta","Baja")),"") -> Alta | H15: =IFERROR(IF('Datos'!$H15="","",'Datos'!$H15),"") -> 0.37804878 | I15: =IFERROR(IF('Datos'!$O15="","",'Datos'!$O15),"") -> 0.35587523 | J15: =IFERROR(IF(OR($H15="",$I15=""),"",IF($H15<=$I15,"Bajo","Alto")),"") -> Alto | K15: =IFERROR(IF(OR($G15="",$J15=""),"",IF(AND($G15="Alta",$J15="Bajo"),"Winner",IF(AND($G15="Baja",$J15="Alto"),"Loser","Marginal"))),"") -> Marginal | L15: =IFERROR(IF($K15="","",IF($K15="Winner","Popular y con el food cost por debajo de la media de su familia.",IF($K15="Marginal","Cumple en una sola de las dos: o vende, o tiene el food cost sano.","Poco pedido y con el food cost por encima de su familia."))),"") -> Cumple en una sola de las dos: o vende, o tiene el food cost sano. | M15: =IFERROR(IF($K15="","",IF($K15="Winner","Mantener y proteger el escandallo: es el que aguanta una subida del proveedor.",IF($K15="Marginal","Mirar las otras lecturas antes de tocarlo: el problema es de precio o es de carta.","Reformular la receta o retirarlo de la carta."))),"") -> Mirar las otras lecturas antes de tocarlo: el problema es de precio o es de carta.
A16: 12 | B16: =IFERROR(IF('Datos'!$B16="","",'Datos'!$B16),"") -> Chuletón de vaca madurada (500 g) | C16: =IFERROR(IF('Datos'!$C16="","",'Datos'!$C16),"") -> Principales | D16: =IFERROR(IF('Datos'!$D16="","",'Datos'!$D16),"") -> 110 | E16: =IFERROR(IF('Datos'!$L16="","",'Datos'!$L16),"") -> 0.054455446 | F16: =IFERROR(IF('Datos'!$M16="","",'Datos'!$M16),"") -> 0.077777778 | G16: =IFERROR(IF(OR($E16="",$F16=""),"",IF($E16>=$F16,"Alta","Baja")),"") -> Baja | H16: =IFERROR(IF('Datos'!$H16="","",'Datos'!$H16),"") -> 0.45259939 | I16: =IFERROR(IF('Datos'!$O16="","",'Datos'!$O16),"") -> 0.35587523 | J16: =IFERROR(IF(OR($H16="",$I16=""),"",IF($H16<=$I16,"Bajo","Alto")),"") -> Alto | K16: =IFERROR(IF(OR($G16="",$J16=""),"",IF(AND($G16="Alta",$J16="Bajo"),"Winner",IF(AND($G16="Baja",$J16="Alto"),"Loser","Marginal"))),"") -> Loser | L16: =IFERROR(IF($K16="","",IF($K16="Winner","Popular y con el food cost por debajo de la media de su familia.",IF($K16="Marginal","Cumple en una sola de las dos: o vende, o tiene el food cost sano.","Poco pedido y con el food cost por encima de su familia."))),"") -> Poco pedido y con el food cost por encima de su familia. | M16: =IFERROR(IF($K16="","",IF($K16="Winner","Mantener y proteger el escandallo: es el que aguanta una subida del proveedor.",IF($K16="Marginal","Mirar las otras lecturas antes de tocarlo: el problema es de precio o es de carta.","Reformular la receta o retirarlo de la carta."))),"") -> Reformular la receta o retirarlo de la carta.
... A29: 25 | B29: =IFERROR(IF('Datos'!$B29="","",'Datos'!$B29),"") | C29: =IFERROR(IF('Datos'!$C29="","",'Datos'!$C29),"") | D29: =IFERROR(IF('Datos'!$D29="","",'Datos'!$D29),"") | E29: =IFERROR(IF('Datos'!$L29="","",'Datos'!$L29),"") | F29: =IFERROR(IF('Datos'!$M29="","",'Datos'!$M29),"") | G29: =IFERROR(IF(OR($E29="",$F29=""),"",IF($E29>=$F29,"Alta","Baja")),"") | H29: =IFERROR(IF('Datos'!$H29="","",'Datos'!$H29),"") | I29: =IFERROR(IF('Datos'!$O29="","",'Datos'!$O29),"") | J29: =IFERROR(IF(OR($H29="",$I29=""),"",IF($H29<=$I29,"Bajo","Alto")),"") | K29: =IFERROR(IF(OR($G29="",$J29=""),"",IF(AND($G29="Alta",$J29="Bajo"),"Winner",IF(AND($G29="Baja",$J29="Alto"),"Loser","Marginal"))),"") | L29: =IFERROR(IF($K29="","",IF($K29="Winner","Popular y con el food cost por debajo de la media de su familia.",IF($K29="Marginal","Cumple en una sola de las dos: o vende, o tiene el food cost sano.","Poco pedido y con el food cost por encima de su familia."))),"") | M29: =IFERROR(IF($K29="","",IF($K29="Winner","Mantener y proteger el escandallo: es el que aguanta una subida del proveedor.",IF($K29="Marginal","Mirar las otras lecturas antes de tocarlo: el problema es de precio o es de carta.","Reformular la receta o retirarlo de la carta."))),"")
A31: RESUMEN — lo calcula el libro
B32: Clasificación | C32: Platos | D32: Uds vendidas | E32: % de las uds de la carta | F32: Food cost medio ponderado del grupo (%)
B33: Winner | C33: =COUNTIF($K$5:$K$29,$B33) -> 8 | D33: =IFERROR(SUMIF($K$5:$K$29,$B33,$D$5:$D$29),"") -> 2940 | E33: =IFERROR(IF(SUM($D$5:$D$29)=0,"",$D33/SUM($D$5:$D$29)),"") -> 0.6036961 | F33: =IFERROR(IF($D33=0,"",SUMPRODUCT(--($K$5:$K$29=$B33),$D$5:$D$29,$H$5:$H$29)/$D33),"") -> 0.26906401
B34: Marginal | C34: =COUNTIF($K$5:$K$29,$B34) -> 7 | D34: =IFERROR(SUMIF($K$5:$K$29,$B34,$D$5:$D$29),"") -> 1460 | E34: =IFERROR(IF(SUM($D$5:$D$29)=0,"",$D34/SUM($D$5:$D$29)),"") -> 0.29979466 | F34: =IFERROR(IF($D34=0,"",SUMPRODUCT(--($K$5:$K$29=$B34),$D$5:$D$29,$H$5:$H$29)/$D34),"") -> 0.32030632
B35: Loser | C35: =COUNTIF($K$5:$K$29,$B35) -> 5 | D35: =IFERROR(SUMIF($K$5:$K$29,$B35,$D$5:$D$29),"") -> 470 | E35: =IFERROR(IF(SUM($D$5:$D$29)=0,"",$D35/SUM($D$5:$D$29)),"") -> 0.09650924 | F35: =IFERROR(IF($D35=0,"",SUMPRODUCT(--($K$5:$K$29=$B35),$D$5:$D$29,$H$5:$H$29)/$D35),"") -> 0.40689192

Sheet Pavesic
A1: Pavesic — food cost % × margen ponderado por unidades
A2: AI Chef Pro · aichef.pro — Guía Food Cost + Ingeniería de Menú
E3: El margen ponderado (MC × uds) mide cuánto dinero aporta el plato al total, no cuánto deja por unidad.
A4: # | B4: Plato | C4: Familia | D4: Uds vendidas | E4: Food cost del plato (%) | F4: Food cost medio ponderado de su familia (%) | G4: Nivel de food cost | H4: MC ponderado: MC × uds (€) | I4: Media del MC ponderado de su familia (€) | J4: Nivel de MC ponderado | K4: Clasificación | L4: Qué significa | M4: Acción recomendada
A5: 1 | B5: =IFERROR(IF('Datos'!$B5="","",'Datos'!$B5),"") -> Croquetas de jamón ibérico (6 ud) | C5: =IFERROR(IF('Datos'!$C5="","",'Datos'!$C5),"") -> Entrantes | D5: =IFERROR(IF('Datos'!$D5="","",'Datos'!$D5),"") -> 420 | E5: =IFERROR(IF('Datos'!$H5="","",'Datos'!$H5),"") -> 0.24418605 | F5: =IFERROR(IF('Datos'!$O5="","",'Datos'!$O5),"") -> 0.30714746 | G5: =IFERROR(IF(OR($E5="",$F5=""),"",IF($E5<=$F5,"Bajo","Alto")),"") -> Bajo | H5: =IFERROR(IF('Datos'!$P5="","",'Datos'!$P5),"") -> 2730 | I5: =IFERROR(IF('Datos'!$Q5="","",'Datos'!$Q5),"") -> 1844.5714 | J5: =IFERROR(IF(OR($H5="",$I5=""),"",IF($H5>=$I5,"Alto","Bajo")),"") -> Alto | K5: =IFERROR(IF(OR($G5="",$J5=""),"",IF(AND($G5="Bajo",$J5="Alto"),"Prime",IF(AND($G5="Alto",$J5="Alto"),"Standard",IF(AND($G5="Bajo",$J5="Bajo"),"Sleeper","Problem")))),"") -> Prime | L5: =IFERROR(IF($K5="","",IF($K5="Prime","Food cost bajo y aporta mucho margen en euros al total.",IF($K5="Standard","Aporta mucho margen en euros pese a tener el food cost alto.",IF($K5="Sleeper","Food cost sano, pero aporta poco margen en euros al total.","Food cost alto y aporta poco margen en euros al total.")))),"") -> Food cost bajo y aporta mucho margen en euros al total. | M5: =IFERROR(IF($K5="","",IF($K5="Prime","Mantener y promocionar: aquí está el dinero de la familia.",IF($K5="Standard","Vigilar el escandallo: gana por volumen, no por eficiencia.",IF($K5="Sleeper","Darle visibilidad: el margen está, falta que se pida.","Reformular la receta o retirarlo de la carta.")))),"") -> Mantener y promocionar: aquí está el dinero de la familia.
A6: 2 | B6: =IFERROR(IF('Datos'!$B6="","",'Datos'!$B6),"") -> Ensalada de tomate rosa, ventresca y cebolleta | C6: =IFERROR(IF('Datos'!$C6="","",'Datos'!$C6),"") -> Entrantes | D6: =IFERROR(IF('Datos'!$D6="","",'Datos'!$D6),"") -> 310 | E6: =IFERROR(IF('Datos'!$H6="","",'Datos'!$H6),"") -> 0.30508475 | F6: =IFERROR(IF('Datos'!$O6="","",'Datos'!$O6),"") -> 0.30714746 | G6: =IFERROR(IF(OR($E6="",$F6=""),"",IF($E6<=$F6,"Bajo","Alto")),"") -> Bajo | H6: =IFERROR(IF('Datos'!$P6="","",'Datos'!$P6),"") -> 2542 | I6: =IFERROR(IF('Datos'!$Q6="","",'Datos'!$Q6),"") -> 1844.5714 | J6: =IFERROR(IF(OR($H6="",$I6=""),"",IF($H6>=$I6,"Alto","Bajo")),"") -> Alto | K6: =IFERROR(IF(OR($G6="",$J6=""),"",IF(AND($G6="Bajo",$J6="Alto"),"Prime",IF(AND($G6="Alto",$J6="Alto"),"Standard",IF(AND($G6="Bajo",$J6="Bajo"),"Sleeper","Problem")))),"") -> Prime | L6: =IFERROR(IF($K6="","",IF($K6="Prime","Food cost bajo y aporta mucho margen en euros al total.",IF($K6="Standard","Aporta mucho margen en euros pese a tener el food cost alto.",IF($K6="Sleeper","Food cost sano, pero aporta poco margen en euros al total.","Food cost alto y aporta poco margen en euros al total.")))),"") -> Food cost bajo y aporta mucho margen en euros al total. | M6: =IFERROR(IF($K6="","",IF($K6="Prime","Mantener y promocionar: aquí está el dinero de la familia.",IF($K6="Standard","Vigilar el escandallo: gana por volumen, no por eficiencia.",IF($K6="Sleeper","Darle visibilidad: el margen está, falta que se pida.","Reformular la receta o retirarlo de la carta.")))),"") -> Mantener y promocionar: aquí está el dinero de la familia.
A7: 3 | B7: =IFERROR(IF('Datos'!$B7="","",'Datos'!$B7),"") -> Gambas al ajillo | C7: =IFERROR(IF('Datos'!$C7="","",'Datos'!$C7),"") -> Entrantes | D7: =IFERROR(IF('Datos'!$D7="","",'Datos'!$D7),"") -> 260 | E7: =IFERROR(IF('Datos'!$H7="","",'Datos'!$H7),"") -> 0.44516129 | F7: =IFERROR(IF('Datos'!$O7="","",'Datos'!$O7),"") -> 0.30714746 | G7: =IFERROR(IF(OR($E7="",$F7=""),"",IF($E7<=$F7,"Bajo","Alto")),"") -> Alto | H7: =IFERROR(IF('Datos'!$P7="","",'Datos'!$P7),"") -> 2236 | I7: =IFERROR(IF('Datos'!$Q7="","",'Datos'!$Q7),"") -> 1844.5714 | J7: =IFERROR(IF(OR($H7="",$I7=""),"",IF($H7>=$I7,"Alto","Bajo")),"") -> Alto | K7: =IFERROR(IF(OR($G7="",$J7=""),"",IF(AND($G7="Bajo",$J7="Alto"),"Prime",IF(AND($G7="Alto",$J7="Alto"),"Standard",IF(AND($G7="Bajo",$J7="Bajo"),"Sleeper","Problem")))),"") -> Standard | L7: =IFERROR(IF($K7="","",IF($K7="Prime","Food cost bajo y aporta mucho margen en euros al total.",IF($K7="Standard","Aporta mucho margen en euros pese a tener el food cost alto.",IF($K7="Sleeper","Food cost sano, pero aporta poco margen en euros al total.","Food cost alto y aporta poco margen en euros al total.")))),"") -> Aporta mucho margen en euros pese a tener el food cost alto. | M7: =IFERROR(IF($K7="","",IF($K7="Prime","Mantener y promocionar: aquí está el dinero de la familia.",IF($K7="Standard","Vigilar el escandallo: gana por volumen, no por eficiencia.",IF($K7="Sleeper","Darle visibilidad: el margen está, falta que se pida.","Reformular la receta o retirarlo de la carta.")))),"") -> Vigilar el escandallo: gana por volumen, no por eficiencia.
A8: 4 | B8: =IFERROR(IF('Datos'!$B8="","",'Datos'!$B8),"") -> Huevos rotos con patatas y chistorra | C8: =IFERROR(IF('Datos'!$C8="","",'Datos'!$C8),"") -> Entrantes | D8: =IFERROR(IF('Datos'!$D8="","",'Datos'!$D8),"") -> 380 | E8: =IFERROR(IF('Datos'!$H8="","",'Datos'!$H8),"") -> 0.24489796 | F8: =IFERROR(IF('Datos'!$O8="","",'Datos'!$O8),"") -> 0.30714746 | G8: =IFERROR(IF(OR($E8="",$F8=""),"",IF($E8<=$F8,"Bajo","Alto")),"") -> Bajo | H8: =IFERROR(IF('Datos'!$P8="","",'Datos'!$P8),"") -> 2812 | I8: =IFERROR(IF('Datos'!$Q8="","",'Datos'!$Q8),"") -> 1844.5714 | J8: =IFERROR(IF(OR($H8="",$I8=""),"",IF($H8>=$I8,"Alto","Bajo")),"") -> Alto | K8: =IFERROR(IF(OR($G8="",$J8=""),"",IF(AND($G8="Bajo",$J8="Alto"),"Prime",IF(AND($G8="Alto",$J8="Alto"),"Standard",IF(AND($G8="Bajo",$J8="Bajo"),"Sleeper","Problem")))),"") -> Prime | L8: =IFERROR(IF($K8="","",IF($K8="Prime","Food cost bajo y aporta mucho margen en euros al total.",IF($K8="Standard","Aporta mucho margen en euros pese a tener el food cost alto.",IF($K8="Sleeper","Food cost sano, pero aporta poco margen en euros al total.","Food cost alto y aporta poco margen en euros al total.")))),"") -> Food cost bajo y aporta mucho margen en euros al total. | M8: =IFERROR(IF($K8="","",IF($K8="Prime","Mantener y promocionar: aquí está el dinero de la familia.",IF($K8="Standard","Vigilar el escandallo: gana por volumen, no por eficiencia.",IF($K8="Sleeper","Darle visibilidad: el margen está, falta que se pida.","Reformular la receta o retirarlo de la carta.")))),"") -> Mantener y promocionar: aquí está el dinero de la familia.
A9: 5 | B9: =IFERROR(IF('Datos'!$B9="","",'Datos'!$B9),"") -> Tabla de quesos de la zona | C9: =IFERROR(IF('Datos'!$C9="","",'Datos'!$C9),"") -> Entrantes | D9: =IFERROR(IF('Datos'!$D9="","",'Datos'!$D9),"") -> 90 | E9: =IFERROR(IF('Datos'!$H9="","",'Datos'!$H9),"") -> 0.38235294 | F9: =IFERROR(IF('Datos'!$O9="","",'Datos'!$O9),"") -> 0.30714746 | G9: =IFERROR(IF(OR($E9="",$F9=""),"",IF($E9<=$F9,"Bajo","Alto")),"") -> Alto | H9: =IFERROR(IF('Datos'!$P9="","",'Datos'!$P9),"") -> 756 | I9: =IFERROR(IF('Datos'!$Q9="","",'Datos'!$Q9),"") -> 1844.5714 | J9: =IFERROR(IF(OR($H9="",$I9=""),"",IF($H9>=$I9,"Alto","Bajo")),"") -> Bajo | K9: =IFERROR(IF(OR($G9="",$J9=""),"",IF(AND($G9="Bajo",$J9="Alto"),"Prime",IF(AND($G9="Alto",$J9="Alto"),"Standard",IF(AND($G9="Bajo",$J9="Bajo"),"Sleeper","Problem")))),"") -> Problem | L9: =IFERROR(IF($K9="","",IF($K9="Prime","Food cost bajo y aporta mucho margen en euros al total.",IF($K9="Standard","Aporta mucho margen en euros pese a tener el food cost alto.",IF($K9="Sleeper","Food cost sano, pero aporta poco margen en euros al total.","Food cost alto y aporta poco margen en euros al total.")))),"") -> Food cost alto y aporta poco margen en euros al total. | M9: =IFERROR(IF($K9="","",IF($K9="Prime","Mantener y promocionar: aquí está el dinero de la familia.",IF($K9="Standard","Vigilar el escandallo: gana por volumen, no por eficiencia.",IF($K9="Sleeper","Darle visibilidad: el margen está, falta que se pida.","Reformular la receta o retirarlo de la carta.")))),"") -> Reformular la receta o retirarlo de la carta.
A10: 6 | B10: =IFERROR(IF('Datos'!$B10="","",'Datos'!$B10),"") -> Alcachofas confitadas con jamón | C10: =IFERROR(IF('Datos'!$C10="","",'Datos'!$C10),"") -> Entrantes | D10: =IFERROR(IF('Datos'!$D10="","",'Datos'!$D10),"") -> 120 | E10: =IFERROR(IF('Datos'!$H10="","",'Datos'!$H10),"") -> 0.28440367 | F10: =IFERROR(IF('Datos'!$O10="","",'Datos'!$O10),"") -> 0.30714746 | G10: =IFERROR(IF(OR($E10="",$F10=""),"",IF($E10<=$F10,"Bajo","Alto")),"") -> Bajo | H10: =IFERROR(IF('Datos'!$P10="","",'Datos'!$P10),"") -> 936 | I10: =IFERROR(IF('Datos'!$Q10="","",'Datos'!$Q10),"") -> 1844.5714 | J10: =IFERROR(IF(OR($H10="",$I10=""),"",IF($H10>=$I10,"Alto","Bajo")),"") -> Bajo | K10: =IFERROR(IF(OR($G10="",$J10=""),"",IF(AND($G10="Bajo",$J10="Alto"),"Prime",IF(AND($G10="Alto",$J10="Alto"),"Standard",IF(AND($G10="Bajo",$J10="Bajo"),"Sleeper","Problem")))),"") -> Sleeper | L10: =IFERROR(IF($K10="","",IF($K10="Prime","Food cost bajo y aporta mucho margen en euros al total.",IF($K10="Standard","Aporta mucho margen en euros pese a tener el food cost alto.",IF($K10="Sleeper","Food cost sano, pero aporta poco margen en euros al total.","Food cost alto y aporta poco margen en euros al total.")))),"") -> Food cost sano, pero aporta poco margen en euros al total. | M10: =IFERROR(IF($K10="","",IF($K10="Prime","Mantener y promocionar: aquí está el dinero de la familia.",IF($K10="Standard","Vigilar el escandallo: gana por volumen, no por eficiencia.",IF($K10="Sleeper","Darle visibilidad: el margen está, falta que se pida.","Reformular la receta o retirarlo de la carta.")))),"") -> Darle visibilidad: el margen está, falta que se pida.
A11: 7 | B11: =IFERROR(IF('Datos'!$B11="","",'Datos'!$B11),"") -> Sopa de tomate asado con albahaca | C11: =IFERROR(IF('Datos'!$C11="","",'Datos'!$C11),"") -> Entrantes | D11: =IFERROR(IF('Datos'!$D11="","",'Datos'!$D11),"") -> 150 | E11: =IFERROR(IF('Datos'!$H11="","",'Datos'!$H11),"") -> 0.16666667 | F11: =IFERROR(IF('Datos'!$O11="","",'Datos'!$O11),"") -> 0.30714746 | G11: =IFERROR(IF(OR($E11="",$F11=""),"",IF($E11<=$F11,"Bajo","Alto")),"") -> Bajo | H11: =IFERROR(IF('Datos'!$P11="","",'Datos'!$P11),"") -> 900 | I11: =IFERROR(IF('Datos'!$Q11="","",'Datos'!$Q11),"") -> 1844.5714 | J11: =IFERROR(IF(OR($H11="",$I11=""),"",IF($H11>=$I11,"Alto","Bajo")),"") -> Bajo | K11: =IFERROR(IF(OR($G11="",$J11=""),"",IF(AND($G11="Bajo",$J11="Alto"),"Prime",IF(AND($G11="Alto",$J11="Alto"),"Standard",IF(AND($G11="Bajo",$J11="Bajo"),"Sleeper","Problem")))),"") -> Sleeper | L11: =IFERROR(IF($K11="","",IF($K11="Prime","Food cost bajo y aporta mucho margen en euros al total.",IF($K11="Standard","Aporta mucho margen en euros pese a tener el food cost alto.",IF($K11="Sleeper","Food cost sano, pero aporta poco margen en euros al total.","Food cost alto y aporta poco margen en euros al total.")))),"") -> Food cost sano, pero aporta poco margen en euros al total. | M11: =IFERROR(IF($K11="","",IF($K11="Prime","Mantener y promocionar: aquí está el dinero de la familia.",IF($K11="Standard","Vigilar el escandallo: gana por volumen, no por eficiencia.",IF($K11="Sleeper","Darle visibilidad: el margen está, falta que se pida.","Reformular la receta o retirarlo de la carta.")))),"") -> Darle visibilidad: el margen está, falta que se pida.
A12: 8 | B12: =IFERROR(IF('Datos'!$B12="","",'Datos'!$B12),"") -> Solomillo de cerdo ibérico con puré de boniato | C12: =IFERROR(IF('Datos'!$C12="","",'Datos'!$C12),"") -> Principales | D12: =IFERROR(IF('Datos'!$D12="","",'Datos'!$D12),"") -> 340 | E12: =IFERROR(IF('Datos'!$H12="","",'Datos'!$H12),"") -> 0.32774566 | F12: =IFERROR(IF('Datos'!$O12="","",'Datos'!$O12),"") -> 0.35587523 | G12: =IFERROR(IF(OR($E12="",$F12=""),"",IF($E12<=$F12,"Bajo","Alto")),"") -> Bajo | H12: =IFERROR(IF('Datos'!$P12="","",'Datos'!$P12),"") -> 3954.2 | I12: =IFERROR(IF('Datos'!$Q12="","",'Datos'!$Q12),"") -> 2422.9111 | J12: =IFERROR(IF(OR($H12="",$I12=""),"",IF($H12>=$I12,"Alto","Bajo")),"") -> Alto | K12: =IFERROR(IF(OR($G12="",$J12=""),"",IF(AND($G12="Bajo",$J12="Alto"),"Prime",IF(AND($G12="Alto",$J12="Alto"),"Standard",IF(AND($G12="Bajo",$J12="Bajo"),"Sleeper","Problem")))),"") -> Prime | L12: =IFERROR(IF($K12="","",IF($K12="Prime","Food cost bajo y aporta mucho margen en euros al total.",IF($K12="Standard","Aporta mucho margen en euros pese a tener el food cost alto.",IF($K12="Sleeper","Food cost sano, pero aporta poco margen en euros al total.","Food cost alto y aporta poco margen en euros al total.")))),"") -> Food cost bajo y aporta mucho margen en euros al total. | M12: =IFERROR(IF($K12="","",IF($K12="Prime","Mantener y promocionar: aquí está el dinero de la familia.",IF($K12="Standard","Vigilar el escandallo: gana por volumen, no por eficiencia.",IF($K12="Sleeper","Darle visibilidad: el margen está, falta que se pida.","Reformular la receta o retirarlo de la carta.")))),"") -> Mantener y promocionar: aquí está el dinero de la familia.
A13: 9 | B13: =IFERROR(IF('Datos'!$B13="","",'Datos'!$B13),"") -> Bacalao confitado al pil-pil | C13: =IFERROR(IF('Datos'!$C13="","",'Datos'!$C13),"") -> Principales | D13: =IFERROR(IF('Datos'!$D13="","",'Datos'!$D13),"") -> 190 | E13: =IFERROR(IF('Datos'!$H13="","",'Datos'!$H13),"") -> 0.38743455 | F13: =IFERROR(IF('Datos'!$O13="","",'Datos'!$O13),"") -> 0.35587523 | G13: =IFERROR(IF(OR($E13="",$F13=""),"",IF($E13<=$F13,"Bajo","Alto")),"") -> Alto | H13: =IFERROR(IF('Datos'!$P13="","",'Datos'!$P13),"") -> 2223 | I13: =IFERROR(IF('Datos'!$Q13="","",'Datos'!$Q13),"") -> 2422.9111 | J13: =IFERROR(IF(OR($H13="",$I13=""),"",IF($H13>=$I13,"Alto","Bajo")),"") -> Bajo | K13: =IFERROR(IF(OR($G13="",$J13=""),"",IF(AND($G13="Bajo",$J13="Alto"),"Prime",IF(AND($G13="Alto",$J13="Alto"),"Standard",IF(AND($G13="Bajo",$J13="Bajo"),"Sleeper","Problem")))),"") -> Problem | L13: =IFERROR(IF($K13="","",IF($K13="Prime","Food cost bajo y aporta mucho margen en euros al total.",IF($K13="Standard","Aporta mucho margen en euros pese a tener el food cost alto.",IF($K13="Sleeper","Food cost sano, pero aporta poco margen en euros al total.","Food cost alto y aporta poco margen en euros al total.")))),"") -> Food cost alto y aporta poco margen en euros al total. | M13: =IFERROR(IF($K13="","",IF($K13="Prime","Mantener y promocionar: aquí está el dinero de la familia.",IF($K13="Standard","Vigilar el escandallo: gana por volumen, no por eficiencia.",IF($K13="Sleeper","Darle visibilidad: el margen está, falta que se pida.","Reformular la receta o retirarlo de la carta.")))),"") -> Reformular la receta o retirarlo de la carta.
A14: 10 | B14: =IFERROR(IF('Datos'!$B14="","",'Datos'!$B14),"") -> Hamburguesa de vaca madurada con patatas | C14: =IFERROR(IF('Datos'!$C14="","",'Datos'!$C14),"") -> Principales | D14: =IFERROR(IF('Datos'!$D14="","",'Datos'!$D14),"") -> 460 | E14: =IFERROR(IF('Datos'!$H14="","",'Datos'!$H14),"") -> 0.31617647 | F14: =IFERROR(IF('Datos'!$O14="","",'Datos'!$O14),"") -> 0.35587523 | G14: =IFERROR(IF(OR($E14="",$F14=""),"",IF($E14<=$F14,"Bajo","Alto")),"") -> Bajo | H14: =IFERROR(IF('Datos'!$P14="","",'Datos'!$P14),"") -> 4278 | I14: =IFERROR(IF('Datos'!$Q14="","",'Datos'!$Q14),"") -> 2422.9111 | J14: =IFERROR(IF(OR($H14="",$I14=""),"",IF($H14>=$I14,"Alto","Bajo")),"") -> Alto | K14: =IFERROR(IF(OR($G14="",$J14=""),"",IF(AND($G14="Bajo",$J14="Alto"),"Prime",IF(AND($G14="Alto",$J14="Alto"),"Standard",IF(AND($G14="Bajo",$J14="Bajo"),"Sleeper","Problem")))),"") -> Prime | L14: =IFERROR(IF($K14="","",IF($K14="Prime","Food cost bajo y aporta mucho margen en euros al total.",IF($K14="Standard","Aporta mucho margen en euros pese a tener el food cost alto.",IF($K14="Sleeper","Food cost sano, pero aporta poco margen en euros al total.","Food cost alto y aporta poco margen en euros al total.")))),"") -> Food cost bajo y aporta mucho margen en euros al total. | M14: =IFERROR(IF($K14="","",IF($K14="Prime","Mantener y promocionar: aquí está el dinero de la familia.",IF($K14="Standard","Vigilar el escandallo: gana por volumen, no por eficiencia.",IF($K14="Sleeper","Darle visibilidad: el margen está, falta que se pida.","Reformular la receta o retirarlo de la carta.")))),"") -> Mantener y promocionar: aquí está el dinero de la familia.
A15: 11 | B15: =IFERROR(IF('Datos'!$B15="","",'Datos'!$B15),"") -> Arroz meloso de secreto ibérico y setas | C15: =IFERROR(IF('Datos'!$C15="","",'Datos'!$C15),"") -> Principales | D15: =IFERROR(IF('Datos'!$D15="","",'Datos'!$D15),"") -> 270 | E15: =IFERROR(IF('Datos'!$H15="","",'Datos'!$H15),"") -> 0.37804878 | F15: =IFERROR(IF('Datos'!$O15="","",'Datos'!$O15),"") -> 0.35587523 | G15: =IFERROR(IF(OR($E15="",$F15=""),"",IF($E15<=$F15,"Bajo","Alto")),"") -> Alto | H15: =IFERROR(IF('Datos'!$P15="","",'Datos'!$P15),"") -> 2754 | I15: =IFERROR(IF('Datos'!$Q15="","",'Datos'!$Q15),"") -> 2422.9111 | J15: =IFERROR(IF(OR($H15="",$I15=""),"",IF($H15>=$I15,"Alto","Bajo")),"") -> Alto | K15: =IFERROR(IF(OR($G15="",$J15=""),"",IF(AND($G15="Bajo",$J15="Alto"),"Prime",IF(AND($G15="Alto",$J15="Alto"),"Standard",IF(AND($G15="Bajo",$J15="Bajo"),"Sleeper","Problem")))),"") -> Standard | L15: =IFERROR(IF($K15="","",IF($K15="Prime","Food cost bajo y aporta mucho margen en euros al total.",IF($K15="Standard","Aporta mucho margen en euros pese a tener el food cost alto.",IF($K15="Sleeper","Food cost sano, pero aporta poco margen en euros al total.","Food cost alto y aporta poco margen en euros al total.")))),"") -> Aporta mucho margen en euros pese a tener el food cost alto. | M15: =IFERROR(IF($K15="","",IF($K15="Prime","Mantener y promocionar: aquí está el dinero de la familia.",IF($K15="Standard","Vigilar el escandallo: gana por volumen, no por eficiencia.",IF($K15="Sleeper","Darle visibilidad: el margen está, falta que se pida.","Reformular la receta o retirarlo de la carta.")))),"") -> Vigilar el escandallo: gana por volumen, no por eficiencia.
A16: 12 | B16: =IFERROR(IF('Datos'!$B16="","",'Datos'!$B16),"") -> Chuletón de vaca madurada (500 g) | C16: =IFERROR(IF('Datos'!$C16="","",'Datos'!$C16),"") -> Principales | D16: =IFERROR(IF('Datos'!$D16="","",'Datos'!$D16),"") -> 110 | E16: =IFERROR(IF('Datos'!$H16="","",'Datos'!$H16),"") -> 0.45259939 | F16: =IFERROR(IF('Datos'!$O16="","",'Datos'!$O16),"") -> 0.35587523 | G16: =IFERROR(IF(OR($E16="",$F16=""),"",IF($E16<=$F16,"Bajo","Alto")),"") -> Alto | H16: =IFERROR(IF('Datos'!$P16="","",'Datos'!$P16),"") -> 1969 | I16: =IFERROR(IF('Datos'!$Q16="","",'Datos'!$Q16),"") -> 2422.9111 | J16: =IFERROR(IF(OR($H16="",$I16=""),"",IF($H16>=$I16,"Alto","Bajo")),"") -> Bajo | K16: =IFERROR(IF(OR($G16="",$J16=""),"",IF(AND($G16="Bajo",$J16="Alto"),"Prime",IF(AND($G16="Alto",$J16="Alto"),"Standard",IF(AND($G16="Bajo",$J16="Bajo"),"Sleeper","Problem")))),"") -> Problem | L16: =IFERROR(IF($K16="","",IF($K16="Prime","Food cost bajo y aporta mucho margen en euros al total.",IF($K16="Standard","Aporta mucho margen en euros pese a tener el food cost alto.",IF($K16="Sleeper","Food cost sano, pero aporta poco margen en euros al total.","Food cost alto y aporta poco margen en euros al total.")))),"") -> Food cost alto y aporta poco margen en euros al total. | M16: =IFERROR(IF($K16="","",IF($K16="Prime","Mantener y promocionar: aquí está el dinero de la familia.",IF($K16="Standard","Vigilar el escandallo: gana por volumen, no por eficiencia.",IF($K16="Sleeper","Darle visibilidad: el margen está, falta que se pida.","Reformular la receta o retirarlo de la carta.")))),"") -> Reformular la receta o retirarlo de la carta.
... A29: 25 | B29: =IFERROR(IF('Datos'!$B29="","",'Datos'!$B29),"") | C29: =IFERROR(IF('Datos'!$C29="","",'Datos'!$C29),"") | D29: =IFERROR(IF('Datos'!$D29="","",'Datos'!$D29),"") | E29: =IFERROR(IF('Datos'!$H29="","",'Datos'!$H29),"") | F29: =IFERROR(IF('Datos'!$O29="","",'Datos'!$O29),"") | G29: =IFERROR(IF(OR($E29="",$F29=""),"",IF($E29<=$F29,"Bajo","Alto")),"") | H29: =IFERROR(IF('Datos'!$P29="","",'Datos'!$P29),"") | I29: =IFERROR(IF('Datos'!$Q29="","",'Datos'!$Q29),"") | J29: =IFERROR(IF(OR($H29="",$I29=""),"",IF($H29>=$I29,"Alto","Bajo")),"") | K29: =IFERROR(IF(OR($G29="",$J29=""),"",IF(AND($G29="Bajo",$J29="Alto"),"Prime",IF(AND($G29="Alto",$J29="Alto"),"Standard",IF(AND($G29="Bajo",$J29="Bajo"),"Sleeper","Problem")))),"") | L29: =IFERROR(IF($K29="","",IF($K29="Prime","Food cost bajo y aporta mucho margen en euros al total.",IF($K29="Standard","Aporta mucho margen en euros pese a tener el food cost alto.",IF($K29="Sleeper","Food cost sano, pero aporta poco margen en euros al total.","Food cost alto y aporta poco margen en euros al total.")))),"") | M29: =IFERROR(IF($K29="","",IF($K29="Prime","Mantener y promocionar: aquí está el dinero de la familia.",IF($K29="Standard","Vigilar el escandallo: gana por volumen, no por eficiencia.",IF($K29="Sleeper","Darle visibilidad: el margen está, falta que se pida.","Reformular la receta o retirarlo de la carta.")))),"")
A31: RESUMEN — lo calcula el libro
B32: Clasificación | C32: Platos | D32: Uds vendidas | E32: % de las uds de la carta | F32: MC ponderado total del grupo (€)
B33: Prime | C33: =COUNTIF($K$5:$K$29,$B33) -> 7 | D33: =IFERROR(SUMIF($K$5:$K$29,$B33,$D$5:$D$29),"") -> 2730 | E33: =IFERROR(IF(SUM($D$5:$D$29)=0,"",$D33/SUM($D$5:$D$29)),"") -> 0.56057495 | F33: =IFERROR(SUMIF($K$5:$K$29,$B33,$H$5:$H$29),"") -> 21408.2
B34: Standard | C34: =COUNTIF($K$5:$K$29,$B34) -> 3 | D34: =IFERROR(SUMIF($K$5:$K$29,$B34,$D$5:$D$29),"") -> 860 | E34: =IFERROR(IF(SUM($D$5:$D$29)=0,"",$D34/SUM($D$5:$D$29)),"") -> 0.17659138 | F34: =IFERROR(SUMIF($K$5:$K$29,$B34,$H$5:$H$29),"") -> 6508
B35: Sleeper | C35: =COUNTIF($K$5:$K$29,$B35) -> 4 | D35: =IFERROR(SUMIF($K$5:$K$29,$B35,$D$5:$D$29),"") -> 620 | E35: =IFERROR(IF(SUM($D$5:$D$29)=0,"",$D35/SUM($D$5:$D$29)),"") -> 0.12731006 | F35: =IFERROR(SUMIF($K$5:$K$29,$B35,$H$5:$H$29),"") -> 3992
B36: Problem | C36: =COUNTIF($K$5:$K$29,$B36) -> 6 | D36: =IFERROR(SUMIF($K$5:$K$29,$B36,$D$5:$D$29),"") -> 660 | E36: =IFERROR(IF(SUM($D$5:$D$29)=0,"",$D36/SUM($D$5:$D$29)),"") -> 0.13552361 | F36: =IFERROR(SUMIF($K$5:$K$29,$B36,$H$5:$H$29),"") -> 7830

Sheet Goal Value
A1: Goal Value (Hayes & Huffman) — el método que mete el personal
A2: AI Chef Pro · aichef.pro — Guía Food Cost + Ingeniería de Menú
E3: Goal Value = (1 − food cost %) × uds × PVP × (1 − (personal % + otros variables % + food cost %)) — el food cost pesa dos veces: es lo que separa a Goal Value de Pavesic y penaliza al plato caro de producir.
A4: # | B4: Plato | C4: Familia | D4: Uds vendidas | E4: Food cost del plato (%) | F4: PVP sin IVA (€) | G4: Goal Value del plato | H4: Uds medias de su familia | I4: PVP medio ponderado de su familia (€) | J4: Food cost medio ponderado de su familia (%) | K4: Goal Value objetivo de su familia | L4: Lectura | M4: Distancia al objetivo (índice) | N4: Qué revisar
A5: 1 | B5: =IFERROR(IF('Datos'!$B5="","",'Datos'!$B5),"") -> Croquetas de jamón ibérico (6 ud) | C5: =IFERROR(IF('Datos'!$C5="","",'Datos'!$C5),"") -> Entrantes | D5: =IFERROR(IF('Datos'!$D5="","",'Datos'!$D5),"") -> 420 | E5: =IFERROR(IF('Datos'!$H5="","",'Datos'!$H5),"") -> 0.24418605 | F5: =IFERROR(IF('Datos'!$F5="","",'Datos'!$F5),"") -> 8.6 | G5: =IFERROR(IF(OR($D5="",$E5="",$F5="",$D$33+$D$34+$E5>=1),"",(1-$E5)*$D5*$F5*(1-($D$33+$D$34+$E5))),"") -> 916.77209 | H5: =IFERROR(IF(OR('Datos'!$K5="",'Datos'!$K5=0),"",'Datos'!$J5/'Datos'!$K5),"") -> 247.14286 | I5: =IFERROR(IF(OR('Datos'!$J5="",'Datos'!$J5=0),"",SUMPRODUCT(--('Datos'!$C$5:$C$29='Datos'!$C5),'Datos'!$D$5:$D$29,'Datos'!$F$5:$F$29)/'Datos'!$J5),"") -> 10.772254 | J5: =IFERROR(IF('Datos'!$O5="","",'Datos'!$O5),"") -> 0.30714746 | K5: =IFERROR(IF(OR($H5="",$I5="",$J5="",$D$33+$D$34+$J5>=1),"",(1-$J5)*$H5*$I5*(1-($D$33+$D$34+$J5))),"") -> 503.29601 | L5: =IFERROR(IF(OR($G5="",$K5=""),"",IF($G5>=$K5,"Por encima del objetivo","Por debajo del objetivo")),"") -> Por encima del objetivo | M5: =IFERROR(IF(OR($G5="",$K5=""),"",$G5-$K5),"") -> 413.47609 | N5: =IFERROR(IF($L5="","",IF($L5="Por encima del objetivo","Cumple el objetivo de su familia: mantenlo y protégelo.",IF($E5>$J5,"Su food cost está por encima de la media de la familia: baja coste o sube precio.",IF($D5<$H5,"Vende menos que la media de su familia: es problema de carta y de sala, no de coste.","Su precio está por debajo de la media de su familia: revísalo antes de tocar la receta.")))),"") -> Cumple el objetivo de su familia: mantenlo y protégelo.
A6: 2 | B6: =IFERROR(IF('Datos'!$B6="","",'Datos'!$B6),"") -> Ensalada de tomate rosa, ventresca y cebolleta | C6: =IFERROR(IF('Datos'!$C6="","",'Datos'!$C6),"") -> Entrantes | D6: =IFERROR(IF('Datos'!$D6="","",'Datos'!$D6),"") -> 310 | E6: =IFERROR(IF('Datos'!$H6="","",'Datos'!$H6),"") -> 0.30508475 | F6: =IFERROR(IF('Datos'!$F6="","",'Datos'!$F6),"") -> 11.8 | G6: =IFERROR(IF(OR($D6="",$E6="",$F6="",$D$33+$D$34+$E6>=1),"",(1-$E6)*$D6*$F6*(1-($D$33+$D$34+$E6))),"") -> 698.83458 | H6: =IFERROR(IF(OR('Datos'!$K6="",'Datos'!$K6=0),"",'Datos'!$J6/'Datos'!$K6),"") -> 247.14286 | I6: =IFERROR(IF(OR('Datos'!$J6="",'Datos'!$J6=0),"",SUMPRODUCT(--('Datos'!$C$5:$C$29='Datos'!$C6),'Datos'!$D$5:$D$29,'Datos'!$F$5:$F$29)/'Datos'!$J6),"") -> 10.772254 | J6: =IFERROR(IF('Datos'!$O6="","",'Datos'!$O6),"") -> 0.30714746 | K6: =IFERROR(IF(OR($H6="",$I6="",$J6="",$D$33+$D$34+$J6>=1),"",(1-$J6)*$H6*$I6*(1-($D$33+$D$34+$J6))),"") -> 503.29601 | L6: =IFERROR(IF(OR($G6="",$K6=""),"",IF($G6>=$K6,"Por encima del objetivo","Por debajo del objetivo")),"") -> Por encima del objetivo | M6: =IFERROR(IF(OR($G6="",$K6=""),"",$G6-$K6),"") -> 195.53857 | N6: =IFERROR(IF($L6="","",IF($L6="Por encima del objetivo","Cumple el objetivo de su familia: mantenlo y protégelo.",IF($E6>$J6,"Su food cost está por encima de la media de la familia: baja coste o sube precio.",IF($D6<$H6,"Vende menos que la media de su familia: es problema de carta y de sala, no de coste.","Su precio está por debajo de la media de su familia: revísalo antes de tocar la receta.")))),"") -> Cumple el objetivo de su familia: mantenlo y protégelo.
A7: 3 | B7: =IFERROR(IF('Datos'!$B7="","",'Datos'!$B7),"") -> Gambas al ajillo | C7: =IFERROR(IF('Datos'!$C7="","",'Datos'!$C7),"") -> Entrantes | D7: =IFERROR(IF('Datos'!$D7="","",'Datos'!$D7),"") -> 260 | E7: =IFERROR(IF('Datos'!$H7="","",'Datos'!$H7),"") -> 0.44516129 | F7: =IFERROR(IF('Datos'!$F7="","",'Datos'!$F7),"") -> 15.5 | G7: =IFERROR(IF(OR($D7="",$E7="",$F7="",$D$33+$D$34+$E7>=1),"",(1-$E7)*$D7*$F7*(1-($D$33+$D$34+$E7))),"") -> 301.49935 | H7: =IFERROR(IF(OR('Datos'!$K7="",'Datos'!$K7=0),"",'Datos'!$J7/'Datos'!$K7),"") -> 247.14286 | I7: =IFERROR(IF(OR('Datos'!$J7="",'Datos'!$J7=0),"",SUMPRODUCT(--('Datos'!$C$5:$C$29='Datos'!$C7),'Datos'!$D$5:$D$29,'Datos'!$F$5:$F$29)/'Datos'!$J7),"") -> 10.772254 | J7: =IFERROR(IF('Datos'!$O7="","",'Datos'!$O7),"") -> 0.30714746 | K7: =IFERROR(IF(OR($H7="",$I7="",$J7="",$D$33+$D$34+$J7>=1),"",(1-$J7)*$H7*$I7*(1-($D$33+$D$34+$J7))),"") -> 503.29601 | L7: =IFERROR(IF(OR($G7="",$K7=""),"",IF($G7>=$K7,"Por encima del objetivo","Por debajo del objetivo")),"") -> Por debajo del objetivo | M7: =IFERROR(IF(OR($G7="",$K7=""),"",$G7-$K7),"") -> -201.79665 | N7: =IFERROR(IF($L7="","",IF($L7="Por encima del objetivo","Cumple el objetivo de su familia: mantenlo y protégelo.",IF($E7>$J7,"Su food cost está por encima de la media de la familia: baja coste o sube precio.",IF($D7<$H7,"Vende menos que la media de su familia: es problema de carta y de sala, no de coste.","Su precio está por debajo de la media de su familia: revísalo antes de tocar la receta.")))),"") -> Su food cost está por encima de la media de la familia: baja coste o sube precio.
A8: 4 | B8: =IFERROR(IF('Datos'!$B8="","",'Datos'!$B8),"") -> Huevos rotos con patatas y chistorra | C8: =IFERROR(IF('Datos'!$C8="","",'Datos'!$C8),"") -> Entrantes | D8: =IFERROR(IF('Datos'!$D8="","",'Datos'!$D8),"") -> 380 | E8: =IFERROR(IF('Datos'!$H8="","",'Datos'!$H8),"") -> 0.24489796 | F8: =IFERROR(IF('Datos'!$F8="","",'Datos'!$F8),"") -> 9.8 | G8: =IFERROR(IF(OR($D8="",$E8="",$F8="",$D$33+$D$34+$E8>=1),"",(1-$E8)*$D8*$F8*(1-($D$33+$D$34+$E8))),"") -> 942.30694 | H8: =IFERROR(IF(OR('Datos'!$K8="",'Datos'!$K8=0),"",'Datos'!$J8/'Datos'!$K8),"") -> 247.14286 | I8: =IFERROR(IF(OR('Datos'!$J8="",'Datos'!$J8=0),"",SUMPRODUCT(--('Datos'!$C$5:$C$29='Datos'!$C8),'Datos'!$D$5:$D$29,'Datos'!$F$5:$F$29)/'Datos'!$J8),"") -> 10.772254 | J8: =IFERROR(IF('Datos'!$O8="","",'Datos'!$O8),"") -> 0.30714746 | K8: =IFERROR(IF(OR($H8="",$I8="",$J8="",$D$33+$D$34+$J8>=1),"",(1-$J8)*$H8*$I8*(1-($D$33+$D$34+$J8))),"") -> 503.29601 | L8: =IFERROR(IF(OR($G8="",$K8=""),"",IF($G8>=$K8,"Por encima del objetivo","Por debajo del objetivo")),"") -> Por encima del objetivo | M8: =IFERROR(IF(OR($G8="",$K8=""),"",$G8-$K8),"") -> 439.01093 | N8: =IFERROR(IF($L8="","",IF($L8="Por encima del objetivo","Cumple el objetivo de su familia: mantenlo y protégelo.",IF($E8>$J8,"Su food cost está por encima de la media de la familia: baja coste o sube precio.",IF($D8<$H8,"Vende menos que la media de su familia: es problema de carta y de sala, no de coste.","Su precio está por debajo de la media de su familia: revísalo antes de tocar la receta.")))),"") -> Cumple el objetivo de su familia: mantenlo y protégelo.
A9: 5 | B9: =IFERROR(IF('Datos'!$B9="","",'Datos'!$B9),"") -> Tabla de quesos de la zona | C9: =IFERROR(IF('Datos'!$C9="","",'Datos'!$C9),"") -> Entrantes | D9: =IFERROR(IF('Datos'!$D9="","",'Datos'!$D9),"") -> 90 | E9: =IFERROR(IF('Datos'!$H9="","",'Datos'!$H9),"") -> 0.38235294 | F9: =IFERROR(IF('Datos'!$F9="","",'Datos'!$F9),"") -> 13.6 | G9: =IFERROR(IF(OR($D9="",$E9="",$F9="",$D$33+$D$34+$E9>=1),"",(1-$E9)*$D9*$F9*(1-($D$33+$D$34+$E9))),"") -> 149.42118 | H9: =IFERROR(IF(OR('Datos'!$K9="",'Datos'!$K9=0),"",'Datos'!$J9/'Datos'!$K9),"") -> 247.14286 | I9: =IFERROR(IF(OR('Datos'!$J9="",'Datos'!$J9=0),"",SUMPRODUCT(--('Datos'!$C$5:$C$29='Datos'!$C9),'Datos'!$D$5:$D$29,'Datos'!$F$5:$F$29)/'Datos'!$J9),"") -> 10.772254 | J9: =IFERROR(IF('Datos'!$O9="","",'Datos'!$O9),"") -> 0.30714746 | K9: =IFERROR(IF(OR($H9="",$I9="",$J9="",$D$33+$D$34+$J9>=1),"",(1-$J9)*$H9*$I9*(1-($D$33+$D$34+$J9))),"") -> 503.29601 | L9: =IFERROR(IF(OR($G9="",$K9=""),"",IF($G9>=$K9,"Por encima del objetivo","Por debajo del objetivo")),"") -> Por debajo del objetivo | M9: =IFERROR(IF(OR($G9="",$K9=""),"",$G9-$K9),"") -> -353.87483 | N9: =IFERROR(IF($L9="","",IF($L9="Por encima del objetivo","Cumple el objetivo de su familia: mantenlo y protégelo.",IF($E9>$J9,"Su food cost está por encima de la media de la familia: baja coste o sube precio.",IF($D9<$H9,"Vende menos que la media de su familia: es problema de carta y de sala, no de coste.","Su precio está por debajo de la media de su familia: revísalo antes de tocar la receta.")))),"") -> Su food cost está por encima de la media de la familia: baja coste o sube precio.
A10: 6 | B10: =IFERROR(IF('Datos'!$B10="","",'Datos'!$B10),"") -> Alcachofas confitadas con jamón | C10: =IFERROR(IF('Datos'!$C10="","",'Datos'!$C10),"") -> Entrantes | D10: =IFERROR(IF('Datos'!$D10="","",'Datos'!$D10),"") -> 120 | E10: =IFERROR(IF('Datos'!$H10="","",'Datos'!$H10),"") -> 0.28440367 | F10: =IFERROR(IF('Datos'!$F10="","",'Datos'!$F10),"") -> 10.9 | G10: =IFERROR(IF(OR($D10="",$E10="",$F10="",$D$33+$D$34+$E10>=1),"",(1-$E10)*$D10*$F10*(1-($D$33+$D$34+$E10))),"") -> 276.67817 | H10: =IFERROR(IF(OR('Datos'!$K10="",'Datos'!$K10=0),"",'Datos'!$J10/'Datos'!$K10),"") -> 247.14286 | I10: =IFERROR(IF(OR('Datos'!$J10="",'Datos'!$J10=0),"",SUMPRODUCT(--('Datos'!$C$5:$C$29='Datos'!$C10),'Datos'!$D$5:$D$29,'Datos'!$F$5:$F$29)/'Datos'!$J10),"") -> 10.772254 | J10: =IFERROR(IF('Datos'!$O10="","",'Datos'!$O10),"") -> 0.30714746 | K10: =IFERROR(IF(OR($H10="",$I10="",$J10="",$D$33+$D$34+$J10>=1),"",(1-$J10)*$H10*$I10*(1-($D$33+$D$34+$J10))),"") -> 503.29601 | L10: =IFERROR(IF(OR($G10="",$K10=""),"",IF($G10>=$K10,"Por encima del objetivo","Por debajo del objetivo")),"") -> Por debajo del objetivo | M10: =IFERROR(IF(OR($G10="",$K10=""),"",$G10-$K10),"") -> -226.61784 | N10: =IFERROR(IF($L10="","",IF($L10="Por encima del objetivo","Cumple el objetivo de su familia: mantenlo y protégelo.",IF($E10>$J10,"Su food cost está por encima de la media de la familia: baja coste o sube precio.",IF($D10<$H10,"Vende menos que la media de su familia: es problema de carta y de sala, no de coste.","Su precio está por debajo de la media de su familia: revísalo antes de tocar la receta.")))),"") -> Vende menos que la media de su familia: es problema de carta y de sala, no de coste.
A11: 7 | B11: =IFERROR(IF('Datos'!$B11="","",'Datos'!$B11),"") -> Sopa de tomate asado con albahaca | C11: =IFERROR(IF('Datos'!$C11="","",'Datos'!$C11),"") -> Entrantes | D11: =IFERROR(IF('Datos'!$D11="","",'Datos'!$D11),"") -> 150 | E11: =IFERROR(IF('Datos'!$H11="","",'Datos'!$H11),"") -> 0.16666667 | F11: =IFERROR(IF('Datos'!$F11="","",'Datos'!$F11),"") -> 7.2 | G11: =IFERROR(IF(OR($D11="",$E11="",$F11="",$D$33+$D$34+$E11>=1),"",(1-$E11)*$D11*$F11*(1-($D$33+$D$34+$E11))),"") -> 372 | H11: =IFERROR(IF(OR('Datos'!$K11="",'Datos'!$K11=0),"",'Datos'!$J11/'Datos'!$K11),"") -> 247.14286 | I11: =IFERROR(IF(OR('Datos'!$J11="",'Datos'!$J11=0),"",SUMPRODUCT(--('Datos'!$C$5:$C$29='Datos'!$C11),'Datos'!$D$5:$D$29,'Datos'!$F$5:$F$29)/'Datos'!$J11),"") -> 10.772254 | J11: =IFERROR(IF('Datos'!$O11="","",'Datos'!$O11),"") -> 0.30714746 | K11: =IFERROR(IF(OR($H11="",$I11="",$J11="",$D$33+$D$34+$J11>=1),"",(1-$J11)*$H11*$I11*(1-($D$33+$D$34+$J11))),"") -> 503.29601 | L11: =IFERROR(IF(OR($G11="",$K11=""),"",IF($G11>=$K11,"Por encima del objetivo","Por debajo del objetivo")),"") -> Por debajo del objetivo | M11: =IFERROR(IF(OR($G11="",$K11=""),"",$G11-$K11),"") -> -131.29601 | N11: =IFERROR(IF($L11="","",IF($L11="Por encima del objetivo","Cumple el objetivo de su familia: mantenlo y protégelo.",IF($E11>$J11,"Su food cost está por encima de la media de la familia: baja coste o sube precio.",IF($D11<$H11,"Vende menos que la media de su familia: es problema de carta y de sala, no de coste.","Su precio está por debajo de la media de su familia: revísalo antes de tocar la receta.")))),"") -> Vende menos que la media de su familia: es problema de carta y de sala, no de coste.
A12: 8 | B12: =IFERROR(IF('Datos'!$B12="","",'Datos'!$B12),"") -> Solomillo de cerdo ibérico con puré de boniato | C12: =IFERROR(IF('Datos'!$C12="","",'Datos'!$C12),"") -> Principales | D12: =IFERROR(IF('Datos'!$D12="","",'Datos'!$D12),"") -> 340 | E12: =IFERROR(IF('Datos'!$H12="","",'Datos'!$H12),"") -> 0.32774566 | F12: =IFERROR(IF('Datos'!$F12="","",'Datos'!$F12),"") -> 17.3 | G12: =IFERROR(IF(OR($D12="",$E12="",$F12="",$D$33+$D$34+$E12>=1),"",(1-$E12)*$D12*$F12*(1-($D$33+$D$34+$E12))),"") -> 997.46409 | H12: =IFERROR(IF(OR('Datos'!$K12="",'Datos'!$K12=0),"",'Datos'!$J12/'Datos'!$K12),"") -> 224.44444 | I12: =IFERROR(IF(OR('Datos'!$J12="",'Datos'!$J12=0),"",SUMPRODUCT(--('Datos'!$C$5:$C$29='Datos'!$C12),'Datos'!$D$5:$D$29,'Datos'!$F$5:$F$29)/'Datos'!$J12),"") -> 16.759406 | J12: =IFERROR(IF('Datos'!$O12="","",'Datos'!$O12),"") -> 0.35587523 | K12: =IFERROR(IF(OR($H12="",$I12="",$J12="",$D$33+$D$34+$J12>=1),"",(1-$J12)*$H12*$I12*(1-($D$33+$D$34+$J12))),"") -> 543.0344 | L12: =IFERROR(IF(OR($G12="",$K12=""),"",IF($G12>=$K12,"Por encima del objetivo","Por debajo del objetivo")),"") -> Por encima del objetivo | M12: =IFERROR(IF(OR($G12="",$K12=""),"",$G12-$K12),"") -> 454.42969 | N12: =IFERROR(IF($L12="","",IF($L12="Por encima del objetivo","Cumple el objetivo de su familia: mantenlo y protégelo.",IF($E12>$J12,"Su food cost está por encima de la media de la familia: baja coste o sube precio.",IF($D12<$H12,"Vende menos que la media de su familia: es problema de carta y de sala, no de coste.","Su precio está por debajo de la media de su familia: revísalo antes de tocar la receta.")))),"") -> Cumple el objetivo de su familia: mantenlo y protégelo.
A13: 9 | B13: =IFERROR(IF('Datos'!$B13="","",'Datos'!$B13),"") -> Bacalao confitado al pil-pil | C13: =IFERROR(IF('Datos'!$C13="","",'Datos'!$C13),"") -> Principales | D13: =IFERROR(IF('Datos'!$D13="","",'Datos'!$D13),"") -> 190 | E13: =IFERROR(IF('Datos'!$H13="","",'Datos'!$H13),"") -> 0.38743455 | F13: =IFERROR(IF('Datos'!$F13="","",'Datos'!$F13),"") -> 19.1 | G13: =IFERROR(IF(OR($D13="",$E13="",$F13="",$D$33+$D$34+$E13>=1),"",(1-$E13)*$D13*$F13*(1-($D$33+$D$34+$E13))),"") -> 428.07298 | H13: =IFERROR(IF(OR('Datos'!$K13="",'Datos'!$K13=0),"",'Datos'!$J13/'Datos'!$K13),"") -> 224.44444 | I13: =IFERROR(IF(OR('Datos'!$J13="",'Datos'!$J13=0),"",SUMPRODUCT(--('Datos'!$C$5:$C$29='Datos'!$C13),'Datos'!$D$5:$D$29,'Datos'!$F$5:$F$29)/'Datos'!$J13),"") -> 16.759406 | J13: =IFERROR(IF('Datos'!$O13="","",'Datos'!$O13),"") -> 0.35587523 | K13: =IFERROR(IF(OR($H13="",$I13="",$J13="",$D$33+$D$34+$J13>=1),"",(1-$J13)*$H13*$I13*(1-($D$33+$D$34+$J13))),"") -> 543.0344 | L13: =IFERROR(IF(OR($G13="",$K13=""),"",IF($G13>=$K13,"Por encima del objetivo","Por debajo del objetivo")),"") -> Por debajo del objetivo | M13: =IFERROR(IF(OR($G13="",$K13=""),"",$G13-$K13),"") -> -114.96141 | N13: =IFERROR(IF($L13="","",IF($L13="Por encima del objetivo","Cumple el objetivo de su familia: mantenlo y protégelo.",IF($E13>$J13,"Su food cost está por encima de la media de la familia: baja coste o sube precio.",IF($D13<$H13,"Vende menos que la media de su familia: es problema de carta y de sala, no de coste.","Su precio está por debajo de la media de su familia: revísalo antes de tocar la receta.")))),"") -> Su food cost está por encima de la media de la familia: baja coste o sube precio.
A14: 10 | B14: =IFERROR(IF('Datos'!$B14="","",'Datos'!$B14),"") -> Hamburguesa de vaca madurada con patatas | C14: =IFERROR(IF('Datos'!$C14="","",'Datos'!$C14),"") -> Principales | D14: =IFERROR(IF('Datos'!$D14="","",'Datos'!$D14),"") -> 460 | E14: =IFERROR(IF('Datos'!$H14="","",'Datos'!$H14),"") -> 0.31617647 | F14: =IFERROR(IF('Datos'!$F14="","",'Datos'!$F14),"") -> 13.6 | G14: =IFERROR(IF(OR($D14="",$E14="",$F14="",$D$33+$D$34+$E14>=1),"",(1-$E14)*$D14*$F14*(1-($D$33+$D$34+$E14))),"") -> 1128.6371 | H14: =IFERROR(IF(OR('Datos'!$K14="",'Datos'!$K14=0),"",'Datos'!$J14/'Datos'!$K14),"") -> 224.44444 | I14: =IFERROR(IF(OR('Datos'!$J14="",'Datos'!$J14=0),"",SUMPRODUCT(--('Datos'!$C$5:$C$29='Datos'!$C14),'Datos'!$D$5:$D$29,'Datos'!$F$5:$F$29)/'Datos'!$J14),"") -> 16.759406 | J14: =IFERROR(IF('Datos'!$O14="","",'Datos'!$O14),"") -> 0.35587523 | K14: =IFERROR(IF(OR($H14="",$I14="",$J14="",$D$33+$D$34+$J14>=1),"",(1-$J14)*$H14*$I14*(1-($D$33+$D$34+$J14))),"") -> 543.0344 | L14: =IFERROR(IF(OR($G14="",$K14=""),"",IF($G14>=$K14,"Por encima del objetivo","Por debajo del objetivo")),"") -> Por encima del objetivo | M14: =IFERROR(IF(OR($G14="",$K14=""),"",$G14-$K14),"") -> 585.60266 | N14: =IFERROR(IF($L14="","",IF($L14="Por encima del objetivo","Cumple el objetivo de su familia: mantenlo y protégelo.",IF($E14>$J14,"Su food cost está por encima de la media de la familia: baja coste o sube precio.",IF($D14<$H14,"Vende menos que la media de su familia: es problema de carta y de sala, no de coste.","Su precio está por debajo de la media de su familia: revísalo antes de tocar la receta.")))),"") -> Cumple el objetivo de su familia: mantenlo y protégelo.
A15: 11 | B15: =IFERROR(IF('Datos'!$B15="","",'Datos'!$B15),"") -> Arroz meloso de secreto ibérico y setas | C15: =IFERROR(IF('Datos'!$C15="","",'Datos'!$C15),"") -> Principales | D15: =IFERROR(IF('Datos'!$D15="","",'Datos'!$D15),"") -> 270 | E15: =IFERROR(IF('Datos'!$H15="","",'Datos'!$H15),"") -> 0.37804878 | F15: =IFERROR(IF('Datos'!$F15="","",'Datos'!$F15),"") -> 16.4 | G15: =IFERROR(IF(OR($D15="",$E15="",$F15="",$D$33+$D$34+$E15>=1),"",(1-$E15)*$D15*$F15*(1-($D$33+$D$34+$E15))),"") -> 556.17366 | H15: =IFERROR(IF(OR('Datos'!$K15="",'Datos'!$K15=0),"",'Datos'!$J15/'Datos'!$K15),"") -> 224.44444 | I15: =IFERROR(IF(OR('Datos'!$J15="",'Datos'!$J15=0),"",SUMPRODUCT(--('Datos'!$C$5:$C$29='Datos'!$C15),'Datos'!$D$5:$D$29,'Datos'!$F$5:$F$29)/'Datos'!$J15),"") -> 16.759406 | J15: =IFERROR(IF('Datos'!$O15="","",'Datos'!$O15),"") -> 0.35587523 | K15: =IFERROR(IF(OR($H15="",$I15="",$J15="",$D$33+$D$34+$J15>=1),"",(1-$J15)*$H15*$I15*(1-($D$33+$D$34+$J15))),"") -> 543.0344 | L15: =IFERROR(IF(OR($G15="",$K15=""),"",IF($G15>=$K15,"Por encima del objetivo","Por debajo del objetivo")),"") -> Por encima del objetivo | M15: =IFERROR(IF(OR($G15="",$K15=""),"",$G15-$K15),"") -> 13.13926 | N15: =IFERROR(IF($L15="","",IF($L15="Por encima del objetivo","Cumple el objetivo de su familia: mantenlo y protégelo.",IF($E15>$J15,"Su food cost está por encima de la media de la familia: baja coste o sube precio.",IF($D15<$H15,"Vende menos que la media de su familia: es problema de carta y de sala, no de coste.","Su precio está por debajo de la media de su familia: revísalo antes de tocar la receta.")))),"") -> Cumple el objetivo de su familia: mantenlo y protégelo.
A16: 12 | B16: =IFERROR(IF('Datos'!$B16="","",'Datos'!$B16),"") -> Chuletón de vaca madurada (500 g) | C16: =IFERROR(IF('Datos'!$C16="","",'Datos'!$C16),"") -> Principales | D16: =IFERROR(IF('Datos'!$D16="","",'Datos'!$D16),"") -> 110 | E16: =IFERROR(IF('Datos'!$H16="","",'Datos'!$H16),"") -> 0.45259939 | F16: =IFERROR(IF('Datos'!$F16="","",'Datos'!$F16),"") -> 32.7 | G16: =IFERROR(IF(OR($D16="",$E16="",$F16="",$D$33+$D$34+$E16>=1),"",(1-$E16)*$D16*$F16*(1-($D$33+$D$34+$E16))),"") -> 250.8518 | H16: =IFERROR(IF(OR('Datos'!$K16="",'Datos'!$K16=0),"",'Datos'!$J16/'Datos'!$K16),"") -> 224.44444 | I16: =IFERROR(IF(OR('Datos'!$J16="",'Datos'!$J16=0),"",SUMPRODUCT(--('Datos'!$C$5:$C$29='Datos'!$C16),'Datos'!$D$5:$D$29,'Datos'!$F$5:$F$29)/'Datos'!$J16),"") -> 16.759406 | J16: =IFERROR(IF('Datos'!$O16="","",'Datos'!$O16),"") -> 0.35587523 | K16: =IFERROR(IF(OR($H16="",$I16="",$J16="",$D$33+$D$34+$J16>=1),"",(1-$J16)*$H16*$I16*(1-($D$33+$D$34+$J16))),"") -> 543.0344 | L16: =IFERROR(IF(OR($G16="",$K16=""),"",IF($G16>=$K16,"Por encima del objetivo","Por debajo del objetivo")),"") -> Por debajo del objetivo | M16: =IFERROR(IF(OR($G16="",$K16=""),"",$G16-$K16),"") -> -292.18259 | N16: =IFERROR(IF($L16="","",IF($L16="Por encima del objetivo","Cumple el objetivo de su familia: mantenlo y protégelo.",IF($E16>$J16,"Su food cost está por encima de la media de la familia: baja coste o sube precio.",IF($D16<$H16,"Vende menos que la media de su familia: es problema de carta y de sala, no de coste.","Su precio está por debajo de la media de su familia: revísalo antes de tocar la receta.")))),"") -> Su food cost está por encima de la media de la familia: baja coste o sube precio.
... A29: 25 | B29: =IFERROR(IF('Datos'!$B29="","",'Datos'!$B29),"") | C29: =IFERROR(IF('Datos'!$C29="","",'Datos'!$C29),"") | D29: =IFERROR(IF('Datos'!$D29="","",'Datos'!$D29),"") | E29: =IFERROR(IF('Datos'!$H29="","",'Datos'!$H29),"") | F29: =IFERROR(IF('Datos'!$F29="","",'Datos'!$F29),"") | G29: =IFERROR(IF(OR($D29="",$E29="",$F29="",$D$33+$D$34+$E29>=1),"",(1-$E29)*$D29*$F29*(1-($D$33+$D$34+$E29))),"") | H29: =IFERROR(IF(OR('Datos'!$K29="",'Datos'!$K29=0),"",'Datos'!$J29/'Datos'!$K29),"") | I29: =IFERROR(IF(OR('Datos'!$J29="",'Datos'!$J29=0),"",SUMPRODUCT(--('Datos'!$C$5:$C$29='Datos'!$C29),'Datos'!$D$5:$D$29,'Datos'!$F$5:$F$29)/'Datos'!$J29),"") | J29: =IFERROR(IF('Datos'!$O29="","",'Datos'!$O29),"") | K29: =IFERROR(IF(OR($H29="",$I29="",$J29="",$D$33+$D$34+$J29>=1),"",(1-$J29)*$H29*$I29*(1-($D$33+$D$34+$J29))),"") | L29: =IFERROR(IF(OR($G29="",$K29=""),"",IF($G29>=$K29,"Por encima del objetivo","Por debajo del objetivo")),"") | M29: =IFERROR(IF(OR($G29="",$K29=""),"",$G29-$K29),"") | N29: =IFERROR(IF($L29="","",IF($L29="Por encima del objetivo","Cumple el objetivo de su familia: mantenlo y protégelo.",IF($E29>$J29,"Su food cost está por encima de la media de la familia: baja coste o sube precio.",IF($D29<$H29,"Vende menos que la media de su familia: es problema de carta y de sala, no de coste.","Su precio está por debajo de la media de su familia: revísalo antes de tocar la receta.")))),"")
A32: PARÁMETROS Y RESUMEN — lo calcula el libro
B33: Coste de personal sobre ventas (%) | D33: 0.32 | F33: Personal con Seguridad Social incluida, sobre ventas netas. El 32 % es el punto medio de la horquilla 30-35 % del servicio en mesa en España; en barra o autoservicio baja. Cámbialo por el tuyo.
B34: Otros costes variables sobre ventas (%) | D34: 0.1 | F34: Lo que se mueve con la venta y no es producto ni personal: energía de cocina, consumibles y comisiones de tarjeta y de plataformas. Cámbialo por el tuyo.
B35: Goal Value medio de la carta (índice) | D35: =IFERROR(AVERAGE($G$5:$G$29),"") -> 520.55159
B36: Platos por encima del objetivo de su familia | D36: =COUNTIF($L$5:$L$29,"Por encima del objetivo") -> 9
B37: Platos por debajo del objetivo de su familia | D37: =COUNTIF($L$5:$L$29,"Por debajo del objetivo") -> 11

Sheet Comparativa
A1: Comparativa — dónde discrepan los cuatro métodos
A2: AI Chef Pro · aichef.pro — Guía Food Cost + Ingeniería de Menú
E3: Coincidir no da más seguridad: sólo dice que el plato se ve igual desde cualquier ángulo. El valor está en las filas que discrepan.
A4: # | B4: Plato | C4: Familia | D4: Kasavana & Smith | E4: Miller | F4: Pavesic | G4: Goal Value | H4: Lecturas fuera de la mejor categoría | I4: Diagnóstico | J4: Decisión sugerida
A5: 1 | B5: =IFERROR(IF('Datos'!$B5="","",'Datos'!$B5),"") -> Croquetas de jamón ibérico (6 ud) | C5: =IFERROR(IF('Datos'!$C5="","",'Datos'!$C5),"") -> Entrantes | D5: =IFERROR(IF('Kasavana-Smith'!$K5="","",'Kasavana-Smith'!$K5),"") -> Plowhorse | E5: =IFERROR(IF('Miller'!$K5="","",'Miller'!$K5),"") -> Winner | F5: =IFERROR(IF('Pavesic'!$K5="","",'Pavesic'!$K5),"") -> Prime | G5: =IFERROR(IF('Goal Value'!$L5="","",'Goal Value'!$L5),"") -> Por encima del objetivo | H5: =IFERROR(IF($B5="","",IF($D5="Star",0,1)+IF($E5="Winner",0,1)+IF($F5="Prime",0,1)+IF($G5="Por encima del objetivo",0,1)),"") -> 1 | I5: =IFERROR(IF($B5="","",IF($H5=0,"Las cuatro lecturas coinciden en lo mejor: mantener, destacar en carta y proteger receta y proveedor.",IF(AND($D5="Dog",$E5="Loser",$F5="Problem"),"Poco pedido, food cost alto y aporta poco margen al total: candidato a retirar o a reformular de raíz.",IF(AND($D5="Plowhorse",$E5="Winner"),"Popular con margen bajo: subir precio o bajar coste.",IF(AND($D5="Plowhorse",$E5="Loser"),"Popular pero caro de producir y de margen corto: reformular la receta antes de tocar el precio.",IF(AND('Datos'!$G5>='Datos'!$N5,'Datos'!$H5>'Datos'!$O5),"MC alto con food cost pobre: proteger el margen en euros, revisar precio, no retirar.",IF(AND($D5="Puzzle",$E5="Winner"),"Rentable y con food cost sano, pero poco pedido: es problema de carta, no de cocina. Renómbralo, súbelo de posición o que lo sugiera la sala.",IF($F5="Sleeper","Food cost sano pero aporta poco margen al total: dale visibilidad antes de retirarlo.",IF(AND($G5="Por debajo del objetivo",$D5="Star"),"Vende y deja margen, pero se queda por debajo del Goal Value de su familia: va justo de recorrido, revisa el precio.",IF($D5="Dog","Poco pedido: antes de retirarlo comprueba si es de temporada o si acompaña a otro plato que sí vende.","Las lecturas discrepan: cada método mide dos de las tres variables (popularidad, margen en euros y food cost). Decide con la que más te duela este mes.")))))))))),"") -> Popular con margen bajo: subir precio o bajar coste. | J5: =IFERROR(IF($B5="","",IF($H5=0,"Mantener",IF(AND($D5="Dog",$E5="Loser"),"Retirar",IF($D5="Plowhorse","Resubir",IF($D5="Puzzle","Rediseñar",IF($F5="Problem","Reformular","Revisar")))))),"") -> Resubir
A6: 2 | B6: =IFERROR(IF('Datos'!$B6="","",'Datos'!$B6),"") -> Ensalada de tomate rosa, ventresca y cebolleta | C6: =IFERROR(IF('Datos'!$C6="","",'Datos'!$C6),"") -> Entrantes | D6: =IFERROR(IF('Kasavana-Smith'!$K6="","",'Kasavana-Smith'!$K6),"") -> Star | E6: =IFERROR(IF('Miller'!$K6="","",'Miller'!$K6),"") -> Winner | F6: =IFERROR(IF('Pavesic'!$K6="","",'Pavesic'!$K6),"") -> Prime | G6: =IFERROR(IF('Goal Value'!$L6="","",'Goal Value'!$L6),"") -> Por encima del objetivo | H6: =IFERROR(IF($B6="","",IF($D6="Star",0,1)+IF($E6="Winner",0,1)+IF($F6="Prime",0,1)+IF($G6="Por encima del objetivo",0,1)),"") -> 0 | I6: =IFERROR(IF($B6="","",IF($H6=0,"Las cuatro lecturas coinciden en lo mejor: mantener, destacar en carta y proteger receta y proveedor.",IF(AND($D6="Dog",$E6="Loser",$F6="Problem"),"Poco pedido, food cost alto y aporta poco margen al total: candidato a retirar o a reformular de raíz.",IF(AND($D6="Plowhorse",$E6="Winner"),"Popular con margen bajo: subir precio o bajar coste.",IF(AND($D6="Plowhorse",$E6="Loser"),"Popular pero caro de producir y de margen corto: reformular la receta antes de tocar el precio.",IF(AND('Datos'!$G6>='Datos'!$N6,'Datos'!$H6>'Datos'!$O6),"MC alto con food cost pobre: proteger el margen en euros, revisar precio, no retirar.",IF(AND($D6="Puzzle",$E6="Winner"),"Rentable y con food cost sano, pero poco pedido: es problema de carta, no de cocina. Renómbralo, súbelo de posición o que lo sugiera la sala.",IF($F6="Sleeper","Food cost sano pero aporta poco margen al total: dale visibilidad antes de retirarlo.",IF(AND($G6="Por debajo del objetivo",$D6="Star"),"Vende y deja margen, pero se queda por debajo del Goal Value de su familia: va justo de recorrido, revisa el precio.",IF($D6="Dog","Poco pedido: antes de retirarlo comprueba si es de temporada o si acompaña a otro plato que sí vende.","Las lecturas discrepan: cada método mide dos de las tres variables (popularidad, margen en euros y food cost). Decide con la que más te duela este mes.")))))))))),"") -> Las cuatro lecturas coinciden en lo mejor: mantener, destacar en carta y proteger receta y proveedor. | J6: =IFERROR(IF($B6="","",IF($H6=0,"Mantener",IF(AND($D6="Dog",$E6="Loser"),"Retirar",IF($D6="Plowhorse","Resubir",IF($D6="Puzzle","Rediseñar",IF($F6="Problem","Reformular","Revisar")))))),"") -> Mantener
A7: 3 | B7: =IFERROR(IF('Datos'!$B7="","",'Datos'!$B7),"") -> Gambas al ajillo | C7: =IFERROR(IF('Datos'!$C7="","",'Datos'!$C7),"") -> Entrantes | D7: =IFERROR(IF('Kasavana-Smith'!$K7="","",'Kasavana-Smith'!$K7),"") -> Star | E7: =IFERROR(IF('Miller'!$K7="","",'Miller'!$K7),"") -> Marginal | F7: =IFERROR(IF('Pavesic'!$K7="","",'Pavesic'!$K7),"") -> Standard | G7: =IFERROR(IF('Goal Value'!$L7="","",'Goal Value'!$L7),"") -> Por debajo del objetivo | H7: =IFERROR(IF($B7="","",IF($D7="Star",0,1)+IF($E7="Winner",0,1)+IF($F7="Prime",0,1)+IF($G7="Por encima del objetivo",0,1)),"") -> 3 | I7: =IFERROR(IF($B7="","",IF($H7=0,"Las cuatro lecturas coinciden en lo mejor: mantener, destacar en carta y proteger receta y proveedor.",IF(AND($D7="Dog",$E7="Loser",$F7="Problem"),"Poco pedido, food cost alto y aporta poco margen al total: candidato a retirar o a reformular de raíz.",IF(AND($D7="Plowhorse",$E7="Winner"),"Popular con margen bajo: subir precio o bajar coste.",IF(AND($D7="Plowhorse",$E7="Loser"),"Popular pero caro de producir y de margen corto: reformular la receta antes de tocar el precio.",IF(AND('Datos'!$G7>='Datos'!$N7,'Datos'!$H7>'Datos'!$O7),"MC alto con food cost pobre: proteger el margen en euros, revisar precio, no retirar.",IF(AND($D7="Puzzle",$E7="Winner"),"Rentable y con food cost sano, pero poco pedido: es problema de carta, no de cocina. Renómbralo, súbelo de posición o que lo sugiera la sala.",IF($F7="Sleeper","Food cost sano pero aporta poco margen al total: dale visibilidad antes de retirarlo.",IF(AND($G7="Por debajo del objetivo",$D7="Star"),"Vende y deja margen, pero se queda por debajo del Goal Value de su familia: va justo de recorrido, revisa el precio.",IF($D7="Dog","Poco pedido: antes de retirarlo comprueba si es de temporada o si acompaña a otro plato que sí vende.","Las lecturas discrepan: cada método mide dos de las tres variables (popularidad, margen en euros y food cost). Decide con la que más te duela este mes.")))))))))),"") -> MC alto con food cost pobre: proteger el margen en euros, revisar precio, no retirar. | J7: =IFERROR(IF($B7="","",IF($H7=0,"Mantener",IF(AND($D7="Dog",$E7="Loser"),"Retirar",IF($D7="Plowhorse","Resubir",IF($D7="Puzzle","Rediseñar",IF($F7="Problem","Reformular","Revisar")))))),"") -> Revisar
A8: 4 | B8: =IFERROR(IF('Datos'!$B8="","",'Datos'!$B8),"") -> Huevos rotos con patatas y chistorra | C8: =IFERROR(IF('Datos'!$C8="","",'Datos'!$C8),"") -> Entrantes | D8: =IFERROR(IF('Kasavana-Smith'!$K8="","",'Kasavana-Smith'!$K8),"") -> Plowhorse | E8: =IFERROR(IF('Miller'!$K8="","",'Miller'!$K8),"") -> Winner | F8: =IFERROR(IF('Pavesic'!$K8="","",'Pavesic'!$K8),"") -> Prime | G8: =IFERROR(IF('Goal Value'!$L8="","",'Goal Value'!$L8),"") -> Por encima del objetivo | H8: =IFERROR(IF($B8="","",IF($D8="Star",0,1)+IF($E8="Winner",0,1)+IF($F8="Prime",0,1)+IF($G8="Por encima del objetivo",0,1)),"") -> 1 | I8: =IFERROR(IF($B8="","",IF($H8=0,"Las cuatro lecturas coinciden en lo mejor: mantener, destacar en carta y proteger receta y proveedor.",IF(AND($D8="Dog",$E8="Loser",$F8="Problem"),"Poco pedido, food cost alto y aporta poco margen al total: candidato a retirar o a reformular de raíz.",IF(AND($D8="Plowhorse",$E8="Winner"),"Popular con margen bajo: subir precio o bajar coste.",IF(AND($D8="Plowhorse",$E8="Loser"),"Popular pero caro de producir y de margen corto: reformular la receta antes de tocar el precio.",IF(AND('Datos'!$G8>='Datos'!$N8,'Datos'!$H8>'Datos'!$O8),"MC alto con food cost pobre: proteger el margen en euros, revisar precio, no retirar.",IF(AND($D8="Puzzle",$E8="Winner"),"Rentable y con food cost sano, pero poco pedido: es problema de carta, no de cocina. Renómbralo, súbelo de posición o que lo sugiera la sala.",IF($F8="Sleeper","Food cost sano pero aporta poco margen al total: dale visibilidad antes de retirarlo.",IF(AND($G8="Por debajo del objetivo",$D8="Star"),"Vende y deja margen, pero se queda por debajo del Goal Value de su familia: va justo de recorrido, revisa el precio.",IF($D8="Dog","Poco pedido: antes de retirarlo comprueba si es de temporada o si acompaña a otro plato que sí vende.","Las lecturas discrepan: cada método mide dos de las tres variables (popularidad, margen en euros y food cost). Decide con la que más te duela este mes.")))))))))),"") -> Popular con margen bajo: subir precio o bajar coste. | J8: =IFERROR(IF($B8="","",IF($H8=0,"Mantener",IF(AND($D8="Dog",$E8="Loser"),"Retirar",IF($D8="Plowhorse","Resubir",IF($D8="Puzzle","Rediseñar",IF($F8="Problem","Reformular","Revisar")))))),"") -> Resubir
A9: 5 | B9: =IFERROR(IF('Datos'!$B9="","",'Datos'!$B9),"") -> Tabla de quesos de la zona | C9: =IFERROR(IF('Datos'!$C9="","",'Datos'!$C9),"") -> Entrantes | D9: =IFERROR(IF('Kasavana-Smith'!$K9="","",'Kasavana-Smith'!$K9),"") -> Puzzle | E9: =IFERROR(IF('Miller'!$K9="","",'Miller'!$K9),"") -> Loser | F9: =IFERROR(IF('Pavesic'!$K9="","",'Pavesic'!$K9),"") -> Problem | G9: =IFERROR(IF('Goal Value'!$L9="","",'Goal Value'!$L9),"") -> Por debajo del objetivo | H9: =IFERROR(IF($B9="","",IF($D9="Star",0,1)+IF($E9="Winner",0,1)+IF($F9="Prime",0,1)+IF($G9="Por encima del objetivo",0,1)),"") -> 4 | I9: =IFERROR(IF($B9="","",IF($H9=0,"Las cuatro lecturas coinciden en lo mejor: mantener, destacar en carta y proteger receta y proveedor.",IF(AND($D9="Dog",$E9="Loser",$F9="Problem"),"Poco pedido, food cost alto y aporta poco margen al total: candidato a retirar o a reformular de raíz.",IF(AND($D9="Plowhorse",$E9="Winner"),"Popular con margen bajo: subir precio o bajar coste.",IF(AND($D9="Plowhorse",$E9="Loser"),"Popular pero caro de producir y de margen corto: reformular la receta antes de tocar el precio.",IF(AND('Datos'!$G9>='Datos'!$N9,'Datos'!$H9>'Datos'!$O9),"MC alto con food cost pobre: proteger el margen en euros, revisar precio, no retirar.",IF(AND($D9="Puzzle",$E9="Winner"),"Rentable y con food cost sano, pero poco pedido: es problema de carta, no de cocina. Renómbralo, súbelo de posición o que lo sugiera la sala.",IF($F9="Sleeper","Food cost sano pero aporta poco margen al total: dale visibilidad antes de retirarlo.",IF(AND($G9="Por debajo del objetivo",$D9="Star"),"Vende y deja margen, pero se queda por debajo del Goal Value de su familia: va justo de recorrido, revisa el precio.",IF($D9="Dog","Poco pedido: antes de retirarlo comprueba si es de temporada o si acompaña a otro plato que sí vende.","Las lecturas discrepan: cada método mide dos de las tres variables (popularidad, margen en euros y food cost). Decide con la que más te duela este mes.")))))))))),"") -> MC alto con food cost pobre: proteger el margen en euros, revisar precio, no retirar. | J9: =IFERROR(IF($B9="","",IF($H9=0,"Mantener",IF(AND($D9="Dog",$E9="Loser"),"Retirar",IF($D9="Plowhorse","Resubir",IF($D9="Puzzle","Rediseñar",IF($F9="Problem","Reformular","Revisar")))))),"") -> Rediseñar
A10: 6 | B10: =IFERROR(IF('Datos'!$B10="","",'Datos'!$B10),"") -> Alcachofas confitadas con jamón | C10: =IFERROR(IF('Datos'!$C10="","",'Datos'!$C10),"") -> Entrantes | D10: =IFERROR(IF('Kasavana-Smith'!$K10="","",'Kasavana-Smith'!$K10),"") -> Puzzle | E10: =IFERROR(IF('Miller'!$K10="","",'Miller'!$K10),"") -> Marginal | F10: =IFERROR(IF('Pavesic'!$K10="","",'Pavesic'!$K10),"") -> Sleeper | G10: =IFERROR(IF('Goal Value'!$L10="","",'Goal Value'!$L10),"") -> Por debajo del objetivo | H10: =IFERROR(IF($B10="","",IF($D10="Star",0,1)+IF($E10="Winner",0,1)+IF($F10="Prime",0,1)+IF($G10="Por encima del objetivo",0,1)),"") -> 4 | I10: =IFERROR(IF($B10="","",IF($H10=0,"Las cuatro lecturas coinciden en lo mejor: mantener, destacar en carta y proteger receta y proveedor.",IF(AND($D10="Dog",$E10="Loser",$F10="Problem"),"Poco pedido, food cost alto y aporta poco margen al total: candidato a retirar o a reformular de raíz.",IF(AND($D10="Plowhorse",$E10="Winner"),"Popular con margen bajo: subir precio o bajar coste.",IF(AND($D10="Plowhorse",$E10="Loser"),"Popular pero caro de producir y de margen corto: reformular la receta antes de tocar el precio.",IF(AND('Datos'!$G10>='Datos'!$N10,'Datos'!$H10>'Datos'!$O10),"MC alto con food cost pobre: proteger el margen en euros, revisar precio, no retirar.",IF(AND($D10="Puzzle",$E10="Winner"),"Rentable y con food cost sano, pero poco pedido: es problema de carta, no de cocina. Renómbralo, súbelo de posición o que lo sugiera la sala.",IF($F10="Sleeper","Food cost sano pero aporta poco margen al total: dale visibilidad antes de retirarlo.",IF(AND($G10="Por debajo del objetivo",$D10="Star"),"Vende y deja margen, pero se queda por debajo del Goal Value de su familia: va justo de recorrido, revisa el precio.",IF($D10="Dog","Poco pedido: antes de retirarlo comprueba si es de temporada o si acompaña a otro plato que sí vende.","Las lecturas discrepan: cada método mide dos de las tres variables (popularidad, margen en euros y food cost). Decide con la que más te duela este mes.")))))))))),"") -> Food cost sano pero aporta poco margen al total: dale visibilidad antes de retirarlo. | J10: =IFERROR(IF($B10="","",IF($H10=0,"Mantener",IF(AND($D10="Dog",$E10="Loser"),"Retirar",IF($D10="Plowhorse","Resubir",IF($D10="Puzzle","Rediseñar",IF($F10="Problem","Reformular","Revisar")))))),"") -> Rediseñar
A11: 7 | B11: =IFERROR(IF('Datos'!$B11="","",'Datos'!$B11),"") -> Sopa de tomate asado con albahaca | C11: =IFERROR(IF('Datos'!$C11="","",'Datos'!$C11),"") -> Entrantes | D11: =IFERROR(IF('Kasavana-Smith'!$K11="","",'Kasavana-Smith'!$K11),"") -> Dog | E11: =IFERROR(IF('Miller'!$K11="","",'Miller'!$K11),"") -> Marginal | F11: =IFERROR(IF('Pavesic'!$K11="","",'Pavesic'!$K11),"") -> Sleeper | G11: =IFERROR(IF('Goal Value'!$L11="","",'Goal Value'!$L11),"") -> Por debajo del objetivo | H11: =IFERROR(IF($B11="","",IF($D11="Star",0,1)+IF($E11="Winner",0,1)+IF($F11="Prime",0,1)+IF($G11="Por encima del objetivo",0,1)),"") -> 4 | I11: =IFERROR(IF($B11="","",IF($H11=0,"Las cuatro lecturas coinciden en lo mejor: mantener, destacar en carta y proteger receta y proveedor.",IF(AND($D11="Dog",$E11="Loser",$F11="Problem"),"Poco pedido, food cost alto y aporta poco margen al total: candidato a retirar o a reformular de raíz.",IF(AND($D11="Plowhorse",$E11="Winner"),"Popular con margen bajo: subir precio o bajar coste.",IF(AND($D11="Plowhorse",$E11="Loser"),"Popular pero caro de producir y de margen corto: reformular la receta antes de tocar el precio.",IF(AND('Datos'!$G11>='Datos'!$N11,'Datos'!$H11>'Datos'!$O11),"MC alto con food cost pobre: proteger el margen en euros, revisar precio, no retirar.",IF(AND($D11="Puzzle",$E11="Winner"),"Rentable y con food cost sano, pero poco pedido: es problema de carta, no de cocina. Renómbralo, súbelo de posición o que lo sugiera la sala.",IF($F11="Sleeper","Food cost sano pero aporta poco margen al total: dale visibilidad antes de retirarlo.",IF(AND($G11="Por debajo del objetivo",$D11="Star"),"Vende y deja margen, pero se queda por debajo del Goal Value de su familia: va justo de recorrido, revisa el precio.",IF($D11="Dog","Poco pedido: antes de retirarlo comprueba si es de temporada o si acompaña a otro plato que sí vende.","Las lecturas discrepan: cada método mide dos de las tres variables (popularidad, margen en euros y food cost). Decide con la que más te duela este mes.")))))))))),"") -> Food cost sano pero aporta poco margen al total: dale visibilidad antes de retirarlo. | J11: =IFERROR(IF($B11="","",IF($H11=0,"Mantener",IF(AND($D11="Dog",$E11="Loser"),"Retirar",IF($D11="Plowhorse","Resubir",IF($D11="Puzzle","Rediseñar",IF($F11="Problem","Reformular","Revisar")))))),"") -> Revisar
A12: 8 | B12: =IFERROR(IF('Datos'!$B12="","",'Datos'!$B12),"") -> Solomillo de cerdo ibérico con puré de boniato | C12: =IFERROR(IF('Datos'!$C12="","",'Datos'!$C12),"") -> Principales | D12: =IFERROR(IF('Kasavana-Smith'!$K12="","",'Kasavana-Smith'!$K12),"") -> Star | E12: =IFERROR(IF('Miller'!$K12="","",'Miller'!$K12),"") -> Winner | F12: =IFERROR(IF('Pavesic'!$K12="","",'Pavesic'!$K12),"") -> Prime | G12: =IFERROR(IF('Goal Value'!$L12="","",'Goal Value'!$L12),"") -> Por encima del objetivo | H12: =IFERROR(IF($B12="","",IF($D12="Star",0,1)+IF($E12="Winner",0,1)+IF($F12="Prime",0,1)+IF($G12="Por encima del objetivo",0,1)),"") -> 0 | I12: =IFERROR(IF($B12="","",IF($H12=0,"Las cuatro lecturas coinciden en lo mejor: mantener, destacar en carta y proteger receta y proveedor.",IF(AND($D12="Dog",$E12="Loser",$F12="Problem"),"Poco pedido, food cost alto y aporta poco margen al total: candidato a retirar o a reformular de raíz.",IF(AND($D12="Plowhorse",$E12="Winner"),"Popular con margen bajo: subir precio o bajar coste.",IF(AND($D12="Plowhorse",$E12="Loser"),"Popular pero caro de producir y de margen corto: reformular la receta antes de tocar el precio.",IF(AND('Datos'!$G12>='Datos'!$N12,'Datos'!$H12>'Datos'!$O12),"MC alto con food cost pobre: proteger el margen en euros, revisar precio, no retirar.",IF(AND($D12="Puzzle",$E12="Winner"),"Rentable y con food cost sano, pero poco pedido: es problema de carta, no de cocina. Renómbralo, súbelo de posición o que lo sugiera la sala.",IF($F12="Sleeper","Food cost sano pero aporta poco margen al total: dale visibilidad antes de retirarlo.",IF(AND($G12="Por debajo del objetivo",$D12="Star"),"Vende y deja margen, pero se queda por debajo del Goal Value de su familia: va justo de recorrido, revisa el precio.",IF($D12="Dog","Poco pedido: antes de retirarlo comprueba si es de temporada o si acompaña a otro plato que sí vende.","Las lecturas discrepan: cada método mide dos de las tres variables (popularidad, margen en euros y food cost). Decide con la que más te duela este mes.")))))))))),"") -> Las cuatro lecturas coinciden en lo mejor: mantener, destacar en carta y proteger receta y proveedor. | J12: =IFERROR(IF($B12="","",IF($H12=0,"Mantener",IF(AND($D12="Dog",$E12="Loser"),"Retirar",IF($D12="Plowhorse","Resubir",IF($D12="Puzzle","Rediseñar",IF($F12="Problem","Reformular","Revisar")))))),"") -> Mantener
A13: 9 | B13: =IFERROR(IF('Datos'!$B13="","",'Datos'!$B13),"") -> Bacalao confitado al pil-pil | C13: =IFERROR(IF('Datos'!$C13="","",'Datos'!$C13),"") -> Principales | D13: =IFERROR(IF('Kasavana-Smith'!$K13="","",'Kasavana-Smith'!$K13),"") -> Star | E13: =IFERROR(IF('Miller'!$K13="","",'Miller'!$K13),"") -> Marginal | F13: =IFERROR(IF('Pavesic'!$K13="","",'Pavesic'!$K13),"") -> Problem | G13: =IFERROR(IF('Goal Value'!$L13="","",'Goal Value'!$L13),"") -> Por debajo del objetivo | H13: =IFERROR(IF($B13="","",IF($D13="Star",0,1)+IF($E13="Winner",0,1)+IF($F13="Prime",0,1)+IF($G13="Por encima del objetivo",0,1)),"") -> 3 | I13: =IFERROR(IF($B13="","",IF($H13=0,"Las cuatro lecturas coinciden en lo mejor: mantener, destacar en carta y proteger receta y proveedor.",IF(AND($D13="Dog",$E13="Loser",$F13="Problem"),"Poco pedido, food cost alto y aporta poco margen al total: candidato a retirar o a reformular de raíz.",IF(AND($D13="Plowhorse",$E13="Winner"),"Popular con margen bajo: subir precio o bajar coste.",IF(AND($D13="Plowhorse",$E13="Loser"),"Popular pero caro de producir y de margen corto: reformular la receta antes de tocar el precio.",IF(AND('Datos'!$G13>='Datos'!$N13,'Datos'!$H13>'Datos'!$O13),"MC alto con food cost pobre: proteger el margen en euros, revisar precio, no retirar.",IF(AND($D13="Puzzle",$E13="Winner"),"Rentable y con food cost sano, pero poco pedido: es problema de carta, no de cocina. Renómbralo, súbelo de posición o que lo sugiera la sala.",IF($F13="Sleeper","Food cost sano pero aporta poco margen al total: dale visibilidad antes de retirarlo.",IF(AND($G13="Por debajo del objetivo",$D13="Star"),"Vende y deja margen, pero se queda por debajo del Goal Value de su familia: va justo de recorrido, revisa el precio.",IF($D13="Dog","Poco pedido: antes de retirarlo comprueba si es de temporada o si acompaña a otro plato que sí vende.","Las lecturas discrepan: cada método mide dos de las tres variables (popularidad, margen en euros y food cost). Decide con la que más te duela este mes.")))))))))),"") -> MC alto con food cost pobre: proteger el margen en euros, revisar precio, no retirar. | J13: =IFERROR(IF($B13="","",IF($H13=0,"Mantener",IF(AND($D13="Dog",$E13="Loser"),"Retirar",IF($D13="Plowhorse","Resubir",IF($D13="Puzzle","Rediseñar",IF($F13="Problem","Reformular","Revisar")))))),"") -> Reformular
A14: 10 | B14: =IFERROR(IF('Datos'!$B14="","",'Datos'!$B14),"") -> Hamburguesa de vaca madurada con patatas | C14: =IFERROR(IF('Datos'!$C14="","",'Datos'!$C14),"") -> Principales | D14: =IFERROR(IF('Kasavana-Smith'!$K14="","",'Kasavana-Smith'!$K14),"") -> Plowhorse | E14: =IFERROR(IF('Miller'!$K14="","",'Miller'!$K14),"") -> Winner | F14: =IFERROR(IF('Pavesic'!$K14="","",'Pavesic'!$K14),"") -> Prime | G14: =IFERROR(IF('Goal Value'!$L14="","",'Goal Value'!$L14),"") -> Por encima del objetivo | H14: =IFERROR(IF($B14="","",IF($D14="Star",0,1)+IF($E14="Winner",0,1)+IF($F14="Prime",0,1)+IF($G14="Por encima del objetivo",0,1)),"") -> 1 | I14: =IFERROR(IF($B14="","",IF($H14=0,"Las cuatro lecturas coinciden en lo mejor: mantener, destacar en carta y proteger receta y proveedor.",IF(AND($D14="Dog",$E14="Loser",$F14="Problem"),"Poco pedido, food cost alto y aporta poco margen al total: candidato a retirar o a reformular de raíz.",IF(AND($D14="Plowhorse",$E14="Winner"),"Popular con margen bajo: subir precio o bajar coste.",IF(AND($D14="Plowhorse",$E14="Loser"),"Popular pero caro de producir y de margen corto: reformular la receta antes de tocar el precio.",IF(AND('Datos'!$G14>='Datos'!$N14,'Datos'!$H14>'Datos'!$O14),"MC alto con food cost pobre: proteger el margen en euros, revisar precio, no retirar.",IF(AND($D14="Puzzle",$E14="Winner"),"Rentable y con food cost sano, pero poco pedido: es problema de carta, no de cocina. Renómbralo, súbelo de posición o que lo sugiera la sala.",IF($F14="Sleeper","Food cost sano pero aporta poco margen al total: dale visibilidad antes de retirarlo.",IF(AND($G14="Por debajo del objetivo",$D14="Star"),"Vende y deja margen, pero se queda por debajo del Goal Value de su familia: va justo de recorrido, revisa el precio.",IF($D14="Dog","Poco pedido: antes de retirarlo comprueba si es de temporada o si acompaña a otro plato que sí vende.","Las lecturas discrepan: cada método mide dos de las tres variables (popularidad, margen en euros y food cost). Decide con la que más te duela este mes.")))))))))),"") -> Popular con margen bajo: subir precio o bajar coste. | J14: =IFERROR(IF($B14="","",IF($H14=0,"Mantener",IF(AND($D14="Dog",$E14="Loser"),"Retirar",IF($D14="Plowhorse","Resubir",IF($D14="Puzzle","Rediseñar",IF($F14="Problem","Reformular","Revisar")))))),"") -> Resubir
A15: 11 | B15: =IFERROR(IF('Datos'!$B15="","",'Datos'!$B15),"") -> Arroz meloso de secreto ibérico y setas | C15: =IFERROR(IF('Datos'!$C15="","",'Datos'!$C15),"") -> Principales | D15: =IFERROR(IF('Kasavana-Smith'!$K15="","",'Kasavana-Smith'!$K15),"") -> Plowhorse | E15: =IFERROR(IF('Miller'!$K15="","",'Miller'!$K15),"") -> Marginal | F15: =IFERROR(IF('Pavesic'!$K15="","",'Pavesic'!$K15),"") -> Standard | G15: =IFERROR(IF('Goal Value'!$L15="","",'Goal Value'!$L15),"") -> Por encima del objetivo | H15: =IFERROR(IF($B15="","",IF($D15="Star",0,1)+IF($E15="Winner",0,1)+IF($F15="Prime",0,1)+IF($G15="Por encima del objetivo",0,1)),"") -> 3 | I15: =IFERROR(IF($B15="","",IF($H15=0,"Las cuatro lecturas coinciden en lo mejor: mantener, destacar en carta y proteger receta y proveedor.",IF(AND($D15="Dog",$E15="Loser",$F15="Problem"),"Poco pedido, food cost alto y aporta poco margen al total: candidato a retirar o a reformular de raíz.",IF(AND($D15="Plowhorse",$E15="Winner"),"Popular con margen bajo: subir precio o bajar coste.",IF(AND($D15="Plowhorse",$E15="Loser"),"Popular pero caro de producir y de margen corto: reformular la receta antes de tocar el precio.",IF(AND('Datos'!$G15>='Datos'!$N15,'Datos'!$H15>'Datos'!$O15),"MC alto con food cost pobre: proteger el margen en euros, revisar precio, no retirar.",IF(AND($D15="Puzzle",$E15="Winner"),"Rentable y con food cost sano, pero poco pedido: es problema de carta, no de cocina. Renómbralo, súbelo de posición o que lo sugiera la sala.",IF($F15="Sleeper","Food cost sano pero aporta poco margen al total: dale visibilidad antes de retirarlo.",IF(AND($G15="Por debajo del objetivo",$D15="Star"),"Vende y deja margen, pero se queda por debajo del Goal Value de su familia: va justo de recorrido, revisa el precio.",IF($D15="Dog","Poco pedido: antes de retirarlo comprueba si es de temporada o si acompaña a otro plato que sí vende.","Las lecturas discrepan: cada método mide dos de las tres variables (popularidad, margen en euros y food cost). Decide con la que más te duela este mes.")))))))))),"") -> Las lecturas discrepan: cada método mide dos de las tres variables (popularidad, margen en euros y food cost). Decide con la que más te duela este mes. | J15: =IFERROR(IF($B15="","",IF($H15=0,"Mantener",IF(AND($D15="Dog",$E15="Loser"),"Retirar",IF($D15="Plowhorse","Resubir",IF($D15="Puzzle","Rediseñar",IF($F15="Problem","Reformular","Revisar")))))),"") -> Resubir
A16: 12 | B16: =IFERROR(IF('Datos'!$B16="","",'Datos'!$B16),"") -> Chuletón de vaca madurada (500 g) | C16: =IFERROR(IF('Datos'!$C16="","",'Datos'!$C16),"") -> Principales | D16: =IFERROR(IF('Kasavana-Smith'!$K16="","",'Kasavana-Smith'!$K16),"") -> Puzzle | E16: =IFERROR(IF('Miller'!$K16="","",'Miller'!$K16),"") -> Loser | F16: =IFERROR(IF('Pavesic'!$K16="","",'Pavesic'!$K16),"") -> Problem | G16: =IFERROR(IF('Goal Value'!$L16="","",'Goal Value'!$L16),"") -> Por debajo del objetivo | H16: =IFERROR(IF($B16="","",IF($D16="Star",0,1)+IF($E16="Winner",0,1)+IF($F16="Prime",0,1)+IF($G16="Por encima del objetivo",0,1)),"") -> 4 | I16: =IFERROR(IF($B16="","",IF($H16=0,"Las cuatro lecturas coinciden en lo mejor: mantener, destacar en carta y proteger receta y proveedor.",IF(AND($D16="Dog",$E16="Loser",$F16="Problem"),"Poco pedido, food cost alto y aporta poco margen al total: candidato a retirar o a reformular de raíz.",IF(AND($D16="Plowhorse",$E16="Winner"),"Popular con margen bajo: subir precio o bajar coste.",IF(AND($D16="Plowhorse",$E16="Loser"),"Popular pero caro de producir y de margen corto: reformular la receta antes de tocar el precio.",IF(AND('Datos'!$G16>='Datos'!$N16,'Datos'!$H16>'Datos'!$O16),"MC alto con food cost pobre: proteger el margen en euros, revisar precio, no retirar.",IF(AND($D16="Puzzle",$E16="Winner"),"Rentable y con food cost sano, pero poco pedido: es problema de carta, no de cocina. Renómbralo, súbelo de posición o que lo sugiera la sala.",IF($F16="Sleeper","Food cost sano pero aporta poco margen al total: dale visibilidad antes de retirarlo.",IF(AND($G16="Por debajo del objetivo",$D16="Star"),"Vende y deja margen, pero se queda por debajo del Goal Value de su familia: va justo de recorrido, revisa el precio.",IF($D16="Dog","Poco pedido: antes de retirarlo comprueba si es de temporada o si acompaña a otro plato que sí vende.","Las lecturas discrepan: cada método mide dos de las tres variables (popularidad, margen en euros y food cost). Decide con la que más te duela este mes.")))))))))),"") -> MC alto con food cost pobre: proteger el margen en euros, revisar precio, no retirar. | J16: =IFERROR(IF($B16="","",IF($H16=0,"Mantener",IF(AND($D16="Dog",$E16="Loser"),"Retirar",IF($D16="Plowhorse","Resubir",IF($D16="Puzzle","Rediseñar",IF($F16="Problem","Reformular","Revisar")))))),"") -> Rediseñar
... A29: 25 | B29: =IFERROR(IF('Datos'!$B29="","",'Datos'!$B29),"") | C29: =IFERROR(IF('Datos'!$C29="","",'Datos'!$C29),"") | D29: =IFERROR(IF('Kasavana-Smith'!$K29="","",'Kasavana-Smith'!$K29),"") | E29: =IFERROR(IF('Miller'!$K29="","",'Miller'!$K29),"") | F29: =IFERROR(IF('Pavesic'!$K29="","",'Pavesic'!$K29),"") | G29: =IFERROR(IF('Goal Value'!$L29="","",'Goal Value'!$L29),"") | H29: =IFERROR(IF($B29="","",IF($D29="Star",0,1)+IF($E29="Winner",0,1)+IF($F29="Prime",0,1)+IF($G29="Por encima del objetivo",0,1)),"") | I29: =IFERROR(IF($B29="","",IF($H29=0,"Las cuatro lecturas coinciden en lo mejor: mantener, destacar en carta y proteger receta y proveedor.",IF(AND($D29="Dog",$E29="Loser",$F29="Problem"),"Poco pedido, food cost alto y aporta poco margen al total: candidato a retirar o a reformular de raíz.",IF(AND($D29="Plowhorse",$E29="Winner"),"Popular con margen bajo: subir precio o bajar coste.",IF(AND($D29="Plowhorse",$E29="Loser"),"Popular pero caro de producir y de margen corto: reformular la receta antes de tocar el precio.",IF(AND('Datos'!$G29>='Datos'!$N29,'Datos'!$H29>'Datos'!$O29),"MC alto con food cost pobre: proteger el margen en euros, revisar precio, no retirar.",IF(AND($D29="Puzzle",$E29="Winner"),"Rentable y con food cost sano, pero poco pedido: es problema de carta, no de cocina. Renómbralo, súbelo de posición o que lo sugiera la sala.",IF($F29="Sleeper","Food cost sano pero aporta poco margen al total: dale visibilidad antes de retirarlo.",IF(AND($G29="Por debajo del objetivo",$D29="Star"),"Vende y deja margen, pero se queda por debajo del Goal Value de su familia: va justo de recorrido, revisa el precio.",IF($D29="Dog","Poco pedido: antes de retirarlo comprueba si es de temporada o si acompaña a otro plato que sí vende.","Las lecturas discrepan: cada método mide dos de las tres variables (popularidad, margen en euros y food cost). Decide con la que más te duela este mes.")))))))))),"") | J29: =IFERROR(IF($B29="","",IF($H29=0,"Mantener",IF(AND($D29="Dog",$E29="Loser"),"Retirar",IF($D29="Plowhorse","Resubir",IF($D29="Puzzle","Rediseñar",IF($F29="Problem","Reformular","Revisar")))))),"")
A31: RESUMEN — lo calcula el libro
B32: Lecturas fuera de la mejor categoría | C32: Platos | D32: % de la carta
B33: 0 | C33: =COUNTIF($H$5:$H$29,$B33) -> 3 | D33: =IFERROR(IF(COUNTIF($B$5:$B$29,"<>")=0,"",$C33/COUNTIF($B$5:$B$29,"<>")),"") -> 0.15
B34: 1 | C34: =COUNTIF($H$5:$H$29,$B34) -> 4 | D34: =IFERROR(IF(COUNTIF($B$5:$B$29,"<>")=0,"",$C34/COUNTIF($B$5:$B$29,"<>")),"") -> 0.2
B35: 2 | C35: =COUNTIF($H$5:$H$29,$B35) -> 1 | D35: =IFERROR(IF(COUNTIF($B$5:$B$29,"<>")=0,"",$C35/COUNTIF($B$5:$B$29,"<>")),"") -> 0.05
B36: 3 | C36: =COUNTIF($H$5:$H$29,$B36) -> 4 | D36: =IFERROR(IF(COUNTIF($B$5:$B$29,"<>")=0,"",$C36/COUNTIF($B$5:$B$29,"<>")),"") -> 0.2
B37: 4 | C37: =COUNTIF($H$5:$H$29,$B37) -> 8 | D37: =IFERROR(IF(COUNTIF($B$5:$B$29,"<>")=0,"",$C37/COUNTIF($B$5:$B$29,"<>")),"") -> 0.4
B39: Platos con las cuatro lecturas en la mejor categoría | C39: =COUNTIF($H$5:$H$29,0) -> 3
B40: Platos con tres o cuatro lecturas fuera | C40: =COUNTIF($H$5:$H$29,3)+COUNTIF($H$5:$H$29,4) -> 12

Sheet Menú Precio Fijo
A1: Menú de precio fijo — el margen lo decide el mix
A2: AI Chef Pro · aichef.pro — Guía Food Cost + Ingeniería de Menú
D3: En un menú cerrado el precio ya está puesto: lo que mueve el margen es qué elige la gente.
A4: Curso | B4: Opción | C4: Coste por ración (€) | D4: Mix base (%) | E4: Mix escenario A (%) | F4: Mix escenario B (%) | G4: Nota
A5: Primeros | B5: Ensalada de la huerta | C5: 1.1 | D5: 0.4 | E5: 0.25 | F5: 0.35 | G5: Cada curso suma 100 %: es el reparto de elecciones, no un descuento.
A6: Primeros | B6: Crema de calabaza | C6: 1.05 | D6: 0.25 | E6: 0.2 | F6: 0.45
A7: Primeros | B7: Pasta al pesto | C7: 1.6 | D7: 0.35 | E7: 0.55 | F7: 0.2
A8: Primeros
A9: Segundos | B9: Pollo asado con patatas | C9: 2.8 | D9: 0.45 | E9: 0.3 | F9: 0.6 | G9: Escenario A: el comensal se va a la opción más cara. Escenario B: se va a la más barata.
A10: Segundos | B10: Merluza a la romana | C10: 3.9 | D10: 0.3 | E10: 0.45 | F10: 0.15
A11: Segundos | B11: Albóndigas de ternera | C11: 3.2 | D11: 0.25 | E11: 0.25 | F11: 0.25
A12: Segundos
A13: Postres | B13: Flan casero | C13: 0.5 | D13: 0.55 | E13: 0.4 | F13: 0.7
A14: Postres | B14: Fruta del tiempo | C14: 0.7 | D14: 0.45 | E14: 0.6 | F14: 0.3
A15: Postres
A18: PARÁMETROS DEL MENÚ
A19: PVP del menú, con IVA (€) | C19: 14.5 | E19: El precio que ve el comensal en la pizarra o en la carta.
A20: Tipo de IVA de restauración (%) | C20: 0.1 | E20: 10 % en restauración, INCLUIDA la bebida alcohólica servida en sala: el art. 91.Uno.2.2 de la Ley del IVA grava a ese tipo los servicios de hostelería y «el suministro de comidas y bebidas para consumir en el acto», y no excluye el alcohol. Cámbialo aquí y se recalcula todo el libro.
A21: PVP del menú, sin IVA (€) | C21: =IFERROR(IF(OR($C$19="",$C$20=""),"",$C$19/(1+$C$20)),"") -> 13.181818
A22: Costes fijos por menú (€) | C22: 0.55 | E22: Pan, agua o copa de vino de la casa y café si van incluidos, prorrateados por menú servido.
A23: Food cost objetivo del menú (%) | C23: 0.3 | E23: Objetivo de la casa. Si el menú se pasa de aquí, la fila «Food cost del menú» se pone en rojo.
A24: Menús servidos al mes | C24: 100 | E24: Cuántos menús de este tipo sirves al mes: escala el margen por menú al margen del mes.
A25: COSTE MEDIO PONDERADO POR CURSO — lo calcula el libro
A26: Curso | B26: Suma del mix base (%) | C26: Coste medio base (€) | D26: Suma del mix A (%) | E26: Coste medio A (€) | F26: Suma del mix B (%) | G26: Coste medio B (€)
A27: Primeros | B27: =IFERROR(SUMIF($A$5:$A$16,$A27,$D$5:$D$16),"") -> 1 | C27: =IFERROR(SUMPRODUCT(--($A$5:$A$16=$A27),$C$5:$C$16,$D$5:$D$16),"") -> 1.2625 | D27: =IFERROR(SUMIF($A$5:$A$16,$A27,$E$5:$E$16),"") -> 1 | E27: =IFERROR(SUMPRODUCT(--($A$5:$A$16=$A27),$C$5:$C$16,$E$5:$E$16),"") -> 1.365 | F27: =IFERROR(SUMIF($A$5:$A$16,$A27,$F$5:$F$16),"") -> 1 | G27: =IFERROR(SUMPRODUCT(--($A$5:$A$16=$A27),$C$5:$C$16,$F$5:$F$16),"") -> 1.1775
A28: Segundos | B28: =IFERROR(SUMIF($A$5:$A$16,$A28,$D$5:$D$16),"") -> 1 | C28: =IFERROR(SUMPRODUCT(--($A$5:$A$16=$A28),$C$5:$C$16,$D$5:$D$16),"") -> 3.23 | D28: =IFERROR(SUMIF($A$5:$A$16,$A28,$E$5:$E$16),"") -> 1 | E28: =IFERROR(SUMPRODUCT(--($A$5:$A$16=$A28),$C$5:$C$16,$E$5:$E$16),"") -> 3.395 | F28: =IFERROR(SUMIF($A$5:$A$16,$A28,$F$5:$F$16),"") -> 1 | G28: =IFERROR(SUMPRODUCT(--($A$5:$A$16=$A28),$C$5:$C$16,$F$5:$F$16),"") -> 3.065
A29: Postres | B29: =IFERROR(SUMIF($A$5:$A$16,$A29,$D$5:$D$16),"") -> 1 | C29: =IFERROR(SUMPRODUCT(--($A$5:$A$16=$A29),$C$5:$C$16,$D$5:$D$16),"") -> 0.59 | D29: =IFERROR(SUMIF($A$5:$A$16,$A29,$E$5:$E$16),"") -> 1 | E29: =IFERROR(SUMPRODUCT(--($A$5:$A$16=$A29),$C$5:$C$16,$E$5:$E$16),"") -> 0.62 | F29: =IFERROR(SUMIF($A$5:$A$16,$A29,$F$5:$F$16),"") -> 1 | G29: =IFERROR(SUMPRODUCT(--($A$5:$A$16=$A29),$C$5:$C$16,$F$5:$F$16),"") -> 0.56
A30: Si una suma de mix no da 100 % se pone en rojo: el reparto de ese curso está mal repartido.
A32: RESULTADO DEL MENÚ — lo calcula el libro
A33: Concepto | B33: Mix base | C33: Escenario A | D33: Escenario B
A34: Coste medio de los primeros (€) | B34: =IFERROR($C$27,"") -> 1.2625 | C34: =IFERROR($E$27,"") -> 1.365 | D34: =IFERROR($G$27,"") -> 1.1775
A35: Coste medio de los segundos (€) | B35: =IFERROR($C$28,"") -> 3.23 | C35: =IFERROR($E$28,"") -> 3.395 | D35: =IFERROR($G$28,"") -> 3.065
A36: Coste medio de los postres (€) | B36: =IFERROR($C$29,"") -> 0.59 | C36: =IFERROR($E$29,"") -> 0.62 | D36: =IFERROR($G$29,"") -> 0.56
A37: Costes fijos por menú (€) | B37: =IFERROR($C$22,"") -> 0.55 | C37: =IFERROR($C$22,"") -> 0.55 | D37: =IFERROR($C$22,"") -> 0.55
A38: Coste medio total del menú (€) | B38: =IFERROR(SUM(B34:B37),"") -> 5.6325 | C38: =IFERROR(SUM(C34:C37),"") -> 5.93 | D38: =IFERROR(SUM(D34:D37),"") -> 5.3525
A39: Food cost del menú (%) | B39: =IFERROR(IF(OR($C$21="",$C$21=0,B38=""),"",B38/$C$21),"") -> 0.4272931 | C39: =IFERROR(IF(OR($C$21="",$C$21=0,C38=""),"",C38/$C$21),"") -> 0.44986207 | D39: =IFERROR(IF(OR($C$21="",$C$21=0,D38=""),"",D38/$C$21),"") -> 0.40605172 | F39: Rojo = por encima del food cost objetivo del menú.
A40: Margen de contribución por menú (€) | B40: =IFERROR(IF(OR($C$21="",B38=""),"",$C$21-B38),"") -> 7.5493182 | C40: =IFERROR(IF(OR($C$21="",C38=""),"",$C$21-C38),"") -> 7.2518182 | D40: =IFERROR(IF(OR($C$21="",D38=""),"",$C$21-D38),"") -> 7.8293182
A41: Margen sobre los menús servidos al mes (€) | B41: =IFERROR(IF(B40="","",B40*$C$24),"") -> 754.93182 | C41: =IFERROR(IF(C40="","",C40*$C$24),"") -> 725.18182 | D41: =IFERROR(IF(D40="","",D40*$C$24),"") -> 782.93182
A43: Los tres escenarios usan el MISMO precio y los MISMOS costes: lo único que cambia es el reparto de elecciones. Esa diferencia es el margen que te juegas cada día en el menú.
A44: En el ejemplo el menú se queda POR ENCIMA del food cost objetivo de la casa. Es lo habitual en un menú de precio cerrado: o subes el precio, o cambias las opciones que ofreces, o asumes que el menú trae clientela y el margen lo hace la carta. Lo que no vale es no saberlo.
