Workbook

Sheet Instrucciones
A1: Simulador de repricing multicanal
A2: AI Chef Pro · aichef.pro — Guía Food Cost + Ingeniería de Menú
A4: Instrucciones de uso
A5: 1. Hoja «Carta»: escribe en las celdas verdes cada plato con su coste por ración, el PVP que tiene HOY en el comedor (sin IVA), el tipo de producto, el precio techo que acepta el mercado y las unidades que vendes al mes.
A6: 2. Hoja «Parámetros»: pon la comisión, el packaging por pedido, los platos por pedido y el food cost objetivo de CADA canal. Son los de tu contrato, no una tarifa oficial.
A7: 3. Revisa la matriz de IVA repercutido: manda el canal y el tipo de producto, y las fórmulas la leen con INDEX/MATCH.
A8: 4. Lee «Food cost efectivo al PVP de sala»: es en lo que se convierte tu food cost si publicas en la app el mismo precio que tienes en el comedor.
A9: 5. Compara el «PVP sin IVA necesario» con tu precio techo. La columna «¿Viable?» marca los platos que no caben en ese canal a tu objetivo.
A10: 6. «PVP que puedes cobrar» es el menor de los dos: si el precio necesario pasa del techo, cobras el techo y el food cost se te va; ahí está el margen mensual real de cada canal.
A11: 7. Hoja «Resumen»: platos viables, food cost medio, margen mensual por canal y diferencia frente a la sala.
A12: 8. Las unidades vendidas son las mismas en los tres canales a propósito: la pregunta que responde el libro es qué margen daría ESE volumen en cada canal, no cuánto venderías en cada uno.
A14: Celdas verdes = campos editables
... A23: Versión 1.0 · septiembre 2026 · aichef.pro/guia-food-cost-ingenieria-menu · info@aichef.pro

Sheet Parámetros
A1: Parámetros del simulador
A2: AI Chef Pro · aichef.pro — Guía Food Cost + Ingeniería de Menú
A4: MATRIZ DE IVA REPERCUTIDO POR CANAL Y TIPO DE PRODUCTO
A5: Canal | B5: Comida | C5: Refresco/azucarada | D5: Bebida alcohólica
A6: Sala | B6: 0.1 | C6: 0.1 | D6: 0.1
A7: Take away | B7: 0.1 | C7: 0.21 | D7: 0.21
A8: Delivery | B8: 0.1 | C8: 0.21 | D8: 0.21
A9: Sala — 10 % para todo el consumo en el local, alcohol incluido: art. 91.Uno.2.2.º de la Ley del IVA (servicios de hostelería y suministro de comidas y bebidas para consumir en el acto).
A10: Take away — Sin servicio es entrega de bienes y manda el tipo del producto: comida elaborada 10 % (art. 91.Uno.1.1.º); bebidas alcohólicas y refrescos, zumos y gaseosas con azúcares o edulcorantes añadidos, 21 % (excluidos del tipo reducido desde el 1-ene-2021).
A11: Delivery — Misma regla que el take away: es entrega de bienes, no servicio de hostelería.
A12: Fuente: Ley 37/1992 del IVA, texto consolidado: https://www.boe.es/buscar/act.php?id=BOE-A-1992-28740
A14: PARÁMETROS DEL SIMULADOR POR CANAL
A15: Canal | B15: Comisión de la plataforma (%) | C15: Packaging (€/pedido) | D15: Platos por pedido (n.º) | E15: Food cost objetivo (%) | F15: Packaging por plato (€)
A16: Sala | B16: 0 | C16: 0 | D16: 1 | E16: 0.3 | F16: =IFERROR(IF(OR($C16="",$D16="",$D16=0),"",$C16/$D16),"") -> 0
A17: Take away | B17: 0 | C17: 1.75 | D17: 2.5 | E17: 0.3 | F17: =IFERROR(IF(OR($C17="",$D17="",$D17=0),"",$C17/$D17),"") -> 0.7
A18: Delivery | B18: 0.3 | C18: 1.75 | D18: 2.5 | E18: 0.4 | F18: =IFERROR(IF(OR($C18="",$D18="",$D18=0),"",$C18/$D18),"") -> 0.7
A19: En sala no hay packaging ni comisión: el packaging por plato sale de dividir el envase de un pedido entre los platos que lleva ese pedido.
A20: La comisión se aplica sobre el precio CON el que vendes en la plataforma; el food cost objetivo puede ser distinto en cada canal si decides que el delivery trabaje con otro margen.
A22: COMISIONES DE LAS PLATAFORMAS — ORDEN DE MAGNITUD (INFORMATIVO, NO ES UN TARIFARIO)
A23: Plataforma | B23: Comisión y cuotas de referencia
A24: Glovo | B24: 15-35 % + IVA según zona y si la plataforma reparte; cuota mensual aprox. 39 €
A25: Uber Eats | B25: 30 % / 25 % / 15-20 % + IVA según plan
A26: Just Eat | B26: 13 % + IVA solo marketing (reparto propio) · 25-35 % + IVA servicio completo · 0,30 €/pedido
A27: Deliveroo | B27: 30 % + IVA estándar · 25 % + IVA a partir de 500 pedidos/mes · cuota tecnológica 50 €/mes
A28: Fuente: Orden de magnitud de mercado 2025-2026 según qamarero.com (consultado el 2026-09-03). Las plataformas no publican tarifario: usa el porcentaje de TU contrato.
A29: Packaging de referencia: 1,35-2,15 €/pedido (misma fuente). Usa el coste real de TU envase.

Sheet Carta
A1: Carta: el mismo plato en sala, take away y delivery
A2: AI Chef Pro · aichef.pro — Guía Food Cost + Ingeniería de Menú
A3: El coste por ración sale de la ficha de escandallo; el PVP de sala es el que tienes hoy en la carta, sin IVA. | H3: Sala | O3: Take away | V3: Delivery
A4: # | B4: Plato | C4: Coste por ración, sin IVA (€) | D4: PVP en sala, sin IVA (€) | E4: Tipo de producto (IVA) | F4: Precio techo del mercado, sin IVA (€) | G4: Uds vendidas al mes (n.º) | H4: Food cost efectivo al PVP de sala (%) | I4: PVP sin IVA necesario para el food cost objetivo (€) | J4: PVP con IVA para el cliente (€) | K4: ¿Viable? (PVP necesario vs precio techo) | L4: PVP que puedes cobrar, sin IVA (€) | M4: Ingreso neto por plato (€) | N4: Margen mensual (€) | O4: Food cost efectivo al PVP de sala (%) | P4: PVP sin IVA necesario para el food cost objetivo (€) | Q4: PVP con IVA para el cliente (€) | R4: ¿Viable? (PVP necesario vs precio techo) | S4: PVP que puedes cobrar, sin IVA (€) | T4: Ingreso neto por plato (€) | U4: Margen mensual (€) | V4: Food cost efectivo al PVP de sala (%) | W4: PVP sin IVA necesario para el food cost objetivo (€) | X4: PVP con IVA para el cliente (€) | Y4: ¿Viable? (PVP necesario vs precio techo) | Z4: PVP que puedes cobrar, sin IVA (€) | AA4: Ingreso neto por plato (€) | AB4: Margen mensual (€)
A5: 1 | B5: Croquetas de jamón ibérico (6 ud) | C5: 2.1 | D5: 8.6 | E5: Comida | F5: 11.6 | G5: 420 | H5: =IFERROR(IF(OR($C5="",$D5=""),"",($C5+$D$34)/($D5*(1-$C$34))),"") -> 0.24418605 | I5: =IFERROR(IF($C5="","",($C5+$D$34)/($E$34*(1-$C$34))),"") -> 7 | J5: =IFERROR(IF(OR($I5="",$E5=""),"",$I5*(1+INDEX(Parámetros!$B$6:$D$8,MATCH($B$34,Parámetros!$A$6:$A$8,0),MATCH($E5,Parámetros!$B$5:$D$5,0)))),"") -> 7.7 | K5: =IF(OR($I5="",$F5=""),"",IF($I5<=$F5,"Sí","No: no llega al precio que acepta el mercado")) -> Sí | L5: =IFERROR(IF(OR($I5="",$F5=""),"",MIN($I5,$F5)),"") -> 7 | M5: =IFERROR(IF($L5="","",$L5*(1-$C$34)-$D$34),"") -> 7 | N5: =IFERROR(IF(OR($M5="",$C5="",$G5=""),"",($M5-$C5)*$G5),"") -> 2058 | O5: =IFERROR(IF(OR($C5="",$D5=""),"",($C5+$D$35)/($D5*(1-$C$35))),"") -> 0.3255814 | P5: =IFERROR(IF($C5="","",($C5+$D$35)/($E$35*(1-$C$35))),"") -> 9.3333333 | Q5: =IFERROR(IF(OR($P5="",$E5=""),"",$P5*(1+INDEX(Parámetros!$B$6:$D$8,MATCH($B$35,Parámetros!$A$6:$A$8,0),MATCH($E5,Parámetros!$B$5:$D$5,0)))),"") -> 10.266667 | R5: =IF(OR($P5="",$F5=""),"",IF($P5<=$F5,"Sí","No: excluir o reformular")) -> Sí | S5: =IFERROR(IF(OR($P5="",$F5=""),"",MIN($P5,$F5)),"") -> 9.3333333 | T5: =IFERROR(IF($S5="","",$S5*(1-$C$35)-$D$35),"") -> 8.6333333 | U5: =IFERROR(IF(OR($T5="",$C5="",$G5=""),"",($T5-$C5)*$G5),"") -> 2744 | V5: =IFERROR(IF(OR($C5="",$D5=""),"",($C5+$D$36)/($D5*(1-$C$36))),"") -> 0.46511628 | W5: =IFERROR(IF($C5="","",($C5+$D$36)/($E$36*(1-$C$36))),"") -> 10 | X5: =IFERROR(IF(OR($W5="",$E5=""),"",$W5*(1+INDEX(Parámetros!$B$6:$D$8,MATCH($B$36,Parámetros!$A$6:$A$8,0),MATCH($E5,Parámetros!$B$5:$D$5,0)))),"") -> 11 | Y5: =IF(OR($W5="",$F5=""),"",IF($W5<=$F5,"Sí","No: excluir o reformular")) -> Sí | Z5: =IFERROR(IF(OR($W5="",$F5=""),"",MIN($W5,$F5)),"") -> 10 | AA5: =IFERROR(IF($Z5="","",$Z5*(1-$C$36)-$D$36),"") -> 6.3 | AB5: =IFERROR(IF(OR($AA5="",$C5="",$G5=""),"",($AA5-$C5)*$G5),"") -> 1764
A6: 2 | B6: Ensalada de tomate rosa, ventresca y cebolleta | C6: 3.6 | D6: 11.8 | E6: Comida | F6: 15.9 | G6: 310 | H6: =IFERROR(IF(OR($C6="",$D6=""),"",($C6+$D$34)/($D6*(1-$C$34))),"") -> 0.30508475 | I6: =IFERROR(IF($C6="","",($C6+$D$34)/($E$34*(1-$C$34))),"") -> 12 | J6: =IFERROR(IF(OR($I6="",$E6=""),"",$I6*(1+INDEX(Parámetros!$B$6:$D$8,MATCH($B$34,Parámetros!$A$6:$A$8,0),MATCH($E6,Parámetros!$B$5:$D$5,0)))),"") -> 13.2 | K6: =IF(OR($I6="",$F6=""),"",IF($I6<=$F6,"Sí","No: no llega al precio que acepta el mercado")) -> Sí | L6: =IFERROR(IF(OR($I6="",$F6=""),"",MIN($I6,$F6)),"") -> 12 | M6: =IFERROR(IF($L6="","",$L6*(1-$C$34)-$D$34),"") -> 12 | N6: =IFERROR(IF(OR($M6="",$C6="",$G6=""),"",($M6-$C6)*$G6),"") -> 2604 | O6: =IFERROR(IF(OR($C6="",$D6=""),"",($C6+$D$35)/($D6*(1-$C$35))),"") -> 0.36440678 | P6: =IFERROR(IF($C6="","",($C6+$D$35)/($E$35*(1-$C$35))),"") -> 14.333333 | Q6: =IFERROR(IF(OR($P6="",$E6=""),"",$P6*(1+INDEX(Parámetros!$B$6:$D$8,MATCH($B$35,Parámetros!$A$6:$A$8,0),MATCH($E6,Parámetros!$B$5:$D$5,0)))),"") -> 15.766667 | R6: =IF(OR($P6="",$F6=""),"",IF($P6<=$F6,"Sí","No: excluir o reformular")) -> Sí | S6: =IFERROR(IF(OR($P6="",$F6=""),"",MIN($P6,$F6)),"") -> 14.333333 | T6: =IFERROR(IF($S6="","",$S6*(1-$C$35)-$D$35),"") -> 13.633333 | U6: =IFERROR(IF(OR($T6="",$C6="",$G6=""),"",($T6-$C6)*$G6),"") -> 3110.3333 | V6: =IFERROR(IF(OR($C6="",$D6=""),"",($C6+$D$36)/($D6*(1-$C$36))),"") -> 0.52058111 | W6: =IFERROR(IF($C6="","",($C6+$D$36)/($E$36*(1-$C$36))),"") -> 15.357143 | X6: =IFERROR(IF(OR($W6="",$E6=""),"",$W6*(1+INDEX(Parámetros!$B$6:$D$8,MATCH($B$36,Parámetros!$A$6:$A$8,0),MATCH($E6,Parámetros!$B$5:$D$5,0)))),"") -> 16.892857 | Y6: =IF(OR($W6="",$F6=""),"",IF($W6<=$F6,"Sí","No: excluir o reformular")) -> Sí | Z6: =IFERROR(IF(OR($W6="",$F6=""),"",MIN($W6,$F6)),"") -> 15.357143 | AA6: =IFERROR(IF($Z6="","",$Z6*(1-$C$36)-$D$36),"") -> 10.05 | AB6: =IFERROR(IF(OR($AA6="",$C6="",$G6=""),"",($AA6-$C6)*$G6),"") -> 1999.5
A7: 3 | B7: Gambas al ajillo | C7: 6.9 | D7: 15.5 | E7: Comida | F7: 20.9 | G7: 260 | H7: =IFERROR(IF(OR($C7="",$D7=""),"",($C7+$D$34)/($D7*(1-$C$34))),"") -> 0.44516129 | I7: =IFERROR(IF($C7="","",($C7+$D$34)/($E$34*(1-$C$34))),"") -> 23 | J7: =IFERROR(IF(OR($I7="",$E7=""),"",$I7*(1+INDEX(Parámetros!$B$6:$D$8,MATCH($B$34,Parámetros!$A$6:$A$8,0),MATCH($E7,Parámetros!$B$5:$D$5,0)))),"") -> 25.3 | K7: =IF(OR($I7="",$F7=""),"",IF($I7<=$F7,"Sí","No: no llega al precio que acepta el mercado")) -> No: no llega al precio que acepta el mercado | L7: =IFERROR(IF(OR($I7="",$F7=""),"",MIN($I7,$F7)),"") -> 20.9 | M7: =IFERROR(IF($L7="","",$L7*(1-$C$34)-$D$34),"") -> 20.9 | N7: =IFERROR(IF(OR($M7="",$C7="",$G7=""),"",($M7-$C7)*$G7),"") -> 3640 | O7: =IFERROR(IF(OR($C7="",$D7=""),"",($C7+$D$35)/($D7*(1-$C$35))),"") -> 0.49032258 | P7: =IFERROR(IF($C7="","",($C7+$D$35)/($E$35*(1-$C$35))),"") -> 25.333333 | Q7: =IFERROR(IF(OR($P7="",$E7=""),"",$P7*(1+INDEX(Parámetros!$B$6:$D$8,MATCH($B$35,Parámetros!$A$6:$A$8,0),MATCH($E7,Parámetros!$B$5:$D$5,0)))),"") -> 27.866667 | R7: =IF(OR($P7="",$F7=""),"",IF($P7<=$F7,"Sí","No: excluir o reformular")) -> No: excluir o reformular | S7: =IFERROR(IF(OR($P7="",$F7=""),"",MIN($P7,$F7)),"") -> 20.9 | T7: =IFERROR(IF($S7="","",$S7*(1-$C$35)-$D$35),"") -> 20.2 | U7: =IFERROR(IF(OR($T7="",$C7="",$G7=""),"",($T7-$C7)*$G7),"") -> 3458 | V7: =IFERROR(IF(OR($C7="",$D7=""),"",($C7+$D$36)/($D7*(1-$C$36))),"") -> 0.70046083 | W7: =IFERROR(IF($C7="","",($C7+$D$36)/($E$36*(1-$C$36))),"") -> 27.142857 | X7: =IFERROR(IF(OR($W7="",$E7=""),"",$W7*(1+INDEX(Parámetros!$B$6:$D$8,MATCH($B$36,Parámetros!$A$6:$A$8,0),MATCH($E7,Parámetros!$B$5:$D$5,0)))),"") -> 29.857143 | Y7: =IF(OR($W7="",$F7=""),"",IF($W7<=$F7,"Sí","No: excluir o reformular")) -> No: excluir o reformular | Z7: =IFERROR(IF(OR($W7="",$F7=""),"",MIN($W7,$F7)),"") -> 20.9 | AA7: =IFERROR(IF($Z7="","",$Z7*(1-$C$36)-$D$36),"") -> 13.93 | AB7: =IFERROR(IF(OR($AA7="",$C7="",$G7=""),"",($AA7-$C7)*$G7),"") -> 1827.8
A8: 4 | B8: Huevos rotos con patatas y chistorra | C8: 2.4 | D8: 9.8 | E8: Comida | F8: 13.2 | G8: 380 | H8: =IFERROR(IF(OR($C8="",$D8=""),"",($C8+$D$34)/($D8*(1-$C$34))),"") -> 0.24489796 | I8: =IFERROR(IF($C8="","",($C8+$D$34)/($E$34*(1-$C$34))),"") -> 8 | J8: =IFERROR(IF(OR($I8="",$E8=""),"",$I8*(1+INDEX(Parámetros!$B$6:$D$8,MATCH($B$34,Parámetros!$A$6:$A$8,0),MATCH($E8,Parámetros!$B$5:$D$5,0)))),"") -> 8.8 | K8: =IF(OR($I8="",$F8=""),"",IF($I8<=$F8,"Sí","No: no llega al precio que acepta el mercado")) -> Sí | L8: =IFERROR(IF(OR($I8="",$F8=""),"",MIN($I8,$F8)),"") -> 8 | M8: =IFERROR(IF($L8="","",$L8*(1-$C$34)-$D$34),"") -> 8 | N8: =IFERROR(IF(OR($M8="",$C8="",$G8=""),"",($M8-$C8)*$G8),"") -> 2128 | O8: =IFERROR(IF(OR($C8="",$D8=""),"",($C8+$D$35)/($D8*(1-$C$35))),"") -> 0.31632653 | P8: =IFERROR(IF($C8="","",($C8+$D$35)/($E$35*(1-$C$35))),"") -> 10.333333 | Q8: =IFERROR(IF(OR($P8="",$E8=""),"",$P8*(1+INDEX(Parámetros!$B$6:$D$8,MATCH($B$35,Parámetros!$A$6:$A$8,0),MATCH($E8,Parámetros!$B$5:$D$5,0)))),"") -> 11.366667 | R8: =IF(OR($P8="",$F8=""),"",IF($P8<=$F8,"Sí","No: excluir o reformular")) -> Sí | S8: =IFERROR(IF(OR($P8="",$F8=""),"",MIN($P8,$F8)),"") -> 10.333333 | T8: =IFERROR(IF($S8="","",$S8*(1-$C$35)-$D$35),"") -> 9.6333333 | U8: =IFERROR(IF(OR($T8="",$C8="",$G8=""),"",($T8-$C8)*$G8),"") -> 2748.6667 | V8: =IFERROR(IF(OR($C8="",$D8=""),"",($C8+$D$36)/($D8*(1-$C$36))),"") -> 0.45189504 | W8: =IFERROR(IF($C8="","",($C8+$D$36)/($E$36*(1-$C$36))),"") -> 11.071429 | X8: =IFERROR(IF(OR($W8="",$E8=""),"",$W8*(1+INDEX(Parámetros!$B$6:$D$8,MATCH($B$36,Parámetros!$A$6:$A$8,0),MATCH($E8,Parámetros!$B$5:$D$5,0)))),"") -> 12.178571 | Y8: =IF(OR($W8="",$F8=""),"",IF($W8<=$F8,"Sí","No: excluir o reformular")) -> Sí | Z8: =IFERROR(IF(OR($W8="",$F8=""),"",MIN($W8,$F8)),"") -> 11.071429 | AA8: =IFERROR(IF($Z8="","",$Z8*(1-$C$36)-$D$36),"") -> 7.05 | AB8: =IFERROR(IF(OR($AA8="",$C8="",$G8=""),"",($AA8-$C8)*$G8),"") -> 1767
A9: 5 | B9: Tabla de quesos de la zona | C9: 5.2 | D9: 13.6 | E9: Comida | F9: 18.4 | G9: 90 | H9: =IFERROR(IF(OR($C9="",$D9=""),"",($C9+$D$34)/($D9*(1-$C$34))),"") -> 0.38235294 | I9: =IFERROR(IF($C9="","",($C9+$D$34)/($E$34*(1-$C$34))),"") -> 17.333333 | J9: =IFERROR(IF(OR($I9="",$E9=""),"",$I9*(1+INDEX(Parámetros!$B$6:$D$8,MATCH($B$34,Parámetros!$A$6:$A$8,0),MATCH($E9,Parámetros!$B$5:$D$5,0)))),"") -> 19.066667 | K9: =IF(OR($I9="",$F9=""),"",IF($I9<=$F9,"Sí","No: no llega al precio que acepta el mercado")) -> Sí | L9: =IFERROR(IF(OR($I9="",$F9=""),"",MIN($I9,$F9)),"") -> 17.333333 | M9: =IFERROR(IF($L9="","",$L9*(1-$C$34)-$D$34),"") -> 17.333333 | N9: =IFERROR(IF(OR($M9="",$C9="",$G9=""),"",($M9-$C9)*$G9),"") -> 1092 | O9: =IFERROR(IF(OR($C9="",$D9=""),"",($C9+$D$35)/($D9*(1-$C$35))),"") -> 0.43382353 | P9: =IFERROR(IF($C9="","",($C9+$D$35)/($E$35*(1-$C$35))),"") -> 19.666667 | Q9: =IFERROR(IF(OR($P9="",$E9=""),"",$P9*(1+INDEX(Parámetros!$B$6:$D$8,MATCH($B$35,Parámetros!$A$6:$A$8,0),MATCH($E9,Parámetros!$B$5:$D$5,0)))),"") -> 21.633333 | R9: =IF(OR($P9="",$F9=""),"",IF($P9<=$F9,"Sí","No: excluir o reformular")) -> No: excluir o reformular | S9: =IFERROR(IF(OR($P9="",$F9=""),"",MIN($P9,$F9)),"") -> 18.4 | T9: =IFERROR(IF($S9="","",$S9*(1-$C$35)-$D$35),"") -> 17.7 | U9: =IFERROR(IF(OR($T9="",$C9="",$G9=""),"",($T9-$C9)*$G9),"") -> 1125 | V9: =IFERROR(IF(OR($C9="",$D9=""),"",($C9+$D$36)/($D9*(1-$C$36))),"") -> 0.6197479 | W9: =IFERROR(IF($C9="","",($C9+$D$36)/($E$36*(1-$C$36))),"") -> 21.071429 | X9: =IFERROR(IF(OR($W9="",$E9=""),"",$W9*(1+INDEX(Parámetros!$B$6:$D$8,MATCH($B$36,Parámetros!$A$6:$A$8,0),MATCH($E9,Parámetros!$B$5:$D$5,0)))),"") -> 23.178571 | Y9: =IF(OR($W9="",$F9=""),"",IF($W9<=$F9,"Sí","No: excluir o reformular")) -> No: excluir o reformular | Z9: =IFERROR(IF(OR($W9="",$F9=""),"",MIN($W9,$F9)),"") -> 18.4 | AA9: =IFERROR(IF($Z9="","",$Z9*(1-$C$36)-$D$36),"") -> 12.18 | AB9: =IFERROR(IF(OR($AA9="",$C9="",$G9=""),"",($AA9-$C9)*$G9),"") -> 628.2
A10: 6 | B10: Alcachofas confitadas con jamón | C10: 3.1 | D10: 10.9 | E10: Comida | F10: 14.7 | G10: 120 | H10: =IFERROR(IF(OR($C10="",$D10=""),"",($C10+$D$34)/($D10*(1-$C$34))),"") -> 0.28440367 | I10: =IFERROR(IF($C10="","",($C10+$D$34)/($E$34*(1-$C$34))),"") -> 10.333333 | J10: =IFERROR(IF(OR($I10="",$E10=""),"",$I10*(1+INDEX(Parámetros!$B$6:$D$8,MATCH($B$34,Parámetros!$A$6:$A$8,0),MATCH($E10,Parámetros!$B$5:$D$5,0)))),"") -> 11.366667 | K10: =IF(OR($I10="",$F10=""),"",IF($I10<=$F10,"Sí","No: no llega al precio que acepta el mercado")) -> Sí | L10: =IFERROR(IF(OR($I10="",$F10=""),"",MIN($I10,$F10)),"") -> 10.333333 | M10: =IFERROR(IF($L10="","",$L10*(1-$C$34)-$D$34),"") -> 10.333333 | N10: =IFERROR(IF(OR($M10="",$C10="",$G10=""),"",($M10-$C10)*$G10),"") -> 868 | O10: =IFERROR(IF(OR($C10="",$D10=""),"",($C10+$D$35)/($D10*(1-$C$35))),"") -> 0.34862385 | P10: =IFERROR(IF($C10="","",($C10+$D$35)/($E$35*(1-$C$35))),"") -> 12.666667 | Q10: =IFERROR(IF(OR($P10="",$E10=""),"",$P10*(1+INDEX(Parámetros!$B$6:$D$8,MATCH($B$35,Parámetros!$A$6:$A$8,0),MATCH($E10,Parámetros!$B$5:$D$5,0)))),"") -> 13.933333 | R10: =IF(OR($P10="",$F10=""),"",IF($P10<=$F10,"Sí","No: excluir o reformular")) -> Sí | S10: =IFERROR(IF(OR($P10="",$F10=""),"",MIN($P10,$F10)),"") -> 12.666667 | T10: =IFERROR(IF($S10="","",$S10*(1-$C$35)-$D$35),"") -> 11.966667 | U10: =IFERROR(IF(OR($T10="",$C10="",$G10=""),"",($T10-$C10)*$G10),"") -> 1064 | V10: =IFERROR(IF(OR($C10="",$D10=""),"",($C10+$D$36)/($D10*(1-$C$36))),"") -> 0.49803408 | W10: =IFERROR(IF($C10="","",($C10+$D$36)/($E$36*(1-$C$36))),"") -> 13.571429 | X10: =IFERROR(IF(OR($W10="",$E10=""),"",$W10*(1+INDEX(Parámetros!$B$6:$D$8,MATCH($B$36,Parámetros!$A$6:$A$8,0),MATCH($E10,Parámetros!$B$5:$D$5,0)))),"") -> 14.928571 | Y10: =IF(OR($W10="",$F10=""),"",IF($W10<=$F10,"Sí","No: excluir o reformular")) -> Sí | Z10: =IFERROR(IF(OR($W10="",$F10=""),"",MIN($W10,$F10)),"") -> 13.571429 | AA10: =IFERROR(IF($Z10="","",$Z10*(1-$C$36)-$D$36),"") -> 8.8 | AB10: =IFERROR(IF(OR($AA10="",$C10="",$G10=""),"",($AA10-$C10)*$G10),"") -> 684
A11: 7 | B11: Sopa de tomate asado con albahaca | C11: 1.2 | D11: 7.2 | E11: Comida | F11: 9.7 | G11: 150 | H11: =IFERROR(IF(OR($C11="",$D11=""),"",($C11+$D$34)/($D11*(1-$C$34))),"") -> 0.16666667 | I11: =IFERROR(IF($C11="","",($C11+$D$34)/($E$34*(1-$C$34))),"") -> 4 | J11: =IFERROR(IF(OR($I11="",$E11=""),"",$I11*(1+INDEX(Parámetros!$B$6:$D$8,MATCH($B$34,Parámetros!$A$6:$A$8,0),MATCH($E11,Parámetros!$B$5:$D$5,0)))),"") -> 4.4 | K11: =IF(OR($I11="",$F11=""),"",IF($I11<=$F11,"Sí","No: no llega al precio que acepta el mercado")) -> Sí | L11: =IFERROR(IF(OR($I11="",$F11=""),"",MIN($I11,$F11)),"") -> 4 | M11: =IFERROR(IF($L11="","",$L11*(1-$C$34)-$D$34),"") -> 4 | N11: =IFERROR(IF(OR($M11="",$C11="",$G11=""),"",($M11-$C11)*$G11),"") -> 420 | O11: =IFERROR(IF(OR($C11="",$D11=""),"",($C11+$D$35)/($D11*(1-$C$35))),"") -> 0.26388889 | P11: =IFERROR(IF($C11="","",($C11+$D$35)/($E$35*(1-$C$35))),"") -> 6.3333333 | Q11: =IFERROR(IF(OR($P11="",$E11=""),"",$P11*(1+INDEX(Parámetros!$B$6:$D$8,MATCH($B$35,Parámetros!$A$6:$A$8,0),MATCH($E11,Parámetros!$B$5:$D$5,0)))),"") -> 6.9666667 | R11: =IF(OR($P11="",$F11=""),"",IF($P11<=$F11,"Sí","No: excluir o reformular")) -> Sí | S11: =IFERROR(IF(OR($P11="",$F11=""),"",MIN($P11,$F11)),"") -> 6.3333333 | T11: =IFERROR(IF($S11="","",$S11*(1-$C$35)-$D$35),"") -> 5.6333333 | U11: =IFERROR(IF(OR($T11="",$C11="",$G11=""),"",($T11-$C11)*$G11),"") -> 665 | V11: =IFERROR(IF(OR($C11="",$D11=""),"",($C11+$D$36)/($D11*(1-$C$36))),"") -> 0.37698413 | W11: =IFERROR(IF($C11="","",($C11+$D$36)/($E$36*(1-$C$36))),"") -> 6.7857143 | X11: =IFERROR(IF(OR($W11="",$E11=""),"",$W11*(1+INDEX(Parámetros!$B$6:$D$8,MATCH($B$36,Parámetros!$A$6:$A$8,0),MATCH($E11,Parámetros!$B$5:$D$5,0)))),"") -> 7.4642857 | Y11: =IF(OR($W11="",$F11=""),"",IF($W11<=$F11,"Sí","No: excluir o reformular")) -> Sí | Z11: =IFERROR(IF(OR($W11="",$F11=""),"",MIN($W11,$F11)),"") -> 6.7857143 | AA11: =IFERROR(IF($Z11="","",$Z11*(1-$C$36)-$D$36),"") -> 4.05 | AB11: =IFERROR(IF(OR($AA11="",$C11="",$G11=""),"",($AA11-$C11)*$G11),"") -> 427.5
A12: 8 | B12: Solomillo de cerdo ibérico con puré de boniato | C12: 5.67 | D12: 17.3 | E12: Comida | F12: 23.4 | G12: 340 | H12: =IFERROR(IF(OR($C12="",$D12=""),"",($C12+$D$34)/($D12*(1-$C$34))),"") -> 0.32774566 | I12: =IFERROR(IF($C12="","",($C12+$D$34)/($E$34*(1-$C$34))),"") -> 18.9 | J12: =IFERROR(IF(OR($I12="",$E12=""),"",$I12*(1+INDEX(Parámetros!$B$6:$D$8,MATCH($B$34,Parámetros!$A$6:$A$8,0),MATCH($E12,Parámetros!$B$5:$D$5,0)))),"") -> 20.79 | K12: =IF(OR($I12="",$F12=""),"",IF($I12<=$F12,"Sí","No: no llega al precio que acepta el mercado")) -> Sí | L12: =IFERROR(IF(OR($I12="",$F12=""),"",MIN($I12,$F12)),"") -> 18.9 | M12: =IFERROR(IF($L12="","",$L12*(1-$C$34)-$D$34),"") -> 18.9 | N12: =IFERROR(IF(OR($M12="",$C12="",$G12=""),"",($M12-$C12)*$G12),"") -> 4498.2 | O12: =IFERROR(IF(OR($C12="",$D12=""),"",($C12+$D$35)/($D12*(1-$C$35))),"") -> 0.36820809 | P12: =IFERROR(IF($C12="","",($C12+$D$35)/($E$35*(1-$C$35))),"") -> 21.233333 | Q12: =IFERROR(IF(OR($P12="",$E12=""),"",$P12*(1+INDEX(Parámetros!$B$6:$D$8,MATCH($B$35,Parámetros!$A$6:$A$8,0),MATCH($E12,Parámetros!$B$5:$D$5,0)))),"") -> 23.356667 | R12: =IF(OR($P12="",$F12=""),"",IF($P12<=$F12,"Sí","No: excluir o reformular")) -> Sí | S12: =IFERROR(IF(OR($P12="",$F12=""),"",MIN($P12,$F12)),"") -> 21.233333 | T12: =IFERROR(IF($S12="","",$S12*(1-$C$35)-$D$35),"") -> 20.533333 | U12: =IFERROR(IF(OR($T12="",$C12="",$G12=""),"",($T12-$C12)*$G12),"") -> 5053.5333 | V12: =IFERROR(IF(OR($C12="",$D12=""),"",($C12+$D$36)/($D12*(1-$C$36))),"") -> 0.52601156 | W12: =IFERROR(IF($C12="","",($C12+$D$36)/($E$36*(1-$C$36))),"") -> 22.75 | X12: =IFERROR(IF(OR($W12="",$E12=""),"",$W12*(1+INDEX(Parámetros!$B$6:$D$8,MATCH($B$36,Parámetros!$A$6:$A$8,0),MATCH($E12,Parámetros!$B$5:$D$5,0)))),"") -> 25.025 | Y12: =IF(OR($W12="",$F12=""),"",IF($W12<=$F12,"Sí","No: excluir o reformular")) -> Sí | Z12: =IFERROR(IF(OR($W12="",$F12=""),"",MIN($W12,$F12)),"") -> 22.75 | AA12: =IFERROR(IF($Z12="","",$Z12*(1-$C$36)-$D$36),"") -> 15.225 | AB12: =IFERROR(IF(OR($AA12="",$C12="",$G12=""),"",($AA12-$C12)*$G12),"") -> 3248.7
A13: 9 | B13: Bacalao confitado al pil-pil | C13: 7.4 | D13: 19.1 | E13: Comida | F13: 25.8 | G13: 190 | H13: =IFERROR(IF(OR($C13="",$D13=""),"",($C13+$D$34)/($D13*(1-$C$34))),"") -> 0.38743455 | I13: =IFERROR(IF($C13="","",($C13+$D$34)/($E$34*(1-$C$34))),"") -> 24.666667 | J13: =IFERROR(IF(OR($I13="",$E13=""),"",$I13*(1+INDEX(Parámetros!$B$6:$D$8,MATCH($B$34,Parámetros!$A$6:$A$8,0),MATCH($E13,Parámetros!$B$5:$D$5,0)))),"") -> 27.133333 | K13: =IF(OR($I13="",$F13=""),"",IF($I13<=$F13,"Sí","No: no llega al precio que acepta el mercado")) -> Sí | L13: =IFERROR(IF(OR($I13="",$F13=""),"",MIN($I13,$F13)),"") -> 24.666667 | M13: =IFERROR(IF($L13="","",$L13*(1-$C$34)-$D$34),"") -> 24.666667 | N13: =IFERROR(IF(OR($M13="",$C13="",$G13=""),"",($M13-$C13)*$G13),"") -> 3280.6667 | O13: =IFERROR(IF(OR($C13="",$D13=""),"",($C13+$D$35)/($D13*(1-$C$35))),"") -> 0.42408377 | P13: =IFERROR(IF($C13="","",($C13+$D$35)/($E$35*(1-$C$35))),"") -> 27 | Q13: =IFERROR(IF(OR($P13="",$E13=""),"",$P13*(1+INDEX(Parámetros!$B$6:$D$8,MATCH($B$35,Parámetros!$A$6:$A$8,0),MATCH($E13,Parámetros!$B$5:$D$5,0)))),"") -> 29.7 | R13: =IF(OR($P13="",$F13=""),"",IF($P13<=$F13,"Sí","No: excluir o reformular")) -> No: excluir o reformular | S13: =IFERROR(IF(OR($P13="",$F13=""),"",MIN($P13,$F13)),"") -> 25.8 | T13: =IFERROR(IF($S13="","",$S13*(1-$C$35)-$D$35),"") -> 25.1 | U13: =IFERROR(IF(OR($T13="",$C13="",$G13=""),"",($T13-$C13)*$G13),"") -> 3363 | V13: =IFERROR(IF(OR($C13="",$D13=""),"",($C13+$D$36)/($D13*(1-$C$36))),"") -> 0.60583396 | W13: =IFERROR(IF($C13="","",($C13+$D$36)/($E$36*(1-$C$36))),"") -> 28.928571 | X13: =IFERROR(IF(OR($W13="",$E13=""),"",$W13*(1+INDEX(Parámetros!$B$6:$D$8,MATCH($B$36,Parámetros!$A$6:$A$8,0),MATCH($E13,Parámetros!$B$5:$D$5,0)))),"") -> 31.821429 | Y13: =IF(OR($W13="",$F13=""),"",IF($W13<=$F13,"Sí","No: excluir o reformular")) -> No: excluir o reformular | Z13: =IFERROR(IF(OR($W13="",$F13=""),"",MIN($W13,$F13)),"") -> 25.8 | AA13: =IFERROR(IF($Z13="","",$Z13*(1-$C$36)-$D$36),"") -> 17.36 | AB13: =IFERROR(IF(OR($AA13="",$C13="",$G13=""),"",($AA13-$C13)*$G13),"") -> 1892.4
A14: 10 | B14: Hamburguesa de vaca madurada con patatas | C14: 4.3 | D14: 13.6 | E14: Comida | F14: 18.4 | G14: 460 | H14: =IFERROR(IF(OR($C14="",$D14=""),"",($C14+$D$34)/($D14*(1-$C$34))),"") -> 0.31617647 | I14: =IFERROR(IF($C14="","",($C14+$D$34)/($E$34*(1-$C$34))),"") -> 14.333333 | J14: =IFERROR(IF(OR($I14="",$E14=""),"",$I14*(1+INDEX(Parámetros!$B$6:$D$8,MATCH($B$34,Parámetros!$A$6:$A$8,0),MATCH($E14,Parámetros!$B$5:$D$5,0)))),"") -> 15.766667 | K14: =IF(OR($I14="",$F14=""),"",IF($I14<=$F14,"Sí","No: no llega al precio que acepta el mercado")) -> Sí | L14: =IFERROR(IF(OR($I14="",$F14=""),"",MIN($I14,$F14)),"") -> 14.333333 | M14: =IFERROR(IF($L14="","",$L14*(1-$C$34)-$D$34),"") -> 14.333333 | N14: =IFERROR(IF(OR($M14="",$C14="",$G14=""),"",($M14-$C14)*$G14),"") -> 4615.3333 | O14: =IFERROR(IF(OR($C14="",$D14=""),"",($C14+$D$35)/($D14*(1-$C$35))),"") -> 0.36764706 | P14: =IFERROR(IF($C14="","",($C14+$D$35)/($E$35*(1-$C$35))),"") -> 16.666667 | Q14: =IFERROR(IF(OR($P14="",$E14=""),"",$P14*(1+INDEX(Parámetros!$B$6:$D$8,MATCH($B$35,Parámetros!$A$6:$A$8,0),MATCH($E14,Parámetros!$B$5:$D$5,0)))),"") -> 18.333333 | R14: =IF(OR($P14="",$F14=""),"",IF($P14<=$F14,"Sí","No: excluir o reformular")) -> Sí | S14: =IFERROR(IF(OR($P14="",$F14=""),"",MIN($P14,$F14)),"") -> 16.666667 | T14: =IFERROR(IF($S14="","",$S14*(1-$C$35)-$D$35),"") -> 15.966667 | U14: =IFERROR(IF(OR($T14="",$C14="",$G14=""),"",($T14-$C14)*$G14),"") -> 5366.6667 | V14: =IFERROR(IF(OR($C14="",$D14=""),"",($C14+$D$36)/($D14*(1-$C$36))),"") -> 0.52521008 | W14: =IFERROR(IF($C14="","",($C14+$D$36)/($E$36*(1-$C$36))),"") -> 17.857143 | X14: =IFERROR(IF(OR($W14="",$E14=""),"",$W14*(1+INDEX(Parámetros!$B$6:$D$8,MATCH($B$36,Parámetros!$A$6:$A$8,0),MATCH($E14,Parámetros!$B$5:$D$5,0)))),"") -> 19.642857 | Y14: =IF(OR($W14="",$F14=""),"",IF($W14<=$F14,"Sí","No: excluir o reformular")) -> Sí | Z14: =IFERROR(IF(OR($W14="",$F14=""),"",MIN($W14,$F14)),"") -> 17.857143 | AA14: =IFERROR(IF($Z14="","",$Z14*(1-$C$36)-$D$36),"") -> 11.8 | AB14: =IFERROR(IF(OR($AA14="",$C14="",$G14=""),"",($AA14-$C14)*$G14),"") -> 3450
A15: 11 | B15: Arroz meloso de secreto ibérico y setas | C15: 6.2 | D15: 16.4 | E15: Comida | F15: 22.1 | G15: 270 | H15: =IFERROR(IF(OR($C15="",$D15=""),"",($C15+$D$34)/($D15*(1-$C$34))),"") -> 0.37804878 | I15: =IFERROR(IF($C15="","",($C15+$D$34)/($E$34*(1-$C$34))),"") -> 20.666667 | J15: =IFERROR(IF(OR($I15="",$E15=""),"",$I15*(1+INDEX(Parámetros!$B$6:$D$8,MATCH($B$34,Parámetros!$A$6:$A$8,0),MATCH($E15,Parámetros!$B$5:$D$5,0)))),"") -> 22.733333 | K15: =IF(OR($I15="",$F15=""),"",IF($I15<=$F15,"Sí","No: no llega al precio que acepta el mercado")) -> Sí | L15: =IFERROR(IF(OR($I15="",$F15=""),"",MIN($I15,$F15)),"") -> 20.666667 | M15: =IFERROR(IF($L15="","",$L15*(1-$C$34)-$D$34),"") -> 20.666667 | N15: =IFERROR(IF(OR($M15="",$C15="",$G15=""),"",($M15-$C15)*$G15),"") -> 3906 | O15: =IFERROR(IF(OR($C15="",$D15=""),"",($C15+$D$35)/($D15*(1-$C$35))),"") -> 0.42073171 | P15: =IFERROR(IF($C15="","",($C15+$D$35)/($E$35*(1-$C$35))),"") -> 23 | Q15: =IFERROR(IF(OR($P15="",$E15=""),"",$P15*(1+INDEX(Parámetros!$B$6:$D$8,MATCH($B$35,Parámetros!$A$6:$A$8,0),MATCH($E15,Parámetros!$B$5:$D$5,0)))),"") -> 25.3 | R15: =IF(OR($P15="",$F15=""),"",IF($P15<=$F15,"Sí","No: excluir o reformular")) -> No: excluir o reformular | S15: =IFERROR(IF(OR($P15="",$F15=""),"",MIN($P15,$F15)),"") -> 22.1 | T15: =IFERROR(IF($S15="","",$S15*(1-$C$35)-$D$35),"") -> 21.4 | U15: =IFERROR(IF(OR($T15="",$C15="",$G15=""),"",($T15-$C15)*$G15),"") -> 4104 | V15: =IFERROR(IF(OR($C15="",$D15=""),"",($C15+$D$36)/($D15*(1-$C$36))),"") -> 0.6010453 | W15: =IFERROR(IF($C15="","",($C15+$D$36)/($E$36*(1-$C$36))),"") -> 24.642857 | X15: =IFERROR(IF(OR($W15="",$E15=""),"",$W15*(1+INDEX(Parámetros!$B$6:$D$8,MATCH($B$36,Parámetros!$A$6:$A$8,0),MATCH($E15,Parámetros!$B$5:$D$5,0)))),"") -> 27.107143 | Y15: =IF(OR($W15="",$F15=""),"",IF($W15<=$F15,"Sí","No: excluir o reformular")) -> No: excluir o reformular | Z15: =IFERROR(IF(OR($W15="",$F15=""),"",MIN($W15,$F15)),"") -> 22.1 | AA15: =IFERROR(IF($Z15="","",$Z15*(1-$C$36)-$D$36),"") -> 14.77 | AB15: =IFERROR(IF(OR($AA15="",$C15="",$G15=""),"",($AA15-$C15)*$G15),"") -> 2313.9
A16: 12 | B16: Chuletón de vaca madurada (500 g) | C16: 14.8 | D16: 32.7 | E16: Comida | F16: 44.1 | G16: 110 | H16: =IFERROR(IF(OR($C16="",$D16=""),"",($C16+$D$34)/($D16*(1-$C$34))),"") -> 0.45259939 | I16: =IFERROR(IF($C16="","",($C16+$D$34)/($E$34*(1-$C$34))),"") -> 49.333333 | J16: =IFERROR(IF(OR($I16="",$E16=""),"",$I16*(1+INDEX(Parámetros!$B$6:$D$8,MATCH($B$34,Parámetros!$A$6:$A$8,0),MATCH($E16,Parámetros!$B$5:$D$5,0)))),"") -> 54.266667 | K16: =IF(OR($I16="",$F16=""),"",IF($I16<=$F16,"Sí","No: no llega al precio que acepta el mercado")) -> No: no llega al precio que acepta el mercado | L16: =IFERROR(IF(OR($I16="",$F16=""),"",MIN($I16,$F16)),"") -> 44.1 | M16: =IFERROR(IF($L16="","",$L16*(1-$C$34)-$D$34),"") -> 44.1 | N16: =IFERROR(IF(OR($M16="",$C16="",$G16=""),"",($M16-$C16)*$G16),"") -> 3223 | O16: =IFERROR(IF(OR($C16="",$D16=""),"",($C16+$D$35)/($D16*(1-$C$35))),"") -> 0.47400612 | P16: =IFERROR(IF($C16="","",($C16+$D$35)/($E$35*(1-$C$35))),"") -> 51.666667 | Q16: =IFERROR(IF(OR($P16="",$E16=""),"",$P16*(1+INDEX(Parámetros!$B$6:$D$8,MATCH($B$35,Parámetros!$A$6:$A$8,0),MATCH($E16,Parámetros!$B$5:$D$5,0)))),"") -> 56.833333 | R16: =IF(OR($P16="",$F16=""),"",IF($P16<=$F16,"Sí","No: excluir o reformular")) -> No: excluir o reformular | S16: =IFERROR(IF(OR($P16="",$F16=""),"",MIN($P16,$F16)),"") -> 44.1 | T16: =IFERROR(IF($S16="","",$S16*(1-$C$35)-$D$35),"") -> 43.4 | U16: =IFERROR(IF(OR($T16="",$C16="",$G16=""),"",($T16-$C16)*$G16),"") -> 3146 | V16: =IFERROR(IF(OR($C16="",$D16=""),"",($C16+$D$36)/($D16*(1-$C$36))),"") -> 0.67715159 | W16: =IFERROR(IF($C16="","",($C16+$D$36)/($E$36*(1-$C$36))),"") -> 55.357143 | X16: =IFERROR(IF(OR($W16="",$E16=""),"",$W16*(1+INDEX(Parámetros!$B$6:$D$8,MATCH($B$36,Parámetros!$A$6:$A$8,0),MATCH($E16,Parámetros!$B$5:$D$5,0)))),"") -> 60.892857 | Y16: =IF(OR($W16="",$F16=""),"",IF($W16<=$F16,"Sí","No: excluir o reformular")) -> No: excluir o reformular | Z16: =IFERROR(IF(OR($W16="",$F16=""),"",MIN($W16,$F16)),"") -> 44.1 | AA16: =IFERROR(IF($Z16="","",$Z16*(1-$C$36)-$D$36),"") -> 30.17 | AB16: =IFERROR(IF(OR($AA16="",$C16="",$G16=""),"",($AA16-$C16)*$G16),"") -> 1690.7
... A24: 20 | B24: Fruta de temporada preparada | C24: 1.4 | D24: 4.5 | E24: Comida | F24: 6.1 | G24: 60 | H24: =IFERROR(IF(OR($C24="",$D24=""),"",($C24+$D$34)/($D24*(1-$C$34))),"") -> 0.31111111 | I24: =IFERROR(IF($C24="","",($C24+$D$34)/($E$34*(1-$C$34))),"") -> 4.6666667 | J24: =IFERROR(IF(OR($I24="",$E24=""),"",$I24*(1+INDEX(Parámetros!$B$6:$D$8,MATCH($B$34,Parámetros!$A$6:$A$8,0),MATCH($E24,Parámetros!$B$5:$D$5,0)))),"") -> 5.1333333 | K24: =IF(OR($I24="",$F24=""),"",IF($I24<=$F24,"Sí","No: no llega al precio que acepta el mercado")) -> Sí | L24: =IFERROR(IF(OR($I24="",$F24=""),"",MIN($I24,$F24)),"") -> 4.6666667 | M24: =IFERROR(IF($L24="","",$L24*(1-$C$34)-$D$34),"") -> 4.6666667 | N24: =IFERROR(IF(OR($M24="",$C24="",$G24=""),"",($M24-$C24)*$G24),"") -> 196 | O24: =IFERROR(IF(OR($C24="",$D24=""),"",($C24+$D$35)/($D24*(1-$C$35))),"") -> 0.46666667 | P24: =IFERROR(IF($C24="","",($C24+$D$35)/($E$35*(1-$C$35))),"") -> 7 | Q24: =IFERROR(IF(OR($P24="",$E24=""),"",$P24*(1+INDEX(Parámetros!$B$6:$D$8,MATCH($B$35,Parámetros!$A$6:$A$8,0),MATCH($E24,Parámetros!$B$5:$D$5,0)))),"") -> 7.7 | R24: =IF(OR($P24="",$F24=""),"",IF($P24<=$F24,"Sí","No: excluir o reformular")) -> No: excluir o reformular | S24: =IFERROR(IF(OR($P24="",$F24=""),"",MIN($P24,$F24)),"") -> 6.1 | T24: =IFERROR(IF($S24="","",$S24*(1-$C$35)-$D$35),"") -> 5.4 | U24: =IFERROR(IF(OR($T24="",$C24="",$G24=""),"",($T24-$C24)*$G24),"") -> 240 | V24: =IFERROR(IF(OR($C24="",$D24=""),"",($C24+$D$36)/($D24*(1-$C$36))),"") -> 0.66666667 | W24: =IFERROR(IF($C24="","",($C24+$D$36)/($E$36*(1-$C$36))),"") -> 7.5 | X24: =IFERROR(IF(OR($W24="",$E24=""),"",$W24*(1+INDEX(Parámetros!$B$6:$D$8,MATCH($B$36,Parámetros!$A$6:$A$8,0),MATCH($E24,Parámetros!$B$5:$D$5,0)))),"") -> 8.25 | Y24: =IF(OR($W24="",$F24=""),"",IF($W24<=$F24,"Sí","No: excluir o reformular")) -> No: excluir o reformular | Z24: =IFERROR(IF(OR($W24="",$F24=""),"",MIN($W24,$F24)),"") -> 6.1 | AA24: =IFERROR(IF($Z24="","",$Z24*(1-$C$36)-$D$36),"") -> 3.57 | AB24: =IFERROR(IF(OR($AA24="",$C24="",$G24=""),"",($AA24-$C24)*$G24),"") -> 130.2
A25: 21 | H25: =IFERROR(IF(OR($C25="",$D25=""),"",($C25+$D$34)/($D25*(1-$C$34))),"") | I25: =IFERROR(IF($C25="","",($C25+$D$34)/($E$34*(1-$C$34))),"") | J25: =IFERROR(IF(OR($I25="",$E25=""),"",$I25*(1+INDEX(Parámetros!$B$6:$D$8,MATCH($B$34,Parámetros!$A$6:$A$8,0),MATCH($E25,Parámetros!$B$5:$D$5,0)))),"") | K25: =IF(OR($I25="",$F25=""),"",IF($I25<=$F25,"Sí","No: no llega al precio que acepta el mercado")) | L25: =IFERROR(IF(OR($I25="",$F25=""),"",MIN($I25,$F25)),"") | M25: =IFERROR(IF($L25="","",$L25*(1-$C$34)-$D$34),"") | N25: =IFERROR(IF(OR($M25="",$C25="",$G25=""),"",($M25-$C25)*$G25),"") | O25: =IFERROR(IF(OR($C25="",$D25=""),"",($C25+$D$35)/($D25*(1-$C$35))),"") | P25: =IFERROR(IF($C25="","",($C25+$D$35)/($E$35*(1-$C$35))),"") | Q25: =IFERROR(IF(OR($P25="",$E25=""),"",$P25*(1+INDEX(Parámetros!$B$6:$D$8,MATCH($B$35,Parámetros!$A$6:$A$8,0),MATCH($E25,Parámetros!$B$5:$D$5,0)))),"") | R25: =IF(OR($P25="",$F25=""),"",IF($P25<=$F25,"Sí","No: excluir o reformular")) | S25: =IFERROR(IF(OR($P25="",$F25=""),"",MIN($P25,$F25)),"") | T25: =IFERROR(IF($S25="","",$S25*(1-$C$35)-$D$35),"") | U25: =IFERROR(IF(OR($T25="",$C25="",$G25=""),"",($T25-$C25)*$G25),"") | V25: =IFERROR(IF(OR($C25="",$D25=""),"",($C25+$D$36)/($D25*(1-$C$36))),"") | W25: =IFERROR(IF($C25="","",($C25+$D$36)/($E$36*(1-$C$36))),"") | X25: =IFERROR(IF(OR($W25="",$E25=""),"",$W25*(1+INDEX(Parámetros!$B$6:$D$8,MATCH($B$36,Parámetros!$A$6:$A$8,0),MATCH($E25,Parámetros!$B$5:$D$5,0)))),"") | Y25: =IF(OR($W25="",$F25=""),"",IF($W25<=$F25,"Sí","No: excluir o reformular")) | Z25: =IFERROR(IF(OR($W25="",$F25=""),"",MIN($W25,$F25)),"") | AA25: =IFERROR(IF($Z25="","",$Z25*(1-$C$36)-$D$36),"") | AB25: =IFERROR(IF(OR($AA25="",$C25="",$G25=""),"",($AA25-$C25)*$G25),"")
A26: 22 | H26: =IFERROR(IF(OR($C26="",$D26=""),"",($C26+$D$34)/($D26*(1-$C$34))),"") | I26: =IFERROR(IF($C26="","",($C26+$D$34)/($E$34*(1-$C$34))),"") | J26: =IFERROR(IF(OR($I26="",$E26=""),"",$I26*(1+INDEX(Parámetros!$B$6:$D$8,MATCH($B$34,Parámetros!$A$6:$A$8,0),MATCH($E26,Parámetros!$B$5:$D$5,0)))),"") | K26: =IF(OR($I26="",$F26=""),"",IF($I26<=$F26,"Sí","No: no llega al precio que acepta el mercado")) | L26: =IFERROR(IF(OR($I26="",$F26=""),"",MIN($I26,$F26)),"") | M26: =IFERROR(IF($L26="","",$L26*(1-$C$34)-$D$34),"") | N26: =IFERROR(IF(OR($M26="",$C26="",$G26=""),"",($M26-$C26)*$G26),"") | O26: =IFERROR(IF(OR($C26="",$D26=""),"",($C26+$D$35)/($D26*(1-$C$35))),"") | P26: =IFERROR(IF($C26="","",($C26+$D$35)/($E$35*(1-$C$35))),"") | Q26: =IFERROR(IF(OR($P26="",$E26=""),"",$P26*(1+INDEX(Parámetros!$B$6:$D$8,MATCH($B$35,Parámetros!$A$6:$A$8,0),MATCH($E26,Parámetros!$B$5:$D$5,0)))),"") | R26: =IF(OR($P26="",$F26=""),"",IF($P26<=$F26,"Sí","No: excluir o reformular")) | S26: =IFERROR(IF(OR($P26="",$F26=""),"",MIN($P26,$F26)),"") | T26: =IFERROR(IF($S26="","",$S26*(1-$C$35)-$D$35),"") | U26: =IFERROR(IF(OR($T26="",$C26="",$G26=""),"",($T26-$C26)*$G26),"") | V26: =IFERROR(IF(OR($C26="",$D26=""),"",($C26+$D$36)/($D26*(1-$C$36))),"") | W26: =IFERROR(IF($C26="","",($C26+$D$36)/($E$36*(1-$C$36))),"") | X26: =IFERROR(IF(OR($W26="",$E26=""),"",$W26*(1+INDEX(Parámetros!$B$6:$D$8,MATCH($B$36,Parámetros!$A$6:$A$8,0),MATCH($E26,Parámetros!$B$5:$D$5,0)))),"") | Y26: =IF(OR($W26="",$F26=""),"",IF($W26<=$F26,"Sí","No: excluir o reformular")) | Z26: =IFERROR(IF(OR($W26="",$F26=""),"",MIN($W26,$F26)),"") | AA26: =IFERROR(IF($Z26="","",$Z26*(1-$C$36)-$D$36),"") | AB26: =IFERROR(IF(OR($AA26="",$C26="",$G26=""),"",($AA26-$C26)*$G26),"")
A27: 23 | H27: =IFERROR(IF(OR($C27="",$D27=""),"",($C27+$D$34)/($D27*(1-$C$34))),"") | I27: =IFERROR(IF($C27="","",($C27+$D$34)/($E$34*(1-$C$34))),"") | J27: =IFERROR(IF(OR($I27="",$E27=""),"",$I27*(1+INDEX(Parámetros!$B$6:$D$8,MATCH($B$34,Parámetros!$A$6:$A$8,0),MATCH($E27,Parámetros!$B$5:$D$5,0)))),"") | K27: =IF(OR($I27="",$F27=""),"",IF($I27<=$F27,"Sí","No: no llega al precio que acepta el mercado")) | L27: =IFERROR(IF(OR($I27="",$F27=""),"",MIN($I27,$F27)),"") | M27: =IFERROR(IF($L27="","",$L27*(1-$C$34)-$D$34),"") | N27: =IFERROR(IF(OR($M27="",$C27="",$G27=""),"",($M27-$C27)*$G27),"") | O27: =IFERROR(IF(OR($C27="",$D27=""),"",($C27+$D$35)/($D27*(1-$C$35))),"") | P27: =IFERROR(IF($C27="","",($C27+$D$35)/($E$35*(1-$C$35))),"") | Q27: =IFERROR(IF(OR($P27="",$E27=""),"",$P27*(1+INDEX(Parámetros!$B$6:$D$8,MATCH($B$35,Parámetros!$A$6:$A$8,0),MATCH($E27,Parámetros!$B$5:$D$5,0)))),"") | R27: =IF(OR($P27="",$F27=""),"",IF($P27<=$F27,"Sí","No: excluir o reformular")) | S27: =IFERROR(IF(OR($P27="",$F27=""),"",MIN($P27,$F27)),"") | T27: =IFERROR(IF($S27="","",$S27*(1-$C$35)-$D$35),"") | U27: =IFERROR(IF(OR($T27="",$C27="",$G27=""),"",($T27-$C27)*$G27),"") | V27: =IFERROR(IF(OR($C27="",$D27=""),"",($C27+$D$36)/($D27*(1-$C$36))),"") | W27: =IFERROR(IF($C27="","",($C27+$D$36)/($E$36*(1-$C$36))),"") | X27: =IFERROR(IF(OR($W27="",$E27=""),"",$W27*(1+INDEX(Parámetros!$B$6:$D$8,MATCH($B$36,Parámetros!$A$6:$A$8,0),MATCH($E27,Parámetros!$B$5:$D$5,0)))),"") | Y27: =IF(OR($W27="",$F27=""),"",IF($W27<=$F27,"Sí","No: excluir o reformular")) | Z27: =IFERROR(IF(OR($W27="",$F27=""),"",MIN($W27,$F27)),"") | AA27: =IFERROR(IF($Z27="","",$Z27*(1-$C$36)-$D$36),"") | AB27: =IFERROR(IF(OR($AA27="",$C27="",$G27=""),"",($AA27-$C27)*$G27),"")
A28: 24 | H28: =IFERROR(IF(OR($C28="",$D28=""),"",($C28+$D$34)/($D28*(1-$C$34))),"") | I28: =IFERROR(IF($C28="","",($C28+$D$34)/($E$34*(1-$C$34))),"") | J28: =IFERROR(IF(OR($I28="",$E28=""),"",$I28*(1+INDEX(Parámetros!$B$6:$D$8,MATCH($B$34,Parámetros!$A$6:$A$8,0),MATCH($E28,Parámetros!$B$5:$D$5,0)))),"") | K28: =IF(OR($I28="",$F28=""),"",IF($I28<=$F28,"Sí","No: no llega al precio que acepta el mercado")) | L28: =IFERROR(IF(OR($I28="",$F28=""),"",MIN($I28,$F28)),"") | M28: =IFERROR(IF($L28="","",$L28*(1-$C$34)-$D$34),"") | N28: =IFERROR(IF(OR($M28="",$C28="",$G28=""),"",($M28-$C28)*$G28),"") | O28: =IFERROR(IF(OR($C28="",$D28=""),"",($C28+$D$35)/($D28*(1-$C$35))),"") | P28: =IFERROR(IF($C28="","",($C28+$D$35)/($E$35*(1-$C$35))),"") | Q28: =IFERROR(IF(OR($P28="",$E28=""),"",$P28*(1+INDEX(Parámetros!$B$6:$D$8,MATCH($B$35,Parámetros!$A$6:$A$8,0),MATCH($E28,Parámetros!$B$5:$D$5,0)))),"") | R28: =IF(OR($P28="",$F28=""),"",IF($P28<=$F28,"Sí","No: excluir o reformular")) | S28: =IFERROR(IF(OR($P28="",$F28=""),"",MIN($P28,$F28)),"") | T28: =IFERROR(IF($S28="","",$S28*(1-$C$35)-$D$35),"") | U28: =IFERROR(IF(OR($T28="",$C28="",$G28=""),"",($T28-$C28)*$G28),"") | V28: =IFERROR(IF(OR($C28="",$D28=""),"",($C28+$D$36)/($D28*(1-$C$36))),"") | W28: =IFERROR(IF($C28="","",($C28+$D$36)/($E$36*(1-$C$36))),"") | X28: =IFERROR(IF(OR($W28="",$E28=""),"",$W28*(1+INDEX(Parámetros!$B$6:$D$8,MATCH($B$36,Parámetros!$A$6:$A$8,0),MATCH($E28,Parámetros!$B$5:$D$5,0)))),"") | Y28: =IF(OR($W28="",$F28=""),"",IF($W28<=$F28,"Sí","No: excluir o reformular")) | Z28: =IFERROR(IF(OR($W28="",$F28=""),"",MIN($W28,$F28)),"") | AA28: =IFERROR(IF($Z28="","",$Z28*(1-$C$36)-$D$36),"") | AB28: =IFERROR(IF(OR($AA28="",$C28="",$G28=""),"",($AA28-$C28)*$G28),"")
A29: 25 | H29: =IFERROR(IF(OR($C29="",$D29=""),"",($C29+$D$34)/($D29*(1-$C$34))),"") | I29: =IFERROR(IF($C29="","",($C29+$D$34)/($E$34*(1-$C$34))),"") | J29: =IFERROR(IF(OR($I29="",$E29=""),"",$I29*(1+INDEX(Parámetros!$B$6:$D$8,MATCH($B$34,Parámetros!$A$6:$A$8,0),MATCH($E29,Parámetros!$B$5:$D$5,0)))),"") | K29: =IF(OR($I29="",$F29=""),"",IF($I29<=$F29,"Sí","No: no llega al precio que acepta el mercado")) | L29: =IFERROR(IF(OR($I29="",$F29=""),"",MIN($I29,$F29)),"") | M29: =IFERROR(IF($L29="","",$L29*(1-$C$34)-$D$34),"") | N29: =IFERROR(IF(OR($M29="",$C29="",$G29=""),"",($M29-$C29)*$G29),"") | O29: =IFERROR(IF(OR($C29="",$D29=""),"",($C29+$D$35)/($D29*(1-$C$35))),"") | P29: =IFERROR(IF($C29="","",($C29+$D$35)/($E$35*(1-$C$35))),"") | Q29: =IFERROR(IF(OR($P29="",$E29=""),"",$P29*(1+INDEX(Parámetros!$B$6:$D$8,MATCH($B$35,Parámetros!$A$6:$A$8,0),MATCH($E29,Parámetros!$B$5:$D$5,0)))),"") | R29: =IF(OR($P29="",$F29=""),"",IF($P29<=$F29,"Sí","No: excluir o reformular")) | S29: =IFERROR(IF(OR($P29="",$F29=""),"",MIN($P29,$F29)),"") | T29: =IFERROR(IF($S29="","",$S29*(1-$C$35)-$D$35),"") | U29: =IFERROR(IF(OR($T29="",$C29="",$G29=""),"",($T29-$C29)*$G29),"") | V29: =IFERROR(IF(OR($C29="",$D29=""),"",($C29+$D$36)/($D29*(1-$C$36))),"") | W29: =IFERROR(IF($C29="","",($C29+$D$36)/($E$36*(1-$C$36))),"") | X29: =IFERROR(IF(OR($W29="",$E29=""),"",$W29*(1+INDEX(Parámetros!$B$6:$D$8,MATCH($B$36,Parámetros!$A$6:$A$8,0),MATCH($E29,Parámetros!$B$5:$D$5,0)))),"") | Y29: =IF(OR($W29="",$F29=""),"",IF($W29<=$F29,"Sí","No: excluir o reformular")) | Z29: =IFERROR(IF(OR($W29="",$F29=""),"",MIN($W29,$F29)),"") | AA29: =IFERROR(IF($Z29="","",$Z29*(1-$C$36)-$D$36),"") | AB29: =IFERROR(IF(OR($AA29="",$C29="",$G29=""),"",($AA29-$C29)*$G29),"")
B30: TOTAL / MEDIA | G30: =IF(COUNT(G5:G29)=0,"",SUM(G5:G29)) -> 4870 | H30: =IFERROR(IF(COUNT(H5:H29)=0,"",AVERAGE(H5:H29)),"") -> 0.31402549 | N30: =IF(COUNT(N5:N29)=0,"",SUM(N5:N29)) -> 43634.867 | O30: =IFERROR(IF(COUNT(O5:O29)=0,"",AVERAGE(O5:O29)),"") -> 0.38188296 | U30: =IF(COUNT(U5:U29)=0,"",SUM(U5:U29)) -> 49596.867 | V30: =IFERROR(IF(COUNT(V5:V29)=0,"",AVERAGE(V5:V29)),"") -> 0.54554709 | AB30: =IF(COUNT(AB5:AB29)=0,"",SUM(AB5:AB29)) -> 30050
B32: PARÁMETROS EN VIGOR — se leen de la hoja «Parámetros»; cámbialos allí, no aquí
B33: Canal | C33: Comisión (%) | D33: Packaging por plato (€) | E33: Food cost objetivo (%)
B34: =Parámetros!$A$16 -> Sala | C34: =IF(Parámetros!$B$16="","",Parámetros!$B$16) -> 0 | D34: =IF(Parámetros!$F$16="","",Parámetros!$F$16) -> 0 | E34: =IF(Parámetros!$E$16="","",Parámetros!$E$16) -> 0.3
B35: =Parámetros!$A$17 -> Take away | C35: =IF(Parámetros!$B$17="","",Parámetros!$B$17) -> 0 | D35: =IF(Parámetros!$F$17="","",Parámetros!$F$17) -> 0.7 | E35: =IF(Parámetros!$E$17="","",Parámetros!$E$17) -> 0.3
B36: =Parámetros!$A$18 -> Delivery | C36: =IF(Parámetros!$B$18="","",Parámetros!$B$18) -> 0.3 | D36: =IF(Parámetros!$F$18="","",Parámetros!$F$18) -> 0.7 | E36: =IF(Parámetros!$E$18="","",Parámetros!$E$18) -> 0.4

Sheet Resumen
A1: Resumen por canal
A2: AI Chef Pro · aichef.pro — Guía Food Cost + Ingeniería de Menú
A3: Todo se calcula desde la hoja «Carta»: aquí no se teclea nada.
A4: Canal | B4: Platos viables (n.º) | C4: Platos a excluir o reformular (n.º) | D4: Food cost efectivo medio al PVP de sala (media simple, %) | E4: Food cost objetivo del canal (%) | F4: PVP medio necesario, sin IVA (€) | G4: Margen mensual total (€) | H4: Margen mensual medio por plato (€) | I4: Diferencia de margen frente a la sala (€/mes)
A5: =Carta!$B$34 -> Sala | B5: =COUNTIF(Carta!$K$5:$K$29,"Sí") -> 16 | C5: =IFERROR(COUNT(Carta!$C$5:$C$29)-$B5,"") -> 4 | D5: =IFERROR(IF(COUNT(Carta!$H$5:$H$29)=0,"",AVERAGE(Carta!$H$5:$H$29)),"") -> 0.31402549 | E5: =IF(Carta!$E$34="","",Carta!$E$34) -> 0.3 | F5: =IFERROR(IF(COUNT(Carta!$I$5:$I$29)=0,"",AVERAGE(Carta!$I$5:$I$29)),"") -> 15.511667 | G5: =IF(Carta!$N$30="","",Carta!$N$30) -> 43634.867 | H5: =IFERROR(IF(OR($G5="",COUNT(Carta!$N$5:$N$29)=0),"",$G5/COUNT(Carta!$N$5:$N$29)),"") -> 2181.7433 | I5: Canal de referencia
A6: =Carta!$B$35 -> Take away | B6: =COUNTIF(Carta!$R$5:$R$29,"Sí") -> 12 | C6: =IFERROR(COUNT(Carta!$C$5:$C$29)-$B6,"") -> 8 | D6: =IFERROR(IF(COUNT(Carta!$O$5:$O$29)=0,"",AVERAGE(Carta!$O$5:$O$29)),"") -> 0.38188296 | E6: =IF(Carta!$E$35="","",Carta!$E$35) -> 0.3 | F6: =IFERROR(IF(COUNT(Carta!$P$5:$P$29)=0,"",AVERAGE(Carta!$P$5:$P$29)),"") -> 17.845 | G6: =IF(Carta!$U$30="","",Carta!$U$30) -> 49596.867 | H6: =IFERROR(IF(OR($G6="",COUNT(Carta!$U$5:$U$29)=0),"",$G6/COUNT(Carta!$U$5:$U$29)),"") -> 2479.8433 | I6: =IFERROR(IF(OR($G6="",$G$5=""),"",$G6-$G$5),"") -> 5962
A7: =Carta!$B$36 -> Delivery | B7: =COUNTIF(Carta!$Y$5:$Y$29,"Sí") -> 12 | C7: =IFERROR(COUNT(Carta!$C$5:$C$29)-$B7,"") -> 8 | D7: =IFERROR(IF(COUNT(Carta!$V$5:$V$29)=0,"",AVERAGE(Carta!$V$5:$V$29)),"") -> 0.54554709 | E7: =IF(Carta!$E$36="","",Carta!$E$36) -> 0.4 | F7: =IFERROR(IF(COUNT(Carta!$W$5:$W$29)=0,"",AVERAGE(Carta!$W$5:$W$29)),"") -> 19.119643 | G7: =IF(Carta!$AB$30="","",Carta!$AB$30) -> 30050 | H7: =IFERROR(IF(OR($G7="",COUNT(Carta!$AB$5:$AB$29)=0),"",$G7/COUNT(Carta!$AB$5:$AB$29)),"") -> 1502.5 | I7: =IFERROR(IF(OR($G7="",$G$5=""),"",$G7-$G$5),"") -> -13584.867
A9: CÓMO SE LEE
A10: Un food cost medio muy por encima del objetivo en take away o delivery no significa que el canal sea malo: significa que estás vendiendo con el precio del comedor en un canal que cobra comisión y envase.
A11: Con los datos de ejemplo, NINGÚN plato es viable en delivery: al 30 % de comisión y con un food cost objetivo del 30 %, el precio que haría falta se sale del techo en los veinte. Es el resultado normal de llevar la carta del comedor a una app sin rediseñarla, y la salida no es bajar el objetivo a ojo, sino una carta de delivery más corta, con platos de coste bajo y con el envase ya metido en el precio.
A12: En sala, un «No» no quiere decir que retires el plato: quiere decir que ese plato no llega a tu food cost objetivo al precio que acepta el mercado. Los platos de coste alto (chuletón, pescado de lonja) se ponen a precio por MARGEN, no por factor: eso lo resuelve el libro «precio-objetivo-multi-metodo.xlsx».
A13: Si un plato necesita un precio que el mercado no paga, tienes cuatro salidas: reformularlo para bajar el coste, subirlo hasta donde llegue el techo y aceptar peor food cost, sacarlo de ese canal, o sustituirlo por otro plato pensado para ese canal.
A14: La columna «Margen mensual» ya cobra el precio que puedes cobrar de verdad (el menor entre el necesario y el techo): por eso el margen de delivery puede quedarse muy por debajo del de sala aunque vendas lo mismo.
A15: El margen de esta hoja es margen de CONTRIBUCIÓN (precio neto menos coste de producto). No descuenta personal ni estructura: eso lo mide el libro «cuadro-de-mando-prime-cost.xlsx».
