Workbook

Sheet Instructions
B2: 📋 Prix Fixe & Set Menu Costing
B3: Food Cost Kit Pro — AI Chef Pro
B4: www.aichef.pro
B6: How to use this template
B8: ▸ The "Starter", "Main", and "Dessert" tabs: one recipe cost card each.
B9: ▸ The "Menu Summary" tab: the full menu's cost (bread, drink, and coffee included) and the suggested menu price.
B10: ▸ The "Weekly Rotation" tab: the five Monday-through-Friday menus with their cost, menu price, and daily food cost, plus the week's average.
B11: ▸ The target food cost is edited ONCE, in the Menu Summary.
B12: ▸ GREEN cells are editable; everything else is a formula.
B14: Recipe cost card columns
B16: ▸ Ingredient: the product exactly as you buy it.
B17: ▸ Category: the ingredient's family (dropdown). It's what preloads the trim loss % in the empty rows.
... B112: Version 2.1 · September 2026 · aichef.pro/en/digital-products/food-cost-templates · info@aichef.pro

Sheet Starter
A1: Starter — Mediterranean Salad
A2: Enter your ingredients and quantities. Green cells are editable.
L3: 📷 Dish Photo
A4: Ingredient | B4: Category | C4: Purchase unit | D4: Price/Unit | E4: Quantity | F4: Recipe unit | G4: Factor | H4: Trim loss % | I4: AP qty | J4: Cost
A5: Spring mix | B5: Leafy greens | C5: lb | D5: 3.66 | E5: 3 | F5: oz | G5: =IF(C5&F5="","",IFERROR(VLOOKUP(C5&"→"&F5,Conversions!$A$5:$B$286,2,FALSE),"?")) -> 16 | H5: 0.05 | I5: =IFERROR(IF(E5="","",E5/(1-H5)),"check trim loss") -> 3.1578947 | J5: =IF(G5="?","check units",IFERROR(I5*D5/G5,"")) -> 0.72236842
A6: Roma tomato | B6: Fruiting vegetables | C6: lb | D6: 1.83 | E6: 3.5 | F6: oz | G6: =IF(C6&F6="","",IFERROR(VLOOKUP(C6&"→"&F6,Conversions!$A$5:$B$286,2,FALSE),"?")) -> 16 | H6: 0.1 | I6: =IFERROR(IF(E6="","",E6/(1-H6)),"check trim loss") -> 3.8888889 | J6: =IF(G6="?","check units",IFERROR(I6*D6/G6,"")) -> 0.44479167
A7: Persian cucumber | B7: Fruiting vegetables | C7: lb | D7: 2.21 | E7: 2 | F7: oz | G7: =IF(C7&F7="","",IFERROR(VLOOKUP(C7&"→"&F7,Conversions!$A$5:$B$286,2,FALSE),"?")) -> 16 | H7: 0.12 | I7: =IFERROR(IF(E7="","",E7/(1-H7)),"check trim loss") -> 2.2727273 | J7: =IF(G7="?","check units",IFERROR(I7*D7/G7,"")) -> 0.31392045
A8: Red onion | B8: Root vegetables | C8: lb | D8: 1.34 | E8: 1 | F8: oz | G8: =IF(C8&F8="","",IFERROR(VLOOKUP(C8&"→"&F8,Conversions!$A$5:$B$286,2,FALSE),"?")) -> 16 | H8: 0.12 | I8: =IFERROR(IF(E8="","",E8/(1-H8)),"check trim loss") -> 1.1363636 | J8: =IF(G8="?","check units",IFERROR(I8*D8/G8,"")) -> 0.095170455 | L8: Photo of the finished dish: Review → Unprotect Sheet, then Insert → Picture
A9: Kalamata olives (pitted) | B9: Canned & pickled | C9: lb | D9: 5.45 | E9: 0.75 | F9: oz | G9: =IF(C9&F9="","",IFERROR(VLOOKUP(C9&"→"&F9,Conversions!$A$5:$B$286,2,FALSE),"?")) -> 16 | H9: 0.02 | I9: =IFERROR(IF(E9="","",E9/(1-H9)),"check trim loss") -> 0.76530612 | J9: =IF(G9="?","check units",IFERROR(I9*D9/G9,"")) -> 0.2606824
A10: Feta cheese | B10: Dairy | C10: lb | D10: 7.28 | E10: 1.5 | F10: oz | G10: =IF(C10&F10="","",IFERROR(VLOOKUP(C10&"→"&F10,Conversions!$A$5:$B$286,2,FALSE),"?")) -> 16 | H10: 0.03 | I10: =IFERROR(IF(E10="","",E10/(1-H10)),"check trim loss") -> 1.5463918 | J10: =IF(G10="?","check units",IFERROR(I10*D10/G10,"")) -> 0.70360825
A11: EVOO | B11: Oils & fats | C11: L | D11: 8.58 | E11: 4 | F11: tsp | G11: =IF(C11&F11="","",IFERROR(VLOOKUP(C11&"→"&F11,Conversions!$A$5:$B$286,2,FALSE),"?")) -> 202.88414 | H11: 0.03 | I11: =IFERROR(IF(E11="","",E11/(1-H11)),"check trim loss") -> 4.1237113 | J11: =IF(G11="?","check units",IFERROR(I11*D11/G11,"")) -> 0.17439236
G12: =IF(C12&F12="","",IFERROR(VLOOKUP(C12&"→"&F12,Conversions!$A$5:$B$286,2,FALSE),"?")) | H12: =IFERROR(VLOOKUP(B12,'Trim Loss Factors'!$A$5:$C$25,2,FALSE),"") | I12: =IFERROR(IF(E12="","",E12/(1-H12)),"check trim loss") | J12: =IF(G12="?","check units",IFERROR(I12*D12/G12,""))
G13: =IF(C13&F13="","",IFERROR(VLOOKUP(C13&"→"&F13,Conversions!$A$5:$B$286,2,FALSE),"?")) | H13: =IFERROR(VLOOKUP(B13,'Trim Loss Factors'!$A$5:$C$25,2,FALSE),"") | I13: =IFERROR(IF(E13="","",E13/(1-H13)),"check trim loss") | J13: =IF(G13="?","check units",IFERROR(I13*D13/G13,""))
G14: =IF(C14&F14="","",IFERROR(VLOOKUP(C14&"→"&F14,Conversions!$A$5:$B$286,2,FALSE),"?")) | H14: =IFERROR(VLOOKUP(B14,'Trim Loss Factors'!$A$5:$C$25,2,FALSE),"") | I14: =IFERROR(IF(E14="","",E14/(1-H14)),"check trim loss") | J14: =IF(G14="?","check units",IFERROR(I14*D14/G14,""))
G15: =IF(C15&F15="","",IFERROR(VLOOKUP(C15&"→"&F15,Conversions!$A$5:$B$286,2,FALSE),"?")) | H15: =IFERROR(VLOOKUP(B15,'Trim Loss Factors'!$A$5:$C$25,2,FALSE),"") | I15: =IFERROR(IF(E15="","",E15/(1-H15)),"check trim loss") | J15: =IF(G15="?","check units",IFERROR(I15*D15/G15,""))
G16: =IF(C16&F16="","",IFERROR(VLOOKUP(C16&"→"&F16,Conversions!$A$5:$B$286,2,FALSE),"?")) | H16: =IFERROR(VLOOKUP(B16,'Trim Loss Factors'!$A$5:$C$25,2,FALSE),"") | I16: =IFERROR(IF(E16="","",E16/(1-H16)),"check trim loss") | J16: =IF(G16="?","check units",IFERROR(I16*D16/G16,""))
G17: =IF(C17&F17="","",IFERROR(VLOOKUP(C17&"→"&F17,Conversions!$A$5:$B$286,2,FALSE),"?")) | H17: =IFERROR(VLOOKUP(B17,'Trim Loss Factors'!$A$5:$C$25,2,FALSE),"") | I17: =IFERROR(IF(E17="","",E17/(1-H17)),"check trim loss") | J17: =IF(G17="?","check units",IFERROR(I17*D17/G17,""))
G18: =IF(C18&F18="","",IFERROR(VLOOKUP(C18&"→"&F18,Conversions!$A$5:$B$286,2,FALSE),"?")) | H18: =IFERROR(VLOOKUP(B18,'Trim Loss Factors'!$A$5:$C$25,2,FALSE),"") | I18: =IFERROR(IF(E18="","",E18/(1-H18)),"check trim loss") | J18: =IF(G18="?","check units",IFERROR(I18*D18/G18,""))
G19: =IF(C19&F19="","",IFERROR(VLOOKUP(C19&"→"&F19,Conversions!$A$5:$B$286,2,FALSE),"?")) | H19: =IFERROR(VLOOKUP(B19,'Trim Loss Factors'!$A$5:$C$25,2,FALSE),"") | I19: =IFERROR(IF(E19="","",E19/(1-H19)),"check trim loss") | J19: =IF(G19="?","check units",IFERROR(I19*D19/G19,""))
G20: =IF(C20&F20="","",IFERROR(VLOOKUP(C20&"→"&F20,Conversions!$A$5:$B$286,2,FALSE),"?")) | H20: =IFERROR(VLOOKUP(B20,'Trim Loss Factors'!$A$5:$C$25,2,FALSE),"") | I20: =IFERROR(IF(E20="","",E20/(1-H20)),"check trim loss") | J20: =IF(G20="?","check units",IFERROR(I20*D20/G20,""))
G21: =IF(C21&F21="","",IFERROR(VLOOKUP(C21&"→"&F21,Conversions!$A$5:$B$286,2,FALSE),"?")) | H21: =IFERROR(VLOOKUP(B21,'Trim Loss Factors'!$A$5:$C$25,2,FALSE),"") | I21: =IFERROR(IF(E21="","",E21/(1-H21)),"check trim loss") | J21: =IF(G21="?","check units",IFERROR(I21*D21/G21,""))
A23: TOTAL INGREDIENT COST | J23: =SUM(J5:J21) -> 2.714934
A24: Q-factor (%) | I24: 0.1 | J24: =J23*I24 -> 0.2714934
A25: TOTAL DISH COST | J25: =J23+J24 -> 2.9864274
A26: Number of portions | I26: 1
A27: COST PER PORTION | J27: =IFERROR(J25/I26,"") -> 2.9864274
A29: Target food cost % — edited on the Summary tab | I29: ='Menu Summary'!$C$13 -> 0.32
A30: Suggested menu price (pre-tax) | J30: =IFERROR(J27/I29,"") -> 9.3325856
A31: Tax rate (%) | I31: 0
A32: Menu price incl. tax | J32: =IFERROR(J30*(1+I31),"") -> 9.3325856
A33: Gross profit per portion (at suggested price) | J33: =IFERROR(J30-J27,"") -> 6.3461582
A34: Target GP % (at suggested price) | J34: =IFERROR((J30-J27)/J30,"") -> 0.68
A36: Current menu price (pre-tax / ex VAT)
A37: Actual food cost % (actual GP % = 100% − this) | J37: =IFERROR(J27/I36,"")

Sheet Main
A1: Main — Roast Chicken with Potatoes
A2: Enter your ingredients and quantities. Green cells are editable.
L3: 📷 Dish Photo
A4: Ingredient | B4: Category | C4: Purchase unit | D4: Price/Unit | E4: Quantity | F4: Recipe unit | G4: Factor | H4: Trim loss % | I4: AP qty | J4: Cost
A5: Chicken thigh (bone-in) | B5: Poultry | C5: lb | D5: 1.67 | E5: 9 | F5: oz | G5: =IF(C5&F5="","",IFERROR(VLOOKUP(C5&"→"&F5,Conversions!$A$5:$B$286,2,FALSE),"?")) -> 16 | H5: 0.25 | I5: =IFERROR(IF(E5="","",E5/(1-H5)),"check trim loss") -> 12 | J5: =IF(G5="?","check units",IFERROR(I5*D5/G5,"")) -> 1.2525
A6: Potato | B6: Root vegetables | C6: 50 lb bag | D6: 36.48 | E6: 7 | F6: oz | G6: =IF(C6&F6="","",IFERROR(VLOOKUP(C6&"→"&F6,Conversions!$A$5:$B$286,2,FALSE),"?")) -> 800 | H6: 0.12 | I6: =IFERROR(IF(E6="","",E6/(1-H6)),"check trim loss") -> 7.9545455 | J6: =IF(G6="?","check units",IFERROR(I6*D6/G6,"")) -> 0.36272727
A7: Red bell pepper | B7: Fruiting vegetables | C7: lb | D7: 2.75 | E7: 2 | F7: oz | G7: =IF(C7&F7="","",IFERROR(VLOOKUP(C7&"→"&F7,Conversions!$A$5:$B$286,2,FALSE),"?")) -> 16 | H7: 0.15 | I7: =IFERROR(IF(E7="","",E7/(1-H7)),"check trim loss") -> 2.3529412 | J7: =IF(G7="?","check units",IFERROR(I7*D7/G7,"")) -> 0.40441176
A8: Peeled garlic | B8: Herbs & spices | C8: lb | D8: 4.1 | E8: 0.35 | F8: oz | G8: =IF(C8&F8="","",IFERROR(VLOOKUP(C8&"→"&F8,Conversions!$A$5:$B$286,2,FALSE),"?")) -> 16 | H8: 0.03 | I8: =IFERROR(IF(E8="","",E8/(1-H8)),"check trim loss") -> 0.36082474 | J8: =IF(G8="?","check units",IFERROR(I8*D8/G8,"")) -> 0.09246134 | L8: Photo of the finished dish: Review → Unprotect Sheet, then Insert → Picture
A9: Fresh rosemary (1 sprig ≈ 1/12 bunch) | B9: Herbs & spices | C9: bunch | D9: 0.69 | E9: 0.083 | F9: bunch | G9: =IF(C9&F9="","",IFERROR(VLOOKUP(C9&"→"&F9,Conversions!$A$5:$B$286,2,FALSE),"?")) -> 1 | H9: 0.2 | I9: =IFERROR(IF(E9="","",E9/(1-H9)),"check trim loss") -> 0.10375 | J9: =IF(G9="?","check units",IFERROR(I9*D9/G9,"")) -> 0.0715875
A10: EVOO | B10: Oils & fats | C10: L | D10: 8.58 | E10: 0.75 | F10: fl oz | G10: =IF(C10&F10="","",IFERROR(VLOOKUP(C10&"→"&F10,Conversions!$A$5:$B$286,2,FALSE),"?")) -> 33.814023 | H10: 0.03 | I10: =IFERROR(IF(E10="","",E10/(1-H10)),"check trim loss") -> 0.77319588 | J10: =IF(G10="?","check units",IFERROR(I10*D10/G10,"")) -> 0.1961914
G11: =IF(C11&F11="","",IFERROR(VLOOKUP(C11&"→"&F11,Conversions!$A$5:$B$286,2,FALSE),"?")) | H11: =IFERROR(VLOOKUP(B11,'Trim Loss Factors'!$A$5:$C$25,2,FALSE),"") | I11: =IFERROR(IF(E11="","",E11/(1-H11)),"check trim loss") | J11: =IF(G11="?","check units",IFERROR(I11*D11/G11,""))
G12: =IF(C12&F12="","",IFERROR(VLOOKUP(C12&"→"&F12,Conversions!$A$5:$B$286,2,FALSE),"?")) | H12: =IFERROR(VLOOKUP(B12,'Trim Loss Factors'!$A$5:$C$25,2,FALSE),"") | I12: =IFERROR(IF(E12="","",E12/(1-H12)),"check trim loss") | J12: =IF(G12="?","check units",IFERROR(I12*D12/G12,""))
G13: =IF(C13&F13="","",IFERROR(VLOOKUP(C13&"→"&F13,Conversions!$A$5:$B$286,2,FALSE),"?")) | H13: =IFERROR(VLOOKUP(B13,'Trim Loss Factors'!$A$5:$C$25,2,FALSE),"") | I13: =IFERROR(IF(E13="","",E13/(1-H13)),"check trim loss") | J13: =IF(G13="?","check units",IFERROR(I13*D13/G13,""))
G14: =IF(C14&F14="","",IFERROR(VLOOKUP(C14&"→"&F14,Conversions!$A$5:$B$286,2,FALSE),"?")) | H14: =IFERROR(VLOOKUP(B14,'Trim Loss Factors'!$A$5:$C$25,2,FALSE),"") | I14: =IFERROR(IF(E14="","",E14/(1-H14)),"check trim loss") | J14: =IF(G14="?","check units",IFERROR(I14*D14/G14,""))
G15: =IF(C15&F15="","",IFERROR(VLOOKUP(C15&"→"&F15,Conversions!$A$5:$B$286,2,FALSE),"?")) | H15: =IFERROR(VLOOKUP(B15,'Trim Loss Factors'!$A$5:$C$25,2,FALSE),"") | I15: =IFERROR(IF(E15="","",E15/(1-H15)),"check trim loss") | J15: =IF(G15="?","check units",IFERROR(I15*D15/G15,""))
G16: =IF(C16&F16="","",IFERROR(VLOOKUP(C16&"→"&F16,Conversions!$A$5:$B$286,2,FALSE),"?")) | H16: =IFERROR(VLOOKUP(B16,'Trim Loss Factors'!$A$5:$C$25,2,FALSE),"") | I16: =IFERROR(IF(E16="","",E16/(1-H16)),"check trim loss") | J16: =IF(G16="?","check units",IFERROR(I16*D16/G16,""))
G17: =IF(C17&F17="","",IFERROR(VLOOKUP(C17&"→"&F17,Conversions!$A$5:$B$286,2,FALSE),"?")) | H17: =IFERROR(VLOOKUP(B17,'Trim Loss Factors'!$A$5:$C$25,2,FALSE),"") | I17: =IFERROR(IF(E17="","",E17/(1-H17)),"check trim loss") | J17: =IF(G17="?","check units",IFERROR(I17*D17/G17,""))
G18: =IF(C18&F18="","",IFERROR(VLOOKUP(C18&"→"&F18,Conversions!$A$5:$B$286,2,FALSE),"?")) | H18: =IFERROR(VLOOKUP(B18,'Trim Loss Factors'!$A$5:$C$25,2,FALSE),"") | I18: =IFERROR(IF(E18="","",E18/(1-H18)),"check trim loss") | J18: =IF(G18="?","check units",IFERROR(I18*D18/G18,""))
G19: =IF(C19&F19="","",IFERROR(VLOOKUP(C19&"→"&F19,Conversions!$A$5:$B$286,2,FALSE),"?")) | H19: =IFERROR(VLOOKUP(B19,'Trim Loss Factors'!$A$5:$C$25,2,FALSE),"") | I19: =IFERROR(IF(E19="","",E19/(1-H19)),"check trim loss") | J19: =IF(G19="?","check units",IFERROR(I19*D19/G19,""))
G20: =IF(C20&F20="","",IFERROR(VLOOKUP(C20&"→"&F20,Conversions!$A$5:$B$286,2,FALSE),"?")) | H20: =IFERROR(VLOOKUP(B20,'Trim Loss Factors'!$A$5:$C$25,2,FALSE),"") | I20: =IFERROR(IF(E20="","",E20/(1-H20)),"check trim loss") | J20: =IF(G20="?","check units",IFERROR(I20*D20/G20,""))
A22: TOTAL INGREDIENT COST | J22: =SUM(J5:J20) -> 2.3798793
A23: Q-factor (%) | I23: 0.1 | J23: =J22*I23 -> 0.23798793
A24: TOTAL DISH COST | J24: =J22+J23 -> 2.6178672
A25: Number of portions | I25: 1
A26: COST PER PORTION | J26: =IFERROR(J24/I25,"") -> 2.6178672
A28: Target food cost % — edited on the Summary tab | I28: ='Menu Summary'!$C$13 -> 0.32
A29: Suggested menu price (pre-tax) | J29: =IFERROR(J26/I28,"") -> 8.180835
A30: Tax rate (%) | I30: 0
A31: Menu price incl. tax | J31: =IFERROR(J29*(1+I30),"") -> 8.180835
A32: Gross profit per portion (at suggested price) | J32: =IFERROR(J29-J26,"") -> 5.5629678
A33: Target GP % (at suggested price) | J33: =IFERROR((J29-J26)/J29,"") -> 0.68
A35: Current menu price (pre-tax / ex VAT)
A36: Actual food cost % (actual GP % = 100% − this) | J36: =IFERROR(J26/I35,"")

Sheet Dessert
A1: Dessert — Homemade Flan
A2: Enter your ingredients and quantities. Green cells are editable.
L3: 📷 Dish Photo
A4: Ingredient | B4: Category | C4: Purchase unit | D4: Price/Unit | E4: Quantity | F4: Recipe unit | G4: Factor | H4: Trim loss % | I4: AP qty | J4: Cost
A5: Large egg | B5: Eggs | C5: dozen | D5: 2.27 | E5: 0.5 | F5: each | G5: =IF(C5&F5="","",IFERROR(VLOOKUP(C5&"→"&F5,Conversions!$A$5:$B$286,2,FALSE),"?")) -> 12 | H5: 0 | I5: =IFERROR(IF(E5="","",E5/(1-H5)),"check trim loss") -> 0.5 | J5: =IF(G5="?","check units",IFERROR(I5*D5/G5,"")) -> 0.094583333
A6: Whole milk | B6: Dairy | C6: gal | D6: 4.23 | E6: 5 | F6: fl oz | G6: =IF(C6&F6="","",IFERROR(VLOOKUP(C6&"→"&F6,Conversions!$A$5:$B$286,2,FALSE),"?")) -> 128 | H6: 0.03 | I6: =IFERROR(IF(E6="","",E6/(1-H6)),"check trim loss") -> 5.1546392 | J6: =IF(G6="?","check units",IFERROR(I6*D6/G6,"")) -> 0.17034472
A7: Sugar | B7: Dry goods & grains | C7: 50 lb bag | D7: 50.49 | E7: 1.5 | F7: oz | G7: =IF(C7&F7="","",IFERROR(VLOOKUP(C7&"→"&F7,Conversions!$A$5:$B$286,2,FALSE),"?")) -> 800 | H7: 0.02 | I7: =IFERROR(IF(E7="","",E7/(1-H7)),"check trim loss") -> 1.5306122 | J7: =IF(G7="?","check units",IFERROR(I7*D7/G7,"")) -> 0.096600765
A8: Vanilla extract | B8: Herbs & spices | C8: pt | D8: 28.99 | E8: 0.5 | F8: tsp | G8: =IF(C8&F8="","",IFERROR(VLOOKUP(C8&"→"&F8,Conversions!$A$5:$B$286,2,FALSE),"?")) -> 96 | H8: 0.05 | I8: =IFERROR(IF(E8="","",E8/(1-H8)),"check trim loss") -> 0.52631579 | J8: =IF(G8="?","check units",IFERROR(I8*D8/G8,"")) -> 0.1589364 | L8: Photo of the finished dish: Review → Unprotect Sheet, then Insert → Picture
A9: Caramel sauce | B9: Sauces & condiments | C9: gal | D9: 34.99 | E9: 0.75 | F9: tbsp | G9: =IF(C9&F9="","",IFERROR(VLOOKUP(C9&"→"&F9,Conversions!$A$5:$B$286,2,FALSE),"?")) -> 256 | H9: 0.05 | I9: =IFERROR(IF(E9="","",E9/(1-H9)),"check trim loss") -> 0.78947368 | J9: =IF(G9="?","check units",IFERROR(I9*D9/G9,"")) -> 0.10790502
G10: =IF(C10&F10="","",IFERROR(VLOOKUP(C10&"→"&F10,Conversions!$A$5:$B$286,2,FALSE),"?")) | H10: =IFERROR(VLOOKUP(B10,'Trim Loss Factors'!$A$5:$C$25,2,FALSE),"") | I10: =IFERROR(IF(E10="","",E10/(1-H10)),"check trim loss") | J10: =IF(G10="?","check units",IFERROR(I10*D10/G10,""))
G11: =IF(C11&F11="","",IFERROR(VLOOKUP(C11&"→"&F11,Conversions!$A$5:$B$286,2,FALSE),"?")) | H11: =IFERROR(VLOOKUP(B11,'Trim Loss Factors'!$A$5:$C$25,2,FALSE),"") | I11: =IFERROR(IF(E11="","",E11/(1-H11)),"check trim loss") | J11: =IF(G11="?","check units",IFERROR(I11*D11/G11,""))
G12: =IF(C12&F12="","",IFERROR(VLOOKUP(C12&"→"&F12,Conversions!$A$5:$B$286,2,FALSE),"?")) | H12: =IFERROR(VLOOKUP(B12,'Trim Loss Factors'!$A$5:$C$25,2,FALSE),"") | I12: =IFERROR(IF(E12="","",E12/(1-H12)),"check trim loss") | J12: =IF(G12="?","check units",IFERROR(I12*D12/G12,""))
G13: =IF(C13&F13="","",IFERROR(VLOOKUP(C13&"→"&F13,Conversions!$A$5:$B$286,2,FALSE),"?")) | H13: =IFERROR(VLOOKUP(B13,'Trim Loss Factors'!$A$5:$C$25,2,FALSE),"") | I13: =IFERROR(IF(E13="","",E13/(1-H13)),"check trim loss") | J13: =IF(G13="?","check units",IFERROR(I13*D13/G13,""))
G14: =IF(C14&F14="","",IFERROR(VLOOKUP(C14&"→"&F14,Conversions!$A$5:$B$286,2,FALSE),"?")) | H14: =IFERROR(VLOOKUP(B14,'Trim Loss Factors'!$A$5:$C$25,2,FALSE),"") | I14: =IFERROR(IF(E14="","",E14/(1-H14)),"check trim loss") | J14: =IF(G14="?","check units",IFERROR(I14*D14/G14,""))
G15: =IF(C15&F15="","",IFERROR(VLOOKUP(C15&"→"&F15,Conversions!$A$5:$B$286,2,FALSE),"?")) | H15: =IFERROR(VLOOKUP(B15,'Trim Loss Factors'!$A$5:$C$25,2,FALSE),"") | I15: =IFERROR(IF(E15="","",E15/(1-H15)),"check trim loss") | J15: =IF(G15="?","check units",IFERROR(I15*D15/G15,""))
G16: =IF(C16&F16="","",IFERROR(VLOOKUP(C16&"→"&F16,Conversions!$A$5:$B$286,2,FALSE),"?")) | H16: =IFERROR(VLOOKUP(B16,'Trim Loss Factors'!$A$5:$C$25,2,FALSE),"") | I16: =IFERROR(IF(E16="","",E16/(1-H16)),"check trim loss") | J16: =IF(G16="?","check units",IFERROR(I16*D16/G16,""))
G17: =IF(C17&F17="","",IFERROR(VLOOKUP(C17&"→"&F17,Conversions!$A$5:$B$286,2,FALSE),"?")) | H17: =IFERROR(VLOOKUP(B17,'Trim Loss Factors'!$A$5:$C$25,2,FALSE),"") | I17: =IFERROR(IF(E17="","",E17/(1-H17)),"check trim loss") | J17: =IF(G17="?","check units",IFERROR(I17*D17/G17,""))
G18: =IF(C18&F18="","",IFERROR(VLOOKUP(C18&"→"&F18,Conversions!$A$5:$B$286,2,FALSE),"?")) | H18: =IFERROR(VLOOKUP(B18,'Trim Loss Factors'!$A$5:$C$25,2,FALSE),"") | I18: =IFERROR(IF(E18="","",E18/(1-H18)),"check trim loss") | J18: =IF(G18="?","check units",IFERROR(I18*D18/G18,""))
G19: =IF(C19&F19="","",IFERROR(VLOOKUP(C19&"→"&F19,Conversions!$A$5:$B$286,2,FALSE),"?")) | H19: =IFERROR(VLOOKUP(B19,'Trim Loss Factors'!$A$5:$C$25,2,FALSE),"") | I19: =IFERROR(IF(E19="","",E19/(1-H19)),"check trim loss") | J19: =IF(G19="?","check units",IFERROR(I19*D19/G19,""))
A21: TOTAL INGREDIENT COST | J21: =SUM(J5:J19) -> 0.62837024
A22: Q-factor (%) | I22: 0.1 | J22: =J21*I22 -> 0.062837024
A23: TOTAL DISH COST | J23: =J21+J22 -> 0.69120726
A24: Number of portions | I24: 1
A25: COST PER PORTION | J25: =IFERROR(J23/I24,"") -> 0.69120726
A27: Target food cost % — edited on the Summary tab | I27: ='Menu Summary'!$C$13 -> 0.32
A28: Suggested menu price (pre-tax) | J28: =IFERROR(J25/I27,"") -> 2.1600227
A29: Tax rate (%) | I29: 0
A30: Menu price incl. tax | J30: =IFERROR(J28*(1+I29),"") -> 2.1600227
A31: Gross profit per portion (at suggested price) | J31: =IFERROR(J28-J25,"") -> 1.4688154
A32: Target GP % (at suggested price) | J32: =IFERROR((J28-J25)/J28,"") -> 0.68
A34: Current menu price (pre-tax / ex VAT)
A35: Actual food cost % (actual GP % = 100% − this) | J35: =IFERROR(J25/I34,"")

Sheet Menu Summary
B2: Summary — Prix Fixe & Set Menu
B4: Item | C4: Cost
B5: Starter | C5: =Starter!$J$27 -> 2.9864274
B6: Main | C6: =Main!$J$26 -> 2.6178672
B7: Dessert | C7: =Dessert!$J$25 -> 0.69120726
B8: Bread & butter (per guest) | C8: 0.33
B9: Drink (if included) | C9: 0
B10: Coffee (if included) | C10: 0
B11: TOTAL PRIX FIXE MENU COST | C11: =SUM(C5:C10) -> 6.6255019
B13: Target food cost (%) — the only food cost figure in this workbook: every dish reads it from here | C13: 0.32
B14: SUGGESTED MENU PRICE (PRE-TAX) | C14: =IFERROR(C11/C13,"") -> 20.704693
B15: Tax rate (%) | C15: 0
B16: Menu price incl. tax | C16: =IFERROR(C14*(1+C15),"") -> 20.704693
B18: Example: this prix fixe sells at $22 (pre-tax), so its actual food cost is TOTAL PRIX FIXE MENU COST ÷ 22 = 30.1%. Dishes aren't sold separately, which is why each one leaves "Current menu price" blank.

Sheet Weekly Rotation
A1: Weekly Rotation — the 5 daily menus
A2: Color code: GREEN = you type it in. GRAY = pulled from another tab, don't touch it. MONDAY has its name and cost linked to the "Starter", "Main", and "Dessert" tabs: change the recipe there and it updates here automatically (that's why its three cost cells are gray). From TUESDAY through FRIDAY, you type in the name and cost of each dish yourself, in the green cells. The Menu price column is also gray: it's the menu's single price and comes from the "Menu Summary" tab, so the food cost is what changes each day. Charging a different price on a specific day (a holiday)? Go to Review → Unprotect Sheet (Google Sheets: Data → Protect sheets and ranges) and type over that cell.
J3: Target food cost (from Summary) | K3: ='Menu Summary'!$C$13 -> 0.32
A4: Day | B4: Starter | C4: Cost | D4: Main | E4: Cost | F4: Dessert | G4: Cost | H4: Extras (bread/drink/coffee) | I4: MENU COST | J4: Menu price (from Summary) | K4: FOOD COST (%)
A5: Monday | B5: Mediterranean Salad | C5: =Starter!$J$27 -> 2.9864274 | D5: Roast Chicken with Potatoes | E5: =Main!$J$26 -> 2.6178672 | F5: Homemade Flan | G5: =Dessert!$J$25 -> 0.69120726 | H5: ='Menu Summary'!$C$8+'Menu Summary'!$C$9+'Menu Summary'!$C$10 -> 0.33 | I5: =IF(SUM(C5,E5,G5)=0,"",SUM(C5,E5,G5,H5)) -> 6.6255019 | J5: ='Menu Summary'!$C$14 -> 20.704693 | K5: =IFERROR(I5/J5,"") -> 0.32
A6: Tuesday | H6: ='Menu Summary'!$C$8+'Menu Summary'!$C$9+'Menu Summary'!$C$10 -> 0.33 | I6: =IF(SUM(C6,E6,G6)=0,"",SUM(C6,E6,G6,H6)) | J6: ='Menu Summary'!$C$14 -> 20.704693 | K6: =IFERROR(I6/J6,"")
A7: Wednesday | H7: ='Menu Summary'!$C$8+'Menu Summary'!$C$9+'Menu Summary'!$C$10 -> 0.33 | I7: =IF(SUM(C7,E7,G7)=0,"",SUM(C7,E7,G7,H7)) | J7: ='Menu Summary'!$C$14 -> 20.704693 | K7: =IFERROR(I7/J7,"")
A8: Thursday | H8: ='Menu Summary'!$C$8+'Menu Summary'!$C$9+'Menu Summary'!$C$10 -> 0.33 | I8: =IF(SUM(C8,E8,G8)=0,"",SUM(C8,E8,G8,H8)) | J8: ='Menu Summary'!$C$14 -> 20.704693 | K8: =IFERROR(I8/J8,"")
A9: Friday | H9: ='Menu Summary'!$C$8+'Menu Summary'!$C$9+'Menu Summary'!$C$10 -> 0.33 | I9: =IF(SUM(C9,E9,G9)=0,"",SUM(C9,E9,G9,H9)) | J9: ='Menu Summary'!$C$14 -> 20.704693 | K9: =IFERROR(I9/J9,"")
A11: WEEKLY AVERAGE | I11: =IFERROR(SUM(I5:I9)/COUNTIF(I5:I9,">0"),"") -> 6.6255019 | J11: =IFERROR(SUM(J5:J9)/COUNTIF(J5:J9,">0"),"") -> 20.704693 | K11: =IFERROR(I11/J11,"") -> 0.32

Sheet Conversions
A1: Purchase unit → Recipe unit conversion table
A2: The "Factor" column of every recipe cost card uses it. You can add pairs at the end, up to row 286: the key is written "purchase→recipe".
A4: Conversion (purchase→recipe) | B4: Factor | C4: What it means
A5: lb→lb | B5: 1 | C5: same unit
A6: lb→oz | B6: 16 | C6: 1 lb = 16 oz
A7: lb→kg | B7: 0.45359237 | C7: 1 lb = 0.4536 kg
A8: lb→g | B8: 453.59237 | C8: 1 lb = 453.59 g
A9: oz→oz | B9: 1 | C9: same unit (oz = weight; fl oz = volume)
A10: oz→lb | B10: 0.0625 | C10: 1 oz = 0.0625 lb
A11: oz→kg | B11: 0.028349523 | C11: 1 oz = 0.0283 kg
A12: oz→g | B12: 28.349523 | C12: 1 oz = 28.3495 g
A13: kg→kg | B13: 1 | C13: same unit
A14: kg→lb | B14: 2.2046226 | C14: 1 kg = 2.2046 lb
A15: kg→oz | B15: 35.273962 | C15: 1 kg = 35.274 oz
A16: kg→g | B16: 1000 | C16: 1 kg = 1,000 g
... A147: bottle→ml | B147: 750 | C147: bottle size in ml: 750 (US wine & spirits). UK spirits: type 700 here — edit only this cell
A148: bottle→fl oz | B148: =IF(AND(ISNUMBER(B147),B147>0),B147/29.5735295625,"?") -> 25.360517 | C148: from the bottle size in ml (row 147)
A149: bottle→cl | B149: =IF(AND(ISNUMBER(B147),B147>0),B147/10,"?") -> 75 | C149: from the bottle size in ml (row 147)
A150: bottle→L | B150: =IF(AND(ISNUMBER(B147),B147>0),B147/1000,"?") -> 0.75 | C150: from the bottle size in ml (row 147)
A151: bottle→each | B151: 1 | C151: one bottle counted as one unit
A152: can→can | B152: 1 | C152: same unit (bought and used as one can)
A153: can→ml | B153: 355 | C153: beverage can 12 fl oz = 355 ml (UK: 330). Edit only this cell. For #10 food cans buy in oz
A154: can→fl oz | B154: =IF(AND(ISNUMBER(B153),B153>0),B153/29.5735295625,"?") -> 12.003978 | C154: from the can size in ml (row 153)
A155: can→cl | B155: =IF(AND(ISNUMBER(B153),B153>0),B153/10,"?") -> 35.5 | C155: from the can size in ml (row 153)
A156: can→L | B156: =IF(AND(ISNUMBER(B153),B153>0),B153/1000,"?") -> 0.355 | C156: from the can size in ml (row 153)
A157: can→each | B157: 1 | C157: one can counted as one unit
A158: bunch→bunch | B158: 1 | C158: same unit (bought and used as one bunch)
A159: bunch→each | B159: 1 | C159: one bunch counted as one unit (no default weight)
A160: packet→packet | B160: 1 | C160: same unit (bought and used as one packet)
A161: packet→each | B161: 1 | C161: one packet counted as one unit (no default weight)
A162: 15 dz case→15 dz case | B162: 1 | C162: same unit: type the 15 dz case price as invoiced (half case of eggs)
A163: 15 dz case→each | B163: 180 | C163: 1 × 15 dz case = 180 each
A164: 15 dz case→dozen | B164: 15 | C164: 1 × 15 dz case = 15 dozen
A165: 30 dz case→30 dz case | B165: 1 | C165: same unit: type the 30 dz case price as invoiced (full case of eggs)
A166: 30 dz case→each | B166: 360 | C166: 1 × 30 dz case = 360 each
A167: 30 dz case→dozen | B167: 30 | C167: 1 × 30 dz case = 30 dozen
A168: 50 lb bag→50 lb bag | B168: 1 | C168: same unit: type the 50 lb bag price as invoiced (e.g. flour, sugar)
... A256: 50 L keg→cl | B256: 5000 | C256: 1 × 50 L keg = 5,000 cl

Sheet Trim Loss Factors
A1: Reference trim loss % by category
A2: Typical is the trim loss % that preloads in the empty rows of the recipe cost card when you pick a category. Adjust it to your supplier. Yield % = 100% − trim loss %.
A3: Measure your real trim loss with template 12 (Yield Test) and type it in Trim loss % on the cost card. Reference yields for many foods: USDA Food Buying Guide (foodbuyingguide.fns.usda.gov).
A4: Category | B4: Typical trim loss % | C4: Min trim loss % | D4: Max trim loss % | E4: Notes
A5: Beef & red meat | B5: 0.2 | C5: 0.15 | D5: 0.25
A6: Poultry | B6: 0.25 | C6: 0.2 | D6: 0.3
A7: Fish | B7: 0.35 | C7: 0.3 | D7: 0.45 | E7: Gutted, head-on fish cut on the bone. Whole round fish to skin-on fillet loses 50-60%: measure it with template 12.
A8: Shellfish | B8: 0.45 | C8: 0.35 | D8: 0.55
A9: Leafy greens | B9: 0.25 | C9: 0.2 | D9: 0.35 | E9: Also stems and flowers, such as asparagus and cauliflower.
A10: Root vegetables | B10: 0.12 | C10: 0.08 | D10: 0.18
A11: Fruiting vegetables | B11: 0.1 | C11: 0.06 | D11: 0.15
A12: Fruit | B12: 0.15 | C12: 0.1 | D12: 0.25
A13: Dairy | B13: 0.03 | C13: 0.01 | D13: 0.05
A14: Dry goods & grains | B14: 0.02 | C14: 0.01 | D14: 0.04
A15: Frozen | B15: 0.07 | C15: 0.03 | D15: 0.1
A16: Bread & pastry | B16: 0.05 | C16: 0.02 | D16: 0.1
A17: Eggs | B17: 0.11 | C17: 0.1 | D17: 0.13
A18: Oils & fats | B18: 0.03 | C18: 0.01 | D18: 0.05
A19: Herbs & spices | B19: 0.2 | C19: 0.1 | D19: 0.3
A20: Chocolate & cocoa | B20: 0.05 | C20: 0.02 | D20: 0.08
A21: Beverages & spirits | B21: 0.02 | C21: 0.01 | D21: 0.04
... A25: Pasta & rice | B25: 0.02 | C25: 0.01 | D25: 0.04
