Workbook

Sheet Instructions
B2: 📋 Food Truck Menu Pricing & Break-Even
B3: Food Cost Kit Pro — AI Chef Pro
B4: www.aichef.pro
B6: How to use this template
B8: ▸ One tab per menu item: smash burger, loaded fries, and pulled pork.
B9: ▸ The "Break-Even" tab: enter your daily fixed costs and sales mix, and the sheet tells you how many units you need to sell to cover them and at what revenue.
B10: ▸ The contribution margin comes from the three recipe cost card tabs: change a recipe or a price and the break-even point moves on its own.
B11: ▸ Reference target food cost for a food truck: 28-35%.
B12: ▸ GREEN cells are editable; everything else is a formula.
B14: Recipe cost card columns
B16: ▸ Ingredient: the product exactly as you buy it.
B17: ▸ Category: the ingredient's family (dropdown). It's what preloads the trim loss % in the empty rows.
... B113: Version 2.1 · September 2026 · aichef.pro/en/digital-products/food-cost-templates · info@aichef.pro

Sheet Smash Burger
A1: Double Smash Burger with Cheese
A2: Enter your ingredients and quantities. Green cells are editable.
L3: 📷 Dish Photo
A4: Ingredient | B4: Category | C4: Purchase unit | D4: Price/Unit | E4: Quantity | F4: Recipe unit | G4: Factor | H4: Trim loss % | I4: AP qty | J4: Cost
A5: Ground beef (80/20), 2 x 3 oz balls | B5: Beef & red meat | C5: lb | D5: 3.33 | E5: 6 | F5: oz | G5: =IF(C5&F5="","",IFERROR(VLOOKUP(C5&"→"&F5,Conversions!$A$5:$B$286,2,FALSE),"?")) -> 16 | H5: 0 | I5: =IFERROR(IF(E5="","",E5/(1-H5)),"check trim loss") -> 6 | J5: =IF(G5="?","check units",IFERROR(I5*D5/G5,"")) -> 1.24875
A6: Brioche bun | B6: Bread & pastry | C6: each | D6: 0.9374 | E6: 1 | F6: each | G6: =IF(C6&F6="","",IFERROR(VLOOKUP(C6&"→"&F6,Conversions!$A$5:$B$286,2,FALSE),"?")) -> 1 | H6: 0 | I6: =IFERROR(IF(E6="","",E6/(1-H6)),"check trim loss") -> 1 | J6: =IF(G6="?","check units",IFERROR(I6*D6/G6,"")) -> 0.9374
A7: American cheese (slices) | B7: Dairy | C7: each | D7: 0.1377 | E7: 2 | F7: each | G7: =IF(C7&F7="","",IFERROR(VLOOKUP(C7&"→"&F7,Conversions!$A$5:$B$286,2,FALSE),"?")) -> 1 | H7: 0 | I7: =IFERROR(IF(E7="","",E7/(1-H7)),"check trim loss") -> 2 | J7: =IF(G7="?","check units",IFERROR(I7*D7/G7,"")) -> 0.2754
A8: Onion | B8: Root vegetables | C8: lb | D8: 1.22 | E8: 1.5 | F8: oz | G8: =IF(C8&F8="","",IFERROR(VLOOKUP(C8&"→"&F8,Conversions!$A$5:$B$286,2,FALSE),"?")) -> 16 | H8: 0.12 | I8: =IFERROR(IF(E8="","",E8/(1-H8)),"check trim loss") -> 1.7045455 | J8: =IF(G8="?","check units",IFERROR(I8*D8/G8,"")) -> 0.12997159 | L8: Photo of the finished dish: Review → Unprotect Sheet, then Insert → Picture
A9: Iceberg lettuce | B9: Leafy greens | C9: lb | D9: 1.47 | E9: 0.75 | F9: oz | G9: =IF(C9&F9="","",IFERROR(VLOOKUP(C9&"→"&F9,Conversions!$A$5:$B$286,2,FALSE),"?")) -> 16 | H9: 0.25 | I9: =IFERROR(IF(E9="","",E9/(1-H9)),"check trim loss") -> 1 | J9: =IF(G9="?","check units",IFERROR(I9*D9/G9,"")) -> 0.091875
A10: Tomato | B10: Fruiting vegetables | C10: lb | D10: 1.98 | E10: 1 | F10: oz | G10: =IF(C10&F10="","",IFERROR(VLOOKUP(C10&"→"&F10,Conversions!$A$5:$B$286,2,FALSE),"?")) -> 16 | H10: 0.1 | I10: =IFERROR(IF(E10="","",E10/(1-H10)),"check trim loss") -> 1.1111111 | J10: =IF(G10="?","check units",IFERROR(I10*D10/G10,"")) -> 0.1375
A11: Special sauce | B11: Sauces & condiments | C11: qt | D11: 3.44 | E11: 0.75 | F11: fl oz | G11: =IF(C11&F11="","",IFERROR(VLOOKUP(C11&"→"&F11,Conversions!$A$5:$B$286,2,FALSE),"?")) -> 32 | H11: 0.05 | I11: =IFERROR(IF(E11="","",E11/(1-H11)),"check trim loss") -> 0.78947368 | J11: =IF(G11="?","check units",IFERROR(I11*D11/G11,"")) -> 0.084868421
A12: Pickle chips | B12: Canned & pickled | C12: lb | D12: 1.39 | E12: 0.75 | F12: oz | G12: =IF(C12&F12="","",IFERROR(VLOOKUP(C12&"→"&F12,Conversions!$A$5:$B$286,2,FALSE),"?")) -> 16 | H12: 0.02 | I12: =IFERROR(IF(E12="","",E12/(1-H12)),"check trim loss") -> 0.76530612 | J12: =IF(G12="?","check units",IFERROR(I12*D12/G12,"")) -> 0.066485969
G13: =IF(C13&F13="","",IFERROR(VLOOKUP(C13&"→"&F13,Conversions!$A$5:$B$286,2,FALSE),"?")) | H13: =IFERROR(VLOOKUP(B13,'Trim Loss Factors'!$A$5:$C$25,2,FALSE),"") | I13: =IFERROR(IF(E13="","",E13/(1-H13)),"check trim loss") | J13: =IF(G13="?","check units",IFERROR(I13*D13/G13,""))
G14: =IF(C14&F14="","",IFERROR(VLOOKUP(C14&"→"&F14,Conversions!$A$5:$B$286,2,FALSE),"?")) | H14: =IFERROR(VLOOKUP(B14,'Trim Loss Factors'!$A$5:$C$25,2,FALSE),"") | I14: =IFERROR(IF(E14="","",E14/(1-H14)),"check trim loss") | J14: =IF(G14="?","check units",IFERROR(I14*D14/G14,""))
G15: =IF(C15&F15="","",IFERROR(VLOOKUP(C15&"→"&F15,Conversions!$A$5:$B$286,2,FALSE),"?")) | H15: =IFERROR(VLOOKUP(B15,'Trim Loss Factors'!$A$5:$C$25,2,FALSE),"") | I15: =IFERROR(IF(E15="","",E15/(1-H15)),"check trim loss") | J15: =IF(G15="?","check units",IFERROR(I15*D15/G15,""))
G16: =IF(C16&F16="","",IFERROR(VLOOKUP(C16&"→"&F16,Conversions!$A$5:$B$286,2,FALSE),"?")) | H16: =IFERROR(VLOOKUP(B16,'Trim Loss Factors'!$A$5:$C$25,2,FALSE),"") | I16: =IFERROR(IF(E16="","",E16/(1-H16)),"check trim loss") | J16: =IF(G16="?","check units",IFERROR(I16*D16/G16,""))
G17: =IF(C17&F17="","",IFERROR(VLOOKUP(C17&"→"&F17,Conversions!$A$5:$B$286,2,FALSE),"?")) | H17: =IFERROR(VLOOKUP(B17,'Trim Loss Factors'!$A$5:$C$25,2,FALSE),"") | I17: =IFERROR(IF(E17="","",E17/(1-H17)),"check trim loss") | J17: =IF(G17="?","check units",IFERROR(I17*D17/G17,""))
G18: =IF(C18&F18="","",IFERROR(VLOOKUP(C18&"→"&F18,Conversions!$A$5:$B$286,2,FALSE),"?")) | H18: =IFERROR(VLOOKUP(B18,'Trim Loss Factors'!$A$5:$C$25,2,FALSE),"") | I18: =IFERROR(IF(E18="","",E18/(1-H18)),"check trim loss") | J18: =IF(G18="?","check units",IFERROR(I18*D18/G18,""))
G19: =IF(C19&F19="","",IFERROR(VLOOKUP(C19&"→"&F19,Conversions!$A$5:$B$286,2,FALSE),"?")) | H19: =IFERROR(VLOOKUP(B19,'Trim Loss Factors'!$A$5:$C$25,2,FALSE),"") | I19: =IFERROR(IF(E19="","",E19/(1-H19)),"check trim loss") | J19: =IF(G19="?","check units",IFERROR(I19*D19/G19,""))
G20: =IF(C20&F20="","",IFERROR(VLOOKUP(C20&"→"&F20,Conversions!$A$5:$B$286,2,FALSE),"?")) | H20: =IFERROR(VLOOKUP(B20,'Trim Loss Factors'!$A$5:$C$25,2,FALSE),"") | I20: =IFERROR(IF(E20="","",E20/(1-H20)),"check trim loss") | J20: =IF(G20="?","check units",IFERROR(I20*D20/G20,""))
G21: =IF(C21&F21="","",IFERROR(VLOOKUP(C21&"→"&F21,Conversions!$A$5:$B$286,2,FALSE),"?")) | H21: =IFERROR(VLOOKUP(B21,'Trim Loss Factors'!$A$5:$C$25,2,FALSE),"") | I21: =IFERROR(IF(E21="","",E21/(1-H21)),"check trim loss") | J21: =IF(G21="?","check units",IFERROR(I21*D21/G21,""))
G22: =IF(C22&F22="","",IFERROR(VLOOKUP(C22&"→"&F22,Conversions!$A$5:$B$286,2,FALSE),"?")) | H22: =IFERROR(VLOOKUP(B22,'Trim Loss Factors'!$A$5:$C$25,2,FALSE),"") | I22: =IFERROR(IF(E22="","",E22/(1-H22)),"check trim loss") | J22: =IF(G22="?","check units",IFERROR(I22*D22/G22,""))
A24: TOTAL INGREDIENT COST | J24: =SUM(J5:J22) -> 2.972251
A25: Q-factor (%) | I25: 0.1 | J25: =J24*I25 -> 0.2972251
A26: TOTAL DISH COST | J26: =J24+J25 -> 3.2694761
A27: Number of portions | I27: 1
A28: COST PER PORTION | J28: =IFERROR(J26/I27,"") -> 3.2694761
A30: Target food cost % | I30: 0.3
A31: Suggested menu price (pre-tax) | J31: =IFERROR(J28/I30,"") -> 10.898254
A32: Tax rate (%) | I32: 0
A33: Menu price incl. tax | J33: =IFERROR(J31*(1+I32),"") -> 10.898254
A34: Gross profit per portion (at suggested price) | J34: =IFERROR(J31-J28,"") -> 7.6287775
A35: Target GP % (at suggested price) | J35: =IFERROR((J31-J28)/J31,"") -> 0.7
A37: Current menu price (pre-tax / ex VAT) | I37: 11
A38: Actual food cost % (actual GP % = 100% − this) | J38: =IFERROR(J28/I37,"") -> 0.2972251

Sheet Loaded Fries
A1: Loaded Fries with Pulled Pork
A2: Enter your ingredients and quantities. Green cells are editable.
L3: 📷 Dish Photo
A4: Ingredient | B4: Category | C4: Purchase unit | D4: Price/Unit | E4: Quantity | F4: Recipe unit | G4: Factor | H4: Trim loss % | I4: AP qty | J4: Cost
A5: Potatoes (for fries) | B5: Root vegetables | C5: 50 lb bag | D5: 36.48 | E5: 9 | F5: oz | G5: =IF(C5&F5="","",IFERROR(VLOOKUP(C5&"→"&F5,Conversions!$A$5:$B$286,2,FALSE),"?")) -> 800 | H5: 0.12 | I5: =IFERROR(IF(E5="","",E5/(1-H5)),"check trim loss") -> 10.227273 | J5: =IF(G5="?","check units",IFERROR(I5*D5/G5,"")) -> 0.46636364
A6: Pulled pork | B6: Beef & red meat | C6: lb | D6: 8.28 | E6: 3.5 | F6: oz | G6: =IF(C6&F6="","",IFERROR(VLOOKUP(C6&"→"&F6,Conversions!$A$5:$B$286,2,FALSE),"?")) -> 16 | H6: 0.1 | I6: =IFERROR(IF(E6="","",E6/(1-H6)),"check trim loss") -> 3.8888889 | J6: =IF(G6="?","check units",IFERROR(I6*D6/G6,"")) -> 2.0125
A7: Shredded cheddar cheese | B7: Dairy | C7: lb | D7: 3.05 | E7: 1.5 | F7: oz | G7: =IF(C7&F7="","",IFERROR(VLOOKUP(C7&"→"&F7,Conversions!$A$5:$B$286,2,FALSE),"?")) -> 16 | H7: 0.03 | I7: =IFERROR(IF(E7="","",E7/(1-H7)),"check trim loss") -> 1.5463918 | J7: =IF(G7="?","check units",IFERROR(I7*D7/G7,"")) -> 0.29478093
A8: BBQ sauce | B8: Sauces & condiments | C8: 4x1 gal case | D8: 58.99 | E8: 1 | F8: fl oz | G8: =IF(C8&F8="","",IFERROR(VLOOKUP(C8&"→"&F8,Conversions!$A$5:$B$286,2,FALSE),"?")) -> 512 | H8: 0.05 | I8: =IFERROR(IF(E8="","",E8/(1-H8)),"check trim loss") -> 1.0526316 | J8: =IF(G8="?","check units",IFERROR(I8*D8/G8,"")) -> 0.12127878 | L8: Photo of the finished dish: Review → Unprotect Sheet, then Insert → Picture
A9: Chives (1 sprig ≈ 1/12 bunch) | B9: Herbs & spices | C9: bunch | D9: 0.72 | E9: 0.083 | F9: bunch | G9: =IF(C9&F9="","",IFERROR(VLOOKUP(C9&"→"&F9,Conversions!$A$5:$B$286,2,FALSE),"?")) -> 1 | H9: 0.2 | I9: =IFERROR(IF(E9="","",E9/(1-H9)),"check trim loss") -> 0.10375 | J9: =IF(G9="?","check units",IFERROR(I9*D9/G9,"")) -> 0.0747
A10: Fryer oil (canola) | B10: Oils & fats | C10: lb | D10: 1.26 | E10: 3.25 | F10: oz | G10: =IF(C10&F10="","",IFERROR(VLOOKUP(C10&"→"&F10,Conversions!$A$5:$B$286,2,FALSE),"?")) -> 16 | H10: 0 | I10: =IFERROR(IF(E10="","",E10/(1-H10)),"check trim loss") -> 3.25 | J10: =IF(G10="?","check units",IFERROR(I10*D10/G10,"")) -> 0.2559375
G11: =IF(C11&F11="","",IFERROR(VLOOKUP(C11&"→"&F11,Conversions!$A$5:$B$286,2,FALSE),"?")) | H11: =IFERROR(VLOOKUP(B11,'Trim Loss Factors'!$A$5:$C$25,2,FALSE),"") | I11: =IFERROR(IF(E11="","",E11/(1-H11)),"check trim loss") | J11: =IF(G11="?","check units",IFERROR(I11*D11/G11,""))
G12: =IF(C12&F12="","",IFERROR(VLOOKUP(C12&"→"&F12,Conversions!$A$5:$B$286,2,FALSE),"?")) | H12: =IFERROR(VLOOKUP(B12,'Trim Loss Factors'!$A$5:$C$25,2,FALSE),"") | I12: =IFERROR(IF(E12="","",E12/(1-H12)),"check trim loss") | J12: =IF(G12="?","check units",IFERROR(I12*D12/G12,""))
G13: =IF(C13&F13="","",IFERROR(VLOOKUP(C13&"→"&F13,Conversions!$A$5:$B$286,2,FALSE),"?")) | H13: =IFERROR(VLOOKUP(B13,'Trim Loss Factors'!$A$5:$C$25,2,FALSE),"") | I13: =IFERROR(IF(E13="","",E13/(1-H13)),"check trim loss") | J13: =IF(G13="?","check units",IFERROR(I13*D13/G13,""))
G14: =IF(C14&F14="","",IFERROR(VLOOKUP(C14&"→"&F14,Conversions!$A$5:$B$286,2,FALSE),"?")) | H14: =IFERROR(VLOOKUP(B14,'Trim Loss Factors'!$A$5:$C$25,2,FALSE),"") | I14: =IFERROR(IF(E14="","",E14/(1-H14)),"check trim loss") | J14: =IF(G14="?","check units",IFERROR(I14*D14/G14,""))
G15: =IF(C15&F15="","",IFERROR(VLOOKUP(C15&"→"&F15,Conversions!$A$5:$B$286,2,FALSE),"?")) | H15: =IFERROR(VLOOKUP(B15,'Trim Loss Factors'!$A$5:$C$25,2,FALSE),"") | I15: =IFERROR(IF(E15="","",E15/(1-H15)),"check trim loss") | J15: =IF(G15="?","check units",IFERROR(I15*D15/G15,""))
G16: =IF(C16&F16="","",IFERROR(VLOOKUP(C16&"→"&F16,Conversions!$A$5:$B$286,2,FALSE),"?")) | H16: =IFERROR(VLOOKUP(B16,'Trim Loss Factors'!$A$5:$C$25,2,FALSE),"") | I16: =IFERROR(IF(E16="","",E16/(1-H16)),"check trim loss") | J16: =IF(G16="?","check units",IFERROR(I16*D16/G16,""))
G17: =IF(C17&F17="","",IFERROR(VLOOKUP(C17&"→"&F17,Conversions!$A$5:$B$286,2,FALSE),"?")) | H17: =IFERROR(VLOOKUP(B17,'Trim Loss Factors'!$A$5:$C$25,2,FALSE),"") | I17: =IFERROR(IF(E17="","",E17/(1-H17)),"check trim loss") | J17: =IF(G17="?","check units",IFERROR(I17*D17/G17,""))
G18: =IF(C18&F18="","",IFERROR(VLOOKUP(C18&"→"&F18,Conversions!$A$5:$B$286,2,FALSE),"?")) | H18: =IFERROR(VLOOKUP(B18,'Trim Loss Factors'!$A$5:$C$25,2,FALSE),"") | I18: =IFERROR(IF(E18="","",E18/(1-H18)),"check trim loss") | J18: =IF(G18="?","check units",IFERROR(I18*D18/G18,""))
G19: =IF(C19&F19="","",IFERROR(VLOOKUP(C19&"→"&F19,Conversions!$A$5:$B$286,2,FALSE),"?")) | H19: =IFERROR(VLOOKUP(B19,'Trim Loss Factors'!$A$5:$C$25,2,FALSE),"") | I19: =IFERROR(IF(E19="","",E19/(1-H19)),"check trim loss") | J19: =IF(G19="?","check units",IFERROR(I19*D19/G19,""))
G20: =IF(C20&F20="","",IFERROR(VLOOKUP(C20&"→"&F20,Conversions!$A$5:$B$286,2,FALSE),"?")) | H20: =IFERROR(VLOOKUP(B20,'Trim Loss Factors'!$A$5:$C$25,2,FALSE),"") | I20: =IFERROR(IF(E20="","",E20/(1-H20)),"check trim loss") | J20: =IF(G20="?","check units",IFERROR(I20*D20/G20,""))
A22: TOTAL INGREDIENT COST | J22: =SUM(J5:J20) -> 3.2255608
A23: Q-factor (%) | I23: 0.1 | J23: =J22*I23 -> 0.32255608
A24: TOTAL DISH COST | J24: =J22+J23 -> 3.5481169
A25: Number of portions | I25: 1
A26: COST PER PORTION | J26: =IFERROR(J24/I25,"") -> 3.5481169
A28: Target food cost % | I28: 0.3
A29: Suggested menu price (pre-tax) | J29: =IFERROR(J26/I28,"") -> 11.827056
A30: Tax rate (%) | I30: 0
A31: Menu price incl. tax | J31: =IFERROR(J29*(1+I30),"") -> 11.827056
A32: Gross profit per portion (at suggested price) | J32: =IFERROR(J29-J26,"") -> 8.2789395
A33: Target GP % (at suggested price) | J33: =IFERROR((J29-J26)/J29,"") -> 0.7
A35: Current menu price (pre-tax / ex VAT) | I35: 11
A36: Actual food cost % (actual GP % = 100% − this) | J36: =IFERROR(J26/I35,"") -> 0.32255608

Sheet Pulled Pork Sandwich
A1: Pulled Pork Sandwich
A2: Enter your ingredients and quantities. Green cells are editable.
L3: 📷 Dish Photo
A4: Ingredient | B4: Category | C4: Purchase unit | D4: Price/Unit | E4: Quantity | F4: Recipe unit | G4: Factor | H4: Trim loss % | I4: AP qty | J4: Cost
A5: Pulled pork | B5: Beef & red meat | C5: lb | D5: 8.28 | E5: 5.5 | F5: oz | G5: =IF(C5&F5="","",IFERROR(VLOOKUP(C5&"→"&F5,Conversions!$A$5:$B$286,2,FALSE),"?")) -> 16 | H5: 0.1 | I5: =IFERROR(IF(E5="","",E5/(1-H5)),"check trim loss") -> 6.1111111 | J5: =IF(G5="?","check units",IFERROR(I5*D5/G5,"")) -> 3.1625
A6: Brioche bun, large | B6: Bread & pastry | C6: each | D6: 0.9999 | E6: 1 | F6: each | G6: =IF(C6&F6="","",IFERROR(VLOOKUP(C6&"→"&F6,Conversions!$A$5:$B$286,2,FALSE),"?")) -> 1 | H6: 0 | I6: =IFERROR(IF(E6="","",E6/(1-H6)),"check trim loss") -> 1 | J6: =IF(G6="?","check units",IFERROR(I6*D6/G6,"")) -> 0.9999
A7: Coleslaw mix | B7: Leafy greens | C7: lb | D7: 2 | E7: 2 | F7: oz | G7: =IF(C7&F7="","",IFERROR(VLOOKUP(C7&"→"&F7,Conversions!$A$5:$B$286,2,FALSE),"?")) -> 16 | H7: 0.1 | I7: =IFERROR(IF(E7="","",E7/(1-H7)),"check trim loss") -> 2.2222222 | J7: =IF(G7="?","check units",IFERROR(I7*D7/G7,"")) -> 0.27777778
A8: BBQ sauce | B8: Sauces & condiments | C8: 4x1 gal case | D8: 58.99 | E8: 1 | F8: fl oz | G8: =IF(C8&F8="","",IFERROR(VLOOKUP(C8&"→"&F8,Conversions!$A$5:$B$286,2,FALSE),"?")) -> 512 | H8: 0.05 | I8: =IFERROR(IF(E8="","",E8/(1-H8)),"check trim loss") -> 1.0526316 | J8: =IF(G8="?","check units",IFERROR(I8*D8/G8,"")) -> 0.12127878 | L8: Photo of the finished dish: Review → Unprotect Sheet, then Insert → Picture
A9: Pickle chips | B9: Canned & pickled | C9: lb | D9: 1.39 | E9: 0.75 | F9: oz | G9: =IF(C9&F9="","",IFERROR(VLOOKUP(C9&"→"&F9,Conversions!$A$5:$B$286,2,FALSE),"?")) -> 16 | H9: 0.02 | I9: =IFERROR(IF(E9="","",E9/(1-H9)),"check trim loss") -> 0.76530612 | J9: =IF(G9="?","check units",IFERROR(I9*D9/G9,"")) -> 0.066485969
G10: =IF(C10&F10="","",IFERROR(VLOOKUP(C10&"→"&F10,Conversions!$A$5:$B$286,2,FALSE),"?")) | H10: =IFERROR(VLOOKUP(B10,'Trim Loss Factors'!$A$5:$C$25,2,FALSE),"") | I10: =IFERROR(IF(E10="","",E10/(1-H10)),"check trim loss") | J10: =IF(G10="?","check units",IFERROR(I10*D10/G10,""))
G11: =IF(C11&F11="","",IFERROR(VLOOKUP(C11&"→"&F11,Conversions!$A$5:$B$286,2,FALSE),"?")) | H11: =IFERROR(VLOOKUP(B11,'Trim Loss Factors'!$A$5:$C$25,2,FALSE),"") | I11: =IFERROR(IF(E11="","",E11/(1-H11)),"check trim loss") | J11: =IF(G11="?","check units",IFERROR(I11*D11/G11,""))
G12: =IF(C12&F12="","",IFERROR(VLOOKUP(C12&"→"&F12,Conversions!$A$5:$B$286,2,FALSE),"?")) | H12: =IFERROR(VLOOKUP(B12,'Trim Loss Factors'!$A$5:$C$25,2,FALSE),"") | I12: =IFERROR(IF(E12="","",E12/(1-H12)),"check trim loss") | J12: =IF(G12="?","check units",IFERROR(I12*D12/G12,""))
G13: =IF(C13&F13="","",IFERROR(VLOOKUP(C13&"→"&F13,Conversions!$A$5:$B$286,2,FALSE),"?")) | H13: =IFERROR(VLOOKUP(B13,'Trim Loss Factors'!$A$5:$C$25,2,FALSE),"") | I13: =IFERROR(IF(E13="","",E13/(1-H13)),"check trim loss") | J13: =IF(G13="?","check units",IFERROR(I13*D13/G13,""))
G14: =IF(C14&F14="","",IFERROR(VLOOKUP(C14&"→"&F14,Conversions!$A$5:$B$286,2,FALSE),"?")) | H14: =IFERROR(VLOOKUP(B14,'Trim Loss Factors'!$A$5:$C$25,2,FALSE),"") | I14: =IFERROR(IF(E14="","",E14/(1-H14)),"check trim loss") | J14: =IF(G14="?","check units",IFERROR(I14*D14/G14,""))
G15: =IF(C15&F15="","",IFERROR(VLOOKUP(C15&"→"&F15,Conversions!$A$5:$B$286,2,FALSE),"?")) | H15: =IFERROR(VLOOKUP(B15,'Trim Loss Factors'!$A$5:$C$25,2,FALSE),"") | I15: =IFERROR(IF(E15="","",E15/(1-H15)),"check trim loss") | J15: =IF(G15="?","check units",IFERROR(I15*D15/G15,""))
G16: =IF(C16&F16="","",IFERROR(VLOOKUP(C16&"→"&F16,Conversions!$A$5:$B$286,2,FALSE),"?")) | H16: =IFERROR(VLOOKUP(B16,'Trim Loss Factors'!$A$5:$C$25,2,FALSE),"") | I16: =IFERROR(IF(E16="","",E16/(1-H16)),"check trim loss") | J16: =IF(G16="?","check units",IFERROR(I16*D16/G16,""))
G17: =IF(C17&F17="","",IFERROR(VLOOKUP(C17&"→"&F17,Conversions!$A$5:$B$286,2,FALSE),"?")) | H17: =IFERROR(VLOOKUP(B17,'Trim Loss Factors'!$A$5:$C$25,2,FALSE),"") | I17: =IFERROR(IF(E17="","",E17/(1-H17)),"check trim loss") | J17: =IF(G17="?","check units",IFERROR(I17*D17/G17,""))
G18: =IF(C18&F18="","",IFERROR(VLOOKUP(C18&"→"&F18,Conversions!$A$5:$B$286,2,FALSE),"?")) | H18: =IFERROR(VLOOKUP(B18,'Trim Loss Factors'!$A$5:$C$25,2,FALSE),"") | I18: =IFERROR(IF(E18="","",E18/(1-H18)),"check trim loss") | J18: =IF(G18="?","check units",IFERROR(I18*D18/G18,""))
G19: =IF(C19&F19="","",IFERROR(VLOOKUP(C19&"→"&F19,Conversions!$A$5:$B$286,2,FALSE),"?")) | H19: =IFERROR(VLOOKUP(B19,'Trim Loss Factors'!$A$5:$C$25,2,FALSE),"") | I19: =IFERROR(IF(E19="","",E19/(1-H19)),"check trim loss") | J19: =IF(G19="?","check units",IFERROR(I19*D19/G19,""))
A21: TOTAL INGREDIENT COST | J21: =SUM(J5:J19) -> 4.6279425
A22: Q-factor (%) | I22: 0.1 | J22: =J21*I22 -> 0.46279425
A23: TOTAL DISH COST | J23: =J21+J22 -> 5.0907368
A24: Number of portions | I24: 1
A25: COST PER PORTION | J25: =IFERROR(J23/I24,"") -> 5.0907368
A27: Target food cost % | I27: 0.3
A28: Suggested menu price (pre-tax) | J28: =IFERROR(J25/I27,"") -> 16.969123
A29: Tax rate (%) | I29: 0
A30: Menu price incl. tax | J30: =IFERROR(J28*(1+I29),"") -> 16.969123
A31: Gross profit per portion (at suggested price) | J31: =IFERROR(J28-J25,"") -> 11.878386
A32: Target GP % (at suggested price) | J32: =IFERROR((J28-J25)/J28,"") -> 0.7
A34: Current menu price (pre-tax / ex VAT) | I34: 15
A35: Actual food cost % (actual GP % = 100% − this) | J35: =IFERROR(J25/I34,"") -> 0.33938245

Sheet Break-Even
A1: Daily Break-Even — Food Truck
A2: How many units you need to sell each day just to cover your fixed costs. The margin comes from the recipe cost card tabs: change a recipe or a price and this sheet updates itself. The menu price used is whatever you entered in "Current menu price (pre-tax / ex VAT)" on each tab; while that cell is empty, the sheet uses the suggested menu price instead, which is almost never what you actually charge.
A4: Daily fixed costs
A5: Item | B5: Amount (per day)
A6: Commissary & parking | B6: 45
A7: Insurance, permits & licenses (daily share) | B7: 25
A8: Fuel, propane & generator | B8: 30
A9: Staff (2 people per shift) | B9: 300
A10: Truck & equipment depreciation | B10: 50
A11: Cleaning, water & waste | B11: 15
A12: TOTAL FIXED COSTS (per day) | B12: =SUM(B6:B11) -> 465
A14: Contribution margin per unit
A15: Product | B15: Menu price (pre-tax) | C15: Unit cost | D15: Margin | E15: Sales mix
A16: Smash Burger | B16: =IF('Smash Burger'!$I$37="",'Smash Burger'!$J$31,'Smash Burger'!$I$37) -> 11 | C16: ='Smash Burger'!$J$28 -> 3.2694761 | D16: =IFERROR(B16-C16,"") -> 7.7305239 | E16: 0.5
A17: Loaded Fries | B17: =IF('Loaded Fries'!$I$35="",'Loaded Fries'!$J$29,'Loaded Fries'!$I$35) -> 11 | C17: ='Loaded Fries'!$J$26 -> 3.5481169 | D17: =IFERROR(B17-C17,"") -> 7.4518831 | E17: 0.25
A18: Pulled Pork Sandwich | B18: =IF('Pulled Pork Sandwich'!$I$34="",'Pulled Pork Sandwich'!$J$28,'Pulled Pork Sandwich'!$I$34) -> 15 | C18: ='Pulled Pork Sandwich'!$J$25 -> 5.0907368 | D18: =IFERROR(B18-C18,"") -> 9.9092632 | E18: 0.25
A19: WEIGHTED AVERAGE MENU PRICE (per unit) | B19: =IFERROR(SUMPRODUCT(B16:B18,E16:E18)/SUM(E16:E18),"") -> 12
A20: WEIGHTED AVERAGE MARGIN (per unit) | B20: =IFERROR(SUMPRODUCT(D16:D18,E16:E18)/SUM(E16:E18),"") -> 8.2055485
A22: Result
A23: UNITS/DAY TO COVER COSTS | B23: =IFERROR(ROUNDUP(B12/B20,0),"") -> 57
A24: MINIMUM REVENUE (pre-tax, per day) | B24: =IFERROR(B23*B19,"") -> 684
A25: Tax rate (%) | B25: 0
A26: MINIMUM REVENUE (incl. tax, per day) | B26: =IFERROR(B24*(1+B25),"") -> 684
A28: The "Sales mix" is what share of what you sell is each product: if on a given day half your sales are burgers and the rest is split evenly, enter 50% / 25% / 25%. It doesn't have to add up to 100% — the sheet weights whatever numbers you enter.

Sheet Conversions
A1: Purchase unit → Recipe unit conversion table
A2: The "Factor" column of every recipe cost card uses it. You can add pairs at the end, up to row 286: the key is written "purchase→recipe".
A4: Conversion (purchase→recipe) | B4: Factor | C4: What it means
A5: lb→lb | B5: 1 | C5: same unit
A6: lb→oz | B6: 16 | C6: 1 lb = 16 oz
A7: lb→kg | B7: 0.45359237 | C7: 1 lb = 0.4536 kg
A8: lb→g | B8: 453.59237 | C8: 1 lb = 453.59 g
A9: oz→oz | B9: 1 | C9: same unit (oz = weight; fl oz = volume)
A10: oz→lb | B10: 0.0625 | C10: 1 oz = 0.0625 lb
A11: oz→kg | B11: 0.028349523 | C11: 1 oz = 0.0283 kg
A12: oz→g | B12: 28.349523 | C12: 1 oz = 28.3495 g
A13: kg→kg | B13: 1 | C13: same unit
A14: kg→lb | B14: 2.2046226 | C14: 1 kg = 2.2046 lb
A15: kg→oz | B15: 35.273962 | C15: 1 kg = 35.274 oz
A16: kg→g | B16: 1000 | C16: 1 kg = 1,000 g
... A147: bottle→ml | B147: 750 | C147: bottle size in ml: 750 (US wine & spirits). UK spirits: type 700 here — edit only this cell
A148: bottle→fl oz | B148: =IF(AND(ISNUMBER(B147),B147>0),B147/29.5735295625,"?") -> 25.360517 | C148: from the bottle size in ml (row 147)
A149: bottle→cl | B149: =IF(AND(ISNUMBER(B147),B147>0),B147/10,"?") -> 75 | C149: from the bottle size in ml (row 147)
A150: bottle→L | B150: =IF(AND(ISNUMBER(B147),B147>0),B147/1000,"?") -> 0.75 | C150: from the bottle size in ml (row 147)
A151: bottle→each | B151: 1 | C151: one bottle counted as one unit
A152: can→can | B152: 1 | C152: same unit (bought and used as one can)
A153: can→ml | B153: 355 | C153: beverage can 12 fl oz = 355 ml (UK: 330). Edit only this cell. For #10 food cans buy in oz
A154: can→fl oz | B154: =IF(AND(ISNUMBER(B153),B153>0),B153/29.5735295625,"?") -> 12.003978 | C154: from the can size in ml (row 153)
A155: can→cl | B155: =IF(AND(ISNUMBER(B153),B153>0),B153/10,"?") -> 35.5 | C155: from the can size in ml (row 153)
A156: can→L | B156: =IF(AND(ISNUMBER(B153),B153>0),B153/1000,"?") -> 0.355 | C156: from the can size in ml (row 153)
A157: can→each | B157: 1 | C157: one can counted as one unit
A158: bunch→bunch | B158: 1 | C158: same unit (bought and used as one bunch)
A159: bunch→each | B159: 1 | C159: one bunch counted as one unit (no default weight)
A160: packet→packet | B160: 1 | C160: same unit (bought and used as one packet)
A161: packet→each | B161: 1 | C161: one packet counted as one unit (no default weight)
A162: 15 dz case→15 dz case | B162: 1 | C162: same unit: type the 15 dz case price as invoiced (half case of eggs)
A163: 15 dz case→each | B163: 180 | C163: 1 × 15 dz case = 180 each
A164: 15 dz case→dozen | B164: 15 | C164: 1 × 15 dz case = 15 dozen
A165: 30 dz case→30 dz case | B165: 1 | C165: same unit: type the 30 dz case price as invoiced (full case of eggs)
A166: 30 dz case→each | B166: 360 | C166: 1 × 30 dz case = 360 each
A167: 30 dz case→dozen | B167: 30 | C167: 1 × 30 dz case = 30 dozen
A168: 50 lb bag→50 lb bag | B168: 1 | C168: same unit: type the 50 lb bag price as invoiced (e.g. flour, sugar)
... A256: 50 L keg→cl | B256: 5000 | C256: 1 × 50 L keg = 5,000 cl

Sheet Trim Loss Factors
A1: Reference trim loss % by category
A2: Typical is the trim loss % that preloads in the empty rows of the recipe cost card when you pick a category. Adjust it to your supplier. Yield % = 100% − trim loss %.
A3: Measure your real trim loss with template 12 (Yield Test) and type it in Trim loss % on the cost card. Reference yields for many foods: USDA Food Buying Guide (foodbuyingguide.fns.usda.gov).
A4: Category | B4: Typical trim loss % | C4: Min trim loss % | D4: Max trim loss % | E4: Notes
A5: Beef & red meat | B5: 0.2 | C5: 0.15 | D5: 0.25
A6: Poultry | B6: 0.25 | C6: 0.2 | D6: 0.3
A7: Fish | B7: 0.35 | C7: 0.3 | D7: 0.45 | E7: Gutted, head-on fish cut on the bone. Whole round fish to skin-on fillet loses 50-60%: measure it with template 12.
A8: Shellfish | B8: 0.45 | C8: 0.35 | D8: 0.55
A9: Leafy greens | B9: 0.25 | C9: 0.2 | D9: 0.35 | E9: Also stems and flowers, such as asparagus and cauliflower.
A10: Root vegetables | B10: 0.12 | C10: 0.08 | D10: 0.18
A11: Fruiting vegetables | B11: 0.1 | C11: 0.06 | D11: 0.15
A12: Fruit | B12: 0.15 | C12: 0.1 | D12: 0.25
A13: Dairy | B13: 0.03 | C13: 0.01 | D13: 0.05
A14: Dry goods & grains | B14: 0.02 | C14: 0.01 | D14: 0.04
A15: Frozen | B15: 0.07 | C15: 0.03 | D15: 0.1
A16: Bread & pastry | B16: 0.05 | C16: 0.02 | D16: 0.1
A17: Eggs | B17: 0.11 | C17: 0.1 | D17: 0.13
A18: Oils & fats | B18: 0.03 | C18: 0.01 | D18: 0.05
A19: Herbs & spices | B19: 0.2 | C19: 0.1 | D19: 0.3
A20: Chocolate & cocoa | B20: 0.05 | C20: 0.02 | D20: 0.08
A21: Beverages & spirits | B21: 0.02 | C21: 0.01 | D21: 0.04
... A25: Pasta & rice | B25: 0.02 | C25: 0.01 | D25: 0.04
