Workbook

Sheet Instructions
B2: 📋 BONUS: Actual vs Theoretical Food Cost (Inventory & Waste)
B3: Food Cost Kit Pro — AI Chef Pro
B4: www.aichef.pro
B6: ▸ "Sales for the Period" tab: what you've sold and how much of each product goes into each portion.
B7: ▸ "Inventory" tab: your actual stock. It compares what you used with what you should have used, and puts a dollar value on it.
B8: ▸ "Waste Checklist" tab: the month's log of incidents.
B9: ▸ Only the GREEN cells get filled in.
B11: How Theoretical Usage Is Calculated
B13: ▸ Theoretical usage = Σ (portions sold of the dish × quantity of that product per portion).
B14: ▸ Filled in on "Sales for the Period": one row per dish, portions sold in column B, and the quantity per portion under each product.
B15: ▸ The quantity is the AP (as-purchased) quantity from the recipe cost card (the "AP qty" column, with the butchering trim loss already built in): if you use the edible-portion quantity instead, all that trim will show up as a hidden loss.
B16: ▸ The TOTALS row is what feeds the "Theoretical usage" column on the Inventory tab. Nothing needs to be copied by hand.
... B62: Version 2.1 · September 2026 · aichef.pro/en/digital-products/food-cost-templates · info@aichef.pro

Sheet Inventory
A1: Inventory Control — Weekly/Monthly
A2: Period:
A3: Actual usage = beginning inventory + purchases − ending inventory. Theoretical usage = what you SHOULD have used based on what you sold (the "Sales for the Period" tab). The variance, valued in dollars, is your hidden loss: breakage, theft, uncontrolled portioning or outdated recipe cost cards.
A4: Product | B4: Unit | C4: Beginning inventory | D4: Purchases | E4: Ending inventory | F4: Actual usage | G4: Theoretical usage | H4: Variance (units) | I4: Unit price | J4: Value of the variance
A5: Beef tenderloin (PSMO) | B5: lb | C5: 25.41 | D5: 88.93 | E5: 26.99 | F5: =IFERROR(IF(SUM(C5:E5)=0,"",C5+D5-E5),"") -> 87.35 | G5: =IFERROR(IF('Sales for the Period'!C15=0,"",'Sales for the Period'!C15),"") -> 83.8524 | H5: =IFERROR(IF(F5="","",IF(G5="","",F5-G5)),"") -> 3.4976 | I5: 17.21 | J5: =IFERROR(IF(H5="","",H5*I5),"") -> 60.193696
A6: Chicken thighs | B6: lb | F6: =IFERROR(IF(SUM(C6:E6)=0,"",C6+D6-E6),"") | G6: =IFERROR(IF('Sales for the Period'!D15=0,"",'Sales for the Period'!D15),"") | H6: =IFERROR(IF(F6="","",IF(G6="","",F6-G6)),"") | I6: 1.67 | J6: =IFERROR(IF(H6="","",H6*I6),"")
A7: Branzino (whole) | B7: lb | C7: 13.23 | D7: 59.52 | E7: 11.02 | F7: =IFERROR(IF(SUM(C7:E7)=0,"",C7+D7-E7),"") -> 61.73 | G7: =IFERROR(IF('Sales for the Period'!E15=0,"",'Sales for the Period'!E15),"") -> 59.96576 | H7: =IFERROR(IF(F7="","",IF(G7="","",F7-G7)),"") -> 1.76424 | I7: 10.99 | J7: =IFERROR(IF(H7="","",H7*I7),"") -> 19.388998
A8: Shrimp 16/20 | B8: lb | F8: =IFERROR(IF(SUM(C8:E8)=0,"",C8+D8-E8),"") | G8: =IFERROR(IF('Sales for the Period'!F15=0,"",'Sales for the Period'!F15),"") | H8: =IFERROR(IF(F8="","",IF(G8="","",F8-G8)),"") | I8: 8.99 | J8: =IFERROR(IF(H8="","",H8*I8),"")
A9: Potatoes | B9: lb | C9: 49.3 | D9: 50 | E9: 34.2 | F9: =IFERROR(IF(SUM(C9:E9)=0,"",C9+D9-E9),"") -> 65.1 | G9: =IFERROR(IF('Sales for the Period'!G15=0,"",'Sales for the Period'!G15),"") -> 61.55304 | H9: =IFERROR(IF(F9="","",IF(G9="","",F9-G9)),"") -> 3.54696 | I9: 0.7296 | J9: =IFERROR(IF(H9="","",H9*I9),"") -> 2.587862
A10: Tomatoes | B10: lb | C10: 13.2 | D10: 25 | E10: 12.85 | F10: =IFERROR(IF(SUM(C10:E10)=0,"",C10+D10-E10),"") -> 25.35 | G10: =IFERROR(IF('Sales for the Period'!H15=0,"",'Sales for the Period'!H15),"") -> 23.1486 | H10: =IFERROR(IF(F10="","",IF(G10="","",F10-G10)),"") -> 2.2014 | I10: 1.98 | J10: =IFERROR(IF(H10="","",H10*I10),"") -> 4.358772
A11: Spring mix | B11: lb | C11: 8.8 | D11: 36 | E11: 6.22 | F11: =IFERROR(IF(SUM(C11:E11)=0,"",C11+D11-E11),"") -> 38.58 | G11: =IFERROR(IF('Sales for the Period'!I15=0,"",'Sales for the Period'!I15),"") -> 36.37635 | H11: =IFERROR(IF(F11="","",IF(G11="","",F11-G11)),"") -> 2.20365 | I11: 3.66 | J11: =IFERROR(IF(H11="","",H11*I11),"") -> 8.065359
A12: Butter | B12: lb | C12: 9.7 | D12: 6 | E12: 7.65 | F12: =IFERROR(IF(SUM(C12:E12)=0,"",C12+D12-E12),"") -> 8.05 | G12: =IFERROR(IF('Sales for the Period'!J15=0,"",'Sales for the Period'!J15),"") -> 7.73196 | H12: =IFERROR(IF(F12="","",IF(G12="","",F12-G12)),"") -> 0.31804 | I12: 3.23 | J12: =IFERROR(IF(H12="","",H12*I12),"") -> 1.0272692
A13: Extra virgin olive oil | B13: L | C13: 10 | D13: 6 | E13: 12.5 | F13: =IFERROR(IF(SUM(C13:E13)=0,"",C13+D13-E13),"") -> 3.5 | G13: =IFERROR(IF('Sales for the Period'!K15=0,"",'Sales for the Period'!K15),"") -> 3.1 | H13: =IFERROR(IF(F13="","",IF(G13="","",F13-G13)),"") -> 0.4 | I13: 8.58 | J13: =IFERROR(IF(H13="","",H13*I13),"") -> 3.432
A14: Dry white wine | B14: L | C14: 12 | D14: 6 | E14: 14 | F14: =IFERROR(IF(SUM(C14:E14)=0,"",C14+D14-E14),"") -> 4 | G14: =IFERROR(IF('Sales for the Period'!L15=0,"",'Sales for the Period'!L15),"") -> 3.6 | H14: =IFERROR(IF(F14="","",IF(G14="","",F14-G14)),"") -> 0.4 | I14: 13.75 | J14: =IFERROR(IF(H14="","",H14*I14),"") -> 5.5
A15: All-purpose flour | B15: lb | F15: =IFERROR(IF(SUM(C15:E15)=0,"",C15+D15-E15),"") | G15: =IFERROR(IF('Sales for the Period'!M15=0,"",'Sales for the Period'!M15),"") | H15: =IFERROR(IF(F15="","",IF(G15="","",F15-G15)),"") | I15: 0.5998 | J15: =IFERROR(IF(H15="","",H15*I15),"")
A16: Sugar | B16: lb | F16: =IFERROR(IF(SUM(C16:E16)=0,"",C16+D16-E16),"") | G16: =IFERROR(IF('Sales for the Period'!N15=0,"",'Sales for the Period'!N15),"") | H16: =IFERROR(IF(F16="","",IF(G16="","",F16-G16)),"") | I16: 1.01 | J16: =IFERROR(IF(H16="","",H16*I16),"")
A17: Eggs | B17: dozen | F17: =IFERROR(IF(SUM(C17:E17)=0,"",C17+D17-E17),"") | G17: =IFERROR(IF('Sales for the Period'!O15=0,"",'Sales for the Period'!O15),"") | H17: =IFERROR(IF(F17="","",IF(G17="","",F17-G17)),"") | I17: 2.27 | J17: =IFERROR(IF(H17="","",H17*I17),"")
A18: Heavy cream | B18: qt | F18: =IFERROR(IF(SUM(C18:E18)=0,"",C18+D18-E18),"") | G18: =IFERROR(IF('Sales for the Period'!P15=0,"",'Sales for the Period'!P15),"") | H18: =IFERROR(IF(F18="","",IF(G18="","",F18-G18)),"") | I18: 4.98 | J18: =IFERROR(IF(H18="","",H18*I18),"")
A19: Dark chocolate 70% | B19: lb | F19: =IFERROR(IF(SUM(C19:E19)=0,"",C19+D19-E19),"") | G19: =IFERROR(IF('Sales for the Period'!Q15=0,"",'Sales for the Period'!Q15),"") | H19: =IFERROR(IF(F19="","",IF(G19="","",F19-G19)),"") | I19: 9.84 | J19: =IFERROR(IF(H19="","",H19*I19),"")
A20: TOTAL VALUE OF VARIANCE | J20: =SUM(J5:J19) -> 104.55396
A22: A POSITIVE variance means you've used more than what you sold accounts for. Always start with the product with the highest dollar variance, not the one with the biggest variance in units.
A23: Products with no sales logged leave theoretical usage and variance blank: with no sales, there's no theoretical figure to compare against, and a zero there would make all of the usage look like a loss.

Sheet Sales for the Period
A1: Sales for the Period — Portions Sold per Dish
A2: One row per dish: how many portions you sold and how much of each inventory product EACH portion uses. The quantity is the AP (as-purchased) figure from the recipe cost card (the "AP qty" column, already including the trim). The TOTALS row multiplies portions × quantity and is the "Theoretical usage" that shows up on the "Inventory" tab.
B3: Unit → | C3: =Inventory!B5 -> lb | D3: =Inventory!B6 -> lb | E3: =Inventory!B7 -> lb | F3: =Inventory!B8 -> lb | G3: =Inventory!B9 -> lb | H3: =Inventory!B10 -> lb | I3: =Inventory!B11 -> lb | J3: =Inventory!B12 -> lb | K3: =Inventory!B13 -> L | L3: =Inventory!B14 -> L | M3: =Inventory!B15 -> lb | N3: =Inventory!B16 -> lb | O3: =Inventory!B17 -> dozen | P3: =Inventory!B18 -> qt | Q3: =Inventory!B19 -> lb
A4: Dish | B4: Portions sold | C4: =Inventory!A5 -> Beef tenderloin (PSMO) | D4: =Inventory!A6 -> Chicken thighs | E4: =Inventory!A7 -> Branzino (whole) | F4: =Inventory!A8 -> Shrimp 16/20 | G4: =Inventory!A9 -> Potatoes | H4: =Inventory!A10 -> Tomatoes | I4: =Inventory!A11 -> Spring mix | J4: =Inventory!A12 -> Butter | K4: =Inventory!A13 -> Extra virgin olive oil | L4: =Inventory!A14 -> Dry white wine | M4: =Inventory!A15 -> All-purpose flour | N4: =Inventory!A16 -> Sugar | O4: =Inventory!A17 -> Eggs | P4: =Inventory!A18 -> Heavy cream | Q4: =Inventory!A19 -> Dark chocolate 70%
A5: Beef Tenderloin with PX Sherry Reduction | B5: 120 | C5: 0.69877 | G5: 0.355114 | J5: 0.064433 | L5: 0.03
A6: Grilled Branzino | B6: 80 | E6: 0.749572 | G6: 0.236742 | K6: 0.02
A7: House Salad | B7: 150 | H7: 0.154324 | I7: 0.242509 | K7: 0.01
A15: TOTALS (portions · theoretical usage) | B15: =SUM(B5:B14) -> 350 | C15: =IFERROR(SUMPRODUCT($B$5:$B$14,C5:C14),"") -> 83.8524 | D15: =IFERROR(SUMPRODUCT($B$5:$B$14,D5:D14),"") -> 0 | E15: =IFERROR(SUMPRODUCT($B$5:$B$14,E5:E14),"") -> 59.96576 | F15: =IFERROR(SUMPRODUCT($B$5:$B$14,F5:F14),"") -> 0 | G15: =IFERROR(SUMPRODUCT($B$5:$B$14,G5:G14),"") -> 61.55304 | H15: =IFERROR(SUMPRODUCT($B$5:$B$14,H5:H14),"") -> 23.1486 | I15: =IFERROR(SUMPRODUCT($B$5:$B$14,I5:I14),"") -> 36.37635 | J15: =IFERROR(SUMPRODUCT($B$5:$B$14,J5:J14),"") -> 7.73196 | ... Q15: =IFERROR(SUMPRODUCT($B$5:$B$14,Q5:Q14),"") -> 0
A17: The names and units in the header are pulled from the "Inventory" tab: change a product there and it updates here automatically.

Sheet Waste Checklist
A1: Incident Log (Month)
A2: 90 lines: about three incidents a day over a month. Log each waste incident as soon as it happens — by the end of the shift, nobody remembers.
A3: Date | B3: Product | C3: Quantity | D3: Reason | E3: Corrective action | F3: Estimated cost
A94: TOTAL WASTE FOR THE PERIOD | F94: =SUM(F4:F93) -> 0
