Workbook

Sheet 0. Assumptions
A1: ASSUMPTIONS — the RATES and DRIVERS of the model are typed here
A2: Change the GREEN cells: the rest of the workbook recalculates on its own. Expense items are typed on their own tab (also in green) and are not repeated here. Amounts are in US dollars (or your own currency).
A3: BUSINESS ACTIVITY
A4: Events per year (year-1 average) | B4: 160 | C4: Average number of events you work per year, counting every wedding, corporate event and private party. It is the main volume driver of the whole workbook: the P&L, break-even and scenarios all read it, and years 2 and 3 grow in events. Compare it with the capacity row further down (max events a year your bars and crews can handle).
A5: Average price per guest (excl. sales tax and alcohol; bar package + add-ons) | B5: 14 | C5: Price per guest for a dry hire event (your client buys the alcohol; you bring the bar, the bartenders and everything else), EXCL. sales tax and excl. alcohol: the bar package plus add-ons, with bartenders, mixers, garnishes, ice and cups included, the service charge in and the voluntary gratuity out. Price per guest incl. sales tax = this value × (1 + your sales tax rate). At 95 guests, 14 per guest gives 1,330 per event: above Check Cherry's $750 median and in the upper quarter (the middle half runs $450-$1,275; see the benchmarks table on the "Instructions" tab). the Pricing Calculator builds your quote from your own costs and hours: divide its subtotal by the billable guests to bring it here.
A6: Average guests per event | B6: 95 | C6: Average number of guests per event across your whole mix, from private parties of about 60 to weddings of 120. Check Cherry booking data puts the typical event near 80 guests (see the benchmarks table on the "Instructions" tab). Sales per event = guests × price per guest. One cell for the whole workbook: the P&L, break-even and scenarios all read it, so they always agree.
A7: Volume growth in year 2 | B7: 0.1 | C7: Growth in events in year 2 over year 1 (enter 0.1 for 10%). Kept modest on purpose: two crews and a Saturday calendar cap how many events you can work, and weddings are booked about two months ahead, so referrals from venues and planners take a season to show up.
A8: Volume growth in year 3 | B8: 0.08 | C8: Growth in events in year 3 over year 2, kept conservative for the same reason: repeat corporate clients and planner referrals build up slowly.
A9: Price per guest incl. sales tax (calculated) | B9: =IFERROR(IF($B$5="","",$B$5*(1+SUMPRODUCT('3-Year P&L'!$E$10:$E$11,'3-Year P&L'!$G$10:$G$11))),"") -> 15.12 | C9: =IFERROR("Price per guest excl. sales tax plus the weighted sales tax of your sales lines ("&TEXT(SUMPRODUCT('3-Year P&L'!$E$10:$E$11,'3-Year P&L'!$G$10:$G$11)*100,"0")&"%), rounded. In the US the quote adds sales tax on top, and whether the bartending service and the service charge are taxable depends on the state (California taxes them); in the UK, VAT is included in the price.","") -> Price per guest excl. sales tax plus the weighted sales tax of your sales lines (8%), rounded. In the US the quote adds sales tax on top, and whether the bartending service and the service charge are taxable depends on the state (California taxes them); in the UK, VAT is included in the price.
A10: SALES MIX AND COST OF GOODS SOLD
A11: BAR PACKAGES share of sales (bartending service, bar, mixers, garnishes, ice) | B11: 0.85 | C11: Share of BAR PACKAGES in total sales: bartending service, bar, mixers, garnishes, ice and cups. It is an INPUT: change it here and the P&L, the cash flow and the sales tax collected recalculate on their own.
A12: ADD-ONS share of sales (travel fees, extra hours, glassware, specialty bars) | B12: =IFERROR(IF(COUNT(B11)=0,"",1-B11),"") -> 0.15 | C12: Calculated as the remainder: bar packages + add-ons = 100%. Add-ons are travel fees, extra hours of service, glassware, champagne service and specialty bars.
A13: Cost of goods on BAR PACKAGE sales (mixers, garnishes, ice, N/A drinks) | B13: 0.19 | C13: Cost of goods sold on bar package sales: mixers, garnishes, ice and non-alcoholic drinks (Kit estimate; see the ice and mixers row in the benchmarks table on the "Instructions" tab). There is no alcohol in it: in dry hire the host buys it. Test it at a higher rate (more fresh juice, more garnish) before you trust the result.
A14: Cost of goods on ADD-ON sales | B14: 0.2 | C14: Cost of goods sold on add-on sales: specialty bars, champagne service and rented extra glassware (Kit estimate). Set above the bar package rate because these items bring their own ingredients or rental fees. No alcohol: the host buys it.
A15: Cups, straws, napkins and bar disposables as % of sales | B15: 0.04 | C15: Cups, straws, napkins, coasters and the printed drink menu sign, as a % of sales (Kit estimate). It sits next to cost of goods sold instead of hiding in miscellaneous. Some cities and venues restrict single-use plastics, so check the rules and price compostable cups if you need them.
A16: Share of sales booked through gig marketplaces (GigSalad, The Bash, Thumbtack) | B16: 0.2 | C16: Share of your sales booked through gig marketplaces such as GigSalad, The Bash and Thumbtack, rather than by hosts and planners who book you directly. Set it to 0 if you only sell direct. The marketplace sends you the booking and keeps a fee (next row).
A17: Marketplace fee on those bookings | B17: 0.05 | C17: Fee the marketplace keeps on those bookings. GigSalad charges 5% of the confirmed booking on its free plan and 2.5% on the paid plan, and nothing per lead (gigsalad.com); Thumbtack charges per lead instead, so convert that cost to a % of booked sales. Fees change: check the current schedule when you sign up. Not used while the marketplace share is 0%.
A18: Card processing fee | B18: 0.03 | C18: Card fees on total sales. Hosts and planners mostly pay by card, with some ACH or check from companies, which lowers the cost. The example (3%) is a blended rate: a percentage plus a per-transaction fee, which weighs more on small deposits. Check your processor's statement and enter your effective rate (Kit estimate).
A19: LABOR
A20: Employer payroll taxes | B20: 0.1 | C20: FICA (Social Security 6.2% + Medicare 1.45%) + federal and state unemployment taxes (FUTA / SUTA). Workers' comp is in the insurance line. The example uses a lean 10% with no benefits; ask your payroll provider for your rate.
A21: Monthly pay periods per year (keep 12) | B21: 12 | C21: Annual gross pay = monthly gross pay × this number. Keep 12 in the US: it counts the monthly salaries the model pays in a year, not how often you run payroll (weekly or biweekly payroll pays the same annual amount)
A22: Federal minimum wage, annual full-time | B22: 15080 | C22: US federal minimum wage: 7.25 per hour × 2,080 hours = 15,080 per year for a full-time job. Your state or city may set a higher floor: enter it in the state / local minimum wage cell below. Check the current rates at dol.gov
A23: STORAGE, TRAILER PARKING AND FIXED COSTS
A24: Storage unit & trailer parking, per month | B24: 600 | C24: Monthly cost of the storage unit (or garage) where the bar, glassware and supplies live, plus the parking spot for the trailer. It is not storefront rent: you work at the host's venue. The deposit and the months before opening are calculated from this cell. If your county requires a commissary for ice or garnish, add it here (Kit estimate: +300-800 per month).
A25: Storage unit deposit (months) | B25: 1 | C25: Months of deposit on the storage unit. Many facilities ask for about one month up front: far less than the deposit on a commercial lease. Agree it in writing.
A26: Monthly utilities (storage unit power and water) | B26: 100 | C26: Electricity and water for the storage unit (lights, the wash area, charging), plus any utilities the storage rent does not cover. Fuel for the tow vehicle and the generator is not here: it is in the "Vehicle and trailer fuel, maintenance and registration" line of the "3-Year P&L". It is the one cell for this cost, so you change it in one place and the rest of the workbook follows.
A27: Insurance (per year) | B27: 4000 | C27: Yearly insurance: general liability plus liquor liability (Kit estimate 600-1,000), commercial auto covering the trailer (about 1,800), workers' comp for your W-2 bartenders (about 1,000) and equipment coverage (about 300). Venues ask for a COI naming them as additional insured, and general liability plus liquor liability start around $550 a year, bundled (insurancecanopy.com). The total is a Kit estimate: get quotes before you fix it.
A28: Miscellaneous and contingency as % of sales | B28: 0.03 | C28: Last-minute costs of each event: extra ice, mixers bought on the way, parking at the venue. It is a VARIABLE cost: it rises and falls with the number of events, so it cannot sit among the fixed costs or it would move the break-even without anyone noticing. Fuel, maintenance and registration of the tow vehicle and trailer have their own line in the P&L.
A29: FINANCING
A30: Owner's equity contributed | B30: 28000 | C30: Your own money. Lenders usually expect an owner equity injection (often around 10% for SBA start-ups; many want 20-30%) on the total cash needed in this plan.
A31: Loan requested | B31: 49000 | C31: Principal requested from your lender: an SBA 7(a) loan through your bank, or a small SBA Microloan (up to 50,000). This is the cell. It is the only loan that the amortization schedule, the P&L interest and the DSCR use. The "Financing" tab checks that the sources of funds match the total cash needed on the "Startup Costs" tab (which includes working capital and the trailer and fit-out contingency): copy the loan suggested there into this cell until the difference reaches zero.
A32: Nominal annual interest rate (not APR) | B32: 0.1 | C32: Nominal annual rate (not APR). The example (10%) is the kit's assumption for a small SBA loan. A smaller loan secured by a used trailer and bar equipment often prices above a storefront loan: ask two lenders for quotes, and ask about SBA-guaranteed loans, before you set it.
A33: Loan term (years) | B33: 7 | C33: Total years, interest-only period included. A trailer and bar equipment lose value faster than a storefront build-out, so the term is shorter. SBA 7(a) allows up to 10 years for equipment and working capital.
A34: Interest-only period (years) | B34: 0 | C34: ZERO by default: repayment starts in year 1, so the year-1 DSCR already measures the full loan payment. If you negotiate an interest-only first year, enter it here and read the year-1 DSCR with care.
A35: Working capital (months of fixed costs) | B35: 3 | C35: The minimum this workbook asks for (see "Instructions"): a cushion below 3 months does not cover a slow stretch, such as the off-season for weddings or a corporate client who pays late.
A36: TAXES
A37: Effective income tax rate (years 1-2) | B37: 0.25 | C37: Example: 21% federal rate for a C corporation plus state tax, rounded to 25%. If you operate as a sole proprietorship, LLC taxed as a pass-through or S corporation, the business itself pays 0% here and you pay tax on the profit personally: set this to 0 and budget for your personal tax separately. The model applies this rate to the first two years with positive taxable income
A38: Effective income tax rate (from year 3) | B38: 0.25 | C38: From the third year with positive taxable income. Same example rate (21% federal C corporation + state). Confirm the rate that applies to you with your accountant and change it here
A39: Sales tax rate on sales | B39: 0.08 | C39: Example rate: state + local sales tax combined, applied to the whole invoice (bar service, add-ons and service charge). Whether bartending services are taxable varies by state: California taxes them (cdtfa.ca.gov). UK: 20% VAT on the service.
A40: Sales tax rate on alcohol sold (licensed only) | B40: 0.08 | C40: Same example rate as above. Some states add separate liquor taxes: include them here if they apply to you. Alcohol served on site has its own rate in the sales tax breakdown block, further down. Utilities, equipment and services are handled in the cell below
A41: Recoverable input tax on purchases and capex | B41: 0 | C41: In the US, the sales tax you pay on purchases is a cost, not a credit: leave this at 0%. UK: 20% if you are VAT-registered
A42: Net operating losses carried forward | B42: 0 | C42: Net operating losses from earlier years still to be offset at the start. Federal rules let you offset up to 80% of taxable income in a year; the model offsets 100% as a simplification
A43: DEPRECIATION
A44: Useful life of the bar trailer and its conversion (years) | B44: 7 | C44: The bar trailer, its conversion, the generator and the storage fit-out: everything that rides with the trailer is depreciated with it over the same life. Straight-line book depreciation; tax methods such as MACRS or Section 179 are separate, so confirm with your accountant.
A45: Useful life of bar equipment, glassware and software (years) | B45: 5 | C45: Portable bar, bar tools, glassware, coolers, booking software and tablet. Loading and unloading at every event wears them faster than a fixed bar, so a short life is prudent. Straight-line book depreciation; MACRS or Section 179 are tax treatments: confirm with your accountant.
A47: GROWTH AND COST INFLATION
A48: Annual increase in fixed costs | B48: 0 | C48: SET TO ZERO: all three columns are in year-1 prices (real terms). Raise it if you want to project in nominal terms
A49: RAMP-UP AND CAPACITY
A51: Max events a year your bars and crews can handle | B51: 260 | C51: INFORMATION ONLY: it does not enter any calculation in this workbook. It is your estimate of the most events a year your bars and crews can handle: two setups (the trailer and the portable bar) times roughly 130 bookable days each, because Saturdays are the bottleneck. Compare it with the events per year you plan and with the optimistic scenario: if the plan goes above it, you need a third setup or more bartenders. Volume itself is driven by the "Events per year" cell above.
A52: Month-1 activity as a % of steady-state activity | B52: 0.45 | C52: A new mobile bar does not book in month one what it books in month eight: weddings are reserved about two months ahead and the first year is slow (see the first-year row in the benchmarks table on the "Instructions" tab). Events per year above is the year-1 AVERAGE: the ramp only spreads year 1's sales across the months (slower start, stronger finish) and keeps the annual total. At 100% there is no ramp.
A53: Months to reach steady state | B53: 9 | C53: The ramp rises in a straight line from the percentage above to 100% over this number of months
A54: Months of storage rent BEFORE opening | B54: 2 | C54: Converting the trailer, getting your permits and preselling at bridal shows takes weeks, so you pay storage rent and trailer parking before your first event. It belongs in startup costs, not in the P&L.
A55: Contingency on the trailer, conversion and fit-out lines (%) | B55: 0.1 | C55: Calculated by formula on the trailer, conversion, generator, storage fit-out and inspection lines: if you change the trailer price, the contingency recalculates on its own. The note on that row of the "Startup Costs" tab lists exactly which lines are included.
A57: RECEIPTS, PAYMENTS AND SALES TAX BREAKDOWN
A58: Average collection days | B58: 1 | C58: Average days between the event and the money in your bank. A deposit (30% is typical) is paid when the host books and the balance before the event, so most of the money arrives before you work. Raise it if corporate clients or marketplaces pay later. The workbook does not model deposits: they improve your real cash flow.
A59: Average days to pay suppliers | B59: 7 | C59: What your suppliers finance for you. It is the first thing you lose if you fall behind on a payment
A60: Month of extra pay period 1 (only if pay periods > 12) | B60: 7 | C60: Month of the year (1-12) when the first extra pay period is paid out. Only used if pay periods > 12
A61: Month of extra pay period 2 (only if pay periods > 12) | B61: 12 | C61: Month of the year (1-12) when the second extra pay period is paid out. Only used if pay periods > 12
A62: ALCOHOL as a share of add-on sales (0% in dry hire: the host buys it) | B62: 0 | C62: ZERO by default: in dry hire the host buys the alcohol and your certified bartenders serve it, so you sell none. Selling alcohol requires a liquor license (and, in many states, a special event permit): see the full-service option in section 9 of the Word plan and check your state before adding it. Keep liquor liability coverage whenever your bartenders pour at an event.
A63: Sales tax rate on alcohol served on site | B63: 0.08 | C63: Only used if you enter alcohol sales above, which is zero in this plan. Example rate: the same as the rest of the sales (state + local combined). Some states tax alcohol at a different rate or add liquor taxes: if you sell alcohol, enter the rate that applies.
A64: CONTROL THRESHOLDS AND FLOORS
A65: DSCR limit (minimum acceptable) | B65: 1.15 | C65: Below 1.0 the business does not generate enough to repay the loan. Lenders often write a minimum DSCR into the loan covenants: ask yours. Kit default: 1.15×
A66: DSCR target (green) | B66: 1.25 | C66: What lenders commonly look for before approving a loan comfortably. Kit default: 1.25× (editable estimate)
A67: Minimum cushion above break-even | B67: 0.15 | C67: Minimum cushion of the plan above break-even (plan ÷ break-even − 1). The drop you can absorb is 1 − break-even ÷ plan: a 15% cushion lets events fall by about 13% before costs stop being covered
A68: State / local minimum wage, annual full-time | C68: Enter the minimum wage of your state or city, annualized for a full-time job (hourly rate × 2,080 hours). The pay floor in the "Staffing" tab is the HIGHER of this cell and the federal minimum. With 0 or blank, the traffic light compares only against the federal floor. Check current rates at dol.gov.

Sheet Startup Costs
A1: BUSINESS PLAN: MOBILE BAR & EVENT BARTENDING
A2: Estimated Startup Costs
A3: US kit example (2026) — replace with your own quotes.
A5: Item | B5: Amount | C5: % of startup costs | D5: Notes | E5: Taxable / recoverable tax?
A6: STARTUP COSTS | B6: =IFERROR(IF(COUNT(B7:B23)=0,"",SUM(B7:B23)),"") -> 47530 | C6: =IFERROR(B6/$B$26,"") -> 0.61749647
A7: Bar trailer, used (6 x 12 ft (1.8 x 3.7 m) cargo / concession or horse trailer) | B7: 9000 | C7: =IFERROR(B7/$B$26,"") -> 0.11692548 | D7: A used bar trailer (6 x 12 ft (1.8 x 3.7 m) cargo, concession or horse trailer) that you convert. The tow vehicle is yours, so it costs 0 in the plan: if you do not have one, a used pickup is an extra purchase starting around $10,000 (checkcherry.com). Prices vary a lot with size and condition, so get several quotes. | E7: Yes
A8: Trailer conversion (bar top, cabinetry, hand sink, water tanks, LED, electrical) | B8: 12000 | C8: =IFERROR(B8/$B$26,"") -> 0.15590064 | D8: Bar top, cabinets, hand sink and fresh and gray water tanks, LED lighting and the electrical work. A basic conversion typically starts around 5,000 and a custom build costs several times more (Kit estimate). | E8: Yes
A9: Wrap, signage and bar facade | B9: 2500 | C9: =IFERROR(B9/$B$26,"") -> 0.032479301 | D9: Trailer wrap, signage and the bar facade: your rolling billboard at every venue and the first thing guests photograph. | E9: Yes
A10: Portable bar for the second crew and indoor venues | B10: 2000 | C10: =IFERROR(B10/$B$26,"") -> 0.025983441 | D10: A portable bar for the second crew and for indoor venues where the trailer does not fit. Basic units start around 1,000 (checkcherry.com); a nicer one with a lit back bar costs more. | E10: Yes
A11: Inverter generator and power | B11: 1800 | C11: =IFERROR(B11/$B$26,"") -> 0.023385097 | D11: A quiet inverter generator and the cabling, for venues without power. Typical range 800-3,000 (Kit estimate). | E11: Yes
A12: Storage unit fit-out (shelving, glass racks, wash station) | B12: 1000 | C12: =IFERROR(B12/$B$26,"") -> 0.01299172 | D12: Shelving, glassware racks and a wash area inside the storage unit. Ask the facility what it already provides before you budget this line. | E12: Yes
A13: LLC formation, contracts and legal | B13: 1500 | C13: =IFERROR(B13/$B$26,"") -> 0.019487581 | D13: State filing fees for the articles of organization (Secretary of State) plus any attorney or filing-service fees; a registered agent is also needed. Fees vary a lot by state. The "Taxable / recoverable tax?" column is set to No: it only matters if you enter a recoverable input tax rate (for example UK VAT). | E13: No
A14: First-year permits and certifications (business license, sales tax permit, TABC / RBS / TIPS) | B14: 1000 | C14: =IFERROR(B14/$B$26,"") -> 0.01299172 | D14: Business license, sales tax permit and responsible-service certifications (TABC in Texas, RBS in California, TIPS or ServSafe Alcohol) for year 1. It varies a lot by state and city: get the amounts for yours before you close the budget. | E14: No
A15: Health permit / unit inspection (only if your county requires it) | B15: 500 | C15: =IFERROR(B15/$B$26,"") -> 0.0064958602 | D15: Only if your county requires it: ask your county health department whether ice, cut garnish or the hand sink trigger a unit inspection. If not, enter 0. | E15: Yes
A16: Booking software, card reader and tablet | B16: 800 | C16: =IFERROR(B16/$B$26,"") -> 0.010393376 | D16: Booking software and CRM for proposals, contracts and deposits, plus a card reader and a tablet. | E16: Yes
A17: Bar tools and smallwares (4 stations) | B17: 1200 | C17: =IFERROR(B17/$B$26,"") -> 0.015590064 | D17: Shakers, jiggers, speed rails, strainers, ice scoops and bar mats for 4 stations: the equipment that gets depreciated. Daily disposables are NOT depreciated: they go in the disposables line of the P&L, at the % of sales set in "0. Assumptions". | E17: Yes
A18: Opening inventory (mixers, syrups, garnishes, cups, napkins) | B18: 1500 | C18: =IFERROR(B18/$B$26,"") -> 0.019487581 | D18: Mixers, syrups, garnishes, cups and napkins for your first events. No alcohol: in dry hire the host buys it. With 0% recoverable input tax (the US default), any sales tax you pay on this purchase is treated as a cost. | E18: Yes
... A20: Glassware (300 pieces + racks), coolers, ice bins and dispensers | B20: 3500 | C20: =IFERROR(B20/$B$26,"") -> 0.045471021 | D20: Glassware (300 pieces plus racks), coolers, ice bins and dispensers for events where the host does not rent glass. | E20: Yes
A21: Storage unit deposit | B21: =IFERROR(IF('0. Assumptions'!$B$24="","",'0. Assumptions'!$B$24*'0. Assumptions'!$B$25),"") -> 600 | C21: =IFERROR(B21/$B$26,"") -> 0.0077950322 | D21: =IFERROR(""&TEXT('0. Assumptions'!$B$25,"0")&IF('0. Assumptions'!$B$25=1," month"," months")&" of rent, from ""0. Assumptions"". Refundable when the storage unit lease ends: it is not depreciated and carries no tax","") -> 1 month of rent, from "0. Assumptions". Refundable when the storage unit lease ends: it is not depreciated and carries no tax | E21: No
A22: Storage rent before opening | B22: =IFERROR(IF('0. Assumptions'!$B$24="","",'0. Assumptions'!$B$24*'0. Assumptions'!$B$54),"") -> 1200 | C22: =IFERROR(B22/$B$26,"") -> 0.015590064 | D22: =IFERROR("Rent "&IF('0. Assumptions'!$B$54=1,"for the month","for the "&TEXT('0. Assumptions'!$B$54,"0")&" months")&" of trailer build, permits and pre-sales before opening. It does not overlap the P&L, which starts on opening day: its twelve months are twelve trading months","") -> Rent for the 2 months of trailer build, permits and pre-sales before opening. It does not overlap the P&L, which starts on opening day: its twelve months are twelve trading months | E22: Yes
A23: Trailer and fit-out contingency | B23: =IFERROR(IF(COUNT(B7,B8,B11,B12,B15)=0,"",ROUND((B7+B8+B11+B12+B15)*'0. Assumptions'!$B$55,0)),"") -> 2430 | C23: =IFERROR(B23/$B$26,"") -> 0.031569881 | D23: =IFERROR("At "&TEXT('0. Assumptions'!$B$55,"0%")&" of the BUILD-OUT items of this block (used bar trailer, trailer conversion, inverter generator, storage unit fit-out and the health permit / unit inspection), not of the whole block: the other items are left out. No lender funds a "&"build-out without a cushion: the percentage is in ""0. Assumptions""","") -> At 10% of the BUILD-OUT items of this block (used bar trailer, trailer conversion, inverter generator, storage unit fit-out and the health permit / unit inspection), not of the whole block: the other items are left out. No lender funds a build-out without a cushion: the percentage is in "0. Assumptions" | E23: Yes
A24: WORKING CAPITAL | B24: =IFERROR(IF(B25="","",B25),"") -> 29442.1 | C24: =IFERROR(B24/$B$26,"") -> 0.38250353
A25: Operating cushion until break-even | B25: =IFERROR(IF('0. Assumptions'!$B$35*('3-Year P&L'!$B$38-'3-Year P&L'!$B$36)=0,"",'0. Assumptions'!$B$35*('3-Year P&L'!$B$38-'3-Year P&L'!$B$36)/12),"") -> 29442.1 | C25: =IFERROR(B25/$B$26,"") -> 0.38250353 | D25: =IFERROR("Covers "&TEXT('0. Assumptions'!$B$35,"0")&IF('0. Assumptions'!$B$35=1," month"," months")&" of year-1 CASH fixed costs (the P&L fixed costs minus depreciation, which is not paid out), the minimum the Instructions of this workbook ask for","") -> Covers 3 months of year-1 CASH fixed costs (the P&L fixed costs minus depreciation, which is not paid out), the minimum the Instructions of this workbook ask for | E25: No
A26: TOTAL STARTUP COSTS (sum of the blocks) | B26: =IFERROR(B6+B24,"") -> 76972.1 | D26: =IFERROR("The percentages in column C are read on this figure, which includes the working capital ("&TEXT(C24,"0%")&" of the total). To compare the breakdown with another plan, use the CAPEX row below.","") -> The percentages in column C are read on this figure, which includes the working capital (38% of the total). To compare the breakdown with another plan, use the CAPEX row below.
A27: CAPEX (startup costs excluding working capital) | B27: =IFERROR(B26-B24,"") -> 47530 | D27: What you buy: trailer, conversion, equipment, launch and formation costs. The cash cushion is not an investment: it is working capital.
A28: Recoverable input tax on capex | B28: =IFERROR(IF(B26="","",SUMIF($E$7:$E$23,"Yes",$B$7:$B$23)*'0. Assumptions'!$B$41),"") -> 0 | D28: =IFERROR("At "&TEXT('0. Assumptions'!$B$41,"0%")&" on the items marked ""Yes"" in the tax column. US: the sales tax you pay on equipment is part of its cost and is not recovered, so this rate is 0. UK (VAT-registered): 20%, reclaimed on your VAT return, but you pay it first, so the loan has to cover it","") -> At 0% on the items marked "Yes" in the tax column. US: the sales tax you pay on equipment is part of its cost and is not recovered, so this rate is 0. UK (VAT-registered): 20%, reclaimed on your VAT return, but you pay it first, so the loan has to cover it
A29: TOTAL CASH NEEDED AT LAUNCH | B29: =IFERROR(B26+B28,"") -> 76972.1 | D29: This is the figure the Financing tab has to cover
A30: DEPRECIATION BASES (not added to startup costs)
A31: Trailer, conversion and fit-out (depreciated over the trailer life) | B31: =IFERROR(IF(B7="","",B7+B8+B11+B12+B15+B23),"") -> 26730 | D31: =IFERROR("Depreciated over "&TEXT('0. Assumptions'!$B$44,"0")&" years","") -> Depreciated over 7 years
A32: Machinery, furniture and equipment | B32: =IFERROR(IF(B9="","",B9+B10+B16+B17+B20),"") -> 10000 | D32: =IFERROR("Depreciated over "&TEXT('0. Assumptions'!$B$45,"0")&" years","") -> Depreciated over 5 years
A33: Annual depreciation of fixed assets | B33: =IFERROR(B31/MAX(1,'0. Assumptions'!$B$44)+B32/MAX(1,'0. Assumptions'!$B$45),"") -> 5818.5714 | D33: =IFERROR("Not depreciated, because they are not fixed assets: LLC formation and legal, first-year permits and certifications, opening inventory, website, photos and launch, the storage unit deposit, pre-opening storage rent and the working capital "&"reserve. They add up to "&TEXT(B26-B31-B32,"#,##0")&" of the "&TEXT(B26,"#,##0")&" total investment.","") -> Not depreciated, because they are not fixed assets: LLC formation and legal, first-year permits and certifications, opening inventory, website, photos and launch, the storage unit deposit, pre-opening storage rent and the working capital reserve. They add up to 40242 of the 76972 total investment.

Sheet 3-Year P&L
A1: PRO FORMA P&L — 3 YEARS
A2: Base case — mobile bar (dry hire)
A4: Item | B4: Year 1 | C4: Year 2 | D4: Year 3 | E4: % of sales (year 1) | F4: Notes | G4: Sales tax rate on the line (%)
A5: REVENUE
A6: Events per year (average) | B6: =IFERROR(IF('0. Assumptions'!$B$4="","",'0. Assumptions'!$B$4),"") -> 160 | C6: =IFERROR(B6*(1+'0. Assumptions'!$B$7),"") -> 176 | D6: =IFERROR(C6*(1+'0. Assumptions'!$B$8),"") -> 190.08 | F6: Growth for years 2 and 3 is set in "0. Assumptions"
A7: Average price per guest (excl. sales tax) | B7: =IFERROR(IF('0. Assumptions'!$B$5="","",'0. Assumptions'!$B$5),"") -> 14 | C7: =IFERROR(IF(B7="","",B7),"") -> 14 | D7: =IFERROR(IF(C7="","",C7),"") -> 14 | F7: Held constant at year-1 prices: a price increase is a separate decision
A8: Average guests per event | B8: =IFERROR(IF('0. Assumptions'!$B$6="","",'0. Assumptions'!$B$6),"") -> 95 | C8: =IFERROR(IF(B8="","",B8),"") -> 95 | D8: =IFERROR(IF(C8="","",C8),"") -> 95
A9: TOTAL REVENUE (excl. sales tax) | B9: =IFERROR(IF(B6*B7*B8=0,"",B6*B7*B8),"") -> 212800 | C9: =IFERROR(IF(C6*C7*C8=0,"",C6*C7*C8),"") -> 234080 | D9: =IFERROR(IF(D6*D7*D8=0,"",D6*D7*D8),"") -> 252806.4 | E9: =IFERROR(IF(B9="","",1),"") -> 1
A10: Bar package sales (bartending service, bar, mixers, garnishes, ice) | B10: =IFERROR(IF(B9="","",B9*$E$10),"") -> 180880 | C10: =IFERROR(IF(C9="","",C9*$E$10),"") -> 198968 | D10: =IFERROR(IF(D9="","",D9*$E$10),"") -> 214885.44 | E10: =IFERROR(IF('0. Assumptions'!$B$11="","",'0. Assumptions'!$B$11),"") -> 0.85 | F10: Bar package sales: bartending service, bar, mixers, garnishes, ice and cups per guest, for weddings, corporate events and private parties. No alcohol: the host buys it. All of it carries cost of goods sold at the bar package rate. | G10: =IFERROR(IF(B9="","",'0. Assumptions'!$B$39),"") -> 0.08
A11: Add-on sales (travel fees, extra hours, glassware, specialty bars) | B11: =IFERROR(IF(B9="","",B9*$E$11),"") -> 31920 | C11: =IFERROR(IF(C9="","",C9*$E$11),"") -> 35112 | D11: =IFERROR(IF(D9="","",D9*$E$11),"") -> 37920.96 | E11: =IFERROR(IF('0. Assumptions'!$B$12="","",'0. Assumptions'!$B$12),"") -> 0.15 | F11: Add-on sales: travel fees, extra hours of service, glassware, champagne service and specialty bars. They carry cost of goods sold at the add-on rate. | G11: =IFERROR(IF(B9="","",('0. Assumptions'!$B$62*((1-'0. Assumptions'!$B$16)*'0. Assumptions'!$B$63+'0. Assumptions'!$B$16*'0. Assumptions'!$B$40)+(1-'0. Assumptions'!$B$62)*'0. Assumptions'!$B$39)),"") -> 0.08
A12: VARIABLE COSTS
A13: Cost of goods — bar packages (mixers, garnishes, ice) | B13: =IFERROR(IF(B9="","",B9*'0. Assumptions'!$B$11*'0. Assumptions'!$B$13),"") -> 34367.2 | C13: =IFERROR(IF(C9="","",C9*'0. Assumptions'!$B$11*'0. Assumptions'!$B$13),"") -> 37803.92 | D13: =IFERROR(IF(D9="","",D9*'0. Assumptions'!$B$11*'0. Assumptions'!$B$13),"") -> 40828.234 | E13: =IFERROR(B13/$B$9,"") -> 0.1615 | F13: =IFERROR("At "&TEXT('0. Assumptions'!$B$13,"0%")&" of BAR PACKAGE sales (mixers, garnishes, ice), not of total sales: add-ons have their own line","") -> At 19% of BAR PACKAGE sales (mixers, garnishes, ice), not of total sales: add-ons have their own line | G13: =IFERROR(IF(B9="","",'0. Assumptions'!$B$41),"") -> 0
A14: Cost of goods — add-ons | B14: =IFERROR(IF(B9="","",B9*'0. Assumptions'!$B$12*'0. Assumptions'!$B$14),"") -> 6384 | C14: =IFERROR(IF(C9="","",C9*'0. Assumptions'!$B$12*'0. Assumptions'!$B$14),"") -> 7022.4 | D14: =IFERROR(IF(D9="","",D9*'0. Assumptions'!$B$12*'0. Assumptions'!$B$14),"") -> 7584.192 | E14: =IFERROR(B14/$B$9,"") -> 0.03 | F14: =IFERROR("At "&TEXT('0. Assumptions'!$B$14,"0%")&" of ADD-ON sales","") -> At 20% of ADD-ON sales | G14: =IFERROR(IF(B9="","",'0. Assumptions'!$B$41),"") -> 0
A15: Cups, straws, napkins and bar disposables | B15: =IFERROR(IF(B9="","",B9*'0. Assumptions'!$B$15),"") -> 8512 | C15: =IFERROR(IF(C9="","",C9*'0. Assumptions'!$B$15),"") -> 9363.2 | D15: =IFERROR(IF(D9="","",D9*'0. Assumptions'!$B$15),"") -> 10112.256 | E15: =IFERROR(B15/$B$9,"") -> 0.04 | G15: =IFERROR(IF(B9="","",'0. Assumptions'!$B$41),"") -> 0
A16: Gig marketplace fees | B16: =IFERROR(IF(B9="","",B9*'0. Assumptions'!$B$16*'0. Assumptions'!$B$17),"") -> 2128 | C16: =IFERROR(IF(C9="","",C9*'0. Assumptions'!$B$16*'0. Assumptions'!$B$17),"") -> 2340.8 | D16: =IFERROR(IF(D9="","",D9*'0. Assumptions'!$B$16*'0. Assumptions'!$B$17),"") -> 2528.064 | E16: =IFERROR(B16/$B$9,"") -> 0.01 | F16: Applied to the sales of THAT CHANNEL. With 0% marketplace sales in "0. Assumptions", this line is zero. | G16: =IFERROR(IF(B9="","",'0. Assumptions'!$B$41),"") -> 0
A17: Card processing fees | B17: =IFERROR(IF(B9="","",B9*'0. Assumptions'!$B$18),"") -> 6384 | C17: =IFERROR(IF(C9="","",C9*'0. Assumptions'!$B$18),"") -> 7022.4 | D17: =IFERROR(IF(D9="","",D9*'0. Assumptions'!$B$18),"") -> 7584.192 | E17: =IFERROR(B17/$B$9,"") -> 0.03 | F17: Card processing fees are not subject to sales tax: no tax is recovered or deducted for them | G17: 0
A18: Miscellaneous and contingency | B18: =IFERROR(IF(B9="","",B9*'0. Assumptions'!$B$28),"") -> 6384 | C18: =IFERROR(IF(C9="","",C9*'0. Assumptions'!$B$28),"") -> 7022.4 | D18: =IFERROR(IF(D9="","",D9*'0. Assumptions'!$B$28),"") -> 7584.192 | E18: =IFERROR(B18/$B$9,"") -> 0.03 | F18: =IFERROR("At "&TEXT('0. Assumptions'!$B$28,"0%")&" of sales: a cushion for unbudgeted event costs (extra ice, last-minute mixers, venue parking). It is a VARIABLE cost: it moves with the number of events, so it cannot sit in fixed costs (fuel, maintenance and registration of the tow "&"vehicle and the trailer are in row 27)","") -> At 3% of sales: a cushion for unbudgeted event costs (extra ice, last-minute mixers, venue parking). It is a VARIABLE cost: it moves with the number of events, so it cannot sit in fixed costs (fuel, maintenance and registration of the tow vehicle and the trailer are in row 27) | G18: =IFERROR(IF(B9="","",'0. Assumptions'!$B$41),"") -> 0
A19: TOTAL VARIABLE COSTS | B19: =IFERROR(IF(B9="","",SUM(B13:B18)),"") -> 64159.2 | C19: =IFERROR(IF(C9="","",SUM(C13:C18)),"") -> 70575.12 | D19: =IFERROR(IF(D9="","",SUM(D13:D18)),"") -> 76221.13 | E19: =IFERROR(B19/$B$9,"") -> 0.3015
A20: GROSS MARGIN | B20: =IFERROR(IF(B9="","",B9-B19),"") -> 148640.8 | C20: =IFERROR(IF(C9="","",C9-C19),"") -> 163504.88 | D20: =IFERROR(IF(D9="","",D9-D19),"") -> 176585.27 | E20: =IFERROR(B20/$B$9,"") -> 0.6985
A21: FIXED COSTS
A22: Storage unit & trailer parking | B22: =IFERROR(IF(B9="","",'0. Assumptions'!$B$24*12),"") -> 7200 | C22: =IFERROR(IF(C9="","",B22*(1+'0. Assumptions'!$B$48)),"") -> 7200 | D22: =IFERROR(IF(D9="","",C22*(1+'0. Assumptions'!$B$48)),"") -> 7200 | E22: =IFERROR(B22/$B$9,"") -> 0.033834586 | F22: The monthly amount is typed in "0. Assumptions"; here it is multiplied by twelve. It covers your storage unit and the parking spot for the trailer, not storefront rent. The months before opening are on the "Startup Costs" tab and are NOT counted twice. | G22: =IFERROR(IF(B9="","",'0. Assumptions'!$B$41),"") -> 0
A23: Labor (wages + employer payroll taxes) | B23: =IFERROR(IF(B9="","",Staffing!$G$9),"") -> 78368.4 | C23: =IFERROR(IF(C9="","",Staffing!$B$13),"") -> 81368.4 | D23: =IFERROR(IF(D9="","",Staffing!$B$14),"") -> 84368.4 | E23: =IFERROR(B23/$B$9,"") -> 0.36827256 | F23: Comes from the Staffing tab: it is the SAME number, not a separate estimate. Years 2 and 3 add the new hires declared on that tab, not a percentage of volume | G23: 0
A24: Utilities (storage unit power and water) | B24: =IFERROR(IF(B9="","",'0. Assumptions'!$B$26*12),"") -> 1200 | C24: =IFERROR(IF(C9="","",B24*(1+'0. Assumptions'!$B$48)),"") -> 1200 | D24: =IFERROR(IF(D9="","",C24*(1+'0. Assumptions'!$B$48)),"") -> 1200 | E24: =IFERROR(B24/$B$9,"") -> 0.0056390977 | F24: Electricity and water for the storage unit, plus any utilities the storage rent does not cover. Fuel for the tow vehicle and the generator is in the vehicle and trailer line. | G24: =IFERROR(IF(B9="","",'0. Assumptions'!$B$41),"") -> 0
A25: Insurance (general and liquor liability, auto, workers' comp) | B25: =IFERROR(IF(B9="","",'0. Assumptions'!$B$27),"") -> 4000 | C25: =IFERROR(IF(C9="","",B25*(1+'0. Assumptions'!$B$48)),"") -> 4000 | D25: =IFERROR(IF(D9="","",C25*(1+'0. Assumptions'!$B$48)),"") -> 4000 | E25: =IFERROR(B25/$B$9,"") -> 0.018796992 | F25: Insurance premiums are not subject to sales tax: there is no recoverable tax on them | G25: 0
A26: Permits and certifications renewal | B26: 500 | C26: =IFERROR(IF(C9="","",B26*(1+'0. Assumptions'!$B$48)),"") -> 500 | D26: =IFERROR(IF(D9="","",C26*(1+'0. Assumptions'!$B$48)),"") -> 500 | E26: =IFERROR(B26/$B$9,"") -> 0.0023496241 | G26: =IFERROR(IF(B9="","",'0. Assumptions'!$B$41),"") -> 0
A27: Vehicle and trailer fuel, maintenance and registration | B27: 4000 | C27: =IFERROR(IF(C9="","",B27*(1+'0. Assumptions'!$B$48)),"") -> 4000 | D27: =IFERROR(IF(D9="","",C27*(1+'0. Assumptions'!$B$48)),"") -> 4000 | E27: =IFERROR(B27/$B$9,"") -> 0.018796992 | G27: =IFERROR(IF(B9="","",'0. Assumptions'!$B$41),"") -> 0
A28: Marketing and advertising | B28: 9000 | C28: =IFERROR(IF(C9="","",B28*(1+'0. Assumptions'!$B$48)),"") -> 9000 | D28: =IFERROR(IF(D9="","",C28*(1+'0. Assumptions'!$B$48)),"") -> 9000 | E28: =IFERROR(B28/$B$9,"") -> 0.042293233 | G28: =IFERROR(IF(B9="","",'0. Assumptions'!$B$41),"") -> 0
A29: Accounting / bookkeeping | B29: 2400 | C29: =IFERROR(IF(C9="","",B29*(1+'0. Assumptions'!$B$48)),"") -> 2400 | D29: =IFERROR(IF(D9="","",C29*(1+'0. Assumptions'!$B$48)),"") -> 2400 | E29: =IFERROR(B29/$B$9,"") -> 0.011278195 | G29: =IFERROR(IF(B9="","",'0. Assumptions'!$B$41),"") -> 0
A30: Software (booking / CRM, e-signature, POS) | B30: 1500 | C30: =IFERROR(IF(C9="","",B30*(1+'0. Assumptions'!$B$48)),"") -> 1500 | D30: =IFERROR(IF(D9="","",C30*(1+'0. Assumptions'!$B$48)),"") -> 1500 | E30: =IFERROR(B30/$B$9,"") -> 0.0070488722 | G30: =IFERROR(IF(B9="","",'0. Assumptions'!$B$41),"") -> 0
A31: Glass washing, linens and bar towels | B31: 1200 | C31: =IFERROR(IF(C9="","",B31*(1+'0. Assumptions'!$B$48)),"") -> 1200 | D31: =IFERROR(IF(D9="","",C31*(1+'0. Assumptions'!$B$48)),"") -> 1200 | E31: =IFERROR(B31/$B$9,"") -> 0.0056390977 | G31: =IFERROR(IF(B9="","",'0. Assumptions'!$B$41),"") -> 0
A32: Phone and internet | B32: 900 | C32: =IFERROR(IF(C9="","",B32*(1+'0. Assumptions'!$B$48)),"") -> 900 | D32: =IFERROR(IF(D9="","",C32*(1+'0. Assumptions'!$B$48)),"") -> 900 | E32: =IFERROR(B32/$B$9,"") -> 0.0042293233 | F32: Business mobile plan and data for the card reader at venues with weak signal. Get a quote from your carrier. | G32: =IFERROR(IF(B9="","",'0. Assumptions'!$B$41),"") -> 0
A33: Equipment repair and breakage | B33: 1200 | C33: =IFERROR(IF(C9="","",B33*(1+'0. Assumptions'!$B$48)),"") -> 1200 | D33: =IFERROR(IF(D9="","",C33*(1+'0. Assumptions'!$B$48)),"") -> 1200 | E33: =IFERROR(B33/$B$9,"") -> 0.0056390977 | F33: Replacing broken or lost glassware and repairing equipment. Glass breaks at events, so restock every season. | G33: =IFERROR(IF(B9="","",'0. Assumptions'!$B$41),"") -> 0
A34: Staff training and server certifications (TIPS / TABC / RBS) | B34: 400 | C34: =IFERROR(IF(C9="","",B34*(1+'0. Assumptions'!$B$48)),"") -> 400 | D34: =IFERROR(IF(D9="","",C34*(1+'0. Assumptions'!$B$48)),"") -> 400 | E34: =IFERROR(B34/$B$9,"") -> 0.0018796992 | F34: Responsible-service certifications for you and your bartenders (TIPS, TABC, RBS or ServSafe Alcohol) and their renewals. The certificate you need varies by state, and many venues ask for it anyway. | G34: =IFERROR(IF(B9="","",'0. Assumptions'!$B$41),"") -> 0
A35: Tastings and cocktail menu consultations for prospects | B35: 1000 | C35: =IFERROR(IF(C9="","",B35*(1+'0. Assumptions'!$B$48)),"") -> 1000 | D35: =IFERROR(IF(D9="","",C35*(1+'0. Assumptions'!$B$48)),"") -> 1000 | E35: =IFERROR(B35/$B$9,"") -> 0.0046992481 | F35: Tastings and drink menu consultations for couples and planners: mixers, garnish and your time. Many operators credit the tasting toward the booking: if you do, lower this line. | G35: =IFERROR(IF(B9="","",'0. Assumptions'!$B$41),"") -> 0
A36: Depreciation of fixed assets | B36: =IFERROR(IF(B9="","",'Startup Costs'!$B$33),"") -> 5818.5714 | C36: =IFERROR(IF(C9="","",B36),"") -> 5818.5714 | D36: =IFERROR(IF(D9="","",B36),"") -> 5818.5714 | E36: =IFERROR(B36/$B$9,"") -> 0.027342911 | F36: Comes from the depreciation bases on the Startup Costs tab: real fixed assets only. It does NOT rise with inflation: it is a charge on the HISTORICAL cost of the assets | G36: 0
A37: Interest expense (loan interest) | B37: =IFERROR(IF(B9="","",Financing!$B$44),"") -> 4900 | C37: =IFERROR(IF(C9="","",Financing!$B$46),"") -> 4383.5131 | D37: =IFERROR(IF(D9="","",Financing!$B$48),"") -> 3815.3774 | E37: =IFERROR(B37/$B$9,"") -> 0.023026316 | F37: Only INTEREST is an expense. Principal repaid appears on the cash flow tab | G37: 0
A38: TOTAL FIXED COSTS | B38: =IFERROR(IF(B9="","",SUM(B22:B37)),"") -> 123586.97 | C38: =IFERROR(IF(C9="","",SUM(C22:C37)),"") -> 126070.48 | D38: =IFERROR(IF(D9="","",SUM(D22:D37)),"") -> 128502.35 | E38: =IFERROR(B38/$B$9,"") -> 0.58076584
A39: Recoverable input tax on variable costs | B39: =IFERROR(IF(B9="","",SUMPRODUCT(B13:B18,G13:G18)),"") -> 0 | C39: =IFERROR(IF(C9="","",SUMPRODUCT(C13:C18,G13:G18)),"") -> 0 | D39: =IFERROR(IF(D9="","",SUMPRODUCT(D13:D18,G13:G18)),"") -> 0 | F39: Each line at ITS OWN rate, read from the column next to it. It is what the cash flow tab overpays to suppliers and later deducts (zero wherever no tax is recoverable)
A40: Recoverable input tax on fixed costs | B40: =IFERROR(IF(B9="","",SUMPRODUCT(B22:B37,G22:G37)),"") -> 0 | C40: =IFERROR(IF(C9="","",SUMPRODUCT(C22:C37,G22:G37)),"") -> 0 | D40: =IFERROR(IF(D9="","",SUMPRODUCT(D22:D37,G22:G37)),"") -> 0
A41: PRE-TAX INCOME (EBT) | B41: =IFERROR(IF(B9="","",B20-B38),"") -> 25053.829 | C41: =IFERROR(IF(C9="","",C20-C38),"") -> 37434.396 | D41: =IFERROR(IF(D9="","",D20-D38),"") -> 48082.922 | E41: =IFERROR(B41/$B$9,"") -> 0.11773416
A42: Net operating losses carried forward (opening) | B42: =IFERROR(IF(B9="","",'0. Assumptions'!$B$42),"") -> 0 | C42: =IFERROR(IF(C9="","",B47),"") -> 0 | D42: =IFERROR(IF(D9="","",C47),"") -> 0 | F42: Federal rules let a year's losses offset the profits of later years (the federal limit is 80% of taxable income; this model offsets 100% as a simplification)
A43: Taxable income (after loss offset) | B43: =IFERROR(IF(B9="","",MAX(0,B41-B42)),"") -> 25053.829 | C43: =IFERROR(IF(C9="","",MAX(0,C41-C42)),"") -> 37434.396 | D43: =IFERROR(IF(D9="","",MAX(0,D41-D42)),"") -> 48082.922
A44: Years with positive taxable income (cumulative) | B44: =IFERROR(IF(B9="","",IF(B43>0,1,0)),"") -> 1 | C44: =IFERROR(IF(C9="","",B44+IF(C43>0,1,0)),"") -> 2 | D44: =IFERROR(IF(D9="","",C44+IF(D43>0,1,0)),"") -> 3
A45: Effective income tax rate applied | B45: =IFERROR(IF(B9="","",IF(B43<=0,"",IF(B44<=2,'0. Assumptions'!$B$37,'0. Assumptions'!$B$38))),"") -> 0.25 | C45: =IFERROR(IF(C9="","",IF(C43<=0,"",IF(C44<=2,'0. Assumptions'!$B$37,'0. Assumptions'!$B$38))),"") -> 0.25 | D45: =IFERROR(IF(D9="","",IF(D43<=0,"",IF(D44<=2,'0. Assumptions'!$B$37,'0. Assumptions'!$B$38))),"") -> 0.25 | F45: The "years 1-2" rate applies to the first two years with positive taxable income, not to the first two calendar years of the business. The model approximates this by counting the first two profitable years
A46: Income tax | B46: =IFERROR(IF(B9="","",IF(B45="",0,B43*B45)),"") -> 6263.4571 | C46: =IFERROR(IF(C9="","",IF(C45="",0,C43*C45)),"") -> 9358.5989 | D46: =IFERROR(IF(D9="","",IF(D45="",0,D43*D45)),"") -> 12020.73
A47: Net operating losses carried forward (closing) | B47: =IFERROR(IF(B9="","",MAX(0,B42-B41)),"") -> 0 | C47: =IFERROR(IF(C9="","",MAX(0,C42-C41)),"") -> 0 | D47: =IFERROR(IF(D9="","",MAX(0,D42-D41)),"") -> 0
A48: NET INCOME | B48: =IFERROR(IF(B9="","",B41-B46),"") -> 18790.371 | C48: =IFERROR(IF(C9="","",C41-C46),"") -> 28075.797 | D48: =IFERROR(IF(D9="","",D41-D46),"") -> 36062.191 | E48: =IFERROR(B48/$B$9,"") -> 0.088300618
A49: KEY RATIOS
A50: Ratio | B50: Year 1 | C50: Year 2 | D50: Year 3 | E50: Threshold | F50: Comment
A51: Gross margin / Sales | B51: =IFERROR(IF(B9="","",B20/B9),"") -> 0.6985 | C51: =IFERROR(IF(C9="","",C20/C9),"") -> 0.6985 | D51: =IFERROR(IF(D9="","",D20/D9),"") -> 0.6985 | E51: 0.65 | F51: Floor set by this workbook: kit benchmark (editable estimate). The workbook's gross margin also subtracts card fees, marketplace fees and miscellaneous event costs, so it sits below the margin of bar package pricing alone.
A52: Cost of goods sold (bar packages + add-ons) | B52: =IFERROR(IF(B9="","",B13+B14),"") -> 40751.2 | C52: =IFERROR(IF(C9="","",C13+C14),"") -> 44826.32 | D52: =IFERROR(IF(D9="","",D13+D14),"") -> 48412.426
A53: Cost of goods sold / Sales | B53: =IFERROR(IF(B9="","",B52/B9),"") -> 0.1915 | C53: =IFERROR(IF(C9="","",C52/C9),"") -> 0.1915 | D53: =IFERROR(IF(D9="","",D52/D9),"") -> 0.1915 | E53: 0.26 | F53: Ceiling for cost of goods sold on bar packages and add-ons (disposables have their own line): kit benchmark (editable estimate). No alcohol in it: in dry hire the host buys it.
A54: Labor cost / Sales | B54: =IFERROR(IF(B9="","",B23/B9),"") -> 0.36827256 | C54: =IFERROR(IF(C9="","",C23/C9),"") -> 0.34760936 | D54: =IFERROR(IF(D9="","",D23/D9),"") -> 0.33372731 | E54: 0.4 | F54: Ceiling for labor: kit benchmark (editable estimate). It includes your own pay as Owner & Lead Bartender plus the W-2 event bartenders and barbacks.
A55: Storage & parking / Sales | B55: =IFERROR(IF(B9="","",B22/B9),"") -> 0.033834586 | C55: =IFERROR(IF(C9="","",C22/C9),"") -> 0.030758715 | D55: =IFERROR(IF(D9="","",D22/D9),"") -> 0.028480292 | E55: 0.06 | F55: There is no storefront rent in this workbook: 6% is a prudent ceiling for the storage unit and trailer parking, a kit benchmark (editable estimate). A bar with its own premises carries a much higher occupancy cost.
A56: Net income / Sales | B56: =IFERROR(IF(B9="","",B48/B9),"") -> 0.088300618 | C56: =IFERROR(IF(C9="","",C48/C9),"") -> 0.11994103 | D56: =IFERROR(IF(D9="","",D48/D9),"") -> 0.14264746 | E56: 0.05 | F56: Floor of 5%: a kit benchmark (editable estimate). A new business with a loan to repay starts lower: if you land under it, review the price per guest and the events per year first.
A57: Break-even reached | B57: =IFERROR(IF(B9="","",IF(B9>='Break-Even'!$B$16,"Yes","No")),"") -> Yes | C57: =IFERROR(IF(C9="","",IF(C9>='Break-Even'!$C$16,"Yes","No")),"") -> Yes | D57: =IFERROR(IF(D9="","",IF(D9>='Break-Even'!$D$16,"Yes","No")),"") -> Yes | F57: Compares each year's sales with that same year's threshold, which the Break-Even tab calculates with that year's fixed costs
A59: All figures are EXCL. SALES TAX. Years 2 and 3 are in year-1 prices unless you raise cost inflation in the "0. Assumptions" tab. The "Sales tax rate on the line (%)" column shows, on SALES lines, the rate collected on each one and, on COST lines, the rate paid on that item. The cash flow tab reads it: insurance and card fees carry no sales tax, and wages, depreciation and interest carry none either.

Sheet Break-Even
A1: BREAK-EVEN ANALYSIS
A2: Break-even — Mobile Bar
A4: Variable | B4: Year 1 | C4: Year 2 | D4: Year 3 | E4: Notes
A5: BASE DATA BY YEAR
A6: Annual fixed costs | B6: =IFERROR(IF('3-Year P&L'!$B$9="","",'3-Year P&L'!$B$38),"") -> 123586.97 | C6: =IFERROR(IF('3-Year P&L'!$C$9="","",'3-Year P&L'!$C$38),"") -> 126070.48 | D6: =IFERROR(IF('3-Year P&L'!$D$9="","",'3-Year P&L'!$D$38),"") -> 128502.35 | E6: The SAME fixed costs as the P&L. Each year has its own, which is why the threshold cannot be a single one for all three years
A7: Monthly fixed costs | B7: =IFERROR(IF('3-Year P&L'!$B$9="","",B6/12),"") -> 10298.914 | C7: =IFERROR(IF('3-Year P&L'!$C$9="","",C6/12),"") -> 10505.874 | D7: =IFERROR(IF('3-Year P&L'!$D$9="","",D6/12),"") -> 10708.529
A8: Average price per guest (excl. sales tax) | B8: =IFERROR(IF('3-Year P&L'!$B$9="","",'3-Year P&L'!$B$7),"") -> 14 | C8: =IFERROR(IF('3-Year P&L'!$C$9="","",'3-Year P&L'!$C$7),"") -> 14 | D8: =IFERROR(IF('3-Year P&L'!$D$9="","",'3-Year P&L'!$D$7),"") -> 14
A9: Variable cost per guest | B9: =IFERROR(IF('3-Year P&L'!$B$9="","",'3-Year P&L'!$B$19/('3-Year P&L'!$B$6*'3-Year P&L'!$B$8)),"") -> 4.221 | C9: =IFERROR(IF('3-Year P&L'!$C$9="","",'3-Year P&L'!$C$19/('3-Year P&L'!$C$6*'3-Year P&L'!$C$8)),"") -> 4.221 | D9: =IFERROR(IF('3-Year P&L'!$D$9="","",'3-Year P&L'!$D$19/('3-Year P&L'!$D$6*'3-Year P&L'!$D$8)),"") -> 4.221 | E9: Comes from the P&L total variable costs, not from a separate estimate. It includes miscellaneous and contingency, which is a percentage of sales
A10: Contribution margin per guest | B10: =IFERROR(IF('3-Year P&L'!$B$9="","",B8-B9),"") -> 9.779 | C10: =IFERROR(IF('3-Year P&L'!$C$9="","",C8-C9),"") -> 9.779 | D10: =IFERROR(IF('3-Year P&L'!$D$9="","",D8-D9),"") -> 9.779 | E10: Price per guest minus variable cost per guest
A11: Average guests per event | B11: =IFERROR(IF('3-Year P&L'!$B$9="","",'3-Year P&L'!$B$8),"") -> 95 | C11: =IFERROR(IF('3-Year P&L'!$C$9="","",'3-Year P&L'!$C$8),"") -> 95 | D11: =IFERROR(IF('3-Year P&L'!$D$9="","",'3-Year P&L'!$D$8),"") -> 95 | E11: The same calendar as the P&L and the scenarios
A12: Principal repaid in the year | B12: =IFERROR(IF('3-Year P&L'!$B$9="","",Financing!$B$45),"") -> 5164.8695 | C12: =IFERROR(IF('3-Year P&L'!$C$9="","",Financing!$B$47),"") -> 5681.3564 | D12: =IFERROR(IF('3-Year P&L'!$D$9="","",Financing!$B$49),"") -> 6249.4921 | E12: Principal is NOT a P&L expense, but it leaves the cash account. Without it, the published break-even threshold would sit below the real one
A13: ACCOUNTING BREAK-EVEN (includes depreciation)
A14: Guests needed per year | B14: =IFERROR(IF('3-Year P&L'!$B$9="","",IF(B10<=0,"",B6/B10)),"") -> 12637.997 | C14: =IFERROR(IF('3-Year P&L'!$C$9="","",IF(C10<=0,"",C6/C10)),"") -> 12891.961 | D14: =IFERROR(IF('3-Year P&L'!$D$9="","",IF(D10<=0,"",D6/D10)),"") -> 13140.643
A15: Events needed per year | B15: =IFERROR(IF('3-Year P&L'!$B$9="","",B14/B11),"") -> 133.03155 | C15: =IFERROR(IF('3-Year P&L'!$C$9="","",C14/C11),"") -> 135.70485 | D15: =IFERROR(IF('3-Year P&L'!$D$9="","",D14/D11),"") -> 138.32256
A16: Revenue needed per year | B16: =IFERROR(IF('3-Year P&L'!$B$9="","",B14*B8),"") -> 176931.96 | C16: =IFERROR(IF('3-Year P&L'!$C$9="","",C14*C8),"") -> 180487.45 | D16: =IFERROR(IF('3-Year P&L'!$D$9="","",D14*D8),"") -> 183969
A17: CASH BREAK-EVEN (loan payments in, depreciation out)
A18: Cash fixed costs + principal repaid for the year | B18: =IFERROR(IF('3-Year P&L'!$B$9="","",B6-'3-Year P&L'!$B$36+B12),"") -> 122933.27 | C18: =IFERROR(IF('3-Year P&L'!$C$9="","",C6-'3-Year P&L'!$C$36+C12),"") -> 125933.27 | D18: =IFERROR(IF('3-Year P&L'!$D$9="","",D6-'3-Year P&L'!$D$36+D12),"") -> 128933.27 | E18: The P&L fixed costs without depreciation (which is not paid in cash) and WITH principal repaid (which is). This is the threshold that decides whether cash holds up
A19: Guests needed per year (cash) | B19: =IFERROR(IF('3-Year P&L'!$B$9="","",IF(B10<=0,"",B18/B10)),"") -> 12571.149 | C19: =IFERROR(IF('3-Year P&L'!$C$9="","",IF(C10<=0,"",C18/C10)),"") -> 12877.929 | D19: =IFERROR(IF('3-Year P&L'!$D$9="","",IF(D10<=0,"",D18/D10)),"") -> 13184.709
A20: Events needed per year (cash) | B20: =IFERROR(IF('3-Year P&L'!$B$9="","",B19/B11),"") -> 132.32789 | C20: =IFERROR(IF('3-Year P&L'!$C$9="","",C19/C11),"") -> 135.55715 | D20: =IFERROR(IF('3-Year P&L'!$D$9="","",D19/D11),"") -> 138.78641
A21: Revenue needed per year (cash) | B21: =IFERROR(IF('3-Year P&L'!$B$9="","",B19*B8),"") -> 175996.09 | C21: =IFERROR(IF('3-Year P&L'!$C$9="","",C19*C8),"") -> 180291.01 | D21: =IFERROR(IF('3-Year P&L'!$D$9="","",D19*D8),"") -> 184585.93
A22: COMPARISON WITH THE PLAN
A23: Events per year in the plan | B23: =IFERROR(IF('3-Year P&L'!$B$9="","",'3-Year P&L'!$B$6),"") -> 160 | C23: =IFERROR(IF('3-Year P&L'!$C$9="","",'3-Year P&L'!$C$6),"") -> 176 | D23: =IFERROR(IF('3-Year P&L'!$D$9="","",'3-Year P&L'!$D$6),"") -> 190.08
A24: Cushion above CASH break-even (%) | B24: =IFERROR(IF('3-Year P&L'!$B$9="","",B23/B20-1),"") -> 0.20911776 | C24: =IFERROR(IF('3-Year P&L'!$C$9="","",C23/C20-1),"") -> 0.29834539 | D24: =IFERROR(IF('3-Year P&L'!$D$9="","",D23/D20-1),"") -> 0.36958654 | E24: How far the plan sits above the cash break-even (plan ÷ break-even − 1); the drop you can absorb is 1 − break-even ÷ plan. The required minimum is set in the "0. Assumptions" tab
A25: INTERPRETATION
A26: =IFERROR("With the average price per guest excl. sales tax above, you need "&TEXT(ROUNDUP(B15,0),"0")&" events a year at your average of "&TEXT(B11,"0")&" guests per event to avoid losing money (accounting break-even, depreciation included), and "&TEXT(ROUNDUP(B20,0),"0")&" for cash to hold (cash break-even: depreciation out, because it is not paid, and the year's loan payment in"&IF(B12=0,"; no principal is repaid this year (interest-only period or no loan)","")&"). The ""Revenue needed per year"" rows show the same figures in your currency.","") -> With the average price per guest excl. sales tax above, you need 134 events a year at your average of 95 guests per event to avoid losing money (accounting break-even, depreciation included), and 133 for cash to hold (cash break-even: depreciation out, because it is not paid, and the year's loan payment in). The "Revenue needed per year" rows show the same figures in your currency.
A28: BREAK-EVEN SENSITIVITY
A29: Events per year needed to cover costs for each price per guest (columns, in steps around the plan's price) and each variable cost per guest (rows). Green cells are below the events per year the plan forecasts.
A31: Events per year needed: price per guest excl. sales tax (columns) × variable cost per guest (rows) | B31: =IFERROR($B$8-1,"") -> 13 | C31: =IFERROR(IF($B$8="","",$B$8),"") -> 14 | D31: =IFERROR($B$8+1,"") -> 15 | E31: =IFERROR($B$8+2,"") -> 16
A32: =IFERROR($B$9*0.85,"") -> 3.58785 | B32: =IFERROR(IF($B$31-$A32<=0,"",$B$6/($B$31-$A32)/$B$11),"") -> 138.21661 | C32: =IFERROR(IF($C$31-$A32<=0,"",$B$6/($C$31-$A32)/$B$11),"") -> 124.94206 | D32: =IFERROR(IF($D$31-$A32<=0,"",$B$6/($D$31-$A32)/$B$11),"") -> 113.9939 | E32: =IFERROR(IF($E$31-$A32<=0,"",$B$6/($E$31-$A32)/$B$11),"") -> 104.80984
A33: =IFERROR($B$9*0.925,"") -> 3.904425 | B33: =IFERROR(IF($B$31-$A33<=0,"",$B$6/($B$31-$A33)/$B$11),"") -> 143.0273 | C33: =IFERROR(IF($C$31-$A33<=0,"",$B$6/($C$31-$A33)/$B$11),"") -> 128.85997 | D33: =IFERROR(IF($D$31-$A33<=0,"",$B$6/($D$31-$A33)/$B$11),"") -> 117.24633 | E33: =IFERROR(IF($E$31-$A33<=0,"",$B$6/($E$31-$A33)/$B$11),"") -> 107.55301
A34: =IFERROR($B$9*1.0,"") -> 4.221 | B34: =IFERROR(IF($B$31-$A34<=0,"",$B$6/($B$31-$A34)/$B$11),"") -> 148.18493 | C34: =IFERROR(IF($C$31-$A34<=0,"",$B$6/($C$31-$A34)/$B$11),"") -> 133.03155 | D34: =IFERROR(IF($D$31-$A34<=0,"",$B$6/($D$31-$A34)/$B$11),"") -> 120.68981 | E34: =IFERROR(IF($E$31-$A34<=0,"",$B$6/($E$31-$A34)/$B$11),"") -> 110.44363
A35: =IFERROR($B$9*1.075,"") -> 4.537575 | B35: =IFERROR(IF($B$31-$A35<=0,"",$B$6/($B$31-$A35)/$B$11),"") -> 153.72845 | C35: =IFERROR(IF($C$31-$A35<=0,"",$B$6/($C$31-$A35)/$B$11),"") -> 137.48225 | D35: =IFERROR(IF($D$31-$A35<=0,"",$B$6/($D$31-$A35)/$B$11),"") -> 124.34168 | E35: =IFERROR(IF($E$31-$A35<=0,"",$B$6/($E$31-$A35)/$B$11),"") -> 113.49392
A36: =IFERROR($B$9*1.15,"") -> 4.85415 | B36: =IFERROR(IF($B$31-$A36<=0,"",$B$6/($B$31-$A36)/$B$11),"") -> 159.70285 | C36: =IFERROR(IF($C$31-$A36<=0,"",$B$6/($C$31-$A36)/$B$11),"") -> 142.24107 | D36: =IFERROR(IF($D$31-$A36<=0,"",$B$6/($D$31-$A36)/$B$11),"") -> 128.22144 | E36: =IFERROR(IF($E$31-$A36<=0,"",$B$6/($E$31-$A36)/$B$11),"") -> 116.71748

Sheet Scenarios
A1: SCENARIO ANALYSIS
A4: Metric | B4: Pessimistic | C4: Base | D4: Optimistic | E4: Notes
A5: Events per year | B5: 120 | C5: =IFERROR(IF('3-Year P&L'!$B$6="","",'3-Year P&L'!$B$6),"") -> 160 | D5: 200
A6: Average price per guest (excl. sales tax) | B6: 12.6 | C6: =IFERROR(IF('3-Year P&L'!$B$7="","",'3-Year P&L'!$B$7),"") -> 14 | D6: 15.4
A7: Average guests per event | B7: 86 | C7: =IFERROR(IF('3-Year P&L'!$B$8="","",'3-Year P&L'!$B$8),"") -> 95 | D7: 105
A8: ANNUAL REVENUE (excl. sales tax) | B8: =IFERROR(IF(B5*B6*B7=0,"",B5*B6*B7),"") -> 130032 | C8: =IFERROR(IF(C5*C6*C7=0,"",C5*C6*C7),"") -> 212800 | D8: =IFERROR(IF(D5*D6*D7=0,"",D5*D6*D7),"") -> 323400
A9: Cost of goods — bar packages (mixers, garnishes, ice) | B9: =IFERROR(IF(B8="","",B8*'0. Assumptions'!$B$11*'0. Assumptions'!$B$13),"") -> 21000.168 | C9: =IFERROR(IF(C8="","",C8*'0. Assumptions'!$B$11*'0. Assumptions'!$B$13),"") -> 34367.2 | D9: =IFERROR(IF(D8="","",D8*'0. Assumptions'!$B$11*'0. Assumptions'!$B$13),"") -> 52229.1
A10: Cost of goods — add-ons | B10: =IFERROR(IF(B8="","",B8*'0. Assumptions'!$B$12*'0. Assumptions'!$B$14),"") -> 3900.96 | C10: =IFERROR(IF(C8="","",C8*'0. Assumptions'!$B$12*'0. Assumptions'!$B$14),"") -> 6384 | D10: =IFERROR(IF(D8="","",D8*'0. Assumptions'!$B$12*'0. Assumptions'!$B$14),"") -> 9702
A11: Cups, straws, napkins and bar disposables | B11: =IFERROR(IF(B8="","",B8*'0. Assumptions'!$B$15),"") -> 5201.28 | C11: =IFERROR(IF(C8="","",C8*'0. Assumptions'!$B$15),"") -> 8512 | D11: =IFERROR(IF(D8="","",D8*'0. Assumptions'!$B$15),"") -> 12936
A12: Gig marketplace fees | B12: =IFERROR(IF(B8="","",B8*'0. Assumptions'!$B$16*'0. Assumptions'!$B$17),"") -> 1300.32 | C12: =IFERROR(IF(C8="","",C8*'0. Assumptions'!$B$16*'0. Assumptions'!$B$17),"") -> 2128 | D12: =IFERROR(IF(D8="","",D8*'0. Assumptions'!$B$16*'0. Assumptions'!$B$17),"") -> 3234
A13: Card processing fees | B13: =IFERROR(IF(B8="","",B8*'0. Assumptions'!$B$18),"") -> 3900.96 | C13: =IFERROR(IF(C8="","",C8*'0. Assumptions'!$B$18),"") -> 6384 | D13: =IFERROR(IF(D8="","",D8*'0. Assumptions'!$B$18),"") -> 9702
A14: Miscellaneous and contingency | B14: =IFERROR(IF(B8="","",B8*'0. Assumptions'!$B$28),"") -> 3900.96 | C14: =IFERROR(IF(C8="","",C8*'0. Assumptions'!$B$28),"") -> 6384 | D14: =IFERROR(IF(D8="","",D8*'0. Assumptions'!$B$28),"") -> 9702
A15: TOTAL VARIABLE COSTS | B15: =IFERROR(IF(B8="","",SUM(B9:B14)),"") -> 39204.648 | C15: =IFERROR(IF(C8="","",SUM(C9:C14)),"") -> 64159.2 | D15: =IFERROR(IF(D8="","",SUM(D9:D14)),"") -> 97505.1
A16: GROSS MARGIN | B16: =IFERROR(IF(B8="","",B8-B15),"") -> 90827.352 | C16: =IFERROR(IF(C8="","",C8-C15),"") -> 148640.8 | D16: =IFERROR(IF(D8="","",D8-D15),"") -> 225894.9
A17: FIXED COSTS (the P&L's) | B17: =IFERROR(IF(B8="","",'3-Year P&L'!$B$38),"") -> 123586.97 | C17: =IFERROR(IF(C8="","",'3-Year P&L'!$B$38),"") -> 123586.97 | D17: =IFERROR(IF(D8="","",'3-Year P&L'!$B$38),"") -> 123586.97 | E17: Fixed costs do not change with the scenario: that is why they are fixed
A18: PRE-TAX INCOME (EBT) | B18: =IFERROR(IF(B8="","",B16-B17),"") -> -32759.619 | C18: =IFERROR(IF(C8="","",C16-C17),"") -> 25053.829 | D18: =IFERROR(IF(D8="","",D16-D17),"") -> 102307.93
A19: Income tax | B19: =IFERROR(IF(B8="","",MAX(0,B18-'0. Assumptions'!$B$42)*'0. Assumptions'!$B$37),"") -> 0 | C19: =IFERROR(IF(C8="","",MAX(0,C18-'0. Assumptions'!$B$42)*'0. Assumptions'!$B$37),"") -> 6263.4571 | D19: =IFERROR(IF(D8="","",MAX(0,D18-'0. Assumptions'!$B$42)*'0. Assumptions'!$B$37),"") -> 25576.982 | E19: At the "years 1-2" effective income tax rate, offsetting prior net operating losses
A20: NET INCOME | B20: =IFERROR(IF(B8="","",B18-B19),"") -> -32759.619 | C20: =IFERROR(IF(C8="","",C18-C19),"") -> 18790.371 | D20: =IFERROR(IF(D8="","",D18-D19),"") -> 76730.946
A21: Events per year to break even | B21: =IFERROR(IF(B8="","",IF(B6-B15/(B5*B7)<=0,"",B17/(B6-B15/(B5*B7))/B7)),"") -> 163.28161 | C21: =IFERROR(IF(C8="","",IF(C6-C15/(C5*C7)<=0,"",C17/(C6-C15/(C5*C7))/C7)),"") -> 133.03155 | D21: =IFERROR(IF(D8="","",IF(D6-D15/(D5*D7)<=0,"",D17/(D6-D15/(D5*D7))/D7)),"") -> 109.41989
A22: WHAT EACH SCENARIO DEMANDS
A23: Labor cost / Sales | B23: =IFERROR(IF(B8="","",'3-Year P&L'!$B$23/B8),"") -> 0.60268549 | C23: =IFERROR(IF(C8="","",'3-Year P&L'!$B$23/C8),"") -> 0.36827256 | D23: =IFERROR(IF(D8="","",'3-Year P&L'!$B$23/D8),"") -> 0.24232653 | E23: The SAME staffing in all three scenarios. In the pessimistic case your real cost of event bartenders and barbacks falls with the number of events (you pay hours per event), so the real result would be somewhat better than shown. If labor cost still blows up, adjust it in the "Staffing" tab, not here.
A24: Guests per year per full-time equivalent | B24: =IFERROR(IF(B8="","",B5*B7/Staffing!$C$9),"") -> 5578.3784 | C24: =IFERROR(IF(C8="","",C5*C7/Staffing!$C$9),"") -> 8216.2162 | D24: =IFERROR(IF(D8="","",D5*D7/Staffing!$C$9),"") -> 11351.351 | E24: Guests each full-time equivalent in the "Staffing" table would have to serve in a year. In the optimistic scenario it tells you whether you need to hire
A25: Year-1 closing cash balance (estimate, same method in all three scenarios) | B25: =IFERROR(IF(B8="","",'Startup Costs'!$B$25+B20+'3-Year P&L'!$B$36-Financing!$B$45),"") -> -2663.8175 | C25: =IFERROR(IF(C8="","",'Startup Costs'!$B$25+C20+'3-Year P&L'!$B$36-Financing!$B$45),"") -> 48886.173 | D25: =IFERROR(IF(D8="","",'Startup Costs'!$B$25+D20+'3-Year P&L'!$B$36-Financing!$B$45),"") -> 106826.75 | E25: ESTIMATED balance: working capital plus the year's result, adding back depreciation (which is not paid) and subtracting loan principal. It does not include the timing gap between receipts and payments or the sales tax settlement, so the three columns can be compared with each other. In red, the scenario runs out of cash
A26: Actual month-12 balance from the 12-Month Cash Flow tab (Base case only) | C26: =IFERROR(IF(C8="","",'12-Month Cash Flow'!$M$22),"") -> 58962.499 | E26: The ACTUAL base-case balance, with its timing of receipts and payments and its sales tax settlement. It exists only for the Base scenario, the only one with its own monthly cash flow: that is why it is not in the row above, where it would be compared against two estimates
A28: The "Base" column reads its three inputs (events per year, price per guest and guests per event) from the "0. Assumptions" tab, so it reproduces EXACTLY year 1 of the P&L. The other two scenarios use the same cost rates: only events, price and guests change. FIXED COSTS are the same in all three, while variable costs follow the sales of each scenario.

Sheet Staffing
A1: STAFFING STRUCTURE AND COSTS
A2: =IFERROR("Payroll — "&TEXT('0. Assumptions'!$B$21,"0")&" pay periods + employer taxes "&TEXT('0. Assumptions'!$B$20*100,"0")&"%","") -> Payroll — 12 pay periods + employer taxes 10%
A4: Position | B4: People | C4: FTE | D4: Gross pay per month (total for the position) | E4: Employer payroll taxes (total for the position) | F4: Cost per month (total for the position) | G4: Cost per year | H4: Hours per week per person | I4: Hours per year for the position | J4: Notes
A5: Owner & Lead Bartender (sales and operations) | B5: 1 | C5: 1 | D5: 3250 | E5: =IFERROR(IF(D5="","",D5*'0. Assumptions'!$B$20),"") -> 325 | F5: =IFERROR(IF(D5="","",D5+E5),"") -> 3575 | G5: =IFERROR(IF(D5="","",F5*MAX(12,'0. Assumptions'!$B$21)),"") -> 42900 | H5: =IFERROR(IF(D5="","",C5*$B$16),"") -> 40 | I5: =IFERROR(IF(D5="","",H5*B5*$B$17),"") -> 2000 | J5: Sells, runs the tastings, designs the drink menus and leads the bar for crew 1. Covers the main shift at every event.
A6: Second-crew lead bartender (part-time W-2) | B6: 1 | C6: 0.25 | D6: 867 | E6: =IFERROR(IF(D6="","",D6*'0. Assumptions'!$B$20),"") -> 86.7 | F6: =IFERROR(IF(D6="","",D6+E6),"") -> 953.7 | G6: =IFERROR(IF(D6="","",F6*MAX(12,'0. Assumptions'!$B$21)),"") -> 11444.4 | H6: =IFERROR(IF(D6="","",C6*$B$16),"") -> 10 | I6: =IFERROR(IF(D6="","",H6*B6*$B$17),"") -> 500 | J6: Leads the second crew on peak-season Saturdays: setup, service and breakdown. Part-time W-2, paid at or above the pay floor in proportion to FTE.
A7: Event bartenders (hourly W-2) | B7: 5 | C7: 0.1 | D7: 1560 | E7: =IFERROR(IF(D7="","",D7*'0. Assumptions'!$B$20),"") -> 156 | F7: =IFERROR(IF(D7="","",D7+E7),"") -> 1716 | G7: =IFERROR(IF(D7="","",F7*MAX(12,'0. Assumptions'!$B$21)),"") -> 20592 | H7: =IFERROR(IF(D7="","",C7*$B$16),"") -> 4 | I7: =IFERROR(IF(D7="","",H7*B7*$B$17),"") -> 1000 | J7: Bartenders hired per event and paid hourly as W-2 employees. Their FTE is a fraction because they only work event hours. Voluntary tips are theirs (FLSA). Treating them as 1099 contractors is a misclassification risk (FLSA; California AB5). Paid at or above the pay floor in proportion to FTE.
A8: Barbacks / setup crew (hourly W-2) | B8: 2 | C8: 0.05 | D8: 260 | E8: =IFERROR(IF(D8="","",D8*'0. Assumptions'!$B$20),"") -> 26 | F8: =IFERROR(IF(D8="","",D8+E8),"") -> 286 | G8: =IFERROR(IF(D8="","",F8*MAX(12,'0. Assumptions'!$B$21)),"") -> 3432 | H8: =IFERROR(IF(D8="","",C8*$B$16),"") -> 2 | I8: =IFERROR(IF(D8="","",H8*B8*$B$17),"") -> 200 | J8: Barbacks hired by the hour as W-2 employees: loading, ice, setup and breakdown at larger events. Paid at or above the pay floor in proportion to FTE.
A9: TOTAL STAFF | B9: =IFERROR(IF(COUNT(D5:D8)=0,"",SUM(B5:B8)),"") -> 9 | C9: =IFERROR(IF(COUNT(D5:D8)=0,"",SUMPRODUCT(B5:B8,C5:C8)),"") -> 1.85 | D9: =IFERROR(IF(COUNT(D5:D8)=0,"",SUM(D5:D8)),"") -> 5937 | E9: =IFERROR(IF(COUNT(D5:D8)=0,"",SUM(E5:E8)),"") -> 593.7 | F9: =IFERROR(IF(COUNT(D5:D8)=0,"",SUM(F5:F8)),"") -> 6530.7 | G9: =IFERROR(IF(COUNT(D5:D8)=0,"",SUM(G5:G8)),"") -> 78368.4 | I9: =IFERROR(IF(COUNT(D5:D8)=0,"",SUM(I5:I8)),"") -> 3700
A10: STAFF GROWTH (stepped cost)
A11: Annual cost of year-2 hires | B11: 3000 | J11: FULL ANNUAL cost (gross pay + employer payroll taxes, over all pay periods) of whoever you hire that year. The P&L adds it to the previous year's cost: staffing grows by people, not by a percentage
A12: Annual cost of year-3 hires | B12: 3000 | J12: FULL ANNUAL cost (gross pay + employer payroll taxes, over all pay periods) of whoever you hire that year. The P&L adds it to the previous year's cost: staffing grows by people, not by a percentage
A13: Labor cost, year 2 | B13: =IFERROR(IF(G9="","",G9*(1+'0. Assumptions'!$B$48)+B11),"") -> 81368.4
A14: Labor cost, year 3 | B14: =IFERROR(IF(B13="","",B13*(1+'0. Assumptions'!$B$48)+B12),"") -> 84368.4
A15: COVERAGE OF EVENT HOURS
A16: Full-time week (hours per week) | B16: 40 | J16: 40 hours a week is the FLSA overtime threshold for non-exempt employees; some states add daily overtime rules. Change it if your own full-time week is different
A17: Weeks worked per year per person | B17: 50 | J17: 50 weeks: 52 minus about two weeks of vacation, holidays and average absences. There is no federal vacation requirement in the US: adjust it to your own policy
A18: Hours per person per event (prep, loading, travel, setup, service, breakdown) | B18: 8 | J18: Hours of work that one event needs: shopping, packing, loading, transport, setup, service, breakdown and cleanup. Serving is only part of it. Hours × people × events per year sets the event staff cost.
A19: People per event (bartenders and barbacks, average) | B19: 2.2 | J19: Average number of people working each event. A large wedding needs more hands: raise it here and the staffing sizes itself.
A20: Event hours to cover per year | B20: =IFERROR(IF(OR(B18="",B19="",'0. Assumptions'!$B$4=""),"",B18*B19*'0. Assumptions'!$B$4),"") -> 2816
A21: Hours hired per year | B21: =IFERROR(IF(I9="","",I9),"") -> 3700
A22: Coverage (hired / needed) | B22: =IFERROR(B21/B20,"") -> 1.3139205 | J22: Below 100% the staff cannot cover the hours the plan declares: either hire more or cut the hours
A24: Columns D-G are TOTALS for the row. Event bartenders and barbacks are hourly W-2 employees with payroll taxes and workers' comp: paying them as 1099 contractors is a misclassification risk (FLSA; California AB5). Tips belong to the staff: the employer keeps none of them (FLSA).
A25: The pay floor is the HIGHER of the federal minimum wage and your state / local minimum wage, both in the "0. Assumptions" tab; part-time positions get it in proportion. There is no single national table above the federal floor: the state / local cell is delivered empty so you can enter the rate for your state and city.

Sheet Instructions
A1: HOW TO USE THIS WORKBOOK — Mobile Bar Financial Projections
A3: HOW TO USE THIS WORKBOOK
A4: This financial plan is a MODEL: you type only in the GREEN cells and everything else recalculates on its own.
A5: 1. "0. Assumptions" is the control sheet: events per year, price per guest excl. sales tax, guests per event, the bar package and add-on mix, cost of goods sold, storage and trailer parking, financing and taxes.
A6: 2. Startup cost items, fixed costs and staffing are typed in their own tab, also in green. No number is typed twice.
A7: 3. Only "Break-Even" is derived entirely from the rest. The other three tabs also have green cells you can edit: the pessimistic and optimistic scenarios in "Scenarios", seasonality and the launch ramp-up in "12-Month Cash Flow", and the other funding sources in "Financing" (rows 8-11 count as sources but are not amortized: your bank or SBA 7(a) loan goes in "Loan requested" on "0. Assumptions"). Everything else is calculated.
A8: 4. All figures are EXCL. SALES TAX. To turn a quoted price into a price excl. sales tax, divide it by 1 + your sales tax rate (with an 8% rate, divide by 1.08); if an item is taxed at a different rate in your state, use that rate. Sales tax on services varies by state: in some, the whole bar package invoice is taxable, including bartender labor and rentals; check yours. The rate of each sales line is in the "Sales tax rate on the line (%)" column of the P&L, and from it come the receipts, the sales tax collected and the equivalent price per guest incl. sales tax. With the default 0% recoverable input tax, the sales tax you pay on purchases and startup costs is treated as a cost; in the UK, enter 20% if you are VAT-registered.
A9: 5. If you change the staffing, the P&L reads it on its own: labor cost comes from the "Staffing" tab, not from a separate estimate.
A10: 6. The "12-Month Cash Flow" tab answers the question that decides a bank deal: in which month the cash runs out. The minimum balance of the year can never be in red.
A11: 7. The "Financing" tab matches what you need with what you put in and builds the amortization schedule of the loan. If the difference is red, the plan is not funded.
A12: 8. The Word business plan in this kit uses the same example figures as this workbook. The workbook is the one that recalculates on its own when you change a green cell: if you change one, update the matching figures in the Word document.
A14: RATIOS AUDITED BY THIS WORKBOOK
A15: Thresholds live in the "Threshold" column of the KEY RATIOS block of the P&L: change them there and the traffic light changes with them.
A17: Ratio | B17: Year 1 value | C17: Threshold | D17: Status
A18: Cost of goods sold / Sales | B18: =IFERROR(IF('3-Year P&L'!$B$53="","",'3-Year P&L'!$B$53),"") -> 0.1915 | C18: =IFERROR(IF('3-Year P&L'!$E$53="","",'3-Year P&L'!$E$53),"") -> 0.26 | D18: =IFERROR(IF(OR(B18="",C18=""),"",IF(B18<=C18,"OK","REVIEW")),"") -> OK
A19: Labor cost / Sales | B19: =IFERROR(IF('3-Year P&L'!$B$54="","",'3-Year P&L'!$B$54),"") -> 0.36827256 | C19: =IFERROR(IF('3-Year P&L'!$E$54="","",'3-Year P&L'!$E$54),"") -> 0.4 | D19: =IFERROR(IF(OR(B19="",C19=""),"",IF(B19<=C19,"OK","REVIEW")),"") -> OK
A20: Storage & parking / Sales | B20: =IFERROR(IF('3-Year P&L'!$B$55="","",'3-Year P&L'!$B$55),"") -> 0.033834586 | C20: =IFERROR(IF('3-Year P&L'!$E$55="","",'3-Year P&L'!$E$55),"") -> 0.06 | D20: =IFERROR(IF(OR(B20="",C20=""),"",IF(B20<=C20,"OK","REVIEW")),"") -> OK
A21: Net income / Sales | B21: =IFERROR(IF('3-Year P&L'!$B$56="","",'3-Year P&L'!$B$56),"") -> 0.088300618 | C21: =IFERROR(IF('3-Year P&L'!$E$56="","",'3-Year P&L'!$E$56),"") -> 0.05 | D21: =IFERROR(IF(OR(B21="",C21=""),"",IF(B21>=C21,"OK","REVIEW")),"") -> OK
A22: Gross margin / Sales | B22: =IFERROR(IF('3-Year P&L'!$B$51="","",'3-Year P&L'!$B$51),"") -> 0.6985 | C22: =IFERROR(IF('3-Year P&L'!$E$51="","",'3-Year P&L'!$E$51),"") -> 0.65 | D22: =IFERROR(IF(OR(B22="",C22=""),"",IF(B22>=C22,"OK","REVIEW")),"") -> OK
A24: THIS PLAN'S KEY FIGURES
A25: Total startup costs (sum of the blocks) | B25: =IFERROR(IF('Startup Costs'!$B$26="","",'Startup Costs'!$B$26),"") -> 76972.1
A26: Total cash needed at launch | B26: =IFERROR(IF('Startup Costs'!$B$29="","",'Startup Costs'!$B$29),"") -> 76972.1
A27: Working capital funded | B27: =IFERROR(IF('Startup Costs'!$B$25="","",'Startup Costs'!$B$25),"") -> 29442.1
A28: Forecast year-1 revenue | B28: =IFERROR(IF('3-Year P&L'!$B$9="","",'3-Year P&L'!$B$9),"") -> 212800
A29: Year-1 net income | B29: =IFERROR(IF('3-Year P&L'!$B$48="","",'3-Year P&L'!$B$48),"") -> 18790.371
A30: Events per year for the ACCOUNTING break-even (depreciation included) | B30: =IFERROR(IF('Break-Even'!$B$15="","",'Break-Even'!$B$15),"") -> 133.03155
A31: Project payback (years), before debt | B31: =IFERROR(IF('12-Month Cash Flow'!$B$31="","",'12-Month Cash Flow'!$B$31),"") -> 2.2
A33: WHY THIS MODEL IS BUILT THIS WAY
A34: Item | B34: Common shortcut | C34: This workbook | D34: Why
A35: Labor cost in the P&L | B35: A typed-in number that does not match the Staffing tab | C35: Read directly from the Staffing tab | D35: If you change a salary, the whole plan recalculates, so the P&L and the staffing table can never disagree.
A36: Staffing | B36: One line called "staff", with no link to event hours or pay floors | C36: Positions with their FTE, sized to the hours your events need, with event staff paid per event | D36: A plan staffed for fewer hours than it sells does not work on its own numbers. This layout makes that gap visible before a lender does.
A37: Events, guests and price | B37: Sales typed as one lump sum, with no link to bookings | C37: Revenue = events per year × guests per event × price per guest, one cell each for the whole workbook | D37: Break-even, scenarios and the P&L read the same three cells, so they always agree, and you can see which lever moves the result: more events, bigger events or a higher price.
A38: Price per guest | B38: A price with no statement of whether sales tax or service is included | C38: Declared EXCL. sales tax, with service included and the voluntary gratuity left out | D38: Declaring it changes no number: it just says what the number is. Price per guest incl. sales tax = price per guest × (1 + sales tax rate), and the workbook calculates it for you.
A39: Storage unit and trailer parking | B39: Left out: the model shows no cost of space | C39: A monthly storage and trailer parking cost, plus a deposit and rent for the months before opening | D39: A mobile bar has no premises, but the bar, the glassware and the trailer have to live somewhere between events. Leaving it out makes the business look like it has no occupancy cost.
A40: Working capital | B40: A round number labeled "3 months" that does not match the fixed costs | C40: Three months of cash fixed costs, calculated by formula | D40: A round number often covers far less than the label says. This cushion is what keeps you open through a slow month between wedding seasons.
A41: Depreciation | B41: One useful life for everything, including items that are not fixed assets | C41: Two useful lives: the bar trailer with its conversion, generator and storage fit-out, and the portable bar with the tools and glassware. The Startup Costs tab calculates the annual charge. | D41: The trailer and the bar equipment wear out at different speeds. Working capital, opening inventory and launch marketing are not fixed assets, so they are not depreciated.
A42: Insurance and liquor liability | B42: Counted twice: once in startup costs and again as an annual expense | C42: Counted once, as an annual expense | D42: Counting a premium in both places inflates the startup costs, the cash you need to raise and the loan you ask for.
A43: Storage power and water | B43: A separate line, on top of utilities | C43: Included in the utilities cell | D43: Writing it in two places counts it twice: here it lives in one cell and the rest of the workbook follows.
A44: Startup contingency | B44: A lump sum typed by hand | C44: A percentage calculated on the trailer, conversion, generator, storage fit-out and inspection lines | D44: If you change the trailer price, the contingency recalculates instead of staying at the old amount.
A45: Income tax | B45: A flat rate every year, with no offset for losses | C45: One effective rate for years 1-2 and another from year 3, offsetting net operating losses carried forward | D45: A loss in one year reduces taxable profit in later years. The model offsets losses fully as a simplification (federal rules cap the offset at 80% of taxable income). If you operate as a pass-through (sole proprietorship or LLC), set the rate to 0 and budget your personal tax separately.
... A51: Wages and minimum wage | B51: Wages never compared with any legal floor | C51: No row below the pay floor in proportion to its FTE, and a cell for your state or local minimum wage | D51: State and local minimums are often higher than the federal one: enter yours in "0. Assumptions" and the traffic light warns you when a wage falls short.
A53: US MOBILE BAR BENCHMARKS (sourced) AND KIT ESTIMATES
A54: Benchmark | B54: Value | C54: Source | D54: Note
A55: Price per event (median; excl. alcohol and tips) | B55: $750 median; middle 50% $450-$1,275; mean $1,173 | C55: checkcherry.com | D55: 1,334 bookings since January 2024. Compare it with your price per guest × guests per event in "0. Assumptions".
A56: Price by guest count | B56: Up to 50 guests $575 · 51-100 $700 · 101-150 $1,063 · 151+ $1,438 | C56: checkcherry.com | D56: The typical event runs about 80 guests.
A57: Price by event length | B57: Up to 3 h $575 · 4 h $675 · 5 h $898 · 6+ h $1,275 | C57: checkcherry.com | D57: Longer events cost more but less per hour: use it to set your extra-hour rate.
A58: Bartender-only service (dry hire, no bar) | B58: $375 for about 4 h, or about $75-$120 per bartender hour | C58: checkcherry.com | D58: The floor of dry hire pricing: a quick check for your hourly rate.
A59: Deposit and travel fee | B59: Deposit about 30%; 26% of bookings charge a travel fee (median 36 miles; free up to about 25) | C59: checkcherry.com | D59: Set your travel fee as an add-on, and ask for the deposit to secure the date.
A60: Seasonality and calendar | B60: October about 13% and May 12.4% of bookings; January 3.8%; median lead time 62 days; 85% Friday to Sunday | C60: checkcherry.com | D60: Peak wedding season (May-June, September-October) is where the Saturday bottleneck of your two crews shows. Shape the ramp in "12-Month Cash Flow" around it.
A61: First year in business (12+ months of activity) | B61: Median 3 events and $1,650; top 10% about 39 events and $35,500 | C61: checkcherry.com | D61: The kit example is a fully built operation with two crews. The ramp in "0. Assumptions" and the pessimistic scenario show what a slower start does to your cash.
A62: Drinks per guest | B62: 2 in the first hour, then 1 per hour | C62: eventplanning.com | D62: Use it to size mixers, ice and cups, and to check how many guests one bartender can serve.
A63: Bartender ratio | B63: 1 per 50 guests (full bar); 1 per 75 (beer and wine) | C63: Kit estimate | D63: Drives the people per event in "Staffing". Add a barback for larger setups.
A64: Bartender wage (BLS, May 2025) | B64: Mean $19.61 per hour; median $16.51 (includes tips) | C64: bls.gov | D64: BLS Occupational Employment and Wage Statistics, code 35-3011. Compare with the hourly rate in "Staffing" and with your state minimum wage.
A65: Marketplace commission | B65: GigSalad 5% (free plan) or 2.5% (paid plan) of the confirmed booking; nothing per lead | C65: gigsalad.com | D65: Thumbtack charges per lead instead. Fees change: check before you sign up.
... A68: Ice, mixers and garnish | B68: Ice 1.5 lb (0.68 kg) per guest; mixers, garnish and ice about $2.25 per guest | C68: Kit estimate | D68: Use it to check the cost of goods sold rate on bar packages. The real figure depends on your drink menu.
A70: To edit a cell that is not green: Review → Unprotect Sheet (there is no password).
A71: More templates and kits in the catalog at aichef.pro/en/digital-products
A72: Designed by John Guerrero — chef and restaurant consultant since 2010, in the kitchen since age 17 · johnguerrero.es
A73: Version 2.2 · October 2026 · aichef.pro/en/digital-products/mobile-bar-business-plan · info@aichef.pro
A74: Planning tool, not financial, tax or legal advice. Requirements vary by state, county and city — check with your accountant and local authorities.

Sheet 12-Month Cash Flow
A1: CASH FLOW FORECAST — YEAR 1
A2: The P&L tells you whether the business makes money; this tab tells you whether you have cash left to get to the end of the month. It is the first one a lender looks at.
A4: Item | B4: Month 1 | C4: Month 2 | D4: Month 3 | E4: Month 4 | F4: Month 5 | G4: Month 6 | H4: Month 7 | I4: Month 8 | J4: Month 9 | K4: Month 10 | L4: Month 11 | M4: Month 12 | N4: Year
A5: Monthly seasonality (adds up to 100%) | B5: 0.075 | C5: 0.105 | D5: 0.124 | E5: 0.09 | F5: 0.056 | G5: 0.065 | H5: 0.115 | I5: 0.13 | J5: 0.085 | K5: 0.075 | L5: 0.038 | M5: 0.042 | N5: =IFERROR(IF('3-Year P&L'!$B$9="","",SUM(B5:M5)),"") -> 1 | O5: Share of the year's events per month (100% in total). Month 1 = opening month (March in the example). The 30% deposit is not modeled: it improves real cash.
A6: Launch ramp-up (% of steady-state activity) | B6: =IFERROR(IF('3-Year P&L'!$B$9="","",MIN(1,'0. Assumptions'!$B$52+(1-'0. Assumptions'!$B$52)*0/MAX(1,'0. Assumptions'!$B$53-1))),"") -> 0.45 | C6: =IFERROR(IF('3-Year P&L'!$B$9="","",MIN(1,'0. Assumptions'!$B$52+(1-'0. Assumptions'!$B$52)*1/MAX(1,'0. Assumptions'!$B$53-1))),"") -> 0.51875 | D6: =IFERROR(IF('3-Year P&L'!$B$9="","",MIN(1,'0. Assumptions'!$B$52+(1-'0. Assumptions'!$B$52)*2/MAX(1,'0. Assumptions'!$B$53-1))),"") -> 0.5875 | E6: =IFERROR(IF('3-Year P&L'!$B$9="","",MIN(1,'0. Assumptions'!$B$52+(1-'0. Assumptions'!$B$52)*3/MAX(1,'0. Assumptions'!$B$53-1))),"") -> 0.65625 | F6: =IFERROR(IF('3-Year P&L'!$B$9="","",MIN(1,'0. Assumptions'!$B$52+(1-'0. Assumptions'!$B$52)*4/MAX(1,'0. Assumptions'!$B$53-1))),"") -> 0.725 | G6: =IFERROR(IF('3-Year P&L'!$B$9="","",MIN(1,'0. Assumptions'!$B$52+(1-'0. Assumptions'!$B$52)*5/MAX(1,'0. Assumptions'!$B$53-1))),"") -> 0.79375 | H6: =IFERROR(IF('3-Year P&L'!$B$9="","",MIN(1,'0. Assumptions'!$B$52+(1-'0. Assumptions'!$B$52)*6/MAX(1,'0. Assumptions'!$B$53-1))),"") -> 0.8625 | I6: =IFERROR(IF('3-Year P&L'!$B$9="","",MIN(1,'0. Assumptions'!$B$52+(1-'0. Assumptions'!$B$52)*7/MAX(1,'0. Assumptions'!$B$53-1))),"") -> 0.93125 | J6: =IFERROR(IF('3-Year P&L'!$B$9="","",MIN(1,'0. Assumptions'!$B$52+(1-'0. Assumptions'!$B$52)*8/MAX(1,'0. Assumptions'!$B$53-1))),"") -> 1 | K6: =IFERROR(IF('3-Year P&L'!$B$9="","",MIN(1,'0. Assumptions'!$B$52+(1-'0. Assumptions'!$B$52)*9/MAX(1,'0. Assumptions'!$B$53-1))),"") -> 1 | L6: =IFERROR(IF('3-Year P&L'!$B$9="","",MIN(1,'0. Assumptions'!$B$52+(1-'0. Assumptions'!$B$52)*10/MAX(1,'0. Assumptions'!$B$53-1))),"") -> 1 | M6: =IFERROR(IF('3-Year P&L'!$B$9="","",MIN(1,'0. Assumptions'!$B$52+(1-'0. Assumptions'!$B$52)*11/MAX(1,'0. Assumptions'!$B$53-1))),"") -> 1 | O6: Rises in a straight line from the month-1 percentage to 100% over the number of months you set in Assumptions. With month 1 at 100%, the ramp disappears
A7: Split of activity by month (calculated) | B7: =IFERROR(IF('3-Year P&L'!$B$9="","",B5*B6/SUMPRODUCT($B$5:$M$5,$B$6:$M$6)),"") -> 0.043685079 | C7: =IFERROR(IF('3-Year P&L'!$B$9="","",C5*C6/SUMPRODUCT($B$5:$M$5,$B$6:$M$6)),"") -> 0.070502864 | D7: =IFERROR(IF('3-Year P&L'!$B$9="","",D5*D6/SUMPRODUCT($B$5:$M$5,$B$6:$M$6)),"") -> 0.094295052 | E7: =IFERROR(IF('3-Year P&L'!$B$9="","",E5*E6/SUMPRODUCT($B$5:$M$5,$B$6:$M$6)),"") -> 0.076448888 | F7: =IFERROR(IF('3-Year P&L'!$B$9="","",F5*F6/SUMPRODUCT($B$5:$M$5,$B$6:$M$6)),"") -> 0.052551532 | G7: =IFERROR(IF('3-Year P&L'!$B$9="","",G5*G6/SUMPRODUCT($B$5:$M$5,$B$6:$M$6)),"") -> 0.066781542 | H7: =IFERROR(IF('3-Year P&L'!$B$9="","",H5*H6/SUMPRODUCT($B$5:$M$5,$B$6:$M$6)),"") -> 0.12838559 | I7: =IFERROR(IF('3-Year P&L'!$B$9="","",I5*I6/SUMPRODUCT($B$5:$M$5,$B$6:$M$6)),"") -> 0.1567 | ... M7: =IFERROR(IF('3-Year P&L'!$B$9="","",M5*M6/SUMPRODUCT($B$5:$M$5,$B$6:$M$6)),"") -> 0.054363654 | N7: =IFERROR(IF('3-Year P&L'!$B$9="","",SUM(B7:M7)),"") -> 1 | O7: Seasonality × ramp-up, normalized to 100%: the YEAR brings in what the P&L says, but split the way a business that has just opened would split it
A8: CASH IN
A9: Sales collected (incl. sales tax collected) | B9: =IFERROR(IF('3-Year P&L'!$B$9="","",('3-Year P&L'!$B$9+'3-Year P&L'!$B$9*SUMPRODUCT('3-Year P&L'!$E$10:$E$11,'3-Year P&L'!$G$10:$G$11))*B7*(1-MIN(30,'0. Assumptions'!$B$58)/30)),"") -> 9705.217 | C9: =IFERROR(IF('3-Year P&L'!$B$9="","",('3-Year P&L'!$B$9+'3-Year P&L'!$B$9*SUMPRODUCT('3-Year P&L'!$E$10:$E$11,'3-Year P&L'!$G$10:$G$11))*(C7*(1-MIN(30,'0. Assumptions'!$B$58)/30)+B7*MIN(30,'0. Assumptions'!$B$58)/30)),"") -> 15997.804 | D9: =IFERROR(IF('3-Year P&L'!$B$9="","",('3-Year P&L'!$B$9+'3-Year P&L'!$B$9*SUMPRODUCT('3-Year P&L'!$E$10:$E$11,'3-Year P&L'!$G$10:$G$11))*(D7*(1-MIN(30,'0. Assumptions'!$B$58)/30)+C7*MIN(30,'0. Assumptions'!$B$58)/30)),"") -> 21488.999 | E9: =IFERROR(IF('3-Year P&L'!$B$9="","",('3-Year P&L'!$B$9+'3-Year P&L'!$B$9*SUMPRODUCT('3-Year P&L'!$E$10:$E$11,'3-Year P&L'!$G$10:$G$11))*(E7*(1-MIN(30,'0. Assumptions'!$B$58)/30)+D7*MIN(30,'0. Assumptions'!$B$58)/30)),"") -> 17706.505 | F9: =IFERROR(IF('3-Year P&L'!$B$9="","",('3-Year P&L'!$B$9+'3-Year P&L'!$B$9*SUMPRODUCT('3-Year P&L'!$E$10:$E$11,'3-Year P&L'!$G$10:$G$11))*(F7*(1-MIN(30,'0. Assumptions'!$B$58)/30)+E7*MIN(30,'0. Assumptions'!$B$58)/30)),"") -> 12260.676 | G9: =IFERROR(IF('3-Year P&L'!$B$9="","",('3-Year P&L'!$B$9+'3-Year P&L'!$B$9*SUMPRODUCT('3-Year P&L'!$E$10:$E$11,'3-Year P&L'!$G$10:$G$11))*(G7*(1-MIN(30,'0. Assumptions'!$B$58)/30)+F7*MIN(30,'0. Assumptions'!$B$58)/30)),"") -> 15238.988 | H9: =IFERROR(IF('3-Year P&L'!$B$9="","",('3-Year P&L'!$B$9+'3-Year P&L'!$B$9*SUMPRODUCT('3-Year P&L'!$E$10:$E$11,'3-Year P&L'!$G$10:$G$11))*(H7*(1-MIN(30,'0. Assumptions'!$B$58)/30)+G7*MIN(30,'0. Assumptions'!$B$58)/30)),"") -> 29034.154 | I9: =IFERROR(IF('3-Year P&L'!$B$9="","",('3-Year P&L'!$B$9+'3-Year P&L'!$B$9*SUMPRODUCT('3-Year P&L'!$E$10:$E$11,'3-Year P&L'!$G$10:$G$11))*(I7*(1-MIN(30,'0. Assumptions'!$B$58)/30)+H7*MIN(30,'0. Assumptions'!$B$58)/30)),"") -> 35796.509 | J9: =IFERROR(IF('3-Year P&L'!$B$9="","",('3-Year P&L'!$B$9+'3-Year P&L'!$B$9*SUMPRODUCT('3-Year P&L'!$E$10:$E$11,'3-Year P&L'!$G$10:$G$11))*(J7*(1-MIN(30,'0. Assumptions'!$B$58)/30)+I7*MIN(30,'0. Assumptions'!$B$58)/30)),"") -> 25643.216 | ... M9: =IFERROR(IF('3-Year P&L'!$B$9="","",('3-Year P&L'!$B$9+'3-Year P&L'!$B$9*SUMPRODUCT('3-Year P&L'!$E$10:$E$11,'3-Year P&L'!$G$10:$G$11))*(M7*(1-MIN(30,'0. Assumptions'!$B$58)/30)+L7*MIN(30,'0. Assumptions'!$B$58)/30)),"") -> 12454.409 | N9: =IFERROR(IF('3-Year P&L'!$B$9="","",SUM(B9:M9)),"") -> 229407.53 | O9: The month's sales plus the sales tax collected, adjusted by the average collection days from the Assumptions tab
A10: CASH OUT
A11: Purchases and variable costs (incl. sales tax) | B11: =IFERROR(IF('3-Year P&L'!$B$9="","",-('3-Year P&L'!$B$13*(1+'3-Year P&L'!$G$13)+'3-Year P&L'!$B$14*(1+'3-Year P&L'!$G$14)+'3-Year P&L'!$B$15*(1+'3-Year P&L'!$G$15)+'3-Year P&L'!$B$16*(1+'3-Year P&L'!$G$16)+'3-Year P&L'!$B$17*(1+'3-Year P&L'!$G$17)+'3-Year P&L'!$B$18*(1+'3-Year P&L'!$G$18))*B7*(1-MIN(30,'0. Assumptions'!$B$59)/30)),"") -> -2148.8131 | C11: =IFERROR(IF('3-Year P&L'!$B$9="","",-('3-Year P&L'!$B$13*(1+'3-Year P&L'!$G$13)+'3-Year P&L'!$B$14*(1+'3-Year P&L'!$G$14)+'3-Year P&L'!$B$15*(1+'3-Year P&L'!$G$15)+'3-Year P&L'!$B$16*(1+'3-Year P&L'!$G$16)+'3-Year P&L'!$B$17*(1+'3-Year P&L'!$G$17)+'3-Year P&L'!$B$18*(1+'3-Year P&L'!$G$18))*(C7*(1-MIN(30,'0. Assumptions'!$B$59)/30)+B7*MIN(30,'0. Assumptions'!$B$59)/30)),"") -> -4121.9322 | D11: =IFERROR(IF('3-Year P&L'!$B$9="","",-('3-Year P&L'!$B$13*(1+'3-Year P&L'!$G$13)+'3-Year P&L'!$B$14*(1+'3-Year P&L'!$G$14)+'3-Year P&L'!$B$15*(1+'3-Year P&L'!$G$15)+'3-Year P&L'!$B$16*(1+'3-Year P&L'!$G$16)+'3-Year P&L'!$B$17*(1+'3-Year P&L'!$G$17)+'3-Year P&L'!$B$18*(1+'3-Year P&L'!$G$18))*(D7*(1-MIN(30,'0. Assumptions'!$B$59)/30)+C7*MIN(30,'0. Assumptions'!$B$59)/30)),"") -> -5693.7146 | E11: =IFERROR(IF('3-Year P&L'!$B$9="","",-('3-Year P&L'!$B$13*(1+'3-Year P&L'!$G$13)+'3-Year P&L'!$B$14*(1+'3-Year P&L'!$G$14)+'3-Year P&L'!$B$15*(1+'3-Year P&L'!$G$15)+'3-Year P&L'!$B$16*(1+'3-Year P&L'!$G$16)+'3-Year P&L'!$B$17*(1+'3-Year P&L'!$G$17)+'3-Year P&L'!$B$18*(1+'3-Year P&L'!$G$18))*(E7*(1-MIN(30,'0. Assumptions'!$B$59)/30)+D7*MIN(30,'0. Assumptions'!$B$59)/30)),"") -> -5172.0652 | F11: =IFERROR(IF('3-Year P&L'!$B$9="","",-('3-Year P&L'!$B$13*(1+'3-Year P&L'!$G$13)+'3-Year P&L'!$B$14*(1+'3-Year P&L'!$G$14)+'3-Year P&L'!$B$15*(1+'3-Year P&L'!$G$15)+'3-Year P&L'!$B$16*(1+'3-Year P&L'!$G$16)+'3-Year P&L'!$B$17*(1+'3-Year P&L'!$G$17)+'3-Year P&L'!$B$18*(1+'3-Year P&L'!$G$18))*(F7*(1-MIN(30,'0. Assumptions'!$B$59)/30)+E7*MIN(30,'0. Assumptions'!$B$59)/30)),"") -> -3729.4192 | G11: =IFERROR(IF('3-Year P&L'!$B$9="","",-('3-Year P&L'!$B$13*(1+'3-Year P&L'!$G$13)+'3-Year P&L'!$B$14*(1+'3-Year P&L'!$G$14)+'3-Year P&L'!$B$15*(1+'3-Year P&L'!$G$15)+'3-Year P&L'!$B$16*(1+'3-Year P&L'!$G$16)+'3-Year P&L'!$B$17*(1+'3-Year P&L'!$G$17)+'3-Year P&L'!$B$18*(1+'3-Year P&L'!$G$18))*(G7*(1-MIN(30,'0. Assumptions'!$B$59)/30)+F7*MIN(30,'0. Assumptions'!$B$59)/30)),"") -> -4071.6202 | H11: =IFERROR(IF('3-Year P&L'!$B$9="","",-('3-Year P&L'!$B$13*(1+'3-Year P&L'!$G$13)+'3-Year P&L'!$B$14*(1+'3-Year P&L'!$G$14)+'3-Year P&L'!$B$15*(1+'3-Year P&L'!$G$15)+'3-Year P&L'!$B$16*(1+'3-Year P&L'!$G$16)+'3-Year P&L'!$B$17*(1+'3-Year P&L'!$G$17)+'3-Year P&L'!$B$18*(1+'3-Year P&L'!$G$18))*(H7*(1-MIN(30,'0. Assumptions'!$B$59)/30)+G7*MIN(30,'0. Assumptions'!$B$59)/30)),"") -> -7314.8748 | I11: =IFERROR(IF('3-Year P&L'!$B$9="","",-('3-Year P&L'!$B$13*(1+'3-Year P&L'!$G$13)+'3-Year P&L'!$B$14*(1+'3-Year P&L'!$G$14)+'3-Year P&L'!$B$15*(1+'3-Year P&L'!$G$15)+'3-Year P&L'!$B$16*(1+'3-Year P&L'!$G$16)+'3-Year P&L'!$B$17*(1+'3-Year P&L'!$G$17)+'3-Year P&L'!$B$18*(1+'3-Year P&L'!$G$18))*(I7*(1-MIN(30,'0. Assumptions'!$B$59)/30)+H7*MIN(30,'0. Assumptions'!$B$59)/30)),"") -> -9629.8662 | J11: =IFERROR(IF('3-Year P&L'!$B$9="","",-('3-Year P&L'!$B$13*(1+'3-Year P&L'!$G$13)+'3-Year P&L'!$B$14*(1+'3-Year P&L'!$G$14)+'3-Year P&L'!$B$15*(1+'3-Year P&L'!$G$15)+'3-Year P&L'!$B$16*(1+'3-Year P&L'!$G$16)+'3-Year P&L'!$B$17*(1+'3-Year P&L'!$G$17)+'3-Year P&L'!$B$18*(1+'3-Year P&L'!$G$18))*(J7*(1-MIN(30,'0. Assumptions'!$B$59)/30)+I7*MIN(30,'0. Assumptions'!$B$59)/30)),"") -> -7757.6998 | ... M11: =IFERROR(IF('3-Year P&L'!$B$9="","",-('3-Year P&L'!$B$13*(1+'3-Year P&L'!$G$13)+'3-Year P&L'!$B$14*(1+'3-Year P&L'!$G$14)+'3-Year P&L'!$B$15*(1+'3-Year P&L'!$G$15)+'3-Year P&L'!$B$16*(1+'3-Year P&L'!$G$16)+'3-Year P&L'!$B$17*(1+'3-Year P&L'!$G$17)+'3-Year P&L'!$B$18*(1+'3-Year P&L'!$G$18))*(M7*(1-MIN(30,'0. Assumptions'!$B$59)/30)+L7*MIN(30,'0. Assumptions'!$B$59)/30)),"") -> -3410.419 | N11: =IFERROR(IF('3-Year P&L'!$B$9="","",SUM(B11:M11)),"") -> -63345.35 | O11: =IFERROR("Mixers, garnishes, ice, disposables, fees and contingencies, each at ITS tax rate (column G of the P&L; 0 in the US, where the sales tax you pay is part of the cost) and with the supplier payment days from ""0. Assumptions""."&IF('0. Assumptions'!$B$59=0,""," With "&TEXT('0. Assumptions'!$B$59,"0")&" payment days, the last purchases of the year are paid next year: the ""Year"" column of this row holds "&TEXT(MAX(0,12-ROUNDUP('0. Assumptions'!$B$59/30,0)),"0")&" months of purchases, not the year's cost."),"") -> Mixers, garnishes, ice, disposables, fees and contingencies, each at ITS tax rate (column G of the P&L; 0 in the US, where the sales tax you pay is part of the cost) and with the supplier payment days from "0. Assumptions". With 7 payment days, the last purchases of the year are paid next year: the "Year" column of this row holds 11 months of purchases, not the year's cost.
A12: Operating fixed costs (incl. sales tax) | B12: =IFERROR(IF('3-Year P&L'!$B$9="","",-('3-Year P&L'!$B$38-'3-Year P&L'!$B$23-'3-Year P&L'!$B$36-'3-Year P&L'!$B$37+'3-Year P&L'!$B$40)/12),"") -> -2875 | C12: =IFERROR(IF('3-Year P&L'!$B$9="","",-('3-Year P&L'!$B$38-'3-Year P&L'!$B$23-'3-Year P&L'!$B$36-'3-Year P&L'!$B$37+'3-Year P&L'!$B$40)/12),"") -> -2875 | D12: =IFERROR(IF('3-Year P&L'!$B$9="","",-('3-Year P&L'!$B$38-'3-Year P&L'!$B$23-'3-Year P&L'!$B$36-'3-Year P&L'!$B$37+'3-Year P&L'!$B$40)/12),"") -> -2875 | E12: =IFERROR(IF('3-Year P&L'!$B$9="","",-('3-Year P&L'!$B$38-'3-Year P&L'!$B$23-'3-Year P&L'!$B$36-'3-Year P&L'!$B$37+'3-Year P&L'!$B$40)/12),"") -> -2875 | F12: =IFERROR(IF('3-Year P&L'!$B$9="","",-('3-Year P&L'!$B$38-'3-Year P&L'!$B$23-'3-Year P&L'!$B$36-'3-Year P&L'!$B$37+'3-Year P&L'!$B$40)/12),"") -> -2875 | G12: =IFERROR(IF('3-Year P&L'!$B$9="","",-('3-Year P&L'!$B$38-'3-Year P&L'!$B$23-'3-Year P&L'!$B$36-'3-Year P&L'!$B$37+'3-Year P&L'!$B$40)/12),"") -> -2875 | H12: =IFERROR(IF('3-Year P&L'!$B$9="","",-('3-Year P&L'!$B$38-'3-Year P&L'!$B$23-'3-Year P&L'!$B$36-'3-Year P&L'!$B$37+'3-Year P&L'!$B$40)/12),"") -> -2875 | I12: =IFERROR(IF('3-Year P&L'!$B$9="","",-('3-Year P&L'!$B$38-'3-Year P&L'!$B$23-'3-Year P&L'!$B$36-'3-Year P&L'!$B$37+'3-Year P&L'!$B$40)/12),"") -> -2875 | ... M12: =IFERROR(IF('3-Year P&L'!$B$9="","",-('3-Year P&L'!$B$38-'3-Year P&L'!$B$23-'3-Year P&L'!$B$36-'3-Year P&L'!$B$37+'3-Year P&L'!$B$40)/12),"") -> -2875 | N12: =IFERROR(IF('3-Year P&L'!$B$9="","",SUM(B12:M12)),"") -> -34500 | O12: The fixed costs that leave cash, each with its own tax rate: insurance carries none
A13: Payroll and employer payroll taxes | B13: =IFERROR(IF('3-Year P&L'!$B$9="","",-'3-Year P&L'!$B$23/MAX(12,'0. Assumptions'!$B$21)*(1+IF(1='0. Assumptions'!$B$60,(MAX(12,'0. Assumptions'!$B$21)-12)/2,0)+IF(1='0. Assumptions'!$B$61,(MAX(12,'0. Assumptions'!$B$21)-12)/2,0))),"") -> -6530.7 | C13: =IFERROR(IF('3-Year P&L'!$B$9="","",-'3-Year P&L'!$B$23/MAX(12,'0. Assumptions'!$B$21)*(1+IF(2='0. Assumptions'!$B$60,(MAX(12,'0. Assumptions'!$B$21)-12)/2,0)+IF(2='0. Assumptions'!$B$61,(MAX(12,'0. Assumptions'!$B$21)-12)/2,0))),"") -> -6530.7 | D13: =IFERROR(IF('3-Year P&L'!$B$9="","",-'3-Year P&L'!$B$23/MAX(12,'0. Assumptions'!$B$21)*(1+IF(3='0. Assumptions'!$B$60,(MAX(12,'0. Assumptions'!$B$21)-12)/2,0)+IF(3='0. Assumptions'!$B$61,(MAX(12,'0. Assumptions'!$B$21)-12)/2,0))),"") -> -6530.7 | E13: =IFERROR(IF('3-Year P&L'!$B$9="","",-'3-Year P&L'!$B$23/MAX(12,'0. Assumptions'!$B$21)*(1+IF(4='0. Assumptions'!$B$60,(MAX(12,'0. Assumptions'!$B$21)-12)/2,0)+IF(4='0. Assumptions'!$B$61,(MAX(12,'0. Assumptions'!$B$21)-12)/2,0))),"") -> -6530.7 | F13: =IFERROR(IF('3-Year P&L'!$B$9="","",-'3-Year P&L'!$B$23/MAX(12,'0. Assumptions'!$B$21)*(1+IF(5='0. Assumptions'!$B$60,(MAX(12,'0. Assumptions'!$B$21)-12)/2,0)+IF(5='0. Assumptions'!$B$61,(MAX(12,'0. Assumptions'!$B$21)-12)/2,0))),"") -> -6530.7 | G13: =IFERROR(IF('3-Year P&L'!$B$9="","",-'3-Year P&L'!$B$23/MAX(12,'0. Assumptions'!$B$21)*(1+IF(6='0. Assumptions'!$B$60,(MAX(12,'0. Assumptions'!$B$21)-12)/2,0)+IF(6='0. Assumptions'!$B$61,(MAX(12,'0. Assumptions'!$B$21)-12)/2,0))),"") -> -6530.7 | H13: =IFERROR(IF('3-Year P&L'!$B$9="","",-'3-Year P&L'!$B$23/MAX(12,'0. Assumptions'!$B$21)*(1+IF(7='0. Assumptions'!$B$60,(MAX(12,'0. Assumptions'!$B$21)-12)/2,0)+IF(7='0. Assumptions'!$B$61,(MAX(12,'0. Assumptions'!$B$21)-12)/2,0))),"") -> -6530.7 | I13: =IFERROR(IF('3-Year P&L'!$B$9="","",-'3-Year P&L'!$B$23/MAX(12,'0. Assumptions'!$B$21)*(1+IF(8='0. Assumptions'!$B$60,(MAX(12,'0. Assumptions'!$B$21)-12)/2,0)+IF(8='0. Assumptions'!$B$61,(MAX(12,'0. Assumptions'!$B$21)-12)/2,0))),"") -> -6530.7 | J13: =IFERROR(IF('3-Year P&L'!$B$9="","",-'3-Year P&L'!$B$23/MAX(12,'0. Assumptions'!$B$21)*(1+IF(9='0. Assumptions'!$B$60,(MAX(12,'0. Assumptions'!$B$21)-12)/2,0)+IF(9='0. Assumptions'!$B$61,(MAX(12,'0. Assumptions'!$B$21)-12)/2,0))),"") -> -6530.7 | K13: =IFERROR(IF('3-Year P&L'!$B$9="","",-'3-Year P&L'!$B$23/MAX(12,'0. Assumptions'!$B$21)*(1+IF(10='0. Assumptions'!$B$60,(MAX(12,'0. Assumptions'!$B$21)-12)/2,0)+IF(10='0. Assumptions'!$B$61,(MAX(12,'0. Assumptions'!$B$21)-12)/2,0))),"") -> -6530.7 | L13: =IFERROR(IF('3-Year P&L'!$B$9="","",-'3-Year P&L'!$B$23/MAX(12,'0. Assumptions'!$B$21)*(1+IF(11='0. Assumptions'!$B$60,(MAX(12,'0. Assumptions'!$B$21)-12)/2,0)+IF(11='0. Assumptions'!$B$61,(MAX(12,'0. Assumptions'!$B$21)-12)/2,0))),"") -> -6530.7 | M13: =IFERROR(IF('3-Year P&L'!$B$9="","",-'3-Year P&L'!$B$23/MAX(12,'0. Assumptions'!$B$21)*(1+IF(12='0. Assumptions'!$B$60,(MAX(12,'0. Assumptions'!$B$21)-12)/2,0)+IF(12='0. Assumptions'!$B$61,(MAX(12,'0. Assumptions'!$B$21)-12)/2,0))),"") -> -6530.7 | N13: =IFERROR(IF('3-Year P&L'!$B$9="","",SUM(B13:M13)),"") -> -78368.4 | O13: Twelve monthly installments plus extra pay periods in the months you set in Assumptions (only if pay periods > 12). The total for the year is the same as the P&L's
A14: Loan interest | B14: =IFERROR(IF('3-Year P&L'!$B$9="","",-Financing!$B$44/12),"") -> -408.33333 | C14: =IFERROR(IF('3-Year P&L'!$B$9="","",-Financing!$B$44/12),"") -> -408.33333 | D14: =IFERROR(IF('3-Year P&L'!$B$9="","",-Financing!$B$44/12),"") -> -408.33333 | E14: =IFERROR(IF('3-Year P&L'!$B$9="","",-Financing!$B$44/12),"") -> -408.33333 | F14: =IFERROR(IF('3-Year P&L'!$B$9="","",-Financing!$B$44/12),"") -> -408.33333 | G14: =IFERROR(IF('3-Year P&L'!$B$9="","",-Financing!$B$44/12),"") -> -408.33333 | H14: =IFERROR(IF('3-Year P&L'!$B$9="","",-Financing!$B$44/12),"") -> -408.33333 | I14: =IFERROR(IF('3-Year P&L'!$B$9="","",-Financing!$B$44/12),"") -> -408.33333 | ... M14: =IFERROR(IF('3-Year P&L'!$B$9="","",-Financing!$B$44/12),"") -> -408.33333 | N14: =IFERROR(IF('3-Year P&L'!$B$9="","",SUM(B14:M14)),"") -> -4900
A15: Loan principal repaid | B15: =IFERROR(IF('3-Year P&L'!$B$9="","",-Financing!$B$45/12),"") -> -430.40579 | C15: =IFERROR(IF('3-Year P&L'!$B$9="","",-Financing!$B$45/12),"") -> -430.40579 | D15: =IFERROR(IF('3-Year P&L'!$B$9="","",-Financing!$B$45/12),"") -> -430.40579 | E15: =IFERROR(IF('3-Year P&L'!$B$9="","",-Financing!$B$45/12),"") -> -430.40579 | F15: =IFERROR(IF('3-Year P&L'!$B$9="","",-Financing!$B$45/12),"") -> -430.40579 | G15: =IFERROR(IF('3-Year P&L'!$B$9="","",-Financing!$B$45/12),"") -> -430.40579 | H15: =IFERROR(IF('3-Year P&L'!$B$9="","",-Financing!$B$45/12),"") -> -430.40579 | I15: =IFERROR(IF('3-Year P&L'!$B$9="","",-Financing!$B$45/12),"") -> -430.40579 | ... M15: =IFERROR(IF('3-Year P&L'!$B$9="","",-Financing!$B$45/12),"") -> -430.40579 | N15: =IFERROR(IF('3-Year P&L'!$B$9="","",SUM(B15:M15)),"") -> -5164.8695
A16: Sales tax collected (memo) | B16: =IFERROR(IF('3-Year P&L'!$B$9="","",'3-Year P&L'!$B$9*B7*SUMPRODUCT('3-Year P&L'!$E$10:$E$11,'3-Year P&L'!$G$10:$G$11)),"") -> 743.69479 | C16: =IFERROR(IF('3-Year P&L'!$B$9="","",'3-Year P&L'!$B$9*C7*SUMPRODUCT('3-Year P&L'!$E$10:$E$11,'3-Year P&L'!$G$10:$G$11)),"") -> 1200.2408 | D16: =IFERROR(IF('3-Year P&L'!$B$9="","",'3-Year P&L'!$B$9*D7*SUMPRODUCT('3-Year P&L'!$E$10:$E$11,'3-Year P&L'!$G$10:$G$11)),"") -> 1605.279 | E16: =IFERROR(IF('3-Year P&L'!$B$9="","",'3-Year P&L'!$B$9*E7*SUMPRODUCT('3-Year P&L'!$E$10:$E$11,'3-Year P&L'!$G$10:$G$11)),"") -> 1301.4659 | F16: =IFERROR(IF('3-Year P&L'!$B$9="","",'3-Year P&L'!$B$9*F7*SUMPRODUCT('3-Year P&L'!$E$10:$E$11,'3-Year P&L'!$G$10:$G$11)),"") -> 894.63728 | G16: =IFERROR(IF('3-Year P&L'!$B$9="","",'3-Year P&L'!$B$9*G7*SUMPRODUCT('3-Year P&L'!$E$10:$E$11,'3-Year P&L'!$G$10:$G$11)),"") -> 1136.889 | H16: =IFERROR(IF('3-Year P&L'!$B$9="","",'3-Year P&L'!$B$9*H7*SUMPRODUCT('3-Year P&L'!$E$10:$E$11,'3-Year P&L'!$G$10:$G$11)),"") -> 2185.6363 | I16: =IFERROR(IF('3-Year P&L'!$B$9="","",'3-Year P&L'!$B$9*I7*SUMPRODUCT('3-Year P&L'!$E$10:$E$11,'3-Year P&L'!$G$10:$G$11)),"") -> 2667.6607 | ... M16: =IFERROR(IF('3-Year P&L'!$B$9="","",'3-Year P&L'!$B$9*M7*SUMPRODUCT('3-Year P&L'!$E$10:$E$11,'3-Year P&L'!$G$10:$G$11)),"") -> 925.48685 | N16: =IFERROR(IF('3-Year P&L'!$B$9="","",SUM(B16:M16)),"") -> 17024 | O16: Each sales line at ITS OWN rate, read from the sales tax column of the P&L (alcohol to go has its own rate cell in the Assumptions tab)
A17: Recoverable input tax (memo) | B17: =IFERROR(IF('3-Year P&L'!$B$9="","",'3-Year P&L'!$B$39*B7+'3-Year P&L'!$B$40/12),"") -> 0 | C17: =IFERROR(IF('3-Year P&L'!$B$9="","",'3-Year P&L'!$B$39*C7+'3-Year P&L'!$B$40/12),"") -> 0 | D17: =IFERROR(IF('3-Year P&L'!$B$9="","",'3-Year P&L'!$B$39*D7+'3-Year P&L'!$B$40/12),"") -> 0 | E17: =IFERROR(IF('3-Year P&L'!$B$9="","",'3-Year P&L'!$B$39*E7+'3-Year P&L'!$B$40/12),"") -> 0 | F17: =IFERROR(IF('3-Year P&L'!$B$9="","",'3-Year P&L'!$B$39*F7+'3-Year P&L'!$B$40/12),"") -> 0 | G17: =IFERROR(IF('3-Year P&L'!$B$9="","",'3-Year P&L'!$B$39*G7+'3-Year P&L'!$B$40/12),"") -> 0 | H17: =IFERROR(IF('3-Year P&L'!$B$9="","",'3-Year P&L'!$B$39*H7+'3-Year P&L'!$B$40/12),"") -> 0 | I17: =IFERROR(IF('3-Year P&L'!$B$9="","",'3-Year P&L'!$B$39*I7+'3-Year P&L'!$B$40/12),"") -> 0 | ... M17: =IFERROR(IF('3-Year P&L'!$B$9="","",'3-Year P&L'!$B$39*M7+'3-Year P&L'!$B$40/12),"") -> 0 | N17: =IFERROR(IF('3-Year P&L'!$B$9="","",SUM(B17:M17)),"") -> 0 | O17: Each item at its own rate, read from the tax column of the P&L: insurance and card processing fees carry none
A18: Carried forward (capex input tax included) | E18: =IFERROR(IF('3-Year P&L'!$B$9="","",'Startup Costs'!$B$28),"") -> 0 | H18: =IFERROR(IF('3-Year P&L'!$B$9="","",MAX(0,-E19)),"") -> 0 | K18: =IFERROR(IF('3-Year P&L'!$B$9="","",MAX(0,-H19)),"") -> 0 | O18: Sales tax paid on STARTUP COSTS enters here: it is offset against the tax collected in later quarters until used up. With 0% recoverable input tax (the US default) this line stays at zero
A19: Quarterly sales tax return | E19: =IFERROR(IF('3-Year P&L'!$B$9="","",SUM(B16:D16)-SUM(B17:D17)-E18),"") -> 3549.2145 | H19: =IFERROR(IF('3-Year P&L'!$B$9="","",SUM(E16:G16)-SUM(E17:G17)-H18),"") -> 3332.9921 | K19: =IFERROR(IF('3-Year P&L'!$B$9="","",SUM(H16:J16)-SUM(H17:J17)-K18),"") -> 6726.3062 | O19: Sales tax collected minus recoverable input tax for the quarter, minus what was carried forward. If negative, nothing is paid: it is offset in the next quarter. With 0% recoverable input tax (the US default) it equals the sales tax collected in the quarter
A20: Sales tax remitted (quarterly filer) | E20: =IFERROR(IF('3-Year P&L'!$B$9="","",IF(E19<=0,"",-E19)),"") -> -3549.2145 | H20: =IFERROR(IF('3-Year P&L'!$B$9="","",IF(H19<=0,"",-H19)),"") -> -3332.9921 | K20: =IFERROR(IF('3-Year P&L'!$B$9="","",IF(K19<=0,"",-K19)),"") -> -6726.3062 | N20: =IFERROR(IF('3-Year P&L'!$B$9="","",SUM(B20:M20)),"") -> -13608.513 | O20: Cash only leaves when the quarter's result is positive. Months without a settlement are left blank, not zero. The cell turns RED when the payment takes more cash than is left that month. The model settles quarterly, in the month after each plan quarter (Months 4, 7 and 10, and the fourth quarter in Month 13: April, July, October and January when Month 1 is January): if your state requires monthly filing, expect smaller payments every month instead
A21: MONTHLY NET CASH FLOW | B21: =IFERROR(IF('3-Year P&L'!$B$9="","",SUM(B9:B15)+IF(B20="",0,B20)),"") -> -2688.0353 | C21: =IFERROR(IF('3-Year P&L'!$B$9="","",SUM(C9:C15)+IF(C20="",0,C20)),"") -> 1631.4331 | D21: =IFERROR(IF('3-Year P&L'!$B$9="","",SUM(D9:D15)+IF(D20="",0,D20)),"") -> 5550.8451 | E21: =IFERROR(IF('3-Year P&L'!$B$9="","",SUM(E9:E15)+IF(E20="",0,E20)),"") -> -1259.2136 | F21: =IFERROR(IF('3-Year P&L'!$B$9="","",SUM(F9:F15)+IF(F20="",0,F20)),"") -> -1713.1821 | G21: =IFERROR(IF('3-Year P&L'!$B$9="","",SUM(G9:G15)+IF(G20="",0,G20)),"") -> 922.92854 | H21: =IFERROR(IF('3-Year P&L'!$B$9="","",SUM(H9:H15)+IF(H20="",0,H20)),"") -> 8141.8483 | I21: =IFERROR(IF('3-Year P&L'!$B$9="","",SUM(I9:I15)+IF(I20="",0,I20)),"") -> 15922.204 | ... M21: =IFERROR(IF('3-Year P&L'!$B$9="","",SUM(M9:M15)+IF(M20="",0,M20)),"") -> -1200.4495 | N21: =IFERROR(IF('3-Year P&L'!$B$9="","",SUM(B21:M21)),"") -> 29520.399
A22: CUMULATIVE CASH BALANCE | B22: =IFERROR(IF('3-Year P&L'!$B$9="","",'Startup Costs'!$B$25+B21),"") -> 26754.065 | C22: =IFERROR(IF('3-Year P&L'!$B$9="","",B22+C21),"") -> 28385.498 | D22: =IFERROR(IF('3-Year P&L'!$B$9="","",C22+D21),"") -> 33936.343 | E22: =IFERROR(IF('3-Year P&L'!$B$9="","",D22+E21),"") -> 32677.129 | F22: =IFERROR(IF('3-Year P&L'!$B$9="","",E22+F21),"") -> 30963.947 | G22: =IFERROR(IF('3-Year P&L'!$B$9="","",F22+G21),"") -> 31886.876 | H22: =IFERROR(IF('3-Year P&L'!$B$9="","",G22+H21),"") -> 40028.724 | I22: =IFERROR(IF('3-Year P&L'!$B$9="","",H22+I21),"") -> 55950.928 | J22: =IFERROR(IF('3-Year P&L'!$B$9="","",I22+J21),"") -> 63592.005 | ... M22: =IFERROR(IF('3-Year P&L'!$B$9="","",L22+M21),"") -> 58962.499
A23: Minimum balance of the year | B23: =IFERROR(IF('3-Year P&L'!$B$9="","",IF(COUNT(B22:M22)=0,"",MIN(B22:M22))),"") -> 26754.065 | D23: If negative, raise working capital or the loan: you run out of cash
A24: Month when cash bottoms out | B24: =IFERROR(IF('3-Year P&L'!$B$9="","",IF(COUNT(B22:M22)=0,"",MATCH(MIN(B22:M22),B22:M22,0))),"") -> 1 | D24: It answers the question that decides a bank deal: in which month the cash runs out
A25: RETURN ON INVESTMENT
A26: Free cash flow before debt, year 1 | B26: =IFERROR(IF('3-Year P&L'!$B$9="","",'3-Year P&L'!$B$48+'3-Year P&L'!$B$36+Financing!$B$44),"") -> 29508.943 | D26: Net income plus depreciation (which is not paid) plus that year's interest: principal is not subtracted because this flow is BEFORE debt. The SAME basis as years 2 and 3, so the payback compares like with like
A27: Free cash flow before debt, year 2 | B27: =IFERROR(IF('3-Year P&L'!$B$9="","",'3-Year P&L'!$C$48+'3-Year P&L'!$C$36+Financing!$B$46),"") -> 38277.881 | D27: Net income plus depreciation (which is not paid) plus that year's interest: principal is not subtracted because this flow is BEFORE debt. Without a monthly table, it is an estimate
A28: Free cash flow before debt, year 3 | B28: =IFERROR(IF('3-Year P&L'!$B$9="","",'3-Year P&L'!$D$48+'3-Year P&L'!$D$36+Financing!$B$48),"") -> 45696.14 | D28: Net income plus depreciation (which is not paid) plus that year's interest: principal is not subtracted because this flow is BEFORE debt. Without a monthly table, it is an estimate
A29: For reference: ACTUAL year-1 cash flow (monthly table, before debt) | B29: =IFERROR(IF('3-Year P&L'!$B$9="","",N21+Financing!$B$44+Financing!$B$45),"") -> 39585.268 | D29: The sum of the twelve monthly net cash flows above, adding back the interest and principal paid that year. It is NOT the one the payback uses: it includes sales tax not yet settled and supplier credit, two things that have to be paid back and that years 2 and 3 do not have
A30: Investment to recover (net of recoverable input tax) | B30: =IFERROR(IF('3-Year P&L'!$B$9="","",'Startup Costs'!$B$29-'Startup Costs'!$B$28),"") -> 76972.1 | D30: CAPEX plus working capital: the total cash needed MINUS the recoverable input tax on startup costs, which is not lost (it is recovered through the quarterly return, and this tab offsets it quarter by quarter; it is zero in the US default). Working capital is recovered when you close, but until then it is tied up
A31: Project payback (years), before debt | B31: =IFERROR(IF('3-Year P&L'!$B$9="","",IF(B26>=B30,ROUND(B30/B26,1),IF(B26+B27>=B30,ROUND(1+(B30-B26)/B27,1),IF(B26+B27+B28>=B30,ROUND(2+(B30-B26-B27)/B28,1),"Over 3 years")))),"") -> 2.2 | D31: Measures how long the business takes to repay the investment with what it generates BEFORE paying the lender, on the SAME cash flow basis in all three years. Whether you can afford the loan payment is shown by the DSCR in the Financing tab
A32: Payback on CAPEX, excluding working capital (years) | B32: =IFERROR(IF('3-Year P&L'!$B$9="","",IF(B26>='Startup Costs'!$B$27,ROUND('Startup Costs'!$B$27/B26,1),IF(B26+B27>='Startup Costs'!$B$27,ROUND(1+('Startup Costs'!$B$27-B26)/B27,1),IF(B26+B27+B28>='Startup Costs'!$B$27,ROUND(2+('Startup Costs'!$B$27-B26-B27)/B28,1),"Over 3 years")))),"") -> 1.5 | D32: The same calculation on what you BUY (trailer, conversion, equipment, launch and formation costs), without working capital: that money is not spent, it is tied up and comes back when you close the business. Informational: the payback that is published is the one above.
A34: Fourth-quarter sales tax is settled in January of the following year, so it does not appear in this table. The model pays year-1 income tax in July of year 2 (a simplification: estimated tax payments are usually quarterly). The loan payment is spread in twelve equal parts following the ANNUAL schedule in the Financing tab, and payroll in twelve monthly installments (plus extra pay periods in their month, only if pay periods > 12).

Sheet Financing
A1: FINANCING PLAN
A2: What you need, where it comes from and what it costs to repay. It is the sheet your lender asks for along with the P&L.
A4: Item | B4: Amount | C4: Notes
A5: SOURCES OF FUNDS
A6: Owner's equity (your own money) | B6: =IFERROR(IF('0. Assumptions'!$B$30="","",'0. Assumptions'!$B$30),"") -> 28000
A7: Loan requested — bank or SBA 7(a) (amortized below) | B7: =IFERROR(IF('0. Assumptions'!$B$31="","",'0. Assumptions'!$B$31),"") -> 49000
A8: Other loan (not in the schedule or the DSCR — enter your loan in row 7) | B8: 0 | C8: A source of funds only: NOT amortized, so it is not in the schedule, the P&L interest or the DSCR. Enter your bank or SBA 7(a) loan in row 7 ("Loan requested" in "0. Assumptions"); use this row only for a second loan
A9: SBA Microloan (not in the schedule or the DSCR — enter your loan in row 7) | B9: 0 | C9: SBA Microloans go up to $50,000 through nonprofit intermediaries. Like row 8, a source of funds only: not in the schedule or the DSCR. If it is your only loan, enter it in row 7 instead
A10: Investors / partners (equity: dilutes, not repaid) | B10: 0 | C10: Equity: it dilutes your ownership and is not repaid
A11: Local grants (usually paid after you spend) | B11: 0 | C11: Usually paid AFTER you document the spending
A12: TOTAL SOURCES OF FUNDS | B12: =IFERROR(IF(COUNT(B6:B11)=0,"",SUM(B6:B11)),"") -> 77000
A13: USES OF FUNDS
A14: Total cash needed at launch | B14: =IFERROR(IF('Startup Costs'!$B$29="","",'Startup Costs'!$B$29),"") -> 76972.1 | C14: Startup costs plus any recoverable tax you have to advance (zero by default in the US)
A15: Difference (sources - uses) | B15: =IFERROR(B12-B14,"") -> 27.9 | C15: In red (negative), the plan is NOT funded. Far above zero is not free either: you pay interest on money you do not use
A16: Difference as a % of uses | B16: =IFERROR(B15/B14,"") -> 0.000362469 | C16: Amber above the margin you set: it is debt you pay for without needing it
A17: Acceptable over-funding (%) | B17: 0.05 | C17: A small cushion over the need is healthy; 20% extra is interest thrown away
A18: Loan that would match sources to needs | B18: =IFERROR(MAX(0,B14-B12+B7),"") -> 48972.1 | C18: Copy it into "Loan requested" in the "0. Assumptions" tab and the difference goes to zero. Rows 8-11 lower this figure, but only the row-7 loan is amortized and counted in the DSCR
A19: LOAN TERMS
A20: Principal amount | B20: =IFERROR(IF('0. Assumptions'!$B$31=0,"",'0. Assumptions'!$B$31),"") -> 49000
A21: Nominal annual interest rate (not APR) | B21: =IFERROR(IF('0. Assumptions'!$B$32="","",'0. Assumptions'!$B$32),"") -> 0.1
A22: Total term (years) | B22: =IFERROR(IF('0. Assumptions'!$B$33="","",'0. Assumptions'!$B$33),"") -> 7
A23: Interest-only period applied (years) | B23: =IFERROR(IF(OR('0. Assumptions'!$B$34="",'0. Assumptions'!$B$33=""),"",IF('0. Assumptions'!$B$34>='0. Assumptions'!$B$33,0,'0. Assumptions'!$B$34)),"") -> 0 | C23: An interest-only period equal to or longer than the term does not exist: the sheet cancels it at the source
A24: Annual payment during repayment | B24: =IFERROR(IF(B22-B23<=0,"",IF(B21=0,B20/(B22-B23),B20*B21/(1-(1+B21)^-(B22-B23)))),"") -> 10064.869 | C24: Standard amortizing loan with a level annual payment. At a 0% rate it is the principal divided by the repayment years: without that branch the schedule would shut down entirely
A25: AMORTIZATION SCHEDULE
A26: Year | B26: Opening balance | C26: Interest | D26: Principal repaid | E26: Total payment | F26: Closing balance | G26: Cash flow available for debt service (after tax; from year 4 on, year 3 held flat) | H26: DSCR for the year
A27: 1 | B27: =IFERROR(IF(B20="","",B20),"") -> 49000 | C27: =IFERROR(IF(OR(1>B22,B27=""),"",B27*B21),"") -> 4900 | D27: =IFERROR(IF(OR(1>B22,B27=""),"",IF(1<=B23,0,MIN(B27,B24-C27))),"") -> 5164.8695 | E27: =IFERROR(IF(C27="","",C27+D27),"") -> 10064.869 | F27: =IFERROR(IF(D27="","",B27-D27),"") -> 43835.131 | G27: =IFERROR(IF(E27="","",'3-Year P&L'!$B$41-'3-Year P&L'!$B$46+'3-Year P&L'!$B$36+'3-Year P&L'!$B$37),"") -> 29508.943 | H27: =IFERROR(IF(OR(E27="",E27=0),"",G27/E27),"") -> 2.9318754
A28: 2 | B28: =IFERROR(IF(OR(2>B22,F27=""),"",F27),"") -> 43835.131 | C28: =IFERROR(IF(OR(2>B22,B28=""),"",B28*B21),"") -> 4383.5131 | D28: =IFERROR(IF(OR(2>B22,B28=""),"",IF(2<=B23,0,MIN(B28,B24-C28))),"") -> 5681.3564 | E28: =IFERROR(IF(C28="","",C28+D28),"") -> 10064.869 | F28: =IFERROR(IF(D28="","",B28-D28),"") -> 38153.774 | G28: =IFERROR(IF(E28="","",'3-Year P&L'!$C$41-'3-Year P&L'!$C$46+'3-Year P&L'!$C$36+'3-Year P&L'!$C$37),"") -> 38277.881 | H28: =IFERROR(IF(OR(E28="",E28=0),"",G28/E28),"") -> 3.8031175
A29: 3 | B29: =IFERROR(IF(OR(3>B22,F28=""),"",F28),"") -> 38153.774 | C29: =IFERROR(IF(OR(3>B22,B29=""),"",B29*B21),"") -> 3815.3774 | D29: =IFERROR(IF(OR(3>B22,B29=""),"",IF(3<=B23,0,MIN(B29,B24-C29))),"") -> 6249.4921 | E29: =IFERROR(IF(C29="","",C29+D29),"") -> 10064.869 | F29: =IFERROR(IF(D29="","",B29-D29),"") -> 31904.282 | G29: =IFERROR(IF(E29="","",'3-Year P&L'!$D$41-'3-Year P&L'!$D$46+'3-Year P&L'!$D$36+'3-Year P&L'!$D$37),"") -> 45696.14 | H29: =IFERROR(IF(OR(E29="",E29=0),"",G29/E29),"") -> 4.5401622
A30: 4 | B30: =IFERROR(IF(OR(4>B22,F29=""),"",F29),"") -> 31904.282 | C30: =IFERROR(IF(OR(4>B22,B30=""),"",B30*B21),"") -> 3190.4282 | D30: =IFERROR(IF(OR(4>B22,B30=""),"",IF(4<=B23,0,MIN(B30,B24-C30))),"") -> 6874.4413 | E30: =IFERROR(IF(C30="","",C30+D30),"") -> 10064.869 | F30: =IFERROR(IF(D30="","",B30-D30),"") -> 25029.841 | G30: =IFERROR(IF(E30="","",'3-Year P&L'!$D$41-'3-Year P&L'!$D$46+'3-Year P&L'!$D$36+'3-Year P&L'!$D$37),"") -> 45696.14 | H30: =IFERROR(IF(OR(E30="",E30=0),"",G30/E30),"") -> 4.5401622
A31: 5 | B31: =IFERROR(IF(OR(5>B22,F30=""),"",F30),"") -> 25029.841 | C31: =IFERROR(IF(OR(5>B22,B31=""),"",B31*B21),"") -> 2502.9841 | D31: =IFERROR(IF(OR(5>B22,B31=""),"",IF(5<=B23,0,MIN(B31,B24-C31))),"") -> 7561.8854 | E31: =IFERROR(IF(C31="","",C31+D31),"") -> 10064.869 | F31: =IFERROR(IF(D31="","",B31-D31),"") -> 17467.955 | G31: =IFERROR(IF(E31="","",'3-Year P&L'!$D$41-'3-Year P&L'!$D$46+'3-Year P&L'!$D$36+'3-Year P&L'!$D$37),"") -> 45696.14 | H31: =IFERROR(IF(OR(E31="",E31=0),"",G31/E31),"") -> 4.5401622
A32: 6 | B32: =IFERROR(IF(OR(6>B22,F31=""),"",F31),"") -> 17467.955 | C32: =IFERROR(IF(OR(6>B22,B32=""),"",B32*B21),"") -> 1746.7955 | D32: =IFERROR(IF(OR(6>B22,B32=""),"",IF(6<=B23,0,MIN(B32,B24-C32))),"") -> 8318.074 | E32: =IFERROR(IF(C32="","",C32+D32),"") -> 10064.869 | F32: =IFERROR(IF(D32="","",B32-D32),"") -> 9149.8814 | G32: =IFERROR(IF(E32="","",'3-Year P&L'!$D$41-'3-Year P&L'!$D$46+'3-Year P&L'!$D$36+'3-Year P&L'!$D$37),"") -> 45696.14 | H32: =IFERROR(IF(OR(E32="",E32=0),"",G32/E32),"") -> 4.5401622
A33: 7 | B33: =IFERROR(IF(OR(7>B22,F32=""),"",F32),"") -> 9149.8814 | C33: =IFERROR(IF(OR(7>B22,B33=""),"",B33*B21),"") -> 914.98814 | D33: =IFERROR(IF(OR(7>B22,B33=""),"",IF(7<=B23,0,MIN(B33,B24-C33))),"") -> 9149.8814 | E33: =IFERROR(IF(C33="","",C33+D33),"") -> 10064.869 | F33: =IFERROR(IF(D33="","",B33-D33),"") -> 6.002665e-11 | G33: =IFERROR(IF(E33="","",'3-Year P&L'!$D$41-'3-Year P&L'!$D$46+'3-Year P&L'!$D$36+'3-Year P&L'!$D$37),"") -> 45696.14 | H33: =IFERROR(IF(OR(E33="",E33=0),"",G33/E33),"") -> 4.5401622
A34: 8 | B34: =IFERROR(IF(OR(8>B22,F33=""),"",F33),"") | C34: =IFERROR(IF(OR(8>B22,B34=""),"",B34*B21),"") | D34: =IFERROR(IF(OR(8>B22,B34=""),"",IF(8<=B23,0,MIN(B34,B24-C34))),"") | E34: =IFERROR(IF(C34="","",C34+D34),"") | F34: =IFERROR(IF(D34="","",B34-D34),"") | G34: =IFERROR(IF(E34="","",'3-Year P&L'!$D$41-'3-Year P&L'!$D$46+'3-Year P&L'!$D$36+'3-Year P&L'!$D$37),"") | H34: =IFERROR(IF(OR(E34="",E34=0),"",G34/E34),"")
A35: 9 | B35: =IFERROR(IF(OR(9>B22,F34=""),"",F34),"") | C35: =IFERROR(IF(OR(9>B22,B35=""),"",B35*B21),"") | D35: =IFERROR(IF(OR(9>B22,B35=""),"",IF(9<=B23,0,MIN(B35,B24-C35))),"") | E35: =IFERROR(IF(C35="","",C35+D35),"") | F35: =IFERROR(IF(D35="","",B35-D35),"") | G35: =IFERROR(IF(E35="","",'3-Year P&L'!$D$41-'3-Year P&L'!$D$46+'3-Year P&L'!$D$36+'3-Year P&L'!$D$37),"") | H35: =IFERROR(IF(OR(E35="",E35=0),"",G35/E35),"")
A36: 10 | B36: =IFERROR(IF(OR(10>B22,F35=""),"",F35),"") | C36: =IFERROR(IF(OR(10>B22,B36=""),"",B36*B21),"") | D36: =IFERROR(IF(OR(10>B22,B36=""),"",IF(10<=B23,0,MIN(B36,B24-C36))),"") | E36: =IFERROR(IF(C36="","",C36+D36),"") | F36: =IFERROR(IF(D36="","",B36-D36),"") | G36: =IFERROR(IF(E36="","",'3-Year P&L'!$D$41-'3-Year P&L'!$D$46+'3-Year P&L'!$D$36+'3-Year P&L'!$D$37),"") | H36: =IFERROR(IF(OR(E36="",E36=0),"",G36/E36),"")
A37: 11 | B37: =IFERROR(IF(OR(11>B22,F36=""),"",F36),"") | C37: =IFERROR(IF(OR(11>B22,B37=""),"",B37*B21),"") | D37: =IFERROR(IF(OR(11>B22,B37=""),"",IF(11<=B23,0,MIN(B37,B24-C37))),"") | E37: =IFERROR(IF(C37="","",C37+D37),"") | F37: =IFERROR(IF(D37="","",B37-D37),"") | G37: =IFERROR(IF(E37="","",'3-Year P&L'!$D$41-'3-Year P&L'!$D$46+'3-Year P&L'!$D$36+'3-Year P&L'!$D$37),"") | H37: =IFERROR(IF(OR(E37="",E37=0),"",G37/E37),"")
A38: 12 | B38: =IFERROR(IF(OR(12>B22,F37=""),"",F37),"") | C38: =IFERROR(IF(OR(12>B22,B38=""),"",B38*B21),"") | D38: =IFERROR(IF(OR(12>B22,B38=""),"",IF(12<=B23,0,MIN(B38,B24-C38))),"") | E38: =IFERROR(IF(C38="","",C38+D38),"") | F38: =IFERROR(IF(D38="","",B38-D38),"") | G38: =IFERROR(IF(E38="","",'3-Year P&L'!$D$41-'3-Year P&L'!$D$46+'3-Year P&L'!$D$36+'3-Year P&L'!$D$37),"") | H38: =IFERROR(IF(OR(E38="",E38=0),"",G38/E38),"")
A39: 13 | B39: =IFERROR(IF(OR(13>B22,F38=""),"",F38),"") | C39: =IFERROR(IF(OR(13>B22,B39=""),"",B39*B21),"") | D39: =IFERROR(IF(OR(13>B22,B39=""),"",IF(13<=B23,0,MIN(B39,B24-C39))),"") | E39: =IFERROR(IF(C39="","",C39+D39),"") | F39: =IFERROR(IF(D39="","",B39-D39),"") | G39: =IFERROR(IF(E39="","",'3-Year P&L'!$D$41-'3-Year P&L'!$D$46+'3-Year P&L'!$D$36+'3-Year P&L'!$D$37),"") | H39: =IFERROR(IF(OR(E39="",E39=0),"",G39/E39),"")
A40: 14 | B40: =IFERROR(IF(OR(14>B22,F39=""),"",F39),"") | C40: =IFERROR(IF(OR(14>B22,B40=""),"",B40*B21),"") | D40: =IFERROR(IF(OR(14>B22,B40=""),"",IF(14<=B23,0,MIN(B40,B24-C40))),"") | E40: =IFERROR(IF(C40="","",C40+D40),"") | F40: =IFERROR(IF(D40="","",B40-D40),"") | G40: =IFERROR(IF(E40="","",'3-Year P&L'!$D$41-'3-Year P&L'!$D$46+'3-Year P&L'!$D$36+'3-Year P&L'!$D$37),"") | H40: =IFERROR(IF(OR(E40="",E40=0),"",G40/E40),"")
A41: 15 | B41: =IFERROR(IF(OR(15>B22,F40=""),"",F40),"") | C41: =IFERROR(IF(OR(15>B22,B41=""),"",B41*B21),"") | D41: =IFERROR(IF(OR(15>B22,B41=""),"",IF(15<=B23,0,MIN(B41,B24-C41))),"") | E41: =IFERROR(IF(C41="","",C41+D41),"") | F41: =IFERROR(IF(D41="","",B41-D41),"") | G41: =IFERROR(IF(E41="","",'3-Year P&L'!$D$41-'3-Year P&L'!$D$46+'3-Year P&L'!$D$36+'3-Year P&L'!$D$37),"") | H41: =IFERROR(IF(OR(E41="",E41=0),"",G41/E41),"")
A42: Schedule closing tolerance | B42: 0.01 | C42: Rounding margin. Above it, the schedule does not close and there is principal left unpaid
A43: Balance outstanding at maturity | B43: =IFERROR(IF(B20="","",ROUND(B20-SUM(D27:D41),2)),"") -> 0 | C43: Must be zero: the principal repaid in the schedule has to equal the amount borrowed. If it is positive, the term falls short
A44: Year-1 interest | B44: =IFERROR(IF(B20="","",IF(C27="",0,C27)),"") -> 4900
A45: Year-1 principal repaid | B45: =IFERROR(IF(B20="","",IF(D27="",0,D27)),"") -> 5164.8695
A46: Year-2 interest | B46: =IFERROR(IF(B20="","",IF(C28="",0,C28)),"") -> 4383.5131
A47: Year-2 principal repaid | B47: =IFERROR(IF(B20="","",IF(D28="",0,D28)),"") -> 5681.3564
A48: Year-3 interest | B48: =IFERROR(IF(B20="","",IF(C29="",0,C29)),"") -> 3815.3774
A49: Year-3 principal repaid | B49: =IFERROR(IF(B20="","",IF(D29="",0,D29)),"") -> 6249.4921
A50: DEBT SERVICE COVERAGE RATIO (DSCR)
A51: Year-1 DSCR | B51: =IFERROR(('3-Year P&L'!$B$41-'3-Year P&L'!$B$46+'3-Year P&L'!$B$36+B44)/(B44+B45),"") -> 2.9318754 | C51: An INTEREST-ONLY year, if there is one: with only interest in the denominator the ratio shoots up and does not measure the business
A52: Year-2 DSCR | B52: =IFERROR(('3-Year P&L'!$C$41-'3-Year P&L'!$C$46+'3-Year P&L'!$C$36+B46)/(B46+B47),"") -> 3.8031175
A53: Year-3 DSCR | B53: =IFERROR(('3-Year P&L'!$D$41-'3-Year P&L'!$D$46+'3-Year P&L'!$D$36+B48)/(B48+B49),"") -> 4.5401622
A54: Minimum DSCR across the whole schedule | B54: =IFERROR(IF(COUNT(H27:H41)=0,"",MIN(H27:H41)),"") -> 2.9318754 | C54: The worst year of the life of the loan, not the best of the three the P&L projects. It is the number that decides a loan. Mind the scope: years 1 to 3 come from the P&L, and from year 4 on the schedule HOLDS year 3's cash flow, so the minimum over those years is a sustained projection, not a calculated year. The cash flow is after tax
A56: DSCR is calculated BEFORE debt and AFTER tax: income tax is subtracted from pre-tax income, depreciation and interest are added back, and the result is divided by what has to be paid that year. Below the minimum in the "0. Assumptions" tab, the business does not generate enough to repay the loan. In the schedule, the available cash flow from year 4 on is held at year 3's: the P&L projects only three years, and no growth is invented here that has not been calculated.
