Workbook

Sheet Instrucciones
B2: 📋 Escandallo — Menú Degustación
B3: Kit de Escandallos Pro — AI Chef Pro
B4: www.aichef.pro
B6: Cómo usar esta plantilla
B8: ▸ Cada pestaña es un pase del menú degustación
B9: ▸ La pestaña 'Resumen' suma automáticamente todos los pases
B10: ▸ Introduce ingredientes y cantidades en cada pestaña de pase
B11: ▸ El PVP se calcula sobre el coste total de todos los pases
B13: — Kit de Escandallos Pro · AI Chef Pro · aichef.pro
B15: © 2026 AI Chef Pro · Todos los derechos reservados

Sheet 1. Aperitivo
A1: Aperitivo — Tartar de Atún con Aguacate
A2: Introduce tus ingredientes y cantidades. Las celdas verdes son editables.
K3: 📷 Foto del Plato
A4: Ingrediente | B4: Categoría | C4: Ud. Compra | D4: Precio/Ud (€) | E4: Cantidad | F4: Ud. Uso | G4: Merma (%) | H4: Cant. Bruta | I4: Coste (€)
A5: Atún rojo (lomo) | B5: Pescado | C5: kg | D5: 42 | E5: 0.08 | F5: kg | G5: 0.35 | H5: =E5/(1-G5) | I5: =H5*D5
A6: Aguacate Hass | B6: Fruta | C6: ud | D6: 1.5 | E6: 0.5 | F6: ud | G6: 0.3 | H6: =E6/(1-G6) | I6: =H6*D6
A7: Sésamo tostado | B7: Secos/granos | C7: kg | D7: 12 | E7: 0.005 | F7: kg | G7: 0.02 | H7: =E7/(1-G7) | I7: =H7*D7
A8: Salsa de soja | B8: Bebidas/licores | C8: L | D8: 6 | E8: 0.015 | F8: L | G8: 0.02 | H8: =E8/(1-G8) | I8: =H8*D8 | K8: Arrastra aquí la foto del plato terminado
A9: Aceite de sésamo | B9: Aceites/grasas | C9: L | D9: 14 | E9: 0.01 | F9: L | G9: 0.03 | H9: =E9/(1-G9) | I9: =H9*D9
H10: =IF(E10="","",E10/(1-G10)) | I10: =IF(H10="","",H10*D10)
H11: =IF(E11="","",E11/(1-G11)) | I11: =IF(H11="","",H11*D11)
H12: =IF(E12="","",E12/(1-G12)) | I12: =IF(H12="","",H12*D12)
H13: =IF(E13="","",E13/(1-G13)) | I13: =IF(H13="","",H13*D13)
H14: =IF(E14="","",E14/(1-G14)) | I14: =IF(H14="","",H14*D14)
K15: Insertar → Imagen → Desde archivo
A16: COSTE TOTAL INGREDIENTES | I16: =SUM(I5:I14)
A17: Coste elaboración (%) | H17: 0.1 | I17: =I16*H17
A18: COSTE TOTAL DEL PLATO | I18: =I16+I17
A20: Food Cost objetivo (%) | H20: 0.3
A21: PVP SUGERIDO (sin IVA) | I21: =I18/H20
A22: PVP CON IVA (10% hostelería) | I22: =I21*1.10
A23: Margen bruto (€) | I23: =I21-I18
A24: Margen bruto (%) | I24: =I23/I21

Sheet 2. Entrante
A1: Entrante — Vieira con Coliflor y Trufa
A2: Introduce tus ingredientes y cantidades. Las celdas verdes son editables.
K3: 📷 Foto del Plato
A4: Ingrediente | B4: Categoría | C4: Ud. Compra | D4: Precio/Ud (€) | E4: Cantidad | F4: Ud. Uso | G4: Merma (%) | H4: Cant. Bruta | I4: Coste (€)
A5: Vieira fresca (grande) | B5: Marisco | C5: kg | D5: 48 | E5: 0.06 | F5: kg | G5: 0.45 | H5: =E5/(1-G5) | I5: =H5*D5
A6: Coliflor | B6: Verdura raíz | C6: kg | D6: 2.5 | E6: 0.1 | F6: kg | G6: 0.3 | H6: =E6/(1-G6) | I6: =H6*D6
A7: Trufa negra | B7: Verdura raíz | C7: kg | D7: 800 | E7: 0.005 | F7: kg | G7: 0.1 | H7: =E7/(1-G7) | I7: =H7*D7
A8: Nata 35% MG | B8: Lácteos | C8: L | D8: 3.8 | E8: 0.05 | F8: L | G8: 0.03 | H8: =E8/(1-G8) | I8: =H8*D8 | K8: Arrastra aquí la foto del plato terminado
A9: Mantequilla | B9: Lácteos | C9: kg | D9: 9 | E9: 0.02 | F9: kg | G9: 0.03 | H9: =E9/(1-G9) | I9: =H9*D9
H10: =IF(E10="","",E10/(1-G10)) | I10: =IF(H10="","",H10*D10)
H11: =IF(E11="","",E11/(1-G11)) | I11: =IF(H11="","",H11*D11)
H12: =IF(E12="","",E12/(1-G12)) | I12: =IF(H12="","",H12*D12)
H13: =IF(E13="","",E13/(1-G13)) | I13: =IF(H13="","",H13*D13)
H14: =IF(E14="","",E14/(1-G14)) | I14: =IF(H14="","",H14*D14)
K15: Insertar → Imagen → Desde archivo
A16: COSTE TOTAL INGREDIENTES | I16: =SUM(I5:I14)
A17: Coste elaboración (%) | H17: 0.1 | I17: =I16*H17
A18: COSTE TOTAL DEL PLATO | I18: =I16+I17
A20: Food Cost objetivo (%) | H20: 0.3
A21: PVP SUGERIDO (sin IVA) | I21: =I18/H20
A22: PVP CON IVA (10% hostelería) | I22: =I21*1.10
A23: Margen bruto (€) | I23: =I21-I18
A24: Margen bruto (%) | I24: =I23/I21

Sheet 3. Pescado
A1: Pescado — Lubina con Beurre Blanc
A2: Introduce tus ingredientes y cantidades. Las celdas verdes son editables.
K3: 📷 Foto del Plato
A4: Ingrediente | B4: Categoría | C4: Ud. Compra | D4: Precio/Ud (€) | E4: Cantidad | F4: Ud. Uso | G4: Merma (%) | H4: Cant. Bruta | I4: Coste (€)
A5: Lubina salvaje | B5: Pescado | C5: kg | D5: 32 | E5: 0.16 | F5: kg | G5: 0.4 | H5: =E5/(1-G5) | I5: =H5*D5
A6: Chalota | B6: Verdura raíz | C6: kg | D6: 4.5 | E6: 0.03 | F6: kg | G6: 0.15 | H6: =E6/(1-G6) | I6: =H6*D6
A7: Vino blanco seco | B7: Bebidas/licores | C7: L | D7: 5 | E7: 0.04 | F7: L | G7: 0.02 | H7: =E7/(1-G7) | I7: =H7*D7
A8: Mantequilla | B8: Lácteos | C8: kg | D8: 9 | E8: 0.04 | F8: kg | G8: 0.03 | H8: =E8/(1-G8) | I8: =H8*D8 | K8: Arrastra aquí la foto del plato terminado
A9: Hinojo fresco | B9: Verdura hoja | C9: kg | D9: 5 | E9: 0.06 | F9: kg | G9: 0.25 | H9: =E9/(1-G9) | I9: =H9*D9
H10: =IF(E10="","",E10/(1-G10)) | I10: =IF(H10="","",H10*D10)
H11: =IF(E11="","",E11/(1-G11)) | I11: =IF(H11="","",H11*D11)
H12: =IF(E12="","",E12/(1-G12)) | I12: =IF(H12="","",H12*D12)
H13: =IF(E13="","",E13/(1-G13)) | I13: =IF(H13="","",H13*D13)
H14: =IF(E14="","",E14/(1-G14)) | I14: =IF(H14="","",H14*D14)
K15: Insertar → Imagen → Desde archivo
A16: COSTE TOTAL INGREDIENTES | I16: =SUM(I5:I14)
A17: Coste elaboración (%) | H17: 0.1 | I17: =I16*H17
A18: COSTE TOTAL DEL PLATO | I18: =I16+I17
A20: Food Cost objetivo (%) | H20: 0.3
A21: PVP SUGERIDO (sin IVA) | I21: =I18/H20
A22: PVP CON IVA (10% hostelería) | I22: =I21*1.10
A23: Margen bruto (€) | I23: =I21-I18
A24: Margen bruto (%) | I24: =I23/I21

Sheet 4. Carne
A1: Carne — Carrillera Ibérica al Vino Tinto
A2: Introduce tus ingredientes y cantidades. Las celdas verdes son editables.
K3: 📷 Foto del Plato
A4: Ingrediente | B4: Categoría | C4: Ud. Compra | D4: Precio/Ud (€) | E4: Cantidad | F4: Ud. Uso | G4: Merma (%) | H4: Cant. Bruta | I4: Coste (€)
A5: Carrillera ibérica | B5: Carne roja | C5: kg | D5: 18 | E5: 0.2 | F5: kg | G5: 0.15 | H5: =E5/(1-G5) | I5: =H5*D5
A6: Vino tinto reserva | B6: Bebidas/licores | C6: L | D6: 6 | E6: 0.1 | F6: L | G6: 0.02 | H6: =E6/(1-G6) | I6: =H6*D6
A7: Zanahoria | B7: Verdura raíz | C7: kg | D7: 1.2 | E7: 0.05 | F7: kg | G7: 0.12 | H7: =E7/(1-G7) | I7: =H7*D7
A8: Puré de boniato | B8: Verdura raíz | C8: kg | D8: 2.5 | E8: 0.1 | F8: kg | G8: 0.15 | H8: =E8/(1-G8) | I8: =H8*D8 | K8: Arrastra aquí la foto del plato terminado
A9: Romero fresco | B9: Especias/hierbas | C9: manojo | D9: 1 | E9: 0.5 | F9: ud | G9: 0.2 | H9: =E9/(1-G9) | I9: =H9*D9
H10: =IF(E10="","",E10/(1-G10)) | I10: =IF(H10="","",H10*D10)
H11: =IF(E11="","",E11/(1-G11)) | I11: =IF(H11="","",H11*D11)
H12: =IF(E12="","",E12/(1-G12)) | I12: =IF(H12="","",H12*D12)
H13: =IF(E13="","",E13/(1-G13)) | I13: =IF(H13="","",H13*D13)
H14: =IF(E14="","",E14/(1-G14)) | I14: =IF(H14="","",H14*D14)
K15: Insertar → Imagen → Desde archivo
A16: COSTE TOTAL INGREDIENTES | I16: =SUM(I5:I14)
A17: Coste elaboración (%) | H17: 0.1 | I17: =I16*H17
A18: COSTE TOTAL DEL PLATO | I18: =I16+I17
A20: Food Cost objetivo (%) | H20: 0.3
A21: PVP SUGERIDO (sin IVA) | I21: =I18/H20
A22: PVP CON IVA (10% hostelería) | I22: =I21*1.10
A23: Margen bruto (€) | I23: =I21-I18
A24: Margen bruto (%) | I24: =I23/I21

Sheet 5. Postre
A1: Postre — Esfera de Chocolate con Fruta de la Pasión
A2: Introduce tus ingredientes y cantidades. Las celdas verdes son editables.
K3: 📷 Foto del Plato
A4: Ingrediente | B4: Categoría | C4: Ud. Compra | D4: Precio/Ud (€) | E4: Cantidad | F4: Ud. Uso | G4: Merma (%) | H4: Cant. Bruta | I4: Coste (€)
A5: Chocolate negro 70% | B5: Chocolate/cacao | C5: kg | D5: 18 | E5: 0.06 | F5: kg | G5: 0.05 | H5: =E5/(1-G5) | I5: =H5*D5
A6: Fruta de la pasión | B6: Fruta | C6: kg | D6: 14 | E6: 0.04 | F6: kg | G6: 0.5 | H6: =E6/(1-G6) | I6: =H6*D6
A7: Nata 35% MG | B7: Lácteos | C7: L | D7: 3.8 | E7: 0.06 | F7: L | G7: 0.03 | H7: =E7/(1-G7) | I7: =H7*D7
A8: Azúcar | B8: Secos/granos | C8: kg | D8: 1.2 | E8: 0.025 | F8: kg | G8: 0.02 | H8: =E8/(1-G8) | I8: =H8*D8 | K8: Arrastra aquí la foto del plato terminado
A9: Manteca de cacao | B9: Chocolate/cacao | C9: kg | D9: 22 | E9: 0.015 | F9: kg | G9: 0.05 | H9: =E9/(1-G9) | I9: =H9*D9
H10: =IF(E10="","",E10/(1-G10)) | I10: =IF(H10="","",H10*D10)
H11: =IF(E11="","",E11/(1-G11)) | I11: =IF(H11="","",H11*D11)
H12: =IF(E12="","",E12/(1-G12)) | I12: =IF(H12="","",H12*D12)
H13: =IF(E13="","",E13/(1-G13)) | I13: =IF(H13="","",H13*D13)
H14: =IF(E14="","",E14/(1-G14)) | I14: =IF(H14="","",H14*D14)
K15: Insertar → Imagen → Desde archivo
A16: COSTE TOTAL INGREDIENTES | I16: =SUM(I5:I14)
A17: Coste elaboración (%) | H17: 0.1 | I17: =I16*H17
A18: COSTE TOTAL DEL PLATO | I18: =I16+I17
A20: Food Cost objetivo (%) | H20: 0.3
A21: PVP SUGERIDO (sin IVA) | I21: =I18/H20
A22: PVP CON IVA (10% hostelería) | I22: =I21*1.10
A23: Margen bruto (€) | I23: =I21-I18
A24: Margen bruto (%) | I24: =I23/I21

Sheet Resumen
B2: Resumen — Menú Degustación
B4: Pase | C4: Coste (€)
B5: 1. Aperitivo | C5: ='1. Aperitivo'!I18
B6: 2. Entrante | C6: ='2. Entrante'!I18
B7: 3. Pescado | C7: ='3. Pescado'!I18
B8: 4. Carne | C8: ='4. Carne'!I18
B9: 5. Postre | C9: ='5. Postre'!I18
B10: COSTE TOTAL MENÚ | C10: =SUM(C5:C9)
B12: Food Cost objetivo (%) | C12: 0.25
B13: PVP SUGERIDO (sin IVA) | C13: =C10/C12
B14: PVP CON IVA (10%) | C14: =C13*1.10
