Workbook

Sheet Instrucciones
A1: Plan financiero a 3 años
A2: AI Chef Pro · aichef.pro — Cómo Montar una Pastelería
A3: Para qué sirve: saber si el negocio se sostiene, cuándo llega al equilibrio y qué canal lo sostiene.
A5: Instrucciones de uso
A6: 1. Hoja «0. Supuestos»: es el cuadro de mandos. Aquí se teclean las TASAS y los DRIVERS —tickets al día, ticket medio, días de apertura, tipos de IVA, food cost objetivo, condiciones del préstamo, umbrales de control—, y el resto del libro se recalcula solo. Las partidas de gasto se teclean en su hoja, no aquí.
A7: 2. Hoja «Inversión Inicial»: cuánto cuesta abrir, partida a partida, con su columna «¿Lleva IVA?» y su TIPO por línea. Sin esa columna el CAPEX sale hasta un 21 % desviado, que es el error más caro de todo el proceso. Abajo salen el IVA que hay que ADELANTAR y la necesidad total de caja.
A8: 3. Hoja «PyG 3 Años»: la cuenta de resultados. El AÑO 2 es el año de crucero; el año 1 lleva la rampa de arranque y el año 3 crece sobre el crucero. El sueldo del propietario, la amortización y los intereses van DENTRO de los costes fijos: si no, la rentabilidad que publica un plan de negocio no significa nada.
A9: 4. Hoja «Punto de Equilibrio»: cuántos tickets al día hay que hacer para no perder dinero, en dos versiones. La CONTABLE incluye la amortización; la de CAJA le quita la amortización (que no se paga) y le suma la devolución de principal (que sí). La segunda es la que decide si llegas a fin de mes.
A10: 5. Hoja «Escenarios»: el mismo modelo con tres juegos de tickets, ticket medio y días de apertura. La columna «Realista» lee el año de crucero del P&L, así que no puede desviarse de él.
A11: 6. Hoja «Personal»: cinco personas y tres jornadas y media, con el bruto del convenio en celda verde y la Seguridad Social a cargo de la empresa DENTRO. Del bruto al coste empresa hay un tercio más: es el salto que más sorprende.
A12: 7. Hoja «Tesorería 12 meses»: el P&L dice si el negocio gana dinero; esta hoja dice si le queda caja para llegar a fin de mes. Trae la estacionalidad mes a mes, la rampa de arranque, el desfase de cobros y pagos y la liquidación trimestral del IVA.
A13: 8. Hoja «Financiación»: de dónde sale el dinero y cuánto cuesta devolverlo. El cuadro de amortización es MENSUAL, con 84 filas, porque la carencia de este caso son seis meses y un cuadro anual no sabe expresar medio año. Abajo, el DSCR año a año: es el número que decide la operación bancaria.
... A26: QUÉ HACE ESTE LIBRO Y QUÉ HACE OTRO (para no teclear dos veces)
A27: Producto o libro | B27: Qué aporta | C27: Qué NO hace este libro
A28: kit-tareas-pasteleria (12 €) | B28: La operación del obrador que ya tienes: plan de producción semanal, encargos, alérgenos de vitrina, temperaturas. | C28: Este libro NO planifica producción ni controla encargos. Toma su resultado en euros y lo proyecta a tres años.
A29: kit-escandallos (12 €) y el libro «carta-de-apertura-y-escandallo» | B29: El coste real de cada pieza, con su mano de obra y su margen. | C29: Aquí el coste de ventas entra como UN porcentaje sobre las ventas: la regla del 32 %. Cuando midas el tuyo, cámbialo en «0. Supuestos».
A30: plan-negocio-panaderia (35 €) | B30: El dossier completo que se le entrega al banco, con memoria escrita. | C30: Este libro es el motor de números de una GUÍA de apertura. Si vas a pedir financiación de verdad, el dossier del banco es aquel producto.
A31: El libro «calculadora-capex-pasteleria» de esta misma guía | B31: El CAPEX partida a partida, la variante del formato y la comparación entre traspaso y obra nueva. | C31: Aquí sólo entran los TOTALES por bloque. Las dos celdas de equipamiento de la hoja de Inversión vienen sembradas y son verdes: sustitúyelas por el total de aquel libro cuando lo tengas cerrado.
A32: En todo este paquete no hay ni una fórmula que apunte a otro fichero. Lo que viene de otro libro viene COPIADO y declarado: un enlace entre ficheros se rompe en cuanto alguien mueve una carpeta, y entonces el libro miente sin avisar.
A34: Cada cuánto se usa este libro
A35: Cadencia: «0. Supuestos» e «Inversión Inicial», MIENTRAS BUSCAS LOCAL y pides presupuestos, tantas veces como haga falta. El P&L, el punto de equilibrio y los escenarios, UNA VEZ ANTES DE FIRMAR y otra antes de sentarte con el banco. «Tesorería 12 meses», CADA MES durante el primer año, sustituyendo la previsión por lo que pasó de verdad. «Canales y Punto Muerto», cada vez que te plantees abrir o cerrar un canal.
A37: Para editar la estructura o una celda que no esté en verde: Revisar > Desproteger hoja (no tiene contraseña).
A39: Diseñado por John Guerrero — chef y consultor gastronómico desde 2010, en cocina desde los 17 años.
A40: Versión 1.0 · septiembre 2026 · aichef.pro/guia-pasteleria-obrador · info@aichef.pro

Sheet 0. Supuestos
A1: Supuestos: las Tasas y los Drivers del Modelo
A2: AI Chef Pro · aichef.pro — Cómo Montar una Pastelería
A3: Cambia las celdas VERDES y el resto del libro se recalcula solo. Las partidas de gasto se teclean en su hoja, no aquí. Cada supuesto lleva al lado de dónde sale y qué pasa si lo mueves.
A5: ACTIVIDAD
A6: Tickets al día en velocidad de crucero | B6: 183 | C6: SUPUESTO. No existe dato público de tráfico de pastelería en España, así que este número no es un benchmark: es el que hace que el modelo tenga qué calcular. Cuéntalos tú en la puerta de tres pastelerías parecidas a la que quieres abrir, un sábado y un martes.
A7: Piezas por ticket | B7: 2.6 | C7: SUPUESTO. De aquí sale el ticket medio, que NO se teclea: se calcula. Publicar un «ticket medio de pastelería» sería inventarse un dato que no existe.
A8: PVP medio ponderado de la carta, CON IVA (€/pieza) | B8: 2.4557 | C8: Sale de las 30 referencias del libro «carta-de-apertura-y-escandallo», ponderadas por su mix de ventas. Si cambias la carta allí, trae aquí el nuevo PVP medio: es COPIA declarada, no un vínculo entre ficheros.
A9: Ticket medio CON IVA (€) | B9: =IFERROR($B$7*$B$8,"") -> 6.38482 | C9: Piezas por ticket x PVP medio ponderado. Es lo que ve el cliente en el datáfono.
A10: Ticket medio SIN IVA (€) | B10: =IFERROR($B$9/(1+$B$20),"") -> 5.8688137 | C10: Es el que entra en el P&L: la cuenta de resultados va siempre sin IVA. Se divide por el IVA MEDIO de la carta, no por un tipo suelto, porque los panes van al 4 % y el resto al 10 %.
A11: Días de apertura al año | B11: 300 | C11: SUPUESTO: 6 días por semana x 52 semanas = 312, menos 12 días de cierre en agosto. Los festivos NO se descuentan: la pastelería tiene libertad horaria por ley estatal cuando es la actividad principal. El MISMO dato lo usan el P&L, el punto de equilibrio y los escenarios.
A12: Actividad del año 1 sobre la de crucero (%) | B12: =IFERROR(SUMPRODUCT('Tesorería 12 meses'!B6:M6,'Tesorería 12 meses'!B7:M7),"") -> 0.87639985 | C12: NO se teclea: sale de la estacionalidad y de la rampa de la hoja de Tesorería. Un local que abre no factura desde el primer día lo que factura a los seis meses, y proyectar el año 1 a velocidad de crucero es el error que más planes de negocio tumba.
A13: Crecimiento de volumen del año 3 (%) | B13: 0.04 | C13: SUPUESTO. El año 2 ya es el de crucero: el año 3 sólo crece lo que dé la clientela fija, no un salto de negocio. Un 4 % es prudente; si pones más, tendrás que decir de dónde sale.
A14: IVA Y TIPOS
A15: IVA de pastelería, bollería y confitería (%) | B15: 0.1 | C15: El 10 % sale de la regla general de alimentos del art. 91.Uno.1.1.o de la Ley 37/1992: no porque un precepto los nombre, sino porque no están en la lista cerrada del 4 % ni excluidos del 10 %.
A16: IVA del pan (%) | B16: 0.04 | C16: TODOS los productos del RD 308/2019 (pan común, pan especial y semielaborados, con o sin gluten) van al 4 %. El cruasán sigue al 10 %: el RD 308/2019 sólo regula el pan y no menciona la bollería.
A17: IVA general (%) | B17: 0.21 | C17: Tipo general del art. 90.Uno de la Ley 37/1992. Es el que soportas en obra, maquinaria, packaging y servicios.
A18: IVA medio de las compras de materia prima (%) | B18: 0.1 | C18: SUPUESTO de trabajo: harinas y azúcares se mueven entre el 4 % y el 10 %, chocolate y mantequilla al 10 %, y el packaging al 21 %. Sólo afecta a la TESORERÍA (lo que adelantas al proveedor), nunca al resultado. Píde a tu distribuidor una factura de ejemplo y afínalo.
A19: Peso del pan sobre las ventas sin IVA (%) | B19: 0.201276 | C19: Sale de la familia «panes de acompañamiento» de la carta del libro 4, ponderada por su mix. Existe porque el pan tributa al 4 % y el resto al 10 %: sin este reparto, la caja y las ventas netas no cuadran.
A20: IVA medio ponderado de la carta (%) | B20: =IFERROR($B$19*$B$16+(1-$B$19)*$B$15,"") -> 0.08792344 | C20: No es un tipo legal: es el que hace falta para pasar de caja a ventas netas cuando vendes a dos tipos distintos.
A21: COSTE DE VENTAS
A22: Coste de ventas sobre las ventas (food cost, %) | B22: 0.32 | C22: REGLA ÚNICA de la casa: margen bruto del 65-70 % equivale a un food cost del 30-35 %, y son la misma regla dicha dos veces. El 32 % es el punto medio. Incluye lo que el escandallo de la pieza deja fuera: producto de terceros que revende el despacho, merma real, packaging y subida de materia prima. Por eso es MAYOR que tu escandallo, y por eso es el supuesto conservador.
A23: Margen bruto objetivo (%) | B23: =IFERROR(1-$B$22,"") -> 0.68 | C23: Se DERIVA del food cost, no se guarda aparte: si se guardaran los dos, antes o después dirían cosas distintas.
A24: PERSONAL
A25: Seguridad Social a cargo de la empresa (%) | B25: 0.33 | C25: Cotización empresarial aproximada sobre el salario bruto (contingencias comunes, desempleo, FOGASA y formación). Ajústala a tu convenio y a tus contratos.
A26: Número de pagas del convenio | B26: 15 | C26: El convenio de pastelería de Madrid paga 15, no 14, y eso cambia el coste mes a mes y el reparto de la tesorería. Busca el tuyo: el convenio es provincial o autonómico.
A27: SMI vigente (€/año, 14 pagas) | B27: 17094 | C27: 1.221 €/mes × 14 pagas = 17.094 €/año — Real Decreto 126/2026, de 18 de febrero (BOE-A-2026-3815), con efectos desde el 1-ene-2026. El convenio provincial de hostelería prevalece si fija un mínimo superior.
A28: Jornada completa (horas/semana) | B28: 40 | C28: SUPUESTO: la jornada anual del convenio de Madrid no se ha verificado. Comprueba la de tu convenio antes de dimensionar turnos.
A29: LOCAL Y GASTOS FIJOS
A30: Alquiler mensual del local (€) | B30: 1200 | C30: SUPUESTO para una ciudad media. Los cinco traspasos de Barcelona del research se mueven entre 850 y 1.300 €/mes para 63-85 m2; aquí se toma la parte baja porque Barcelona no es una ciudad media.
A31: Fianza del alquiler (meses de renta) | B31: 2 | C31: SUPUESTO. La fianza no es un gasto: es un depósito que se recupera. Va en la inversión porque hay que tenerla el día de la firma.
A32: Suministros mensuales de luz, gas y agua (€) | B32: 1450 | C32: SUPUESTO. Con 62 kW instalados y frío 24 horas es la segunda partida del negocio. No se estima: se le pide la simulación a la comercializadora con la potencia del proyecto eléctrico.
A33: Retribución mensual del propietario (€) | B33: 2400 | C33: SUPUESTO, y renglón propio de los fijos con la cuota de autónomos dentro. Si el dueño está en el obrador, su trabajo tiene un coste aunque no se lo pague a fin de mes.
A34: Subida anual de los costes fijos (%) | B34: 0 | C34: A CERO: las tres columnas del P&L están en euros del año 1 (términos reales). Súbela si quieres proyectar en euros corrientes, pero entonces sube también el ticket medio o estarás proyectando una pérdida de margen que no has decidido.
A35: FINANCIACIÓN
A36: Recursos propios aportados (€) | B36: 201826.48 | C36: SUPUESTO sembrado para que el plan quede financiado: es la necesidad total de caja menos el préstamo. Míralo dos veces, porque es mucho dinero: si no lo tienes, o baja la inversión (mira la hoja «Traspaso vs Obra Nueva» del libro de CAPEX) o sube el préstamo, y entonces vigila el DSCR de la hoja de Financiación.
A37: Préstamo bancario solicitado (€) | B37: 60000 | C37: SUPUESTO. Las condiciones las pone tu banco y dependen de la garantía. Pide oferta a dos entidades y a una línea ICO antes de fijarlo.
A38: Tipo de interés nominal anual (%) | B38: 0.062 | C38: SUPUESTO.
A39: Plazo total del préstamo (meses) | B39: 84 | C39: SUPUESTO: 7 años, carencia incluida. El cuadro de amortización de la hoja de Financiación tiene 84 filas; si alargas el plazo por encima de 84 meses, tendrás que añadirlas.
A40: Carencia de principal (meses) | B40: 6 | C40: SUPUESTO, y es lo PRIMERO que hay que negociar: la carencia es lo que hace que el préstamo no se coma la caja justo en la rampa de arranque. Durante la carencia sólo se pagan intereses.
A41: Fondo de maniobra (meses de costes fijos) | B41: 4 | C41: SUPUESTO. Meses de gastos fijos que hay que tener en caja el día que abres. Es una partida de la inversión, no una propina.
A42: FISCAL
A43: Impuesto de Sociedades, entidad de nueva creación (%) | B43: 0.15 | C43: Art. 29.1 de la Ley del Impuesto sobre Sociedades: se aplica al PRIMER ejercicio con base imponible positiva y al siguiente. Si eres autónomo y no sociedad, esta línea no te aplica: tributas en IRPF.
A44: Impuesto de Sociedades, tipo general (%) | B44: 0.25 | C44: A partir del tercer ejercicio con base positiva.
A45: Bases negativas de ejercicios anteriores (€) | B45: 0 | C45: Pérdidas pendientes de compensar al empezar. En una apertura son cero: se rellena si arrancas dentro de una sociedad que ya existía.
A46: AMORTIZACIÓN
A47: Años de amortización del inmovilizado | B47: 10 | C47: SUPUESTO, y en la práctica obra y maquinaria tienen coeficientes distintos. Sin amortización la rentabilidad publicada es mentira: los hornos se gastan.
A48: ARRANQUE
A49: Actividad del mes 1 sobre la de crucero (%) | B49: 0.55 | C49: SUPUESTO. Con el 100 % eliminas la rampa y el año 1 se proyecta como si abrieras a pleno rendimiento, que es justo lo que no pasa.
A50: Meses hasta alcanzar el régimen de crucero | B50: 6 | C50: SUPUESTO. La rampa sube en línea recta desde el porcentaje de arriba hasta el 100 % en este número de meses.
A51: COBROS Y PAGOS
A52: Días medios de cobro | B52: =IFERROR(SUMPRODUCT('Canales y Punto Muerto'!B6:B9,'Canales y Punto Muerto'!F6:F9),"") -> 2.25 | C52: NO se teclea: sale de la hoja «Canales y Punto Muerto», ponderando los días de cobro de cada canal por su peso en las ventas. El mostrador cobra al contado; el B2B, a 45 días, y ahí financias tú.
A53: Días medios de pago a proveedor | B53: 30 | C53: SUPUESTO. Es lo que te financian tus proveedores, y lo primero que se pierde si te retrasas en un pago.
A54: Mes de la primera paga extra (1-12) | B54: 7 | C54: SUPUESTO. Con 15 pagas hay TRES meses en los que la nómina sale doble; escribe aquí en cuáles cae en tu convenio.
A55: Mes de la segunda paga extra (1-12) | B55: 12 | C55: SUPUESTO.
A56: Mes de la tercera paga extra (1-12) | B56: 3 | C56: SUPUESTO. Si tu convenio paga 14, pon aquí un número fuera de 1-12 (por ejemplo 0) y baja a 14 las pagas de arriba.
A57: UMBRALES Y SUELOS DE CONTROL
A58: DSCR mínimo aceptable | B58: 1 | C58: Por debajo de 1 el negocio no genera lo suficiente para pagar el préstamo. Pon el que te exija tu banco en el contrato.
A59: DSCR objetivo (verde) | B59: 1.25 | C59: Lo que suele pedir una entidad para dar el préstamo sin garantías adicionales.
A60: Holgura mínima sobre el punto de equilibrio (%) | B60: 0.15 | C60: Cuánto deben superar las ventas previstas a las del equilibrio de caja (costes fijos y cuota del préstamo). La caída que aguantas es algo menor: con un 15 % de holgura, un 13 % de lo previsto.
A61: Margen neto de referencia, suelo (%) | B61: 0.08 | C61: Rentabilidad neta de una pastelería «yendo bien» declarada por el gerente de una casa de cuarta generación: 8-12 %. No es un objetivo ni un benchmark del sector: es un testimonio, y está aquí para que contrastes tu proyección.
A62: Margen neto de referencia, techo (%) | B62: 0.12 | C62: Si tu proyección sale por encima del 12 %, desconfía de ella antes de enseñarla: casi siempre falta un coste.
A63: Techo de coste de personal sobre ventas (%) | B63: 0.35 | C63: SUPUESTO de control. En un obrador con despacho el personal es la primera partida; por encima de este techo, o subes precios o redimensionas turnos.
A64: Techo de alquiler sobre ventas (%) | B64: 0.1 | C64: SUPUESTO de control. Un alquiler por encima del 10 % de las ventas se come el margen de todo lo demás.
A65: Paso de la sensibilidad del coste variable (€) | B65: 0.2 | C65: Cuánto sube y baja el coste variable por ticket en la tabla de sensibilidad del punto de equilibrio.

Sheet Inversión Inicial
A1: Inversión Inicial: Cuánto Cuesta Abrir
A2: AI Chef Pro · aichef.pro — Cómo Montar una Pastelería
A3: Cada línea lleva su columna «¿Lleva IVA?» y su TIPO. Sin esa columna el CAPEX sale hasta un 21 % desviado, que es el error más caro de todo el proceso. Lo que no tengas presupuestado, déjalo en su valor sembrado y márcalo para pedirlo.
A5: Concepto | B5: Importe (€, base sin IVA) | C5: % s/inversión | D5: ¿Lleva IVA? | E5: Tipo de IVA de la línea | F5: Notas
A6: Obra civil e instalaciones · Obra civil, escenario medio (900 €/m² × 90 m²) | B6: 81000 | C6: =IFERROR(B6/$B$19,"") -> 0.35539471 | D6: Sí | E6: 0.21 | F6: Escenario de referencia. Los otros dos, en `ESCENARIOS_OBRA`. [Fuente: PS-85b]
A7: Equipamiento de obrador · Equipamiento de obrador (dotación de La Clara) | B7: 54296.24 | C7: =IFERROR(B7/$B$19,"") -> 0.23822959 | D7: Sí | E7: 0.21 | F7: Total del bloque, sembrado desde la dotación tipo del libro «checklist-equipamiento-y-proveedores», TODO llevado a base sin IVA. Sustitúyelo por tus presupuestos reales cuando los tengas: es COPIA declarada, no un vínculo entre ficheros. [Fuente: PS-72 + PS-78 + PS-79 + PS-81 + supuesto]
A8: Tienda y vitrina · Tienda y vitrina (dotación de La Clara) | B8: 12684.1 | C8: =IFERROR(B8/$B$19,"") -> 0.055652618 | D8: Sí | E8: 0.21 | F8: Total del bloque, sembrado desde la dotación tipo del libro «checklist-equipamiento-y-proveedores», TODO llevado a base sin IVA. Sustitúyelo por tus presupuestos reales cuando los tengas: es COPIA declarada, no un vínculo entre ficheros. [Fuente: PS-76 + PS-77 + supuesto]
A9: Licencias y proyecto técnico · Proyecto técnico visado | B9: 5000 | C9: =IFERROR(B9/$B$19,"") -> 0.021937945 | D9: Sí | E9: 0.21 | F9: [Fuente: PS-85e]
A10: Licencias y proyecto técnico · Asesoramiento profesional | B10: 1000 | C10: =IFERROR(B10/$B$19,"") -> 0.0043875891 | D10: Sí | E10: 0.21 | F10: [Fuente: PS-85f]
A11: Licencias y proyecto técnico · Tasas municipales de licencia de actividad | B11: 1800 | C11: =IFERROR(B11/$B$19,"") -> 0.0078976603 | D11: No | E11: 0 | F11: Las tasas municipales no llevan IVA, y su importe cambia en cada ayuntamiento: es el número que hay que ir a buscar, no copiar (PA-05). [Fuente: supuesto]
A12: Licencias y proyecto técnico · Comunicación o declaración responsable al registro autonómico | B12: 120 | C12: =IFERROR(B12/$B$19,"") -> 0.00052651069 | D12: No | E12: 0 | F12: No es una licencia y NO habilita para abrir: es un trámite de información que se presenta al iniciar la actividad (PA-04). El importe es supuesto y en varias CCAA es gratuito. [Fuente: PA-04 + supuesto]
A13: Fianza y garantías · Fianza de arrendamiento (2 meses) | B13: 2400 | C13: =IFERROR(B13/$B$19,"") -> 0.010530214 | D13: No | E13: 0 | F13: La fianza no es un gasto: es un depósito que se recupera. Va en el CAPEX porque hay que tenerla el día de la firma. [Fuente: supuesto]
A14: Packaging inicial · Primer pedido de packaging, bolsas, cajas y etiquetas | B14: 2500 | C14: =IFERROR(B14/$B$19,"") -> 0.010968973 | D14: Sí | E14: 0.21 | F14: Empieza con el mínimo del proveedor: el packaging personalizado obliga a pedidos grandes y es dinero parado en el almacén. [Fuente: supuesto]
A15: Marketing de apertura · Marketing de apertura | B15: 5000 | C15: =IFERROR(B15/$B$19,"") -> 0.021937945 | D15: Sí | E15: 0.21 | F15: [Fuente: PS-85g]
A16: Fondo de maniobra · Colchón de tesorería (meses de gastos fijos) | B16: =IFERROR('0. Supuestos'!$B$41*'PyG 3 Años'!C33/12,"") -> 62115.262 | C16: =IFERROR(B16/$B$19,"") -> 0.27253624 | D16: No | E16: 0 | F16: Se calcula: meses de colchón x costes fijos mensuales del año de crucero. No es inversión que se compra, es caja: por eso sale del CAPEX en la fila de abajo. [Fuente: supuesto]
A17: SUBTOTAL DE INVERSIÓN (sin el fondo de maniobra) | B17: =IFERROR(IF(COUNT(B6:B15)=0,"",SUM(B6:B15)),"") -> 165800.34 | C17: =IFERROR(B17/$B$19,"") -> 0.72746376
A18: FONDO DE MANIOBRA | B18: =IFERROR(B16,"") -> 62115.262 | C18: =IFERROR(B18/$B$19,"") -> 0.27253624
A19: INVERSIÓN TOTAL (lo que se compra más la caja del arranque) | B19: =IFERROR(B17+B18,"") -> 227915.6
A20: CAPEX (inversión sin el fondo de maniobra) | B20: =IFERROR(B19-B18,"") -> 165800.34 | F20: Es lo que se COMPRA: obra, equipamiento, licencias, packaging y lanzamiento. El colchón de caja no es inversión, es liquidez.
A21: IVA soportado sobre la inversión (recuperable, pero hay que ADELANTARLO) | B21: =IFERROR(SUMPRODUCT(B6:B16,E6:E16),"") -> 33910.871 | F21: Cada línea a SU tipo, leído de la columna de al lado. Se recupera por el modelo 303, pero tarda: la hoja de Tesorería lo arrastra trimestre a trimestre y esa espera es la partida que más sorprende.
A22: NECESIDAD TOTAL DE CAJA AL ARRANQUE | B22: =IFERROR(B19+B21,"") -> 261826.47 | F22: Es la cifra que tiene que cubrir la hoja de Financiación.
A23: Comprobación: líneas con «Sí» y tipo cero, o al revés | B23: =IFERROR(SUMPRODUCT((D6:D16="Sí")*(E6:E16=0))+SUMPRODUCT((D6:D16="No")*(E6:E16>0)),"") -> 0 | F23: Tiene que valer cero. Si se pone en rojo, una línea dice «Sí» y tiene el tipo a cero (o al revés) y el IVA de la inversión está mal calculado.
A25: BASES DE AMORTIZACIÓN (no suman a la inversión)
A26: Inmovilizado amortizable | B26: =IFERROR(B17-B13-B14,"") -> 160900.34 | F26: Todo el subtotal menos la fianza (es un depósito que se recupera) y el primer pedido de packaging (son existencias, no inmovilizado).
A27: Amortización anual del inmovilizado | B27: =IFERROR(B26/MAX(1,'0. Supuestos'!$B$47),"") -> 16090.034 | F27: Es la línea que entra en los costes fijos del P&L. Sin ella la rentabilidad publicada es mentira: los hornos se gastan.
A29: Todas las cifras de la columna «Importe» van en BASE SIN IVA. El IVA de cada línea se calcula aparte, abajo, para que puedas ver cuánto dinero tienes que adelantar y cuánto vas a recuperar. La renta que pagues ANTES de abrir no está aquí: si la vas a pagar, súmala a la línea de fianza y dilo en su nota, para que el libro de CAPEX y éste sigan diciendo lo mismo.
A31: Listas de validación (no las borres: de aquí salen los desplegables)
A32: ¿Lleva IVA?
A33: Sí
A34: No

Sheet PyG 3 Años
A1: Cuenta de Resultados a 3 Años
A2: AI Chef Pro · aichef.pro — Cómo Montar una Pastelería
A3: El AÑO 2 es el año de crucero: es el que citan la guía y el business plan. El año 1 lleva la rampa de arranque y el año 3 crece sobre el crucero. Sueldo del propietario, amortización e intereses van DENTRO de los costes fijos.
A5: Concepto | B5: Año 1 (arranque) | C5: Año 2 (crucero) | D5: Año 3 | E5: % s/ventas (año 2) | F5: Tipo de IVA de la línea | G5: Notas
A6: INGRESOS
A7: Tickets al día | B7: =IFERROR('0. Supuestos'!$B$6,"") -> 183 | C7: =IFERROR('0. Supuestos'!$B$6,"") -> 183 | D7: =IFERROR(C7*(1+'0. Supuestos'!$B$13),"") -> 190.32 | G7: Los años 1 y 2 comparten el tráfico de crucero; lo que separa al año 1 es la rampa de la fila de abajo, no menos clientes al día en el mes 12.
A8: Ticket medio sin IVA (€) | B8: =IFERROR('0. Supuestos'!$B$10,"") -> 5.8688137 | C8: =IFERROR('0. Supuestos'!$B$10,"") -> 5.8688137 | D8: =IFERROR('0. Supuestos'!$B$10,"") -> 5.8688137 | G8: Constante en euros del año 1: una subida de precios es una decisión aparte, y se toma en la carta, no aquí.
A9: Días de apertura al año | B9: =IFERROR('0. Supuestos'!$B$11,"") -> 300 | C9: =IFERROR('0. Supuestos'!$B$11,"") -> 300 | D9: =IFERROR('0. Supuestos'!$B$11,"") -> 300
A10: Actividad sobre la velocidad de crucero (%) | B10: =IFERROR('0. Supuestos'!$B$12,"") -> 0.87639985 | C10: 1 | D10: 1 | G10: El año 1 lo calcula «0. Supuestos» desde la rampa y la estacionalidad de la hoja de Tesorería. Los años 2 y 3 están al 100 % porque el año 2 es, por definición, el de crucero: si crees que vas a tardar más en llegar, bájalos.
A11: INGRESOS TOTALES (sin IVA) | B11: =IFERROR(IF(B7*B8*B9*B10=0,"",B7*B8*B9*B10),"") -> 282374.17 | C11: =IFERROR(IF(C7*C8*C9*C10=0,"",C7*C8*C9*C10),"") -> 322197.87 | D11: =IFERROR(IF(D7*D8*D9*D10=0,"",D7*D8*D9*D10),"") -> 335085.79 | E11: =IFERROR(C11/$C$11,"") -> 1
A12: Ventas de pastelería, bollería y tartas | B12: =IFERROR(IF(B11="","",B11*(1-'0. Supuestos'!$B$19)),"") -> 225539.02 | C12: =IFERROR(IF(C11="","",C11*(1-'0. Supuestos'!$B$19)),"") -> 257347.17 | D12: =IFERROR(IF(D11="","",D11*(1-'0. Supuestos'!$B$19)),"") -> 267641.06 | E12: =IFERROR(C12/$C$11,"") -> 0.798724 | F12: =IFERROR('0. Supuestos'!$B$15,"") -> 0.1
A13: Ventas de pan de acompañamiento | B13: =IFERROR(IF(B11="","",B11*'0. Supuestos'!$B$19),"") -> 56835.143 | C13: =IFERROR(IF(C11="","",C11*'0. Supuestos'!$B$19),"") -> 64850.699 | D13: =IFERROR(IF(D11="","",D11*'0. Supuestos'!$B$19),"") -> 67444.727 | E13: =IFERROR(C13/$C$11,"") -> 0.201276 | F13: =IFERROR('0. Supuestos'!$B$16,"") -> 0.04 | G13: El pan va al 4 % y todo lo demás al 10 %. Separar las dos líneas no es un capricho contable: es lo que hace que la caja y el modelo 303 cuadren.
A14: COSTES VARIABLES
A15: Coste de ventas (materia prima, packaging y merma) | B15: =IFERROR(IF(B11="","",B11*'0. Supuestos'!$B$22),"") -> 90359.734 | C15: =IFERROR(IF(C11="","",C11*'0. Supuestos'!$B$22),"") -> 103103.32 | D15: =IFERROR(IF(D11="","",D11*'0. Supuestos'!$B$22),"") -> 107227.45 | E15: =IFERROR(C15/$C$11,"") -> 0.32 | F15: =IFERROR('0. Supuestos'!$B$18,"") -> 0.1 | G15: A la REGLA ÚNICA del 32 %, no al food cost de escandallo de la carta: la regla incluye el producto de terceros que revende el despacho, la merma real, el packaging y la subida de la materia prima. Es el supuesto conservador, y la diferencia con tu escandallo es tu colchón.
A16: TOTAL COSTES VARIABLES | B16: =IFERROR(IF(B11="","",SUM(B15:B15)),"") -> 90359.734 | C16: =IFERROR(IF(C11="","",SUM(C15:C15)),"") -> 103103.32 | D16: =IFERROR(IF(D11="","",SUM(D15:D15)),"") -> 107227.45 | E16: =IFERROR(C16/$C$11,"") -> 0.32
A17: MARGEN BRUTO | B17: =IFERROR(IF(B11="","",B11-B16),"") -> 192014.43 | C17: =IFERROR(IF(C11="","",C11-C16),"") -> 219094.55 | D17: =IFERROR(IF(D11="","",D11-D16),"") -> 227858.34 | E17: =IFERROR(C17/$C$11,"") -> 0.68
A18: COSTES FIJOS
A19: Personal (nóminas y Seguridad Social) | B19: =IFERROR(IF(B11="","",'Personal'!$I$11),"") -> 92776.079 | C19: =IFERROR(IF(C11="","",'Personal'!$I$11),"") -> 92776.079 | D19: =IFERROR(IF(D11="","",'Personal'!$I$11),"") -> 92776.079 | E19: =IFERROR(C19/$C$11,"") -> 0.28794752 | F19: 0 | G19: Sale de la hoja de Personal: es el MISMO número, no una estimación aparte. Las nóminas no llevan IVA. Si contratas a alguien en el año 2 o el 3, añádelo allí y aquí se ve.
A20: Retribución del propietario (incluida la cuota de autónomos) | B20: =IFERROR(IF(B11="","",'0. Supuestos'!$B$33*12),"") -> 28800 | C20: =IFERROR(IF(C11="","",B20*(1+'0. Supuestos'!$B$34)),"") -> 28800 | D20: =IFERROR(IF(D11="","",C20*(1+'0. Supuestos'!$B$34)),"") -> 28800 | E20: =IFERROR(C20/$C$11,"") -> 0.089386065 | F20: 0 | G20: Renglón propio, y no está dentro de la plantilla de cinco personas. Un negocio que sólo es rentable porque su dueño no cobra no es rentable.
A21: Alquiler del local | B21: =IFERROR(IF(B11="","",'0. Supuestos'!$B$30*12),"") -> 14400 | C21: =IFERROR(IF(C11="","",B21*(1+'0. Supuestos'!$B$34)),"") -> 14400 | D21: =IFERROR(IF(D11="","",C21*(1+'0. Supuestos'!$B$34)),"") -> 14400 | E21: =IFERROR(C21/$C$11,"") -> 0.044693033 | F21: =IFERROR('0. Supuestos'!$B$17,"") -> 0.21 | G21: El importe mensual está en «0. Supuestos»; aquí se multiplica por doce. El arrendamiento de local de negocio lleva IVA al tipo general.
A22: Suministros (electricidad, gas y agua) | B22: =IFERROR(IF(B11="","",'0. Supuestos'!$B$32*12),"") -> 17400 | C22: =IFERROR(IF(C11="","",B22*(1+'0. Supuestos'!$B$34)),"") -> 17400 | D22: =IFERROR(IF(D11="","",C22*(1+'0. Supuestos'!$B$34)),"") -> 17400 | E22: =IFERROR(C22/$C$11,"") -> 0.054004081 | F22: =IFERROR('0. Supuestos'!$B$17,"") -> 0.21 | G22: Luz y gas van al 21 %; el agua, al 10 %. El libro aplica a toda la partida el tipo de la columna de al lado: si el agua te pesa, sepárala en su propia línea.
A23: Seguros (responsabilidad civil y continente) | B23: 1440 | C23: =IFERROR(IF(C11="","",B23*(1+'0. Supuestos'!$B$34)),"") -> 1440 | D23: =IFERROR(IF(D11="","",C23*(1+'0. Supuestos'!$B$34)),"") -> 1440 | E23: =IFERROR(C23/$C$11,"") -> 0.0044693033 | F23: 0 | G23: Supuesto. El de RC no está verificado como obligatorio: depende de tu CCAA. Las operaciones de seguro están exentas de IVA (art. 20.Uno.16 de la Ley 37/1992), y por eso su tipo va a cero.
A24: Gestoría y asesoría | B24: 2640 | C24: =IFERROR(IF(C11="","",B24*(1+'0. Supuestos'!$B$34)),"") -> 2640 | D24: =IFERROR(IF(D11="","",C24*(1+'0. Supuestos'!$B$34)),"") -> 2640 | E24: =IFERROR(C24/$C$11,"") -> 0.0081937226 | F24: 0.21 | G24: Supuesto.
A25: Software, TPV y pasarela de cobro | B25: 720 | C25: =IFERROR(IF(C11="","",B25*(1+'0. Supuestos'!$B$34)),"") -> 720 | D25: =IFERROR(IF(D11="","",C25*(1+'0. Supuestos'!$B$34)),"") -> 720 | E25: =IFERROR(C25/$C$11,"") -> 0.0022346516 | F25: 0.21 | G25: Supuesto. Con Verifactu en el horizonte esta cuota deja de ser opcional.
A26: Telefonía e internet | B26: 660 | C26: =IFERROR(IF(C11="","",B26*(1+'0. Supuestos'!$B$34)),"") -> 660 | D26: =IFERROR(IF(D11="","",C26*(1+'0. Supuestos'!$B$34)),"") -> 660 | E26: =IFERROR(C26/$C$11,"") -> 0.0020484307 | F26: 0.21 | G26: Supuesto.
A27: Limpieza y consumibles | B27: 2160 | C27: =IFERROR(IF(C11="","",B27*(1+'0. Supuestos'!$B$34)),"") -> 2160 | D27: =IFERROR(IF(D11="","",C27*(1+'0. Supuestos'!$B$34)),"") -> 2160 | E27: =IFERROR(C27/$C$11,"") -> 0.0067039549 | F27: 0.21 | G27: Supuesto.
A28: Mantenimiento de equipos | B28: 1800 | C28: =IFERROR(IF(C11="","",B28*(1+'0. Supuestos'!$B$34)),"") -> 1800 | D28: =IFERROR(IF(D11="","",C28*(1+'0. Supuestos'!$B$34)),"") -> 1800 | E28: =IFERROR(C28/$C$11,"") -> 0.0055866291 | F28: 0.21 | G28: Supuesto. Con horno de gas, súmale la inspección periódica obligatoria cada 5 años, que se te repercute.
A29: Publicidad y redes | B29: 2400 | C29: =IFERROR(IF(C11="","",B29*(1+'0. Supuestos'!$B$34)),"") -> 2400 | D29: =IFERROR(IF(D11="","",C29*(1+'0. Supuestos'!$B$34)),"") -> 2400 | E29: =IFERROR(C29/$C$11,"") -> 0.0074488388 | F29: 0.21 | G29: Supuesto.
A30: Otros gastos de estructura | B30: 1800 | C30: =IFERROR(IF(C11="","",B30*(1+'0. Supuestos'!$B$34)),"") -> 1800 | D30: =IFERROR(IF(D11="","",C30*(1+'0. Supuestos'!$B$34)),"") -> 1800 | E30: =IFERROR(C30/$C$11,"") -> 0.0055866291 | F30: 0.21 | G30: Supuesto.
A31: Amortización del inmovilizado | B31: =IFERROR(IF(B11="","",'Inversión Inicial'!$B$27),"") -> 16090.034 | C31: =IFERROR(IF(C11="","",'Inversión Inicial'!$B$27),"") -> 16090.034 | D31: =IFERROR(IF(D11="","",'Inversión Inicial'!$B$27),"") -> 16090.034 | E31: =IFERROR(C31/$C$11,"") -> 0.049938362 | F31: 0 | G31: Sale de la base de amortización de la hoja de Inversión. No sube con el IPC: es un reparto contable de una inversión ya hecha.
A32: Gastos financieros del préstamo | B32: =IFERROR(IF(B11="","",'Financiación'!$B$116),"") -> 3671.1048 | C32: =IFERROR(IF(C11="","",'Financiación'!$B$117),"") -> 3259.673 | D32: =IFERROR(IF(D11="","",'Financiación'!$B$118),"") -> 2750.6598 | E32: =IFERROR(C32/$C$11,"") -> 0.010116991 | F32: 0 | G32: Sólo los INTERESES son gasto. La devolución del principal sale de la caja pero no del resultado: va en la hoja de Tesorería.
A33: TOTAL COSTES FIJOS | B33: =IFERROR(IF(B11="","",SUM(B19:B32)),"") -> 186757.22 | C33: =IFERROR(IF(C11="","",SUM(C19:C32)),"") -> 186345.79 | D33: =IFERROR(IF(D11="","",SUM(D19:D32)),"") -> 185836.77 | E33: =IFERROR(C33/$C$11,"") -> 0.57835821
A34: IVA soportado de los costes variables | B34: =IFERROR(IF(B11="","",B15*$F$15),"") -> 9035.9734 | C34: =IFERROR(IF(C11="","",C15*$F$15),"") -> 10310.332 | D34: =IFERROR(IF(D11="","",D15*$F$15),"") -> 10722.745
A35: IVA soportado de los costes fijos | B35: =IFERROR(IF(B11="","",SUMPRODUCT(B19:B32,$F$19:$F$32)),"") -> 9235.8 | C35: =IFERROR(IF(C11="","",SUMPRODUCT(C19:C32,$F$19:$F$32)),"") -> 9235.8 | D35: =IFERROR(IF(D11="","",SUMPRODUCT(D19:D32,$F$19:$F$32)),"") -> 9235.8 | G35: Cada línea a SU tipo, leído de la columna de al lado. Es lo que la hoja de Tesorería paga de más a los proveedores y luego recupera en el modelo 303.
A36: RESULTADO ANTES DE IMPUESTOS | B36: =IFERROR(IF(B11="","",B17-B33),"") -> 5257.2164 | C36: =IFERROR(IF(C11="","",C17-C33),"") -> 32748.768 | D36: =IFERROR(IF(D11="","",D17-D33),"") -> 42021.563 | E36: =IFERROR(C36/$C$11,"") -> 0.10164179
A37: Bases negativas pendientes al inicio | B37: =IFERROR(IF(B11="","",'0. Supuestos'!$B$45),"") -> 0 | C37: =IFERROR(IF(C11="","",B42),"") -> 0 | D37: =IFERROR(IF(D11="","",C42),"") -> 0 | G37: Art. 26 de la Ley del Impuesto sobre Sociedades: las pérdidas de un ejercicio se compensan con los beneficios de los siguientes.
A38: Base imponible (después de compensar) | B38: =IFERROR(IF(B11="","",MAX(0,B36-B37)),"") -> 5257.2164 | C38: =IFERROR(IF(C11="","",MAX(0,C36-C37)),"") -> 32748.768 | D38: =IFERROR(IF(D11="","",MAX(0,D36-D37)),"") -> 42021.563
A39: Ejercicios con base positiva (acumulado) | B39: =IFERROR(IF(B11="","",IF(B38>0,1,0)),"") -> 1 | C39: =IFERROR(IF(C11="","",B39+IF(C38>0,1,0)),"") -> 2 | D39: =IFERROR(IF(D11="","",C39+IF(D38>0,1,0)),"") -> 3
A40: Tipo de Impuesto de Sociedades aplicado | B40: =IFERROR(IF(B11="","",IF(B38<=0,"",IF(B39<=2,'0. Supuestos'!$B$43,'0. Supuestos'!$B$44))),"") -> 0.15 | C40: =IFERROR(IF(C11="","",IF(C38<=0,"",IF(C39<=2,'0. Supuestos'!$B$43,'0. Supuestos'!$B$44))),"") -> 0.15 | D40: =IFERROR(IF(D11="","",IF(D38<=0,"",IF(D39<=2,'0. Supuestos'!$B$43,'0. Supuestos'!$B$44))),"") -> 0.25 | G40: El 15 % de entidad de nueva creación se aplica al PRIMER ejercicio con base positiva y al siguiente, no a los dos primeros años naturales. Si tributas en IRPF, esta línea no te aplica.
A41: Impuesto de Sociedades | B41: =IFERROR(IF(B11="","",IF(B40="",0,B38*B40)),"") -> 788.58246 | C41: =IFERROR(IF(C11="","",IF(C40="",0,C38*C40)),"") -> 4912.3152 | D41: =IFERROR(IF(D11="","",IF(D40="",0,D38*D40)),"") -> 10505.391
A42: Bases negativas pendientes al cierre | B42: =IFERROR(IF(B11="","",MAX(0,B37-B36)),"") -> 0 | C42: =IFERROR(IF(C11="","",MAX(0,C37-C36)),"") -> 0 | D42: =IFERROR(IF(D11="","",MAX(0,D37-D36)),"") -> 0
A43: RESULTADO NETO | B43: =IFERROR(IF(B11="","",B36-B41),"") -> 4468.634 | C43: =IFERROR(IF(C11="","",C36-C41),"") -> 27836.453 | D43: =IFERROR(IF(D11="","",D36-D41),"") -> 31516.172 | E43: =IFERROR(C43/$C$11,"") -> 0.08639552
A44: RATIOS CLAVE
A45: Ratio | B45: Año 1 | C45: Año 2 | D45: Año 3 | E45: Umbral | G45: Comentario
A46: Margen bruto / ventas | B46: =IFERROR(IF(B11="","",B17/B11),"") -> 0.68 | C46: =IFERROR(IF(C11="","",C17/C11),"") -> 0.68 | D46: =IFERROR(IF(D11="","",D17/D11),"") -> 0.68 | E46: =IFERROR('0. Supuestos'!$B$23,"") -> 0.68 | G46: El suelo es la regla única de margen del propio libro. Por debajo, o suben los precios o baja el coste de la materia prima.
A47: Coste de ventas / ventas | B47: =IFERROR(IF(B11="","",B15/B11),"") -> 0.32 | C47: =IFERROR(IF(C11="","",C15/C11),"") -> 0.32 | D47: =IFERROR(IF(D11="","",D15/D11),"") -> 0.32 | E47: =IFERROR('0. Supuestos'!$B$22,"") -> 0.32 | G47: Es el food cost proyectado. Cuando midas el tuyo con el escandallo, cámbialo en «0. Supuestos» y mira qué le pasa a este cuadro.
A48: Coste de personal / ventas | B48: =IFERROR(IF(B11="","",B19/B11),"") -> 0.32855725 | C48: =IFERROR(IF(C11="","",C19/C11),"") -> 0.28794752 | D48: =IFERROR(IF(D11="","",D19/D11),"") -> 0.27687262 | E48: =IFERROR('0. Supuestos'!$B$63,"") -> 0.35 | G48: En un obrador con despacho el personal es la primera partida. Por encima del techo, o subes precios o redimensionas turnos.
A49: Alquiler / ventas | B49: =IFERROR(IF(B11="","",B21/B11),"") -> 0.050996166 | C49: =IFERROR(IF(C11="","",C21/C11),"") -> 0.044693033 | D49: =IFERROR(IF(D11="","",D21/D11),"") -> 0.04297407 | E49: =IFERROR('0. Supuestos'!$B$64,"") -> 0.1 | G49: Un alquiler por encima del techo se come el margen de todo lo demás, y no se renegocia una vez firmado.
A50: Resultado neto / ventas | B50: =IFERROR(IF(B11="","",B43/B11),"") -> 0.015825222 | C50: =IFERROR(IF(C11="","",C43/C11),"") -> 0.08639552 | D50: =IFERROR(IF(D11="","",D43/D11),"") -> 0.094054041 | E50: =IFERROR('0. Supuestos'!$B$61,"") -> 0.08 | G50: El suelo es el extremo bajo de la banda de referencia declarada por un pastelero de cuarta generación sobre su propia casa (8-12 %).
A51: Margen neto dentro de la banda de referencia (8-12 %) | B51: =IFERROR(IF(B50="","",IF(AND(B50>='0. Supuestos'!$B$61,B50<='0. Supuestos'!$B$62),"Sí","No: revísalo")),"") -> No: revísalo | C51: =IFERROR(IF(C50="","",IF(AND(C50>='0. Supuestos'!$B$61,C50<='0. Supuestos'!$B$62),"Sí","No: revísalo")),"") -> Sí | D51: =IFERROR(IF(D50="","",IF(AND(D50>='0. Supuestos'!$B$61,D50<='0. Supuestos'!$B$62),"Sí","No: revísalo")),"") -> Sí | G51: Si sale por ENCIMA del 12 %, desconfía antes de enseñarlo: casi siempre falta un coste. Si sale por debajo del 8 %, el negocio no está mal planteado por fuerza, pero tiene poco donde caerse.
A52: Punto de equilibrio alcanzado | B52: =IFERROR(IF(B11="","",IF(B11>='Punto de Equilibrio'!$B$17,"Sí","No")),"") -> Sí | C52: =IFERROR(IF(C11="","",IF(C11>='Punto de Equilibrio'!$C$17,"Sí","No")),"") -> Sí | D52: =IFERROR(IF(D11="","",IF(D11>='Punto de Equilibrio'!$D$17,"Sí","No")),"") -> Sí | G52: Compara las ventas de CADA año con el umbral contable de ese mismo año, que calcula la hoja «Punto de Equilibrio». El umbral de caja, que es el que de verdad te deja dormir, está allí.
A54: Todas las cifras van SIN IVA. Las columnas de los años 2 y 3 están en euros del año 1 mientras la «Subida anual de los costes fijos» de «0. Supuestos» valga cero. Y una advertencia que vale dinero: si tu proyección del año 1 sale en positivo, míralo dos veces. Casi ninguna apertura gana dinero el primer año, y lo que decide si sobrevives no es este cuadro sino la hoja de Tesorería.

Sheet Punto de Equilibrio
A1: Punto de Equilibrio: Cuántos Tickets al Día
A2: AI Chef Pro · aichef.pro — Cómo Montar una Pastelería
A3: Dos umbrales, y no dicen lo mismo. El CONTABLE incluye la amortización; el de CAJA le quita la amortización (que no se paga) y le suma la devolución de principal (que sí). El segundo es el que decide si llegas a fin de mes.
A5: Variable | B5: Año 1 | C5: Año 2 | D5: Año 3 | E5: Notas
A6: DATOS BASE POR AÑO
A7: Costes fijos anuales | B7: =IFERROR(IF('PyG 3 Años'!B11="","",'PyG 3 Años'!B33),"") -> 186757.22 | C7: =IFERROR(IF('PyG 3 Años'!C11="","",'PyG 3 Años'!C33),"") -> 186345.79 | D7: =IFERROR(IF('PyG 3 Años'!D11="","",'PyG 3 Años'!D33),"") -> 185836.77 | E7: Los MISMOS costes fijos del P&L. Cada año tiene los suyos: por eso el umbral no puede ser uno solo para los tres.
A8: Costes fijos mensuales | B8: =IFERROR(IF('PyG 3 Años'!B11="","",B7/12),"") -> 15563.101 | C8: =IFERROR(IF('PyG 3 Años'!C11="","",C7/12),"") -> 15528.815 | D8: =IFERROR(IF('PyG 3 Años'!D11="","",D7/12),"") -> 15486.398
A9: Ticket medio sin IVA (€) | B9: =IFERROR(IF('PyG 3 Años'!B11="","",'PyG 3 Años'!B8),"") -> 5.8688137 | C9: =IFERROR(IF('PyG 3 Años'!C11="","",'PyG 3 Años'!C8),"") -> 5.8688137 | D9: =IFERROR(IF('PyG 3 Años'!D11="","",'PyG 3 Años'!D8),"") -> 5.8688137
A10: Coste variable por ticket (€) | B10: =IFERROR(IF('PyG 3 Años'!B11="","",'PyG 3 Años'!B16/('PyG 3 Años'!B7*'PyG 3 Años'!B9*'PyG 3 Años'!B10)),"") -> 1.8780204 | C10: =IFERROR(IF('PyG 3 Años'!C11="","",'PyG 3 Años'!C16/('PyG 3 Años'!C7*'PyG 3 Años'!C9*'PyG 3 Años'!C10)),"") -> 1.8780204 | D10: =IFERROR(IF('PyG 3 Años'!D11="","",'PyG 3 Años'!D16/('PyG 3 Años'!D7*'PyG 3 Años'!D9*'PyG 3 Años'!D10)),"") -> 1.8780204 | E10: Sale del total de costes variables del P&L dividido por los tickets de ese año, no de una estimación aparte.
A11: Margen de contribución por ticket (€) | B11: =IFERROR(IF('PyG 3 Años'!B11="","",B9-B10),"") -> 3.9907933 | C11: =IFERROR(IF('PyG 3 Años'!C11="","",C9-C10),"") -> 3.9907933 | D11: =IFERROR(IF('PyG 3 Años'!D11="","",D9-D10),"") -> 3.9907933 | E11: Ticket menos coste variable unitario. Es lo que deja cada cliente para pagar los fijos.
A12: Días de apertura al año | B12: =IFERROR(IF('PyG 3 Años'!B11="","",'PyG 3 Años'!B9),"") -> 300 | C12: =IFERROR(IF('PyG 3 Años'!C11="","",'PyG 3 Años'!C9),"") -> 300 | D12: =IFERROR(IF('PyG 3 Años'!D11="","",'PyG 3 Años'!D9),"") -> 300
A13: Devolución de principal del año (sale de caja) | B13: =IFERROR(IF('PyG 3 Años'!B11="","",'Financiación'!$C$116),"") -> 3808.3297 | C13: =IFERROR(IF('PyG 3 Años'!C11="","",'Financiación'!$C$117),"") -> 7979.196 | D13: =IFERROR(IF('PyG 3 Años'!D11="","",'Financiación'!$C$118),"") -> 8488.2092 | E13: El principal NO es gasto del P&L, pero sale de la caja. Sin él, el umbral de equilibrio se publica por debajo de lo que de verdad hay que facturar.
A14: PUNTO DE EQUILIBRIO CONTABLE (incluye la amortización)
A15: Tickets necesarios al año | B15: =IFERROR(IF('PyG 3 Años'!B11="","",IF(B11<=0,"",B7/B11)),"") -> 46797.016 | C15: =IFERROR(IF('PyG 3 Años'!C11="","",IF(C11<=0,"",C7/C11)),"") -> 46693.92 | D15: =IFERROR(IF('PyG 3 Años'!D11="","",IF(D11<=0,"",D7/D11)),"") -> 46566.373
A16: Tickets necesarios al día | B16: =IFERROR(IF('PyG 3 Años'!B11="","",B15/B12),"") -> 155.99005 | C16: =IFERROR(IF('PyG 3 Años'!C11="","",C15/C12),"") -> 155.6464 | D16: =IFERROR(IF('PyG 3 Años'!D11="","",D15/D12),"") -> 155.22124
A17: Ingresos necesarios al año (sin IVA) | B17: =IFERROR(IF('PyG 3 Años'!B11="","",B15*B9),"") -> 274642.97 | C17: =IFERROR(IF('PyG 3 Años'!C11="","",C15*C9),"") -> 274037.92 | D17: =IFERROR(IF('PyG 3 Años'!D11="","",D15*D9),"") -> 273289.37
A18: Ingresos necesarios al mes (sin IVA) | B18: =IFERROR(IF('PyG 3 Años'!B11="","",B17/12),"") -> 22886.914 | C18: =IFERROR(IF('PyG 3 Años'!C11="","",C17/12),"") -> 22836.493 | D18: =IFERROR(IF('PyG 3 Años'!D11="","",D17/12),"") -> 22774.114
A19: PUNTO DE EQUILIBRIO DE CAJA (incluye la cuota del préstamo)
A20: Costes fijos de caja más el principal del año | B20: =IFERROR(IF('PyG 3 Años'!B11="","",B7-'PyG 3 Años'!B31+B13),"") -> 174475.51 | C20: =IFERROR(IF('PyG 3 Años'!C11="","",C7-'PyG 3 Años'!C31+C13),"") -> 178234.95 | D20: =IFERROR(IF('PyG 3 Años'!D11="","",D7-'PyG 3 Años'!D31+D13),"") -> 178234.95 | E20: Los fijos del P&L sin la amortización (que no se paga) y CON la devolución de principal (que sí). Es el umbral que decide si sobrevives, no el contable.
A21: Tickets necesarios al año (caja) | B21: =IFERROR(IF('PyG 3 Años'!B11="","",IF(B11<=0,"",B20/B11)),"") -> 43719.506 | C21: =IFERROR(IF('PyG 3 Años'!C11="","",IF(C11<=0,"",C20/C11)),"") -> 44661.533 | D21: =IFERROR(IF('PyG 3 Años'!D11="","",IF(D11<=0,"",D20/D11)),"") -> 44661.533
A22: Tickets necesarios al día (caja) | B22: =IFERROR(IF('PyG 3 Años'!B11="","",B21/B12),"") -> 145.73169 | C22: =IFERROR(IF('PyG 3 Años'!C11="","",C21/C12),"") -> 148.87178 | D22: =IFERROR(IF('PyG 3 Años'!D11="","",D21/D12),"") -> 148.87178
A23: Ingresos necesarios al año (caja, sin IVA) | B23: =IFERROR(IF('PyG 3 Años'!B11="","",B21*B9),"") -> 256581.64 | C23: =IFERROR(IF('PyG 3 Años'!C11="","",C21*C9),"") -> 262110.22 | D23: =IFERROR(IF('PyG 3 Años'!D11="","",D21*D9),"") -> 262110.22
A24: CONTRASTE CON EL PLAN
A25: Tickets al día previstos en el plan | B25: =IFERROR(IF('PyG 3 Años'!B11="","",'PyG 3 Años'!B7*'PyG 3 Años'!B10),"") -> 160.38117 | C25: =IFERROR(IF('PyG 3 Años'!C11="","",'PyG 3 Años'!C7*'PyG 3 Años'!C10),"") -> 183 | D25: =IFERROR(IF('PyG 3 Años'!D11="","",'PyG 3 Años'!D7*'PyG 3 Años'!D10),"") -> 190.32
A26: Holgura sobre el equilibrio de CAJA (%) | B26: =IFERROR(IF('PyG 3 Años'!B11="","",IF(B22<=0,"",B25/B22-1)),"") -> 0.10052368 | C26: =IFERROR(IF('PyG 3 Años'!C11="","",IF(C22<=0,"",C25/C22-1)),"") -> 0.22924576 | D26: =IFERROR(IF('PyG 3 Años'!D11="","",IF(D22<=0,"",D25/D22-1)),"") -> 0.27841559 | E26: Cuánto superan tus ventas previstas a las del equilibrio de caja. La caída que aguantas antes de no poder pagar los fijos y la cuota es algo menor: con un 25 % de holgura, un 20 %. El mínimo exigible está en «0. Supuestos».
A27: Lectura de la holgura | B27: =IFERROR(IF('PyG 3 Años'!B11="","",IF(B26<0,"Por debajo del equilibrio",IF(B26<'0. Supuestos'!$B$60,"Ajustada","Suficiente"))),"") -> Ajustada | C27: =IFERROR(IF('PyG 3 Años'!C11="","",IF(C26<0,"Por debajo del equilibrio",IF(C26<'0. Supuestos'!$B$60,"Ajustada","Suficiente"))),"") -> Suficiente | D27: =IFERROR(IF('PyG 3 Años'!D11="","",IF(D26<0,"Por debajo del equilibrio",IF(D26<'0. Supuestos'!$B$60,"Ajustada","Suficiente"))),"") -> Suficiente
A28: Lectura rápida: si los tickets al día previstos están por debajo de los tickets al día de CAJA, el negocio no genera para pagar los fijos y la cuota, y da igual lo que diga el resultado contable. Si están justo por encima, no tienes margen para un mes malo: negocia carencia, baja inversión o revisa el ticket medio antes de firmar nada.
A30: SENSIBILIDAD DEL PUNTO DE EQUILIBRIO (año de crucero)
A31: Tickets al día necesarios: ticket medio (columnas) x coste variable por ticket (filas) | B31: =IFERROR($C$9-1,"") -> 4.8688137 | C31: =IFERROR($C$9,"") -> 5.8688137 | D31: =IFERROR($C$9+1,"") -> 6.8688137 | E31: =IFERROR($C$9+2,"") -> 7.8688137
A32: =IFERROR($C$10-2*'0. Supuestos'!$B$65,"") -> 1.4780204 | B32: =IFERROR(IF(B$31-$A32<=0,"",$C$7/(B$31-$A32)/$C$12),"") -> 183.18799 | C32: =IFERROR(IF(C$31-$A32<=0,"",$C$7/(C$31-$A32)/$C$12),"") -> 141.46706 | D32: =IFERROR(IF(D$31-$A32<=0,"",$C$7/(D$31-$A32)/$C$12),"") -> 115.22471 | E32: =IFERROR(IF(E$31-$A32<=0,"",$C$7/(E$31-$A32)/$C$12),"") -> 97.194916
A33: =IFERROR($C$10-1*'0. Supuestos'!$B$65,"") -> 1.6780204 | B33: =IFERROR(IF(B$31-$A33<=0,"",$C$7/(B$31-$A33)/$C$12),"") -> 194.67028 | C33: =IFERROR(IF(C$31-$A33<=0,"",$C$7/(C$31-$A33)/$C$12),"") -> 148.21839 | D33: =IFERROR(IF(D$31-$A33<=0,"",$C$7/(D$31-$A33)/$C$12),"") -> 119.66429 | E33: =IFERROR(IF(E$31-$A33<=0,"",$C$7/(E$31-$A33)/$C$12),"") -> 100.3349
A34: =IFERROR($C$10,"") -> 1.8780204 | B34: =IFERROR(IF(B$31-$A34<=0,"",$C$7/(B$31-$A34)/$C$12),"") -> 207.68825 | C34: =IFERROR(IF(C$31-$A34<=0,"",$C$7/(C$31-$A34)/$C$12),"") -> 155.6464 | D34: =IFERROR(IF(D$31-$A34<=0,"",$C$7/(D$31-$A34)/$C$12),"") -> 124.4597 | E34: =IFERROR(IF(E$31-$A34<=0,"",$C$7/(E$31-$A34)/$C$12),"") -> 103.68453
A35: =IFERROR($C$10+1*'0. Supuestos'!$B$65,"") -> 2.0780204 | B35: =IFERROR(IF(B$31-$A35<=0,"",$C$7/(B$31-$A35)/$C$12),"") -> 222.57206 | C35: =IFERROR(IF(C$31-$A35<=0,"",$C$7/(C$31-$A35)/$C$12),"") -> 163.85821 | D35: =IFERROR(IF(D$31-$A35<=0,"",$C$7/(D$31-$A35)/$C$12),"") -> 129.65548 | E35: =IFERROR(IF(E$31-$A35<=0,"",$C$7/(E$31-$A35)/$C$12),"") -> 107.26555
A36: =IFERROR($C$10+2*'0. Supuestos'!$B$65,"") -> 2.2780204 | B36: =IFERROR(IF(B$31-$A36<=0,"",$C$7/(B$31-$A36)/$C$12),"") -> 239.75383 | C36: =IFERROR(IF(C$31-$A36<=0,"",$C$7/(C$31-$A36)/$C$12),"") -> 172.98479 | D36: =IFERROR(IF(D$31-$A36<=0,"",$C$7/(D$31-$A36)/$C$12),"") -> 135.30398 | E36: =IFERROR(IF(E$31-$A36<=0,"",$C$7/(E$31-$A36)/$C$12),"") -> 111.10277
A38: La celda del centro es tu escenario. Muévete una columna a la izquierda y estarás viendo qué pasa si tienes que bajar el ticket medio un euro; una fila hacia abajo, qué pasa si la mantequilla y el cacao te suben el coste variable. Los dos movimientos han pasado en los últimos tres años.

Sheet Escenarios
A1: Escenarios: Pesimista, Realista y Optimista
A2: AI Chef Pro · aichef.pro — Cómo Montar una Pastelería
A3: La columna «Realista» LEE el año de crucero del P&L, así que no puede desviarse de él. Las otras dos son verdes: son tus apuestas, y la de la izquierda es la que hay que poder sobrevivir.
A5: Métrica | B5: Pesimista | C5: Realista | D5: Optimista | E5: Notas
A6: Tickets al día | B6: 140 | C6: =IFERROR('PyG 3 Años'!C7,"") -> 183 | D6: 220 | E6: SUPUESTOS los dos extremos. El pesimista no es «un mal día»: es el año entero yendo mal.
A7: Ticket medio sin IVA (€) | B7: 5.2 | C7: =IFERROR('PyG 3 Años'!C8,"") -> 5.8688137 | D7: 6.6 | E7: SUPUESTOS. Bajar el ticket medio un euro pesa más que perder veinte clientes al día: míralo en la tabla de sensibilidad del punto de equilibrio.
A8: Días de apertura al año | B8: 290 | C8: =IFERROR('PyG 3 Años'!C9,"") -> 300 | D8: 305 | E8: SUPUESTOS.
A9: INGRESOS ANUALES (sin IVA) | B9: =IFERROR(IF(B6*B7*B8=0,"",B6*B7*B8),"") -> 211120 | C9: =IFERROR(IF(C6*C7*C8=0,"",C6*C7*C8),"") -> 322197.87 | D9: =IFERROR(IF(D6*D7*D8=0,"",D6*D7*D8),"") -> 442860
A10: Coste de ventas (regla única del food cost) | B10: =IFERROR(IF(B9="","",B9*'0. Supuestos'!$B$22),"") -> 67558.4 | C10: =IFERROR(IF(C9="","",C9*'0. Supuestos'!$B$22),"") -> 103103.32 | D10: =IFERROR(IF(D9="","",D9*'0. Supuestos'!$B$22),"") -> 141715.2
A11: TOTAL COSTES VARIABLES | B11: =IFERROR(IF(B9="","",SUM(B10:B10)),"") -> 67558.4 | C11: =IFERROR(IF(C9="","",SUM(C10:C10)),"") -> 103103.32 | D11: =IFERROR(IF(D9="","",SUM(D10:D10)),"") -> 141715.2
A12: MARGEN BRUTO | B12: =IFERROR(IF(B9="","",B9-B11),"") -> 143561.6 | C12: =IFERROR(IF(C9="","",C9-C11),"") -> 219094.55 | D12: =IFERROR(IF(D9="","",D9-D11),"") -> 301144.8
A13: COSTES FIJOS (los del año de crucero del P&L) | B13: =IFERROR(IF(B9="","",'PyG 3 Años'!$C$33),"") -> 186345.79 | C13: =IFERROR(IF(C9="","",'PyG 3 Años'!$C$33),"") -> 186345.79 | D13: =IFERROR(IF(D9="","",'PyG 3 Años'!$C$33),"") -> 186345.79 | E13: Los costes fijos no cambian con el escenario: por eso son fijos. Si en el pesimista se disparan sobre las ventas, el ajuste hay que hacerlo en la hoja de Personal, no aquí.
A14: RESULTADO ANTES DE IMPUESTOS | B14: =IFERROR(IF(B9="","",B12-B13),"") -> -42784.185 | C14: =IFERROR(IF(C9="","",C12-C13),"") -> 32748.768 | D14: =IFERROR(IF(D9="","",D12-D13),"") -> 114799.01
A15: Impuesto de Sociedades | B15: =IFERROR(IF(B9="","",MAX(0,B14-'0. Supuestos'!$B$45)*'0. Supuestos'!$B$43),"") -> 0 | C15: =IFERROR(IF(C9="","",MAX(0,C14-'0. Supuestos'!$B$45)*'0. Supuestos'!$B$43),"") -> 4912.3152 | D15: =IFERROR(IF(D9="","",MAX(0,D14-'0. Supuestos'!$B$45)*'0. Supuestos'!$B$43),"") -> 17219.852 | E15: Al tipo de entidad de nueva creación, compensando las bases negativas anteriores. Con resultado negativo no hay cuota.
A16: RESULTADO NETO | B16: =IFERROR(IF(B9="","",B14-B15),"") -> -42784.185 | C16: =IFERROR(IF(C9="","",C14-C15),"") -> 27836.453 | D16: =IFERROR(IF(D9="","",D14-D15),"") -> 97579.162
A17: Margen neto (%) | B17: =IFERROR(IF(B9="","",B16/B9),"") -> -0.2026534 | C17: =IFERROR(IF(C9="","",C16/C9),"") -> 0.08639552 | D17: =IFERROR(IF(D9="","",D16/D9),"") -> 0.22033862 | E17: Contrástalo con la banda de referencia del 8-12 % de «0. Supuestos». El optimista que se va muy por encima suele estar olvidándose de un coste, no descubriendo un negocio mejor.
A18: Tickets al día para el equilibrio | B18: =IFERROR(IF(B9="","",IF(B7-B11/(B6*B8)<=0,"",B13/(B7-B11/(B6*B8))/B8)),"") -> 181.72276 | C18: =IFERROR(IF(C9="","",IF(C7-C11/(C6*C8)<=0,"",C13/(C7-C11/(C6*C8))/C8)),"") -> 155.6464 | D18: =IFERROR(IF(D9="","",IF(D7-D11/(D6*D8)<=0,"",D13/(D7-D11/(D6*D8))/D8)),"") -> 136.13409
A19: LO QUE CADA ESCENARIO EXIGE
A20: Coste de personal / ventas | B20: =IFERROR(IF(B9="","",'PyG 3 Años'!$C$19/B9),"") -> 0.43944713 | C20: =IFERROR(IF(C9="","",'PyG 3 Años'!$C$19/C9),"") -> 0.28794752 | D20: =IFERROR(IF(D9="","",'PyG 3 Años'!$C$19/D9),"") -> 0.20949302 | E20: La MISMA plantilla en los tres escenarios: cinco personas y tres jornadas y media. En el pesimista es donde se ve si esa plantilla se sostiene.
A21: Ventas al año por jornada equivalente (€) | B21: =IFERROR(IF(B9="","",B9/'Personal'!$C$11),"") -> 60320 | C21: =IFERROR(IF(C9="","",C9/'Personal'!$C$11),"") -> 92056.535 | D21: =IFERROR(IF(D9="","",D9/'Personal'!$C$11),"") -> 126531.43 | E21: Cuánto tendría que facturar cada jornada completa del cuadro de Personal. En el optimista dice si hace falta contratar antes de llegar ahí.
A22: Saldo de caja estimado al cierre del año 1 (mismo método en los tres) | B22: =IFERROR(IF(B9="","",'Inversión Inicial'!$B$18+B16+'PyG 3 Años'!$C$31-'Financiación'!$C$116),"") -> 31612.781 | C22: =IFERROR(IF(C9="","",'Inversión Inicial'!$B$18+C16+'PyG 3 Años'!$C$31-'Financiación'!$C$116),"") -> 102233.42 | D22: =IFERROR(IF(D9="","",'Inversión Inicial'!$B$18+D16+'PyG 3 Años'!$C$31-'Financiación'!$C$116),"") -> 171976.13 | E22: Fondo de maniobra más el resultado del año, devolviendo la amortización (que no se paga) y restando el principal (que sí). Es una ESTIMACIÓN: el saldo de verdad, con su desfase de cobros y su liquidación de IVA, está en la hoja de Tesorería.
A23: Saldo real del mes 12 de la hoja de Tesorería (sólo el realista) | C23: =IFERROR(IF(C9="","",'Tesorería 12 meses'!M23),"") -> 95212.518 | E23: Sólo existe para el caso base: la tesorería mes a mes está construida sobre el año 1 del P&L, no sobre los escenarios.
A25: La columna «Realista» lee sus tres datos del año de crucero del P&L, así que reproduce EXACTAMENTE ese año. Si quieres mover el caso base, muévelo en «0. Supuestos» y esta columna te sigue.

Sheet Personal
A1: Personal: Cinco Personas y Tres Jornadas y Media
A2: AI Chef Pro · aichef.pro — Cómo Montar una Pastelería
A3: Los cuatro perfiles son los del kit de tareas de pastelería, con DOS personas en Dependiente Vitrina. El bruto sale del convenio, en celda verde, y la Seguridad Social a cargo de la empresa va DENTRO: del bruto al coste empresa hay un tercio más.
A5: Persona y perfil | B5: Personas | C5: Jornada | D5: Grupo de convenio | E5: Bruto mes del grupo (€) | F5: Bruto mes del puesto (€) | G5: Seguridad Social a cargo de la empresa (€) | H5: Coste mes (€) | I5: Coste año (€) | J5: Horas/semana | K5: Notas
A6: P1 · Jefe Pastelero | B6: 1 | C6: 1 | D6: Grupo 2 | E6: =IFERROR(INDEX($E$15:$E$20,MATCH(D6,$A$15:$A$20,0)),"") -> 1427.89 | F6: =IFERROR(E6*C6*B6,"") -> 1427.89 | G6: =IFERROR(F6*'0. Supuestos'!$B$25,"") -> 471.2037 | H6: =IFERROR(F6+G6,"") -> 1899.0937 | I6: =IFERROR(H6*MAX(12,'0. Supuestos'!$B$26),"") -> 28486.406 | J6: 40 | K6: Área OBRADOR · turno de Madrugada (04:30-12:30)
A7: P2 · Pastelero | B7: 1 | C7: 1 | D7: Grupo 3 | E7: =IFERROR(INDEX($E$15:$E$20,MATCH(D7,$A$15:$A$20,0)),"") -> 1376.91 | F7: =IFERROR(E7*C7*B7,"") -> 1376.91 | G7: =IFERROR(F7*'0. Supuestos'!$B$25,"") -> 454.3803 | H7: =IFERROR(F7+G7,"") -> 1831.2903 | I7: =IFERROR(H7*MAX(12,'0. Supuestos'!$B$26),"") -> 27469.355 | J7: 40 | K7: Área OBRADOR · turno de Madrugada (05:00-13:00)
A8: P3 · Ayudante | B8: 1 | C8: 0.5 | D8: Grupo 5 | E8: =IFERROR(INDEX($E$15:$E$20,MATCH(D8,$A$15:$A$20,0)),"") -> 1192.42 | F8: =IFERROR(E8*C8*B8,"") -> 596.21 | G8: =IFERROR(F8*'0. Supuestos'!$B$25,"") -> 196.7493 | H8: =IFERROR(F8+G8,"") -> 792.9593 | I8: =IFERROR(H8*MAX(12,'0. Supuestos'!$B$26),"") -> 11894.39 | J8: 20 | K8: Área OBRADOR · turno de Mañana (07:00-11:00)
A9: P4 · Dependiente Vitrina A | B9: 1 | C9: 0.5 | D9: Grupo 4 | E9: =IFERROR(INDEX($E$15:$E$20,MATCH(D9,$A$15:$A$20,0)),"") -> 1249.42 | F9: =IFERROR(E9*C9*B9,"") -> 624.71 | G9: =IFERROR(F9*'0. Supuestos'!$B$25,"") -> 206.1543 | H9: =IFERROR(F9+G9,"") -> 830.8643 | I9: =IFERROR(H9*MAX(12,'0. Supuestos'!$B$26),"") -> 12462.965 | J9: 20 | K9: Área COMERCIO · turno de Mañana (08:00-12:00)
A10: P5 · Dependiente Vitrina B | B10: 1 | C10: 0.5 | D10: Grupo 4 | E10: =IFERROR(INDEX($E$15:$E$20,MATCH(D10,$A$15:$A$20,0)),"") -> 1249.42 | F10: =IFERROR(E10*C10*B10,"") -> 624.71 | G10: =IFERROR(F10*'0. Supuestos'!$B$25,"") -> 206.1543 | H10: =IFERROR(F10+G10,"") -> 830.8643 | I10: =IFERROR(H10*MAX(12,'0. Supuestos'!$B$26),"") -> 12462.965 | J10: 20 | K10: Área COMERCIO · turno de Tarde (16:30-20:30)
A11: TOTAL PLANTILLA | B11: =IFERROR(IF(COUNT(E6:E10)=0,"",SUM(B6:B10)),"") -> 5 | C11: =IFERROR(IF(COUNT(E6:E10)=0,"",SUM(C6:C10)),"") -> 3.5 | F11: =IFERROR(IF(COUNT(E6:E10)=0,"",SUM(F6:F10)),"") -> 4650.43 | G11: =IFERROR(IF(COUNT(E6:E10)=0,"",SUM(G6:G10)),"") -> 1534.6419 | H11: =IFERROR(IF(COUNT(E6:E10)=0,"",SUM(H6:H10)),"") -> 6185.0719 | I11: =IFERROR(IF(COUNT(E6:E10)=0,"",SUM(I6:I10)),"") -> 92776.079 | J11: =IFERROR(IF(COUNT(E6:E10)=0,"",SUM(J6:J10)),"") -> 140 | K11: Este «Coste año» es el que lee el P&L. No hay una segunda estimación de personal en ninguna parte del libro.
A13: EL CONVENIO DE REFERENCIA (sustitúyelo por el tuyo)
A14: Grupo | B14: Denominación del grupo | E14: Bruto mes (€) | F14: Bruto año (€) | G14: Áreas funcionales | I14: Puestos que cita
A15: Grupo 1 | B15: Técnicos y titulados superiores | E15: 1733.88 | F15: =IFERROR(E15*MAX(12,'0. Supuestos'!$B$26),"") -> 26008.2 | G15: ADMINISTRACIÓN | I15: -
A16: Grupo 2 | B16: Dirección, jefes y encargados | E16: 1427.89 | F16: =IFERROR(E16*MAX(12,'0. Supuestos'!$B$26),"") -> 21418.35 | G16: OBRADOR / COMERCIO / ADMINISTRACIÓN | I16: maestro de obrador
A17: Grupo 3 | B17: Personal especialista | E17: 1376.91 | F17: =IFERROR(E17*MAX(12,'0. Supuestos'!$B$26),"") -> 20653.65 | G17: OBRADOR / COMERCIO | I17: oficial 1.ª de producción, encargado de sección, dependiente mayor
A18: Grupo 4 | B18: Personal cualificado | E18: 1249.42 | F18: =IFERROR(E18*MAX(12,'0. Supuestos'!$B$26),"") -> 18741.3 | G18: OBRADOR / COMERCIO | I18: oficial 2.ª de producción, oficial 1.ª de envasado, dependiente, conductor
A19: Grupo 5 | B19: Personal de apoyo | E19: 1192.42 | F19: =IFERROR(E19*MAX(12,'0. Supuestos'!$B$26),"") -> 17886.3 | G19: OBRADOR / COMERCIO | I19: ayudante de producción, oficial de acabado, ayudante de comercio
A20: Grupo 6 | B20: Personal de ayuda en servicios auxiliares | E20: 1192.42 | F20: =IFERROR(E20*MAX(12,'0. Supuestos'!$B$26),"") -> 17886.3 | G20: OBRADOR / COMERCIO | I20: peón, limpiador, almacenero
A22: CONTRASTE CON EL SMI
A23: Bruto anual del grupo más bajo (€) | B23: =IFERROR(IF(COUNT(F15:F20)=0,"",MIN(F15:F20)),"") -> 17886.3
A24: SMI anual de referencia (€) | B24: =IFERROR('0. Supuestos'!$B$27,"") -> 17094
A25: ¿Algún grupo queda por debajo del SMI? | B25: =IFERROR(IF(B23="","",IF(B23<B24,"Sí: revísalo con tu asesor","No: en pastelería manda el convenio")),"") -> No: en pastelería manda el convenio | K25: El SMI es una referencia ANUAL en cómputo global, no un mínimo por concepto. En pastelería manda el convenio: en Madrid el grupo más bajo ya lo supera. Las dos cosas caducan el 31-12-2026.
A27: HORAS Y DIMENSIONADO
A28: Horas contratadas a la semana | B28: =IFERROR(J11,"") -> 140
A29: Jornadas completas equivalentes | B29: =IFERROR(C11,"") -> 3.5
A30: Personas con más horas de las que da su jornada | B30: =IFERROR(SUMPRODUCT((J6:J10>C6:C10*'0. Supuestos'!$B$28)*1),"") -> 0 | K30: Tiene que valer cero. Si se pone en rojo, alguien está contratado a media jornada y trabajando más horas de las que cobra: eso no es un ahorro, es una inspección.
A32: El refuerzo de las campañas NO está en este cuadro: la estacionalidad manda tres personas más en Reyes y una o dos en el resto de los picos, y eso se dimensiona y se cuesta en los libros «estacionalidad-y-picos» y «plantilla-turnos-y-coste-personal». Aquí está la plantilla ESTABLE, que es la que entra en los costes fijos del P&L.

Sheet Tesorería 12 meses
A1: Tesorería de los 12 Primeros Meses
A2: AI Chef Pro · aichef.pro — Cómo Montar una Pastelería
A3: El P&L dice si el negocio gana dinero; esta hoja dice si le queda caja para llegar a fin de mes. Es la primera que mira un banco, y la que más aperturas ha salvado.
A5: Concepto | B5: Mes 1 | C5: Mes 2 | D5: Mes 3 | E5: Mes 4 | F5: Mes 5 | G5: Mes 6 | H5: Mes 7 | I5: Mes 8 | J5: Mes 9 | K5: Mes 10 | L5: Mes 11 | M5: Mes 12 | N5: Año (€) | O5: Notas
A6: Estacionalidad del mes (tiene que sumar 100 %) | B6: 0.111667 | C6: 0.0775 | D6: 0.080833 | E6: 0.086667 | F6: 0.089167 | G6: 0.080833 | H6: 0.070833 | I6: 0.054167 | J6: 0.075833 | K6: 0.079167 | L6: 0.09 | M6: 0.103333 | N6: =IFERROR(SUM(B6:M6),"") -> 1 | O6: Enero manda por el roscón y diciembre por la Navidad; agosto es el suelo. Es el perfil de una ciudad media: en costa, agosto sube. Tiene que sumar 100 %, y la celda del año te lo dice.
A7: Rampa de arranque (% de la actividad de crucero) | B7: =IFERROR(MIN(1,'0. Supuestos'!$B$49+(1-'0. Supuestos'!$B$49)*0/MAX(1,'0. Supuestos'!$B$50-1)),"") -> 0.55 | C7: =IFERROR(MIN(1,'0. Supuestos'!$B$49+(1-'0. Supuestos'!$B$49)*1/MAX(1,'0. Supuestos'!$B$50-1)),"") -> 0.64 | D7: =IFERROR(MIN(1,'0. Supuestos'!$B$49+(1-'0. Supuestos'!$B$49)*2/MAX(1,'0. Supuestos'!$B$50-1)),"") -> 0.73 | E7: =IFERROR(MIN(1,'0. Supuestos'!$B$49+(1-'0. Supuestos'!$B$49)*3/MAX(1,'0. Supuestos'!$B$50-1)),"") -> 0.82 | F7: =IFERROR(MIN(1,'0. Supuestos'!$B$49+(1-'0. Supuestos'!$B$49)*4/MAX(1,'0. Supuestos'!$B$50-1)),"") -> 0.91 | G7: =IFERROR(MIN(1,'0. Supuestos'!$B$49+(1-'0. Supuestos'!$B$49)*5/MAX(1,'0. Supuestos'!$B$50-1)),"") -> 1 | H7: =IFERROR(MIN(1,'0. Supuestos'!$B$49+(1-'0. Supuestos'!$B$49)*6/MAX(1,'0. Supuestos'!$B$50-1)),"") -> 1 | I7: =IFERROR(MIN(1,'0. Supuestos'!$B$49+(1-'0. Supuestos'!$B$49)*7/MAX(1,'0. Supuestos'!$B$50-1)),"") -> 1 | J7: =IFERROR(MIN(1,'0. Supuestos'!$B$49+(1-'0. Supuestos'!$B$49)*8/MAX(1,'0. Supuestos'!$B$50-1)),"") -> 1 | K7: =IFERROR(MIN(1,'0. Supuestos'!$B$49+(1-'0. Supuestos'!$B$49)*9/MAX(1,'0. Supuestos'!$B$50-1)),"") -> 1 | L7: =IFERROR(MIN(1,'0. Supuestos'!$B$49+(1-'0. Supuestos'!$B$49)*10/MAX(1,'0. Supuestos'!$B$50-1)),"") -> 1 | M7: =IFERROR(MIN(1,'0. Supuestos'!$B$49+(1-'0. Supuestos'!$B$49)*11/MAX(1,'0. Supuestos'!$B$50-1)),"") -> 1 | O7: Sube en línea recta desde el porcentaje del mes 1 hasta el 100 % en los meses que digas en «0. Supuestos». Con el 100 % en el mes 1 la rampa desaparece, y entonces estás proyectando una apertura que no existe.
A8: Reparto de la actividad por mes (calculado) | B8: =IFERROR(B6*B7/SUMPRODUCT($B$6:$M$6,$B$7:$M$7),"") -> 0.070078572 | C8: =IFERROR(C6*C7/SUMPRODUCT($B$6:$M$6,$B$7:$M$7),"") -> 0.056595172 | D8: =IFERROR(D6*D7/SUMPRODUCT($B$6:$M$6,$B$7:$M$7),"") -> 0.067330101 | E8: =IFERROR(E6*E7/SUMPRODUCT($B$6:$M$6,$B$7:$M$7),"") -> 0.08108963 | F8: =IFERROR(F6*F7/SUMPRODUCT($B$6:$M$6,$B$7:$M$7),"") -> 0.092585559 | G8: =IFERROR(G6*G7/SUMPRODUCT($B$6:$M$6,$B$7:$M$7),"") -> 0.092233014 | H8: =IFERROR(H6*H7/SUMPRODUCT($B$6:$M$6,$B$7:$M$7),"") -> 0.080822698 | I8: =IFERROR(I6*I7/SUMPRODUCT($B$6:$M$6,$B$7:$M$7),"") -> 0.061806263 | ... M8: =IFERROR(M6*M7/SUMPRODUCT($B$6:$M$6,$B$7:$M$7),"") -> 0.11790623 | N8: =IFERROR(SUM(B8:M8),"") -> 1 | O8: Estacionalidad x rampa, normalizado al 100 %: el AÑO factura lo que dice el P&L, pero repartido como lo reparte la realidad.
A9: COBROS
A10: Ventas cobradas (con el IVA repercutido dentro) | B10: =IFERROR(IF('PyG 3 Años'!$B$11="","",'PyG 3 Años'!$B$11*(1+'0. Supuestos'!$B$20)*(B8*(1-'0. Supuestos'!$B$52/30))),"") -> 19913.623 | C10: =IFERROR(IF('PyG 3 Años'!$B$11="","",'PyG 3 Años'!$B$11*(1+'0. Supuestos'!$B$20)*(C8*(1-'0. Supuestos'!$B$52/30)+B8*('0. Supuestos'!$B$52/30))),"") -> 17696.779 | D10: =IFERROR(IF('PyG 3 Años'!$B$11="","",'PyG 3 Años'!$B$11*(1+'0. Supuestos'!$B$20)*(D8*(1-'0. Supuestos'!$B$52/30)+C8*('0. Supuestos'!$B$52/30))),"") -> 20436.572 | E10: =IFERROR(IF('PyG 3 Años'!$B$11="","",'PyG 3 Años'!$B$11*(1+'0. Supuestos'!$B$20)*(E8*(1-'0. Supuestos'!$B$52/30)+D8*('0. Supuestos'!$B$52/30))),"") -> 24593.833 | F10: =IFERROR(IF('PyG 3 Años'!$B$11="","",'PyG 3 Años'!$B$11*(1+'0. Supuestos'!$B$20)*(F8*(1-'0. Supuestos'!$B$52/30)+E8*('0. Supuestos'!$B$52/30))),"") -> 28177.553 | G10: =IFERROR(IF('PyG 3 Años'!$B$11="","",'PyG 3 Años'!$B$11*(1+'0. Supuestos'!$B$20)*(G8*(1-'0. Supuestos'!$B$52/30)+F8*('0. Supuestos'!$B$52/30))),"") -> 28342.241 | H10: =IFERROR(IF('PyG 3 Años'!$B$11="","",'PyG 3 Años'!$B$11*(1+'0. Supuestos'!$B$20)*(H8*(1-'0. Supuestos'!$B$52/30)+G8*('0. Supuestos'!$B$52/30))),"") -> 25091.747 | I10: =IFERROR(IF('PyG 3 Años'!$B$11="","",'PyG 3 Años'!$B$11*(1+'0. Supuestos'!$B$20)*(I8*(1-'0. Supuestos'!$B$52/30)+H8*('0. Supuestos'!$B$52/30))),"") -> 19425.116 | J10: =IFERROR(IF('PyG 3 Años'!$B$11="","",'PyG 3 Años'!$B$11*(1+'0. Supuestos'!$B$20)*(J8*(1-'0. Supuestos'!$B$52/30)+I8*('0. Supuestos'!$B$52/30))),"") -> 26011.897 | ... M10: =IFERROR(IF('PyG 3 Años'!$B$11="","",'PyG 3 Años'!$B$11*(1+'0. Supuestos'!$B$20)*(M8*(1-'0. Supuestos'!$B$52/30)+L8*('0. Supuestos'!$B$52/30))),"") -> 35870.449 | N10: =IFERROR(IF('PyG 3 Años'!$B$11="","",SUM(B10:M10)),"") -> 304484.9 | O10: Ventas del mes con el IVA repercutido, corregidas por los días medios de cobro que calcula la hoja de canales. El mostrador cobra al contado; el B2B, a 45 días.
A11: PAGOS
A12: Compras y coste de ventas (IVA incluido) | B12: =IFERROR(IF('PyG 3 Años'!$B$11="","",-'PyG 3 Años'!$B$15*(1+'PyG 3 Años'!$F$15)*(B8*(1-'0. Supuestos'!$B$53/30))+0),"") -> 0 | C12: =IFERROR(IF('PyG 3 Años'!$B$11="","",-'PyG 3 Años'!$B$15*(1+'PyG 3 Años'!$F$15)*(C8*(1-'0. Supuestos'!$B$53/30)+B8*('0. Supuestos'!$B$53/30))+0),"") -> -6965.5092 | D12: =IFERROR(IF('PyG 3 Años'!$B$11="","",-'PyG 3 Años'!$B$15*(1+'PyG 3 Años'!$F$15)*(D8*(1-'0. Supuestos'!$B$53/30)+C8*('0. Supuestos'!$B$53/30))+0),"") -> -5625.3171 | E12: =IFERROR(IF('PyG 3 Años'!$B$11="","",-'PyG 3 Años'!$B$15*(1+'PyG 3 Años'!$F$15)*(E8*(1-'0. Supuestos'!$B$53/30)+D8*('0. Supuestos'!$B$53/30))+0),"") -> -6692.3229 | F12: =IFERROR(IF('PyG 3 Años'!$B$11="","",-'PyG 3 Años'!$B$15*(1+'PyG 3 Años'!$F$15)*(F8*(1-'0. Supuestos'!$B$53/30)+E8*('0. Supuestos'!$B$53/30))+0),"") -> -8059.9611 | G12: =IFERROR(IF('PyG 3 Años'!$B$11="","",-'PyG 3 Años'!$B$15*(1+'PyG 3 Años'!$F$15)*(G8*(1-'0. Supuestos'!$B$53/30)+F8*('0. Supuestos'!$B$53/30))+0),"") -> -9202.6071 | H12: =IFERROR(IF('PyG 3 Años'!$B$11="","",-'PyG 3 Años'!$B$15*(1+'PyG 3 Años'!$F$15)*(H8*(1-'0. Supuestos'!$B$53/30)+G8*('0. Supuestos'!$B$53/30))+0),"") -> -9167.5657 | I12: =IFERROR(IF('PyG 3 Años'!$B$11="","",-'PyG 3 Años'!$B$15*(1+'PyG 3 Años'!$F$15)*(I8*(1-'0. Supuestos'!$B$53/30)+H8*('0. Supuestos'!$B$53/30))+0),"") -> -8033.4292 | J12: =IFERROR(IF('PyG 3 Años'!$B$11="","",-'PyG 3 Años'!$B$15*(1+'PyG 3 Años'!$F$15)*(J8*(1-'0. Supuestos'!$B$53/30)+I8*('0. Supuestos'!$B$53/30))+0),"") -> -6143.2772 | ... M12: =IFERROR(IF('PyG 3 Años'!$B$11="","",-'PyG 3 Años'!$B$15*(1+'PyG 3 Años'!$F$15)*(M8*(1-'0. Supuestos'!$B$53/30)+L8*('0. Supuestos'!$B$53/30))+0),"") -> -10207.229 | N12: =IFERROR(IF('PyG 3 Años'!$B$11="","",SUM(B12:M12)),"") -> -87676.334 | O12: Con los días medios de pago a proveedor de «0. Supuestos». A 30 días el mes 1 no paga nada: el proveedor te está financiando el arranque, y por eso perder ese crédito por un retraso sale tan caro.
A13: Costes fijos de explotación (IVA incluido) | B13: =IFERROR(IF('PyG 3 Años'!$B$11="","",-(('PyG 3 Años'!$B$33-'PyG 3 Años'!$B$19-'PyG 3 Años'!$B$31-'PyG 3 Años'!$B$32)+'PyG 3 Años'!$B$35)/12),"") -> -6954.65 | C13: =IFERROR(IF('PyG 3 Años'!$B$11="","",-(('PyG 3 Años'!$B$33-'PyG 3 Años'!$B$19-'PyG 3 Años'!$B$31-'PyG 3 Años'!$B$32)+'PyG 3 Años'!$B$35)/12),"") -> -6954.65 | D13: =IFERROR(IF('PyG 3 Años'!$B$11="","",-(('PyG 3 Años'!$B$33-'PyG 3 Años'!$B$19-'PyG 3 Años'!$B$31-'PyG 3 Años'!$B$32)+'PyG 3 Años'!$B$35)/12),"") -> -6954.65 | E13: =IFERROR(IF('PyG 3 Años'!$B$11="","",-(('PyG 3 Años'!$B$33-'PyG 3 Años'!$B$19-'PyG 3 Años'!$B$31-'PyG 3 Años'!$B$32)+'PyG 3 Años'!$B$35)/12),"") -> -6954.65 | F13: =IFERROR(IF('PyG 3 Años'!$B$11="","",-(('PyG 3 Años'!$B$33-'PyG 3 Años'!$B$19-'PyG 3 Años'!$B$31-'PyG 3 Años'!$B$32)+'PyG 3 Años'!$B$35)/12),"") -> -6954.65 | G13: =IFERROR(IF('PyG 3 Años'!$B$11="","",-(('PyG 3 Años'!$B$33-'PyG 3 Años'!$B$19-'PyG 3 Años'!$B$31-'PyG 3 Años'!$B$32)+'PyG 3 Años'!$B$35)/12),"") -> -6954.65 | H13: =IFERROR(IF('PyG 3 Años'!$B$11="","",-(('PyG 3 Años'!$B$33-'PyG 3 Años'!$B$19-'PyG 3 Años'!$B$31-'PyG 3 Años'!$B$32)+'PyG 3 Años'!$B$35)/12),"") -> -6954.65 | I13: =IFERROR(IF('PyG 3 Años'!$B$11="","",-(('PyG 3 Años'!$B$33-'PyG 3 Años'!$B$19-'PyG 3 Años'!$B$31-'PyG 3 Años'!$B$32)+'PyG 3 Años'!$B$35)/12),"") -> -6954.65 | ... M13: =IFERROR(IF('PyG 3 Años'!$B$11="","",-(('PyG 3 Años'!$B$33-'PyG 3 Años'!$B$19-'PyG 3 Años'!$B$31-'PyG 3 Años'!$B$32)+'PyG 3 Años'!$B$35)/12),"") -> -6954.65 | N13: =IFERROR(IF('PyG 3 Años'!$B$11="","",SUM(B13:M13)),"") -> -83455.8 | O13: Los fijos que salen de caja, cada uno con su tipo de IVA: sin las nóminas (van abajo), sin la amortización (no se paga) y sin los intereses (van aparte).
A14: Nóminas y Seguridad Social | B14: =IFERROR(IF('PyG 3 Años'!$B$11="","",-'PyG 3 Años'!$B$19/MAX(12,'0. Supuestos'!$B$26)*(1+IF(1='0. Supuestos'!$B$54,1,0)+IF(1='0. Supuestos'!$B$55,1,0)+IF(1='0. Supuestos'!$B$56,1,0))),"") -> -6185.0719 | C14: =IFERROR(IF('PyG 3 Años'!$B$11="","",-'PyG 3 Años'!$B$19/MAX(12,'0. Supuestos'!$B$26)*(1+IF(2='0. Supuestos'!$B$54,1,0)+IF(2='0. Supuestos'!$B$55,1,0)+IF(2='0. Supuestos'!$B$56,1,0))),"") -> -6185.0719 | D14: =IFERROR(IF('PyG 3 Años'!$B$11="","",-'PyG 3 Años'!$B$19/MAX(12,'0. Supuestos'!$B$26)*(1+IF(3='0. Supuestos'!$B$54,1,0)+IF(3='0. Supuestos'!$B$55,1,0)+IF(3='0. Supuestos'!$B$56,1,0))),"") -> -12370.144 | E14: =IFERROR(IF('PyG 3 Años'!$B$11="","",-'PyG 3 Años'!$B$19/MAX(12,'0. Supuestos'!$B$26)*(1+IF(4='0. Supuestos'!$B$54,1,0)+IF(4='0. Supuestos'!$B$55,1,0)+IF(4='0. Supuestos'!$B$56,1,0))),"") -> -6185.0719 | F14: =IFERROR(IF('PyG 3 Años'!$B$11="","",-'PyG 3 Años'!$B$19/MAX(12,'0. Supuestos'!$B$26)*(1+IF(5='0. Supuestos'!$B$54,1,0)+IF(5='0. Supuestos'!$B$55,1,0)+IF(5='0. Supuestos'!$B$56,1,0))),"") -> -6185.0719 | G14: =IFERROR(IF('PyG 3 Años'!$B$11="","",-'PyG 3 Años'!$B$19/MAX(12,'0. Supuestos'!$B$26)*(1+IF(6='0. Supuestos'!$B$54,1,0)+IF(6='0. Supuestos'!$B$55,1,0)+IF(6='0. Supuestos'!$B$56,1,0))),"") -> -6185.0719 | H14: =IFERROR(IF('PyG 3 Años'!$B$11="","",-'PyG 3 Años'!$B$19/MAX(12,'0. Supuestos'!$B$26)*(1+IF(7='0. Supuestos'!$B$54,1,0)+IF(7='0. Supuestos'!$B$55,1,0)+IF(7='0. Supuestos'!$B$56,1,0))),"") -> -12370.144 | I14: =IFERROR(IF('PyG 3 Años'!$B$11="","",-'PyG 3 Años'!$B$19/MAX(12,'0. Supuestos'!$B$26)*(1+IF(8='0. Supuestos'!$B$54,1,0)+IF(8='0. Supuestos'!$B$55,1,0)+IF(8='0. Supuestos'!$B$56,1,0))),"") -> -6185.0719 | J14: =IFERROR(IF('PyG 3 Años'!$B$11="","",-'PyG 3 Años'!$B$19/MAX(12,'0. Supuestos'!$B$26)*(1+IF(9='0. Supuestos'!$B$54,1,0)+IF(9='0. Supuestos'!$B$55,1,0)+IF(9='0. Supuestos'!$B$56,1,0))),"") -> -6185.0719 | K14: =IFERROR(IF('PyG 3 Años'!$B$11="","",-'PyG 3 Años'!$B$19/MAX(12,'0. Supuestos'!$B$26)*(1+IF(10='0. Supuestos'!$B$54,1,0)+IF(10='0. Supuestos'!$B$55,1,0)+IF(10='0. Supuestos'!$B$56,1,0))),"") -> -6185.0719 | L14: =IFERROR(IF('PyG 3 Años'!$B$11="","",-'PyG 3 Años'!$B$19/MAX(12,'0. Supuestos'!$B$26)*(1+IF(11='0. Supuestos'!$B$54,1,0)+IF(11='0. Supuestos'!$B$55,1,0)+IF(11='0. Supuestos'!$B$56,1,0))),"") -> -6185.0719 | M14: =IFERROR(IF('PyG 3 Años'!$B$11="","",-'PyG 3 Años'!$B$19/MAX(12,'0. Supuestos'!$B$26)*(1+IF(12='0. Supuestos'!$B$54,1,0)+IF(12='0. Supuestos'!$B$55,1,0)+IF(12='0. Supuestos'!$B$56,1,0))),"") -> -12370.144 | N14: =IFERROR(IF('PyG 3 Años'!$B$11="","",SUM(B14:M14)),"") -> -92776.079 | O14: Doce mensualidades más las pagas extra en los meses que digas. Con 15 pagas hay tres meses que salen dobles, y siempre pillan a contrapié: uno de ellos suele caer en el mes flojo.
A15: Intereses del préstamo | B15: =IFERROR(IF('PyG 3 Años'!$B$11="","",-IF('Financiación'!C26="",0,'Financiación'!C26)),"") -> -310 | C15: =IFERROR(IF('PyG 3 Años'!$B$11="","",-IF('Financiación'!C27="",0,'Financiación'!C27)),"") -> -310 | D15: =IFERROR(IF('PyG 3 Años'!$B$11="","",-IF('Financiación'!C28="",0,'Financiación'!C28)),"") -> -310 | E15: =IFERROR(IF('PyG 3 Años'!$B$11="","",-IF('Financiación'!C29="",0,'Financiación'!C29)),"") -> -310 | F15: =IFERROR(IF('PyG 3 Años'!$B$11="","",-IF('Financiación'!C30="",0,'Financiación'!C30)),"") -> -310 | G15: =IFERROR(IF('PyG 3 Años'!$B$11="","",-IF('Financiación'!C31="",0,'Financiación'!C31)),"") -> -310 | H15: =IFERROR(IF('PyG 3 Años'!$B$11="","",-IF('Financiación'!C32="",0,'Financiación'!C32)),"") -> -310 | I15: =IFERROR(IF('PyG 3 Años'!$B$11="","",-IF('Financiación'!C33="",0,'Financiación'!C33)),"") -> -306.76271 | J15: =IFERROR(IF('PyG 3 Años'!$B$11="","",-IF('Financiación'!C34="",0,'Financiación'!C34)),"") -> -303.50869 | K15: =IFERROR(IF('PyG 3 Años'!$B$11="","",-IF('Financiación'!C35="",0,'Financiación'!C35)),"") -> -300.23786 | L15: =IFERROR(IF('PyG 3 Años'!$B$11="","",-IF('Financiación'!C36="",0,'Financiación'!C36)),"") -> -296.95013 | M15: =IFERROR(IF('PyG 3 Años'!$B$11="","",-IF('Financiación'!C37="",0,'Financiación'!C37)),"") -> -293.64542 | N15: =IFERROR(IF('PyG 3 Años'!$B$11="","",SUM(B15:M15)),"") -> -3671.1048
A16: Devolución de principal del préstamo | B16: =IFERROR(IF('PyG 3 Años'!$B$11="","",-IF('Financiación'!D26="",0,'Financiación'!D26)),"") -> 0 | C16: =IFERROR(IF('PyG 3 Años'!$B$11="","",-IF('Financiación'!D27="",0,'Financiación'!D27)),"") -> 0 | D16: =IFERROR(IF('PyG 3 Años'!$B$11="","",-IF('Financiación'!D28="",0,'Financiación'!D28)),"") -> 0 | E16: =IFERROR(IF('PyG 3 Años'!$B$11="","",-IF('Financiación'!D29="",0,'Financiación'!D29)),"") -> 0 | F16: =IFERROR(IF('PyG 3 Años'!$B$11="","",-IF('Financiación'!D30="",0,'Financiación'!D30)),"") -> 0 | G16: =IFERROR(IF('PyG 3 Años'!$B$11="","",-IF('Financiación'!D31="",0,'Financiación'!D31)),"") -> 0 | H16: =IFERROR(IF('PyG 3 Años'!$B$11="","",-IF('Financiación'!D32="",0,'Financiación'!D32)),"") -> -626.57242 | I16: =IFERROR(IF('PyG 3 Años'!$B$11="","",-IF('Financiación'!D33="",0,'Financiación'!D33)),"") -> -629.80971 | J16: =IFERROR(IF('PyG 3 Años'!$B$11="","",-IF('Financiación'!D34="",0,'Financiación'!D34)),"") -> -633.06372 | K16: =IFERROR(IF('PyG 3 Años'!$B$11="","",-IF('Financiación'!D35="",0,'Financiación'!D35)),"") -> -636.33455 | L16: =IFERROR(IF('PyG 3 Años'!$B$11="","",-IF('Financiación'!D36="",0,'Financiación'!D36)),"") -> -639.62228 | M16: =IFERROR(IF('PyG 3 Años'!$B$11="","",-IF('Financiación'!D37="",0,'Financiación'!D37)),"") -> -642.927 | N16: =IFERROR(IF('PyG 3 Años'!$B$11="","",SUM(B16:M16)),"") -> -3808.3297 | O16: Sale del cuadro MENSUAL de la hoja de Financiación. Durante la carencia esta fila vale cero, y ése es justo el efecto que se negocia con el banco.
A17: IVA repercutido del mes (memoria) | B17: =IFERROR(IF('PyG 3 Años'!$B$11="","",'PyG 3 Años'!$B$11*B8*'0. Supuestos'!$B$20),"") -> 1739.8623 | C17: =IFERROR(IF('PyG 3 Años'!$B$11="","",'PyG 3 Años'!$B$11*C8*'0. Supuestos'!$B$20),"") -> 1405.1058 | D17: =IFERROR(IF('PyG 3 Años'!$B$11="","",'PyG 3 Años'!$B$11*D8*'0. Supuestos'!$B$20),"") -> 1671.6252 | E17: =IFERROR(IF('PyG 3 Años'!$B$11="","",'PyG 3 Años'!$B$11*E8*'0. Supuestos'!$B$20),"") -> 2013.2372 | F17: =IFERROR(IF('PyG 3 Años'!$B$11="","",'PyG 3 Años'!$B$11*F8*'0. Supuestos'!$B$20),"") -> 2298.6502 | G17: =IFERROR(IF('PyG 3 Años'!$B$11="","",'PyG 3 Años'!$B$11*G8*'0. Supuestos'!$B$20),"") -> 2289.8975 | H17: =IFERROR(IF('PyG 3 Años'!$B$11="","",'PyG 3 Años'!$B$11*H8*'0. Supuestos'!$B$20),"") -> 2006.61 | I17: =IFERROR(IF('PyG 3 Años'!$B$11="","",'PyG 3 Años'!$B$11*I8*'0. Supuestos'!$B$20),"") -> 1534.4831 | ... M17: =IFERROR(IF('PyG 3 Años'!$B$11="","",'PyG 3 Años'!$B$11*M8*'0. Supuestos'!$B$20),"") -> 2927.2942 | N17: =IFERROR(IF('PyG 3 Años'!$B$11="","",SUM(B17:M17)),"") -> 24827.308
A18: IVA soportado del mes (memoria) | B18: =IFERROR(IF('PyG 3 Años'!$B$11="","",'PyG 3 Años'!$B$34*B8+'PyG 3 Años'!$B$35/12),"") -> 1402.8781 | C18: =IFERROR(IF('PyG 3 Años'!$B$11="","",'PyG 3 Años'!$B$34*C8+'PyG 3 Años'!$B$35/12),"") -> 1281.0425 | D18: =IFERROR(IF('PyG 3 Años'!$B$11="","",'PyG 3 Años'!$B$34*D8+'PyG 3 Años'!$B$35/12),"") -> 1378.043 | E18: =IFERROR(IF('PyG 3 Años'!$B$11="","",'PyG 3 Años'!$B$34*E8+'PyG 3 Años'!$B$35/12),"") -> 1502.3737 | F18: =IFERROR(IF('PyG 3 Años'!$B$11="","",'PyG 3 Años'!$B$34*F8+'PyG 3 Años'!$B$35/12),"") -> 1606.2506 | G18: =IFERROR(IF('PyG 3 Años'!$B$11="","",'PyG 3 Años'!$B$34*G8+'PyG 3 Años'!$B$35/12),"") -> 1603.0651 | H18: =IFERROR(IF('PyG 3 Años'!$B$11="","",'PyG 3 Años'!$B$34*H8+'PyG 3 Años'!$B$35/12),"") -> 1499.9617 | I18: =IFERROR(IF('PyG 3 Años'!$B$11="","",'PyG 3 Años'!$B$34*I8+'PyG 3 Años'!$B$35/12),"") -> 1328.1297 | ... M18: =IFERROR(IF('PyG 3 Años'!$B$11="","",'PyG 3 Años'!$B$34*M8+'PyG 3 Años'!$B$35/12),"") -> 1835.0475 | N18: =IFERROR(IF('PyG 3 Años'!$B$11="","",SUM(B18:M18)),"") -> 18271.773
A19: IVA a compensar arrastrado (inversión incluida) | E19: =IFERROR(IF('PyG 3 Años'!$B$11="","",'Inversión Inicial'!$B$21),"") -> 33910.871 | H19: =IFERROR(IF('PyG 3 Años'!$B$11="","",MAX(0,-E20)),"") -> 33156.242 | K19: =IFERROR(IF('PyG 3 Años'!$B$11="","",MAX(0,-H20)),"") -> 31266.146 | O19: El IVA soportado de la INVERSIÓN entra aquí y se compensa contra el repercutido de los trimestres siguientes. Con una inversión grande tardas medio año en recuperarlo, y ese medio año lo financias tú.
A20: Resultado de la liquidación trimestral | E20: =IFERROR(IF('PyG 3 Años'!$B$11="","",SUM(B17:D17)-SUM(B18:D18)-E19),"") -> -33156.242 | H20: =IFERROR(IF('PyG 3 Años'!$B$11="","",SUM(E17:G17)-SUM(E18:G18)-H19),"") -> -31266.146 | K20: =IFERROR(IF('PyG 3 Años'!$B$11="","",SUM(H17:J17)-SUM(H18:J18)-K19),"") -> -29956.404
A21: Pago del IVA (modelo 303) | E21: =IFERROR(IF('PyG 3 Años'!$B$11="","",IF(E20<=0,"",-E20)),"") | H21: =IFERROR(IF('PyG 3 Años'!$B$11="","",IF(H20<=0,"",-H20)),"") | K21: =IFERROR(IF('PyG 3 Años'!$B$11="","",IF(K20<=0,"",-K20)),"") | N21: =IFERROR(IF('PyG 3 Años'!$B$11="","",IF(E21="",0,E21)+IF(H21="",0,H21)+IF(K21="",0,K21)),"") -> 0 | O21: Sólo sale caja cuando el resultado del trimestre es positivo. Los meses sin liquidación van en BLANCO, no a cero: cero significaría «liquidé y no pagué nada», que es otra cosa. El cuarto trimestre se liquida en enero del año siguiente y por eso no aparece.
A22: FLUJO DEL MES | B22: =IFERROR(IF('PyG 3 Años'!$B$11="","",SUM(B10:B16)+IF(B21="",0,B21)),"") -> 6463.9008 | C22: =IFERROR(IF('PyG 3 Años'!$B$11="","",SUM(C10:C16)+IF(C21="",0,C21)),"") -> -2718.4518 | D22: =IFERROR(IF('PyG 3 Años'!$B$11="","",SUM(D10:D16)+IF(D21="",0,D21)),"") -> -4823.5386 | E22: =IFERROR(IF('PyG 3 Años'!$B$11="","",SUM(E10:E16)+IF(E21="",0,E21)),"") -> 4451.7882 | F22: =IFERROR(IF('PyG 3 Años'!$B$11="","",SUM(F10:F16)+IF(F21="",0,F21)),"") -> 6667.8698 | G22: =IFERROR(IF('PyG 3 Años'!$B$11="","",SUM(G10:G16)+IF(G21="",0,G21)),"") -> 5689.9118 | H22: =IFERROR(IF('PyG 3 Años'!$B$11="","",SUM(H10:H16)+IF(H21="",0,H21)),"") -> -4337.185 | I22: =IFERROR(IF('PyG 3 Años'!$B$11="","",SUM(I10:I16)+IF(I21="",0,I21)),"") -> -2684.6074 | ... M22: =IFERROR(IF('PyG 3 Años'!$B$11="","",SUM(M10:M16)+IF(M21="",0,M21)),"") -> 5401.8543 | N22: =IFERROR(IF('PyG 3 Años'!$B$11="","",SUM(B22:M22)),"") -> 33097.256
A23: SALDO ACUMULADO DE CAJA | B23: =IFERROR(IF('PyG 3 Años'!$B$11="","",'Inversión Inicial'!$B$18+B22),"") -> 68579.163 | C23: =IFERROR(IF('PyG 3 Años'!$B$11="","",B23+C22),"") -> 65860.711 | D23: =IFERROR(IF('PyG 3 Años'!$B$11="","",C23+D22),"") -> 61037.172 | E23: =IFERROR(IF('PyG 3 Años'!$B$11="","",D23+E22),"") -> 65488.96 | F23: =IFERROR(IF('PyG 3 Años'!$B$11="","",E23+F22),"") -> 72156.83 | G23: =IFERROR(IF('PyG 3 Años'!$B$11="","",F23+G22),"") -> 77846.742 | H23: =IFERROR(IF('PyG 3 Años'!$B$11="","",G23+H22),"") -> 73509.557 | I23: =IFERROR(IF('PyG 3 Años'!$B$11="","",H23+I22),"") -> 70824.95 | J23: =IFERROR(IF('PyG 3 Años'!$B$11="","",I23+J22),"") -> 76617.275 | ... M23: =IFERROR(IF('PyG 3 Años'!$B$11="","",L23+M22),"") -> 95212.518
A24: Saldo mínimo del año (€) | B24: =IFERROR(IF('PyG 3 Años'!$B$11="","",IF(COUNT(B23:M23)=0,"",MIN(B23:M23))),"") -> 61037.172 | O24: Si es negativo te quedas sin caja: sube el fondo de maniobra, sube el préstamo o negocia más carencia. No lo dejes para verlo pasar.
A25: Mes en el que la caja toca fondo | B25: =IFERROR(IF('PyG 3 Años'!$B$11="","",IF(COUNT(B23:M23)=0,"",MATCH(MIN(B23:M23),B23:M23,0))),"") -> 3 | O25: Es la respuesta a la pregunta que decide una operación bancaria: en qué mes se agota la caja.
A27: RETORNO DE LA INVERSIÓN
A28: Flujo de caja libre antes de la deuda, año 1 | B28: =IFERROR(IF('PyG 3 Años'!$B$11="","",'PyG 3 Años'!B43+'PyG 3 Años'!B31+'Financiación'!$B$116),"") -> 24229.773 | O28: Resultado neto más amortización (que no se paga) más los intereses de ese año: el principal no se resta porque este flujo se compara con la inversión, no con la deuda.
A29: Flujo de caja libre antes de la deuda, año 2 | B29: =IFERROR(IF('PyG 3 Años'!$B$11="","",'PyG 3 Años'!C43+'PyG 3 Años'!C31+'Financiación'!$B$117),"") -> 47186.16
A30: Flujo de caja libre antes de la deuda, año 3 | B30: =IFERROR(IF('PyG 3 Años'!$B$11="","",'PyG 3 Años'!D43+'PyG 3 Años'!D31+'Financiación'!$B$118),"") -> 50356.866
A31: Inversión a recuperar (sin el IVA, que se recupera por el 303) | B31: =IFERROR(IF('PyG 3 Años'!$B$11="","",'Inversión Inicial'!$B$22-'Inversión Inicial'!$B$21),"") -> 227915.6
A32: Payback del proyecto (años), antes de la deuda | B32: =IFERROR(IF('PyG 3 Años'!$B$11="","",IF(B28>=B31,ROUND(B31/B28,1),IF(B28+B29>=B31,ROUND(1+(B31-B28)/B29,1),IF(B28+B29+B30>=B31,ROUND(2+(B31-B28-B29)/B30,1),"Más de 3 años")))),"") -> Más de 3 años | O32: Cuánto tarda el negocio en devolver la inversión con lo que genera ANTES de pagar al banco. Si sale «Más de 3 años», este libro no proyecta lo suficiente para decírtelo: es una señal, no un fallo.
A34: Escribe los ingresos y los gastos SIN IVA en el resto del libro: la capa de IVA de esta hoja lo añade, porque la tesorería es caja. El Impuesto de Sociedades no está en este cuadro: se paga en julio del año siguiente, fuera de los doce meses.

Sheet Financiación
A1: Financiación: de Dónde Sale y Cuánto Cuesta Devolverlo
A2: AI Chef Pro · aichef.pro — Cómo Montar una Pastelería
A3: El cuadro de amortización es MENSUAL, con 84 filas, porque la carencia de este caso son seis meses y un cuadro anual no sabe expresar medio año. La cuota es una anualidad algebraica del sistema francés.
A5: ORIGEN DE FONDOS
A6: Recursos propios aportados | B6: =IFERROR('0. Supuestos'!$B$36,"") -> 201826.48 | H6: Aportación de los socios o del promotor. Un banco quiere ver un 25-30 % de fondos propios sobre la necesidad total antes de sentarse a hablar.
A7: Préstamo bancario | B7: =IFERROR('0. Supuestos'!$B$37,"") -> 60000
A8: Otras fuentes (ICO, ENISA, subvenciones, socios) | B8: 0 | H8: A cero por defecto. Las subvenciones suelen cobrarse DESPUÉS de justificar el gasto: no cuentes con ellas para pagar la obra.
A9: TOTAL ORIGEN DE FONDOS | B9: =IFERROR(IF(COUNT(B6:B8)=0,"",SUM(B6:B8)),"") -> 261826.48
A10: USOS
A11: Necesidad total de caja al arranque | B11: =IFERROR('Inversión Inicial'!$B$22,"") -> 261826.47 | H11: Inversión más el IVA que hay que adelantar.
A12: Diferencia (origen menos usos) | B12: =IFERROR(B9-B11,"") -> 0.0067797356 | H12: En negativo el plan NO está financiado. Muy por encima de cero tampoco es gratis: son intereses que pagas sin necesitarlos.
A13: Diferencia sobre los usos (%) | B13: =IFERROR(B12/B11,"") -> 2.5894004e-08
A14: Préstamo que ajustaría el origen a la necesidad | B14: =IFERROR(MAX(0,B11-B9+B7),"") -> 59999.993 | H14: Cópialo en «Préstamo bancario solicitado» de «0. Supuestos» y la diferencia de arriba se pone a cero. Después mira el DSCR: pedir más siempre se puede, devolverlo no.
A15: CONDICIONES DEL PRÉSTAMO
A16: Importe del principal | B16: =IFERROR(IF('0. Supuestos'!$B$37=0,"",'0. Supuestos'!$B$37),"") -> 60000
A17: Tipo de interés nominal anual | B17: =IFERROR('0. Supuestos'!$B$38,"") -> 0.062
A18: Tipo mensual | B18: =IFERROR(B17/12,"") -> 0.0051666667
A19: Plazo total (meses) | B19: =IFERROR('0. Supuestos'!$B$39,"") -> 84
A20: Carencia de principal aplicada (meses) | B20: =IFERROR(IF('0. Supuestos'!$B$40>='0. Supuestos'!$B$39,'0. Supuestos'!$B$39-1,'0. Supuestos'!$B$40),"") -> 6 | H20: Una carencia igual o mayor que el plazo no existe: la hoja la anula en origen.
A21: Meses de amortización | B21: =IFERROR(B19-B20,"") -> 78
A22: Cuota mensual durante la amortización | B22: =IFERROR(IF(B21<=0,"",IF(B18=0,B16/B21,B16*B18/(1-(1+B18)^(-B21)))),"") -> 936.57242
A23: Sistema francés, escrito como anualidad algebraica: capital x tipo mensual dividido por uno menos (uno más el tipo) elevado a menos el número de cuotas. Con el tipo al 0 % es el principal entre los meses de amortización. No se usa la función PMT: la familia la tiene prohibida porque no todos los motores de hoja de cálculo la evalúan igual.
A25: Mes | B25: Capital pendiente (€) | C25: Intereses (€) | D25: Amortización de principal (€) | E25: Cuota total (€) | F25: Capital al cierre (€) | H25: Notas
A26: 1 | B26: =IFERROR(IF($B$16="","",$B$16),"") -> 60000 | C26: =IFERROR(IF(OR(A26>$B$19,B26=""),"",B26*$B$18),"") -> 310 | D26: =IFERROR(IF(OR(A26>$B$19,B26=""),"",IF(A26<=$B$20,0,MIN(B26,$B$22-C26))),"") -> 0 | E26: =IFERROR(IF(C26="","",C26+D26),"") -> 310 | F26: =IFERROR(IF(D26="","",B26-D26),"") -> 60000 | H26: Durante la carencia la columna de amortización vale cero y sólo se pagan intereses. Es lo que hace que el préstamo no se coma la caja en la rampa de arranque, y es lo primero que hay que negociar.
A27: 2 | B27: =IFERROR(IF(OR(A27>$B$19,F26=""),"",F26),"") -> 60000 | C27: =IFERROR(IF(OR(A27>$B$19,B27=""),"",B27*$B$18),"") -> 310 | D27: =IFERROR(IF(OR(A27>$B$19,B27=""),"",IF(A27<=$B$20,0,MIN(B27,$B$22-C27))),"") -> 0 | E27: =IFERROR(IF(C27="","",C27+D27),"") -> 310 | F27: =IFERROR(IF(D27="","",B27-D27),"") -> 60000
A28: 3 | B28: =IFERROR(IF(OR(A28>$B$19,F27=""),"",F27),"") -> 60000 | C28: =IFERROR(IF(OR(A28>$B$19,B28=""),"",B28*$B$18),"") -> 310 | D28: =IFERROR(IF(OR(A28>$B$19,B28=""),"",IF(A28<=$B$20,0,MIN(B28,$B$22-C28))),"") -> 0 | E28: =IFERROR(IF(C28="","",C28+D28),"") -> 310 | F28: =IFERROR(IF(D28="","",B28-D28),"") -> 60000
A29: 4 | B29: =IFERROR(IF(OR(A29>$B$19,F28=""),"",F28),"") -> 60000 | C29: =IFERROR(IF(OR(A29>$B$19,B29=""),"",B29*$B$18),"") -> 310 | D29: =IFERROR(IF(OR(A29>$B$19,B29=""),"",IF(A29<=$B$20,0,MIN(B29,$B$22-C29))),"") -> 0 | E29: =IFERROR(IF(C29="","",C29+D29),"") -> 310 | F29: =IFERROR(IF(D29="","",B29-D29),"") -> 60000
A30: 5 | B30: =IFERROR(IF(OR(A30>$B$19,F29=""),"",F29),"") -> 60000 | C30: =IFERROR(IF(OR(A30>$B$19,B30=""),"",B30*$B$18),"") -> 310 | D30: =IFERROR(IF(OR(A30>$B$19,B30=""),"",IF(A30<=$B$20,0,MIN(B30,$B$22-C30))),"") -> 0 | E30: =IFERROR(IF(C30="","",C30+D30),"") -> 310 | F30: =IFERROR(IF(D30="","",B30-D30),"") -> 60000
A31: 6 | B31: =IFERROR(IF(OR(A31>$B$19,F30=""),"",F30),"") -> 60000 | C31: =IFERROR(IF(OR(A31>$B$19,B31=""),"",B31*$B$18),"") -> 310 | D31: =IFERROR(IF(OR(A31>$B$19,B31=""),"",IF(A31<=$B$20,0,MIN(B31,$B$22-C31))),"") -> 0 | E31: =IFERROR(IF(C31="","",C31+D31),"") -> 310 | F31: =IFERROR(IF(D31="","",B31-D31),"") -> 60000
A32: 7 | B32: =IFERROR(IF(OR(A32>$B$19,F31=""),"",F31),"") -> 60000 | C32: =IFERROR(IF(OR(A32>$B$19,B32=""),"",B32*$B$18),"") -> 310 | D32: =IFERROR(IF(OR(A32>$B$19,B32=""),"",IF(A32<=$B$20,0,MIN(B32,$B$22-C32))),"") -> 626.57242 | E32: =IFERROR(IF(C32="","",C32+D32),"") -> 936.57242 | F32: =IFERROR(IF(D32="","",B32-D32),"") -> 59373.428
A33: 8 | B33: =IFERROR(IF(OR(A33>$B$19,F32=""),"",F32),"") -> 59373.428 | C33: =IFERROR(IF(OR(A33>$B$19,B33=""),"",B33*$B$18),"") -> 306.76271 | D33: =IFERROR(IF(OR(A33>$B$19,B33=""),"",IF(A33<=$B$20,0,MIN(B33,$B$22-C33))),"") -> 629.80971 | E33: =IFERROR(IF(C33="","",C33+D33),"") -> 936.57242 | F33: =IFERROR(IF(D33="","",B33-D33),"") -> 58743.618
A34: 9 | B34: =IFERROR(IF(OR(A34>$B$19,F33=""),"",F33),"") -> 58743.618 | C34: =IFERROR(IF(OR(A34>$B$19,B34=""),"",B34*$B$18),"") -> 303.50869 | D34: =IFERROR(IF(OR(A34>$B$19,B34=""),"",IF(A34<=$B$20,0,MIN(B34,$B$22-C34))),"") -> 633.06372 | E34: =IFERROR(IF(C34="","",C34+D34),"") -> 936.57242 | F34: =IFERROR(IF(D34="","",B34-D34),"") -> 58110.554
A35: 10 | B35: =IFERROR(IF(OR(A35>$B$19,F34=""),"",F34),"") -> 58110.554 | C35: =IFERROR(IF(OR(A35>$B$19,B35=""),"",B35*$B$18),"") -> 300.23786 | D35: =IFERROR(IF(OR(A35>$B$19,B35=""),"",IF(A35<=$B$20,0,MIN(B35,$B$22-C35))),"") -> 636.33455 | E35: =IFERROR(IF(C35="","",C35+D35),"") -> 936.57242 | F35: =IFERROR(IF(D35="","",B35-D35),"") -> 57474.22
A36: 11 | B36: =IFERROR(IF(OR(A36>$B$19,F35=""),"",F35),"") -> 57474.22 | C36: =IFERROR(IF(OR(A36>$B$19,B36=""),"",B36*$B$18),"") -> 296.95013 | D36: =IFERROR(IF(OR(A36>$B$19,B36=""),"",IF(A36<=$B$20,0,MIN(B36,$B$22-C36))),"") -> 639.62228 | E36: =IFERROR(IF(C36="","",C36+D36),"") -> 936.57242 | F36: =IFERROR(IF(D36="","",B36-D36),"") -> 56834.597
A37: 12 | B37: =IFERROR(IF(OR(A37>$B$19,F36=""),"",F36),"") -> 56834.597 | C37: =IFERROR(IF(OR(A37>$B$19,B37=""),"",B37*$B$18),"") -> 293.64542 | D37: =IFERROR(IF(OR(A37>$B$19,B37=""),"",IF(A37<=$B$20,0,MIN(B37,$B$22-C37))),"") -> 642.927 | E37: =IFERROR(IF(C37="","",C37+D37),"") -> 936.57242 | F37: =IFERROR(IF(D37="","",B37-D37),"") -> 56191.67
A38: 13 | B38: =IFERROR(IF(OR(A38>$B$19,F37=""),"",F37),"") -> 56191.67 | C38: =IFERROR(IF(OR(A38>$B$19,B38=""),"",B38*$B$18),"") -> 290.32363 | D38: =IFERROR(IF(OR(A38>$B$19,B38=""),"",IF(A38<=$B$20,0,MIN(B38,$B$22-C38))),"") -> 646.24879 | E38: =IFERROR(IF(C38="","",C38+D38),"") -> 936.57242 | F38: =IFERROR(IF(D38="","",B38-D38),"") -> 55545.422
... A109: 84 | B109: =IFERROR(IF(OR(A109>$B$19,F108=""),"",F108),"") -> 931.75833 | C109: =IFERROR(IF(OR(A109>$B$19,B109=""),"",B109*$B$18),"") -> 4.8140847 | D109: =IFERROR(IF(OR(A109>$B$19,B109=""),"",IF(A109<=$B$20,0,MIN(B109,$B$22-C109))),"") -> 931.75833 | E109: =IFERROR(IF(C109="","",C109+D109),"") -> 936.57242 | F109: =IFERROR(IF(D109="","",B109-D109),"") -> 1.4043735e-09
A110: Tolerancia de cierre del cuadro (€) | B110: 0.01
A111: Capital pendiente al vencimiento | B111: =IFERROR(IF($B$16="","",ROUND($B$16-SUM(D26:D109),2)),"") -> 0
A112: ¿Cierra el cuadro de amortización? | B112: =IFERROR(IF(B111="","",IF(ABS(B111)<=B110,"Sí","No: revisa el plazo")),"") -> Sí | H112: Tiene que decir «Sí»: el principal devuelto en el cuadro tiene que ser el prestado. Si dice que no, el plazo no da para amortizarlo con esa cuota y queda capital sin devolver al vencimiento.
A114: RESUMEN POR AÑO Y COBERTURA DEL SERVICIO DE LA DEUDA (DSCR)
A115: Año | B115: Intereses (€) | C115: Principal devuelto (€) | D115: Cuota total (€) | E115: Flujo disponible para la deuda (€) | F115: DSCR | H115: Notas
A116: 1 | B116: =IFERROR(SUM(C26:C37),"") -> 3671.1048 | C116: =IFERROR(SUM(D26:D37),"") -> 3808.3297 | D116: =IFERROR(B116+C116,"") -> 7479.4345 | E116: =IFERROR('PyG 3 Años'!B36-'PyG 3 Años'!B41+'PyG 3 Años'!B31+B116,"") -> 24229.773 | F116: =IFERROR(IF(OR(D116="",D116=0),"",E116/D116),"") -> 3.2395193 | H116: El flujo disponible se calcula ANTES de la deuda y DESPUÉS de impuestos: al resultado antes de impuestos se le resta la cuota del Impuesto de Sociedades y se le suma la amortización, que no se paga. Del año 4 en adelante se mantiene el flujo del año 3: este libro no proyecta más lejos, y decirlo es más honesto que inventarse un crecimiento.
A117: 2 | B117: =IFERROR(SUM(C38:C49),"") -> 3259.673 | C117: =IFERROR(SUM(D38:D49),"") -> 7979.196 | D117: =IFERROR(B117+C117,"") -> 11238.869 | E117: =IFERROR('PyG 3 Años'!C36-'PyG 3 Años'!C41+'PyG 3 Años'!C31+B117,"") -> 47186.16 | F117: =IFERROR(IF(OR(D117="",D117=0),"",E117/D117),"") -> 4.1984794
A118: 3 | B118: =IFERROR(SUM(C50:C61),"") -> 2750.6598 | C118: =IFERROR(SUM(D50:D61),"") -> 8488.2092 | D118: =IFERROR(B118+C118,"") -> 11238.869 | E118: =IFERROR('PyG 3 Años'!D36-'PyG 3 Años'!D41+'PyG 3 Años'!D31+B118,"") -> 50356.866 | F118: =IFERROR(IF(OR(D118="",D118=0),"",E118/D118),"") -> 4.4805991
A119: 4 | B119: =IFERROR(SUM(C62:C73),"") -> 2209.1755 | C119: =IFERROR(SUM(D62:D73),"") -> 9029.6935 | D119: =IFERROR(B119+C119,"") -> 11238.869 | E119: =IFERROR('PyG 3 Años'!D36-'PyG 3 Años'!D41+'PyG 3 Años'!D31+B119,"") -> 49815.382 | F119: =IFERROR(IF(OR(D119="",D119=0),"",E119/D119),"") -> 4.4324195
A120: 5 | B120: =IFERROR(SUM(C74:C85),"") -> 1633.1485 | C120: =IFERROR(SUM(D74:D85),"") -> 9605.7205 | D120: =IFERROR(B120+C120,"") -> 11238.869 | E120: =IFERROR('PyG 3 Años'!D36-'PyG 3 Años'!D41+'PyG 3 Años'!D31+B120,"") -> 49239.355 | F120: =IFERROR(IF(OR(D120="",D120=0),"",E120/D120),"") -> 4.3811664
A121: 6 | B121: =IFERROR(SUM(C86:C97),"") -> 1020.3753 | C121: =IFERROR(SUM(D86:D97),"") -> 10218.494 | D121: =IFERROR(B121+C121,"") -> 11238.869 | E121: =IFERROR('PyG 3 Años'!D36-'PyG 3 Años'!D41+'PyG 3 Años'!D31+B121,"") -> 48626.582 | F121: =IFERROR(IF(OR(D121="",D121=0),"",E121/D121),"") -> 4.3266437
A122: 7 | B122: =IFERROR(SUM(C98:C109),"") -> 368.51167 | C122: =IFERROR(SUM(D98:D109),"") -> 10870.357 | D122: =IFERROR(B122+C122,"") -> 11238.869 | E122: =IFERROR('PyG 3 Años'!D36-'PyG 3 Años'!D41+'PyG 3 Años'!D31+B122,"") -> 47974.718 | F122: =IFERROR(IF(OR(D122="",D122=0),"",E122/D122),"") -> 4.2686429
A123: DSCR mínimo de todo el cuadro | B123: =IFERROR(IF(COUNT(F116:F122)=0,"",MIN(F116:F122)),"") -> 3.2395193 | H123: Es el PEOR año de los que dura el préstamo, no el mejor de los tres que proyecta el P&L. Es el número que decide la operación.
A124: Lectura del DSCR | B124: =IFERROR(IF(B123="","",IF(B123<'0. Supuestos'!$B$58,"Por debajo del mínimo",IF(B123<'0. Supuestos'!$B$59,"Entre el mínimo y el objetivo","En objetivo"))),"") -> En objetivo
A126: El año de carencia infla el DSCR: con sólo intereses en el denominador el ratio se dispara y no está midiendo el negocio, está midiendo que todavía no devuelves nada. Mira el año 2 y el año 3, que es cuando la cuota está completa.

Sheet Canales y Punto Muerto
A1: Canales y Punto Muerto: Qué Canal Sostiene el Negocio
A2: AI Chef Pro · aichef.pro — Cómo Montar una Pastelería
A3: Cada canal tiene su margen, su coste de servir, su comisión y sus días de cobro. La suma no es lo interesante: lo interesante es qué pasa con el punto muerto cuando quitas uno.
A5: Canal | B5: % de las ventas | C5: Margen bruto (%) | D5: Coste de servir (%) | E5: Comisión de plataforma (%) | F5: Días de cobro | G5: Margen de contribución (%) | H5: Ventas del año de crucero (€) | I5: Margen de contribución (€) | J5: Notas
A6: Mostrador | B6: 0.78 | C6: 0.68 | D6: 0 | E6: 0 | F6: 0 | G6: =IFERROR(C6-D6-E6,"") -> 0.68 | H6: =IFERROR(IF('PyG 3 Años'!$C$11="","",'PyG 3 Años'!$C$11*B6),"") -> 251314.34 | I6: =IFERROR(IF(H6="","",H6*G6),"") -> 170893.75 | J6: Cobro al contado. Es el canal que paga el alquiler.
A7: Encargos | B7: 0.14 | C7: 0.7 | D7: 0.02 | E7: 0 | F7: 0 | G7: =IFERROR(C7-D7-E7,"") -> 0.68 | H7: =IFERROR(IF('PyG 3 Años'!$C$11="","",'PyG 3 Años'!$C$11*B7),"") -> 45107.702 | I7: =IFERROR(IF(H7="","",H7*G7),"") -> 30673.237 | J7: Anticipo del 30 % al reservar (supuesto): es lo que convierte una anulación en una molestia y no en una pérdida. Mejor margen porque el producto se hace contra pedido y la merma es cero.
A8: B2B (cafeterías y restaurantes de la zona) | B8: 0.05 | C8: 0.52 | D8: 0.03 | E8: 0 | F8: 45 | G8: =IFERROR(C8-D8-E8,"") -> 0.49 | H8: =IFERROR(IF('PyG 3 Años'!$C$11="","",'PyG 3 Años'!$C$11*B8),"") -> 16109.894 | I8: =IFERROR(IF(H8="","",H8*G8),"") -> 7893.8479 | J8: El 5 % sale de PS-53 (venta a crédito a 30-60 días). Peor margen y cobro a 45 días: financias tú. Y ojo, es el canal que puede meterte en el art. 3 del RD 1021/2022 si dejas de ser marginal, localizado o restringido (PA-02): basta con servir a UN solo cliente inscrito en el RGSEAA para perder el requisito de «restringido».
A9: Online y envío | B9: 0.03 | C9: 0.6 | D9: 0.09 | E9: 0 | F9: 0 | G9: =IFERROR(C9-D9-E9,"") -> 0.51 | H9: =IFERROR(IF('PyG 3 Años'!$C$11="","",'PyG 3 Años'!$C$11*B9),"") -> 9665.9362 | I9: =IFERROR(IF(H9="","",H9*G9),"") -> 4929.6275 | J9: Comisión 0 % porque es web propia. Si vendes por marketplace, mete su comisión en la celda verde: es el número que decide si el canal existe. La venta a distancia YA está dentro de la definición de minorista (PA-01b y PA-27): vender online no te saca de este régimen. Y hay información obligatoria ANTES de la compra (PA-28).
A10: TOTAL | B10: =IFERROR(IF(COUNT(B6:B9)=0,"",SUM(B6:B9)),"") -> 1 | G10: =IFERROR(I10/H10,"") -> 0.6654 | H10: =IFERROR(IF(COUNT(H6:H9)=0,"",SUM(H6:H9)),"") -> 322197.87 | I10: =IFERROR(IF(COUNT(I6:I9)=0,"",SUM(I6:I9)),"") -> 214390.46 | J10: La columna «% de las ventas» tiene que sumar 100 %. Si no suma, todo lo de abajo está mal.
A12: EL PUNTO MUERTO, CANAL A CANAL
A13: Costes fijos del año de crucero (€) | B13: =IFERROR('PyG 3 Años'!$C$33,"") -> 186345.79
A14: Costes fijos mensuales (€) | B14: =IFERROR(B13/12,"") -> 15528.815
A15: Margen de contribución medio ponderado (%) | B15: =IFERROR(G10,"") -> 0.6654
A16: Margen bruto objetivo de la regla única (%) | B16: =IFERROR('0. Supuestos'!$B$23,"") -> 0.68
A17: Lo que se llevan servir, cobrar y las comisiones (%) | B17: =IFERROR(B16-B15,"") -> 0.0146 | J17: La diferencia entre el margen bruto de la carta y el margen de contribución real. No es un error de ninguno de los dos: es lo que cuesta poner el producto en manos del cliente por cada vía.
A18: Punto muerto mensual CON todos los canales (€) | B18: =IFERROR(IF(B15<=0,"",B14/B15),"") -> 23337.565
A19: Punto muerto mensual SIN el canal B2B (€) | B19: =IFERROR(IF(OR(H10-H8<=0,(I10-I8)/(H10-H8)<=0),"",B14/((I10-I8)/(H10-H8))),"") -> 23018.216
A20: Diferencia (€/mes) | B20: =IFERROR(IF(OR(B19="",B18=""),"",B19-B18),"") -> -319.34848 | J20: Si sale NEGATIVA, quitar el B2B te BAJA el punto muerto: ese canal estaba tirando del margen medio hacia abajo, y lo que aporta es volumen, no rentabilidad. Ojo, eso no dice que haya que cerrarlo: dice qué tienes que exigirle.
A21: Canal que sostiene el negocio | B21: =IFERROR(IF(COUNT(I6:I9)=0,"",INDEX($A$6:$A$9,MATCH(MAX($I$6:$I$9),$I$6:$I$9,0))),"") -> Mostrador
A22: Aporte de ese canal al margen de contribución (%) | B22: =IFERROR(IF(I10="","",MAX($I$6:$I$9)/I10),"") -> 0.79711452 | J22: Es el canal que paga el alquiler. Todo lo que pongas en marcha en los otros tres se financia con éste, así que lo primero que hay que proteger es su margen.
A24: EL AVISO DEL ART. 3: CUÁNDO EL B2B TE CAMBIA DE RÉGIMEN
A25: Peso del B2B sobre las ventas (%) | B25: =IFERROR(B8,"") -> 0.05
A26: Umbral de la vía a) del art. 3.2 (%) | B26: 0.25 | J26: Una actividad es marginal si el suministro a otros minoristas es menor o igual al 25 % del volumen anual O si la comercialización total no pasa de 500 kg a la semana. Son vías ALTERNATIVAS: basta cumplir una. La de los kilos se comprueba en el libro «checklist-legal-y-licencias».
A27: Lectura del art. 3 por la vía del porcentaje | B27: =IFERROR(IF(B25=0,"Sin B2B: el art. 3 no te aplica",IF(B25<=B26,"Marginal por la vía a): sigue la comprobación en el libro de licencias","Por encima del 25 %: comprueba la vía de los 500 kg antes de nada")),"") -> Marginal por la vía a): sigue la comprobación en el libro de licencias
A28: El art. 3 del RD 1021/2022 sólo se activa si suministras a establecimientos minoristas de DISTINTA titularidad. Si entras, las tres condiciones son ACUMULATIVAS -marginal Y localizado Y restringido- y hay que presentar declaración responsable y llevar registro de destinatarios, cantidades y fechas. Este aviso mira sólo el porcentaje: el árbol completo está en el libro «checklist-legal-y-licencias».
A29: Días medios de cobro ponderados | B29: =IFERROR('0. Supuestos'!$B$52,"") -> 2.25 | J29: Es el número que usa la hoja de Tesorería para desfasar los cobros. Sube solo en cuanto crece el B2B, y ése es su coste oculto: no es sólo que deje menos margen, es que lo deja más tarde.
A31: Los porcentajes de esta hoja son SUPUESTOS salvo el peso del B2B, que sale de la única cifra publicada de estructura de cobro de una pastelería española: 95 % de venta directa y 5 % a crédito a 30-60 días. El reparto entre mostrador, encargos y online es una hipótesis de trabajo: cámbiala por la tuya en cuanto tengas tres meses de datos reales del TPV.
