Workbook

Sheet Instrucciones
A1: Plantilla, turnos y coste de personal
A2: AI Chef Pro · aichef.pro — Cómo Montar una Pastelería
A3: Para qué sirve: decidir cuánta gente necesitas, de qué perfil, en qué turno y cuánto cuesta de verdad con la Seguridad Social dentro.
A5: Instrucciones de uso
A6: 1. Hoja «Parámetros»: los seis grupos del convenio de pastelería de Madrid de 2026, las pagas, la Seguridad Social a cargo de la empresa, la jornada completa y el mes en el que piensas abrir. Todo en verde: si tu provincia tiene convenio propio -y casi todas lo tienen-, sustituye los seis brutos por los tuyos y el libro entero se recalcula.
A7: 2. Hoja «Turnos Semanales»: cuántas horas hace cada persona cada día. Viene rellena con la plantilla del caso «La Clara»: cinco personas y 3,5 jornadas. La hoja suma las horas por persona y por día, separa obrador de despacho y avisa si algún día que abres se queda sin nadie en el mostrador.
A8: 3. Hoja «Horas y Coste»: asigna a cada persona su grupo de convenio y la hoja calcula el bruto ajustado a su jornada, el bruto anual con las 15 pagas, el coste de empresa con la Seguridad Social dentro y el coste por hora. Avisa si alguien pasa de la jornada completa y si un grupo se te queda por debajo del SMI.
A9: 4. Hoja «Plan de Contratación»: cuándo das de alta a cada uno y cuánto cuesta el primer año, que NO es el año de crucero porque nadie entra el día 1. Debajo, el refuerzo de las seis campañas: personas, horas y coste de cada pico.
A10: 5. Lleva al libro 5 (plan financiero) sólo dos números: el coste de personal del año de crucero y el del primer año. Se copian a mano, a propósito: en todo este pack no hay ni una fórmula que apunte a otro fichero.
A12: Celdas verdes = campos editables
A14: Lo que conviene saber antes de empezar
A15: DEL BRUTO AL COSTE DE EMPRESA HAY UN 33 %, Y ESE ES EL NÚMERO QUE HUNDE LOS PLANES. Un ayudante de 1.192,42 € al mes no cuesta 1.192,42 €: con 15 pagas y la Seguridad Social a cargo de la empresa cuesta casi 24.000 € al año a jornada completa. La plantilla del caso «La Clara» -cinco personas, 3,5 jornadas- sale por encima de los 92.000 € anuales. Ese es el número que se lleva al plan financiero.
... A30: Versión 1.0 · septiembre 2026 · aichef.pro/guia-pasteleria-obrador · info@aichef.pro

Sheet Parámetros
A1: Parámetros: Convenio, Cotización y Jornada
A2: AI Chef Pro · aichef.pro — Cómo Montar una Pastelería
A3: Todo lo verde de esta hoja gobierna las otras tres. Los seis brutos son los del convenio de pastelería de Madrid de 2026: sustitúyelos por los de tu convenio provincial.
A5: Los seis grupos del convenio de referencia
A6: Convenio del Sector de Comercio e Industria de Confitería, Pastelería, Bollería, Repostería, Heladería y Platos Cocinados de la Comunidad de Madrid, código 28001025011981. Revisión salarial 2026 publicada en el BOCM núm. 50, de 28 de febrero de 2026, vigencia 1-ene-2026 a 31-dic-2026. Tablas a 15 pagas.
A7: Grupo | B7: Descripción funcional | C7: Bruto mensual (€) | D7: Bruto anual publicado (€) | E7: Áreas funcionales | F7: Puestos que cita el convenio | G7: Nota
A8: 1 | B8: Técnicos y titulados superiores | C8: 1733.88 | D8: 26008.2 | E8: ADMINISTRACIÓN | G8: Bruto de tabla, sin antigüedad, plus de nocturnidad ni horas extra. El obrador entra de madrugada: mira el plus de nocturnidad de tu convenio antes de cerrar el número.
A9: 2 | B9: Dirección, jefes y encargados | C9: 1427.89 | D9: 21418.35 | E9: OBRADOR · COMERCIO · ADMINISTRACIÓN | F9: maestro de obrador | G9: Bruto de tabla, sin antigüedad, plus de nocturnidad ni horas extra. El obrador entra de madrugada: mira el plus de nocturnidad de tu convenio antes de cerrar el número.
A10: 3 | B10: Personal especialista | C10: 1376.91 | D10: 20653.65 | E10: OBRADOR · COMERCIO | F10: oficial 1.ª de producción, encargado de sección, dependiente mayor | G10: Bruto de tabla, sin antigüedad, plus de nocturnidad ni horas extra. El obrador entra de madrugada: mira el plus de nocturnidad de tu convenio antes de cerrar el número.
A11: 4 | B11: Personal cualificado | C11: 1249.42 | D11: 18741.3 | E11: OBRADOR · COMERCIO | F11: oficial 2.ª de producción, oficial 1.ª de envasado, dependiente, conductor | G11: Bruto de tabla, sin antigüedad, plus de nocturnidad ni horas extra. El obrador entra de madrugada: mira el plus de nocturnidad de tu convenio antes de cerrar el número.
A12: 5 | B12: Personal de apoyo | C12: 1192.42 | D12: 17886.3 | E12: OBRADOR · COMERCIO | F12: ayudante de producción, oficial de acabado, ayudante de comercio | G12: Bruto de tabla, sin antigüedad, plus de nocturnidad ni horas extra. El obrador entra de madrugada: mira el plus de nocturnidad de tu convenio antes de cerrar el número.
A13: 6 | B13: Personal de ayuda en servicios auxiliares | C13: 1192.42 | D13: 17886.3 | E13: OBRADOR · COMERCIO | F13: peón, limpiador, almacenero | G13: Bruto de tabla, sin antigüedad, plus de nocturnidad ni horas extra. El obrador entra de madrugada: mira el plus de nocturnidad de tu convenio antes de cerrar el número.
A15: Pagas del convenio | C15: 15 | E15: El convenio de Madrid paga 15, no 14, y eso cambia el coste todos los meses. Si tu convenio prorratea las extras, sigue siendo 15: lo que cambia es cuándo se pagan, no cuánto.
A16: Bruto anual del grupo más bajo (€) | C16: =IFERROR(MIN($C$8:$C$13)*$C$15,"") -> 17886.3 | E16: Se calcula con los brutos de arriba y las pagas: es el número que se compara con el SMI.
A17: Referencia anual del SMI (€) | C17: 17094 | E17: Cuantía ANUAL de referencia del art. 3.1 del RD 126/2026, en cómputo global: no es un mínimo por concepto ni el resultado de multiplicar por catorce. CADUCA el 31-12-2026.
A18: ¿Manda el convenio o el SMI? | C18: =IF($C$16="","",IF($C$16>=$C$17,"Manda el convenio: el grupo más bajo supera el SMI","OJO: el grupo más bajo se queda por debajo del SMI anual")) -> Manda el convenio: el grupo más bajo supera el SMI | E18: En pastelería manda el convenio. Este aviso existe por si tecleas el de otra provincia: ningún grupo puede quedar por debajo del SMI en cómputo anual.
A20: Cotización, jornada y calendario
A21: Seguridad Social a cargo de la empresa (%) | C21: 0.33 | E21: Cotización empresarial aproximada sobre el salario bruto (contingencias comunes, desempleo, FOGASA y formación). Ajústala a tu convenio y a tus contratos.
A22: Horas semanales de jornada completa | C22: 40 | E22: SUPUESTO: la jornada anual del convenio de Madrid no está verificada. Cámbiala por la de tu convenio; es la que decide si alguien se pasa de jornada y cuántas jornadas equivalentes tienes.
A23: Horas anuales de contrato | C23: 1780 | E23: SUPUESTO: 40 h × 52 semanas = 2.080, menos 30 días naturales de vacaciones y los festivos. Es el divisor del coste por hora, y por eso el coste por hora sale más caro de lo que la gente espera.
A24: Días de apertura a la semana | C24: 6 | E24: SUPUESTO. La pastelería tiene libertad horaria por ley estatal cuando es su actividad principal, así que abrir en domingo o en festivo es una decisión tuya, no un permiso que se pida.
A25: Mes de apertura previsto (1 a 12) | C25: 9 | E25: SUPUESTO: septiembre. No es ninguno de los seis picos y deja tres meses y medio de rodaje antes de Reyes, que es la campaña que decide el año. La fecha realista la calcula la ruta crítica del libro 6.
A27: Los seis brutos y las pagas son datos verificados contra el BOCM el 10-09-2026 (pasa el ratón por encima de cada celda para ver la fuente). Todo lo demás de esta hoja es SUPUESTO y se dice en cada nota. Un convenio provincial distinto no cambia ninguna fórmula de este libro: cambia seis números.
A28: Lo que esta hoja NO trae, a propósito: antigüedad, plus de nocturnidad, horas extra, pluses de transporte y bonificaciones a la contratación. Son reales y cambian el coste, pero dependen de tu convenio y de cada contrato: cuando los tengas, súmalos al bruto mensual de cada grupo.
A31: Diseñado por John Guerrero — chef y consultor gastronómico desde 2010, en cocina desde los 17 años.
A32: Versión 1.0 · septiembre 2026 · aichef.pro/guia-pasteleria-obrador · info@aichef.pro

Sheet Turnos Semanales
A1: Turnos Semanales
A2: AI Chef Pro · aichef.pro — Cómo Montar una Pastelería
A3: Cinco personas y 3,5 jornadas: el dimensionado del caso «La Clara». Los cuatro perfiles son los literales del 04-tareas-perfiles.xlsx del kit, con dos personas en Dependiente Vitrina.
A5: ¿Qué días abre el despacho?
A6: Día | E6: L | F6: M | G6: X | H6: J | I6: V | J6: S | K6: D
A7: ¿Abre el despacho? | E7: Sí | F7: Sí | G7: Sí | H7: Sí | I7: Sí | J7: Sí | K7: No | L7: SUPUESTO: seis días, con el domingo cerrado. Es una decisión tuya, no un permiso: la pastelería tiene libertad horaria.
A9: Horas por persona y día
A10: Id | B10: Persona (perfil del kit) | C10: Área | D10: Turno | E10: L | F10: M | G10: X | H10: J | I10: V | J10: S | K10: D | L10: Horas planificadas / semana | M10: Horas contratadas / semana | N10: Diferencia (h) | O10: Nota
A11: P1 | B11: Jefe Pastelero | C11: OBRADOR | D11: Madrugada (04:30-12:30) | E11: 0 | F11: 8 | G11: 8 | H11: 8 | I11: 8 | J11: 8 | K11: 0 | L11: =SUM($E11:$K11) -> 40 | M11: 40 | N11: =IFERROR(IF(OR($L11="",$M11=""),"",$L11-$M11),"") -> 0 | O11: Jornada contratada: completa. Las horas del reparto son un SUPUESTO que cuadra con esa jornada.
A12: P2 | B12: Pastelero | C12: OBRADOR | D12: Madrugada (05:00-13:00) | E12: 8 | F12: 8 | G12: 8 | H12: 8 | I12: 8 | J12: 0 | K12: 0 | L12: =SUM($E12:$K12) -> 40 | M12: 40 | N12: =IFERROR(IF(OR($L12="",$M12=""),"",$L12-$M12),"") -> 0 | O12: Jornada contratada: completa. Las horas del reparto son un SUPUESTO que cuadra con esa jornada.
A13: P3 | B13: Ayudante | C13: OBRADOR | D13: Mañana (07:00-11:00) | E13: 4 | F13: 4 | G13: 4 | H13: 4 | I13: 4 | J13: 0 | K13: 0 | L13: =SUM($E13:$K13) -> 20 | M13: 20 | N13: =IFERROR(IF(OR($L13="",$M13=""),"",$L13-$M13),"") -> 0 | O13: Jornada contratada: 50 %. Las horas del reparto son un SUPUESTO que cuadra con esa jornada.
A14: P4 | B14: Dependiente Vitrina A | C14: COMERCIO | D14: Mañana (08:00-12:00) | E14: 4 | F14: 4 | G14: 4 | H14: 4 | I14: 4 | J14: 0 | K14: 0 | L14: =SUM($E14:$K14) -> 20 | M14: 20 | N14: =IFERROR(IF(OR($L14="",$M14=""),"",$L14-$M14),"") -> 0 | O14: Jornada contratada: 50 %. Las horas del reparto son un SUPUESTO que cuadra con esa jornada.
A15: P5 | B15: Dependiente Vitrina B | C15: COMERCIO | D15: Tarde (16:30-20:30) | E15: 0 | F15: 4 | G15: 4 | H15: 4 | I15: 4 | J15: 4 | K15: 0 | L15: =SUM($E15:$K15) -> 20 | M15: 20 | N15: =IFERROR(IF(OR($L15="",$M15=""),"",$L15-$M15),"") -> 0 | O15: Jornada contratada: 50 %. Las horas del reparto son un SUPUESTO que cuadra con esa jornada.
A16: TOTAL de la plantilla | E16: =SUM($E$11:$E$15) -> 16 | F16: =SUM($F$11:$F$15) -> 28 | G16: =SUM($G$11:$G$15) -> 28 | H16: =SUM($H$11:$H$15) -> 28 | I16: =SUM($I$11:$I$15) -> 28 | J16: =SUM($J$11:$J$15) -> 12 | K16: =SUM($K$11:$K$15) -> 0 | L16: =SUM($L$11:$L$15) -> 140 | M16: =SUM($M$11:$M$15) -> 140
A17: Horas de OBRADOR por día | E17: =SUMPRODUCT(--($C$11:$C$15="OBRADOR"),$E$11:$E$15) -> 12 | F17: =SUMPRODUCT(--($C$11:$C$15="OBRADOR"),$F$11:$F$15) -> 20 | G17: =SUMPRODUCT(--($C$11:$C$15="OBRADOR"),$G$11:$G$15) -> 20 | H17: =SUMPRODUCT(--($C$11:$C$15="OBRADOR"),$H$11:$H$15) -> 20 | I17: =SUMPRODUCT(--($C$11:$C$15="OBRADOR"),$I$11:$I$15) -> 20 | J17: =SUMPRODUCT(--($C$11:$C$15="OBRADOR"),$J$11:$J$15) -> 8 | K17: =SUMPRODUCT(--($C$11:$C$15="OBRADOR"),$K$11:$K$15) -> 0
A18: Horas de DESPACHO por día | E18: =SUMPRODUCT(--($C$11:$C$15="COMERCIO"),$E$11:$E$15) -> 4 | F18: =SUMPRODUCT(--($C$11:$C$15="COMERCIO"),$F$11:$F$15) -> 8 | G18: =SUMPRODUCT(--($C$11:$C$15="COMERCIO"),$G$11:$G$15) -> 8 | H18: =SUMPRODUCT(--($C$11:$C$15="COMERCIO"),$H$11:$H$15) -> 8 | I18: =SUMPRODUCT(--($C$11:$C$15="COMERCIO"),$I$11:$I$15) -> 8 | J18: =SUMPRODUCT(--($C$11:$C$15="COMERCIO"),$J$11:$J$15) -> 4 | K18: =SUMPRODUCT(--($C$11:$C$15="COMERCIO"),$K$11:$K$15) -> 0
A19: Cobertura del despacho | E19: =IF($E$7<>"Sí","Cerrado",IF($E$18=0,"SIN NADIE","Cubierto")) -> Cubierto | F19: =IF($F$7<>"Sí","Cerrado",IF($F$18=0,"SIN NADIE","Cubierto")) -> Cubierto | G19: =IF($G$7<>"Sí","Cerrado",IF($G$18=0,"SIN NADIE","Cubierto")) -> Cubierto | H19: =IF($H$7<>"Sí","Cerrado",IF($H$18=0,"SIN NADIE","Cubierto")) -> Cubierto | I19: =IF($I$7<>"Sí","Cerrado",IF($I$18=0,"SIN NADIE","Cubierto")) -> Cubierto | J19: =IF($J$7<>"Sí","Cerrado",IF($J$18=0,"SIN NADIE","Cubierto")) -> Cubierto | K19: =IF($K$7<>"Sí","Cerrado",IF($K$18=0,"SIN NADIE","Cubierto")) -> Cerrado
A21: Resumen de la semana
A22: Horas planificadas a la semana | E22: =$L$16 -> 140 | H22: Es la semana tipo de velocidad de crucero, sin campañas.
A23: Jornadas equivalentes | E23: =IFERROR($L$16/'Parámetros'!$C$22,"") -> 3.5 | H23: Horas planificadas divididas por la jornada completa. El caso «La Clara» son 3,5 jornadas repartidas en cinco personas.
A24: Horas de obrador a la semana | E24: =SUMPRODUCT(--($C$11:$C$15="OBRADOR"),$E$11:$E$15)+SUMPRODUCT(--($C$11:$C$15="OBRADOR"),$F$11:$F$15)+SUMPRODUCT(--($C$11:$C$15="OBRADOR"),$G$11:$G$15)+SUMPRODUCT(--($C$11:$C$15="OBRADOR"),$H$11:$H$15)+SUMPRODUCT(--($C$11:$C$15="OBRADOR"),$I$11:$I$15)+SUMPRODUCT(--($C$11:$C$15="OBRADOR"),$J$11:$J$15)+SUMPRODUCT(--($C$11:$C$15="OBRADOR"),$K$11:$K$15) -> 100 | H24: Son las que tienen que dar de sí para la producción que calcula el libro 1. Si no llegan, el problema no es el horno.
A25: Horas de despacho a la semana | E25: =SUMPRODUCT(--($C$11:$C$15="COMERCIO"),$E$11:$E$15)+SUMPRODUCT(--($C$11:$C$15="COMERCIO"),$F$11:$F$15)+SUMPRODUCT(--($C$11:$C$15="COMERCIO"),$G$11:$G$15)+SUMPRODUCT(--($C$11:$C$15="COMERCIO"),$H$11:$H$15)+SUMPRODUCT(--($C$11:$C$15="COMERCIO"),$I$11:$I$15)+SUMPRODUCT(--($C$11:$C$15="COMERCIO"),$J$11:$J$15)+SUMPRODUCT(--($C$11:$C$15="COMERCIO"),$K$11:$K$15) -> 40 | H25: Mostrador y atención. En una pastelería de barrio la venta se concentra en dos franjas y en el sábado.
A26: Días abiertos sin nadie en el mostrador | E26: =COUNTIF($E$19:$K$19,"SIN NADIE") -> 0 | H26: Tiene que ser cero antes de firmar los contratos. Es el fallo de dimensionado más caro y el más fácil de ver.
A28: Lista (origen del desplegable)
A29: Nº | B29: ¿Abre el despacho?
A30: 1 | B30: Sí
A31: 2 | B31: No
A33: El reparto de horas por día es un SUPUESTO que cuadra las horas contratadas de cada persona con los seis días de apertura. Tu reparto real depende de a qué hora entra el obrador (aquí, entre las 04:30 y las 05:00) y de dónde tengas los picos de venta. Lo que no cambia es la aritmética: si planificas más horas de las que contratas, la columna «Diferencia» lo dice.
A34: Esta hoja no es el cuadrante del día a día ni el registro de jornada, que es obligatorio y se lleva aparte. Es el dimensionado con el que se firman los contratos y se calcula el coste.
A35: Qué hace cada perfil en su turno está en el 04-tareas-perfiles.xlsx del Kit de Tareas Pastelería (12 €): este libro no lo repite (regla R6 de la SPEC).
A37: Diseñado por John Guerrero — chef y consultor gastronómico desde 2010, en cocina desde los 17 años.
A38: Versión 1.0 · septiembre 2026 · aichef.pro/guia-pasteleria-obrador · info@aichef.pro

Sheet Horas y Coste
A1: Horas y Coste de Personal
A2: AI Chef Pro · aichef.pro — Cómo Montar una Pastelería
A3: Del bruto de tabla al coste de empresa hay un 33 %: quince pagas y la Seguridad Social a cargo de la empresa. Es el número que se lleva al plan financiero, no el bruto.
A5: Coste persona a persona
A6: Id | B6: Persona (perfil del kit) | C6: Área | D6: Grupo de convenio | E6: Bruto mensual del grupo (€) | F6: Jornada equivalente | G6: Horas / semana | H6: Bruto mensual ajustado (€) | I6: Bruto anual (€) | J6: Coste empresa mes (€) | K6: Coste empresa año (€) | L6: Coste por hora (€) | M6: Aviso de jornada | N6: Aviso de SMI
A7: P1 | B7: Jefe Pastelero | C7: OBRADOR | D7: Dirección, jefes y encargados | E7: =IFERROR(INDEX('Parámetros'!$C$8:$C$13,MATCH($D7,'Parámetros'!$B$8:$B$13,0)),"") -> 1427.89 | F7: =IFERROR(IF($G7="","",$G7/'Parámetros'!$C$22),"") -> 1 | G7: ='Turnos Semanales'!$L$11 -> 40 | H7: =IFERROR(IF(OR($E7="",$F7=""),"",$E7*$F7),"") -> 1427.89 | I7: =IFERROR(IF($H7="","",$H7*'Parámetros'!$C$15),"") -> 21418.35 | J7: =IFERROR(IF($K7="","",$K7/12),"") -> 2373.8671 | K7: =IFERROR(IF($I7="","",$I7*(1+'Parámetros'!$C$21)),"") -> 28486.406 | L7: =IFERROR(IF(OR($K7="",$F7=""),"",$K7/('Parámetros'!$C$23*$F7)),"") -> 16.003599 | M7: =IF($G7="","",IF($G7>'Parámetros'!$C$22,"Se pasa de la jornada completa","")) | N7: =IFERROR(IF($E7="","",IF($E7*'Parámetros'!$C$15<'Parámetros'!$C$17,"El grupo queda por debajo del SMI anual","")),"")
A8: P2 | B8: Pastelero | C8: OBRADOR | D8: Personal especialista | E8: =IFERROR(INDEX('Parámetros'!$C$8:$C$13,MATCH($D8,'Parámetros'!$B$8:$B$13,0)),"") -> 1376.91 | F8: =IFERROR(IF($G8="","",$G8/'Parámetros'!$C$22),"") -> 1 | G8: ='Turnos Semanales'!$L$12 -> 40 | H8: =IFERROR(IF(OR($E8="",$F8=""),"",$E8*$F8),"") -> 1376.91 | I8: =IFERROR(IF($H8="","",$H8*'Parámetros'!$C$15),"") -> 20653.65 | J8: =IFERROR(IF($K8="","",$K8/12),"") -> 2289.1129 | K8: =IFERROR(IF($I8="","",$I8*(1+'Parámetros'!$C$21)),"") -> 27469.355 | L8: =IFERROR(IF(OR($K8="",$F8=""),"",$K8/('Parámetros'!$C$23*$F8)),"") -> 15.432222 | M8: =IF($G8="","",IF($G8>'Parámetros'!$C$22,"Se pasa de la jornada completa","")) | N8: =IFERROR(IF($E8="","",IF($E8*'Parámetros'!$C$15<'Parámetros'!$C$17,"El grupo queda por debajo del SMI anual","")),"")
A9: P3 | B9: Ayudante | C9: OBRADOR | D9: Personal de apoyo | E9: =IFERROR(INDEX('Parámetros'!$C$8:$C$13,MATCH($D9,'Parámetros'!$B$8:$B$13,0)),"") -> 1192.42 | F9: =IFERROR(IF($G9="","",$G9/'Parámetros'!$C$22),"") -> 0.5 | G9: ='Turnos Semanales'!$L$13 -> 20 | H9: =IFERROR(IF(OR($E9="",$F9=""),"",$E9*$F9),"") -> 596.21 | I9: =IFERROR(IF($H9="","",$H9*'Parámetros'!$C$15),"") -> 8943.15 | J9: =IFERROR(IF($K9="","",$K9/12),"") -> 991.19913 | K9: =IFERROR(IF($I9="","",$I9*(1+'Parámetros'!$C$21)),"") -> 11894.39 | L9: =IFERROR(IF(OR($K9="",$F9=""),"",$K9/('Parámetros'!$C$23*$F9)),"") -> 13.364483 | M9: =IF($G9="","",IF($G9>'Parámetros'!$C$22,"Se pasa de la jornada completa","")) | N9: =IFERROR(IF($E9="","",IF($E9*'Parámetros'!$C$15<'Parámetros'!$C$17,"El grupo queda por debajo del SMI anual","")),"")
A10: P4 | B10: Dependiente Vitrina A | C10: COMERCIO | D10: Personal cualificado | E10: =IFERROR(INDEX('Parámetros'!$C$8:$C$13,MATCH($D10,'Parámetros'!$B$8:$B$13,0)),"") -> 1249.42 | F10: =IFERROR(IF($G10="","",$G10/'Parámetros'!$C$22),"") -> 0.5 | G10: ='Turnos Semanales'!$L$14 -> 20 | H10: =IFERROR(IF(OR($E10="",$F10=""),"",$E10*$F10),"") -> 624.71 | I10: =IFERROR(IF($H10="","",$H10*'Parámetros'!$C$15),"") -> 9370.65 | J10: =IFERROR(IF($K10="","",$K10/12),"") -> 1038.5804 | K10: =IFERROR(IF($I10="","",$I10*(1+'Parámetros'!$C$21)),"") -> 12462.965 | L10: =IFERROR(IF(OR($K10="",$F10=""),"",$K10/('Parámetros'!$C$23*$F10)),"") -> 14.003331 | M10: =IF($G10="","",IF($G10>'Parámetros'!$C$22,"Se pasa de la jornada completa","")) | N10: =IFERROR(IF($E10="","",IF($E10*'Parámetros'!$C$15<'Parámetros'!$C$17,"El grupo queda por debajo del SMI anual","")),"")
A11: P5 | B11: Dependiente Vitrina B | C11: COMERCIO | D11: Personal cualificado | E11: =IFERROR(INDEX('Parámetros'!$C$8:$C$13,MATCH($D11,'Parámetros'!$B$8:$B$13,0)),"") -> 1249.42 | F11: =IFERROR(IF($G11="","",$G11/'Parámetros'!$C$22),"") -> 0.5 | G11: ='Turnos Semanales'!$L$15 -> 20 | H11: =IFERROR(IF(OR($E11="",$F11=""),"",$E11*$F11),"") -> 624.71 | I11: =IFERROR(IF($H11="","",$H11*'Parámetros'!$C$15),"") -> 9370.65 | J11: =IFERROR(IF($K11="","",$K11/12),"") -> 1038.5804 | K11: =IFERROR(IF($I11="","",$I11*(1+'Parámetros'!$C$21)),"") -> 12462.965 | L11: =IFERROR(IF(OR($K11="",$F11=""),"",$K11/('Parámetros'!$C$23*$F11)),"") -> 14.003331 | M11: =IF($G11="","",IF($G11>'Parámetros'!$C$22,"Se pasa de la jornada completa","")) | N11: =IFERROR(IF($E11="","",IF($E11*'Parámetros'!$C$15<'Parámetros'!$C$17,"El grupo queda por debajo del SMI anual","")),"")
A12: TOTAL de la plantilla | F12: =SUM($F$7:$F$11) -> 3.5 | G12: =SUM($G$7:$G$11) -> 140 | H12: =SUM($H$7:$H$11) -> 4650.43 | I12: =SUM($I$7:$I$11) -> 69756.45 | J12: =SUM($J$7:$J$11) -> 7731.3399 | K12: =SUM($K$7:$K$11) -> 92776.079
A14: Lo que se lleva al plan financiero
A15: Coste de personal al mes (€) | E15: =$J$12 -> 7731.3399 | G15: Coste de empresa, con la Seguridad Social dentro. Es una de las dos partidas grandes de los gastos fijos del libro 5.
A16: Coste de personal al año (€) | E16: =$K$12 -> 92776.079 | G16: El año de crucero completo. El primer año cuesta menos porque nadie entra el día 1: eso lo calcula la hoja «Plan de Contratación».
A17: Jornadas equivalentes | E17: =$F$12 -> 3.5 | G17: Cinco personas, 3,5 jornadas. Contar personas en vez de jornadas es el error que hace que un plan parezca sobredimensionado.
A18: Coste medio por hora PAGADA de la plantilla (€) | E18: =IFERROR(IF($F$12=0,"",$K$12/('Parámetros'!$C$23*$F$12)),"") -> 14.891826 | G18: Media de TODA la plantilla (obrador + despacho), sobre horas PAGADAS. NO es el «coste hora productiva de obrador» del libro 4 (17,94 €, carta-de-apertura-y-escandallo.xlsx, sólo obrador y sólo horas productivas) ni el «coste por hora PAGADA del refuerzo» del libro 3 (13,36 €, estacionalidad-y-picos.xlsx, sólo el grupo 5): las tres son correctas y miden un denominador distinto.
A19: Lo que cuesta la Seguridad Social al año (€) | E19: =IFERROR($K$12-$I$12,"") -> 23019.629 | G19: La diferencia entre lo que cobran y lo que pagas. No es negociable y no se puede olvidar.
A20: Suma de los brutos anuales (€) | E20: =$I$12 -> 69756.45 | G20: Lo que perciben las cinco personas, antes de cotizaciones.
A22: Lista de grupos (origen del desplegable)
A23: Grupo | B23: Descripción funcional
A24: ='Parámetros'!$A$8 -> 1 | B24: ='Parámetros'!$B$8 -> Técnicos y titulados superiores
A25: ='Parámetros'!$A$9 -> 2 | B25: ='Parámetros'!$B$9 -> Dirección, jefes y encargados
A26: ='Parámetros'!$A$10 -> 3 | B26: ='Parámetros'!$B$10 -> Personal especialista
A27: ='Parámetros'!$A$11 -> 4 | B27: ='Parámetros'!$B$11 -> Personal cualificado
A28: ='Parámetros'!$A$12 -> 5 | B28: ='Parámetros'!$B$12 -> Personal de apoyo
A29: ='Parámetros'!$A$13 -> 6 | B29: ='Parámetros'!$B$13 -> Personal de ayuda en servicios auxiliares
A31: Las horas de la columna G se leen de la hoja «Turnos Semanales»: si cambias un turno, aquí cambia el coste. La jornada equivalente es horas planificadas partido por jornada completa, así que un contrato de 20 horas cuesta la mitad que uno de 40 del mismo grupo. Lo que no se prorratea es lo que no depende de la jornada: ropa de trabajo, formación y reconocimiento médico cuestan casi lo mismo para media jornada que para una completa.
A32: La Seguridad Social del 33 % es una aproximación de la cotización empresarial (contingencias comunes, desempleo, FOGASA y formación). Tu tipo real depende del contrato, de la actividad y de las bonificaciones que te apliquen: cámbialo en «Parámetros» y todo el libro se recalcula.
A33: Este libro no calcula nóminas ni cotizaciones exactas, y no sustituye a tu gestoría: calcula el DIMENSIONADO y su coste, que es lo que hay que saber antes de firmar el arrendamiento.
A35: Diseñado por John Guerrero — chef y consultor gastronómico desde 2010, en cocina desde los 17 años.
A36: Versión 1.0 · septiembre 2026 · aichef.pro/guia-pasteleria-obrador · info@aichef.pro

Sheet Plan de Contratación
A1: Plan de Contratación y Refuerzo de Campañas
A2: AI Chef Pro · aichef.pro — Cómo Montar una Pastelería
A3: El primer año no cuesta lo que el año de crucero: nadie entra el día 1 y las campañas se refuerzan. Éstos son los dos números que van al plan financiero.
A5: Altas de la plantilla
A6: Id | B6: Persona (perfil del kit) | C6: Fecha de alta prevista | D6: Mes de alta | E6: Meses en el año 1 | F6: Coste empresa mes (€) | G6: Coste del año 1 (€) | H6: Coste del año de crucero (€) | I6: Ahorro del año 1 (€) | J6: Por qué entra cuando entra | K6: Nota
A7: P1 | B7: Jefe Pastelero | C7: 46601 | D7: =IFERROR(IF($C7="","",MONTH($C7)),"") -> 8 | E7: =IFERROR(IF($D7="","",MIN(12,MAX(0,12-($D7-'Parámetros'!$C$25)))),"") -> 12 | F7: ='Horas y Coste'!$J$7 -> 2373.8671 | G7: =IFERROR(IF(OR($E7="",$F7=""),"",$E7*$F7),"") -> 28486.406 | H7: ='Horas y Coste'!$K$7 -> 28486.406 | I7: =IFERROR(IF(OR($G7="",$H7=""),"",$H7-$G7),"") -> 3.6379788e-12 | J7: Un mes antes de abrir: cierra la carta de apertura, hace las pruebas de producción y recibe la maquinaria. | K7: El alta en la Seguridad Social es PREVIA al inicio de la prestación de servicios: se comunica antes de que la persona empiece, no el mismo día.
A8: P2 | B8: Pastelero | C8: 46615 | D8: =IFERROR(IF($C8="","",MONTH($C8)),"") -> 8 | E8: =IFERROR(IF($D8="","",MIN(12,MAX(0,12-($D8-'Parámetros'!$C$25)))),"") -> 12 | F8: ='Horas y Coste'!$J$8 -> 2289.1129 | G8: =IFERROR(IF(OR($E8="",$F8=""),"",$E8*$F8),"") -> 27469.355 | H8: ='Horas y Coste'!$K$8 -> 27469.355 | I8: =IFERROR(IF(OR($G8="",$H8=""),"",$H8-$G8),"") -> 3.6379788e-12 | J8: Dos semanas antes: entra cuando ya hay obrador montado y hay que ensayar las tandas de verdad. | K8: El alta en la Seguridad Social es PREVIA al inicio de la prestación de servicios: se comunica antes de que la persona empiece, no el mismo día.
A9: P3 | B9: Ayudante | C9: 46631 | D9: =IFERROR(IF($C9="","",MONTH($C9)),"") -> 9 | E9: =IFERROR(IF($D9="","",MIN(12,MAX(0,12-($D9-'Parámetros'!$C$25)))),"") -> 12 | F9: ='Horas y Coste'!$J$9 -> 991.19913 | G9: =IFERROR(IF(OR($E9="",$F9=""),"",$E9*$F9),"") -> 11894.39 | H9: ='Horas y Coste'!$K$9 -> 11894.39 | I9: =IFERROR(IF(OR($G9="",$H9=""),"",$H9-$G9),"") -> 0 | J9: El día de la apertura: hasta que no hay producción diaria no hay nada que ayudar. | K9: El alta en la Seguridad Social es PREVIA al inicio de la prestación de servicios: se comunica antes de que la persona empiece, no el mismo día.
A10: P4 | B10: Dependiente Vitrina A | C10: 46631 | D10: =IFERROR(IF($C10="","",MONTH($C10)),"") -> 9 | E10: =IFERROR(IF($D10="","",MIN(12,MAX(0,12-($D10-'Parámetros'!$C$25)))),"") -> 12 | F10: ='Horas y Coste'!$J$10 -> 1038.5804 | G10: =IFERROR(IF(OR($E10="",$F10=""),"",$E10*$F10),"") -> 12462.965 | H10: ='Horas y Coste'!$K$10 -> 12462.965 | I10: =IFERROR(IF(OR($G10="",$H10=""),"",$H10-$G10),"") -> 0 | J10: El día de la apertura, turno de mañana. | K10: El alta en la Seguridad Social es PREVIA al inicio de la prestación de servicios: se comunica antes de que la persona empiece, no el mismo día.
A11: P5 | B11: Dependiente Vitrina B | C11: 46722 | D11: =IFERROR(IF($C11="","",MONTH($C11)),"") -> 12 | E11: =IFERROR(IF($D11="","",MIN(12,MAX(0,12-($D11-'Parámetros'!$C$25)))),"") -> 9 | F11: ='Horas y Coste'!$J$11 -> 1038.5804 | G11: =IFERROR(IF(OR($E11="",$F11=""),"",$E11*$F11),"") -> 9347.2234 | H11: ='Horas y Coste'!$K$11 -> 12462.965 | I11: =IFERROR(IF(OR($G11="",$H11=""),"",$H11-$G11),"") -> 3115.7411 | J11: Tres meses después de abrir: el turno de tarde se abre cuando la venta de tarde lo justifica, y llega a tiempo para la campaña de Navidad. | K11: El alta en la Seguridad Social es PREVIA al inicio de la prestación de servicios: se comunica antes de que la persona empiece, no el mismo día.
A12: TOTAL de la plantilla | F12: =SUM($F$7:$F$11) -> 7731.3399 | G12: =SUM($G$7:$G$11) -> 89660.337 | H12: =SUM($H$7:$H$11) -> 92776.079 | I12: =SUM($I$7:$I$11) -> 3115.7411
A14: Refuerzo de las seis campañas
A15: Nº | B15: Campaña | C15: Fechas | D15: Mes | E15: Personas de refuerzo | F15: Horas por persona | G15: Grupo de convenio | H15: Coste por hora (€) | I15: Coste del refuerzo (€) | J15: Antelación de compra | K15: Nota
A16: 1 | B16: Reyes | C16: 2 a 6 de enero | D16: 1 | E16: 3 | F16: 40 | G16: Personal de apoyo | H16: =IFERROR(INDEX('Parámetros'!$C$8:$C$13,MATCH($G16,'Parámetros'!$B$8:$B$13,0))*'Parámetros'!$C$15*(1+'Parámetros'!$C$21)/'Parámetros'!$C$23,"") -> 13.364483 | I16: =IFERROR(IF(OR($E16="",$F16="",$H16=""),"",$E16*$F16*$H16),"") -> 1603.7379 | J16: 6 semanas antes | K16: El pico que decide el año. Referencias de escala, nunca de precio ni de cuota: PS-35 (unos 30 millones de roscones en España en la campaña 2025/26), PS-36 (más de 2,9 millones en la Comunidad de Madrid) y PS-38 (El Corte Inglés 850.000, Viena Capellanes 72.000). PS-46: el supermercado entra con rosc
A17: 2 | B17: San Valentín | C17: 13 y 14 de febrero | D17: 2 | E17: 0 | F17: 0 | G17: Personal de apoyo | H17: =IFERROR(INDEX('Parámetros'!$C$8:$C$13,MATCH($G17,'Parámetros'!$B$8:$B$13,0))*'Parámetros'!$C$15*(1+'Parámetros'!$C$21)/'Parámetros'!$C$23,"") -> 13.364483 | I17: =IFERROR(IF(OR($E17="",$F17="",$H17=""),"",$E17*$F17*$H17),"") -> 0 | J17: 3 semanas antes | K17: Campaña de dos días y de ticket alto, no de volumen: se gana con cajas y presentación, no con más horno. En el kit, la producción especial de esta fecha son tartas corazón, bombones y macarons.
A18: 3 | B18: Día del Padre y de la Madre | C18: 19 de marzo y primer domingo de mayo | D18: 3 | E18: 1 | F18: 16 | G18: Personal de apoyo | H18: =IFERROR(INDEX('Parámetros'!$C$8:$C$13,MATCH($G18,'Parámetros'!$B$8:$B$13,0))*'Parámetros'!$C$15*(1+'Parámetros'!$C$21)/'Parámetros'!$C$23,"") -> 13.364483 | I18: =IFERROR(IF(OR($E18="",$F18="",$H18=""),"",$E18*$F18*$H18),"") -> 213.83172 | J18: 3 semanas antes | K18: Dos fechas con el mismo patrón de trabajo -tarta con dedicatoria, por encargo- y por eso van juntas como una sola campaña operativa. El kit las separa en su calendario porque a él le importan las fechas; a la guía le importa la carga de obrador.
A19: 4 | B19: Semana Santa | C19: del Domingo de Ramos al Domingo de Resurrección | D19: 4 | E19: 1 | F19: 40 | G19: Personal de apoyo | H19: =IFERROR(INDEX('Parámetros'!$C$8:$C$13,MATCH($G19,'Parámetros'!$B$8:$B$13,0))*'Parámetros'!$C$15*(1+'Parámetros'!$C$21)/'Parámetros'!$C$23,"") -> 13.364483 | I19: =IFERROR(IF(OR($E19="",$F19="",$H19=""),"",$E19*$F19*$H19),"") -> 534.5793 | J19: 4 semanas antes | K19: Ocho días seguidos de producción extra, que es más agotador que los cinco de Reyes aunque el pico sea menor. Torrijas y monas a la vez: una necesita freidora y frío, la otra horno y chocolate.
A20: 5 | B20: Comuniones | C20: de mediados de abril a mediados de junio | D20: 5 | E20: 1 | F20: 60 | G20: Personal de apoyo | H20: =IFERROR(INDEX('Parámetros'!$C$8:$C$13,MATCH($G20,'Parámetros'!$B$8:$B$13,0))*'Parámetros'!$C$15*(1+'Parámetros'!$C$21)/'Parámetros'!$C$23,"") -> 13.364483 | I20: =IFERROR(IF(OR($E20="",$F20="",$H20=""),"",$E20*$F20*$H20),"") -> 801.86896 | J20: 5 semanas antes | K20: No es un pico, es una MESETA de dos meses, y por eso se aguanta con plantilla y no con horas extra. Todo va por encargo: anticipo, calendario de entrega y riesgo de anulación (cap. 16). La herramienta de gestión del encargo es el 11-control-encargos.xlsx del kit, que la guía no rehace (R2).
A21: 6 | B21: Todos los Santos | C21: 30 y 31 de octubre y 1 de noviembre | D21: 11 | E21: 2 | F21: 24 | G21: Personal de apoyo | H21: =IFERROR(INDEX('Parámetros'!$C$8:$C$13,MATCH($G21,'Parámetros'!$B$8:$B$13,0))*'Parámetros'!$C$15*(1+'Parámetros'!$C$21)/'Parámetros'!$C$23,"") -> 13.364483 | I21: =IFERROR(IF(OR($E21="",$F21="",$H21=""),"",$E21*$F21*$H21),"") -> 641.49516 | J21: 4 semanas antes | K21: Tres días con tres referencias que sólo se hacen ahora: buñuelos, huesos de santo y panellets. Los buñuelos van rellenos (4 °C y 24 h) y los otros dos son estables a temperatura ambiente: por eso los buñuelos se hacen el mismo día y los huesos de santo se pueden adelantar. Ese detalle legal ES la pl
A22: TOTAL del refuerzo de campañas | E22: =SUM($E$16:$E$21) -> 8 | F22: =SUM($F$16:$F$21) -> 180 | I22: =SUM($I$16:$I$21) -> 3795.5131
A24: Los dos números que van al plan financiero
A25: Coste de la plantilla en el año 1 (€) | F25: =$G$12 -> 89660.337 | H25: Sólo los meses que cada uno está de alta desde la apertura.
A26: Coste del refuerzo de campañas en un año (€) | F26: =$I$22 -> 3795.5131 | H26: Las seis campañas juntas. Se paga en el mes de la campaña o al siguiente: mira la tesorería del libro 5 justo ahí.
A27: Coste de personal acumulado del primer año (€) | F27: =IFERROR($F$25+$F$26,"") -> 93455.85 | H27: Éste es el número del año 1. Es el que hay que meter en el plan, no el de crucero.
A28: Coste de personal del año de crucero (€) | F28: ='Horas y Coste'!$E$16 -> 92776.079 | H28: Doce meses con toda la plantilla, sin refuerzo. Es el que se usa a partir del año 2.
A29: Diferencia entre el año 1 y el de crucero (€) | F29: =IFERROR($F$27-$F$28,"") -> 679.77193 | H29: Negativo = el primer año cuesta menos porque no está todo el mundo los doce meses.
A30: Veredicto del arranque | F30: =IF($F$29="","",IF($F$29<0,"El primer año ahorra en personal: no lo confundas con que el negocio vaya bien","El refuerzo se come el ahorro del arranque: revisa las campañas")) -> El refuerzo se come el ahorro del arranque: revisa las campañas | H30: En el año 1 el ahorro de personal coincide con los meses en los que tampoco hay ventas: la rampa de arranque del libro 5 lo pone en su sitio.
A32: Lista de grupos (origen del desplegable)
A33: Grupo | B33: Descripción funcional
A34: ='Parámetros'!$A$8 -> 1 | B34: ='Parámetros'!$B$8 -> Técnicos y titulados superiores
A35: ='Parámetros'!$A$9 -> 2 | B35: ='Parámetros'!$B$9 -> Dirección, jefes y encargados
A36: ='Parámetros'!$A$10 -> 3 | B36: ='Parámetros'!$B$10 -> Personal especialista
A37: ='Parámetros'!$A$11 -> 4 | B37: ='Parámetros'!$B$11 -> Personal cualificado
A38: ='Parámetros'!$A$12 -> 5 | B38: ='Parámetros'!$B$12 -> Personal de apoyo
A39: ='Parámetros'!$A$13 -> 6 | B39: ='Parámetros'!$B$13 -> Personal de ayuda en servicios auxiliares
A41: Las fechas de alta que vienen puestas son SUPUESTOS coherentes con el mes de apertura de «Parámetros»: el obrador entra antes porque hay que ensayar las tandas, y el despacho el mismo día. El cálculo de meses del año 1 cuenta desde el mes de apertura, con aritmética de meses y sin funciones de calendario.
A42: El refuerzo de campaña se calcula con el coste por hora del grupo que elijas, que ya lleva las quince pagas y la Seguridad Social dentro. San Valentín viene con cero personas de refuerzo a propósito: son dos días de ticket alto y poco volumen, y se aguanta con la plantilla. Reyes viene con tres, que es lo que pide multiplicar por seis la producción del obrador durante cinco días.
A43: Lo que este libro no decide: el TIPO de contrato del refuerzo. Eso depende de la causa que puedas acreditar y de tu convenio, y lo tiene que ver tu gestoría antes de la primera campaña, no durante.
A45: Diseñado por John Guerrero — chef y consultor gastronómico desde 2010, en cocina desde los 17 años.
A46: Versión 1.0 · septiembre 2026 · aichef.pro/guia-pasteleria-obrador · info@aichef.pro
