Workbook

Sheet Instrucciones
A1: Checklist Vajilla, Cristalería y Cubertería
A2: AI Chef Pro · aichef.pro — Restaurante Gastronómico
A4: Instrucciones de uso
A5: 1. Rellena las celdas verdes con tus datos; el resto lo calcula el libro.
A6: 2. Las hojas están protegidas SIN contraseña para que una copia accidental no borre una fórmula.
A8: Celdas verdes = campos editables
A10: Parámetros de este libro (edítalos: el libro recalcula)
A11: Plazas de sala | B11: 65 | C11: 65 plazas — es el supuesto del propio producto (título del pack y checklist-diseno-sala fila 1: «Plano de sala con 65 plazas»).
A12: Rotación de lavado (veces por servicio) | B12: 1.5 | C12: 1,5 — la regla de dotación del §3.4 de la SPEC: piezas = plazas × factor por comensal × rotación. Con 1,0 no hay margen para lavar entre pases.
A14: Para editar la estructura o una celda que no esté en verde: Revisar → Desproteger hoja (no tiene contraseña).
A15: Diseñado por John Guerrero — chef y consultor gastronómico desde 2010, en cocina desde los 17 años · johnguerrero.es
A16: Versión 2.0 · agosto 2026 · aichef.pro/guia-restaurante-gastronomico · info@aichef.pro

Sheet Vajilla, Cristalería
A1: Checklist Vajilla, Cristalería y Cubertería
A2: AI Chef Pro · aichef.pro — Restaurante Gastronómico
A4: # | B4: Categoría | C4: Tarea / Ítem | D4: Responsable | E4: Fecha Límite | F4: Estado | G4: Coste Est. (€) | H4: Notas | I4: Factor por comensal (menú degustación) — vacío = no es pieza por comensal | J4: Menú degustación (uds) | K4: Dotación de carta (uds) | L4: Coste ajustado a menú degustación (€)
A5: 1 | B5: Platos | C5: Plato llano principal (×100) | D5: Maître | F5: Pendiente | G5: 2000 | I5: 2 | J5: =IF($I5="","",ROUND($I5*Instrucciones!$B$11*Instrucciones!$B$12,0)) -> 195 | K5: 100 | L5: =IFERROR(IF(OR($K5="",$K5=0,$J5="",$G5=""),"",ROUND($G5*$J5/$K5,2)),"") -> 3900
A6: 2 | B6: Platos | C6: Plato hondo / sopero (×80) | D6: Maître | F6: Pendiente | G6: 1600 | I6: 1 | J6: =IF($I6="","",ROUND($I6*Instrucciones!$B$11*Instrucciones!$B$12,0)) -> 98 | K6: 80 | L6: =IFERROR(IF(OR($K6="",$K6=0,$J6="",$G6=""),"",ROUND($G6*$J6/$K6,2)),"") -> 1960
A7: 3 | B7: Platos | C7: Plato postre (×80) | D7: Maître | F7: Pendiente | G7: 1200 | I7: 1 | J7: =IF($I7="","",ROUND($I7*Instrucciones!$B$11*Instrucciones!$B$12,0)) -> 98 | K7: 80 | L7: =IFERROR(IF(OR($K7="",$K7=0,$J7="",$G7=""),"",ROUND($G7*$J7/$K7,2)),"") -> 1470
A8: 4 | B8: Platos | C8: Plato pan (×80) | D8: Maître | F8: Pendiente | G8: 800 | I8: 1 | J8: =IF($I8="","",ROUND($I8*Instrucciones!$B$11*Instrucciones!$B$12,0)) -> 98 | K8: 80 | L8: =IFERROR(IF(OR($K8="",$K8=0,$J8="",$G8=""),"",ROUND($G8*$J8/$K8,2)),"") -> 980
A9: 5 | B9: Platos | C9: Platos presentación / show plate (×70) | D9: Chef | F9: Pendiente | G9: 2100 | I9: 1 | J9: =IF($I9="","",ROUND($I9*Instrucciones!$B$11*Instrucciones!$B$12,0)) -> 98 | K9: 70 | L9: =IFERROR(IF(OR($K9="",$K9=0,$J9="",$G9=""),"",ROUND($G9*$J9/$K9,2)),"") -> 2940
A10: 6 | B10: Platos | C10: Boles variados para entrantes (×60) | D10: Chef | F10: Pendiente | G10: 900 | I10: 3 | J10: =IF($I10="","",ROUND($I10*Instrucciones!$B$11*Instrucciones!$B$12,0)) -> 293 | K10: 60 | L10: =IFERROR(IF(OR($K10="",$K10=0,$J10="",$G10=""),"",ROUND($G10*$J10/$K10,2)),"") -> 4395
A11: 7 | B11: Platos | C11: Pizarras / bandejas presentación (×20) | D11: Chef | F11: Pendiente | G11: 600 | I11: 1 | J11: =IF($I11="","",ROUND($I11*Instrucciones!$B$11*Instrucciones!$B$12,0)) -> 98 | K11: 20 | L11: =IFERROR(IF(OR($K11="",$K11=0,$J11="",$G11=""),"",ROUND($G11*$J11/$K11,2)),"") -> 2940
A12: 8 | B12: Platos | C12: Vajilla petit fours / mignardises (×70) | D12: Chef Pastelero | F12: Pendiente | G12: 500 | I12: 1 | J12: =IF($I12="","",ROUND($I12*Instrucciones!$B$11*Instrucciones!$B$12,0)) -> 98 | K12: 70 | L12: =IFERROR(IF(OR($K12="",$K12=0,$J12="",$G12=""),"",ROUND($G12*$J12/$K12,2)),"") -> 700
A13: 9 | B13: Cristalería | C13: Copa vino tinto Burgundy (×80) | D13: Sommelier | F13: Pendiente | G13: 1600 | I13: 2 | J13: =IF($I13="","",ROUND($I13*Instrucciones!$B$11*Instrucciones!$B$12,0)) -> 195 | K13: 80 | L13: =IFERROR(IF(OR($K13="",$K13=0,$J13="",$G13=""),"",ROUND($G13*$J13/$K13,2)),"") -> 3900
A14: 10 | B14: Cristalería | C14: Copa vino tinto Bordeaux (×80) | D14: Sommelier | F14: Pendiente | G14: 1600 | I14: 2 | J14: =IF($I14="","",ROUND($I14*Instrucciones!$B$11*Instrucciones!$B$12,0)) -> 195 | K14: 80 | L14: =IFERROR(IF(OR($K14="",$K14=0,$J14="",$G14=""),"",ROUND($G14*$J14/$K14,2)),"") -> 3900
A15: 11 | B15: Cristalería | C15: Copa vino blanco (×80) | D15: Sommelier | F15: Pendiente | G15: 1200 | I15: 1 | J15: =IF($I15="","",ROUND($I15*Instrucciones!$B$11*Instrucciones!$B$12,0)) -> 98 | K15: 80 | L15: =IFERROR(IF(OR($K15="",$K15=0,$J15="",$G15=""),"",ROUND($G15*$J15/$K15,2)),"") -> 1470
A16: 12 | B16: Cristalería | C16: Copa champán / espumoso (×60) | D16: Sommelier | F16: Pendiente | G16: 900 | I16: 1 | J16: =IF($I16="","",ROUND($I16*Instrucciones!$B$11*Instrucciones!$B$12,0)) -> 98 | K16: 60 | L16: =IFERROR(IF(OR($K16="",$K16=0,$J16="",$G16=""),"",ROUND($G16*$J16/$K16,2)),"") -> 1470
... A19: 15 | B19: Cristalería | C19: Copa de postre / licor (×40) | D19: Sommelier | F19: Pendiente | G19: 400 | I19: 1 | J19: =IF($I19="","",ROUND($I19*Instrucciones!$B$11*Instrucciones!$B$12,0)) -> 98 | K19: 40 | L19: =IFERROR(IF(OR($K19="",$K19=0,$J19="",$G19=""),"",ROUND($G19*$J19/$K19,2)),"") -> 980
A20: 16 | B20: Cristalería | C20: Decantadores (×6) | D20: Sommelier | F20: Pendiente | G20: 600 | J20: =IF($I20="","",ROUND($I20*Instrucciones!$B$11*Instrucciones!$B$12,0)) | K20: 6 | L20: =IFERROR(IF(OR($K20="",$K20=0,$J20="",$G20=""),"",ROUND($G20*$J20/$K20,2)),"")
A21: 17 | B21: Cristalería | C21: Jarra de agua cristal (×20) | D21: Maître | F21: Pendiente | G21: 400 | J21: =IF($I21="","",ROUND($I21*Instrucciones!$B$11*Instrucciones!$B$12,0)) | K21: 20 | L21: =IFERROR(IF(OR($K21="",$K21=0,$J21="",$G21=""),"",ROUND($G21*$J21/$K21,2)),"")
A22: 18 | B22: Cristalería | C22: Copa de cata ISO para sommelier y formación (×12) | D22: Sommelier | F22: Pendiente | H22: Sin importe tasado en la guía: pide presupuesto y escríbelo aquí (la celda es editable y el TOTAL se recalcula). | J22: =IF($I22="","",ROUND($I22*Instrucciones!$B$11*Instrucciones!$B$12,0)) | K22: 12 | L22: =IFERROR(IF(OR($K22="",$K22=0,$J22="",$G22=""),"",ROUND($G22*$J22/$K22,2)),"")
A23: 19 | B23: Cristalería | C23: Copa de vino generoso / jerez (×40) | D23: Sommelier | F23: Pendiente | H23: Un maridaje largo abre y cierra con generosos: sin copa propia se sirven en la de blanco. Sin importe tasado en la guía: pide presupuesto y escríbelo aquí (la celda es editable y el TOTAL se recalcula). | I23: 1 | J23: =IF($I23="","",ROUND($I23*Instrucciones!$B$11*Instrucciones!$B$12,0)) -> 98 | K23: 40 | L23: =IFERROR(IF(OR($K23="",$K23=0,$J23="",$G23=""),"",ROUND($G23*$J23/$K23,2)),"")
A24: 20 | B24: Cristalería | C24: Cubiteras y soportes de pie para espumosos (×6) | D24: Sommelier | F24: Pendiente | H24: Sin importe tasado en la guía: pide presupuesto y escríbelo aquí (la celda es editable y el TOTAL se recalcula). | J24: =IF($I24="","",ROUND($I24*Instrucciones!$B$11*Instrucciones!$B$12,0)) | K24: 6 | L24: =IFERROR(IF(OR($K24="",$K24=0,$J24="",$G24=""),"",ROUND($G24*$J24/$K24,2)),"")
A25: 21 | B25: Cubertería | C25: Cuchillo mesa principal (×80) | D25: Maître | F25: Pendiente | G25: 800 | I25: 2 | J25: =IF($I25="","",ROUND($I25*Instrucciones!$B$11*Instrucciones!$B$12,0)) -> 195 | K25: 80 | L25: =IFERROR(IF(OR($K25="",$K25=0,$J25="",$G25=""),"",ROUND($G25*$J25/$K25,2)),"") -> 1950
A26: 22 | B26: Cubertería | C26: Tenedor mesa principal (×80) | D26: Maître | F26: Pendiente | G26: 800 | I26: 2 | J26: =IF($I26="","",ROUND($I26*Instrucciones!$B$11*Instrucciones!$B$12,0)) -> 195 | K26: 80 | L26: =IFERROR(IF(OR($K26="",$K26=0,$J26="",$G26=""),"",ROUND($G26*$J26/$K26,2)),"") -> 1950
A27: 23 | B27: Cubertería | C27: Cuchara sopera (×80) | D27: Maître | F27: Pendiente | G27: 600 | I27: 1 | J27: =IF($I27="","",ROUND($I27*Instrucciones!$B$11*Instrucciones!$B$12,0)) -> 98 | K27: 80 | L27: =IFERROR(IF(OR($K27="",$K27=0,$J27="",$G27=""),"",ROUND($G27*$J27/$K27,2)),"") -> 735
A28: 24 | B28: Cubertería | C28: Pala pescado (×80) | D28: Maître | F28: Pendiente | G28: 700 | I28: 2 | J28: =IF($I28="","",ROUND($I28*Instrucciones!$B$11*Instrucciones!$B$12,0)) -> 195 | K28: 80 | L28: =IFERROR(IF(OR($K28="",$K28=0,$J28="",$G28=""),"",ROUND($G28*$J28/$K28,2)),"") -> 1706.25
A29: 25 | B29: Cubertería | C29: Tenedor postre (×80) | D29: Maître | F29: Pendiente | G29: 500 | I29: 1 | J29: =IF($I29="","",ROUND($I29*Instrucciones!$B$11*Instrucciones!$B$12,0)) -> 98 | K29: 80 | L29: =IFERROR(IF(OR($K29="",$K29=0,$J29="",$G29=""),"",ROUND($G29*$J29/$K29,2)),"") -> 612.5
A30: 26 | B30: Cubertería | C30: Cuchara postre (×80) | D30: Maître | F30: Pendiente | G30: 500 | I30: 1 | J30: =IF($I30="","",ROUND($I30*Instrucciones!$B$11*Instrucciones!$B$12,0)) -> 98 | K30: 80 | L30: =IFERROR(IF(OR($K30="",$K30=0,$J30="",$G30=""),"",ROUND($G30*$J30/$K30,2)),"") -> 612.5
A31: 27 | B31: Cubertería | C31: Cuchillo mantequilla (×80) | D31: Maître | F31: Pendiente | G31: 400 | I31: 1 | J31: =IF($I31="","",ROUND($I31*Instrucciones!$B$11*Instrucciones!$B$12,0)) -> 98 | K31: 80 | L31: =IFERROR(IF(OR($K31="",$K31=0,$J31="",$G31=""),"",ROUND($G31*$J31/$K31,2)),"") -> 490
A32: 28 | B32: Cubertería | C32: Cucharilla café / infusión (×80) | D32: Maître | F32: Pendiente | G32: 300 | I32: 1 | J32: =IF($I32="","",ROUND($I32*Instrucciones!$B$11*Instrucciones!$B$12,0)) -> 98 | K32: 80 | L32: =IFERROR(IF(OR($K32="",$K32=0,$J32="",$G32=""),"",ROUND($G32*$J32/$K32,2)),"") -> 367.5
A33: 29 | B33: Cubertería | C33: Pinzas servicio (×10) | D33: Maître | F33: Pendiente | G33: 200 | J33: =IF($I33="","",ROUND($I33*Instrucciones!$B$11*Instrucciones!$B$12,0)) | K33: 10 | L33: =IFERROR(IF(OR($K33="",$K33=0,$J33="",$G33=""),"",ROUND($G33*$J33/$K33,2)),"")
A34: 30 | B34: Cubertería | C34: Cuchara de degustación / amuse-bouche (×100) | D34: Maître | F34: Pendiente | H34: Un menú de 8‑12 pases empieza con snacks: es la pieza que más rota. Sin importe tasado en la guía: pide presupuesto y escríbelo aquí (la celda es editable y el TOTAL se recalcula). | I34: 2 | J34: =IF($I34="","",ROUND($I34*Instrucciones!$B$11*Instrucciones!$B$12,0)) -> 195 | K34: 100 | L34: =IFERROR(IF(OR($K34="",$K34=0,$J34="",$G34=""),"",ROUND($G34*$J34/$K34,2)),"")
A35: 31 | B35: Cubertería | C35: Cubertería de crudos y tartar (tenedor y cucharilla pequeños, ×80) | D35: Maître | F35: Pendiente | H35: Sin importe tasado en la guía: pide presupuesto y escríbelo aquí (la celda es editable y el TOTAL se recalcula). | I35: 1 | J35: =IF($I35="","",ROUND($I35*Instrucciones!$B$11*Instrucciones!$B$12,0)) -> 98 | L35: =IFERROR(IF(OR($K35="",$K35=0,$J35="",$G35=""),"",ROUND($G35*$J35/$K35,2)),"")
A36: 32 | B36: Mantelería | C36: Manteles individuales o de mesa (×40) | D36: Maître | F36: Pendiente | G36: 1200 | I36: 1 | J36: =IF($I36="","",ROUND($I36*Instrucciones!$B$11*Instrucciones!$B$12,0)) -> 98 | K36: 40 | L36: =IFERROR(IF(OR($K36="",$K36=0,$J36="",$G36=""),"",ROUND($G36*$J36/$K36,2)),"") -> 2940
A37: 33 | B37: Mantelería | C37: Servilletas tela (×120) | D37: Maître | F37: Pendiente | G37: 600 | I37: 2 | J37: =IF($I37="","",ROUND($I37*Instrucciones!$B$11*Instrucciones!$B$12,0)) -> 195 | K37: 120 | L37: =IFERROR(IF(OR($K37="",$K37=0,$J37="",$G37=""),"",ROUND($G37*$J37/$K37,2)),"") -> 975
A38: 34 | B38: Mantelería | C38: Muletones protectores (×20) | D38: Maître | F38: Pendiente | G38: 400 | J38: =IF($I38="","",ROUND($I38*Instrucciones!$B$11*Instrucciones!$B$12,0)) | K38: 20 | L38: =IFERROR(IF(OR($K38="",$K38=0,$J38="",$G38=""),"",ROUND($G38*$J38/$K38,2)),"")
A39: 35 | B39: Mantelería | C39: Paños de lino para abrillantado de copas (×40) | D39: Maître | F39: Pendiente | H39: Con 300‑600 copas por servicio, el abrillantado es una tarea de brigada, no un detalle. Sin importe tasado en la guía: pide presupuesto y escríbelo aquí (la celda es editable y el TOTAL se recalcula). | J39: =IF($I39="","",ROUND($I39*Instrucciones!$B$11*Instrucciones!$B$12,0)) | K39: 40 | L39: =IFERROR(IF(OR($K39="",$K39=0,$J39="",$G39=""),"",ROUND($G39*$J39/$K39,2)),"")
A40: 36 | B40: Petit menage | C40: Saleros y pimenteros (×20 sets) | D40: Maître | F40: Pendiente | G40: 300 | J40: =IF($I40="","",ROUND($I40*Instrucciones!$B$11*Instrucciones!$B$12,0)) | L40: =IFERROR(IF(OR($K40="",$K40=0,$J40="",$G40=""),"",ROUND($G40*$J40/$K40,2)),"")
A41: 37 | B41: Petit menage | C41: Aceiteras / vinajeras (×10) | D41: Maître | F41: Pendiente | G41: 200 | J41: =IF($I41="","",ROUND($I41*Instrucciones!$B$11*Instrucciones!$B$12,0)) | K41: 10 | L41: =IFERROR(IF(OR($K41="",$K41=0,$J41="",$G41=""),"",ROUND($G41*$J41/$K41,2)),"")
A42: 38 | B42: Petit menage | C42: Cestitas de pan (×20) | D42: Maître | F42: Pendiente | G42: 300 | J42: =IF($I42="","",ROUND($I42*Instrucciones!$B$11*Instrucciones!$B$12,0)) | K42: 20 | L42: =IFERROR(IF(OR($K42="",$K42=0,$J42="",$G42=""),"",ROUND($G42*$J42/$K42,2)),"")
A43: 39 | B43: Petit menage | C43: Portavelas / centros mesa (×20) | D43: Maître | F43: Pendiente | G43: 400 | J43: =IF($I43="","",ROUND($I43*Instrucciones!$B$11*Instrucciones!$B$12,0)) | K43: 20 | L43: =IFERROR(IF(OR($K43="",$K43=0,$J43="",$G43=""),"",ROUND($G43*$J43/$K43,2)),"")
A44: 40 | B44: Servicio vino | C44: Sacacorchos Pulltap / Laguiole (×6) | D44: Sommelier | F44: Pendiente | G44: 300 | J44: =IF($I44="","",ROUND($I44*Instrucciones!$B$11*Instrucciones!$B$12,0)) | K44: 6 | L44: =IFERROR(IF(OR($K44="",$K44=0,$J44="",$G44=""),"",ROUND($G44*$J44/$K44,2)),"")
A45: 41 | B45: Servicio vino | C45: Enfriadores de mesa (×10) | D45: Sommelier | F45: Pendiente | G45: 500 | J45: =IF($I45="","",ROUND($I45*Instrucciones!$B$11*Instrucciones!$B$12,0)) | K45: 10 | L45: =IFERROR(IF(OR($K45="",$K45=0,$J45="",$G45=""),"",ROUND($G45*$J45/$K45,2)),"")
A46: 42 | B46: Servicio vino | C46: Drop stops / antigoteo (×20) | D46: Sommelier | F46: Pendiente | G46: 40 | J46: =IF($I46="","",ROUND($I46*Instrucciones!$B$11*Instrucciones!$B$12,0)) | K46: 20 | L46: =IFERROR(IF(OR($K46="",$K46=0,$J46="",$G46=""),"",ROUND($G46*$J46/$K46,2)),"")
A47: 43 | B47: Servicio vino | C47: Termómetro de vino digital | D47: Sommelier | F47: Pendiente | G47: 30 | J47: =IF($I47="","",ROUND($I47*Instrucciones!$B$11*Instrucciones!$B$12,0)) | L47: =IFERROR(IF(OR($K47="",$K47=0,$J47="",$G47=""),"",ROUND($G47*$J47/$K47,2)),"")
A48: 44 | B48: Cocina pase | C48: Pinzas emplatado profesionales (×10) | D48: Chef | F48: Pendiente | G48: 200 | J48: =IF($I48="","",ROUND($I48*Instrucciones!$B$11*Instrucciones!$B$12,0)) | K48: 10 | L48: =IFERROR(IF(OR($K48="",$K48=0,$J48="",$G48=""),"",ROUND($G48*$J48/$K48,2)),"")
A49: 45 | B49: Cocina pase | C49: Biberones de salsa (×20) | D49: Chef | F49: Pendiente | G49: 60 | J49: =IF($I49="","",ROUND($I49*Instrucciones!$B$11*Instrucciones!$B$12,0)) | K49: 20 | L49: =IFERROR(IF(OR($K49="",$K49=0,$J49="",$G49=""),"",ROUND($G49*$J49/$K49,2)),"")
A50: 46 | B50: Cocina pase | C50: Cloches / campanas (×10) | D50: Chef | F50: Pendiente | G50: 500 | J50: =IF($I50="","",ROUND($I50*Instrucciones!$B$11*Instrucciones!$B$12,0)) | K50: 10 | L50: =IFERROR(IF(OR($K50="",$K50=0,$J50="",$G50=""),"",ROUND($G50*$J50/$K50,2)),"")
A51: 47 | B51: Reposición | C51: Stock seguridad platos (+20%) | D51: Maître | F51: Pendiente | G51: 1500 | J51: =IF($I51="","",ROUND($I51*Instrucciones!$B$11*Instrucciones!$B$12,0)) | L51: =IFERROR(IF(OR($K51="",$K51=0,$J51="",$G51=""),"",ROUND($G51*$J51/$K51,2)),"")
A52: 48 | B52: Reposición | C52: Stock seguridad copas (+25%) | D52: Sommelier | F52: Pendiente | G52: 1000 | J52: =IF($I52="","",ROUND($I52*Instrucciones!$B$11*Instrucciones!$B$12,0)) | L52: =IFERROR(IF(OR($K52="",$K52=0,$J52="",$G52=""),"",ROUND($G52*$J52/$K52,2)),"")
A53: 49 | B53: Reposición | C53: Stock seguridad cubertería (+15%) | D53: Maître | F53: Pendiente | G53: 500 | J53: =IF($I53="","",ROUND($I53*Instrucciones!$B$11*Instrucciones!$B$12,0)) | L53: =IFERROR(IF(OR($K53="",$K53=0,$J53="",$G53=""),"",ROUND($G53*$J53/$K53,2)),"")
A54: 50 | B54: Reposición | C54: Cajas y fundas de almacenaje y transporte de cristalería (×10) | D54: Sommelier | F54: Pendiente | H54: Sin importe tasado en la guía: pide presupuesto y escríbelo aquí (la celda es editable y el TOTAL se recalcula). | J54: =IF($I54="","",ROUND($I54*Instrucciones!$B$11*Instrucciones!$B$12,0)) | K54: 10 | L54: =IFERROR(IF(OR($K54="",$K54=0,$J54="",$G54=""),"",ROUND($G54*$J54/$K54,2)),"")
A56: RESUMEN — lo calcula el libro (v2.0)
A57: TOTAL PRESUPUESTADO (€) | G57: =SUM(G5:G54) -> 30230
A58: Partidas SIN importe (a presupuestar) | G58: =COUNTIF(B5:B54,"<>")-COUNT(G5:G54) -> 7 | H58: El TOTAL de arriba es un SUELO: no incluye estas partidas, que van a presupuestar.
A59: TOTAL AJUSTADO A MENÚ DEGUSTACIÓN (€) | L59: =SUM(L5:L54) -> 45303.75
A60: Avance del checklist (% completado) | F60: =IFERROR(COUNTIF(F5:F54,"Completado")/COUNTIF(F5:F54,"<>"),"") -> 0 | G60: Estado terminal de este checklist: «Completado»
A62: SUBTOTALES POR CATEGORÍA
A63: Platos | G63: =SUMIF($B$5:$B$54,$A63,$G$5:$G$54) -> 9700
A64: Cristalería | G64: =SUMIF($B$5:$B$54,$A64,$G$5:$G$54) -> 7700
A65: Cubertería | G65: =SUMIF($B$5:$B$54,$A65,$G$5:$G$54) -> 4800
A66: Mantelería | G66: =SUMIF($B$5:$B$54,$A66,$G$5:$G$54) -> 2200
A67: Petit menage | G67: =SUMIF($B$5:$B$54,$A67,$G$5:$G$54) -> 1200
A68: Servicio vino | G68: =SUMIF($B$5:$B$54,$A68,$G$5:$G$54) -> 870
A69: Cocina pase | G69: =SUMIF($B$5:$B$54,$A69,$G$5:$G$54) -> 760
A70: Reposición | G70: =SUMIF($B$5:$B$54,$A70,$G$5:$G$54) -> 3000
A72: AI Chef Pro · aichef.pro — Restaurante Gastronómico
