Workbook

Sheet Instrucciones
A1: Plan Financiero 3 Años — Restaurante Gastronómico
A2: AI Chef Pro · aichef.pro — Restaurante Gastronómico
A4: Instrucciones de uso
A5: 1. Rellena las celdas verdes con tus datos de inversión y costes previstos.
A6: 2. Las fórmulas calcularán automáticamente P&L, margen y proyección a 3 años.
A7: 3. La pestaña 'Inversión' desglosa el CAPEX por categoría.
A8: 4. La pestaña 'P&L Mensual' calcula la cuenta de resultados mensual.
A9: 5. La pestaña 'Proyección 3 Años' extrapola con crecimiento anual.
A11: Celdas verdes = campos editables
A15: La pestaña «Proyección 3 Años» ya existe: el Año 1 sale del P&L Mensual por referencia, corregido por la rampa de arranque de sus dos celdas verdes (los mismos meses que modela cash-flow-break-even.xlsx, así que las dos facturaciones del año 1 coinciden); los años 2 y 3 salen de los dos porcentajes verdes sobre el ritmo de crucero.
A17: La columna «Real (€)» de esta hoja «Inversión» se entrega VACÍA a propósito: es donde vas anotando lo que pagas de verdad, y por eso su fila TOTAL aparece en blanco hasta que escribas la primera cifra (el libro nunca escribe un 0 donde no hay dato). La «Desviación (%)» se enciende sola en cuanto haya un Real.
A19: La pestaña «Financiación» calcula la cuota del préstamo y su cuadro de amortización; sus intereses alimentan la proyección y su cuota mensual se repite en cash-flow-break-even.xlsx.
... A26: Versión 2.0 · agosto 2026 · aichef.pro/guia-restaurante-gastronomico · info@aichef.pro

Sheet Inversión
A1: Inversión Inicial — CAPEX
A2: AI Chef Pro · aichef.pro — Restaurante Gastronómico
A4: # | B4: Concepto | C4: Presupuesto (€) | D4: Real (€) | E4: Desviación (%) | F4: Categoría equivalente en calculadora-capex.xlsx
A5: 1 | B5: Obra civil y reforma integral | C5: 250000 | E5: =IF(D5="","",IFERROR((D5-C5)/C5,"")) | F5: Obra civil y reforma integral
A6: 2 | B6: Instalaciones (electricidad, fontanería, gas, ventilación) | C6: 60000 | E6: =IF(D6="","",IFERROR((D6-C6)/C6,"")) | F6: Obra civil y reforma integral
A7: 3 | B7: Equipamiento cocina caliente | C7: 78000 | E7: =IF(D7="","",IFERROR((D7-C7)/C7,"")) | F7: Equipamiento cocina profesional
A8: 4 | B8: Equipamiento cocina fría | C8: 42000 | E8: =IF(D8="","",IFERROR((D8-C8)/C8,"")) | F8: Equipamiento cocina profesional
A9: 5 | B9: Pastelería y obrador | C9: 14000 | E9: =IF(D9="","",IFERROR((D9-C9)/C9,"")) | F9: Equipamiento cocina profesional
A10: 6 | B10: Zona de pase y expedición | C10: 8000 | E10: =IF(D10="","",IFERROR((D10-C10)/C10,"")) | F10: Equipamiento cocina profesional
A11: 7 | B11: Plonge y lavado | C11: 6430.4 | E11: =IF(D11="","",IFERROR((D11-C11)/C11,"")) | F11: Equipamiento cocina profesional
A12: 8 | B12: Almacenamiento y cámaras | C12: 13000 | E12: =IF(D12="","",IFERROR((D12-C12)/C12,"")) | F12: Equipamiento cocina profesional
A13: 9 | B13: Mobiliario sala (mesas, sillas, sofás) | C13: 62000 | E13: =IF(D13="","",IFERROR((D13-C13)/C13,"")) | F13: Mobiliario sala (65 plazas)
A14: 10 | B14: Iluminación y decoración | C14: 46200 | E14: =IF(D14="","",IFERROR((D14-C14)/C14,"")) | F14: Interiorismo y decoración
A15: 11 | B15: Vajilla, cristalería, cubertería | C15: 26000 | E15: =IF(D15="","",IFERROR((D15-C15)/C15,"")) | F15: Vajilla, cristalería, cubertería
A16: 12 | B16: Mantelería y textil | C16: 4230 | E16: =IF(D16="","",IFERROR((D16-C16)/C16,"")) | F16: Vajilla, cristalería, cubertería
... A25: 21 | B25: Uniformes equipo | C25: 3500 | E25: =IF(D25="","",IFERROR((D25-C25)/C25,"")) | F25: Seguros y otros
A26: 22 | B26: Fondo de maniobra (6 meses) | C26: =IF(C43="","",C43) -> 934320.48 | E26: =IF(D26="","",IFERROR((D26-C26)/C26,"")) | F26: Fondo de maniobra (6 meses)
B27: TOTAL | C27: =IF(COUNT(C5:C26)=0,"",SUM(C5:C26)) -> 1668340.9 | D27: =IF(COUNT(D5:D26)=0,"",SUM(D5:D26)) | E27: =IF(D27="","",IFERROR((D27-C27)/C27,""))
A29: AI Chef Pro · aichef.pro — Restaurante Gastronómico
A31: PREAPERTURA Y FONDO DE MANIOBRA — lo calcula el libro (la fila 26 de la tabla sale de aquí)
A32: Coste mensual de estructura (fijos sin amortización + variables) (€) | C32: =IF(OR('P&L Mensual'!B32="",'P&L Mensual'!B15=""),"",'P&L Mensual'!B32+'P&L Mensual'!B15) -> 155720.08
A33: Alquiler mensual (€) | C33: =IF('P&L Mensual'!B22="","",'P&L Mensual'!B22) -> 17000
A34: Coste mensual de la brigada (€) | C34: =IF(COUNT('P&L Mensual'!B20,'P&L Mensual'!B21)=0,"",SUM('P&L Mensual'!B20,'P&L Mensual'!B21)) -> 59801.68
A35: Meses de renta ANTES de abrir (fuera de la carencia que negocies) | C35: 6
A36: Meses de nómina de la brigada ANTES de abrir | C36: 2
A37: Rentas y suministros de preapertura (€) | C37: =IF(OR(C33="",C35=""),"",C33*C35) -> 102000
A38: Nóminas de preapertura (€) | C38: =IF(OR(C34="",C36=""),"",C34*C36) -> 119603.36
A39: TOTAL COSTES DE PREAPERTURA (€) | C39: =IF(COUNT(C37:C38)=0,"",SUM(C37:C38)) -> 221603.36
A40: El cronograma de este mismo pack firma el arrendamiento en el mes 3 y contrata la brigada en el 12 para abrir en el 18: hay renta y hay nóminas antes de facturar un euro, y el checklist legal lo dice («son 6‑10 meses de renta antes de facturar»). Esta partida no está entre los conceptos de la tabla de arriba: se suma aparte, en la necesidad total.
A42: Meses de colchón (mínimo 6) | C42: 6
A43: Fondo de maniobra necesario (€) | C43: =IF(OR(C32="",C42=""),"",C32*C42) -> 934320.48
A44: Los 60.000 / 120.000 / 200.000 € que trae calculadora-capex.xlsx no cubren ni dos meses de la estructura que describe el propio libro. Aquí se dimensiona con TUS costes: rellena el P&L Mensual y esta fila se calcula sola. El coste de personal sale de plantilla-turnos-brigada.xlsx (§7-bis.7).
A46: NECESIDAD TOTAL DE FINANCIACIÓN (€) — CAPEX de la tabla + preapertura | C46: =IF(OR(C27="",C27=0),"",C27+IF(ISNUMBER(C39),C39,0)) -> 1889944.2
A47: Esta es la cifra que tiene que cuadrar la hoja «Financiación»: fondos propios + préstamo + otras fuentes. El fondo de maniobra ya está dentro, en la fila 26 de la tabla.

Sheet P&L Mensual
A1: Cuenta de Resultados Mensual
A2: AI Chef Pro · aichef.pro — Restaurante Gastronómico
A3: Todas las cifras van SIN IVA. En el cash flow también se escriben sin IVA: su capa de IVA (modelo 303) lo añade aparte, porque la tesorería es caja.
A4: Concepto | B4: Importe (€) | C4: % s/Ventas | D4: Notas
A5: INGRESOS
A6: Comidas (cubiertos × ticket medio) | B6: 40106 | C6: =IF(OR($B$10="",$B$10=0,B6=""),"",B6/$B$10) -> 0.21138683 | D6: Escenario REALISTA de pl-mensual-escenarios.xlsx: 25 cubiertos de comida × 72,92 € × 22 días. Valor de ejemplo: cámbialo por el tuyo y el libro entero se recalcula.
A7: Cenas (cubiertos × ticket medio) | B7: 115434 | C7: =IF(OR($B$10="",$B$10=0,B7=""),"",B7/$B$10) -> 0.60841837 | D7: 45 cubiertos de cena × 116,60 € × 22 días (escenario realista).
A8: Vinos y bebidas | B8: 34188 | C8: =IF(OR($B$10="",$B$10=0,B8=""),"",B8/$B$10) -> 0.18019481 | D8: Maridaje y copa del simulador de ticket medio: (18,00 + 4,20) € × 70 cubiertos × 22 días.
A9: Eventos privados / chef's table | B9: 0 | C9: =IF(OR($B$10="",$B$10=0,B9=""),"",B9/$B$10) -> 0
A10: TOTAL INGRESOS | B10: =IF(COUNT(B6:B9)=0,"",SUM(B6:B9)) -> 189728 | C10: =IF(OR($B$10="",$B$10=0,B10=""),"",B10/$B$10) -> 1
A12: COSTES VARIABLES
A13: Materia prima (food cost) | B13: 45636.36 | C13: =IF(OR($B$10="",$B$10=0,B13=""),"",B13/$B$10) -> 0.24053571
A14: Bebidas (coste bodega) | B14: 11282.04 | C14: =IF(OR($B$10="",$B$10=0,B14=""),"",B14/$B$10) -> 0.059464286
A15: TOTAL COSTES VARIABLES | B15: =IF(COUNT(B13:B14)=0,"",SUM(B13:B14)) -> 56918.4 | C15: =IF(OR($B$10="",$B$10=0,B15=""),"",B15/$B$10) -> 0.3
A17: MARGEN BRUTO | B17: =IF(OR(B10="",B15=""),"",B10-B15) -> 132809.6 | C17: =IF(OR($B$10="",$B$10=0,B17=""),"",B17/$B$10) -> 0.7
A19: COSTES FIJOS
A20: Personal cocina | B20: 38390.01 | C20: =IF(OR($B$10="",$B$10=0,B20=""),"",B20/$B$10) -> 0.20234235 | D20: Coste CON la Seguridad Social de la empresa. La fuente del coste de personal es plantilla-turnos-brigada.xlsx (§7-bis.7): 59.801,68 €/mes = 717.620,12 €/año para las 24 personas del cuadrante, con el 33 % de SS.
A21: Personal sala | B21: 21411.67 | C21: =IF(OR($B$10="",$B$10=0,B21=""),"",B21/$B$10) -> 0.11285456
A22: Alquiler | B22: 17000 | C22: =IF(OR($B$10="",$B$10=0,B22=""),"",B22/$B$10) -> 0.089601956
A23: Suministros (luz, gas, agua) | B23: 6000 | C23: =IF(OR($B$10="",$B$10=0,B23=""),"",B23/$B$10) -> 0.03162422
A24: Seguros | B24: 900 | C24: =IF(OR($B$10="",$B$10=0,B24=""),"",B24/$B$10) -> 0.004743633
A25: Marketing | B25: 3500 | C25: =IF(OR($B$10="",$B$10=0,B25=""),"",B25/$B$10) -> 0.018447462
A26: Tecnología y software | B26: 1200 | C26: =IF(OR($B$10="",$B$10=0,B26=""),"",B26/$B$10) -> 0.006324844
A27: Mantenimiento y reparaciones | B27: 2400 | C27: =IF(OR($B$10="",$B$10=0,B27=""),"",B27/$B$10) -> 0.012649688
A28: Limpieza externa | B28: 2800 | C28: =IF(OR($B$10="",$B$10=0,B28=""),"",B28/$B$10) -> 0.014757969
A29: Asesoría y gestoría | B29: 1200 | C29: =IF(OR($B$10="",$B$10=0,B29=""),"",B29/$B$10) -> 0.006324844
A30: Amortización equipamiento | B30: 6000 | C30: =IF(OR($B$10="",$B$10=0,B30=""),"",B30/$B$10) -> 0.03162422 | D30: Queda FUERA del EBITDA (fila 32) y resta en el EBIT (fila 37): un EBITDA con la amortización dentro es un EBIT con otro nombre.
A31: Otros gastos fijos | B31: 4000 | C31: =IF(OR($B$10="",$B$10=0,B31=""),"",B31/$B$10) -> 0.021082813
A32: TOTAL COSTES FIJOS (sin amortización) | B32: =IF(COUNT(B20:B29,B31)=0,"",SUM(B20:B29)+B31) -> 98801.68 | C32: =IF(OR($B$10="",$B$10=0,B32=""),"",B32/$B$10) -> 0.52075434 | D32: No incluye la amortización de la fila 30: por eso la fila de abajo es EBITDA y no EBIT.
A34: EBITDA | B34: =IF(OR(B17="",B32=""),"",B17-B32) -> 34007.92 | C34: =IF(OR($B$10="",$B$10=0,B34=""),"",B34/$B$10) -> 0.17924566
A35: Margen EBITDA | B35: =IF(OR(B10="",B10=0,B34=""),"",B34/B10) -> 0.17924566
A36: Amortización (fuera del EBITDA, ver fila 30) | B36: =IF(B30="","",B30) -> 6000 | C36: =IF(OR($B$10="",$B$10=0,B36=""),"",B36/$B$10) -> 0.03162422
A37: EBIT (resultado de explotación) | B37: =IF(B34="","",B34-IF(ISNUMBER(B36),B36,0)) -> 28007.92 | C37: =IF(OR($B$10="",$B$10=0,B37=""),"",B37/$B$10) -> 0.14762144

Sheet Proyección 3 Años
A1: Proyección a 3 años
A2: AI Chef Pro · aichef.pro — Restaurante Gastronómico
A4: Concepto | B4: Año 1 | C4: Año 2 | D4: Año 3 | E4: Notas
A5: PARÁMETROS
A6: Crecimiento de ventas (%) | C6: 0.08 | D6: 0.05 | E6: Sobre el año anterior. El Año 1 es la base: sale del P&L mensual de este mismo libro.
A7: Inflación de costes (%) | C7: 0.03 | D7: 0.03
A8: Tipo del Impuesto de Sociedades (%) | B8: 0.25 | C8: 0.25 | D8: 0.25 | E8: Tipo general 25 %. Una entidad de NUEVA CREACIÓN tributa al 15 % en el primer ejercicio con base positiva y en el siguiente (art. 29.1 LIS).
A9: Meses de rampa hasta el mes de crucero | B9: 6 | E9: Cuántos meses tardas en llegar al ritmo de crucero. Escribe 0 y el Año 1 vuelve a ser el mes tipo × 12. Con 6 y 60 %, el Año 1 factura exactamente lo mismo que cash-flow-break-even.xlsx de este mismo pack, que modela la misma rampa mes a mes.
A10: % del crucero que se factura el primer mes | B10: 0.6 | E10: Qué parte del mes de crucero facturas el PRIMER mes. De ahí sube en línea recta hasta el 100 % en el mes de crucero.
A12: CUENTA DE RESULTADOS PREVISIONAL
A13: Ingresos (€) | B13: =IF(OR('P&L Mensual'!B10="",'P&L Mensual'!B10=0),"",'P&L Mensual'!B10*IF(OR($B$9="",$B$9<=1,$B$10=""),12,$B$9*(1+$B$10)/2+(12-$B$9))) -> 2049062.4 | C13: =IF($B$13="","",('P&L Mensual'!B10*12)*(1+C6)) -> 2458874.9 | D13: =IF($B$13="","",C13*(1+D6)) -> 2581818.6 | E13: Año 1 = el mes tipo del P&L Mensual (el mes de CRUCERO) × la suma de los doce factores de la rampa de arriba; con 0 meses de rampa, × 12. El cash flow de este mismo pack reparte la rampa mes a mes; el TOTAL del año coincide al céntimo. Los años 2 y 3 parten del ritmo de CRUCERO anualizado, no del año 1, porque en ellos ya no hay rampa. Si cambias el P&L, cambia la proyección entera: no hay ni una constante aquí.
A14: Costes variables (€) | B14: =IFERROR(IF($B$13="","",'P&L Mensual'!B15*IF(OR($B$9="",$B$9<=1,$B$10=""),12,$B$9*(1+$B$10)/2+(12-$B$9))),"") -> 614718.72 | C14: =IF($B$13="","",('P&L Mensual'!B15*12)*(1+C6)*(1+C7)) -> 759792.34 | D14: =IF($B$13="","",C14*(1+D6)*(1+D7)) -> 821715.41 | E14: Los costes variables llevan la misma rampa que las ventas; los fijos y la amortización, no.
A15: Margen bruto (€) | B15: =IF($B$13="","",B13-B14) -> 1434343.7 | C15: =IF($B$13="","",C13-C14) -> 1699082.5 | D15: =IF($B$13="","",D13-D14) -> 1760103.2
A16: Costes fijos sin amortización (€) | B16: =IFERROR(IF($B$13="","",'P&L Mensual'!B32*12),"") -> 1185620.2 | C16: =IF($B$13="","",B16*(1+C7)) -> 1221188.8 | D16: =IF($B$13="","",C16*(1+D7)) -> 1257824.4
A17: EBITDA (€) | B17: =IF($B$13="","",B15-B16) -> 248723.52 | C17: =IF($B$13="","",C15-C16) -> 477893.78 | D17: =IF($B$13="","",D15-D16) -> 502278.78
A18: Amortización (€) | B18: =IFERROR(IF($B$13="","",'P&L Mensual'!B30*12),"") -> 72000 | C18: =IF($B$13="","",B18) -> 72000 | D18: =IF($B$13="","",C18) -> 72000
A19: EBIT — resultado de explotación (€) | B19: =IF($B$13="","",B17-B18) -> 176723.52 | C19: =IF($B$13="","",C17-C18) -> 405893.78 | D19: =IF($B$13="","",D17-D18) -> 430278.78
A20: Gastos financieros (€) | B20: =IF($B$13="","",IF(ISNUMBER('Financiación'!D18),'Financiación'!D18,0)) -> 38500 | C20: =IF($B$13="","",IF(ISNUMBER('Financiación'!D19),'Financiación'!D19,0)) -> 36956.883 | D20: =IF($B$13="","",IF(ISNUMBER('Financiación'!D20),'Financiación'!D20,0)) -> 33469.349 | E20: Intereses del año, tomados del cuadro francés de la hoja «Financiación».
A21: BAI — beneficio antes de impuestos (€) | B21: =IF($B$13="","",B19-B20) -> 138223.52 | C21: =IF($B$13="","",C19-C20) -> 368936.89 | D21: =IF($B$13="","",D19-D20) -> 396809.43
A22: Impuesto de Sociedades (€) | B22: =IF($B$13="","",IF(B21<=0,0,B21*B8)) -> 34555.88 | C22: =IF($B$13="","",IF(C21<=0,0,C21*C8)) -> 92234.224 | D22: =IF($B$13="","",IF(D21<=0,0,D21*D8)) -> 99202.358
A23: Resultado neto (€) | B23: =IF($B$13="","",B21-B22) -> 103667.64 | C23: =IF($B$13="","",C21-C22) -> 276702.67 | D23: =IF($B$13="","",D21-D22) -> 297607.08
A24: Margen EBITDA (%) | B24: =IF($B$13="","",IFERROR(B17/B13,"")) -> 0.12138406 | C24: =IF($B$13="","",IFERROR(C17/C13,"")) -> 0.19435465 | D24: =IF($B$13="","",IFERROR(D17/D13,"")) -> 0.19454457

Sheet Financiación
A1: Financiación del proyecto
A2: AI Chef Pro · aichef.pro — Restaurante Gastronómico
A4: PARÁMETROS DEL PRÉSTAMO
A5: Importe del préstamo (€) | B5: 700000
A6: Plazo (años) | B6: 10
A7: Tipo de interés nominal anual (%) | B7: 0.055
A8: Carencia (años, solo intereses) | B8: 1
A10: Tipo mensual (%) | B10: =B7/12 -> 0.0045833333
A11: Cuotas de amortización (meses) | B11: =(B6-B8)*12 -> 108
A12: Cuota MENSUAL tras la carencia (€) — la que va al cash flow | B12: =IF(B5=0,"",IF(B11<=0,"",IFERROR(B5*B10/(1-(1+B10)^-B11),""))) -> 8231.9979
A13: Cuota mensual DURANTE la carencia (€) — solo intereses | B13: =IF(B5=0,"",IF(B8<=0,"",B5*B10)) -> 3208.3333
A14: Meses de carencia | B14: =B8*12 -> 12
A15: La cuota se calcula como anualidad: importe × i / (1 - (1+i)^-n), con i mensual y n el número de cuotas. Durante la carencia solo se pagan intereses y el capital pendiente no baja.
A16: El cuadro cubre 10 años; si tu plazo es mayor, copia la última fila hacia abajo. La cuota mensual de B12 es la que se repite en cash-flow-break-even.xlsx (no hay enlace entre libros: un .xlsx movido de carpeta daría #REF!).
A17: Año | B17: Capital inicial (€) | C17: Cuota del año (€) | D17: Intereses (€) | E17: Amortización del principal (€) | F17: Capital pendiente (€)
A18: 1 | B18: =$B$5 -> 700000 | C18: =IF($B$8>=$B$6,"La carencia no puede igualar ni superar el plazo",IF(A18>$B$6,0,IF(A18<=$B$8,$B$5*$B$7,$B$12*12))) -> 38500 | D18: =IF(ISNUMBER(C18),C18-E18,B18*$B$7) -> 38500 | E18: =IF(ISNUMBER(C18),B18-F18,0) -> 0 | F18: =IF($B$8>=$B$6,B18,IF(A18>=$B$6,0,IFERROR($B$5*((1+$B$10)^$B$11-(1+$B$10)^MIN($B$11,MAX(0,12*A18-$B$14)))/((1+$B$10)^$B$11-1),B18))) -> 700000
A19: 2 | B19: =F18 -> 700000 | C19: =IF($B$8>=$B$6,"La carencia no puede igualar ni superar el plazo",IF(A19>$B$6,0,IF(A19<=$B$8,$B$5*$B$7,$B$12*12))) -> 98783.975 | D19: =IF(ISNUMBER(C19),C19-E19,B19*$B$7) -> 36956.883 | E19: =IF(ISNUMBER(C19),B19-F19,0) -> 61827.092 | F19: =IF($B$8>=$B$6,B19,IF(A19>=$B$6,0,IFERROR($B$5*((1+$B$10)^$B$11-(1+$B$10)^MIN($B$11,MAX(0,12*A19-$B$14)))/((1+$B$10)^$B$11-1),B19))) -> 638172.91
A20: 3 | B20: =F19 -> 638172.91 | C20: =IF($B$8>=$B$6,"La carencia no puede igualar ni superar el plazo",IF(A20>$B$6,0,IF(A20<=$B$8,$B$5*$B$7,$B$12*12))) -> 98783.975 | D20: =IF(ISNUMBER(C20),C20-E20,B20*$B$7) -> 33469.349 | E20: =IF(ISNUMBER(C20),B20-F20,0) -> 65314.626 | F20: =IF($B$8>=$B$6,B20,IF(A20>=$B$6,0,IFERROR($B$5*((1+$B$10)^$B$11-(1+$B$10)^MIN($B$11,MAX(0,12*A20-$B$14)))/((1+$B$10)^$B$11-1),B20))) -> 572858.28
A21: 4 | B21: =F20 -> 572858.28 | C21: =IF($B$8>=$B$6,"La carencia no puede igualar ni superar el plazo",IF(A21>$B$6,0,IF(A21<=$B$8,$B$5*$B$7,$B$12*12))) -> 98783.975 | D21: =IF(ISNUMBER(C21),C21-E21,B21*$B$7) -> 29785.091 | E21: =IF(ISNUMBER(C21),B21-F21,0) -> 68998.884 | F21: =IF($B$8>=$B$6,B21,IF(A21>=$B$6,0,IFERROR($B$5*((1+$B$10)^$B$11-(1+$B$10)^MIN($B$11,MAX(0,12*A21-$B$14)))/((1+$B$10)^$B$11-1),B21))) -> 503859.4
A22: 5 | B22: =F21 -> 503859.4 | C22: =IF($B$8>=$B$6,"La carencia no puede igualar ni superar el plazo",IF(A22>$B$6,0,IF(A22<=$B$8,$B$5*$B$7,$B$12*12))) -> 98783.975 | D22: =IF(ISNUMBER(C22),C22-E22,B22*$B$7) -> 25893.012 | E22: =IF(ISNUMBER(C22),B22-F22,0) -> 72890.964 | F22: =IF($B$8>=$B$6,B22,IF(A22>=$B$6,0,IFERROR($B$5*((1+$B$10)^$B$11-(1+$B$10)^MIN($B$11,MAX(0,12*A22-$B$14)))/((1+$B$10)^$B$11-1),B22))) -> 430968.43
A23: 6 | B23: =F22 -> 430968.43 | C23: =IF($B$8>=$B$6,"La carencia no puede igualar ni superar el plazo",IF(A23>$B$6,0,IF(A23<=$B$8,$B$5*$B$7,$B$12*12))) -> 98783.975 | D23: =IF(ISNUMBER(C23),C23-E23,B23*$B$7) -> 21781.388 | E23: =IF(ISNUMBER(C23),B23-F23,0) -> 77002.587 | F23: =IF($B$8>=$B$6,B23,IF(A23>=$B$6,0,IFERROR($B$5*((1+$B$10)^$B$11-(1+$B$10)^MIN($B$11,MAX(0,12*A23-$B$14)))/((1+$B$10)^$B$11-1),B23))) -> 353965.85
A24: 7 | B24: =F23 -> 353965.85 | C24: =IF($B$8>=$B$6,"La carencia no puede igualar ni superar el plazo",IF(A24>$B$6,0,IF(A24<=$B$8,$B$5*$B$7,$B$12*12))) -> 98783.975 | D24: =IF(ISNUMBER(C24),C24-E24,B24*$B$7) -> 17437.837 | E24: =IF(ISNUMBER(C24),B24-F24,0) -> 81346.138 | F24: =IF($B$8>=$B$6,B24,IF(A24>=$B$6,0,IFERROR($B$5*((1+$B$10)^$B$11-(1+$B$10)^MIN($B$11,MAX(0,12*A24-$B$14)))/((1+$B$10)^$B$11-1),B24))) -> 272619.71
A25: 8 | B25: =F24 -> 272619.71 | C25: =IF($B$8>=$B$6,"La carencia no puede igualar ni superar el plazo",IF(A25>$B$6,0,IF(A25<=$B$8,$B$5*$B$7,$B$12*12))) -> 98783.975 | D25: =IF(ISNUMBER(C25),C25-E25,B25*$B$7) -> 12849.275 | E25: =IF(ISNUMBER(C25),B25-F25,0) -> 85934.7 | F25: =IF($B$8>=$B$6,B25,IF(A25>=$B$6,0,IFERROR($B$5*((1+$B$10)^$B$11-(1+$B$10)^MIN($B$11,MAX(0,12*A25-$B$14)))/((1+$B$10)^$B$11-1),B25))) -> 186685.01
A26: 9 | B26: =F25 -> 186685.01 | C26: =IF($B$8>=$B$6,"La carencia no puede igualar ni superar el plazo",IF(A26>$B$6,0,IF(A26<=$B$8,$B$5*$B$7,$B$12*12))) -> 98783.975 | D26: =IF(ISNUMBER(C26),C26-E26,B26*$B$7) -> 8001.8829 | E26: =IF(ISNUMBER(C26),B26-F26,0) -> 90782.092 | F26: =IF($B$8>=$B$6,B26,IF(A26>=$B$6,0,IFERROR($B$5*((1+$B$10)^$B$11-(1+$B$10)^MIN($B$11,MAX(0,12*A26-$B$14)))/((1+$B$10)^$B$11-1),B26))) -> 95902.916
A27: 10 | B27: =F26 -> 95902.916 | C27: =IF($B$8>=$B$6,"La carencia no puede igualar ni superar el plazo",IF(A27>$B$6,0,IF(A27<=$B$8,$B$5*$B$7,$B$12*12))) -> 98783.975 | D27: =IF(ISNUMBER(C27),C27-E27,B27*$B$7) -> 2881.0593 | E27: =IF(ISNUMBER(C27),B27-F27,0) -> 95902.916 | F27: =IF($B$8>=$B$6,B27,IF(A27>=$B$6,0,IFERROR($B$5*((1+$B$10)^$B$11-(1+$B$10)^MIN($B$11,MAX(0,12*A27-$B$14)))/((1+$B$10)^$B$11-1),B27))) -> 0
A29: PLAN DE FINANCIACIÓN — tiene que cuadrar con la hoja «Inversión»
A30: Necesidad total de financiación (€) | B30: =IF('Inversión'!C46="","",'Inversión'!C46) -> 1889944.2 | C30: Sale de la hoja «Inversión» de este mismo libro: los 22 conceptos de CAPEX (con el fondo de maniobra ya calculado) más los costes de preapertura.
A31: Fondos propios / aportación de socios (€) | B31: 1189944.2
A32: Préstamo bancario (€) | B32: =B5 -> 700000
A33: Otras fuentes (subvención, ENISA, socio industrial) (€) | B33: 0
A34: TOTAL FINANCIACIÓN (€) | B34: =IF(COUNT(B31:B33)=0,"",SUM(B31:B33)) -> 1889944.2
A35: Diferencia (necesidad - financiación) (€) | B35: =IF(OR(B30="",B34=""),"",ROUND(B30-B34,2)) -> 0
A36: Si esta fila no es cero, el plan NO está financiado: sube el préstamo o los fondos propios, baja los meses de colchón o recorta el CAPEX. Es la primera comprobación que hace un analista de riesgos y la que decide si el expediente sigue adelante.
